{
  "type": "Feature",
  "properties": {
    "iso:country":"US",
    "sg:address":"4786 Amarosa St",
    "sg:city":"Santa Barbara",
    "sg:classifiers":[
        {
            "category":"Organizations",
            "subcategory":"Religious Organization",
            "type":"Services"
        }
    ],
    "sg:phone":"+1 805 964 2245",
    "sg:postcode":"93110",
    "sg:province":"CA",
    "sg:tags":[
        "church"
    ],
    "wof:name":"Child Evangelism Fellowship",
    "wof:placetype":"venue"
},
  "geometry": {"coordinates":[-119.787229,34.432089],"type":"Point"}
}