{
  "type": "Feature",
  "properties": {
    "iso:country":"US",
    "sg:address":"760-A Gilman St",
    "sg:city":"Berkeley",
    "sg:classifiers":[
        {
            "category":"Travel",
            "subcategory":"Travel Agent",
            "type":"Entertainment"
        }
    ],
    "sg:phone":"+1 510 558 2150",
    "sg:postcode":"94710",
    "sg:province":"CA",
    "sg:website":"www.aviatravel.com/",
    "wof:name":"Avia Travel",
    "wof:placetype":"venue"
},
  "geometry": {"coordinates":[-122.303032,37.87907],"type":"Point"}
}