{
  "type": "Feature",
  "properties": {
    "addr:full":"7323 Starward Dr Dublin CA 94568",
    "addr:housenumber":"7323",
    "addr:postcode":"94568",
    "addr:street":"Starward Dr",
    "iso:country":"US",
    "sg:address":"7323 Starward Dr",
    "sg:city":"Dublin",
    "sg:classifiers":[
        {
            "category":"Real Estate",
            "subcategory":"Real Estate Operator",
            "type":"Services"
        }
    ],
    "sg:phone":"+1 925 828 4616",
    "sg:postcode":"94568",
    "sg:province":"CA",
    "sg:tags":[
        "apartment"
    ],
    "wof:name":"Greenwood Apartments",
    "wof:placetype":"venue"
},
  "geometry": {"coordinates":[-121.935383,37.707706],"type":"Point"}
}