{
  "type": "Feature",
  "properties": {
    "iso:country":"US",
    "sg:address":"2305 Pacific Highway",
    "sg:city":"San Diego",
    "sg:classifiers":[
        {
            "category":"Retail",
            "subcategory":"Auto Rental",
            "type":"Services"
        }
    ],
    "sg:phone":"+1 619 817 8131",
    "sg:postcode":"92101",
    "sg:province":"CA",
    "sg:tags":[
        "car"
    ],
    "sg:website":"www.acerentacar.com",
    "wof:name":"Ace Rent A Car",
    "wof:placetype":"venue"
},
  "geometry": {"coordinates":[-117.172641,32.727863],"type":"Point"}
}