{
  "type": "Feature",
  "properties": {
    "addr:full":"2200 Sunrise Blvd Gold River CA 95670",
    "addr:housenumber":"2200",
    "addr:postcode":"95670",
    "addr:street":"Sunrise Blvd",
    "iso:country":"US",
    "sg:address":"2200 Sunrise Blvd",
    "sg:city":"Gold River",
    "sg:classifiers":[
        {
            "category":"Professional",
            "subcategory":"Lawyer & Legal Services",
            "type":"Services"
        }
    ],
    "sg:phone":"+1 916 925 1081",
    "sg:postcode":"95670",
    "sg:province":"CA",
    "wof:name":"Quattrin Johnson & Campora",
    "wof:placetype":"venue"
},
  "geometry": {"coordinates":[-121.26799800000001,38.6189],"type":"Point"}
}