{
  "type": "Feature",
  "properties": {
    "iso:country":"US",
    "sg:address":"5225 E 2nd St",
    "sg:city":"Long Beach",
    "sg:classifiers":[
        {
            "category":"Manufacturing",
            "subcategory":"Printing",
            "type":"Manufacturing & Wholesale Goods"
        }
    ],
    "sg:phone":"+1 562 433 2000",
    "sg:postcode":"90803",
    "sg:province":"CA",
    "sg:tags":[
        "newspaper"
    ],
    "sg:website":"www.gazettes.com",
    "wof:name":"Grunion Gazette",
    "wof:placetype":"venue"
},
  "geometry": {"coordinates":[-118.13389599999999,33.759855],"type":"Point"}
}