{
  "type": "Feature",
  "properties": {
    "iso:country":"US",
    "sg:address":"481 W Duarte Rd",
    "sg:city":"Arcadia",
    "sg:classifiers":[
        {
            "category":"Travel",
            "subcategory":"Travel Agent",
            "type":"Entertainment"
        }
    ],
    "sg:phone":"+1 626 821 6400",
    "sg:postcode":"91007",
    "sg:province":"CA",
    "sg:tags":[
        "agency"
    ],
    "wof:name":"Los Angeles Palm Travel",
    "wof:placetype":"venue"
},
  "geometry": {"coordinates":[-118.047049,34.127363],"type":"Point"}
}