{
  "type": "Feature",
  "properties": {
    "addr:full":"1681 Royal Ave Simi Valley CA 93065",
    "addr:housenumber":"1681",
    "addr:postcode":"93065",
    "addr:street":"Royal Ave",
    "iso:country":"US",
    "sg:address":"1681 Royal Ave",
    "sg:city":"Simi Valley",
    "sg:classifiers":[
        {
            "category":"Shopping",
            "subcategory":"Clothing, Apparel, & Fashions",
            "type":"Retail Goods"
        }
    ],
    "sg:phone":"+1 805 526 8739",
    "sg:postcode":"93065",
    "sg:province":"CA",
    "sg:tags":[
        "shoes"
    ],
    "wof:name":"Hello Sexy Girl",
    "wof:placetype":"venue"
},
  "geometry": {"coordinates":[-118.766706,34.264546],"type":"Point"}
}