{
  "type": "Feature",
  "properties": {
    "addr:full":"2185 W Cleveland Ave H Madera CA 93637",
    "addr:housenumber":"2185",
    "addr:postcode":"93637",
    "addr:street":"W Cleveland Ave H",
    "iso:country":"US",
    "sg:address":"2185 W Cleveland Ave H",
    "sg:city":"Madera",
    "sg:classifiers":[
        {
            "category":"Banks & Credit Unions",
            "subcategory":"Financial Services",
            "type":"Services"
        }
    ],
    "sg:phone":"+1 559 673 6853",
    "sg:postcode":"93637",
    "sg:province":"CA",
    "sg:tags":[
        "cashing",
        "check"
    ],
    "wof:name":"Money Mart",
    "wof:placetype":"venue"
},
  "geometry": {"coordinates":[-120.083287,36.97464],"type":"Point"}
}