{
  "type": "Feature",
  "properties": {
    "iso:country":"US",
    "sg:address":"22994 el Toro Rd",
    "sg:city":"Lake Forest",
    "sg:classifiers":[
        {
            "category":"Building & Trades",
            "subcategory":"Electrical",
            "type":"Services"
        }
    ],
    "sg:phone":"+1 949 540 2525",
    "sg:postcode":"92630",
    "sg:province":"CA",
    "sg:tags":[
        "communications",
        "electrical",
        "contractor"
    ],
    "wof:name":"Telogic Communications Inc",
    "wof:placetype":"venue"
},
  "geometry": {"coordinates":[-117.628258,33.669959],"type":"Point"}
}