{
  "type": "Feature",
  "properties": {
    "addr:full":"313 Soquel Ave Santa Cruz CA 95062",
    "addr:housenumber":"313",
    "addr:postcode":"95062",
    "addr:street":"Soquel Ave",
    "iso:country":"US",
    "sg:address":"313 Soquel Ave",
    "sg:city":"Santa Cruz",
    "sg:classifiers":[
        {
            "category":"Social Services",
            "type":"Services"
        }
    ],
    "sg:phone":"+1 831 420 0928",
    "sg:postcode":"95062",
    "sg:province":"CA",
    "sg:tags":[
        "counselor",
        "marriage",
        "family"
    ],
    "wof:name":"Safe Connections For Kids",
    "wof:placetype":"venue"
},
  "geometry": {"coordinates":[-122.019184,36.974558],"type":"Point"}
}