{
  "type": "Feature",
  "properties": {
    "iso:country":"US",
    "sg:address":"2155 Park Marina Dr # 45",
    "sg:city":"Redding",
    "sg:classifiers":[
        {
            "category":"Real Estate",
            "subcategory":"Real Estate Services",
            "type":"Services"
        },
        {
            "category":"Real Estate",
            "subcategory":"Real Estate Operator",
            "type":"Services"
        }
    ],
    "sg:phone":"+1 530 244 6234",
    "sg:postcode":"96001",
    "sg:province":"CA",
    "sg:tags":[
        "vacancy",
        "apartment",
        "rental",
        "listing"
    ],
    "wof:name":"Park Marina Village Apartments",
    "wof:placetype":"venue"
},
  "geometry": {"coordinates":[-122.372281,40.582357],"type":"Point"}
}