{
  "type": "Feature",
  "properties": {
    "iso:country":"US",
    "sg:address":"815 S Walnut Ave",
    "sg:city":"Brea",
    "sg:classifiers":[
        {
            "category":"Professional",
            "type":"Services"
        }
    ],
    "sg:phone":"+1 714 257 7356",
    "sg:postcode":"92821",
    "sg:province":"CA",
    "wof:name":"Ntheskn Images",
    "wof:placetype":"venue"
},
  "geometry": {"coordinates":[-117.906462,33.907819],"type":"Point"}
}