{
  "type": "Feature",
  "properties": {
    "iso:country":"US",
    "sg:address":"2701 Cottage Way",
    "sg:city":"Sacramento",
    "sg:classifiers":[
        {
            "category":"Professional",
            "subcategory":"Accounting & Tax Preparation",
            "type":"Services"
        }
    ],
    "sg:phone":"+1 916 482 1200",
    "sg:postcode":"95825",
    "sg:province":"CA",
    "sg:tags":[
        "consultant"
    ],
    "wof:name":"Sales Tax Reduction Specialist",
    "wof:placetype":"venue"
},
  "geometry": {"coordinates":[-121.397308,38.603361],"type":"Point"}
}