{
  "type": "Feature",
  "properties": {
    "addr:full":"115 W Pacheco Blvd Los Banos CA 93635",
    "addr:housenumber":"115",
    "addr:postcode":"93635",
    "addr:street":"W Pacheco Blvd",
    "iso:country":"US",
    "sg:address":"115 W Pacheco Blvd",
    "sg:city":"Los Banos",
    "sg:classifiers":[
        {
            "category":"Food & Beverages",
            "subcategory":"Groceries & Convenience Stores",
            "type":"Retail Goods"
        }
    ],
    "sg:phone":"+1 209 827 4803",
    "sg:postcode":"93635",
    "sg:province":"CA",
    "wof:name":"King Bee Oriental Store",
    "wof:placetype":"venue"
},
  "geometry": {"coordinates":[-120.85521199999999,37.674286],"type":"Point"}
}