{
  "type": "Feature",
  "properties": {
    "iso:country":"US",
    "sg:address":"2520 S Fairview St",
    "sg:city":"Santa Ana",
    "sg:classifiers":[
        {
            "category":"Manufacturing",
            "subcategory":"Tools & Machinery",
            "type":"Manufacturing & Wholesale Goods"
        }
    ],
    "sg:phone":"+1 714 432 8849",
    "sg:postcode":"92704",
    "sg:province":"CA",
    "sg:tags":[
        "industrial",
        "mfg"
    ],
    "wof:name":"Rubicon Avation",
    "wof:placetype":"venue"
},
  "geometry": {"coordinates":[-117.907955,33.70889],"type":"Point"}
}