{
  "type": "Feature",
  "properties": {
    "addr:full":"5318 E 2nd St Long Beach CA 90803",
    "addr:housenumber":"5318",
    "addr:postcode":"90803",
    "addr:street":"E 2Nd St",
    "iso:country":"US",
    "sg:address":"5318 E 2nd St",
    "sg:city":"Long Beach",
    "sg:classifiers":[
        {
            "category":"Retail",
            "subcategory":"Auto Repair",
            "type":"Services"
        }
    ],
    "sg:phone":"+1 562 307 0745",
    "sg:postcode":"90803",
    "sg:province":"CA",
    "sg:tags":[
        "body",
        "automobile",
        "painting"
    ],
    "wof:name":"A Paintless Dent Repair",
    "wof:placetype":"venue"
},
  "geometry": {"coordinates":[-118.132487,33.759211],"type":"Point"}
}