{
  "type": "Feature",
  "properties": {
    "iso:country":"US",
    "sg:address":"6972 Village Pkwy",
    "sg:city":"Dublin",
    "sg:classifiers":[
        {
            "category":"Personal",
            "subcategory":"Beauty Salon",
            "type":"Services"
        }
    ],
    "sg:phone":"+1 925 560 1404",
    "sg:postcode":"94568",
    "sg:province":"CA",
    "wof:name":"Strictly French",
    "wof:placetype":"venue"
},
  "geometry": {"coordinates":[-121.923883,37.706017],"type":"Point"}
}