{
  "type": "Feature",
  "properties": {
    "addr:full":"1345 Orange Ave Coronado CA 92118",
    "addr:housenumber":"1345",
    "addr:postcode":"92118",
    "addr:street":"Orange Ave",
    "iso:country":"US",
    "sg:address":"1345 Orange Ave",
    "sg:city":"Coronado",
    "sg:classifiers":[
        {
            "category":"Professional",
            "type":"Services"
        }
    ],
    "sg:phone":"+1 619 437 7219",
    "sg:postcode":"92118",
    "sg:province":"CA",
    "sg:tags":[
        "establishment"
    ],
    "wof:name":"Brookstone",
    "wof:placetype":"venue"
},
  "geometry": {"coordinates":[-117.178668,32.683257],"type":"Point"}
}