{
  "type": "Feature",
  "properties": {
    "addr:full":"6971 El Camino Real Carlsbad CA 92009",
    "addr:housenumber":"6971",
    "addr:postcode":"92009",
    "addr:street":"El Camino Real",
    "iso:country":"US",
    "sg:address":"6971 El Camino Real",
    "sg:city":"Carlsbad",
    "sg:classifiers":[
        {
            "category":"Restaurant",
            "type":"Food & Drink"
        }
    ],
    "sg:phone":"+1 760 431 5010",
    "sg:postcode":"92009",
    "sg:province":"CA",
    "wof:name":"Togo's Eatery",
    "wof:placetype":"venue"
},
  "geometry": {"coordinates":[-117.266998,33.102798],"type":"Point"}
}