{
  "type": "Feature",
  "properties": {
    "iso:country":"US",
    "sg:address":"4343 Fistor Dr",
    "sg:city":"Santa Rosa",
    "sg:classifiers":[
        {
            "category":"Wholesale",
            "subcategory":"Home Furnishings",
            "type":"Manufacturing & Wholesale Goods"
        }
    ],
    "sg:phone":"+1 707 539 0377",
    "sg:postcode":"95409",
    "sg:province":"CA",
    "wof:name":"Gayle Dilles Custom Framing",
    "wof:placetype":"venue"
},
  "geometry": {"coordinates":[-122.676852,38.480213],"type":"Point"}
}