{
  "type": "Feature",
  "properties": {
    "iso:country":"US",
    "sg:address":"1201 Clearview Dr",
    "sg:city":"Hollister",
    "sg:classifiers":[
        {
            "category":"Building & Trades",
            "subcategory":"Electrical",
            "type":"Services"
        }
    ],
    "sg:phone":"+1 831 636 8134",
    "sg:postcode":"95023",
    "sg:province":"CA",
    "sg:tags":[
        "electrician"
    ],
    "wof:name":"Granata Electric",
    "wof:placetype":"venue"
},
  "geometry": {"coordinates":[-121.376183,36.842018],"type":"Point"}
}