{
  "type": "Feature",
  "properties": {
    "iso:country":"US",
    "sg:address":"3031 Telegraph Ave",
    "sg:city":"Berkeley",
    "sg:classifiers":[
        {
            "category":"Health Services",
            "subcategory":"Health Practitioner",
            "type":"Services"
        }
    ],
    "sg:phone":"+1 510 843 7397",
    "sg:postcode":"94705",
    "sg:province":"CA",
    "sg:tags":[
        "acupuncture"
    ],
    "wof:name":"Robert Zeiger LAC",
    "wof:placetype":"venue"
},
  "geometry": {"coordinates":[-122.259698,37.854807],"type":"Point"}
}