{
  "type": "Feature",
  "properties": {
    "iso:country":"US",
    "sg:address":"2131 N Van Ness Blvd",
    "sg:city":"Fresno",
    "sg:classifiers":[
        {
            "category":"Organizations",
            "subcategory":"Religious Organization",
            "type":"Services"
        }
    ],
    "sg:phone":"+1 559 227 8489",
    "sg:postcode":"93704",
    "sg:province":"CA",
    "sg:tags":[
        "church"
    ],
    "sg:website":"www.bigredchurch.org",
    "wof:name":"First Congregational Church",
    "wof:placetype":"venue"
},
  "geometry": {"coordinates":[-119.804159,36.770108],"type":"Point"}
}