{
  "type": "Feature",
  "properties": {
    "addr:full":"3405 Watt Ave Sacramento CA 95821",
    "addr:housenumber":"3405",
    "addr:postcode":"95821",
    "addr:street":"Watt Ave",
    "iso:country":"US",
    "sg:address":"3405 Watt Ave",
    "sg:city":"Sacramento",
    "sg:classifiers":[
        {
            "category":"Fast Food",
            "type":"Food & Drink"
        },
        {
            "category":"Restaurant",
            "type":"Food & Drink"
        }
    ],
    "sg:phone":"+1 916 489 9350",
    "sg:postcode":"95821",
    "sg:province":"CA",
    "sg:tags":[
        "style",
        "pan",
        "chinese",
        "family",
        "asian"
    ],
    "wof:name":"Ming Palace Restaurant",
    "wof:placetype":"venue"
},
  "geometry": {"coordinates":[-121.38298,38.626392],"type":"Point"}
}