{
  "type": "Feature",
  "properties": {
    "iso:country":"US",
    "sg:address":"1399 Roxbury Dr",
    "sg:city":"Los Angeles",
    "sg:classifiers":[
        {
            "category":"Education",
            "subcategory":"School",
            "type":"Public Place"
        }
    ],
    "sg:phone":"+1 310 772 2480",
    "sg:postcode":"90035",
    "sg:province":"CA",
    "wof:name":"Yeshiva University HI SC La",
    "wof:placetype":"venue"
},
  "geometry": {"coordinates":[-118.402637,34.0547],"type":"Point"}
}