{
  "type": "Feature",
  "properties": {
    "iso:country":"US",
    "sg:address":"2600 10th St",
    "sg:city":"Berkeley",
    "sg:classifiers":[
        {
            "category":"Education",
            "subcategory":"Special Training",
            "type":"Public Place"
        }
    ],
    "sg:phone":"+1 510 549 3456",
    "sg:postcode":"94710",
    "sg:province":"CA",
    "sg:tags":[
        "adult"
    ],
    "sg:website":"berkeleydigital.com",
    "wof:name":"Berkeley Digital Film Institute",
    "wof:placetype":"venue"
},
  "geometry": {"coordinates":[-122.290299,37.858337],"type":"Point"}
}