{
  "type": "Feature",
  "properties": {
    "addr:full":"16730 Gridley Rd Cerritos CA 90703",
    "addr:postcode":"16730;ca 90703",
    "addr:street":"Gridley Rd",
    "iso:country":"US",
    "sg:address":"16730 Gridley Rd",
    "sg:city":"Cerritos",
    "sg:classifiers":[
        {
            "category":"Wholesale",
            "subcategory":"Durable Goods & Equipment",
            "type":"Manufacturing & Wholesale Goods"
        }
    ],
    "sg:phone":"+1 562 924 7909",
    "sg:postcode":"90703",
    "sg:province":"CA",
    "wof:name":"Goldenwest Sales",
    "wof:placetype":"venue"
},
  "geometry": {"coordinates":[-118.090998,33.879478],"type":"Point"}
}