{
  "type": "Feature",
  "properties": {
    "addr:full":"9559 Rhea Ave Northridge CA 91324",
    "addr:housenumber":"9559",
    "addr:postcode":"91324",
    "addr:street":"Rhea Ave",
    "iso:country":"US",
    "sg:address":"9559 Rhea Ave",
    "sg:city":"Northridge",
    "sg:classifiers":[
        {
            "category":"Shopping",
            "subcategory":"Computers & Home Electronics",
            "type":"Retail Goods"
        }
    ],
    "sg:phone":"+1 818 718 8075",
    "sg:postcode":"91324",
    "sg:province":"CA",
    "sg:tags":[
        "equipment",
        "dealer"
    ],
    "wof:name":"Optima Computer Enterprises",
    "wof:placetype":"venue"
},
  "geometry": {"coordinates":[-118.541442,34.243831],"type":"Point"}
}