{
  "type": "Feature",
  "properties": {
    "iso:country":"US",
    "sg:address":"9559 Rhea Ave",
    "sg:city":"Northridge",
    "sg:classifiers":[
        {
            "category":"Shopping",
            "subcategory":"Computers & Home Electronics",
            "type":"Retail Goods"
        }
    ],
    "sg:phone":"+1 818 718 8075",
    "sg:postcode":"91324",
    "sg:province":"CA",
    "sg:tags":[
        "equipment",
        "dealer"
    ],
    "wof:name":"Optima Computer Enterprises",
    "wof:placetype":"venue"
},
  "geometry": {"coordinates":[-118.541442,34.243831],"type":"Point"}
}