{
  "type": "Feature",
  "properties": {
    "iso:country":"US",
    "sg:address":"3324 State St",
    "sg:city":"Santa Barbara",
    "sg:classifiers":[
        {
            "category":"Personal",
            "subcategory":"Beauty Salon",
            "type":"Services"
        }
    ],
    "sg:phone":"+1 805 682 0511",
    "sg:postcode":"93105",
    "sg:province":"CA",
    "sg:tags":[
        "treatment",
        "skin"
    ],
    "wof:name":"Radiance",
    "wof:placetype":"venue"
},
  "geometry": {"coordinates":[-119.736014,34.44047],"type":"Point"}
}