{
  "type": "Feature",
  "properties": {
    "addr:full":"4190 Bonita Rd Bonita CA 91902",
    "addr:housenumber":"4190",
    "addr:postcode":"91902",
    "addr:street":"Bonita Rd",
    "iso:country":"US",
    "sg:address":"4190 Bonita Rd",
    "sg:city":"Bonita",
    "sg:classifiers":[
        {
            "category":"Professional",
            "subcategory":"Lawyer & Legal Services",
            "type":"Services"
        }
    ],
    "sg:phone":"+1 619 475 7882",
    "sg:postcode":"91902",
    "sg:province":"CA",
    "sg:tags":[
        "attorney"
    ],
    "wof:name":"Batcher & Zarcone LLP",
    "wof:placetype":"venue"
},
  "geometry": {"coordinates":[-117.04040500000001,32.658112],"type":"Point"}
}