{
  "type": "Feature",
  "properties": {
    "iso:country":"US",
    "sg:address":"1675 Robinhood Rd",
    "sg:city":"Vista",
    "sg:classifiers":[
        {
            "category":"Building & Trades",
            "subcategory":"Construction",
            "type":"Services"
        }
    ],
    "sg:phone":"+1 760 598 9600",
    "sg:postcode":"92084",
    "sg:province":"CA",
    "sg:tags":[
        "family",
        "general",
        "new",
        "home",
        "contractor",
        "renovation"
    ],
    "wof:name":"Ted Vollgraff & Associates",
    "wof:placetype":"venue"
},
  "geometry": {"coordinates":[-117.175737,33.180619],"type":"Point"}
}