{
  "type": "Feature",
  "properties": {
    "iso:country":"US",
    "sg:address":"1030 Kearny St",
    "sg:city":"San Francisco",
    "sg:classifiers":[
        {
            "category":"Shopping",
            "subcategory":"Adult",
            "type":"Retail Goods"
        },
        {
            "category":"Animal Shelter",
            "type":"Public Place"
        },
        {
            "category":"Cinema",
            "subcategory":"Movie Rental",
            "type":"Entertainment"
        }
    ],
    "sg:phone":"+1 415 391 9246",
    "sg:postcode":"94133",
    "sg:province":"CA",
    "sg:tags":[
        "game",
        "video"
    ],
    "sg:website":"www.AdultMegaStores.com",
    "wof:name":"Kearny Adult Superstore",
    "wof:placetype":"venue"
},
  "geometry": {"coordinates":[-122.40537399999999,37.797595],"type":"Point"}
}