{
  "type": "Feature",
  "properties": {
    "addr:full":"44075 Jackson St Indio CA 92201",
    "addr:housenumber":"44075",
    "addr:postcode":"92201",
    "addr:street":"Jackson St",
    "iso:country":"US",
    "sg:address":"44075 Jackson St",
    "sg:city":"Indio",
    "sg:classifiers":[
        {
            "category":"Personal",
            "subcategory":"Barber",
            "type":"Services"
        }
    ],
    "sg:phone":"+1 760 347 3960",
    "sg:postcode":"92201",
    "sg:province":"CA",
    "wof:name":"Andy's Barber Shop",
    "wof:placetype":"venue"
},
  "geometry": {"coordinates":[-116.21632700000001,33.729476],"type":"Point"}
}