{
  "type": "Feature",
  "properties": {
    "addr:full":"226 Grand Ave South San Francisco CA 94080",
    "addr:housenumber":"226",
    "addr:postcode":"94080",
    "addr:street":"Grand Ave",
    "iso:country":"US",
    "sg:address":"226 Grand Ave",
    "sg:city":"South San Francisco",
    "sg:classifiers":[
        {
            "category":"Retail",
            "subcategory":"Photofinishing",
            "type":"Services"
        }
    ],
    "sg:phone":"+1 650 737 6044",
    "sg:postcode":"94080",
    "sg:province":"CA",
    "sg:tags":[
        "photo",
        "photography",
        "finishing",
        "store"
    ],
    "wof:name":"Tyle Color 1 Hour Photo",
    "wof:placetype":"venue"
},
  "geometry": {"coordinates":[-122.408981,37.654923],"type":"Point"}
}