{
  "type": "Feature",
  "properties": {
    "addr:full":"2041 Upper Black Rock Rd Cool CA 95614",
    "addr:housenumber":"2041",
    "addr:postcode":"95614",
    "addr:street":"Upper Black Rock Rd",
    "iso:country":"US",
    "sg:address":"2041 Upper Black Rock Rd",
    "sg:city":"Cool",
    "sg:classifiers":[
        {
            "category":"Real Estate",
            "subcategory":"Real Estate Agent",
            "type":"Services"
        }
    ],
    "sg:phone":"+1 530 823 1900",
    "sg:postcode":"95614",
    "sg:province":"CA",
    "wof:name":"Stewart Real Estate Team",
    "wof:placetype":"venue"
},
  "geometry": {"coordinates":[-120.971802,38.898869],"type":"Point"}
}