{
  "type": "Feature",
  "properties": {
    "iso:country":"US",
    "sg:address":"5776 Broadway St",
    "sg:city":"Sacramento",
    "sg:classifiers":[
        {
            "category":"Personal",
            "subcategory":"Beauty Salon",
            "type":"Services"
        }
    ],
    "sg:phone":"+1 916 454 1889",
    "sg:postcode":"95820",
    "sg:province":"CA",
    "sg:tags":[
        "manicuring"
    ],
    "wof:name":"Nails By Stacey",
    "wof:placetype":"venue"
},
  "geometry": {"coordinates":[-121.438787,38.546648],"type":"Point"}
}