{
  "type": "Feature",
  "properties": {
    "iso:country":"US",
    "sg:address":"10225 Telephone Rd",
    "sg:city":"Ventura",
    "sg:classifiers":[
        {
            "category":"Restaurant",
            "type":"Food & Drink"
        }
    ],
    "sg:menulink":"http://www.allmenus.com/ca/ventura/74075-ameci-pizza--pasta/menu/",
    "sg:phone":"+1 805 659 4483",
    "sg:postcode":"93004",
    "sg:province":"CA",
    "sg:tags":[
        "american",
        "pizza"
    ],
    "wof:name":"Ameci Pizza & Pasta",
    "wof:placetype":"venue"
},
  "geometry": {"coordinates":[-119.162358,34.277529],"type":"Point"}
}