{
  "type": "Feature",
  "properties": {
    "addr:full":"1503 McCormack Ave Sacramento CA 95811",
    "addr:housenumber":"1503",
    "addr:postcode":"95811",
    "addr:street":"Mccormack Ave",
    "iso:country":"US",
    "sg:address":"1503 McCormack Ave",
    "sg:city":"Sacramento",
    "sg:classifiers":[
        {
            "category":"Wholesale",
            "subcategory":"Motor Vehicles",
            "type":"Manufacturing & Wholesale Goods"
        }
    ],
    "sg:phone":"+1 916 447 9222",
    "sg:postcode":"95811",
    "sg:province":"CA",
    "sg:tags":[
        "trailer"
    ],
    "wof:name":"Tom's Refrigeration Svc",
    "wof:placetype":"venue"
},
  "geometry": {"coordinates":[-121.481639,38.591682],"type":"Point"}
}