{
  "type": "Feature",
  "properties": {
    "addr:full":"1390 Florin Rd Sacramento CA 95822",
    "addr:housenumber":"1390",
    "addr:postcode":"95822",
    "addr:street":"Florin Rd",
    "iso:country":"US",
    "sg:address":"1390 Florin Rd",
    "sg:city":"Sacramento",
    "sg:classifiers":[
        {
            "category":"Organizations",
            "subcategory":"Religious Organization",
            "type":"Services"
        }
    ],
    "sg:phone":"+1 916 422 0550",
    "sg:postcode":"95822",
    "sg:province":"CA",
    "sg:tags":[
        "church"
    ],
    "sg:website":"www.livingstonescrc.com",
    "wof:name":"Living Stones Christian Reform",
    "wof:placetype":"venue"
},
  "geometry": {"coordinates":[-121.505263,38.495567],"type":"Point"}
}