{
  "type": "Feature",
  "properties": {
    "addr:full":"1245 N. Spring St Los Angeles CA 90012",
    "addr:housenumber":"1245",
    "addr:postcode":"90012",
    "addr:street":"N. Spring St",
    "iso:country":"US",
    "sg:address":"1245 N. Spring St",
    "sg:city":"Los Angeles",
    "sg:classifiers":[
        {
            "category":"Arts & Performance",
            "subcategory":"Festival",
            "type":"Entertainment"
        }
    ],
    "sg:postcode":"90012",
    "sg:province":"CA",
    "sg:website":"www.newbelgium.com/events/tour-d...",
    "wof:name":"New Belgium Brewery Presents Tour de Fat",
    "wof:placetype":"venue"
},
  "geometry": {"coordinates":[-118.234275,34.066264],"type":"Point"}
}