{
  "type": "Feature",
  "properties": {
    "iso:country":"US",
    "sg:address":"17834 Chatsworth St",
    "sg:city":"Granada Hills",
    "sg:classifiers":[
        {
            "category":"Professional",
            "subcategory":"Accounting & Tax Preparation",
            "type":"Services"
        }
    ],
    "sg:phone":"+1 818 831 7881",
    "sg:postcode":"91344",
    "sg:province":"CA",
    "sg:tags":[
        "return",
        "filing"
    ],
    "wof:name":"I S Kroop",
    "wof:placetype":"venue"
},
  "geometry": {"coordinates":[-118.52286700000001,34.264826],"type":"Point"}
}