{
  "type": "Feature",
  "properties": {
    "addr:full":"2838 E Thousand Oaks Blvd Thousand Oaks CA 91362",
    "addr:housenumber":"2838",
    "addr:postcode":"91362",
    "addr:street":"E Thousand Oaks Blvd",
    "iso:country":"US",
    "sg:address":"2838 E Thousand Oaks Blvd",
    "sg:city":"Thousand Oaks",
    "sg:classifiers":[
        {
            "category":"Food & Beverages",
            "subcategory":"Bakery",
            "type":"Retail Goods"
        }
    ],
    "sg:phone":"+1 805 495 5509",
    "sg:postcode":"91362",
    "sg:province":"CA",
    "sg:tags":[
        "baker"
    ],
    "wof:name":"Plusko's Valley Bakery",
    "wof:placetype":"venue"
},
  "geometry": {"coordinates":[-118.83874,34.171143],"type":"Point"}
}