{
  "type": "Feature",
  "properties": {
    "addr:full":"6534 Easton St Los Angeles CA 90022",
    "addr:housenumber":"6534",
    "addr:postcode":"90022",
    "addr:street":"Easton St",
    "iso:country":"US",
    "sg:address":"6534 Easton St",
    "sg:city":"Los Angeles",
    "sg:classifiers":[
        {
            "category":"Wholesale",
            "subcategory":"Plants",
            "type":"Manufacturing & Wholesale Goods"
        }
    ],
    "sg:phone":"+1 323 887 9249",
    "sg:postcode":"90022",
    "sg:province":"CA",
    "sg:tags":[
        "supply"
    ],
    "wof:name":"Montana Wholesale Nursery",
    "wof:placetype":"venue"
},
  "geometry": {"coordinates":[-118.133849,34.012773],"type":"Point"}
}