{
  "type": "Feature",
  "properties": {
    "addr:full":"119 S Adams St Anaheim CA 92802",
    "addr:housenumber":"119",
    "addr:postcode":"92802",
    "addr:street":"S Adams St",
    "iso:country":"US",
    "sg:address":"119 S Adams St",
    "sg:city":"Anaheim",
    "sg:classifiers":[
        {
            "category":"Wholesale",
            "subcategory":"Construction Materials",
            "type":"Manufacturing & Wholesale Goods"
        }
    ],
    "sg:phone":"+1 714 630 8393",
    "sg:postcode":"92802",
    "sg:province":"CA",
    "sg:tags":[
        "marble"
    ],
    "wof:name":"Aram's Venetian Marble",
    "wof:placetype":"venue"
},
  "geometry": {"coordinates":[-117.932052,33.830547],"type":"Point"}
}