{
  "type": "Feature",
  "properties": {
    "addr:full":"1429 Lincoln Blvd Santa Monica CA 90401",
    "addr:housenumber":"1429",
    "addr:postcode":"90401",
    "addr:street":"Lincoln Blvd",
    "iso:country":"US",
    "sg:address":"1429 Lincoln Blvd",
    "sg:city":"Santa Monica",
    "sg:classifiers":[
        {
            "category":"Building & Trades",
            "subcategory":"Plumbing",
            "type":"Services"
        }
    ],
    "sg:phone":"+1 310 453 9595",
    "sg:postcode":"90401",
    "sg:province":"CA",
    "sg:tags":[
        "plumbing",
        "contractor"
    ],
    "wof:name":"Cast Iron Plumbing",
    "wof:placetype":"venue"
},
  "geometry": {"coordinates":[-118.49003999999999,34.018478],"type":"Point"}
}