{
  "type": "Feature",
  "properties": {
    "addr:full":"3700 Eastern Ave Sacramento CA 95821",
    "addr:housenumber":"3700",
    "addr:postcode":"95821",
    "addr:street":"Eastern Ave",
    "iso:country":"US",
    "sg:address":"3700 Eastern Ave",
    "sg:city":"Sacramento",
    "sg:classifiers":[
        {
            "category":"Professional",
            "type":"Services"
        }
    ],
    "sg:phone":"+1 916 488 8595",
    "sg:postcode":"95821",
    "sg:province":"CA",
    "wof:name":"Plaza Solada",
    "wof:placetype":"venue"
},
  "geometry": {"coordinates":[-121.36456,38.63409],"type":"Point"}
}