{
  "type": "Feature",
  "properties": {
    "iso:country":"US",
    "sg:address":"291 Auburn Folsom Rd",
    "sg:city":"Auburn",
    "sg:classifiers":[
        {
            "category":"Museum",
            "type":"Entertainment"
        }
    ],
    "sg:phone":"+1 530 823 3646",
    "sg:postcode":"95603",
    "sg:province":"CA",
    "sg:tags":[
        "organization",
        "arts",
        "information"
    ],
    "wof:name":"Gallery One-Placer Arts League",
    "wof:placetype":"venue"
},
  "geometry": {"coordinates":[-121.076369,38.894012],"type":"Point"}
}