{
  "type": "Feature",
  "properties": {
    "iso:country":"US",
    "sg:address":"1148 Magnolia Ave",
    "sg:city":"Los Angeles",
    "sg:classifiers":[
        {
            "category":"Banks & Credit Unions",
            "subcategory":"Investment Brokerage",
            "type":"Services"
        }
    ],
    "sg:phone":"+1 213 487 2045",
    "sg:postcode":"90006",
    "sg:province":"CA",
    "wof:name":"GBY Investment Inc",
    "wof:placetype":"venue"
},
  "geometry": {"coordinates":[-118.28645299999999,34.049938],"type":"Point"}
}