{
  "type": "Feature",
  "properties": {
    "iso:country":"US",
    "sg:address":"709 W Channel Islands Blvd",
    "sg:city":"Port Hueneme",
    "sg:classifiers":[
        {
            "category":"Manufacturing",
            "subcategory":"Printing",
            "type":"Manufacturing & Wholesale Goods"
        }
    ],
    "sg:phone":"+1 805 240 9277",
    "sg:postcode":"93041",
    "sg:province":"CA",
    "sg:tags":[
        "commercial"
    ],
    "wof:name":"Dgl Engraving",
    "wof:placetype":"venue"
},
  "geometry": {"coordinates":[-119.221312,34.175851],"type":"Point"}
}