{
  "type": "Feature",
  "properties": {
    "iso:country":"US",
    "sg:address":"26845 Jefferson Ave",
    "sg:city":"Murrieta",
    "sg:classifiers":[
        {
            "category":"Professional",
            "subcategory":"Business Services",
            "type":"Services"
        }
    ],
    "sg:phone":"+1 951 695 3349",
    "sg:postcode":"92562",
    "sg:province":"CA",
    "sg:tags":[
        "embroidery"
    ],
    "wof:name":"Stitch Pro",
    "wof:placetype":"venue"
},
  "geometry": {"coordinates":[-117.17481600000001,33.528889],"type":"Point"}
}