{
  "type": "Feature",
  "properties": {
    "iso:country":"US",
    "sg:address":"2302 Kimberly Ct",
    "sg:city":"Carlsbad",
    "sg:classifiers":[
        {
            "category":"Professional",
            "type":"Services"
        }
    ],
    "sg:phone":"+1 760 434 4022",
    "sg:postcode":"92008",
    "sg:province":"CA",
    "wof:name":"Off Bond Street LLP",
    "wof:placetype":"venue"
},
  "geometry": {"coordinates":[-117.324079,33.170619],"type":"Point"}
}