{
  "type": "Feature",
  "properties": {
    "addr:full":"3109 Alder Way West Sacramento CA 95691",
    "addr:housenumber":"3109",
    "addr:postcode":"95691",
    "addr:street":"Alder Way",
    "iso:country":"US",
    "sg:address":"3109 Alder Way",
    "sg:city":"West Sacramento",
    "sg:classifiers":[
        {
            "category":"Professional",
            "type":"Services"
        }
    ],
    "sg:phone":"+1 916 375 1122",
    "sg:postcode":"95691",
    "sg:province":"CA",
    "sg:website":"www.hoodlift.com",
    "wof:name":"Hoodlift",
    "wof:placetype":"venue"
},
  "geometry": {"coordinates":[-121.524244,38.542232],"type":"Point"}
}