{
  "type": "Feature",
  "properties": {
    "iso:country":"US",
    "sg:address":"218 E 17th St",
    "sg:city":"Costa Mesa",
    "sg:classifiers":[
        {
            "category":"Personal",
            "subcategory":"Nail Salon",
            "type":"Services"
        }
    ],
    "sg:phone":"+1 949 631 3488",
    "sg:postcode":"92627",
    "sg:province":"CA",
    "sg:website":"www.mimisnail.com",
    "wof:name":"Mimi's Nails & Spa",
    "wof:placetype":"venue"
},
  "geometry": {"coordinates":[-117.917933,33.63532],"type":"Point"}
}