{
  "type": "Feature",
  "properties": {
    "addr:full":"14572 Brookhurst Street Westminster CA 92683",
    "addr:housenumber":"14572",
    "addr:postcode":"92683",
    "addr:street":"Brookhurst Street",
    "iso:country":"US",
    "sg:address":"14572 Brookhurst Street",
    "sg:city":"Westminster",
    "sg:classifiers":[
        {
            "category":"Shopping",
            "subcategory":"Mobile Phones",
            "type":"Retail Goods"
        }
    ],
    "sg:phone":"+1 714 210 1881",
    "sg:postcode":"92683",
    "sg:province":"CA",
    "wof:name":"Cellu-Link",
    "wof:placetype":"venue"
},
  "geometry": {"coordinates":[-117.954958,33.751324],"type":"Point"}
}