{
  "type": "Feature",
  "properties": {
    "iso:country":"US",
    "sg:address":"763 Bridgeway",
    "sg:city":"Sausalito",
    "sg:classifiers":[
        {
            "category":"Wholesale",
            "subcategory":"Stationery",
            "type":"Manufacturing & Wholesale Goods"
        }
    ],
    "sg:phone":"+1 415 331 0377",
    "sg:postcode":"94965",
    "sg:province":"CA",
    "sg:tags":[
        "paper"
    ],
    "sg:website":"www.engsdesign.com",
    "wof:name":"Eng Design",
    "wof:placetype":"venue"
},
  "geometry": {"coordinates":[-122.480108,37.856577],"type":"Point"}
}