{
  "type": "Feature",
  "properties": {
    "iso:country":"US",
    "sg:address":"2414 Serviss St",
    "sg:city":"Durham",
    "sg:classifiers":[
        {
            "category":"Retail",
            "subcategory":"Animal Services",
            "type":"Services"
        }
    ],
    "sg:phone":"+1 530 345 3400",
    "sg:postcode":"95938",
    "sg:province":"CA",
    "wof:name":"Dirty Dogs No More",
    "wof:placetype":"venue"
},
  "geometry": {"coordinates":[-121.802726,39.638171],"type":"Point"}
}