{
  "type": "Feature",
  "properties": {
    "iso:country":"US",
    "sg:address":"1265 S Bascom Ave",
    "sg:city":"San Jose",
    "sg:classifiers":[
        {
            "category":"Restaurant",
            "type":"Food & Drink"
        }
    ],
    "sg:phone":"+1 408 278 9872",
    "sg:postcode":"95128",
    "sg:province":"CA",
    "wof:name":"Mr Chow Restaurant",
    "wof:placetype":"venue"
},
  "geometry": {"coordinates":[-121.93179600000001,37.303235],"type":"Point"}
}