{
  "type": "Feature",
  "properties": {
    "addr:full":"10838 Hole Ave Riverside CA 92505",
    "addr:housenumber":"10838",
    "addr:postcode":"92505",
    "addr:street":"Hole Ave",
    "iso:country":"US",
    "sg:address":"10838 Hole Ave",
    "sg:city":"Riverside",
    "sg:classifiers":[
        {
            "category":"Social Services",
            "type":"Services"
        },
        {
            "category":"Health Services",
            "subcategory":"Clinic",
            "type":"Services"
        }
    ],
    "sg:phone":"+1 951 687 7090",
    "sg:postcode":"92505",
    "sg:province":"CA",
    "sg:tags":[
        "information",
        "services-information",
        "program",
        "treatment",
        "referral",
        "alcoholism"
    ],
    "sg:website":"http://www.aa.org",
    "wof:name":"Alcoholicos Anonimos Riverside",
    "wof:placetype":"venue"
},
  "geometry": {"coordinates":[-117.48265600000001,33.918245],"type":"Point"}
}