{
  "type": "Feature",
  "properties": {
    "iso:country":"US",
    "sg:address":"1550 Apple Orchard Ln",
    "sg:city":"San Luis Obispo",
    "sg:classifiers":[
        {
            "category":"Building & Trades",
            "subcategory":"Construction",
            "type":"Services"
        }
    ],
    "sg:phone":"+1 805 595 2525",
    "sg:postcode":"93405",
    "sg:province":"CA",
    "sg:tags":[
        "designer"
    ],
    "wof:name":"Design Resource Group",
    "wof:placetype":"venue"
},
  "geometry": {"coordinates":[-120.718008,35.189739],"type":"Point"}
}