{
  "type": "Feature",
  "properties": {
    "addr:full":"2021 E Via Burton Ste C Fullerton CA 92806",
    "addr:housenumber":"2021",
    "addr:postcode":"92806",
    "addr:street":"E Via Burton Ste C",
    "iso:country":"US",
    "sg:address":"2021 E Via Burton Ste C",
    "sg:city":"Fullerton",
    "sg:classifiers":[
        {
            "category":"Building & Trades",
            "subcategory":"Electrical",
            "type":"Services"
        }
    ],
    "sg:phone":"+1 714 738 3053",
    "sg:postcode":"92806",
    "sg:province":"CA",
    "sg:tags":[
        "electrician"
    ],
    "wof:name":"Saber Electric Co",
    "wof:placetype":"venue"
},
  "geometry": {"coordinates":[-117.88820699999999,33.856609],"type":"Point"}
}