{
  "type": "Feature",
  "properties": {
    "addr:full":"2640 Mercantile Dr Rancho Cordova CA 95742",
    "addr:housenumber":"2640",
    "addr:postcode":"95742",
    "addr:street":"Mercantile Dr",
    "iso:country":"US",
    "sg:address":"2640 Mercantile Dr",
    "sg:city":"Rancho Cordova",
    "sg:classifiers":[
        {
            "category":"Wholesale",
            "subcategory":"Durable Goods & Equipment",
            "type":"Manufacturing & Wholesale Goods"
        }
    ],
    "sg:phone":"+1 916 635 1444",
    "sg:postcode":"95742",
    "sg:province":"CA",
    "sg:tags":[
        "representative",
        "manufacturer"
    ],
    "wof:name":"Capri Sales",
    "wof:placetype":"venue"
},
  "geometry": {"coordinates":[-121.261095,38.604396],"type":"Point"}
}