{
  "type": "Feature",
  "properties": {
    "addr:full":"1740 E Garry Ave Santa Ana CA 92705",
    "addr:housenumber":"1740",
    "addr:postcode":"92705",
    "addr:street":"E Garry Ave",
    "iso:country":"US",
    "sg:address":"1740 E Garry Ave",
    "sg:city":"Santa Ana",
    "sg:classifiers":[
        {
            "category":"Insurance",
            "subcategory":"Insurance Agent",
            "type":"Services"
        }
    ],
    "sg:phone":"+1 949 770 1219",
    "sg:postcode":"92705",
    "sg:province":"CA",
    "wof:name":"Sirisant Larsen Insurance Svcs",
    "wof:placetype":"venue"
},
  "geometry": {"coordinates":[-117.85301800000001,33.704874],"type":"Point"}
}