{
  "type": "Feature",
  "properties": {
    "addr:full":"2836 Santa Monica Blvd Santa Monica CA 90404",
    "addr:housenumber":"2836",
    "addr:postcode":"90404",
    "addr:street":"Santa Monica Blvd",
    "iso:country":"US",
    "sg:address":"2836 Santa Monica Blvd",
    "sg:city":"Santa Monica",
    "sg:classifiers":[
        {
            "category":"Restaurant",
            "type":"Food & Drink"
        }
    ],
    "sg:phone":"+1 310 828 5567",
    "sg:postcode":"90404",
    "sg:province":"CA",
    "wof:name":"Neeta's India Fiji Food",
    "wof:placetype":"venue"
},
  "geometry": {"coordinates":[-118.471745,34.035217],"type":"Point"}
}