{
  "type": "Feature",
  "properties": {
    "addr:full":"8038 Haven Ave Rancho Cucamonga CA 91730",
    "addr:housenumber":"8038",
    "addr:postcode":"91730",
    "addr:street":"Haven Ave",
    "iso:country":"US",
    "sg:address":"8038 Haven Ave",
    "sg:city":"Rancho Cucamonga",
    "sg:classifiers":[
        {
            "category":"Banks & Credit Unions",
            "subcategory":"Investment Brokerage",
            "type":"Services"
        }
    ],
    "sg:phone":"+1 909 944 0888",
    "sg:postcode":"91730",
    "sg:province":"CA",
    "sg:tags":[
        "security"
    ],
    "wof:name":"Edward Jones Co",
    "wof:placetype":"venue"
},
  "geometry": {"coordinates":[-117.57592200000001,34.109361],"type":"Point"}
}