{
  "type": "Feature",
  "properties": {
    "iso:country":"US",
    "sg:address":"3003 Peerless Ave",
    "sg:city":"Bakersfield",
    "sg:classifiers":[
        {
            "category":"Manufacturing",
            "subcategory":"Glass & Minerals",
            "type":"Manufacturing & Wholesale Goods"
        }
    ],
    "sg:phone":"+1 661 703 1889",
    "sg:postcode":"93308",
    "sg:province":"CA",
    "sg:tags":[
        "plate",
        "window",
        "glass-auto"
    ],
    "wof:name":"Affordable Glass",
    "wof:placetype":"venue"
},
  "geometry": {"coordinates":[-119.01985500000001,35.434012],"type":"Point"}
}