{
  "type": "Feature",
  "properties": {
    "iso:country":"US",
    "sg:address":"21901 Horizon Ct",
    "sg:city":"Tehachapi",
    "sg:classifiers":[
        {
            "category":"Building & Trades",
            "subcategory":"Landscaping Services",
            "type":"Services"
        }
    ],
    "sg:phone":"+1 661 821 6476",
    "sg:postcode":"93561",
    "sg:province":"CA",
    "wof:name":"J&J Sales Inc",
    "wof:placetype":"venue"
},
  "geometry": {"coordinates":[-118.624225,35.135074],"type":"Point"}
}