{
  "type": "Feature",
  "properties": {
    "addr:full":"535 White Birch Dr Windsor CA 95492",
    "addr:housenumber":"535",
    "addr:postcode":"95492",
    "addr:street":"White Birch Dr",
    "iso:country":"US",
    "sg:address":"535 White Birch Dr",
    "sg:city":"Windsor",
    "sg:classifiers":[
        {
            "category":"Building & Trades",
            "subcategory":"Construction",
            "type":"Services"
        }
    ],
    "sg:phone":"+1 707 836 8901",
    "sg:postcode":"95492",
    "sg:province":"CA",
    "sg:tags":[
        "concrete",
        "contractor"
    ],
    "wof:name":"Shoreline",
    "wof:placetype":"venue"
},
  "geometry": {"coordinates":[-122.796223,38.544555],"type":"Point"}
}