{
  "type": "Feature",
  "properties": {
    "addr:full":"441 Laurel Ave San Anselmo CA 94960",
    "addr:housenumber":"441",
    "addr:postcode":"94960",
    "addr:street":"Laurel Ave",
    "iso:country":"US",
    "sg:address":"441 Laurel Ave",
    "sg:city":"San Anselmo",
    "sg:classifiers":[
        {
            "category":"Professional",
            "type":"Services"
        }
    ],
    "sg:phone":"+1 415 721 0274",
    "sg:postcode":"94960",
    "sg:province":"CA",
    "sg:tags":[
        "establishment"
    ],
    "wof:name":"Pwma Group",
    "wof:placetype":"venue"
},
  "geometry": {"coordinates":[-122.576193,37.973054],"type":"Point"}
}