{
  "type": "Feature",
  "properties": {
    "addr:full":"3849 N Fine Ave Fresno CA 93727",
    "addr:housenumber":"3849",
    "addr:postcode":"93727",
    "addr:street":"N Fine Ave",
    "iso:country":"US",
    "sg:address":"3849 N Fine Ave",
    "sg:city":"Fresno",
    "sg:classifiers":[
        {
            "category":"Wholesale",
            "subcategory":"Auto Parts",
            "type":"Manufacturing & Wholesale Goods"
        }
    ],
    "sg:phone":"+1 559 292 7851",
    "sg:postcode":"93727",
    "sg:province":"CA",
    "sg:tags":[
        "automobile"
    ],
    "wof:name":"Automotive Electronic",
    "wof:placetype":"venue"
},
  "geometry": {"coordinates":[-119.729946,36.787412],"type":"Point"}
}