{
  "type": "Feature",
  "properties": {
    "iso:country":"US",
    "sg:address":"19275 Sonoma Hwy",
    "sg:city":"Sonoma",
    "sg:classifiers":[
        {
            "category":"Real Estate",
            "subcategory":"Real Estate Operator",
            "type":"Services"
        }
    ],
    "sg:phone":"+1 707 996 3833",
    "sg:postcode":"95476",
    "sg:province":"CA",
    "sg:tags":[
        "mobile",
        "home",
        "community"
    ],
    "wof:name":"Rancho De Sonoma",
    "wof:placetype":"venue"
},
  "geometry": {"coordinates":[-122.475256,38.298801],"type":"Point"}
}