{
  "type": "Feature",
  "properties": {
    "iso:country":"US",
    "sg:address":"85 S Baldwin Ave",
    "sg:city":"Sierra Madre",
    "sg:classifiers":[
        {
            "category":"Shopping",
            "subcategory":"Florist",
            "type":"Retail Goods"
        }
    ],
    "sg:phone":"+1 626 355 2019",
    "sg:postcode":"91024",
    "sg:province":"CA",
    "wof:name":"Donna Embree Specialty Florist",
    "wof:placetype":"venue"
},
  "geometry": {"coordinates":[-118.29338,34.160347],"type":"Point"}
}