{
  "type": "Feature",
  "properties": {
    "iso:country":"US",
    "sg:address":"3228 W Rosecrans Ave",
    "sg:city":"Hawthorne",
    "sg:classifiers":[
        {
            "category":"Building & Trades",
            "subcategory":"Electrical",
            "type":"Services"
        },
        {
            "category":"Retail",
            "subcategory":"Auto Repair",
            "type":"Services"
        }
    ],
    "sg:phone":"+1 310 675 8466",
    "sg:postcode":"90250",
    "sg:province":"CA",
    "sg:tags":[
        "automobile",
        "electrician",
        "electric"
    ],
    "wof:name":"N & A Auto Electric & Air Condition Service",
    "wof:placetype":"venue"
},
  "geometry": {"coordinates":[-118.329318,33.901932],"type":"Point"}
}