{
  "type": "Feature",
  "properties": {
    "iso:country":"US",
    "sg:address":"6324 Temple City Blvd",
    "sg:city":"Temple City",
    "sg:classifiers":[
        {
            "category":"Manufacturing",
            "subcategory":"Apparel",
            "type":"Manufacturing & Wholesale Goods"
        }
    ],
    "sg:phone":"+1 626 286 9642",
    "sg:postcode":"91780",
    "sg:province":"CA",
    "sg:tags":[
        "drapery",
        "contractor"
    ],
    "wof:name":"Fitzgerald General Drapery Svc",
    "wof:placetype":"venue"
},
  "geometry": {"coordinates":[-118.062377,34.114411],"type":"Point"}
}