{
  "type": "Feature",
  "properties": {
    "addr:full":"245 Fischer Ave Costa Mesa CA 92626",
    "addr:housenumber":"245",
    "addr:postcode":"92626",
    "addr:street":"Fischer Ave",
    "iso:country":"US",
    "sg:address":"245 Fischer Ave",
    "sg:city":"Costa Mesa",
    "sg:classifiers":[
        {
            "category":"Real Estate",
            "subcategory":"Real Estate Agent",
            "type":"Services"
        }
    ],
    "sg:phone":"+1 714 428 0100",
    "sg:postcode":"92626",
    "sg:province":"CA",
    "wof:name":"Gateway Title Co",
    "wof:placetype":"venue"
},
  "geometry": {"coordinates":[-117.87963000000001,33.675803],"type":"Point"}
}