{
  "type": "Feature",
  "properties": {
    "addr:full":"2001 K St Ste F Sacramento CA 95811",
    "addr:housenumber":"2001",
    "addr:postcode":"95811",
    "addr:street":"K St Ste F",
    "iso:country":"US",
    "sg:address":"2001 K St Ste F",
    "sg:city":"Sacramento",
    "sg:classifiers":[
        {
            "category":"Professional",
            "subcategory":"Art Services",
            "type":"Services"
        },
        {
            "category":"Communications",
            "type":"Services"
        }
    ],
    "sg:phone":"+1 916 444 6255",
    "sg:postcode":"95811",
    "sg:province":"CA",
    "sg:tags":[
        "web",
        "graphic",
        "design"
    ],
    "sg:website":"www.joeblo.net",
    "wof:name":"Joe Blo Advertising & Design",
    "wof:placetype":"venue"
},
  "geometry": {"coordinates":[-121.47996999999999,38.575835],"type":"Point"}
}