{
  "type": "Feature",
  "properties": {
    "addr:full":"2525 Westminster Ave Ste C Santa Ana CA 92706",
    "addr:housenumber":"2525",
    "addr:postcode":"92706",
    "addr:street":"Westminster Ave Ste C",
    "iso:country":"US",
    "sg:address":"2525 Westminster Ave Ste C",
    "sg:city":"Santa Ana",
    "sg:classifiers":[
        {
            "category":"Personal",
            "subcategory":"Nail Salon",
            "type":"Services"
        }
    ],
    "sg:phone":"+1 714 554 8135",
    "sg:postcode":"92706",
    "sg:province":"CA",
    "wof:name":"In-Styles Hair & Nails Beauty Salon",
    "wof:placetype":"venue"
},
  "geometry": {"coordinates":[-117.90300000000001,33.759998],"type":"Point"}
}