{
  "type": "Feature",
  "properties": {
    "iso:country":"US",
    "sg:address":"816 el Terino Ave",
    "sg:city":"Modesto",
    "sg:classifiers":[
        {
            "category":"Home & Garden",
            "subcategory":"Building Materials",
            "type":"Retail Goods"
        }
    ],
    "sg:phone":"+1 209 529 6004",
    "sg:postcode":"95350",
    "sg:province":"CA",
    "sg:tags":[
        "decorative",
        "glass"
    ],
    "wof:name":"Custom Art Glass",
    "wof:placetype":"venue"
},
  "geometry": {"coordinates":[-120.978345,37.65362],"type":"Point"}
}