{
  "type": "Feature",
  "properties": {
    "addr:full":"15694 Allison Ranch Rd Grass Valley CA 95949",
    "addr:housenumber":"15694",
    "addr:postcode":"95949",
    "addr:street":"Allison Ranch Rd",
    "iso:country":"US",
    "sg:address":"15694 Allison Ranch Rd",
    "sg:city":"Grass Valley",
    "sg:classifiers":[
        {
            "category":"Organizations",
            "subcategory":"Community Association",
            "type":"Services"
        }
    ],
    "sg:phone":"+1 530 273 1070",
    "sg:postcode":"95949",
    "sg:province":"CA",
    "sg:tags":[
        "fraternal"
    ],
    "wof:name":"Loyal Order Of Moose",
    "wof:placetype":"venue"
},
  "geometry": {"coordinates":[-121.06366800000001,39.156131],"type":"Point"}
}