{
  "type": "Feature",
  "properties": {
    "iso:country":"US",
    "sg:address":"701 Fairgrounds Dr",
    "sg:city":"Sacramento",
    "sg:classifiers":[
        {
            "category":"Personal",
            "subcategory":"Beauty Salon",
            "type":"Services"
        }
    ],
    "sg:phone":"+1 916 455 8457",
    "sg:postcode":"95817",
    "sg:province":"CA",
    "wof:name":"Klip & Kurl",
    "wof:placetype":"venue"
},
  "geometry": {"coordinates":[-121.44059799999999,38.549546],"type":"Point"}
}