{
  "type": "Feature",
  "properties": {
    "addr:full":"2760 E Trimble Road San Jose CA 95132",
    "addr:housenumber":"2760",
    "addr:postcode":"95132",
    "addr:street":"E Trimble Road",
    "iso:country":"US",
    "sg:address":"2760 E Trimble Road",
    "sg:city":"San Jose",
    "sg:classifiers":[
        {
            "category":"Education",
            "subcategory":"School",
            "type":"Public Place"
        }
    ],
    "sg:phone":"+1 408 923 1940",
    "sg:postcode":"95132",
    "sg:province":"CA",
    "sg:tags":[
        "high",
        "middle",
        "elementary"
    ],
    "wof:name":"Berryessa Union School District",
    "wof:placetype":"venue"
},
  "geometry": {"coordinates":[-121.881812,37.409497],"type":"Point"}
}