{
  "type": "Feature",
  "properties": {
    "iso:country":"US",
    "sg:address":"2151 Amanda Ln",
    "sg:city":"Escondido",
    "sg:classifiers":[
        {
            "category":"Manufacturing",
            "subcategory":"Apparel",
            "type":"Manufacturing & Wholesale Goods"
        }
    ],
    "sg:phone":"+1 619 339 2437",
    "sg:postcode":"92029",
    "sg:province":"CA",
    "sg:tags":[
        "work",
        "clothing",
        "mfg"
    ],
    "wof:name":"Starsuit",
    "wof:placetype":"venue"
},
  "geometry": {"coordinates":[-117.099256,33.095628],"type":"Point"}
}