{
  "type": "Feature",
  "properties": {
    "addr:full":"8118 West Ln Stockton CA 95210",
    "addr:housenumber":"8118",
    "addr:postcode":"95210",
    "addr:street":"West Ln",
    "iso:country":"US",
    "sg:address":"8118 West Ln",
    "sg:city":"Stockton",
    "sg:classifiers":[
        {
            "category":"Food & Beverages",
            "subcategory":"Groceries & Convenience Stores",
            "type":"Retail Goods"
        }
    ],
    "sg:phone":"+1 209 478 0422",
    "sg:postcode":"95210",
    "sg:province":"CA",
    "sg:tags":[
        "grocer"
    ],
    "wof:name":"A J Mart",
    "wof:placetype":"venue"
},
  "geometry": {"coordinates":[-121.29482400000001,38.02301],"type":"Point"}
}