{
  "type": "Feature",
  "properties": {
    "addr:full":"9580 Oak Avenue Pkwy Folsom CA 95630",
    "addr:housenumber":"9580",
    "addr:postcode":"95630",
    "addr:street":"Oak Avenue Pkwy",
    "iso:country":"US",
    "sg:address":"9580 Oak Avenue Pkwy",
    "sg:city":"Folsom",
    "sg:classifiers":[
        {
            "category":"Building & Trades",
            "subcategory":"Construction",
            "type":"Services"
        }
    ],
    "sg:phone":"+1 916 989 2834",
    "sg:postcode":"95630",
    "sg:province":"CA",
    "sg:tags":[
        "general",
        "contractor"
    ],
    "wof:name":"Classic Co",
    "wof:placetype":"venue"
},
  "geometry": {"coordinates":[-121.192633,38.699664],"type":"Point"}
}