{
  "type": "Feature",
  "properties": {
    "addr:full":"2951 G St Merced CA 95340",
    "addr:housenumber":"2951",
    "addr:postcode":"95340",
    "addr:street":"G St",
    "iso:country":"US",
    "sg:address":"2951 G St",
    "sg:city":"Merced",
    "sg:classifiers":[
        {
            "category":"Personal",
            "type":"Services"
        },
        {
            "category":"Arena",
            "subcategory":"Sports Club",
            "type":"Entertainment"
        }
    ],
    "sg:phone":"+1 209 723 3377",
    "sg:postcode":"95340",
    "sg:province":"CA",
    "sg:tags":[
        "trainer",
        "consultant",
        "physical",
        "health",
        "fitness"
    ],
    "sg:website":"http://www.inshapeclubs.com",
    "wof:name":"In Shape City",
    "wof:placetype":"venue"
},
  "geometry": {"coordinates":[-120.46946,37.31324],"type":"Point"}
}