{
  "type": "Feature",
  "properties": {
    "addr:full":"16206 Pioneer Blvd Norwalk CA 90650",
    "addr:housenumber":"16206",
    "addr:postcode":"90650",
    "addr:street":"Pioneer Blvd",
    "iso:country":"US",
    "sg:address":"16206 Pioneer Blvd",
    "sg:city":"Norwalk",
    "sg:classifiers":[
        {
            "category":"Personal",
            "subcategory":"Beauty Salon",
            "type":"Services"
        }
    ],
    "sg:phone":"+1 562 921 0992",
    "sg:postcode":"90650",
    "sg:province":"CA",
    "sg:tags":[
        "nail"
    ],
    "wof:name":"Chiki's Salon",
    "wof:placetype":"venue"
},
  "geometry": {"coordinates":[-118.083,33.883999],"type":"Point"}
}