{
  "type": "Feature",
  "properties": {
    "iso:country":"US",
    "sg:address":"2850 Goodwater Ave",
    "sg:city":"Redding",
    "sg:classifiers":[
        {
            "category":"Professional",
            "subcategory":"Business Services",
            "type":"Services"
        }
    ],
    "sg:phone":"+1 530 224 1607",
    "sg:postcode":"96002",
    "sg:province":"CA",
    "wof:name":"Business 2 Business Ent",
    "wof:placetype":"venue"
},
  "geometry": {"coordinates":[-122.31479,40.565385],"type":"Point"}
}