{
  "type": "Feature",
  "properties": {
    "iso:country":"US",
    "sg:address":"111 N Rengstorff Ave.",
    "sg:city":"Mountain View",
    "sg:classifiers":[
        {
            "category":"Real Estate",
            "subcategory":"Real Estate Operator",
            "type":"Services"
        }
    ],
    "sg:phone":"+1 866 491 3430",
    "sg:postcode":"94043",
    "sg:province":"CA",
    "sg:tags":[
        "apartment"
    ],
    "sg:website":"www.Liveatnorthpark.com",
    "wof:name":"North Park Apartments",
    "wof:placetype":"venue"
},
  "geometry": {"coordinates":[-122.096273,37.40469],"type":"Point"}
}