{
  "type": "Feature",
  "properties": {
    "addr:full":"1525 Douglas St Red Bluff CA 96080",
    "addr:housenumber":"1525",
    "addr:postcode":"96080",
    "addr:street":"Douglas St",
    "iso:country":"US",
    "sg:address":"1525 Douglas St",
    "sg:city":"Red Bluff",
    "sg:classifiers":[
        {
            "category":"Education",
            "subcategory":"School",
            "type":"Public Place"
        }
    ],
    "sg:phone":"+1 530 529 8700",
    "sg:postcode":"96080",
    "sg:province":"CA",
    "wof:name":"Red Bluff Union High Schl Dist",
    "wof:placetype":"venue"
},
  "geometry": {"coordinates":[-122.253209,40.178139],"type":"Point"}
}