{
  "type": "Feature",
  "properties": {
    "iso:country":"US",
    "sg:address":"476 E Lassen Ave",
    "sg:city":"Chico",
    "sg:classifiers":[
        {
            "category":"Real Estate",
            "subcategory":"Real Estate Operator",
            "type":"Services"
        }
    ],
    "sg:phone":"+1 530 894 3036",
    "sg:postcode":"95973",
    "sg:province":"CA",
    "sg:tags":[
        "apartment"
    ],
    "wof:name":"Joshua Tree Apartments",
    "wof:placetype":"venue"
},
  "geometry": {"coordinates":[-121.859648,39.764463],"type":"Point"}
}