{
  "type": "Feature",
  "properties": {
    "addr:full":"34220 Whitehead Ln Fremont CA 94555",
    "addr:housenumber":"34220",
    "addr:postcode":"94555",
    "addr:street":"Whitehead Ln",
    "iso:country":"US",
    "sg:address":"34220 Whitehead Ln",
    "sg:city":"Fremont",
    "sg:classifiers":[
        {
            "category":"Professional",
            "type":"Services"
        }
    ],
    "sg:phone":"+1 510 797 3427",
    "sg:postcode":"94555",
    "sg:province":"CA",
    "wof:name":"M&B Call High Tech Comm",
    "wof:placetype":"venue"
},
  "geometry": {"coordinates":[-122.033113,37.582274],"type":"Point"}
}