{
  "type": "Feature",
  "properties": {
    "iso:country":"US",
    "sg:address":"437 S Robertson Boulevard",
    "sg:city":"Beverly Hills",
    "sg:classifiers":[
        {
            "category":"Health Services",
            "subcategory":"Clinic",
            "type":"Services"
        }
    ],
    "sg:phone":"+1 310 274 2148",
    "sg:postcode":"90211",
    "sg:province":"CA",
    "sg:tags":[
        "medical"
    ],
    "wof:name":"Hearing Help Providers",
    "wof:placetype":"venue"
},
  "geometry": {"coordinates":[-118.3835,34.059317],"type":"Point"}
}