{
  "type": "Feature",
  "properties": {
    "addr:full":"1140 S De Anza Blvd San Jose CA 95129",
    "addr:housenumber":"1140",
    "addr:postcode":"95129",
    "addr:street":"S De Anza Blvd",
    "iso:country":"US",
    "sg:address":"1140 S De Anza Blvd",
    "sg:city":"San Jose",
    "sg:classifiers":[
        {
            "category":"Shopping",
            "subcategory":"Bicycles & Sporting Goods",
            "type":"Retail Goods"
        },
        {
            "category":"Recreation",
            "subcategory":"Fishing",
            "type":"Entertainment"
        }
    ],
    "sg:phone":"+1 408 873 0113",
    "sg:postcode":"95129",
    "sg:province":"CA",
    "sg:tags":[
        "outdoor",
        "gear"
    ],
    "wof:name":"Fishermans Warehouse Delta Bait & Tackle",
    "wof:placetype":"venue"
},
  "geometry": {"coordinates":[-122.03211400000001,37.304578],"type":"Point"}
}