{
  "type": "Feature",
  "properties": {
    "addr:full":"911 W Carlos St Alturas CA 96101",
    "addr:housenumber":"911",
    "addr:postcode":"96101",
    "addr:street":"W Carlos St",
    "iso:country":"US",
    "sg:address":"911 W Carlos St",
    "sg:city":"Alturas",
    "sg:classifiers":[
        {
            "category":"Personal",
            "subcategory":"Beauty Salon",
            "type":"Services"
        }
    ],
    "sg:phone":"+1 530 233 7090",
    "sg:postcode":"96101",
    "sg:province":"CA",
    "wof:name":"Images",
    "wof:placetype":"venue"
},
  "geometry": {"coordinates":[-120.55515800000001,41.481845],"type":"Point"}
}