{
  "type": "Feature",
  "properties": {
    "iso:country":"US",
    "sg:address":"7297 Navajo Rd",
    "sg:city":"San Diego",
    "sg:classifiers":[
        {
            "category":"Travel",
            "subcategory":"Travel Agent",
            "type":"Entertainment"
        }
    ],
    "sg:phone":"+1 619 589 6700",
    "sg:postcode":"92119",
    "sg:province":"CA",
    "sg:tags":[
        "agency"
    ],
    "wof:name":"Travel Design International",
    "wof:placetype":"venue"
},
  "geometry": {"coordinates":[-117.04581399999999,32.803828],"type":"Point"}
}