{
  "type": "Feature",
  "properties": {
    "iso:country":"US",
    "sg:address":"440 River Rd Ste J",
    "sg:city":"Corona",
    "sg:classifiers":[
        {
            "category":"Bakery",
            "type":"Food & Drink"
        }
    ],
    "sg:phone":"+1 951 736 3001",
    "sg:postcode":"92880",
    "sg:province":"CA",
    "sg:website":"http://www.interstatebakeriescorp.com",
    "wof:name":"Wonder Hostess Bakery",
    "wof:placetype":"venue"
},
  "geometry": {"coordinates":[-117.568558,33.892349],"type":"Point"}
}