{
  "type": "Feature",
  "properties": {
    "addr:full":"9008 Artesia Blvd Bellflower CA 90706",
    "addr:housenumber":"9008",
    "addr:postcode":"90706",
    "addr:street":"Artesia Blvd",
    "iso:country":"US",
    "sg:address":"9008 Artesia Blvd",
    "sg:city":"Bellflower",
    "sg:classifiers":[
        {
            "category":"Restaurant",
            "type":"Food & Drink"
        }
    ],
    "sg:phone":"+1 562 867 8017",
    "sg:postcode":"90706",
    "sg:province":"CA",
    "sg:tags":[
        "thai"
    ],
    "wof:name":"Thai Kitchen Express",
    "wof:placetype":"venue"
},
  "geometry": {"coordinates":[-118.14209700000001,33.874671],"type":"Point"}
}