{
  "type": "Feature",
  "properties": {
    "iso:country":"US",
    "sg:address":"13025 S Normandie Ave",
    "sg:city":"Gardena",
    "sg:classifiers":[
        {
            "category":"Manufacturing",
            "subcategory":"Metals",
            "type":"Manufacturing & Wholesale Goods"
        }
    ],
    "sg:phone":"+1 310 532 9794",
    "sg:postcode":"90249",
    "sg:province":"CA",
    "sg:tags":[
        "stampings",
        "mfg"
    ],
    "wof:name":"S R D Stamping",
    "wof:placetype":"venue"
},
  "geometry": {"coordinates":[-118.300443,33.914025],"type":"Point"}
}