{
  "type": "Feature",
  "properties": {
    "addr:full":"10132 Balboa Blvd Granada Hills CA 91344",
    "addr:housenumber":"10132",
    "addr:postcode":"91344",
    "addr:street":"Balboa Blvd",
    "iso:country":"US",
    "sg:address":"10132 Balboa Blvd",
    "sg:city":"Granada Hills",
    "sg:classifiers":[
        {
            "category":"Shopping",
            "subcategory":"Shoes",
            "type":"Retail Goods"
        }
    ],
    "sg:phone":"+1 818 363 5700",
    "sg:postcode":"91344",
    "sg:province":"CA",
    "sg:tags":[
        "parlor",
        "shoe"
    ],
    "wof:name":"Noel Shoe Repair",
    "wof:placetype":"venue"
},
  "geometry": {"coordinates":[-118.502269,34.256482],"type":"Point"}
}