{
  "type": "Feature",
  "properties": {
    "addr:full":"13359 Ventura Blvd Sherman Oaks CA 91423",
    "addr:housenumber":"13359",
    "addr:postcode":"91423",
    "addr:street":"Ventura Blvd",
    "iso:country":"US",
    "sg:address":"13359 Ventura Blvd",
    "sg:city":"Sherman Oaks",
    "sg:classifiers":[
        {
            "category":"Restaurant",
            "type":"Food & Drink"
        }
    ],
    "sg:phone":"+1 818 501 0181",
    "sg:postcode":"91423",
    "sg:province":"CA",
    "wof:name":"Fondue French Restaurant & Bar",
    "wof:placetype":"venue"
},
  "geometry": {"coordinates":[-118.42450700000001,34.146971],"type":"Point"}
}