{
  "type": "Feature",
  "properties": {
    "iso:country":"US",
    "sg:address":"8666 W Stockton Blvd",
    "sg:city":"Sacramento",
    "sg:classifiers":[
        {
            "category":"Retail",
            "subcategory":"Storage",
            "type":"Services"
        }
    ],
    "sg:phone":"+1 916 689 8629",
    "sg:postcode":"95814",
    "sg:province":"CA",
    "sg:tags":[
        "self"
    ],
    "sg:website":"www.sentrystorage.com",
    "wof:name":"Storage Sentry",
    "wof:placetype":"venue"
},
  "geometry": {"coordinates":[-121.491997,38.577599],"type":"Point"}
}