{
  "type": "Feature",
  "properties": {
    "iso:country":"US",
    "sg:address":"18025 Pioneer Blvd",
    "sg:city":"Artesia",
    "sg:classifiers":[
        {
            "category":"Health Services",
            "subcategory":"Nursing And Care Facility",
            "type":"Services"
        }
    ],
    "sg:phone":"+1 562 860 3351",
    "sg:postcode":"90701",
    "sg:province":"CA",
    "sg:tags":[
        "home",
        "medical",
        "rest"
    ],
    "wof:name":"Founder's House Of Hope",
    "wof:placetype":"venue"
},
  "geometry": {"coordinates":[-118.082835,33.866768],"type":"Point"}
}