{
  "type": "Feature",
  "properties": {
    "iso:country":"US",
    "sg:address":"7323 Winnetka Ave",
    "sg:city":"Winnetka",
    "sg:classifiers":[
        {
            "category":"Shopping",
            "subcategory":"Clothing, Apparel, & Fashions",
            "type":"Retail Goods"
        }
    ],
    "sg:phone":"+1 818 668 4448",
    "sg:postcode":"91306",
    "sg:province":"CA",
    "sg:tags":[
        "apparel",
        "women's"
    ],
    "wof:name":"Lady'qs Fashion",
    "wof:placetype":"venue"
},
  "geometry": {"coordinates":[-118.570993,34.203747],"type":"Point"}
}