{
  "type": "Feature",
  "properties": {
    "addr:full":"39867 Fremont Blvd Fremont CA 94538",
    "addr:housenumber":"39867",
    "addr:postcode":"94538",
    "addr:street":"Fremont Blvd",
    "iso:country":"US",
    "sg:address":"39867 Fremont Blvd",
    "sg:city":"Fremont",
    "sg:classifiers":[
        {
            "category":"Building & Trades",
            "subcategory":"Cleaning & Sanitation",
            "type":"Services"
        }
    ],
    "sg:phone":"+1 510 226 1085",
    "sg:postcode":"94538",
    "sg:province":"CA",
    "sg:tags":[
        "janitor"
    ],
    "wof:name":"You'Ve Got It Maid",
    "wof:placetype":"venue"
},
  "geometry": {"coordinates":[-121.974762,37.54145],"type":"Point"}
}