{
  "type": "Feature",
  "properties": {
    "iso:country":"US",
    "sg:address":"3938 Cerritos Ave",
    "sg:city":"Los Alamitos",
    "sg:classifiers":[
        {
            "category":"Home & Garden",
            "subcategory":"Home Furnishings",
            "type":"Retail Goods"
        },
        {
            "category":"Home & Garden",
            "subcategory":"Furniture",
            "type":"Retail Goods"
        }
    ],
    "sg:phone":"+1 562 493 5899",
    "sg:postcode":"90720",
    "sg:province":"CA",
    "sg:tags":[
        "decor",
        "store"
    ],
    "sg:website":"www.thecozygreenchair.com",
    "wof:name":"Chartreuse",
    "wof:placetype":"venue"
},
  "geometry": {"coordinates":[-118.063362,33.81027],"type":"Point"}
}