{
  "type": "Feature",
  "properties": {
    "addr:full":"856 Hillside Ave Albany CA 94706",
    "addr:housenumber":"856",
    "addr:postcode":"94706",
    "addr:street":"Hillside Ave",
    "iso:country":"US",
    "sg:address":"856 Hillside Ave",
    "sg:city":"Albany",
    "sg:classifiers":[
        {
            "category":"Health Services",
            "subcategory":"Doctor",
            "type":"Services"
        }
    ],
    "sg:phone":"+1 510 525 3745",
    "sg:postcode":"94706",
    "sg:province":"CA",
    "sg:tags":[
        "physician",
        "surgeon"
    ],
    "wof:name":"Byong Ki You",
    "wof:placetype":"venue"
},
  "geometry": {"coordinates":[-122.304107,37.891333],"type":"Point"}
}