{
  "type": "Feature",
  "properties": {
    "iso:country":"US",
    "sg:address":"4727 Artesia Boulevard",
    "sg:city":"Lawndale",
    "sg:classifiers":[
        {
            "category":"Shopping",
            "subcategory":"Computers & Home Electronics",
            "type":"Retail Goods"
        }
    ],
    "sg:phone":"+1 310 214 0804",
    "sg:postcode":"90260",
    "sg:province":"CA",
    "wof:name":"Digital House Connection",
    "wof:placetype":"venue"
},
  "geometry": {"coordinates":[-118.35988500000001,33.872961],"type":"Point"}
}