{
  "type": "Feature",
  "properties": {
    "iso:country":"US",
    "sg:address":"7462 N Figueroa St Ste 101",
    "sg:city":"Los Angeles",
    "sg:classifiers":[
        {
            "category":"Professional",
            "subcategory":"Lawyer & Legal Services",
            "type":"Services"
        }
    ],
    "sg:phone":"+1 323 550 1400",
    "sg:postcode":"90041",
    "sg:province":"CA",
    "wof:name":"Gerard A Fierro And Associates",
    "wof:placetype":"venue"
},
  "geometry": {"coordinates":[-118.18695700000001,34.139911],"type":"Point"}
}