{
  "type": "Feature",
  "properties": {
    "iso:country":"US",
    "sg:address":"5820 Shellmound St",
    "sg:city":"Emeryville",
    "sg:classifiers":[
        {
            "category":"Personal",
            "subcategory":"Beauty Salon",
            "type":"Services"
        }
    ],
    "sg:phone":"+1 510 652 6283",
    "sg:postcode":"94608",
    "sg:province":"CA",
    "wof:name":"Sterling Hair & Now",
    "wof:placetype":"venue"
},
  "geometry": {"coordinates":[-122.293282,37.838885],"type":"Point"}
}