{
  "type": "Feature",
  "properties": {
    "addr:full":"2235 Encinitas Blvd Encinitas CA 92024",
    "addr:housenumber":"2235",
    "addr:postcode":"92024",
    "addr:street":"Encinitas Blvd",
    "iso:country":"US",
    "sg:address":"2235 Encinitas Blvd",
    "sg:city":"Encinitas",
    "sg:classifiers":[
        {
            "category":"Banks & Credit Unions",
            "subcategory":"Investment Brokerage",
            "type":"Services"
        }
    ],
    "sg:phone":"+1 760 944 5100",
    "sg:postcode":"92024",
    "sg:province":"CA",
    "sg:tags":[
        "security",
        "management",
        "consulting"
    ],
    "wof:name":"Gilmore & Co",
    "wof:placetype":"venue"
},
  "geometry": {"coordinates":[-117.23927,33.03742],"type":"Point"}
}