{
  "type": "Feature",
  "properties": {
    "addr:full":"5415 Oberlin Dr San Diego CA 92121",
    "addr:housenumber":"5415",
    "addr:postcode":"92121",
    "addr:street":"Oberlin Dr",
    "iso:country":"US",
    "sg:address":"5415 Oberlin Dr",
    "sg:city":"San Diego",
    "sg:classifiers":[
        {
            "category":"Professional",
            "subcategory":"Accounting & Tax Preparation",
            "type":"Services"
        }
    ],
    "sg:phone":"+1 858 535 2000",
    "sg:postcode":"92121",
    "sg:province":"CA",
    "wof:name":"J H Cohn LLP",
    "wof:placetype":"venue"
},
  "geometry": {"coordinates":[-117.19566500000001,32.892203],"type":"Point"}
}