{
  "type": "Feature",
  "properties": {
    "addr:full":"5452 Laurel Canyon Blvd Valley Village CA 91607",
    "addr:housenumber":"5452",
    "addr:postcode":"91607",
    "addr:street":"Laurel Canyon Blvd",
    "iso:country":"US",
    "sg:address":"5452 Laurel Canyon Blvd",
    "sg:city":"Valley Village",
    "sg:classifiers":[
        {
            "category":"Retail",
            "subcategory":"Auto Repair",
            "type":"Services"
        }
    ],
    "sg:phone":"+1 818 845 1575",
    "sg:postcode":"91607",
    "sg:province":"CA",
    "wof:name":"Atco Transmission Centers",
    "wof:placetype":"venue"
},
  "geometry": {"coordinates":[-118.396004,34.169998],"type":"Point"}
}