{
  "type": "Feature",
  "properties": {
    "iso:country":"US",
    "sg:address":"2000 Hoefner Ave",
    "sg:city":"Los Angeles",
    "sg:classifiers":[
        {
            "category":"Manufacturing",
            "subcategory":"Rubber & Plastics",
            "type":"Manufacturing & Wholesale Goods"
        }
    ],
    "sg:phone":"+1 323 665 5288",
    "sg:postcode":"90040",
    "sg:province":"CA",
    "sg:website":"www.conroyknowlton.com",
    "wof:name":"Conroy & Knowlton Inc",
    "wof:placetype":"venue"
},
  "geometry": {"coordinates":[-118.15306200000001,34.00852],"type":"Point"}
}