{
  "type": "Feature",
  "properties": {
    "addr:full":"2434 Adeline St Oakland CA 94607",
    "addr:housenumber":"2434",
    "addr:postcode":"94607",
    "addr:street":"Adeline St",
    "iso:country":"US",
    "sg:address":"2434 Adeline St",
    "sg:city":"Oakland",
    "sg:classifiers":[
        {
            "category":"Arts & Performance",
            "subcategory":"Art Gallery",
            "type":"Entertainment"
        }
    ],
    "sg:phone":"+1 510 893 6419",
    "sg:postcode":"94607",
    "sg:province":"CA",
    "sg:tags":[
        "fine",
        "artist"
    ],
    "wof:name":"M Studio",
    "wof:placetype":"venue"
},
  "geometry": {"coordinates":[-122.28324600000001,37.817434],"type":"Point"}
}