{
  "type": "Feature",
  "properties": {
    "iso:country":"US",
    "sg:address":"8039 1/2 Imperial Hwy",
    "sg:city":"Downey",
    "sg:classifiers":[
        {
            "category":"Sports & Exercise",
            "subcategory":"Bicycle Rental",
            "type":"Entertainment"
        }
    ],
    "sg:phone":"+1 562 862 6769",
    "sg:postcode":"90241",
    "sg:province":"CA",
    "sg:tags":[
        "wear"
    ],
    "wof:name":"Rick's Airbrush & Designz -Da Gear Spot",
    "wof:placetype":"venue"
},
  "geometry": {"coordinates":[-118.11291300000001,33.91715],"type":"Point"}
}