{
  "type": "Feature",
  "properties": {
    "iso:country":"US",
    "sg:address":"740 Pine St",
    "sg:city":"Paso Robles",
    "sg:classifiers":[
        {
            "category":"Shopping",
            "subcategory":"Shoes",
            "type":"Retail Goods"
        }
    ],
    "sg:phone":"+1 805 226 7378",
    "sg:postcode":"93446",
    "sg:province":"CA",
    "wof:name":"Making Tracks & Co",
    "wof:placetype":"venue"
},
  "geometry": {"coordinates":[-120.688386,35.622215],"type":"Point"}
}