{
  "type": "Feature",
  "properties": {
    "iso:country":"US",
    "sg:address":"295 W Commercial St",
    "sg:city":"Pomona",
    "sg:classifiers":[
        {
            "category":"Manufacturing",
            "subcategory":"Printing",
            "type":"Manufacturing & Wholesale Goods"
        }
    ],
    "sg:phone":"+1 909 620 7707",
    "sg:postcode":"91768",
    "sg:province":"CA",
    "sg:tags":[
        "printer"
    ],
    "wof:name":"Bradshaw Bros Printing",
    "wof:placetype":"venue"
},
  "geometry": {"coordinates":[-117.752615,34.059675],"type":"Point"}
}