{
  "type": "Feature",
  "properties": {
    "addr:full":"230 E Betteravia Rd Santa Maria CA 93454",
    "addr:housenumber":"230",
    "addr:postcode":"93454",
    "addr:street":"E Betteravia Rd",
    "iso:country":"US",
    "sg:address":"230 E Betteravia Rd",
    "sg:city":"Santa Maria",
    "sg:classifiers":[
        {
            "category":"Retail",
            "subcategory":"Laundry & Dry Cleaning",
            "type":"Services"
        }
    ],
    "sg:phone":"+1 805 922 1985",
    "sg:postcode":"93454",
    "sg:province":"CA",
    "sg:tags":[
        "coin",
        "power"
    ],
    "wof:name":"Lucky Laundry",
    "wof:placetype":"venue"
},
  "geometry": {"coordinates":[-120.434089,34.920948],"type":"Point"}
}