{
  "type": "Feature",
  "properties": {
    "iso:country":"US",
    "sg:address":"11858 Rosecrans Ave",
    "sg:city":"Norwalk",
    "sg:classifiers":[
        {
            "category":"Health Services",
            "subcategory":"Health Practitioner",
            "type":"Services"
        }
    ],
    "sg:phone":"+1 562 868 8478",
    "sg:postcode":"90650",
    "sg:province":"CA",
    "sg:tags":[
        "acupuncture"
    ],
    "wof:name":"Best Acupuncture",
    "wof:placetype":"venue"
},
  "geometry": {"coordinates":[-118.052874,33.902002],"type":"Point"}
}