{
  "type": "Feature",
  "properties": {
    "addr:full":"130 Bernard St Bakersfield CA 93305",
    "addr:housenumber":"130",
    "addr:postcode":"93305",
    "addr:street":"Bernard St",
    "iso:country":"US",
    "sg:address":"130 Bernard St",
    "sg:city":"Bakersfield",
    "sg:classifiers":[
        {
            "category":"Government",
            "subcategory":"Fire Station",
            "type":"Public Place"
        }
    ],
    "sg:phone":"+1 661 631 0138",
    "sg:postcode":"93305",
    "sg:province":"CA",
    "sg:tags":[
        "department"
    ],
    "wof:name":"Bakersfield Fire Station",
    "wof:placetype":"venue"
},
  "geometry": {"coordinates":[-118.999492,35.39031],"type":"Point"}
}