{
  "type": "Feature",
  "properties": {
    "addr:full":"13800 Skyline Blvd Woodside CA 94062",
    "addr:housenumber":"13800",
    "addr:postcode":"94062",
    "addr:street":"Skyline Blvd",
    "iso:country":"US",
    "sg:address":"13800 Skyline Blvd",
    "sg:city":"Woodside",
    "sg:classifiers":[
        {
            "category":"Recreation",
            "type":"Entertainment"
        }
    ],
    "sg:phone":"+1 650 851 9999",
    "sg:postcode":"94062",
    "sg:province":"CA",
    "sg:tags":[
        "parks"
    ],
    "wof:name":"Henrik Ibsen Park",
    "wof:placetype":"venue"
},
  "geometry": {"coordinates":[-122.31876699999999,37.434807],"type":"Point"}
}