{
  "type": "Feature",
  "properties": {
    "iso:country":"US",
    "sg:address":"11465 Sunrise Gold Cir",
    "sg:city":"Rancho Cordova",
    "sg:classifiers":[
        {
            "category":"Shopping",
            "subcategory":"Florist",
            "type":"Retail Goods"
        }
    ],
    "sg:phone":"+1 916 858 8503",
    "sg:postcode":"95742",
    "sg:province":"CA",
    "wof:name":"Elegant Flowers 2",
    "wof:placetype":"venue"
},
  "geometry": {"coordinates":[-121.262371,38.597463],"type":"Point"}
}