{
  "type": "Feature",
  "properties": {
    "iso:country":"US",
    "sg:address":"550 E Carson Plaza Dr",
    "sg:city":"Carson",
    "sg:classifiers":[
        {
            "category":"Retail",
            "subcategory":"Portrait Studio",
            "type":"Services"
        }
    ],
    "sg:phone":"+1 310 515 2127",
    "sg:postcode":"90746",
    "sg:province":"CA",
    "sg:tags":[
        "photographer"
    ],
    "wof:name":"Way We Were Productions",
    "wof:placetype":"venue"
},
  "geometry": {"coordinates":[-118.26436699999999,33.845233],"type":"Point"}
}