{
  "type": "Feature",
  "properties": {
    "iso:country":"US",
    "sg:address":"4170 Oceanside Blvd. Suite 189",
    "sg:city":"Oceanside",
    "sg:classifiers":[
        {
            "category":"Personal",
            "subcategory":"Beauty Salon",
            "type":"Services"
        }
    ],
    "sg:phone":"+1 760 631 0726",
    "sg:postcode":"92056",
    "sg:province":"CA",
    "sg:tags":[
        "hair"
    ],
    "sg:website":"majesticsalonanddayspa.com/",
    "wof:name":"Majestic Salon and Day Spa",
    "wof:placetype":"venue"
},
  "geometry": {"coordinates":[-117.2859,33.20823],"type":"Point"}
}