{
  "type": "Feature",
  "properties": {
    "addr:full":"1524 W San Carlos St San Jose CA 95110",
    "addr:housenumber":"1524",
    "addr:postcode":"95110",
    "addr:street":"W San Carlos St",
    "iso:country":"US",
    "sg:address":"1524 W San Carlos St",
    "sg:city":"San Jose",
    "sg:classifiers":[
        {
            "category":"Shopping",
            "subcategory":"Gifts & Souvenirs",
            "type":"Retail Goods"
        }
    ],
    "sg:phone":"+1 408 995 6434",
    "sg:postcode":"95110",
    "sg:province":"CA",
    "wof:name":"Dulceria MI Carnaval Party Sup",
    "wof:placetype":"venue"
},
  "geometry": {"coordinates":[-121.91743,37.323384],"type":"Point"}
}