{
  "type": "Feature",
  "properties": {
    "iso:country":"US",
    "sg:address":"100 Daniel Dr",
    "sg:city":"Alamo",
    "sg:classifiers":[
        {
            "category":"Food & Beverages",
            "subcategory":"Specialty",
            "type":"Retail Goods"
        }
    ],
    "sg:phone":"+1 925 837 3501",
    "sg:postcode":"94507",
    "sg:province":"CA",
    "sg:tags":[
        "water",
        "bulk",
        "company"
    ],
    "wof:name":"Snatina Water Co Inc",
    "wof:placetype":"venue"
},
  "geometry": {"coordinates":[-122.023447,37.839019],"type":"Point"}
}