{
  "type": "Feature",
  "properties": {
    "addr:full":"542 San Ramon Valley Blvd Danville CA 94526",
    "addr:housenumber":"542",
    "addr:postcode":"94526",
    "addr:street":"San Ramon Valley Blvd",
    "iso:country":"US",
    "sg:address":"542 San Ramon Valley Blvd",
    "sg:city":"Danville",
    "sg:classifiers":[
        {
            "category":"Shopping",
            "subcategory":"Bicycles & Sporting Goods",
            "type":"Retail Goods"
        },
        {
            "category":"Professional",
            "subcategory":"Printing & Photocopies",
            "type":"Services"
        },
        {
            "category":"Sports & Exercise",
            "subcategory":"Tennis Court",
            "type":"Entertainment"
        }
    ],
    "sg:phone":"+1 925 837 3320",
    "sg:postcode":"94526",
    "sg:province":"CA",
    "sg:tags":[
        "supply",
        "trophies",
        "equipment",
        "medal",
        "plaque"
    ],
    "sg:website":"http://www.tennistrophiesandteetime.com",
    "wof:name":"Tennis Trophies & Tee Time",
    "wof:placetype":"venue"
},
  "geometry": {"coordinates":[-121.996568,37.817473],"type":"Point"}
}