{
  "type": "Feature",
  "properties": {
    "addr:full":"4619 Auburn Blvd Sacramento CA 95841",
    "addr:housenumber":"4619",
    "addr:postcode":"95841",
    "addr:street":"Auburn Blvd",
    "iso:country":"US",
    "sg:address":"4619 Auburn Blvd",
    "sg:city":"Sacramento",
    "sg:classifiers":[
        {
            "category":"Professional",
            "subcategory":"Accounting & Tax Preparation",
            "type":"Services"
        }
    ],
    "sg:phone":"+1 916 480 0746",
    "sg:postcode":"95841",
    "sg:province":"CA",
    "sg:tags":[
        "billing"
    ],
    "wof:name":"Data Support Svc",
    "wof:placetype":"venue"
},
  "geometry": {"coordinates":[-121.35519499999999,38.65297],"type":"Point"}
}