{
  "type": "Feature",
  "properties": {
    "iso:country":"US",
    "sg:address":"5175 Lakewood Blvd",
    "sg:city":"Lakewood",
    "sg:classifiers":[
        {
            "category":"Restaurant",
            "type":"Food & Drink"
        }
    ],
    "sg:menulink":"http://www.allmenus.com/ca/long-beach-lakewood/163986-togos-eatery/menu/",
    "sg:phone":"+1 562 602 0597",
    "sg:postcode":"90712",
    "sg:province":"CA",
    "sg:tags":[
        "wrap",
        "american",
        "sandwich"
    ],
    "wof:name":"Togo's Eatery",
    "wof:placetype":"venue"
},
  "geometry": {"coordinates":[-118.142627,33.851935],"type":"Point"}
}