{
  "type": "Feature",
  "properties": {
    "iso:country":"US",
    "sg:address":"3475 W Shaw Ave",
    "sg:city":"Fresno",
    "sg:classifiers":[
        {
            "category":"Wholesale",
            "subcategory":"Fruits & Vegetables",
            "type":"Manufacturing & Wholesale Goods"
        }
    ],
    "sg:phone":"+1 559 276 7021",
    "sg:postcode":"93711",
    "sg:province":"CA",
    "sg:tags":[
        "shipper"
    ],
    "wof:name":"Allied Grape Growers",
    "wof:placetype":"venue"
},
  "geometry": {"coordinates":[-119.852186,36.808193],"type":"Point"}
}