{
  "type": "Feature",
  "properties": {
    "iso:country":"US",
    "sg:address":"7838 Convoy Ct",
    "sg:city":"San Diego",
    "sg:classifiers":[
        {
            "category":"Building & Trades",
            "subcategory":"Construction",
            "type":"Services"
        }
    ],
    "sg:phone":"+1 858 571 3388",
    "sg:postcode":"92117",
    "sg:province":"CA",
    "sg:tags":[
        "painting",
        "contractor"
    ],
    "wof:name":"Enterprises Inc",
    "wof:placetype":"venue"
},
  "geometry": {"coordinates":[-117.150514,32.834753],"type":"Point"}
}