{
  "type": "Feature",
  "properties": {
    "iso:country":"US",
    "sg:address":"5711 W Ave M",
    "sg:city":"Lancaster",
    "sg:classifiers":[
        {
            "category":"Building & Trades",
            "subcategory":"Construction",
            "type":"Services"
        }
    ],
    "sg:phone":"+1 661 718 8111",
    "sg:postcode":"93536",
    "sg:province":"CA",
    "sg:tags":[
        "coping",
        "plastering",
        "tiling",
        "pool",
        "swimming"
    ],
    "wof:name":"Ace Pools",
    "wof:placetype":"venue"
},
  "geometry": {"coordinates":[-118.231646,34.645703],"type":"Point"}
}