{
  "type": "Feature",
  "properties": {
    "iso:country":"US",
    "sg:address":"18900 Saticoy St",
    "sg:city":"Reseda",
    "sg:classifiers":[
        {
            "category":"Social Services",
            "subcategory":"Child Care",
            "type":"Services"
        }
    ],
    "sg:phone":"+1 818 996 1077",
    "sg:postcode":"91335",
    "sg:province":"CA",
    "wof:name":"Toddlers Club House",
    "wof:placetype":"venue"
},
  "geometry": {"coordinates":[-118.546976,34.208374],"type":"Point"}
}