{
  "type": "Feature",
  "properties": {
    "addr:full":"616 Cll Rinconada Santa Barbara CA 93105",
    "addr:housenumber":"616",
    "addr:postcode":"93105",
    "addr:street":"Cll Rinconada",
    "iso:country":"US",
    "sg:address":"616 Cll Rinconada",
    "sg:city":"Santa Barbara",
    "sg:classifiers":[
        {
            "category":"Home & Garden",
            "subcategory":"Garden Supply",
            "type":"Retail Goods"
        }
    ],
    "sg:phone":"+1 805 563 0308",
    "sg:postcode":"93105",
    "sg:province":"CA",
    "sg:tags":[
        "ornament"
    ],
    "wof:name":"Homescapes Of Santa Barbara",
    "wof:placetype":"venue"
},
  "geometry": {"coordinates":[-119.731499,34.448142],"type":"Point"}
}