{
  "type": "Feature",
  "properties": {
    "addr:full":"1003 Wellesley Ave Modesto CA 95350",
    "addr:housenumber":"1003",
    "addr:postcode":"ca 95350",
    "addr:street":"Wellesley Ave",
    "iso:country":"US",
    "sg:address":"1003 Wellesley Ave",
    "sg:city":"Modesto",
    "sg:classifiers":[
        {
            "category":"Professional",
            "subcategory":"Management & Consulting",
            "type":"Services"
        }
    ],
    "sg:phone":"+1 209 572 2327",
    "sg:postcode":"95350",
    "sg:province":"CA",
    "sg:tags":[
        "consultant",
        "business"
    ],
    "wof:name":"JTS Enteprises",
    "wof:placetype":"venue"
},
  "geometry": {"coordinates":[-121.00649,37.658451],"type":"Point"}
}