{
  "type": "Feature",
  "properties": {
    "iso:country":"US",
    "sg:address":"11525 Crenshaw Boulevard",
    "sg:city":"Inglewood",
    "sg:classifiers":[
        {
            "category":"Banks & Credit Unions",
            "subcategory":"Bank",
            "type":"Services"
        }
    ],
    "sg:phone":"+1 310 884 1870",
    "sg:postcode":"90303",
    "sg:province":"CA",
    "sg:website":"www.bankofamerica.com",
    "wof:name":"Bank of America",
    "wof:placetype":"venue"
},
  "geometry": {"coordinates":[-118.326421,33.929224],"type":"Point"}
}