{
  "type": "Feature",
  "properties": {
    "addr:full":"27215 Camp Plenty Rd Santa Clarita CA 91351",
    "addr:housenumber":"27215",
    "addr:postcode":"91351",
    "addr:street":"Camp Plenty Rd",
    "iso:country":"US",
    "sg:address":"27215 Camp Plenty Rd",
    "sg:city":"Santa Clarita",
    "sg:classifiers":[
        {
            "category":"Personal",
            "subcategory":"Massage",
            "type":"Services"
        }
    ],
    "sg:phone":"+1 661 299 5711",
    "sg:postcode":"91351",
    "sg:province":"CA",
    "wof:name":"Blue Sand Mind & Body",
    "wof:placetype":"venue"
},
  "geometry": {"coordinates":[-118.475813,34.416423],"type":"Point"}
}