{
  "type": "Feature",
  "properties": {
    "addr:full":"1702-L Meridian Ave #169 San Jose CA 95125",
    "addr:housenumber":"1702-l",
    "addr:postcode":"95125",
    "addr:street":"Meridian Ave # 169",
    "iso:country":"US",
    "sg:address":"1702-L Meridian Ave #169",
    "sg:city":"San Jose",
    "sg:classifiers":[
        {
            "category":"Health Services",
            "subcategory":"Health Practitioner",
            "type":"Services"
        }
    ],
    "sg:phone":"+1 408 313 9094",
    "sg:postcode":"95125",
    "sg:province":"CA",
    "sg:tags":[
        "nutritionist"
    ],
    "wof:name":"MonaVie",
    "wof:placetype":"venue"
},
  "geometry": {"coordinates":[-121.91343500000001,37.29246],"type":"Point"}
}