{
  "type": "Feature",
  "properties": {
    "iso:country":"US",
    "sg:address":"3500 Pegasus Dr",
    "sg:city":"Bakersfield",
    "sg:classifiers":[
        {
            "category":"Building & Trades",
            "subcategory":"Construction",
            "type":"Services"
        }
    ],
    "sg:phone":"+1 661 833 4400",
    "sg:postcode":"93308",
    "sg:province":"CA",
    "sg:tags":[
        "contractor"
    ],
    "sg:website":"www.arbinc.com",
    "wof:name":"ARB Inc",
    "wof:placetype":"venue"
},
  "geometry": {"coordinates":[-119.068917,35.436976],"type":"Point"}
}