{
  "type": "Feature",
  "properties": {
    "iso:country":"US",
    "sg:address":"570 S Atlantic Blvd",
    "sg:city":"Los Angeles",
    "sg:classifiers":[
        {
            "category":"Recreation",
            "type":"Entertainment"
        }
    ],
    "sg:phone":"+1 323 260 2341",
    "sg:postcode":"90022",
    "sg:province":"CA",
    "sg:tags":[
        "parks"
    ],
    "wof:name":"Atlantic Avenue Park",
    "wof:placetype":"venue"
},
  "geometry": {"coordinates":[-118.15562300000001,34.025442],"type":"Point"}
}