{
  "type": "Feature",
  "properties": {
    "iso:country":"US",
    "sg:address":"16015 P St",
    "sg:city":"Mojave",
    "sg:classifiers":[
        {
            "category":"Professional",
            "subcategory":"Engineering",
            "type":"Services"
        }
    ],
    "sg:phone":"+1 661 824 3706",
    "sg:postcode":"93501",
    "sg:province":"CA",
    "sg:tags":[
        "engineer"
    ],
    "wof:name":"Rocket Propulsion Engineering",
    "wof:placetype":"venue"
},
  "geometry": {"coordinates":[-118.166268,35.055745],"type":"Point"}
}