{
  "type": "Feature",
  "properties": {
    "iso:country":"US",
    "sg:address":"1459 N Avalon Blvd",
    "sg:city":"Wilmington",
    "sg:classifiers":[
        {
            "category":"Personal",
            "subcategory":"Beauty Salon",
            "type":"Services"
        }
    ],
    "sg:phone":"+1 310 549 1267",
    "sg:postcode":"90744",
    "sg:province":"CA",
    "sg:tags":[
        "hair"
    ],
    "wof:name":"Magaly's Beauty Salon",
    "wof:placetype":"venue"
},
  "geometry": {"coordinates":[-118.264,33.792599],"type":"Point"}
}