{
  "type": "Feature",
  "properties": {
    "iso:country":"US",
    "sg:address":"5836 Republic St",
    "sg:city":"Riverside",
    "sg:classifiers":[
        {
            "category":"Autos & Motor Vehicles",
            "subcategory":"Auto Supplies",
            "type":"Retail Goods"
        }
    ],
    "sg:phone":"+1 951 352 2080",
    "sg:postcode":"92504",
    "sg:province":"CA",
    "sg:tags":[
        "wheel",
        "cover"
    ],
    "sg:website":"www.wheeltechintl.com",
    "wof:name":"Wheeltech International Corp",
    "wof:placetype":"venue"
},
  "geometry": {"coordinates":[-117.43831,33.964795],"type":"Point"}
}