{
  "type": "Feature",
  "properties": {
    "iso:country":"US",
    "sg:address":"1029 11th St",
    "sg:city":"Lakeport",
    "sg:classifiers":[
        {
            "category":"Shopping",
            "subcategory":"Music",
            "type":"Retail Goods"
        }
    ],
    "sg:phone":"+1 707 263 7222",
    "sg:postcode":"95453",
    "sg:province":"CA",
    "sg:tags":[
        "video",
        "disc",
        "tape",
        "cassette"
    ],
    "wof:name":"National Video Cassettes",
    "wof:placetype":"venue"
},
  "geometry": {"coordinates":[-122.92687599999999,39.049005],"type":"Point"}
}