{
  "type": "Feature",
  "properties": {
    "iso:country":"US",
    "sg:address":"900 Mangrove Ave",
    "sg:city":"Chico",
    "sg:classifiers":[
        {
            "category":"Banks & Credit Unions",
            "subcategory":"Bank",
            "type":"Services"
        }
    ],
    "sg:phone":"+1 530 891 9000",
    "sg:postcode":"95926",
    "sg:province":"CA",
    "wof:name":"Butte Community Bank",
    "wof:placetype":"venue"
},
  "geometry": {"coordinates":[-121.83779,39.741186],"type":"Point"}
}