{
  "type": "Feature",
  "properties": {
    "addr:full":"24 el Camino Ave San Rafael CA 94901",
    "addr:housenumber":"24",
    "addr:postcode":"94901",
    "addr:street":"El Camino Ave",
    "iso:country":"US",
    "sg:address":"24 el Camino Ave",
    "sg:city":"San Rafael",
    "sg:classifiers":[
        {
            "category":"Building & Trades",
            "subcategory":"Landscaping Services",
            "type":"Services"
        }
    ],
    "sg:phone":"+1 415 457 5575",
    "sg:postcode":"94901",
    "sg:province":"CA",
    "sg:tags":[
        "designer",
        "landscape"
    ],
    "wof:name":"Merryvale House & Garden",
    "wof:placetype":"venue"
},
  "geometry": {"coordinates":[-122.539681,37.974869],"type":"Point"}
}