{
  "type": "Feature",
  "properties": {
    "iso:country":"US",
    "sg:address":"9373 Activity Rd",
    "sg:city":"San Diego",
    "sg:classifiers":[
        {
            "category":"Manufacturing",
            "subcategory":"Printing",
            "type":"Manufacturing & Wholesale Goods"
        }
    ],
    "sg:phone":"+1 858 586 1629",
    "sg:postcode":"92126",
    "sg:province":"CA",
    "wof:name":"Raised Ink Printers",
    "wof:placetype":"venue"
},
  "geometry": {"coordinates":[-117.124549,32.896966],"type":"Point"}
}