{
  "type": "Feature",
  "properties": {
    "addr:full":"40 Airport Blvd South San Francisco CA 94080",
    "addr:housenumber":"40",
    "addr:postcode":"94080",
    "addr:street":"Airport Blvd",
    "iso:country":"US",
    "sg:address":"40 Airport Blvd",
    "sg:city":"South San Francisco",
    "sg:classifiers":[
        {
            "category":"Professional",
            "type":"Services"
        }
    ],
    "sg:phone":"+1 650 589 9162",
    "sg:postcode":"94080",
    "sg:province":"CA",
    "sg:tags":[
        "caterer"
    ],
    "wof:name":"Lsg Sky Chefs",
    "wof:placetype":"venue"
},
  "geometry": {"coordinates":[-122.408997,37.6516],"type":"Point"}
}