{
  "type": "Feature",
  "properties": {
    "addr:full":"1401 N Los Robles Ave Pasadena CA 91104",
    "addr:housenumber":"1401",
    "addr:postcode":"91104",
    "addr:street":"N Los Robles Ave",
    "iso:country":"US",
    "sg:address":"1401 N Los Robles Ave",
    "sg:city":"Pasadena",
    "sg:classifiers":[
        {
            "category":"Real Estate",
            "subcategory":"Real Estate Operator",
            "type":"Services"
        }
    ],
    "sg:phone":"+1 626 794 9369",
    "sg:postcode":"91104",
    "sg:province":"CA",
    "sg:tags":[
        "apartment"
    ],
    "wof:name":"Mb Equity",
    "wof:placetype":"venue"
},
  "geometry": {"coordinates":[-118.141998,34.1698],"type":"Point"}
}