{
  "type": "Feature",
  "properties": {
    "iso:country":"US",
    "sg:address":"2805 Porter St",
    "sg:city":"Soquel",
    "sg:classifiers":[
        {
            "category":"Real Estate",
            "subcategory":"Real Estate Agent",
            "type":"Services"
        }
    ],
    "sg:phone":"+1 831 476 2506",
    "sg:postcode":"95073",
    "sg:province":"CA",
    "sg:tags":[
        "exchanger"
    ],
    "sg:website":"http://www.ronwalken.com",
    "wof:name":"Xchange Solutions, Inc.",
    "wof:placetype":"venue"
},
  "geometry": {"coordinates":[-121.957376,36.986672],"type":"Point"}
}