{
  "type": "Feature",
  "properties": {
    "iso:country":"US",
    "sg:address":"8538 Hamilton Avenue",
    "sg:city":"Huntington Beach",
    "sg:classifiers":[
        {
            "category":"Building & Trades",
            "subcategory":"Pest Control",
            "type":"Services"
        }
    ],
    "sg:phone":"+1 714 374 6850",
    "sg:postcode":"92646",
    "sg:province":"CA",
    "wof:name":"Coastal Pacific Termite",
    "wof:placetype":"venue"
},
  "geometry": {"coordinates":[-117.97859099999999,33.650319],"type":"Point"}
}