{
  "type": "Feature",
  "properties": {
    "addr:full":"201 N Euclid Ave Upland CA 91786",
    "addr:housenumber":"201",
    "addr:postcode":"91786",
    "addr:street":"N Euclid Ave",
    "iso:country":"US",
    "sg:address":"201 N Euclid Ave",
    "sg:city":"Upland",
    "sg:classifiers":[
        {
            "category":"Shopping",
            "subcategory":"Jewelry",
            "type":"Retail Goods"
        }
    ],
    "sg:phone":"+1 909 608 1620",
    "sg:postcode":"91786",
    "sg:province":"CA",
    "sg:tags":[
        "jeweler"
    ],
    "wof:name":"Gem World Inc",
    "wof:placetype":"venue"
},
  "geometry": {"coordinates":[-117.65113700000001,34.097263],"type":"Point"}
}