{
  "type": "Feature",
  "properties": {
    "iso:country":"US",
    "sg:address":"11500 del Monte Ave",
    "sg:city":"Castroville",
    "sg:classifiers":[
        {
            "category":"Professional",
            "type":"Services"
        }
    ],
    "sg:phone":"+1 831 633 5884",
    "sg:postcode":"95012",
    "sg:province":"CA",
    "sg:tags":[
        "harvesting-contract"
    ],
    "wof:name":"Valley Pride Inc",
    "wof:placetype":"venue"
},
  "geometry": {"coordinates":[-121.74543,36.761879],"type":"Point"}
}