{
  "type": "Feature",
  "properties": {
    "iso:country":"US",
    "sg:address":"1490 W Whittier Blvd",
    "sg:city":"La Habra",
    "sg:classifiers":[
        {
            "category":"Personal",
            "subcategory":"Beauty Salon",
            "type":"Services"
        }
    ],
    "sg:phone":"+1 562 690 4143",
    "sg:postcode":"90631",
    "sg:province":"CA",
    "wof:name":"LA Habra Hair & Nail Studio",
    "wof:placetype":"venue"
},
  "geometry": {"coordinates":[-117.961544,33.939229],"type":"Point"}
}