{
  "type": "Feature",
  "properties": {
    "iso:country":"US",
    "sg:address":"9 Neptune",
    "sg:city":"San Francisco",
    "sg:classifiers":[
        {
            "category":"Building & Trades",
            "subcategory":"Construction",
            "type":"Services"
        },
        {
            "category":"Professional",
            "subcategory":"Computer Services",
            "type":"Services"
        }
    ],
    "sg:phone":"+1 415 279 7881",
    "sg:postcode":"94199",
    "sg:province":"CA",
    "sg:tags":[
        "repair",
        "painter"
    ],
    "wof:name":"Philip Marigmen",
    "wof:placetype":"venue"
},
  "geometry": {"coordinates":[-122.396911,37.731216],"type":"Point"}
}