{
  "type": "Feature",
  "properties": {
    "iso:country":"US",
    "sg:address":"19642 Ventura Blvd Ste B",
    "sg:city":"Tarzana",
    "sg:classifiers":[
        {
            "category":"Health Services",
            "subcategory":"Doctor",
            "type":"Services"
        }
    ],
    "sg:phone":"+1 818 708 1112",
    "sg:postcode":"91356",
    "sg:province":"CA",
    "sg:tags":[
        "surgeon",
        "oral"
    ],
    "wof:name":"Hekmatnia Michel DDS",
    "wof:placetype":"venue"
},
  "geometry": {"coordinates":[-118.561639,34.172626],"type":"Point"}
}