{
  "type": "Feature",
  "properties": {
    "iso:country":"US",
    "sg:address":"524 Chiechi Ave",
    "sg:city":"San Jose",
    "sg:classifiers":[
        {
            "category":"Manufacturing",
            "subcategory":"Signs",
            "type":"Manufacturing & Wholesale Goods"
        }
    ],
    "sg:phone":"+1 408 293 4481",
    "sg:postcode":"95126",
    "sg:province":"CA",
    "sg:tags":[
        "advertising",
        "specialty"
    ],
    "wof:name":"Valery Signs",
    "wof:placetype":"venue"
},
  "geometry": {"coordinates":[-121.91803,37.319376],"type":"Point"}
}