{
  "type": "Feature",
  "properties": {
    "addr:full":"100 Willow Plz Visalia CA 93291",
    "addr:housenumber":"100",
    "addr:postcode":"93291",
    "addr:street":"Willow Plz",
    "iso:country":"US",
    "sg:address":"100 Willow Plz",
    "sg:city":"Visalia",
    "sg:classifiers":[
        {
            "category":"Professional",
            "subcategory":"Business Services",
            "type":"Services"
        }
    ],
    "sg:phone":"+1 559 738 1800",
    "sg:postcode":"93291",
    "sg:province":"CA",
    "sg:tags":[
        "consultant",
        "coach"
    ],
    "wof:name":"Howard R Broadman Private Jdg",
    "wof:placetype":"venue"
},
  "geometry": {"coordinates":[-119.29232,36.328346],"type":"Point"}
}