{
  "type": "Feature",
  "properties": {
    "addr:full":"735 Crocker Ave Daly City CA 94014",
    "addr:housenumber":"735",
    "addr:postcode":"94014",
    "addr:street":"Crocker Ave",
    "iso:country":"US",
    "sg:address":"735 Crocker Ave",
    "sg:city":"Daly City",
    "sg:classifiers":[
        {
            "category":"Personal",
            "type":"Services"
        }
    ],
    "sg:phone":"+1 415 704 4186",
    "sg:postcode":"94014",
    "sg:province":"CA",
    "sg:tags":[
        "towing"
    ],
    "sg:website":"www.theautotowing.com/Daly-City/",
    "wof:name":"Auto Towing Daly City",
    "wof:placetype":"venue"
},
  "geometry": {"coordinates":[-122.454016,37.702453],"type":"Point"}
}