{
  "type": "Feature",
  "properties": {
    "iso:country":"US",
    "sg:address":"708 S Temescal St",
    "sg:city":"Corona",
    "sg:classifiers":[
        {
            "category":"Manufacturing",
            "subcategory":"Glass & Minerals",
            "type":"Manufacturing & Wholesale Goods"
        }
    ],
    "sg:phone":"+1 951 736 1881",
    "sg:postcode":"92879",
    "sg:province":"CA",
    "sg:tags":[
        "product",
        "structural",
        "clay"
    ],
    "wof:name":"MCP Industries",
    "wof:placetype":"venue"
},
  "geometry": {"coordinates":[-117.527279,33.872714],"type":"Point"}
}