{
  "type": "Feature",
  "properties": {
    "addr:full":"6086 York Boulevard Los Angeles CA 90042",
    "addr:housenumber":"6086",
    "addr:postcode":"90042",
    "addr:street":"York Boulevard",
    "iso:country":"US",
    "sg:address":"6086 York Boulevard",
    "sg:city":"Los Angeles",
    "sg:classifiers":[
        {
            "category":"Professional",
            "subcategory":"Lawyer & Legal Services",
            "type":"Services"
        }
    ],
    "sg:phone":"+1 213 484 0098",
    "sg:postcode":"90042",
    "sg:province":"CA",
    "wof:name":"Gutierrez Oscar Atty At Law",
    "wof:placetype":"venue"
},
  "geometry": {"coordinates":[-118.186454,34.117451],"type":"Point"}
}