{
  "type": "Feature",
  "properties": {
    "addr:full":"1541 Bayshore Hwy Burlingame CA 94010",
    "addr:housenumber":"1541",
    "addr:postcode":"94010",
    "addr:street":"Bayshore Hwy",
    "iso:country":"US",
    "sg:address":"1541 Bayshore Hwy",
    "sg:city":"Burlingame",
    "sg:classifiers":[
        {
            "category":"Professional",
            "subcategory":"Lawyer & Legal Services",
            "type":"Services"
        }
    ],
    "sg:phone":"+1 650 697 9431",
    "sg:postcode":"94010",
    "sg:province":"CA",
    "sg:tags":[
        "investigation",
        "private"
    ],
    "sg:website":"www.aalegalservice.com",
    "wof:name":"A & A Legal Service, Inc",
    "wof:placetype":"venue"
},
  "geometry": {"coordinates":[-122.36677,37.598593],"type":"Point"}
}