{
  "type": "Feature",
  "properties": {
    "addr:full":"1108 Waterloo Rd Stockton CA 95205",
    "addr:housenumber":"1108",
    "addr:postcode":"95205",
    "addr:street":"Waterloo Rd",
    "iso:country":"US",
    "sg:address":"1108 Waterloo Rd",
    "sg:city":"Stockton",
    "sg:classifiers":[
        {
            "category":"Restaurant",
            "type":"Food & Drink"
        }
    ],
    "sg:phone":"+1 209 465 4810",
    "sg:postcode":"95205",
    "sg:province":"CA",
    "wof:name":"Salo Salo",
    "wof:placetype":"venue"
},
  "geometry": {"coordinates":[-121.270864,37.969178],"type":"Point"}
}