{
  "type": "Feature",
  "properties": {
    "addr:full":"451 S Brand Blvd San Fernando CA 91340",
    "addr:housenumber":"451",
    "addr:postcode":"91340",
    "addr:street":"S Brand Blvd",
    "iso:country":"US",
    "sg:address":"451 S Brand Blvd",
    "sg:city":"San Fernando",
    "sg:classifiers":[
        {
            "category":"Organizations",
            "subcategory":"Community Association",
            "type":"Services"
        }
    ],
    "sg:phone":"+1 818 837 1173",
    "sg:postcode":"91340",
    "sg:province":"CA",
    "sg:tags":[
        "educational"
    ],
    "wof:name":"Institute For Leadership Dev",
    "wof:placetype":"venue"
},
  "geometry": {"coordinates":[-118.442716,34.279581],"type":"Point"}
}