{
  "type": "Feature",
  "properties": {
    "iso:country":"US",
    "sg:address":"3649 J St",
    "sg:city":"Sacramento",
    "sg:classifiers":[
        {
            "category":"Restaurant",
            "type":"Food & Drink"
        }
    ],
    "sg:phone":"+1 916 455 7803",
    "sg:postcode":"95816",
    "sg:province":"CA",
    "sg:tags":[
        "italian"
    ],
    "sg:website":"www.latrattoriabohemia.com",
    "wof:name":"La Trattoria Bohemia",
    "wof:placetype":"venue"
},
  "geometry": {"coordinates":[-121.45700100000001,38.570801],"type":"Point"}
}