{
  "type": "Feature",
  "properties": {
    "addr:full":"359 Sutter St San Francisco CA 90108",
    "addr:housenumber":"359",
    "addr:postcode":"90108",
    "addr:street":"Sutter St",
    "iso:country":"US",
    "sg:address":"359 Sutter St",
    "sg:city":"San Francisco",
    "sg:classifiers":[
        {
            "category":"Personal",
            "subcategory":"Beauty Salon",
            "type":"Services"
        },
        {
            "category":"Education",
            "subcategory":"School",
            "type":"Public Place"
        }
    ],
    "sg:phone":"+1 415 397 5105",
    "sg:postcode":"90108",
    "sg:province":"CA",
    "sg:tags":[
        "hair"
    ],
    "sg:website":"www.sassoon.com/salons/usa/san-f...",
    "wof:name":"Sassoon Salon",
    "wof:placetype":"venue"
},
  "geometry": {"coordinates":[-122.40626,37.789266],"type":"Point"}
}