{
  "type": "Feature",
  "properties": {
    "addr:full":"1348 Windward Cir West Sacramento CA 95691",
    "addr:housenumber":"1348",
    "addr:postcode":"95691",
    "addr:street":"Windward Cir",
    "iso:country":"US",
    "sg:address":"1348 Windward Cir",
    "sg:city":"West Sacramento",
    "sg:classifiers":[
        {
            "category":"Wholesale",
            "subcategory":"Durable Goods & Equipment",
            "type":"Manufacturing & Wholesale Goods"
        }
    ],
    "sg:phone":"+1 916 374 8155",
    "sg:postcode":"95691",
    "sg:province":"CA",
    "sg:tags":[
        "importer"
    ],
    "wof:name":"Sona Spice Co",
    "wof:placetype":"venue"
},
  "geometry": {"coordinates":[-121.54274100000001,38.572046],"type":"Point"}
}