{
  "type": "Feature",
  "properties": {
    "addr:full":"950 W San Marcos Blvd San Marcos CA 92078",
    "addr:housenumber":"950",
    "addr:postcode":"92078",
    "addr:street":"W San Marcos Blvd",
    "iso:country":"US",
    "sg:address":"950 W San Marcos Blvd",
    "sg:city":"San Marcos",
    "sg:classifiers":[
        {
            "category":"Professional",
            "type":"Services"
        }
    ],
    "sg:phone":"+1 760 744 6224",
    "sg:postcode":"92078",
    "sg:province":"CA",
    "sg:tags":[
        "establishment"
    ],
    "wof:name":"Major Development Inc",
    "wof:placetype":"venue"
},
  "geometry": {"coordinates":[-117.185909,33.135328],"type":"Point"}
}