{
  "type": "Feature",
  "properties": {
    "addr:full":"2927 W Capitol Avenue West Sacramento CA 95691",
    "addr:housenumber":"2927",
    "addr:postcode":"95691",
    "addr:street":"W Capitol Avenue",
    "iso:country":"US",
    "sg:address":"2927 W Capitol Avenue",
    "sg:city":"West Sacramento",
    "sg:classifiers":[
        {
            "category":"Restaurant",
            "type":"Food & Drink"
        },
        {
            "category":"Bakery",
            "type":"Food & Drink"
        }
    ],
    "sg:phone":"+1 916 374 8259",
    "sg:postcode":"95691",
    "sg:province":"CA",
    "sg:tags":[
        "mexican"
    ],
    "wof:name":"Panaderia La Purisima",
    "wof:placetype":"venue"
},
  "geometry": {"coordinates":[-121.54962999999999,38.579077],"type":"Point"}
}