{
  "type": "Feature",
  "properties": {
    "iso:country":"US",
    "sg:address":"2604 N Wilmington Ave",
    "sg:city":"Compton",
    "sg:classifiers":[
        {
            "category":"Building & Trades",
            "subcategory":"Construction",
            "type":"Services"
        }
    ],
    "sg:phone":"+1 310 632 6304",
    "sg:postcode":"90222",
    "sg:province":"CA",
    "sg:tags":[
        "contractor"
    ],
    "wof:name":"Kennedy Roofing Co",
    "wof:placetype":"venue"
},
  "geometry": {"coordinates":[-118.238989,33.914714],"type":"Point"}
}