{
  "type": "Feature",
  "properties": {
    "addr:full":"4880 San Juan Ave Fair Oaks CA 95628",
    "addr:housenumber":"4880",
    "addr:postcode":"95628",
    "addr:street":"San Juan Ave",
    "iso:country":"US",
    "sg:address":"4880 San Juan Ave",
    "sg:city":"Fair Oaks",
    "sg:classifiers":[
        {
            "category":"Professional",
            "type":"Services"
        }
    ],
    "sg:phone":"+1 916 961 5375",
    "sg:postcode":"95628",
    "sg:province":"CA",
    "wof:name":"3 Dfairway Co",
    "wof:placetype":"venue"
},
  "geometry": {"coordinates":[-121.29198,38.651938],"type":"Point"}
}