{
  "type": "Feature",
  "properties": {
    "iso:country":"US",
    "sg:address":"1954 Camden Ave Ste 6",
    "sg:city":"San Jose",
    "sg:classifiers":[
        {
            "category":"Sports & Exercise",
            "subcategory":"Playing Field",
            "type":"Entertainment"
        },
        {
            "category":"Health Services",
            "subcategory":"Chiropractor",
            "type":"Services"
        }
    ],
    "sg:phone":"+1 408 377 4700",
    "sg:postcode":"95124",
    "sg:province":"CA",
    "sg:tags":[
        "instruction",
        "fitness"
    ],
    "sg:website":"www.sbaychiro.com",
    "wof:name":"South Bay Chiropractic - Farima N. Yeganegi, D.C.",
    "wof:placetype":"venue"
},
  "geometry": {"coordinates":[-121.92484,37.261653],"type":"Point"}
}