{
  "type": "Feature",
  "properties": {
    "addr:full":"9717 Pebble Beach Dr Santee CA 92071",
    "addr:housenumber":"9717",
    "addr:postcode":"92071",
    "addr:street":"Pebble Beach Dr",
    "iso:country":"US",
    "sg:address":"9717 Pebble Beach Dr",
    "sg:city":"Santee",
    "sg:classifiers":[
        {
            "category":"Retail",
            "subcategory":"Laundry & Dry Cleaning",
            "type":"Services"
        }
    ],
    "sg:phone":"+1 619 448 8575",
    "sg:postcode":"92071",
    "sg:province":"CA",
    "sg:tags":[
        "repairing",
        "rug",
        "carpet"
    ],
    "wof:name":"Exceptional Carpet Svc",
    "wof:placetype":"venue"
},
  "geometry": {"coordinates":[-117.007795,32.851916],"type":"Point"}
}