{
  "type": "Feature",
  "properties": {
    "addr:full":"824 Venice Blvd Los Angeles CA 90015",
    "addr:housenumber":"824",
    "addr:postcode":"90015",
    "addr:street":"Venice Blvd",
    "iso:country":"US",
    "sg:address":"824 Venice Blvd",
    "sg:city":"Los Angeles",
    "sg:classifiers":[
        {
            "category":"Building & Trades",
            "subcategory":"Construction",
            "type":"Services"
        }
    ],
    "sg:phone":"+1 213 741 1680",
    "sg:postcode":"90015",
    "sg:province":"CA",
    "sg:tags":[
        "home",
        "builder"
    ],
    "wof:name":"C K Home Development Inc",
    "wof:placetype":"venue"
},
  "geometry": {"coordinates":[-118.274895,34.039497],"type":"Point"}
}