{
  "type": "Feature",
  "properties": {
    "iso:country":"US",
    "sg:address":"2000 5th Street",
    "sg:city":"Berkeley",
    "sg:classifiers":[
        {
            "category":"Food & Beverages",
            "subcategory":"Groceries & Convenience Stores",
            "type":"Retail Goods"
        }
    ],
    "sg:phone":"+1 510 845 1999",
    "sg:postcode":"94710",
    "sg:province":"CA",
    "wof:name":"Grocery Outlet",
    "wof:placetype":"venue"
},
  "geometry": {"coordinates":[-122.299004,37.867401],"type":"Point"}
}