{
  "type": "Feature",
  "properties": {
    "addr:full":"15707 E Imperial Hwy Ste B La Mirada CA 90638",
    "addr:housenumber":"15707",
    "addr:postcode":"90638",
    "addr:street":"E Imperial Hwy Ste B",
    "iso:country":"US",
    "sg:address":"15707 E Imperial Hwy Ste B",
    "sg:city":"La Mirada",
    "sg:classifiers":[
        {
            "category":"Professional",
            "subcategory":"Art Services",
            "type":"Services"
        }
    ],
    "sg:phone":"+1 562 318 5964",
    "sg:postcode":"90638",
    "sg:province":"CA",
    "sg:tags":[
        "photographer"
    ],
    "sg:website":"schlick-photography.com/",
    "wof:name":"Schlick Photography",
    "wof:placetype":"venue"
},
  "geometry": {"coordinates":[-117.996399,33.91735],"type":"Point"}
}