{
  "type": "Feature",
  "properties": {
    "iso:country":"US",
    "sg:address":"3073 Red Deer Ct",
    "sg:city":"Auburn",
    "sg:classifiers":[
        {
            "category":"Real Estate",
            "subcategory":"Real Estate Agent",
            "type":"Services"
        }
    ],
    "sg:phone":"+1 530 885 4580",
    "sg:postcode":"95602",
    "sg:province":"CA",
    "wof:name":"Apexx Realty Inc",
    "wof:placetype":"venue"
},
  "geometry": {"coordinates":[-121.08344,38.959072],"type":"Point"}
}