{
  "type": "Feature",
  "properties": {
    "addr:full":"3525 Old Conejo Rd Newbury Park CA 91320",
    "addr:housenumber":"3525",
    "addr:postcode":"91320",
    "addr:street":"Old Conejo Rd",
    "iso:country":"US",
    "sg:address":"3525 Old Conejo Rd",
    "sg:city":"Newbury Park",
    "sg:classifiers":[
        {
            "category":"Shopping",
            "type":"Retail Goods"
        }
    ],
    "sg:phone":"+1 805 376 0093",
    "sg:postcode":"91320",
    "sg:province":"CA",
    "sg:tags":[
        "product",
        "wood"
    ],
    "wof:name":"Wood Ranch Management Co",
    "wof:placetype":"venue"
},
  "geometry": {"coordinates":[-118.952065,34.191915],"type":"Point"}
}