{
  "type": "Feature",
  "properties": {
    "addr:full":"3600 W Segerstrom Ave Santa Ana CA 92704",
    "addr:housenumber":"3600",
    "addr:postcode":"92704",
    "addr:street":"W Segerstrom Ave",
    "iso:country":"US",
    "sg:address":"3600 W Segerstrom Ave",
    "sg:city":"Santa Ana",
    "sg:classifiers":[
        {
            "category":"Building & Trades",
            "subcategory":"Electrical",
            "type":"Services"
        }
    ],
    "sg:phone":"+1 714 979 7300",
    "sg:postcode":"92704",
    "sg:province":"CA",
    "sg:tags":[
        "control",
        "air",
        "industrial",
        "system",
        "pollution"
    ],
    "wof:name":"Wahlco Inc",
    "wof:placetype":"venue"
},
  "geometry": {"coordinates":[-117.91821899999999,33.708621],"type":"Point"}
}