{
  "type": "Feature",
  "properties": {
    "iso:country":"US",
    "sg:address":"2417 Bobwhite Way",
    "sg:city":"Santa Rosa",
    "sg:classifiers":[
        {
            "category":"Personal",
            "subcategory":"Beauty Salon",
            "type":"Services"
        }
    ],
    "sg:phone":"+1 707 823 6722",
    "sg:postcode":"95403",
    "sg:province":"CA",
    "sg:tags":[
        "manicuring"
    ],
    "wof:name":"Personal Elegance Nail Salon",
    "wof:placetype":"venue"
},
  "geometry": {"coordinates":[-122.767939,38.464751],"type":"Point"}
}