{
  "type": "Feature",
  "properties": {
    "addr:full":"83597 Indio Blvd Indio CA 92201",
    "addr:housenumber":"83597",
    "addr:postcode":"92201",
    "addr:street":"Indio Blvd",
    "iso:country":"US",
    "sg:address":"83597 Indio Blvd",
    "sg:city":"Indio",
    "sg:classifiers":[
        {
            "category":"Travel",
            "subcategory":"Hotels & Motels",
            "type":"Entertainment"
        }
    ],
    "sg:phone":"+1 760 347 5180",
    "sg:postcode":"92201",
    "sg:province":"CA",
    "wof:name":"City Center Motel",
    "wof:placetype":"venue"
},
  "geometry": {"coordinates":[-116.20469900000001,33.713591],"type":"Point"}
}