{
  "type": "Feature",
  "properties": {
    "addr:full":"1251 N Manassero St Ste 405B Anaheim CA 92807",
    "addr:housenumber":"1251",
    "addr:postcode":"92807",
    "addr:street":"N Manassero St Ste 405B",
    "iso:country":"US",
    "sg:address":"1251 N Manassero St Ste 405B",
    "sg:city":"Anaheim",
    "sg:classifiers":[
        {
            "category":"Arts & Performance",
            "subcategory":"Music",
            "type":"Entertainment"
        }
    ],
    "sg:phone":"+1 714 970 9751",
    "sg:postcode":"92807",
    "sg:province":"CA",
    "sg:tags":[
        "dj"
    ],
    "wof:name":"Tony D's Productions All Occasion Mobile D J",
    "wof:placetype":"venue"
},
  "geometry": {"coordinates":[-117.81199599999999,33.860298],"type":"Point"}
}