{
  "type": "Feature",
  "properties": {
    "addr:full":"1037 Ranleigh Way Oakland CA 94610",
    "addr:housenumber":"1037",
    "addr:postcode":"94610",
    "addr:street":"Ranleigh Way",
    "iso:country":"US",
    "sg:address":"1037 Ranleigh Way",
    "sg:city":"Oakland",
    "sg:classifiers":[
        {
            "category":"Wholesale",
            "subcategory":"Stationery",
            "type":"Manufacturing & Wholesale Goods"
        }
    ],
    "sg:phone":"+1 510 835 9338",
    "sg:postcode":"94610",
    "sg:province":"CA",
    "sg:tags":[
        "supply"
    ],
    "wof:name":"Creative Memories",
    "wof:placetype":"venue"
},
  "geometry": {"coordinates":[-122.235376,37.818731],"type":"Point"}
}