{
  "type": "Feature",
  "properties": {
    "iso:country":"US",
    "sg:address":"1300 E California Ave",
    "sg:city":"Bakersfield",
    "sg:classifiers":[
        {
            "category":"Retail",
            "subcategory":"Auto Repair",
            "type":"Services"
        }
    ],
    "sg:phone":"+1 661 324 7886",
    "sg:postcode":"93307",
    "sg:province":"CA",
    "sg:tags":[
        "automobile",
        "smog"
    ],
    "wof:name":"E-Z Smog & Repair Co",
    "wof:placetype":"venue"
},
  "geometry": {"coordinates":[-118.984141,35.368488],"type":"Point"}
}