{
  "type": "Feature",
  "properties": {
    "addr:full":"2361 Harold St Kingsburg CA 93631",
    "addr:housenumber":"2361",
    "addr:postcode":"93631",
    "addr:street":"Harold St",
    "iso:country":"US",
    "sg:address":"2361 Harold St",
    "sg:city":"Kingsburg",
    "sg:classifiers":[
        {
            "category":"Farming",
            "subcategory":"Farm",
            "type":"Manufacturing & Wholesale Goods"
        }
    ],
    "sg:phone":"+1 559 897 1431",
    "sg:postcode":"93631",
    "sg:province":"CA",
    "sg:tags":[
        "crop",
        "general"
    ],
    "wof:name":"Steve Fukagawa",
    "wof:placetype":"venue"
},
  "geometry": {"coordinates":[-119.54093899999999,36.526936],"type":"Point"}
}