{
  "type": "Feature",
  "properties": {
    "addr:full":"1800 E Heim Ave Orange CA 92865",
    "addr:housenumber":"1800",
    "addr:postcode":"92865",
    "addr:street":"E Heim Ave",
    "iso:country":"US",
    "sg:address":"1800 E Heim Ave",
    "sg:city":"Orange",
    "sg:classifiers":[
        {
            "category":"Building & Trades",
            "subcategory":"Landscaping Services",
            "type":"Services"
        }
    ],
    "sg:phone":"+1 714 637 6478",
    "sg:postcode":"92865",
    "sg:province":"CA",
    "sg:tags":[
        "landscape"
    ],
    "wof:name":"Pepe Ralph",
    "wof:placetype":"venue"
},
  "geometry": {"coordinates":[-117.83529799999999,33.830154],"type":"Point"}
}