{
  "type": "Feature",
  "properties": {
    "addr:full":"2400 Studebaker Rd Long Beach CA 90899",
    "addr:housenumber":"2400",
    "addr:postcode":"90899",
    "addr:street":"Studebaker Rd",
    "iso:country":"US",
    "sg:address":"2400 Studebaker Rd",
    "sg:city":"Long Beach",
    "sg:classifiers":[
        {
            "category":"Sports & Exercise",
            "subcategory":"Golf",
            "type":"Entertainment"
        }
    ],
    "sg:phone":"+1 562 430 5411",
    "sg:postcode":"90899",
    "sg:province":"CA",
    "sg:website":"eldoradopark.americangolf.com/",
    "wof:name":"Eldorado Golf Course",
    "wof:placetype":"venue"
},
  "geometry": {"coordinates":[-118.099115,33.799831],"type":"Point"}
}