{
  "type": "Feature",
  "properties": {
    "iso:country":"US",
    "sg:address":"1056 Washington St",
    "sg:city":"Red Bluff",
    "sg:classifiers":[
        {
            "category":"Health Services",
            "subcategory":"Doctor",
            "type":"Services"
        }
    ],
    "sg:phone":"+1 530 529 1750",
    "sg:postcode":"96080",
    "sg:province":"CA",
    "sg:tags":[
        "physician",
        "surgeon"
    ],
    "wof:name":"James W Tysinger Jr MD",
    "wof:placetype":"venue"
},
  "geometry": {"coordinates":[-122.23857700000001,40.180034],"type":"Point"}
}