{
  "type": "Feature",
  "properties": {
    "iso:country":"US",
    "sg:address":"134 S Bella Vista St",
    "sg:city":"Anaheim",
    "sg:classifiers":[
        {
            "category":"Real Estate",
            "subcategory":"Real Estate Operator",
            "type":"Services"
        }
    ],
    "sg:phone":"+1 714 826 1066",
    "sg:postcode":"92804",
    "sg:province":"CA",
    "sg:tags":[
        "apartment"
    ],
    "wof:name":"Glenforset Apt",
    "wof:placetype":"venue"
},
  "geometry": {"coordinates":[-118.008003,33.8307],"type":"Point"}
}