{
  "type": "Feature",
  "properties": {
    "iso:country":"US",
    "sg:address":"1131 Frienza Ave",
    "sg:city":"Sacramento",
    "sg:classifiers":[
        {
            "category":"Taxi",
            "type":"Transportation"
        }
    ],
    "sg:phone":"+1 916 224 3595",
    "sg:postcode":"95815",
    "sg:province":"CA",
    "sg:tags":[
        "taxicab"
    ],
    "wof:name":"First Class Taxi",
    "wof:placetype":"venue"
},
  "geometry": {"coordinates":[-121.441164,38.613002],"type":"Point"}
}