{
  "type": "Feature",
  "properties": {
    "addr:full":"2653 Groton Pl Escondido CA 92025",
    "addr:housenumber":"2653",
    "addr:postcode":"92025",
    "addr:street":"Groton Pl",
    "iso:country":"US",
    "sg:address":"2653 Groton Pl",
    "sg:city":"Escondido",
    "sg:classifiers":[
        {
            "category":"Professional",
            "type":"Services"
        }
    ],
    "sg:phone":"+1 760 480 4850",
    "sg:postcode":"92025",
    "sg:province":"CA",
    "sg:tags":[
        "establishment"
    ],
    "wof:name":"Balor USA",
    "wof:placetype":"venue"
},
  "geometry": {"coordinates":[-117.044602,33.08727],"type":"Point"}
}