{
  "type": "Feature",
  "properties": {
    "iso:country":"US",
    "sg:address":"18747 Clarkdale Ave",
    "sg:city":"Artesia",
    "sg:classifiers":[
        {
            "category":"Social Services",
            "subcategory":"Child Care",
            "type":"Services"
        }
    ],
    "sg:phone":"+1 562 653 0290",
    "sg:postcode":"90701",
    "sg:province":"CA",
    "sg:tags":[
        "day"
    ],
    "wof:name":"Artesia Child Development",
    "wof:placetype":"venue"
},
  "geometry": {"coordinates":[-118.080002,33.859699],"type":"Point"}
}