{
  "type": "Feature",
  "properties": {
    "addr:full":"18747 Clarkdale Ave Artesia CA 90701",
    "addr:housenumber":"18747",
    "addr:postcode":"90701",
    "addr:street":"Clarkdale Ave",
    "iso:country":"US",
    "sg:address":"18747 Clarkdale Ave",
    "sg:city":"Artesia",
    "sg:classifiers":[
        {
            "category":"Social Services",
            "subcategory":"Child Care",
            "type":"Services"
        }
    ],
    "sg:phone":"+1 562 653 0290",
    "sg:postcode":"90701",
    "sg:province":"CA",
    "sg:tags":[
        "day"
    ],
    "wof:name":"Artesia Child Development",
    "wof:placetype":"venue"
},
  "geometry": {"coordinates":[-118.08000199999999,33.859699],"type":"Point"}
}