{
  "type": "Feature",
  "properties": {
    "addr:full":"16240 Church St Morgan Hill CA 95037",
    "addr:housenumber":"16240",
    "addr:postcode":"95037",
    "addr:street":"Church St",
    "iso:country":"US",
    "sg:address":"16240 Church St",
    "sg:city":"Morgan Hill",
    "sg:classifiers":[
        {
            "category":"Wholesale",
            "subcategory":"Electrical",
            "type":"Manufacturing & Wholesale Goods"
        }
    ],
    "sg:phone":"+1 408 779 5233",
    "sg:postcode":"95037",
    "sg:province":"CA",
    "sg:tags":[
        "equipment",
        "electric",
        "supply"
    ],
    "wof:name":"Ilcon Technology",
    "wof:placetype":"venue"
},
  "geometry": {"coordinates":[-121.64598700000001,37.121733],"type":"Point"}
}