{
  "type": "Feature",
  "properties": {
    "addr:full":"36159 Panorama Dr Yucaipa CA 92399",
    "addr:housenumber":"36159",
    "addr:postcode":"92399",
    "addr:street":"Panorama Dr",
    "iso:country":"US",
    "sg:address":"36159 Panorama Dr",
    "sg:city":"Yucaipa",
    "sg:classifiers":[
        {
            "category":"Wholesale",
            "subcategory":"Machinery & Supplies",
            "type":"Manufacturing & Wholesale Goods"
        }
    ],
    "sg:phone":"+1 909 797 2527",
    "sg:postcode":"92399",
    "sg:province":"CA",
    "sg:tags":[
        "equipment",
        "establishment"
    ],
    "wof:name":"Swipe Sales",
    "wof:placetype":"venue"
},
  "geometry": {"coordinates":[-117.014015,34.042321],"type":"Point"}
}