{
  "type": "Feature",
  "properties": {
    "addr:full":"4939 Dry Creek Rd Healdsburg CA 95448",
    "addr:housenumber":"4939",
    "addr:postcode":"95448",
    "addr:street":"Dry Creek Rd",
    "iso:country":"US",
    "sg:address":"4939 Dry Creek Rd",
    "sg:city":"Healdsburg",
    "sg:classifiers":[
        {
            "category":"Winery",
            "type":"Food & Drink"
        }
    ],
    "sg:phone":"+1 707 433 1036",
    "sg:postcode":"95448",
    "sg:province":"CA",
    "wof:name":"Del Carlo Winery",
    "wof:placetype":"venue"
},
  "geometry": {"coordinates":[-122.936723,38.673665],"type":"Point"}
}