{
  "type": "Feature",
  "properties": {
    "addr:full":"5185 Hollywood Blvd Los Angeles CA 90027",
    "addr:housenumber":"5185",
    "addr:postcode":"90027",
    "addr:street":"Hollywood Blvd",
    "iso:country":"US",
    "sg:address":"5185 Hollywood Blvd",
    "sg:city":"Los Angeles",
    "sg:classifiers":[
        {
            "category":"Food & Beverages",
            "subcategory":"Candy",
            "type":"Retail Goods"
        },
        {
            "category":"Restaurant",
            "type":"Food & Drink"
        }
    ],
    "sg:phone":"+1 323 667 2055",
    "sg:postcode":"90027",
    "sg:province":"CA",
    "sg:tags":[
        "dessert",
        "thai"
    ],
    "wof:name":"Kanom Thai Ram 2",
    "wof:placetype":"venue"
},
  "geometry": {"coordinates":[-118.303135,34.102041],"type":"Point"}
}