{
  "type": "Feature",
  "properties": {
    "iso:country":"US",
    "sg:address":"1675 Lyle Dr",
    "sg:city":"San Jose",
    "sg:classifiers":[
        {
            "category":"Professional",
            "type":"Services"
        }
    ],
    "sg:phone":"+1 408 255 2358",
    "sg:postcode":"95129",
    "sg:province":"CA",
    "wof:name":"David Amato",
    "wof:placetype":"venue"
},
  "geometry": {"coordinates":[-122.000928,37.293358],"type":"Point"}
}