{
  "type": "Feature",
  "properties": {
    "iso:country":"US",
    "sg:address":"1620 W El Camino Ave Ste 105",
    "sg:city":"Sacramento",
    "sg:classifiers":[
        {
            "category":"Restaurant",
            "type":"Food & Drink"
        }
    ],
    "sg:phone":"+1 916 646 4826",
    "sg:postcode":"95833",
    "sg:province":"CA",
    "sg:tags":[
        "mexican"
    ],
    "wof:name":"Mezcal Taqueria",
    "wof:placetype":"venue"
},
  "geometry": {"coordinates":[-121.498293,38.612645],"type":"Point"}
}