{
  "type": "Feature",
  "properties": {
    "iso:country":"US",
    "sg:address":"4579 54th St",
    "sg:city":"San Diego",
    "sg:classifiers":[
        {
            "category":"Wholesale",
            "subcategory":"Apparel",
            "type":"Manufacturing & Wholesale Goods"
        }
    ],
    "sg:phone":"+1 619 991 0417",
    "sg:postcode":"92115",
    "sg:province":"CA",
    "sg:tags":[
        "clothing"
    ],
    "wof:name":"Bea Mater",
    "wof:placetype":"venue"
},
  "geometry": {"coordinates":[-117.079353,32.759802],"type":"Point"}
}