{
  "type": "Feature",
  "properties": {
    "addr:full":"938 S Hatcher Ave City Of Industry CA 91748",
    "addr:housenumber":"938",
    "addr:postcode":"91748",
    "addr:street":"S Hatcher Ave",
    "iso:country":"US",
    "sg:address":"938 S Hatcher Ave",
    "sg:city":"City Of Industry",
    "sg:classifiers":[
        {
            "category":"Wholesale",
            "subcategory":"Metals & Minerals",
            "type":"Manufacturing & Wholesale Goods"
        }
    ],
    "sg:phone":"+1 626 810 8382",
    "sg:postcode":"91748",
    "sg:province":"CA",
    "sg:tags":[
        "die",
        "casting"
    ],
    "wof:name":"Jada Toys Inc",
    "wof:placetype":"venue"
},
  "geometry": {"coordinates":[-117.92307599999999,34.003399],"type":"Point"}
}