{
  "type": "Feature",
  "properties": {
    "iso:country":"US",
    "sg:address":"1300 Quail St",
    "sg:city":"Newport Beach",
    "sg:classifiers":[
        {
            "category":"Utilities",
            "subcategory":"Telephone",
            "type":"Services"
        }
    ],
    "sg:phone":"+1 949 260 9630",
    "sg:postcode":"92660",
    "sg:province":"CA",
    "sg:tags":[
        "communications"
    ],
    "wof:name":"Cellularbeyond Co",
    "wof:placetype":"venue"
},
  "geometry": {"coordinates":[-117.866008,33.659074],"type":"Point"}
}