{
  "type": "Feature",
  "properties": {
    "addr:full":"7519 Paradise Rd Modesto CA 95358",
    "addr:housenumber":"7519",
    "addr:postcode":"ca 95358",
    "addr:street":"Paradise Rd",
    "iso:country":"US",
    "sg:address":"7519 Paradise Rd",
    "sg:city":"Modesto",
    "sg:classifiers":[
        {
            "category":"Farming",
            "subcategory":"Crops",
            "type":"Manufacturing & Wholesale Goods"
        }
    ],
    "sg:phone":"+1 209 523 7046",
    "sg:postcode":"95358",
    "sg:province":"CA",
    "sg:tags":[
        "grove",
        "nut",
        "tree"
    ],
    "wof:name":"J Bizzini Ranch",
    "wof:placetype":"venue"
},
  "geometry": {"coordinates":[-121.14354400000001,37.614445],"type":"Point"}
}