{
  "type": "Feature",
  "properties": {
    "iso:country":"US",
    "sg:address":"109 S Pine St",
    "sg:city":"Dorris",
    "sg:classifiers":[
        {
            "category":"Food & Beverages",
            "subcategory":"Groceries & Convenience Stores",
            "type":"Retail Goods"
        }
    ],
    "sg:phone":"+1 530 397 2401",
    "sg:postcode":"96023",
    "sg:province":"CA",
    "sg:tags":[
        "grocer"
    ],
    "wof:name":"Skoog's Market",
    "wof:placetype":"venue"
},
  "geometry": {"coordinates":[-121.916895,41.965841],"type":"Point"}
}