{
  "type": "Feature",
  "properties": {
    "iso:country":"US",
    "sg:address":"1236 McAndrew Rd",
    "sg:city":"Ojai",
    "sg:classifiers":[
        {
            "category":"Organizations",
            "subcategory":"Non-profit Organization",
            "type":"Services"
        }
    ],
    "sg:phone":"+1 805 646 3967",
    "sg:postcode":"93023",
    "sg:province":"CA",
    "wof:name":"Lindley Institute",
    "wof:placetype":"venue"
},
  "geometry": {"coordinates":[-119.184022,34.459285],"type":"Point"}
}