{
  "type": "Feature",
  "properties": {
    "addr:full":"1 Capitol Mall Sacramento CA 95814",
    "addr:housenumber":"1",
    "addr:postcode":"95814",
    "addr:street":"Capitol Mall",
    "iso:country":"US",
    "sg:address":"1 Capitol Mall",
    "sg:city":"Sacramento",
    "sg:classifiers":[
        {
            "category":"Professional",
            "subcategory":"Lawyer & Legal Services",
            "type":"Services"
        }
    ],
    "sg:phone":"+1 916 498 9911",
    "sg:postcode":"95814",
    "sg:province":"CA",
    "wof:name":"Carichoff Robert A",
    "wof:placetype":"venue"
},
  "geometry": {"coordinates":[-121.50700399999999,38.580299],"type":"Point"}
}