{
  "type": "Feature",
  "properties": {
    "addr:full":"12202 Foothill Blvd Sylmar CA 91342",
    "addr:housenumber":"12202",
    "addr:postcode":"91342",
    "addr:street":"Foothill Blvd",
    "iso:country":"US",
    "sg:address":"12202 Foothill Blvd",
    "sg:city":"Sylmar",
    "sg:classifiers":[
        {
            "category":"Shopping",
            "subcategory":"Books",
            "type":"Retail Goods"
        }
    ],
    "sg:phone":"+1 818 834 4151",
    "sg:postcode":"91342",
    "sg:province":"CA",
    "sg:tags":[
        "dealer"
    ],
    "wof:name":"Skoob's Book & Gift Depot",
    "wof:placetype":"venue"
},
  "geometry": {"coordinates":[-118.40487899999999,34.283833],"type":"Point"}
}