{
  "type": "Feature",
  "properties": {
    "iso:country":"US",
    "sg:address":"42 Pala Ave",
    "sg:city":"San Jose",
    "sg:classifiers":[
        {
            "category":"Freight",
            "type":"Transportation"
        }
    ],
    "sg:phone":"+1 408 729 8351",
    "sg:postcode":"95127",
    "sg:province":"CA",
    "sg:tags":[
        "hauling",
        "trucking"
    ],
    "wof:name":"Working For My Wife",
    "wof:placetype":"venue"
},
  "geometry": {"coordinates":[-121.835292,37.363373],"type":"Point"}
}