{
  "type": "Feature",
  "properties": {
    "addr:full":"529 Root Rd Modesto CA 95357",
    "addr:housenumber":"529",
    "addr:postcode":"ca 95357",
    "addr:street":"Root Rd",
    "iso:country":"US",
    "sg:address":"529 Root Rd",
    "sg:city":"Modesto",
    "sg:classifiers":[
        {
            "category":"Farming",
            "subcategory":"Crops",
            "type":"Manufacturing & Wholesale Goods"
        }
    ],
    "sg:phone":"+1 209 571 0261",
    "sg:postcode":"95357",
    "sg:province":"CA",
    "sg:tags":[
        "grove",
        "nut",
        "tree"
    ],
    "wof:name":"Mike Grass",
    "wof:placetype":"venue"
},
  "geometry": {"coordinates":[-120.893603,37.647946],"type":"Point"}
}