{
  "type": "Feature",
  "properties": {
    "addr:full":"27872 Colonial Mission Viejo CA 92692",
    "addr:housenumber":"27872",
    "addr:postcode":"92692",
    "addr:street":"Colonial",
    "iso:country":"US",
    "sg:address":"27872 Colonial",
    "sg:city":"Mission Viejo",
    "sg:classifiers":[
        {
            "category":"Professional",
            "type":"Services"
        }
    ],
    "sg:phone":"+1 949 829 6979",
    "sg:postcode":"92692",
    "sg:province":"CA",
    "wof:name":"Med-Rep",
    "wof:placetype":"venue"
},
  "geometry": {"coordinates":[-117.645132,33.622328],"type":"Point"}
}