{
  "type": "Feature",
  "properties": {
    "addr:full":"2241 N Harrison St San Bernardino CA 92404",
    "addr:housenumber":"2241",
    "addr:postcode":"92404",
    "addr:street":"N Harrison St",
    "iso:country":"US",
    "sg:address":"2241 N Harrison St",
    "sg:city":"San Bernardino",
    "sg:classifiers":[
        {
            "category":"Building & Trades",
            "subcategory":"Landscaping Services",
            "type":"Services"
        }
    ],
    "sg:phone":"+1 909 886 9437",
    "sg:postcode":"92404",
    "sg:province":"CA",
    "sg:tags":[
        "lawn",
        "maintenance",
        "grounds"
    ],
    "wof:name":"Sunshine Day Landscaping",
    "wof:placetype":"venue"
},
  "geometry": {"coordinates":[-117.264657,34.138633],"type":"Point"}
}