{
  "type": "Feature",
  "properties": {
    "iso:country":"US",
    "sg:address":"1701 Nimbus Rd",
    "sg:city":"Rancho Cordova",
    "sg:classifiers":[
        {
            "category":"Government",
            "subcategory":"Office",
            "type":"Public Place"
        }
    ],
    "sg:phone":"+1 916 358 2950",
    "sg:postcode":"95670",
    "sg:province":"CA",
    "sg:tags":[
        "conservation"
    ],
    "wof:name":"Pesticides Investigations Lab",
    "wof:placetype":"venue"
},
  "geometry": {"coordinates":[-121.237324,38.631698],"type":"Point"}
}