{
  "type": "Feature",
  "properties": {
    "addr:full":"455 Market St Fl 6 San Francisco CA 94105",
    "addr:housenumber":"455",
    "addr:postcode":"6;94105",
    "addr:street":"Market St",
    "iso:country":"US",
    "sg:address":"455 Market St Fl 6",
    "sg:city":"San Francisco",
    "sg:classifiers":[
        {
            "category":"Banks & Credit Unions",
            "subcategory":"Financial Services",
            "type":"Services"
        },
        {
            "category":"Organizations",
            "subcategory":"Non-profit Organization",
            "type":"Services"
        }
    ],
    "sg:phone":"+1 415 744 6827",
    "sg:postcode":"94105",
    "sg:province":"CA",
    "sg:tags":[
        "service/non-profit",
        "advising",
        "community"
    ],
    "sg:website":"www.sfscore.org/",
    "wof:name":"SCORE",
    "wof:placetype":"venue"
},
  "geometry": {"coordinates":[-122.403194,37.776574],"type":"Point"}
}