{
  "type": "Feature",
  "properties": {
    "addr:full":"19340 Porto Fino Rd Tuolumne CA 95379",
    "addr:housenumber":"19340",
    "addr:postcode":"95379",
    "addr:street":"Fino Rd",
    "iso:country":"US",
    "sg:address":"19340 Porto Fino Rd",
    "sg:city":"Tuolumne",
    "sg:classifiers":[
        {
            "category":"Professional",
            "subcategory":"Detective & Security Services",
            "type":"Services"
        }
    ],
    "sg:phone":"+1 209 928 5911",
    "sg:postcode":"95379",
    "sg:province":"CA",
    "sg:tags":[
        "control",
        "monitoring",
        "system"
    ],
    "wof:name":"Tuolumne Rancheria Tribal Security",
    "wof:placetype":"venue"
},
  "geometry": {"coordinates":[-120.245062,37.972201],"type":"Point"}
}