{
  "type": "Feature",
  "properties": {
    "addr:full":"4242 Lincoln Boulevard Marina Del Rey CA 90292",
    "addr:housenumber":"4242",
    "addr:postcode":"90292",
    "addr:street":"Lincoln Boulevard",
    "iso:country":"US",
    "sg:address":"4242 Lincoln Boulevard",
    "sg:city":"Marina Del Rey",
    "sg:classifiers":[
        {
            "category":"Professional",
            "subcategory":"Business Services",
            "type":"Services"
        }
    ],
    "sg:phone":"+1 310 821 5792",
    "sg:postcode":"90292",
    "sg:province":"CA",
    "sg:tags":[
        "delivery",
        "courier"
    ],
    "wof:name":"Box & Ship",
    "wof:placetype":"venue"
},
  "geometry": {"coordinates":[-118.443724,33.985783],"type":"Point"}
}