{
  "type": "Feature",
  "properties": {
    "iso:country":"US",
    "sg:address":"6201 Lambert Ln",
    "sg:city":"El Dorado",
    "sg:classifiers":[
        {
            "category":"Shopping",
            "subcategory":"Computers & Home Electronics",
            "type":"Retail Goods"
        }
    ],
    "sg:phone":"+1 530 622 4544",
    "sg:postcode":"95623",
    "sg:province":"CA",
    "sg:tags":[
        "publishing"
    ],
    "wof:name":"Creative Works",
    "wof:placetype":"venue"
},
  "geometry": {"coordinates":[-120.854771,38.692563],"type":"Point"}
}