{
  "type": "Feature",
  "properties": {
    "iso:country":"US",
    "sg:address":"9990 County Farm Rd",
    "sg:city":"Riverside",
    "sg:classifiers":[
        {
            "category":"Government",
            "subcategory":"Office",
            "type":"Public Place"
        },
        {
            "category":"Health Services",
            "subcategory":"Clinic",
            "type":"Services"
        }
    ],
    "sg:phone":"+1 951 358 4647",
    "sg:postcode":"92503",
    "sg:province":"CA",
    "sg:tags":[
        "program",
        "administrative",
        "outpatient",
        "specialty"
    ],
    "wof:name":"Mental Health Dept",
    "wof:placetype":"venue"
},
  "geometry": {"coordinates":[-117.454261,33.920072],"type":"Point"}
}