{
  "type": "Feature",
  "properties": {
    "addr:full":"546 Santa Gertrudis Way Gonzales CA 93926",
    "addr:housenumber":"546",
    "addr:postcode":"93926",
    "addr:street":"Santa Gertrudis Way",
    "iso:country":"US",
    "sg:address":"546 Santa Gertrudis Way",
    "sg:city":"Gonzales",
    "sg:classifiers":[
        {
            "category":"Social Services",
            "subcategory":"Child Care",
            "type":"Services"
        }
    ],
    "sg:phone":"+1 831 675 3755",
    "sg:postcode":"93926",
    "sg:province":"CA",
    "wof:name":"ABC Daycare",
    "wof:placetype":"venue"
},
  "geometry": {"coordinates":[-121.430993,36.509216],"type":"Point"}
}