{
  "type": "Feature",
  "properties": {
    "addr:full":"6240 San Juan Ave Citrus Heights CA 95610",
    "addr:housenumber":"6240",
    "addr:postcode":"95610",
    "addr:street":"San Juan Ave",
    "iso:country":"US",
    "sg:address":"6240 San Juan Ave",
    "sg:city":"Citrus Heights",
    "sg:classifiers":[
        {
            "category":"Shopping",
            "subcategory":"Books",
            "type":"Retail Goods"
        }
    ],
    "sg:phone":"+1 916 723 2918",
    "sg:postcode":"95610",
    "sg:province":"CA",
    "sg:tags":[
        "bookstore"
    ],
    "wof:name":"Cj's Paperback Exchange",
    "wof:placetype":"venue"
},
  "geometry": {"coordinates":[-121.290828,38.679728],"type":"Point"}
}