{
  "type": "Feature",
  "properties": {
    "addr:full":"13507 Hubbard St Sylmar CA 91342",
    "addr:housenumber":"13507",
    "addr:postcode":"91342",
    "addr:street":"Hubbard St",
    "iso:country":"US",
    "sg:address":"13507 Hubbard St",
    "sg:city":"Sylmar",
    "sg:classifiers":[
        {
            "category":"Banks & Credit Unions",
            "subcategory":"Bank",
            "type":"Services"
        }
    ],
    "sg:phone":"+1 818 833 7557",
    "sg:postcode":"91342",
    "sg:province":"CA",
    "sg:tags":[
        "loan",
        "real estate"
    ],
    "wof:name":"Exodus Financial",
    "wof:placetype":"venue"
},
  "geometry": {"coordinates":[-118.42759,34.30997],"type":"Point"}
}