{
  "type": "Feature",
  "properties": {
    "addr:full":"6287 E Clinton Ave Fresno CA 93727",
    "addr:housenumber":"6287",
    "addr:postcode":"93727",
    "addr:street":"E Clinton Ave",
    "iso:country":"US",
    "sg:address":"6287 E Clinton Ave",
    "sg:city":"Fresno",
    "sg:classifiers":[
        {
            "category":"Building & Trades",
            "subcategory":"Construction",
            "type":"Services"
        }
    ],
    "sg:phone":"+1 559 436 0808",
    "sg:postcode":"93727",
    "sg:province":"CA",
    "sg:tags":[
        "contractor"
    ],
    "wof:name":"Pool Polishers",
    "wof:placetype":"venue"
},
  "geometry": {"coordinates":[-119.673152,36.772113],"type":"Point"}
}