{
  "type": "Feature",
  "properties": {
    "iso:country":"US",
    "sg:address":"1690 W 6th St",
    "sg:city":"Corona",
    "sg:classifiers":[
        {
            "category":"Personal",
            "subcategory":"Beauty Salon",
            "type":"Services"
        }
    ],
    "sg:phone":"+1 951 279 5468",
    "sg:postcode":"92882",
    "sg:province":"CA",
    "wof:name":"Top Hair & Nails Spa",
    "wof:placetype":"venue"
},
  "geometry": {"coordinates":[-117.596879,33.878591],"type":"Point"}
}