{
  "type": "Feature",
  "properties": {
    "addr:full":"1403 Scott St San Diego CA 92106",
    "addr:housenumber":"1403",
    "addr:postcode":"92106",
    "addr:street":"Scott St",
    "iso:country":"US",
    "sg:address":"1403 Scott St",
    "sg:city":"San Diego",
    "sg:classifiers":[
        {
            "category":"Restaurant",
            "type":"Food & Drink"
        }
    ],
    "sg:phone":"+1 619 222 8787",
    "sg:postcode":"92106",
    "sg:province":"CA",
    "sg:tags":[
        "seafood"
    ],
    "wof:name":"Mitch's Seafood",
    "wof:placetype":"venue"
},
  "geometry": {"coordinates":[-117.227377,32.72411],"type":"Point"}
}