{
  "type": "Feature",
  "properties": {
    "iso:country":"US",
    "sg:address":"13471 Magnolia St",
    "sg:city":"Garden Grove",
    "sg:classifiers":[
        {
            "category":"Restaurant",
            "type":"Food & Drink"
        }
    ],
    "sg:phone":"+1 714 530 2215",
    "sg:postcode":"92844",
    "sg:province":"CA",
    "wof:name":"Del Taco",
    "wof:placetype":"venue"
},
  "geometry": {"coordinates":[-117.972486,33.767934],"type":"Point"}
}