{
  "type": "Feature",
  "properties": {
    "addr:full":"500 E Carson St Carson CA 90745",
    "addr:housenumber":"500",
    "addr:postcode":"90745",
    "addr:street":"E Carson St",
    "iso:country":"US",
    "sg:address":"500 E Carson St",
    "sg:city":"Carson",
    "sg:classifiers":[
        {
            "category":"Home & Garden",
            "subcategory":"Carpets & Floor Coverings",
            "type":"Retail Goods"
        }
    ],
    "sg:phone":"+1 310 816 0809",
    "sg:postcode":"90745",
    "sg:province":"CA",
    "sg:tags":[
        "dealer",
        "rug"
    ],
    "wof:name":"Carpet Crew",
    "wof:placetype":"venue"
},
  "geometry": {"coordinates":[-118.267044,33.831584],"type":"Point"}
}