{
  "type": "Feature",
  "properties": {
    "addr:full":"5670 Wilshire Blvd Los Angeles CA 90036",
    "addr:housenumber":"5670",
    "addr:postcode":"90036",
    "addr:street":"Wilshire Blvd",
    "iso:country":"US",
    "sg:address":"5670 Wilshire Blvd",
    "sg:city":"Los Angeles",
    "sg:classifiers":[
        {
            "category":"Insurance",
            "subcategory":"Insurance Agent",
            "type":"Services"
        }
    ],
    "sg:phone":"+1 323 857 9400",
    "sg:postcode":"90036",
    "sg:province":"CA",
    "sg:tags":[
        "broker"
    ],
    "sg:website":"www.lemacassociates.com",
    "wof:name":"Lemac & Associates Inc",
    "wof:placetype":"venue"
},
  "geometry": {"coordinates":[-118.352197,34.062255],"type":"Point"}
}