{
  "type": "Feature",
  "properties": {
    "addr:full":"25800 Jeronimo Rd Mission Viejo CA 92691",
    "addr:housenumber":"25800",
    "addr:postcode":"92691",
    "addr:street":"Jeronimo Rd",
    "iso:country":"US",
    "sg:address":"25800 Jeronimo Rd",
    "sg:city":"Mission Viejo",
    "sg:classifiers":[
        {
            "category":"Restaurant",
            "type":"Food & Drink"
        }
    ],
    "sg:menulink":"http://www.allmenus.com/ca/trabuco/62389-waba-grill/menu/",
    "sg:phone":"+1 949 380 8803",
    "sg:postcode":"92691",
    "sg:province":"CA",
    "sg:tags":[
        "japanese",
        "asian"
    ],
    "wof:name":"Waba Grill",
    "wof:placetype":"venue"
},
  "geometry": {"coordinates":[-117.67941,33.617296],"type":"Point"}
}