{
  "type": "Feature",
  "properties": {
    "addr:full":"2859 Adams Ave San Diego CA 92116",
    "addr:housenumber":"2859",
    "addr:postcode":"92116",
    "addr:street":"Adams Ave",
    "iso:country":"US",
    "sg:address":"2859 Adams Ave",
    "sg:city":"San Diego",
    "sg:classifiers":[
        {
            "category":"Retail",
            "subcategory":"Funeral Services",
            "type":"Services"
        }
    ],
    "sg:phone":"+1 619 281 7055",
    "sg:postcode":"92116",
    "sg:province":"CA",
    "sg:tags":[
        "director"
    ],
    "sg:website":"www.allfamilyowned.com",
    "wof:name":"Mayer Mortuary",
    "wof:placetype":"venue"
},
  "geometry": {"coordinates":[-117.132228,32.762803],"type":"Point"}
}