{
  "type": "Feature",
  "properties": {
    "iso:country":"US",
    "sg:address":"2117 Pearl St",
    "sg:city":"Santa Monica",
    "sg:classifiers":[
        {
            "category":"Arts & Performance",
            "subcategory":"Theater",
            "type":"Entertainment"
        }
    ],
    "sg:phone":"+1 310 392 5673",
    "sg:postcode":"90405",
    "sg:province":"CA",
    "sg:tags":[
        "television",
        "program",
        "producer"
    ],
    "wof:name":"Frank",
    "wof:placetype":"venue"
},
  "geometry": {"coordinates":[-118.46544799999999,34.017827],"type":"Point"}
}