{
  "type": "Feature",
  "properties": {
    "iso:country":"US",
    "sg:address":"11555 Cherrylee Dr",
    "sg:city":"El Monte",
    "sg:classifiers":[
        {
            "category":"Professional",
            "type":"Services"
        }
    ],
    "sg:phone":"+1 626 444 1666",
    "sg:postcode":"91732",
    "sg:province":"CA",
    "wof:name":"Donna Carbajal",
    "wof:placetype":"venue"
},
  "geometry": {"coordinates":[-118.013727,34.095633],"type":"Point"}
}