{
  "type": "Feature",
  "properties": {
    "addr:full":"105 Beech Pl El Cajon CA 92021",
    "addr:housenumber":"105",
    "addr:postcode":"92021",
    "addr:street":"Beech Pl",
    "iso:country":"US",
    "sg:address":"105 Beech Pl",
    "sg:city":"El Cajon",
    "sg:classifiers":[
        {
            "category":"Professional",
            "subcategory":"Accounting & Tax Preparation",
            "type":"Services"
        }
    ],
    "sg:phone":"+1 619 328 9052",
    "sg:postcode":"92021",
    "sg:province":"CA",
    "sg:tags":[
        "billing"
    ],
    "wof:name":"Electronic Healthcare Billing",
    "wof:placetype":"venue"
},
  "geometry": {"coordinates":[-116.867007,32.80193],"type":"Point"}
}