{
  "type": "Feature",
  "properties": {
    "iso:country":"US",
    "sg:address":"1904 Franklin St Ste 710",
    "sg:city":"Oakland",
    "sg:classifiers":[
        {
            "category":"Health Services",
            "subcategory":"Medical Lab",
            "type":"Services"
        }
    ],
    "sg:phone":"+1 510 832 1559",
    "sg:postcode":"94612",
    "sg:province":"CA",
    "sg:tags":[
        "laboratory",
        "dental"
    ],
    "wof:name":"Stardent Ceramics Lab",
    "wof:placetype":"venue"
},
  "geometry": {"coordinates":[-122.267759,37.807342],"type":"Point"}
}