{
  "type": "Feature",
  "properties": {
    "addr:full":"2202 S Figueroa St. Los Angeles CA 90015",
    "addr:housenumber":"2202",
    "addr:postcode":"90015",
    "addr:street":"S Figueroa St.",
    "iso:country":"US",
    "sg:address":"2202 S Figueroa St.",
    "sg:city":"Los Angeles",
    "sg:classifiers":[
        {
            "category":"Real Estate",
            "subcategory":"Architect",
            "type":"Services"
        }
    ],
    "sg:phone":"+1 818 483 4830",
    "sg:postcode":"90015",
    "sg:province":"CA",
    "sg:website":"engineerinlosangeles.info",
    "wof:name":"Marvin Hornstein Structural Engineer",
    "wof:placetype":"venue"
},
  "geometry": {"coordinates":[-118.27393499999999,34.031376],"type":"Point"}
}