{
  "type": "Feature",
  "properties": {
    "iso:country":"US",
    "sg:address":"13115 W Washington Blvd",
    "sg:city":"Los Angeles",
    "sg:classifiers":[
        {
            "category":"Banks & Credit Unions",
            "subcategory":"Investment Brokerage",
            "type":"Services"
        }
    ],
    "sg:phone":"+1 310 306 5032",
    "sg:postcode":"90066",
    "sg:province":"CA",
    "sg:tags":[
        "consultant",
        "planning",
        "financial"
    ],
    "wof:name":"Parlett Financial Svc Inc",
    "wof:placetype":"venue"
},
  "geometry": {"coordinates":[-118.44145399999999,33.993832],"type":"Point"}
}