{
  "type": "Feature",
  "properties": {
    "iso:country":"US",
    "sfac:artist":"Hall, Diane Andrews",
    "sfac:created_at":"01/01/1970 12:33:29 AM +0000",
    "sfac:credit_line":"Collection of the City and County of San Francisco. Commissioned for Laguna Honda Hospital and Rehabilitation Center by the San Francisco Arts Commission.",
    "sfac:location_description":"Laguna Honda : North Residence : L1 : East Wall",
    "sfac:medium":"Glass tile mosaic",
    "sfac:revision":"2-89901dfad9fc7c8df6b76e69b2871adb",
    "sfac:title":"Morning Light 2",
    "wof:name":"Morning Light 2",
    "wof:placetype":"venue"
},
  "geometry": {"coordinates":[-122.4556651,37.7478586],"type":"Point"}
}