{
  "type": "Feature",
  "properties": {
    "iso:country":"US",
    "sg:address":"15 S Raymond Ave",
    "sg:city":"Pasadena",
    "sg:classifiers":[
        {
            "category":"Banks & Credit Unions",
            "subcategory":"Bank",
            "type":"Services"
        }
    ],
    "sg:phone":"+1 818 243 8326",
    "sg:postcode":"91105",
    "sg:province":"CA",
    "sg:tags":[
        "loan",
        "real estate"
    ],
    "wof:name":"Team Equity",
    "wof:placetype":"venue"
},
  "geometry": {"coordinates":[-118.148965,34.145618],"type":"Point"}
}