{
  "type": "Feature",
  "properties": {
    "addr:full":"7676 Hazard Center Dr San Diego CA 92108",
    "addr:housenumber":"7676",
    "addr:postcode":"92108",
    "addr:street":"Hazard Center Dr",
    "iso:country":"US",
    "sg:address":"7676 Hazard Center Dr",
    "sg:city":"San Diego",
    "sg:classifiers":[
        {
            "category":"Professional",
            "subcategory":"Management & Consulting",
            "type":"Services"
        }
    ],
    "sg:phone":"+1 619 542 4800",
    "sg:postcode":"92108",
    "sg:province":"CA",
    "sg:tags":[
        "consultant",
        "business"
    ],
    "sg:website":"www.gartner.com",
    "wof:name":"Gartner Inc",
    "wof:placetype":"venue"
},
  "geometry": {"coordinates":[-117.156763,32.770948],"type":"Point"}
}