{
  "type": "Feature",
  "properties": {
    "iso:country":"US",
    "sg:address":"1665 S Rancho Santa Fe Rd Ste B",
    "sg:city":"San Marcos",
    "sg:classifiers":[
        {
            "category":"Deli",
            "type":"Food & Drink"
        },
        {
            "category":"Food & Beverages",
            "subcategory":"Bakery",
            "type":"Retail Goods"
        }
    ],
    "sg:phone":"+1 760 744 8391",
    "sg:postcode":"92078",
    "sg:province":"CA",
    "sg:tags":[
        "sandwich"
    ],
    "sg:website":"www.eatyourlunch.net",
    "wof:name":"Eat Your Lunch",
    "wof:placetype":"venue"
},
  "geometry": {"coordinates":[-117.225066,33.105496],"type":"Point"}
}