{
  "type": "Feature",
  "properties": {
    "addr:full":"216 W Perkins St Ukiah CA 95482",
    "addr:housenumber":"216",
    "addr:postcode":"ca 95482",
    "addr:street":"W Perkins St",
    "iso:country":"US",
    "sg:address":"216 W Perkins St",
    "sg:city":"Ukiah",
    "sg:classifiers":[
        {
            "category":"Health Services",
            "subcategory":"Doctor",
            "type":"Services"
        }
    ],
    "sg:phone":"+1 707 462 1640",
    "sg:postcode":"95482",
    "sg:province":"CA",
    "sg:tags":[
        "physician",
        "surgeon"
    ],
    "wof:name":"Daniel Mandelbaum MD",
    "wof:placetype":"venue"
},
  "geometry": {"coordinates":[-123.208736,39.149887],"type":"Point"}
}