{
  "type": "Feature",
  "properties": {
    "addr:full":"4500 Millbrook Way Bakersfield CA 93313",
    "addr:housenumber":"4500",
    "addr:postcode":"93313",
    "addr:street":"Millbrook Way",
    "iso:country":"US",
    "sg:address":"4500 Millbrook Way",
    "sg:city":"Bakersfield",
    "sg:classifiers":[
        {
            "category":"Retail",
            "subcategory":"Laundry & Dry Cleaning",
            "type":"Services"
        }
    ],
    "sg:phone":"+1 661 837 2240",
    "sg:postcode":"93313",
    "sg:province":"CA",
    "sg:tags":[
        "cleaners",
        "rug",
        "carpet"
    ],
    "wof:name":"KENN Paul-Carpet Dry Cleaning",
    "wof:placetype":"venue"
},
  "geometry": {"coordinates":[-119.052537,35.302387],"type":"Point"}
}