{
  "type": "Feature",
  "properties": {
    "addr:full":"11505 Jefferson Blvd Culver City CA 90230",
    "addr:housenumber":"11505",
    "addr:postcode":"90230",
    "addr:street":"Jefferson Blvd",
    "iso:country":"US",
    "sg:address":"11505 Jefferson Blvd",
    "sg:city":"Culver City",
    "sg:classifiers":[
        {
            "category":"Manufacturing",
            "subcategory":"Retail Goods",
            "type":"Manufacturing & Wholesale Goods"
        }
    ],
    "sg:phone":"+1 310 398 4884",
    "sg:postcode":"90230",
    "sg:province":"CA",
    "sg:tags":[
        "manufacturer"
    ],
    "wof:name":"Applied Effects",
    "wof:placetype":"venue"
},
  "geometry": {"coordinates":[-118.39787800000001,33.988537],"type":"Point"}
}