{
  "type": "Feature",
  "properties": {
    "iso:country":"US",
    "sg:address":"5890 Santa Teresa Blvd",
    "sg:city":"San Jose",
    "sg:classifiers":[
        {
            "category":"Insurance",
            "subcategory":"Insurance Agent",
            "type":"Services"
        }
    ],
    "sg:phone":"+1 408 360 0830",
    "sg:postcode":"95123",
    "sg:province":"CA",
    "wof:name":"Allstate Insurance",
    "wof:placetype":"venue"
},
  "geometry": {"coordinates":[-121.831344,37.23695],"type":"Point"}
}