{
  "type": "Feature",
  "properties": {
    "addr:full":"3607 W Olympic Blvd Los Angeles CA 90019",
    "addr:housenumber":"3607",
    "addr:postcode":"90019",
    "addr:street":"W Olympic Blvd",
    "iso:country":"US",
    "sg:address":"3607 W Olympic Blvd",
    "sg:city":"Los Angeles",
    "sg:classifiers":[
        {
            "category":"Real Estate",
            "subcategory":"Architect",
            "type":"Services"
        }
    ],
    "sg:phone":"+1 323 766 9728",
    "sg:postcode":"90019",
    "sg:province":"CA",
    "wof:name":"Doo Mo Development",
    "wof:placetype":"venue"
},
  "geometry": {"coordinates":[-118.31853,34.053104],"type":"Point"}
}