{
  "type": "Feature",
  "properties": {
    "iso:country":"US",
    "sg:address":"408 Santa Florita Ave",
    "sg:city":"Millbrae",
    "sg:classifiers":[
        {
            "category":"Freight",
            "type":"Transportation"
        }
    ],
    "sg:phone":"+1 650 872 6638",
    "sg:postcode":"94030",
    "sg:province":"CA",
    "sg:tags":[
        "operator",
        "local",
        "trucking"
    ],
    "wof:name":"Lynco Delivery Systems Inc",
    "wof:placetype":"venue"
},
  "geometry": {"coordinates":[-122.412468,37.611292],"type":"Point"}
}