{
  "type": "Feature",
  "properties": {
    "addr:full":"4732-A Telephone Road Ventura CA 93003",
    "addr:housenumber":"4732-a",
    "addr:postcode":"93003",
    "addr:street":"Telephone Road",
    "iso:country":"US",
    "sg:address":"4732-A Telephone Road",
    "sg:city":"Ventura",
    "sg:classifiers":[
        {
            "category":"Real Estate",
            "subcategory":"Real Estate Services",
            "type":"Services"
        },
        {
            "category":"Real Estate",
            "subcategory":"Developer",
            "type":"Services"
        },
        {
            "category":"Real Estate",
            "subcategory":"Real Estate Agent",
            "type":"Services"
        },
        {
            "category":"Home & Garden",
            "subcategory":"Mobile Homes",
            "type":"Retail Goods"
        }
    ],
    "sg:phone":"+1 805 901 2108",
    "sg:postcode":"93003",
    "sg:province":"CA",
    "sg:tags":[
        "investing",
        "information",
        "consultant",
        "referral",
        "townhouses"
    ],
    "sg:website":"http://www.HollySellsVenturaCounty.com",
    "wof:name":"Holly ALdrich with ERA Cusick Realty",
    "wof:placetype":"venue"
},
  "geometry": {"coordinates":[-119.234354,34.260405],"type":"Point"}
}