{
  "type": "Feature",
  "properties": {
    "iso:country":"US",
    "sg:address":"775 Post St",
    "sg:city":"San Francisco",
    "sg:classifiers":[
        {
            "category":"Professional",
            "type":"Services"
        }
    ],
    "sg:phone":"+1 415 292 7953",
    "sg:postcode":"94109",
    "sg:province":"CA",
    "wof:name":"Jump",
    "wof:placetype":"venue"
},
  "geometry": {"coordinates":[-122.41400400000001,37.787539],"type":"Point"}
}