{
  "type": "Feature",
  "properties": {
    "addr:full":"924 Caton Ct Sonoma CA 95476",
    "addr:housenumber":"924",
    "addr:postcode":"95476",
    "addr:street":"Caton Ct",
    "iso:country":"US",
    "sg:address":"924 Caton Ct",
    "sg:city":"Sonoma",
    "sg:classifiers":[
        {
            "category":"Food & Beverages",
            "subcategory":"Liquor & Beverages",
            "type":"Retail Goods"
        }
    ],
    "sg:phone":"+1 707 996 0420",
    "sg:postcode":"95476",
    "sg:province":"CA",
    "sg:tags":[
        "wine"
    ],
    "wof:name":"Bonneau Wines LLC",
    "wof:placetype":"venue"
},
  "geometry": {"coordinates":[-122.50934100000001,38.338051],"type":"Point"}
}