{
  "type": "Feature",
  "properties": {
    "addr:full":"1770 Hester Avenue San Jose CA 95128",
    "addr:housenumber":"1770",
    "addr:postcode":"95128",
    "addr:street":"Hester Avenue",
    "iso:country":"US",
    "sg:address":"1770 Hester Avenue",
    "sg:city":"San Jose",
    "sg:classifiers":[
        {
            "category":"Professional",
            "subcategory":"Accounting & Tax Preparation",
            "type":"Services"
        },
        {
            "category":"Professional",
            "subcategory":"Lawyer & Legal Services",
            "type":"Services"
        }
    ],
    "sg:phone":"+1 408 295 2020",
    "sg:postcode":"95128",
    "sg:province":"CA",
    "sg:tags":[
        "notary",
        "accountant"
    ],
    "wof:name":"Courier Financial Consulting & Income Tax",
    "wof:placetype":"venue"
},
  "geometry": {"coordinates":[-121.925065,37.323707],"type":"Point"}
}