{
  "type": "Feature",
  "properties": {
    "iso:country":"US",
    "sg:address":"100 Indianola Rd",
    "sg:city":"Eureka",
    "sg:classifiers":[
        {
            "category":"Autos & Motor Vehicles",
            "subcategory":"Recreational Vehicle Sales",
            "type":"Retail Goods"
        }
    ],
    "sg:phone":"+1 707 443 2277",
    "sg:postcode":"95503",
    "sg:province":"CA",
    "wof:name":"J's Rv Ctr",
    "wof:placetype":"venue"
},
  "geometry": {"coordinates":[-124.092141,40.81903],"type":"Point"}
}