{
  "type": "Feature",
  "properties": {
    "iso:country":"US",
    "sg:address":"7978 Los Pinos Cir",
    "sg:city":"Carlsbad",
    "sg:classifiers":[
        {
            "category":"Building & Trades",
            "subcategory":"Electrical",
            "type":"Services"
        }
    ],
    "sg:phone":"+1 760 942 3500",
    "sg:postcode":"92009",
    "sg:province":"CA",
    "sg:tags":[
        "electric",
        "contractor"
    ],
    "wof:name":"Pacific Coast Electric Inc",
    "wof:placetype":"venue"
},
  "geometry": {"coordinates":[-117.255888,33.068574],"type":"Point"}
}