{
  "type": "Feature",
  "properties": {
    "addr:full":"1063 E 42nd St Los Angeles CA 90011",
    "addr:housenumber":"1063",
    "addr:postcode":"90011",
    "addr:street":"E 42Nd St",
    "iso:country":"US",
    "sg:address":"1063 E 42nd St",
    "sg:city":"Los Angeles",
    "sg:classifiers":[
        {
            "category":"Building & Trades",
            "subcategory":"Construction",
            "type":"Services"
        }
    ],
    "sg:phone":"+1 323 233 3383",
    "sg:postcode":"90011",
    "sg:province":"CA",
    "sg:tags":[
        "carpenter"
    ],
    "wof:name":"L & S Carpenter",
    "wof:placetype":"venue"
},
  "geometry": {"coordinates":[-118.257773,34.007611],"type":"Point"}
}