{
  "type": "Feature",
  "properties": {
    "iso:country":"US",
    "sg:address":"534 22nd St",
    "sg:city":"Oakland",
    "sg:classifiers":[
        {
            "category":"Organizations",
            "subcategory":"Religious Organization",
            "type":"Services"
        }
    ],
    "sg:phone":"+1 510 433 0822",
    "sg:postcode":"94612",
    "sg:province":"CA",
    "sg:tags":[
        "church"
    ],
    "wof:name":"Northern California Inter-Relg",
    "wof:placetype":"venue"
},
  "geometry": {"coordinates":[-122.27240999999999,37.81164],"type":"Point"}
}