{
  "type": "Feature",
  "properties": {
    "iso:country":"US",
    "sg:address":"801 Orange Ave Ste 206",
    "sg:city":"Coronado",
    "sg:classifiers":[
        {
            "category":"Personal",
            "subcategory":"Massage",
            "type":"Services"
        }
    ],
    "sg:phone":"+1 619 435 4600",
    "sg:postcode":"92118",
    "sg:province":"CA",
    "sg:website":"www.spanicos.com/",
    "wof:name":"Spa Nicos",
    "wof:placetype":"venue"
},
  "geometry": {"coordinates":[-117.17791,32.688357],"type":"Point"}
}