{
  "type": "Feature",
  "properties": {
    "addr:full":"1002 Cypress Way Tehachapi CA 93561",
    "addr:housenumber":"1002",
    "addr:postcode":"93561",
    "addr:street":"Cypress Way",
    "iso:country":"US",
    "sg:address":"1002 Cypress Way",
    "sg:city":"Tehachapi",
    "sg:classifiers":[
        {
            "category":"Health Services",
            "subcategory":"Nursing And Care Facility",
            "type":"Services"
        }
    ],
    "sg:phone":"+1 661 822 3597",
    "sg:postcode":"93561",
    "sg:province":"CA",
    "sg:tags":[
        "home",
        "retirement",
        "community"
    ],
    "wof:name":"Patton Family Home For Seniors",
    "wof:placetype":"venue"
},
  "geometry": {"coordinates":[-118.448195,35.120415],"type":"Point"}
}