{
  "type": "Feature",
  "properties": {
    "addr:full":"7833 Highland Ave Citrus Heights CA 95610",
    "addr:housenumber":"7833",
    "addr:postcode":"95610",
    "addr:street":"Highland Ave",
    "iso:country":"US",
    "sg:address":"7833 Highland Ave",
    "sg:city":"Citrus Heights",
    "sg:classifiers":[
        {
            "category":"Organizations",
            "subcategory":"Religious Organization",
            "type":"Services"
        }
    ],
    "sg:phone":"+1 916 723 4663",
    "sg:postcode":"95610",
    "sg:province":"CA",
    "sg:website":"www.umc.org",
    "wof:name":"Sacramento Choun Korean United Methodist Church",
    "wof:placetype":"venue"
},
  "geometry": {"coordinates":[-121.274002,38.689499],"type":"Point"}
}