{
  "type": "Feature",
  "properties": {
    "addr:full":"205 el Monte Ct Madera CA 93637",
    "addr:housenumber":"205",
    "addr:postcode":"93637",
    "addr:street":"El Monte Ct",
    "iso:country":"US",
    "sg:address":"205 el Monte Ct",
    "sg:city":"Madera",
    "sg:classifiers":[
        {
            "category":"Social Services",
            "subcategory":"Child Care",
            "type":"Services"
        }
    ],
    "sg:phone":"+1 559 674 3119",
    "sg:postcode":"93637",
    "sg:province":"CA",
    "wof:name":"Pat's Day Care",
    "wof:placetype":"venue"
},
  "geometry": {"coordinates":[-120.059245,36.948305],"type":"Point"}
}