{
  "type": "Feature",
  "properties": {
    "addr:full":"279 E Brokaw Rd San Jose CA 95112",
    "addr:housenumber":"279",
    "addr:postcode":"95112",
    "addr:street":"E Brokaw Rd",
    "iso:country":"US",
    "sg:address":"279 E Brokaw Rd",
    "sg:city":"San Jose",
    "sg:classifiers":[
        {
            "category":"Manufacturing",
            "subcategory":"Electronics",
            "type":"Manufacturing & Wholesale Goods"
        }
    ],
    "sg:phone":"+1 408 452 1081",
    "sg:postcode":"95112",
    "sg:province":"CA",
    "sg:tags":[
        "equipment",
        "electronic",
        "supply"
    ],
    "sg:website":"www.spectrasys.com",
    "wof:name":"Spectra Systems",
    "wof:placetype":"venue"
},
  "geometry": {"coordinates":[-121.914873,37.376288],"type":"Point"}
}