{
  "type": "Feature",
  "properties": {
    "iso:country":"US",
    "sg:address":"50 Alessandro Pl Ste 310",
    "sg:city":"Pasadena",
    "sg:classifiers":[
        {
            "category":"Health Services",
            "subcategory":"Doctor",
            "type":"Services"
        }
    ],
    "sg:phone":"+1 626 796 9114",
    "sg:postcode":"91105",
    "sg:province":"CA",
    "sg:tags":[
        "obstetrician",
        "gynecologist"
    ],
    "wof:name":"Pasadena Women's Medical Group Inc",
    "wof:placetype":"venue"
},
  "geometry": {"coordinates":[-118.151971,34.130624],"type":"Point"}
}