{
  "type": "Feature",
  "properties": {
    "iso:country":"US",
    "sg:address":"3830 McCall Ave",
    "sg:city":"Selma",
    "sg:classifiers":[
        {
            "category":"Government",
            "subcategory":"Post Office",
            "type":"Public Place"
        }
    ],
    "sg:phone":"+1 559 896 0125",
    "sg:postcode":"93662",
    "sg:province":"CA",
    "sg:tags":[
        "postal"
    ],
    "wof:name":"US Post Office",
    "wof:placetype":"venue"
},
  "geometry": {"coordinates":[-119.610527,36.589853],"type":"Point"}
}