{
  "type": "Feature",
  "properties": {
    "iso:country":"US",
    "sg:address":"12820 Lakeland Rd",
    "sg:city":"Santa Fe Springs",
    "sg:classifiers":[
        {
            "category":"Building & Trades",
            "subcategory":"Plumbing",
            "type":"Services"
        }
    ],
    "sg:phone":"+1 562 691 3045",
    "sg:postcode":"90670",
    "sg:province":"CA",
    "sg:tags":[
        "sheet",
        "work",
        "metal",
        "contractor"
    ],
    "wof:name":"R & R Sheet Metal",
    "wof:placetype":"venue"
},
  "geometry": {"coordinates":[-118.05809000000001,33.931658],"type":"Point"}
}