{
  "type": "Feature",
  "properties": {
    "addr:full":"13367 Borden Ave Sylmar CA 91342",
    "addr:housenumber":"13367",
    "addr:postcode":"91342",
    "addr:street":"Borden Ave",
    "iso:country":"US",
    "sg:address":"13367 Borden Ave",
    "sg:city":"Sylmar",
    "sg:classifiers":[
        {
            "category":"Organizations",
            "subcategory":"Religious Organization",
            "type":"Services"
        }
    ],
    "sg:phone":"+1 818 364 5557",
    "sg:postcode":"91342",
    "sg:province":"CA",
    "sg:tags":[
        "monastery",
        "convent"
    ],
    "wof:name":"Franciscan Sisters",
    "wof:placetype":"venue"
},
  "geometry": {"coordinates":[-118.453729,34.315647],"type":"Point"}
}