{
  "type": "Feature",
  "properties": {
    "addr:full":"383 Diablo Rd Ste 116 Danville CA 94526",
    "addr:housenumber":"383",
    "addr:postcode":"94526",
    "addr:street":"Diablo Rd Ste 116",
    "iso:country":"US",
    "sg:address":"383 Diablo Rd Ste 116",
    "sg:city":"Danville",
    "sg:classifiers":[
        {
            "category":"Organizations",
            "subcategory":"Membership Organization",
            "type":"Services"
        }
    ],
    "sg:phone":"+1 925 855 1200",
    "sg:postcode":"94526",
    "sg:province":"CA",
    "sg:tags":[
        "military",
        "veteran"
    ],
    "wof:name":"Veterans Memorial Building Development Committee Of San Ramon Valley",
    "wof:placetype":"venue"
},
  "geometry": {"coordinates":[-121.994804,37.822878],"type":"Point"}
}