{
  "type": "Feature",
  "properties": {
    "addr:full":"UCSF Medical Center 505 Parnassus Ave San Francisco CA 94143",
    "addr:housenumber":"505",
    "addr:postcode":"94143",
    "addr:street":"Parnassus Ave",
    "iso:country":"US",
    "sg:address":"UCSF Medical Center 505 Parnassus Ave",
    "sg:city":"San Francisco",
    "sg:classifiers":[
        {
            "category":"Health Services",
            "subcategory":"Hospital",
            "type":"Services"
        },
        {
            "category":"Shopping",
            "subcategory":"Gifts & Souvenirs",
            "type":"Retail Goods"
        }
    ],
    "sg:phone":"+1 415 353 1845",
    "sg:postcode":"94143",
    "sg:province":"CA",
    "sg:tags":[
        "flower"
    ],
    "sg:website":"www.ucsfhealth.org/secure/giftsh...",
    "wof:name":"UCSF Hospital Moffitt Gift Shop",
    "wof:placetype":"venue"
},
  "geometry": {"coordinates":[-122.458074,37.763389],"type":"Point"}
}