{
  "type": "Feature",
  "properties": {
    "addr:full":"22971 Triton Way Laguna Hills CA 92653",
    "addr:housenumber":"22971",
    "addr:postcode":"92653",
    "addr:street":"Triton Way",
    "iso:country":"US",
    "sg:address":"22971 Triton Way",
    "sg:city":"Laguna Hills",
    "sg:classifiers":[
        {
            "category":"Autos & Motor Vehicles",
            "subcategory":"Auto Supplies",
            "type":"Retail Goods"
        }
    ],
    "sg:phone":"+1 949 768 4311",
    "sg:postcode":"92653",
    "sg:province":"CA",
    "sg:tags":[
        "automobile",
        "parts"
    ],
    "wof:name":"Oasis Off Road Mfg",
    "wof:placetype":"venue"
},
  "geometry": {"coordinates":[-117.73207499999999,33.629366],"type":"Point"}
}