{
  "type": "Feature",
  "properties": {
    "addr:full":"10896 Cedar Ave Bloomington CA 92316",
    "addr:housenumber":"10896",
    "addr:postcode":"92316",
    "addr:street":"Cedar Ave",
    "iso:country":"US",
    "sg:address":"10896 Cedar Ave",
    "sg:city":"Bloomington",
    "sg:classifiers":[
        {
            "category":"Food & Beverages",
            "subcategory":"Liquor & Beverages",
            "type":"Retail Goods"
        }
    ],
    "sg:phone":"+1 909 877 2256",
    "sg:postcode":"92316",
    "sg:province":"CA",
    "sg:tags":[
        "wine"
    ],
    "wof:name":"C & H Liquors",
    "wof:placetype":"venue"
},
  "geometry": {"coordinates":[-117.396497,34.060371],"type":"Point"}
}