{
  "type": "Feature",
  "properties": {
    "iso:country":"US",
    "sg:address":"1017 W Foothill Blvd",
    "sg:city":"Azusa",
    "sg:classifiers":[
        {
            "category":"Building & Trades",
            "subcategory":"Plumbing",
            "type":"Services"
        }
    ],
    "sg:phone":"+1 626 815 1632",
    "sg:postcode":"91702",
    "sg:province":"CA",
    "sg:tags":[
        "conditioning",
        "air",
        "system",
        "contractor"
    ],
    "wof:name":"Comfort Climate Control",
    "wof:placetype":"venue"
},
  "geometry": {"coordinates":[-117.921488,34.133692],"type":"Point"}
}