{
  "type": "Feature",
  "properties": {
    "addr:full":"8820 W Pico Blvd Los Angeles CA 90035",
    "addr:housenumber":"8820",
    "addr:postcode":"90035",
    "addr:street":"W Pico Blvd",
    "iso:country":"US",
    "sg:address":"8820 W Pico Blvd",
    "sg:city":"Los Angeles",
    "sg:classifiers":[
        {
            "category":"Shopping",
            "subcategory":"Clothing, Apparel, & Fashions",
            "type":"Retail Goods"
        }
    ],
    "sg:phone":"+1 310 273 1559",
    "sg:postcode":"90035",
    "sg:province":"CA",
    "sg:tags":[
        "tailor"
    ],
    "wof:name":"Woody Wilson Cllctn Cstm Tailr",
    "wof:placetype":"venue"
},
  "geometry": {"coordinates":[-118.38410399999999,34.054739],"type":"Point"}
}