{
  "type": "Feature",
  "properties": {
    "addr:full":"2911 N San Fernando Rd Los Angeles CA 90065",
    "addr:housenumber":"2911",
    "addr:postcode":"90065",
    "addr:street":"N San Fernando Rd",
    "iso:country":"US",
    "sg:address":"2911 N San Fernando Rd",
    "sg:city":"Los Angeles",
    "sg:classifiers":[
        {
            "category":"Professional",
            "type":"Services"
        }
    ],
    "sg:phone":"+1 323 256 0704",
    "sg:postcode":"90065",
    "sg:province":"CA",
    "wof:name":"Roberts Catering Svc",
    "wof:placetype":"venue"
},
  "geometry": {"coordinates":[-118.243206,34.110765],"type":"Point"}
}