{
  "type": "Feature",
  "properties": {
    "iso:country":"US",
    "sg:address":"8400 Enterprise Way",
    "sg:city":"Oakland",
    "sg:classifiers":[
        {
            "category":"Social Services",
            "subcategory":"Job Training",
            "type":"Services"
        }
    ],
    "sg:phone":"+1 510 553 0991",
    "sg:postcode":"94621",
    "sg:province":"CA",
    "sg:tags":[
        "apprenticeship",
        "program"
    ],
    "wof:name":"Bac Local 3 Apprentice Office",
    "wof:placetype":"venue"
},
  "geometry": {"coordinates":[-122.195177,37.744025],"type":"Point"}
}