{
  "type": "Feature",
  "properties": {
    "addr:full":"405 Kains Ave Albany CA 94706",
    "addr:housenumber":"405",
    "addr:postcode":"94706",
    "addr:street":"Kains Ave",
    "iso:country":"US",
    "sg:address":"405 Kains Ave",
    "sg:city":"Albany",
    "sg:classifiers":[
        {
            "category":"Real Estate",
            "subcategory":"Real Estate Services",
            "type":"Services"
        },
        {
            "category":"Banks & Credit Unions",
            "subcategory":"Investment Brokerage",
            "type":"Services"
        },
        {
            "category":"Banks & Credit Unions",
            "subcategory":"Financial Services",
            "type":"Services"
        }
    ],
    "sg:phone":"+1 510 525 0073",
    "sg:postcode":"94706",
    "sg:province":"CA",
    "sg:tags":[
        "loan",
        "management",
        "broker",
        "mortgage"
    ],
    "wof:name":"Hannah Investment",
    "wof:placetype":"venue"
},
  "geometry": {"coordinates":[-122.300348,37.897764],"type":"Point"}
}