{
  "type": "Feature",
  "properties": {
    "addr:full":"801 Oakdale Rd Modesto CA 95355",
    "addr:housenumber":"801",
    "addr:postcode":"ca 95355",
    "addr:street":"Oakdale Rd",
    "iso:country":"US",
    "sg:address":"801 Oakdale Rd",
    "sg:city":"Modesto",
    "sg:classifiers":[
        {
            "category":"Restaurant",
            "type":"Food & Drink"
        }
    ],
    "sg:phone":"+1 209 238 0222",
    "sg:postcode":"95355",
    "sg:province":"CA",
    "wof:name":"Baja Fresh",
    "wof:placetype":"venue"
},
  "geometry": {"coordinates":[-120.95700100000001,37.653099],"type":"Point"}
}