{
  "type": "Feature",
  "properties": {
    "iso:country":"US",
    "sg:address":"2 Guerrero St",
    "sg:city":"San Francisco",
    "sg:classifiers":[
        {
            "category":"Personal",
            "subcategory":"Beauty Salon",
            "type":"Services"
        }
    ],
    "sg:phone":"+1 415 701 7424",
    "sg:postcode":"94103",
    "sg:province":"CA",
    "wof:name":"Shag Hair Salon",
    "wof:placetype":"venue"
},
  "geometry": {"coordinates":[-122.424581,37.769735],"type":"Point"}
}