{
  "type": "Feature",
  "properties": {
    "iso:country":"US",
    "sg:address":"5419 Hollywood Blvd",
    "sg:city":"Los Angeles",
    "sg:classifiers":[
        {
            "category":"Airline",
            "type":"Transportation"
        }
    ],
    "sg:phone":"+1 323 238 4641",
    "sg:postcode":"90027",
    "sg:province":"CA",
    "sg:website":"www.privatejetcharterflightslosa...",
    "wof:name":"Private Jet Charter Flights",
    "wof:placetype":"venue"
},
  "geometry": {"coordinates":[-118.307544,34.101763],"type":"Point"}
}