{
  "type": "Feature",
  "properties": {
    "addr:full":"5419 Hollywood Blvd Los Angeles CA 90027",
    "addr:housenumber":"5419",
    "addr:postcode":"90027",
    "addr:street":"Hollywood Blvd",
    "iso:country":"US",
    "sg:address":"5419 Hollywood Blvd",
    "sg:city":"Los Angeles",
    "sg:classifiers":[
        {
            "category":"Airline",
            "type":"Transportation"
        }
    ],
    "sg:phone":"+1 323 238 4641",
    "sg:postcode":"90027",
    "sg:province":"CA",
    "sg:website":"www.privatejetcharterflightslosa...",
    "wof:name":"Private Jet Charter Flights",
    "wof:placetype":"venue"
},
  "geometry": {"coordinates":[-118.30754399999999,34.101763],"type":"Point"}
}