{
  "type": "Feature",
  "properties": {
    "addr:full":"1416 9th St Lbby Sacramento CA 95814",
    "addr:housenumber":"1416",
    "addr:postcode":"95814",
    "addr:street":"9Th St",
    "iso:country":"US",
    "sg:address":"1416 9th St Lbby",
    "sg:city":"Sacramento",
    "sg:classifiers":[
        {
            "category":"Professional",
            "subcategory":"Engineering",
            "type":"Services"
        }
    ],
    "sg:phone":"+1 916 653 8055",
    "sg:postcode":"95814",
    "sg:province":"CA",
    "sg:tags":[
        "consulting",
        "engineer"
    ],
    "wof:name":"Leslie Frederick Harder Jr",
    "wof:placetype":"venue"
},
  "geometry": {"coordinates":[-121.496798,38.576048],"type":"Point"}
}