{
  "type": "Feature",
  "properties": {
    "iso:country":"US",
    "sg:address":"8561 Pierce Dr",
    "sg:city":"Buena Park",
    "sg:classifiers":[
        {
            "category":"Building & Trades",
            "subcategory":"Electrical",
            "type":"Services"
        }
    ],
    "sg:phone":"+1 714 995 6460",
    "sg:postcode":"90620",
    "sg:province":"CA",
    "sg:tags":[
        "electrical",
        "contractor"
    ],
    "wof:name":"Loop Electrical Systems",
    "wof:placetype":"venue"
},
  "geometry": {"coordinates":[-118.006333,33.837841],"type":"Point"}
}