{
  "type": "Feature",
  "properties": {
    "iso:country":"US",
    "sg:address":"9661 Brighton Way",
    "sg:city":"Beverly Hills",
    "sg:classifiers":[
        {
            "category":"Shopping",
            "subcategory":"Clothing, Apparel, & Fashions",
            "type":"Retail Goods"
        }
    ],
    "sg:phone":"+1 310 888 8882",
    "sg:postcode":"90210",
    "sg:province":"CA",
    "sg:tags":[
        "children's",
        "men's",
        "clothing",
        "women's"
    ],
    "sg:website":"www.petit-bateau.us",
    "wof:name":"Petit Bateau",
    "wof:placetype":"venue"
},
  "geometry": {"coordinates":[-118.405147,34.067852],"type":"Point"}
}