{
  "type": "Feature",
  "properties": {
    "iso:country":"US",
    "sg:address":"655 Sunset Dr",
    "sg:city":"Paradise",
    "sg:classifiers":[
        {
            "category":"Wholesale",
            "subcategory":"Metals & Minerals",
            "type":"Manufacturing & Wholesale Goods"
        }
    ],
    "sg:phone":"+1 530 877 9602",
    "sg:postcode":"95969",
    "sg:province":"CA",
    "sg:tags":[
        "equipment",
        "detecting"
    ],
    "wof:name":"Van Camp Robert",
    "wof:placetype":"venue"
},
  "geometry": {"coordinates":[-121.626541,39.768719],"type":"Point"}
}