{
  "type": "Feature",
  "properties": {
    "iso:country":"US",
    "sg:address":"4280 Lerida Dr",
    "sg:city":"San Diego",
    "sg:classifiers":[
        {
            "category":"Building & Trades",
            "subcategory":"Construction",
            "type":"Services"
        }
    ],
    "sg:phone":"+1 619 583 2400",
    "sg:postcode":"92115",
    "sg:province":"CA",
    "sg:tags":[
        "siding",
        "contractor"
    ],
    "wof:name":"Eide's Custom Remodels",
    "wof:placetype":"venue"
},
  "geometry": {"coordinates":[-117.059973,32.756307],"type":"Point"}
}