{
  "type": "Feature",
  "properties": {
    "addr:full":"Zephyr Real Estate 215 W Portal San Francisco CA 94127",
    "addr:housenumber":"215",
    "addr:postcode":"94127",
    "addr:street":"W Portal",
    "iso:country":"US",
    "sg:address":"Zephyr Real Estate 215 W Portal",
    "sg:city":"San Francisco",
    "sg:classifiers":[
        {
            "category":"Real Estate",
            "subcategory":"Real Estate Agent",
            "type":"Services"
        }
    ],
    "sg:phone":"+1 415 846 7246",
    "sg:postcode":"94127",
    "sg:province":"CA",
    "sg:website":"www.kevinfeather.com",
    "wof:name":"Kevin Feather",
    "wof:placetype":"venue"
},
  "geometry": {"coordinates":[-122.468166,37.738738],"type":"Point"}
}