{
  "type": "Feature",
  "properties": {
    "iso:country":"US",
    "sg:address":"1527 Cypress St",
    "sg:city":"Walnut Creek",
    "sg:classifiers":[
        {
            "category":"Shopping",
            "subcategory":"Musical Instruments",
            "type":"Retail Goods"
        }
    ],
    "sg:phone":"+1 925 930 8554",
    "sg:postcode":"94596",
    "sg:province":"CA",
    "sg:tags":[
        "piano"
    ],
    "wof:name":"A Legacy Piano Resales",
    "wof:placetype":"venue"
},
  "geometry": {"coordinates":[-122.062004,37.898878],"type":"Point"}
}