{
  "type": "Feature",
  "properties": {
    "addr:full":"15427 Foothill Blvd Fontana CA 92335",
    "addr:housenumber":"15427",
    "addr:postcode":"92335",
    "addr:street":"Foothill Blvd",
    "iso:country":"US",
    "sg:address":"15427 Foothill Blvd",
    "sg:city":"Fontana",
    "sg:classifiers":[
        {
            "category":"Freight",
            "type":"Transportation"
        }
    ],
    "sg:phone":"+1 951 300 1758",
    "sg:postcode":"92335",
    "sg:province":"CA",
    "sg:tags":[
        "operator",
        "trucking"
    ],
    "wof:name":"Inland Transporters LLC",
    "wof:placetype":"venue"
},
  "geometry": {"coordinates":[-117.46543699999999,34.106448],"type":"Point"}
}