{
  "type": "Feature",
  "properties": {
    "addr:full":"8800 Cal Center Dr Sacramento CA 95826",
    "addr:postcode":"8800;95826",
    "addr:street":"Center Dr",
    "iso:country":"US",
    "sg:address":"8800 Cal Center Dr",
    "sg:city":"Sacramento",
    "sg:classifiers":[
        {
            "category":"Government",
            "subcategory":"Office",
            "type":"Public Place"
        }
    ],
    "sg:phone":"+1 916 255 3545",
    "sg:postcode":"95826",
    "sg:province":"CA",
    "sg:tags":[
        "waste",
        "management"
    ],
    "wof:name":"Sacramento Regional Office",
    "wof:placetype":"venue"
},
  "geometry": {"coordinates":[-121.375131,38.555797],"type":"Point"}
}