{
  "type": "Feature",
  "properties": {
    "addr:full":"1055 Carlsbad Village Dr Carlsbad CA 92008",
    "addr:housenumber":"1055",
    "addr:postcode":"92008",
    "addr:street":"Carlsbad Village Dr",
    "iso:country":"US",
    "sg:address":"1055 Carlsbad Village Dr",
    "sg:city":"Carlsbad",
    "sg:classifiers":[
        {
            "category":"Shopping",
            "subcategory":"Jewelry",
            "type":"Retail Goods"
        }
    ],
    "sg:phone":"+1 760 729 5121",
    "sg:postcode":"92008",
    "sg:province":"CA",
    "sg:tags":[
        "watch"
    ],
    "wof:name":"Bob's Carlsbad Clock Shop Sales & Repr & Antqe Mll",
    "wof:placetype":"venue"
},
  "geometry": {"coordinates":[-117.34200300000001,33.163799],"type":"Point"}
}