{
  "type": "Feature",
  "properties": {
    "iso:country":"US",
    "sg:address":"11782 Western Ave",
    "sg:city":"Stanton",
    "sg:classifiers":[
        {
            "category":"Retail",
            "subcategory":"Auto Repair",
            "type":"Services"
        }
    ],
    "sg:phone":"+1 714 895 7784",
    "sg:postcode":"90680",
    "sg:province":"CA",
    "sg:tags":[
        "automobile",
        "electric"
    ],
    "wof:name":"Winder Alternators",
    "wof:placetype":"venue"
},
  "geometry": {"coordinates":[-118.001487,33.792201],"type":"Point"}
}