{
  "type": "Feature",
  "properties": {
    "addr:full":"2955 Junipero Serra Blvd Daly City CA 94014",
    "addr:housenumber":"2955",
    "addr:postcode":"94014",
    "addr:street":"Junipero Serra Blvd",
    "iso:country":"US",
    "sg:address":"2955 Junipero Serra Blvd",
    "sg:city":"Daly City",
    "sg:classifiers":[
        {
            "category":"Personal",
            "subcategory":"Barber",
            "type":"Services"
        }
    ],
    "sg:phone":"+1 650 992 4700",
    "sg:postcode":"94014",
    "sg:province":"CA",
    "wof:name":"Accent On Men",
    "wof:placetype":"venue"
},
  "geometry": {"coordinates":[-122.47043600000001,37.687488],"type":"Point"}
}