{
  "type": "Feature",
  "properties": {
    "addr:full":"2925 E St Eureka CA 95501",
    "addr:housenumber":"2925",
    "addr:postcode":"95501",
    "addr:street":"E St",
    "iso:country":"US",
    "sg:address":"2925 E St",
    "sg:city":"Eureka",
    "sg:classifiers":[
        {
            "category":"Restaurant",
            "type":"Food & Drink"
        }
    ],
    "sg:phone":"+1 707 442 9218",
    "sg:postcode":"95501",
    "sg:province":"CA",
    "wof:name":"Coney Island",
    "wof:placetype":"venue"
},
  "geometry": {"coordinates":[-124.164547,40.781353],"type":"Point"}
}