{
  "type": "Feature",
  "properties": {
    "iso:country":"US",
    "sg:address":"1440 Olivewood Ln",
    "sg:city":"Alpine",
    "sg:classifiers":[
        {
            "category":"Real Estate",
            "subcategory":"Real Estate Operator",
            "type":"Services"
        }
    ],
    "sg:phone":"+1 866 417 7932",
    "sg:postcode":"91901",
    "sg:province":"CA",
    "sg:tags":[
        "apartment"
    ],
    "sg:website":"http://www.forrent.com/apartment-community-profile/1021815.php?cmp=CAC-CSearchProfile",
    "wof:name":"Alpine Terrace",
    "wof:placetype":"venue"
},
  "geometry": {"coordinates":[-116.76863899999999,32.834733],"type":"Point"}
}