{
  "type": "Feature",
  "properties": {
    "iso:country":"US",
    "sg:address":"3281 S Maple Ave",
    "sg:city":"Fresno",
    "sg:classifiers":[
        {
            "category":"Professional",
            "subcategory":"Engineering",
            "type":"Services"
        }
    ],
    "sg:phone":"+1 559 486 1695",
    "sg:postcode":"93725",
    "sg:province":"CA",
    "sg:tags":[
        "engineer"
    ],
    "wof:name":"Tetra Tech Inc",
    "wof:placetype":"venue"
},
  "geometry": {"coordinates":[-119.745729,36.687016],"type":"Point"}
}