{
  "type": "Feature",
  "properties": {
    "addr:full":"2231 J St Sacramento CA 95816",
    "addr:housenumber":"2231",
    "addr:postcode":"95816",
    "addr:street":"J St",
    "iso:country":"US",
    "sg:address":"2231 J St",
    "sg:city":"Sacramento",
    "sg:classifiers":[
        {
            "category":"Shopping",
            "type":"Retail Goods"
        }
    ],
    "sg:phone":"+1 916 448 8108",
    "sg:postcode":"95816",
    "sg:province":"CA",
    "sg:tags":[
        "hearing",
        "equipment",
        "supply",
        "merchandise",
        "impaired"
    ],
    "wof:name":"All Ears Hearing Aid Center",
    "wof:placetype":"venue"
},
  "geometry": {"coordinates":[-121.476191,38.575806],"type":"Point"}
}