{
  "type": "Feature",
  "properties": {
    "iso:country":"US",
    "sg:address":"2401 E Katella Ave Ste 505",
    "sg:city":"Anaheim",
    "sg:classifiers":[
        {
            "category":"Professional",
            "subcategory":"Lawyer & Legal Services",
            "type":"Services"
        }
    ],
    "sg:phone":"+1 714 385 0123",
    "sg:postcode":"92806",
    "sg:province":"CA",
    "wof:name":"Law Offices of John H Smith III",
    "wof:placetype":"venue"
},
  "geometry": {"coordinates":[-117.883003,33.805801],"type":"Point"}
}