{
  "type": "Feature",
  "properties": {
    "iso:country":"US",
    "sg:address":"55 S Lake Ave",
    "sg:city":"Pasadena",
    "sg:classifiers":[
        {
            "category":"Insurance",
            "subcategory":"Title Insurance",
            "type":"Services"
        }
    ],
    "sg:phone":"+1 626 304 9797",
    "sg:postcode":"91101",
    "sg:province":"CA",
    "wof:name":"Land Title Insurance Company",
    "wof:placetype":"venue"
},
  "geometry": {"coordinates":[-118.13242200000001,34.145509],"type":"Point"}
}