{
  "type": "Feature",
  "properties": {
    "iso:country":"US",
    "sg:address":"5550 Wardell Way",
    "sg:city":"Sacramento",
    "sg:classifiers":[
        {
            "category":"Building & Trades",
            "subcategory":"Electrical",
            "type":"Services"
        }
    ],
    "sg:phone":"+1 916 613 9285",
    "sg:postcode":"95823",
    "sg:province":"CA",
    "sg:tags":[
        "electrician"
    ],
    "wof:name":"Rhino Electric",
    "wof:placetype":"venue"
},
  "geometry": {"coordinates":[-121.438222,38.479211],"type":"Point"}
}