{
  "type": "Feature",
  "properties": {
    "addr:full":"1933 Otoole Way San Jose CA 95131",
    "addr:housenumber":"1933",
    "addr:postcode":"95131",
    "addr:street":"Otoole Way",
    "iso:country":"US",
    "sg:address":"1933 Otoole Way",
    "sg:city":"San Jose",
    "sg:classifiers":[
        {
            "category":"Real Estate",
            "subcategory":"Real Estate Operator",
            "type":"Services"
        },
        {
            "category":"Professional",
            "subcategory":"Lawyer & Legal Services",
            "type":"Services"
        }
    ],
    "sg:phone":"+1 408 922 0530",
    "sg:postcode":"95131",
    "sg:province":"CA",
    "sg:tags":[
        "apartment"
    ],
    "wof:name":"Hsu Michael Law Offices of",
    "wof:placetype":"venue"
},
  "geometry": {"coordinates":[-121.905841,37.38598],"type":"Point"}
}