{
  "type": "Feature",
  "properties": {
    "addr:full":"20459 Yorba Linda Blvd Yorba Linda CA 92886",
    "addr:housenumber":"20459",
    "addr:postcode":"92886",
    "addr:street":"Yorba Linda Blvd",
    "iso:country":"US",
    "sg:address":"20459 Yorba Linda Blvd",
    "sg:city":"Yorba Linda",
    "sg:classifiers":[
        {
            "category":"Real Estate",
            "subcategory":"Real Estate Agent",
            "type":"Services"
        }
    ],
    "sg:phone":"+1 714 777 5112",
    "sg:postcode":"92886",
    "sg:province":"CA",
    "sg:tags":[
        "loan",
        "broker"
    ],
    "wof:name":"Re/Max",
    "wof:placetype":"venue"
},
  "geometry": {"coordinates":[-117.779526,33.891032],"type":"Point"}
}