{
  "type": "Feature",
  "properties": {
    "addr:full":"400 S. El Camino Real Suite 375 San Mateo CA 94402",
    "addr:housenumber":"400",
    "addr:postcode":"94402",
    "addr:street":"S. El Camino Real Suite 375",
    "iso:country":"US",
    "sg:address":"400 S. El Camino Real Suite 375",
    "sg:city":"San Mateo",
    "sg:classifiers":[
        {
            "category":"Professional",
            "subcategory":"Computer Services",
            "type":"Services"
        }
    ],
    "sg:phone":"+1 866 338 1306",
    "sg:postcode":"94402",
    "sg:province":"CA",
    "sg:website":"http://www.conduit.com",
    "wof:name":"Conduit",
    "wof:placetype":"venue"
},
  "geometry": {"coordinates":[-122.324479,37.561645],"type":"Point"}
}