{
  "type": "Feature",
  "properties": {
    "addr:full":"901 S La Brea Ave Inglewood CA 90302",
    "addr:housenumber":"901",
    "addr:postcode":"90302",
    "addr:street":"S La Brea Ave",
    "iso:country":"US",
    "sg:address":"901 S La Brea Ave",
    "sg:city":"Inglewood",
    "sg:classifiers":[
        {
            "category":"Restaurant",
            "type":"Food & Drink"
        }
    ],
    "sg:phone":"+1 310 677 1900",
    "sg:postcode":"90302",
    "sg:province":"CA",
    "sg:tags":[
        "italian"
    ],
    "sg:website":"www.dominos.com/",
    "wof:name":"Domino's Pizza",
    "wof:placetype":"venue"
},
  "geometry": {"coordinates":[-118.35275300000001,33.952616],"type":"Point"}
}