{
  "type": "Feature",
  "properties": {
    "addr:full":"120 Hidden Valley Pkwy Norco CA 92860",
    "addr:housenumber":"120",
    "addr:postcode":"92860",
    "addr:street":"Hidden Valley Pkwy",
    "iso:country":"US",
    "sg:address":"120 Hidden Valley Pkwy",
    "sg:city":"Norco",
    "sg:classifiers":[
        {
            "category":"Personal",
            "subcategory":"Nail Salon",
            "type":"Services"
        }
    ],
    "sg:phone":"+1 951 479 0259",
    "sg:postcode":"92860",
    "sg:province":"CA",
    "wof:name":"True Touch Nails & Spa",
    "wof:placetype":"venue"
},
  "geometry": {"coordinates":[-117.562223,33.898061],"type":"Point"}
}