{
  "type": "Feature",
  "properties": {
    "iso:country":"US",
    "sg:address":"514 E Ivy St",
    "sg:city":"Hanford",
    "sg:classifiers":[
        {
            "category":"Shopping",
            "subcategory":"Gifts & Souvenirs",
            "type":"Retail Goods"
        }
    ],
    "sg:phone":"+1 559 587 0193",
    "sg:postcode":"93230",
    "sg:province":"CA",
    "wof:name":"Central Valli Kali Novelties",
    "wof:placetype":"venue"
},
  "geometry": {"coordinates":[-119.639406,36.332231],"type":"Point"}
}