{
  "type": "Feature",
  "properties": {
    "iso:country":"US",
    "sg:address":"2205 Harrison Ave",
    "sg:city":"San Diego",
    "sg:classifiers":[
        {
            "category":"Organizations",
            "subcategory":"Religious Organization",
            "type":"Services"
        }
    ],
    "sg:phone":"+1 619 234 5506",
    "sg:postcode":"92113",
    "sg:province":"CA",
    "sg:tags":[
        "church"
    ],
    "sg:website":"www.newhopefriendship.org",
    "wof:name":"New Hope Friendship Church",
    "wof:placetype":"venue"
},
  "geometry": {"coordinates":[-117.134584,32.700126],"type":"Point"}
}