{
  "type": "Feature",
  "properties": {
    "iso:country":"US",
    "sg:address":"8714 Imperial Hwy",
    "sg:city":"Downey",
    "sg:classifiers":[
        {
            "category":"Retail",
            "subcategory":"Repair Shop",
            "type":"Services"
        }
    ],
    "sg:phone":"+1 562 869 5850",
    "sg:postcode":"90242",
    "sg:province":"CA",
    "sg:tags":[
        "repairing",
        "lawn",
        "supply",
        "mower"
    ],
    "wof:name":"Viramontes' Lawnmower Shop",
    "wof:placetype":"venue"
},
  "geometry": {"coordinates":[-118.139719,33.917533],"type":"Point"}
}