{
  "type": "Feature",
  "properties": {
    "iso:country":"US",
    "sg:address":"517 Clipper St",
    "sg:city":"San Francisco",
    "sg:classifiers":[
        {
            "category":"Manufacturing",
            "subcategory":"Printing",
            "type":"Manufacturing & Wholesale Goods"
        }
    ],
    "sg:phone":"+1 415 824 7702",
    "sg:postcode":"94114",
    "sg:province":"CA",
    "sg:tags":[
        "broker"
    ],
    "wof:name":"Robinson Printing Brokerage",
    "wof:placetype":"venue"
},
  "geometry": {"coordinates":[-122.43794,37.748576],"type":"Point"}
}