{
  "type": "Feature",
  "properties": {
    "iso:country":"US",
    "sg:address":"7213 Hollywood Blvd",
    "sg:city":"West Hollywood",
    "sg:classifiers":[
        {
            "category":"Health Services",
            "subcategory":"Clinic",
            "type":"Services"
        }
    ],
    "sg:phone":"+1 323 882 6033",
    "sg:postcode":"90046",
    "sg:province":"CA",
    "wof:name":"LA Patients & Caregivers Grp",
    "wof:placetype":"venue"
},
  "geometry": {"coordinates":[-118.347174,34.101687],"type":"Point"}
}