{
  "type": "Feature",
  "properties": {
    "iso:country":"US",
    "sg:address":"1 Results Way",
    "sg:city":"Cupertino",
    "sg:classifiers":[
        {
            "category":"Wholesale",
            "subcategory":"Machinery & Supplies",
            "type":"Manufacturing & Wholesale Goods"
        }
    ],
    "sg:phone":"+1 408 255 1500",
    "sg:postcode":"95014",
    "sg:province":"CA",
    "sg:tags":[
        "equipment",
        "industrial"
    ],
    "wof:name":"Measurex Latin America",
    "wof:placetype":"venue"
},
  "geometry": {"coordinates":[-122.05137,37.31715],"type":"Point"}
}