{
  "type": "Feature",
  "properties": {
    "iso:country":"US",
    "sg:address":"2008 Paradise Rd",
    "sg:city":"Modesto",
    "sg:classifiers":[
        {
            "category":"Professional",
            "type":"Services"
        }
    ],
    "sg:phone":"+1 209 530 9539",
    "sg:postcode":"95358",
    "sg:province":"CA",
    "sg:tags":[
        "establishment"
    ],
    "wof:name":"Silvestreus Custom Design",
    "wof:placetype":"venue"
},
  "geometry": {"coordinates":[-121.035702,37.615297],"type":"Point"}
}