{
  "type": "Feature",
  "properties": {
    "iso:country":"US",
    "sg:address":"1613 Squirrel Ln",
    "sg:city":"Ventura",
    "sg:classifiers":[
        {
            "category":"Communications",
            "subcategory":"Film & Video Production",
            "type":"Services"
        }
    ],
    "sg:phone":"+1 805 659 1000",
    "sg:postcode":"93003",
    "sg:province":"CA",
    "sg:tags":[
        "taping"
    ],
    "wof:name":"A Advantage Video Productions",
    "wof:placetype":"venue"
},
  "geometry": {"coordinates":[-119.195175,34.261997],"type":"Point"}
}