{
  "type": "Feature",
  "properties": {
    "addr:full":"13400 Kirkham Way Poway CA 92064",
    "addr:housenumber":"13400",
    "addr:postcode":"ca 92064",
    "addr:street":"Kirkham Way",
    "iso:country":"US",
    "sg:address":"13400 Kirkham Way",
    "sg:city":"Poway",
    "sg:classifiers":[
        {
            "category":"Home & Garden",
            "subcategory":"Building Materials",
            "type":"Retail Goods"
        }
    ],
    "sg:phone":"+1 858 748 8070",
    "sg:postcode":"92064",
    "sg:province":"CA",
    "wof:name":"Pro Con Supply",
    "wof:placetype":"venue"
},
  "geometry": {"coordinates":[-117.04591000000001,32.935095],"type":"Point"}
}