{
  "type": "Feature",
  "properties": {
    "iso:country":"US",
    "sg:address":"5330 Allison Ln",
    "sg:city":"Riverside",
    "sg:classifiers":[
        {
            "category":"Personal",
            "type":"Services"
        }
    ],
    "sg:phone":"+1 951 685 2317",
    "sg:postcode":"92509",
    "sg:province":"CA",
    "sg:tags":[
        "miscellaneous"
    ],
    "wof:name":"Post Lady",
    "wof:placetype":"venue"
},
  "geometry": {"coordinates":[-117.50246199999999,33.991963],"type":"Point"}
}