{
  "type": "Feature",
  "properties": {
    "addr:full":"1315 el Camino Real Menlo Park CA 94025",
    "addr:housenumber":"1315",
    "addr:postcode":"94025",
    "addr:street":"El Camino Real",
    "iso:country":"US",
    "sg:address":"1315 el Camino Real",
    "sg:city":"Menlo Park",
    "sg:classifiers":[
        {
            "category":"Travel",
            "subcategory":"Hotels & Motels",
            "type":"Entertainment"
        }
    ],
    "sg:phone":"+1 650 326 7530",
    "sg:postcode":"94025",
    "sg:province":"CA",
    "wof:name":"Menlo Park Inn",
    "wof:placetype":"venue"
},
  "geometry": {"coordinates":[-122.18642199999999,37.45511],"type":"Point"}
}