{
  "type": "Feature",
  "properties": {
    "addr:full":"12961 Ramona Blvd Irwindale CA 91706",
    "addr:housenumber":"12961",
    "addr:postcode":"91706",
    "addr:street":"Ramona Blvd",
    "iso:country":"US",
    "sg:address":"12961 Ramona Blvd",
    "sg:city":"Irwindale",
    "sg:classifiers":[
        {
            "category":"Building & Trades",
            "subcategory":"Construction",
            "type":"Services"
        }
    ],
    "sg:phone":"+1 626 814 4404",
    "sg:postcode":"91706",
    "sg:province":"CA",
    "sg:tags":[
        "maker",
        "cabinet"
    ],
    "wof:name":"J R Custom Cabinets",
    "wof:placetype":"venue"
},
  "geometry": {"coordinates":[-117.989777,34.079498],"type":"Point"}
}