{
  "type": "Feature",
  "properties": {
    "addr:full":"383 S Palm Canyon Dr Palm Springs CA 92262",
    "addr:housenumber":"383",
    "addr:postcode":"92262",
    "addr:street":"S Palm Canyon Dr",
    "iso:country":"US",
    "sg:address":"383 S Palm Canyon Dr",
    "sg:city":"Palm Springs",
    "sg:classifiers":[
        {
            "category":"Professional",
            "type":"Services"
        }
    ],
    "sg:phone":"+1 760 778 9911",
    "sg:postcode":"92262",
    "sg:province":"CA",
    "wof:name":"Ednah Root Foundation",
    "wof:placetype":"venue"
},
  "geometry": {"coordinates":[-116.546858,33.817347],"type":"Point"}
}