{
  "type": "Feature",
  "properties": {
    "iso:country":"US",
    "sg:address":"3701 Lone Tree Way",
    "sg:city":"Antioch",
    "sg:classifiers":[
        {
            "category":"Professional",
            "subcategory":"Accounting & Tax Preparation",
            "type":"Services"
        }
    ],
    "sg:phone":"+1 925 754 7110",
    "sg:postcode":"94509",
    "sg:province":"CA",
    "sg:tags":[
        "return",
        "filing"
    ],
    "wof:name":"BMG Income Tax & Payroll Svc",
    "wof:placetype":"venue"
},
  "geometry": {"coordinates":[-121.805637,37.983331],"type":"Point"}
}