{
  "type": "Feature",
  "properties": {
    "addr:full":"5560 S Centinela Ave Los Angeles CA 90066",
    "addr:housenumber":"5560",
    "addr:postcode":"90066",
    "addr:street":"S Centinela Ave",
    "iso:country":"US",
    "sg:address":"5560 S Centinela Ave",
    "sg:city":"Los Angeles",
    "sg:classifiers":[
        {
            "category":"Building & Trades",
            "subcategory":"Construction",
            "type":"Services"
        }
    ],
    "sg:phone":"+1 310 821 1785",
    "sg:postcode":"90066",
    "sg:province":"CA",
    "sg:tags":[
        "contractor"
    ],
    "wof:name":"Hoffman & Associates Building Corp",
    "wof:placetype":"venue"
},
  "geometry": {"coordinates":[-118.410004,33.981701],"type":"Point"}
}