{
  "type": "Feature",
  "properties": {
    "iso:country":"US",
    "sg:address":"3000 Colby Street Suite 304",
    "sg:city":"Berkeley",
    "sg:classifiers":[
        {
            "category":"Health Services",
            "subcategory":"Doctor",
            "type":"Services"
        }
    ],
    "sg:phone":"+1 510 848 7533",
    "sg:postcode":"94705",
    "sg:province":"CA",
    "wof:name":"Charles McLaughlin, MD",
    "wof:placetype":"venue"
},
  "geometry": {"coordinates":[-122.25770799999999,37.855295],"type":"Point"}
}