{
  "type": "Feature",
  "properties": {
    "addr:full":"2952 Carson Rd Placerville CA 95667",
    "addr:housenumber":"2952",
    "addr:postcode":"95667",
    "addr:street":"Carson Rd",
    "iso:country":"US",
    "sg:address":"2952 Carson Rd",
    "sg:city":"Placerville",
    "sg:classifiers":[
        {
            "category":"Farming",
            "subcategory":"Orchard",
            "type":"Manufacturing & Wholesale Goods"
        }
    ],
    "sg:phone":"+1 530 626 1508",
    "sg:postcode":"95667",
    "sg:province":"CA",
    "sg:tags":[
        "fruit",
        "tree"
    ],
    "wof:name":"Gold Country Orchard",
    "wof:placetype":"venue"
},
  "geometry": {"coordinates":[-120.716638,38.738614],"type":"Point"}
}