{
  "type": "Feature",
  "properties": {
    "addr:full":"380 World Way Los Angeles CA 90045",
    "addr:housenumber":"380",
    "addr:postcode":"90045",
    "addr:street":"World Way",
    "iso:country":"US",
    "sg:address":"380 World Way",
    "sg:city":"Los Angeles",
    "sg:classifiers":[
        {
            "category":"Banks & Credit Unions",
            "subcategory":"Bank",
            "type":"Services"
        }
    ],
    "sg:phone":"+1 310 338 9736",
    "sg:postcode":"90045",
    "sg:province":"CA",
    "sg:tags":[
        "broker",
        "foreign",
        "dealer",
        "exchange"
    ],
    "sg:website":"www.iceplc.com",
    "wof:name":"Ice Currency Exchange",
    "wof:placetype":"venue"
},
  "geometry": {"coordinates":[-118.40681600000001,33.944724],"type":"Point"}
}