{
  "type": "Feature",
  "properties": {
    "iso:country":"US",
    "sg:address":"2011 Perkins Ln",
    "sg:city":"Redondo Beach",
    "sg:classifiers":[
        {
            "category":"Professional",
            "subcategory":"Accounting & Tax Preparation",
            "type":"Services"
        }
    ],
    "sg:phone":"+1 310 542 6069",
    "sg:postcode":"90278",
    "sg:province":"CA",
    "sg:tags":[
        "return",
        "filing"
    ],
    "wof:name":"Mary Jane Healy Accounting Svc",
    "wof:placetype":"venue"
},
  "geometry": {"coordinates":[-118.36226000000001,33.873718],"type":"Point"}
}