{
  "type": "Feature",
  "properties": {
    "iso:country":"US",
    "sg:address":"31760 Mission Trl",
    "sg:city":"Lake Elsinore",
    "sg:classifiers":[
        {
            "category":"Autos & Motor Vehicles",
            "subcategory":"Auto Supplies",
            "type":"Retail Goods"
        }
    ],
    "sg:phone":"+1 951 245 1948",
    "sg:postcode":"92530",
    "sg:province":"CA",
    "sg:tags":[
        "automobile",
        "parts"
    ],
    "wof:name":"Autoaid",
    "wof:placetype":"venue"
},
  "geometry": {"coordinates":[-117.299022,33.658815],"type":"Point"}
}