{
  "type": "Feature",
  "properties": {
    "iso:country":"US",
    "sg:address":"671 W Arrow Hwy",
    "sg:city":"Claremont",
    "sg:classifiers":[
        {
            "category":"Professional",
            "subcategory":"Management & Consulting",
            "type":"Services"
        }
    ],
    "sg:phone":"+1 909 625 9117",
    "sg:postcode":"91711",
    "sg:province":"CA",
    "sg:tags":[
        "consultant",
        "business"
    ],
    "wof:name":"Cn Management",
    "wof:placetype":"venue"
},
  "geometry": {"coordinates":[-117.72441000000001,34.090438],"type":"Point"}
}