{
  "type": "Feature",
  "properties": {
    "addr:full":"4026 Hilton Head Way Tarzana CA 91356",
    "addr:housenumber":"4026",
    "addr:postcode":"91356",
    "addr:street":"Hilton Head Way",
    "iso:country":"US",
    "sg:address":"4026 Hilton Head Way",
    "sg:city":"Tarzana",
    "sg:classifiers":[
        {
            "category":"Health Services",
            "subcategory":"Doctor",
            "type":"Services"
        },
        {
            "category":"Health Services",
            "subcategory":"Hospital",
            "type":"Services"
        }
    ],
    "sg:phone":"+1 818 324 9185",
    "sg:postcode":"91356",
    "sg:province":"CA",
    "sg:tags":[
        "consultant",
        "medical",
        "practice",
        "nursing",
        "home"
    ],
    "wof:name":"Precise Consultation",
    "wof:placetype":"venue"
},
  "geometry": {"coordinates":[-118.53265399999999,34.144103],"type":"Point"}
}