{
  "type": "Feature",
  "properties": {
    "addr:full":"27811 Greenspot Rd Highland CA 92346",
    "addr:housenumber":"27811",
    "addr:postcode":"92346",
    "addr:street":"Greenspot Rd",
    "iso:country":"US",
    "sg:address":"27811 Greenspot Rd",
    "sg:city":"Highland",
    "sg:classifiers":[
        {
            "category":"Insurance",
            "subcategory":"Insurance Agent",
            "type":"Services"
        },
        {
            "category":"Insurance",
            "subcategory":"Hazard Insurance",
            "type":"Services"
        },
        {
            "category":"Insurance",
            "subcategory":"Title Insurance",
            "type":"Services"
        },
        {
            "category":"Insurance",
            "subcategory":"Life Insurance",
            "type":"Services"
        }
    ],
    "sg:phone":"+1 909 864 4110",
    "sg:postcode":"92346",
    "sg:province":"CA",
    "sg:tags":[
        "business",
        "auto",
        "commercial",
        "homeowner",
        "motorcycle",
        "renter"
    ],
    "wof:name":"Allstate Insurance Company - Gardner Son",
    "wof:placetype":"venue"
},
  "geometry": {"coordinates":[-117.17292,34.109535],"type":"Point"}
}