{
  "type": "Feature",
  "properties": {
    "addr:full":"100 Citadel Dr Los Angeles CA 90040",
    "addr:housenumber":"100",
    "addr:postcode":"90040",
    "addr:street":"Citadel Dr",
    "iso:country":"US",
    "sg:address":"100 Citadel Dr",
    "sg:city":"Los Angeles",
    "sg:classifiers":[
        {
            "category":"Shopping",
            "subcategory":"Clothing, Apparel, & Fashions",
            "type":"Retail Goods"
        }
    ],
    "sg:phone":"+1 323 887 8906",
    "sg:postcode":"90040",
    "sg:province":"CA",
    "sg:tags":[
        "lingerie"
    ],
    "wof:name":"Maidenform Outlet No 24",
    "wof:placetype":"venue"
},
  "geometry": {"coordinates":[-118.15300000000001,34.0051],"type":"Point"}
}