{
  "type": "Feature",
  "properties": {
    "addr:full":"16 Ottawa St San Mateo CA 94401",
    "addr:housenumber":"16",
    "addr:postcode":"94401",
    "addr:street":"Ottawa St",
    "iso:country":"US",
    "sg:address":"16 Ottawa St",
    "sg:city":"San Mateo",
    "sg:classifiers":[
        {
            "category":"Professional",
            "type":"Services"
        }
    ],
    "sg:phone":"+1 650 344 2881",
    "sg:postcode":"94401",
    "sg:province":"CA",
    "wof:name":"Euroarts",
    "wof:placetype":"venue"
},
  "geometry": {"coordinates":[-122.313683,37.577022],"type":"Point"}
}