{
  "type": "Feature",
  "properties": {
    "addr:full":"7700 Bell Rd Windsor CA 95492",
    "addr:housenumber":"7700",
    "addr:postcode":"95492",
    "addr:street":"Bell Rd",
    "iso:country":"US",
    "sg:address":"7700 Bell Rd",
    "sg:city":"Windsor",
    "sg:classifiers":[
        {
            "category":"Real Estate",
            "subcategory":"Developer",
            "type":"Services"
        }
    ],
    "sg:phone":"+1 707 838 6633",
    "sg:postcode":"95492",
    "sg:province":"CA",
    "wof:name":"Windsor Business Park-SBR Dev",
    "wof:placetype":"venue"
},
  "geometry": {"coordinates":[-122.799935,38.535352],"type":"Point"}
}