{
  "type": "Feature",
  "properties": {
    "iso:country":"US",
    "sg:address":"1311 W Carson St",
    "sg:city":"Torrance",
    "sg:classifiers":[
        {
            "category":"Fast Food",
            "type":"Food & Drink"
        }
    ],
    "sg:postcode":"90501",
    "sg:province":"CA",
    "sg:tags":[
        "burger"
    ],
    "wof:name":"Louis Burgers IV",
    "wof:placetype":"venue"
},
  "geometry": {"coordinates":[-118.300045,33.831522],"type":"Point"}
}