{
  "type": "Feature",
  "properties": {
    "addr:full":"3559 E 1st St Los Angeles CA 90063",
    "addr:housenumber":"3559",
    "addr:postcode":"90063",
    "addr:street":"E 1St St",
    "iso:country":"US",
    "sg:address":"3559 E 1st St",
    "sg:city":"Los Angeles",
    "sg:classifiers":[
        {
            "category":"Food & Beverages",
            "subcategory":"Bakery",
            "type":"Retail Goods"
        }
    ],
    "sg:phone":"+1 323 261 5613",
    "sg:postcode":"90063",
    "sg:province":"CA",
    "sg:tags":[
        "baker"
    ],
    "wof:name":"La Espiga De Oro Bakery",
    "wof:placetype":"venue"
},
  "geometry": {"coordinates":[-118.191002,34.036098],"type":"Point"}
}