{
  "type": "Feature",
  "properties": {
    "iso:country":"US",
    "sg:address":"125 W Hermosa St",
    "sg:city":"Lindsay",
    "sg:classifiers":[
        {
            "category":"Fast Food",
            "type":"Food & Drink"
        },
        {
            "category":"Restaurant",
            "type":"Food & Drink"
        }
    ],
    "sg:phone":"+1 559 562 3330",
    "sg:postcode":"93247",
    "sg:province":"CA",
    "sg:tags":[
        "take"
    ],
    "wof:name":"In Bob's Drive",
    "wof:placetype":"venue"
},
  "geometry": {"coordinates":[-119.09168,36.204892],"type":"Point"}
}