{
  "type": "Feature",
  "properties": {
    "iso:country":"US",
    "sg:address":"10946 Woodward Ave",
    "sg:city":"Sunland",
    "sg:classifiers":[
        {
            "category":"Manufacturing",
            "subcategory":"Printing",
            "type":"Manufacturing & Wholesale Goods"
        }
    ],
    "sg:phone":"+1 818 353 0209",
    "sg:postcode":"91040",
    "sg:province":"CA",
    "sg:tags":[
        "lithographic",
        "commercial"
    ],
    "wof:name":"T&T Printing",
    "wof:placetype":"venue"
},
  "geometry": {"coordinates":[-118.30698,34.26955],"type":"Point"}
}