{
  "type": "Feature",
  "properties": {
    "addr:full":"1415 E Gage Ave Los Angeles CA 90001",
    "addr:housenumber":"1415",
    "addr:postcode":"90001",
    "addr:street":"E Gage Ave",
    "iso:country":"US",
    "sg:address":"1415 E Gage Ave",
    "sg:city":"Los Angeles",
    "sg:classifiers":[
        {
            "category":"Shopping",
            "subcategory":"Clothing, Apparel, & Fashions",
            "type":"Retail Goods"
        }
    ],
    "sg:phone":"+1 323 584 8457",
    "sg:postcode":"90001",
    "sg:province":"CA",
    "wof:name":"Save Plus Inc",
    "wof:placetype":"venue"
},
  "geometry": {"coordinates":[-118.24795899999999,33.982006],"type":"Point"}
}