{
  "type": "Feature",
  "properties": {
    "addr:full":"2020 Cam del Rio N San Diego CA 92108",
    "addr:housenumber":"2020",
    "addr:postcode":"92108",
    "addr:street":"Cam Del Rio N",
    "iso:country":"US",
    "sg:address":"2020 Cam del Rio N",
    "sg:city":"San Diego",
    "sg:classifiers":[
        {
            "category":"Health Services",
            "subcategory":"Doctor",
            "type":"Services"
        }
    ],
    "sg:phone":"+1 619 523 4969",
    "sg:postcode":"92108",
    "sg:province":"CA",
    "sg:tags":[
        "physician",
        "surgeon"
    ],
    "wof:name":"Marc D Rose MD",
    "wof:placetype":"venue"
},
  "geometry": {"coordinates":[-117.14214200000001,32.770634],"type":"Point"}
}