{
  "type": "Feature",
  "properties": {
    "iso:country":"US",
    "sg:address":"1318 S 1st St",
    "sg:city":"Turlock",
    "sg:classifiers":[
        {
            "category":"Manufacturing",
            "subcategory":"Tools & Machinery",
            "type":"Manufacturing & Wholesale Goods"
        }
    ],
    "sg:phone":"+1 209 632 5787",
    "sg:postcode":"95380",
    "sg:province":"CA",
    "sg:tags":[
        "machine",
        "shop"
    ],
    "wof:name":"Stb Machine Shop Inc",
    "wof:placetype":"venue"
},
  "geometry": {"coordinates":[-120.836084,37.483722],"type":"Point"}
}