{
  "type": "Feature",
  "properties": {
    "iso:country":"US",
    "sg:address":"4220 Verdant St",
    "sg:city":"Los Angeles",
    "sg:classifiers":[
        {
            "category":"Manufacturing",
            "subcategory":"Tools & Machinery",
            "type":"Manufacturing & Wholesale Goods"
        }
    ],
    "sg:phone":"+1 818 241 0705",
    "sg:postcode":"90039",
    "sg:province":"CA",
    "sg:tags":[
        "physician",
        "surgeon"
    ],
    "wof:name":"I Care Intl",
    "wof:placetype":"venue"
},
  "geometry": {"coordinates":[-118.265333,34.131371],"type":"Point"}
}