{
  "type": "Feature",
  "properties": {
    "addr:full":"1153 Bordeaux Dr Ste 205 Sunnyvale CA 94089",
    "addr:housenumber":"1153",
    "addr:postcode":"94089",
    "addr:street":"Bordeaux Dr Ste 205",
    "iso:country":"US",
    "sg:address":"1153 Bordeaux Dr Ste 205",
    "sg:city":"Sunnyvale",
    "sg:classifiers":[
        {
            "category":"Professional",
            "subcategory":"Accounting & Tax Preparation",
            "type":"Services"
        },
        {
            "category":"Banks & Credit Unions",
            "subcategory":"Financial Services",
            "type":"Services"
        }
    ],
    "sg:phone":"+1 408 745 1099",
    "sg:postcode":"94089",
    "sg:province":"CA",
    "sg:tags":[
        "accountant",
        "advising"
    ],
    "sg:website":"www.hovavtax.com",
    "wof:name":"Hovav Tax Services",
    "wof:placetype":"venue"
},
  "geometry": {"coordinates":[-122.023841,37.405958],"type":"Point"}
}