{
  "type": "Feature",
  "properties": {
    "addr:full":"760 E Parkridge Ave Corona CA 92879",
    "addr:housenumber":"760",
    "addr:postcode":"92879",
    "addr:street":"E Parkridge Ave",
    "iso:country":"US",
    "sg:address":"760 E Parkridge Ave",
    "sg:city":"Corona",
    "sg:classifiers":[
        {
            "category":"Professional",
            "type":"Services"
        }
    ],
    "sg:phone":"+1 951 278 1402",
    "sg:postcode":"92879",
    "sg:province":"CA",
    "wof:name":"Prenett Air Charter LLC",
    "wof:placetype":"venue"
},
  "geometry": {"coordinates":[-117.55094200000001,33.885305],"type":"Point"}
}