{
  "type": "Feature",
  "properties": {
    "addr:full":"9055 Locust St Elk Grove CA 95624",
    "addr:housenumber":"9055",
    "addr:postcode":"95624",
    "addr:street":"Locust St",
    "iso:country":"US",
    "sg:address":"9055 Locust St",
    "sg:city":"Elk Grove",
    "sg:classifiers":[
        {
            "category":"Education",
            "subcategory":"School",
            "type":"Public Place"
        }
    ],
    "sg:phone":"+1 916 685 8303",
    "sg:postcode":"95624",
    "sg:province":"CA",
    "wof:name":"Advanced Instrl Model Chtr Sch",
    "wof:placetype":"venue"
},
  "geometry": {"coordinates":[-121.363252,38.410199],"type":"Point"}
}