{
  "type": "Feature",
  "properties": {
    "addr:full":"125 N 12th Ave Upland CA 91786",
    "addr:housenumber":"125",
    "addr:postcode":"91786",
    "addr:street":"N 12Th Ave",
    "iso:country":"US",
    "sg:address":"125 N 12th Ave",
    "sg:city":"Upland",
    "sg:classifiers":[
        {
            "category":"Building & Trades",
            "subcategory":"Construction",
            "type":"Services"
        }
    ],
    "sg:phone":"+1 909 946 4177",
    "sg:postcode":"91786",
    "sg:province":"CA",
    "sg:tags":[
        "tile",
        "dealer"
    ],
    "wof:name":"John A Gilbertson Tile Custom",
    "wof:placetype":"venue"
},
  "geometry": {"coordinates":[-117.635299,34.094978],"type":"Point"}
}