{
  "type": "Feature",
  "properties": {
    "addr:full":"444 S Cedros Ave Ste 175 Solana Beach CA 92075",
    "addr:housenumber":"444",
    "addr:postcode":"92075",
    "addr:street":"S Cedros Ave Ste 175",
    "iso:country":"US",
    "sg:address":"444 S Cedros Ave Ste 175",
    "sg:city":"Solana Beach",
    "sg:classifiers":[
        {
            "category":"Building & Trades",
            "subcategory":"Construction",
            "type":"Services"
        }
    ],
    "sg:phone":"+1 858 794 3222",
    "sg:postcode":"92075",
    "sg:province":"CA",
    "sg:tags":[
        "interior",
        "design"
    ],
    "wof:name":"Design Corp",
    "wof:placetype":"venue"
},
  "geometry": {"coordinates":[-117.269997,32.987499],"type":"Point"}
}