{
  "type": "Feature",
  "properties": {
    "iso:country":"US",
    "sg:address":"252 E Bellevue Rd",
    "sg:city":"Atwater",
    "sg:classifiers":[
        {
            "category":"Wholesale",
            "subcategory":"Sporting Goods",
            "type":"Manufacturing & Wholesale Goods"
        }
    ],
    "sg:phone":"+1 209 357 7149",
    "sg:postcode":"95301",
    "sg:province":"CA",
    "sg:tags":[
        "business"
    ],
    "wof:name":"Clearwater Pools",
    "wof:placetype":"venue"
},
  "geometry": {"coordinates":[-120.59492299999999,37.360392],"type":"Point"}
}