{
  "type": "Feature",
  "properties": {
    "addr:full":"22837 Pacific Coast Hwy Malibu CA 90265",
    "addr:housenumber":"22837",
    "addr:postcode":"90265",
    "addr:street":"Pacific Coast Hwy",
    "iso:country":"US",
    "sg:address":"22837 Pacific Coast Hwy",
    "sg:city":"Malibu",
    "sg:classifiers":[
        {
            "category":"Health Services",
            "subcategory":"Health Practitioner",
            "type":"Services"
        }
    ],
    "sg:phone":"+1 310 456 1044",
    "sg:postcode":"90265",
    "sg:province":"CA",
    "sg:tags":[
        "hypnotist"
    ],
    "wof:name":"Adrian Finkelstein",
    "wof:placetype":"venue"
},
  "geometry": {"coordinates":[-118.6724,34.039167],"type":"Point"}
}