{
  "type": "Feature",
  "properties": {
    "addr:full":"12662 W Chapman Ave Garden Grove CA 92840",
    "addr:housenumber":"12662",
    "addr:postcode":"92840",
    "addr:street":"W Chapman Ave",
    "iso:country":"US",
    "sg:address":"12662 W Chapman Ave",
    "sg:city":"Garden Grove",
    "sg:classifiers":[
        {
            "category":"Wholesale",
            "subcategory":"Machinery & Supplies",
            "type":"Manufacturing & Wholesale Goods"
        }
    ],
    "sg:phone":"+1 714 750 0787",
    "sg:postcode":"92840",
    "sg:province":"CA",
    "sg:tags":[
        "equipment",
        "establishment"
    ],
    "wof:name":"Kathy Beauty Supply",
    "wof:placetype":"venue"
},
  "geometry": {"coordinates":[-117.913408,33.788766],"type":"Point"}
}