{
  "type": "Feature",
  "properties": {
    "addr:full":"725 36th St Manhattan Beach CA 90266",
    "addr:housenumber":"725",
    "addr:postcode":"90266",
    "addr:street":"36Th St",
    "iso:country":"US",
    "sg:address":"725 36th St",
    "sg:city":"Manhattan Beach",
    "sg:classifiers":[
        {
            "category":"Professional",
            "subcategory":"Management & Consulting",
            "type":"Services"
        }
    ],
    "sg:phone":"+1 310 546 1939",
    "sg:postcode":"90266",
    "sg:province":"CA",
    "sg:tags":[
        "consultant",
        "business"
    ],
    "sg:website":"www.rschendel.com",
    "wof:name":"Chemical & Refining Technology",
    "wof:placetype":"venue"
},
  "geometry": {"coordinates":[-118.404945,33.900992],"type":"Point"}
}