{
  "type": "Feature",
  "properties": {
    "addr:full":"20400 Stevens Creek Blvd Cupertino CA 95014",
    "addr:housenumber":"20400",
    "addr:postcode":"95014",
    "addr:street":"Stevens Creek Blvd",
    "iso:country":"US",
    "sg:address":"20400 Stevens Creek Blvd",
    "sg:city":"Cupertino",
    "sg:classifiers":[
        {
            "category":"Professional",
            "subcategory":"Computer Services",
            "type":"Services"
        },
        {
            "category":"Internet Cafe",
            "subcategory":"None",
            "type":"Food & Drink"
        }
    ],
    "sg:phone":"+1 408 725 7904",
    "sg:postcode":"95014",
    "sg:province":"CA",
    "sg:tags":[
        "software",
        "product",
        "isp",
        "provider"
    ],
    "wof:name":"VM Ops",
    "wof:placetype":"venue"
},
  "geometry": {"coordinates":[-122.03028,37.322822],"type":"Point"}
}