{
  "type": "Feature",
  "properties": {
    "iso:country":"US",
    "sg:address":"459 61st St",
    "sg:city":"Oakland",
    "sg:classifiers":[
        {
            "category":"Organizations",
            "subcategory":"Religious Organization",
            "type":"Services"
        }
    ],
    "sg:phone":"+1 510 654 8788",
    "sg:postcode":"94609",
    "sg:province":"CA",
    "sg:tags":[
        "church"
    ],
    "wof:name":"Rock Truth Baptist Church",
    "wof:placetype":"venue"
},
  "geometry": {"coordinates":[-122.258213,37.847519],"type":"Point"}
}