{
  "type": "Feature",
  "properties": {
    "addr:full":"3727 Mission St San Francisco CA 94110",
    "addr:housenumber":"3727",
    "addr:postcode":"94110",
    "addr:street":"Mission St",
    "iso:country":"US",
    "sg:address":"3727 Mission St",
    "sg:city":"San Francisco",
    "sg:classifiers":[
        {
            "category":"Social Services",
            "subcategory":"Child Care",
            "type":"Services"
        }
    ],
    "sg:phone":"+1 415 401 7911",
    "sg:postcode":"94110",
    "sg:province":"CA",
    "wof:name":"Fannie's Child Care",
    "wof:placetype":"venue"
},
  "geometry": {"coordinates":[-122.42398,37.737306],"type":"Point"}
}