{
  "type": "Feature",
  "properties": {
    "addr:full":"1180 Old Topanga Canyon Rd Topanga CA 90290",
    "addr:housenumber":"1180",
    "addr:postcode":"90290",
    "addr:street":"Old Topanga Canyon Rd",
    "iso:country":"US",
    "sg:address":"1180 Old Topanga Canyon Rd",
    "sg:city":"Topanga",
    "sg:classifiers":[
        {
            "category":"Utilities",
            "subcategory":"Fuel Oil & Lpg",
            "type":"Services"
        }
    ],
    "sg:phone":"+1 805 577 1129",
    "sg:postcode":"90290",
    "sg:province":"CA",
    "sg:tags":[
        "development",
        "exploration",
        "gas"
    ],
    "sg:website":"http://www.hardrockdrilling.com",
    "wof:name":"Hardrock Drilling",
    "wof:placetype":"venue"
},
  "geometry": {"coordinates":[-118.626394,34.104073],"type":"Point"}
}