{
  "type": "Feature",
  "properties": {
    "addr:full":"300 Lakeside Dr Oakland CA 94601",
    "addr:housenumber":"300",
    "addr:postcode":"94601",
    "addr:street":"Lakeside Dr",
    "iso:country":"US",
    "sg:address":"300 Lakeside Dr",
    "sg:city":"Oakland",
    "sg:classifiers":[
        {
            "category":"Professional",
            "subcategory":"Lawyer & Legal Services",
            "type":"Services"
        }
    ],
    "sg:phone":"+1 510 451 0544",
    "sg:postcode":"94601",
    "sg:province":"CA",
    "wof:name":"Rockwell Lawrence K",
    "wof:placetype":"venue"
},
  "geometry": {"coordinates":[-122.218002,37.779701],"type":"Point"}
}