{
  "type": "Feature",
  "properties": {
    "addr:full":"6633 Topanga Canyon Blvd Woodland Hills CA 91303",
    "addr:housenumber":"6633",
    "addr:postcode":"91303",
    "addr:street":"Topanga Canyon Blvd",
    "iso:country":"US",
    "sg:address":"6633 Topanga Canyon Blvd",
    "sg:city":"Woodland Hills",
    "sg:classifiers":[
        {
            "category":"Building & Trades",
            "subcategory":"Cleaning & Sanitation",
            "type":"Services"
        }
    ],
    "sg:phone":"+1 818 337 0963",
    "sg:postcode":"91303",
    "sg:province":"CA",
    "sg:tags":[
        "carpet"
    ],
    "sg:website":"www.b-acleanteam.com/",
    "wof:name":"B-A Clean Team",
    "wof:placetype":"venue"
},
  "geometry": {"coordinates":[-118.60629400000001,34.190471],"type":"Point"}
}