{
  "type": "Feature",
  "properties": {
    "iso:country":"US",
    "sg:address":"1390 N Mcdowell Blvd",
    "sg:city":"Petaluma",
    "sg:classifiers":[
        {
            "category":"Professional",
            "subcategory":"Business Services",
            "type":"Services"
        }
    ],
    "sg:phone":"+1 707 792 2757",
    "sg:postcode":"94954",
    "sg:province":"CA",
    "sg:tags":[
        "consultant",
        "coach"
    ],
    "sg:website":"http://www.mylesdesign.com",
    "wof:name":"Myles Design",
    "wof:placetype":"venue"
},
  "geometry": {"coordinates":[-122.66896300000001,38.275515],"type":"Point"}
}