{
  "type": "Feature",
  "properties": {
    "addr:full":"4901 Canterbury Dr San Diego CA 92116",
    "addr:housenumber":"4901",
    "addr:postcode":"92116",
    "addr:street":"Canterbury Dr",
    "iso:country":"US",
    "sg:address":"4901 Canterbury Dr",
    "sg:city":"San Diego",
    "sg:classifiers":[
        {
            "category":"Banks & Credit Unions",
            "subcategory":"Financial Services",
            "type":"Services"
        }
    ],
    "sg:phone":"+1 619 283 2910",
    "sg:postcode":"92116",
    "sg:province":"CA",
    "sg:tags":[
        "trust",
        "management"
    ],
    "wof:name":"Colburn Inter Vivos Trust",
    "wof:placetype":"venue"
},
  "geometry": {"coordinates":[-117.109675,32.769657],"type":"Point"}
}