{
  "type": "Feature",
  "properties": {
    "iso:country":"US",
    "sg:address":"100 Avram Ave",
    "sg:city":"Rohnert Park",
    "sg:classifiers":[
        {
            "category":"Social Services",
            "type":"Services"
        }
    ],
    "sg:phone":"+1 707 795 5833",
    "sg:postcode":"94928",
    "sg:province":"CA",
    "sg:tags":[
        "counselor",
        "marriage",
        "family"
    ],
    "wof:name":"June Lewis",
    "wof:placetype":"venue"
},
  "geometry": {"coordinates":[-122.70996,38.342509],"type":"Point"}
}