{
  "type": "Feature",
  "properties": {
    "iso:country":"US",
    "sg:address":"595 Brennan Ave",
    "sg:city":"San Jose",
    "sg:classifiers":[
        {
            "category":"Building & Trades",
            "subcategory":"Construction",
            "type":"Services"
        }
    ],
    "sg:phone":"+1 408 433 0538",
    "sg:postcode":"95131",
    "sg:province":"CA",
    "sg:tags":[
        "contractor"
    ],
    "wof:name":"Orchard Commercial",
    "wof:placetype":"venue"
},
  "geometry": {"coordinates":[-121.915935,37.390604],"type":"Point"}
}