{
  "type": "Feature",
  "properties": {
    "iso:country":"US",
    "sg:address":"825 College Ave",
    "sg:city":"Santa Rosa",
    "sg:classifiers":[
        {
            "category":"Health Services",
            "subcategory":"Health Practitioner",
            "type":"Services"
        }
    ],
    "sg:phone":"+1 707 591 0900",
    "sg:postcode":"95404",
    "sg:province":"CA",
    "sg:tags":[
        "psychologist"
    ],
    "wof:name":"Rachel S Charon PHD",
    "wof:placetype":"venue"
},
  "geometry": {"coordinates":[-122.712576,38.445587],"type":"Point"}
}