{
  "type": "Feature",
  "properties": {
    "addr:full":"2190 Main St Morro Bay CA 93442",
    "addr:housenumber":"2190",
    "addr:postcode":"93442",
    "addr:street":"Main St",
    "iso:country":"US",
    "sg:address":"2190 Main St",
    "sg:city":"Morro Bay",
    "sg:classifiers":[
        {
            "category":"Retail",
            "subcategory":"Auto Repair",
            "type":"Services"
        }
    ],
    "sg:phone":"+1 805 772 2261",
    "sg:postcode":"93442",
    "sg:province":"CA",
    "sg:tags":[
        "muffler",
        "exhaust",
        "system"
    ],
    "wof:name":"Erik's Muffler & Welding",
    "wof:placetype":"venue"
},
  "geometry": {"coordinates":[-120.856807,35.384865],"type":"Point"}
}