{
  "type": "Feature",
  "properties": {
    "addr:full":"10542 Calle Lee Ste 102 Los Alamitos CA 90720",
    "addr:housenumber":"10542",
    "addr:postcode":"90720",
    "addr:street":"Calle Lee Ste 102",
    "iso:country":"US",
    "sg:address":"10542 Calle Lee Ste 102",
    "sg:city":"Los Alamitos",
    "sg:classifiers":[
        {
            "category":"Banks & Credit Unions",
            "subcategory":"Financial Services",
            "type":"Services"
        }
    ],
    "sg:phone":"+1 714 527 8480",
    "sg:postcode":"90720",
    "sg:province":"CA",
    "sg:tags":[
        "broker",
        "mortgage"
    ],
    "wof:name":"Pinnacle Home Loan",
    "wof:placetype":"venue"
},
  "geometry": {"coordinates":[-118.056999,33.8097],"type":"Point"}
}