{
  "type": "Feature",
  "properties": {
    "iso:country":"US",
    "sg:address":"138 Spuraway Dr",
    "sg:city":"San Mateo",
    "sg:classifiers":[
        {
            "category":"Building & Trades",
            "subcategory":"Construction",
            "type":"Services"
        }
    ],
    "sg:phone":"+1 650 627 8683",
    "sg:postcode":"94403",
    "sg:province":"CA",
    "sg:tags":[
        "contractor"
    ],
    "wof:name":"Extreme Pressure Clean",
    "wof:placetype":"venue"
},
  "geometry": {"coordinates":[-122.317743,37.547405],"type":"Point"}
}