{
  "type": "Feature",
  "properties": {
    "addr:full":"114 E 25th Ave Ste E San Mateo CA 94403",
    "addr:housenumber":"114",
    "addr:postcode":"94403",
    "addr:street":"E 25Th Ave Ste E",
    "iso:country":"US",
    "sg:address":"114 E 25th Ave Ste E",
    "sg:city":"San Mateo",
    "sg:classifiers":[
        {
            "category":"Education",
            "subcategory":"Kindergarten",
            "type":"Public Place"
        }
    ],
    "sg:phone":"+1 650 312 1289",
    "sg:postcode":"94403",
    "sg:province":"CA",
    "sg:tags":[
        "school",
        "driving"
    ],
    "wof:name":"Alice Traffic School",
    "wof:placetype":"venue"
},
  "geometry": {"coordinates":[-122.30423500000001,37.545413],"type":"Point"}
}