{
  "type": "Feature",
  "properties": {
    "addr:full":"815 3rd Ave Chula Vista CA 91911",
    "addr:housenumber":"815",
    "addr:postcode":"91911",
    "addr:street":"3Rd Ave",
    "iso:country":"US",
    "sg:address":"815 3rd Ave",
    "sg:city":"Chula Vista",
    "sg:classifiers":[
        {
            "category":"Social Services",
            "subcategory":"Job Training",
            "type":"Services"
        }
    ],
    "sg:phone":"+1 619 425 5898",
    "sg:postcode":"91911",
    "sg:province":"CA",
    "sg:tags":[
        "rehabilitation"
    ],
    "wof:name":"Martin & Assoc",
    "wof:placetype":"venue"
},
  "geometry": {"coordinates":[-117.072377,32.622282],"type":"Point"}
}