{
  "type": "Feature",
  "properties": {
    "iso:country":"US",
    "sg:address":"5531 Silver Lode Dr",
    "sg:city":"Placerville",
    "sg:classifiers":[
        {
            "category":"Building & Trades",
            "subcategory":"Landscaping Services",
            "type":"Services"
        }
    ],
    "sg:phone":"+1 530 644 1089",
    "sg:postcode":"95667",
    "sg:province":"CA",
    "sg:tags":[
        "logging"
    ],
    "wof:name":"TREE Service Unlimited",
    "wof:placetype":"venue"
},
  "geometry": {"coordinates":[-120.86518599999999,38.693617],"type":"Point"}
}