{
  "type": "Feature",
  "properties": {
    "addr:full":"1496 Columbia Ave Riverside CA 92507",
    "addr:housenumber":"1496",
    "addr:postcode":"92507",
    "addr:street":"Columbia Ave",
    "iso:country":"US",
    "sg:address":"1496 Columbia Ave",
    "sg:city":"Riverside",
    "sg:classifiers":[
        {
            "category":"Organizations",
            "subcategory":"Community Association",
            "type":"Services"
        }
    ],
    "sg:phone":"+1 951 779 9024",
    "sg:postcode":"92507",
    "sg:province":"CA",
    "sg:tags":[
        "club"
    ],
    "sg:website":"www.steamonly.org",
    "wof:name":"Riverside Live Steamers Inc",
    "wof:placetype":"venue"
},
  "geometry": {"coordinates":[-117.340035,34.001136],"type":"Point"}
}