{
  "type": "Feature",
  "properties": {
    "addr:full":"246 2nd St San Francisco CA 94105",
    "addr:housenumber":"246",
    "addr:postcode":"94105",
    "addr:street":"2Nd St",
    "iso:country":"US",
    "sg:address":"246 2nd St",
    "sg:city":"San Francisco",
    "sg:classifiers":[
        {
            "category":"Food & Beverages",
            "subcategory":"Liquor & Beverages",
            "type":"Retail Goods"
        }
    ],
    "sg:phone":"+1 415 495 7286",
    "sg:postcode":"94105",
    "sg:province":"CA",
    "sg:tags":[
        "beer",
        "spirit",
        "wine"
    ],
    "wof:name":"Soma Wines & Spirits",
    "wof:placetype":"venue"
},
  "geometry": {"coordinates":[-122.397398,37.785746],"type":"Point"}
}