{
  "type": "Feature",
  "properties": {
    "iso:country":"US",
    "sg:address":"111 E Compton Blvd",
    "sg:city":"Compton",
    "sg:classifiers":[
        {
            "category":"Banks & Credit Unions",
            "subcategory":"Bank",
            "type":"Services"
        }
    ],
    "sg:phone":"+1 310 884 5777",
    "sg:postcode":"90220",
    "sg:province":"CA",
    "wof:name":"Wells Fargo Bank",
    "wof:placetype":"venue"
},
  "geometry": {"coordinates":[-118.275132,33.894998],"type":"Point"}
}