{
  "type": "Feature",
  "properties": {
    "addr:full":"545 E St Williams CA 95987",
    "addr:housenumber":"545",
    "addr:postcode":"95987",
    "addr:street":"E St",
    "iso:country":"US",
    "sg:address":"545 E St",
    "sg:city":"Williams",
    "sg:classifiers":[
        {
            "category":"Food & Beverages",
            "subcategory":"Liquor & Beverages",
            "type":"Retail Goods"
        }
    ],
    "sg:phone":"+1 530 473 3443",
    "sg:postcode":"95987",
    "sg:province":"CA",
    "sg:tags":[
        "store"
    ],
    "wof:name":"Williams Liquor & Foods",
    "wof:placetype":"venue"
},
  "geometry": {"coordinates":[-122.147423,39.155499],"type":"Point"}
}