{
  "type": "Feature",
  "properties": {
    "addr:full":"5745 Redwood Rd Oakland CA 94619",
    "addr:housenumber":"5745",
    "addr:postcode":"94619",
    "addr:street":"Redwood Rd",
    "iso:country":"US",
    "sg:address":"5745 Redwood Rd",
    "sg:city":"Oakland",
    "sg:classifiers":[
        {
            "category":"Sports & Exercise",
            "subcategory":"Stables",
            "type":"Entertainment"
        }
    ],
    "sg:phone":"+1 510 531 0262",
    "sg:postcode":"94619",
    "sg:province":"CA",
    "sg:tags":[
        "riding",
        "horseback"
    ],
    "sg:website":"redwoodranchstables.com/index.html",
    "wof:name":"Redwood Ranch",
    "wof:placetype":"venue"
},
  "geometry": {"coordinates":[-122.170362,37.801484],"type":"Point"}
}