{
  "type": "Feature",
  "properties": {
    "addr:full":"4300 Katella Ave Los Alamitos CA 90720",
    "addr:housenumber":"4300",
    "addr:postcode":"90720",
    "addr:street":"Katella Ave",
    "iso:country":"US",
    "sg:address":"4300 Katella Ave",
    "sg:city":"Los Alamitos",
    "sg:classifiers":[
        {
            "category":"Health Services",
            "subcategory":"Dentist",
            "type":"Services"
        }
    ],
    "sg:phone":"+1 714 826 8300",
    "sg:postcode":"90720",
    "sg:province":"CA",
    "wof:name":"Los Alamitos Dental Grp",
    "wof:placetype":"venue"
},
  "geometry": {"coordinates":[-118.057999,33.802898],"type":"Point"}
}