{
  "type": "Feature",
  "properties": {
    "iso:country":"US",
    "sg:address":"5728 S Santa Fe Ave",
    "sg:city":"Vernon",
    "sg:classifiers":[
        {
            "category":"Bars & Pubs",
            "subcategory":"Dive Bar",
            "type":"Food & Drink"
        }
    ],
    "sg:phone":"+1 323 588 2812",
    "sg:postcode":"90058",
    "sg:province":"CA",
    "wof:name":"Kitty Kat",
    "wof:placetype":"venue"
},
  "geometry": {"coordinates":[-118.229942,33.990334],"type":"Point"}
}