{
  "type": "Feature",
  "properties": {
    "addr:full":"280 S Locust St Pomona CA 91766",
    "addr:housenumber":"280",
    "addr:postcode":"91766",
    "addr:street":"S Locust St",
    "iso:country":"US",
    "sg:address":"280 S Locust St",
    "sg:city":"Pomona",
    "sg:classifiers":[
        {
            "category":"Utilities",
            "subcategory":"Telephone",
            "type":"Services"
        }
    ],
    "sg:phone":"+1 909 469 2550",
    "sg:postcode":"91766",
    "sg:province":"CA",
    "sg:tags":[
        "telecommunication"
    ],
    "wof:name":"Verizon Plus",
    "wof:placetype":"venue"
},
  "geometry": {"coordinates":[-117.74896099999999,34.057524],"type":"Point"}
}