{
  "type": "Feature",
  "properties": {
    "iso:country":"US",
    "sg:address":"459 E Colorado Blvd",
    "sg:city":"Pasadena",
    "sg:classifiers":[
        {
            "category":"Real Estate",
            "subcategory":"Real Estate Agent",
            "type":"Services"
        }
    ],
    "sg:phone":"+1 626 229 0909",
    "sg:postcode":"91106",
    "sg:province":"CA",
    "wof:name":"Sotheby's International Realty",
    "wof:placetype":"venue"
},
  "geometry": {"coordinates":[-118.140354,34.145919],"type":"Point"}
}