{
  "type": "Feature",
  "properties": {
    "addr:full":"5640 Roseville Rd Sacramento CA 95842",
    "addr:housenumber":"5640",
    "addr:postcode":"95842",
    "addr:street":"Roseville Rd",
    "iso:country":"US",
    "sg:address":"5640 Roseville Rd",
    "sg:city":"Sacramento",
    "sg:classifiers":[
        {
            "category":"Autos & Motor Vehicles",
            "subcategory":"Motorcycle Sales",
            "type":"Retail Goods"
        }
    ],
    "sg:phone":"+1 916 338 3710",
    "sg:postcode":"95842",
    "sg:province":"CA",
    "wof:name":"V Dawg Cycles",
    "wof:placetype":"venue"
},
  "geometry": {"coordinates":[-121.372405,38.668628],"type":"Point"}
}