{
  "type": "Feature",
  "properties": {
    "iso:country":"US",
    "sg:address":"1020 E Washington St # 100",
    "sg:city":"Colton",
    "sg:classifiers":[
        {
            "category":"Social Services",
            "subcategory":"Child Care",
            "type":"Services"
        }
    ],
    "sg:phone":"+1 909 783 8952",
    "sg:postcode":"92324",
    "sg:province":"CA",
    "sg:tags":[
        "nursery",
        "day"
    ],
    "sg:website":"http://www.4dcollege.com",
    "wof:name":"Tutor Cots",
    "wof:placetype":"venue"
},
  "geometry": {"coordinates":[-117.311441,34.048199],"type":"Point"}
}