{
  "type": "Feature",
  "properties": {
    "addr:full":"3561 W Century Blvd Inglewood CA 90303",
    "addr:housenumber":"3561",
    "addr:postcode":"90303",
    "addr:street":"W Century Blvd",
    "iso:country":"US",
    "sg:address":"3561 W Century Blvd",
    "sg:city":"Inglewood",
    "sg:classifiers":[
        {
            "category":"Shopping",
            "subcategory":"Mobile Phones",
            "type":"Retail Goods"
        }
    ],
    "sg:phone":"+1 310 330 4633",
    "sg:postcode":"90303",
    "sg:province":"CA",
    "wof:name":"Sprint Pcs Personal Communication Services",
    "wof:placetype":"venue"
},
  "geometry": {"coordinates":[-118.334999,33.945499],"type":"Point"}
}