{
  "type": "Feature",
  "properties": {
    "addr:full":"40169 Hwy 49 Oakhurst CA 93644",
    "addr:housenumber":"40169",
    "addr:postcode":"93644",
    "addr:street":"Hwy 49",
    "iso:country":"US",
    "sg:address":"40169 Hwy 49",
    "sg:city":"Oakhurst",
    "sg:classifiers":[
        {
            "category":"Government",
            "subcategory":"Office",
            "type":"Public Place"
        }
    ],
    "sg:phone":"+1 559 658 7456",
    "sg:postcode":"93644",
    "sg:province":"CA",
    "sg:tags":[
        "county",
        "program",
        "health"
    ],
    "wof:name":"Madera County Public Health",
    "wof:placetype":"venue"
},
  "geometry": {"coordinates":[-119.66389599999999,37.336296],"type":"Point"}
}