{
  "type": "Feature",
  "properties": {
    "addr:full":"4879 Newport Ave San Diego CA 92107",
    "addr:housenumber":"4879",
    "addr:postcode":"92107",
    "addr:street":"Newport Ave",
    "iso:country":"US",
    "sg:address":"4879 Newport Ave",
    "sg:city":"San Diego",
    "sg:classifiers":[
        {
            "category":"Building & Trades",
            "subcategory":"Landscaping Services",
            "type":"Services"
        },
        {
            "category":"Home & Garden",
            "subcategory":"Garden Supply",
            "type":"Retail Goods"
        }
    ],
    "sg:phone":"+1 619 222 5011",
    "sg:postcode":"92107",
    "sg:province":"CA",
    "sg:tags":[
        "nursery",
        "gardening",
        "gardener"
    ],
    "sg:website":"greenladyhydroponics.com/",
    "wof:name":"Green Lady Hydroponics",
    "wof:placetype":"venue"
},
  "geometry": {"coordinates":[-117.249174,32.745321],"type":"Point"}
}