{
  "type": "Feature",
  "properties": {
    "iso:country":"US",
    "sg:address":"2604 Sandlewood Dr",
    "sg:city":"Madera",
    "sg:classifiers":[
        {
            "category":"Professional",
            "subcategory":"Detective & Security Services",
            "type":"Services"
        }
    ],
    "sg:phone":"+1 559 673 6854",
    "sg:postcode":"93637",
    "sg:province":"CA",
    "sg:tags":[
        "investigator"
    ],
    "wof:name":"Ed Mulvihill Investigations",
    "wof:placetype":"venue"
},
  "geometry": {"coordinates":[-120.095248,36.963714],"type":"Point"}
}