{
  "type": "Feature",
  "properties": {
    "iso:country":"US",
    "sg:address":"305 Curie Dr",
    "sg:city":"San Jose",
    "sg:classifiers":[
        {
            "category":"Building & Trades",
            "subcategory":"Plumbing",
            "type":"Services"
        }
    ],
    "sg:phone":"+1 408 629 0200",
    "sg:postcode":"95119",
    "sg:province":"CA",
    "sg:tags":[
        "refrigeration",
        "contractor"
    ],
    "wof:name":"Sierra Environmental Systems",
    "wof:placetype":"venue"
},
  "geometry": {"coordinates":[-121.79527,37.227476],"type":"Point"}
}