{
  "type": "Feature",
  "properties": {
    "addr:full":"1050 Shaw Ave Clovis CA 93612",
    "addr:housenumber":"1050",
    "addr:postcode":"93612",
    "addr:street":"Shaw Ave",
    "iso:country":"US",
    "sg:address":"1050 Shaw Ave",
    "sg:city":"Clovis",
    "sg:classifiers":[
        {
            "category":"Shopping",
            "subcategory":"Clothing, Apparel, & Fashions",
            "type":"Retail Goods"
        }
    ],
    "sg:phone":"+1 559 297 7040",
    "sg:postcode":"93612",
    "sg:province":"CA",
    "sg:tags":[
        "clothing",
        "boys'"
    ],
    "wof:name":"Z Fashion",
    "wof:placetype":"venue"
},
  "geometry": {"coordinates":[-119.695503,36.80846],"type":"Point"}
}