{
  "type": "Feature",
  "properties": {
    "addr:full":"312 Starlane Dr La Canada Flintridge CA 91011",
    "addr:housenumber":"312",
    "addr:postcode":"91011",
    "addr:street":"Starlane Dr",
    "iso:country":"US",
    "sg:address":"312 Starlane Dr",
    "sg:city":"La Canada Flintridge",
    "sg:classifiers":[
        {
            "category":"Professional",
            "type":"Services"
        }
    ],
    "sg:phone":"+1 818 790 7608",
    "sg:postcode":"91011",
    "sg:province":"CA",
    "wof:name":"Cardinal F Coate Co",
    "wof:placetype":"venue"
},
  "geometry": {"coordinates":[-118.177736,34.205074],"type":"Point"}
}