{
  "type": "Feature",
  "properties": {
    "iso:country":"US",
    "sg:address":"419 Main St Ste 200",
    "sg:city":"Placerville",
    "sg:classifiers":[
        {
            "category":"Building & Trades",
            "subcategory":"Construction",
            "type":"Services"
        }
    ],
    "sg:phone":"+1 530 622 7525",
    "sg:postcode":"95667",
    "sg:province":"CA",
    "sg:tags":[
        "asbestos",
        "detection",
        "removal"
    ],
    "wof:name":"National Asbestos Flooring Encasement Systems, Inc.",
    "wof:placetype":"venue"
},
  "geometry": {"coordinates":[-120.80111100000001,38.728963],"type":"Point"}
}