{
  "type": "Feature",
  "properties": {
    "iso:country":"US",
    "sg:address":"5330 Lindley Ave",
    "sg:city":"Encino",
    "sg:classifiers":[
        {
            "category":"Professional",
            "type":"Services"
        }
    ],
    "sg:phone":"+1 818 344 9487",
    "sg:postcode":"91316",
    "sg:province":"CA",
    "wof:name":"Green Ave Inc",
    "wof:placetype":"venue"
},
  "geometry": {"coordinates":[-118.527197,34.169198],"type":"Point"}
}