{
  "type": "Feature",
  "properties": {
    "iso:country":"US",
    "sg:address":"20806 E Rocky Point Ln",
    "sg:city":"Walnut",
    "sg:classifiers":[
        {
            "category":"Banks & Credit Unions",
            "subcategory":"Bank",
            "type":"Services"
        }
    ],
    "sg:phone":"+1 909 468 3000",
    "sg:postcode":"91789",
    "sg:province":"CA",
    "sg:tags":[
        "loan",
        "real estate"
    ],
    "wof:name":"Home Loan Intl",
    "wof:placetype":"venue"
},
  "geometry": {"coordinates":[-117.851251,33.980546],"type":"Point"}
}