{
  "type": "Feature",
  "properties": {
    "addr:full":"3339 W 133rd St Hawthorne CA 90250",
    "addr:housenumber":"3339",
    "addr:postcode":"90250",
    "addr:street":"W 133Rd St",
    "iso:country":"US",
    "sg:address":"3339 W 133rd St",
    "sg:city":"Hawthorne",
    "sg:classifiers":[
        {
            "category":"Autos & Motor Vehicles",
            "subcategory":"Automobile Sales",
            "type":"Retail Goods"
        }
    ],
    "sg:phone":"+1 310 679 9916",
    "sg:postcode":"90250",
    "sg:province":"CA",
    "sg:tags":[
        "dealers-used",
        "car",
        "used",
        "cars-wholesale"
    ],
    "wof:name":"Brand Used Cars",
    "wof:placetype":"venue"
},
  "geometry": {"coordinates":[-118.331412,33.911548],"type":"Point"}
}