{
  "type": "Feature",
  "properties": {
    "iso:country":"US",
    "sg:address":"600 California St",
    "sg:city":"San Francisco",
    "sg:classifiers":[
        {
            "category":"Real Estate",
            "subcategory":"Real Estate Agent",
            "type":"Services"
        }
    ],
    "sg:phone":"+1 415 391 3471",
    "sg:postcode":"94108",
    "sg:province":"CA",
    "sg:tags":[
        "management"
    ],
    "sg:website":"www.tmcrealestate.com",
    "wof:name":"Terwilliger Management Co",
    "wof:placetype":"venue"
},
  "geometry": {"coordinates":[-122.405654,37.792487],"type":"Point"}
}