{
  "type": "Feature",
  "properties": {
    "iso:country":"US",
    "sg:address":"331 2nd St",
    "sg:city":"Grass Valley",
    "sg:classifiers":[
        {
            "category":"Building & Trades",
            "subcategory":"Construction",
            "type":"Services"
        }
    ],
    "sg:phone":"+1 530 477 6835",
    "sg:postcode":"95945",
    "sg:province":"CA",
    "sg:tags":[
        "concrete",
        "contractor"
    ],
    "wof:name":"DCB Concrete",
    "wof:placetype":"venue"
},
  "geometry": {"coordinates":[-121.05684599999999,39.221228],"type":"Point"}
}