{
  "type": "Feature",
  "properties": {
    "addr:full":"505 Montgomery Street Suite 500 San Francisco CA 94111",
    "addr:housenumber":"505",
    "addr:postcode":"94111",
    "addr:street":"Montgomery Street Suite 500",
    "iso:country":"US",
    "sg:address":"505 Montgomery Street Suite 500",
    "sg:city":"San Francisco",
    "sg:classifiers":[
        {
            "category":"Professional",
            "subcategory":"Accounting & Tax Preparation",
            "type":"Services"
        }
    ],
    "sg:phone":"+1 415 397 4444",
    "sg:postcode":"94111",
    "sg:province":"CA",
    "sg:tags":[
        "accountant"
    ],
    "wof:name":"Shea Labagh Dobberstein CPA",
    "wof:placetype":"venue"
},
  "geometry": {"coordinates":[-122.403108,37.793836],"type":"Point"}
}