{
  "type": "Feature",
  "properties": {
    "iso:country":"US",
    "sg:address":"2700 E 7th St",
    "sg:city":"Long Beach",
    "sg:classifiers":[
        {
            "category":"Education",
            "subcategory":"Preschool",
            "type":"Public Place"
        },
        {
            "category":"Education",
            "subcategory":"School",
            "type":"Public Place"
        }
    ],
    "sg:phone":"+1 562 438 5544",
    "sg:postcode":"90804",
    "sg:province":"CA",
    "sg:tags":[
        "high",
        "middle",
        "elementary"
    ],
    "wof:name":"Ohio Head Start Program",
    "wof:placetype":"venue"
},
  "geometry": {"coordinates":[-118.160004,33.7752],"type":"Point"}
}