{
  "type": "Feature",
  "properties": {
    "addr:full":"27545 Via Sereno Carmel CA 93923",
    "addr:housenumber":"27545",
    "addr:postcode":"93923",
    "addr:street":"Via Sereno",
    "iso:country":"US",
    "sg:address":"27545 Via Sereno",
    "sg:city":"Carmel",
    "sg:classifiers":[
        {
            "category":"Building & Trades",
            "subcategory":"Construction",
            "type":"Services"
        }
    ],
    "sg:phone":"+1 831 625 2209",
    "sg:postcode":"93923",
    "sg:province":"CA",
    "sg:tags":[
        "builder",
        "repairer",
        "masonry",
        "chimney",
        "contractor"
    ],
    "wof:name":"A D'Aquanno Custom Masonry",
    "wof:placetype":"venue"
},
  "geometry": {"coordinates":[-121.83551199999999,36.527557],"type":"Point"}
}