{
  "type": "Feature",
  "properties": {
    "iso:country":"US",
    "sg:address":"6610 Nancy Ridge Dr",
    "sg:city":"San Diego",
    "sg:classifiers":[
        {
            "category":"Shopping",
            "type":"Retail Goods"
        }
    ],
    "sg:phone":"+1 858 622 4955",
    "sg:postcode":"92121",
    "sg:province":"CA",
    "sg:tags":[
        "limb",
        "artificial"
    ],
    "wof:name":"DAW Industries Inc",
    "wof:placetype":"venue"
},
  "geometry": {"coordinates":[-117.191411,32.888391],"type":"Point"}
}