{
  "type": "Feature",
  "properties": {
    "iso:country":"US",
    "sg:address":"1011 Eastridge Knoll",
    "sg:city":"Fullerton",
    "sg:classifiers":[
        {
            "category":"Building & Trades",
            "subcategory":"Construction",
            "type":"Services"
        }
    ],
    "sg:phone":"+1 714 449 1073",
    "sg:postcode":"92835",
    "sg:province":"CA",
    "sg:tags":[
        "contractor"
    ],
    "wof:name":"Saputo Construction",
    "wof:placetype":"venue"
},
  "geometry": {"coordinates":[-117.938979,33.881187],"type":"Point"}
}