{
  "type": "Feature",
  "properties": {
    "addr:full":"520 S el Camino Real San Mateo CA 94402",
    "addr:housenumber":"520",
    "addr:postcode":"94402",
    "addr:street":"S El Camino Real",
    "iso:country":"US",
    "sg:address":"520 S el Camino Real",
    "sg:city":"San Mateo",
    "sg:classifiers":[
        {
            "category":"Professional",
            "subcategory":"Lawyer & Legal Services",
            "type":"Services"
        }
    ],
    "sg:phone":"+1 650 342 2500",
    "sg:postcode":"94402",
    "sg:province":"CA",
    "sg:tags":[
        "attorney"
    ],
    "wof:name":"Phillip M Lev Law Office",
    "wof:placetype":"venue"
},
  "geometry": {"coordinates":[-122.324095,37.561271],"type":"Point"}
}