{
  "type": "Feature",
  "properties": {
    "iso:country":"US",
    "sg:address":"2500 Fillmore Street",
    "sg:city":"San Francisco",
    "sg:classifiers":[
        {
            "category":"Food & Beverages",
            "subcategory":"Groceries & Convenience Stores",
            "type":"Retail Goods"
        }
    ],
    "sg:phone":"+1 415 775 1908",
    "sg:postcode":"94115",
    "sg:province":"CA",
    "wof:name":"Gino's Grocery Company",
    "wof:placetype":"venue"
},
  "geometry": {"coordinates":[-122.433998,37.792702],"type":"Point"}
}