{
  "type": "Feature",
  "properties": {
    "iso:country":"US",
    "sg:address":"980 King Plz # 5",
    "sg:city":"Daly City",
    "sg:classifiers":[
        {
            "category":"Health Services",
            "subcategory":"Dentist",
            "type":"Services"
        }
    ],
    "sg:phone":"+1 650 878 1373",
    "sg:postcode":"94015",
    "sg:province":"CA",
    "wof:name":"Bautista Raval Dental Ofc",
    "wof:placetype":"venue"
},
  "geometry": {"coordinates":[-122.469002,37.6506],"type":"Point"}
}