{
  "type": "Feature",
  "properties": {
    "addr:full":"3325 Wilshire Blvd Los Angeles CA 90010",
    "addr:housenumber":"3325",
    "addr:postcode":"90010",
    "addr:street":"Wilshire Blvd",
    "iso:country":"US",
    "sg:address":"3325 Wilshire Blvd",
    "sg:city":"Los Angeles",
    "sg:classifiers":[
        {
            "category":"Wholesale",
            "subcategory":"Groceries",
            "type":"Manufacturing & Wholesale Goods"
        }
    ],
    "sg:phone":"+1 213 427 9161",
    "sg:postcode":"90010",
    "sg:province":"CA",
    "wof:name":"Nature 2 Basics",
    "wof:placetype":"venue"
},
  "geometry": {"coordinates":[-118.29469899999999,34.061852],"type":"Point"}
}