{
  "type": "Feature",
  "properties": {
    "iso:country":"US",
    "sg:address":"784 Enterprise Ct",
    "sg:city":"Atwater",
    "sg:classifiers":[
        {
            "category":"Building & Trades",
            "subcategory":"Construction",
            "type":"Services"
        }
    ],
    "sg:phone":"+1 209 358 7748",
    "sg:postcode":"95301",
    "sg:province":"CA",
    "sg:tags":[
        "contractor"
    ],
    "wof:name":"Baker Custom Construction",
    "wof:placetype":"venue"
},
  "geometry": {"coordinates":[-120.600927,37.33684],"type":"Point"}
}