{
  "type": "Feature",
  "properties": {
    "addr:full":"1834 Westwood Blvd Los Angeles CA 90025",
    "addr:housenumber":"1834",
    "addr:postcode":"90025",
    "addr:street":"Westwood Blvd",
    "iso:country":"US",
    "sg:address":"1834 Westwood Blvd",
    "sg:city":"Los Angeles",
    "sg:classifiers":[
        {
            "category":"Restaurant",
            "type":"Food & Drink"
        }
    ],
    "sg:phone":"+1 310 474 4123",
    "sg:postcode":"90025",
    "sg:province":"CA",
    "wof:name":"Fratelli's New York Pizza",
    "wof:placetype":"venue"
},
  "geometry": {"coordinates":[-118.43573000000001,34.048713],"type":"Point"}
}