{
  "type": "Feature",
  "properties": {
    "iso:country":"US",
    "sg:address":"8860 Exposition Blvd",
    "sg:city":"Culver City",
    "sg:classifiers":[
        {
            "category":"Retail",
            "subcategory":"Repair Shop",
            "type":"Services"
        }
    ],
    "sg:phone":"+1 310 559 4953",
    "sg:postcode":"90232",
    "sg:province":"CA",
    "sg:tags":[
        "refinishing",
        "furniture"
    ],
    "wof:name":"International Interior",
    "wof:placetype":"venue"
},
  "geometry": {"coordinates":[-118.387932,34.028068],"type":"Point"}
}