{
  "type": "Feature",
  "properties": {
    "iso:country":"US",
    "sg:address":"333 20th Pl",
    "sg:city":"Manhattan Beach",
    "sg:classifiers":[
        {
            "category":"Retail",
            "subcategory":"Repair Shop",
            "type":"Services"
        }
    ],
    "sg:phone":"+1 310 546 7951",
    "sg:postcode":"90266",
    "sg:province":"CA",
    "sg:tags":[
        "plumbing",
        "drain",
        "cleaning",
        "sewer"
    ],
    "wof:name":"Southern California Plumbing",
    "wof:placetype":"venue"
},
  "geometry": {"coordinates":[-118.412343,33.891143],"type":"Point"}
}