{
  "type": "Feature",
  "properties": {
    "iso:country":"US",
    "sg:address":"4542 Beach Blvd",
    "sg:city":"Buena Park",
    "sg:classifiers":[
        {
            "category":"Banks & Credit Unions",
            "subcategory":"Bank",
            "type":"Services"
        }
    ],
    "sg:phone":"+1 714 523 5550",
    "sg:postcode":"90621",
    "sg:province":"CA",
    "sg:website":"www.saehanbank.com",
    "wof:name":"Sae Han Bank Fullerton Branch",
    "wof:placetype":"venue"
},
  "geometry": {"coordinates":[-117.987999,33.895302],"type":"Point"}
}