{
  "type": "Feature",
  "properties": {
    "iso:country":"US",
    "sg:address":"5710 Cahalan Ave Ste 9",
    "sg:city":"San Jose",
    "sg:classifiers":[
        {
            "category":"Health Services",
            "subcategory":"Dentist",
            "type":"Services"
        }
    ],
    "sg:phone":"+1 408 224 4155",
    "sg:postcode":"95123",
    "sg:province":"CA",
    "wof:name":"Maye Lazaar, DDS",
    "wof:placetype":"venue"
},
  "geometry": {"coordinates":[-121.846468,37.248133],"type":"Point"}
}