{
  "type": "Feature",
  "properties": {
    "iso:country":"US",
    "sg:address":"951 E Imperial Hwy",
    "sg:city":"La Habra",
    "sg:classifiers":[
        {
            "category":"Restaurant",
            "type":"Food & Drink"
        }
    ],
    "sg:phone":"+1 714 525 3422",
    "sg:postcode":"90631",
    "sg:province":"CA",
    "wof:name":"Nick's Superburgers",
    "wof:placetype":"venue"
},
  "geometry": {"coordinates":[-117.933509,33.917461],"type":"Point"}
}