{
  "type": "Feature",
  "properties": {
    "addr:full":"190 E Forest Ave Coalinga CA 93210",
    "addr:housenumber":"190",
    "addr:postcode":"93210",
    "addr:street":"E Forest Ave",
    "iso:country":"US",
    "sg:address":"190 E Forest Ave",
    "sg:city":"Coalinga",
    "sg:classifiers":[
        {
            "category":"Manufacturing",
            "subcategory":"Tools & Machinery",
            "type":"Manufacturing & Wholesale Goods"
        },
        {
            "category":"Home & Garden",
            "subcategory":"Household Appliances",
            "type":"Retail Goods"
        },
        {
            "category":"Autos & Motor Vehicles",
            "subcategory":"Auto Supplies",
            "type":"Retail Goods"
        },
        {
            "category":"Wholesale",
            "subcategory":"Electrical",
            "type":"Manufacturing & Wholesale Goods"
        }
    ],
    "sg:phone":"+1 559 935 1797",
    "sg:postcode":"93210",
    "sg:province":"CA",
    "sg:tags":[
        "dry",
        "battery",
        "cell",
        "cell-wholesale",
        "batteries-dry",
        "batteries-storage-wholesale",
        "batteries-storage",
        "manufacturer"
    ],
    "sg:website":"http://www.11cbi.com",
    "wof:name":"Coalinga Batteries Inc",
    "wof:placetype":"venue"
},
  "geometry": {"coordinates":[-120.35830300000001,36.14006],"type":"Point"}
}