{
  "type": "Feature",
  "properties": {
    "addr:full":"22231 Mulholland Hwy Ste 113 Calabasas CA 91302",
    "addr:housenumber":"22231",
    "addr:postcode":"91302",
    "addr:street":"Mulholland Hwy Ste 113",
    "iso:country":"US",
    "sg:address":"22231 Mulholland Hwy Ste 113",
    "sg:city":"Calabasas",
    "sg:classifiers":[
        {
            "category":"Real Estate",
            "subcategory":"Architect",
            "type":"Services"
        }
    ],
    "sg:phone":"+1 818 591 7172",
    "sg:postcode":"91302",
    "sg:province":"CA",
    "wof:name":"Gepner Cary W & Associates",
    "wof:placetype":"venue"
},
  "geometry": {"coordinates":[-118.61199999999999,34.1478],"type":"Point"}
}