{
  "type": "Feature",
  "properties": {
    "addr:full":"101 N Brand Blvd Ste 1000 Glendale CA 91203",
    "addr:housenumber":"101",
    "addr:postcode":"91203",
    "addr:street":"N Brand Blvd Ste 1000",
    "iso:country":"US",
    "sg:address":"101 N Brand Blvd Ste 1000",
    "sg:city":"Glendale",
    "sg:classifiers":[
        {
            "category":"Shopping",
            "subcategory":"Hobbies, Toys, & Games",
            "type":"Retail Goods"
        }
    ],
    "sg:phone":"+1 703 418 0311",
    "sg:postcode":"91203",
    "sg:province":"CA",
    "sg:tags":[
        "toy",
        "store"
    ],
    "wof:name":"Disney Store",
    "wof:placetype":"venue"
},
  "geometry": {"coordinates":[-118.255456,34.146864],"type":"Point"}
}