{
  "type": "Feature",
  "properties": {
    "addr:full":"2144 Fern St San Diego CA 92104",
    "addr:housenumber":"2144",
    "addr:postcode":"92104",
    "addr:street":"Fern St",
    "iso:country":"US",
    "sg:address":"2144 Fern St",
    "sg:city":"San Diego",
    "sg:classifiers":[
        {
            "category":"Shopping",
            "subcategory":"Florist",
            "type":"Retail Goods"
        }
    ],
    "sg:phone":"+1 619 851 7275",
    "sg:postcode":"92104",
    "sg:province":"CA",
    "wof:name":"Flora 44",
    "wof:placetype":"venue"
},
  "geometry": {"coordinates":[-117.12966900000001,32.727581],"type":"Point"}
}