{
  "type": "Feature",
  "properties": {
    "addr:full":"5438 W Cypress Ave Visalia CA 93277",
    "addr:housenumber":"5438",
    "addr:postcode":"93277",
    "addr:street":"W Cypress Ave",
    "iso:country":"US",
    "sg:address":"5438 W Cypress Ave",
    "sg:city":"Visalia",
    "sg:classifiers":[
        {
            "category":"Travel",
            "subcategory":"Hotels & Motels",
            "type":"Entertainment"
        },
        {
            "category":"Retail",
            "subcategory":"Event Space",
            "type":"Services"
        }
    ],
    "sg:phone":"+1 559 739 9800",
    "sg:postcode":"93277",
    "sg:province":"CA",
    "sg:tags":[
        "facility",
        "hall",
        "planning",
        "reception",
        "lodging",
        "meeting",
        "banquet"
    ],
    "sg:website":"http://6006.lq.com",
    "wof:name":"La Quinta Inn & Suites",
    "wof:placetype":"venue"
},
  "geometry": {"coordinates":[-119.350889,36.324565],"type":"Point"}
}