{
  "type": "Feature",
  "properties": {
    "addr:full":"2029 E Pontiac Way Fresno CA 93726",
    "addr:housenumber":"2029",
    "addr:postcode":"93726",
    "addr:street":"E Pontiac Way",
    "iso:country":"US",
    "sg:address":"2029 E Pontiac Way",
    "sg:city":"Fresno",
    "sg:classifiers":[
        {
            "category":"Building & Trades",
            "subcategory":"Landscaping Services",
            "type":"Services"
        }
    ],
    "sg:phone":"+1 559 225 5658",
    "sg:postcode":"93726",
    "sg:province":"CA",
    "wof:name":"Bens Gardening",
    "wof:placetype":"venue"
},
  "geometry": {"coordinates":[-119.787238,36.789608],"type":"Point"}
}