{
  "type": "Feature",
  "properties": {
    "addr:full":"736 Inland Center Dr San Bernardino CA 92408",
    "addr:housenumber":"736",
    "addr:postcode":"92408",
    "addr:street":"Inland Center Dr",
    "iso:country":"US",
    "sg:address":"736 Inland Center Dr",
    "sg:city":"San Bernardino",
    "sg:classifiers":[
        {
            "category":"Home & Garden",
            "subcategory":"Furniture",
            "type":"Retail Goods"
        }
    ],
    "sg:phone":"+1 909 884 1281",
    "sg:postcode":"92408",
    "sg:province":"CA",
    "wof:name":"Levitz Furniture",
    "wof:placetype":"venue"
},
  "geometry": {"coordinates":[-117.298129,34.08826],"type":"Point"}
}