{
  "type": "Feature",
  "properties": {
    "addr:full":"2982 Montevideo Dr San Ramon CA 94583",
    "addr:housenumber":"2982",
    "addr:postcode":"94583",
    "addr:street":"Montevideo Dr",
    "iso:country":"US",
    "sg:address":"2982 Montevideo Dr",
    "sg:city":"San Ramon",
    "sg:classifiers":[
        {
            "category":"Social Services",
            "type":"Services"
        }
    ],
    "sg:phone":"+1 925 828 9264",
    "sg:postcode":"94583",
    "sg:province":"CA",
    "sg:tags":[
        "youth",
        "organization",
        "center"
    ],
    "wof:name":"San Ramon Little League",
    "wof:placetype":"venue"
},
  "geometry": {"coordinates":[-121.95586299999999,37.748333],"type":"Point"}
}