{
  "type": "Feature",
  "properties": {
    "addr:full":"6914 Brockton Ave Riverside CA 92506",
    "addr:housenumber":"6914",
    "addr:postcode":"92506",
    "addr:street":"Brockton Ave",
    "iso:country":"US",
    "sg:address":"6914 Brockton Ave",
    "sg:city":"Riverside",
    "sg:classifiers":[
        {
            "category":"Health Services",
            "subcategory":"Chiropractor",
            "type":"Services"
        }
    ],
    "sg:phone":"+1 951 276 0611",
    "sg:postcode":"92506",
    "sg:province":"CA",
    "wof:name":"Trans Pacific Chiropractic",
    "wof:placetype":"venue"
},
  "geometry": {"coordinates":[-117.396686,33.947649],"type":"Point"}
}