{
  "type": "Feature",
  "properties": {
    "iso:country":"US",
    "sg:address":"9180 Whittier Blvd",
    "sg:city":"Pico Rivera",
    "sg:classifiers":[
        {
            "category":"Professional",
            "subcategory":"Accounting & Tax Preparation",
            "type":"Services"
        },
        {
            "category":"Restaurant",
            "type":"Food & Drink"
        }
    ],
    "sg:phone":"+1 562 949 6300",
    "sg:postcode":"90660",
    "sg:province":"CA",
    "sg:tags":[
        "accountant"
    ],
    "wof:name":"Taco Bell No 3670",
    "wof:placetype":"venue"
},
  "geometry": {"coordinates":[-118.081001,34.000099],"type":"Point"}
}