{
  "type": "Feature",
  "properties": {
    "iso:country":"US",
    "sg:address":"13911 Perris Blvd",
    "sg:city":"Moreno Valley",
    "sg:classifiers":[
        {
            "category":"Education",
            "subcategory":"College",
            "type":"Public Place"
        }
    ],
    "sg:phone":"+1 951 485 5667",
    "sg:postcode":"92553",
    "sg:province":"CA",
    "wof:name":"Bus Transportation Dept",
    "wof:placetype":"venue"
},
  "geometry": {"coordinates":[-117.22641,33.917963],"type":"Point"}
}