{
  "type": "Feature",
  "properties": {
    "iso:country":"US",
    "sg:address":"34050 Westchester Ter",
    "sg:city":"Fremont",
    "sg:classifiers":[
        {
            "category":"Real Estate",
            "subcategory":"Real Estate Operator",
            "type":"Services"
        }
    ],
    "sg:phone":"+1 510 794 9981",
    "sg:postcode":"94555",
    "sg:province":"CA",
    "sg:tags":[
        "apartment"
    ],
    "wof:name":"Amber Court",
    "wof:placetype":"venue"
},
  "geometry": {"coordinates":[-122.043189,37.576888],"type":"Point"}
}