{
  "type": "Feature",
  "properties": {
    "addr:full":"2141 Shaw Ave Ste 113 Clovis CA 93611",
    "addr:housenumber":"2141",
    "addr:postcode":"93611",
    "addr:street":"Shaw Ave Ste 113",
    "iso:country":"US",
    "sg:address":"2141 Shaw Ave Ste 113",
    "sg:city":"Clovis",
    "sg:classifiers":[
        {
            "category":"Restaurant",
            "type":"Food & Drink"
        }
    ],
    "sg:phone":"+1 559 297 8310",
    "sg:postcode":"93611",
    "sg:province":"CA",
    "sg:tags":[
        "italian",
        "pizza"
    ],
    "wof:name":"Florentina's Pizza & Pasta",
    "wof:placetype":"venue"
},
  "geometry": {"coordinates":[-119.675016,36.808644],"type":"Point"}
}