{
  "type": "Feature",
  "properties": {
    "addr:full":"4494 N Jackson Ave Fresno CA 93726",
    "addr:housenumber":"4494",
    "addr:postcode":"93726",
    "addr:street":"N Jackson Ave",
    "iso:country":"US",
    "sg:address":"4494 N Jackson Ave",
    "sg:city":"Fresno",
    "sg:classifiers":[
        {
            "category":"Professional",
            "subcategory":"Accounting & Tax Preparation",
            "type":"Services"
        }
    ],
    "sg:phone":"+1 559 224 2345",
    "sg:postcode":"93726",
    "sg:province":"CA",
    "sg:tags":[
        "bookkeeping",
        "billing"
    ],
    "wof:name":"Titus Billing Service",
    "wof:placetype":"venue"
},
  "geometry": {"coordinates":[-119.747975,36.799239],"type":"Point"}
}