{
  "type": "Feature",
  "properties": {
    "iso:country":"US",
    "sg:address":"16654 Daisy Ave",
    "sg:city":"Fountain Valley",
    "sg:classifiers":[
        {
            "category":"Banks & Credit Unions",
            "subcategory":"Investment Brokerage",
            "type":"Services"
        }
    ],
    "sg:phone":"+1 714 842 5285",
    "sg:postcode":"92708",
    "sg:province":"CA",
    "sg:tags":[
        "tax"
    ],
    "wof:name":"Gucci One Financial Services",
    "wof:placetype":"venue"
},
  "geometry": {"coordinates":[-117.97030599999999,33.721459],"type":"Point"}
}