{
  "type": "Feature",
  "properties": {
    "addr:full":"15725 Lakewood Blvd Paramount CA 90723",
    "addr:housenumber":"15725",
    "addr:postcode":"90723",
    "addr:street":"Lakewood Blvd",
    "iso:country":"US",
    "sg:address":"15725 Lakewood Blvd",
    "sg:city":"Paramount",
    "sg:classifiers":[
        {
            "category":"Autos & Motor Vehicles",
            "subcategory":"Motorcycle Sales",
            "type":"Retail Goods"
        }
    ],
    "sg:phone":"+1 562 531 1225",
    "sg:postcode":"90723",
    "sg:province":"CA",
    "sg:tags":[
        "scooter"
    ],
    "sg:website":"midcitieshonda.com/",
    "wof:name":"Mid-Cities Honda-Kawasaki-Sea Doo",
    "wof:placetype":"venue"
},
  "geometry": {"coordinates":[-118.143141,33.89072],"type":"Point"}
}