{
  "type": "Feature",
  "properties": {
    "addr:full":"526 S Sunrise Way Palm Springs CA 92264",
    "addr:housenumber":"526",
    "addr:postcode":"92264",
    "addr:street":"S Sunrise Way",
    "iso:country":"US",
    "sg:address":"526 S Sunrise Way",
    "sg:city":"Palm Springs",
    "sg:classifiers":[
        {
            "category":"Shopping",
            "subcategory":"Used Merchandise",
            "type":"Retail Goods"
        }
    ],
    "sg:phone":"+1 760 322 9071",
    "sg:postcode":"92264",
    "sg:province":"CA",
    "wof:name":"Palm Strings Music",
    "wof:placetype":"venue"
},
  "geometry": {"coordinates":[-116.52815200000001,33.815412],"type":"Point"}
}