{
  "type": "Feature",
  "properties": {
    "addr:full":"2541 5th Ave Oroville CA 95965",
    "addr:housenumber":"2541",
    "addr:postcode":"95965",
    "addr:street":"5Th Ave",
    "iso:country":"US",
    "sg:address":"2541 5th Ave",
    "sg:city":"Oroville",
    "sg:classifiers":[
        {
            "category":"Manufacturing",
            "subcategory":"Toys & Sporting Goods",
            "type":"Manufacturing & Wholesale Goods"
        }
    ],
    "sg:phone":"+1 530 533 8692",
    "sg:postcode":"95965",
    "sg:province":"CA",
    "sg:tags":[
        "athletic"
    ],
    "wof:name":"Cardoza Creations",
    "wof:placetype":"venue"
},
  "geometry": {"coordinates":[-121.565431,39.498341],"type":"Point"}
}