{
  "type": "Feature",
  "properties": {
    "addr:full":"1235 Wildwood Ave Sunnyvale CA 94089",
    "addr:housenumber":"1235",
    "addr:postcode":"94089",
    "addr:street":"Wildwood Ave",
    "iso:country":"US",
    "sg:address":"1235 Wildwood Ave",
    "sg:city":"Sunnyvale",
    "sg:classifiers":[
        {
            "category":"Building & Trades",
            "subcategory":"Plumbing",
            "type":"Services"
        }
    ],
    "sg:phone":"+1 408 738 4663",
    "sg:postcode":"94089",
    "sg:province":"CA",
    "sg:tags":[
        "plumbing",
        "contractor"
    ],
    "wof:name":"Pacesetter Plumbing & Heating",
    "wof:placetype":"venue"
},
  "geometry": {"coordinates":[-121.992552,37.390491],"type":"Point"}
}