{
  "type": "Feature",
  "properties": {
    "addr:full":"14263 E 14th St San Leandro CA 94578",
    "addr:housenumber":"14263",
    "addr:postcode":"94578",
    "addr:street":"E 14Th St",
    "iso:country":"US",
    "sg:address":"14263 E 14th St",
    "sg:city":"San Leandro",
    "sg:classifiers":[
        {
            "category":"Autos & Motor Vehicles",
            "subcategory":"Automobile Sales",
            "type":"Retail Goods"
        }
    ],
    "sg:phone":"+1 510 352 8680",
    "sg:postcode":"94578",
    "sg:province":"CA",
    "sg:tags":[
        "car"
    ],
    "sg:website":"www.carstoreus.com",
    "wof:name":"The Car Store",
    "wof:placetype":"venue"
},
  "geometry": {"coordinates":[-122.138583,37.711758],"type":"Point"}
}