{
  "type": "Feature",
  "properties": {
    "addr:full":"3250 Rippey Rd Loomis CA 95650",
    "addr:housenumber":"3250",
    "addr:postcode":"95650",
    "addr:street":"Rippey Rd",
    "iso:country":"US",
    "sg:address":"3250 Rippey Rd",
    "sg:city":"Loomis",
    "sg:classifiers":[
        {
            "category":"Wholesale",
            "subcategory":"Machinery & Supplies",
            "type":"Manufacturing & Wholesale Goods"
        }
    ],
    "sg:phone":"+1 916 652 6768",
    "sg:postcode":"95650",
    "sg:province":"CA",
    "sg:tags":[
        "dry wall",
        "contractor"
    ],
    "wof:name":"LOOMIS Drywall Supply",
    "wof:placetype":"venue"
},
  "geometry": {"coordinates":[-121.16982299999999,38.851311],"type":"Point"}
}