{
  "type": "Feature",
  "properties": {
    "addr:full":"1880 Logan Ave San Diego CA 92113",
    "addr:housenumber":"1880",
    "addr:postcode":"92113",
    "addr:street":"Logan Ave",
    "iso:country":"US",
    "sg:address":"1880 Logan Ave",
    "sg:city":"San Diego",
    "sg:classifiers":[
        {
            "category":"Social Services",
            "type":"Services"
        }
    ],
    "sg:phone":"+1 619 235 1148",
    "sg:postcode":"92113",
    "sg:province":"CA",
    "sg:tags":[
        "senior",
        "citizen"
    ],
    "wof:name":"Paradise Senior Ctr",
    "wof:placetype":"venue"
},
  "geometry": {"coordinates":[-117.145608,32.702478],"type":"Point"}
}