{
  "type": "Feature",
  "properties": {
    "iso:country":"US",
    "sg:address":"55 Navajo Ave",
    "sg:city":"San Francisco",
    "sg:classifiers":[
        {
            "category":"Professional",
            "subcategory":"Accounting & Tax Preparation",
            "type":"Services"
        },
        {
            "category":"Banks & Credit Unions",
            "subcategory":"Financial Services",
            "type":"Services"
        }
    ],
    "sg:phone":"+1 415 846 0873",
    "sg:postcode":"94112",
    "sg:province":"CA",
    "sg:tags":[
        "accountant"
    ],
    "sg:website":"sftaxprep.com",
    "wof:name":"Peter Hue",
    "wof:placetype":"venue"
},
  "geometry": {"coordinates":[-122.44416200000001,37.719981],"type":"Point"}
}