{
  "type": "Feature",
  "properties": {
    "iso:country":"US",
    "sg:address":"805 W Ave J",
    "sg:city":"Lancaster",
    "sg:classifiers":[
        {
            "category":"Organizations",
            "subcategory":"Non-profit Organization",
            "type":"Services"
        }
    ],
    "sg:phone":"+1 661 945 9421",
    "sg:postcode":"93534",
    "sg:province":"CA",
    "sg:tags":[
        "information",
        "alcoholism",
        "treatment"
    ],
    "wof:name":"Alcohol Drug Abuse Ctr",
    "wof:placetype":"venue"
},
  "geometry": {"coordinates":[-118.143392,34.689445],"type":"Point"}
}