{
  "type": "Feature",
  "properties": {
    "addr:full":"805 W Ave J Lancaster CA 93534",
    "addr:housenumber":"805",
    "addr:postcode":"93534",
    "addr:street":"W Ave J",
    "iso:country":"US",
    "sg:address":"805 W Ave J",
    "sg:city":"Lancaster",
    "sg:classifiers":[
        {
            "category":"Organizations",
            "subcategory":"Non-profit Organization",
            "type":"Services"
        }
    ],
    "sg:phone":"+1 661 945 9421",
    "sg:postcode":"93534",
    "sg:province":"CA",
    "sg:tags":[
        "information",
        "alcoholism",
        "treatment"
    ],
    "wof:name":"Alcohol Drug Abuse Ctr",
    "wof:placetype":"venue"
},
  "geometry": {"coordinates":[-118.14339200000001,34.689445],"type":"Point"}
}