{
  "type": "Feature",
  "properties": {
    "addr:full":"1410 E 7th St Ontario CA 91764",
    "addr:housenumber":"1410",
    "addr:postcode":"91764",
    "addr:street":"E 7Th St",
    "iso:country":"US",
    "sg:address":"1410 E 7th St",
    "sg:city":"Ontario",
    "sg:classifiers":[
        {
            "category":"Home & Garden",
            "subcategory":"Furniture",
            "type":"Retail Goods"
        }
    ],
    "sg:phone":"+1 909 579 0002",
    "sg:postcode":"91764",
    "sg:province":"CA",
    "wof:name":"Times Furniture Inc",
    "wof:placetype":"venue"
},
  "geometry": {"coordinates":[-117.624836,34.088463],"type":"Point"}
}