{
  "type": "Feature",
  "properties": {
    "addr:full":"12712 W Bradbury Rd Turlock CA 95380",
    "addr:housenumber":"12712",
    "addr:postcode":"95380",
    "addr:street":"W Bradbury Rd",
    "iso:country":"US",
    "sg:address":"12712 W Bradbury Rd",
    "sg:city":"Turlock",
    "sg:classifiers":[
        {
            "category":"Real Estate",
            "subcategory":"Real Estate Operator",
            "type":"Services"
        }
    ],
    "sg:phone":"+1 209 634 7060",
    "sg:postcode":"95380",
    "sg:province":"CA",
    "sg:tags":[
        "property",
        "lessor"
    ],
    "wof:name":"Alan Sanders",
    "wof:placetype":"venue"
},
  "geometry": {"coordinates":[-120.990182,37.449291],"type":"Point"}
}