{
  "type": "Feature",
  "properties": {
    "iso:country":"US",
    "sg:address":"11224 Russian River Ct",
    "sg:city":"Rancho Cordova",
    "sg:classifiers":[
        {
            "category":"Professional",
            "type":"Services"
        }
    ],
    "sg:phone":"+1 916 631 7316",
    "sg:postcode":"95670",
    "sg:province":"CA",
    "wof:name":"Ruby & Pearl",
    "wof:placetype":"venue"
},
  "geometry": {"coordinates":[-121.26714,38.626845],"type":"Point"}
}