{
  "type": "Feature",
  "properties": {
    "iso:country":"US",
    "sg:address":"2241 Saint Pauls Way",
    "sg:city":"Modesto",
    "sg:classifiers":[
        {
            "category":"Health Services",
            "subcategory":"Doctor",
            "type":"Services"
        }
    ],
    "sg:phone":"+1 209 524 9950",
    "sg:postcode":"95355",
    "sg:province":"CA",
    "sg:tags":[
        "dentist"
    ],
    "wof:name":"Gregory E Shinkwin DDS",
    "wof:placetype":"venue"
},
  "geometry": {"coordinates":[-120.953716,37.665493],"type":"Point"}
}