{
  "type": "Feature",
  "properties": {
    "iso:country":"US",
    "sg:address":"1710 S Pacific Coast Hwy",
    "sg:city":"Redondo Beach",
    "sg:classifiers":[
        {
            "category":"Education",
            "subcategory":"Music School",
            "type":"Public Place"
        }
    ],
    "sg:phone":"+1 310 374 9765",
    "sg:postcode":"90277",
    "sg:province":"CA",
    "sg:tags":[
        "instrument",
        "teacher",
        "musical"
    ],
    "wof:name":"Rhythm & Notes",
    "wof:placetype":"venue"
},
  "geometry": {"coordinates":[-118.381825,33.817697],"type":"Point"}
}