{
  "type": "Feature",
  "properties": {
    "addr:full":"7201 Painter Ave Whittier CA 90602",
    "addr:housenumber":"7201",
    "addr:postcode":"90602",
    "addr:street":"Painter Ave",
    "iso:country":"US",
    "sg:address":"7201 Painter Ave",
    "sg:city":"Whittier",
    "sg:classifiers":[
        {
            "category":"Health Services",
            "subcategory":"Doctor",
            "type":"Services"
        }
    ],
    "sg:phone":"+1 562 698 7925",
    "sg:postcode":"90602",
    "sg:province":"CA",
    "sg:tags":[
        "dentist"
    ],
    "wof:name":"Alvin C Loo DDS",
    "wof:placetype":"venue"
},
  "geometry": {"coordinates":[-118.03265500000001,33.976324],"type":"Point"}
}