{
  "type": "Feature",
  "properties": {
    "iso:country":"US",
    "sg:address":"180 Grand Ave Suite 1500",
    "sg:city":"Oakland",
    "sg:classifiers":[
        {
            "category":"Professional",
            "subcategory":"Lawyer & Legal Services",
            "type":"Services"
        }
    ],
    "sg:phone":"+1 510 628 0056",
    "sg:postcode":"94612",
    "sg:province":"CA",
    "sg:tags":[
        "litigation",
        "attorney",
        "tort"
    ],
    "wof:name":"Korshak, Kracoff, Kong & Sugano, L.L.P.",
    "wof:placetype":"venue"
},
  "geometry": {"coordinates":[-122.263035,37.811003],"type":"Point"}
}