{
  "type": "Feature",
  "properties": {
    "addr:full":"17836 Gillette Ave Irvine CA 92614",
    "addr:postcode":"17836;92614",
    "addr:street":"Gillette Ave",
    "iso:country":"US",
    "sg:address":"17836 Gillette Ave",
    "sg:city":"Irvine",
    "sg:classifiers":[
        {
            "category":"Utilities",
            "type":"Services"
        }
    ],
    "sg:phone":"+1 949 450 1122",
    "sg:postcode":"92614",
    "sg:province":"CA",
    "sg:tags":[
        "provider",
        "internet"
    ],
    "wof:name":"Netscope Inc",
    "wof:placetype":"venue"
},
  "geometry": {"coordinates":[-117.847495,33.687862],"type":"Point"}
}