{
  "type": "Feature",
  "properties": {
    "addr:full":"2050 Coronado Ave San Diego CA 92154",
    "addr:housenumber":"2050",
    "addr:postcode":"92154",
    "addr:street":"Coronado Ave",
    "iso:country":"US",
    "sg:address":"2050 Coronado Ave",
    "sg:city":"San Diego",
    "sg:classifiers":[
        {
            "category":"Education",
            "subcategory":"School",
            "type":"Public Place"
        }
    ],
    "sg:phone":"+1 619 424 0100",
    "sg:postcode":"92154",
    "sg:province":"CA",
    "sg:tags":[
        "high",
        "middle",
        "elementary"
    ],
    "wof:name":"Mendoza Elementary School",
    "wof:placetype":"venue"
},
  "geometry": {"coordinates":[-117.089996,32.576401],"type":"Point"}
}