{
  "type": "Feature",
  "properties": {
    "iso:country":"US",
    "sg:address":"2000 Carleton St",
    "sg:city":"Berkeley",
    "sg:classifiers":[
        {
            "category":"Education",
            "subcategory":"University",
            "type":"Public Place"
        }
    ],
    "sg:phone":"+1 510 643 5028",
    "sg:postcode":"94720",
    "sg:province":"CA",
    "sg:tags":[
        "college"
    ],
    "wof:name":"University of California Berkeley",
    "wof:placetype":"venue"
},
  "geometry": {"coordinates":[-122.269497,37.860794],"type":"Point"}
}