{
  "type": "Feature",
  "properties": {
    "iso:country":"US",
    "sg:address":"1990 Concord Ave",
    "sg:city":"Concord",
    "sg:classifiers":[
        {
            "category":"Professional",
            "type":"Services"
        }
    ],
    "sg:phone":"+1 925 688 6001",
    "sg:postcode":"94520",
    "sg:province":"CA",
    "sg:tags":[
        "establishment"
    ],
    "wof:name":"New Front Room",
    "wof:placetype":"venue"
},
  "geometry": {"coordinates":[-122.036101,37.976848],"type":"Point"}
}