{
  "type": "Feature",
  "properties": {
    "iso:country":"US",
    "sg:address":"19100 Von Karman Ave",
    "sg:city":"Irvine",
    "sg:classifiers":[
        {
            "category":"Banks & Credit Unions",
            "subcategory":"Bank",
            "type":"Services"
        }
    ],
    "sg:phone":"+1 949 251 9700",
    "sg:postcode":"92612",
    "sg:province":"CA",
    "sg:tags":[
        "loan",
        "real estate"
    ],
    "wof:name":"Benjamin Franklin Financial",
    "wof:placetype":"venue"
},
  "geometry": {"coordinates":[-117.858494,33.670616],"type":"Point"}
}