{
  "type": "Feature",
  "properties": {
    "addr:full":"310 E San Bernardino Rd Covina CA 91723",
    "addr:housenumber":"310",
    "addr:postcode":"91723",
    "addr:street":"E San Bernardino Rd",
    "iso:country":"US",
    "sg:address":"310 E San Bernardino Rd",
    "sg:city":"Covina",
    "sg:classifiers":[
        {
            "category":"Personal",
            "subcategory":"Beauty Salon",
            "type":"Services"
        }
    ],
    "sg:phone":"+1 626 967 0805",
    "sg:postcode":"91723",
    "sg:province":"CA",
    "wof:name":"Le Visage",
    "wof:placetype":"venue"
},
  "geometry": {"coordinates":[-117.885508,34.090503],"type":"Point"}
}