{
  "type": "Feature",
  "properties": {
    "addr:full":"1928 183rd St Torrance CA 90504",
    "addr:housenumber":"1928",
    "addr:postcode":"90504",
    "addr:street":"183Rd St",
    "iso:country":"US",
    "sg:address":"1928 183rd St",
    "sg:city":"Torrance",
    "sg:classifiers":[
        {
            "category":"Food & Beverages",
            "subcategory":"Specialty",
            "type":"Retail Goods"
        }
    ],
    "sg:phone":"+1 310 532 5273",
    "sg:postcode":"90504",
    "sg:province":"CA",
    "sg:tags":[
        "health",
        "diet"
    ],
    "wof:name":"Herbalife Distributor",
    "wof:placetype":"venue"
},
  "geometry": {"coordinates":[-118.312915,33.864774],"type":"Point"}
}