{
  "type": "Feature",
  "properties": {
    "iso:country":"US",
    "sg:address":"24589 Lola Ln",
    "sg:city":"Newhall",
    "sg:classifiers":[
        {
            "category":"Banks & Credit Unions",
            "subcategory":"Investment Brokerage",
            "type":"Services"
        }
    ],
    "sg:phone":"+1 818 906 3353",
    "sg:postcode":"91321",
    "sg:province":"CA",
    "sg:tags":[
        "advisory",
        "financial"
    ],
    "wof:name":"Premier Financial Search",
    "wof:placetype":"venue"
},
  "geometry": {"coordinates":[-118.537111,34.37786],"type":"Point"}
}