{
  "type": "Feature",
  "properties": {
    "iso:country":"US",
    "sg:address":"3350 Coach Ln",
    "sg:city":"Cameron Park",
    "sg:classifiers":[
        {
            "category":"Shopping",
            "subcategory":"Clothing, Apparel, & Fashions",
            "type":"Retail Goods"
        }
    ],
    "sg:phone":"+1 530 676 3632",
    "sg:postcode":"95682",
    "sg:province":"CA",
    "sg:tags":[
        "infant",
        "wear"
    ],
    "wof:name":"All My Children",
    "wof:placetype":"venue"
},
  "geometry": {"coordinates":[-120.970851,38.658074],"type":"Point"}
}