{
  "type": "Feature",
  "properties": {
    "addr:full":"18502 Beach Boulevard Huntington Beach CA 92648",
    "addr:housenumber":"18502",
    "addr:postcode":"92648",
    "addr:street":"Beach Boulevard",
    "iso:country":"US",
    "sg:address":"18502 Beach Boulevard",
    "sg:city":"Huntington Beach",
    "sg:classifiers":[
        {
            "category":"Autos & Motor Vehicles",
            "subcategory":"Fuel & Gas Station",
            "type":"Retail Goods"
        }
    ],
    "sg:phone":"+1 714 964 1751",
    "sg:postcode":"92648",
    "sg:province":"CA",
    "wof:name":"Five Point",
    "wof:placetype":"venue"
},
  "geometry": {"coordinates":[-117.98877299999999,33.693903],"type":"Point"}
}