{
  "type": "Feature",
  "properties": {
    "addr:full":"5325 Telegraph Ave Oakland CA 94609",
    "addr:housenumber":"5325",
    "addr:postcode":"94609",
    "addr:street":"Telegraph Ave",
    "iso:country":"US",
    "sg:address":"5325 Telegraph Ave",
    "sg:city":"Oakland",
    "sg:classifiers":[
        {
            "category":"Transit Center",
            "subcategory":"Freight",
            "type":"Transportation"
        }
    ],
    "sg:phone":"+1 510 655 1357",
    "sg:postcode":"94609",
    "sg:province":"CA",
    "sg:tags":[
        "trucking-heavy",
        "hauling"
    ],
    "wof:name":"Brown's Hauling",
    "wof:placetype":"venue"
},
  "geometry": {"coordinates":[-122.262083,37.838907],"type":"Point"}
}