{
  "type": "Feature",
  "properties": {
    "addr:full":"1251 S Main St Walnut Creek CA 94595",
    "addr:housenumber":"1251",
    "addr:postcode":"94595",
    "addr:street":"S Main St",
    "iso:country":"US",
    "sg:address":"1251 S Main St",
    "sg:city":"Walnut Creek",
    "sg:classifiers":[
        {
            "category":"Shopping",
            "subcategory":"Clothing, Apparel, & Fashions",
            "type":"Retail Goods"
        }
    ],
    "sg:phone":"+1 925 934 9923",
    "sg:postcode":"94595",
    "sg:province":"CA",
    "wof:name":"Ann Taylor Loft",
    "wof:placetype":"venue"
},
  "geometry": {"coordinates":[-122.059999,37.89608],"type":"Point"}
}