{
  "type": "Feature",
  "properties": {
    "iso:country":"US",
    "sg:address":"1845 Ithaca St",
    "sg:city":"Chula Vista",
    "sg:classifiers":[
        {
            "category":"Building & Trades",
            "subcategory":"Landscaping Services",
            "type":"Services"
        }
    ],
    "sg:phone":"+1 619 482 7827",
    "sg:postcode":"91913",
    "sg:province":"CA",
    "sg:tags":[
        "landscape"
    ],
    "wof:name":"Hassle Free",
    "wof:placetype":"venue"
},
  "geometry": {"coordinates":[-116.98616,32.643894],"type":"Point"}
}