{
  "type": "Feature",
  "properties": {
    "iso:country":"US",
    "sg:address":"1737 W Caldwell Ave",
    "sg:city":"Visalia",
    "sg:classifiers":[
        {
            "category":"Banks & Credit Unions",
            "subcategory":"Bank",
            "type":"Services"
        }
    ],
    "sg:phone":"+1 559 627 4810",
    "sg:postcode":"93277",
    "sg:province":"CA",
    "sg:tags":[
        "cashing",
        "check"
    ],
    "wof:name":"Pay Day Now",
    "wof:placetype":"venue"
},
  "geometry": {"coordinates":[-119.30994800000001,36.298339],"type":"Point"}
}