{
  "type": "Feature",
  "properties": {
    "addr:full":"Vanguard Properties 2501 Mission St San Francisco CA 94110",
    "addr:housenumber":"2501",
    "addr:postcode":"94110",
    "addr:street":"Mission St",
    "iso:country":"US",
    "sg:address":"Vanguard Properties 2501 Mission St",
    "sg:city":"San Francisco",
    "sg:classifiers":[
        {
            "category":"Real Estate",
            "subcategory":"Real Estate Agent",
            "type":"Services"
        }
    ],
    "sg:phone":"+1 415 254 5853",
    "sg:postcode":"94110",
    "sg:province":"CA",
    "sg:website":"www.sanfrancisco-re.com",
    "wof:name":"Eugene Pak",
    "wof:placetype":"venue"
},
  "geometry": {"coordinates":[-122.41852900000001,37.756881],"type":"Point"}
}