{
  "type": "Feature",
  "properties": {
    "iso:country":"US",
    "sg:address":"3895 N Perris Blvd",
    "sg:city":"Perris",
    "sg:classifiers":[
        {
            "category":"Insurance",
            "subcategory":"Insurance Agent",
            "type":"Services"
        }
    ],
    "sg:phone":"+1 951 657 3131",
    "sg:postcode":"92571",
    "sg:province":"CA",
    "sg:website":"http://www.farmers.com",
    "wof:name":"Garth D Moore Ins",
    "wof:placetype":"venue"
},
  "geometry": {"coordinates":[-117.226067,33.841264],"type":"Point"}
}