{
  "type": "Feature",
  "properties": {
    "iso:country":"US",
    "sg:address":"7800 Crescent Ave.",
    "sg:city":"Buena Park",
    "sg:classifiers":[
        {
            "category":"Travel",
            "subcategory":"Hotels & Motels",
            "type":"Entertainment"
        }
    ],
    "sg:phone":"+1 714 527 2201",
    "sg:postcode":"90620",
    "sg:province":"CA",
    "sg:website":"www.super8.com",
    "wof:name":"Super 8 Motel",
    "wof:placetype":"venue"
},
  "geometry": {"coordinates":[-117.997156,33.838869],"type":"Point"}
}