{
  "type": "Feature",
  "properties": {
    "addr:full":"445 Bellevue Ave. #302 Oakland CA 94610",
    "addr:housenumber":"445",
    "addr:postcode":"94610",
    "addr:street":"Bellevue Ave. # 302",
    "iso:country":"US",
    "sg:address":"445 Bellevue Ave. #302",
    "sg:city":"Oakland",
    "sg:classifiers":[
        {
            "category":"Health Services",
            "subcategory":"Doctor",
            "type":"Services"
        },
        {
            "category":"Health Services",
            "subcategory":"Clinic",
            "type":"Services"
        },
        {
            "category":"Health Services",
            "subcategory":"Health Practitioner",
            "type":"Services"
        }
    ],
    "sg:phone":"+1 510 832 0717",
    "sg:postcode":"94610",
    "sg:province":"CA",
    "sg:tags":[
        "psychotherapist",
        "psychologist",
        "mental",
        "counseling"
    ],
    "wof:name":"Lesley Parke PHD",
    "wof:placetype":"venue"
},
  "geometry": {"coordinates":[-122.252718,37.808909],"type":"Point"}
}