{
  "type": "Feature",
  "properties": {
    "addr:full":"120 Brannan St San Francisco CA 94107",
    "addr:housenumber":"120",
    "addr:postcode":"94107",
    "addr:street":"Brannan St",
    "iso:country":"US",
    "sg:address":"120 Brannan St",
    "sg:city":"San Francisco",
    "sg:classifiers":[
        {
            "category":"Food & Beverages",
            "subcategory":"Groceries & Convenience Stores",
            "type":"Retail Goods"
        }
    ],
    "sg:phone":"+1 415 227 0151",
    "sg:postcode":"94107",
    "sg:province":"CA",
    "sg:tags":[
        "deli",
        "grocer"
    ],
    "wof:name":"Bayside Market",
    "wof:placetype":"venue"
},
  "geometry": {"coordinates":[-122.389267,37.784214],"type":"Point"}
}