{
  "type": "Feature",
  "properties": {
    "iso:country":"US",
    "sg:address":"71800 Highway 111 Suite A122",
    "sg:city":"Rancho Mirage",
    "sg:classifiers":[
        {
            "category":"Restaurant",
            "type":"Food & Drink"
        }
    ],
    "sg:phone":"+1 760 862 9898",
    "sg:postcode":"92270",
    "sg:province":"CA",
    "sg:tags":[
        "italian"
    ],
    "sg:website":"www.papamariospizzeria.com",
    "wof:name":"Papa Mario's Pizzeria",
    "wof:placetype":"venue"
},
  "geometry": {"coordinates":[-116.41021000000001,33.740579],"type":"Point"}
}