{
  "type": "Feature",
  "properties": {
    "iso:country":"US",
    "sg:address":"191 Lado de Loma Dr",
    "sg:city":"Vista",
    "sg:classifiers":[
        {
            "category":"Freight",
            "type":"Transportation"
        }
    ],
    "sg:phone":"+1 760 726 9708",
    "sg:postcode":"92083",
    "sg:province":"CA",
    "sg:tags":[
        "haul",
        "long",
        "trucking"
    ],
    "wof:name":"D K Express",
    "wof:placetype":"venue"
},
  "geometry": {"coordinates":[-117.247023,33.196596],"type":"Point"}
}