{
  "type": "Feature",
  "properties": {
    "iso:country":"US",
    "sg:address":"2365 E Tahquitz Canyon Way",
    "sg:city":"Palm Springs",
    "sg:classifiers":[
        {
            "category":"Shopping",
            "subcategory":"Clothing, Apparel, & Fashions",
            "type":"Retail Goods"
        }
    ],
    "sg:phone":"+1 760 416 0703",
    "sg:postcode":"92262",
    "sg:province":"CA",
    "wof:name":"Glamour Gal Boutique",
    "wof:placetype":"venue"
},
  "geometry": {"coordinates":[-116.51879,33.823089],"type":"Point"}
}