{
  "type": "Feature",
  "properties": {
    "addr:full":"130 Cabrillo St Costa Mesa CA 92627",
    "addr:housenumber":"130",
    "addr:postcode":"92627",
    "addr:street":"Cabrillo St",
    "iso:country":"US",
    "sg:address":"130 Cabrillo St",
    "sg:city":"Costa Mesa",
    "sg:classifiers":[
        {
            "category":"Personal",
            "subcategory":"Beauty Salon",
            "type":"Services"
        }
    ],
    "sg:phone":"+1 949 275 0390",
    "sg:postcode":"92627",
    "sg:province":"CA",
    "wof:name":"Babe's Hair Works",
    "wof:placetype":"venue"
},
  "geometry": {"coordinates":[-117.91982899999999,33.638087],"type":"Point"}
}