{
  "type": "Feature",
  "properties": {
    "iso:country":"US",
    "sg:address":"484 Lighthouse Ave",
    "sg:city":"Monterey",
    "sg:classifiers":[
        {
            "category":"Professional",
            "type":"Services"
        }
    ],
    "sg:phone":"+1 831 657 2431",
    "sg:postcode":"93940",
    "sg:province":"CA",
    "sg:tags":[
        "establishment"
    ],
    "wof:name":"Incontrol Productions Inc",
    "wof:placetype":"venue"
},
  "geometry": {"coordinates":[-121.900137,36.611659],"type":"Point"}
}