{
  "type": "Feature",
  "properties": {
    "addr:full":"3404 Long Beach Blvd Long Beach CA 90807",
    "addr:housenumber":"3404",
    "addr:postcode":"90807",
    "addr:street":"Long Beach Blvd",
    "iso:country":"US",
    "sg:address":"3404 Long Beach Blvd",
    "sg:city":"Long Beach",
    "sg:classifiers":[
        {
            "category":"Shopping",
            "subcategory":"Mobile Phones",
            "type":"Retail Goods"
        }
    ],
    "sg:phone":"+1 562 981 1200",
    "sg:postcode":"90807",
    "sg:province":"CA",
    "wof:name":"Sprint Store By Elise Wireless",
    "wof:placetype":"venue"
},
  "geometry": {"coordinates":[-118.189239,33.819048],"type":"Point"}
}