{
  "type": "Feature",
  "properties": {
    "iso:country":"US",
    "sg:address":"1533 26th St",
    "sg:city":"Santa Monica",
    "sg:classifiers":[
        {
            "category":"Professional",
            "subcategory":"Business Services",
            "type":"Services"
        }
    ],
    "sg:phone":"+1 310 264 6100",
    "sg:postcode":"90404",
    "sg:province":"CA",
    "sg:tags":[
        "recording",
        "studio"
    ],
    "wof:name":"Wow & Flutter",
    "wof:placetype":"venue"
},
  "geometry": {"coordinates":[-118.471595,34.031117],"type":"Point"}
}