{
  "type": "Feature",
  "properties": {
    "addr:full":"1335 E Gum Ave Woodland CA 95776",
    "addr:housenumber":"1335",
    "addr:postcode":"95776",
    "addr:street":"E Gum Ave",
    "iso:country":"US",
    "sg:address":"1335 E Gum Ave",
    "sg:city":"Woodland",
    "sg:classifiers":[
        {
            "category":"Building & Trades",
            "subcategory":"Construction",
            "type":"Services"
        }
    ],
    "sg:phone":"+1 530 666 6456",
    "sg:postcode":"95776",
    "sg:province":"CA",
    "sg:tags":[
        "contractor"
    ],
    "wof:name":"JTS Contracting",
    "wof:placetype":"venue"
},
  "geometry": {"coordinates":[-121.760144,38.668382],"type":"Point"}
}