{
  "type": "Feature",
  "properties": {
    "addr:full":"13139 Brookhurst St Garden Grove CA 92843",
    "addr:housenumber":"13139",
    "addr:postcode":"92843",
    "addr:street":"Brookhurst St",
    "iso:country":"US",
    "sg:address":"13139 Brookhurst St",
    "sg:city":"Garden Grove",
    "sg:classifiers":[
        {
            "category":"Shopping",
            "subcategory":"Antiques",
            "type":"Retail Goods"
        }
    ],
    "sg:phone":"+1 714 636 8015",
    "sg:postcode":"92843",
    "sg:province":"CA",
    "wof:name":"Sala's Antiques",
    "wof:placetype":"venue"
},
  "geometry": {"coordinates":[-117.95526,33.771843],"type":"Point"}
}