{
  "type": "Feature",
  "properties": {
    "iso:country":"US",
    "sg:address":"1831 Pontius Ave",
    "sg:city":"Los Angeles",
    "sg:classifiers":[
        {
            "category":"Wholesale",
            "subcategory":"Apparel",
            "type":"Manufacturing & Wholesale Goods"
        }
    ],
    "sg:phone":"+1 310 445 9193",
    "sg:postcode":"90025",
    "sg:province":"CA",
    "sg:tags":[
        "clothing",
        "shoes",
        "accessory"
    ],
    "wof:name":"Pacific Marketing Works Inc",
    "wof:placetype":"venue"
},
  "geometry": {"coordinates":[-118.442497,34.044577],"type":"Point"}
}