{
  "type": "Feature",
  "properties": {
    "iso:country":"US",
    "sg:address":"1023 N Main St",
    "sg:city":"Orange",
    "sg:classifiers":[
        {
            "category":"Retail",
            "subcategory":"Repair Shop",
            "type":"Services"
        }
    ],
    "sg:phone":"+1 714 999 0995",
    "sg:postcode":"92868",
    "sg:province":"CA",
    "sg:tags":[
        "machine"
    ],
    "wof:name":"Simplex Office Solutions",
    "wof:placetype":"venue"
},
  "geometry": {"coordinates":[-117.86658799999999,33.8039],"type":"Point"}
}