{
  "type": "Feature",
  "properties": {
    "iso:country":"US",
    "sg:address":"525 Rosarita Dr",
    "sg:city":"Fullerton",
    "sg:classifiers":[
        {
            "category":"Building & Trades",
            "subcategory":"Pest Control",
            "type":"Services"
        }
    ],
    "sg:phone":"+1 714 441 1820",
    "sg:postcode":"92835",
    "sg:province":"CA",
    "wof:name":"Scott Termite Control",
    "wof:placetype":"venue"
},
  "geometry": {"coordinates":[-117.922693,33.907347],"type":"Point"}
}