{
  "type": "Feature",
  "properties": {
    "iso:country":"US",
    "sg:address":"440 Queens Ln",
    "sg:city":"San Jose",
    "sg:classifiers":[
        {
            "category":"Professional",
            "subcategory":"Advertising",
            "type":"Services"
        }
    ],
    "sg:phone":"+1 408 392 9992",
    "sg:postcode":"95112",
    "sg:province":"CA",
    "sg:tags":[
        "mailing",
        "shipping"
    ],
    "wof:name":"Unique Solutions",
    "wof:placetype":"venue"
},
  "geometry": {"coordinates":[-121.90422,37.369091],"type":"Point"}
}