{
  "type": "Feature",
  "properties": {
    "iso:country":"US",
    "sg:address":"31855 Date Palm Dr Ste 3",
    "sg:city":"Cathedral City",
    "sg:classifiers":[
        {
            "category":"Professional",
            "subcategory":"Lawyer & Legal Services",
            "type":"Services"
        },
        {
            "category":"Professional",
            "subcategory":"Printing & Photocopies",
            "type":"Services"
        }
    ],
    "sg:phone":"+1 760 324 8184",
    "sg:postcode":"92234",
    "sg:province":"CA",
    "sg:tags":[
        "notary"
    ],
    "wof:name":"The Ups Store",
    "wof:placetype":"venue"
},
  "geometry": {"coordinates":[-116.459401,33.816768],"type":"Point"}
}