{
  "type": "Feature",
  "properties": {
    "iso:country":"US",
    "sg:address":"450 W Wall Rd",
    "sg:city":"Imperial",
    "sg:classifiers":[
        {
            "category":"Retail",
            "subcategory":"Auto Repair",
            "type":"Services"
        }
    ],
    "sg:phone":"+1 760 352 3592",
    "sg:postcode":"92251",
    "sg:province":"CA",
    "sg:tags":[
        "brake"
    ],
    "wof:name":"Car Barn",
    "wof:placetype":"venue"
},
  "geometry": {"coordinates":[-115.57431,32.821931],"type":"Point"}
}