{
  "type": "Feature",
  "properties": {
    "iso:country":"US",
    "sg:address":"8754 N Millbrook Ave",
    "sg:city":"Fresno",
    "sg:classifiers":[
        {
            "category":"Real Estate",
            "subcategory":"Architect",
            "type":"Services"
        },
        {
            "category":"Building & Trades",
            "subcategory":"Construction",
            "type":"Services"
        }
    ],
    "sg:phone":"+1 559 431 3898",
    "sg:postcode":"93720",
    "sg:province":"CA",
    "sg:tags":[
        "house",
        "architectural"
    ],
    "wof:name":"Rottner & Associates",
    "wof:placetype":"venue"
},
  "geometry": {"coordinates":[-119.765722,36.86293],"type":"Point"}
}