{
  "type": "Feature",
  "properties": {
    "addr:full":"2359 Lincoln Ave Altadena CA 91001",
    "addr:housenumber":"2359",
    "addr:postcode":"91001",
    "addr:street":"Lincoln Ave",
    "iso:country":"US",
    "sg:address":"2359 Lincoln Ave",
    "sg:city":"Altadena",
    "sg:classifiers":[
        {
            "category":"Personal",
            "subcategory":"Beauty Salon",
            "type":"Services"
        },
        {
            "category":"Personal",
            "subcategory":"Nail Salon",
            "type":"Services"
        }
    ],
    "sg:phone":"+1 626 794 3331",
    "sg:postcode":"91001",
    "sg:province":"CA",
    "wof:name":"Pat's Beauty & Nail Salon",
    "wof:placetype":"venue"
},
  "geometry": {"coordinates":[-118.159717,34.186209],"type":"Point"}
}