{
  "type": "Feature",
  "properties": {
    "addr:full":"11742 Riverside Dr Valley Village CA 91607",
    "addr:housenumber":"11742",
    "addr:postcode":"91607",
    "addr:street":"Riverside Dr",
    "iso:country":"US",
    "sg:address":"11742 Riverside Dr",
    "sg:city":"Valley Village",
    "sg:classifiers":[
        {
            "category":"Education",
            "subcategory":"School",
            "type":"Public Place"
        }
    ],
    "sg:phone":"+1 818 762 1212",
    "sg:postcode":"91607",
    "sg:province":"CA",
    "sg:tags":[
        "elementary"
    ],
    "wof:name":"Neighborhood School the",
    "wof:placetype":"venue"
},
  "geometry": {"coordinates":[-118.389,34.1577],"type":"Point"}
}