{
  "type": "Feature",
  "properties": {
    "iso:country":"US",
    "sg:address":"108 Whispering Pines Dr",
    "sg:city":"Scotts Valley",
    "sg:classifiers":[
        {
            "category":"Banks & Credit Unions",
            "subcategory":"Bank",
            "type":"Services"
        }
    ],
    "sg:phone":"+1 831 461 8020",
    "sg:postcode":"95066",
    "sg:province":"CA",
    "sg:tags":[
        "loan",
        "real estate"
    ],
    "wof:name":"Mortgage America",
    "wof:placetype":"venue"
},
  "geometry": {"coordinates":[-122.027207,37.042613],"type":"Point"}
}