{
  "type": "Feature",
  "properties": {
    "iso:country":"US",
    "sg:address":"5542 Brisa St",
    "sg:city":"Livermore",
    "sg:classifiers":[
        {
            "category":"Retail",
            "subcategory":"Repair Shop",
            "type":"Services"
        }
    ],
    "sg:phone":"+1 925 449 5722",
    "sg:postcode":"94550",
    "sg:province":"CA",
    "sg:tags":[
        "upholsterer"
    ],
    "wof:name":"Perry Martin Upholstery",
    "wof:placetype":"venue"
},
  "geometry": {"coordinates":[-121.725007,37.697212],"type":"Point"}
}