{
  "type": "Feature",
  "properties": {
    "iso:country":"US",
    "sg:address":"8776 Helms Ave",
    "sg:city":"Rancho Cucamonga",
    "sg:classifiers":[
        {
            "category":"Building & Trades",
            "subcategory":"Construction",
            "type":"Services"
        }
    ],
    "sg:phone":"+1 909 987 1772",
    "sg:postcode":"91730",
    "sg:province":"CA",
    "sg:tags":[
        "fire",
        "restoration",
        "damage"
    ],
    "wof:name":"Cleaning-Deflooding",
    "wof:placetype":"venue"
},
  "geometry": {"coordinates":[-117.600041,34.094198],"type":"Point"}
}