{
  "type": "Feature",
  "properties": {
    "addr:full":"2849 Walnut Ave Carmichael CA 95608",
    "addr:housenumber":"2849",
    "addr:postcode":"95608",
    "addr:street":"Walnut Ave",
    "iso:country":"US",
    "sg:address":"2849 Walnut Ave",
    "sg:city":"Carmichael",
    "sg:classifiers":[
        {
            "category":"Banks & Credit Unions",
            "subcategory":"Bank",
            "type":"Services"
        }
    ],
    "sg:phone":"+1 916 412 4878",
    "sg:postcode":"95608",
    "sg:province":"CA",
    "sg:tags":[
        "cashing",
        "check"
    ],
    "wof:name":"Low Rate Check Cashing",
    "wof:placetype":"venue"
},
  "geometry": {"coordinates":[-121.346098,38.614644],"type":"Point"}
}