{
  "type": "Feature",
  "properties": {
    "iso:country":"US",
    "sg:address":"54280 Ave Juarez",
    "sg:city":"La Quinta",
    "sg:classifiers":[
        {
            "category":"Retail",
            "subcategory":"Repair Shop",
            "type":"Services"
        }
    ],
    "sg:phone":"+1 760 564 3771",
    "sg:postcode":"92253",
    "sg:province":"CA",
    "sg:tags":[
        "bathtub",
        "sink",
        "refinishing"
    ],
    "wof:name":"Tub & Tile Doctor",
    "wof:placetype":"venue"
},
  "geometry": {"coordinates":[-116.316587,33.652764],"type":"Point"}
}