{
  "type": "Feature",
  "properties": {
    "iso:country":"US",
    "sg:address":"731 S Averill Ave",
    "sg:city":"San Pedro",
    "sg:classifiers":[
        {
            "category":"Organizations",
            "subcategory":"Non-profit Organization",
            "type":"Services"
        }
    ],
    "sg:phone":"+1 310 832 7335",
    "sg:postcode":"90732",
    "sg:province":"CA",
    "wof:name":"Meals On Wheels",
    "wof:placetype":"venue"
},
  "geometry": {"coordinates":[-118.307822,33.737261],"type":"Point"}
}