{
  "type": "Feature",
  "properties": {
    "iso:country":"US",
    "sg:address":"228 E Thompson Blvd",
    "sg:city":"Ventura",
    "sg:classifiers":[
        {
            "category":"Shopping",
            "subcategory":"Clothing, Apparel, & Fashions",
            "type":"Retail Goods"
        }
    ],
    "sg:phone":"+1 805 643 1772",
    "sg:postcode":"93001",
    "sg:province":"CA",
    "sg:tags":[
        "swimwear",
        "accessory"
    ],
    "wof:name":"Tiki Punch Beachwear",
    "wof:placetype":"venue"
},
  "geometry": {"coordinates":[-119.296538,34.278184],"type":"Point"}
}