{
  "type": "Feature",
  "properties": {
    "addr:full":"13620 Lincoln Way Auburn CA 95603",
    "addr:housenumber":"13620",
    "addr:postcode":"ca 95603",
    "addr:street":"Lincoln Way",
    "iso:country":"US",
    "sg:address":"13620 Lincoln Way",
    "sg:city":"Auburn",
    "sg:classifiers":[
        {
            "category":"Wholesale",
            "subcategory":"Office Equipment",
            "type":"Manufacturing & Wholesale Goods"
        }
    ],
    "sg:phone":"+1 530 477 5236",
    "sg:postcode":"95603",
    "sg:province":"CA",
    "wof:name":"Xerox Copiers & Supplies",
    "wof:placetype":"venue"
},
  "geometry": {"coordinates":[-121.055159,38.929719],"type":"Point"}
}