{
  "type": "Feature",
  "properties": {
    "addr:full":"78267 US Hwy 111 La Quinta CA 92253",
    "addr:postcode":"78267;92253",
    "addr:street":"Us Hwy 111",
    "iso:country":"US",
    "sg:address":"78267 US Hwy 111",
    "sg:city":"La Quinta",
    "sg:classifiers":[
        {
            "category":"Shopping",
            "subcategory":"Bicycles & Sporting Goods",
            "type":"Retail Goods"
        }
    ],
    "sg:phone":"+1 760 346 8768",
    "sg:postcode":"92253",
    "sg:province":"CA",
    "sg:tags":[
        "equipment",
        "golf",
        "supply"
    ],
    "sg:website":"www.lumpys.com",
    "wof:name":"Lumpy's Discount Golf & Fshn",
    "wof:placetype":"venue"
},
  "geometry": {"coordinates":[-116.295244,33.715226],"type":"Point"}
}