{
  "type": "Feature",
  "properties": {
    "addr:full":"9601 Wilshire Blvd Beverly Hills CA 90210",
    "addr:housenumber":"9601",
    "addr:postcode":"90210",
    "addr:street":"Wilshire Blvd",
    "iso:country":"US",
    "sg:address":"9601 Wilshire Blvd",
    "sg:city":"Beverly Hills",
    "sg:classifiers":[
        {
            "category":"Sports & Exercise",
            "subcategory":"Gym",
            "type":"Entertainment"
        }
    ],
    "sg:phone":"+1 310 888 8100",
    "sg:postcode":"90210",
    "sg:province":"CA",
    "sg:website":"www.thesportsclubla.com",
    "wof:name":"The Sports Club LA",
    "wof:placetype":"venue"
},
  "geometry": {"coordinates":[-118.40267900000001,34.06713],"type":"Point"}
}