{
  "type": "Feature",
  "properties": {
    "iso:country":"US",
    "sg:address":"8500 Wilshire Blvd",
    "sg:city":"Beverly Hills",
    "sg:classifiers":[
        {
            "category":"Health Services",
            "subcategory":"Doctor",
            "type":"Services"
        }
    ],
    "sg:phone":"+1 310 659 7000",
    "sg:postcode":"90211",
    "sg:province":"CA",
    "wof:name":"Lowe Dorothy H MD",
    "wof:placetype":"venue"
},
  "geometry": {"coordinates":[-118.37624,34.065047],"type":"Point"}
}