{
  "type": "Feature",
  "properties": {
    "addr:full":"1259 Cliff Dr Laguna Beach CA 92651",
    "addr:housenumber":"1259",
    "addr:postcode":"92651",
    "addr:street":"Cliff Dr",
    "iso:country":"US",
    "sg:address":"1259 Cliff Dr",
    "sg:city":"Laguna Beach",
    "sg:classifiers":[
        {
            "category":"Building & Trades",
            "subcategory":"Construction",
            "type":"Services"
        }
    ],
    "sg:phone":"+1 949 497 5771",
    "sg:postcode":"92651",
    "sg:province":"CA",
    "sg:tags":[
        "interior",
        "design"
    ],
    "wof:name":"Jacobson Jackie Asid",
    "wof:placetype":"venue"
},
  "geometry": {"coordinates":[-117.80100299999999,33.547199],"type":"Point"}
}