{
  "type": "Feature",
  "properties": {
    "iso:country":"US",
    "sg:address":"145 Stillman St",
    "sg:city":"San Francisco",
    "sg:classifiers":[
        {
            "category":"Building & Trades",
            "subcategory":"Construction",
            "type":"Services"
        }
    ],
    "sg:phone":"+1 415 409 6600",
    "sg:postcode":"94107",
    "sg:province":"CA",
    "sg:tags":[
        "contractor"
    ],
    "wof:name":"Jonothanboys Construction Grp",
    "wof:placetype":"venue"
},
  "geometry": {"coordinates":[-122.397293,37.781038],"type":"Point"}
}