{
  "type": "Feature",
  "properties": {
    "addr:full":"12953 Alcosta Blvd San Ramon CA 94583",
    "addr:postcode":"12953;94583",
    "addr:street":"Alcosta Blvd",
    "iso:country":"US",
    "sg:address":"12953 Alcosta Blvd",
    "sg:city":"San Ramon",
    "sg:classifiers":[
        {
            "category":"Building & Trades",
            "subcategory":"Cleaning & Sanitation",
            "type":"Services"
        }
    ],
    "sg:phone":"+1 925 866 1211",
    "sg:postcode":"94583",
    "sg:province":"CA",
    "sg:tags":[
        "janitor"
    ],
    "sg:website":"www.abm.com",
    "wof:name":"American Building Maintenance",
    "wof:placetype":"venue"
},
  "geometry": {"coordinates":[-121.964493,37.781379],"type":"Point"}
}