{
  "type": "Feature",
  "properties": {
    "iso:country":"US",
    "sg:address":"28608 Golden Oak Ln",
    "sg:city":"Highland",
    "sg:classifiers":[
        {
            "category":"Professional",
            "subcategory":"Business Services",
            "type":"Services"
        }
    ],
    "sg:phone":"+1 909 862 5000",
    "sg:postcode":"92346",
    "sg:province":"CA",
    "sg:tags":[
        "inspection"
    ],
    "wof:name":"J B Inspections",
    "wof:placetype":"venue"
},
  "geometry": {"coordinates":[-117.18108700000001,34.115282],"type":"Point"}
}