{
  "type": "Feature",
  "properties": {
    "iso:country":"US",
    "sg:address":"3739 Monterey Ave",
    "sg:city":"Baldwin Park",
    "sg:classifiers":[
        {
            "category":"Organizations",
            "subcategory":"Religious Organization",
            "type":"Services"
        }
    ],
    "sg:phone":"+1 626 960 9585",
    "sg:postcode":"91706",
    "sg:province":"CA",
    "sg:tags":[
        "church"
    ],
    "wof:name":"Church Of The Redeemer",
    "wof:placetype":"venue"
},
  "geometry": {"coordinates":[-117.975966,34.07965],"type":"Point"}
}