{
  "type": "Feature",
  "properties": {
    "addr:full":"3516 Monroe Ave San Diego CA 92116",
    "addr:housenumber":"3516",
    "addr:postcode":"92116",
    "addr:street":"Monroe Ave",
    "iso:country":"US",
    "sg:address":"3516 Monroe Ave",
    "sg:city":"San Diego",
    "sg:classifiers":[
        {
            "category":"Wholesale",
            "subcategory":"Plants",
            "type":"Manufacturing & Wholesale Goods"
        }
    ],
    "sg:phone":"+1 619 640 0340",
    "sg:postcode":"92116",
    "sg:province":"CA",
    "sg:tags":[
        "supply"
    ],
    "wof:name":"Roses Just",
    "wof:placetype":"venue"
},
  "geometry": {"coordinates":[-117.1178,32.759101],"type":"Point"}
}