{
  "type": "Feature",
  "properties": {
    "iso:country":"US",
    "sg:address":"4590 Macarthur Blvd",
    "sg:city":"Newport Beach",
    "sg:classifiers":[
        {
            "category":"Banks & Credit Unions",
            "subcategory":"Bank",
            "type":"Services"
        }
    ],
    "sg:phone":"+1 949 863 1208",
    "sg:postcode":"92660",
    "sg:province":"CA",
    "sg:website":"www.citybank.com",
    "wof:name":"Citybank",
    "wof:placetype":"venue"
},
  "geometry": {"coordinates":[-117.864222,33.670589],"type":"Point"}
}