{
  "type": "Feature",
  "properties": {
    "iso:country":"US",
    "sg:address":"1760 Airline Hwy",
    "sg:city":"Hollister",
    "sg:classifiers":[
        {
            "category":"Personal",
            "subcategory":"Beauty Salon",
            "type":"Services"
        }
    ],
    "sg:phone":"+1 831 638 9186",
    "sg:postcode":"95023",
    "sg:province":"CA",
    "wof:name":"Supercuts",
    "wof:placetype":"venue"
},
  "geometry": {"coordinates":[-121.388757,36.836157],"type":"Point"}
}