{
  "type": "Feature",
  "properties": {
    "iso:country":"US",
    "sg:address":"4102 Catalina Pl",
    "sg:city":"San Diego",
    "sg:classifiers":[
        {
            "category":"Government",
            "subcategory":"Office",
            "type":"Public Place"
        }
    ],
    "sg:phone":"+1 619 226 8185",
    "sg:postcode":"92107",
    "sg:province":"CA",
    "sg:tags":[
        "sector",
        "regulation",
        "commercial"
    ],
    "wof:name":"Haener Block Co",
    "wof:placetype":"venue"
},
  "geometry": {"coordinates":[-117.23709599999999,32.738247],"type":"Point"}
}