{
  "type": "Feature",
  "properties": {
    "iso:country":"US",
    "sg:address":"597 Genine Dr",
    "sg:city":"San Jose",
    "sg:classifiers":[
        {
            "category":"Travel",
            "subcategory":"Travel Agent",
            "type":"Entertainment"
        }
    ],
    "sg:phone":"+1 408 926 2020",
    "sg:postcode":"95127",
    "sg:province":"CA",
    "sg:tags":[
        "agency"
    ],
    "wof:name":"Casher Travel",
    "wof:placetype":"venue"
},
  "geometry": {"coordinates":[-121.833592,37.383263],"type":"Point"}
}