{
  "type": "Feature",
  "properties": {
    "iso:country":"US",
    "sg:address":"21896 Ave 304",
    "sg:city":"Exeter",
    "sg:classifiers":[
        {
            "category":"Farming",
            "subcategory":"Orchard",
            "type":"Manufacturing & Wholesale Goods"
        }
    ],
    "sg:phone":"+1 559 592 2036",
    "sg:postcode":"93221",
    "sg:province":"CA",
    "sg:tags":[
        "citrus",
        "grove",
        "fruit"
    ],
    "wof:name":"Phillip Tomlinson",
    "wof:placetype":"venue"
},
  "geometry": {"coordinates":[-119.091081,36.340164],"type":"Point"}
}