{
  "type": "Feature",
  "properties": {
    "addr:full":"27 7th St Eureka CA 95501",
    "addr:housenumber":"27",
    "addr:postcode":"95501",
    "addr:street":"7Th St",
    "iso:country":"US",
    "sg:address":"27 7th St",
    "sg:city":"Eureka",
    "sg:classifiers":[
        {
            "category":"Professional",
            "type":"Services"
        }
    ],
    "sg:phone":"+1 707 445 4639",
    "sg:postcode":"95501",
    "sg:province":"CA",
    "sg:tags":[
        "establishment"
    ],
    "wof:name":"Northwest Acceptance Corp Inc",
    "wof:placetype":"venue"
},
  "geometry": {"coordinates":[-124.170558,40.799654],"type":"Point"}
}