{
  "type": "Feature",
  "properties": {
    "iso:country":"US",
    "sg:address":"341 Broadway St",
    "sg:city":"Chico",
    "sg:classifiers":[
        {
            "category":"Social Services",
            "subcategory":"Job Training",
            "type":"Services"
        }
    ],
    "sg:phone":"+1 530 893 4355",
    "sg:postcode":"95928",
    "sg:province":"CA",
    "sg:tags":[
        "rehabilitation"
    ],
    "wof:name":"Alexander Applied Technique",
    "wof:placetype":"venue"
},
  "geometry": {"coordinates":[-121.839881,39.728675],"type":"Point"}
}