{
  "type": "Feature",
  "properties": {
    "addr:full":"14395 Saratoga Ave Saratoga CA 95070",
    "addr:housenumber":"14395",
    "addr:postcode":"95070",
    "addr:street":"Saratoga Ave",
    "iso:country":"US",
    "sg:address":"14395 Saratoga Ave",
    "sg:city":"Saratoga",
    "sg:classifiers":[
        {
            "category":"Professional",
            "subcategory":"Engineering",
            "type":"Services"
        }
    ],
    "sg:phone":"+1 408 867 6611",
    "sg:postcode":"95070",
    "sg:province":"CA",
    "sg:tags":[
        "engineer"
    ],
    "wof:name":"Engineering Information Systs",
    "wof:placetype":"venue"
},
  "geometry": {"coordinates":[-122.031211,37.259499],"type":"Point"}
}