{
  "type": "Feature",
  "properties": {
    "iso:country":"US",
    "sg:address":"730 W Ventura St",
    "sg:city":"Fillmore",
    "sg:classifiers":[
        {
            "category":"Food & Beverages",
            "subcategory":"Specialty",
            "type":"Retail Goods"
        }
    ],
    "sg:phone":"+1 805 524 0966",
    "sg:postcode":"93015",
    "sg:province":"CA",
    "wof:name":"Coffee Kiosk Inc",
    "wof:placetype":"venue"
},
  "geometry": {"coordinates":[-118.91736,34.396101],"type":"Point"}
}