{
  "type": "Feature",
  "properties": {
    "iso:country":"US",
    "sg:address":"21010 Superior St",
    "sg:city":"Chatsworth",
    "sg:classifiers":[
        {
            "category":"Communications",
            "subcategory":"Film & Video Production",
            "type":"Services"
        }
    ],
    "sg:phone":"+1 818 885 4111",
    "sg:postcode":"91311",
    "sg:province":"CA",
    "sg:tags":[
        "taping"
    ],
    "sg:website":"www.kmdvd.com",
    "wof:name":"Dvd Replication",
    "wof:placetype":"venue"
},
  "geometry": {"coordinates":[-118.592738,34.246276],"type":"Point"}
}