{
  "type": "Feature",
  "properties": {
    "addr:full":"4014 Calmoor St National City CA 91950",
    "addr:housenumber":"4014",
    "addr:postcode":"91950",
    "addr:street":"Calmoor St",
    "iso:country":"US",
    "sg:address":"4014 Calmoor St",
    "sg:city":"National City",
    "sg:classifiers":[
        {
            "category":"Manufacturing",
            "subcategory":"Printing",
            "type":"Manufacturing & Wholesale Goods"
        }
    ],
    "sg:phone":"+1 619 479 4425",
    "sg:postcode":"91950",
    "sg:province":"CA",
    "sg:tags":[
        "book"
    ],
    "wof:name":"House of Nia",
    "wof:placetype":"venue"
},
  "geometry": {"coordinates":[-117.057563,32.658321],"type":"Point"}
}