{
  "type": "Feature",
  "properties": {
    "iso:country":"US",
    "sg:address":"601 del Norte Blvd",
    "sg:city":"Oxnard",
    "sg:classifiers":[
        {
            "category":"Wholesale",
            "subcategory":"Auto Parts",
            "type":"Manufacturing & Wholesale Goods"
        }
    ],
    "sg:phone":"+1 805 485 6196",
    "sg:postcode":"93030",
    "sg:province":"CA",
    "sg:tags":[
        "truck",
        "accessory"
    ],
    "wof:name":"Rhino Lining Of Ventura County",
    "wof:placetype":"venue"
},
  "geometry": {"coordinates":[-119.127133,34.208946],"type":"Point"}
}