{
  "type": "Feature",
  "properties": {
    "iso:country":"US",
    "sg:address":"4606 N Bendel Ave",
    "sg:city":"Fresno",
    "sg:classifiers":[
        {
            "category":"Building & Trades",
            "subcategory":"Construction",
            "type":"Services"
        }
    ],
    "sg:phone":"+1 559 275 7099",
    "sg:postcode":"93722",
    "sg:province":"CA",
    "sg:tags":[
        "asbestos",
        "abatement",
        "waste",
        "hazardous",
        "removal"
    ],
    "sg:website":"www.apccontractors.com",
    "wof:name":"Apc Contractors Inc",
    "wof:placetype":"venue"
},
  "geometry": {"coordinates":[-119.869849,36.805225],"type":"Point"}
}