{
  "type": "Feature",
  "properties": {
    "addr:full":"2740 Mills Park Dr Rancho Cordova CA 95670",
    "addr:housenumber":"2740",
    "addr:postcode":"95670",
    "addr:street":"Mills Park Dr",
    "iso:country":"US",
    "sg:address":"2740 Mills Park Dr",
    "sg:city":"Rancho Cordova",
    "sg:classifiers":[
        {
            "category":"Recreation",
            "subcategory":"Arcade",
            "type":"Entertainment"
        }
    ],
    "sg:phone":"+1 916 361 9186",
    "sg:postcode":"95670",
    "sg:province":"CA",
    "sg:tags":[
        "casino"
    ],
    "wof:name":"Rancho's Club",
    "wof:placetype":"venue"
},
  "geometry": {"coordinates":[-121.29736800000001,38.592708],"type":"Point"}
}