{
  "type": "Feature",
  "properties": {
    "iso:country":"US",
    "sg:address":"2639 Terminal Blvd",
    "sg:city":"Mountain View",
    "sg:classifiers":[
        {
            "category":"Recreation",
            "type":"Entertainment"
        }
    ],
    "sg:phone":"+1 650 940 1824",
    "sg:postcode":"94043",
    "sg:province":"CA",
    "sg:tags":[
        "club",
        "bridge"
    ],
    "wof:name":"Bridge Club",
    "wof:placetype":"venue"
},
  "geometry": {"coordinates":[-122.098771,37.433429],"type":"Point"}
}