{
  "type": "Feature",
  "properties": {
    "iso:country":"US",
    "sg:address":"150 S Juanita St",
    "sg:city":"Hemet",
    "sg:classifiers":[
        {
            "category":"Utilities",
            "subcategory":"Telephone",
            "type":"Services"
        }
    ],
    "sg:phone":"+1 951 929 9494",
    "sg:postcode":"92543",
    "sg:province":"CA",
    "sg:tags":[
        "communication",
        "telecommunication"
    ],
    "sg:website":"http://www.gte.com",
    "wof:name":"Verizon",
    "wof:placetype":"venue"
},
  "geometry": {"coordinates":[-116.968414,33.746607],"type":"Point"}
}