{
  "type": "Feature",
  "properties": {
    "addr:full":"911 Moraga Rd Lafayette CA 94549",
    "addr:housenumber":"911",
    "addr:postcode":"94549",
    "addr:street":"Moraga Rd",
    "iso:country":"US",
    "sg:address":"911 Moraga Rd",
    "sg:city":"Lafayette",
    "sg:classifiers":[
        {
            "category":"Health Services",
            "subcategory":"Medical Lab",
            "type":"Services"
        }
    ],
    "sg:phone":"+1 866 322 7154",
    "sg:postcode":"94549",
    "sg:province":"CA",
    "wof:name":"STD Tests Lafayette STD Testing Center",
    "wof:placetype":"venue"
},
  "geometry": {"coordinates":[-122.11811400000001,37.887565],"type":"Point"}
}