{
  "type": "Feature",
  "properties": {
    "iso:country":"US",
    "sg:address":"5901 Christie Ave",
    "sg:city":"Emeryville",
    "sg:classifiers":[
        {
            "category":"Professional",
            "subcategory":"Management & Consulting",
            "type":"Services"
        }
    ],
    "sg:phone":"+1 510 652 8000",
    "sg:postcode":"94608",
    "sg:province":"CA",
    "sg:tags":[
        "consultant",
        "construction"
    ],
    "sg:website":"www.lovett-silverman.com",
    "wof:name":"L Silverman Constr Conslnt",
    "wof:placetype":"venue"
},
  "geometry": {"coordinates":[-122.294989,37.839424],"type":"Point"}
}