{
  "type": "Feature",
  "properties": {
    "addr:full":"823 Maple Avenue Los Angeles CA 90014",
    "addr:housenumber":"823",
    "addr:postcode":"90014",
    "addr:street":"Maple Avenue",
    "iso:country":"US",
    "sg:address":"823 Maple Avenue",
    "sg:city":"Los Angeles",
    "sg:classifiers":[
        {
            "category":"Shopping",
            "subcategory":"Crafts & Fabrics",
            "type":"Retail Goods"
        }
    ],
    "sg:phone":"+1 213 623 1192",
    "sg:postcode":"90014",
    "sg:province":"CA",
    "sg:tags":[
        "art",
        "supply"
    ],
    "wof:name":"Pics Craft Outlet",
    "wof:placetype":"venue"
},
  "geometry": {"coordinates":[-118.25163000000001,34.040497],"type":"Point"}
}