{
  "type": "Feature",
  "properties": {
    "addr:full":"245 MacArthur Blvd San Leandro CA 94577",
    "addr:housenumber":"245",
    "addr:postcode":"94577",
    "addr:street":"Macarthur Blvd",
    "iso:country":"US",
    "sg:address":"245 MacArthur Blvd",
    "sg:city":"San Leandro",
    "sg:classifiers":[
        {
            "category":"Real Estate",
            "subcategory":"Real Estate Services",
            "type":"Services"
        }
    ],
    "sg:phone":"+1 510 729 8555",
    "sg:postcode":"94577",
    "sg:province":"CA",
    "sg:tags":[
        "management",
        "property"
    ],
    "wof:name":"Affiliated Brokers",
    "wof:placetype":"venue"
},
  "geometry": {"coordinates":[-122.148461,37.740621],"type":"Point"}
}