{
  "type": "Feature",
  "properties": {
    "iso:country":"US",
    "sg:address":"37488 Willowood Dr",
    "sg:city":"Fremont",
    "sg:classifiers":[
        {
            "category":"Real Estate",
            "subcategory":"Real Estate Agent",
            "type":"Services"
        }
    ],
    "sg:phone":"+1 510 657 5700",
    "sg:postcode":"94536",
    "sg:province":"CA",
    "wof:name":"Goulart Group & Assoc",
    "wof:placetype":"venue"
},
  "geometry": {"coordinates":[-122.011706,37.549047],"type":"Point"}
}