{
  "type": "Feature",
  "properties": {
    "addr:full":"425 Market St San Francisco CA 94105",
    "addr:housenumber":"425",
    "addr:postcode":"94105",
    "addr:street":"Market St",
    "iso:country":"US",
    "sg:address":"425 Market St",
    "sg:city":"San Francisco",
    "sg:classifiers":[
        {
            "category":"Professional",
            "subcategory":"Lawyer & Legal Services",
            "type":"Services"
        }
    ],
    "sg:phone":"+1 415 268 7000",
    "sg:postcode":"94105",
    "sg:province":"CA",
    "sg:tags":[
        "attorney"
    ],
    "sg:website":"www.mofo.com",
    "wof:name":"Morrison and Foerster Llp",
    "wof:placetype":"venue"
},
  "geometry": {"coordinates":[-122.398579,37.791529],"type":"Point"}
}