{
  "type": "Feature",
  "properties": {
    "iso:country":"US",
    "sg:address":"3354 San Pablo Ave",
    "sg:city":"Emeryville",
    "sg:classifiers":[
        {
            "category":"Freight",
            "type":"Transportation"
        }
    ],
    "sg:phone":"+1 510 595 9895",
    "sg:postcode":"94608",
    "sg:province":"CA",
    "sg:tags":[
        "operator",
        "local",
        "trucking"
    ],
    "wof:name":"Agape Trucking Co",
    "wof:placetype":"venue"
},
  "geometry": {"coordinates":[-122.278051,37.825293],"type":"Point"}
}