{
  "type": "Feature",
  "properties": {
    "iso:country":"US",
    "sg:address":"69 W Putnam Ave",
    "sg:city":"Porterville",
    "sg:classifiers":[
        {
            "category":"Manufacturing",
            "subcategory":"Printing",
            "type":"Manufacturing & Wholesale Goods"
        }
    ],
    "sg:phone":"+1 559 782 5681",
    "sg:postcode":"93257",
    "sg:province":"CA",
    "sg:tags":[
        "publisher",
        "guide"
    ],
    "wof:name":"Dean-Barrett Publishing",
    "wof:placetype":"venue"
},
  "geometry": {"coordinates":[-119.017832,36.069547],"type":"Point"}
}