{
  "type": "Feature",
  "properties": {
    "iso:country":"US",
    "sg:address":"25855 Rancho Alto",
    "sg:city":"Carmel",
    "sg:classifiers":[
        {
            "category":"Professional",
            "subcategory":"Lawyer & Legal Services",
            "type":"Services"
        }
    ],
    "sg:phone":"+1 831 626 0950",
    "sg:postcode":"93923",
    "sg:province":"CA",
    "sg:tags":[
        "attorney"
    ],
    "wof:name":"Paul W Baker Law Offices",
    "wof:placetype":"venue"
},
  "geometry": {"coordinates":[-121.808754,36.525243],"type":"Point"}
}