{
  "type": "Feature",
  "properties": {
    "addr:full":"107 San Jose Ave San Jose CA 95125",
    "addr:housenumber":"107",
    "addr:postcode":"95125",
    "addr:street":"San Jose Ave",
    "iso:country":"US",
    "sg:address":"107 San Jose Ave",
    "sg:city":"San Jose",
    "sg:classifiers":[
        {
            "category":"Arts & Performance",
            "subcategory":"Arts Center",
            "type":"Entertainment"
        }
    ],
    "sg:phone":"+1 408 990 6677",
    "sg:postcode":"95125",
    "sg:province":"CA",
    "sg:tags":[
        "performing"
    ],
    "sg:website":"www.californiapuppets.com",
    "wof:name":"Jungle Joe",
    "wof:placetype":"venue"
},
  "geometry": {"coordinates":[-121.872366,37.311144],"type":"Point"}
}