{
  "type": "Feature",
  "properties": {
    "iso:country":"US",
    "sg:address":"650 Town Center Drive",
    "sg:city":"Costa Mesa",
    "sg:classifiers":[
        {
            "category":"Professional",
            "subcategory":"Lawyer & Legal Services",
            "type":"Services"
        }
    ],
    "sg:phone":"+1 714 540 1235",
    "sg:postcode":"92626",
    "sg:province":"CA",
    "wof:name":"Pettis Alan W",
    "wof:placetype":"venue"
},
  "geometry": {"coordinates":[-117.883014,33.69257],"type":"Point"}
}