{
  "type": "Feature",
  "properties": {
    "addr:full":"44105 15th St W Lancaster CA 93534",
    "addr:housenumber":"44105",
    "addr:postcode":"93534",
    "addr:street":"15Th St W",
    "iso:country":"US",
    "sg:address":"44105 15th St W",
    "sg:city":"Lancaster",
    "sg:classifiers":[
        {
            "category":"Health Services",
            "subcategory":"Doctor",
            "type":"Services"
        }
    ],
    "sg:phone":"+1 661 949 8643",
    "sg:postcode":"93534",
    "sg:province":"CA",
    "sg:tags":[
        "physician",
        "surgeon"
    ],
    "sg:website":"http://www.valleyorthoinstitute.com",
    "wof:name":"Valley Orthopedic Institute",
    "wof:placetype":"venue"
},
  "geometry": {"coordinates":[-118.156837,34.684113],"type":"Point"}
}