{
  "type": "Feature",
  "properties": {
    "iso:country":"US",
    "sg:address":"1200 Woodrow Ave",
    "sg:city":"Modesto",
    "sg:classifiers":[
        {
            "category":"Personal",
            "subcategory":"Beauty Salon",
            "type":"Services"
        }
    ],
    "sg:phone":"+1 209 527 6154",
    "sg:postcode":"95350",
    "sg:province":"CA",
    "wof:name":"Neighborhood Manor Beauty Sln",
    "wof:placetype":"venue"
},
  "geometry": {"coordinates":[-121.010139,37.685616],"type":"Point"}
}