{
  "type": "Feature",
  "properties": {
    "addr:full":"43176 Bus Park Dr Temecula CA 92590",
    "addr:postcode":"43176;92590",
    "addr:street":"Bus Park Dr",
    "iso:country":"US",
    "sg:address":"43176 Bus Park Dr",
    "sg:city":"Temecula",
    "sg:classifiers":[
        {
            "category":"Utilities",
            "subcategory":"Water",
            "type":"Services"
        }
    ],
    "sg:phone":"+1 951 587 6779",
    "sg:postcode":"92590",
    "sg:province":"CA",
    "sg:tags":[
        "supply"
    ],
    "wof:name":"Kurita America Inc",
    "wof:placetype":"venue"
},
  "geometry": {"coordinates":[-117.166826,33.502545],"type":"Point"}
}