{
  "type": "Feature",
  "properties": {
    "addr:full":"2755 Mission Rancheria Rd Lakeport CA 95453",
    "addr:housenumber":"2755",
    "addr:postcode":"95453",
    "addr:street":"Mission Rancheria Rd",
    "iso:country":"US",
    "sg:address":"2755 Mission Rancheria Rd",
    "sg:city":"Lakeport",
    "sg:classifiers":[
        {
            "category":"Professional",
            "type":"Services"
        }
    ],
    "sg:phone":"+1 707 262 0583",
    "sg:postcode":"95453",
    "sg:province":"CA",
    "sg:tags":[
        "establishment"
    ],
    "wof:name":"Corn Data Network",
    "wof:placetype":"venue"
},
  "geometry": {"coordinates":[-122.887457,39.015121],"type":"Point"}
}