{
  "type": "Feature",
  "properties": {
    "addr:full":"1776 Bowers Ave Santa Clara CA 95051",
    "addr:housenumber":"1776",
    "addr:postcode":"95051",
    "addr:street":"Bowers Ave",
    "iso:country":"US",
    "sg:address":"1776 Bowers Ave",
    "sg:city":"Santa Clara",
    "sg:classifiers":[
        {
            "category":"Building & Trades",
            "subcategory":"Construction",
            "type":"Services"
        }
    ],
    "sg:phone":"+1 408 246 1900",
    "sg:postcode":"95051",
    "sg:province":"CA",
    "sg:tags":[
        "painter"
    ],
    "wof:name":"Smart Painting",
    "wof:placetype":"venue"
},
  "geometry": {"coordinates":[-121.97765,37.354172],"type":"Point"}
}