{
  "type": "Feature",
  "properties": {
    "addr:full":"1627 16th St Sacramento CA 95814",
    "addr:housenumber":"1627",
    "addr:postcode":"95814",
    "addr:street":"16Th St",
    "iso:country":"US",
    "sg:address":"1627 16th St",
    "sg:city":"Sacramento",
    "sg:classifiers":[
        {
            "category":"Restaurant",
            "type":"Food & Drink"
        }
    ],
    "sg:phone":"+1 916 444 3000",
    "sg:postcode":"95814",
    "sg:province":"CA",
    "sg:tags":[
        "pizza"
    ],
    "sg:website":"www.hotitalian.net",
    "wof:name":"Hot Italian",
    "wof:placetype":"venue"
},
  "geometry": {"coordinates":[-121.48828,38.570989],"type":"Point"}
}