{
  "type": "Feature",
  "properties": {
    "iso:country":"US",
    "sg:address":"6404 Wilshire Blvd Ste 1100",
    "sg:city":"Los Angeles",
    "sg:classifiers":[
        {
            "category":"Insurance",
            "subcategory":"Hazard Insurance",
            "type":"Services"
        }
    ],
    "sg:phone":"+1 323 782 0777",
    "sg:postcode":"90048",
    "sg:province":"CA",
    "sg:website":"www.mis-insurance.com",
    "wof:name":"M I S Insurance Services",
    "wof:placetype":"venue"
},
  "geometry": {"coordinates":[-118.368576,34.063412],"type":"Point"}
}