{
  "type": "Feature",
  "properties": {
    "addr:full":"331 Judah St San Francisco CA 94122",
    "addr:housenumber":"331",
    "addr:postcode":"94122",
    "addr:street":"Judah St",
    "iso:country":"US",
    "sg:address":"331 Judah St",
    "sg:city":"San Francisco",
    "sg:classifiers":[
        {
            "category":"Government",
            "subcategory":"Office",
            "type":"Public Place"
        }
    ],
    "sg:phone":"+1 415 665 5024",
    "sg:postcode":"94122",
    "sg:province":"CA",
    "sg:tags":[
        "management"
    ],
    "wof:name":"CER",
    "wof:placetype":"venue"
},
  "geometry": {"coordinates":[-122.465919,37.762115],"type":"Point"}
}