{
  "type": "Feature",
  "properties": {
    "addr:full":"14104 Towne Ave Los Angeles CA 90061",
    "addr:housenumber":"14104",
    "addr:postcode":"90061",
    "addr:street":"Towne Ave",
    "iso:country":"US",
    "sg:address":"14104 Towne Ave",
    "sg:city":"Los Angeles",
    "sg:classifiers":[
        {
            "category":"Manufacturing",
            "subcategory":"Rubber & Plastics",
            "type":"Manufacturing & Wholesale Goods"
        }
    ],
    "sg:phone":"+1 310 515 7102",
    "sg:postcode":"90061",
    "sg:province":"CA",
    "sg:tags":[
        "insulation",
        "roofing",
        "product",
        "foam",
        "mfg"
    ],
    "wof:name":"Falcon Foam",
    "wof:placetype":"venue"
},
  "geometry": {"coordinates":[-118.267381,33.901989],"type":"Point"}
}