{
  "type": "Feature",
  "properties": {
    "iso:country":"US",
    "sg:address":"1122 19th St",
    "sg:city":"Sacramento",
    "sg:classifiers":[
        {
            "category":"Shopping",
            "subcategory":"Clothing, Apparel, & Fashions",
            "type":"Retail Goods"
        },
        {
            "category":"Personal",
            "subcategory":"Beauty Salon",
            "type":"Services"
        }
    ],
    "sg:phone":"+1 916 441 4270",
    "sg:postcode":"95811",
    "sg:province":"CA",
    "sg:tags":[
        "hair",
        "clothing",
        "women's"
    ],
    "sg:website":"www.faceitsalonandspa.com",
    "wof:name":"Face It Salon, Spa & Boutique",
    "wof:placetype":"venue"
},
  "geometry": {"coordinates":[-121.481838,38.57571],"type":"Point"}
}