{
  "type": "Feature",
  "properties": {
    "addr:full":"807 Washington St Oakland CA 94607",
    "addr:housenumber":"807",
    "addr:postcode":"94607",
    "addr:street":"Washington St",
    "iso:country":"US",
    "sg:address":"807 Washington St",
    "sg:city":"Oakland",
    "sg:classifiers":[
        {
            "category":"Personal",
            "subcategory":"Barber",
            "type":"Services"
        }
    ],
    "sg:phone":"+1 510 444 0992",
    "sg:postcode":"94607",
    "sg:province":"CA",
    "wof:name":"Director's Cut",
    "wof:placetype":"venue"
},
  "geometry": {"coordinates":[-122.27469499999999,37.801365],"type":"Point"}
}