{
  "type": "Feature",
  "properties": {
    "iso:country":"US",
    "sg:address":"4400 Saltillo Street",
    "sg:city":"Los Angeles",
    "sg:classifiers":[
        {
            "category":"Arts & Performance",
            "subcategory":"Arts Center",
            "type":"Entertainment"
        }
    ],
    "sg:postcode":"91364",
    "sg:province":"CA",
    "sg:website":"houseathauntedhill.com/",
    "wof:name":"The House At Haunted Hill",
    "wof:placetype":"venue"
},
  "geometry": {"coordinates":[-118.59432200000001,34.149731],"type":"Point"}
}