{
  "type": "Feature",
  "properties": {
    "iso:country":"US",
    "sg:address":"1535 J St Ste B",
    "sg:city":"Modesto",
    "sg:classifiers":[
        {
            "category":"Real Estate",
            "subcategory":"Real Estate Services",
            "type":"Services"
        }
    ],
    "sg:phone":"+1 209 569 0887",
    "sg:postcode":"95354",
    "sg:province":"CA",
    "sg:tags":[
        "management",
        "property"
    ],
    "wof:name":"Genesis Family Enterprises",
    "wof:placetype":"venue"
},
  "geometry": {"coordinates":[-120.99529099999999,37.644446],"type":"Point"}
}