{
  "type": "Feature",
  "properties": {
    "iso:country":"US",
    "sg:address":"3505 Sports Arena Blvd",
    "sg:city":"San Diego",
    "sg:classifiers":[
        {
            "category":"Cinema",
            "subcategory":"Movie Rental",
            "type":"Entertainment"
        }
    ],
    "sg:phone":"+1 619 523 9490",
    "sg:postcode":"92110",
    "sg:province":"CA",
    "sg:tags":[
        "leasing",
        "video",
        "disc",
        "tape"
    ],
    "sg:website":"www.hollywoodvideo.com",
    "wof:name":"Hollywood Video",
    "wof:placetype":"venue"
},
  "geometry": {"coordinates":[-117.213244,32.753849],"type":"Point"}
}