{
  "type": "Feature",
  "properties": {
    "addr:full":"708 Newmark Mall Montebello CA 90640",
    "addr:housenumber":"708",
    "addr:postcode":"90640",
    "addr:street":"Newmark Mall",
    "iso:country":"US",
    "sg:address":"708 Newmark Mall",
    "sg:city":"Montebello",
    "sg:classifiers":[
        {
            "category":"Home & Garden",
            "subcategory":"Household Appliances",
            "type":"Retail Goods"
        }
    ],
    "sg:phone":"+1 323 728 0541",
    "sg:postcode":"90640",
    "sg:province":"CA",
    "sg:tags":[
        "machine",
        "sewing"
    ],
    "wof:name":"Montebello Sewing Ctr",
    "wof:placetype":"venue"
},
  "geometry": {"coordinates":[-118.10691,34.010393],"type":"Point"}
}