{
  "type": "Feature",
  "properties": {
    "addr:full":"2076 San Gabriel Ave Clovis CA 93611",
    "addr:housenumber":"2076",
    "addr:postcode":"93611",
    "addr:street":"San Gabriel Ave",
    "iso:country":"US",
    "sg:address":"2076 San Gabriel Ave",
    "sg:city":"Clovis",
    "sg:classifiers":[
        {
            "category":"Professional",
            "subcategory":"Computer Services",
            "type":"Services"
        }
    ],
    "sg:phone":"+1 559 294 8831",
    "sg:postcode":"93611",
    "sg:province":"CA",
    "sg:tags":[
        "consultant",
        "designer"
    ],
    "wof:name":"R & W Software",
    "wof:placetype":"venue"
},
  "geometry": {"coordinates":[-119.675995,36.803411],"type":"Point"}
}