{
  "type": "Feature",
  "properties": {
    "iso:country":"US",
    "sg:address":"3277 Main St",
    "sg:city":"Napa",
    "sg:classifiers":[
        {
            "category":"Building & Trades",
            "subcategory":"Equipment Rental",
            "type":"Services"
        }
    ],
    "sg:phone":"+1 707 251 9217",
    "sg:postcode":"94558",
    "sg:province":"CA",
    "sg:tags":[
        "audio",
        "leasing"
    ],
    "wof:name":"Napa Valley Audio Visual",
    "wof:placetype":"venue"
},
  "geometry": {"coordinates":[-122.297449,38.322462],"type":"Point"}
}