{
  "type": "Feature",
  "properties": {
    "addr:full":"5000 W Keyes Rd Modesto CA 95358",
    "addr:housenumber":"5000",
    "addr:postcode":"ca 95358",
    "addr:street":"W Keyes Rd",
    "iso:country":"US",
    "sg:address":"5000 W Keyes Rd",
    "sg:city":"Modesto",
    "sg:classifiers":[
        {
            "category":"Farming",
            "subcategory":"Farm",
            "type":"Manufacturing & Wholesale Goods"
        }
    ],
    "sg:phone":"+1 209 537 2939",
    "sg:postcode":"95358",
    "sg:province":"CA",
    "wof:name":"Alamo Farms",
    "wof:placetype":"venue"
},
  "geometry": {"coordinates":[-121.078114,37.551335],"type":"Point"}
}