{
  "type": "Feature",
  "properties": {
    "addr:full":"2275 la Crosse Ave # 206 Colton CA 92324",
    "addr:housenumber":"2275",
    "addr:postcode":"92324",
    "addr:street":"La Crosse Ave # 206",
    "iso:country":"US",
    "sg:address":"2275 la Crosse Ave # 206",
    "sg:city":"Colton",
    "sg:classifiers":[
        {
            "category":"Real Estate",
            "subcategory":"Real Estate Services",
            "type":"Services"
        },
        {
            "category":"Real Estate",
            "subcategory":"Real Estate Agent",
            "type":"Services"
        }
    ],
    "sg:phone":"+1 909 783 1525",
    "sg:postcode":"92324",
    "sg:province":"CA",
    "sg:tags":[
        "buyer",
        "broker"
    ],
    "wof:name":"Crown Real Estate Services",
    "wof:placetype":"venue"
},
  "geometry": {"coordinates":[-117.329385,34.030324],"type":"Point"}
}