{
  "type": "Feature",
  "properties": {
    "addr:full":"485 6th St Hollister CA 95023",
    "addr:housenumber":"485",
    "addr:postcode":"hollister ca 95023",
    "addr:street":"6Th St",
    "iso:country":"US",
    "sg:address":"485 6th St",
    "sg:city":"Hollister",
    "sg:classifiers":[
        {
            "category":"Building & Trades",
            "subcategory":"Plumbing",
            "type":"Services"
        }
    ],
    "sg:phone":"+1 831 635 0687",
    "sg:postcode":"95023",
    "sg:province":"CA",
    "sg:tags":[
        "conditioning",
        "air",
        "system",
        "contractor"
    ],
    "wof:name":"Rescue Heating & Air Cond",
    "wof:placetype":"venue"
},
  "geometry": {"coordinates":[-121.40450300000001,36.850371],"type":"Point"}
}