{
  "type": "Feature",
  "properties": {
    "iso:country":"US",
    "sg:address":"1485 Pomona Rd",
    "sg:city":"Corona",
    "sg:classifiers":[
        {
            "category":"Building & Trades",
            "subcategory":"Construction",
            "type":"Services"
        }
    ],
    "sg:phone":"+1 951 279 4303",
    "sg:postcode":"92882",
    "sg:province":"CA",
    "sg:tags":[
        "repairing",
        "remodeling",
        "contractor"
    ],
    "wof:name":"Loft Masters",
    "wof:placetype":"venue"
},
  "geometry": {"coordinates":[-117.59742,33.881397],"type":"Point"}
}