{
  "type": "Feature",
  "properties": {
    "addr:full":"45612 San Gabriel St Indio CA 92201",
    "addr:postcode":"45612;92201",
    "addr:street":"San Gabriel St",
    "iso:country":"US",
    "sg:address":"45612 San Gabriel St",
    "sg:city":"Indio",
    "sg:classifiers":[
        {
            "category":"Home & Garden",
            "subcategory":"Building Materials",
            "type":"Retail Goods"
        }
    ],
    "sg:phone":"+1 760 345 7884",
    "sg:postcode":"92201",
    "sg:province":"CA",
    "sg:tags":[
        "shutter"
    ],
    "wof:name":"Shutters By Ruth",
    "wof:placetype":"venue"
},
  "geometry": {"coordinates":[-116.24082900000001,33.717587],"type":"Point"}
}