{
  "type": "Feature",
  "properties": {
    "addr:full":"1200 Gough St San Francisco CA 94109",
    "addr:housenumber":"1200",
    "addr:postcode":"94109",
    "addr:street":"Gough St",
    "iso:country":"US",
    "sg:address":"1200 Gough St",
    "sg:city":"San Francisco",
    "sg:classifiers":[
        {
            "category":"Professional",
            "subcategory":"Research",
            "type":"Services"
        }
    ],
    "sg:phone":"+1 415 775 9956",
    "sg:postcode":"94109",
    "sg:province":"CA",
    "sg:tags":[
        "foundation",
        "philanthropic"
    ],
    "wof:name":"Regional Cancer Foundation",
    "wof:placetype":"venue"
},
  "geometry": {"coordinates":[-122.42468700000001,37.785335],"type":"Point"}
}