{
  "type": "Feature",
  "properties": {
    "iso:country":"US",
    "sg:address":"8101 Grandstaff Dr",
    "sg:city":"Sacramento",
    "sg:classifiers":[
        {
            "category":"Education",
            "subcategory":"School",
            "type":"Public Place"
        }
    ],
    "sg:phone":"+1 916 689 2120",
    "sg:postcode":"95823",
    "sg:province":"CA",
    "sg:tags":[
        "elementary"
    ],
    "wof:name":"Elk Grove Unified School District",
    "wof:placetype":"venue"
},
  "geometry": {"coordinates":[-121.42385899999999,38.463268],"type":"Point"}
}