{
  "type": "Feature",
  "properties": {
    "addr:full":"316 E Pico Boulevard Los Angeles CA 90015",
    "addr:housenumber":"316",
    "addr:postcode":"90015",
    "addr:street":"E Pico Boulevard",
    "iso:country":"US",
    "sg:address":"316 E Pico Boulevard",
    "sg:city":"Los Angeles",
    "sg:classifiers":[
        {
            "category":"Restaurant",
            "type":"Food & Drink"
        }
    ],
    "sg:phone":"+1 213 742 8888",
    "sg:postcode":"90015",
    "sg:province":"CA",
    "wof:name":"Cohen Restaurant",
    "wof:placetype":"venue"
},
  "geometry": {"coordinates":[-118.258126,34.035021],"type":"Point"}
}