{
  "type": "Feature",
  "properties": {
    "iso:country":"US",
    "sg:address":"2202 S Shore Ctr Ste F",
    "sg:city":"Alameda",
    "sg:classifiers":[
        {
            "category":"Health Services",
            "subcategory":"Optometrist",
            "type":"Services"
        },
        {
            "category":"Shopping",
            "subcategory":"Optician",
            "type":"Retail Goods"
        }
    ],
    "sg:phone":"+1 510 521 2734",
    "sg:postcode":"94501",
    "sg:province":"CA",
    "sg:tags":[
        "eyewear"
    ],
    "wof:name":"LensCrafters",
    "wof:placetype":"venue"
},
  "geometry": {"coordinates":[-122.253962,37.757213],"type":"Point"}
}