{
  "type": "Feature",
  "properties": {
    "iso:country":"US",
    "sg:address":"374 Industrial Way",
    "sg:city":"Brisbane",
    "sg:classifiers":[
        {
            "category":"Retail",
            "subcategory":"Auto Repair",
            "type":"Services"
        }
    ],
    "sg:phone":"+1 415 467 7290",
    "sg:postcode":"94005",
    "sg:province":"CA",
    "sg:tags":[
        "truck"
    ],
    "wof:name":"L & D Truck & Equipment Repair Inc",
    "wof:placetype":"venue"
},
  "geometry": {"coordinates":[-122.405998,37.697399],"type":"Point"}
}