{
  "type": "Feature",
  "properties": {
    "iso:country":"US",
    "sg:address":"1332 Socorro Ave",
    "sg:city":"Sunnyvale",
    "sg:classifiers":[
        {
            "category":"Retail",
            "subcategory":"Portrait Studio",
            "type":"Services"
        },
        {
            "category":"Professional",
            "subcategory":"Art Services",
            "type":"Services"
        }
    ],
    "sg:phone":"+1 408 773 1190",
    "sg:postcode":"94089",
    "sg:province":"CA",
    "sg:tags":[
        "photographer",
        "photography",
        "store"
    ],
    "sg:website":"www.sunnyvalephotostudio.com",
    "wof:name":"Sunnyvale Photo Studio",
    "wof:placetype":"venue"
},
  "geometry": {"coordinates":[-121.988446,37.391579],"type":"Point"}
}