{
  "type": "Feature",
  "properties": {
    "addr:full":"3505 Gateway Rd Bethel Island CA 94561",
    "addr:housenumber":"3505",
    "addr:postcode":"94561",
    "addr:street":"Gateway Rd",
    "iso:country":"US",
    "sg:address":"3505 Gateway Rd",
    "sg:city":"Bethel Island",
    "sg:classifiers":[
        {
            "category":"Travel",
            "subcategory":"Campground",
            "type":"Entertainment"
        }
    ],
    "sg:phone":"+1 925 684 2144",
    "sg:postcode":"94561",
    "sg:province":"CA",
    "wof:name":"Island Park",
    "wof:placetype":"venue"
},
  "geometry": {"coordinates":[-121.640563,38.019565],"type":"Point"}
}