{
  "type": "Feature",
  "properties": {
    "addr:full":"3370 Samuel Pl Santa Cruz CA 95062",
    "addr:housenumber":"3370",
    "addr:postcode":"95062",
    "addr:street":"Samuel Pl",
    "iso:country":"US",
    "sg:address":"3370 Samuel Pl",
    "sg:city":"Santa Cruz",
    "sg:classifiers":[
        {
            "category":"Building & Trades",
            "subcategory":"Landscaping Services",
            "type":"Services"
        }
    ],
    "sg:phone":"+1 831 462 4988",
    "sg:postcode":"95062",
    "sg:province":"CA",
    "sg:tags":[
        "designer",
        "landscape"
    ],
    "wof:name":"Arnone Landscape Architecture",
    "wof:placetype":"venue"
},
  "geometry": {"coordinates":[-121.972077,36.975402],"type":"Point"}
}