{
  "type": "Feature",
  "properties": {
    "addr:full":"130 Woodward Ave Escondido CA 92025",
    "addr:housenumber":"130",
    "addr:postcode":"92025",
    "addr:street":"Woodward Ave",
    "iso:country":"US",
    "sg:address":"130 Woodward Ave",
    "sg:city":"Escondido",
    "sg:classifiers":[
        {
            "category":"Recreation",
            "type":"Entertainment"
        }
    ],
    "sg:phone":"+1 760 743 9473",
    "sg:postcode":"92025",
    "sg:province":"CA",
    "sg:tags":[
        "parks"
    ],
    "wof:name":"Grape Day Park",
    "wof:placetype":"venue"
},
  "geometry": {"coordinates":[-117.084475,33.125568],"type":"Point"}
}