{
  "type": "Feature",
  "properties": {
    "iso:country":"US",
    "sg:address":"201 E 74th St",
    "sg:city":"Los Angeles",
    "sg:classifiers":[
        {
            "category":"Building & Trades",
            "subcategory":"Construction",
            "type":"Services"
        }
    ],
    "sg:phone":"+1 323 971 0358",
    "sg:postcode":"90003",
    "sg:province":"CA",
    "sg:tags":[
        "residential"
    ],
    "wof:name":"Luis Navarro",
    "wof:placetype":"venue"
},
  "geometry": {"coordinates":[-118.27137500000001,33.973061],"type":"Point"}
}