{
  "type": "Feature",
  "properties": {
    "iso:country":"US",
    "sg:address":"4910 3rd St",
    "sg:city":"San Francisco",
    "sg:classifiers":[
        {
            "category":"Professional",
            "type":"Services"
        }
    ],
    "sg:phone":"+1 415 822 7713",
    "sg:postcode":"94124",
    "sg:province":"CA",
    "wof:name":"99 On 3 Street",
    "wof:placetype":"venue"
},
  "geometry": {"coordinates":[-122.391328,37.7333],"type":"Point"}
}