{
  "type": "Feature",
  "properties": {
    "addr:full":"1305 Ollie Ave Calexico CA 92231",
    "addr:housenumber":"1305",
    "addr:postcode":"92231",
    "addr:street":"Ollie Ave",
    "iso:country":"US",
    "sg:address":"1305 Ollie Ave",
    "sg:city":"Calexico",
    "sg:classifiers":[
        {
            "category":"Shopping",
            "subcategory":"Used Merchandise",
            "type":"Retail Goods"
        }
    ],
    "sg:phone":"+1 760 357 1510",
    "sg:postcode":"92231",
    "sg:province":"CA",
    "sg:tags":[
        "shop",
        "meet",
        "swap"
    ],
    "wof:name":"El Remate Inc",
    "wof:placetype":"venue"
},
  "geometry": {"coordinates":[-115.502455,32.682408],"type":"Point"}
}