{
  "type": "Feature",
  "properties": {
    "addr:full":"3790 Via De La Valle Ste 313 San Diego CA 92014",
    "addr:housenumber":"3790",
    "addr:postcode":"92014",
    "addr:street":"Via De La Valle Ste 313",
    "iso:country":"US",
    "sg:address":"3790 Via De La Valle Ste 313",
    "sg:city":"San Diego",
    "sg:classifiers":[
        {
            "category":"Professional",
            "subcategory":"Lawyer & Legal Services",
            "type":"Services"
        }
    ],
    "sg:phone":"+1 619 696 6200",
    "sg:postcode":"92014",
    "sg:province":"CA",
    "wof:name":"Rechs Randall C Law Offices of",
    "wof:placetype":"venue"
},
  "geometry": {"coordinates":[-117.22895800000001,32.98294],"type":"Point"}
}