{
  "type": "Feature",
  "properties": {
    "addr:full":"30331 Whipple Rd Union City CA 94587",
    "addr:postcode":"30331;94587",
    "addr:street":"Whipple Rd",
    "iso:country":"US",
    "sg:address":"30331 Whipple Rd",
    "sg:city":"Union City",
    "sg:classifiers":[
        {
            "category":"Wholesale",
            "subcategory":"Non-durable Goods",
            "type":"Manufacturing & Wholesale Goods"
        }
    ],
    "sg:phone":"+1 510 441 0135",
    "sg:postcode":"94587",
    "sg:province":"CA",
    "sg:tags":[
        "pet",
        "supply"
    ],
    "wof:name":"Premium Pet Foods",
    "wof:placetype":"venue"
},
  "geometry": {"coordinates":[-122.084625,37.605724],"type":"Point"}
}