{
  "type": "Feature",
  "properties": {
    "addr:full":"18653 Ventura Blvd Tarzana CA 91356",
    "addr:housenumber":"18653",
    "addr:postcode":"91356",
    "addr:street":"Ventura Blvd",
    "iso:country":"US",
    "sg:address":"18653 Ventura Blvd",
    "sg:city":"Tarzana",
    "sg:classifiers":[
        {
            "category":"Banks & Credit Unions",
            "subcategory":"Bank",
            "type":"Services"
        }
    ],
    "sg:phone":"+1 818 882 3788",
    "sg:postcode":"91356",
    "sg:province":"CA",
    "sg:tags":[
        "loan",
        "real estate"
    ],
    "wof:name":"Mortgage World",
    "wof:placetype":"venue"
},
  "geometry": {"coordinates":[-118.538961,34.169946],"type":"Point"}
}