{
  "type": "Feature",
  "properties": {
    "addr:full":"733 56th St Sacramento CA 95819",
    "addr:housenumber":"733",
    "addr:postcode":"95819",
    "addr:street":"56Th St",
    "iso:country":"US",
    "sg:address":"733 56th St",
    "sg:city":"Sacramento",
    "sg:classifiers":[
        {
            "category":"Home & Garden",
            "subcategory":"Garden Supply",
            "type":"Retail Goods"
        }
    ],
    "sg:phone":"+1 916 736 9622",
    "sg:postcode":"95819",
    "sg:province":"CA",
    "sg:tags":[
        "nursery",
        "gardening"
    ],
    "wof:name":"The Garden Gallery",
    "wof:placetype":"venue"
},
  "geometry": {"coordinates":[-121.433847,38.568099],"type":"Point"}
}