{
  "type": "Feature",
  "properties": {
    "iso:country":"US",
    "sg:address":"17492 Apex Cir",
    "sg:city":"Huntington Beach",
    "sg:classifiers":[
        {
            "category":"Professional",
            "type":"Services"
        }
    ],
    "sg:phone":"+1 714 596 2900",
    "sg:postcode":"92647",
    "sg:province":"CA",
    "wof:name":"Delaware Office Works",
    "wof:placetype":"venue"
},
  "geometry": {"coordinates":[-117.997929,33.708473],"type":"Point"}
}