{
  "type": "Feature",
  "properties": {
    "iso:country":"US",
    "sg:address":"1089 Sierra Madre Dr",
    "sg:city":"Salinas",
    "sg:classifiers":[
        {
            "category":"Wholesale",
            "subcategory":"Vending Machines",
            "type":"Manufacturing & Wholesale Goods"
        }
    ],
    "sg:phone":"+1 831 422 4576",
    "sg:postcode":"93901",
    "sg:province":"CA",
    "sg:tags":[
        "broker"
    ],
    "wof:name":"Anna S Kamlan",
    "wof:placetype":"venue"
},
  "geometry": {"coordinates":[-121.674288,36.663422],"type":"Point"}
}