{
  "type": "Feature",
  "properties": {
    "iso:country":"US",
    "sg:address":"645 Haight Street",
    "sg:city":"San Francisco",
    "sg:classifiers":[
        {
            "category":"Arts & Performance",
            "subcategory":"Arts Center",
            "type":"Entertainment"
        }
    ],
    "sg:phone":"+1 415 308 1952",
    "sg:postcode":"94117",
    "sg:province":"CA",
    "sg:tags":[
        "performing"
    ],
    "sg:website":"www.capacitor.org",
    "wof:name":"Capacitor",
    "wof:placetype":"venue"
},
  "geometry": {"coordinates":[-122.432813,37.771518],"type":"Point"}
}