{
  "type": "Feature",
  "properties": {
    "addr:full":"1952 S Corning St Los Angeles CA 90034",
    "addr:housenumber":"1952",
    "addr:postcode":"90034",
    "addr:street":"S Corning St",
    "iso:country":"US",
    "sg:address":"1952 S Corning St",
    "sg:city":"Los Angeles",
    "sg:classifiers":[
        {
            "category":"Professional",
            "type":"Services"
        }
    ],
    "sg:phone":"+1 323 464 1794",
    "sg:postcode":"90034",
    "sg:province":"CA",
    "wof:name":"Guest 4 Tyme",
    "wof:placetype":"venue"
},
  "geometry": {"coordinates":[-118.379885,34.042106],"type":"Point"}
}