{
  "type": "Feature",
  "properties": {
    "addr:full":"13500 Victoria St Etiwanda CA 91739",
    "addr:housenumber":"13500",
    "addr:postcode":"91739",
    "addr:street":"Victoria St",
    "iso:country":"US",
    "sg:address":"13500 Victoria St",
    "sg:city":"Etiwanda",
    "sg:classifiers":[
        {
            "category":"Education",
            "subcategory":"School",
            "type":"Public Place"
        }
    ],
    "sg:phone":"+1 909 899 2531",
    "sg:postcode":"91739",
    "sg:province":"CA",
    "sg:website":"www.etiwanda.com",
    "wof:name":"Etiwanda High School",
    "wof:placetype":"venue"
},
  "geometry": {"coordinates":[-117.50913300000001,34.128374],"type":"Point"}
}