{
  "type": "Feature",
  "properties": {
    "addr:full":"870 Rancheros Dr San Marcos CA 92069",
    "addr:housenumber":"870",
    "addr:postcode":"92069",
    "addr:street":"Rancheros Dr",
    "iso:country":"US",
    "sg:address":"870 Rancheros Dr",
    "sg:city":"San Marcos",
    "sg:classifiers":[
        {
            "category":"Manufacturing",
            "subcategory":"Retail Goods",
            "type":"Manufacturing & Wholesale Goods"
        },
        {
            "category":"Manufacturing",
            "subcategory":"Electronics",
            "type":"Manufacturing & Wholesale Goods"
        }
    ],
    "sg:phone":"+1 760 432 8285",
    "sg:postcode":"92069",
    "sg:province":"CA",
    "sg:tags":[
        "assembly",
        "mfg",
        "research",
        "printed",
        "circuit",
        "fabricating",
        "physical"
    ],
    "wof:name":"A Squared Technologies",
    "wof:placetype":"venue"
},
  "geometry": {"coordinates":[-117.141558,33.14009],"type":"Point"}
}