{
  "type": "Feature",
  "properties": {
    "addr:full":"120 Cooper Rd Santa Barbara CA 93109",
    "addr:housenumber":"120",
    "addr:postcode":"93109",
    "addr:street":"Cooper Rd",
    "iso:country":"US",
    "sg:address":"120 Cooper Rd",
    "sg:city":"Santa Barbara",
    "sg:classifiers":[
        {
            "category":"Professional",
            "type":"Services"
        }
    ],
    "sg:phone":"+1 805 962 8082",
    "sg:postcode":"93109",
    "sg:province":"CA",
    "wof:name":"S W Harms",
    "wof:placetype":"venue"
},
  "geometry": {"coordinates":[-119.729546,34.400638],"type":"Point"}
}