{
  "type": "Feature",
  "properties": {
    "addr:full":"1935 W 11th St Upland CA 91786",
    "addr:housenumber":"1935",
    "addr:postcode":"91786",
    "addr:street":"W 11Th St",
    "iso:country":"US",
    "sg:address":"1935 W 11th St",
    "sg:city":"Upland",
    "sg:classifiers":[
        {
            "category":"Manufacturing",
            "subcategory":"Electronics",
            "type":"Manufacturing & Wholesale Goods"
        }
    ],
    "sg:phone":"+1 909 946 5944",
    "sg:postcode":"91786",
    "sg:province":"CA",
    "sg:tags":[
        "sound",
        "equipment",
        "system"
    ],
    "wof:name":"Upland Loudspeaker Svc",
    "wof:placetype":"venue"
},
  "geometry": {"coordinates":[-117.68674799999999,34.103302],"type":"Point"}
}