{
  "type": "Feature",
  "properties": {
    "addr:full":"11851 Artesia Blvd Artesia CA 90701",
    "addr:housenumber":"11851",
    "addr:postcode":"90701",
    "addr:street":"Artesia Blvd",
    "iso:country":"US",
    "sg:address":"11851 Artesia Blvd",
    "sg:city":"Artesia",
    "sg:classifiers":[
        {
            "category":"Shopping",
            "subcategory":"Pharmacy",
            "type":"Retail Goods"
        }
    ],
    "sg:phone":"+1 562 924 7697",
    "sg:postcode":"90701",
    "sg:province":"CA",
    "sg:tags":[
        "drugstore"
    ],
    "wof:name":"CVS Pharmacy",
    "wof:placetype":"venue"
},
  "geometry": {"coordinates":[-118.08045300000001,33.873126],"type":"Point"}
}