{
  "type": "Feature",
  "properties": {
    "addr:full":"524 S Main St Los Angeles CA 90013",
    "addr:housenumber":"524",
    "addr:postcode":"90013",
    "addr:street":"S Main St",
    "iso:country":"US",
    "sg:address":"524 S Main St",
    "sg:city":"Los Angeles",
    "sg:classifiers":[
        {
            "category":"Restaurant",
            "type":"Food & Drink"
        }
    ],
    "sg:phone":"+1 213 623 8301",
    "sg:postcode":"90013",
    "sg:province":"CA",
    "sg:tags":[
        "diner"
    ],
    "sg:website":"www.5cdiner.com",
    "wof:name":"Nickel Diner",
    "wof:placetype":"venue"
},
  "geometry": {"coordinates":[-118.249088,34.046119],"type":"Point"}
}