{
  "type": "Feature",
  "properties": {
    "iso:country":"US",
    "sg:address":"13334 Hwy 8 Bus",
    "sg:city":"Lakeside",
    "sg:classifiers":[
        {
            "category":"Restaurant",
            "type":"Food & Drink"
        }
    ],
    "sg:phone":"+1 619 390 6510",
    "sg:postcode":"92040",
    "sg:province":"CA",
    "wof:name":"Las Cazuelas Mexican Rstrnt",
    "wof:placetype":"venue"
},
  "geometry": {"coordinates":[-116.90478,32.833155],"type":"Point"}
}