{
  "type": "Feature",
  "properties": {
    "addr:full":"3532 Katella Ave Los Alamitos CA 90720",
    "addr:housenumber":"3532",
    "addr:postcode":"90720",
    "addr:street":"Katella Ave",
    "iso:country":"US",
    "sg:address":"3532 Katella Ave",
    "sg:city":"Los Alamitos",
    "sg:classifiers":[
        {
            "category":"Professional",
            "subcategory":"Lawyer & Legal Services",
            "type":"Services"
        }
    ],
    "sg:phone":"+1 562 493 5571",
    "sg:postcode":"90720",
    "sg:province":"CA",
    "wof:name":"Flax David Allen",
    "wof:placetype":"venue"
},
  "geometry": {"coordinates":[-118.070999,33.803001],"type":"Point"}
}