{
  "type": "Feature",
  "properties": {
    "addr:full":"10863 Venice Blvd Los Angeles CA 90034",
    "addr:housenumber":"10863",
    "addr:postcode":"90034",
    "addr:street":"Venice Blvd",
    "iso:country":"US",
    "sg:address":"10863 Venice Blvd",
    "sg:city":"Los Angeles",
    "sg:classifiers":[
        {
            "category":"Restaurant",
            "type":"Food & Drink"
        }
    ],
    "sg:phone":"+1 310 842 8291",
    "sg:postcode":"90034",
    "sg:province":"CA",
    "sg:tags":[
        "thai"
    ],
    "sg:website":"thaiboomLA.com",
    "wof:name":"Thai Boom",
    "wof:placetype":"venue"
},
  "geometry": {"coordinates":[-118.41067,34.016729],"type":"Point"}
}