{
  "type": "Feature",
  "properties": {
    "iso:country":"US",
    "sg:address":"139 N La Peer Dr",
    "sg:city":"Beverly Hills",
    "sg:classifiers":[
        {
            "category":"Personal",
            "subcategory":"Skin Care",
            "type":"Services"
        }
    ],
    "sg:phone":"+1 310 274 7990",
    "sg:postcode":"90211",
    "sg:province":"CA",
    "sg:website":"www.chezgabriela.com",
    "wof:name":"Chez Gabriela Skin Artist",
    "wof:placetype":"venue"
},
  "geometry": {"coordinates":[-118.386973,34.06826],"type":"Point"}
}