{
  "type": "Feature",
  "properties": {
    "iso:country":"US",
    "sg:address":"1408 Middle Harbor Rd",
    "sg:city":"Oakland",
    "sg:classifiers":[
        {
            "category":"Freight",
            "type":"Transportation"
        }
    ],
    "sg:phone":"+1 510 271 1881",
    "sg:postcode":"94607",
    "sg:province":"CA",
    "sg:tags":[
        "cargo",
        "containerized"
    ],
    "wof:name":"CSX Intermodal Inc",
    "wof:placetype":"venue"
},
  "geometry": {"coordinates":[-122.296409,37.798436],"type":"Point"}
}