{
  "type": "Feature",
  "properties": {
    "iso:country":"US",
    "sg:address":"2397 Broadway St",
    "sg:city":"Redwood City",
    "sg:classifiers":[
        {
            "category":"Restaurant",
            "type":"Food & Drink"
        }
    ],
    "sg:menulink":"http://www.allmenus.com/ca/san-mateo/52411-siciliano-ristorante-italiano/menu/",
    "sg:phone":"+1 650 369 9000",
    "sg:postcode":"94063",
    "sg:province":"CA",
    "sg:tags":[
        "italian"
    ],
    "wof:name":"Siciliano Ristorante Italiano",
    "wof:placetype":"venue"
},
  "geometry": {"coordinates":[-122.230923,37.486329],"type":"Point"}
}