{
  "type": "Feature",
  "properties": {
    "iso:country":"US",
    "sg:address":"1316 Olive Ave",
    "sg:city":"Novato",
    "sg:classifiers":[
        {
            "category":"Building & Trades",
            "subcategory":"Landscaping Services",
            "type":"Services"
        }
    ],
    "sg:phone":"+1 415 897 3763",
    "sg:postcode":"94945",
    "sg:province":"CA",
    "sg:tags":[
        "landscape",
        "contractor"
    ],
    "wof:name":"Alejandro Ruiz",
    "wof:placetype":"venue"
},
  "geometry": {"coordinates":[-122.573308,38.11232],"type":"Point"}
}