{
  "type": "Feature",
  "properties": {
    "addr:full":"312 Mill St Santa Maria CA 93454",
    "addr:housenumber":"312",
    "addr:postcode":"93454",
    "addr:street":"Mill St",
    "iso:country":"US",
    "sg:address":"312 Mill St",
    "sg:city":"Santa Maria",
    "sg:classifiers":[
        {
            "category":"Professional",
            "subcategory":"Lawyer & Legal Services",
            "type":"Services"
        }
    ],
    "sg:phone":"+1 805 928 3641",
    "sg:postcode":"93454",
    "sg:province":"CA",
    "sg:tags":[
        "attorney"
    ],
    "wof:name":"Biley & Biley",
    "wof:placetype":"venue"
},
  "geometry": {"coordinates":[-120.43158099999999,34.955293],"type":"Point"}
}