{
  "type": "Feature",
  "properties": {
    "addr:full":"1370 El Paseo De Saratoga San Jose CA 95130",
    "addr:housenumber":"1370",
    "addr:postcode":"95130",
    "addr:street":"El Paseo De Saratoga",
    "iso:country":"US",
    "sg:address":"1370 El Paseo De Saratoga",
    "sg:city":"San Jose",
    "sg:classifiers":[
        {
            "category":"Personal",
            "subcategory":"Beauty Salon",
            "type":"Services"
        }
    ],
    "sg:phone":"+1 408 871 9818",
    "sg:postcode":"95130",
    "sg:province":"CA",
    "sg:tags":[
        "hair"
    ],
    "sg:website":"www.lecrystal.com",
    "wof:name":"Le Crystal",
    "wof:placetype":"venue"
},
  "geometry": {"coordinates":[-121.98303900000001,37.287819],"type":"Point"}
}