{
  "type": "Feature",
  "properties": {
    "addr:full":"7775 Soquel Dr Aptos CA 95003",
    "addr:housenumber":"7775",
    "addr:postcode":"ca 95003",
    "addr:street":"Soquel Dr",
    "iso:country":"US",
    "sg:address":"7775 Soquel Dr",
    "sg:city":"Aptos",
    "sg:classifiers":[
        {
            "category":"Banks & Credit Unions",
            "subcategory":"Bank",
            "type":"Services"
        },
        {
            "category":"Banks & Credit Unions",
            "subcategory":"Financial Services",
            "type":"Services"
        }
    ],
    "sg:phone":"+1 831 662 6000",
    "sg:postcode":"95003",
    "sg:province":"CA",
    "sg:tags":[
        "saving",
        "loan",
        "commercial"
    ],
    "sg:website":"http://www.sccountybank.com",
    "wof:name":"Santa Cruz County Bank",
    "wof:placetype":"venue"
},
  "geometry": {"coordinates":[-121.90782400000001,36.97915],"type":"Point"}
}