{
  "type": "Feature",
  "properties": {
    "iso:country":"US",
    "sg:address":"12405 Los Nietos Rd Ste 106",
    "sg:city":"Santa Fe Springs",
    "sg:classifiers":[
        {
            "category":"Building & Trades",
            "subcategory":"Construction",
            "type":"Services"
        }
    ],
    "sg:phone":"+1 800 923 4777",
    "sg:postcode":"90670",
    "sg:province":"CA",
    "sg:tags":[
        "contractor"
    ],
    "sg:website":"www.lightenupskylight.com",
    "wof:name":"Lighten Up Skylight",
    "wof:placetype":"venue"
},
  "geometry": {"coordinates":[-118.061922,33.952753],"type":"Point"}
}