{
  "type": "Feature",
  "properties": {
    "addr:full":"5 Rowland Ct Novato CA 94947",
    "addr:housenumber":"5",
    "addr:postcode":"94947",
    "addr:street":"Rowland Ct",
    "iso:country":"US",
    "sg:address":"5 Rowland Ct",
    "sg:city":"Novato",
    "sg:classifiers":[
        {
            "category":"Social Services",
            "subcategory":"Child Care",
            "type":"Services"
        }
    ],
    "sg:phone":"+1 415 892 9499",
    "sg:postcode":"94947",
    "sg:province":"CA",
    "wof:name":"Sweet Pea Day Care",
    "wof:placetype":"venue"
},
  "geometry": {"coordinates":[-122.571411,38.08483],"type":"Point"}
}