{
  "type": "Feature",
  "properties": {
    "iso:country":"US",
    "sg:address":"600 Michael Collins Cir",
    "sg:city":"Montebello",
    "sg:classifiers":[
        {
            "category":"Wholesale",
            "subcategory":"Durable Goods & Equipment",
            "type":"Manufacturing & Wholesale Goods"
        }
    ],
    "sg:phone":"+1 626 405 0808",
    "sg:postcode":"90640",
    "sg:province":"CA",
    "sg:tags":[
        "exporter"
    ],
    "wof:name":"Fukang International Inc",
    "wof:placetype":"venue"
},
  "geometry": {"coordinates":[-118.102175,34.024398],"type":"Point"}
}