{
  "type": "Feature",
  "properties": {
    "iso:country":"US",
    "sg:address":"411 Ivy St",
    "sg:city":"San Diego",
    "sg:classifiers":[
        {
            "category":"Insurance",
            "subcategory":"Title Insurance",
            "type":"Services"
        }
    ],
    "sg:phone":"+1 619 238 1776",
    "sg:postcode":"92101",
    "sg:province":"CA",
    "wof:name":"First American Title Ins Co",
    "wof:placetype":"venue"
},
  "geometry": {"coordinates":[-117.16033899999999,32.728177],"type":"Point"}
}