{
  "type": "Feature",
  "properties": {
    "iso:country":"US",
    "sg:address":"210 E Olympic Blvd",
    "sg:city":"Los Angeles",
    "sg:classifiers":[
        {
            "category":"Shopping",
            "subcategory":"Clothing, Apparel, & Fashions",
            "type":"Retail Goods"
        }
    ],
    "sg:phone":"+1 213 765 0081",
    "sg:postcode":"90015",
    "sg:province":"CA",
    "sg:tags":[
        "shop",
        "bridal"
    ],
    "wof:name":"Juliet Inc",
    "wof:placetype":"venue"
},
  "geometry": {"coordinates":[-118.255089,34.038887],"type":"Point"}
}