{
  "type": "Feature",
  "properties": {
    "iso:country":"US",
    "sg:address":"112 Cradle Bar Ct",
    "sg:city":"Folsom",
    "sg:classifiers":[
        {
            "category":"Insurance",
            "subcategory":"Insurance Agent",
            "type":"Services"
        }
    ],
    "sg:phone":"+1 916 984 1723",
    "sg:postcode":"95630",
    "sg:province":"CA",
    "wof:name":"John Madson Insurance Services",
    "wof:placetype":"venue"
},
  "geometry": {"coordinates":[-121.144423,38.680276],"type":"Point"}
}