{
  "type": "Feature",
  "properties": {
    "iso:country":"US",
    "sg:address":"1255 N Hudson Ave",
    "sg:city":"Pasadena",
    "sg:classifiers":[
        {
            "category":"Professional",
            "type":"Services"
        }
    ],
    "sg:phone":"+1 626 798 7912",
    "sg:postcode":"91104",
    "sg:province":"CA",
    "sg:tags":[
        "establishment"
    ],
    "wof:name":"G & K",
    "wof:placetype":"venue"
},
  "geometry": {"coordinates":[-118.134032,34.168634],"type":"Point"}
}