{
  "type": "Feature",
  "properties": {
    "iso:country":"US",
    "sg:address":"55 Shaw Ave",
    "sg:city":"Clovis",
    "sg:classifiers":[
        {
            "category":"Personal",
            "type":"Services"
        },
        {
            "category":"Health Services",
            "subcategory":"Health Practitioner",
            "type":"Services"
        }
    ],
    "sg:phone":"+1 559 299 0380",
    "sg:postcode":"93612",
    "sg:province":"CA",
    "sg:tags":[
        "food",
        "therapist",
        "massage"
    ],
    "wof:name":"Devon's Holistic Health",
    "wof:placetype":"venue"
},
  "geometry": {"coordinates":[-119.70847,36.808557],"type":"Point"}
}