{
  "type": "Feature",
  "properties": {
    "addr:full":"739 Belden Ave Los Angeles CA 90022",
    "addr:housenumber":"739",
    "addr:postcode":"90022",
    "addr:street":"Belden Ave",
    "iso:country":"US",
    "sg:address":"739 Belden Ave",
    "sg:city":"Los Angeles",
    "sg:classifiers":[
        {
            "category":"Organizations",
            "subcategory":"Religious Organization",
            "type":"Services"
        }
    ],
    "sg:phone":"+1 323 724 1788",
    "sg:postcode":"90022",
    "sg:province":"CA",
    "sg:tags":[
        "church"
    ],
    "wof:name":"Capilla LA Luz",
    "wof:placetype":"venue"
},
  "geometry": {"coordinates":[-118.151914,34.021345],"type":"Point"}
}