{
  "type": "Feature",
  "properties": {
    "addr:full":"593 Woodside Rd Redwood City CA 94061",
    "addr:housenumber":"593",
    "addr:postcode":"94061",
    "addr:street":"Woodside Rd",
    "iso:country":"US",
    "sg:address":"593 Woodside Rd",
    "sg:city":"Redwood City",
    "sg:classifiers":[
        {
            "category":"Personal",
            "subcategory":"Shoe Repair & Shine",
            "type":"Services"
        }
    ],
    "sg:phone":"+1 650 365 2034",
    "sg:postcode":"94061",
    "sg:province":"CA",
    "sg:tags":[
        "repairing",
        "boot"
    ],
    "wof:name":"Joseph Shoe Svc",
    "wof:placetype":"venue"
},
  "geometry": {"coordinates":[-122.22331800000001,37.469973],"type":"Point"}
}