{
  "type": "Feature",
  "properties": {
    "iso:country":"US",
    "sg:address":"40356 Oak Park Way",
    "sg:city":"Oakhurst",
    "sg:classifiers":[
        {
            "category":"Wholesale",
            "subcategory":"Machinery & Supplies",
            "type":"Manufacturing & Wholesale Goods"
        }
    ],
    "sg:phone":"+1 559 642 4001",
    "sg:postcode":"93644",
    "sg:province":"CA",
    "sg:tags":[
        "vacuum",
        "system",
        "cleaning"
    ],
    "wof:name":"Quality Living Technologies",
    "wof:placetype":"venue"
},
  "geometry": {"coordinates":[-119.663871,37.335559],"type":"Point"}
}