{
  "type": "Feature",
  "properties": {
    "iso:country":"US",
    "sg:address":"3154 Berryessa Rd",
    "sg:city":"San Jose",
    "sg:classifiers":[
        {
            "category":"Travel",
            "subcategory":"Travel Agent",
            "type":"Entertainment"
        }
    ],
    "sg:phone":"+1 408 251 1597",
    "sg:postcode":"95132",
    "sg:province":"CA",
    "sg:tags":[
        "operator",
        "tour"
    ],
    "wof:name":"Friendly Tours & Travel",
    "wof:placetype":"venue"
},
  "geometry": {"coordinates":[-121.845405,37.396573],"type":"Point"}
}