{
  "type": "Feature",
  "properties": {
    "iso:country":"US",
    "sg:address":"1951 Nobili Ave",
    "sg:city":"Santa Clara",
    "sg:classifiers":[
        {
            "category":"Shopping",
            "subcategory":"Music",
            "type":"Retail Goods"
        }
    ],
    "sg:phone":"+1 408 246 7477",
    "sg:postcode":"95051",
    "sg:province":"CA",
    "wof:name":"Alan T Mackey",
    "wof:placetype":"venue"
},
  "geometry": {"coordinates":[-121.99023,37.3592],"type":"Point"}
}