{
  "type": "Feature",
  "properties": {
    "iso:country":"US",
    "sg:address":"3772 Tibbetts St",
    "sg:city":"Riverside",
    "sg:classifiers":[
        {
            "category":"Health Services",
            "subcategory":"Clinic",
            "type":"Services"
        },
        {
            "category":"Social Services",
            "type":"Services"
        }
    ],
    "sg:phone":"+1 951 682 8540",
    "sg:postcode":"92506",
    "sg:province":"CA",
    "sg:tags":[
        "information",
        "center",
        "family",
        "outpatient",
        "specialty",
        "planning"
    ],
    "wof:name":"Planned Parenthood Inc",
    "wof:placetype":"venue"
},
  "geometry": {"coordinates":[-117.397775,33.947225],"type":"Point"}
}