{
  "type": "Feature",
  "properties": {
    "addr:full":"206 Stanford Shopping Center Palo Alto CA 94304",
    "addr:housenumber":"206",
    "addr:postcode":"94304",
    "addr:street":"Stanford Shopping Center",
    "iso:country":"US",
    "sg:address":"206 Stanford Shopping Center",
    "sg:city":"Palo Alto",
    "sg:classifiers":[
        {
            "category":"Shopping",
            "subcategory":"Shoes",
            "type":"Retail Goods"
        }
    ],
    "sg:phone":"+1 650 321 4401",
    "sg:postcode":"94304",
    "sg:province":"CA",
    "wof:name":"Athlete's Foot",
    "wof:placetype":"venue"
},
  "geometry": {"coordinates":[-122.17291899999999,37.443143],"type":"Point"}
}