{
  "type": "Feature",
  "properties": {
    "iso:country":"US",
    "sg:address":"4448 University Ave Ste C",
    "sg:city":"San Diego",
    "sg:classifiers":[
        {
            "category":"Shopping",
            "subcategory":"Jewelry",
            "type":"Retail Goods"
        }
    ],
    "sg:phone":"+1 619 283 3766",
    "sg:postcode":"92105",
    "sg:province":"CA",
    "wof:name":"Kim Ngon",
    "wof:placetype":"venue"
},
  "geometry": {"coordinates":[-117.09899900000001,32.749599],"type":"Point"}
}