{
  "type": "Feature",
  "properties": {
    "iso:country":"US",
    "sg:address":"712 Alhambra Ave",
    "sg:city":"Martinez",
    "sg:classifiers":[
        {
            "category":"Organizations",
            "subcategory":"Non-profit Organization",
            "type":"Services"
        }
    ],
    "sg:phone":"+1 925 228 3172",
    "sg:postcode":"94553",
    "sg:province":"CA",
    "sg:tags":[
        "information",
        "alcoholism",
        "treatment"
    ],
    "wof:name":"DVRAA",
    "wof:placetype":"venue"
},
  "geometry": {"coordinates":[-122.137733,38.015861],"type":"Point"}
}