{
  "type": "Feature",
  "properties": {
    "addr:full":"420 Folsom Rd Roseville CA 95678",
    "addr:housenumber":"420",
    "addr:postcode":"95678",
    "addr:street":"Folsom Rd",
    "iso:country":"US",
    "sg:address":"420 Folsom Rd",
    "sg:city":"Roseville",
    "sg:classifiers":[
        {
            "category":"Health Services",
            "subcategory":"Doctor",
            "type":"Services"
        }
    ],
    "sg:phone":"+1 916 782 7225",
    "sg:postcode":"95678",
    "sg:province":"CA",
    "sg:tags":[
        "physician",
        "surgeon"
    ],
    "wof:name":"Integrative Medicine Clinic",
    "wof:placetype":"venue"
},
  "geometry": {"coordinates":[-121.27674,38.74428],"type":"Point"}
}