{
  "type": "Feature",
  "properties": {
    "addr:full":"21040 Homestead Rd Cupertino CA 95014",
    "addr:housenumber":"21040",
    "addr:postcode":"95014",
    "addr:street":"Homestead Rd",
    "iso:country":"US",
    "sg:address":"21040 Homestead Rd",
    "sg:city":"Cupertino",
    "sg:classifiers":[
        {
            "category":"Building & Trades",
            "subcategory":"Construction",
            "type":"Services"
        }
    ],
    "sg:phone":"+1 408 245 5000",
    "sg:postcode":"95014",
    "sg:province":"CA",
    "sg:tags":[
        "contractor"
    ],
    "wof:name":"Habitek Builders Inc",
    "wof:placetype":"venue"
},
  "geometry": {"coordinates":[-122.043093,37.337132],"type":"Point"}
}