{
  "type": "Feature",
  "properties": {
    "iso:country":"US",
    "sg:address":"531 Getty Ct Ste C",
    "sg:city":"Benicia",
    "sg:classifiers":[
        {
            "category":"Manufacturing",
            "subcategory":"Tools & Machinery",
            "type":"Manufacturing & Wholesale Goods"
        }
    ],
    "sg:phone":"+1 800 225 7644",
    "sg:postcode":"94510",
    "sg:province":"CA",
    "sg:tags":[
        "pumps-wholesale",
        "manufacturer"
    ],
    "wof:name":"Krogh Pump Co.",
    "wof:placetype":"venue"
},
  "geometry": {"coordinates":[-122.127589,38.077952],"type":"Point"}
}