{
  "type": "Feature",
  "properties": {
    "addr:full":"8528 N Magnolia #101 El Cajon CA 92020",
    "addr:housenumber":"8528",
    "addr:postcode":"92020",
    "addr:street":"N Magnolia # 101",
    "iso:country":"US",
    "sg:address":"8528 N Magnolia #101",
    "sg:city":"El Cajon",
    "sg:classifiers":[
        {
            "category":"Restaurant",
            "type":"Food & Drink"
        },
        {
            "category":"Food & Beverages",
            "subcategory":"Bakery",
            "type":"Retail Goods"
        }
    ],
    "sg:phone":"+1 619 562 9404",
    "sg:postcode":"92020",
    "sg:province":"CA",
    "sg:tags":[
        "sandwich",
        "pizza"
    ],
    "sg:website":"www.donovanspizzasd.com",
    "wof:name":"Donovan's Pizza and Subs",
    "wof:placetype":"venue"
},
  "geometry": {"coordinates":[-116.96660900000001,32.794869],"type":"Point"}
}