{
  "type": "Feature",
  "properties": {
    "addr:full":"230 California St San Francisco CA 94111",
    "addr:housenumber":"230",
    "addr:postcode":"94111",
    "addr:street":"California St",
    "iso:country":"US",
    "sg:address":"230 California St",
    "sg:city":"San Francisco",
    "sg:classifiers":[
        {
            "category":"Health Services",
            "subcategory":"Clinic",
            "type":"Services"
        },
        {
            "category":"Personal",
            "type":"Services"
        }
    ],
    "sg:phone":"+1 415 397 2727",
    "sg:postcode":"94111",
    "sg:province":"CA",
    "sg:tags":[
        "home",
        "medical"
    ],
    "sg:website":"www.caregiverstaffing.com/",
    "wof:name":"Care Giver Staffing",
    "wof:placetype":"venue"
},
  "geometry": {"coordinates":[-122.399328,37.793581],"type":"Point"}
}