{
  "type": "Feature",
  "properties": {
    "iso:country":"US",
    "sg:address":"4770 Via Escala",
    "sg:city":"Oceanside",
    "sg:classifiers":[
        {
            "category":"Home & Garden",
            "subcategory":"Building Materials",
            "type":"Retail Goods"
        }
    ],
    "sg:phone":"+1 760 945 0180",
    "sg:postcode":"92056",
    "sg:province":"CA",
    "sg:tags":[
        "lumber"
    ],
    "wof:name":"Richard W Geary & Assoc",
    "wof:placetype":"venue"
},
  "geometry": {"coordinates":[-117.288521,33.221578],"type":"Point"}
}