{
  "type": "Feature",
  "properties": {
    "iso:country":"US",
    "sg:address":"5612 Via del Collado",
    "sg:city":"Torrance",
    "sg:classifiers":[
        {
            "category":"Professional",
            "type":"Services"
        }
    ],
    "sg:phone":"+1 310 891 6098",
    "sg:postcode":"90505",
    "sg:province":"CA",
    "wof:name":"W Schroeder LLC",
    "wof:placetype":"venue"
},
  "geometry": {"coordinates":[-118.373981,33.808975],"type":"Point"}
}