{
  "type": "Feature",
  "properties": {
    "addr:full":"1108 Adams St Saint Helena CA 94574",
    "addr:housenumber":"1108",
    "addr:postcode":"94574",
    "addr:street":"Adams St",
    "iso:country":"US",
    "sg:address":"1108 Adams St",
    "sg:city":"Saint Helena",
    "sg:classifiers":[
        {
            "category":"Wholesale",
            "subcategory":"Wine & Distilled Alcoholic Beverages",
            "type":"Manufacturing & Wholesale Goods"
        }
    ],
    "sg:phone":"+1 707 967 8976",
    "sg:postcode":"94574",
    "sg:province":"CA",
    "sg:tags":[
        "liquor"
    ],
    "wof:name":"Southern Wine Spirits of Amer",
    "wof:placetype":"venue"
},
  "geometry": {"coordinates":[-122.47032,38.50537],"type":"Point"}
}