{
  "type": "Feature",
  "properties": {
    "iso:country":"US",
    "sg:address":"2436 Oak St",
    "sg:city":"Bakersfield",
    "sg:classifiers":[
        {
            "category":"Building & Trades",
            "subcategory":"Construction",
            "type":"Services"
        }
    ],
    "sg:phone":"+1 661 325 7138",
    "sg:postcode":"93301",
    "sg:province":"CA",
    "sg:tags":[
        "general",
        "contractor"
    ],
    "wof:name":"Ray Chinn Construction Inc",
    "wof:placetype":"venue"
},
  "geometry": {"coordinates":[-119.038596,35.381863],"type":"Point"}
}