{
  "type": "Feature",
  "properties": {
    "addr:full":"401 N Nopal St Santa Barbara CA 93103",
    "addr:housenumber":"401",
    "addr:postcode":"93103",
    "addr:street":"N Nopal St",
    "iso:country":"US",
    "sg:address":"401 N Nopal St",
    "sg:city":"Santa Barbara",
    "sg:classifiers":[
        {
            "category":"Building & Trades",
            "subcategory":"Construction",
            "type":"Services"
        }
    ],
    "sg:phone":"+1 805 962 4287",
    "sg:postcode":"93103",
    "sg:province":"CA",
    "sg:tags":[
        "maker",
        "cabinet"
    ],
    "wof:name":"Jorgensen's Cabinets Inc",
    "wof:placetype":"venue"
},
  "geometry": {"coordinates":[-119.685828,34.424793],"type":"Point"}
}