{
  "type": "Feature",
  "properties": {
    "iso:country":"US",
    "sg:address":"4547 Rockland Pl",
    "sg:city":"La Canada Fltrdg",
    "sg:classifiers":[
        {
            "category":"Building & Trades",
            "subcategory":"Plumbing",
            "type":"Services"
        }
    ],
    "sg:phone":"+1 818 957 6876",
    "sg:postcode":"91011",
    "sg:province":"CA",
    "sg:tags":[
        "plumbing",
        "contractor"
    ],
    "wof:name":"Valley Plumbing Corp",
    "wof:placetype":"venue"
},
  "geometry": {"coordinates":[-118.226387,34.219224],"type":"Point"}
}