{
  "type": "Feature",
  "properties": {
    "iso:country":"US",
    "sg:address":"5245 Vance St",
    "sg:city":"Eureka",
    "sg:classifiers":[
        {
            "category":"Social Services",
            "type":"Services"
        }
    ],
    "sg:phone":"+1 707 442 3969",
    "sg:postcode":"95503",
    "sg:province":"CA",
    "sg:tags":[
        "care",
        "center",
        "day"
    ],
    "wof:name":"Butler Valley Carole Sund Ctr",
    "wof:placetype":"venue"
},
  "geometry": {"coordinates":[-124.180905,40.758241],"type":"Point"}
}