{
  "type": "Feature",
  "properties": {
    "iso:country":"US",
    "sg:address":"4911 Lincoln Ave",
    "sg:city":"Cypress",
    "sg:classifiers":[
        {
            "category":"Restaurant",
            "type":"Food & Drink"
        }
    ],
    "sg:phone":"+1 714 761 5770",
    "sg:postcode":"90630",
    "sg:province":"CA",
    "sg:tags":[
        "pizza"
    ],
    "wof:name":"Valuetina's Pizza",
    "wof:placetype":"venue"
},
  "geometry": {"coordinates":[-118.046997,33.831902],"type":"Point"}
}