{
  "type": "Feature",
  "properties": {
    "addr:full":"370 Muir Station Rd Martinez CA 94553",
    "addr:housenumber":"370",
    "addr:postcode":"94553",
    "addr:street":"Muir Station Rd",
    "iso:country":"US",
    "sg:address":"370 Muir Station Rd",
    "sg:city":"Martinez",
    "sg:classifiers":[
        {
            "category":"Freight",
            "type":"Transportation"
        }
    ],
    "sg:phone":"+1 925 229 0330",
    "sg:postcode":"94553",
    "sg:province":"CA",
    "sg:tags":[
        "recreational",
        "vehicle"
    ],
    "wof:name":"Pereira A Storage",
    "wof:placetype":"venue"
},
  "geometry": {"coordinates":[-122.12496400000001,37.990809],"type":"Point"}
}