{
  "type": "Feature",
  "properties": {
    "addr:full":"921 E 11th St Los Angeles CA 90021",
    "addr:housenumber":"921",
    "addr:postcode":"90021",
    "addr:street":"E 11Th St",
    "iso:country":"US",
    "sg:address":"921 E 11th St",
    "sg:city":"Los Angeles",
    "sg:classifiers":[
        {
            "category":"Wholesale",
            "subcategory":"Electrical",
            "type":"Manufacturing & Wholesale Goods"
        }
    ],
    "sg:phone":"+1 213 688 1006",
    "sg:postcode":"90021",
    "sg:province":"CA",
    "sg:tags":[
        "equipment",
        "electronic",
        "supply"
    ],
    "sg:website":"www.discountavenue.net",
    "wof:name":"Discount Avenue",
    "wof:placetype":"venue"
},
  "geometry": {"coordinates":[-118.244947,34.031123],"type":"Point"}
}