{
  "type": "Feature",
  "properties": {
    "addr:full":"2040 Lincoln Blvd Tracy CA 95376",
    "addr:housenumber":"2040",
    "addr:postcode":"95376",
    "addr:street":"Lincoln Blvd",
    "iso:country":"US",
    "sg:address":"2040 Lincoln Blvd",
    "sg:city":"Tracy",
    "sg:classifiers":[
        {
            "category":"Professional",
            "subcategory":"Computer Services",
            "type":"Services"
        }
    ],
    "sg:phone":"+1 209 830 4460",
    "sg:postcode":"95376",
    "sg:province":"CA",
    "wof:name":"Nortel Networks",
    "wof:placetype":"venue"
},
  "geometry": {"coordinates":[-121.44349,37.750486],"type":"Point"}
}