{
  "type": "Feature",
  "properties": {
    "addr:full":"4340 Overland Ave Culver City CA 90230",
    "addr:housenumber":"4340",
    "addr:postcode":"90230",
    "addr:street":"Overland Ave",
    "iso:country":"US",
    "sg:address":"4340 Overland Ave",
    "sg:city":"Culver City",
    "sg:classifiers":[
        {
            "category":"Professional",
            "subcategory":"Research",
            "type":"Services"
        }
    ],
    "sg:phone":"+1 310 204 0954",
    "sg:postcode":"90230",
    "sg:province":"CA",
    "sg:tags":[
        "commercial",
        "physical"
    ],
    "wof:name":"Bio Cypher Laboratories",
    "wof:placetype":"venue"
},
  "geometry": {"coordinates":[-118.39987600000001,34.011254],"type":"Point"}
}