{
  "type": "Feature",
  "properties": {
    "addr:full":"116 Doyle St Santa Cruz CA 95062",
    "addr:housenumber":"116",
    "addr:postcode":"95062",
    "addr:street":"Doyle St",
    "iso:country":"US",
    "sg:address":"116 Doyle St",
    "sg:city":"Santa Cruz",
    "sg:classifiers":[
        {
            "category":"Health Services",
            "subcategory":"Chiropractor",
            "type":"Services"
        }
    ],
    "sg:phone":"+1 831 423 4668",
    "sg:postcode":"95062",
    "sg:province":"CA",
    "wof:name":"Essegian Howard J DC Chiropractic Corp",
    "wof:placetype":"venue"
},
  "geometry": {"coordinates":[-122.012001,36.979099],"type":"Point"}
}