{
  "type": "Feature",
  "properties": {
    "addr:full":"6246 Hog Canyon Rd San Miguel CA 93451",
    "addr:housenumber":"6246",
    "addr:postcode":"93451",
    "addr:street":"Hog Canyon Rd",
    "iso:country":"US",
    "sg:address":"6246 Hog Canyon Rd",
    "sg:city":"San Miguel",
    "sg:classifiers":[
        {
            "category":"Retail",
            "subcategory":"Animal Services",
            "type":"Services"
        }
    ],
    "sg:phone":"+1 805 467 9400",
    "sg:postcode":"93451",
    "sg:province":"CA",
    "sg:tags":[
        "breeder",
        "horse"
    ],
    "wof:name":"California Horse Trader",
    "wof:placetype":"venue"
},
  "geometry": {"coordinates":[-120.579796,35.723379],"type":"Point"}
}