{
  "type": "Feature",
  "properties": {
    "addr:full":"935 Durlston Rd Redwood City CA 94062",
    "addr:housenumber":"935",
    "addr:postcode":"94062",
    "addr:street":"Durlston Rd",
    "iso:country":"US",
    "sg:address":"935 Durlston Rd",
    "sg:city":"Redwood City",
    "sg:classifiers":[
        {
            "category":"Building & Trades",
            "subcategory":"Construction",
            "type":"Services"
        }
    ],
    "sg:phone":"+1 650 365 3716",
    "sg:postcode":"94062",
    "sg:province":"CA",
    "wof:name":"Bridge Systems Inc",
    "wof:placetype":"venue"
},
  "geometry": {"coordinates":[-122.250731,37.483158],"type":"Point"}
}