{
  "type": "Feature",
  "properties": {
    "iso:country":"US",
    "sg:address":"5626 N Figueroa St",
    "sg:city":"Los Angeles",
    "sg:classifiers":[
        {
            "category":"Shopping",
            "subcategory":"Stationery & Office Supplies",
            "type":"Retail Goods"
        }
    ],
    "sg:phone":"+1 323 255 4646",
    "sg:postcode":"90042",
    "sg:province":"CA",
    "sg:tags":[
        "equipment"
    ],
    "wof:name":"Astral Imaging",
    "wof:placetype":"venue"
},
  "geometry": {"coordinates":[-118.192931,34.10936],"type":"Point"}
}