{
  "type": "Feature",
  "properties": {
    "iso:country":"US",
    "sg:address":"68 Santa Ana Ave",
    "sg:city":"Long Beach",
    "sg:classifiers":[
        {
            "category":"Professional",
            "subcategory":"Lawyer & Legal Services",
            "type":"Services"
        }
    ],
    "sg:phone":"+1 562 432 6588",
    "sg:postcode":"90803",
    "sg:province":"CA",
    "sg:tags":[
        "attorney"
    ],
    "wof:name":"Barbian & Assoc",
    "wof:placetype":"venue"
},
  "geometry": {"coordinates":[-118.13375499999999,33.754837],"type":"Point"}
}