{
  "type": "Feature",
  "properties": {
    "iso:country":"US",
    "sg:address":"3233 T St",
    "sg:city":"Eureka",
    "sg:classifiers":[
        {
            "category":"Organizations",
            "subcategory":"Religious Organization",
            "type":"Services"
        }
    ],
    "sg:phone":"+1 707 444 2846",
    "sg:postcode":"95503",
    "sg:province":"CA",
    "sg:tags":[
        "synagogue"
    ],
    "wof:name":"Temple Beth-El",
    "wof:placetype":"venue"
},
  "geometry": {"coordinates":[-124.14797799999999,40.779299],"type":"Point"}
}