{
  "type": "Feature",
  "properties": {
    "iso:country":"US",
    "sg:address":"3069 Alamo Dr",
    "sg:city":"Vacaville",
    "sg:classifiers":[
        {
            "category":"Shopping",
            "subcategory":"Clothing, Apparel, & Fashions",
            "type":"Retail Goods"
        }
    ],
    "sg:phone":"+1 707 451 7469",
    "sg:postcode":"95687",
    "sg:province":"CA",
    "wof:name":"Maries Fashions",
    "wof:placetype":"venue"
},
  "geometry": {"coordinates":[-121.95384900000001,38.335443],"type":"Point"}
}