{
  "type": "Feature",
  "properties": {
    "addr:full":"26 Belcanto Irvine CA 92614",
    "addr:housenumber":"26",
    "addr:postcode":"92614",
    "addr:street":"Belcanto",
    "iso:country":"US",
    "sg:address":"26 Belcanto",
    "sg:city":"Irvine",
    "sg:classifiers":[
        {
            "category":"Banks & Credit Unions",
            "subcategory":"Bank",
            "type":"Services"
        }
    ],
    "sg:phone":"+1 949 794 9500",
    "sg:postcode":"92614",
    "sg:province":"CA",
    "sg:tags":[
        "loan",
        "real estate"
    ],
    "wof:name":"Sunrise Security Mortgage",
    "wof:placetype":"venue"
},
  "geometry": {"coordinates":[-117.817177,33.68155],"type":"Point"}
}