{
  "type": "Feature",
  "properties": {
    "addr:full":"218 Nebraska St Ste A Vallejo CA 94590",
    "addr:housenumber":"218",
    "addr:postcode":"94590",
    "addr:street":"Nebraska St Ste A",
    "iso:country":"US",
    "sg:address":"218 Nebraska St Ste A",
    "sg:city":"Vallejo",
    "sg:classifiers":[
        {
            "category":"Building & Trades",
            "subcategory":"Landscaping Services",
            "type":"Services"
        }
    ],
    "sg:phone":"+1 707 648 2562",
    "sg:postcode":"94590",
    "sg:province":"CA",
    "sg:tags":[
        "tree",
        "gardener"
    ],
    "wof:name":"Todd's Green Thumb Tree Svc",
    "wof:placetype":"venue"
},
  "geometry": {"coordinates":[-122.256034,38.113924],"type":"Point"}
}