{
  "type": "Feature",
  "properties": {
    "addr:full":"5600 Wilshire Blvd Los Angeles CA 90036",
    "addr:housenumber":"5600",
    "addr:postcode":"90036",
    "addr:street":"Wilshire Blvd",
    "iso:country":"US",
    "sg:address":"5600 Wilshire Blvd",
    "sg:city":"Los Angeles",
    "sg:classifiers":[
        {
            "category":"Restaurant",
            "type":"Food & Drink"
        }
    ],
    "sg:phone":"+1 323 933 5600",
    "sg:postcode":"90036",
    "sg:province":"CA",
    "sg:tags":[
        "sushi",
        "bar",
        "japanese"
    ],
    "wof:name":"Starfish Sushi",
    "wof:placetype":"venue"
},
  "geometry": {"coordinates":[-118.351291,34.061632],"type":"Point"}
}