{
  "type": "Feature",
  "properties": {
    "addr:full":"7521 Calais Ct Rancho Cucamonga CA 91730",
    "addr:housenumber":"7521",
    "addr:postcode":"91730",
    "addr:street":"Calais Ct",
    "iso:country":"US",
    "sg:address":"7521 Calais Ct",
    "sg:city":"Rancho Cucamonga",
    "sg:classifiers":[
        {
            "category":"Wholesale",
            "subcategory":"Machinery & Supplies",
            "type":"Manufacturing & Wholesale Goods"
        }
    ],
    "sg:phone":"+1 909 484 8636",
    "sg:postcode":"91730",
    "sg:province":"CA",
    "sg:tags":[
        "equipment",
        "industrial"
    ],
    "wof:name":"A & J Pressure Washing",
    "wof:placetype":"venue"
},
  "geometry": {"coordinates":[-117.56115699999999,34.117175],"type":"Point"}
}