{
  "type": "Feature",
  "properties": {
    "iso:country":"US",
    "sg:address":"51 N Main St",
    "sg:city":"Angels Camp",
    "sg:classifiers":[
        {
            "category":"Insurance",
            "subcategory":"Insurance Agent",
            "type":"Services"
        }
    ],
    "sg:phone":"+1 209 736 5910",
    "sg:postcode":"95222",
    "sg:province":"CA",
    "wof:name":"State Farm Insurance",
    "wof:placetype":"venue"
},
  "geometry": {"coordinates":[-120.561476,38.084284],"type":"Point"}
}