{
  "type": "Feature",
  "properties": {
    "iso:country":"US",
    "sg:address":"109 W Mason St",
    "sg:city":"Santa Barbara",
    "sg:classifiers":[
        {
            "category":"Professional",
            "subcategory":"Business Services",
            "type":"Services"
        }
    ],
    "sg:phone":"+1 805 966 9889",
    "sg:postcode":"93101",
    "sg:province":"CA",
    "sg:tags":[
        "interior",
        "consultant",
        "design",
        "decorator"
    ],
    "wof:name":"Kate Brooks Designs",
    "wof:placetype":"venue"
},
  "geometry": {"coordinates":[-119.691861,34.411234],"type":"Point"}
}