{
  "type": "Feature",
  "properties": {
    "addr:full":"26945 Cabot Rd Laguna Hills CA 92653",
    "addr:housenumber":"26945",
    "addr:postcode":"92653",
    "addr:street":"Cabot Rd",
    "iso:country":"US",
    "sg:address":"26945 Cabot Rd",
    "sg:city":"Laguna Hills",
    "sg:classifiers":[
        {
            "category":"Manufacturing",
            "subcategory":"Printing",
            "type":"Manufacturing & Wholesale Goods"
        }
    ],
    "sg:phone":"+1 949 916 1845",
    "sg:postcode":"92653",
    "sg:province":"CA",
    "sg:tags":[
        "printer",
        "commercial"
    ],
    "wof:name":"Enterprise Printing & Graphics",
    "wof:placetype":"venue"
},
  "geometry": {"coordinates":[-117.67442,33.571254],"type":"Point"}
}