{
  "type": "Feature",
  "properties": {
    "iso:country":"US",
    "sg:address":"1202 N Edgemont St",
    "sg:city":"Los Angeles",
    "sg:classifiers":[
        {
            "category":"Utilities",
            "subcategory":"Telephone",
            "type":"Services"
        }
    ],
    "sg:phone":"+1 323 664 8508",
    "sg:postcode":"90029",
    "sg:province":"CA",
    "sg:tags":[
        "distance",
        "reseller",
        "long"
    ],
    "wof:name":"West2east Communications Lllc",
    "wof:placetype":"venue"
},
  "geometry": {"coordinates":[-118.29604,34.095345],"type":"Point"}
}