{
  "type": "Feature",
  "properties": {
    "addr:full":"2660 Victor Ave Redding CA 96002",
    "addr:housenumber":"2660",
    "addr:postcode":"96002",
    "addr:street":"Victor Ave",
    "iso:country":"US",
    "sg:address":"2660 Victor Ave",
    "sg:city":"Redding",
    "sg:classifiers":[
        {
            "category":"Education",
            "subcategory":"Special Training",
            "type":"Public Place"
        }
    ],
    "sg:phone":"+1 530 223 5122",
    "sg:postcode":"96002",
    "sg:province":"CA",
    "sg:tags":[
        "instruction",
        "driving"
    ],
    "sg:website":"www.wrighted.org",
    "wof:name":"Wright Education Svc",
    "wof:placetype":"venue"
},
  "geometry": {"coordinates":[-122.33945199999999,40.565402],"type":"Point"}
}