{
  "type": "Feature",
  "properties": {
    "iso:country":"US",
    "sg:address":"3264 Adeline St",
    "sg:city":"Berkeley",
    "sg:classifiers":[
        {
            "category":"Shopping",
            "subcategory":"Books",
            "type":"Retail Goods"
        }
    ],
    "sg:phone":"+1 510 848 0413",
    "sg:postcode":"94703",
    "sg:province":"CA",
    "sg:tags":[
        "bookstore"
    ],
    "sg:website":"www.otherchangeofhobbit.com",
    "wof:name":"The Other Change of Hobbit",
    "wof:placetype":"venue"
},
  "geometry": {"coordinates":[-122.27170099999999,37.849231],"type":"Point"}
}