{
  "type": "Feature",
  "properties": {
    "iso:country":"US",
    "sg:address":"1901 Laurel Rd",
    "sg:city":"Oceanside",
    "sg:classifiers":[
        {
            "category":"Shopping",
            "subcategory":"Crafts & Fabrics",
            "type":"Retail Goods"
        }
    ],
    "sg:phone":"+1 760 722 4119",
    "sg:postcode":"92054",
    "sg:province":"CA",
    "sg:tags":[
        "sewing"
    ],
    "wof:name":"Bevs Threads",
    "wof:placetype":"venue"
},
  "geometry": {"coordinates":[-117.334698,33.187956],"type":"Point"}
}