{
  "type": "Feature",
  "properties": {
    "addr:full":"3913 Ferndale Ln Concord CA 94519",
    "addr:housenumber":"3913",
    "addr:postcode":"94519",
    "addr:street":"Ferndale Ln",
    "iso:country":"US",
    "sg:address":"3913 Ferndale Ln",
    "sg:city":"Concord",
    "sg:classifiers":[
        {
            "category":"Building & Trades",
            "subcategory":"Plumbing",
            "type":"Services"
        }
    ],
    "sg:phone":"+1 510 872 9595",
    "sg:postcode":"94519",
    "sg:province":"CA",
    "sg:tags":[
        "contractor"
    ],
    "wof:name":"Yarilo Solar",
    "wof:placetype":"venue"
},
  "geometry": {"coordinates":[-122.003669,37.980081],"type":"Point"}
}