{
  "type": "Feature",
  "properties": {
    "iso:country":"US",
    "sg:address":"Town and Country Resort 500 Hotel Cir N",
    "sg:city":"San Diego",
    "sg:classifiers":[
        {
            "category":"Restaurant",
            "type":"Food & Drink"
        }
    ],
    "sg:phone":"+1 619 291 7131",
    "sg:postcode":"92108",
    "sg:province":"CA",
    "sg:tags":[
        "steakhouse"
    ],
    "sg:website":"www.kellyssteakhouse.com/",
    "wof:name":"Kelly's Steakhouse",
    "wof:placetype":"venue"
},
  "geometry": {"coordinates":[-117.16627099999999,32.763478],"type":"Point"}
}