{
  "type": "Feature",
  "properties": {
    "iso:country":"US",
    "sg:address":"2610 S Mansfield Avenue",
    "sg:city":"Los Angeles",
    "sg:classifiers":[
        {
            "category":"Place Of Worship",
            "subcategory":"Church",
            "type":"Public Place"
        }
    ],
    "sg:phone":"+1 323 935 8127",
    "sg:postcode":"90016",
    "sg:province":"CA",
    "wof:name":"St. Agatha Catholic Church",
    "wof:placetype":"venue"
},
  "geometry": {"coordinates":[-118.35252,34.032256],"type":"Point"}
}