{
  "type": "Feature",
  "properties": {
    "addr:full":"2821 Rancho Rio Chico Carlsbad CA 92009",
    "addr:housenumber":"2821",
    "addr:postcode":"92009",
    "addr:street":"Rancho Rio Chico",
    "iso:country":"US",
    "sg:address":"2821 Rancho Rio Chico",
    "sg:city":"Carlsbad",
    "sg:classifiers":[
        {
            "category":"Professional",
            "type":"Services"
        }
    ],
    "sg:phone":"+1 760 931 1728",
    "sg:postcode":"92009",
    "sg:province":"CA",
    "wof:name":"Bruce Schragin",
    "wof:placetype":"venue"
},
  "geometry": {"coordinates":[-117.243612,33.11969],"type":"Point"}
}