{
  "type": "Feature",
  "properties": {
    "iso:country":"US",
    "sg:address":"333 S Hope St",
    "sg:city":"Los Angeles",
    "sg:classifiers":[
        {
            "category":"Real Estate",
            "subcategory":"Architect",
            "type":"Services"
        }
    ],
    "sg:phone":"+1 213 627 7373",
    "sg:postcode":"90071",
    "sg:province":"CA",
    "sg:website":"www.rtkl.com",
    "wof:name":"RTKL Assoc Inc",
    "wof:placetype":"venue"
},
  "geometry": {"coordinates":[-118.252275,34.053711],"type":"Point"}
}