{
  "type": "Feature",
  "properties": {
    "iso:country":"US",
    "sg:address":"1717 Oakdale Rd Frnt",
    "sg:city":"Modesto",
    "sg:classifiers":[
        {
            "category":"Restaurant",
            "type":"Food & Drink"
        }
    ],
    "sg:phone":"+1 209 522 2107",
    "sg:postcode":"95355",
    "sg:province":"CA",
    "wof:name":"La Hacienda De Los Velardes",
    "wof:placetype":"venue"
},
  "geometry": {"coordinates":[-120.958,37.668701],"type":"Point"}
}