{
  "type": "Feature",
  "properties": {
    "iso:country":"US",
    "sg:address":"56 E Colorado Blvd",
    "sg:city":"Pasadena",
    "sg:classifiers":[
        {
            "category":"Personal",
            "subcategory":"Piercing",
            "type":"Services"
        }
    ],
    "sg:phone":"+1 626 405 9253",
    "sg:postcode":"91105",
    "sg:province":"CA",
    "sg:website":"www.prixbodypiercing.com",
    "wof:name":"Prix Body Piercing and Tattoo",
    "wof:placetype":"venue"
},
  "geometry": {"coordinates":[-118.14924600000001,34.145782],"type":"Point"}
}