{
  "type": "Feature",
  "properties": {
    "addr:full":"9191 Elk Grove Blvd Elk Grove CA 95624",
    "addr:housenumber":"9191",
    "addr:postcode":"95624",
    "addr:street":"Elk Grove Blvd",
    "iso:country":"US",
    "sg:address":"9191 Elk Grove Blvd",
    "sg:city":"Elk Grove",
    "sg:classifiers":[
        {
            "category":"Real Estate",
            "subcategory":"Real Estate Operator",
            "type":"Services"
        }
    ],
    "sg:phone":"+1 916 714 3007",
    "sg:postcode":"95624",
    "sg:province":"CA",
    "sg:tags":[
        "apartment"
    ],
    "wof:name":"Luxury Apartments",
    "wof:placetype":"venue"
},
  "geometry": {"coordinates":[-121.35733,38.409105],"type":"Point"}
}