{
  "type": "Feature",
  "properties": {
    "addr:full":"1392 Sunset Blvd Los Angeles CA 90026",
    "addr:housenumber":"1392",
    "addr:postcode":"90026",
    "addr:street":"Sunset Blvd",
    "iso:country":"US",
    "sg:address":"1392 Sunset Blvd",
    "sg:city":"Los Angeles",
    "sg:classifiers":[
        {
            "category":"Retail",
            "subcategory":"Laundry & Dry Cleaning",
            "type":"Services"
        }
    ],
    "sg:phone":"+1 213 975 9390",
    "sg:postcode":"90026",
    "sg:province":"CA",
    "wof:name":"The Happy Shirt",
    "wof:placetype":"venue"
},
  "geometry": {"coordinates":[-118.251807,34.073976],"type":"Point"}
}