{
  "type": "Feature",
  "properties": {
    "iso:country":"US",
    "sg:address":"1209 E Olympic Blvd",
    "sg:city":"Los Angeles",
    "sg:classifiers":[
        {
            "category":"Wholesale",
            "subcategory":"Groceries",
            "type":"Manufacturing & Wholesale Goods"
        }
    ],
    "sg:phone":"+1 213 612 0658",
    "sg:postcode":"90021",
    "sg:province":"CA",
    "wof:name":"Azteca Imports",
    "wof:placetype":"venue"
},
  "geometry": {"coordinates":[-118.244227,34.032228],"type":"Point"}
}