{
  "type": "Feature",
  "properties": {
    "addr:full":"270 Beacon St San Francisco CA 94131",
    "addr:housenumber":"270",
    "addr:postcode":"94131",
    "addr:street":"Beacon St",
    "iso:country":"US",
    "sg:address":"270 Beacon St",
    "sg:city":"San Francisco",
    "sg:classifiers":[
        {
            "category":"Professional",
            "subcategory":"Engineering",
            "type":"Services"
        }
    ],
    "sg:phone":"+1 415 641 9944",
    "sg:postcode":"94131",
    "sg:province":"CA",
    "sg:tags":[
        "engineer"
    ],
    "wof:name":"THM & Assoc",
    "wof:placetype":"venue"
},
  "geometry": {"coordinates":[-122.432306,37.740482],"type":"Point"}
}