{
  "type": "Feature",
  "properties": {
    "iso:country":"US",
    "sg:address":"1008 S Baldwin Ave",
    "sg:city":"Arcadia",
    "sg:classifiers":[
        {
            "category":"Wholesale",
            "subcategory":"Durable Goods & Equipment",
            "type":"Manufacturing & Wholesale Goods"
        }
    ],
    "sg:phone":"+1 626 241 5558",
    "sg:postcode":"91007",
    "sg:province":"CA",
    "sg:tags":[
        "exporter"
    ],
    "wof:name":"Mint Mark Intl Group Inc",
    "wof:placetype":"venue"
},
  "geometry": {"coordinates":[-118.05466699999999,34.128022],"type":"Point"}
}