{
  "type": "Feature",
  "properties": {
    "addr:full":"2814 Todd St Oceanside CA 92054",
    "addr:housenumber":"2814",
    "addr:postcode":"92054",
    "addr:street":"Todd St",
    "iso:country":"US",
    "sg:address":"2814 Todd St",
    "sg:city":"Oceanside",
    "sg:classifiers":[
        {
            "category":"Manufacturing",
            "subcategory":"Retail Goods",
            "type":"Manufacturing & Wholesale Goods"
        }
    ],
    "sg:phone":"+1 760 757 8355",
    "sg:postcode":"92054",
    "sg:province":"CA",
    "sg:tags":[
        "product",
        "mfg"
    ],
    "wof:name":"Dishmon Wood Products",
    "wof:placetype":"venue"
},
  "geometry": {"coordinates":[-117.347903,33.209497],"type":"Point"}
}