{
  "type": "Feature",
  "properties": {
    "iso:country":"US",
    "sg:address":"25832 1/2 Mcbean Pkwy",
    "sg:city":"Valencia",
    "sg:phone":"+1 661 284 3633",
    "sg:postcode":"91355",
    "sg:province":"CA",
    "sg:website":"http://www.lespritdayspa.com",
    "wof:name":"L'Esprit Day Spa",
    "wof:placetype":"venue"
},
  "geometry": {"coordinates":[-118.551269,34.40203],"type":"Point"}
}