{
  "type": "Feature",
  "properties": {
    "addr:full":"2377 Crenshaw Blvd Torrance CA 90501",
    "addr:housenumber":"2377",
    "addr:postcode":"90501",
    "addr:street":"Crenshaw Blvd",
    "iso:country":"US",
    "sg:address":"2377 Crenshaw Blvd",
    "sg:city":"Torrance",
    "sg:classifiers":[
        {
            "category":"Real Estate",
            "subcategory":"Developer",
            "type":"Services"
        }
    ],
    "sg:phone":"+1 310 781 1100",
    "sg:postcode":"90501",
    "sg:province":"CA",
    "wof:name":"Catellus Development Corp",
    "wof:placetype":"venue"
},
  "geometry": {"coordinates":[-118.32848,33.823068],"type":"Point"}
}