{
  "type": "Feature",
  "properties": {
    "addr:full":"42010 Blacow Rd Apt 409 Fremont CA 94538",
    "addr:housenumber":"409",
    "addr:postcode":"42010;94538",
    "addr:street":"Blacow Rd Apt",
    "iso:country":"US",
    "sg:address":"42010 Blacow Rd Apt 409",
    "sg:city":"Fremont",
    "sg:classifiers":[
        {
            "category":"Professional",
            "subcategory":"Art Services",
            "type":"Services"
        }
    ],
    "sg:phone":"+1 510 438 8845",
    "sg:postcode":"94538",
    "sg:province":"CA",
    "sg:tags":[
        "designer",
        "display",
        "producer"
    ],
    "wof:name":"Cola Eric Designs",
    "wof:placetype":"venue"
},
  "geometry": {"coordinates":[-121.95971400000001,37.523739],"type":"Point"}
}