{
  "type": "Feature",
  "properties": {
    "addr:full":"840 The City Dr S Orange CA 92868",
    "addr:housenumber":"840",
    "addr:postcode":"92868",
    "addr:street":"The City Dr S",
    "iso:country":"US",
    "sg:address":"840 The City Dr S",
    "sg:city":"Orange",
    "sg:classifiers":[
        {
            "category":"Deli",
            "type":"Food & Drink"
        }
    ],
    "sg:menulink":"http://www.allmenus.com/ca/anaheim-santa-ana-garden-grove/125923-blimpie-subs--sandwiches/menu/",
    "sg:phone":"+1 714 740 2692",
    "sg:postcode":"92868",
    "sg:province":"CA",
    "sg:tags":[
        "wrap",
        "american",
        "sandwich"
    ],
    "wof:name":"Blimpie Subs & Sandwiches",
    "wof:placetype":"venue"
},
  "geometry": {"coordinates":[-117.89102099999999,33.774836],"type":"Point"}
}