{
  "type": "Feature",
  "properties": {
    "addr:full":"10050 N Wolfe Rd Cupertino CA 95014",
    "addr:housenumber":"10050",
    "addr:postcode":"95014",
    "addr:street":"N Wolfe Rd",
    "iso:country":"US",
    "sg:address":"10050 N Wolfe Rd",
    "sg:city":"Cupertino",
    "sg:classifiers":[
        {
            "category":"Insurance",
            "subcategory":"Insurance Agent",
            "type":"Services"
        }
    ],
    "sg:phone":"+1 408 517 2900",
    "sg:postcode":"95014",
    "sg:province":"CA",
    "wof:name":"Ameritas Acacia Companies",
    "wof:placetype":"venue"
},
  "geometry": {"coordinates":[-122.014415,37.323531],"type":"Point"}
}