{
  "type": "Feature",
  "properties": {
    "addr:full":"3556 Torrance Blvd Torrance CA 90503",
    "addr:housenumber":"3556",
    "addr:postcode":"90503",
    "addr:street":"Torrance Blvd",
    "iso:country":"US",
    "sg:address":"3556 Torrance Blvd",
    "sg:city":"Torrance",
    "sg:classifiers":[
        {
            "category":"Health Services",
            "subcategory":"Doctor",
            "type":"Services"
        }
    ],
    "sg:phone":"+1 310 316 0555",
    "sg:postcode":"90503",
    "sg:province":"CA",
    "sg:tags":[
        "dentist"
    ],
    "wof:name":"LA Boca Bella Dental Arts",
    "wof:placetype":"venue"
},
  "geometry": {"coordinates":[-118.34602,33.837482],"type":"Point"}
}