{
  "type": "Feature",
  "properties": {
    "addr:full":"2111 Hill Haven Rd Solvang CA 93463",
    "addr:housenumber":"2111",
    "addr:postcode":"93463",
    "addr:street":"Hill Haven Rd",
    "iso:country":"US",
    "sg:address":"2111 Hill Haven Rd",
    "sg:city":"Solvang",
    "sg:classifiers":[
        {
            "category":"Building & Trades",
            "subcategory":"Plumbing",
            "type":"Services"
        }
    ],
    "sg:phone":"+1 805 688 3290",
    "sg:postcode":"93463",
    "sg:province":"CA",
    "sg:tags":[
        "plumbing",
        "contractor"
    ],
    "wof:name":"Pierce Plumbing",
    "wof:placetype":"venue"
},
  "geometry": {"coordinates":[-120.12128,34.600242],"type":"Point"}
}