{
  "type": "Feature",
  "properties": {
    "addr:full":"4660 Galena St Riverside CA 92509",
    "addr:housenumber":"4660",
    "addr:postcode":"92509",
    "addr:street":"Galena St",
    "iso:country":"US",
    "sg:address":"4660 Galena St",
    "sg:city":"Riverside",
    "sg:classifiers":[
        {
            "category":"Shopping",
            "subcategory":"Clothing, Apparel, & Fashions",
            "type":"Retail Goods"
        }
    ],
    "sg:phone":"+1 951 361 0938",
    "sg:postcode":"92509",
    "sg:province":"CA",
    "wof:name":"Discount Wear",
    "wof:placetype":"venue"
},
  "geometry": {"coordinates":[-117.455269,34.004495],"type":"Point"}
}