{
  "type": "Feature",
  "properties": {
    "addr:full":"7540 Shoreline Dr Stockton CA 95219",
    "addr:housenumber":"7540",
    "addr:postcode":"95219",
    "addr:street":"Shoreline Dr",
    "iso:country":"US",
    "sg:address":"7540 Shoreline Dr",
    "sg:city":"Stockton",
    "sg:classifiers":[
        {
            "category":"Professional",
            "subcategory":"Lawyer & Legal Services",
            "type":"Services"
        }
    ],
    "sg:phone":"+1 209 478 2000",
    "sg:postcode":"95219",
    "sg:province":"CA",
    "sg:tags":[
        "attorney"
    ],
    "wof:name":"Kroloff Belcher Smart Perry",
    "wof:placetype":"venue"
},
  "geometry": {"coordinates":[-121.360748,38.019959],"type":"Point"}
}