{
  "type": "Feature",
  "properties": {
    "iso:country":"US",
    "sg:address":"7720 Paradise Valley Rd",
    "sg:city":"San Diego",
    "sg:classifiers":[
        {
            "category":"Health Services",
            "subcategory":"Doctor",
            "type":"Services"
        }
    ],
    "sg:phone":"+1 619 267 9200",
    "sg:postcode":"92139",
    "sg:province":"CA",
    "sg:tags":[
        "dentist"
    ],
    "wof:name":"Glenn E Gibson DDS",
    "wof:placetype":"venue"
},
  "geometry": {"coordinates":[-117.028451,32.695963],"type":"Point"}
}