{
  "type": "Feature",
  "properties": {
    "iso:country":"US",
    "sg:address":"471 E. Campbell Ave",
    "sg:city":"Campbell",
    "sg:classifiers":[
        {
            "category":"Home & Garden",
            "subcategory":"Home Furnishings",
            "type":"Retail Goods"
        }
    ],
    "sg:phone":"+1 408 802 7364",
    "sg:postcode":"95008",
    "sg:province":"CA",
    "sg:tags":[
        "bath",
        "kitchen"
    ],
    "wof:name":"Towne Tile & Stone",
    "wof:placetype":"venue"
},
  "geometry": {"coordinates":[-121.94154899999999,37.28745],"type":"Point"}
}