{
  "type": "Feature",
  "properties": {
    "addr:full":"3333 N Cornelia Ave Fresno CA 93722",
    "addr:housenumber":"3333",
    "addr:postcode":"93722",
    "addr:street":"N Cornelia Ave",
    "iso:country":"US",
    "sg:address":"3333 N Cornelia Ave",
    "sg:city":"Fresno",
    "sg:classifiers":[
        {
            "category":"Organizations",
            "subcategory":"Religious Organization",
            "type":"Services"
        }
    ],
    "sg:phone":"+1 559 276 2467",
    "sg:postcode":"93722",
    "sg:province":"CA",
    "sg:tags":[
        "church"
    ],
    "wof:name":"Westwood Baptist Church",
    "wof:placetype":"venue"
},
  "geometry": {"coordinates":[-119.880455,36.785604],"type":"Point"}
}