{
  "type": "Feature",
  "properties": {
    "addr:full":"2051 W 236th St Torrance CA 90501",
    "addr:housenumber":"2051",
    "addr:postcode":"90501",
    "addr:street":"W 236Th St",
    "iso:country":"US",
    "sg:address":"2051 W 236th St",
    "sg:city":"Torrance",
    "sg:classifiers":[
        {
            "category":"Organizations",
            "subcategory":"Religious Organization",
            "type":"Services"
        }
    ],
    "sg:phone":"+1 310 325 1291",
    "sg:postcode":"90501",
    "sg:province":"CA",
    "sg:tags":[
        "church"
    ],
    "wof:name":"Vietnamese Alliance Church",
    "wof:placetype":"venue"
},
  "geometry": {"coordinates":[-118.317278,33.81136],"type":"Point"}
}