{
  "type": "Feature",
  "properties": {
    "addr:full":"6767 Adobe Rd Twentynine Palms CA 92277",
    "addr:housenumber":"6767",
    "addr:postcode":"92277",
    "addr:street":"Adobe Rd",
    "iso:country":"US",
    "sg:address":"6767 Adobe Rd",
    "sg:city":"Twentynine Palms",
    "sg:classifiers":[
        {
            "category":"Building & Trades",
            "subcategory":"Electrical",
            "type":"Services"
        }
    ],
    "sg:phone":"+1 760 367 0024",
    "sg:postcode":"92277",
    "sg:province":"CA",
    "sg:tags":[
        "electric",
        "contractor"
    ],
    "wof:name":"GBC Electrical Svc",
    "wof:placetype":"venue"
},
  "geometry": {"coordinates":[-116.05430800000001,34.130495],"type":"Point"}
}