{
  "type": "Feature",
  "properties": {
    "addr:full":"1400 Standiford Ave Modesto CA 95350",
    "addr:housenumber":"1400",
    "addr:postcode":"ca 95350",
    "addr:street":"Standiford Ave",
    "iso:country":"US",
    "sg:address":"1400 Standiford Ave",
    "sg:city":"Modesto",
    "sg:classifiers":[
        {
            "category":"Professional",
            "subcategory":"Employment Agencies",
            "type":"Services"
        }
    ],
    "sg:phone":"+1 209 527 1079",
    "sg:postcode":"95350",
    "sg:province":"CA",
    "sg:tags":[
        "opportunity"
    ],
    "sg:website":"www.remedystaff.com",
    "wof:name":"Remedy Intelligent Staffing",
    "wof:placetype":"venue"
},
  "geometry": {"coordinates":[-121.01754,37.68942],"type":"Point"}
}