{
  "type": "Feature",
  "properties": {
    "addr:full":"5145 Pearce Ave Lakewood CA 90712",
    "addr:housenumber":"5145",
    "addr:postcode":"90712",
    "addr:street":"Pearce Ave",
    "iso:country":"US",
    "sg:address":"5145 Pearce Ave",
    "sg:city":"Lakewood",
    "sg:classifiers":[
        {
            "category":"Communications",
            "type":"Services"
        }
    ],
    "sg:phone":"+1 562 867 2226",
    "sg:postcode":"90712",
    "sg:province":"CA",
    "sg:tags":[
        "communication"
    ],
    "wof:name":"Unitek Communications",
    "wof:placetype":"venue"
},
  "geometry": {"coordinates":[-118.129912,33.851517],"type":"Point"}
}