{
  "type": "Feature",
  "properties": {
    "iso:country":"US",
    "sg:address":"6860 Pacific Ave",
    "sg:city":"Stockton",
    "sg:classifiers":[
        {
            "category":"Utilities",
            "subcategory":"Mobile Phone",
            "type":"Services"
        }
    ],
    "sg:phone":"+1 209 473 3333",
    "sg:postcode":"95207",
    "sg:province":"CA",
    "sg:tags":[
        "telephone",
        "cellular"
    ],
    "wof:name":"Cellular Solutions",
    "wof:placetype":"venue"
},
  "geometry": {"coordinates":[-121.32099100000001,38.012759],"type":"Point"}
}