{
  "type": "Feature",
  "properties": {
    "addr:full":"1690 Benson Ave Cambria CA 93428",
    "addr:housenumber":"1690",
    "addr:postcode":"93428",
    "addr:street":"Benson Ave",
    "iso:country":"US",
    "sg:address":"1690 Benson Ave",
    "sg:city":"Cambria",
    "sg:classifiers":[
        {
            "category":"Retail",
            "subcategory":"Portrait Studio",
            "type":"Services"
        }
    ],
    "sg:phone":"+1 805 927 0669",
    "sg:postcode":"93428",
    "sg:province":"CA",
    "sg:tags":[
        "photographer"
    ],
    "sg:website":"www.ronbianchetto.com",
    "wof:name":"Ron Bianchetto Photography",
    "wof:placetype":"venue"
},
  "geometry": {"coordinates":[-121.085565,35.545582],"type":"Point"}
}