{
  "type": "Feature",
  "properties": {
    "addr:full":"2829 Nipoma St San Diego CA 92106",
    "addr:housenumber":"2829",
    "addr:postcode":"92106",
    "addr:street":"Nipoma St",
    "iso:country":"US",
    "sg:address":"2829 Nipoma St",
    "sg:city":"San Diego",
    "sg:classifiers":[
        {
            "category":"Health Services",
            "subcategory":"Health Practitioner",
            "type":"Services"
        }
    ],
    "sg:phone":"+1 619 293 0220",
    "sg:postcode":"92106",
    "sg:province":"CA",
    "sg:tags":[
        "acupuncture"
    ],
    "wof:name":"Pacific Coast Acupuncture Med",
    "wof:placetype":"venue"
},
  "geometry": {"coordinates":[-117.223186,32.749419],"type":"Point"}
}