{
  "type": "Feature",
  "properties": {
    "addr:full":"166 Geary St Ste 1102 San Francisco CA 94108",
    "addr:housenumber":"166",
    "addr:postcode":"94108",
    "addr:street":"Geary St Ste 1102",
    "iso:country":"US",
    "sg:address":"166 Geary St Ste 1102",
    "sg:city":"San Francisco",
    "sg:classifiers":[
        {
            "category":"Health Services",
            "subcategory":"Health Practitioner",
            "type":"Services"
        }
    ],
    "sg:phone":"+1 415 682 4610",
    "sg:postcode":"94108",
    "sg:province":"CA",
    "sg:tags":[
        "therapy",
        "physical"
    ],
    "sg:website":"www.tuuli-orthopt.org",
    "wof:name":"Tuuli Orthopedic Physical Therapy",
    "wof:placetype":"venue"
},
  "geometry": {"coordinates":[-122.40613399999999,37.787888],"type":"Point"}
}