{
  "type": "Feature",
  "properties": {
    "addr:full":"8830 Miner St Los Angeles CA 90002",
    "addr:housenumber":"8830",
    "addr:postcode":"90002",
    "addr:street":"Miner St",
    "iso:country":"US",
    "sg:address":"8830 Miner St",
    "sg:city":"Los Angeles",
    "sg:classifiers":[
        {
            "category":"Manufacturing",
            "subcategory":"Apparel",
            "type":"Manufacturing & Wholesale Goods"
        }
    ],
    "sg:phone":"+1 323 582 3421",
    "sg:postcode":"90002",
    "sg:province":"CA",
    "sg:tags":[
        "outerwear",
        "mfg"
    ],
    "wof:name":"E & K Twin Apparel Inc",
    "wof:placetype":"venue"
},
  "geometry": {"coordinates":[-118.234379,33.956538],"type":"Point"}
}