{
  "type": "Feature",
  "properties": {
    "iso:country":"US",
    "sg:address":"1926 El Camino Real",
    "sg:city":"Redwood City",
    "sg:classifiers":[
        {
            "category":"Restaurant",
            "type":"Food & Drink"
        }
    ],
    "sg:menulink":"http://www.allmenus.com/ca/san-mateo/150239-subway/menu/",
    "sg:phone":"+1 650 368 9624",
    "sg:postcode":"94063",
    "sg:province":"CA",
    "sg:tags":[
        "american",
        "sandwich"
    ],
    "wof:name":"Subway",
    "wof:placetype":"venue"
},
  "geometry": {"coordinates":[-122.223347,37.477361],"type":"Point"}
}