{
  "type": "Feature",
  "properties": {
    "iso:country":"US",
    "sg:address":"9952 Las Tunas Dr",
    "sg:city":"Temple City",
    "sg:classifiers":[
        {
            "category":"Real Estate",
            "subcategory":"Real Estate Agent",
            "type":"Services"
        }
    ],
    "sg:phone":"+1 626 572 0629",
    "sg:postcode":"91780",
    "sg:province":"CA",
    "wof:name":"Century 21",
    "wof:placetype":"venue"
},
  "geometry": {"coordinates":[-118.05312,34.107678],"type":"Point"}
}