{
  "type": "Feature",
  "properties": {
    "addr:full":"12490 Mesa Verde Ct Victorville CA 92392",
    "addr:housenumber":"12490",
    "addr:postcode":"92392",
    "addr:street":"Mesa Verde Ct",
    "iso:country":"US",
    "sg:address":"12490 Mesa Verde Ct",
    "sg:city":"Victorville",
    "sg:classifiers":[
        {
            "category":"Professional",
            "type":"Services"
        }
    ],
    "sg:phone":"+1 760 947 5310",
    "sg:postcode":"92392",
    "sg:province":"CA",
    "wof:name":"Alfredo Asuzano",
    "wof:placetype":"venue"
},
  "geometry": {"coordinates":[-117.389291,34.476879],"type":"Point"}
}