{
  "type": "Feature",
  "properties": {
    "addr:full":"14724 Chadron Ave Gardena CA 90249",
    "addr:housenumber":"14724",
    "addr:postcode":"90249",
    "addr:street":"Chadron Ave",
    "iso:country":"US",
    "sg:address":"14724 Chadron Ave",
    "sg:city":"Gardena",
    "sg:classifiers":[
        {
            "category":"Communications",
            "subcategory":"Film & Video Production",
            "type":"Services"
        }
    ],
    "sg:phone":"+1 310 679 3005",
    "sg:postcode":"90249",
    "sg:province":"CA",
    "sg:tags":[
        "motion",
        "picture",
        "studio",
        "producer"
    ],
    "wof:name":"Stonehenge Pictures",
    "wof:placetype":"venue"
},
  "geometry": {"coordinates":[-118.328581,33.899087],"type":"Point"}
}