{
  "type": "Feature",
  "properties": {
    "iso:country":"US",
    "sg:address":"800 69th Ave",
    "sg:city":"Oakland",
    "sg:classifiers":[
        {
            "category":"Real Estate",
            "subcategory":"Real Estate Operator",
            "type":"Services"
        }
    ],
    "sg:phone":"+1 510 569 0239",
    "sg:postcode":"94621",
    "sg:province":"CA",
    "sg:tags":[
        "apartment"
    ],
    "wof:name":"Lion Creek Crossing Apartments",
    "wof:placetype":"venue"
},
  "geometry": {"coordinates":[-122.19817399999999,37.755609],"type":"Point"}
}