{
  "type": "Feature",
  "properties": {
    "addr:full":"1218 Rutledge Way Stockton CA 95207",
    "addr:housenumber":"1218",
    "addr:postcode":"95207",
    "addr:street":"Rutledge Way",
    "iso:country":"US",
    "sg:address":"1218 Rutledge Way",
    "sg:city":"Stockton",
    "sg:classifiers":[
        {
            "category":"Professional",
            "subcategory":"Management & Consulting",
            "type":"Services"
        }
    ],
    "sg:phone":"+1 209 955 1935",
    "sg:postcode":"95207",
    "sg:province":"CA",
    "sg:tags":[
        "consultant",
        "business"
    ],
    "wof:name":"Innovative Financial Solutions",
    "wof:placetype":"venue"
},
  "geometry": {"coordinates":[-121.32443499999999,38.008151],"type":"Point"}
}