{
  "type": "Feature",
  "properties": {
    "addr:full":"43 Live Oak Dr Petaluma CA 94952",
    "addr:housenumber":"43",
    "addr:postcode":"94952",
    "addr:street":"Live Oak Dr",
    "iso:country":"US",
    "sg:address":"43 Live Oak Dr",
    "sg:city":"Petaluma",
    "sg:classifiers":[
        {
            "category":"Home & Garden",
            "subcategory":"Carpets & Floor Coverings",
            "type":"Retail Goods"
        }
    ],
    "sg:phone":"+1 707 762 8590",
    "sg:postcode":"94952",
    "sg:province":"CA",
    "sg:tags":[
        "dealer",
        "rug"
    ],
    "wof:name":"North Bay Floors",
    "wof:placetype":"venue"
},
  "geometry": {"coordinates":[-122.711629,38.285796],"type":"Point"}
}