{
  "type": "Feature",
  "properties": {
    "addr:full":"616 Rose Dr Benicia CA 94510",
    "addr:housenumber":"616",
    "addr:postcode":"94510",
    "addr:street":"Rose Dr",
    "iso:country":"US",
    "sg:address":"616 Rose Dr",
    "sg:city":"Benicia",
    "sg:classifiers":[
        {
            "category":"Professional",
            "type":"Services"
        }
    ],
    "sg:phone":"+1 707 747 1424",
    "sg:postcode":"94510",
    "sg:province":"CA",
    "wof:name":"Sias",
    "wof:placetype":"venue"
},
  "geometry": {"coordinates":[-122.167542,38.083966],"type":"Point"}
}