{
  "type": "Feature",
  "properties": {
    "iso:country":"US",
    "sg:address":"23782 Mercury Rd",
    "sg:city":"Lake Forest",
    "sg:classifiers":[
        {
            "category":"Professional",
            "type":"Services"
        }
    ],
    "sg:phone":"+1 949 589 3112",
    "sg:postcode":"92630",
    "sg:province":"CA",
    "wof:name":"On Wing of Angels",
    "wof:placetype":"venue"
},
  "geometry": {"coordinates":[-117.714624,33.625301],"type":"Point"}
}