{
  "type": "Feature",
  "properties": {
    "addr:full":"6742 Westminster Blvd Westminster CA 92683",
    "addr:housenumber":"6742",
    "addr:postcode":"92683",
    "addr:street":"Westminster Blvd",
    "iso:country":"US",
    "sg:address":"6742 Westminster Blvd",
    "sg:city":"Westminster",
    "sg:classifiers":[
        {
            "category":"Freight",
            "type":"Transportation"
        }
    ],
    "sg:phone":"+1 714 895 7117",
    "sg:postcode":"92683",
    "sg:province":"CA",
    "sg:tags":[
        "general",
        "rental",
        "trailer",
        "utility"
    ],
    "wof:name":"U-Haul",
    "wof:placetype":"venue"
},
  "geometry": {"coordinates":[-118.00977899999999,33.758973],"type":"Point"}
}