{
  "type": "Feature",
  "properties": {
    "iso:country":"US",
    "sg:address":"2625 Aztec Dr",
    "sg:city":"Chico",
    "sg:classifiers":[
        {
            "category":"Wholesale",
            "subcategory":"Electrical",
            "type":"Manufacturing & Wholesale Goods"
        }
    ],
    "sg:phone":"+1 530 345 8992",
    "sg:postcode":"95928",
    "sg:province":"CA",
    "sg:tags":[
        "electronic"
    ],
    "wof:name":"Alternative Retail Solutions",
    "wof:placetype":"venue"
},
  "geometry": {"coordinates":[-121.819412,39.70709],"type":"Point"}
}