{
  "type": "Feature",
  "properties": {
    "iso:country":"US",
    "sg:address":"2500 Durham-Dayton Hwy",
    "sg:city":"Durham",
    "sg:classifiers":[
        {
            "category":"Shopping",
            "subcategory":"Crafts & Fabrics",
            "type":"Retail Goods"
        }
    ],
    "sg:phone":"+1 530 343 6838",
    "sg:postcode":"95938",
    "sg:province":"CA",
    "sg:tags":[
        "shop"
    ],
    "wof:name":"Casual Elegance",
    "wof:placetype":"venue"
},
  "geometry": {"coordinates":[-121.80808,39.646663],"type":"Point"}
}