{
  "type": "Feature",
  "properties": {
    "addr:full":"10959 Jersey Blvd Rancho Cucamonga CA 91730",
    "addr:housenumber":"10959",
    "addr:postcode":"91730",
    "addr:street":"Jersey Blvd",
    "iso:country":"US",
    "sg:address":"10959 Jersey Blvd",
    "sg:city":"Rancho Cucamonga",
    "sg:classifiers":[
        {
            "category":"Real Estate",
            "subcategory":"Developer",
            "type":"Services"
        }
    ],
    "sg:phone":"+1 909 581 1266",
    "sg:postcode":"91730",
    "sg:province":"CA",
    "wof:name":"Schafer Development Group",
    "wof:placetype":"venue"
},
  "geometry": {"coordinates":[-117.56863300000001,34.094553],"type":"Point"}
}