{
  "type": "Feature",
  "properties": {
    "addr:full":"6524 W Olympic Blvd Los Angeles CA 90048",
    "addr:housenumber":"6524",
    "addr:postcode":"90048",
    "addr:street":"W Olympic Blvd",
    "iso:country":"US",
    "sg:address":"6524 W Olympic Blvd",
    "sg:city":"Los Angeles",
    "sg:classifiers":[
        {
            "category":"Wholesale",
            "subcategory":"Stationery",
            "type":"Manufacturing & Wholesale Goods"
        }
    ],
    "sg:phone":"+1 323 655 4551",
    "sg:postcode":"90048",
    "sg:province":"CA",
    "sg:tags":[
        "cards",
        "greeting"
    ],
    "wof:name":"Nelsonart",
    "wof:placetype":"venue"
},
  "geometry": {"coordinates":[-118.37216100000001,34.059043],"type":"Point"}
}