{
  "type": "Feature",
  "properties": {
    "iso:country":"US",
    "sg:address":"4511 Calle Mayor",
    "sg:city":"Torrance",
    "sg:classifiers":[
        {
            "category":"Health Services",
            "subcategory":"Chiropractor",
            "type":"Services"
        }
    ],
    "sg:phone":"+1 310 373 7292",
    "sg:postcode":"90505",
    "sg:province":"CA",
    "wof:name":"Malopolski Bill DC",
    "wof:placetype":"venue"
},
  "geometry": {"coordinates":[-118.36199999999999,33.816898],"type":"Point"}
}