{
  "type": "Feature",
  "properties": {
    "addr:full":"535 W Harvard Blvd Santa Paula CA 93060",
    "addr:housenumber":"535",
    "addr:postcode":"93060",
    "addr:street":"W Harvard Blvd",
    "iso:country":"US",
    "sg:address":"535 W Harvard Blvd",
    "sg:city":"Santa Paula",
    "sg:classifiers":[
        {
            "category":"Restaurant",
            "type":"Food & Drink"
        }
    ],
    "sg:menulink":"http://www.allmenus.com/ca/santa-paula/214120-taco-bell/menu/",
    "sg:phone":"+1 805 525 4466",
    "sg:postcode":"93060",
    "sg:province":"CA",
    "sg:tags":[
        "mexican"
    ],
    "wof:name":"Taco Bell",
    "wof:placetype":"venue"
},
  "geometry": {"coordinates":[-119.080907,34.342844],"type":"Point"}
}