{
  "type": "Feature",
  "properties": {
    "iso:country":"US",
    "sg:address":"2510 M St",
    "sg:city":"Merced",
    "sg:classifiers":[
        {
            "category":"Insurance",
            "subcategory":"Insurance Agent",
            "type":"Services"
        }
    ],
    "sg:phone":"+1 209 726 0234",
    "sg:postcode":"95340",
    "sg:province":"CA",
    "wof:name":"Rucker Insurance",
    "wof:placetype":"venue"
},
  "geometry": {"coordinates":[-120.479642,37.310825],"type":"Point"}
}