{
  "type": "Feature",
  "properties": {
    "iso:country":"US",
    "sg:address":"101 Larkspur Landing Cir",
    "sg:city":"Larkspur",
    "sg:classifiers":[
        {
            "category":"Banks & Credit Unions",
            "subcategory":"Investment Brokerage",
            "type":"Services"
        }
    ],
    "sg:phone":"+1 415 464 2200",
    "sg:postcode":"94904",
    "sg:province":"CA",
    "wof:name":"Hales Capital Advisors",
    "wof:placetype":"venue"
},
  "geometry": {"coordinates":[-122.506795,37.94591],"type":"Point"}
}