{
  "type": "Feature",
  "properties": {
    "iso:country":"US",
    "sg:address":"6303 Mary Ellen Ave",
    "sg:city":"Van Nuys",
    "sg:classifiers":[
        {
            "category":"Manufacturing",
            "subcategory":"Metals",
            "type":"Manufacturing & Wholesale Goods"
        }
    ],
    "sg:phone":"+1 818 787 7739",
    "sg:postcode":"91401",
    "sg:province":"CA",
    "sg:tags":[
        "fabrication",
        "structural"
    ],
    "wof:name":"Ryals Fabrication",
    "wof:placetype":"venue"
},
  "geometry": {"coordinates":[-118.41932,34.186635],"type":"Point"}
}