{
  "type": "Feature",
  "properties": {
    "addr:full":"1253 Ravenshoe Way Chico CA 95973",
    "addr:housenumber":"1253",
    "addr:postcode":"95973",
    "addr:street":"Ravenshoe Way",
    "iso:country":"US",
    "sg:address":"1253 Ravenshoe Way",
    "sg:city":"Chico",
    "sg:classifiers":[
        {
            "category":"Health Services",
            "subcategory":"Health Practitioner",
            "type":"Services"
        }
    ],
    "sg:phone":"+1 530 345 1651",
    "sg:postcode":"95973",
    "sg:province":"CA",
    "sg:tags":[
        "medicine",
        "alternative"
    ],
    "wof:name":"Bowen Body Therapy",
    "wof:placetype":"venue"
},
  "geometry": {"coordinates":[-121.827746,39.762519],"type":"Point"}
}