{
  "type": "Feature",
  "properties": {
    "addr:full":"2015 Bridgeway Sausalito CA 94965",
    "addr:housenumber":"2015",
    "addr:postcode":"94965",
    "addr:street":"Bridgeway",
    "iso:country":"US",
    "sg:address":"2015 Bridgeway",
    "sg:city":"Sausalito",
    "sg:classifiers":[
        {
            "category":"Communications",
            "subcategory":"Film & Video Production",
            "type":"Services"
        }
    ],
    "sg:phone":"+1 415 332 3334",
    "sg:postcode":"94965",
    "sg:province":"CA",
    "sg:tags":[
        "taping"
    ],
    "wof:name":"Graphik Productions",
    "wof:placetype":"venue"
},
  "geometry": {"coordinates":[-122.495519,37.862461],"type":"Point"}
}