{
  "type": "Feature",
  "properties": {
    "addr:full":"483 Cabernet Ct Escalon CA 95320",
    "addr:housenumber":"483",
    "addr:postcode":"95320",
    "addr:street":"Cabernet Ct",
    "iso:country":"US",
    "sg:address":"483 Cabernet Ct",
    "sg:city":"Escalon",
    "sg:classifiers":[
        {
            "category":"Professional",
            "type":"Services"
        }
    ],
    "sg:phone":"+1 209 838 6595",
    "sg:postcode":"95320",
    "sg:province":"CA",
    "wof:name":"James Cadell",
    "wof:placetype":"venue"
},
  "geometry": {"coordinates":[-121.009072,37.790593],"type":"Point"}
}