{
  "type": "Feature",
  "properties": {
    "iso:country":"US",
    "sg:address":"114 Baja Sol Dr",
    "sg:city":"Scotts Valley",
    "sg:classifiers":[
        {
            "category":"Retail",
            "subcategory":"Veterinary Services",
            "type":"Services"
        }
    ],
    "sg:phone":"+1 831 438 0751",
    "sg:postcode":"95066",
    "sg:province":"CA",
    "sg:tags":[
        "veterinarian"
    ],
    "wof:name":"Mc Connell Veterinary Svc",
    "wof:placetype":"venue"
},
  "geometry": {"coordinates":[-122.037259,37.03929],"type":"Point"}
}