{
  "type": "Feature",
  "properties": {
    "iso:country":"US",
    "sg:address":"90 Great Oaks Blvd",
    "sg:city":"San Jose",
    "sg:classifiers":[
        {
            "category":"Real Estate",
            "subcategory":"Real Estate Agent",
            "type":"Services"
        },
        {
            "category":"Professional",
            "subcategory":"Business Services",
            "type":"Services"
        }
    ],
    "sg:phone":"+1 408 227 9830",
    "sg:postcode":"95119",
    "sg:province":"CA",
    "sg:tags":[
        "appraiser"
    ],
    "wof:name":"Valuation Services",
    "wof:placetype":"venue"
},
  "geometry": {"coordinates":[-121.77789900000001,37.234918],"type":"Point"}
}