{
  "type": "Feature",
  "properties": {
    "iso:country":"US",
    "sg:address":"1127 Santa Luisa Dr",
    "sg:city":"Solana Beach",
    "sg:classifiers":[
        {
            "category":"Manufacturing",
            "subcategory":"Printing",
            "type":"Manufacturing & Wholesale Goods"
        }
    ],
    "sg:phone":"+1 858 792 6944",
    "sg:postcode":"92075",
    "sg:province":"CA",
    "sg:tags":[
        "periodical"
    ],
    "wof:name":"Lifepath Publishing",
    "wof:placetype":"venue"
},
  "geometry": {"coordinates":[-117.2462,33.005965],"type":"Point"}
}