{
  "type": "Feature",
  "properties": {
    "addr:full":"6240 Fair Oaks Blvd Carmichael CA 95608",
    "addr:housenumber":"6240",
    "addr:postcode":"95608",
    "addr:street":"Fair Oaks Blvd",
    "iso:country":"US",
    "sg:address":"6240 Fair Oaks Blvd",
    "sg:city":"Carmichael",
    "sg:classifiers":[
        {
            "category":"Professional",
            "type":"Services"
        }
    ],
    "sg:phone":"+1 916 483 2717",
    "sg:postcode":"95608",
    "sg:province":"CA",
    "wof:name":"Abe Koshfam",
    "wof:placetype":"venue"
},
  "geometry": {"coordinates":[-121.32854500000001,38.616273],"type":"Point"}
}