{
  "type": "Feature",
  "properties": {
    "iso:country":"US",
    "sg:address":"438 Market St",
    "sg:city":"Santa Cruz",
    "sg:classifiers":[
        {
            "category":"Shopping",
            "subcategory":"Florist",
            "type":"Retail Goods"
        }
    ],
    "sg:phone":"+1 831 688 6315",
    "sg:postcode":"95060",
    "sg:province":"CA",
    "wof:name":"Velvet Petal",
    "wof:placetype":"venue"
},
  "geometry": {"coordinates":[-122.015145,36.985496],"type":"Point"}
}