{
  "type": "Feature",
  "properties": {
    "iso:country":"US",
    "sg:address":"27323 Jardines",
    "sg:city":"Mission Viejo",
    "sg:classifiers":[
        {
            "category":"Wholesale",
            "subcategory":"Apparel",
            "type":"Manufacturing & Wholesale Goods"
        }
    ],
    "sg:phone":"+1 949 347 0358",
    "sg:postcode":"92692",
    "sg:province":"CA",
    "sg:tags":[
        "clothing"
    ],
    "wof:name":"Galaxy Graphics",
    "wof:placetype":"venue"
},
  "geometry": {"coordinates":[-117.65356,33.56614],"type":"Point"}
}