{
  "type": "Feature",
  "properties": {
    "addr:full":"2399 N Sierra Hwy Bishop CA 93514",
    "addr:housenumber":"2399",
    "addr:postcode":"93514",
    "addr:street":"N Sierra Hwy",
    "iso:country":"US",
    "sg:address":"2399 N Sierra Hwy",
    "sg:city":"Bishop",
    "sg:classifiers":[
        {
            "category":"Shopping",
            "type":"Retail Goods"
        }
    ],
    "sg:phone":"+1 760 873 3393",
    "sg:postcode":"93514",
    "sg:province":"CA",
    "sg:tags":[
        "art",
        "gallery",
        "dealer"
    ],
    "sg:website":"www.coonsgallery.com",
    "wof:name":"Coons Gallery",
    "wof:placetype":"venue"
},
  "geometry": {"coordinates":[-118.41740799999999,37.375901],"type":"Point"}
}