{
  "type": "Feature",
  "properties": {
    "addr:full":"10615 Cullman Ave Whittier CA 90603",
    "addr:housenumber":"10615",
    "addr:postcode":"90603",
    "addr:street":"Cullman Ave",
    "iso:country":"US",
    "sg:address":"10615 Cullman Ave",
    "sg:city":"Whittier",
    "sg:classifiers":[
        {
            "category":"Education",
            "subcategory":"School",
            "type":"Public Place"
        }
    ],
    "sg:phone":"+1 562 943 5523",
    "sg:postcode":"90603",
    "sg:province":"CA",
    "wof:name":"Ellis Education",
    "wof:placetype":"venue"
},
  "geometry": {"coordinates":[-117.98400100000001,33.938801],"type":"Point"}
}