{
  "type": "Feature",
  "properties": {
    "addr:full":"1144 S Broadway Los Angeles CA 90015",
    "addr:housenumber":"1144",
    "addr:postcode":"90015",
    "addr:street":"S Broadway",
    "iso:country":"US",
    "sg:address":"1144 S Broadway",
    "sg:city":"Los Angeles",
    "sg:classifiers":[
        {
            "category":"Wholesale",
            "subcategory":"Durable Goods & Equipment",
            "type":"Manufacturing & Wholesale Goods"
        }
    ],
    "sg:phone":"+1 213 747 2927",
    "sg:postcode":"90015",
    "sg:province":"CA",
    "sg:tags":[
        "exporter"
    ],
    "wof:name":"Lucky International Trading",
    "wof:placetype":"venue"
},
  "geometry": {"coordinates":[-118.259719,34.038783],"type":"Point"}
}