{
  "type": "Feature",
  "properties": {
    "iso:country":"US",
    "sg:address":"8707 Crows Landing Rd",
    "sg:city":"Ceres",
    "sg:classifiers":[
        {
            "category":"Building & Trades",
            "subcategory":"Construction",
            "type":"Services"
        }
    ],
    "sg:phone":"+1 209 667 6143",
    "sg:postcode":"95307",
    "sg:province":"CA",
    "sg:tags":[
        "heavy"
    ],
    "wof:name":"Foiada Lazer Land Leveling",
    "wof:placetype":"venue"
},
  "geometry": {"coordinates":[-120.994693,37.507603],"type":"Point"}
}