{
  "type": "Feature",
  "properties": {
    "addr:full":"14547 Seron Ave Irvine CA 92606",
    "addr:postcode":"14547;92606",
    "addr:street":"Seron Ave",
    "iso:country":"US",
    "sg:address":"14547 Seron Ave",
    "sg:city":"Irvine",
    "sg:classifiers":[
        {
            "category":"Wholesale",
            "subcategory":"Electrical",
            "type":"Manufacturing & Wholesale Goods"
        }
    ],
    "sg:phone":"+1 949 551 4569",
    "sg:postcode":"92606",
    "sg:province":"CA",
    "sg:tags":[
        "equipment",
        "electronic",
        "consultant"
    ],
    "wof:name":"Maheta Company",
    "wof:placetype":"venue"
},
  "geometry": {"coordinates":[-117.796206,33.709797],"type":"Point"}
}