{
  "type": "Feature",
  "properties": {
    "iso:country":"US",
    "sg:address":"968 N Grand Ave",
    "sg:city":"Covina",
    "sg:classifiers":[
        {
            "category":"Professional",
            "type":"Services"
        }
    ],
    "sg:phone":"+1 626 339 4144",
    "sg:postcode":"91724",
    "sg:province":"CA",
    "wof:name":"Barenaked Tanning",
    "wof:placetype":"venue"
},
  "geometry": {"coordinates":[-117.872387,34.09665],"type":"Point"}
}