{
  "type": "Feature",
  "properties": {
    "iso:country":"US",
    "sg:address":"2573 Navarra Dr",
    "sg:city":"Carlsbad",
    "sg:classifiers":[
        {
            "category":"Professional",
            "type":"Services"
        }
    ],
    "sg:phone":"+1 760 632 8590",
    "sg:postcode":"92009",
    "sg:province":"CA",
    "wof:name":"Streamline Picturescom Inc",
    "wof:placetype":"venue"
},
  "geometry": {"coordinates":[-117.250547,33.088789],"type":"Point"}
}