{
  "type": "Feature",
  "properties": {
    "iso:country":"US",
    "sg:address":"1525 Howard St",
    "sg:city":"San Francisco",
    "sg:classifiers":[
        {
            "category":"Autos & Motor Vehicles",
            "subcategory":"Automobile Sales",
            "type":"Retail Goods"
        },
        {
            "category":"Retail",
            "subcategory":"Auto Repair",
            "type":"Services"
        }
    ],
    "sg:phone":"+1 415 241 8100",
    "sg:postcode":"94103",
    "sg:province":"CA",
    "sg:tags":[
        "car"
    ],
    "sg:website":"www.royalmotorsales.com",
    "wof:name":"Royal Motor Sales of San Francisco",
    "wof:placetype":"venue"
},
  "geometry": {"coordinates":[-122.416239,37.772491],"type":"Point"}
}