{
  "type": "Feature",
  "properties": {
    "addr:full":"2801 W Ball Rd Ste 1 Anaheim CA 92804",
    "addr:housenumber":"2801",
    "addr:postcode":"92804",
    "addr:street":"W Ball Rd Ste 1",
    "iso:country":"US",
    "sg:address":"2801 W Ball Rd Ste 1",
    "sg:city":"Anaheim",
    "sg:classifiers":[
        {
            "category":"Food & Beverages",
            "subcategory":"Liquor & Beverages",
            "type":"Retail Goods"
        }
    ],
    "sg:phone":"+1 714 527 1337",
    "sg:postcode":"92804",
    "sg:province":"CA",
    "sg:tags":[
        "beer",
        "spirit",
        "wine"
    ],
    "wof:name":"Lincoln Liquor Store",
    "wof:placetype":"venue"
},
  "geometry": {"coordinates":[-117.985001,33.817501],"type":"Point"}
}