{
  "type": "Feature",
  "properties": {
    "addr:full":"2208 6th St Ceres CA 95307",
    "addr:housenumber":"2208",
    "addr:postcode":"95307",
    "addr:street":"6Th St",
    "iso:country":"US",
    "sg:address":"2208 6th St",
    "sg:city":"Ceres",
    "sg:classifiers":[
        {
            "category":"Professional",
            "subcategory":"Employment Agencies",
            "type":"Services"
        }
    ],
    "sg:phone":"+1 209 394 7141",
    "sg:postcode":"95307",
    "sg:province":"CA",
    "sg:tags":[
        "labor",
        "contractor"
    ],
    "wof:name":"Carranza Contract Labor",
    "wof:placetype":"venue"
},
  "geometry": {"coordinates":[-120.950731,37.597726],"type":"Point"}
}