{
  "type": "Feature",
  "properties": {
    "iso:country":"US",
    "sg:address":"23517 Frigate Ave",
    "sg:city":"Carson",
    "sg:classifiers":[
        {
            "category":"Local Transit",
            "type":"Transportation"
        }
    ],
    "sg:phone":"+1 310 847 7888",
    "sg:postcode":"90745",
    "sg:province":"CA",
    "sg:tags":[
        "passenger"
    ],
    "wof:name":"Angels Care Medical Transport",
    "wof:placetype":"venue"
},
  "geometry": {"coordinates":[-118.277923,33.811071],"type":"Point"}
}