{
  "type": "Feature",
  "properties": {
    "iso:country":"US",
    "sg:address":"1755 N Vermont Ave",
    "sg:city":"Los Angeles",
    "sg:classifiers":[
        {
            "category":"Restaurant",
            "type":"Food & Drink"
        }
    ],
    "sg:phone":"+1 323 953 8900",
    "sg:postcode":"90027",
    "sg:province":"CA",
    "sg:tags":[
        "sushi",
        "bar"
    ],
    "wof:name":"Niko Niko Sushi",
    "wof:placetype":"venue"
},
  "geometry": {"coordinates":[-118.291782,34.103022],"type":"Point"}
}