{
  "type": "Feature",
  "properties": {
    "addr:full":"43453 7th St E Lancaster CA 93535",
    "addr:housenumber":"43453",
    "addr:postcode":"93535",
    "addr:street":"7Th St E",
    "iso:country":"US",
    "sg:address":"43453 7th St E",
    "sg:city":"Lancaster",
    "sg:classifiers":[
        {
            "category":"Building & Trades",
            "subcategory":"Construction",
            "type":"Services"
        }
    ],
    "sg:phone":"+1 661 942 3808",
    "sg:postcode":"93535",
    "sg:province":"CA",
    "sg:tags":[
        "contractor"
    ],
    "wof:name":"Adair Construction",
    "wof:placetype":"venue"
},
  "geometry": {"coordinates":[-118.11797799999999,34.672315],"type":"Point"}
}