{
  "type": "Feature",
  "properties": {
    "addr:full":"1594 N San Antonio Ave Upland CA 91786",
    "addr:housenumber":"1594",
    "addr:postcode":"91786",
    "addr:street":"N San Antonio Ave",
    "iso:country":"US",
    "sg:address":"1594 N San Antonio Ave",
    "sg:city":"Upland",
    "sg:classifiers":[
        {
            "category":"Professional",
            "subcategory":"Management & Consulting",
            "type":"Services"
        }
    ],
    "sg:phone":"+1 909 982 7477",
    "sg:postcode":"91786",
    "sg:province":"CA",
    "sg:tags":[
        "retail",
        "direct",
        "sales"
    ],
    "wof:name":"Soft Drinks Automated",
    "wof:placetype":"venue"
},
  "geometry": {"coordinates":[-117.66081200000001,34.120215],"type":"Point"}
}