{
  "type": "Feature",
  "properties": {
    "addr:full":"180 S Dolliver St Pismo Beach CA 93449",
    "addr:housenumber":"180",
    "addr:postcode":"93449",
    "addr:street":"S Dolliver St",
    "iso:country":"US",
    "sg:address":"180 S Dolliver St",
    "sg:city":"Pismo Beach",
    "sg:classifiers":[
        {
            "category":"Retail",
            "subcategory":"Auto Repair",
            "type":"Services"
        }
    ],
    "sg:phone":"+1 805 773 3868",
    "sg:postcode":"93449",
    "sg:province":"CA",
    "sg:tags":[
        "recreational",
        "vehicle"
    ],
    "wof:name":"Pismo Coast Rv Svc",
    "wof:placetype":"venue"
},
  "geometry": {"coordinates":[-120.63476300000001,35.133244],"type":"Point"}
}