{
  "type": "Feature",
  "properties": {
    "iso:country":"US",
    "sg:address":"180 S Dolliver St",
    "sg:city":"Pismo Beach",
    "sg:classifiers":[
        {
            "category":"Retail",
            "subcategory":"Auto Repair",
            "type":"Services"
        }
    ],
    "sg:phone":"+1 805 773 3868",
    "sg:postcode":"93449",
    "sg:province":"CA",
    "sg:tags":[
        "recreational",
        "vehicle"
    ],
    "wof:name":"Pismo Coast Rv Svc",
    "wof:placetype":"venue"
},
  "geometry": {"coordinates":[-120.634763,35.133244],"type":"Point"}
}