{
  "type": "Feature",
  "properties": {
    "addr:full":"145 S Chaparral Ct Anaheim CA 92808",
    "addr:housenumber":"145",
    "addr:postcode":"92808",
    "addr:street":"S Chaparral Ct",
    "iso:country":"US",
    "sg:address":"145 S Chaparral Ct",
    "sg:city":"Anaheim",
    "sg:classifiers":[
        {
            "category":"Health Services",
            "subcategory":"Doctor",
            "type":"Services"
        }
    ],
    "sg:phone":"+1 714 974 2621",
    "sg:postcode":"92808",
    "sg:province":"CA",
    "sg:tags":[
        "medical"
    ],
    "wof:name":"Rutland Medical Group",
    "wof:placetype":"venue"
},
  "geometry": {"coordinates":[-117.744652,33.865345],"type":"Point"}
}