{
  "type": "Feature",
  "properties": {
    "iso:country":"US",
    "sg:address":"12953 Ventura Blvd",
    "sg:city":"Studio City",
    "sg:classifiers":[
        {
            "category":"Restaurant",
            "type":"Food & Drink"
        }
    ],
    "sg:phone":"+1 818 990 9559",
    "sg:postcode":"91604",
    "sg:province":"CA",
    "wof:name":"Iroha Sushi of Tokyo",
    "wof:placetype":"venue"
},
  "geometry": {"coordinates":[-118.414001,34.1451],"type":"Point"}
}