{
  "type": "Feature",
  "properties": {
    "iso:country":"US",
    "sg:address":"1123 Doverwood St",
    "sg:city":"Corona",
    "sg:classifiers":[
        {
            "category":"Manufacturing",
            "subcategory":"Retail Goods",
            "type":"Manufacturing & Wholesale Goods"
        }
    ],
    "sg:phone":"+1 951 371 4913",
    "sg:postcode":"92880",
    "sg:province":"CA",
    "sg:tags":[
        "product",
        "mfg"
    ],
    "wof:name":"Flyingfoamcom",
    "wof:placetype":"venue"
},
  "geometry": {"coordinates":[-117.587039,33.909034],"type":"Point"}
}