{
  "type": "Feature",
  "properties": {
    "iso:country":"US",
    "sg:address":"18956 Brookhurst St",
    "sg:city":"Fountain Valley",
    "sg:classifiers":[
        {
            "category":"Arts & Performance",
            "subcategory":"Arts Center",
            "type":"Entertainment"
        },
        {
            "category":"Community Center",
            "subcategory":"Social",
            "type":"Public Place"
        }
    ],
    "sg:phone":"+1 714 963 2110",
    "sg:postcode":"92708",
    "sg:province":"CA",
    "sg:tags":[
        "club",
        "performing"
    ],
    "sg:website":"www.bcsdance.com",
    "wof:name":"Beach Cities Stars Dance Studio",
    "wof:placetype":"venue"
},
  "geometry": {"coordinates":[-117.954002,33.687199],"type":"Point"}
}