{
  "type": "Feature",
  "properties": {
    "addr:full":"1603 Aviation Blvd Redondo Beach CA 90278",
    "addr:housenumber":"1603",
    "addr:postcode":"90278",
    "addr:street":"Aviation Blvd",
    "iso:country":"US",
    "sg:address":"1603 Aviation Blvd",
    "sg:city":"Redondo Beach",
    "sg:classifiers":[
        {
            "category":"Freight",
            "type":"Transportation"
        },
        {
            "category":"Airline",
            "type":"Transportation"
        }
    ],
    "sg:phone":"+1 310 374 2042",
    "sg:postcode":"90278",
    "sg:province":"CA",
    "sg:tags":[
        "delivery",
        "courier",
        "air"
    ],
    "wof:name":"Cgi Worldwide Express",
    "wof:placetype":"venue"
},
  "geometry": {"coordinates":[-118.382616,33.869794],"type":"Point"}
}