{
  "type": "Feature",
  "properties": {
    "iso:country":"US",
    "sg:address":"4051 Lorenzo Ter",
    "sg:city":"Fremont",
    "sg:classifiers":[
        {
            "category":"Travel",
            "subcategory":"Travel Agent",
            "type":"Entertainment"
        }
    ],
    "sg:phone":"+1 510 796 3957",
    "sg:postcode":"94536",
    "sg:province":"CA",
    "sg:tags":[
        "agency"
    ],
    "wof:name":"Happy Travels",
    "wof:placetype":"venue"
},
  "geometry": {"coordinates":[-122.02433499999999,37.565467],"type":"Point"}
}