{
  "type": "Feature",
  "properties": {
    "iso:country":"US",
    "sg:address":"4096 Horizon Ln",
    "sg:city":"San Luis Obispo",
    "sg:classifiers":[
        {
            "category":"Autos & Motor Vehicles",
            "subcategory":"Motorcycle Sales",
            "type":"Retail Goods"
        }
    ],
    "sg:phone":"+1 805 541 0129",
    "sg:postcode":"93401",
    "sg:province":"CA",
    "sg:tags":[
        "car",
        "golf",
        "cart"
    ],
    "wof:name":"Central Coast Golf Cars",
    "wof:placetype":"venue"
},
  "geometry": {"coordinates":[-120.666094,35.242846],"type":"Point"}
}