{
  "type": "Feature",
  "properties": {
    "iso:country":"US",
    "sg:address":"210 W Arrow Hwy",
    "sg:city":"San Dimas",
    "sg:classifiers":[
        {
            "category":"Professional",
            "type":"Services"
        }
    ],
    "sg:phone":"+1 909 630 5838",
    "sg:postcode":"91773",
    "sg:province":"CA",
    "wof:name":"Joy Networks Inc",
    "wof:placetype":"venue"
},
  "geometry": {"coordinates":[-117.80957100000001,34.102886],"type":"Point"}
}