{
  "type": "Feature",
  "properties": {
    "addr:full":"1757 Landess Ave Milpitas CA 95035",
    "addr:housenumber":"1757",
    "addr:postcode":"95035",
    "addr:street":"Landess Ave",
    "iso:country":"US",
    "sg:address":"1757 Landess Ave",
    "sg:city":"Milpitas",
    "sg:classifiers":[
        {
            "category":"Health Services",
            "subcategory":"Optometrist",
            "type":"Services"
        }
    ],
    "sg:phone":"+1 408 262 1221",
    "sg:postcode":"95035",
    "sg:province":"CA",
    "wof:name":"Sophie Dao OD",
    "wof:placetype":"venue"
},
  "geometry": {"coordinates":[-121.873743,37.416522],"type":"Point"}
}