{
  "type": "Feature",
  "properties": {
    "iso:country":"US",
    "sg:address":"1491 Creston Rd",
    "sg:city":"Paso Robles",
    "sg:classifiers":[
        {
            "category":"Wholesale",
            "subcategory":"Farm Supplies",
            "type":"Manufacturing & Wholesale Goods"
        }
    ],
    "sg:phone":"+1 805 239 3880",
    "sg:postcode":"93446",
    "sg:province":"CA",
    "sg:tags":[
        "feed"
    ],
    "wof:name":"Lemos Feed & Pet Supply",
    "wof:placetype":"venue"
},
  "geometry": {"coordinates":[-120.659144,35.61642],"type":"Point"}
}