{
  "type": "Feature",
  "properties": {
    "addr:full":"8333 Hercules St La Mesa CA 91942",
    "addr:housenumber":"8333",
    "addr:postcode":"91942",
    "addr:street":"Hercules St",
    "iso:country":"US",
    "sg:address":"8333 Hercules St",
    "sg:city":"La Mesa",
    "sg:classifiers":[
        {
            "category":"Autos & Motor Vehicles",
            "subcategory":"Automobile Sales",
            "type":"Retail Goods"
        }
    ],
    "sg:phone":"+1 619 463 9321",
    "sg:postcode":"91942",
    "sg:province":"CA",
    "sg:tags":[
        "car",
        "dealer"
    ],
    "sg:website":"www.carlburger.com",
    "wof:name":"Carl Burger's Dodge World",
    "wof:placetype":"venue"
},
  "geometry": {"coordinates":[-117.018016,32.773312],"type":"Point"}
}