{
  "type": "Feature",
  "properties": {
    "iso:country":"US",
    "sg:address":"625 N Salsipuedes St",
    "sg:city":"Santa Barbara",
    "sg:classifiers":[
        {
            "category":"Building & Trades",
            "subcategory":"Plumbing",
            "type":"Services"
        }
    ],
    "sg:phone":"+1 805 963 1818",
    "sg:postcode":"93103",
    "sg:province":"CA",
    "sg:tags":[
        "contractor"
    ],
    "wof:name":"A Tri-County Leak Detection",
    "wof:placetype":"venue"
},
  "geometry": {"coordinates":[-119.691064,34.424735],"type":"Point"}
}