{
  "type": "Feature",
  "properties": {
    "addr:full":"1711 Hamilton Ave San Jose CA 95125",
    "addr:housenumber":"1711",
    "addr:postcode":"95125",
    "addr:street":"Hamilton Ave",
    "iso:country":"US",
    "sg:address":"1711 Hamilton Ave",
    "sg:city":"San Jose",
    "sg:classifiers":[
        {
            "category":"Health Services",
            "subcategory":"Doctor",
            "type":"Services"
        }
    ],
    "sg:phone":"+1 408 266 3013",
    "sg:postcode":"95125",
    "sg:province":"CA",
    "sg:tags":[
        "dentist"
    ],
    "wof:name":"Karen Ho DDS",
    "wof:placetype":"venue"
},
  "geometry": {"coordinates":[-121.91792,37.294477],"type":"Point"}
}