{
  "type": "Feature",
  "properties": {
    "addr:full":"3345 Wilshire Boulevard Los Angeles CA 90010",
    "addr:housenumber":"3345",
    "addr:postcode":"90010",
    "addr:street":"Wilshire Boulevard",
    "iso:country":"US",
    "sg:address":"3345 Wilshire Boulevard",
    "sg:city":"Los Angeles",
    "sg:classifiers":[
        {
            "category":"Professional",
            "subcategory":"Lawyer & Legal Services",
            "type":"Services"
        }
    ],
    "sg:phone":"+1 213 487 8950",
    "sg:postcode":"90010",
    "sg:province":"CA",
    "wof:name":"Singer Sheldon F Atty",
    "wof:placetype":"venue"
},
  "geometry": {"coordinates":[-118.296108,34.061829],"type":"Point"}
}