{
  "type": "Feature",
  "properties": {
    "addr:full":"25624 Sherwood Dr Pioneer CA 95666",
    "addr:housenumber":"25624",
    "addr:postcode":"95666",
    "addr:street":"Sherwood Dr",
    "iso:country":"US",
    "sg:address":"25624 Sherwood Dr",
    "sg:city":"Pioneer",
    "sg:classifiers":[
        {
            "category":"Building & Trades",
            "subcategory":"Construction",
            "type":"Services"
        }
    ],
    "sg:phone":"+1 209 295 4580",
    "sg:postcode":"95666",
    "sg:province":"CA",
    "sg:tags":[
        "general",
        "contractor"
    ],
    "wof:name":"Bill Heissenbuttel Construct",
    "wof:placetype":"venue"
},
  "geometry": {"coordinates":[-120.550135,38.480849],"type":"Point"}
}