{
  "type": "Feature",
  "properties": {
    "iso:country":"US",
    "sg:address":"840 Herndon Ave",
    "sg:city":"Clovis",
    "sg:classifiers":[
        {
            "category":"Restaurant",
            "type":"Food & Drink"
        }
    ],
    "sg:phone":"+1 559 322 6899",
    "sg:postcode":"93612",
    "sg:province":"CA",
    "wof:name":"Kam Pai Japanese Restaurant",
    "wof:placetype":"venue"
},
  "geometry": {"coordinates":[-119.703473,36.83739],"type":"Point"}
}