{
  "type": "Feature",
  "properties": {
    "iso:country":"US",
    "sg:address":"15901 Red Hill Ave # 100",
    "sg:city":"Tustin",
    "sg:classifiers":[
        {
            "category":"Banks & Credit Unions",
            "subcategory":"Investment Brokerage",
            "type":"Services"
        },
        {
            "category":"Insurance",
            "subcategory":"Hazard Insurance",
            "type":"Services"
        }
    ],
    "sg:phone":"+1 714 505 7000",
    "sg:postcode":"92780",
    "sg:province":"CA",
    "sg:tags":[
        "agent",
        "resume"
    ],
    "sg:website":"http://www.wgbib.com",
    "wof:name":"Wood Gutmann & Bogart Insurance Brokers",
    "wof:placetype":"venue"
},
  "geometry": {"coordinates":[-117.836578,33.712349],"type":"Point"}
}