{
  "type": "Feature",
  "properties": {
    "addr:full":"24400 Old 44 Dr Millville CA 96062",
    "addr:housenumber":"24400",
    "addr:postcode":"96062",
    "addr:street":"Old 44 Dr",
    "iso:country":"US",
    "sg:address":"24400 Old 44 Dr",
    "sg:city":"Millville",
    "sg:classifiers":[
        {
            "category":"Personal",
            "subcategory":"Beauty Salon",
            "type":"Services"
        }
    ],
    "sg:phone":"+1 530 547 4441",
    "sg:postcode":"96062",
    "sg:province":"CA",
    "wof:name":"Salon 44",
    "wof:placetype":"venue"
},
  "geometry": {"coordinates":[-122.175049,40.543041],"type":"Point"}
}