{
  "type": "Feature",
  "properties": {
    "iso:country":"US",
    "sg:address":"729 W 16th St Suite C-3",
    "sg:city":"Costa Mesa",
    "sg:classifiers":[
        {
            "category":"Shopping",
            "subcategory":"Party Supplies",
            "type":"Retail Goods"
        }
    ],
    "sg:phone":"+1 877 373 7769",
    "sg:postcode":"92627",
    "sg:province":"CA",
    "sg:website":"www.dressmyparty.com/",
    "wof:name":"Dress My Party",
    "wof:placetype":"venue"
},
  "geometry": {"coordinates":[-117.92738900000001,33.632493],"type":"Point"}
}