{
  "type": "Feature",
  "properties": {
    "addr:full":"407 W Imperial Hwy Brea CA 92821",
    "addr:housenumber":"407",
    "addr:postcode":"92821",
    "addr:street":"W Imperial Hwy",
    "iso:country":"US",
    "sg:address":"407 W Imperial Hwy",
    "sg:city":"Brea",
    "sg:classifiers":[
        {
            "category":"Banks & Credit Unions",
            "subcategory":"Bank",
            "type":"Services"
        }
    ],
    "sg:phone":"+1 714 529 6893",
    "sg:postcode":"92821",
    "sg:province":"CA",
    "sg:tags":[
        "depository",
        "banking"
    ],
    "wof:name":"Check Into Cash",
    "wof:placetype":"venue"
},
  "geometry": {"coordinates":[-117.90468300000001,33.917449],"type":"Point"}
}