{
  "type": "Feature",
  "properties": {
    "iso:country":"US",
    "sg:address":"25613 Dollar St Ste 8",
    "sg:city":"Hayward",
    "sg:classifiers":[
        {
            "category":"Retail",
            "subcategory":"Auto Repair",
            "type":"Services"
        }
    ],
    "sg:phone":"+1 510 886 8264",
    "sg:postcode":"94544",
    "sg:province":"CA",
    "wof:name":"ABC Mustang",
    "wof:placetype":"venue"
},
  "geometry": {"coordinates":[-122.071022,37.653727],"type":"Point"}
}