{
  "type": "Feature",
  "properties": {
    "addr:full":"2011 Macarthur Blvd Oakland CA 94602",
    "addr:housenumber":"2011",
    "addr:postcode":"94602",
    "addr:street":"Macarthur Blvd",
    "iso:country":"US",
    "sg:address":"2011 Macarthur Blvd",
    "sg:city":"Oakland",
    "sg:classifiers":[
        {
            "category":"Utilities",
            "subcategory":"Mobile Phone",
            "type":"Services"
        }
    ],
    "sg:phone":"+1 510 531 4300",
    "sg:postcode":"94602",
    "sg:province":"CA",
    "sg:tags":[
        "communication",
        "radiotelephone"
    ],
    "wof:name":"Choice Wireless",
    "wof:placetype":"venue"
},
  "geometry": {"coordinates":[-122.218575,37.800942],"type":"Point"}
}