{
  "type": "Feature",
  "properties": {
    "iso:country":"US",
    "sg:address":"10511 Polo Glen Dr",
    "sg:city":"Bakersfield",
    "sg:classifiers":[
        {
            "category":"Manufacturing",
            "subcategory":"Metals",
            "type":"Manufacturing & Wholesale Goods"
        }
    ],
    "sg:phone":"+1 661 587 8880",
    "sg:postcode":"93312",
    "sg:province":"CA",
    "sg:tags":[
        "steel",
        "processing"
    ],
    "wof:name":"US Steel Tubular Products",
    "wof:placetype":"venue"
},
  "geometry": {"coordinates":[-119.118986,35.402849],"type":"Point"}
}