{
  "type": "Feature",
  "properties": {
    "iso:country":"US",
    "sg:address":"23453 Golden Springs Dr",
    "sg:city":"Diamond Bar",
    "sg:classifiers":[
        {
            "category":"Insurance",
            "subcategory":"Insurance Agent",
            "type":"Services"
        }
    ],
    "sg:phone":"+1 909 396 0113",
    "sg:postcode":"91765",
    "sg:province":"CA",
    "sg:website":"www.allstate.com",
    "wof:name":"Allstate Insurance",
    "wof:placetype":"venue"
},
  "geometry": {"coordinates":[-117.808844,34.018862],"type":"Point"}
}