{
  "type": "Feature",
  "properties": {
    "addr:full":"51 Issaquah Dock Sausalito CA 94965",
    "addr:housenumber":"51",
    "addr:postcode":"94965",
    "addr:street":"Issaquah Dock",
    "iso:country":"US",
    "sg:address":"51 Issaquah Dock",
    "sg:city":"Sausalito",
    "sg:classifiers":[
        {
            "category":"Professional",
            "subcategory":"Management & Consulting",
            "type":"Services"
        }
    ],
    "sg:phone":"+1 415 331 0269",
    "sg:postcode":"94965",
    "sg:province":"CA",
    "sg:tags":[
        "consultant",
        "search",
        "executive"
    ],
    "wof:name":"EA Search",
    "wof:placetype":"venue"
},
  "geometry": {"coordinates":[-122.504278,37.873605],"type":"Point"}
}