{
  "type": "Feature",
  "properties": {
    "iso:country":"US",
    "sg:address":"736 11th St",
    "sg:city":"Colusa",
    "sg:phone":"+1 530 458 4227",
    "sg:postcode":"95932",
    "sg:province":"CA",
    "sg:tags":[
        "farm",
        "rice"
    ],
    "wof:name":"Baber Farms Inc",
    "wof:placetype":"venue"
},
  "geometry": {"coordinates":[-122.018006,39.211117],"type":"Point"}
}