{
  "type": "Feature",
  "properties": {
    "iso:country":"US",
    "sg:address":"7646 Van Nuys Blvd",
    "sg:city":"Van Nuys",
    "sg:classifiers":[
        {
            "category":"Health Services",
            "subcategory":"Doctor",
            "type":"Services"
        }
    ],
    "sg:phone":"+1 818 787 8840",
    "sg:postcode":"91405",
    "sg:province":"CA",
    "wof:name":"Acutherapy",
    "wof:placetype":"venue"
},
  "geometry": {"coordinates":[-118.448516,34.209574],"type":"Point"}
}