{
  "type": "Feature",
  "properties": {
    "iso:country":"US",
    "sg:address":"864 W Manning Ave",
    "sg:city":"Reedley",
    "sg:classifiers":[
        {
            "category":"Restaurant",
            "type":"Food & Drink"
        }
    ],
    "sg:menulink":"http://www.allmenus.com/ca/reedley/197728-kfc---kentucky-fried-chicken/menu/",
    "sg:phone":"+1 559 638 1041",
    "sg:postcode":"93654",
    "sg:province":"CA",
    "sg:tags":[
        "american",
        "chicken"
    ],
    "wof:name":"KFC - Kentucky Fried Chicken",
    "wof:placetype":"venue"
},
  "geometry": {"coordinates":[-119.45733,36.60429],"type":"Point"}
}