{
  "type": "Feature",
  "properties": {
    "addr:full":"40477 Murrieta Hot Springs Rd Murrieta CA 92563",
    "addr:housenumber":"40477",
    "addr:postcode":"92563",
    "addr:street":"Murrieta Hot Springs Rd",
    "iso:country":"US",
    "sg:address":"40477 Murrieta Hot Springs Rd",
    "sg:city":"Murrieta",
    "sg:classifiers":[
        {
            "category":"Shopping",
            "type":"Retail Goods"
        }
    ],
    "sg:phone":"+1 951 698 2464",
    "sg:postcode":"92563",
    "sg:province":"CA",
    "sg:tags":[
        "pet",
        "shop"
    ],
    "wof:name":"Pet Stop",
    "wof:placetype":"venue"
},
  "geometry": {"coordinates":[-117.178934,33.556448],"type":"Point"}
}