{
  "type": "Feature",
  "properties": {
    "iso:country":"US",
    "sg:address":"105 H St",
    "sg:city":"Bakersfield",
    "sg:classifiers":[
        {
            "category":"Real Estate",
            "subcategory":"Surveying",
            "type":"Services"
        }
    ],
    "sg:phone":"+1 661 327 1309",
    "sg:postcode":"93304",
    "sg:province":"CA",
    "sg:tags":[
        "surveyor"
    ],
    "wof:name":"Abacus Surveying",
    "wof:placetype":"venue"
},
  "geometry": {"coordinates":[-119.02138100000001,35.355869],"type":"Point"}
}