{
  "type": "Feature",
  "properties": {
    "iso:country":"US",
    "sg:address":"1226 11th St Ste B",
    "sg:city":"Modesto",
    "sg:classifiers":[
        {
            "category":"Organizations",
            "subcategory":"Non-profit Organization",
            "type":"Services"
        },
        {
            "category":"Science Facility",
            "type":"Public Place"
        }
    ],
    "sg:phone":"+1 209 576 1608",
    "sg:postcode":"95354",
    "sg:province":"CA",
    "sg:tags":[
        "development",
        "laboratories-research",
        "foundations-educational",
        "philanthropic",
        "research"
    ],
    "sg:website":"http://www.stanislauscommunityfoundation.org",
    "wof:name":"Stanislaus Community Foundation",
    "wof:placetype":"venue"
},
  "geometry": {"coordinates":[-121.00191700000001,37.643396],"type":"Point"}
}