{
  "type": "Feature",
  "properties": {
    "iso:country":"US",
    "sg:address":"5046 N West Ave",
    "sg:city":"Fresno",
    "sg:classifiers":[
        {
            "category":"Personal",
            "subcategory":"Beauty Salon",
            "type":"Services"
        }
    ],
    "sg:phone":"+1 559 436 1322",
    "sg:postcode":"93711",
    "sg:province":"CA",
    "wof:name":"Santa Cruz Paul",
    "wof:placetype":"venue"
},
  "geometry": {"coordinates":[-119.82631000000001,36.810345],"type":"Point"}
}