{
  "type": "Feature",
  "properties": {
    "iso:country":"US",
    "sg:address":"18 Technology Drive",
    "sg:city":"Irvine",
    "sg:classifiers":[
        {
            "category":"Professional",
            "type":"Services"
        }
    ],
    "sg:phone":"+1 949 753 1300",
    "sg:postcode":"92618",
    "sg:province":"CA",
    "sg:tags":[
        "caterer"
    ],
    "wof:name":"Kate Kennedy's Catering",
    "wof:placetype":"venue"
},
  "geometry": {"coordinates":[-117.73715799999999,33.650226],"type":"Point"}
}