{
  "type": "Feature",
  "properties": {
    "iso:country":"US",
    "sg:address":"431 Sperry Rd",
    "sg:city":"Stockton",
    "sg:classifiers":[
        {
            "category":"Wholesale",
            "subcategory":"Metals & Minerals",
            "type":"Manufacturing & Wholesale Goods"
        }
    ],
    "sg:phone":"+1 209 982 4870",
    "sg:postcode":"95206",
    "sg:province":"CA",
    "sg:tags":[
        "powder"
    ],
    "sg:website":"www.valimet.com",
    "wof:name":"Valimet Inc",
    "wof:placetype":"venue"
},
  "geometry": {"coordinates":[-121.268321,37.898469],"type":"Point"}
}