{
  "type": "Feature",
  "properties": {
    "addr:full":"9 Chatham Ct Newport Beach CA 92660",
    "addr:housenumber":"9",
    "addr:postcode":"92660",
    "addr:street":"Chatham Ct",
    "iso:country":"US",
    "sg:address":"9 Chatham Ct",
    "sg:city":"Newport Beach",
    "sg:classifiers":[
        {
            "category":"Professional",
            "type":"Services"
        }
    ],
    "sg:phone":"+1 949 759 9998",
    "sg:postcode":"92660",
    "sg:province":"CA",
    "sg:tags":[
        "establishment"
    ],
    "wof:name":"Td I Thernmal Tech",
    "wof:placetype":"venue"
},
  "geometry": {"coordinates":[-117.866242,33.631584],"type":"Point"}
}