{
  "type": "Feature",
  "properties": {
    "addr:full":"13471 Running Gold Rd Sutter Creek CA 95685",
    "addr:housenumber":"13471",
    "addr:postcode":"95685",
    "addr:street":"Running Gold Rd",
    "iso:country":"US",
    "sg:address":"13471 Running Gold Rd",
    "sg:city":"Sutter Creek",
    "sg:classifiers":[
        {
            "category":"Building & Trades",
            "subcategory":"Electrical",
            "type":"Services"
        }
    ],
    "sg:phone":"+1 209 267 0405",
    "sg:postcode":"95685",
    "sg:province":"CA",
    "sg:tags":[
        "electrical",
        "contractor"
    ],
    "wof:name":"Advanced Electric",
    "wof:placetype":"venue"
},
  "geometry": {"coordinates":[-120.771182,38.381682],"type":"Point"}
}