{
  "type": "Feature",
  "properties": {
    "addr:full":"2510 Foothill Blvd La Verne CA 91750",
    "addr:housenumber":"2510",
    "addr:postcode":"91750",
    "addr:street":"Foothill Blvd",
    "iso:country":"US",
    "sg:address":"2510 Foothill Blvd",
    "sg:city":"La Verne",
    "sg:classifiers":[
        {
            "category":"Autos & Motor Vehicles",
            "subcategory":"Fuel & Gas Station",
            "type":"Retail Goods"
        }
    ],
    "sg:phone":"+1 909 593 2507",
    "sg:postcode":"91750",
    "sg:province":"CA",
    "sg:tags":[
        "oil"
    ],
    "wof:name":"Shell",
    "wof:placetype":"venue"
},
  "geometry": {"coordinates":[-117.75902499999999,34.111221],"type":"Point"}
}