{
  "type": "Feature",
  "properties": {
    "addr:full":"1028 W Kirkwall Rd Azusa CA 91702",
    "addr:housenumber":"1028",
    "addr:postcode":"91702",
    "addr:street":"W Kirkwall Rd",
    "iso:country":"US",
    "sg:address":"1028 W Kirkwall Rd",
    "sg:city":"Azusa",
    "sg:classifiers":[
        {
            "category":"Retail",
            "subcategory":"Repair Shop",
            "type":"Services"
        },
        {
            "category":"Building & Trades",
            "subcategory":"Construction",
            "type":"Services"
        },
        {
            "category":"Building & Trades",
            "subcategory":"Electrical",
            "type":"Services"
        },
        {
            "category":"Train Station",
            "subcategory":"Light Rail",
            "type":"Transportation"
        },
        {
            "category":"Professional",
            "subcategory":"Advertising",
            "type":"Services"
        },
        {
            "category":"Commercial Area",
            "type":"Public Place"
        },
        {
            "category":"Manufacturing",
            "subcategory":"Signs",
            "type":"Manufacturing & Wholesale Goods"
        }
    ],
    "sg:phone":"+1 626 334 5600",
    "sg:postcode":"91702",
    "sg:province":"CA",
    "sg:tags":[
        "hanger",
        "electrician",
        "electric",
        "specialty",
        "industrial",
        "lighting",
        "contractors-commercial",
        "maintenance",
        "front",
        "signs-erectors",
        "crane",
        "store",
        "signs-maintenance"
    ],
    "sg:website":"http://www.bksigns.com",
    "wof:name":"B. K. Signs Inc.",
    "wof:placetype":"venue"
},
  "geometry": {"coordinates":[-117.922037,34.111688],"type":"Point"}
}