{
  "type": "Feature",
  "properties": {
    "addr:full":"429 Ingalls St Santa Cruz CA 95060",
    "addr:housenumber":"429",
    "addr:postcode":"95060",
    "addr:street":"Ingalls St",
    "iso:country":"US",
    "sg:address":"429 Ingalls St",
    "sg:city":"Santa Cruz",
    "sg:classifiers":[
        {
            "category":"Coffee & Tea",
            "type":"Food & Drink"
        }
    ],
    "sg:phone":"+1 831 425 7143",
    "sg:postcode":"95060",
    "sg:province":"CA",
    "wof:name":"Java Bob's Coffee Roasting",
    "wof:placetype":"venue"
},
  "geometry": {"coordinates":[-122.04846999999999,36.958232],"type":"Point"}
}