{
  "type": "Feature",
  "properties": {
    "addr:full":"6200 Canoga Ave Fl 3 Woodland Hills CA 91367",
    "addr:housenumber":"6200;3",
    "addr:postcode":"91367",
    "addr:street":"Canoga Ave Fl",
    "iso:country":"US",
    "sg:address":"6200 Canoga Ave Fl 3",
    "sg:city":"Woodland Hills",
    "sg:classifiers":[
        {
            "category":"Shopping Center",
            "type":"Public Place"
        }
    ],
    "sg:phone":"+1 818 348 1200",
    "sg:postcode":"91367",
    "sg:province":"CA",
    "wof:name":"Benefit Mall",
    "wof:placetype":"venue"
},
  "geometry": {"coordinates":[-118.597204,34.18285],"type":"Point"}
}