{
  "type": "Feature",
  "properties": {
    "addr:full":"2377 S Cota Ave Corona CA 92882",
    "addr:housenumber":"2377",
    "addr:postcode":"92882",
    "addr:street":"S Cota Ave",
    "iso:country":"US",
    "sg:address":"2377 S Cota Ave",
    "sg:city":"Corona",
    "sg:classifiers":[
        {
            "category":"Professional",
            "subcategory":"Management & Consulting",
            "type":"Services"
        },
        {
            "category":"Education",
            "subcategory":"Special Training",
            "type":"Public Place"
        },
        {
            "category":"Social Services",
            "subcategory":"Job Training",
            "type":"Services"
        }
    ],
    "sg:phone":"+1 951 738 8118",
    "sg:postcode":"92882",
    "sg:province":"CA",
    "sg:tags":[
        "information",
        "school",
        "assistant",
        "medical",
        "instruction",
        "safety",
        "technician",
        "aid",
        "cpr",
        "dental",
        "first"
    ],
    "wof:name":"Life Support Services",
    "wof:placetype":"venue"
},
  "geometry": {"coordinates":[-117.57735,33.85404],"type":"Point"}
}