{
  "type": "Feature",
  "properties": {
    "addr:full":"1642 E Washington St Colton CA 92324",
    "addr:housenumber":"1642",
    "addr:postcode":"92324",
    "addr:street":"E Washington St",
    "iso:country":"US",
    "sg:address":"1642 E Washington St",
    "sg:city":"Colton",
    "sg:classifiers":[
        {
            "category":"Education",
            "subcategory":"Special Training",
            "type":"Public Place"
        }
    ],
    "sg:phone":"+1 909 370 3800",
    "sg:postcode":"92324",
    "sg:province":"CA",
    "sg:tags":[
        "tutoring"
    ],
    "wof:name":"Sat Capital Education Group",
    "wof:placetype":"venue"
},
  "geometry": {"coordinates":[-117.30137000000001,34.04834],"type":"Point"}
}