{
  "type": "Feature",
  "properties": {
    "addr:full":"140 W Valley Blvd Ste 380 San Gabriel CA 91776",
    "addr:housenumber":"140",
    "addr:postcode":"91776",
    "addr:street":"W Valley Blvd Ste 380",
    "iso:country":"US",
    "sg:address":"140 W Valley Blvd Ste 380",
    "sg:city":"San Gabriel",
    "sg:classifiers":[
        {
            "category":"Shopping",
            "subcategory":"Department Store",
            "type":"Retail Goods"
        }
    ],
    "sg:phone":"+1 626 571 8889",
    "sg:postcode":"91776",
    "sg:province":"CA",
    "wof:name":"Focus Department Store",
    "wof:placetype":"venue"
},
  "geometry": {"coordinates":[-118.099998,34.0797],"type":"Point"}
}