{
  "type": "Feature",
  "properties": {
    "addr:full":"40961 Grimmer Blvd Fremont CA 94538",
    "addr:postcode":"40961;94538",
    "addr:street":"Grimmer Blvd",
    "iso:country":"US",
    "sg:address":"40961 Grimmer Blvd",
    "sg:city":"Fremont",
    "sg:classifiers":[
        {
            "category":"Shopping",
            "subcategory":"Clothing, Apparel, & Fashions",
            "type":"Retail Goods"
        }
    ],
    "sg:phone":"+1 510 623 9711",
    "sg:postcode":"94538",
    "sg:province":"CA",
    "sg:tags":[
        "shop",
        "bridal"
    ],
    "wof:name":"Andrea's Bridal & Tuxedos",
    "wof:placetype":"venue"
},
  "geometry": {"coordinates":[-121.968144,37.533195],"type":"Point"}
}