{
  "type": "Feature",
  "properties": {
    "addr:full":"2528 Cll Jade San Clemente CA 92673",
    "addr:housenumber":"2528",
    "addr:postcode":"92673",
    "addr:street":"Cll Jade",
    "iso:country":"US",
    "sg:address":"2528 Cll Jade",
    "sg:city":"San Clemente",
    "sg:classifiers":[
        {
            "category":"Insurance",
            "subcategory":"Insurance Agent",
            "type":"Services"
        }
    ],
    "sg:phone":"+1 949 481 2528",
    "sg:postcode":"92673",
    "sg:province":"CA",
    "wof:name":"Blue Cross & Blue Shield",
    "wof:placetype":"venue"
},
  "geometry": {"coordinates":[-117.619975,33.452555],"type":"Point"}
}