{
  "type": "Feature",
  "properties": {
    "addr:full":"75 Federal St San Francisco CA 94107",
    "addr:housenumber":"75",
    "addr:postcode":"94107",
    "addr:street":"Federal St",
    "iso:country":"US",
    "sg:address":"75 Federal St",
    "sg:city":"San Francisco",
    "sg:classifiers":[
        {
            "category":"Communications",
            "subcategory":"News Services",
            "type":"Services"
        }
    ],
    "sg:phone":"+1 415 659 9101",
    "sg:postcode":"94107",
    "sg:province":"CA",
    "wof:name":"Inquisit Inc",
    "wof:placetype":"venue"
},
  "geometry": {"coordinates":[-122.39179799999999,37.783799],"type":"Point"}
}