{
  "type": "Feature",
  "properties": {
    "iso:country":"US",
    "sg:address":"252 del Amo Fashion Sq",
    "sg:city":"Torrance",
    "sg:classifiers":[
        {
            "category":"Shopping",
            "subcategory":"Gifts & Souvenirs",
            "type":"Retail Goods"
        }
    ],
    "sg:phone":"+1 310 542 9424",
    "sg:postcode":"90503",
    "sg:province":"CA",
    "sg:tags":[
        "shop"
    ],
    "wof:name":"Brookstone Inc",
    "wof:placetype":"venue"
},
  "geometry": {"coordinates":[-118.351225,33.828366],"type":"Point"}
}