{
  "type": "Feature",
  "properties": {
    "addr:full":"9628 Campo Rd Spring Valley CA 91977",
    "addr:housenumber":"9628",
    "addr:postcode":"91977",
    "addr:street":"Campo Rd",
    "iso:country":"US",
    "sg:address":"9628 Campo Rd",
    "sg:city":"Spring Valley",
    "sg:classifiers":[
        {
            "category":"Professional",
            "type":"Services"
        }
    ],
    "sg:phone":"+1 619 460 4460",
    "sg:postcode":"91977",
    "sg:province":"CA",
    "sg:tags":[
        "establishment"
    ],
    "wof:name":"Brighton Place Spring Val",
    "wof:placetype":"venue"
},
  "geometry": {"coordinates":[-116.987655,32.74807],"type":"Point"}
}