{
  "type": "Feature",
  "properties": {
    "iso:country":"US",
    "sg:address":"3489 Luyung Dr",
    "sg:city":"Rancho Cordova",
    "sg:classifiers":[
        {
            "category":"Building & Trades",
            "subcategory":"Construction",
            "type":"Services"
        }
    ],
    "sg:phone":"+1 916 635 5175",
    "sg:postcode":"95742",
    "sg:province":"CA",
    "sg:tags":[
        "paving",
        "contractor"
    ],
    "wof:name":"Central Striping Svc Inc",
    "wof:placetype":"venue"
},
  "geometry": {"coordinates":[-121.254515,38.578748],"type":"Point"}
}