{
  "type": "Feature",
  "properties": {
    "iso:country":"US",
    "sg:address":"1001 Del Paso Blvd Ste 1",
    "sg:city":"Sacramento",
    "sg:classifiers":[
        {
            "category":"Arts & Performance",
            "subcategory":"Arts Center",
            "type":"Entertainment"
        },
        {
            "category":"Communications",
            "subcategory":"Newspaper",
            "type":"Services"
        },
        {
            "category":"Professional",
            "subcategory":"Art Services",
            "type":"Services"
        }
    ],
    "sg:phone":"+1 916 256 6994",
    "sg:postcode":"95815",
    "sg:province":"CA",
    "sg:tags":[
        "print",
        "medium",
        "graphic",
        "design"
    ],
    "sg:website":"www.signmadness.com",
    "wof:name":"City Signs",
    "wof:placetype":"venue"
},
  "geometry": {"coordinates":[-121.46605099999999,38.603203],"type":"Point"}
}