{
  "type": "Feature",
  "properties": {
    "addr:full":"1605 N Cahuenga Boulevard Suite 206 Los Angeles CA 90028",
    "addr:housenumber":"1605",
    "addr:postcode":"90028",
    "addr:street":"N Cahuenga Boulevard Suite 206",
    "iso:country":"US",
    "sg:address":"1605 N Cahuenga Boulevard Suite 206",
    "sg:city":"Los Angeles",
    "sg:classifiers":[
        {
            "category":"Shopping",
            "subcategory":"Computers & Home Electronics",
            "type":"Retail Goods"
        },
        {
            "category":"Communications",
            "type":"Services"
        }
    ],
    "sg:phone":"+1 323 462 0723",
    "sg:postcode":"90028",
    "sg:province":"CA",
    "sg:tags":[
        "recording",
        "rehearsal",
        "studio"
    ],
    "wof:name":"Barnum H B",
    "wof:placetype":"venue"
},
  "geometry": {"coordinates":[-118.329532,34.099848],"type":"Point"}
}