{
  "type": "Feature",
  "properties": {
    "iso:country":"US",
    "sg:address":"1100 Arcadia Ave",
    "sg:city":"Arcadia",
    "sg:classifiers":[
        {
            "category":"Building & Trades",
            "subcategory":"Construction",
            "type":"Services"
        }
    ],
    "sg:phone":"+1 626 447 3683",
    "sg:postcode":"91007",
    "sg:province":"CA",
    "sg:tags":[
        "contractor"
    ],
    "wof:name":"Aldo Spataro Construction",
    "wof:placetype":"venue"
},
  "geometry": {"coordinates":[-118.066643,34.126497],"type":"Point"}
}