{
  "type": "Feature",
  "properties": {
    "iso:country":"US",
    "sg:address":"4155 Crooked Stick Ln",
    "sg:city":"Corona",
    "sg:classifiers":[
        {
            "category":"Manufacturing",
            "subcategory":"Chemicals & Compounds",
            "type":"Manufacturing & Wholesale Goods"
        }
    ],
    "sg:phone":"+1 951 549 6579",
    "sg:postcode":"92883",
    "sg:province":"CA",
    "sg:tags":[
        "packaging",
        "contract"
    ],
    "wof:name":"Towellette Manufacturing",
    "wof:placetype":"venue"
},
  "geometry": {"coordinates":[-117.524194,33.816918],"type":"Point"}
}