{
  "type": "Feature",
  "properties": {
    "addr:full":"2400 County Center Dr Santa Rosa CA 95403",
    "addr:housenumber":"2400",
    "addr:postcode":"95403",
    "addr:street":"County Center Dr",
    "iso:country":"US",
    "sg:address":"2400 County Center Dr",
    "sg:city":"Santa Rosa",
    "sg:classifiers":[
        {
            "category":"Health Services",
            "subcategory":"Doctor",
            "type":"Services"
        }
    ],
    "sg:phone":"+1 707 546 7246",
    "sg:postcode":"95403",
    "sg:province":"CA",
    "sg:tags":[
        "physician",
        "surgeon"
    ],
    "wof:name":"North Bay Pain Care Ctr",
    "wof:placetype":"venue"
},
  "geometry": {"coordinates":[-122.72615,38.463832],"type":"Point"}
}