{
  "type": "Feature",
  "properties": {
    "iso:country":"US",
    "sg:address":"3575 Sweetwater Cir",
    "sg:city":"Corona",
    "sg:classifiers":[
        {
            "category":"Professional",
            "subcategory":"Lawyer & Legal Services",
            "type":"Services"
        }
    ],
    "sg:phone":"+1 714 535 3544",
    "sg:postcode":"92882",
    "sg:province":"CA",
    "sg:tags":[
        "notary"
    ],
    "wof:name":"Have Notary-Will Travel",
    "wof:placetype":"venue"
},
  "geometry": {"coordinates":[-117.63682300000001,33.877742],"type":"Point"}
}