{
  "type": "Feature",
  "properties": {
    "iso:country":"US",
    "sg:address":"7036 Dublin Blvd",
    "sg:city":"Dublin",
    "sg:classifiers":[
        {
            "category":"Communications",
            "type":"Services"
        }
    ],
    "sg:phone":"+1 925 833 8288",
    "sg:postcode":"94568",
    "sg:province":"CA",
    "sg:tags":[
        "laser"
    ],
    "wof:name":"Azure",
    "wof:placetype":"venue"
},
  "geometry": {"coordinates":[-121.920165,37.705422],"type":"Point"}
}