{
  "type": "Feature",
  "properties": {
    "addr:full":"2802 B Street San Diego CA 92102",
    "addr:housenumber":"2802",
    "addr:postcode":"92102",
    "addr:street":"B Street",
    "iso:country":"US",
    "sg:address":"2802 B Street",
    "sg:city":"San Diego",
    "sg:classifiers":[
        {
            "category":"Cinema",
            "subcategory":"Movie Rental",
            "type":"Entertainment"
        }
    ],
    "sg:phone":"+1 619 236 1448",
    "sg:postcode":"92102",
    "sg:province":"CA",
    "sg:tags":[
        "game",
        "video"
    ],
    "wof:name":"Video Club",
    "wof:placetype":"venue"
},
  "geometry": {"coordinates":[-117.133813,32.717847],"type":"Point"}
}