{
  "type": "Feature",
  "properties": {
    "addr:full":"911 Morro Bay Blvd Morro Bay CA 93442",
    "addr:housenumber":"911",
    "addr:postcode":"93442",
    "addr:street":"Morro Bay Blvd",
    "iso:country":"US",
    "sg:address":"911 Morro Bay Blvd",
    "sg:city":"Morro Bay",
    "sg:classifiers":[
        {
            "category":"Autos & Motor Vehicles",
            "subcategory":"Fuel & Gas Station",
            "type":"Retail Goods"
        }
    ],
    "sg:phone":"+1 805 772 1660",
    "sg:postcode":"93442",
    "sg:province":"CA",
    "sg:tags":[
        "oil"
    ],
    "wof:name":"Morro Bay Mobil",
    "wof:placetype":"venue"
},
  "geometry": {"coordinates":[-120.84200300000001,35.366199],"type":"Point"}
}