{
  "type": "Feature",
  "properties": {
    "addr:full":"1224 Cottonwood St Woodland CA 95695",
    "addr:housenumber":"1224",
    "addr:postcode":"95695",
    "addr:street":"Cottonwood St",
    "iso:country":"US",
    "sg:address":"1224 Cottonwood St",
    "sg:city":"Woodland",
    "sg:classifiers":[
        {
            "category":"Real Estate",
            "subcategory":"Developer",
            "type":"Services"
        }
    ],
    "sg:phone":"+1 530 666 5799",
    "sg:postcode":"95695",
    "sg:province":"CA",
    "wof:name":"TCC Properties Inc",
    "wof:placetype":"venue"
},
  "geometry": {"coordinates":[-121.793503,38.666308],"type":"Point"}
}