{
  "type": "Feature",
  "properties": {
    "addr:full":"2933 E Coast Hwy Corona Del Mar CA 92625",
    "addr:housenumber":"2933",
    "addr:postcode":"92625",
    "addr:street":"E Coast Hwy",
    "iso:country":"US",
    "sg:address":"2933 E Coast Hwy",
    "sg:city":"Corona Del Mar",
    "sg:classifiers":[
        {
            "category":"Restaurant",
            "type":"Food & Drink"
        }
    ],
    "sg:phone":"+1 949 723 0092",
    "sg:postcode":"92625",
    "sg:province":"CA",
    "wof:name":"Subway",
    "wof:placetype":"venue"
},
  "geometry": {"coordinates":[-117.872007,33.599208],"type":"Point"}
}