{
  "type": "Feature",
  "properties": {
    "iso:country":"US",
    "sg:address":"3840 Market St",
    "sg:city":"San Francisco",
    "sg:classifiers":[
        {
            "category":"Real Estate",
            "subcategory":"Real Estate Agent",
            "type":"Services"
        }
    ],
    "sg:phone":"+1 415 648 2306",
    "sg:postcode":"94131",
    "sg:province":"CA",
    "wof:name":"Pat Bernard Realtor",
    "wof:placetype":"venue"
},
  "geometry": {"coordinates":[-122.442674,37.753406],"type":"Point"}
}