{
  "type": "Feature",
  "properties": {
    "iso:country":"US",
    "sg:address":"111 Fletcher Pkwy",
    "sg:city":"El Cajon",
    "sg:classifiers":[
        {
            "category":"Insurance",
            "subcategory":"Insurance Agent",
            "type":"Services"
        }
    ],
    "sg:phone":"+1 619 420 4450",
    "sg:postcode":"92020",
    "sg:province":"CA",
    "wof:name":"Dom Recchia Insurance",
    "wof:placetype":"venue"
},
  "geometry": {"coordinates":[-116.962457,32.80768],"type":"Point"}
}