{
  "type": "Feature",
  "properties": {
    "iso:country":"US",
    "sg:address":"2625 E Florence Avenue",
    "sg:city":"Huntington Park",
    "sg:classifiers":[
        {
            "category":"Banks & Credit Unions",
            "subcategory":"Bank",
            "type":"Services"
        }
    ],
    "sg:phone":"+1 323 582 2255",
    "sg:postcode":"90255",
    "sg:province":"CA",
    "wof:name":"Banco Agricola Comercial De El Salvador",
    "wof:placetype":"venue"
},
  "geometry": {"coordinates":[-118.224377,33.974149],"type":"Point"}
}