{
  "type": "Feature",
  "properties": {
    "iso:country":"US",
    "sg:address":"20 Executive Park Ste 130",
    "sg:city":"Irvine",
    "sg:classifiers":[
        {
            "category":"Professional",
            "subcategory":"Lawyer & Legal Services",
            "type":"Services"
        }
    ],
    "sg:phone":"+1 949 851 9900",
    "sg:postcode":"92614",
    "sg:province":"CA",
    "sg:website":"www.jslawgroup.com",
    "wof:name":"Jorgensen And Salberg",
    "wof:placetype":"venue"
},
  "geometry": {"coordinates":[-117.86073399999999,33.685656],"type":"Point"}
}