{
  "type": "Feature",
  "properties": {
    "addr:full":"1580 Geary Rd Walnut Creek CA 94597",
    "addr:housenumber":"1580",
    "addr:postcode":"94597",
    "addr:street":"Geary Rd",
    "iso:country":"US",
    "sg:address":"1580 Geary Rd",
    "sg:city":"Walnut Creek",
    "sg:classifiers":[
        {
            "category":"Real Estate",
            "subcategory":"Real Estate Operator",
            "type":"Services"
        }
    ],
    "sg:phone":"+1 925 943 1121",
    "sg:postcode":"94597",
    "sg:province":"CA",
    "sg:tags":[
        "retirement",
        "center"
    ],
    "wof:name":"Kensington Place",
    "wof:placetype":"venue"
},
  "geometry": {"coordinates":[-122.065037,37.926468],"type":"Point"}
}