{
  "type": "Feature",
  "properties": {
    "addr:full":"404 S Crest Rd Orange CA 92868",
    "addr:housenumber":"404",
    "addr:postcode":"92868",
    "addr:street":"S Crest Rd",
    "iso:country":"US",
    "sg:address":"404 S Crest Rd",
    "sg:city":"Orange",
    "sg:classifiers":[
        {
            "category":"Professional",
            "subcategory":"Management & Consulting",
            "type":"Services"
        }
    ],
    "sg:phone":"+1 714 935 9715",
    "sg:postcode":"92868",
    "sg:province":"CA",
    "sg:tags":[
        "retail",
        "direct",
        "sales"
    ],
    "wof:name":"Best Drinking Water In Orange",
    "wof:placetype":"venue"
},
  "geometry": {"coordinates":[-117.870419,33.780407],"type":"Point"}
}