{
  "type": "Feature",
  "properties": {
    "addr:full":"11317 S Lilac Ave Bloomington CA 92316",
    "addr:housenumber":"11317",
    "addr:postcode":"92316",
    "addr:street":"S Lilac Ave",
    "iso:country":"US",
    "sg:address":"11317 S Lilac Ave",
    "sg:city":"Bloomington",
    "sg:classifiers":[
        {
            "category":"Building & Trades",
            "subcategory":"Plumbing",
            "type":"Services"
        }
    ],
    "sg:phone":"+1 909 877 2093",
    "sg:postcode":"92316",
    "sg:province":"CA",
    "sg:tags":[
        "tank",
        "septic"
    ],
    "wof:name":"Wileman Pumping Svc",
    "wof:placetype":"venue"
},
  "geometry": {"coordinates":[-117.378877,34.049423],"type":"Point"}
}