{
  "type": "Feature",
  "properties": {
    "iso:country":"US",
    "sg:address":"1140 Garnet Ave",
    "sg:city":"San Diego",
    "sg:classifiers":[
        {
            "category":"Recreation",
            "type":"Entertainment"
        }
    ],
    "sg:phone":"+1 858 273 1709",
    "sg:postcode":"92109",
    "sg:province":"CA",
    "sg:tags":[
        "psychic",
        "medium"
    ],
    "wof:name":"Psychic & Tarot Card Palace",
    "wof:placetype":"venue"
},
  "geometry": {"coordinates":[-117.248888,32.79808],"type":"Point"}
}