{
  "type": "Feature",
  "properties": {
    "iso:country":"US",
    "sg:address":"1000 Atlantic Ave",
    "sg:city":"Alameda",
    "sg:classifiers":[
        {
            "category":"Professional",
            "subcategory":"Engineering",
            "type":"Services"
        }
    ],
    "sg:phone":"+1 510 521 5200",
    "sg:postcode":"94501",
    "sg:province":"CA",
    "sg:tags":[
        "consulting",
        "consultant",
        "energy",
        "conservation",
        "engineer"
    ],
    "wof:name":"Gold Ring Power",
    "wof:placetype":"venue"
},
  "geometry": {"coordinates":[-122.267715,37.780772],"type":"Point"}
}