{
  "type": "Feature",
  "properties": {
    "iso:country":"US",
    "sg:address":"19051 State Rte 88",
    "sg:city":"Lockeford",
    "sg:classifiers":[
        {
            "category":"Education",
            "subcategory":"School",
            "type":"Public Place"
        }
    ],
    "sg:phone":"+1 209 331 7300",
    "sg:postcode":"95237",
    "sg:province":"CA",
    "wof:name":"Clements",
    "wof:placetype":"venue"
},
  "geometry": {"coordinates":[-121.15633800000001,38.152707],"type":"Point"}
}