{
  "type": "Feature",
  "properties": {
    "iso:country":"US",
    "sg:address":"1426 Lincoln Blvd",
    "sg:city":"Santa Monica",
    "sg:classifiers":[
        {
            "category":"Building & Trades",
            "subcategory":"Construction",
            "type":"Services"
        }
    ],
    "sg:phone":"+1 310 394 6600",
    "sg:postcode":"90401",
    "sg:province":"CA",
    "sg:tags":[
        "general",
        "contractor"
    ],
    "wof:name":"Venetian Development & Constr",
    "wof:placetype":"venue"
},
  "geometry": {"coordinates":[-118.489786,34.01815],"type":"Point"}
}