{
  "type": "Feature",
  "properties": {
    "addr:full":"933 Lakeville St Petaluma CA 94952",
    "addr:housenumber":"933",
    "addr:postcode":"94952",
    "addr:street":"Lakeville St",
    "iso:country":"US",
    "sg:address":"933 Lakeville St",
    "sg:city":"Petaluma",
    "sg:classifiers":[
        {
            "category":"Personal",
            "subcategory":"Beauty Salon",
            "type":"Services"
        }
    ],
    "sg:phone":"+1 707 778 1879",
    "sg:postcode":"94952",
    "sg:province":"CA",
    "wof:name":"Beauty Store & More",
    "wof:placetype":"venue"
},
  "geometry": {"coordinates":[-122.62333700000001,38.235462],"type":"Point"}
}