{
  "type": "Feature",
  "properties": {
    "iso:country":"US",
    "sg:address":"455 E 7th St",
    "sg:city":"San Jacinto",
    "sg:classifiers":[
        {
            "category":"Real Estate",
            "subcategory":"Real Estate Operator",
            "type":"Services"
        }
    ],
    "sg:phone":"+1 951 654 2416",
    "sg:postcode":"92583",
    "sg:province":"CA",
    "sg:tags":[
        "mobile",
        "home",
        "community"
    ],
    "wof:name":"Tradewinds Mobile Lodge",
    "wof:placetype":"venue"
},
  "geometry": {"coordinates":[-116.953495,33.780366],"type":"Point"}
}