{
  "type": "Feature",
  "properties": {
    "iso:country":"US",
    "sg:address":"7850 Amador Valley Blvd",
    "sg:city":"Dublin",
    "sg:classifiers":[
        {
            "category":"Autos & Motor Vehicles",
            "subcategory":"Fuel & Gas Station",
            "type":"Retail Goods"
        }
    ],
    "sg:phone":"+1 925 828 8352",
    "sg:postcode":"94568",
    "sg:province":"CA",
    "sg:tags":[
        "oil"
    ],
    "wof:name":"Simon Mui Union 76",
    "wof:placetype":"venue"
},
  "geometry": {"coordinates":[-121.93352400000001,37.707426],"type":"Point"}
}