{
  "type": "Feature",
  "properties": {
    "iso:country":"US",
    "sg:address":"15835 Pomerado Rd",
    "sg:city":"Poway",
    "sg:classifiers":[
        {
            "category":"Health Services",
            "subcategory":"Doctor",
            "type":"Services"
        }
    ],
    "sg:phone":"+1 858 485 1180",
    "sg:postcode":"92064",
    "sg:province":"CA",
    "sg:tags":[
        "dentist"
    ],
    "wof:name":"Bruce W Johnson DDS",
    "wof:placetype":"venue"
},
  "geometry": {"coordinates":[-117.057866,33.003702],"type":"Point"}
}