{
  "type": "Feature",
  "properties": {
    "iso:country":"US",
    "sg:address":"6943 El Camino Real",
    "sg:city":"Carlsbad",
    "sg:classifiers":[
        {
            "category":"Restaurant",
            "type":"Food & Drink"
        }
    ],
    "sg:menulink":"http://www.allmenus.com/ca/oceanside-escondido/7587-allens-new-york-pizza/menu/",
    "sg:phone":"+1 760 918 9999",
    "sg:postcode":"92009",
    "sg:province":"CA",
    "sg:tags":[
        "american",
        "pizza"
    ],
    "wof:name":"Allen's New York Pizza",
    "wof:placetype":"venue"
},
  "geometry": {"coordinates":[-117.26752500000001,33.106102],"type":"Point"}
}