{
  "type": "Feature",
  "properties": {
    "addr:full":"690 W Fremont Ave Sunnyvale CA 94087",
    "addr:housenumber":"690",
    "addr:postcode":"94087",
    "addr:street":"W Fremont Ave",
    "iso:country":"US",
    "sg:address":"690 W Fremont Ave",
    "sg:city":"Sunnyvale",
    "sg:classifiers":[
        {
            "category":"Professional",
            "subcategory":"Accounting & Tax Preparation",
            "type":"Services"
        }
    ],
    "sg:phone":"+1 408 830 9910",
    "sg:postcode":"94087",
    "sg:province":"CA",
    "sg:tags":[
        "accountant"
    ],
    "wof:name":"Sohn & Song Cpa's",
    "wof:placetype":"venue"
},
  "geometry": {"coordinates":[-122.041,37.352001],"type":"Point"}
}