{
  "type": "Feature",
  "properties": {
    "iso:country":"US",
    "sg:address":"231 E 11th St",
    "sg:city":"Tracy",
    "sg:classifiers":[
        {
            "category":"Professional",
            "subcategory":"Management & Consulting",
            "type":"Services"
        }
    ],
    "sg:phone":"+1 209 835 2244",
    "sg:postcode":"95376",
    "sg:province":"CA",
    "sg:tags":[
        "consultant",
        "resource",
        "human"
    ],
    "wof:name":"H R On Demand",
    "wof:placetype":"venue"
},
  "geometry": {"coordinates":[-121.421497,37.739811],"type":"Point"}
}