{
  "type": "Feature",
  "properties": {
    "iso:country":"US",
    "sg:address":"112 Inverness Ct",
    "sg:city":"Benicia",
    "sg:classifiers":[
        {
            "category":"Building & Trades",
            "subcategory":"Construction",
            "type":"Services"
        }
    ],
    "sg:phone":"+1 707 745 2116",
    "sg:postcode":"94510",
    "sg:province":"CA",
    "sg:tags":[
        "coping",
        "plastering",
        "tiling",
        "pool",
        "swimming"
    ],
    "wof:name":"Curtin's Quality Pool Svc",
    "wof:placetype":"venue"
},
  "geometry": {"coordinates":[-122.160961,38.067771],"type":"Point"}
}