{
  "type": "Feature",
  "properties": {
    "iso:country":"US",
    "sg:address":"1928 W Redondo Beach Blvd",
    "sg:city":"Gardena",
    "sg:classifiers":[
        {
            "category":"Retail",
            "subcategory":"Auto Repair",
            "type":"Services"
        }
    ],
    "sg:phone":"+1 310 324 0463",
    "sg:postcode":"90247",
    "sg:province":"CA",
    "wof:name":"Liebsack & Son Auto Service",
    "wof:placetype":"venue"
},
  "geometry": {"coordinates":[-118.311996,33.8876],"type":"Point"}
}