{
  "type": "Feature",
  "properties": {
    "iso:country":"US",
    "sg:address":"33 E Padre St",
    "sg:city":"Goleta",
    "sg:classifiers":[
        {
            "category":"Wholesale",
            "subcategory":"Electrical",
            "type":"Manufacturing & Wholesale Goods"
        }
    ],
    "sg:phone":"+1 805 681 3300",
    "sg:postcode":"93105",
    "sg:province":"CA",
    "sg:tags":[
        "equipment",
        "electronic",
        "supply"
    ],
    "sg:website":"www.motioneng.com",
    "wof:name":"Motion Engineering Inc",
    "wof:placetype":"venue"
},
  "geometry": {"coordinates":[-119.715172,34.432534],"type":"Point"}
}