{
  "type": "Feature",
  "properties": {
    "iso:country":"US",
    "sg:address":"220 Abbott St",
    "sg:city":"Salinas",
    "sg:classifiers":[
        {
            "category":"Building & Trades",
            "subcategory":"Plumbing",
            "type":"Services"
        }
    ],
    "sg:phone":"+1 831 758 2223",
    "sg:postcode":"93901",
    "sg:province":"CA",
    "sg:tags":[
        "plumber",
        "industrial",
        "contractors-commercial"
    ],
    "wof:name":"Abbott Plumbing",
    "wof:placetype":"venue"
},
  "geometry": {"coordinates":[-121.646252,36.668607],"type":"Point"}
}