{
  "type": "Feature",
  "properties": {
    "addr:full":"3228 Mission St",
    "iso:country":"US",
    "name:eng_x_preferred":[
        "Mi Lindo Peru"
    ],
    "wof:name":"Mi Lindo Peru",
    "wof:placetype":"venue"
},
  "geometry": {"coordinates":[-122.42032706738,37.745106760271],"type":"Point"}
}