{
  "type": "Feature",
  "properties": {
    "addr:full":"4250 Pacific Hwy San Diego CA 92110",
    "addr:housenumber":"4250",
    "addr:postcode":"92110",
    "addr:street":"Pacific Hwy",
    "iso:country":"US",
    "sg:address":"4250 Pacific Hwy",
    "sg:city":"San Diego",
    "sg:classifiers":[
        {
            "category":"Shopping",
            "subcategory":"Computers & Home Electronics",
            "type":"Retail Goods"
        }
    ],
    "sg:phone":"+1 619 523 2023",
    "sg:postcode":"92110",
    "sg:province":"CA",
    "sg:tags":[
        "software"
    ],
    "wof:name":"Neptune Sciences",
    "wof:placetype":"venue"
},
  "geometry": {"coordinates":[-117.19586099999999,32.745793],"type":"Point"}
}