{
  "type": "Feature",
  "properties": {
    "addr:full":"1547 S Broadway Santa Maria CA 93454",
    "addr:housenumber":"1547",
    "addr:postcode":"93454",
    "addr:street":"S Broadway",
    "iso:country":"US",
    "sg:address":"1547 S Broadway",
    "sg:city":"Santa Maria",
    "sg:classifiers":[
        {
            "category":"Manufacturing",
            "subcategory":"Signs",
            "type":"Manufacturing & Wholesale Goods"
        },
        {
            "category":"Manufacturing",
            "subcategory":"Printing",
            "type":"Manufacturing & Wholesale Goods"
        }
    ],
    "sg:phone":"+1 805 928 1314",
    "sg:postcode":"93454",
    "sg:province":"CA",
    "sg:tags":[
        "engraving",
        "product",
        "ad",
        "mfg",
        "photocopy",
        "wood",
        "engraver"
    ],
    "sg:website":"www.allenscustomsigns.com",
    "wof:name":"Allen's Custom Signs",
    "wof:placetype":"venue"
},
  "geometry": {"coordinates":[-120.436187,34.932889],"type":"Point"}
}