{
  "type": "Feature",
  "properties": {
    "addr:full":"1507 S Coast Dr Costa Mesa CA 92626",
    "addr:housenumber":"1507",
    "addr:postcode":"92626",
    "addr:street":"S Coast Dr",
    "iso:country":"US",
    "sg:address":"1507 S Coast Dr",
    "sg:city":"Costa Mesa",
    "sg:classifiers":[
        {
            "category":"Restaurant",
            "type":"Food & Drink"
        }
    ],
    "sg:menulink":"http://www.allmenus.com/ca/central-coast/35467-cocos/menu/",
    "sg:phone":"+1 714 545 2351",
    "sg:postcode":"92626",
    "sg:province":"CA",
    "sg:tags":[
        "american"
    ],
    "wof:name":"Coco's",
    "wof:placetype":"venue"
},
  "geometry": {"coordinates":[-117.91979000000001,33.691624],"type":"Point"}
}