{
  "type": "Feature",
  "properties": {
    "iso:country":"US",
    "sg:address":"5120 Robinwood Rd Ste B13",
    "sg:city":"Bonita",
    "sg:classifiers":[
        {
            "category":"Organizations",
            "subcategory":"Religious Organization",
            "type":"Services"
        }
    ],
    "sg:phone":"+1 619 475 1012",
    "sg:postcode":"91902",
    "sg:province":"CA",
    "sg:website":"www.bcrs.net",
    "wof:name":"Bonita Church of Religious Science",
    "wof:placetype":"venue"
},
  "geometry": {"coordinates":[-117.028999,32.681],"type":"Point"}
}