{
  "type": "Feature",
  "properties": {
    "iso:country":"US",
    "sg:address":"1516 Stone Ln",
    "sg:city":"Glendale",
    "sg:classifiers":[
        {
            "category":"Real Estate",
            "subcategory":"Developer",
            "type":"Services"
        }
    ],
    "sg:phone":"+1 818 244 6958",
    "sg:postcode":"91202",
    "sg:province":"CA",
    "wof:name":"Geringer Development Co",
    "wof:placetype":"venue"
},
  "geometry": {"coordinates":[-118.277727,34.173024],"type":"Point"}
}