{
  "type": "Feature",
  "properties": {
    "addr:full":"932 Geneva Ave San Francisco CA 94112",
    "addr:housenumber":"932",
    "addr:postcode":"94112",
    "addr:street":"Geneva Ave",
    "iso:country":"US",
    "sg:address":"932 Geneva Ave",
    "sg:city":"San Francisco",
    "sg:classifiers":[
        {
            "category":"Restaurant",
            "type":"Food & Drink"
        }
    ],
    "sg:phone":"+1 415 333 2182",
    "sg:postcode":"94112",
    "sg:province":"CA",
    "wof:name":"Lucky Wealth Restaurant",
    "wof:placetype":"venue"
},
  "geometry": {"coordinates":[-122.4408,37.716186],"type":"Point"}
}