{
  "type": "Feature",
  "properties": {
    "iso:country":"US",
    "sg:address":"117 N 1st St",
    "sg:city":"La Puente",
    "sg:classifiers":[
        {
            "category":"Banks & Credit Unions",
            "subcategory":"Investment Brokerage",
            "type":"Services"
        }
    ],
    "sg:phone":"+1 626 333 4812",
    "sg:postcode":"91744",
    "sg:province":"CA",
    "sg:tags":[
        "consultant",
        "planning",
        "financial"
    ],
    "wof:name":"Philip E Shura",
    "wof:placetype":"venue"
},
  "geometry": {"coordinates":[-117.952695,34.021333],"type":"Point"}
}