{
  "type": "Feature",
  "properties": {
    "addr:full":"7274 Princeton Ave La Mesa CA 91941",
    "addr:housenumber":"7274",
    "addr:postcode":"91941",
    "addr:street":"Princeton Ave",
    "iso:country":"US",
    "sg:address":"7274 Princeton Ave",
    "sg:city":"La Mesa",
    "sg:classifiers":[
        {
            "category":"Retail",
            "subcategory":"Auto Repair",
            "type":"Services"
        }
    ],
    "sg:phone":"+1 619 461 1050",
    "sg:postcode":"91941",
    "sg:province":"CA",
    "sg:tags":[
        "repairing",
        "automobile"
    ],
    "wof:name":"Mobile Airbag Installation",
    "wof:placetype":"venue"
},
  "geometry": {"coordinates":[-117.039525,32.76042],"type":"Point"}
}