{
  "type": "Feature",
  "properties": {
    "iso:country":"US",
    "sg:address":"1191 N Western Ave",
    "sg:city":"Los Angeles",
    "sg:classifiers":[
        {
            "category":"Shopping",
            "type":"Retail Goods"
        }
    ],
    "sg:phone":"+1 626 810 4948",
    "sg:postcode":"90029",
    "sg:province":"CA",
    "sg:tags":[
        "religious"
    ],
    "wof:name":"Productos Los Pola",
    "wof:placetype":"venue"
},
  "geometry": {"coordinates":[-118.309263,34.092056],"type":"Point"}
}