{
  "type": "Feature",
  "properties": {
    "addr:full":"6205 Meridian Ave San Jose CA 95120",
    "addr:housenumber":"6205",
    "addr:postcode":"95120",
    "addr:street":"Meridian Ave",
    "iso:country":"US",
    "sg:address":"6205 Meridian Ave",
    "sg:city":"San Jose",
    "sg:classifiers":[
        {
            "category":"Retail",
            "subcategory":"Veterinary Services",
            "type":"Services"
        }
    ],
    "sg:phone":"+1 408 268 7378",
    "sg:postcode":"95120",
    "sg:province":"CA",
    "sg:tags":[
        "veterinarian"
    ],
    "wof:name":"Companion Pet Care",
    "wof:placetype":"venue"
},
  "geometry": {"coordinates":[-121.885048,37.224996],"type":"Point"}
}