{
  "type": "Feature",
  "properties": {
    "iso:country":"US",
    "sg:address":"1700 Broadway St",
    "sg:city":"San Francisco",
    "sg:classifiers":[
        {
            "category":"Professional",
            "subcategory":"Business Services",
            "type":"Services"
        }
    ],
    "sg:phone":"+1 415 346 3392",
    "sg:postcode":"94109",
    "sg:province":"CA",
    "sg:tags":[
        "interior",
        "consultant",
        "design",
        "decorator"
    ],
    "wof:name":"OLIVIA B Designs",
    "wof:placetype":"venue"
},
  "geometry": {"coordinates":[-122.4267,37.795316],"type":"Point"}
}