{
  "type": "Feature",
  "properties": {
    "iso:country":"US",
    "sg:address":"523 Encinitas Blvd",
    "sg:city":"Encinitas",
    "sg:classifiers":[
        {
            "category":"Professional",
            "subcategory":"Computer Services",
            "type":"Services"
        }
    ],
    "sg:phone":"+1 760 942 2822",
    "sg:postcode":"92024",
    "sg:province":"CA",
    "sg:tags":[
        "consultant",
        "internet"
    ],
    "wof:name":"Beritas Internet Consulting",
    "wof:placetype":"venue"
},
  "geometry": {"coordinates":[-117.280919,33.046828],"type":"Point"}
}