{
  "type": "Feature",
  "properties": {
    "addr:full":"59 N Santa Cruz Ave Los Gatos CA 95030",
    "addr:housenumber":"59",
    "addr:postcode":"95030",
    "addr:street":"N Santa Cruz Ave",
    "iso:country":"US",
    "sg:address":"59 N Santa Cruz Ave",
    "sg:city":"Los Gatos",
    "sg:classifiers":[
        {
            "category":"Retail",
            "subcategory":"Portrait Studio",
            "type":"Services"
        },
        {
            "category":"Professional",
            "subcategory":"Art Services",
            "type":"Services"
        }
    ],
    "sg:phone":"+1 408 395 3200",
    "sg:postcode":"95030",
    "sg:province":"CA",
    "sg:tags":[
        "photographer",
        "photography",
        "store"
    ],
    "wof:name":"Hellybee Photography",
    "wof:placetype":"venue"
},
  "geometry": {"coordinates":[-121.983357,37.224025],"type":"Point"}
}