{
  "type": "Feature",
  "properties": {
    "addr:full":"1112 Glen Arbor Ave Los Angeles CA 90041",
    "addr:housenumber":"1112",
    "addr:postcode":"90041",
    "addr:street":"Glen Arbor Ave",
    "iso:country":"US",
    "sg:address":"1112 Glen Arbor Ave",
    "sg:city":"Los Angeles",
    "sg:classifiers":[
        {
            "category":"Retail",
            "subcategory":"Repair Shop",
            "type":"Services"
        }
    ],
    "sg:phone":"+1 323 256 1401",
    "sg:postcode":"90041",
    "sg:province":"CA",
    "sg:tags":[
        "lock",
        "locksmith"
    ],
    "wof:name":"Advanced Lock & Safe Svc",
    "wof:placetype":"venue"
},
  "geometry": {"coordinates":[-118.185891,34.135978],"type":"Point"}
}