{
  "type": "Feature",
  "properties": {
    "addr:full":"2112 Monterey Hwy San Jose CA 95112",
    "addr:housenumber":"2112",
    "addr:postcode":"95112",
    "addr:street":"Monterey Hwy",
    "iso:country":"US",
    "sg:address":"2112 Monterey Hwy",
    "sg:city":"San Jose",
    "sg:classifiers":[
        {
            "category":"Real Estate",
            "subcategory":"Real Estate Agent",
            "type":"Services"
        }
    ],
    "sg:phone":"+1 408 271 9344",
    "sg:postcode":"95112",
    "sg:province":"CA",
    "sg:tags":[
        "authorities",
        "housing"
    ],
    "wof:name":"Emergency Housing Consortium",
    "wof:placetype":"venue"
},
  "geometry": {"coordinates":[-121.8601,37.30245],"type":"Point"}
}