{
  "type": "Feature",
  "properties": {
    "addr:full":"404 W 7th Street Suite 200 Los Angeles CA 90014",
    "addr:housenumber":"404",
    "addr:postcode":"90014",
    "addr:street":"W 7Th Street Suite 200",
    "iso:country":"US",
    "sg:address":"404 W 7th Street Suite 200",
    "sg:city":"Los Angeles",
    "sg:classifiers":[
        {
            "category":"Shopping",
            "subcategory":"Jewelry",
            "type":"Retail Goods"
        }
    ],
    "sg:phone":"+1 213 623 5580",
    "sg:postcode":"90014",
    "sg:province":"CA",
    "wof:name":"Final Touch Jewelers",
    "wof:placetype":"venue"
},
  "geometry": {"coordinates":[-118.25449999999999,34.045934],"type":"Point"}
}