{
  "type": "Feature",
  "properties": {
    "addr:full":"6000 Mowry Ave Newark CA 94560",
    "addr:housenumber":"6000",
    "addr:postcode":"94560",
    "addr:street":"Mowry Ave",
    "iso:country":"US",
    "sg:address":"6000 Mowry Ave",
    "sg:city":"Newark",
    "sg:classifiers":[
        {
            "category":"Professional",
            "subcategory":"Accounting & Tax Preparation",
            "type":"Services"
        },
        {
            "category":"Banks & Credit Unions",
            "subcategory":"Financial Services",
            "type":"Services"
        }
    ],
    "sg:phone":"+1 510 794 4229",
    "sg:postcode":"94560",
    "sg:province":"CA",
    "sg:tags":[
        "return",
        "preparation-business",
        "taxes-consultants",
        "loan",
        "reporting",
        "representative",
        "alternative",
        "bookkeeping"
    ],
    "sg:website":"http://www.hrblock.com",
    "wof:name":"H&R Block",
    "wof:placetype":"venue"
},
  "geometry": {"coordinates":[-122.00762899999999,37.524841],"type":"Point"}
}