{
  "type": "Feature",
  "properties": {
    "iso:country":"US",
    "sg:address":"527 Foothill Blvd",
    "sg:city":"La Canada Fltrdg",
    "sg:classifiers":[
        {
            "category":"Recreation",
            "type":"Entertainment"
        }
    ],
    "sg:phone":"+1 818 790 4214",
    "sg:postcode":"91011",
    "sg:province":"CA",
    "sg:tags":[
        "ticket"
    ],
    "sg:website":"www.ticketpalace.com",
    "wof:name":"Ticket Palace",
    "wof:placetype":"venue"
},
  "geometry": {"coordinates":[-118.1906,34.200067],"type":"Point"}
}