{
  "type": "Feature",
  "properties": {
    "iso:country":"US",
    "sg:address":"403 N Crescent Dr",
    "sg:city":"Beverly Hills",
    "sg:classifiers":[
        {
            "category":"Home & Garden",
            "subcategory":"Building Materials",
            "type":"Retail Goods"
        }
    ],
    "sg:phone":"+1 818 764 5615",
    "sg:postcode":"90210",
    "sg:province":"CA",
    "sg:tags":[
        "equipment",
        "fixture",
        "lighting"
    ],
    "sg:website":"www.modalighting.com",
    "wof:name":"Moda Lighting",
    "wof:placetype":"venue"
},
  "geometry": {"coordinates":[-118.400284,34.071233],"type":"Point"}
}