{
  "type": "Feature",
  "properties": {
    "addr:full":"940 N Virgil Ave Los Angeles CA 90029",
    "addr:housenumber":"940",
    "addr:postcode":"90029",
    "addr:street":"N Virgil Ave",
    "iso:country":"US",
    "sg:address":"940 N Virgil Ave",
    "sg:city":"Los Angeles",
    "sg:classifiers":[
        {
            "category":"Food & Beverages",
            "subcategory":"Ethnic Foods",
            "type":"Retail Goods"
        }
    ],
    "sg:postcode":"90029",
    "sg:province":"CA",
    "wof:name":"El Sierreno",
    "wof:placetype":"venue"
},
  "geometry": {"coordinates":[-118.286883,34.088727],"type":"Point"}
}