{
  "type": "Feature",
  "properties": {
    "addr:full":"725 J St Sacramento CA 95814",
    "addr:housenumber":"725",
    "addr:postcode":"95814",
    "addr:street":"J St",
    "iso:country":"US",
    "sg:address":"725 J St",
    "sg:city":"Sacramento",
    "sg:classifiers":[
        {
            "category":"Shopping",
            "subcategory":"Books",
            "type":"Retail Goods"
        }
    ],
    "sg:phone":"+1 916 441 0410",
    "sg:postcode":"95814",
    "sg:province":"CA",
    "sg:tags":[
        "bookstore",
        "publishing",
        "store"
    ],
    "sg:website":"www.americaslegalbookstore.com",
    "wof:name":"Lexicon Publishing",
    "wof:placetype":"venue"
},
  "geometry": {"coordinates":[-121.496002,38.5812],"type":"Point"}
}