{
  "type": "Feature",
  "properties": {
    "addr:full":"40485 Murrieta Hot Springs Rd Murrieta CA 92563",
    "addr:housenumber":"40485",
    "addr:postcode":"92563",
    "addr:street":"Murrieta Hot Springs Rd",
    "iso:country":"US",
    "sg:address":"40485 Murrieta Hot Springs Rd",
    "sg:city":"Murrieta",
    "sg:classifiers":[
        {
            "category":"Recreation",
            "type":"Entertainment"
        }
    ],
    "sg:phone":"+1 909 821 5835",
    "sg:postcode":"92563",
    "sg:province":"CA",
    "sg:tags":[
        "entertainers-family",
        "business"
    ],
    "sg:website":"http://www.jaminjumps.com",
    "wof:name":"Jamin Jumps",
    "wof:placetype":"venue"
},
  "geometry": {"coordinates":[-117.17821600000001,33.556414],"type":"Point"}
}