{
  "type": "Feature",
  "properties": {
    "iso:country":"US",
    "sg:address":"16145 Hwy 67",
    "sg:city":"Ramona",
    "sg:classifiers":[
        {
            "category":"Organizations",
            "subcategory":"Religious Organization",
            "type":"Services"
        }
    ],
    "sg:phone":"+1 760 789 6207",
    "sg:postcode":"92065",
    "sg:province":"CA",
    "sg:tags":[
        "church"
    ],
    "wof:name":"A Touch From Above",
    "wof:placetype":"venue"
},
  "geometry": {"coordinates":[-116.955308,33.007655],"type":"Point"}
}