{
  "type": "Feature",
  "properties": {
    "addr:full":"5047 Center St Chino CA 91710",
    "addr:housenumber":"5047",
    "addr:postcode":"91710",
    "addr:street":"Center St",
    "iso:country":"US",
    "sg:address":"5047 Center St",
    "sg:city":"Chino",
    "sg:classifiers":[
        {
            "category":"Professional",
            "type":"Services"
        }
    ],
    "sg:phone":"+1 909 464 0156",
    "sg:postcode":"91710",
    "sg:province":"CA",
    "wof:name":"Dubs Water Works",
    "wof:placetype":"venue"
},
  "geometry": {"coordinates":[-117.694604,34.020158],"type":"Point"}
}