{
  "type": "Feature",
  "properties": {
    "iso:country":"US",
    "sg:address":"1053 N Hacienda Blvd",
    "sg:city":"La Puente",
    "sg:classifiers":[
        {
            "category":"Home & Garden",
            "subcategory":"Furniture",
            "type":"Retail Goods"
        }
    ],
    "sg:phone":"+1 626 961 2617",
    "sg:postcode":"91744",
    "sg:province":"CA",
    "wof:name":"Town Furniture",
    "wof:placetype":"venue"
},
  "geometry": {"coordinates":[-117.949766,34.039643],"type":"Point"}
}