{
  "type": "Feature",
  "properties": {
    "addr:full":"555 Capitol Mall Ste 766 Sacramento CA 95814",
    "addr:housenumber":"555",
    "addr:postcode":"95814",
    "addr:street":"Capitol Mall Ste 766",
    "iso:country":"US",
    "sg:address":"555 Capitol Mall Ste 766",
    "sg:city":"Sacramento",
    "sg:classifiers":[
        {
            "category":"Professional",
            "subcategory":"Engineering",
            "type":"Services"
        }
    ],
    "sg:phone":"+1 916 442 1230",
    "sg:postcode":"95814",
    "sg:province":"CA",
    "sg:tags":[
        "consulting",
        "engineer"
    ],
    "wof:name":"Prointec Usa",
    "wof:placetype":"venue"
},
  "geometry": {"coordinates":[-121.50078999999999,38.578686],"type":"Point"}
}