{
  "type": "Feature",
  "properties": {
    "addr:full":"16925 Foothill Blvd Fontana CA 92335",
    "addr:housenumber":"16925",
    "addr:postcode":"92335",
    "addr:street":"Foothill Blvd",
    "iso:country":"US",
    "sg:address":"16925 Foothill Blvd",
    "sg:city":"Fontana",
    "sg:classifiers":[
        {
            "category":"Autos & Motor Vehicles",
            "subcategory":"Fuel & Gas Station",
            "type":"Retail Goods"
        }
    ],
    "sg:phone":"+1 909 822 5470",
    "sg:postcode":"92335",
    "sg:province":"CA",
    "sg:tags":[
        "oil"
    ],
    "wof:name":"Ramzy Foothill Mobil",
    "wof:placetype":"venue"
},
  "geometry": {"coordinates":[-117.434844,34.106549],"type":"Point"}
}