{
  "type": "Feature",
  "properties": {
    "addr:full":"17056 Canvas St Canyon Country CA 91387",
    "addr:housenumber":"17056",
    "addr:postcode":"91387",
    "addr:street":"Canvas St",
    "iso:country":"US",
    "sg:address":"17056 Canvas St",
    "sg:city":"Canyon Country",
    "sg:classifiers":[
        {
            "category":"Shopping",
            "subcategory":"Antiques",
            "type":"Retail Goods"
        }
    ],
    "sg:phone":"+1 661 255 3811",
    "sg:postcode":"91387",
    "sg:province":"CA",
    "wof:name":"Dave's Antique & Appraisal Service",
    "wof:placetype":"venue"
},
  "geometry": {"coordinates":[-118.433825,34.425605],"type":"Point"}
}