{
  "type": "Feature",
  "properties": {
    "iso:country":"US",
    "sg:address":"9021 Knott Ave",
    "sg:city":"Buena Park",
    "sg:classifiers":[
        {
            "category":"Health Services",
            "subcategory":"Nursing And Care Facility",
            "type":"Services"
        }
    ],
    "sg:phone":"+1 714 826 2330",
    "sg:postcode":"90620",
    "sg:province":"CA",
    "sg:tags":[
        "living",
        "assisted",
        "skilled",
        "center"
    ],
    "wof:name":"Knott Avenue Care Center",
    "wof:placetype":"venue"
},
  "geometry": {"coordinates":[-118.011009,33.830715],"type":"Point"}
}