{
  "type": "Feature",
  "properties": {
    "addr:full":"3847 E Indianapolis Ave Fresno CA 93726",
    "addr:housenumber":"3847",
    "addr:postcode":"93726",
    "addr:street":"E Indianapolis Ave",
    "iso:country":"US",
    "sg:address":"3847 E Indianapolis Ave",
    "sg:city":"Fresno",
    "sg:classifiers":[
        {
            "category":"Wholesale",
            "subcategory":"Auto Parts",
            "type":"Manufacturing & Wholesale Goods"
        }
    ],
    "sg:phone":"+1 559 647 8384",
    "sg:postcode":"93726",
    "sg:province":"CA",
    "sg:tags":[
        "industrial",
        "tires-wholesale",
        "tire",
        "manufacturer"
    ],
    "wof:name":"Double R Material Handling Service",
    "wof:placetype":"venue"
},
  "geometry": {"coordinates":[-119.75996499999999,36.798899],"type":"Point"}
}