{
  "type": "Feature",
  "properties": {
    "iso:country":"US",
    "sg:address":"712 D St",
    "sg:city":"San Rafael",
    "sg:classifiers":[
        {
            "category":"Personal",
            "subcategory":"Beauty Salon",
            "type":"Services"
        }
    ],
    "sg:phone":"+1 415 457 7546",
    "sg:postcode":"94901",
    "sg:province":"CA",
    "sg:tags":[
        "treatment",
        "skin"
    ],
    "wof:name":"Skin Deep",
    "wof:placetype":"venue"
},
  "geometry": {"coordinates":[-122.532245,37.971416],"type":"Point"}
}