{
  "type": "Feature",
  "properties": {
    "addr:full":"5026 E Montclair Plaza Ln Montclair CA 91763",
    "addr:housenumber":"5026",
    "addr:postcode":"91763",
    "addr:street":"E Montclair Plaza Ln",
    "iso:country":"US",
    "sg:address":"5026 E Montclair Plaza Ln",
    "sg:city":"Montclair",
    "sg:classifiers":[
        {
            "category":"Shopping",
            "subcategory":"Jewelry",
            "type":"Retail Goods"
        }
    ],
    "sg:phone":"+1 909 621 4739",
    "sg:postcode":"91763",
    "sg:province":"CA",
    "sg:tags":[
        "jeweler"
    ],
    "wof:name":"Zales Jewelers",
    "wof:placetype":"venue"
},
  "geometry": {"coordinates":[-117.695041,34.087348],"type":"Point"}
}