{
  "type": "Feature",
  "properties": {
    "iso:country":"US",
    "sg:address":"4167 Bakman Ave",
    "sg:city":"North Hollywood",
    "sg:classifiers":[
        {
            "category":"Professional",
            "type":"Services"
        }
    ],
    "sg:phone":"+1 818 985 0676",
    "sg:postcode":"91602",
    "sg:province":"CA",
    "wof:name":"Campo De Chnga Hstrical Mem As",
    "wof:placetype":"venue"
},
  "geometry": {"coordinates":[-118.37795300000001,34.14403],"type":"Point"}
}