{
  "type": "Feature",
  "properties": {
    "addr:full":"3351 Panama Ln #330 Bakersfield CA 93313",
    "addr:housenumber":"3351",
    "addr:postcode":"93313",
    "addr:street":"Panama Ln # 330",
    "iso:country":"US",
    "sg:address":"3351 Panama Ln #330",
    "sg:city":"Bakersfield",
    "sg:classifiers":[
        {
            "category":"Insurance",
            "subcategory":"Hazard Insurance",
            "type":"Services"
        },
        {
            "category":"Insurance",
            "subcategory":"Insurance Agent",
            "type":"Services"
        },
        {
            "category":"Insurance",
            "subcategory":"Life Insurance",
            "type":"Services"
        },
        {
            "category":"Insurance",
            "subcategory":"Title Insurance",
            "type":"Services"
        }
    ],
    "sg:phone":"+1 661 834 7300",
    "sg:postcode":"93313",
    "sg:province":"CA",
    "sg:tags":[
        "auto",
        "commercial",
        "business",
        "homeowner"
    ],
    "sg:website":"http://www.farmersagent.com/msanchez/",
    "wof:name":"Maximo Sanchez - Farmers Insurance",
    "wof:placetype":"venue"
},
  "geometry": {"coordinates":[-119.03953199999999,35.295846],"type":"Point"}
}