{
  "type": "Feature",
  "properties": {
    "iso:country":"US",
    "sg:address":"867 Clay St",
    "sg:city":"San Francisco",
    "sg:classifiers":[
        {
            "category":"Professional",
            "subcategory":"Accounting & Tax Preparation",
            "type":"Services"
        }
    ],
    "sg:phone":"+1 415 982 1888",
    "sg:postcode":"94108",
    "sg:province":"CA",
    "sg:tags":[
        "return",
        "filing"
    ],
    "wof:name":"Fang Associate",
    "wof:placetype":"venue"
},
  "geometry": {"coordinates":[-122.407903,37.79406],"type":"Point"}
}