{
  "type": "Feature",
  "properties": {
    "iso:country":"US",
    "sg:address":"10336 Loch Lomond Rd Ste 136",
    "sg:city":"Middletown",
    "sg:classifiers":[
        {
            "category":"Bars & Pubs",
            "type":"Food & Drink"
        },
        {
            "category":"Restaurant",
            "type":"Food & Drink"
        }
    ],
    "sg:phone":"+1 707 928 5512",
    "sg:postcode":"95461",
    "sg:province":"CA",
    "sg:tags":[
        "tavern",
        "grill",
        "american",
        "brew"
    ],
    "wof:name":"Loch Lomond Road House",
    "wof:placetype":"venue"
},
  "geometry": {"coordinates":[-122.717726,38.863097],"type":"Point"}
}