{
  "type": "Feature",
  "properties": {
    "addr:full":"311 Tremont St Chula Vista CA 91911",
    "addr:housenumber":"311",
    "addr:postcode":"91911",
    "addr:street":"Tremont St",
    "iso:country":"US",
    "sg:address":"311 Tremont St",
    "sg:city":"Chula Vista",
    "sg:classifiers":[
        {
            "category":"Retail",
            "subcategory":"Auto Repair",
            "type":"Services"
        }
    ],
    "sg:phone":"+1 619 476 1113",
    "sg:postcode":"91911",
    "sg:province":"CA",
    "sg:tags":[
        "body",
        "automobile",
        "painting"
    ],
    "wof:name":"Abels Auto Body",
    "wof:placetype":"venue"
},
  "geometry": {"coordinates":[-117.066243,32.597824],"type":"Point"}
}