{
  "type": "Feature",
  "properties": {
    "addr:full":"11331 Valley View St Cypress CA 90630",
    "addr:housenumber":"11331",
    "addr:postcode":"90630",
    "addr:street":"Valley View St",
    "iso:country":"US",
    "sg:address":"11331 Valley View St",
    "sg:city":"Cypress",
    "sg:classifiers":[
        {
            "category":"Professional",
            "type":"Services"
        }
    ],
    "sg:phone":"+1 562 446 2500",
    "sg:postcode":"90630",
    "sg:province":"CA",
    "sg:tags":[
        "establishment"
    ],
    "wof:name":"Fine Pitch Technology",
    "wof:placetype":"venue"
},
  "geometry": {"coordinates":[-118.02842099999999,33.796328],"type":"Point"}
}