{
  "type": "Feature",
  "properties": {
    "iso:country":"US",
    "sg:address":"Lincoln Blvd. Building 210",
    "sg:city":"San Francisco",
    "sg:classifiers":[
        {
            "category":"Government",
            "subcategory":"Post Office",
            "type":"Public Place"
        }
    ],
    "sg:phone":"+1 800 275 8777",
    "sg:postcode":"94129",
    "sg:province":"CA",
    "wof:name":"US Post Office - Presidio Station",
    "wof:placetype":"venue"
},
  "geometry": {"coordinates":[-122.46709799999999,37.799605],"type":"Point"}
}