{
  "type": "Feature",
  "properties": {
    "addr:full":"1524 Steinhart Ave Redondo Beach CA 90278",
    "addr:housenumber":"1524",
    "addr:postcode":"90278",
    "addr:street":"Steinhart Ave",
    "iso:country":"US",
    "sg:address":"1524 Steinhart Ave",
    "sg:city":"Redondo Beach",
    "sg:classifiers":[
        {
            "category":"Professional",
            "subcategory":"Management & Consulting",
            "type":"Services"
        }
    ],
    "sg:phone":"+1 310 376 4309",
    "sg:postcode":"90278",
    "sg:province":"CA",
    "sg:tags":[
        "consultant",
        "business"
    ],
    "wof:name":"Strother Brunner Inc",
    "wof:placetype":"venue"
},
  "geometry": {"coordinates":[-118.38602400000001,33.868803],"type":"Point"}
}