{
  "type": "Feature",
  "properties": {
    "iso:country":"US",
    "sg:address":"39301 Badger St",
    "sg:city":"Palm Desert",
    "sg:classifiers":[
        {
            "category":"Real Estate",
            "subcategory":"Real Estate Agent",
            "type":"Services"
        }
    ],
    "sg:phone":"+1 760 200 5383",
    "sg:postcode":"92211",
    "sg:province":"CA",
    "sg:tags":[
        "investment"
    ],
    "wof:name":"Newport Western Corp",
    "wof:placetype":"venue"
},
  "geometry": {"coordinates":[-116.3086,33.762415],"type":"Point"}
}