{
  "type": "Feature",
  "properties": {
    "iso:country":"US",
    "sg:address":"2040 N Towne Ave",
    "sg:city":"Pomona",
    "sg:classifiers":[
        {
            "category":"Building & Trades",
            "subcategory":"Construction",
            "type":"Services"
        }
    ],
    "sg:phone":"+1 909 865 8994",
    "sg:postcode":"91767",
    "sg:province":"CA",
    "sg:tags":[
        "contractor"
    ],
    "wof:name":"Shafia Management Co",
    "wof:placetype":"venue"
},
  "geometry": {"coordinates":[-117.740586,34.080091],"type":"Point"}
}