{
  "type": "Feature",
  "properties": {
    "addr:full":"266 Escuela Ave Mountain View CA 94040",
    "addr:housenumber":"266",
    "addr:postcode":"94040",
    "addr:street":"Escuela Ave",
    "iso:country":"US",
    "sg:address":"266 Escuela Ave",
    "sg:city":"Mountain View",
    "sg:classifiers":[
        {
            "category":"Professional",
            "subcategory":"Lawyer & Legal Services",
            "type":"Services"
        }
    ],
    "sg:phone":"+1 650 969 8656",
    "sg:postcode":"94040",
    "sg:province":"CA",
    "sg:tags":[
        "attorney"
    ],
    "wof:name":"Senior Adults Legal Assistance",
    "wof:placetype":"venue"
},
  "geometry": {"coordinates":[-122.09349899999999,37.397874],"type":"Point"}
}