{
  "type": "Feature",
  "properties": {
    "iso:country":"US",
    "sg:address":"3868 W Carson St Ste 300",
    "sg:city":"Torrance",
    "sg:classifiers":[
        {
            "category":"Professional",
            "subcategory":"Lawyer & Legal Services",
            "type":"Services"
        }
    ],
    "sg:phone":"+1 310 464 1242",
    "sg:postcode":"90503",
    "sg:province":"CA",
    "wof:name":"Winterbotham Parham Teeple APC",
    "wof:placetype":"venue"
},
  "geometry": {"coordinates":[-118.355068,33.831088],"type":"Point"}
}