{
  "type": "Feature",
  "properties": {
    "addr:full":"7719 Killdeer Way Elk Grove CA 95758",
    "addr:housenumber":"7719",
    "addr:postcode":"95758",
    "addr:street":"Killdeer Way",
    "iso:country":"US",
    "sg:address":"7719 Killdeer Way",
    "sg:city":"Elk Grove",
    "sg:classifiers":[
        {
            "category":"Shopping",
            "subcategory":"Gifts & Souvenirs",
            "type":"Retail Goods"
        }
    ],
    "sg:phone":"+1 916 541 8232",
    "sg:postcode":"95758",
    "sg:province":"CA",
    "sg:tags":[
        "novelty"
    ],
    "wof:name":"Kindheart Creations",
    "wof:placetype":"venue"
},
  "geometry": {"coordinates":[-121.413707,38.410312],"type":"Point"}
}