{
  "type": "Feature",
  "properties": {
    "iso:country":"US",
    "sg:address":"4044 Bernice Dr",
    "sg:city":"San Diego",
    "sg:classifiers":[
        {
            "category":"Farming",
            "subcategory":"Fish & Marine Products",
            "type":"Manufacturing & Wholesale Goods"
        }
    ],
    "sg:phone":"+1 619 224 1186",
    "sg:postcode":"92107",
    "sg:province":"CA",
    "sg:tags":[
        "fishing"
    ],
    "wof:name":"Sea Chase",
    "wof:placetype":"venue"
},
  "geometry": {"coordinates":[-117.236345,32.738969],"type":"Point"}
}