{
  "type": "Feature",
  "properties": {
    "addr:full":"23023 Cerca Dr Valencia CA 91354",
    "addr:postcode":"23023;91354",
    "addr:street":"Cerca Dr",
    "iso:country":"US",
    "sg:address":"23023 Cerca Dr",
    "sg:city":"Valencia",
    "sg:classifiers":[
        {
            "category":"Real Estate",
            "subcategory":"Real Estate Operator",
            "type":"Services"
        }
    ],
    "sg:phone":"+1 661 299 5232",
    "sg:postcode":"91354",
    "sg:province":"CA",
    "sg:tags":[
        "apartment"
    ],
    "wof:name":"Cornerstone Business Parks",
    "wof:placetype":"venue"
},
  "geometry": {"coordinates":[-118.537795,34.433559],"type":"Point"}
}