{
  "type": "Feature",
  "properties": {
    "iso:country":"US",
    "sg:address":"1428 Cabrillo Ave",
    "sg:city":"Torrance",
    "sg:classifiers":[
        {
            "category":"Shopping",
            "subcategory":"Crafts & Fabrics",
            "type":"Retail Goods"
        },
        {
            "category":"Farming",
            "subcategory":"Fish & Marine Products",
            "type":"Manufacturing & Wholesale Goods"
        },
        {
            "category":"Retail",
            "subcategory":"Repair Shop",
            "type":"Services"
        },
        {
            "category":"Professional",
            "subcategory":"Art Services",
            "type":"Services"
        }
    ],
    "sg:phone":"+1 310 533 1654",
    "sg:postcode":"90501",
    "sg:province":"CA",
    "sg:tags":[
        "picture",
        "frame",
        "restoration",
        "framing"
    ],
    "sg:website":"http://www.carterframing.com",
    "wof:name":"Carter Picture Framing",
    "wof:placetype":"venue"
},
  "geometry": {"coordinates":[-118.31433,33.83411],"type":"Point"}
}