{
  "type": "Feature",
  "properties": {
    "addr:full":"28125 Bradley Rd Sun City CA 92586",
    "addr:housenumber":"28125",
    "addr:postcode":"92586",
    "addr:street":"Bradley Rd",
    "iso:country":"US",
    "sg:address":"28125 Bradley Rd",
    "sg:city":"Sun City",
    "sg:classifiers":[
        {
            "category":"Health Services",
            "subcategory":"Doctor",
            "type":"Services"
        }
    ],
    "sg:phone":"+1 951 679 9355",
    "sg:postcode":"92586",
    "sg:province":"CA",
    "sg:tags":[
        "dentist"
    ],
    "wof:name":"Sun City Dental",
    "wof:placetype":"venue"
},
  "geometry": {"coordinates":[-117.190899,33.716211],"type":"Point"}
}