{
  "type": "Feature",
  "properties": {
    "addr:full":"1791 Whittier Ave Costa Mesa CA 92627",
    "addr:housenumber":"1791",
    "addr:postcode":"92627",
    "addr:street":"Whittier Ave",
    "iso:country":"US",
    "sg:address":"1791 Whittier Ave",
    "sg:city":"Costa Mesa",
    "sg:classifiers":[
        {
            "category":"Manufacturing",
            "subcategory":"Wood Products",
            "type":"Manufacturing & Wholesale Goods"
        }
    ],
    "sg:phone":"+1 949 722 1246",
    "sg:postcode":"92627",
    "sg:province":"CA",
    "sg:tags":[
        "mfg"
    ],
    "wof:name":"J P Woodwork",
    "wof:placetype":"venue"
},
  "geometry": {"coordinates":[-117.940674,33.638571],"type":"Point"}
}