{
  "type": "Feature",
  "properties": {
    "iso:country":"US",
    "sg:address":"8408 Sierra Ave",
    "sg:city":"Fontana",
    "sg:classifiers":[
        {
            "category":"Real Estate",
            "subcategory":"Developer",
            "type":"Services"
        }
    ],
    "sg:phone":"+1 909 822 0553",
    "sg:postcode":"92335",
    "sg:province":"CA",
    "sg:tags":[
        "builder",
        "operative"
    ],
    "wof:name":"Boruchin Enterprises Inc",
    "wof:placetype":"venue"
},
  "geometry": {"coordinates":[-117.43585299999999,34.101161],"type":"Point"}
}