{
  "type": "Feature",
  "properties": {
    "addr:full":"2622 Gleason Ave Los Angeles CA 90033",
    "addr:housenumber":"2622",
    "addr:postcode":"90033",
    "addr:street":"Gleason Ave",
    "iso:country":"US",
    "sg:address":"2622 Gleason Ave",
    "sg:city":"Los Angeles",
    "sg:classifiers":[
        {
            "category":"Wholesale",
            "subcategory":"Fruits & Vegetables",
            "type":"Manufacturing & Wholesale Goods"
        }
    ],
    "sg:phone":"+1 213 488 1499",
    "sg:postcode":"90033",
    "sg:province":"CA",
    "sg:tags":[
        "grocery"
    ],
    "wof:name":"Doreens Tropical Fruit",
    "wof:placetype":"venue"
},
  "geometry": {"coordinates":[-118.206829,34.041233],"type":"Point"}
}