{
  "type": "Feature",
  "properties": {
    "addr:full":"3951 Higuera St Culver City CA 90232",
    "addr:housenumber":"3951",
    "addr:postcode":"90232",
    "addr:street":"Higuera St",
    "iso:country":"US",
    "sg:address":"3951 Higuera St",
    "sg:city":"Culver City",
    "sg:classifiers":[
        {
            "category":"Professional",
            "subcategory":"Art Services",
            "type":"Services"
        }
    ],
    "sg:phone":"+1 310 837 5300",
    "sg:postcode":"90232",
    "sg:province":"CA",
    "sg:tags":[
        "photographer"
    ],
    "sg:website":"www.merfeldphotography.com",
    "wof:name":"Ken Merfeld's Photo Studio",
    "wof:placetype":"venue"
},
  "geometry": {"coordinates":[-118.389398,34.025102],"type":"Point"}
}