{
  "type": "Feature",
  "properties": {
    "iso:country":"US",
    "sg:address":"13142 Knotty Pine St",
    "sg:city":"Moorpark",
    "sg:classifiers":[
        {
            "category":"Wholesale",
            "subcategory":"Non-durable Goods",
            "type":"Manufacturing & Wholesale Goods"
        }
    ],
    "sg:phone":"+1 805 523 9436",
    "sg:postcode":"93021",
    "sg:province":"CA",
    "sg:tags":[
        "dry",
        "goods-wholesale"
    ],
    "sg:website":"http://www.importwarehouse.com",
    "wof:name":"Import Warehouse",
    "wof:placetype":"venue"
},
  "geometry": {"coordinates":[-118.88014200000001,34.270809],"type":"Point"}
}