{
  "type": "Feature",
  "properties": {
    "addr:full":"19010 Pacific Coast Hwy Malibu CA 90265",
    "addr:housenumber":"19010",
    "addr:postcode":"90265",
    "addr:street":"Pacific Coast Hwy",
    "iso:country":"US",
    "sg:address":"19010 Pacific Coast Hwy",
    "sg:city":"Malibu",
    "sg:classifiers":[
        {
            "category":"Health Services",
            "subcategory":"Health Practitioner",
            "type":"Services"
        },
        {
            "category":"Communications",
            "type":"Services"
        }
    ],
    "sg:phone":"+1 310 456 1422",
    "sg:postcode":"90265",
    "sg:province":"CA",
    "sg:tags":[
        "pathologist",
        "speech-language",
        "myofunctional",
        "therapy"
    ],
    "wof:name":"Elinor Bernstein",
    "wof:placetype":"venue"
},
  "geometry": {"coordinates":[-118.590172,34.039579],"type":"Point"}
}