{
  "type": "Feature",
  "properties": {
    "iso:country":"US",
    "sg:address":"450 Sutter St Ste 933",
    "sg:city":"San Francisco",
    "sg:classifiers":[
        {
            "category":"Health Services",
            "subcategory":"Doctor",
            "type":"Services"
        }
    ],
    "sg:phone":"+1 415 362 5443",
    "sg:postcode":"94108",
    "sg:province":"CA",
    "sg:tags":[
        "throat",
        "ear",
        "nose"
    ],
    "sg:website":"sfotomed.com/",
    "wof:name":"Jacob Johnson, MD",
    "wof:placetype":"venue"
},
  "geometry": {"coordinates":[-122.407826,37.789369],"type":"Point"}
}