{
  "type": "Feature",
  "properties": {
    "addr:full":"6204 Osler St San Diego CA 92111",
    "addr:housenumber":"6204",
    "addr:postcode":"92111",
    "addr:street":"Osler St",
    "iso:country":"US",
    "sg:address":"6204 Osler St",
    "sg:city":"San Diego",
    "sg:classifiers":[
        {
            "category":"Retail",
            "subcategory":"Laundry & Dry Cleaning",
            "type":"Services"
        }
    ],
    "sg:phone":"+1 858 576 1489",
    "sg:postcode":"92111",
    "sg:province":"CA",
    "sg:tags":[
        "cleaners",
        "rug",
        "carpet"
    ],
    "wof:name":"Ed & Mary Ann's Pro Carpet",
    "wof:placetype":"venue"
},
  "geometry": {"coordinates":[-117.181273,32.791847],"type":"Point"}
}