{
  "type": "Feature",
  "properties": {
    "iso:country":"US",
    "sg:address":"1251 Montalvo Way",
    "sg:city":"Palm Springs",
    "sg:classifiers":[
        {
            "category":"Building & Trades",
            "subcategory":"Equipment Rental",
            "type":"Services"
        }
    ],
    "sg:phone":"+1 760 327 3380",
    "sg:postcode":"92262",
    "sg:province":"CA",
    "sg:tags":[
        "audio",
        "leasing"
    ],
    "sg:website":"www.avsu.com",
    "wof:name":"Audio Visual Svc Unlimited",
    "wof:placetype":"venue"
},
  "geometry": {"coordinates":[-116.50984,33.838318],"type":"Point"}
}