{
  "type": "Feature",
  "properties": {
    "addr:full":"25 Jordans Pl Chico CA 95973",
    "addr:housenumber":"25",
    "addr:postcode":"95973",
    "addr:street":"Jordans Pl",
    "iso:country":"US",
    "sg:address":"25 Jordans Pl",
    "sg:city":"Chico",
    "sg:classifiers":[
        {
            "category":"Building & Trades",
            "subcategory":"Electrical",
            "type":"Services"
        }
    ],
    "sg:phone":"+1 530 892 8857",
    "sg:postcode":"95973",
    "sg:province":"CA",
    "sg:tags":[
        "electric",
        "contractor"
    ],
    "wof:name":"Lighthouse Electric",
    "wof:placetype":"venue"
},
  "geometry": {"coordinates":[-121.89086500000001,39.746743],"type":"Point"}
}