{
  "type": "Feature",
  "properties": {
    "iso:country":"US",
    "sg:address":"19009 Ventura Blvd",
    "sg:city":"Tarzana",
    "sg:classifiers":[
        {
            "category":"Personal",
            "subcategory":"Beauty Salon",
            "type":"Services"
        }
    ],
    "sg:phone":"+1 818 996 0222",
    "sg:postcode":"91356",
    "sg:province":"CA",
    "wof:name":"Alex Beauty",
    "wof:placetype":"venue"
},
  "geometry": {"coordinates":[-118.548264,34.172591],"type":"Point"}
}