{
  "type": "Feature",
  "properties": {
    "addr:full":"12448 Ventura Blvd Studio City CA 91604",
    "addr:housenumber":"12448",
    "addr:postcode":"91604",
    "addr:street":"Ventura Blvd",
    "iso:country":"US",
    "sg:address":"12448 Ventura Blvd",
    "sg:city":"Studio City",
    "sg:classifiers":[
        {
            "category":"Personal",
            "subcategory":"Beauty Salon",
            "type":"Services"
        }
    ],
    "sg:phone":"+1 818 760 7141",
    "sg:postcode":"91604",
    "sg:province":"CA",
    "sg:tags":[
        "hair"
    ],
    "sg:website":"www.theyellowballoon.com",
    "wof:name":"The Yellow Balloon Inc",
    "wof:placetype":"venue"
},
  "geometry": {"coordinates":[-118.40467700000001,34.142455],"type":"Point"}
}