{
  "type": "Feature",
  "properties": {
    "addr:full":"496 W Camino Real Ave Arcadia CA 91007",
    "addr:housenumber":"496",
    "addr:postcode":"91007",
    "addr:street":"W Camino Real Ave",
    "iso:country":"US",
    "sg:address":"496 W Camino Real Ave",
    "sg:city":"Arcadia",
    "sg:classifiers":[
        {
            "category":"Health Services",
            "subcategory":"Chiropractor",
            "type":"Services"
        }
    ],
    "sg:phone":"+1 626 821 9851",
    "sg:postcode":"91007",
    "sg:province":"CA",
    "sg:tags":[
        "chiropractic"
    ],
    "wof:name":"D C & Charmway Co",
    "wof:placetype":"venue"
},
  "geometry": {"coordinates":[-118.048418,34.12246],"type":"Point"}
}