{
  "type": "Feature",
  "properties": {
    "addr:full":"3001 Winchester Blvd Campbell CA 95008",
    "addr:housenumber":"3001",
    "addr:postcode":"95008",
    "addr:street":"Winchester Blvd",
    "iso:country":"US",
    "sg:address":"3001 Winchester Blvd",
    "sg:city":"Campbell",
    "sg:classifiers":[
        {
            "category":"Building & Trades",
            "subcategory":"Construction",
            "type":"Services"
        }
    ],
    "sg:phone":"+1 408 379 7770",
    "sg:postcode":"95008",
    "sg:province":"CA",
    "sg:tags":[
        "contractor"
    ],
    "wof:name":"E S P Envrnmntlly Safe Pdts PR",
    "wof:placetype":"venue"
},
  "geometry": {"coordinates":[-121.95603,37.26918],"type":"Point"}
}