{
  "type": "Feature",
  "properties": {
    "addr:full":"4251 Susan Ln Penngrove CA 94951",
    "addr:housenumber":"4251",
    "addr:postcode":"94951",
    "addr:street":"Susan Ln",
    "iso:country":"US",
    "sg:address":"4251 Susan Ln",
    "sg:city":"Penngrove",
    "sg:classifiers":[
        {
            "category":"Banks & Credit Unions",
            "subcategory":"Investment Brokerage",
            "type":"Services"
        }
    ],
    "sg:phone":"+1 707 795 2221",
    "sg:postcode":"94951",
    "sg:province":"CA",
    "sg:tags":[
        "stock",
        "bond"
    ],
    "wof:name":"Peter Martensen Investment",
    "wof:placetype":"venue"
},
  "geometry": {"coordinates":[-122.631998,38.327451],"type":"Point"}
}