{
  "type": "Feature",
  "properties": {
    "addr:full":"9880 Research Dr Irvine CA 92618",
    "addr:housenumber":"9880",
    "addr:postcode":"92618",
    "addr:street":"Research Dr",
    "iso:country":"US",
    "sg:address":"9880 Research Dr",
    "sg:city":"Irvine",
    "sg:classifiers":[
        {
            "category":"Professional",
            "subcategory":"Lawyer & Legal Services",
            "type":"Services"
        }
    ],
    "sg:phone":"+1 949 387 7200",
    "sg:postcode":"92618",
    "sg:province":"CA",
    "wof:name":"James Hawkins Attorneys At Law",
    "wof:placetype":"venue"
},
  "geometry": {"coordinates":[-117.727203,33.63061],"type":"Point"}
}