{
  "type": "Feature",
  "properties": {
    "iso:country":"US",
    "sg:address":"1134 N Avalon Blvd",
    "sg:city":"Wilmington",
    "sg:classifiers":[
        {
            "category":"Banks & Credit Unions",
            "subcategory":"Bank",
            "type":"Services"
        }
    ],
    "sg:phone":"+1 310 834 6411",
    "sg:postcode":"90744",
    "sg:province":"CA",
    "wof:name":"ILWU Credit Union",
    "wof:placetype":"venue"
},
  "geometry": {"coordinates":[-118.262837,33.786028],"type":"Point"}
}