{
  "type": "Feature",
  "properties": {
    "addr:full":"2206 E Revere Rd Fresno CA 93720",
    "addr:housenumber":"2206",
    "addr:postcode":"93720",
    "addr:street":"E Revere Rd",
    "iso:country":"US",
    "sg:address":"2206 E Revere Rd",
    "sg:city":"Fresno",
    "sg:classifiers":[
        {
            "category":"Professional",
            "subcategory":"Lawyer & Legal Services",
            "type":"Services"
        }
    ],
    "sg:phone":"+1 559 434 6670",
    "sg:postcode":"93720",
    "sg:province":"CA",
    "sg:tags":[
        "attorney"
    ],
    "wof:name":"Rose Mohan Attorney Of Law",
    "wof:placetype":"venue"
},
  "geometry": {"coordinates":[-119.74229699999999,36.879915],"type":"Point"}
}