{
  "type": "Feature",
  "properties": {
    "iso:country":"US",
    "sg:address":"5245 W Ave L",
    "sg:city":"Lancaster",
    "sg:classifiers":[
        {
            "category":"Building & Trades",
            "subcategory":"Pest Control",
            "type":"Services"
        }
    ],
    "sg:phone":"+1 661 269 1463",
    "sg:postcode":"93536",
    "sg:province":"CA",
    "wof:name":"Pacific West Exterminators",
    "wof:placetype":"venue"
},
  "geometry": {"coordinates":[-118.222813,34.660322],"type":"Point"}
}