{
  "type": "Feature",
  "properties": {
    "addr:full":"3090 Stevens Creek Blvd San Jose CA 95128",
    "addr:housenumber":"3090",
    "addr:postcode":"95128",
    "addr:street":"Stevens Creek Blvd",
    "iso:country":"US",
    "sg:address":"3090 Stevens Creek Blvd",
    "sg:city":"San Jose",
    "sg:classifiers":[
        {
            "category":"Home & Garden",
            "subcategory":"Household Appliances",
            "type":"Retail Goods"
        },
        {
            "category":"Wholesale",
            "subcategory":"Computers",
            "type":"Manufacturing & Wholesale Goods"
        },
        {
            "category":"Shopping",
            "subcategory":"Mobile Phones",
            "type":"Retail Goods"
        },
        {
            "category":"Shopping",
            "subcategory":"Computers & Home Electronics",
            "type":"Retail Goods"
        },
        {
            "category":"Food & Beverages",
            "subcategory":"Groceries & Convenience Stores",
            "type":"Retail Goods"
        }
    ],
    "sg:phone":"+1 408 241 6040",
    "sg:postcode":"95128",
    "sg:province":"CA",
    "sg:website":"www.bestbuy.com",
    "wof:name":"Best Buy",
    "wof:placetype":"venue"
},
  "geometry": {"coordinates":[-121.94918800000001,37.322983],"type":"Point"}
}