{
  "type": "Feature",
  "properties": {
    "addr:full":"8602 Bayonne Dr Huntington Beach CA 92646",
    "addr:housenumber":"8602",
    "addr:postcode":"92646",
    "addr:street":"Bayonne Dr",
    "iso:country":"US",
    "sg:address":"8602 Bayonne Dr",
    "sg:city":"Huntington Beach",
    "sg:phone":"+1 714 964 6894",
    "sg:postcode":"92646",
    "sg:province":"CA",
    "sg:tags":[
        "equipment",
        "commercial"
    ],
    "wof:name":"Rd Equipment Rentals",
    "wof:placetype":"venue"
},
  "geometry": {"coordinates":[-117.979027,33.679876],"type":"Point"}
}