{
  "type": "Feature",
  "properties": {
    "addr:full":"1119 Ordway St Albany CA 94706",
    "addr:housenumber":"1119",
    "addr:postcode":"94706",
    "addr:street":"Ordway St",
    "iso:country":"US",
    "sg:address":"1119 Ordway St",
    "sg:city":"Albany",
    "sg:classifiers":[
        {
            "category":"Social Services",
            "subcategory":"Child Care",
            "type":"Services"
        }
    ],
    "sg:phone":"+1 510 528 0562",
    "sg:postcode":"94706",
    "sg:province":"CA",
    "wof:name":"Montessori Children's House",
    "wof:placetype":"venue"
},
  "geometry": {"coordinates":[-122.28594,37.882541],"type":"Point"}
}