{
  "type": "Feature",
  "properties": {
    "addr:full":"1603 Commerce Way Paso Robles CA 93446",
    "addr:housenumber":"1603",
    "addr:postcode":"93446",
    "addr:street":"Commerce Way",
    "iso:country":"US",
    "sg:address":"1603 Commerce Way",
    "sg:city":"Paso Robles",
    "sg:classifiers":[
        {
            "category":"Wholesale",
            "subcategory":"Stationery",
            "type":"Manufacturing & Wholesale Goods"
        }
    ],
    "sg:phone":"+1 805 237 1910",
    "sg:postcode":"93446",
    "sg:province":"CA",
    "sg:tags":[
        "container",
        "plastic"
    ],
    "wof:name":"Lindamar Industries",
    "wof:placetype":"venue"
},
  "geometry": {"coordinates":[-120.652331,35.615663],"type":"Point"}
}