{
  "type": "Feature",
  "properties": {
    "addr:full":"7084 Co Rd 31 Orland CA 95963",
    "addr:housenumber":"7084;31",
    "addr:postcode":"95963",
    "addr:street":"Co Rd",
    "iso:country":"US",
    "sg:address":"7084 Co Rd 31",
    "sg:city":"Orland",
    "sg:classifiers":[
        {
            "category":"Farming",
            "subcategory":"Dairy Farm",
            "type":"Manufacturing & Wholesale Goods"
        }
    ],
    "sg:phone":"+1 530 934 8463",
    "sg:postcode":"95963",
    "sg:province":"CA",
    "wof:name":"Goedhart Dairy",
    "wof:placetype":"venue"
},
  "geometry": {"coordinates":[-122.132597,39.638302],"type":"Point"}
}