{
  "type": "Feature",
  "properties": {
    "addr:full":"309 E 8th St Los Angeles CA 90014",
    "addr:housenumber":"309",
    "addr:postcode":"90014",
    "addr:street":"E 8Th St",
    "iso:country":"US",
    "sg:address":"309 E 8th St",
    "sg:city":"Los Angeles",
    "sg:classifiers":[
        {
            "category":"Education",
            "subcategory":"Vocational School",
            "type":"Public Place"
        }
    ],
    "sg:phone":"+1 213 955 6173",
    "sg:postcode":"90014",
    "sg:province":"CA",
    "sg:tags":[
        "sewing",
        "instruction"
    ],
    "wof:name":"Sanchez Contractor",
    "wof:placetype":"venue"
},
  "geometry": {"coordinates":[-118.251133,34.040929],"type":"Point"}
}