{
  "type": "Feature",
  "properties": {
    "iso:country":"US",
    "sg:address":"3044 Industry St Ste 105",
    "sg:city":"Oceanside",
    "sg:classifiers":[
        {
            "category":"Building & Trades",
            "subcategory":"Construction",
            "type":"Services"
        }
    ],
    "sg:phone":"+1 760 966 1995",
    "sg:postcode":"92054",
    "sg:province":"CA",
    "sg:tags":[
        "contractor"
    ],
    "wof:name":"Mari John M Reinforcing Steel Contractor",
    "wof:placetype":"venue"
},
  "geometry": {"coordinates":[-117.335999,33.2006],"type":"Point"}
}