{
  "type": "Feature",
  "properties": {
    "addr:full":"3713 Alamo St Simi Valley CA 93063",
    "addr:housenumber":"3713",
    "addr:postcode":"93063",
    "addr:street":"Alamo St",
    "iso:country":"US",
    "sg:address":"3713 Alamo St",
    "sg:city":"Simi Valley",
    "sg:classifiers":[
        {
            "category":"Insurance",
            "subcategory":"Insurance Agent",
            "type":"Services"
        }
    ],
    "sg:phone":"+1 805 520 4997",
    "sg:postcode":"93063",
    "sg:province":"CA",
    "wof:name":"Costello & Assoc Insurance",
    "wof:placetype":"venue"
},
  "geometry": {"coordinates":[-118.724084,34.286386],"type":"Point"}
}