{
  "type": "Feature",
  "properties": {
    "iso:country":"US",
    "sg:address":"7432 Prince Drive",
    "sg:city":"Huntington Beach",
    "sg:classifiers":[
        {
            "category":"Shopping",
            "subcategory":"Stationery & Office Supplies",
            "type":"Retail Goods"
        }
    ],
    "sg:phone":"+1 714 596 4366",
    "sg:postcode":"92647",
    "sg:province":"CA",
    "sg:tags":[
        "equipment"
    ],
    "wof:name":"Express Modular Systems",
    "wof:placetype":"venue"
},
  "geometry": {"coordinates":[-117.999788,33.718159],"type":"Point"}
}