{
  "type": "Feature",
  "properties": {
    "addr:full":"1712 Montana Street Los Angeles CA 90026",
    "addr:housenumber":"1712",
    "addr:postcode":"90026",
    "addr:street":"Montana Street",
    "iso:country":"US",
    "sg:address":"1712 Montana Street",
    "sg:city":"Los Angeles",
    "sg:classifiers":[
        {
            "category":"Social Services",
            "subcategory":"Child Care",
            "type":"Services"
        }
    ],
    "sg:phone":"+1 213 413 1380",
    "sg:postcode":"90026",
    "sg:province":"CA",
    "sg:tags":[
        "day"
    ],
    "wof:name":"Logan Street Children's Center",
    "wof:placetype":"venue"
},
  "geometry": {"coordinates":[-118.257915,34.078624],"type":"Point"}
}