{
  "type": "Feature",
  "properties": {
    "iso:country":"US",
    "sg:address":"413 N Pacific Coast Hwy",
    "sg:city":"Redondo Beach",
    "sg:classifiers":[
        {
            "category":"Shopping",
            "type":"Retail Goods"
        }
    ],
    "sg:phone":"+1 310 318 2653",
    "sg:postcode":"90277",
    "sg:province":"CA",
    "sg:tags":[
        "pet",
        "food",
        "supply"
    ],
    "wof:name":"Centinela Feed & Pet",
    "wof:placetype":"venue"
},
  "geometry": {"coordinates":[-118.388533,33.84883],"type":"Point"}
}