{
  "type": "Feature",
  "properties": {
    "addr:full":"23 E Oak Ave Porterville CA 93257",
    "addr:housenumber":"23",
    "addr:postcode":"93257",
    "addr:street":"E Oak Ave",
    "iso:country":"US",
    "sg:address":"23 E Oak Ave",
    "sg:city":"Porterville",
    "sg:classifiers":[
        {
            "category":"Education",
            "subcategory":"Special Training",
            "type":"Public Place"
        },
        {
            "category":"Professional",
            "subcategory":"Business Services",
            "type":"Services"
        }
    ],
    "sg:phone":"+1 559 783 9018",
    "sg:postcode":"93257",
    "sg:province":"CA",
    "sg:tags":[
        "preparation",
        "test",
        "educational",
        "testing",
        "tutoring"
    ],
    "sg:website":"http://www.caltutoringcompany.com",
    "wof:name":"California Tutoring Company",
    "wof:placetype":"venue"
},
  "geometry": {"coordinates":[-119.015822,36.067895],"type":"Point"}
}