{
  "type": "Feature",
  "properties": {
    "addr:full":"21607 Stevens Creek Blvd Cupertino CA 95014",
    "addr:housenumber":"21607",
    "addr:postcode":"95014",
    "addr:street":"Stevens Creek Blvd",
    "iso:country":"US",
    "sg:address":"21607 Stevens Creek Blvd",
    "sg:city":"Cupertino",
    "sg:classifiers":[
        {
            "category":"Health Services",
            "subcategory":"Health Practitioner",
            "type":"Services"
        }
    ],
    "sg:phone":"+1 408 910 6089",
    "sg:postcode":"95014",
    "sg:province":"CA",
    "sg:tags":[
        "acupuncture"
    ],
    "wof:name":"American Health & Acupuncture Center",
    "wof:placetype":"venue"
},
  "geometry": {"coordinates":[-122.05148,37.322918],"type":"Point"}
}