{
  "type": "Feature",
  "properties": {
    "addr:full":"2056 East St Concord CA 94520",
    "addr:housenumber":"2056",
    "addr:postcode":"94520",
    "addr:street":"East St",
    "iso:country":"US",
    "sg:address":"2056 East St",
    "sg:city":"Concord",
    "sg:classifiers":[
        {
            "category":"Food & Beverages",
            "subcategory":"Candy",
            "type":"Retail Goods"
        }
    ],
    "sg:phone":"+1 925 680 4383",
    "sg:postcode":"94520",
    "sg:province":"CA",
    "sg:tags":[
        "confectionery"
    ],
    "wof:name":"Candy Bar",
    "wof:placetype":"venue"
},
  "geometry": {"coordinates":[-122.031595,37.979514],"type":"Point"}
}