{
  "type": "Feature",
  "properties": {
    "iso:country":"US",
    "sg:address":"97 Gaffey Rd",
    "sg:city":"Watsonville",
    "sg:classifiers":[
        {
            "category":"Transit Center",
            "subcategory":"Freight",
            "type":"Transportation"
        },
        {
            "category":"Freight",
            "type":"Transportation"
        }
    ],
    "sg:phone":"+1 831 763 1082",
    "sg:postcode":"95076",
    "sg:province":"CA",
    "sg:tags":[
        "local",
        "trucking-motor",
        "trucking"
    ],
    "wof:name":"Sunline Trucking & Tractor Service",
    "wof:placetype":"venue"
},
  "geometry": {"coordinates":[-121.734576,36.989362],"type":"Point"}
}