{
  "type": "Feature",
  "properties": {
    "iso:country":"US",
    "sg:address":"13741 Van Nuys Blvd",
    "sg:city":"Pacoima",
    "sg:classifiers":[
        {
            "category":"Autos & Motor Vehicles",
            "subcategory":"Auto Supplies",
            "type":"Retail Goods"
        }
    ],
    "sg:phone":"+1 818 897 7142",
    "sg:postcode":"91331",
    "sg:province":"CA",
    "wof:name":"J Tire Service",
    "wof:placetype":"venue"
},
  "geometry": {"coordinates":[-118.433771,34.257673],"type":"Point"}
}