{
  "type": "Feature",
  "properties": {
    "addr:full":"625 S Riverside Ave Rialto CA 92376",
    "addr:housenumber":"625",
    "addr:postcode":"92376",
    "addr:street":"S Riverside Ave",
    "iso:country":"US",
    "sg:address":"625 S Riverside Ave",
    "sg:city":"Rialto",
    "sg:classifiers":[
        {
            "category":"Manufacturing",
            "subcategory":"Electronics",
            "type":"Manufacturing & Wholesale Goods"
        }
    ],
    "sg:phone":"+1 909 820 4435",
    "sg:postcode":"92376",
    "sg:province":"CA",
    "sg:tags":[
        "record"
    ],
    "wof:name":"Cellu-One",
    "wof:placetype":"venue"
},
  "geometry": {"coordinates":[-117.370282,34.091352],"type":"Point"}
}