{
  "type": "Feature",
  "properties": {
    "addr:full":"5277 Vincent Ave Baldwin Park CA 91706",
    "addr:housenumber":"5277",
    "addr:postcode":"91706",
    "addr:street":"Vincent Ave",
    "iso:country":"US",
    "sg:address":"5277 Vincent Ave",
    "sg:city":"Baldwin Park",
    "sg:classifiers":[
        {
            "category":"Building & Trades",
            "subcategory":"Construction",
            "type":"Services"
        }
    ],
    "sg:phone":"+1 626 633 0919",
    "sg:postcode":"91706",
    "sg:province":"CA",
    "sg:tags":[
        "contractor"
    ],
    "wof:name":"On-Site Construction",
    "wof:placetype":"venue"
},
  "geometry": {"coordinates":[-117.925414,34.10874],"type":"Point"}
}