{
  "type": "Feature",
  "properties": {
    "addr:full":"809 E Parkridge Ave Corona CA 92879",
    "addr:housenumber":"809",
    "addr:postcode":"92879",
    "addr:street":"E Parkridge Ave",
    "iso:country":"US",
    "sg:address":"809 E Parkridge Ave",
    "sg:city":"Corona",
    "sg:classifiers":[
        {
            "category":"Home & Garden",
            "subcategory":"Home Furnishings",
            "type":"Retail Goods"
        }
    ],
    "sg:phone":"+1 951 808 4904",
    "sg:postcode":"92879",
    "sg:province":"CA",
    "sg:tags":[
        "lighting",
        "fixture"
    ],
    "wof:name":"Jetinetics",
    "wof:placetype":"venue"
},
  "geometry": {"coordinates":[-117.550381,33.885861],"type":"Point"}
}