{
  "type": "Feature",
  "properties": {
    "iso:country":"US",
    "sg:address":"4261 Auburn Blvd",
    "sg:city":"Sacramento",
    "sg:classifiers":[
        {
            "category":"Home & Garden",
            "subcategory":"Garden Supply",
            "type":"Retail Goods"
        }
    ],
    "sg:phone":"+1 916 550 1387",
    "sg:postcode":"95841",
    "sg:province":"CA",
    "sg:tags":[
        "nursery",
        "gardening"
    ],
    "sg:website":"www.twodogshydro.biz",
    "wof:name":"Two Dogs Hydroponics",
    "wof:placetype":"venue"
},
  "geometry": {"coordinates":[-121.36467500000001,38.644834],"type":"Point"}
}