{
  "type": "Feature",
  "properties": {
    "addr:full":"1250 E Main St Santa Paula CA 93060",
    "addr:housenumber":"1250",
    "addr:postcode":"93060",
    "addr:street":"E Main St",
    "iso:country":"US",
    "sg:address":"1250 E Main St",
    "sg:city":"Santa Paula",
    "sg:classifiers":[
        {
            "category":"Food & Beverages",
            "subcategory":"Groceries & Convenience Stores",
            "type":"Retail Goods"
        }
    ],
    "sg:phone":"+1 805 933 9559",
    "sg:postcode":"93060",
    "sg:province":"CA",
    "sg:tags":[
        "market"
    ],
    "wof:name":"Nick's Market",
    "wof:placetype":"venue"
},
  "geometry": {"coordinates":[-119.054952,34.355511],"type":"Point"}
}