{
  "type": "Feature",
  "properties": {
    "addr:full":"945 W Huntington Dr Monrovia CA 91016",
    "addr:housenumber":"945",
    "addr:postcode":"91016",
    "addr:street":"W Huntington Dr",
    "iso:country":"US",
    "sg:address":"945 W Huntington Dr",
    "sg:city":"Monrovia",
    "sg:classifiers":[
        {
            "category":"Restaurant",
            "type":"Food & Drink"
        }
    ],
    "sg:phone":"+1 626 256 7969",
    "sg:postcode":"91016",
    "sg:province":"CA",
    "sg:website":"www.macaronigrill.com",
    "wof:name":"Romano's Macaroni Grill",
    "wof:placetype":"venue"
},
  "geometry": {"coordinates":[-118.020411,34.140266],"type":"Point"}
}