{
  "type": "Feature",
  "properties": {
    "iso:country":"US",
    "sg:address":"11591 Yankee Hill Rd",
    "sg:city":"Columbia",
    "sg:classifiers":[
        {
            "category":"Utilities",
            "subcategory":"Water",
            "type":"Services"
        }
    ],
    "sg:phone":"+1 209 532 0432",
    "sg:postcode":"95310",
    "sg:province":"CA",
    "sg:tags":[
        "consultant"
    ],
    "wof:name":"John Offices Of Mills",
    "wof:placetype":"venue"
},
  "geometry": {"coordinates":[-120.392506,38.036762],"type":"Point"}
}