{
  "type": "Feature",
  "properties": {
    "addr:full":"1117 N Gower St Los Angeles CA 90038",
    "addr:housenumber":"1117",
    "addr:postcode":"90038",
    "addr:street":"N Gower St",
    "iso:country":"US",
    "sg:address":"1117 N Gower St",
    "sg:city":"Los Angeles",
    "sg:classifiers":[
        {
            "category":"Communications",
            "subcategory":"Film & Video Production",
            "type":"Services"
        }
    ],
    "sg:phone":"+1 323 463 3166",
    "sg:postcode":"90038",
    "sg:province":"CA",
    "sg:tags":[
        "motion",
        "picture",
        "studio",
        "producer"
    ],
    "wof:name":"House Of Props Inc",
    "wof:placetype":"venue"
},
  "geometry": {"coordinates":[-118.32234699999999,34.092267],"type":"Point"}
}