{
  "type": "Feature",
  "properties": {
    "iso:country":"US",
    "sg:address":"2631 E 126th St",
    "sg:city":"Compton",
    "sg:classifiers":[
        {
            "category":"Manufacturing",
            "subcategory":"Metals",
            "type":"Manufacturing & Wholesale Goods"
        }
    ],
    "sg:phone":"+1 310 639 4343",
    "sg:postcode":"90222",
    "sg:province":"CA",
    "sg:tags":[
        "coating"
    ],
    "sg:website":"www.bowmanplating.com",
    "wof:name":"Bowman Plating Co",
    "wof:placetype":"venue"
},
  "geometry": {"coordinates":[-118.225471,33.918098],"type":"Point"}
}