{
  "type": "Feature",
  "properties": {
    "iso:country":"US",
    "sg:address":"17421 Nichols St",
    "sg:city":"Huntington Beach",
    "sg:classifiers":[
        {
            "category":"Wholesale",
            "subcategory":"Motor Vehicles",
            "type":"Manufacturing & Wholesale Goods"
        }
    ],
    "sg:phone":"+1 714 596 5258",
    "sg:postcode":"92647",
    "sg:province":"CA",
    "wof:name":"FA Motor Sports",
    "wof:placetype":"venue"
},
  "geometry": {"coordinates":[-117.99574,33.709116],"type":"Point"}
}