{
  "type": "Feature",
  "properties": {
    "addr:full":"4777 Davenport Ave Oakland CA 94619",
    "addr:housenumber":"4777",
    "addr:postcode":"94619",
    "addr:street":"Davenport Ave",
    "iso:country":"US",
    "sg:address":"4777 Davenport Ave",
    "sg:city":"Oakland",
    "sg:classifiers":[
        {
            "category":"Building & Trades",
            "subcategory":"Cleaning & Sanitation",
            "type":"Services"
        }
    ],
    "sg:phone":"+1 510 482 5222",
    "sg:postcode":"94619",
    "sg:province":"CA",
    "sg:tags":[
        "janitorial"
    ],
    "wof:name":"Ceiling-Clean",
    "wof:placetype":"venue"
},
  "geometry": {"coordinates":[-122.182782,37.78606],"type":"Point"}
}