{
  "type": "Feature",
  "properties": {
    "addr:full":"4683 Mission St San Francisco CA 94112",
    "addr:housenumber":"4683",
    "addr:postcode":"94112",
    "addr:street":"Mission St",
    "iso:country":"US",
    "sg:address":"4683 Mission St",
    "sg:city":"San Francisco",
    "sg:classifiers":[
        {
            "category":"Restaurant",
            "type":"Food & Drink"
        }
    ],
    "sg:menulink":"http://www.allmenus.com/ca/san-francisco/81808-sheng-xing-china-express/menu/",
    "sg:phone":"+1 415 337 9589",
    "sg:postcode":"94112",
    "sg:province":"CA",
    "sg:tags":[
        "asian",
        "chinese"
    ],
    "wof:name":"Sheng Xing China Express",
    "wof:placetype":"venue"
},
  "geometry": {"coordinates":[-122.43575,37.723488],"type":"Point"}
}