{
  "type": "Feature",
  "properties": {
    "addr:full":"1416 Concannon Blvd Livermore CA 94550",
    "addr:housenumber":"1416",
    "addr:postcode":"94550",
    "addr:street":"Concannon Blvd",
    "iso:country":"US",
    "sg:address":"1416 Concannon Blvd",
    "sg:city":"Livermore",
    "sg:classifiers":[
        {
            "category":"Building & Trades",
            "subcategory":"Construction",
            "type":"Services"
        }
    ],
    "sg:phone":"+1 925 443 9445",
    "sg:postcode":"94550",
    "sg:province":"CA",
    "sg:tags":[
        "excavation",
        "contractor"
    ],
    "wof:name":"Gilbert Excavating Inc",
    "wof:placetype":"venue"
},
  "geometry": {"coordinates":[-121.776167,37.660885],"type":"Point"}
}