{
  "type": "Feature",
  "properties": {
    "addr:full":"7021 Hatillo Ave Winnetka CA 91306",
    "addr:postcode":"7021;91306",
    "addr:street":"Hatillo Ave",
    "iso:country":"US",
    "sg:address":"7021 Hatillo Ave",
    "sg:city":"Winnetka",
    "sg:classifiers":[
        {
            "category":"Professional",
            "subcategory":"Computer Services",
            "type":"Services"
        }
    ],
    "sg:phone":"+1 818 347 3902",
    "sg:postcode":"91306",
    "sg:province":"CA",
    "sg:tags":[
        "home",
        "consulting",
        "page",
        "dev",
        "internet"
    ],
    "sg:website":"www.cybercloud.com",
    "wof:name":"CYBERCLOUD.COM",
    "wof:placetype":"venue"
},
  "geometry": {"coordinates":[-118.56559799999999,34.199762],"type":"Point"}
}