{
  "type": "Feature",
  "properties": {
    "iso:country":"US",
    "sg:address":"897 Independence Ave",
    "sg:city":"Mountain View",
    "sg:classifiers":[
        {
            "category":"Manufacturing",
            "subcategory":"Metals",
            "type":"Manufacturing & Wholesale Goods"
        }
    ],
    "sg:phone":"+1 650 404 6858",
    "sg:postcode":"94303",
    "sg:province":"CA",
    "sg:tags":[
        "coating"
    ],
    "wof:name":"3 L & T Inc",
    "wof:placetype":"venue"
},
  "geometry": {"coordinates":[-122.09717,37.41675],"type":"Point"}
}