{
  "type": "Feature",
  "properties": {
    "addr:full":"662 Fairplex Dr Pomona CA 91768",
    "addr:housenumber":"662",
    "addr:postcode":"91768",
    "addr:street":"Fairplex Dr",
    "iso:country":"US",
    "sg:address":"662 Fairplex Dr",
    "sg:city":"Pomona",
    "sg:classifiers":[
        {
            "category":"Food & Beverages",
            "subcategory":"Bakery",
            "type":"Retail Goods"
        }
    ],
    "sg:phone":"+1 909 620 9095",
    "sg:postcode":"91768",
    "sg:province":"CA",
    "sg:tags":[
        "doughnut"
    ],
    "wof:name":"Pomona Donut",
    "wof:placetype":"venue"
},
  "geometry": {"coordinates":[-117.787474,34.062066],"type":"Point"}
}