{
  "type": "Feature",
  "properties": {
    "iso:country":"US",
    "sg:address":"23733 Malibu Rd",
    "sg:city":"Malibu",
    "sg:classifiers":[
        {
            "category":"Shopping",
            "subcategory":"Clothing, Apparel, & Fashions",
            "type":"Retail Goods"
        }
    ],
    "sg:phone":"+1 310 317 0944",
    "sg:postcode":"90265",
    "sg:province":"CA",
    "wof:name":"Phillippe Derey Co",
    "wof:placetype":"venue"
},
  "geometry": {"coordinates":[-118.692679,34.033693],"type":"Point"}
}