{
  "type": "Feature",
  "properties": {
    "addr:full":"9225 Las Tunas Dr Temple City CA 91780",
    "addr:housenumber":"9225",
    "addr:postcode":"91780",
    "addr:street":"Las Tunas Dr",
    "iso:country":"US",
    "sg:address":"9225 Las Tunas Dr",
    "sg:city":"Temple City",
    "sg:classifiers":[
        {
            "category":"Autos & Motor Vehicles",
            "subcategory":"Auto Supplies",
            "type":"Retail Goods"
        }
    ],
    "sg:phone":"+1 626 286 3187",
    "sg:postcode":"91780",
    "sg:province":"CA",
    "sg:tags":[
        "automobile",
        "parts"
    ],
    "wof:name":"Temple City Auto Parts",
    "wof:placetype":"venue"
},
  "geometry": {"coordinates":[-118.06670699999999,34.10594],"type":"Point"}
}