{
  "type": "Feature",
  "properties": {
    "addr:full":"2820 Glendale Blvd Los Angeles CA 90039",
    "addr:housenumber":"2820",
    "addr:postcode":"90039",
    "addr:street":"Glendale Blvd",
    "iso:country":"US",
    "sg:address":"2820 Glendale Blvd",
    "sg:city":"Los Angeles",
    "sg:classifiers":[
        {
            "category":"Personal",
            "subcategory":"Beauty Salon",
            "type":"Services"
        }
    ],
    "sg:phone":"+1 323 906 1100",
    "sg:postcode":"90039",
    "sg:province":"CA",
    "sg:tags":[
        "spa"
    ],
    "sg:website":"www.theartofyouhc.com",
    "wof:name":"The Art Of You Holistic Center",
    "wof:placetype":"venue"
},
  "geometry": {"coordinates":[-118.263306,34.107762],"type":"Point"}
}