{
  "type": "Feature",
  "properties": {
    "iso:country":"US",
    "sg:address":"763 Altos Oaks Drive",
    "sg:city":"Los Altos",
    "sg:classifiers":[
        {
            "category":"Health Services",
            "subcategory":"Doctor",
            "type":"Services"
        }
    ],
    "sg:phone":"+1 650 948 4707",
    "sg:postcode":"94024",
    "sg:province":"CA",
    "wof:name":"Harris J Mayfield Dr Orthpc Sur",
    "wof:placetype":"venue"
},
  "geometry": {"coordinates":[-122.09387599999999,37.359338],"type":"Point"}
}