{
  "type": "Feature",
  "properties": {
    "iso:country":"US",
    "sg:address":"15620 Elmbrook Drive",
    "sg:city":"La Mirada",
    "sg:classifiers":[
        {
            "category":"Personal",
            "type":"Services"
        }
    ],
    "sg:postcode":"90638",
    "sg:province":"CA",
    "sg:tags":[
        "planning",
        "wedding"
    ],
    "sg:website":"www.krushnamandap.com/index.htm",
    "wof:name":"Krushna Mandap",
    "wof:placetype":"venue"
},
  "geometry": {"coordinates":[-118.001347,33.890104],"type":"Point"}
}