{
  "type": "Feature",
  "properties": {
    "addr:full":"175 S Mathew St Porterville CA 93257",
    "addr:housenumber":"175",
    "addr:postcode":"93257",
    "addr:street":"S Mathew St",
    "iso:country":"US",
    "sg:address":"175 S Mathew St",
    "sg:city":"Porterville",
    "sg:classifiers":[
        {
            "category":"Education",
            "subcategory":"School",
            "type":"Public Place"
        }
    ],
    "sg:phone":"+1 559 782 5902",
    "sg:postcode":"93257",
    "sg:province":"CA",
    "wof:name":"Burton School District",
    "wof:placetype":"venue"
},
  "geometry": {"coordinates":[-119.06191800000001,36.069057],"type":"Point"}
}