{
  "type": "Feature",
  "properties": {
    "addr:full":"4747 Ontiveros Ln Santa Maria CA 93454",
    "addr:postcode":"4747;93454",
    "addr:street":"Ontiveros Ln",
    "iso:country":"US",
    "sg:address":"4747 Ontiveros Ln",
    "sg:city":"Santa Maria",
    "sg:classifiers":[
        {
            "category":"Manufacturing",
            "subcategory":"Food",
            "type":"Manufacturing & Wholesale Goods"
        }
    ],
    "sg:phone":"+1 805 938 5050",
    "sg:postcode":"93454",
    "sg:province":"CA",
    "sg:tags":[
        "winery"
    ],
    "wof:name":"Tantara Winery",
    "wof:placetype":"venue"
},
  "geometry": {"coordinates":[-120.21214000000001,34.984945],"type":"Point"}
}