{
  "type": "Feature",
  "properties": {
    "addr:full":"2839 Pacific Coast Hwy Torrance CA 90505",
    "addr:housenumber":"2839",
    "addr:postcode":"90505",
    "addr:street":"Pacific Coast Hwy",
    "iso:country":"US",
    "sg:address":"2839 Pacific Coast Hwy",
    "sg:city":"Torrance",
    "sg:classifiers":[
        {
            "category":"Home & Garden",
            "subcategory":"Household Appliances",
            "type":"Retail Goods"
        }
    ],
    "sg:phone":"+1 310 257 8877",
    "sg:postcode":"90505",
    "sg:province":"CA",
    "sg:tags":[
        "repair"
    ],
    "wof:name":"Touchpoint Wireless",
    "wof:placetype":"venue"
},
  "geometry": {"coordinates":[-118.33642,33.794428],"type":"Point"}
}