{
  "type": "Feature",
  "properties": {
    "iso:country":"US",
    "sg:address":"4900 Wilshire Blvd",
    "sg:city":"Los Angeles",
    "sg:classifiers":[
        {
            "category":"Education",
            "subcategory":"School",
            "type":"Public Place"
        }
    ],
    "sg:phone":"+1 323 937 2762",
    "sg:postcode":"90010",
    "sg:province":"CA",
    "wof:name":"Wilshire School",
    "wof:placetype":"venue"
},
  "geometry": {"coordinates":[-118.337144,34.062089],"type":"Point"}
}