{
  "type": "Feature",
  "properties": {
    "addr:full":"2051 Hilltop Dr Redding CA 96002",
    "addr:housenumber":"2051",
    "addr:postcode":"96002",
    "addr:street":"Hilltop Dr",
    "iso:country":"US",
    "sg:address":"2051 Hilltop Dr",
    "sg:city":"Redding",
    "sg:classifiers":[
        {
            "category":"Social Services",
            "type":"Services"
        }
    ],
    "sg:phone":"+1 530 221 6960",
    "sg:postcode":"96002",
    "sg:province":"CA",
    "sg:tags":[
        "housing",
        "assistance"
    ],
    "wof:name":"Community Revitalization",
    "wof:placetype":"venue"
},
  "geometry": {"coordinates":[-122.357731,40.577943],"type":"Point"}
}