{
  "type": "Feature",
  "properties": {
    "addr:full":"85 Liberty Ship Way # 101 Sausalito CA 94965",
    "addr:housenumber":"85",
    "addr:postcode":"94965",
    "addr:street":"Liberty Ship Way # 101",
    "iso:country":"US",
    "sg:address":"85 Liberty Ship Way # 101",
    "sg:city":"Sausalito",
    "sg:classifiers":[
        {
            "category":"Health Services",
            "subcategory":"Nursing And Care Facility",
            "type":"Services"
        }
    ],
    "sg:phone":"+1 415 331 6912",
    "sg:postcode":"94965",
    "sg:province":"CA",
    "sg:tags":[
        "equipment",
        "therapy",
        "physical"
    ],
    "sg:website":"http://www.eyespack.com",
    "wof:name":"Corso Enterprises Inc",
    "wof:placetype":"venue"
},
  "geometry": {"coordinates":[-122.493289,37.863198],"type":"Point"}
}