{
  "type": "Feature",
  "properties": {
    "iso:country":"US",
    "sg:address":"120 C St",
    "sg:city":"Davis",
    "sg:classifiers":[
        {
            "category":"Professional",
            "type":"Services"
        }
    ],
    "sg:phone":"+1 530 756 2899",
    "sg:postcode":"95616",
    "sg:province":"CA",
    "wof:name":"MCN E I L Manor",
    "wof:placetype":"venue"
},
  "geometry": {"coordinates":[-121.74311,38.542606],"type":"Point"}
}