{
  "type": "Feature",
  "properties": {
    "addr:full":"1200 S San Pedro St Los Angeles CA 90015",
    "addr:housenumber":"1200",
    "addr:postcode":"90015",
    "addr:street":"S San Pedro St",
    "iso:country":"US",
    "sg:address":"1200 S San Pedro St",
    "sg:city":"Los Angeles",
    "sg:classifiers":[
        {
            "category":"Wholesale",
            "subcategory":"Apparel",
            "type":"Manufacturing & Wholesale Goods"
        }
    ],
    "sg:phone":"+1 213 747 2919",
    "sg:postcode":"90015",
    "sg:province":"CA",
    "wof:name":"Topia",
    "wof:placetype":"venue"
},
  "geometry": {"coordinates":[-118.25399899999999,34.032773],"type":"Point"}
}