{
  "type": "Feature",
  "properties": {
    "iso:country":"US",
    "sg:address":"492 7th St",
    "sg:city":"Oakland",
    "sg:classifiers":[
        {
            "category":"Professional",
            "subcategory":"Lawyer & Legal Services",
            "type":"Services"
        }
    ],
    "sg:phone":"+1 510 444 3797",
    "sg:postcode":"94607",
    "sg:province":"CA",
    "sg:tags":[
        "attorney"
    ],
    "wof:name":"Holland Law Firm",
    "wof:placetype":"venue"
},
  "geometry": {"coordinates":[-122.2744,37.799663],"type":"Point"}
}