{
  "type": "Feature",
  "properties": {
    "addr:full":"1340 Hilltop Dr Redding CA 96003",
    "addr:housenumber":"1340",
    "addr:postcode":"96003",
    "addr:street":"Hilltop Dr",
    "iso:country":"US",
    "sg:address":"1340 Hilltop Dr",
    "sg:city":"Redding",
    "sg:classifiers":[
        {
            "category":"Shopping",
            "subcategory":"Department Store",
            "type":"Retail Goods"
        },
        {
            "category":"Shopping",
            "subcategory":"Discount & Variety Stores",
            "type":"Retail Goods"
        },
        {
            "category":"Shopping",
            "type":"Retail Goods"
        }
    ],
    "sg:phone":"+1 530 224 0865",
    "sg:postcode":"96003",
    "sg:province":"CA",
    "sg:tags":[
        "merchandise"
    ],
    "sg:website":"http://www.biglots.com/",
    "wof:name":"Big Lots",
    "wof:placetype":"venue"
},
  "geometry": {"coordinates":[-122.358142,40.588579],"type":"Point"}
}