{
  "type": "Feature",
  "properties": {
    "addr:full":"1730 Sepulveda Blvd Torrance CA 90501",
    "addr:housenumber":"1730",
    "addr:postcode":"90501",
    "addr:street":"Sepulveda Blvd",
    "iso:country":"US",
    "sg:address":"1730 Sepulveda Blvd",
    "sg:city":"Torrance",
    "sg:classifiers":[
        {
            "category":"Restaurant",
            "type":"Food & Drink"
        }
    ],
    "sg:phone":"+1 310 539 1720",
    "sg:postcode":"90501",
    "sg:province":"CA",
    "wof:name":"Sobashubo Hayakawa",
    "wof:placetype":"venue"
},
  "geometry": {"coordinates":[-118.311103,33.817778],"type":"Point"}
}