{
  "type": "Feature",
  "properties": {
    "iso:country":"US",
    "sg:address":"1429 Motel Dr",
    "sg:city":"Merced",
    "sg:classifiers":[
        {
            "category":"Real Estate",
            "subcategory":"Real Estate Agent",
            "type":"Services"
        }
    ],
    "sg:phone":"+1 209 722 9600",
    "sg:postcode":"95341",
    "sg:province":"CA",
    "sg:tags":[
        "business"
    ],
    "wof:name":"Thomas Wilkins Co",
    "wof:placetype":"venue"
},
  "geometry": {"coordinates":[-120.460043,37.291044],"type":"Point"}
}