{
  "type": "Feature",
  "properties": {
    "addr:full":"3647 W 109th St Inglewood CA 90303",
    "addr:housenumber":"3647",
    "addr:postcode":"90303",
    "addr:street":"W 109Th St",
    "iso:country":"US",
    "sg:address":"3647 W 109th St",
    "sg:city":"Inglewood",
    "sg:classifiers":[
        {
            "category":"Utilities",
            "subcategory":"Refuse",
            "type":"Services"
        }
    ],
    "sg:phone":"+1 310 672 6359",
    "sg:postcode":"90303",
    "sg:province":"CA",
    "sg:tags":[
        "system"
    ],
    "wof:name":"C M Recycling",
    "wof:placetype":"venue"
},
  "geometry": {"coordinates":[-118.33589000000001,33.936843],"type":"Point"}
}