{
  "type": "Feature",
  "properties": {
    "addr:full":"3800 Guerneville Rd Santa Rosa CA 95401",
    "addr:housenumber":"3800",
    "addr:postcode":"95401",
    "addr:street":"Guerneville Rd",
    "iso:country":"US",
    "sg:address":"3800 Guerneville Rd",
    "sg:city":"Santa Rosa",
    "sg:classifiers":[
        {
            "category":"Wholesale",
            "subcategory":"Fruits & Vegetables",
            "type":"Manufacturing & Wholesale Goods"
        }
    ],
    "sg:phone":"+1 707 568 2450",
    "sg:postcode":"95401",
    "sg:province":"CA",
    "sg:tags":[
        "shipper"
    ],
    "wof:name":"Field Fresh Distributors",
    "wof:placetype":"venue"
},
  "geometry": {"coordinates":[-122.815066,38.452355],"type":"Point"}
}