{
  "type": "Feature",
  "properties": {
    "iso:country":"US",
    "sg:address":"37134 47th St E",
    "sg:city":"Palmdale",
    "sg:classifiers":[
        {
            "category":"Restaurant",
            "type":"Food & Drink"
        }
    ],
    "sg:menulink":"http://www.allmenus.com/ca/south-antelope-valley/239974-panda-express/menu/",
    "sg:phone":"+1 661 258 2859",
    "sg:postcode":"93552",
    "sg:province":"CA",
    "sg:tags":[
        "asian",
        "chinese"
    ],
    "wof:name":"Panda Express",
    "wof:placetype":"venue"
},
  "geometry": {"coordinates":[-118.045255,34.556308],"type":"Point"}
}