{
  "type": "Feature",
  "properties": {
    "addr:full":"990 Bay St Mountain View CA 94040",
    "addr:housenumber":"990",
    "addr:postcode":"94040",
    "addr:street":"Bay St",
    "iso:country":"US",
    "sg:address":"990 Bay St",
    "sg:city":"Mountain View",
    "sg:classifiers":[
        {
            "category":"Health Services",
            "subcategory":"Doctor",
            "type":"Services"
        }
    ],
    "sg:phone":"+1 650 968 4000",
    "sg:postcode":"94040",
    "sg:province":"CA",
    "sg:tags":[
        "dentist"
    ],
    "sg:website":"parktowndental.com",
    "wof:name":"Parktown Dental Care",
    "wof:placetype":"venue"
},
  "geometry": {"coordinates":[-122.075372,37.380632],"type":"Point"}
}