{
  "type": "Feature",
  "properties": {
    "addr:full":"14542 Ventura Blvd Sherman Oaks CA 91403",
    "addr:housenumber":"14542",
    "addr:postcode":"91403",
    "addr:street":"Ventura Blvd",
    "iso:country":"US",
    "sg:address":"14542 Ventura Blvd",
    "sg:city":"Sherman Oaks",
    "sg:classifiers":[
        {
            "category":"Real Estate",
            "subcategory":"Real Estate Agent",
            "type":"Services"
        }
    ],
    "sg:phone":"+1 818 784 1704",
    "sg:postcode":"91403",
    "sg:province":"CA",
    "sg:tags":[
        "mortgage"
    ],
    "wof:name":"P C S",
    "wof:placetype":"venue"
},
  "geometry": {"coordinates":[-118.450137,34.151052],"type":"Point"}
}