{
  "type": "Feature",
  "properties": {
    "iso:country":"US",
    "sg:address":"871 Tupelo Wood Ct",
    "sg:city":"Newbury Park",
    "sg:classifiers":[
        {
            "category":"Wholesale",
            "subcategory":"Medical Equipment & Supplies",
            "type":"Manufacturing & Wholesale Goods"
        }
    ],
    "sg:phone":"+1 805 499 5272",
    "sg:postcode":"91320",
    "sg:province":"CA",
    "wof:name":"James Tassio",
    "wof:placetype":"venue"
},
  "geometry": {"coordinates":[-118.90110799999999,34.177739],"type":"Point"}
}