{
  "type": "Feature",
  "properties": {
    "addr:full":"200 E Slauson Ave Los Angeles CA 90011",
    "addr:housenumber":"200",
    "addr:postcode":"90011",
    "addr:street":"E Slauson Ave",
    "iso:country":"US",
    "sg:address":"200 E Slauson Ave",
    "sg:city":"Los Angeles",
    "sg:classifiers":[
        {
            "category":"Manufacturing",
            "subcategory":"Metals",
            "type":"Manufacturing & Wholesale Goods"
        }
    ],
    "sg:phone":"+1 323 235 0224",
    "sg:postcode":"90011",
    "sg:province":"CA",
    "sg:tags":[
        "polishing"
    ],
    "wof:name":"Delux Polishing",
    "wof:placetype":"venue"
},
  "geometry": {"coordinates":[-118.270528,33.989205],"type":"Point"}
}