{
  "type": "Feature",
  "properties": {
    "iso:country":"US",
    "sg:address":"1503 S Coast Dr",
    "sg:city":"Costa Mesa",
    "sg:classifiers":[
        {
            "category":"Government",
            "subcategory":"Office",
            "type":"Public Place"
        }
    ],
    "sg:phone":"+1 714 668 2100",
    "sg:postcode":"92626",
    "sg:province":"CA",
    "sg:tags":[
        "legislative",
        "body"
    ],
    "wof:name":"Ken Maddox Assemblyman",
    "wof:placetype":"venue"
},
  "geometry": {"coordinates":[-117.920816,33.691545],"type":"Point"}
}