{
  "type": "Feature",
  "properties": {
    "iso:country":"US",
    "sg:address":"945 22nd Ave",
    "sg:city":"Oakland",
    "sg:classifiers":[
        {
            "category":"Wholesale",
            "subcategory":"Motor Vehicles",
            "type":"Manufacturing & Wholesale Goods"
        }
    ],
    "sg:phone":"+1 510 532 6249",
    "sg:postcode":"94606",
    "sg:province":"CA",
    "sg:tags":[
        "exporting"
    ],
    "wof:name":"Superservice",
    "wof:placetype":"venue"
},
  "geometry": {"coordinates":[-122.24209399999999,37.780801],"type":"Point"}
}