{
  "type": "Feature",
  "properties": {
    "addr:full":"1039 E El Camino Real Sunnyvale CA 94087",
    "addr:housenumber":"1039",
    "addr:postcode":"94087",
    "addr:street":"E El Camino Real",
    "iso:country":"US",
    "sg:address":"1039 E El Camino Real",
    "sg:city":"Sunnyvale",
    "sg:classifiers":[
        {
            "category":"Building & Trades",
            "subcategory":"Landscaping Services",
            "type":"Services"
        },
        {
            "category":"Community Center",
            "subcategory":"Senior",
            "type":"Public Place"
        },
        {
            "category":"Health Services",
            "subcategory":"Nursing And Care Facility",
            "type":"Services"
        },
        {
            "category":"Social Services",
            "subcategory":"Adult Care",
            "type":"Services"
        },
        {
            "category":"Social Services",
            "subcategory":"Retirement Home",
            "type":"Services"
        }
    ],
    "sg:phone":"+1 408 701 2480",
    "sg:postcode":"94087",
    "sg:province":"CA",
    "sg:tags":[
        "living",
        "apartment",
        "people",
        "assisted",
        "hotel",
        "disabled",
        "elder",
        "independent",
        "convalescent",
        "homes-institutional",
        "citizen",
        "homes-elderly",
        "aged"
    ],
    "sg:website":"http://altfarm.mediaplex.com/ad/ck/11624-100013-2738-30",
    "wof:name":"Belmont Village Senior Living",
    "wof:placetype":"venue"
},
  "geometry": {"coordinates":[-122.006044,37.352266],"type":"Point"}
}