{
  "type": "Feature",
  "properties": {
    "addr:full":"22762 Aspan St Lake Forest CA 92630",
    "addr:housenumber":"22762",
    "addr:postcode":"92630",
    "addr:street":"Aspan St",
    "iso:country":"US",
    "sg:address":"22762 Aspan St",
    "sg:city":"Lake Forest",
    "sg:classifiers":[
        {
            "category":"Shopping",
            "subcategory":"Gifts & Souvenirs",
            "type":"Retail Goods"
        }
    ],
    "sg:phone":"+1 949 540 6227",
    "sg:postcode":"92630",
    "sg:province":"CA",
    "sg:tags":[
        "shop"
    ],
    "wof:name":"Dancing Heart Gifts",
    "wof:placetype":"venue"
},
  "geometry": {"coordinates":[-117.715166,33.632106],"type":"Point"}
}