{
  "type": "Feature",
  "properties": {
    "addr:full":"3009 Highland Ave National City CA 91950",
    "addr:housenumber":"3009",
    "addr:postcode":"91950",
    "addr:street":"Highland Ave",
    "iso:country":"US",
    "sg:address":"3009 Highland Ave",
    "sg:city":"National City",
    "sg:classifiers":[
        {
            "category":"Autos & Motor Vehicles",
            "subcategory":"Fuel & Gas Station",
            "type":"Retail Goods"
        }
    ],
    "sg:phone":"+1 619 474 2088",
    "sg:postcode":"91950",
    "sg:province":"CA",
    "sg:tags":[
        "oil"
    ],
    "wof:name":"Nadir & Son",
    "wof:placetype":"venue"
},
  "geometry": {"coordinates":[-117.09060700000001,32.65751],"type":"Point"}
}