{
  "type": "Feature",
  "properties": {
    "addr:full":"350 Calle Principal Monterey CA 93940",
    "addr:housenumber":"350",
    "addr:postcode":"93940",
    "addr:street":"Calle Principal",
    "iso:country":"US",
    "sg:address":"350 Calle Principal",
    "sg:city":"Monterey",
    "sg:phone":"+1 831 649 4234",
    "sg:postcode":"93940",
    "sg:province":"CA",
    "sg:website":"http://ad.doubleclick.net/clk;227432790;51129303;z?http://www.marriott.com/hotels/travel/MRYCA",
    "wof:name":"Marriott Monterey",
    "wof:placetype":"venue"
},
  "geometry": {"coordinates":[-121.894841,36.600531],"type":"Point"}
}