{
  "type": "Feature",
  "properties": {
    "iso:country":"US",
    "sg:address":"2930 Frances Ave",
    "sg:city":"La Crescenta",
    "sg:classifiers":[
        {
            "category":"Manufacturing",
            "subcategory":"Jewelry",
            "type":"Manufacturing & Wholesale Goods"
        }
    ],
    "sg:phone":"+1 818 957 6061",
    "sg:postcode":"91214",
    "sg:province":"CA",
    "sg:tags":[
        "costume",
        "mfg"
    ],
    "wof:name":"K B Enchanting Creations",
    "wof:placetype":"venue"
},
  "geometry": {"coordinates":[-118.243642,34.238034],"type":"Point"}
}