{
  "type": "Feature",
  "properties": {
    "iso:country":"US",
    "sg:address":"2604 el Camino Real",
    "sg:city":"Carlsbad",
    "sg:classifiers":[
        {
            "category":"Professional",
            "subcategory":"Management & Consulting",
            "type":"Services"
        }
    ],
    "sg:phone":"+1 760 720 7186",
    "sg:postcode":"92008",
    "sg:province":"CA",
    "sg:tags":[
        "communications",
        "consultant"
    ],
    "wof:name":"Positve Perspective",
    "wof:placetype":"venue"
},
  "geometry": {"coordinates":[-117.325817,33.175871],"type":"Point"}
}