{
  "type": "Feature",
  "properties": {
    "iso:country":"US",
    "sg:address":"667 Aileen St",
    "sg:city":"Oakland",
    "sg:classifiers":[
        {
            "category":"Shopping",
            "subcategory":"Clothing, Apparel, & Fashions",
            "type":"Retail Goods"
        }
    ],
    "sg:phone":"+1 510 290 3135",
    "sg:postcode":"94609",
    "sg:province":"CA",
    "sg:tags":[
        "t-shirt"
    ],
    "wof:name":"Sassypants",
    "wof:placetype":"venue"
},
  "geometry": {"coordinates":[-122.266603,37.841774],"type":"Point"}
}