{
  "type": "Feature",
  "properties": {
    "addr:full":"9327 International Blvd Oakland CA 94603",
    "addr:housenumber":"9327",
    "addr:postcode":"94603",
    "addr:street":"International Blvd",
    "iso:country":"US",
    "sg:address":"9327 International Blvd",
    "sg:city":"Oakland",
    "sg:classifiers":[
        {
            "category":"Manufacturing",
            "subcategory":"Metals",
            "type":"Manufacturing & Wholesale Goods"
        }
    ],
    "sg:phone":"+1 415 310 8329",
    "sg:postcode":"94603",
    "sg:province":"CA",
    "sg:tags":[
        "spring",
        "manufacturer",
        "springs-wholesale",
        "mfg"
    ],
    "wof:name":"Gain Mfg Company",
    "wof:placetype":"venue"
},
  "geometry": {"coordinates":[-122.173008,37.747635],"type":"Point"}
}