{
  "type": "Feature",
  "properties": {
    "addr:full":"1212 Beryl St Redondo Beach CA 90277",
    "addr:housenumber":"1212",
    "addr:postcode":"90277",
    "addr:street":"Beryl St",
    "iso:country":"US",
    "sg:address":"1212 Beryl St",
    "sg:city":"Redondo Beach",
    "sg:classifiers":[
        {
            "category":"Shopping",
            "subcategory":"Florist",
            "type":"Retail Goods"
        },
        {
            "category":"Bakery",
            "type":"Food & Drink"
        },
        {
            "category":"Food & Beverages",
            "subcategory":"Groceries & Convenience Stores",
            "type":"Retail Goods"
        }
    ],
    "sg:phone":"+1 310 374 7987",
    "sg:postcode":"90277",
    "sg:province":"CA",
    "wof:name":"Vons",
    "wof:placetype":"venue"
},
  "geometry": {"coordinates":[-118.38099699999999,33.854301],"type":"Point"}
}