{
  "type": "Feature",
  "properties": {
    "iso:country":"US",
    "sg:address":"2750 Prospect Ave",
    "sg:city":"Concord",
    "sg:classifiers":[
        {
            "category":"Retail",
            "subcategory":"Laundry & Dry Cleaning",
            "type":"Services"
        }
    ],
    "sg:phone":"+1 925 709 1160",
    "sg:postcode":"94518",
    "sg:province":"CA",
    "sg:tags":[
        "cleaner",
        "commercial"
    ],
    "wof:name":"Quality One Cleaning",
    "wof:placetype":"venue"
},
  "geometry": {"coordinates":[-122.028098,37.972228],"type":"Point"}
}