{
  "type": "Feature",
  "properties": {
    "iso:country":"US",
    "sg:address":"17530 Ventura Blvd",
    "sg:city":"Encino",
    "sg:classifiers":[
        {
            "category":"Professional",
            "subcategory":"Engineering",
            "type":"Services"
        }
    ],
    "sg:phone":"+1 818 788 6778",
    "sg:postcode":"91316",
    "sg:province":"CA",
    "sg:tags":[
        "engineer"
    ],
    "wof:name":"Shamim Engineering Consultant",
    "wof:placetype":"venue"
},
  "geometry": {"coordinates":[-118.51658399999999,34.161806],"type":"Point"}
}