{
  "type": "Feature",
  "properties": {
    "iso:country":"US",
    "sg:address":"19737 Ventura Blvd",
    "sg:city":"Woodland Hills",
    "sg:classifiers":[
        {
            "category":"Education",
            "subcategory":"Dance Studio",
            "type":"Public Place"
        }
    ],
    "sg:phone":"+1 818 313 9955",
    "sg:postcode":"91364",
    "sg:province":"CA",
    "sg:tags":[
        "instruction",
        "dancing"
    ],
    "wof:name":"Zamuel Ballet Studios",
    "wof:placetype":"venue"
},
  "geometry": {"coordinates":[-118.56364000000001,34.172544],"type":"Point"}
}