{
  "type": "Feature",
  "properties": {
    "addr:full":"12845 Glasgow Dr Red Bluff CA 96080",
    "addr:housenumber":"12845",
    "addr:postcode":"96080",
    "addr:street":"Glasgow Dr",
    "iso:country":"US",
    "sg:address":"12845 Glasgow Dr",
    "sg:city":"Red Bluff",
    "sg:classifiers":[
        {
            "category":"Manufacturing",
            "subcategory":"Tools & Machinery",
            "type":"Manufacturing & Wholesale Goods"
        }
    ],
    "sg:phone":"+1 530 527 6722",
    "sg:postcode":"96080",
    "sg:province":"CA",
    "sg:tags":[
        "machine",
        "shop"
    ],
    "wof:name":"Light Machine Mfg",
    "wof:placetype":"venue"
},
  "geometry": {"coordinates":[-122.269306,40.167525],"type":"Point"}
}