{
  "type": "Feature",
  "properties": {
    "addr:full":"42 Losse Way Chico CA 95926",
    "addr:housenumber":"42",
    "addr:postcode":"95926",
    "addr:street":"Losse Way",
    "iso:country":"US",
    "sg:address":"42 Losse Way",
    "sg:city":"Chico",
    "sg:classifiers":[
        {
            "category":"Home & Garden",
            "subcategory":"Household Appliances",
            "type":"Retail Goods"
        }
    ],
    "sg:phone":"+1 530 342 0654",
    "sg:postcode":"95926",
    "sg:province":"CA",
    "wof:name":"Derr's Appliance Supply",
    "wof:placetype":"venue"
},
  "geometry": {"coordinates":[-121.86918900000001,39.746845],"type":"Point"}
}