{
  "type": "Feature",
  "properties": {
    "addr:full":"380 E Sierra St Portola CA 96122",
    "addr:housenumber":"380",
    "addr:postcode":"96122",
    "addr:street":"E Sierra St",
    "iso:country":"US",
    "sg:address":"380 E Sierra St",
    "sg:city":"Portola",
    "sg:phone":"+1 530 832 4223",
    "sg:postcode":"96122",
    "sg:province":"CA",
    "wof:name":"Sierra Motel",
    "wof:placetype":"venue"
},
  "geometry": {"coordinates":[-120.46369799999999,39.812437],"type":"Point"}
}