{
  "type": "Feature",
  "properties": {
    "iso:country":"US",
    "sg:address":"4644 Valley East Blvd",
    "sg:city":"Arcata",
    "sg:classifiers":[
        {
            "category":"Building & Trades",
            "subcategory":"Plumbing",
            "type":"Services"
        }
    ],
    "sg:phone":"+1 707 825 8025",
    "sg:postcode":"95521",
    "sg:province":"CA",
    "sg:tags":[
        "plumbing",
        "contractor"
    ],
    "wof:name":"Rick's Plumbing",
    "wof:placetype":"venue"
},
  "geometry": {"coordinates":[-124.082871,40.900274],"type":"Point"}
}