{
  "type": "Feature",
  "properties": {
    "iso:country":"US",
    "sg:address":"21251 Deering Ct",
    "sg:city":"Canoga Park",
    "sg:classifiers":[
        {
            "category":"Manufacturing",
            "subcategory":"Tools & Machinery",
            "type":"Manufacturing & Wholesale Goods"
        }
    ],
    "sg:phone":"+1 818 715 0093",
    "sg:postcode":"91304",
    "sg:province":"CA",
    "sg:tags":[
        "physician",
        "surgeon"
    ],
    "sg:website":"www.allmanproducts.com",
    "wof:name":"ALLMAN Products",
    "wof:placetype":"venue"
},
  "geometry": {"coordinates":[-118.596284,34.216917],"type":"Point"}
}