{
  "type": "Feature",
  "properties": {
    "iso:country":"US",
    "sg:address":"5855 Green Valley Cir",
    "sg:city":"Culver City",
    "sg:classifiers":[
        {
            "category":"Professional",
            "subcategory":"Employment Agencies",
            "type":"Services"
        }
    ],
    "sg:phone":"+1 310 670 6067",
    "sg:postcode":"90230",
    "sg:province":"CA",
    "wof:name":"Accountability",
    "wof:placetype":"venue"
},
  "geometry": {"coordinates":[-118.38928300000001,33.983248],"type":"Point"}
}