{
  "type": "Feature",
  "properties": {
    "iso:country":"US",
    "sg:address":"1035 W Mill St",
    "sg:city":"San Bernardino",
    "sg:classifiers":[
        {
            "category":"Home & Garden",
            "subcategory":"Furniture",
            "type":"Retail Goods"
        }
    ],
    "sg:phone":"+1 909 885 7794",
    "sg:postcode":"92410",
    "sg:province":"CA",
    "sg:tags":[
        "body",
        "auto"
    ],
    "wof:name":"Inland Mattress & Upholstery",
    "wof:placetype":"venue"
},
  "geometry": {"coordinates":[-117.30579400000001,34.092079],"type":"Point"}
}