{
  "type": "Feature",
  "properties": {
    "iso:country":"US",
    "sg:address":"16117 W Sunset Blvd",
    "sg:city":"Pacific Palisades",
    "sg:classifiers":[
        {
            "category":"Home & Garden",
            "subcategory":"Furniture",
            "type":"Retail Goods"
        }
    ],
    "sg:phone":"+1 310 454 4703",
    "sg:postcode":"90272",
    "sg:province":"CA",
    "wof:name":"Om Furniture & Decorative",
    "wof:placetype":"venue"
},
  "geometry": {"coordinates":[-118.537941,34.048659],"type":"Point"}
}