{
  "type": "Feature",
  "properties": {
    "addr:full":"455 Tigerwood Way San Jose CA 95111",
    "addr:housenumber":"455",
    "addr:postcode":"95111",
    "addr:street":"Tigerwood Way",
    "iso:country":"US",
    "sg:address":"455 Tigerwood Way",
    "sg:city":"San Jose",
    "sg:classifiers":[
        {
            "category":"Wholesale",
            "subcategory":"Electrical",
            "type":"Manufacturing & Wholesale Goods"
        }
    ],
    "sg:phone":"+1 408 451 9200",
    "sg:postcode":"95111",
    "sg:province":"CA",
    "sg:tags":[
        "equipment",
        "electronic",
        "supply"
    ],
    "wof:name":"Surface Mount Distribution",
    "wof:placetype":"venue"
},
  "geometry": {"coordinates":[-121.799386,37.265569],"type":"Point"}
}