{
  "type": "Feature",
  "properties": {
    "addr:full":"302 N Riverside Ave Rialto CA 92376",
    "addr:housenumber":"302",
    "addr:postcode":"92376",
    "addr:street":"N Riverside Ave",
    "iso:country":"US",
    "sg:address":"302 N Riverside Ave",
    "sg:city":"Rialto",
    "sg:classifiers":[
        {
            "category":"Social Services",
            "subcategory":"Adult Care",
            "type":"Services"
        }
    ],
    "sg:phone":"+1 909 875 8344",
    "sg:postcode":"92376",
    "sg:province":"CA",
    "sg:tags":[
        "foster"
    ],
    "wof:name":"Wilene's Re-Growth Ctr",
    "wof:placetype":"venue"
},
  "geometry": {"coordinates":[-117.370338,34.106715],"type":"Point"}
}