{
  "type": "Feature",
  "properties": {
    "addr:full":"1385 N 2nd St El Cajon CA 92021",
    "addr:housenumber":"1385",
    "addr:postcode":"92021",
    "addr:street":"N 2Nd St",
    "iso:country":"US",
    "sg:address":"1385 N 2nd St",
    "sg:city":"El Cajon",
    "sg:classifiers":[
        {
            "category":"Personal",
            "subcategory":"Beauty Salon",
            "type":"Services"
        }
    ],
    "sg:phone":"+1 619 561 8043",
    "sg:postcode":"92021",
    "sg:province":"CA",
    "wof:name":"Davis House",
    "wof:placetype":"venue"
},
  "geometry": {"coordinates":[-116.935648,32.81352],"type":"Point"}
}