{
  "type": "Feature",
  "properties": {
    "iso:country":"US",
    "sg:address":"1201 N Inyo St",
    "sg:city":"Ridgecrest",
    "sg:classifiers":[
        {
            "category":"Manufacturing",
            "subcategory":"Glass & Minerals",
            "type":"Manufacturing & Wholesale Goods"
        }
    ],
    "sg:phone":"+1 760 446 6442",
    "sg:postcode":"93555",
    "sg:province":"CA",
    "sg:tags":[
        "product",
        "mfg"
    ],
    "wof:name":"Genie Glass",
    "wof:placetype":"venue"
},
  "geometry": {"coordinates":[-117.692182,35.640653],"type":"Point"}
}