{
  "type": "Feature",
  "properties": {
    "iso:country":"US",
    "sg:address":"1311 E Philadelphia St",
    "sg:city":"Ontario",
    "sg:classifiers":[
        {
            "category":"Home & Garden",
            "subcategory":"Building Materials",
            "type":"Retail Goods"
        }
    ],
    "sg:phone":"+1 909 923 6250",
    "sg:postcode":"91761",
    "sg:province":"CA",
    "sg:tags":[
        "hinge"
    ],
    "sg:website":"www.pbbinc.com",
    "wof:name":"PBB Inc",
    "wof:placetype":"venue"
},
  "geometry": {"coordinates":[-117.627113,34.034051],"type":"Point"}
}