{
  "type": "Feature",
  "properties": {
    "iso:country":"US",
    "sg:address":"2061 Whitman Ave",
    "sg:city":"Chico",
    "sg:classifiers":[
        {
            "category":"Personal",
            "subcategory":"Beauty Salon",
            "type":"Services"
        }
    ],
    "sg:phone":"+1 530 898 8438",
    "sg:postcode":"95928",
    "sg:province":"CA",
    "wof:name":"Trends For Hair",
    "wof:placetype":"venue"
},
  "geometry": {"coordinates":[-121.808659,39.721858],"type":"Point"}
}