{
  "type": "Feature",
  "properties": {
    "iso:country":"US",
    "sg:address":"1884 Cll Yucca",
    "sg:city":"Thousand Oaks",
    "sg:classifiers":[
        {
            "category":"Retail",
            "subcategory":"Repair Shop",
            "type":"Services"
        }
    ],
    "sg:phone":"+1 805 375 5700",
    "sg:postcode":"91360",
    "sg:province":"CA",
    "sg:tags":[
        "lock",
        "locksmith"
    ],
    "wof:name":"Thousand Oaks Lock & Key",
    "wof:placetype":"venue"
},
  "geometry": {"coordinates":[-118.9075,34.204625],"type":"Point"}
}