{
  "type": "Feature",
  "properties": {
    "addr:full":"18850 Ventura Blvd Tarzana CA 91356",
    "addr:housenumber":"18850",
    "addr:postcode":"91356",
    "addr:street":"Ventura Blvd",
    "iso:country":"US",
    "sg:address":"18850 Ventura Blvd",
    "sg:city":"Tarzana",
    "sg:classifiers":[
        {
            "category":"Utilities",
            "subcategory":"Mobile Phone",
            "type":"Services"
        }
    ],
    "sg:phone":"+1 818 668 8310",
    "sg:postcode":"91356",
    "sg:province":"CA",
    "sg:tags":[
        "telephone",
        "cellular"
    ],
    "wof:name":"Inspired Communications",
    "wof:placetype":"venue"
},
  "geometry": {"coordinates":[-118.54389999999999,34.171819],"type":"Point"}
}