{
  "type": "Feature",
  "properties": {
    "iso:country":"US",
    "sg:address":"2420 52nd St",
    "sg:city":"San Diego",
    "sg:classifiers":[
        {
            "category":"Organizations",
            "subcategory":"Religious Organization",
            "type":"Services"
        }
    ],
    "sg:phone":"+1 619 263 5660",
    "sg:postcode":"92105",
    "sg:province":"CA",
    "wof:name":"Oak Park Seventh Day Church",
    "wof:placetype":"venue"
},
  "geometry": {"coordinates":[-117.083811,32.731413],"type":"Point"}
}