{
  "type": "Feature",
  "properties": {
    "iso:country":"US",
    "sg:address":"10852 Burbank Blvd",
    "sg:city":"San Fernando Valley",
    "sg:classifiers":[
        {
            "category":"Arena",
            "subcategory":"Sports Club",
            "type":"Entertainment"
        }
    ],
    "sg:phone":"+1 818 753 8991",
    "sg:postcode":"91601",
    "sg:province":"CA",
    "sg:tags":[
        "martial art"
    ],
    "sg:website":"valleytraditionalkarate.com",
    "wof:name":"Valley Traditional Karate",
    "wof:placetype":"venue"
},
  "geometry": {"coordinates":[-118.367678,34.171838],"type":"Point"}
}