{
  "type": "Feature",
  "properties": {
    "addr:full":"21021 Soledad Canyon Rd Santa Clarita CA 91351",
    "addr:housenumber":"21021",
    "addr:postcode":"91351",
    "addr:street":"Soledad Canyon Rd",
    "iso:country":"US",
    "sg:address":"21021 Soledad Canyon Rd",
    "sg:city":"Santa Clarita",
    "sg:classifiers":[
        {
            "category":"Banks & Credit Unions",
            "subcategory":"Bank",
            "type":"Services"
        }
    ],
    "sg:phone":"+1 661 287 6300",
    "sg:postcode":"91351",
    "sg:province":"CA",
    "sg:tags":[
        "loan",
        "real estate"
    ],
    "wof:name":"Tmg Financial Svc",
    "wof:placetype":"venue"
},
  "geometry": {"coordinates":[-118.50295800000001,34.420164],"type":"Point"}
}