{
  "type": "Feature",
  "properties": {
    "iso:country":"US",
    "sg:address":"14804 Ivanhoe Dr",
    "sg:city":"Visalia",
    "sg:classifiers":[
        {
            "category":"Farming",
            "subcategory":"Farm",
            "type":"Manufacturing & Wholesale Goods"
        }
    ],
    "sg:phone":"+1 559 733 8578",
    "sg:postcode":"93292",
    "sg:province":"CA",
    "sg:tags":[
        "crop",
        "general"
    ],
    "wof:name":"Charter Oak Corporation",
    "wof:placetype":"venue"
},
  "geometry": {"coordinates":[-119.24373300000001,36.342749],"type":"Point"}
}