{
  "type": "Feature",
  "properties": {
    "addr:full":"5696 San Pablo Ave Oakland CA 94608",
    "addr:housenumber":"5696",
    "addr:postcode":"94608",
    "addr:street":"San Pablo Ave",
    "iso:country":"US",
    "sg:address":"5696 San Pablo Ave",
    "sg:city":"Oakland",
    "sg:classifiers":[
        {
            "category":"Personal",
            "subcategory":"Beauty Salon",
            "type":"Services"
        }
    ],
    "sg:postcode":"94608",
    "sg:province":"CA",
    "sg:tags":[
        "spa"
    ],
    "wof:name":"Unique barber shop",
    "wof:placetype":"venue"
},
  "geometry": {"coordinates":[-122.282466,37.840205],"type":"Point"}
}