{
  "type": "Feature",
  "properties": {
    "addr:full":"6 Tearpak Ct Sacramento CA 95823",
    "addr:housenumber":"6",
    "addr:postcode":"95823",
    "addr:street":"Tearpak Ct",
    "iso:country":"US",
    "sg:address":"6 Tearpak Ct",
    "sg:city":"Sacramento",
    "sg:classifiers":[
        {
            "category":"Professional",
            "subcategory":"Business Services",
            "type":"Services"
        }
    ],
    "sg:phone":"+1 916 429 2606",
    "sg:postcode":"95823",
    "sg:province":"CA",
    "sg:tags":[
        "recording",
        "studio"
    ],
    "wof:name":"Milan Recording Co",
    "wof:placetype":"venue"
},
  "geometry": {"coordinates":[-121.435074,38.453824],"type":"Point"}
}