{
  "type": "Feature",
  "properties": {
    "addr:full":"9330 Baseline Rd Alta Loma CA 91701",
    "addr:housenumber":"9330",
    "addr:postcode":"91701",
    "addr:street":"Baseline Rd",
    "iso:country":"US",
    "sg:address":"9330 Baseline Rd",
    "sg:city":"Alta Loma",
    "sg:classifiers":[
        {
            "category":"Insurance",
            "subcategory":"Insurance Agent",
            "type":"Services"
        }
    ],
    "sg:phone":"+1 909 945 2969",
    "sg:postcode":"91701",
    "sg:province":"CA",
    "wof:name":"Scarborough",
    "wof:placetype":"venue"
},
  "geometry": {"coordinates":[-117.601024,34.121617],"type":"Point"}
}