{
  "type": "Feature",
  "properties": {
    "iso:country":"US",
    "sg:address":"2129 W Rosecrans Ave",
    "sg:city":"Gardena",
    "sg:classifiers":[
        {
            "category":"Taxi",
            "type":"Transportation"
        }
    ],
    "sg:phone":"+1 323 722 2122",
    "sg:postcode":"90249",
    "sg:province":"CA",
    "sg:tags":[
        "taxicab"
    ],
    "wof:name":"Maywood Bell Taxi",
    "wof:placetype":"venue"
},
  "geometry": {"coordinates":[-118.316231,33.902009],"type":"Point"}
}