{
  "type": "Feature",
  "properties": {
    "iso:country":"US",
    "sg:address":"17705 Sierra Cielo Ln",
    "sg:city":"Jamul",
    "sg:classifiers":[
        {
            "category":"Manufacturing",
            "subcategory":"Printing",
            "type":"Manufacturing & Wholesale Goods"
        }
    ],
    "sg:phone":"+1 619 468 9184",
    "sg:postcode":"91935",
    "sg:province":"CA",
    "sg:tags":[
        "publisher"
    ],
    "wof:name":"Southern California Publishing",
    "wof:placetype":"venue"
},
  "geometry": {"coordinates":[-116.765925,32.686701],"type":"Point"}
}