{
  "type": "Feature",
  "properties": {
    "addr:full":"8 Williams Rd Salinas CA 93905",
    "addr:housenumber":"8",
    "addr:postcode":"93905",
    "addr:street":"Williams Rd",
    "iso:country":"US",
    "sg:address":"8 Williams Rd",
    "sg:city":"Salinas",
    "sg:classifiers":[
        {
            "category":"Autos & Motor Vehicles",
            "subcategory":"Auto Supplies",
            "type":"Retail Goods"
        }
    ],
    "sg:phone":"+1 831 751 6163",
    "sg:postcode":"93905",
    "sg:province":"CA",
    "sg:tags":[
        "tire"
    ],
    "wof:name":"Sanchez New & Used Tires",
    "wof:placetype":"venue"
},
  "geometry": {"coordinates":[-121.618118,36.67321],"type":"Point"}
}