{
  "type": "Feature",
  "properties": {
    "addr:full":"1 Lombard St San Francisco CA 94111",
    "addr:housenumber":"1",
    "addr:postcode":"94111",
    "addr:street":"Lombard St",
    "iso:country":"US",
    "sg:address":"1 Lombard St",
    "sg:city":"San Francisco",
    "sg:classifiers":[
        {
            "category":"Social Services",
            "type":"Services"
        }
    ],
    "sg:phone":"+1 415 834 9934",
    "sg:postcode":"94111",
    "sg:province":"CA",
    "sg:tags":[
        "organization",
        "welfare"
    ],
    "wof:name":"Silver Partners",
    "wof:placetype":"venue"
},
  "geometry": {"coordinates":[-122.40334799999999,37.80403],"type":"Point"}
}