{
  "type": "Feature",
  "properties": {
    "addr:full":"205 Roundtree Way San Rafael CA 94903",
    "addr:housenumber":"205",
    "addr:postcode":"94903",
    "addr:street":"Roundtree Way",
    "iso:country":"US",
    "sg:address":"205 Roundtree Way",
    "sg:city":"San Rafael",
    "sg:classifiers":[
        {
            "category":"Professional",
            "subcategory":"Management & Consulting",
            "type":"Services"
        }
    ],
    "sg:phone":"+1 415 499 1388",
    "sg:postcode":"94903",
    "sg:province":"CA",
    "sg:tags":[
        "personnel",
        "consultant"
    ],
    "wof:name":"Procesing Center",
    "wof:placetype":"venue"
},
  "geometry": {"coordinates":[-122.542913,38.031464],"type":"Point"}
}