{
  "type": "Feature",
  "properties": {
    "addr:full":"220 Halleck St San Francisco CA 94104",
    "addr:housenumber":"220",
    "addr:postcode":"94104",
    "addr:street":"Halleck St",
    "iso:country":"US",
    "sg:address":"220 Halleck St",
    "sg:city":"San Francisco",
    "sg:classifiers":[
        {
            "category":"Professional",
            "subcategory":"Engineering",
            "type":"Services"
        }
    ],
    "sg:phone":"+1 415 561 2566",
    "sg:postcode":"94104",
    "sg:province":"CA",
    "sg:tags":[
        "engineer"
    ],
    "wof:name":"Republic Of Haiti",
    "wof:placetype":"venue"
},
  "geometry": {"coordinates":[-122.40194,37.793533],"type":"Point"}
}