{
  "type": "Feature",
  "properties": {
    "addr:full":"113 Birch St Roseville CA 95678",
    "addr:housenumber":"113",
    "addr:postcode":"95678",
    "addr:street":"Birch St",
    "iso:country":"US",
    "sg:address":"113 Birch St",
    "sg:city":"Roseville",
    "sg:classifiers":[
        {
            "category":"Organizations",
            "subcategory":"Religious Organization",
            "type":"Services"
        }
    ],
    "sg:phone":"+1 916 782 2431",
    "sg:postcode":"95678",
    "sg:province":"CA",
    "sg:tags":[
        "church"
    ],
    "wof:name":"Seventh Day Church Of God",
    "wof:placetype":"venue"
},
  "geometry": {"coordinates":[-121.292486,38.749442],"type":"Point"}
}