{
  "type": "Feature",
  "properties": {
    "addr:full":"330 S 3rd St Ste D San Jose CA 95112",
    "addr:housenumber":"330",
    "addr:postcode":"95112",
    "addr:street":"S 3Rd St Ste D",
    "iso:country":"US",
    "sg:address":"330 S 3rd St Ste D",
    "sg:city":"San Jose",
    "sg:classifiers":[
        {
            "category":"Personal",
            "subcategory":"Beauty Salon",
            "type":"Services"
        },
        {
            "category":"Personal",
            "subcategory":"Barber",
            "type":"Services"
        }
    ],
    "sg:phone":"+1 408 885 1737",
    "sg:postcode":"95112",
    "sg:province":"CA",
    "sg:tags":[
        "hair"
    ],
    "sg:website":"www.lilieshairstudio.com",
    "wof:name":"Lilies Hair Studio",
    "wof:placetype":"venue"
},
  "geometry": {"coordinates":[-121.88419500000001,37.33211],"type":"Point"}
}