{
  "type": "Feature",
  "properties": {
    "addr:full":"14300 San Cristobal Dr La Mirada CA 90638",
    "addr:housenumber":"14300",
    "addr:postcode":"90638",
    "addr:street":"San Cristobal Dr",
    "iso:country":"US",
    "sg:address":"14300 San Cristobal Dr",
    "sg:city":"La Mirada",
    "sg:classifiers":[
        {
            "category":"Government",
            "subcategory":"Office",
            "type":"Public Place"
        }
    ],
    "sg:phone":"+1 562 943 7277",
    "sg:postcode":"90638",
    "sg:province":"CA",
    "sg:tags":[
        "village"
    ],
    "wof:name":"LA Mirada Community Svc Dept",
    "wof:placetype":"venue"
},
  "geometry": {"coordinates":[-118.02595599999999,33.899172],"type":"Point"}
}