{
  "type": "Feature",
  "properties": {
    "iso:country":"US",
    "sg:address":"450 Taraval St",
    "sg:city":"San Francisco",
    "sg:classifiers":[
        {
            "category":"Building & Trades",
            "subcategory":"Construction",
            "type":"Services"
        }
    ],
    "sg:phone":"+1 415 720 3119",
    "sg:postcode":"94116",
    "sg:province":"CA",
    "sg:tags":[
        "contractor"
    ],
    "wof:name":"Dam Construction",
    "wof:placetype":"venue"
},
  "geometry": {"coordinates":[-122.470799,37.743401],"type":"Point"}
}