{
  "type": "Feature",
  "properties": {
    "addr:full":"28 Hammond Irvine CA 92618",
    "addr:housenumber":"28",
    "addr:postcode":"92618",
    "addr:street":"Hammond",
    "iso:country":"US",
    "sg:address":"28 Hammond",
    "sg:city":"Irvine",
    "sg:classifiers":[
        {
            "category":"Home & Garden",
            "subcategory":"Carpets & Floor Coverings",
            "type":"Retail Goods"
        }
    ],
    "sg:phone":"+1 949 305 8510",
    "sg:postcode":"92618",
    "sg:province":"CA",
    "sg:tags":[
        "manufacture",
        "wood",
        "custom"
    ],
    "wof:name":"Oakstone Flooring Inc",
    "wof:placetype":"venue"
},
  "geometry": {"coordinates":[-117.70329700000001,33.661088],"type":"Point"}
}