{
  "type": "Feature",
  "properties": {
    "addr:full":"887 1/2 Sherman St San Diego CA 92110",
    "addr:housenumber":"887 1 / 2",
    "addr:postcode":"92110",
    "addr:street":"Sherman St",
    "iso:country":"US",
    "sg:address":"887 1/2 Sherman St",
    "sg:city":"San Diego",
    "sg:classifiers":[
        {
            "category":"Government",
            "subcategory":"City Hall",
            "type":"Public Place"
        }
    ],
    "sg:phone":"+1 619 225 9453",
    "sg:postcode":"92110",
    "sg:province":"CA",
    "sg:website":"www.projectwildlife.org",
    "wof:name":"Project Wildlife",
    "wof:placetype":"venue"
},
  "geometry": {"coordinates":[-117.200581,32.763445],"type":"Point"}
}