{
  "type": "Feature",
  "properties": {
    "addr:full":"2895 N Towne Ave Pomona CA 91767",
    "addr:housenumber":"2895",
    "addr:postcode":"91767",
    "addr:street":"N Towne Ave",
    "iso:country":"US",
    "sg:address":"2895 N Towne Ave",
    "sg:city":"Pomona",
    "sg:classifiers":[
        {
            "category":"Health Services",
            "subcategory":"Doctor",
            "type":"Services"
        }
    ],
    "sg:phone":"+1 909 621 0927",
    "sg:postcode":"91767",
    "sg:province":"CA",
    "sg:tags":[
        "clinic"
    ],
    "wof:name":"Molina Medical Ctr",
    "wof:placetype":"venue"
},
  "geometry": {"coordinates":[-117.736867,34.098657],"type":"Point"}
}