{
  "type": "Feature",
  "properties": {
    "addr:full":"100 Century Center Court Suite 501 San Jose CA 95112",
    "addr:housenumber":"100",
    "addr:postcode":"95112",
    "addr:street":"Century Center Court Suite 501",
    "iso:country":"US",
    "sg:address":"100 Century Center Court Suite 501",
    "sg:city":"San Jose",
    "sg:classifiers":[
        {
            "category":"Professional",
            "subcategory":"Management & Consulting",
            "type":"Services"
        }
    ],
    "sg:phone":"+1 408 453 1008",
    "sg:postcode":"95112",
    "sg:province":"CA",
    "sg:website":"http://www.quantumsecure.com",
    "wof:name":"Quantum Secure",
    "wof:placetype":"venue"
},
  "geometry": {"coordinates":[-121.91470200000001,37.368515],"type":"Point"}
}