{
  "type": "Feature",
  "properties": {
    "iso:country":"US",
    "sg:address":"550 S Vermont Ave",
    "sg:city":"Los Angeles",
    "sg:classifiers":[
        {
            "category":"Government",
            "subcategory":"Office",
            "type":"Public Place"
        }
    ],
    "sg:phone":"+1 213 351 5110",
    "sg:postcode":"90020",
    "sg:province":"CA",
    "sg:tags":[
        "county",
        "program"
    ],
    "wof:name":"Environmental Health District",
    "wof:placetype":"venue"
},
  "geometry": {"coordinates":[-118.291571,34.06457],"type":"Point"}
}