{
  "type": "Feature",
  "properties": {
    "addr:full":"2609 S Hill St Los Angeles CA 90007",
    "addr:housenumber":"2609",
    "addr:postcode":"90007",
    "addr:street":"S Hill St",
    "iso:country":"US",
    "sg:address":"2609 S Hill St",
    "sg:city":"Los Angeles",
    "sg:classifiers":[
        {
            "category":"Communications",
            "type":"Services"
        }
    ],
    "sg:phone":"+1 818 270 5094",
    "sg:postcode":"90007",
    "sg:province":"CA",
    "sg:tags":[
        "recording",
        "rehearsal",
        "studio"
    ],
    "sg:website":"www.royalrehearsal.com",
    "wof:name":"Royal Rehearsal Studio",
    "wof:placetype":"venue"
},
  "geometry": {"coordinates":[-118.27119999999999,34.02557],"type":"Point"}
}