{
  "type": "Feature",
  "properties": {
    "iso:country":"US",
    "sg:address":"1701 S Mills Ave",
    "sg:city":"Lodi",
    "sg:classifiers":[
        {
            "category":"Health Services",
            "subcategory":"Health Practitioner",
            "type":"Services"
        }
    ],
    "sg:phone":"+1 209 602 5787",
    "sg:postcode":"95242",
    "sg:province":"CA",
    "sg:tags":[
        "hypnotist"
    ],
    "wof:name":"Bay Area Hypnonsis Asst",
    "wof:placetype":"venue"
},
  "geometry": {"coordinates":[-121.298742,38.112328],"type":"Point"}
}