{
  "type": "Feature",
  "properties": {
    "addr:full":"1414 Soquel Avenue Suite 216 Santa Cruz CA 95062",
    "addr:housenumber":"1414",
    "addr:postcode":"95062",
    "addr:street":"Soquel Avenue Suite 216",
    "iso:country":"US",
    "sg:address":"1414 Soquel Avenue Suite 216",
    "sg:city":"Santa Cruz",
    "sg:classifiers":[
        {
            "category":"Professional",
            "subcategory":"Lawyer & Legal Services",
            "type":"Services"
        }
    ],
    "sg:phone":"+1 831 425 4754",
    "sg:postcode":"95062",
    "sg:province":"CA",
    "sg:tags":[
        "personal",
        "injury"
    ],
    "wof:name":"Jovich Linda C, Atty",
    "wof:placetype":"venue"
},
  "geometry": {"coordinates":[-122.00572099999999,36.980813],"type":"Point"}
}