{
  "type": "Feature",
  "properties": {
    "iso:country":"US",
    "sg:address":"618 W Gaffery Rd",
    "sg:city":"Vernalis",
    "sg:phone":"+1 209 835 1039",
    "sg:postcode":"95385",
    "sg:province":"CA",
    "sg:tags":[
        "tomato",
        "apricot",
        "bean",
        "farm"
    ],
    "wof:name":"N & G Petz Farm Inc",
    "wof:placetype":"venue"
},
  "geometry": {"coordinates":[-121.260728,37.594618],"type":"Point"}
}