{
  "type": "Feature",
  "properties": {
    "addr:full":"2260 Main St Chula Vista CA 91911",
    "addr:housenumber":"2260",
    "addr:postcode":"91911",
    "addr:street":"Main St",
    "iso:country":"US",
    "sg:address":"2260 Main St",
    "sg:city":"Chula Vista",
    "sg:classifiers":[
        {
            "category":"Building & Trades",
            "subcategory":"Construction",
            "type":"Services"
        }
    ],
    "sg:phone":"+1 619 429 1736",
    "sg:postcode":"91911",
    "sg:province":"CA",
    "sg:tags":[
        "repairing",
        "remodeling",
        "contractor"
    ],
    "sg:website":"www.prettyhardbody.com",
    "wof:name":"Anderson Plumbing & Remodeling",
    "wof:placetype":"venue"
},
  "geometry": {"coordinates":[-117.08673,32.594947],"type":"Point"}
}