{
  "type": "Feature",
  "properties": {
    "iso:country":"US",
    "sg:address":"22992 Cavanaugh Rd",
    "sg:city":"Lake Forest",
    "sg:classifiers":[
        {
            "category":"Professional",
            "subcategory":"Business Services",
            "type":"Services"
        }
    ],
    "sg:phone":"+1 949 716 3134",
    "sg:postcode":"92630",
    "sg:province":"CA",
    "sg:tags":[
        "fund",
        "promotion",
        "raising"
    ],
    "wof:name":"Mountain Top Designs",
    "wof:placetype":"venue"
},
  "geometry": {"coordinates":[-117.697748,33.628712],"type":"Point"}
}