{
  "type": "Feature",
  "properties": {
    "iso:country":"US",
    "sg:address":"29287 Snapdragon Pl",
    "sg:city":"Canyon Country",
    "sg:classifiers":[
        {
            "category":"Professional",
            "type":"Services"
        }
    ],
    "sg:phone":"+1 661 251 8923",
    "sg:postcode":"91387",
    "sg:province":"CA",
    "wof:name":"Take 1 Motion Picture Pla",
    "wof:placetype":"venue"
},
  "geometry": {"coordinates":[-118.405889,34.437786],"type":"Point"}
}