{
  "type": "Feature",
  "properties": {
    "addr:full":"1340 Fulton Pl Fremont CA 94539",
    "addr:housenumber":"1340",
    "addr:postcode":"94539",
    "addr:street":"Fulton Pl",
    "iso:country":"US",
    "sg:address":"1340 Fulton Pl",
    "sg:city":"Fremont",
    "sg:classifiers":[
        {
            "category":"Manufacturing",
            "subcategory":"Leather Goods",
            "type":"Manufacturing & Wholesale Goods"
        }
    ],
    "sg:phone":"+1 510 770 1933",
    "sg:postcode":"94539",
    "sg:province":"CA",
    "sg:tags":[
        "shoes"
    ],
    "wof:name":"Tumbler Corp",
    "wof:placetype":"venue"
},
  "geometry": {"coordinates":[-121.930786,37.491197],"type":"Point"}
}