{
  "type": "Feature",
  "properties": {
    "addr:full":"5495 Traffic Way Atascadero CA 93422",
    "addr:housenumber":"5495",
    "addr:postcode":"93422",
    "addr:street":"Traffic Way",
    "iso:country":"US",
    "sg:address":"5495 Traffic Way",
    "sg:city":"Atascadero",
    "sg:classifiers":[
        {
            "category":"Wholesale",
            "subcategory":"Seafood",
            "type":"Manufacturing & Wholesale Goods"
        }
    ],
    "sg:phone":"+1 800 273 4741",
    "sg:postcode":"93422",
    "sg:province":"CA",
    "sg:tags":[
        "fish",
        "market"
    ],
    "sg:website":"http://www.ccseafood.com",
    "wof:name":"Central Coast Seafood",
    "wof:placetype":"venue"
},
  "geometry": {"coordinates":[-120.667715,35.496297],"type":"Point"}
}