{
  "type": "Feature",
  "properties": {
    "addr:full":"29600 Island View Dr Rancho Palos Verdes CA 90275",
    "addr:housenumber":"29600",
    "addr:postcode":"90275",
    "addr:street":"Island View Dr",
    "iso:country":"US",
    "sg:address":"29600 Island View Dr",
    "sg:city":"Rancho Palos Verdes",
    "sg:classifiers":[
        {
            "category":"Wholesale",
            "subcategory":"Non-durable Goods",
            "type":"Manufacturing & Wholesale Goods"
        }
    ],
    "sg:phone":"+1 310 544 7674",
    "sg:postcode":"90275",
    "sg:province":"CA",
    "wof:name":"Uniko Traders International Co",
    "wof:placetype":"venue"
},
  "geometry": {"coordinates":[-118.39270999999999,33.763455],"type":"Point"}
}