{
  "type": "Feature",
  "properties": {
    "iso:country":"US",
    "sg:address":"1165 Montgomery Dr",
    "sg:city":"Santa Rosa",
    "sg:classifiers":[
        {
            "category":"Health Services",
            "subcategory":"Doctor",
            "type":"Services"
        }
    ],
    "sg:phone":"+1 707 526 0465",
    "sg:postcode":"95405",
    "sg:province":"CA",
    "sg:tags":[
        "physician",
        "surgeon"
    ],
    "wof:name":"Shelleen Denno MD",
    "wof:placetype":"venue"
},
  "geometry": {"coordinates":[-122.70037,38.443212],"type":"Point"}
}