{
  "type": "Feature",
  "properties": {
    "iso:country":"US",
    "sg:address":"1452 Atherton Cir",
    "sg:city":"Fullerton",
    "sg:classifiers":[
        {
            "category":"Food & Beverages",
            "subcategory":"Groceries & Convenience Stores",
            "type":"Retail Goods"
        }
    ],
    "sg:phone":"+1 714 879 9220",
    "sg:postcode":"92833",
    "sg:province":"CA",
    "wof:name":"Eddies Wholesale Groceries",
    "wof:placetype":"venue"
},
  "geometry": {"coordinates":[-117.950692,33.900188],"type":"Point"}
}