{
  "type": "Feature",
  "properties": {
    "iso:country":"US",
    "sg:address":"946 Arroyo Dr",
    "sg:city":"South Pasadena",
    "sg:classifiers":[
        {
            "category":"Professional",
            "subcategory":"Business Services",
            "type":"Services"
        }
    ],
    "sg:phone":"+1 626 319 6884",
    "sg:postcode":"91030",
    "sg:province":"CA",
    "sg:tags":[
        "event"
    ],
    "wof:name":"J Mari Events",
    "wof:placetype":"venue"
},
  "geometry": {"coordinates":[-118.17014500000001,34.113385],"type":"Point"}
}