{
  "type": "Feature",
  "properties": {
    "addr:full":"591 Redwood Hwy Mill Valley CA 94941",
    "addr:housenumber":"591",
    "addr:postcode":"94941",
    "addr:street":"Redwood Hwy",
    "iso:country":"US",
    "sg:address":"591 Redwood Hwy",
    "sg:city":"Mill Valley",
    "sg:classifiers":[
        {
            "category":"Communications",
            "type":"Services"
        }
    ],
    "sg:phone":"+1 415 389 9913",
    "sg:postcode":"94941",
    "sg:province":"CA",
    "wof:name":"Unlimited Conferencing",
    "wof:placetype":"venue"
},
  "geometry": {"coordinates":[-122.51656800000001,37.890891],"type":"Point"}
}