{
  "type": "Feature",
  "properties": {
    "addr:full":"25 Metro Dr San Jose CA 95110",
    "addr:housenumber":"25",
    "addr:postcode":"95110",
    "addr:street":"Metro Dr",
    "iso:country":"US",
    "sg:address":"25 Metro Dr",
    "sg:city":"San Jose",
    "sg:classifiers":[
        {
            "category":"Education",
            "subcategory":"Vocational School",
            "type":"Public Place"
        }
    ],
    "sg:phone":"+1 408 441 2720",
    "sg:postcode":"95110",
    "sg:province":"CA",
    "sg:tags":[
        "training",
        "computer"
    ],
    "wof:name":"Quickstart Intelligence",
    "wof:placetype":"venue"
},
  "geometry": {"coordinates":[-121.91858000000001,37.368095],"type":"Point"}
}