{
  "type": "Feature",
  "properties": {
    "addr:full":"7144 Edinger Ave Huntington Beach CA 92647",
    "addr:housenumber":"7144",
    "addr:postcode":"92647",
    "addr:street":"Edinger Ave",
    "iso:country":"US",
    "sg:address":"7144 Edinger Ave",
    "sg:city":"Huntington Beach",
    "sg:classifiers":[
        {
            "category":"Restaurant",
            "type":"Food & Drink"
        }
    ],
    "sg:phone":"+1 714 842 6621",
    "sg:postcode":"92647",
    "sg:province":"CA",
    "sg:tags":[
        "japanese"
    ],
    "sg:website":"www.keigos.blogspot.com",
    "wof:name":"Keigo's Japanese Take Out",
    "wof:placetype":"venue"
},
  "geometry": {"coordinates":[-118.005352,33.729551],"type":"Point"}
}