{
  "type": "Feature",
  "properties": {
    "addr:full":"2931 E Ventura Blvd Oxnard CA 93036",
    "addr:housenumber":"2931",
    "addr:postcode":"93036",
    "addr:street":"E Ventura Blvd",
    "iso:country":"US",
    "sg:address":"2931 E Ventura Blvd",
    "sg:city":"Oxnard",
    "sg:classifiers":[
        {
            "category":"Home & Garden",
            "subcategory":"Building Materials",
            "type":"Retail Goods"
        }
    ],
    "sg:phone":"+1 805 983 3600",
    "sg:postcode":"93036",
    "sg:province":"CA",
    "sg:tags":[
        "glass",
        "window",
        "plate"
    ],
    "wof:name":"Glass Wizard",
    "wof:placetype":"venue"
},
  "geometry": {"coordinates":[-119.161722,34.226298],"type":"Point"}
}