{
  "type": "Feature",
  "properties": {
    "iso:country":"US",
    "sg:address":"8299 Allport Ave",
    "sg:city":"Santa Fe Springs",
    "sg:classifiers":[
        {
            "category":"Manufacturing",
            "subcategory":"Furniture",
            "type":"Manufacturing & Wholesale Goods"
        }
    ],
    "sg:phone":"+1 562 693 4315",
    "sg:postcode":"90670",
    "sg:province":"CA",
    "wof:name":"R & J Furniture Mfr",
    "wof:placetype":"venue"
},
  "geometry": {"coordinates":[-118.064804,33.96597],"type":"Point"}
}