{
  "type": "Feature",
  "properties": {
    "iso:country":"US",
    "sg:address":"1330 E Locust St",
    "sg:city":"Ontario",
    "sg:classifiers":[
        {
            "category":"Professional",
            "type":"Services"
        }
    ],
    "sg:phone":"+1 909 930 1541",
    "sg:postcode":"91761",
    "sg:province":"CA",
    "sg:tags":[
        "product",
        "aluminum"
    ],
    "sg:website":"http://www.gerardusa.com",
    "wof:name":"Metals Usa",
    "wof:placetype":"venue"
},
  "geometry": {"coordinates":[-117.626013,34.044797],"type":"Point"}
}