{
  "type": "Feature",
  "properties": {
    "addr:full":"2247 Arata Way Antioch CA 94509",
    "addr:housenumber":"2247",
    "addr:postcode":"ca 94509",
    "addr:street":"Arata Way",
    "iso:country":"US",
    "sg:address":"2247 Arata Way",
    "sg:city":"Antioch",
    "sg:classifiers":[
        {
            "category":"Professional",
            "subcategory":"Art Services",
            "type":"Services"
        }
    ],
    "sg:phone":"+1 925 754 2997",
    "sg:postcode":"94509",
    "sg:province":"CA",
    "sg:tags":[
        "interior",
        "designer",
        "decorator"
    ],
    "wof:name":"Sidrian Construction",
    "wof:placetype":"venue"
},
  "geometry": {"coordinates":[-121.849828,38.005253],"type":"Point"}
}