{
  "type": "Feature",
  "properties": {
    "addr:full":"10161 Reese Cir Salinas CA 93907",
    "addr:housenumber":"10161",
    "addr:postcode":"93907",
    "addr:street":"Reese Cir",
    "iso:country":"US",
    "sg:address":"10161 Reese Cir",
    "sg:city":"Salinas",
    "sg:classifiers":[
        {
            "category":"Retail",
            "subcategory":"Auto Repair",
            "type":"Services"
        }
    ],
    "sg:phone":"+1 831 663 2702",
    "sg:postcode":"93907",
    "sg:province":"CA",
    "wof:name":"Prunedale Automotive Service & Repair",
    "wof:placetype":"venue"
},
  "geometry": {"coordinates":[-121.667,36.771198],"type":"Point"}
}