{
  "type": "Feature",
  "properties": {
    "iso:country":"US",
    "sg:address":"2601 Blanding Ave Ste D",
    "sg:city":"Alameda",
    "sg:classifiers":[
        {
            "category":"Restaurant",
            "type":"Food & Drink"
        },
        {
            "category":"Ice Cream",
            "type":"Food & Drink"
        }
    ],
    "sg:phone":"+1 510 865 2231",
    "sg:postcode":"94501",
    "sg:province":"CA",
    "sg:tags":[
        "frozen",
        "yogurt",
        "dessert"
    ],
    "sg:website":"www.baskinrobbins.com",
    "wof:name":"Baskin Robbins",
    "wof:placetype":"venue"
},
  "geometry": {"coordinates":[-122.233683,37.768613],"type":"Point"}
}