{
  "type": "Feature",
  "properties": {
    "addr:full":"231 W Vernon Avenue Los Angeles CA 90037",
    "addr:housenumber":"231",
    "addr:postcode":"90037",
    "addr:street":"W Vernon Avenue",
    "iso:country":"US",
    "sg:address":"231 W Vernon Avenue",
    "sg:city":"Los Angeles",
    "sg:classifiers":[
        {
            "category":"Health Services",
            "subcategory":"Chiropractor",
            "type":"Services"
        }
    ],
    "sg:phone":"+1 323 238 0200",
    "sg:postcode":"90037",
    "sg:province":"CA",
    "sg:website":"www.newwavehealth.com",
    "wof:name":"New Wave Health Care Center",
    "wof:placetype":"venue"
},
  "geometry": {"coordinates":[-118.276836,34.003804],"type":"Point"}
}