{
  "type": "Feature",
  "properties": {
    "addr:full":"1700 Hamner Ave Ste 105 Norco CA 92860",
    "addr:housenumber":"1700",
    "addr:postcode":"92860",
    "addr:street":"Hamner Ave Ste 105",
    "iso:country":"US",
    "sg:address":"1700 Hamner Ave Ste 105",
    "sg:city":"Norco",
    "sg:classifiers":[
        {
            "category":"Shopping",
            "subcategory":"Mobile Phones",
            "type":"Retail Goods"
        },
        {
            "category":"Home & Garden",
            "subcategory":"Building Materials",
            "type":"Retail Goods"
        }
    ],
    "sg:phone":"+1 951 738 0290",
    "sg:postcode":"92860",
    "sg:province":"CA",
    "sg:tags":[
        "manufactured"
    ],
    "wof:name":"Factory Housing",
    "wof:placetype":"venue"
},
  "geometry": {"coordinates":[-117.56156900000001,33.906719],"type":"Point"}
}