{
  "type": "Feature",
  "properties": {
    "iso:country":"US",
    "sg:address":"26607 Rd 124",
    "sg:city":"Visalia",
    "sg:classifiers":[
        {
            "category":"Banks & Credit Unions",
            "subcategory":"Financial Services",
            "type":"Services"
        }
    ],
    "sg:phone":"+1 559 732 0023",
    "sg:postcode":"93277",
    "sg:province":"CA",
    "sg:tags":[
        "investor"
    ],
    "wof:name":"Burkdoll Investors LP",
    "wof:placetype":"venue"
},
  "geometry": {"coordinates":[-119.296714,36.272394],"type":"Point"}
}