{
  "type": "Feature",
  "properties": {
    "addr:full":"3144 Williams Rd San Jose CA 95117",
    "addr:housenumber":"3144",
    "addr:postcode":"95117",
    "addr:street":"Williams Rd",
    "iso:country":"US",
    "sg:address":"3144 Williams Rd",
    "sg:city":"San Jose",
    "sg:classifiers":[
        {
            "category":"Food & Beverages",
            "subcategory":"Liquor & Beverages",
            "type":"Retail Goods"
        }
    ],
    "sg:phone":"+1 408 260 1098",
    "sg:postcode":"95117",
    "sg:province":"CA",
    "sg:tags":[
        "beer",
        "spirit",
        "wine"
    ],
    "wof:name":"Royal Liquors",
    "wof:placetype":"venue"
},
  "geometry": {"coordinates":[-121.952003,37.308899],"type":"Point"}
}