{
  "type": "Feature",
  "properties": {
    "addr:full":"3728 Cordero Dr Santa Barbara CA 93105",
    "addr:housenumber":"3728",
    "addr:postcode":"93105",
    "addr:street":"Cordero Dr",
    "iso:country":"US",
    "sg:address":"3728 Cordero Dr",
    "sg:city":"Santa Barbara",
    "sg:classifiers":[
        {
            "category":"Communications",
            "type":"Services"
        }
    ],
    "sg:phone":"+1 805 687 0993",
    "sg:postcode":"93105",
    "sg:province":"CA",
    "sg:tags":[
        "communication"
    ],
    "wof:name":"Tempest Media LLC",
    "wof:placetype":"venue"
},
  "geometry": {"coordinates":[-119.744073,34.433932],"type":"Point"}
}