{
  "type": "Feature",
  "properties": {
    "iso:country":"US",
    "sg:address":"5544 Monterey Hwy",
    "sg:city":"San Jose",
    "sg:classifiers":[
        {
            "category":"Health Services",
            "subcategory":"Dentist",
            "type":"Services"
        }
    ],
    "sg:phone":"+1 408 362 9767",
    "sg:postcode":"95138",
    "sg:province":"CA",
    "sg:website":"www.montereydental.com",
    "wof:name":"Monterey Dental",
    "wof:placetype":"venue"
},
  "geometry": {"coordinates":[-121.79765399999999,37.252746],"type":"Point"}
}