{
  "type": "Feature",
  "properties": {
    "iso:country":"US",
    "sg:address":"420 Gregory Ln",
    "sg:city":"Fairfield",
    "sg:classifiers":[
        {
            "category":"Building & Trades",
            "subcategory":"Construction",
            "type":"Services"
        }
    ],
    "sg:phone":"+1 707 428 7403",
    "sg:postcode":"94533",
    "sg:province":"CA",
    "sg:tags":[
        "marking",
        "maintenance",
        "parking"
    ],
    "wof:name":"Public Works-Street-Drainage",
    "wof:placetype":"venue"
},
  "geometry": {"coordinates":[-122.05601799999999,38.247742],"type":"Point"}
}