{
  "type": "Feature",
  "properties": {
    "iso:country":"US",
    "sg:address":"3540 Herman Dr",
    "sg:city":"Lafayette",
    "sg:classifiers":[
        {
            "category":"Building & Trades",
            "subcategory":"Electrical",
            "type":"Services"
        }
    ],
    "sg:phone":"+1 925 284 1666",
    "sg:postcode":"94549",
    "sg:province":"CA",
    "sg:tags":[
        "electric",
        "contractor"
    ],
    "wof:name":"Masspro",
    "wof:placetype":"venue"
},
  "geometry": {"coordinates":[-122.119326,37.885849],"type":"Point"}
}