{
  "type": "Feature",
  "properties": {
    "addr:full":"3216 Naomi Way Placerville CA 95667",
    "addr:housenumber":"3216",
    "addr:postcode":"95667",
    "addr:street":"Naomi Way",
    "iso:country":"US",
    "sg:address":"3216 Naomi Way",
    "sg:city":"Placerville",
    "sg:classifiers":[
        {
            "category":"Professional",
            "subcategory":"Business Services",
            "type":"Services"
        }
    ],
    "sg:phone":"+1 530 295 0778",
    "sg:postcode":"95667",
    "sg:province":"CA",
    "sg:tags":[
        "drafting"
    ],
    "wof:name":"Monarch Drafting & Designs",
    "wof:placetype":"venue"
},
  "geometry": {"coordinates":[-120.793302,38.721995],"type":"Point"}
}