{
  "type": "Feature",
  "properties": {
    "addr:full":"2935 Golf Course Dr Ventura CA 93003",
    "addr:housenumber":"2935",
    "addr:postcode":"93003",
    "addr:street":"Golf Course Dr",
    "iso:country":"US",
    "sg:address":"2935 Golf Course Dr",
    "sg:city":"Ventura",
    "sg:classifiers":[
        {
            "category":"Manufacturing",
            "subcategory":"Electronics",
            "type":"Manufacturing & Wholesale Goods"
        }
    ],
    "sg:phone":"+1 805 339 9060",
    "sg:postcode":"93003",
    "sg:province":"CA",
    "sg:tags":[
        "equipment",
        "electronic",
        "supply"
    ],
    "sg:website":"www.hollandelectronics.com",
    "wof:name":"Holland Electronics Corp",
    "wof:placetype":"venue"
},
  "geometry": {"coordinates":[-119.207855,34.246583],"type":"Point"}
}