{
  "type": "Feature",
  "properties": {
    "addr:full":"20535 Devonshire St Chatsworth CA 91311",
    "addr:housenumber":"20535",
    "addr:postcode":"91311",
    "addr:street":"Devonshire St",
    "iso:country":"US",
    "sg:address":"20535 Devonshire St",
    "sg:city":"Chatsworth",
    "sg:classifiers":[
        {
            "category":"Retail",
            "subcategory":"Laundry & Dry Cleaning",
            "type":"Services"
        }
    ],
    "sg:phone":"+1 818 700 0262",
    "sg:postcode":"91311",
    "sg:province":"CA",
    "sg:tags":[
        "cleaners"
    ],
    "wof:name":"Mason Cleaners",
    "wof:placetype":"venue"
},
  "geometry": {"coordinates":[-118.580804,34.257324],"type":"Point"}
}