{
  "type": "Feature",
  "properties": {
    "addr:full":"12085 Melcher Rd Mc Farland CA 93250",
    "addr:postcode":"12085;93250",
    "addr:street":"Melcher Rd",
    "iso:country":"US",
    "sg:address":"12085 Melcher Rd",
    "sg:city":"Mc Farland",
    "sg:classifiers":[
        {
            "category":"Farming",
            "subcategory":"Farm",
            "type":"Manufacturing & Wholesale Goods"
        }
    ],
    "sg:phone":"+1 661 792 2544",
    "sg:postcode":"93250",
    "sg:province":"CA",
    "wof:name":"Pompeo Fiorini",
    "wof:placetype":"venue"
},
  "geometry": {"coordinates":[-119.276454,35.714703],"type":"Point"}
}