{
  "type": "Feature",
  "properties": {
    "iso:country":"US",
    "sg:address":"3844 N Blackstone Ave",
    "sg:city":"Fresno",
    "sg:classifiers":[
        {
            "category":"Travel",
            "subcategory":"Hotels & Motels",
            "type":"Entertainment"
        }
    ],
    "sg:phone":"+1 559 222 3054",
    "sg:postcode":"93726",
    "sg:province":"CA",
    "wof:name":"Manchester Motel",
    "wof:placetype":"venue"
},
  "geometry": {"coordinates":[-119.790482,36.787398],"type":"Point"}
}