{
  "type": "Feature",
  "properties": {
    "iso:country":"US",
    "sg:address":"72449 Highway 111",
    "sg:city":"Palm Desert",
    "sg:classifiers":[
        {
            "category":"Shopping",
            "subcategory":"Department Store",
            "type":"Retail Goods"
        }
    ],
    "sg:phone":"+1 760 340 0657",
    "sg:postcode":"92260",
    "sg:province":"CA",
    "sg:website":"www.tjmaxx.com",
    "wof:name":"T J Maxx",
    "wof:placetype":"venue"
},
  "geometry": {"coordinates":[-116.402,33.727001],"type":"Point"}
}