{
  "type": "Feature",
  "properties": {
    "addr:full":"18668 Galton Ln Hayward CA 94541",
    "addr:housenumber":"18668",
    "addr:postcode":"94541",
    "addr:street":"Galton Ln",
    "iso:country":"US",
    "sg:address":"18668 Galton Ln",
    "sg:city":"Hayward",
    "sg:classifiers":[
        {
            "category":"Travel",
            "subcategory":"Travel Agent",
            "type":"Entertainment"
        }
    ],
    "sg:phone":"+1 510 317 7613",
    "sg:postcode":"94541",
    "sg:province":"CA",
    "sg:tags":[
        "agency"
    ],
    "wof:name":"Sun Destination Travel",
    "wof:placetype":"venue"
},
  "geometry": {"coordinates":[-122.12017400000001,37.67119],"type":"Point"}
}