{
  "type": "Feature",
  "properties": {
    "iso:country":"US",
    "sg:address":"1130 Industrial Ave",
    "sg:city":"Escondido",
    "sg:classifiers":[
        {
            "category":"Home & Garden",
            "subcategory":"Building Materials",
            "type":"Retail Goods"
        }
    ],
    "sg:phone":"+1 760 745 7963",
    "sg:postcode":"92029",
    "sg:province":"CA",
    "sg:tags":[
        "glass",
        "window",
        "plate"
    ],
    "wof:name":"Stuart's Glass & Screen Co",
    "wof:placetype":"venue"
},
  "geometry": {"coordinates":[-117.105553,33.119146],"type":"Point"}
}