{
  "type": "Feature",
  "properties": {
    "addr:full":"2092 Sir Francis Drake Blvd Fairfax CA 94930",
    "addr:housenumber":"2092",
    "addr:postcode":"94930",
    "addr:street":"Sir Francis Drake Blvd",
    "iso:country":"US",
    "sg:address":"2092 Sir Francis Drake Blvd",
    "sg:city":"Fairfax",
    "sg:classifiers":[
        {
            "category":"Building & Trades",
            "subcategory":"Electrical",
            "type":"Services"
        }
    ],
    "sg:phone":"+1 415 459 4511",
    "sg:postcode":"94930",
    "sg:province":"CA",
    "sg:tags":[
        "electric",
        "contractor"
    ],
    "wof:name":"Shining Star Electric",
    "wof:placetype":"venue"
},
  "geometry": {"coordinates":[-122.589743,37.987381],"type":"Point"}
}