{
  "type": "Feature",
  "properties": {
    "iso:country":"US",
    "sg:address":"1350 Travis Blvd",
    "sg:city":"Fairfield",
    "sg:classifiers":[
        {
            "category":"Shopping",
            "subcategory":"Clothing, Apparel, & Fashions",
            "type":"Retail Goods"
        }
    ],
    "sg:phone":"+1 707 434 9502",
    "sg:postcode":"94533",
    "sg:province":"CA",
    "wof:name":"Casual Corner",
    "wof:placetype":"venue"
},
  "geometry": {"coordinates":[-122.051902,38.25827],"type":"Point"}
}