{
  "type": "Feature",
  "properties": {
    "addr:full":"2010 Crow Canyon Pl San Ramon CA 94583",
    "addr:housenumber":"2010",
    "addr:postcode":"94583",
    "addr:street":"Crow Canyon Pl",
    "iso:country":"US",
    "sg:address":"2010 Crow Canyon Pl",
    "sg:city":"San Ramon",
    "sg:classifiers":[
        {
            "category":"Professional",
            "subcategory":"Computer Services",
            "type":"Services"
        }
    ],
    "sg:phone":"+1 925 866 1100",
    "sg:postcode":"94583",
    "sg:province":"CA",
    "sg:tags":[
        "processing",
        "datum"
    ],
    "wof:name":"ADP Claims Svc",
    "wof:placetype":"venue"
},
  "geometry": {"coordinates":[-121.971833,37.778793],"type":"Point"}
}