{
  "type": "Feature",
  "properties": {
    "addr:full":"17042 Greentree Ln Huntington Beach CA 92649",
    "addr:housenumber":"17042",
    "addr:postcode":"92649",
    "addr:street":"Greentree Ln",
    "iso:country":"US",
    "sg:address":"17042 Greentree Ln",
    "sg:city":"Huntington Beach",
    "sg:classifiers":[
        {
            "category":"Government",
            "subcategory":"Office",
            "type":"Public Place"
        }
    ],
    "sg:phone":"+1 714 840 9589",
    "sg:postcode":"92649",
    "sg:province":"CA",
    "wof:name":"Life Enhancement Foundation",
    "wof:placetype":"venue"
},
  "geometry": {"coordinates":[-118.03652700000001,33.71415],"type":"Point"}
}