{
  "type": "Feature",
  "properties": {
    "addr:full":"10571 Cll Lee Los Alamitos CA 90720",
    "addr:housenumber":"10571",
    "addr:postcode":"90720",
    "addr:street":"Cll Lee",
    "iso:country":"US",
    "sg:address":"10571 Cll Lee",
    "sg:city":"Los Alamitos",
    "sg:classifiers":[
        {
            "category":"Building & Trades",
            "subcategory":"Plumbing",
            "type":"Services"
        }
    ],
    "sg:phone":"+1 714 827 7838",
    "sg:postcode":"90720",
    "sg:province":"CA",
    "sg:tags":[
        "control",
        "air",
        "pollution"
    ],
    "wof:name":"Air Emmisions Testing Svc",
    "wof:placetype":"venue"
},
  "geometry": {"coordinates":[-118.057405,33.80857],"type":"Point"}
}