{
  "type": "Feature",
  "properties": {
    "addr:full":"5738 Marconi Ave Carmichael CA 95608",
    "addr:housenumber":"5738",
    "addr:postcode":"95608",
    "addr:street":"Marconi Ave",
    "iso:country":"US",
    "sg:address":"5738 Marconi Ave",
    "sg:city":"Carmichael",
    "sg:classifiers":[
        {
            "category":"Professional",
            "subcategory":"Business Services",
            "type":"Services"
        }
    ],
    "sg:phone":"+1 916 488 8451",
    "sg:postcode":"95608",
    "sg:province":"CA",
    "sg:tags":[
        "paging",
        "answering"
    ],
    "wof:name":"Ever-Rite Answering Svc",
    "wof:placetype":"venue"
},
  "geometry": {"coordinates":[-121.329131,38.617091],"type":"Point"}
}