{
  "type": "Feature",
  "properties": {
    "addr:full":"5909 Trawler Way Citrus Heights CA 95621",
    "addr:housenumber":"5909",
    "addr:postcode":"95621",
    "addr:street":"Trawler Way",
    "iso:country":"US",
    "sg:address":"5909 Trawler Way",
    "sg:city":"Citrus Heights",
    "sg:classifiers":[
        {
            "category":"Building & Trades",
            "subcategory":"Electrical",
            "type":"Services"
        }
    ],
    "sg:phone":"+1 916 723 5995",
    "sg:postcode":"95621",
    "sg:province":"CA",
    "sg:tags":[
        "telecommunication",
        "contractor"
    ],
    "wof:name":"Vail Communications",
    "wof:placetype":"venue"
},
  "geometry": {"coordinates":[-121.32474499999999,38.700339],"type":"Point"}
}