{
  "type": "Feature",
  "properties": {
    "iso:country":"US",
    "sg:address":"1337 Bruce St",
    "sg:city":"Chico",
    "sg:classifiers":[
        {
            "category":"Manufacturing",
            "subcategory":"Lumber",
            "type":"Manufacturing & Wholesale Goods"
        }
    ],
    "sg:phone":"+1 530 343 9726",
    "sg:postcode":"95928",
    "sg:province":"CA",
    "sg:tags":[
        "forestry"
    ],
    "wof:name":"McCollum Tree Service",
    "wof:placetype":"venue"
},
  "geometry": {"coordinates":[-121.818656,39.728745],"type":"Point"}
}