{
  "type": "Feature",
  "properties": {
    "addr:full":"556 Elsie Ave San Leandro CA 94577",
    "addr:housenumber":"556",
    "addr:postcode":"94577",
    "addr:street":"Elsie Ave",
    "iso:country":"US",
    "sg:address":"556 Elsie Ave",
    "sg:city":"San Leandro",
    "sg:classifiers":[
        {
            "category":"Professional",
            "type":"Services"
        }
    ],
    "sg:phone":"+1 510 614 8150",
    "sg:postcode":"94577",
    "sg:province":"CA",
    "wof:name":"Dirkx Workx",
    "wof:placetype":"venue"
},
  "geometry": {"coordinates":[-122.15022500000001,37.721532],"type":"Point"}
}