{
  "type": "Feature",
  "properties": {
    "iso:country":"US",
    "sg:address":"3170 Vista Del Camino Ste K",
    "sg:city":"Marina",
    "sg:classifiers":[
        {
            "category":"Personal",
            "subcategory":"Nail Salon",
            "type":"Services"
        }
    ],
    "sg:phone":"+1 831 384 7022",
    "sg:postcode":"93933",
    "sg:province":"CA",
    "wof:name":"Luxury Nail & Spa",
    "wof:placetype":"venue"
},
  "geometry": {"coordinates":[-121.796559,36.68725],"type":"Point"}
}