{
  "type": "Feature",
  "properties": {
    "iso:country":"US",
    "sg:address":"10367 Hole Ave",
    "sg:city":"Riverside",
    "sg:classifiers":[
        {
            "category":"Professional",
            "subcategory":"Lawyer & Legal Services",
            "type":"Services"
        }
    ],
    "sg:phone":"+1 951 352 8700",
    "sg:postcode":"92505",
    "sg:province":"CA",
    "sg:tags":[
        "attorney",
        "law",
        "family",
        "divorce",
        "assistance",
        "child",
        "criminal",
        "document",
        "custody"
    ],
    "sg:website":"http://www.riversidedivorcefirm.com",
    "wof:name":"Richard K Isles Attorney at Law",
    "wof:placetype":"venue"
},
  "geometry": {"coordinates":[-117.466925,33.915675],"type":"Point"}
}