{
  "type": "Feature",
  "properties": {
    "iso:country":"US",
    "sg:address":"1660 W Linne Rd",
    "sg:city":"Tracy",
    "sg:classifiers":[
        {
            "category":"Autos & Motor Vehicles",
            "subcategory":"Automobile Sales",
            "type":"Retail Goods"
        }
    ],
    "sg:phone":"+1 209 830 0529",
    "sg:postcode":"95377",
    "sg:province":"CA",
    "sg:tags":[
        "car",
        "dealer"
    ],
    "wof:name":"Bay Auto",
    "wof:placetype":"venue"
},
  "geometry": {"coordinates":[-121.308255,37.696401],"type":"Point"}
}