{
  "type": "Feature",
  "properties": {
    "addr:full":"91 Cernon St Vacaville CA 95688",
    "addr:housenumber":"91",
    "addr:postcode":"95688",
    "addr:street":"Cernon St",
    "iso:country":"US",
    "sg:address":"91 Cernon St",
    "sg:city":"Vacaville",
    "sg:classifiers":[
        {
            "category":"Building & Trades",
            "subcategory":"Construction",
            "type":"Services"
        }
    ],
    "sg:phone":"+1 707 451 7293",
    "sg:postcode":"95688",
    "sg:province":"CA",
    "sg:tags":[
        "contractor"
    ],
    "wof:name":"West & East Bay Construction",
    "wof:placetype":"venue"
},
  "geometry": {"coordinates":[-121.989867,38.36103],"type":"Point"}
}