{
  "type": "Feature",
  "properties": {
    "iso:country":"US",
    "sg:address":"4167 Bakman Ave",
    "sg:city":"North Hollywood",
    "sg:classifiers":[
        {
            "category":"Real Estate",
            "subcategory":"Real Estate Operator",
            "type":"Services"
        }
    ],
    "sg:phone":"+1 818 762 3998",
    "sg:postcode":"91602",
    "sg:province":"CA",
    "sg:tags":[
        "building",
        "commercial"
    ],
    "wof:name":"Weddington Inv Prpts LLC",
    "wof:placetype":"venue"
},
  "geometry": {"coordinates":[-118.37795300000001,34.14403],"type":"Point"}
}