{
  "type": "Feature",
  "properties": {
    "iso:country":"US",
    "sg:address":"6851 Canby Ave",
    "sg:city":"Reseda",
    "sg:classifiers":[
        {
            "category":"Professional",
            "subcategory":"Business Services",
            "type":"Services"
        }
    ],
    "sg:phone":"+1 818 343 7117",
    "sg:postcode":"91335",
    "sg:province":"CA",
    "sg:tags":[
        "liquidator"
    ],
    "wof:name":"Superior Liquidators",
    "wof:placetype":"venue"
},
  "geometry": {"coordinates":[-118.53482,34.194501],"type":"Point"}
}