{
  "type": "Feature",
  "properties": {
    "iso:country":"US",
    "sg:address":"706 12th Ave",
    "sg:city":"Kingsburg",
    "sg:classifiers":[
        {
            "category":"Building & Trades",
            "subcategory":"Construction",
            "type":"Services"
        }
    ],
    "sg:phone":"+1 559 897 2538",
    "sg:postcode":"93631",
    "sg:province":"CA",
    "sg:tags":[
        "concrete",
        "contractor"
    ],
    "wof:name":"Malagon Concrete",
    "wof:placetype":"venue"
},
  "geometry": {"coordinates":[-119.554041,36.505303],"type":"Point"}
}