{
  "type": "Feature",
  "properties": {
    "iso:country":"US",
    "sg:address":"2013 Wilshire Blvd",
    "sg:city":"Los Angeles",
    "sg:classifiers":[
        {
            "category":"Shopping",
            "subcategory":"Pharmacy",
            "type":"Retail Goods"
        }
    ],
    "sg:phone":"+1 213 483 8025",
    "sg:postcode":"90057",
    "sg:province":"CA",
    "wof:name":"Wilshire Pharmacy",
    "wof:placetype":"venue"
},
  "geometry": {"coordinates":[-118.275724,34.057927],"type":"Point"}
}