{
  "type": "Feature",
  "properties": {
    "iso:country":"US",
    "sg:address":"1349 Walker Ave",
    "sg:city":"Modesto",
    "sg:classifiers":[
        {
            "category":"Building & Trades",
            "subcategory":"Construction",
            "type":"Services"
        }
    ],
    "sg:phone":"+1 209 523 1790",
    "sg:postcode":"95358",
    "sg:province":"CA",
    "sg:tags":[
        "tile",
        "dealer"
    ],
    "wof:name":"Herb & Jeff Tile",
    "wof:placetype":"venue"
},
  "geometry": {"coordinates":[-121.034589,37.655855],"type":"Point"}
}