{
  "type": "Feature",
  "properties": {
    "iso:country":"US",
    "sg:address":"581 B Natoma St",
    "sg:city":"San Francisco",
    "sg:classifiers":[
        {
            "category":"Professional",
            "subcategory":"Computer Services",
            "type":"Services"
        }
    ],
    "sg:phone":"+1 415 850 7774",
    "sg:postcode":"94103",
    "sg:province":"CA",
    "sg:tags":[
        "repair"
    ],
    "sg:website":"www.deconstrukted.com",
    "wof:name":"deconstrukted solutions",
    "wof:placetype":"venue"
},
  "geometry": {"coordinates":[-122.409485,37.77856],"type":"Point"}
}