{
  "type": "Feature",
  "properties": {
    "addr:full":"28 Richardson Ave San Francisco CA 94123",
    "addr:housenumber":"28",
    "addr:postcode":"94123",
    "addr:street":"Richardson Ave",
    "iso:country":"US",
    "sg:address":"28 Richardson Ave",
    "sg:city":"San Francisco",
    "sg:classifiers":[
        {
            "category":"Building & Trades",
            "subcategory":"Construction",
            "type":"Services"
        }
    ],
    "sg:phone":"+1 415 412 1523",
    "sg:postcode":"94123",
    "sg:province":"CA",
    "sg:tags":[
        "scaffolding"
    ],
    "wof:name":"Mander Scaffold",
    "wof:placetype":"venue"
},
  "geometry": {"coordinates":[-122.445627,37.799471],"type":"Point"}
}