{
  "type": "Feature",
  "properties": {
    "addr:full":"108 E Olive Ave Porterville CA 93257",
    "addr:housenumber":"108",
    "addr:postcode":"93257",
    "addr:street":"E Olive Ave",
    "iso:country":"US",
    "sg:address":"108 E Olive Ave",
    "sg:city":"Porterville",
    "sg:classifiers":[
        {
            "category":"Building & Trades",
            "subcategory":"Construction",
            "type":"Services"
        }
    ],
    "sg:phone":"+1 559 782 3399",
    "sg:postcode":"93257",
    "sg:province":"CA",
    "sg:tags":[
        "resurfacing",
        "laying",
        "refinishing",
        "floor"
    ],
    "wof:name":"Pro Flooring Installations",
    "wof:placetype":"venue"
},
  "geometry": {"coordinates":[-119.01322,36.065198],"type":"Point"}
}