{
  "type": "Feature",
  "properties": {
    "addr:full":"19040 Van Buren Blvd Riverside CA 92508",
    "addr:housenumber":"19040",
    "addr:postcode":"92508",
    "addr:street":"Van Buren Blvd",
    "iso:country":"US",
    "sg:address":"19040 Van Buren Blvd",
    "sg:city":"Riverside",
    "sg:classifiers":[
        {
            "category":"Health Services",
            "subcategory":"Hospital",
            "type":"Services"
        }
    ],
    "sg:phone":"+1 951 789 5660",
    "sg:postcode":"92508",
    "sg:province":"CA",
    "sg:tags":[
        "medical",
        "surgical",
        "emergency"
    ],
    "wof:name":"Raincross Express Care",
    "wof:placetype":"venue"
},
  "geometry": {"coordinates":[-117.32847700000001,33.887673],"type":"Point"}
}