{
  "type": "Feature",
  "properties": {
    "iso:country":"US",
    "sg:address":"524 W Lambert Rd",
    "sg:city":"La Habra",
    "sg:classifiers":[
        {
            "category":"Personal",
            "subcategory":"Beauty Salon",
            "type":"Services"
        }
    ],
    "sg:phone":"+1 562 697 0200",
    "sg:postcode":"90631",
    "sg:province":"CA",
    "wof:name":"Elegants Beauty Salon",
    "wof:placetype":"venue"
},
  "geometry": {"coordinates":[-117.95108500000001,33.924511],"type":"Point"}
}