{
  "type": "Feature",
  "properties": {
    "addr:full":"1684 Logan Ave San Diego CA 92113",
    "addr:housenumber":"1684",
    "addr:postcode":"92113",
    "addr:street":"Logan Ave",
    "iso:country":"US",
    "sg:address":"1684 Logan Ave",
    "sg:city":"San Diego",
    "sg:classifiers":[
        {
            "category":"Wholesale",
            "subcategory":"Auto Parts",
            "type":"Manufacturing & Wholesale Goods"
        },
        {
            "category":"Wholesale",
            "subcategory":"Scrap",
            "type":"Manufacturing & Wholesale Goods"
        }
    ],
    "sg:phone":"+1 619 239 9119",
    "sg:postcode":"92113",
    "sg:province":"CA",
    "sg:tags":[
        "automobile",
        "rebuilt",
        "material"
    ],
    "wof:name":"F & D Foreign Recycling",
    "wof:placetype":"venue"
},
  "geometry": {"coordinates":[-117.14814,32.704302],"type":"Point"}
}