{
  "type": "Feature",
  "properties": {
    "iso:country":"US",
    "sg:address":"126 W Carson St",
    "sg:city":"Carson",
    "sg:phone":"+1 310 549 4251",
    "sg:postcode":"90745",
    "sg:province":"CA",
    "wof:name":"Tambuli Oriental Foods",
    "wof:placetype":"venue"
},
  "geometry": {"coordinates":[-118.27853399999999,33.831558],"type":"Point"}
}