{
  "type": "Feature",
  "properties": {
    "iso:country":"US",
    "sg:address":"1112 Montana Ave",
    "sg:city":"Santa Monica",
    "sg:classifiers":[
        {
            "category":"Professional",
            "subcategory":"Business Services",
            "type":"Services"
        }
    ],
    "sg:phone":"+1 310 587 1566",
    "sg:postcode":"90403",
    "sg:province":"CA",
    "sg:tags":[
        "interior",
        "consultant",
        "design",
        "decorator"
    ],
    "wof:name":"Quilted Monkey",
    "wof:placetype":"venue"
},
  "geometry": {"coordinates":[-118.497556,34.030148],"type":"Point"}
}