{
  "type": "Feature",
  "properties": {
    "addr:full":"18005 Sky Park Cir Ste H Irvine CA 92614",
    "addr:housenumber":"18005",
    "addr:postcode":"92614",
    "addr:street":"Sky Park Cir Ste H",
    "iso:country":"US",
    "sg:address":"18005 Sky Park Cir Ste H",
    "sg:city":"Irvine",
    "sg:classifiers":[
        {
            "category":"Banks & Credit Unions",
            "subcategory":"Investment Brokerage",
            "type":"Services"
        }
    ],
    "sg:phone":"+1 949 476 8088",
    "sg:postcode":"92614",
    "sg:province":"CA",
    "sg:tags":[
        "investing"
    ],
    "sg:website":"www.ashwillinvestments.com",
    "wof:name":"Ashwill Investments",
    "wof:placetype":"venue"
},
  "geometry": {"coordinates":[-117.856979,33.687885],"type":"Point"}
}