{
  "type": "Feature",
  "properties": {
    "addr:full":"8106 Long Beach Boulevard South Gate CA 90280",
    "addr:housenumber":"8106",
    "addr:postcode":"90280",
    "addr:street":"Long Beach Boulevard;Gate",
    "iso:country":"US",
    "sg:address":"8106 Long Beach Boulevard",
    "sg:city":"South Gate",
    "sg:classifiers":[
        {
            "category":"Health Services",
            "subcategory":"Optometrist",
            "type":"Services"
        }
    ],
    "sg:phone":"+1 323 585 5411",
    "sg:postcode":"90280",
    "sg:province":"CA",
    "wof:name":"Levy Charles H OD",
    "wof:placetype":"venue"
},
  "geometry": {"coordinates":[-118.225324,33.964851],"type":"Point"}
}