{
  "type": "Feature",
  "properties": {
    "addr:full":"145 N Wolfe Rd Sunnyvale CA 94086",
    "addr:housenumber":"145",
    "addr:postcode":"94086",
    "addr:street":"N Wolfe Rd",
    "iso:country":"US",
    "sg:address":"145 N Wolfe Rd",
    "sg:city":"Sunnyvale",
    "sg:classifiers":[
        {
            "category":"Real Estate",
            "subcategory":"Real Estate Services",
            "type":"Services"
        }
    ],
    "sg:phone":"+1 408 324 4900",
    "sg:postcode":"94086",
    "sg:province":"CA",
    "sg:tags":[
        "company",
        "title"
    ],
    "wof:name":"Fidelity National Title",
    "wof:placetype":"venue"
},
  "geometry": {"coordinates":[-122.01382599999999,37.373588],"type":"Point"}
}