{
  "type": "Feature",
  "properties": {
    "iso:country":"US",
    "sg:address":"145 N Wolfe Rd",
    "sg:city":"Sunnyvale",
    "sg:classifiers":[
        {
            "category":"Real Estate",
            "subcategory":"Real Estate Services",
            "type":"Services"
        }
    ],
    "sg:phone":"+1 408 324 4900",
    "sg:postcode":"94086",
    "sg:province":"CA",
    "sg:tags":[
        "company",
        "title"
    ],
    "wof:name":"Fidelity National Title",
    "wof:placetype":"venue"
},
  "geometry": {"coordinates":[-122.013826,37.373588],"type":"Point"}
}