{
  "type": "Feature",
  "properties": {
    "addr:full":"12900 Haster St Garden Grove CA 92840",
    "addr:postcode":"12900;92840",
    "addr:street":"Haster St",
    "iso:country":"US",
    "sg:address":"12900 Haster St",
    "sg:city":"Garden Grove",
    "sg:classifiers":[
        {
            "category":"Wholesale",
            "subcategory":"Chemicals & Plastics",
            "type":"Manufacturing & Wholesale Goods"
        }
    ],
    "sg:phone":"+1 714 621 0052",
    "sg:postcode":"92840",
    "sg:province":"CA",
    "sg:tags":[
        "cleaning",
        "compound"
    ],
    "wof:name":"American Building Svc Co",
    "wof:placetype":"venue"
},
  "geometry": {"coordinates":[-117.906047,33.774768],"type":"Point"}
}