{
  "type": "Feature",
  "properties": {
    "iso:country":"US",
    "sg:address":"227 N Jackson Avenue",
    "sg:city":"San Jose",
    "sg:classifiers":[
        {
            "category":"Health Services",
            "subcategory":"Doctor",
            "type":"Services"
        }
    ],
    "sg:phone":"+1 408 347 2370",
    "sg:postcode":"95116",
    "sg:province":"CA",
    "sg:tags":[
        "medicine",
        "internal"
    ],
    "wof:name":"Bruhn Charles MD",
    "wof:placetype":"venue"
},
  "geometry": {"coordinates":[-121.848336,37.363251],"type":"Point"}
}