{
  "type": "Feature",
  "properties": {
    "iso:country":"US",
    "sg:address":"16755 Von Karman Ave",
    "sg:city":"Irvine",
    "sg:classifiers":[
        {
            "category":"Building & Trades",
            "subcategory":"Construction",
            "type":"Services"
        }
    ],
    "sg:phone":"+1 949 756 2667",
    "sg:postcode":"92606",
    "sg:province":"CA",
    "sg:tags":[
        "contractor"
    ],
    "wof:name":"J A Jones Management Services",
    "wof:placetype":"venue"
},
  "geometry": {"coordinates":[-117.836264,33.695963],"type":"Point"}
}