{
  "type": "Feature",
  "properties": {
    "iso:country":"US",
    "sg:address":"184 S Main St",
    "sg:city":"Milpitas",
    "sg:classifiers":[
        {
            "category":"Personal",
            "subcategory":"Beauty Salon",
            "type":"Services"
        }
    ],
    "sg:phone":"+1 408 263 3800",
    "sg:postcode":"95035",
    "sg:province":"CA",
    "wof:name":"Ritz Superhair",
    "wof:placetype":"venue"
},
  "geometry": {"coordinates":[-121.906932,37.430496],"type":"Point"}
}