{
  "type": "Feature",
  "properties": {
    "iso:country":"US",
    "sg:address":"1766 E 46th St",
    "sg:city":"Vernon",
    "sg:classifiers":[
        {
            "category":"Manufacturing",
            "subcategory":"Textiles",
            "type":"Manufacturing & Wholesale Goods"
        }
    ],
    "sg:phone":"+1 213 626 6765",
    "sg:postcode":"90058",
    "sg:province":"CA",
    "sg:tags":[
        "machinery"
    ],
    "wof:name":"Ahearn/Eastman Cutting",
    "wof:placetype":"venue"
},
  "geometry": {"coordinates":[-118.241041,34.00164],"type":"Point"}
}