{
  "type": "Feature",
  "properties": {
    "iso:country":"US",
    "sg:address":"4378 Leisure Ln",
    "sg:city":"Placerville",
    "sg:classifiers":[
        {
            "category":"Personal",
            "subcategory":"Beauty Salon",
            "type":"Services"
        }
    ],
    "sg:phone":"+1 530 644 6396",
    "sg:postcode":"95667",
    "sg:province":"CA",
    "wof:name":"Shonna Doos",
    "wof:placetype":"venue"
},
  "geometry": {"coordinates":[-120.668413,38.685778],"type":"Point"}
}