{
  "type": "Feature",
  "properties": {
    "iso:country":"US",
    "sg:address":"4747 24th St",
    "sg:city":"Sacramento",
    "sg:classifiers":[
        {
            "category":"Wholesale",
            "subcategory":"Electrical",
            "type":"Manufacturing & Wholesale Goods"
        }
    ],
    "sg:phone":"+1 916 457 1601",
    "sg:postcode":"95822",
    "sg:province":"CA",
    "sg:tags":[
        "equipment",
        "electric",
        "supply"
    ],
    "sg:website":"www.cves.net",
    "wof:name":"Central Valley Electric",
    "wof:placetype":"venue"
},
  "geometry": {"coordinates":[-121.483147,38.53188],"type":"Point"}
}