{
  "type": "Feature",
  "properties": {
    "iso:country":"US",
    "sg:address":"1062 W Imperial Hwy",
    "sg:city":"Los Angeles",
    "sg:classifiers":[
        {
            "category":"Personal",
            "subcategory":"Beauty Salon",
            "type":"Services"
        }
    ],
    "sg:phone":"+1 323 754 7978",
    "sg:postcode":"90044",
    "sg:province":"CA",
    "wof:name":"Escort Beauty Salon",
    "wof:placetype":"venue"
},
  "geometry": {"coordinates":[-118.293492,33.930839],"type":"Point"}
}