{
  "type": "Feature",
  "properties": {
    "iso:country":"US",
    "sg:address":"1500 Quail Street",
    "sg:city":"Newport Beach",
    "sg:classifiers":[
        {
            "category":"Professional",
            "subcategory":"Accounting & Tax Preparation",
            "type":"Services"
        }
    ],
    "sg:phone":"+1 949 252 0252",
    "sg:postcode":"92660",
    "sg:province":"CA",
    "sg:tags":[
        "accountant"
    ],
    "wof:name":"Geyer Roger T CPA",
    "wof:placetype":"venue"
},
  "geometry": {"coordinates":[-117.86855300000001,33.660903],"type":"Point"}
}