{
  "type": "Feature",
  "properties": {
    "iso:country":"US",
    "sg:address":"23505 Crenshaw Blvd Ste 149",
    "sg:city":"Torrance",
    "sg:classifiers":[
        {
            "category":"Home & Garden",
            "subcategory":"Furniture",
            "type":"Retail Goods"
        }
    ],
    "sg:phone":"+1 310 891 0810",
    "sg:postcode":"90505",
    "sg:province":"CA",
    "sg:tags":[
        "store"
    ],
    "sg:website":"www.bestpricedfurniture.com",
    "wof:name":"Best Priced Furniture Dot Com",
    "wof:placetype":"venue"
},
  "geometry": {"coordinates":[-118.328225,33.812704],"type":"Point"}
}