{
  "type": "Feature",
  "properties": {
    "iso:country":"US",
    "sg:address":"5920 Evergreen Ln",
    "sg:city":"Mariposa",
    "sg:classifiers":[
        {
            "category":"Shopping",
            "type":"Retail Goods"
        }
    ],
    "sg:phone":"+1 209 966 3642",
    "sg:postcode":"95338",
    "sg:province":"CA",
    "sg:tags":[
        "art",
        "gallery",
        "dealer"
    ],
    "wof:name":"Morning Star Gallery",
    "wof:placetype":"venue"
},
  "geometry": {"coordinates":[-119.826514,37.502208],"type":"Point"}
}