{
  "type": "Feature",
  "properties": {
    "iso:country":"US",
    "sg:address":"200 Lambert St",
    "sg:city":"Oxnard",
    "sg:classifiers":[
        {
            "category":"Wholesale",
            "subcategory":"Metals & Minerals",
            "type":"Manufacturing & Wholesale Goods"
        }
    ],
    "sg:phone":"+1 805 485 4350",
    "sg:postcode":"93036",
    "sg:province":"CA",
    "sg:tags":[
        "pipe"
    ],
    "wof:name":"Famcon Pipe & Supply Inc",
    "wof:placetype":"venue"
},
  "geometry": {"coordinates":[-119.161143,34.254238],"type":"Point"}
}