{
  "type": "Feature",
  "properties": {
    "iso:country":"US",
    "sg:address":"12818 S Western Avenue",
    "sg:city":"Gardena",
    "sg:classifiers":[
        {
            "category":"Building & Trades",
            "subcategory":"Plumbing",
            "type":"Services"
        }
    ],
    "sg:phone":"+1 310 532 0039",
    "sg:postcode":"90249",
    "sg:province":"CA",
    "sg:website":"www.magicplumbing.com",
    "wof:name":"Magic Plumbing",
    "wof:placetype":"venue"
},
  "geometry": {"coordinates":[-118.309201,33.916003],"type":"Point"}
}