{
  "type": "Feature",
  "properties": {
    "iso:country":"US",
    "sg:address":"73375 el Paseo",
    "sg:city":"Palm Desert",
    "sg:classifiers":[
        {
            "category":"Shopping",
            "subcategory":"Gifts & Souvenirs",
            "type":"Retail Goods"
        }
    ],
    "sg:phone":"+1 760 341 2330",
    "sg:postcode":"92260",
    "sg:province":"CA",
    "sg:tags":[
        "shop"
    ],
    "wof:name":"Storekeeper",
    "wof:placetype":"venue"
},
  "geometry": {"coordinates":[-116.38657000000001,33.719698],"type":"Point"}
}