{
  "type": "Feature",
  "properties": {
    "addr:full":"273 S Rancho Santa Fe Rd San Marcos CA 92078",
    "addr:housenumber":"273",
    "addr:postcode":"92078",
    "addr:street":"S Rancho Santa Fe Rd",
    "iso:country":"US",
    "sg:address":"273 S Rancho Santa Fe Rd",
    "sg:city":"San Marcos",
    "sg:classifiers":[
        {
            "category":"Personal",
            "subcategory":"Beauty Salon",
            "type":"Services"
        }
    ],
    "sg:phone":"+1 760 736 4090",
    "sg:postcode":"92078",
    "sg:province":"CA",
    "wof:name":"Nora Salon",
    "wof:placetype":"venue"
},
  "geometry": {"coordinates":[-117.201685,33.143253],"type":"Point"}
}