{
  "type": "Feature",
  "properties": {
    "iso:country":"US",
    "sg:address":"1779 Scott St",
    "sg:city":"St Helena",
    "sg:classifiers":[
        {
            "category":"Farming",
            "subcategory":"Vineyard",
            "type":"Manufacturing & Wholesale Goods"
        },
        {
            "category":"Farming",
            "subcategory":"Farm & Veterinary Services",
            "type":"Manufacturing & Wholesale Goods"
        }
    ],
    "sg:phone":"+1 707 967 9937",
    "sg:postcode":"94574",
    "sg:province":"CA",
    "sg:tags":[
        "management"
    ],
    "wof:name":"Old Kraft Vineyard",
    "wof:placetype":"venue"
},
  "geometry": {"coordinates":[-122.479691,38.502949],"type":"Point"}
}