{
  "type": "Feature",
  "properties": {
    "addr:full":"300 N Altadena Dr Pasadena CA 91107",
    "addr:housenumber":"300",
    "addr:postcode":"91107",
    "addr:street":"N Altadena Dr",
    "iso:country":"US",
    "sg:address":"300 N Altadena Dr",
    "sg:city":"Pasadena",
    "sg:classifiers":[
        {
            "category":"Autos & Motor Vehicles",
            "subcategory":"Auto Supplies",
            "type":"Retail Goods"
        },
        {
            "category":"Retail",
            "subcategory":"Car Wash",
            "type":"Services"
        },
        {
            "category":"Professional",
            "subcategory":"Computer Services",
            "type":"Services"
        }
    ],
    "sg:phone":"+1 626 577 7648",
    "sg:postcode":"91107",
    "sg:province":"CA",
    "sg:tags":[
        "wheel",
        "stereo",
        "installation",
        "tire",
        "automobile",
        "detailing",
        "tinting",
        "window",
        "part"
    ],
    "sg:website":"www.vipcenters.com",
    "wof:name":"V I P Auto Customs Inc",
    "wof:placetype":"venue"
},
  "geometry": {"coordinates":[-118.098221,34.151295],"type":"Point"}
}