{
  "type": "Feature",
  "properties": {
    "addr:full":"24343 Magic Mountain Pkwy Valencia CA 91355",
    "addr:postcode":"24343;91355",
    "addr:street":"Magic Mountain Pkwy",
    "iso:country":"US",
    "sg:address":"24343 Magic Mountain Pkwy",
    "sg:city":"Valencia",
    "sg:classifiers":[
        {
            "category":"Manufacturing",
            "subcategory":"Printing",
            "type":"Manufacturing & Wholesale Goods"
        }
    ],
    "sg:phone":"+1 661 255 2845",
    "sg:postcode":"91355",
    "sg:province":"CA",
    "sg:tags":[
        "printer"
    ],
    "sg:website":"www.agvalencia.com",
    "wof:name":"Alpha Graphics",
    "wof:placetype":"venue"
},
  "geometry": {"coordinates":[-118.56422600000001,34.42029],"type":"Point"}
}