{
  "type": "Feature",
  "properties": {
    "iso:country":"US",
    "sg:address":"2011 Fresno St",
    "sg:city":"Fresno",
    "sg:classifiers":[
        {
            "category":"Restaurant",
            "type":"Food & Drink"
        }
    ],
    "sg:phone":"+1 559 445 0739",
    "sg:postcode":"93721",
    "sg:province":"CA",
    "wof:name":"Subway Sandwiches & Salads",
    "wof:placetype":"venue"
},
  "geometry": {"coordinates":[-119.79142299999999,36.736598],"type":"Point"}
}