{
  "type": "Feature",
  "properties": {
    "addr:full":"3565 Rolling Hills Rd Sheridan CA 95681",
    "addr:housenumber":"3565",
    "addr:postcode":"95681",
    "addr:street":"Rolling Hills Rd",
    "iso:country":"US",
    "sg:address":"3565 Rolling Hills Rd",
    "sg:city":"Sheridan",
    "sg:classifiers":[
        {
            "category":"Retail",
            "subcategory":"Auto Repair",
            "type":"Services"
        }
    ],
    "sg:phone":"+1 916 806 7223",
    "sg:postcode":"95681",
    "sg:province":"CA",
    "sg:tags":[
        "car",
        "parts",
        "race"
    ],
    "wof:name":"Casner Racing Enterprises",
    "wof:placetype":"venue"
},
  "geometry": {"coordinates":[-121.350414,38.991996],"type":"Point"}
}