{
  "type": "Feature",
  "properties": {
    "addr:full":"7271 Snyder Ln Rohnert Park CA 94928",
    "addr:housenumber":"7271",
    "addr:postcode":"94928",
    "addr:street":"Snyder Ln",
    "iso:country":"US",
    "sg:address":"7271 Snyder Ln",
    "sg:city":"Rohnert Park",
    "sg:classifiers":[
        {
            "category":"Shopping",
            "subcategory":"Music",
            "type":"Retail Goods"
        }
    ],
    "sg:phone":"+1 707 792 1506",
    "sg:postcode":"94928",
    "sg:province":"CA",
    "sg:tags":[
        "video",
        "disc",
        "tape",
        "cassette"
    ],
    "wof:name":"Game Cage",
    "wof:placetype":"venue"
},
  "geometry": {"coordinates":[-122.68549299999999,38.339578],"type":"Point"}
}