{
  "type": "Feature",
  "properties": {
    "iso:country":"US",
    "sg:address":"15 S Humboldt St",
    "sg:city":"San Mateo",
    "sg:classifiers":[
        {
            "category":"Place Of Worship",
            "subcategory":"Church",
            "type":"Public Place"
        }
    ],
    "sg:phone":"+1 650 342 0959",
    "sg:postcode":"94401",
    "sg:province":"CA",
    "sg:website":"www.cbcsm.org",
    "wof:name":"Community Baptist Church",
    "wof:placetype":"venue"
},
  "geometry": {"coordinates":[-122.319,37.571999],"type":"Point"}
}