{
  "type": "Feature",
  "properties": {
    "addr:full":"1301 20th St Santa Monica CA 90404",
    "addr:housenumber":"1301",
    "addr:postcode":"90404",
    "addr:street":"20Th St",
    "iso:country":"US",
    "sg:address":"1301 20th St",
    "sg:city":"Santa Monica",
    "sg:classifiers":[
        {
            "category":"Health Services",
            "subcategory":"Doctor",
            "type":"Services"
        }
    ],
    "sg:phone":"+1 310 315 9211",
    "sg:postcode":"90404",
    "sg:province":"CA",
    "sg:tags":[
        "physician",
        "surgeon"
    ],
    "wof:name":"Kao Plastic Surgery",
    "wof:placetype":"venue"
},
  "geometry": {"coordinates":[-118.47997599999999,34.028698],"type":"Point"}
}