{
  "type": "Feature",
  "properties": {
    "iso:country":"US",
    "sg:address":"1624 Alpine Ave",
    "sg:city":"Stockton",
    "sg:classifiers":[
        {
            "category":"Freight",
            "type":"Transportation"
        }
    ],
    "sg:phone":"+1 209 948 8020",
    "sg:postcode":"95205",
    "sg:province":"CA",
    "sg:tags":[
        "trucking"
    ],
    "sg:website":"www.fitchbros.com",
    "wof:name":"Fitch Bros Trucking Inc",
    "wof:placetype":"venue"
},
  "geometry": {"coordinates":[-121.281463,37.984356],"type":"Point"}
}