{
  "type": "Feature",
  "properties": {
    "iso:country":"US",
    "sg:address":"9051 Siempre Viva Rd",
    "sg:city":"San Diego",
    "sg:classifiers":[
        {
            "category":"Freight",
            "type":"Transportation"
        }
    ],
    "sg:phone":"+1 619 661 7144",
    "sg:postcode":"92154",
    "sg:province":"CA",
    "sg:tags":[
        "arrangement"
    ],
    "wof:name":"Chavez Smith & Associates",
    "wof:placetype":"venue"
},
  "geometry": {"coordinates":[-116.945797,32.553],"type":"Point"}
}