{
  "type": "Feature",
  "properties": {
    "addr:full":"2634 Hamner Ave Norco CA 92860",
    "addr:housenumber":"2634",
    "addr:postcode":"92860",
    "addr:street":"Hamner Ave",
    "iso:country":"US",
    "sg:address":"2634 Hamner Ave",
    "sg:city":"Norco",
    "sg:classifiers":[
        {
            "category":"Shopping",
            "subcategory":"Used Merchandise",
            "type":"Retail Goods"
        }
    ],
    "sg:phone":"+1 951 736 7713",
    "sg:postcode":"92860",
    "sg:province":"CA",
    "sg:tags":[
        "pawnbroker"
    ],
    "wof:name":"Norco Loan & Jewelry",
    "wof:placetype":"venue"
},
  "geometry": {"coordinates":[-117.559459,33.920786],"type":"Point"}
}