{
  "type": "Feature",
  "properties": {
    "iso:country":"US",
    "sg:address":"2746 W Tenaya Ave",
    "sg:city":"Fresno",
    "sg:classifiers":[
        {
            "category":"Farming",
            "subcategory":"Vineyard",
            "type":"Manufacturing & Wholesale Goods"
        }
    ],
    "sg:phone":"+1 559 439 0982",
    "sg:postcode":"93711",
    "sg:province":"CA",
    "wof:name":"P & G Vineyards",
    "wof:placetype":"venue"
},
  "geometry": {"coordinates":[-119.84277,36.829244],"type":"Point"}
}