{
  "type": "Feature",
  "properties": {
    "iso:country":"US",
    "sg:address":"3100 E Imperial Hwy",
    "sg:city":"Lynwood",
    "sg:classifiers":[
        {
            "category":"Shopping",
            "subcategory":"Clothing, Apparel, & Fashions",
            "type":"Retail Goods"
        },
        {
            "category":"Manufacturing",
            "subcategory":"Apparel",
            "type":"Manufacturing & Wholesale Goods"
        }
    ],
    "sg:phone":"+1 310 632 2990",
    "sg:postcode":"90262",
    "sg:province":"CA",
    "sg:tags":[
        "apparel-wholesale",
        "manufacturer",
        "women's"
    ],
    "wof:name":"Hip Hop Zone",
    "wof:placetype":"venue"
},
  "geometry": {"coordinates":[-118.21629299999999,33.93045],"type":"Point"}
}