{
  "type": "Feature",
  "properties": {
    "addr:full":"508 W Broadway Glendale CA 91204",
    "addr:housenumber":"508",
    "addr:postcode":"91204",
    "addr:street":"W Broadway",
    "iso:country":"US",
    "sg:address":"508 W Broadway",
    "sg:city":"Glendale",
    "sg:classifiers":[
        {
            "category":"Food & Beverages",
            "subcategory":"Groceries & Convenience Stores",
            "type":"Retail Goods"
        }
    ],
    "sg:phone":"+1 818 243 3332",
    "sg:postcode":"91204",
    "sg:province":"CA",
    "wof:name":"Broadway Mart & Deli",
    "wof:placetype":"venue"
},
  "geometry": {"coordinates":[-118.26566,34.14672],"type":"Point"}
}