{
  "type": "Feature",
  "properties": {
    "iso:country":"US",
    "sg:address":"Cahalan Ave and Pearlwood Wy",
    "sg:city":"San Jose",
    "sg:classifiers":[
        {
            "category":"Park",
            "type":"Public Place"
        }
    ],
    "sg:postcode":"95123",
    "sg:province":"CA",
    "sg:website":"www.sjparks.org/neighborhood/cah...",
    "wof:name":"Cahalan Park",
    "wof:placetype":"venue"
},
  "geometry": {"coordinates":[-121.848522,37.245114],"type":"Point"}
}