{
  "type": "Feature",
  "properties": {
    "iso:country":"US",
    "sg:address":"400 Newport Center Drive Suite 302",
    "sg:city":"Newport Beach",
    "sg:classifiers":[
        {
            "category":"Health Services",
            "subcategory":"Doctor",
            "type":"Services"
        }
    ],
    "sg:phone":"+1 949 644 1240",
    "sg:postcode":"92660",
    "sg:province":"CA",
    "sg:website":"www.drgrazer.com",
    "wof:name":"Grazer Jon M MD Mph",
    "wof:placetype":"venue"
},
  "geometry": {"coordinates":[-117.87290400000001,33.613909],"type":"Point"}
}