{
  "type": "Feature",
  "properties": {
    "iso:country":"US",
    "sg:address":"4101 Birch St",
    "sg:city":"Newport Beach",
    "sg:classifiers":[
        {
            "category":"Professional",
            "subcategory":"Business Services",
            "type":"Services"
        }
    ],
    "sg:phone":"+1 949 261 6169",
    "sg:postcode":"92660",
    "sg:province":"CA",
    "sg:tags":[
        "auctioneer"
    ],
    "wof:name":"Ostrin & Ostrin Co",
    "wof:placetype":"venue"
},
  "geometry": {"coordinates":[-117.87008,33.66428],"type":"Point"}
}