{
  "type": "Feature",
  "properties": {
    "addr:full":"6418 1/2 Whittier Blvd Los Angeles CA 90022",
    "addr:housenumber":"6418 1 / 2",
    "addr:postcode":"90022",
    "addr:street":"Whittier Blvd",
    "iso:country":"US",
    "sg:address":"6418 1/2 Whittier Blvd",
    "sg:city":"Los Angeles",
    "sg:classifiers":[
        {
            "category":"Professional",
            "subcategory":"Lawyer & Legal Services",
            "type":"Services"
        }
    ],
    "sg:phone":"+1 323 722 8007",
    "sg:postcode":"90022",
    "sg:province":"CA",
    "wof:name":"Hochberg Bradley Law Offices of",
    "wof:placetype":"venue"
},
  "geometry": {"coordinates":[-118.13391900000001,34.015221],"type":"Point"}
}