{
  "type": "Feature",
  "properties": {
    "iso:country":"US",
    "sg:address":"1666 N Main St",
    "sg:city":"Salinas",
    "sg:classifiers":[
        {
            "category":"Shopping",
            "subcategory":"Clothing, Apparel, & Fashions",
            "type":"Retail Goods"
        }
    ],
    "sg:phone":"+1 831 442 2010",
    "sg:postcode":"93906",
    "sg:province":"CA",
    "sg:tags":[
        "wig",
        "toupee",
        "hairpiece"
    ],
    "wof:name":"Ciao Fashion Wig",
    "wof:placetype":"venue"
},
  "geometry": {"coordinates":[-121.6539,36.710489],"type":"Point"}
}