{
  "type": "Feature",
  "properties": {
    "iso:country":"US",
    "sg:address":"1423 The Alameda",
    "sg:city":"San Jose",
    "sg:classifiers":[
        {
            "category":"Restaurant",
            "type":"Food & Drink"
        }
    ],
    "sg:phone":"+1 408 947 7927",
    "sg:postcode":"95126",
    "sg:province":"CA",
    "sg:tags":[
        "thai"
    ],
    "wof:name":"Tee Nee Thai Cuisine",
    "wof:placetype":"venue"
},
  "geometry": {"coordinates":[-121.914106,37.333221],"type":"Point"}
}