{
  "type": "Feature",
  "properties": {
    "iso:country":"US",
    "sg:address":"316 E Tulare Ave",
    "sg:city":"Tulare",
    "sg:classifiers":[
        {
            "category":"Professional",
            "subcategory":"Business Services",
            "type":"Services"
        }
    ],
    "sg:phone":"+1 559 688 8577",
    "sg:postcode":"93274",
    "sg:province":"CA",
    "sg:tags":[
        "appraiser"
    ],
    "wof:name":"Tom Ariaz",
    "wof:placetype":"venue"
},
  "geometry": {"coordinates":[-119.34425899999999,36.208436],"type":"Point"}
}