{
  "type": "Feature",
  "properties": {
    "iso:country":"US",
    "sg:address":"551 N Cypress St",
    "sg:city":"La Habra",
    "sg:classifiers":[
        {
            "category":"Building & Trades",
            "subcategory":"Construction",
            "type":"Services"
        }
    ],
    "sg:phone":"+1 562 691 0018",
    "sg:postcode":"90631",
    "sg:province":"CA",
    "sg:tags":[
        "maker",
        "cabinet"
    ],
    "wof:name":"Interior Exterior Designs",
    "wof:placetype":"venue"
},
  "geometry": {"coordinates":[-117.941868,33.936769],"type":"Point"}
}