{
  "type": "Feature",
  "properties": {
    "addr:full":"1405 E Cypress Ave # 150 Reedley CA 93654",
    "addr:housenumber":"1405",
    "addr:postcode":"93654",
    "addr:street":"E Cypress Ave # 150",
    "iso:country":"US",
    "sg:address":"1405 E Cypress Ave # 150",
    "sg:city":"Reedley",
    "sg:classifiers":[
        {
            "category":"Real Estate",
            "subcategory":"Real Estate Operator",
            "type":"Services"
        }
    ],
    "sg:phone":"+1 559 637 1812",
    "sg:postcode":"93654",
    "sg:province":"CA",
    "sg:tags":[
        "apartment"
    ],
    "wof:name":"Cypress Estates Retirement Hm",
    "wof:placetype":"venue"
},
  "geometry": {"coordinates":[-119.434771,36.60775],"type":"Point"}
}