{
  "type": "Feature",
  "properties": {
    "addr:full":"2465 Ash St Vista CA 92081",
    "addr:housenumber":"2465",
    "addr:postcode":"92081",
    "addr:street":"Ash St",
    "iso:country":"US",
    "sg:address":"2465 Ash St",
    "sg:city":"Vista",
    "sg:classifiers":[
        {
            "category":"Food & Beverages",
            "subcategory":"Specialty",
            "type":"Retail Goods"
        }
    ],
    "sg:phone":"+1 858 513 1150",
    "sg:postcode":"92081",
    "sg:province":"CA",
    "sg:tags":[
        "health",
        "diet"
    ],
    "wof:name":"Global Health Trax",
    "wof:placetype":"venue"
},
  "geometry": {"coordinates":[-117.218294,33.150109],"type":"Point"}
}