{
  "type": "Feature",
  "properties": {
    "iso:country":"US",
    "sg:address":"3350 E 29th St",
    "sg:city":"Long Beach",
    "sg:classifiers":[
        {
            "category":"Professional",
            "subcategory":"Advertising",
            "type":"Services"
        }
    ],
    "sg:phone":"+1 562 424 3445",
    "sg:postcode":"90806",
    "sg:province":"CA",
    "wof:name":"North East Long Beach Advrtsng",
    "wof:placetype":"venue"
},
  "geometry": {"coordinates":[-118.158237,33.80915],"type":"Point"}
}