{
  "type": "Feature",
  "properties": {
    "iso:country":"US",
    "sg:address":"18307 Colima Rd",
    "sg:city":"Rowland Heights",
    "sg:classifiers":[
        {
            "category":"Restaurant",
            "type":"Food & Drink"
        }
    ],
    "sg:menulink":"http://www.allmenus.com/ca/east-san-gabriel-valley/238793-yoshinoya/menu/",
    "sg:phone":"+1 626 810 3764",
    "sg:postcode":"91748",
    "sg:province":"CA",
    "sg:tags":[
        "korean",
        "noodle",
        "bar",
        "japanese",
        "asian"
    ],
    "wof:name":"Yoshinoya",
    "wof:placetype":"venue"
},
  "geometry": {"coordinates":[-117.90530699999999,33.98867],"type":"Point"}
}