{
  "type": "Feature",
  "properties": {
    "iso:country":"US",
    "sg:address":"6916 Ben Ave",
    "sg:city":"North Hollywood",
    "sg:classifiers":[
        {
            "category":"Utilities",
            "subcategory":"Refuse",
            "type":"Services"
        }
    ],
    "sg:phone":"+1 818 383 7720",
    "sg:postcode":"91605",
    "sg:province":"CA",
    "sg:tags":[
        "garbage",
        "collection"
    ],
    "wof:name":"Jose Hauling & Clean Up",
    "wof:placetype":"venue"
},
  "geometry": {"coordinates":[-118.394233,34.197284],"type":"Point"}
}