{
  "type": "Feature",
  "properties": {
    "addr:full":"3340 Ptarmigan Dr Walnut Creek CA 94595",
    "addr:postcode":"3340;94595",
    "addr:street":"Ptarmigan Dr",
    "iso:country":"US",
    "sg:address":"3340 Ptarmigan Dr",
    "sg:city":"Walnut Creek",
    "sg:classifiers":[
        {
            "category":"Banks & Credit Unions",
            "subcategory":"Investment Brokerage",
            "type":"Services"
        }
    ],
    "sg:phone":"+1 925 932 2792",
    "sg:postcode":"94595",
    "sg:province":"CA",
    "sg:tags":[
        "consultant",
        "planning",
        "financial"
    ],
    "wof:name":"Laughlin Financial",
    "wof:placetype":"venue"
},
  "geometry": {"coordinates":[-122.07177900000001,37.856628],"type":"Point"}
}