{
  "type": "Feature",
  "properties": {
    "iso:country":"US",
    "sg:address":"4219 el Camino Real",
    "sg:city":"Palo Alto",
    "sg:classifiers":[
        {
            "category":"Personal",
            "subcategory":"Beauty Salon",
            "type":"Services"
        }
    ],
    "sg:phone":"+1 650 493 7772",
    "sg:postcode":"94306",
    "sg:province":"CA",
    "wof:name":"Lisa's Styling",
    "wof:placetype":"venue"
},
  "geometry": {"coordinates":[-122.12263,37.40944],"type":"Point"}
}