{
  "type": "Feature",
  "properties": {
    "addr:full":"330 Davis St Vacaville CA 95688",
    "addr:housenumber":"330",
    "addr:postcode":"95688",
    "addr:street":"Davis St",
    "iso:country":"US",
    "sg:address":"330 Davis St",
    "sg:city":"Vacaville",
    "sg:classifiers":[
        {
            "category":"Banks & Credit Unions",
            "subcategory":"Bank",
            "type":"Services"
        }
    ],
    "sg:phone":"+1 707 448 1100",
    "sg:postcode":"95688",
    "sg:province":"CA",
    "sg:website":"www.bankofthewest.com",
    "wof:name":"Bank Of The West",
    "wof:placetype":"venue"
},
  "geometry": {"coordinates":[-121.98647200000001,38.355166],"type":"Point"}
}