{
  "type": "Feature",
  "properties": {
    "iso:country":"US",
    "sg:address":"35 Marie St",
    "sg:city":"Sausalito",
    "sg:classifiers":[
        {
            "category":"Manufacturing",
            "subcategory":"Printing",
            "type":"Manufacturing & Wholesale Goods"
        }
    ],
    "sg:phone":"+1 415 332 1458",
    "sg:postcode":"94965",
    "sg:province":"CA",
    "sg:tags":[
        "publisher"
    ],
    "wof:name":"Post-Apollo Press",
    "wof:placetype":"venue"
},
  "geometry": {"coordinates":[-122.493837,37.8596],"type":"Point"}
}