{
  "type": "Feature",
  "properties": {
    "addr:full":"5748 Hollister Ave Goleta CA 93117",
    "addr:housenumber":"5748",
    "addr:postcode":"93117",
    "addr:street":"Hollister Ave",
    "iso:country":"US",
    "sg:address":"5748 Hollister Ave",
    "sg:city":"Goleta",
    "sg:classifiers":[
        {
            "category":"Building & Trades",
            "subcategory":"Plumbing",
            "type":"Services"
        }
    ],
    "sg:phone":"+1 805 964 1706",
    "sg:postcode":"93117",
    "sg:province":"CA",
    "sg:tags":[
        "plumbing",
        "contractor"
    ],
    "wof:name":"Oasis Plumbing Co",
    "wof:placetype":"venue"
},
  "geometry": {"coordinates":[-119.822948,34.43575],"type":"Point"}
}