{
  "type": "Feature",
  "properties": {
    "addr:full":"1430 Cutting Boulevard Richmond CA 94804",
    "addr:housenumber":"1430",
    "addr:postcode":"94804",
    "addr:street":"Cutting Boulevard",
    "iso:country":"US",
    "sg:address":"1430 Cutting Boulevard",
    "sg:city":"Richmond",
    "sg:classifiers":[
        {
            "category":"Food & Beverages",
            "subcategory":"Groceries & Convenience Stores",
            "type":"Retail Goods"
        }
    ],
    "sg:phone":"+1 510 231 0163",
    "sg:postcode":"94804",
    "sg:province":"CA",
    "wof:name":"Fiesta Latina",
    "wof:placetype":"venue"
},
  "geometry": {"coordinates":[-122.35516800000001,37.924745],"type":"Point"}
}