{
  "type": "Feature",
  "properties": {
    "iso:country":"US",
    "sg:address":"180 Newport Center Dr",
    "sg:city":"Newport Beach",
    "sg:classifiers":[
        {
            "category":"Real Estate",
            "subcategory":"Real Estate Agent",
            "type":"Services"
        }
    ],
    "sg:phone":"+1 949 720 8484",
    "sg:postcode":"92660",
    "sg:province":"CA",
    "sg:tags":[
        "consultant"
    ],
    "wof:name":"Pierpoint Advisors",
    "wof:placetype":"venue"
},
  "geometry": {"coordinates":[-117.878027,33.611746],"type":"Point"}
}