{
  "type": "Feature",
  "properties": {
    "iso:country":"US",
    "sg:address":"295 W 2nd St",
    "sg:city":"Pomona",
    "sg:classifiers":[
        {
            "category":"Shopping",
            "subcategory":"Clothing, Apparel, & Fashions",
            "type":"Retail Goods"
        }
    ],
    "sg:phone":"+1 909 865 0799",
    "sg:postcode":"91766",
    "sg:province":"CA",
    "wof:name":"Passion For Fashion",
    "wof:placetype":"venue"
},
  "geometry": {"coordinates":[-117.75145999999999,34.057886],"type":"Point"}
}