{
  "type": "Feature",
  "properties": {
    "iso:country":"US",
    "sg:address":"39300 State Highway 70",
    "sg:city":"Quincy",
    "sg:classifiers":[
        {
            "category":"Travel",
            "subcategory":"Hotels & Motels",
            "type":"Entertainment"
        }
    ],
    "sg:phone":"+1 530 283 1765",
    "sg:postcode":"95971",
    "sg:province":"CA",
    "wof:name":"Evergreen Motel & Trailer Park",
    "wof:placetype":"venue"
},
  "geometry": {"coordinates":[-120.941299,39.982487],"type":"Point"}
}