{
  "type": "Feature",
  "properties": {
    "iso:country":"US",
    "sg:address":"12551 Saticoy St",
    "sg:city":"North Hollywood",
    "sg:classifiers":[
        {
            "category":"Wholesale",
            "subcategory":"Chemicals & Plastics",
            "type":"Manufacturing & Wholesale Goods"
        }
    ],
    "sg:phone":"+1 818 255 3351",
    "sg:postcode":"91605",
    "sg:province":"CA",
    "wof:name":"Fine Ingredients",
    "wof:placetype":"venue"
},
  "geometry": {"coordinates":[-118.40570200000001,34.208538],"type":"Point"}
}