{
  "type": "Feature",
  "properties": {
    "addr:full":"1671 Lander Ave Turlock CA 95380",
    "addr:housenumber":"1671",
    "addr:postcode":"95380",
    "addr:street":"Lander Ave",
    "iso:country":"US",
    "sg:address":"1671 Lander Ave",
    "sg:city":"Turlock",
    "sg:classifiers":[
        {
            "category":"Personal",
            "subcategory":"Beauty Salon",
            "type":"Services"
        }
    ],
    "sg:phone":"+1 209 656 8859",
    "sg:postcode":"95380",
    "sg:province":"CA",
    "sg:tags":[
        "manicuring"
    ],
    "wof:name":"Cali Nails",
    "wof:placetype":"venue"
},
  "geometry": {"coordinates":[-120.849051,37.47749],"type":"Point"}
}