{
  "type": "Feature",
  "properties": {
    "iso:country":"US",
    "sg:address":"1260 N Holliston Ave",
    "sg:city":"Pasadena",
    "sg:classifiers":[
        {
            "category":"Food & Beverages",
            "subcategory":"Specialty",
            "type":"Retail Goods"
        }
    ],
    "sg:phone":"+1 626 797 5360",
    "sg:postcode":"91104",
    "sg:province":"CA",
    "sg:tags":[
        "health",
        "diet"
    ],
    "wof:name":"Biblehealth",
    "wof:placetype":"venue"
},
  "geometry": {"coordinates":[-118.122979,34.163071],"type":"Point"}
}