{
  "type": "Feature",
  "properties": {
    "iso:country":"US",
    "sg:address":"751 Raintree Dr",
    "sg:city":"Carlsbad",
    "sg:classifiers":[
        {
            "category":"Travel",
            "subcategory":"Hotels & Motels",
            "type":"Entertainment"
        }
    ],
    "sg:phone":"+1 760 931 1185",
    "sg:postcode":"92011",
    "sg:province":"CA",
    "sg:website":"www.choicehotels.com/ires/en-us/...",
    "wof:name":"Quality Inn & Suites Carlsbad State Beach & Legoland Area",
    "wof:placetype":"venue"
},
  "geometry": {"coordinates":[-117.31341500000001,33.104489],"type":"Point"}
}