{
  "type": "Feature",
  "properties": {
    "addr:full":"850 Branciforte Ave Santa Cruz CA 95060",
    "addr:housenumber":"850",
    "addr:postcode":"95060",
    "addr:street":"Branciforte Ave",
    "iso:country":"US",
    "sg:address":"850 Branciforte Ave",
    "sg:city":"Santa Cruz",
    "sg:classifiers":[
        {
            "category":"Professional",
            "subcategory":"Art Services",
            "type":"Services"
        }
    ],
    "sg:phone":"+1 408 431 8532",
    "sg:postcode":"95060",
    "sg:province":"CA",
    "sg:tags":[
        "photographer"
    ],
    "sg:website":"ccphoto.shutterfly.com",
    "wof:name":"Cake Consulting Photography",
    "wof:placetype":"venue"
},
  "geometry": {"coordinates":[-122.01406799999999,36.981213],"type":"Point"}
}