{
  "type": "Feature",
  "properties": {
    "iso:country":"US",
    "sg:address":"1601 N Gower St",
    "sg:city":"Los Angeles",
    "sg:classifiers":[
        {
            "category":"Health Services",
            "subcategory":"Clinic",
            "type":"Services"
        }
    ],
    "sg:phone":"+1 323 462 3939",
    "sg:postcode":"90028",
    "sg:province":"CA",
    "wof:name":"Hollywood Beauty Inst",
    "wof:placetype":"venue"
},
  "geometry": {"coordinates":[-118.322311,34.100437],"type":"Point"}
}