{
  "type": "Feature",
  "properties": {
    "addr:full":"928 S Western Ave #132 Los Angeles CA 90189",
    "addr:housenumber":"928",
    "addr:postcode":"90189",
    "addr:street":"S Western Ave # 132",
    "iso:country":"US",
    "sg:address":"928 S Western Ave #132",
    "sg:city":"Los Angeles",
    "sg:classifiers":[
        {
            "category":"Food & Beverages",
            "subcategory":"Candy",
            "type":"Retail Goods"
        },
        {
            "category":"Restaurant",
            "type":"Food & Drink"
        },
        {
            "category":"Fast Food",
            "type":"Food & Drink"
        }
    ],
    "sg:phone":"+1 213 738 5954",
    "sg:postcode":"90189",
    "sg:province":"CA",
    "sg:tags":[
        "dessert",
        "korean"
    ],
    "sg:website":"www.koreatownplaza.com",
    "wof:name":"Chicken and Boba",
    "wof:placetype":"venue"
},
  "geometry": {"coordinates":[-118.309066,34.054704],"type":"Point"}
}