{
  "type": "Feature",
  "properties": {
    "iso:country":"US",
    "sg:address":"1100 Lincoln Ave",
    "sg:city":"Napa",
    "sg:classifiers":[
        {
            "category":"Professional",
            "subcategory":"Employment Agencies",
            "type":"Services"
        }
    ],
    "sg:phone":"+1 707 224 9610",
    "sg:postcode":"94558",
    "sg:province":"CA",
    "wof:name":"Staffchex Inc.",
    "wof:placetype":"venue"
},
  "geometry": {"coordinates":[-122.294487,38.308609],"type":"Point"}
}