{
  "type": "Feature",
  "properties": {
    "addr:full":"500 N Gage Ave Los Angeles CA 90063",
    "addr:housenumber":"500",
    "addr:postcode":"90063",
    "addr:street":"N Gage Ave",
    "iso:country":"US",
    "sg:address":"500 N Gage Ave",
    "sg:city":"Los Angeles",
    "sg:classifiers":[
        {
            "category":"Food & Beverages",
            "subcategory":"Groceries & Convenience Stores",
            "type":"Retail Goods"
        }
    ],
    "sg:phone":"+1 323 263 6105",
    "sg:postcode":"90063",
    "sg:province":"CA",
    "sg:tags":[
        "grocer"
    ],
    "wof:name":"Jolly Market",
    "wof:placetype":"venue"
},
  "geometry": {"coordinates":[-118.184684,34.043683],"type":"Point"}
}