{
  "type": "Feature",
  "properties": {
    "addr:full":"18281 Gothard St Huntington Beach CA 92647",
    "addr:housenumber":"18281",
    "addr:postcode":"92647",
    "addr:street":"Gothard St",
    "iso:country":"US",
    "sg:address":"18281 Gothard St",
    "sg:city":"Huntington Beach",
    "sg:classifiers":[
        {
            "category":"Home & Garden",
            "subcategory":"Home Furnishings",
            "type":"Retail Goods"
        }
    ],
    "sg:phone":"+1 714 848 8884",
    "sg:postcode":"92647",
    "sg:province":"CA",
    "sg:tags":[
        "floor",
        "covering"
    ],
    "wof:name":"Sandys Design Center",
    "wof:placetype":"venue"
},
  "geometry": {"coordinates":[-117.999905,33.696957],"type":"Point"}
}