{
  "type": "Feature",
  "properties": {
    "addr:full":"2720 E Plaza Blvd Ste H National City CA 91950",
    "addr:housenumber":"2720",
    "addr:postcode":"91950",
    "addr:street":"E Plaza Blvd Ste H",
    "iso:country":"US",
    "sg:address":"2720 E Plaza Blvd Ste H",
    "sg:city":"National City",
    "sg:classifiers":[
        {
            "category":"Restaurant",
            "type":"Food & Drink"
        },
        {
            "category":"Bakery",
            "type":"Food & Drink"
        }
    ],
    "sg:phone":"+1 619 470 3742",
    "sg:postcode":"91950",
    "sg:province":"CA",
    "sg:tags":[
        "filipino"
    ],
    "wof:name":"Valerio's Family Bake Shop",
    "wof:placetype":"venue"
},
  "geometry": {"coordinates":[-117.07809399999999,32.680504],"type":"Point"}
}