{
  "type": "Feature",
  "properties": {
    "addr:full":"5304 Monterey Hwy San Jose CA 95111",
    "addr:housenumber":"5304",
    "addr:postcode":"95111",
    "addr:street":"Monterey Hwy",
    "iso:country":"US",
    "sg:address":"5304 Monterey Hwy",
    "sg:city":"San Jose",
    "sg:classifiers":[
        {
            "category":"Restaurant",
            "type":"Food & Drink"
        }
    ],
    "sg:phone":"+1 408 224 3243",
    "sg:postcode":"95111",
    "sg:province":"CA",
    "sg:tags":[
        "mexican"
    ],
    "wof:name":"Trines Cafe 6 & Pizza",
    "wof:placetype":"venue"
},
  "geometry": {"coordinates":[-121.80500000000001,37.257401],"type":"Point"}
}