{
  "type": "Feature",
  "properties": {
    "addr:full":"2734 Freedom Blvd Watsonville CA 95076",
    "addr:housenumber":"2734",
    "addr:postcode":"95076",
    "addr:street":"Freedom Blvd",
    "iso:country":"US",
    "sg:address":"2734 Freedom Blvd",
    "sg:city":"Watsonville",
    "sg:classifiers":[
        {
            "category":"Shopping",
            "subcategory":"Used Merchandise",
            "type":"Retail Goods"
        }
    ],
    "sg:phone":"+1 831 722 5810",
    "sg:postcode":"95076",
    "sg:province":"CA",
    "wof:name":"Chintzias Home & Garden",
    "wof:placetype":"venue"
},
  "geometry": {"coordinates":[-121.791946,36.948915],"type":"Point"}
}