{
  "type": "Feature",
  "properties": {
    "addr:full":"7979 Ivanhoe Ave Ste 400 La Jolla CA 92037",
    "addr:housenumber":"7979",
    "addr:postcode":"92037",
    "addr:street":"Ivanhoe Ave Ste 400",
    "iso:country":"US",
    "sg:address":"7979 Ivanhoe Ave Ste 400",
    "sg:city":"La Jolla",
    "sg:classifiers":[
        {
            "category":"Professional",
            "subcategory":"Lawyer & Legal Services",
            "type":"Services"
        }
    ],
    "sg:phone":"+1 858 459 7144",
    "sg:postcode":"92037",
    "sg:province":"CA",
    "wof:name":"Graze Lawrence",
    "wof:placetype":"venue"
},
  "geometry": {"coordinates":[-117.27235899999999,32.848658],"type":"Point"}
}