{
  "type": "Feature",
  "properties": {
    "addr:full":"1070 Linden Ave Carpinteria CA 93013",
    "addr:housenumber":"1070",
    "addr:postcode":"93013",
    "addr:street":"Linden Ave",
    "iso:country":"US",
    "sg:address":"1070 Linden Ave",
    "sg:city":"Carpinteria",
    "sg:classifiers":[
        {
            "category":"Manufacturing",
            "subcategory":"Tools & Machinery",
            "type":"Manufacturing & Wholesale Goods"
        }
    ],
    "sg:phone":"+1 805 684 6401",
    "sg:postcode":"93013",
    "sg:province":"CA",
    "sg:tags":[
        "mfg",
        "industrial",
        "general"
    ],
    "wof:name":"Andre Barclay",
    "wof:placetype":"venue"
},
  "geometry": {"coordinates":[-119.517904,34.399092],"type":"Point"}
}