{
  "type": "Feature",
  "properties": {
    "iso:country":"US",
    "sg:address":"572 E Foothill Blvd",
    "sg:city":"San Luis Obispo",
    "sg:classifiers":[
        {
            "category":"Real Estate",
            "subcategory":"Real Estate Operator",
            "type":"Services"
        }
    ],
    "sg:phone":"+1 805 543 5292",
    "sg:postcode":"93405",
    "sg:province":"CA",
    "sg:tags":[
        "apartment"
    ],
    "sg:website":"www.czechchalet.com",
    "wof:name":"Czech Chalet",
    "wof:placetype":"venue"
},
  "geometry": {"coordinates":[-120.67629700000001,35.294188],"type":"Point"}
}