{
  "type": "Feature",
  "properties": {
    "iso:country":"US",
    "sg:address":"2231 Cam del Rio S",
    "sg:city":"San Diego",
    "sg:classifiers":[
        {
            "category":"Health Services",
            "subcategory":"Health Practitioner",
            "type":"Services"
        }
    ],
    "sg:phone":"+1 619 281 5521",
    "sg:postcode":"92108",
    "sg:province":"CA",
    "wof:name":"Kathleen Durning PHD",
    "wof:placetype":"venue"
},
  "geometry": {"coordinates":[-117.150172,32.765855],"type":"Point"}
}