{
  "type": "Feature",
  "properties": {
    "iso:country":"US",
    "sg:address":"1101 Golden Springs Dr",
    "sg:city":"Diamond Bar",
    "sg:classifiers":[
        {
            "category":"Arts & Performance",
            "subcategory":"Theater",
            "type":"Entertainment"
        }
    ],
    "sg:phone":"+1 909 396 0505",
    "sg:postcode":"91765",
    "sg:province":"CA",
    "sg:tags":[
        "live",
        "music"
    ],
    "wof:name":"Select Sounds Mobile Disc",
    "wof:placetype":"venue"
},
  "geometry": {"coordinates":[-117.796235,34.035672],"type":"Point"}
}