{
  "type": "Feature",
  "properties": {
    "addr:full":"13872 Old el Camino Real San Diego CA 92130",
    "addr:housenumber":"13872",
    "addr:postcode":"92130",
    "addr:street":"Old El Camino Real",
    "iso:country":"US",
    "sg:address":"13872 Old el Camino Real",
    "sg:city":"San Diego",
    "sg:classifiers":[
        {
            "category":"Retail",
            "subcategory":"Animal Services",
            "type":"Services"
        }
    ],
    "sg:phone":"+1 858 350 5867",
    "sg:postcode":"92130",
    "sg:province":"CA",
    "wof:name":"Del Mar Hunters",
    "wof:placetype":"venue"
},
  "geometry": {"coordinates":[-117.23315100000001,32.965517],"type":"Point"}
}