{
  "type": "Feature",
  "properties": {
    "iso:country":"US",
    "sg:address":"7303 Pearblossom Hwy",
    "sg:city":"Littlerock",
    "sg:classifiers":[
        {
            "category":"Retail",
            "subcategory":"Auto Rental",
            "type":"Services"
        }
    ],
    "sg:phone":"+1 661 944 0280",
    "sg:postcode":"93543",
    "sg:province":"CA",
    "sg:tags":[
        "leasing",
        "tractor"
    ],
    "wof:name":"R Ferrer & Sons",
    "wof:placetype":"venue"
},
  "geometry": {"coordinates":[-118.001105,34.521107],"type":"Point"}
}