{
  "type": "Feature",
  "properties": {
    "iso:country":"US",
    "sg:address":"1146 Dorset Ln",
    "sg:city":"Costa Mesa",
    "sg:classifiers":[
        {
            "category":"Restaurant",
            "type":"Food & Drink"
        }
    ],
    "sg:phone":"+1 714 557 0706",
    "sg:postcode":"92626",
    "sg:province":"CA",
    "sg:tags":[
        "eating"
    ],
    "wof:name":"Alfis Cafe",
    "wof:placetype":"venue"
},
  "geometry": {"coordinates":[-117.90486300000001,33.681776],"type":"Point"}
}