{
  "type": "Feature",
  "properties": {
    "iso:country":"US",
    "sg:address":"8801 Lakewood Blvd",
    "sg:city":"Downey",
    "sg:classifiers":[
        {
            "category":"Coffee & Tea",
            "type":"Food & Drink"
        }
    ],
    "sg:phone":"+1 562 862 6326",
    "sg:postcode":"90240",
    "sg:province":"CA",
    "wof:name":"Starbucks",
    "wof:placetype":"venue"
},
  "geometry": {"coordinates":[-118.11020000000001,33.960962],"type":"Point"}
}