{
  "type": "Feature",
  "properties": {
    "iso:country":"US",
    "sg:address":"2401 W Turner Rd",
    "sg:city":"Lodi",
    "sg:classifiers":[
        {
            "category":"Insurance",
            "subcategory":"Insurance Agent",
            "type":"Services"
        }
    ],
    "sg:phone":"+1 209 365 0988",
    "sg:postcode":"95242",
    "sg:province":"CA",
    "wof:name":"State Farm Insurance",
    "wof:placetype":"venue"
},
  "geometry": {"coordinates":[-121.345507,38.145753],"type":"Point"}
}