{
  "type": "Feature",
  "properties": {
    "addr:full":"310 Capstan Ct Redwood City CA 94065",
    "addr:housenumber":"310",
    "addr:postcode":"94065",
    "addr:street":"Capstan Ct",
    "iso:country":"US",
    "sg:address":"310 Capstan Ct",
    "sg:city":"Redwood City",
    "sg:classifiers":[
        {
            "category":"Wholesale",
            "subcategory":"Machinery & Supplies",
            "type":"Manufacturing & Wholesale Goods"
        }
    ],
    "sg:phone":"+1 650 593 3820",
    "sg:postcode":"94065",
    "sg:province":"CA",
    "sg:tags":[
        "equipment",
        "establishment"
    ],
    "wof:name":"Amway Products",
    "wof:placetype":"venue"
},
  "geometry": {"coordinates":[-122.255869,37.526274],"type":"Point"}
}