{
  "type": "Feature",
  "properties": {
    "iso:country":"US",
    "sg:address":"8182 Florin Rd",
    "sg:city":"Sacramento",
    "sg:classifiers":[
        {
            "category":"Education",
            "subcategory":"Special Training",
            "type":"Public Place"
        }
    ],
    "sg:phone":"+1 916 381 3211",
    "sg:postcode":"95828",
    "sg:province":"CA",
    "sg:tags":[
        "instruction",
        "driving"
    ],
    "sg:website":"www.westpointdrivingschool.com",
    "wof:name":"West Point Driving & Traffic",
    "wof:placetype":"venue"
},
  "geometry": {"coordinates":[-121.407225,38.495968],"type":"Point"}
}