{
  "type": "Feature",
  "properties": {
    "iso:country":"US",
    "sg:address":"4359 Lennox Blvd",
    "sg:city":"Inglewood",
    "sg:classifiers":[
        {
            "category":"Education",
            "subcategory":"Library",
            "type":"Public Place"
        }
    ],
    "sg:phone":"+1 310 674 0385",
    "sg:postcode":"90304",
    "sg:province":"CA",
    "sg:tags":[
        "educational",
        "program",
        "administrative"
    ],
    "wof:name":"County Public Library",
    "wof:placetype":"venue"
},
  "geometry": {"coordinates":[-118.352182,33.938275],"type":"Point"}
}