{
  "type": "Feature",
  "properties": {
    "addr:full":"6236 Woodruff Ave Lakewood CA 90713",
    "addr:housenumber":"6236",
    "addr:postcode":"90713",
    "addr:street":"Woodruff Ave",
    "iso:country":"US",
    "sg:address":"6236 Woodruff Ave",
    "sg:city":"Lakewood",
    "sg:classifiers":[
        {
            "category":"Education",
            "subcategory":"Preschool",
            "type":"Public Place"
        },
        {
            "category":"Education",
            "subcategory":"School",
            "type":"Public Place"
        }
    ],
    "sg:phone":"+1 562 866 2918",
    "sg:postcode":"90713",
    "sg:province":"CA",
    "sg:tags":[
        "elementary"
    ],
    "wof:name":"Lakewood Christian Preschool",
    "wof:placetype":"venue"
},
  "geometry": {"coordinates":[-118.116997,33.868099],"type":"Point"}
}