{
  "type": "Feature",
  "properties": {
    "addr:full":"1538 Glendale Boulevard Los Angeles CA 90026",
    "addr:housenumber":"1538",
    "addr:postcode":"90026",
    "addr:street":"Glendale Boulevard",
    "iso:country":"US",
    "sg:address":"1538 Glendale Boulevard",
    "sg:city":"Los Angeles",
    "sg:classifiers":[
        {
            "category":"Restaurant",
            "type":"Food & Drink"
        }
    ],
    "sg:phone":"+1 213 989 0367",
    "sg:postcode":"90026",
    "sg:province":"CA",
    "sg:tags":[
        "mexican"
    ],
    "wof:name":"1Taco Mexico No 24",
    "wof:placetype":"venue"
},
  "geometry": {"coordinates":[-118.259782,34.082637],"type":"Point"}
}