{
  "type": "Feature",
  "properties": {
    "iso:country":"US",
    "sg:address":"25403 Redlands Blvd",
    "sg:city":"Loma Linda",
    "sg:classifiers":[
        {
            "category":"Food & Beverages",
            "subcategory":"Groceries & Convenience Stores",
            "type":"Retail Goods"
        }
    ],
    "sg:phone":"+1 909 799 9432",
    "sg:postcode":"92354",
    "sg:province":"CA",
    "wof:name":"C 2 Food Mart",
    "wof:placetype":"venue"
},
  "geometry": {"coordinates":[-117.24808,34.062983],"type":"Point"}
}