{
  "type": "Feature",
  "properties": {
    "iso:country":"US",
    "sg:address":"2299 Harbor Blvd",
    "sg:city":"Costa Mesa",
    "sg:classifiers":[
        {
            "category":"Retail",
            "subcategory":"Repair Shop",
            "type":"Services"
        }
    ],
    "sg:phone":"+1 949 645 7257",
    "sg:postcode":"92626",
    "sg:province":"CA",
    "sg:tags":[
        "appliance",
        "electrical"
    ],
    "sg:website":"www.palsvacuumsewingcenter.com/home",
    "wof:name":"Pal's Vacuum Sewing Centers",
    "wof:placetype":"venue"
},
  "geometry": {"coordinates":[-117.91921499999999,33.65797],"type":"Point"}
}