{
  "type": "Feature",
  "properties": {
    "iso:country":"US",
    "sg:address":"19 Western Ave",
    "sg:city":"Petaluma",
    "sg:classifiers":[
        {
            "category":"Bars & Pubs",
            "type":"Food & Drink"
        }
    ],
    "sg:phone":"+1 707 762 6647",
    "sg:postcode":"94952",
    "sg:province":"CA",
    "sg:tags":[
        "lounge",
        "cocktail"
    ],
    "wof:name":"Andresen's",
    "wof:placetype":"venue"
},
  "geometry": {"coordinates":[-122.642076,38.233447],"type":"Point"}
}