{
  "type": "Feature",
  "properties": {
    "addr:full":"570 Newhall St San Jose CA 95110",
    "addr:housenumber":"570",
    "addr:postcode":"95110",
    "addr:street":"Newhall St",
    "iso:country":"US",
    "sg:address":"570 Newhall St",
    "sg:city":"San Jose",
    "sg:classifiers":[
        {
            "category":"Local Transit",
            "type":"Transportation"
        }
    ],
    "sg:phone":"+1 408 885 1700",
    "sg:postcode":"95110",
    "sg:province":"CA",
    "sg:tags":[
        "limousine"
    ],
    "wof:name":"Champagne Limousine",
    "wof:placetype":"venue"
},
  "geometry": {"coordinates":[-121.920531,37.349169],"type":"Point"}
}