{
  "type": "Feature",
  "properties": {
    "addr:full":"2000 W Flotilla St Montebello CA 90640",
    "addr:housenumber":"2000",
    "addr:postcode":"90640",
    "addr:street":"W Flotilla St",
    "iso:country":"US",
    "sg:address":"2000 W Flotilla St",
    "sg:city":"Montebello",
    "sg:classifiers":[
        {
            "category":"Local Transit",
            "type":"Transportation"
        }
    ],
    "sg:phone":"+1 800 371 5465",
    "sg:postcode":"90640",
    "sg:province":"CA",
    "sg:tags":[
        "public"
    ],
    "sg:website":"www.metrolinktrains.com",
    "wof:name":"Montebello/Commerce Metrolink Station",
    "wof:placetype":"venue"
},
  "geometry": {"coordinates":[-118.127501,34.005444],"type":"Point"}
}