{
  "type": "Feature",
  "properties": {
    "addr:full":"1815 Monterey Rd. San Jose CA 95112",
    "addr:housenumber":"1815",
    "addr:postcode":"95112",
    "addr:street":"Monterey Rd.",
    "iso:country":"US",
    "sg:address":"1815 Monterey Rd.",
    "sg:city":"San Jose",
    "sg:classifiers":[
        {
            "category":"Home & Garden",
            "subcategory":"Garden Supply",
            "type":"Retail Goods"
        }
    ],
    "sg:phone":"+1 408 271 5000",
    "sg:postcode":"95112",
    "sg:province":"CA",
    "sg:tags":[
        "nursery",
        "gardening"
    ],
    "wof:name":"Fuji Garden Center",
    "wof:placetype":"venue"
},
  "geometry": {"coordinates":[-121.867299,37.309614],"type":"Point"}
}