{
  "type": "Feature",
  "properties": {
    "addr:full":"150 El Camino Real Ste A South San Francisco CA 94080",
    "addr:housenumber":"150",
    "addr:postcode":"94080",
    "addr:street":"El Camino Real Ste A",
    "iso:country":"US",
    "sg:address":"150 El Camino Real Ste A",
    "sg:city":"South San Francisco",
    "sg:classifiers":[
        {
            "category":"Banks & Credit Unions",
            "subcategory":"Bank",
            "type":"Services"
        }
    ],
    "sg:phone":"+1 650 363 1725",
    "sg:postcode":"94080",
    "sg:province":"CA",
    "wof:name":"San Mateo Credit Union",
    "wof:placetype":"venue"
},
  "geometry": {"coordinates":[-122.424004,37.6413],"type":"Point"}
}