{
  "type": "Feature",
  "properties": {
    "addr:full":"3501 Loma Vista Rd Ventura CA 93003",
    "addr:housenumber":"3501",
    "addr:postcode":"93003",
    "addr:street":"Loma Vista Rd",
    "iso:country":"US",
    "sg:address":"3501 Loma Vista Rd",
    "sg:city":"Ventura",
    "sg:classifiers":[
        {
            "category":"Place Of Worship",
            "type":"Public Place"
        }
    ],
    "sg:phone":"+1 805 643 5300",
    "sg:postcode":"93003",
    "sg:province":"CA",
    "sg:tags":[
        "church"
    ],
    "wof:name":"Mormon Church",
    "wof:placetype":"venue"
},
  "geometry": {"coordinates":[-119.24854999999999,34.276711],"type":"Point"}
}