{
  "type": "Feature",
  "properties": {
    "iso:country":"US",
    "sg:address":"3019 Champion St",
    "sg:city":"Oakland",
    "sg:classifiers":[
        {
            "category":"Building & Trades",
            "subcategory":"Construction",
            "type":"Services"
        }
    ],
    "sg:phone":"+1 415 271 4021",
    "sg:postcode":"94602",
    "sg:province":"CA",
    "sg:tags":[
        "contractor"
    ],
    "sg:website":"www.pacificstarconstruction.net",
    "wof:name":"Pacific Star Construction",
    "wof:placetype":"venue"
},
  "geometry": {"coordinates":[-122.21712599999999,37.794519],"type":"Point"}
}