{
  "type": "Feature",
  "properties": {
    "iso:country":"US",
    "sg:address":"449 S Beverly Dr",
    "sg:city":"Beverly Hills",
    "sg:classifiers":[
        {
            "category":"Travel",
            "subcategory":"Travel Agent",
            "type":"Entertainment"
        }
    ],
    "sg:phone":"+1 310 553 5555",
    "sg:postcode":"90212",
    "sg:province":"CA",
    "sg:tags":[
        "agency",
        "bureau"
    ],
    "wof:name":"Revel Travel Svc",
    "wof:placetype":"venue"
},
  "geometry": {"coordinates":[-118.397929,34.058787],"type":"Point"}
}