{
  "type": "Feature",
  "properties": {
    "addr:full":"3800 Vanowen St Burbank CA 91505",
    "addr:postcode":"3800;91505",
    "addr:street":"Vanowen St",
    "iso:country":"US",
    "sg:address":"3800 Vanowen St",
    "sg:city":"Burbank",
    "sg:classifiers":[
        {
            "category":"Professional",
            "type":"Services"
        }
    ],
    "sg:phone":"+1 818 295 6100",
    "sg:postcode":"91505",
    "sg:province":"CA",
    "sg:tags":[
        "establishment"
    ],
    "wof:name":"LA Graphico Inc",
    "wof:placetype":"venue"
},
  "geometry": {"coordinates":[-118.349091,34.191804],"type":"Point"}
}