{
  "type": "Feature",
  "properties": {
    "addr:full":"2195 del Mar Rd Norco CA 92860",
    "addr:housenumber":"2195",
    "addr:postcode":"92860",
    "addr:street":"Del Mar Rd",
    "iso:country":"US",
    "sg:address":"2195 del Mar Rd",
    "sg:city":"Norco",
    "sg:classifiers":[
        {
            "category":"Freight",
            "type":"Transportation"
        }
    ],
    "sg:phone":"+1 951 808 1212",
    "sg:postcode":"92860",
    "sg:province":"CA",
    "sg:tags":[
        "operator",
        "trucking"
    ],
    "wof:name":"Synergy Auto Transport",
    "wof:placetype":"venue"
},
  "geometry": {"coordinates":[-117.581407,33.912587],"type":"Point"}
}