{
  "type": "Feature",
  "properties": {
    "addr:full":"229 F St Ste A Chula Vista CA 91910",
    "addr:housenumber":"229",
    "addr:postcode":"91910",
    "addr:street":"F St Ste A",
    "iso:country":"US",
    "sg:address":"229 F St Ste A",
    "sg:city":"Chula Vista",
    "sg:classifiers":[
        {
            "category":"Professional",
            "subcategory":"Lawyer & Legal Services",
            "type":"Services"
        }
    ],
    "sg:phone":"+1 619 426 9000",
    "sg:postcode":"91910",
    "sg:province":"CA",
    "wof:name":"Wraith Saxon J Atty",
    "wof:placetype":"venue"
},
  "geometry": {"coordinates":[-117.08448199999999,32.639739],"type":"Point"}
}