{
  "type": "Feature",
  "properties": {
    "addr:full":"1243 12th St Los Osos CA 93402",
    "addr:housenumber":"1243",
    "addr:postcode":"93402",
    "addr:street":"12Th St",
    "iso:country":"US",
    "sg:address":"1243 12th St",
    "sg:city":"Los Osos",
    "sg:classifiers":[
        {
            "category":"Personal",
            "subcategory":"Beauty Salon",
            "type":"Services"
        }
    ],
    "sg:phone":"+1 805 528 2345",
    "sg:postcode":"93402",
    "sg:province":"CA",
    "wof:name":"Creative Styles",
    "wof:placetype":"venue"
},
  "geometry": {"coordinates":[-120.82995699999999,35.329153],"type":"Point"}
}