{
  "type": "Feature",
  "properties": {
    "iso:country":"US",
    "sg:address":"13547 Meganwood Pl",
    "sg:city":"La Mirada",
    "sg:classifiers":[
        {
            "category":"Professional",
            "subcategory":"Management & Consulting",
            "type":"Services"
        }
    ],
    "sg:phone":"+1 562 947 3038",
    "sg:postcode":"90638",
    "sg:province":"CA",
    "wof:name":"Progressive Automation Corp",
    "wof:placetype":"venue"
},
  "geometry": {"coordinates":[-117.98633700000001,33.906284],"type":"Point"}
}