{
  "type": "Feature",
  "properties": {
    "addr:full":"1907 Dartmouth Way Ofc Salinas CA 93906",
    "addr:housenumber":"1907",
    "addr:postcode":"93906",
    "addr:street":"Dartmouth Way",
    "iso:country":"US",
    "sg:address":"1907 Dartmouth Way Ofc",
    "sg:city":"Salinas",
    "sg:classifiers":[
        {
            "category":"Real Estate",
            "subcategory":"Real Estate Services",
            "type":"Services"
        },
        {
            "category":"Real Estate",
            "subcategory":"Real Estate Operator",
            "type":"Services"
        }
    ],
    "sg:phone":"+1 831 444 0102",
    "sg:postcode":"93906",
    "sg:province":"CA",
    "sg:tags":[
        "vacancy",
        "apartment",
        "rental",
        "listing"
    ],
    "wof:name":"Harden Ranch Apartments",
    "wof:placetype":"venue"
},
  "geometry": {"coordinates":[-121.64878299999999,36.717866],"type":"Point"}
}