{
  "type": "Feature",
  "properties": {
    "addr:full":"23 Orinda Way Orinda CA 94563",
    "addr:housenumber":"23",
    "addr:postcode":"94563",
    "addr:street":"Orinda Way",
    "iso:country":"US",
    "sg:address":"23 Orinda Way",
    "sg:city":"Orinda",
    "sg:classifiers":[
        {
            "category":"Retail",
            "subcategory":"Veterinary Services",
            "type":"Services"
        }
    ],
    "sg:phone":"+1 510 528 4900",
    "sg:postcode":"94563",
    "sg:province":"CA",
    "sg:tags":[
        "veterinarian"
    ],
    "wof:name":"Orinda Veterinary Dental Service",
    "wof:placetype":"venue"
},
  "geometry": {"coordinates":[-122.18800400000001,37.882],"type":"Point"}
}