{
  "type": "Feature",
  "properties": {
    "addr:full":"17130 Sequoia St Hesperia CA 92345",
    "addr:housenumber":"17130",
    "addr:postcode":"92345",
    "addr:street":"Sequoia St",
    "iso:country":"US",
    "sg:address":"17130 Sequoia St",
    "sg:city":"Hesperia",
    "sg:classifiers":[
        {
            "category":"Health Services",
            "subcategory":"Clinic",
            "type":"Services"
        }
    ],
    "sg:phone":"+1 760 947 4423",
    "sg:postcode":"92345",
    "sg:province":"CA",
    "sg:tags":[
        "alternative",
        "care"
    ],
    "wof:name":"In Roads",
    "wof:placetype":"venue"
},
  "geometry": {"coordinates":[-117.288657,34.469159],"type":"Point"}
}