{
  "type": "Feature",
  "properties": {
    "addr:full":"650 Poplar Ave South San Francisco CA 94080",
    "addr:housenumber":"650",
    "addr:postcode":"94080",
    "addr:street":"Poplar Ave",
    "iso:country":"US",
    "sg:address":"650 Poplar Ave",
    "sg:city":"South San Francisco",
    "sg:classifiers":[
        {
            "category":"Recreation",
            "type":"Entertainment"
        }
    ],
    "sg:postcode":"94080",
    "sg:province":"CA",
    "sg:tags":[
        "hiking"
    ],
    "wof:name":"Sign Hill Park",
    "wof:placetype":"venue"
},
  "geometry": {"coordinates":[-122.419673,37.661725],"type":"Point"}
}