{
  "type": "Feature",
  "properties": {
    "addr:full":"1650 Dominguez Ranch Rd Corona CA 92882",
    "addr:housenumber":"1650",
    "addr:postcode":"92882",
    "addr:street":"Dominguez Ranch Rd",
    "iso:country":"US",
    "sg:address":"1650 Dominguez Ranch Rd",
    "sg:city":"Corona",
    "sg:classifiers":[
        {
            "category":"Manufacturing",
            "subcategory":"Retail Goods",
            "type":"Manufacturing & Wholesale Goods"
        }
    ],
    "sg:phone":"+1 951 520 9665",
    "sg:postcode":"92882",
    "sg:province":"CA",
    "sg:tags":[
        "product",
        "mfg"
    ],
    "wof:name":"Nucer Steel",
    "wof:placetype":"venue"
},
  "geometry": {"coordinates":[-117.644087,33.872582],"type":"Point"}
}