{
  "type": "Feature",
  "properties": {
    "iso:country":"US",
    "sg:address":"835 W Elkhorn Blvd",
    "sg:city":"Rio Linda",
    "sg:classifiers":[
        {
            "category":"Wholesale",
            "subcategory":"Construction Materials",
            "type":"Manufacturing & Wholesale Goods"
        }
    ],
    "sg:phone":"+1 916 991 2210",
    "sg:postcode":"95673",
    "sg:province":"CA",
    "sg:tags":[
        "aggregate"
    ],
    "wof:name":"Glass Mtn Pumice Inc",
    "wof:placetype":"venue"
},
  "geometry": {"coordinates":[-121.472111,38.684151],"type":"Point"}
}