{
  "type": "Feature",
  "properties": {
    "iso:country":"US",
    "sg:address":"6146 Allbrook Cir",
    "sg:city":"Pleasanton",
    "sg:classifiers":[
        {
            "category":"Banks & Credit Unions",
            "subcategory":"Investment Brokerage",
            "type":"Services"
        }
    ],
    "sg:phone":"+1 925 600 8031",
    "sg:postcode":"94588",
    "sg:province":"CA",
    "wof:name":"Edward Jones Co",
    "wof:placetype":"venue"
},
  "geometry": {"coordinates":[-121.906223,37.690861],"type":"Point"}
}