{
  "type": "Feature",
  "properties": {
    "iso:country":"US",
    "sg:address":"11255 Woodruff Ave Unit C",
    "sg:city":"Downey",
    "sg:classifiers":[
        {
            "category":"Sports & Exercise",
            "subcategory":"Race Track",
            "type":"Entertainment"
        },
        {
            "category":"Home & Garden",
            "subcategory":"Kitchen Supply",
            "type":"Retail Goods"
        }
    ],
    "sg:phone":"+1 562 803 9484",
    "sg:postcode":"90241",
    "sg:province":"CA",
    "sg:tags":[
        "equipment",
        "restaurant"
    ],
    "wof:name":"Hampton Blowers",
    "wof:placetype":"venue"
},
  "geometry": {"coordinates":[-118.11673,33.930462],"type":"Point"}
}