{
  "type": "Feature",
  "properties": {
    "addr:full":"310 W Cutting Blvd Richmond CA 94804",
    "addr:housenumber":"310",
    "addr:postcode":"94804",
    "addr:street":"W Cutting Blvd",
    "iso:country":"US",
    "sg:address":"310 W Cutting Blvd",
    "sg:city":"Richmond",
    "sg:classifiers":[
        {
            "category":"Manufacturing",
            "subcategory":"Watercraft",
            "type":"Manufacturing & Wholesale Goods"
        }
    ],
    "sg:phone":"+1 510 237 0140",
    "sg:postcode":"94804",
    "sg:province":"CA",
    "sg:tags":[
        "repair",
        "trade",
        "contractor"
    ],
    "sg:website":"www.bay-ship.com",
    "wof:name":"Bay Ship & Yacht Co",
    "wof:placetype":"venue"
},
  "geometry": {"coordinates":[-122.36923299999999,37.925185],"type":"Point"}
}