{
  "type": "Feature",
  "properties": {
    "addr:full":"468 E 10th St Tracy CA 95376",
    "addr:housenumber":"468",
    "addr:postcode":"95376",
    "addr:street":"E 10Th St",
    "iso:country":"US",
    "sg:address":"468 E 10th St",
    "sg:city":"Tracy",
    "sg:classifiers":[
        {
            "category":"Retail",
            "subcategory":"Auto Repair",
            "type":"Services"
        }
    ],
    "sg:phone":"+1 209 836 3223",
    "sg:postcode":"95376",
    "sg:province":"CA",
    "sg:tags":[
        "body",
        "repairing",
        "customizing",
        "painting",
        "automobile"
    ],
    "sg:website":"http://www.aandrautobodyshop.com",
    "wof:name":"A & R Auto Body Collision And Paint",
    "wof:placetype":"venue"
},
  "geometry": {"coordinates":[-121.418176,37.738312],"type":"Point"}
}