{
  "type": "Feature",
  "properties": {
    "iso:country":"US",
    "sg:address":"28005 Smyth Dr",
    "sg:city":"Valencia",
    "sg:classifiers":[
        {
            "category":"Health Services",
            "subcategory":"Hospital",
            "type":"Services"
        }
    ],
    "sg:phone":"+1 661 295 4633",
    "sg:postcode":"91355",
    "sg:province":"CA",
    "wof:name":"Scientific Hospital Supplies",
    "wof:placetype":"venue"
},
  "geometry": {"coordinates":[-118.57166100000001,34.443013],"type":"Point"}
}