{
  "type": "Feature",
  "properties": {
    "addr:full":"2349 N Watney Way Fairfield CA 94533",
    "addr:housenumber":"2349",
    "addr:postcode":"94533",
    "addr:street":"N Watney Way",
    "iso:country":"US",
    "sg:address":"2349 N Watney Way",
    "sg:city":"Fairfield",
    "sg:classifiers":[
        {
            "category":"Professional",
            "subcategory":"Management & Consulting",
            "type":"Services"
        }
    ],
    "sg:phone":"+1 707 423 4240",
    "sg:postcode":"94533",
    "sg:province":"CA",
    "sg:tags":[
        "job"
    ],
    "wof:name":"P P G Regional Training Center",
    "wof:placetype":"venue"
},
  "geometry": {"coordinates":[-122.073517,38.238469],"type":"Point"}
}