{
  "type": "Feature",
  "properties": {
    "addr:full":"630 San Antonio Rd Mountain View CA 94040",
    "addr:housenumber":"630",
    "addr:postcode":"94040",
    "addr:street":"San Antonio Rd",
    "iso:country":"US",
    "sg:address":"630 San Antonio Rd",
    "sg:city":"Mountain View",
    "sg:classifiers":[
        {
            "category":"Shopping",
            "subcategory":"Books",
            "type":"Retail Goods"
        }
    ],
    "sg:phone":"+1 650 941 7900",
    "sg:postcode":"94040",
    "sg:province":"CA",
    "sg:tags":[
        "dealer"
    ],
    "wof:name":"Tower Records/Video/Books",
    "wof:placetype":"venue"
},
  "geometry": {"coordinates":[-122.11344,37.40127],"type":"Point"}
}