{
  "type": "Feature",
  "properties": {
    "addr:full":"2102 E Cesar E Chavez Ave Los Angeles CA 90033",
    "addr:housenumber":"2102",
    "addr:postcode":"90033",
    "addr:street":"E Cesar E Chavez Ave",
    "iso:country":"US",
    "sg:address":"2102 E Cesar E Chavez Ave",
    "sg:city":"Los Angeles",
    "sg:classifiers":[
        {
            "category":"Banks & Credit Unions",
            "subcategory":"Bank",
            "type":"Services"
        }
    ],
    "sg:phone":"+1 323 264 0749",
    "sg:postcode":"90033",
    "sg:province":"CA",
    "sg:tags":[
        "money",
        "order"
    ],
    "wof:name":"Montoya Acosta Corp",
    "wof:placetype":"venue"
},
  "geometry": {"coordinates":[-118.210705,34.048031],"type":"Point"}
}