{
  "type": "Feature",
  "properties": {
    "iso:country":"US",
    "sg:address":"1331 1st St",
    "sg:city":"Napa",
    "sg:classifiers":[
        {
            "category":"Shopping",
            "subcategory":"Clothing, Apparel, & Fashions",
            "type":"Retail Goods"
        }
    ],
    "sg:phone":"+1 707 255 5617",
    "sg:postcode":"94559",
    "sg:province":"CA",
    "wof:name":"Talbots",
    "wof:placetype":"venue"
},
  "geometry": {"coordinates":[-122.28823,38.297735],"type":"Point"}
}