{
  "type": "Feature",
  "properties": {
    "addr:full":"5523 E Slauson Ave Los Angeles CA 90040",
    "addr:housenumber":"5523",
    "addr:postcode":"90040",
    "addr:street":"E Slauson Ave",
    "iso:country":"US",
    "sg:address":"5523 E Slauson Ave",
    "sg:city":"Los Angeles",
    "sg:classifiers":[
        {
            "category":"Wholesale",
            "subcategory":"Apparel",
            "type":"Manufacturing & Wholesale Goods"
        }
    ],
    "sg:phone":"+1 323 728 3366",
    "sg:postcode":"90040",
    "sg:province":"CA",
    "sg:tags":[
        "clothing"
    ],
    "wof:name":"J C Clothing Inc",
    "wof:placetype":"venue"
},
  "geometry": {"coordinates":[-118.162828,33.986081],"type":"Point"}
}