{
  "type": "Feature",
  "properties": {
    "iso:country":"US",
    "sg:address":"6247 Royal Oak Ct",
    "sg:city":"San Jose",
    "sg:classifiers":[
        {
            "category":"Professional",
            "type":"Services"
        }
    ],
    "sg:phone":"+1 408 224 4524",
    "sg:postcode":"95123",
    "sg:province":"CA",
    "wof:name":"Galex Research",
    "wof:placetype":"venue"
},
  "geometry": {"coordinates":[-121.816709,37.232164],"type":"Point"}
}