{
  "type": "Feature",
  "properties": {
    "iso:country":"US",
    "sg:address":"550 E Latham Ave Ste 2",
    "sg:city":"Hemet",
    "sg:classifiers":[
        {
            "category":"Health Services",
            "subcategory":"Doctor",
            "type":"Services"
        },
        {
            "category":"Health Services",
            "subcategory":"Dentist",
            "type":"Services"
        }
    ],
    "sg:phone":"+1 951 929 8863",
    "sg:postcode":"92543",
    "sg:province":"CA",
    "sg:tags":[
        "dentists-oral",
        "physician",
        "maxillofacial",
        "surgeons",
        "surgery",
        "oral"
    ],
    "wof:name":"Byron L Carr Dmd And Ronald E Duffin D",
    "wof:placetype":"venue"
},
  "geometry": {"coordinates":[-116.966786,33.749371],"type":"Point"}
}