{
  "type": "Feature",
  "properties": {
    "iso:country":"US",
    "sg:address":"300 Orchard City Drive",
    "sg:city":"Campbell",
    "sg:classifiers":[
        {
            "category":"Utilities",
            "type":"Services"
        }
    ],
    "sg:phone":"+1 408 370 3727",
    "sg:postcode":"95008",
    "sg:province":"CA",
    "sg:tags":[
        "provider",
        "internet"
    ],
    "sg:website":"www.wisair.com",
    "wof:name":"Wisair.",
    "wof:placetype":"venue"
},
  "geometry": {"coordinates":[-121.944845,37.286205],"type":"Point"}
}