{
  "type": "Feature",
  "properties": {
    "iso:country":"US",
    "sg:address":"22350 Foresthill Rd",
    "sg:city":"Foresthill",
    "sg:classifiers":[
        {
            "category":"Transit Center",
            "subcategory":"Freight",
            "type":"Transportation"
        },
        {
            "category":"Freight",
            "type":"Transportation"
        }
    ],
    "sg:phone":"+1 530 367 3957",
    "sg:postcode":"95631",
    "sg:province":"CA",
    "sg:tags":[
        "local",
        "trucking-motor",
        "trucking"
    ],
    "wof:name":"Jon Yourd Trucking",
    "wof:placetype":"venue"
},
  "geometry": {"coordinates":[-120.854141,39.007191],"type":"Point"}
}