{
  "type": "Feature",
  "properties": {
    "iso:country":"US",
    "sg:address":"220 Lorton Ave",
    "sg:city":"Burlingame",
    "sg:classifiers":[
        {
            "category":"Bars & Pubs",
            "type":"Food & Drink"
        }
    ],
    "sg:phone":"+1 650 342 8998",
    "sg:postcode":"94012",
    "sg:province":"CA",
    "wof:name":"The Alibi",
    "wof:placetype":"venue"
},
  "geometry": {"coordinates":[-122.34493999999999,37.578312],"type":"Point"}
}