{
  "type": "Feature",
  "properties": {
    "addr:full":"455 Cleveland Ave Petaluma CA 94952",
    "addr:housenumber":"455",
    "addr:postcode":"94952",
    "addr:street":"Cleveland Ave",
    "iso:country":"US",
    "sg:address":"455 Cleveland Ave",
    "sg:city":"Petaluma",
    "sg:classifiers":[
        {
            "category":"Wholesale",
            "subcategory":"Medical Equipment & Supplies",
            "type":"Manufacturing & Wholesale Goods"
        }
    ],
    "sg:phone":"+1 707 547 1740",
    "sg:postcode":"94952",
    "sg:province":"CA",
    "sg:tags":[
        "physician",
        "surgeon"
    ],
    "sg:website":"www.cardiolineusa.com",
    "wof:name":"Cardioline USA Inc",
    "wof:placetype":"venue"
},
  "geometry": {"coordinates":[-122.668319,38.230918],"type":"Point"}
}