{
  "type": "Feature",
  "properties": {
    "addr:full":"1840 W 220th St Ste 300 Torrance CA 90501",
    "addr:housenumber":"1840",
    "addr:postcode":"90501",
    "addr:street":"W 220Th St Ste 300",
    "iso:country":"US",
    "sg:address":"1840 W 220th St Ste 300",
    "sg:city":"Torrance",
    "sg:classifiers":[
        {
            "category":"Building & Trades",
            "subcategory":"Cleaning & Sanitation",
            "type":"Services"
        }
    ],
    "sg:phone":"+1 310 618 1422",
    "sg:postcode":"90501",
    "sg:province":"CA",
    "sg:tags":[
        "janitorial"
    ],
    "wof:name":"Unlimited Commercial",
    "wof:placetype":"venue"
},
  "geometry": {"coordinates":[-118.312845,33.827898],"type":"Point"}
}