{
  "type": "Feature",
  "properties": {
    "addr:full":"780 McDonnell Rd San Francisco CA 94128",
    "addr:housenumber":"780",
    "addr:postcode":"94128",
    "addr:street":"Mcdonnell Rd",
    "iso:country":"US",
    "sg:address":"780 McDonnell Rd",
    "sg:city":"San Francisco",
    "sg:classifiers":[
        {
            "category":"Retail",
            "subcategory":"Auto Rental",
            "type":"Services"
        }
    ],
    "sg:phone":"+1 650 697 9200",
    "sg:postcode":"94128",
    "sg:province":"CA",
    "sg:tags":[
        "car"
    ],
    "wof:name":"Enterprise Rent-A-Car",
    "wof:placetype":"venue"
},
  "geometry": {"coordinates":[-122.400087,37.629349],"type":"Point"}
}