{
  "type": "Feature",
  "properties": {
    "iso:country":"US",
    "sg:address":"459 Shannon Dr",
    "sg:city":"Vacaville",
    "sg:classifiers":[
        {
            "category":"Building & Trades",
            "subcategory":"Construction",
            "type":"Services"
        }
    ],
    "sg:phone":"+1 707 448 3342",
    "sg:postcode":"95688",
    "sg:province":"CA",
    "sg:tags":[
        "excavation",
        "excavating",
        "contractor"
    ],
    "wof:name":"Sells Ray Grading & Backhoe",
    "wof:placetype":"venue"
},
  "geometry": {"coordinates":[-121.97374499999999,38.380864],"type":"Point"}
}