{
  "type": "Feature",
  "properties": {
    "iso:country":"US",
    "sg:address":"13925 Yale Avenue",
    "sg:city":"Irvine",
    "sg:classifiers":[
        {
            "category":"Retail",
            "subcategory":"Veterinary Services",
            "type":"Services"
        },
        {
            "category":"Retail",
            "subcategory":"Pet Boarding",
            "type":"Services"
        }
    ],
    "sg:phone":"+1 949 559 1992",
    "sg:postcode":"92620",
    "sg:province":"CA",
    "sg:tags":[
        "veterinarian",
        "boarding/pet",
        "sitting"
    ],
    "sg:website":"www.northwoodanimal.com",
    "wof:name":"Pursley Jennifer DVM",
    "wof:placetype":"venue"
},
  "geometry": {"coordinates":[-117.77249999999999,33.704014],"type":"Point"}
}