{
  "type": "Feature",
  "properties": {
    "addr:full":"758 S Mollison Ave Apt 1 El Cajon CA 92020",
    "addr:housenumber":"758",
    "addr:postcode":"92020",
    "addr:street":"S Mollison Ave Apt 1",
    "iso:country":"US",
    "sg:address":"758 S Mollison Ave Apt 1",
    "sg:city":"El Cajon",
    "sg:classifiers":[
        {
            "category":"Real Estate",
            "subcategory":"Real Estate Operator",
            "type":"Services"
        }
    ],
    "sg:phone":"+1 619 444 9968",
    "sg:postcode":"92020",
    "sg:province":"CA",
    "sg:tags":[
        "apartment"
    ],
    "wof:name":"Mollison Villas West",
    "wof:placetype":"venue"
},
  "geometry": {"coordinates":[-116.950996,32.786598],"type":"Point"}
}