{
  "type": "Feature",
  "properties": {
    "iso:country":"US",
    "sg:address":"861 W Harbor Dr",
    "sg:city":"San Diego",
    "sg:classifiers":[
        {
            "category":"Bars & Pubs",
            "type":"Food & Drink"
        },
        {
            "category":"Restaurant",
            "type":"Food & Drink"
        }
    ],
    "sg:phone":"+1 619 232 7581",
    "sg:postcode":"92101",
    "sg:province":"CA",
    "sg:tags":[
        "seafood"
    ],
    "wof:name":"Edgewater Grill",
    "wof:placetype":"venue"
},
  "geometry": {"coordinates":[-117.171296,32.708708],"type":"Point"}
}