{
  "type": "Feature",
  "properties": {
    "iso:country":"US",
    "sg:address":"1081 Market Pl",
    "sg:city":"San Ramon",
    "sg:classifiers":[
        {
            "category":"Health Services",
            "subcategory":"Doctor",
            "type":"Services"
        }
    ],
    "sg:phone":"+1 925 275 0404",
    "sg:postcode":"94583",
    "sg:province":"CA",
    "sg:tags":[
        "physician",
        "surgeon"
    ],
    "wof:name":"Suresh K Sachdeva MD",
    "wof:placetype":"venue"
},
  "geometry": {"coordinates":[-121.95286,37.763446],"type":"Point"}
}