{
  "type": "Feature",
  "properties": {
    "addr:full":"350 S Figueroa St Los Angeles CA 90071",
    "addr:housenumber":"350",
    "addr:postcode":"90071",
    "addr:street":"S Figueroa St",
    "iso:country":"US",
    "sg:address":"350 S Figueroa St",
    "sg:city":"Los Angeles",
    "sg:classifiers":[
        {
            "category":"Government",
            "subcategory":"Office",
            "type":"Public Place"
        },
        {
            "category":"Wholesale",
            "subcategory":"Durable Goods & Equipment",
            "type":"Manufacturing & Wholesale Goods"
        }
    ],
    "sg:phone":"+1 213 617 1461",
    "sg:postcode":"90071",
    "sg:province":"CA",
    "sg:tags":[
        "commission",
        "exporter",
        "trade"
    ],
    "wof:name":"Guanajuato Trade Office- Los A",
    "wof:placetype":"venue"
},
  "geometry": {"coordinates":[-118.25522599999999,34.054327],"type":"Point"}
}