{
  "type": "Feature",
  "properties": {
    "iso:country":"US",
    "sg:address":"3490 Sacramento Dr",
    "sg:city":"San Luis Obispo",
    "sg:classifiers":[
        {
            "category":"Utilities",
            "subcategory":"Telephone",
            "type":"Services"
        }
    ],
    "sg:phone":"+1 805 549 7811",
    "sg:postcode":"93401",
    "sg:province":"CA",
    "sg:tags":[
        "company"
    ],
    "wof:name":"MCI",
    "wof:placetype":"venue"
},
  "geometry": {"coordinates":[-120.64513100000001,35.257602],"type":"Point"}
}