{
  "type": "Feature",
  "properties": {
    "addr:full":"2100 Sanguinetti Ln Stockton CA 95205",
    "addr:housenumber":"2100",
    "addr:postcode":"95205",
    "addr:street":"Sanguinetti Ln",
    "iso:country":"US",
    "sg:address":"2100 Sanguinetti Ln",
    "sg:city":"Stockton",
    "sg:classifiers":[
        {
            "category":"Professional",
            "subcategory":"Advertising",
            "type":"Services"
        },
        {
            "category":"Manufacturing",
            "subcategory":"Signs",
            "type":"Manufacturing & Wholesale Goods"
        }
    ],
    "sg:phone":"+1 209 948 1713",
    "sg:postcode":"95205",
    "sg:province":"CA",
    "sg:tags":[
        "specialty"
    ],
    "sg:website":"http://www.deltasigns.net",
    "wof:name":"Delta Signs",
    "wof:placetype":"venue"
},
  "geometry": {"coordinates":[-121.269379,37.978588],"type":"Point"}
}