{
  "type": "Feature",
  "properties": {
    "addr:full":"8788 Balboa Ave San Diego CA 92117",
    "addr:housenumber":"8788",
    "addr:postcode":"92117",
    "addr:street":"Balboa Ave",
    "iso:country":"US",
    "sg:address":"8788 Balboa Ave",
    "sg:city":"San Diego",
    "sg:classifiers":[
        {
            "category":"Professional",
            "subcategory":"Testing Lab",
            "type":"Services"
        }
    ],
    "sg:phone":"+1 619 583 6633",
    "sg:postcode":"92117",
    "sg:province":"CA",
    "sg:tags":[
        "laboratory"
    ],
    "sg:website":"www.gforceca.com",
    "wof:name":"G Force",
    "wof:placetype":"venue"
},
  "geometry": {"coordinates":[-117.13424500000001,32.822111],"type":"Point"}
}