{
  "type": "Feature",
  "properties": {
    "iso:country":"US",
    "sg:address":"8788 Balboa Ave",
    "sg:city":"San Diego",
    "sg:classifiers":[
        {
            "category":"Professional",
            "subcategory":"Testing Lab",
            "type":"Services"
        }
    ],
    "sg:phone":"+1 619 583 6633",
    "sg:postcode":"92117",
    "sg:province":"CA",
    "sg:tags":[
        "laboratory"
    ],
    "sg:website":"www.gforceca.com",
    "wof:name":"G Force",
    "wof:placetype":"venue"
},
  "geometry": {"coordinates":[-117.134245,32.822111],"type":"Point"}
}