{
  "type": "Feature",
  "properties": {
    "iso:country":"US",
    "sg:address":"1614 Bonita Ave",
    "sg:city":"Berkeley",
    "sg:classifiers":[
        {
            "category":"Manufacturing",
            "subcategory":"Soap",
            "type":"Manufacturing & Wholesale Goods"
        }
    ],
    "sg:phone":"+1 510 848 4412",
    "sg:postcode":"94709",
    "sg:province":"CA",
    "sg:tags":[
        "perfume-wholesale",
        "manufacturer"
    ],
    "wof:name":"Parfum Phyto",
    "wof:placetype":"venue"
},
  "geometry": {"coordinates":[-122.272509,37.877719],"type":"Point"}
}