{
  "type": "Feature",
  "properties": {
    "iso:country":"US",
    "sg:address":"8052 Limonite Ave",
    "sg:city":"Riverside",
    "sg:classifiers":[
        {
            "category":"Shopping",
            "subcategory":"Clothing, Apparel, & Fashions",
            "type":"Retail Goods"
        }
    ],
    "sg:phone":"+1 951 360 6490",
    "sg:postcode":"92509",
    "sg:province":"CA",
    "wof:name":"Backyard Boogie",
    "wof:placetype":"venue"
},
  "geometry": {"coordinates":[-117.465577,33.976037],"type":"Point"}
}