{
  "type": "Feature",
  "properties": {
    "addr:full":"137 E Hamilton Ave Campbell CA 95008",
    "addr:housenumber":"137",
    "addr:postcode":"95008",
    "addr:street":"E Hamilton Ave",
    "iso:country":"US",
    "sg:address":"137 E Hamilton Ave",
    "sg:city":"Campbell",
    "sg:classifiers":[
        {
            "category":"Health Services",
            "subcategory":"Health Practitioner",
            "type":"Services"
        }
    ],
    "sg:phone":"+1 408 370 3431",
    "sg:postcode":"95008",
    "sg:province":"CA",
    "sg:tags":[
        "psychologist"
    ],
    "wof:name":"Debra Mendlowitz PHD",
    "wof:placetype":"venue"
},
  "geometry": {"coordinates":[-121.947818,37.294239],"type":"Point"}
}