{
  "type": "Feature",
  "properties": {
    "iso:country":"US",
    "sg:address":"7115 Watt Ave",
    "sg:city":"North Highlands",
    "sg:classifiers":[
        {
            "category":"Home & Garden",
            "subcategory":"Hardware",
            "type":"Retail Goods"
        }
    ],
    "sg:phone":"+1 916 331 1228",
    "sg:postcode":"95660",
    "sg:province":"CA",
    "sg:tags":[
        "store"
    ],
    "wof:name":"Supply Hardware",
    "wof:placetype":"venue"
},
  "geometry": {"coordinates":[-121.384073,38.696186],"type":"Point"}
}