{
  "type": "Feature",
  "properties": {
    "iso:country":"US",
    "sg:address":"10789 Tierrasanta Blvd",
    "sg:city":"San Diego",
    "sg:classifiers":[
        {
            "category":"Health Services",
            "subcategory":"Doctor",
            "type":"Services"
        }
    ],
    "sg:phone":"+1 858 565 0212",
    "sg:postcode":"92124",
    "sg:province":"CA",
    "sg:tags":[
        "dentist"
    ],
    "wof:name":"Lillan R Liberto DDS",
    "wof:placetype":"venue"
},
  "geometry": {"coordinates":[-117.09964100000001,32.822531],"type":"Point"}
}