{
  "type": "Feature",
  "properties": {
    "addr:full":"2630 San Gabriel Blvd #200 Rosemead CA 91770",
    "addr:housenumber":"2630",
    "addr:postcode":"91770",
    "addr:street":"San Gabriel Blvd # 200",
    "iso:country":"US",
    "sg:address":"2630 San Gabriel Blvd #200",
    "sg:city":"Rosemead",
    "sg:classifiers":[
        {
            "category":"Health Services",
            "subcategory":"Doctor",
            "type":"Services"
        },
        {
            "category":"Health Services",
            "subcategory":"Chiropractor",
            "type":"Services"
        }
    ],
    "sg:phone":"+1 626 280 9968",
    "sg:postcode":"91770",
    "sg:province":"CA",
    "wof:name":"Bo K. Luk, DC",
    "wof:placetype":"venue"
},
  "geometry": {"coordinates":[-118.089924,34.059971],"type":"Point"}
}