{
  "type": "Feature",
  "properties": {
    "iso:country":"US",
    "sg:address":"1022 San Fernando Rd",
    "sg:city":"San Fernando",
    "sg:classifiers":[
        {
            "category":"Banks & Credit Unions",
            "subcategory":"Bank",
            "type":"Services"
        }
    ],
    "sg:phone":"+1 818 365 9015",
    "sg:postcode":"91340",
    "sg:province":"CA",
    "wof:name":"HSBC",
    "wof:placetype":"venue"
},
  "geometry": {"coordinates":[-118.44077799999999,34.282129],"type":"Point"}
}