{
  "type": "Feature",
  "properties": {
    "addr:full":"1149 E Champlain Dr Fresno CA 93720",
    "addr:housenumber":"1149",
    "addr:postcode":"93720",
    "addr:street":"E Champlain Dr",
    "iso:country":"US",
    "sg:address":"1149 E Champlain Dr",
    "sg:city":"Fresno",
    "sg:classifiers":[
        {
            "category":"Home & Garden",
            "subcategory":"Furniture",
            "type":"Retail Goods"
        }
    ],
    "sg:phone":"+1 559 434 1303",
    "sg:postcode":"93720",
    "sg:province":"CA",
    "wof:name":"Park Avenue West",
    "wof:placetype":"venue"
},
  "geometry": {"coordinates":[-119.761483,36.870617],"type":"Point"}
}