{
  "type": "Feature",
  "properties": {
    "addr:full":"325 N 18th St Montebello CA 90640",
    "addr:housenumber":"325",
    "addr:postcode":"90640",
    "addr:street":"N 18Th St",
    "iso:country":"US",
    "sg:address":"325 N 18th St",
    "sg:city":"Montebello",
    "sg:classifiers":[
        {
            "category":"Banks & Credit Unions",
            "subcategory":"Bank",
            "type":"Services"
        }
    ],
    "sg:phone":"+1 323 726 1206",
    "sg:postcode":"90640",
    "sg:province":"CA",
    "sg:tags":[
        "loan"
    ],
    "wof:name":"American Capital",
    "wof:placetype":"venue"
},
  "geometry": {"coordinates":[-118.118847,34.017577],"type":"Point"}
}