{
  "type": "Feature",
  "properties": {
    "addr:full":"599 E McGlincey Ln Campbell CA 95008",
    "addr:housenumber":"599",
    "addr:postcode":"95008",
    "addr:street":"E Mcglincey Ln",
    "iso:country":"US",
    "sg:address":"599 E McGlincey Ln",
    "sg:city":"Campbell",
    "sg:classifiers":[
        {
            "category":"Building & Trades",
            "subcategory":"Cleaning & Sanitation",
            "type":"Services"
        }
    ],
    "sg:phone":"+1 408 371 5291",
    "sg:postcode":"95008",
    "sg:province":"CA",
    "sg:tags":[
        "processing",
        "cryogenic"
    ],
    "wof:name":"Vbs Industries",
    "wof:placetype":"venue"
},
  "geometry": {"coordinates":[-121.940573,37.277913],"type":"Point"}
}