{
  "type": "Feature",
  "properties": {
    "iso:country":"US",
    "sg:address":"4647 E Washington Ave",
    "sg:city":"Fresno",
    "sg:classifiers":[
        {
            "category":"Personal",
            "type":"Services"
        }
    ],
    "sg:phone":"+1 559 696 0957",
    "sg:postcode":"93702",
    "sg:province":"CA",
    "sg:tags":[
        "therapist",
        "massage"
    ],
    "wof:name":"Ruben Salinas Massage",
    "wof:placetype":"venue"
},
  "geometry": {"coordinates":[-119.74524599999999,36.747807],"type":"Point"}
}