{
  "type": "Feature",
  "properties": {
    "sfgov:dept":"7",
    "sfgov:deptname":"SF Unified School District (SFUSD)",
    "sfgov:facility_i":"0000003123",
    "sfgov:school_typ":"Elementary",
    "wof:categories":[
        "education_and_religion:education=school"
    ],
    "wof:name":"Parks, Rosa Elementary School",
    "wof:placetype":"venue"
},
  "geometry": {"coordinates":[-122.43001153983712,37.78349340332897],"type":"Point"}
}