{
  "type": "Feature",
  "properties": {
    "iso:country":"US",
    "sg:address":"6233 E Allison Cir",
    "sg:city":"Orange",
    "sg:classifiers":[
        {
            "category":"Organizations",
            "subcategory":"Professional Association",
            "type":"Services"
        }
    ],
    "sg:phone":"+1 714 744 4250",
    "sg:postcode":"92869",
    "sg:province":"CA",
    "wof:name":"American Academy-Pediatrics",
    "wof:placetype":"venue"
},
  "geometry": {"coordinates":[-117.786743,33.7838],"type":"Point"}
}