{
  "type": "Feature",
  "properties": {
    "iso:country":"US",
    "sg:address":"15760 Ventura Blvd",
    "sg:city":"Encino",
    "sg:classifiers":[
        {
            "category":"Wholesale",
            "subcategory":"Stationery",
            "type":"Manufacturing & Wholesale Goods"
        }
    ],
    "sg:phone":"+1 818 461 9300",
    "sg:postcode":"91436",
    "sg:province":"CA",
    "sg:tags":[
        "product",
        "paper"
    ],
    "sg:website":"www.nbexport.com",
    "wof:name":"National Board Exchange",
    "wof:placetype":"venue"
},
  "geometry": {"coordinates":[-118.475694,34.155168],"type":"Point"}
}