{
  "type": "Feature",
  "properties": {
    "iso:country":"US",
    "sg:address":"1345 Jackson Gate Rd",
    "sg:city":"Jackson",
    "sg:classifiers":[
        {
            "category":"Retail",
            "subcategory":"Car Wash",
            "type":"Services"
        }
    ],
    "sg:phone":"+1 209 223 3808",
    "sg:postcode":"95642",
    "sg:province":"CA",
    "sg:tags":[
        "automobile",
        "detail",
        "clean"
    ],
    "wof:name":"Jason's Auto Detailing",
    "wof:placetype":"venue"
},
  "geometry": {"coordinates":[-120.77531,38.367632],"type":"Point"}
}