{
  "type": "Feature",
  "properties": {
    "iso:country":"US",
    "sg:address":"6056 Rutland Dr Ste 10",
    "sg:city":"Carmichael",
    "sg:classifiers":[
        {
            "category":"Banks & Credit Unions",
            "subcategory":"Financial Services",
            "type":"Services"
        }
    ],
    "sg:phone":"+1 888 303 3894",
    "sg:postcode":"95608",
    "sg:province":"CA",
    "sg:tags":[
        "broker",
        "mortgage"
    ],
    "wof:name":"USA HOME SAVERPROGRAM.COM",
    "wof:placetype":"venue"
},
  "geometry": {"coordinates":[-121.32365,38.662215],"type":"Point"}
}