{
  "type": "Feature",
  "properties": {
    "iso:country":"US",
    "sg:address":"40674 Jean Rd W",
    "sg:city":"Oakhurst",
    "sg:classifiers":[
        {
            "category":"Building & Trades",
            "subcategory":"Electrical",
            "type":"Services"
        }
    ],
    "sg:phone":"+1 559 658 2100",
    "sg:postcode":"93644",
    "sg:province":"CA",
    "sg:tags":[
        "industrial",
        "electrician",
        "electric",
        "contractors-commercial"
    ],
    "wof:name":"Reda Electric",
    "wof:placetype":"venue"
},
  "geometry": {"coordinates":[-119.61296,37.341573],"type":"Point"}
}