{
  "type": "Feature",
  "properties": {
    "iso:country":"US",
    "sg:address":"1100 Kings Hwy",
    "sg:city":"Boulder Creek",
    "sg:classifiers":[
        {
            "category":"Real Estate",
            "subcategory":"Real Estate Agent",
            "type":"Services"
        }
    ],
    "sg:phone":"+1 831 338 1974",
    "sg:postcode":"95006",
    "sg:province":"CA",
    "sg:website":"www.redwoodland.com",
    "wof:name":"Redwood Land Co",
    "wof:placetype":"venue"
},
  "geometry": {"coordinates":[-122.150723,37.165177],"type":"Point"}
}