{
  "type": "Feature",
  "properties": {
    "addr:full":"1308 E Imperial Ave El Segundo CA 90245",
    "addr:housenumber":"1308",
    "addr:postcode":"90245",
    "addr:street":"E Imperial Ave",
    "iso:country":"US",
    "sg:address":"1308 E Imperial Ave",
    "sg:city":"El Segundo",
    "sg:classifiers":[
        {
            "category":"Professional",
            "subcategory":"Printing & Photocopies",
            "type":"Services"
        }
    ],
    "sg:phone":"+1 310 657 0940",
    "sg:postcode":"90245",
    "sg:province":"CA",
    "sg:website":"www.PrintingPlusUSA.com",
    "wof:name":"Printing Plus",
    "wof:placetype":"venue"
},
  "geometry": {"coordinates":[-118.40224499999999,33.930856],"type":"Point"}
}