{
  "type": "Feature",
  "properties": {
    "addr:full":"17258 Wentzel Way Granada Hills CA 91344",
    "addr:postcode":"17258;91344",
    "addr:street":"Wentzel Way",
    "iso:country":"US",
    "sg:address":"17258 Wentzel Way",
    "sg:city":"Granada Hills",
    "sg:classifiers":[
        {
            "category":"Building & Trades",
            "subcategory":"Electrical",
            "type":"Services"
        }
    ],
    "sg:phone":"+1 818 366 0194",
    "sg:postcode":"91344",
    "sg:province":"CA",
    "sg:tags":[
        "electrical",
        "contractor"
    ],
    "wof:name":"Em Electrical Contractor",
    "wof:placetype":"venue"
},
  "geometry": {"coordinates":[-118.51099600000001,34.30584],"type":"Point"}
}