{
  "type": "Feature",
  "properties": {
    "iso:country":"US",
    "sg:address":"45655 Northport Loop E",
    "sg:city":"Fremont",
    "sg:classifiers":[
        {
            "category":"Manufacturing",
            "subcategory":"Electronics",
            "type":"Manufacturing & Wholesale Goods"
        }
    ],
    "sg:phone":"+1 510 657 8801",
    "sg:postcode":"94538",
    "sg:province":"CA",
    "sg:tags":[
        "semiconductor",
        "devices"
    ],
    "sg:website":"www.aetusa.com",
    "wof:name":"Advanced Epi Techology Corp",
    "wof:placetype":"venue"
},
  "geometry": {"coordinates":[-121.954702,37.493719],"type":"Point"}
}