{
  "type": "Feature",
  "properties": {
    "iso:country":"US",
    "sg:address":"7861 Klusman Ave",
    "sg:city":"Rancho Cucamonga",
    "sg:classifiers":[
        {
            "category":"Building & Trades",
            "subcategory":"Construction",
            "type":"Services"
        }
    ],
    "sg:phone":"+1 909 980 8927",
    "sg:postcode":"91730",
    "sg:province":"CA",
    "sg:tags":[
        "dry wall",
        "contractor"
    ],
    "wof:name":"Nunnally Drywall",
    "wof:placetype":"venue"
},
  "geometry": {"coordinates":[-117.595465,34.112205],"type":"Point"}
}