{
  "type": "Feature",
  "properties": {
    "addr:full":"726 Santa Monica Blvd Santa Monica CA 90401",
    "addr:housenumber":"726",
    "addr:postcode":"90401",
    "addr:street":"Santa Monica Blvd",
    "iso:country":"US",
    "sg:address":"726 Santa Monica Blvd",
    "sg:city":"Santa Monica",
    "sg:classifiers":[
        {
            "category":"Health Services",
            "subcategory":"Podiatrist",
            "type":"Services"
        }
    ],
    "sg:phone":"+1 310 458 7645",
    "sg:postcode":"90401",
    "sg:province":"CA",
    "wof:name":"Suvepa Lertwongkanako DPM",
    "wof:placetype":"venue"
},
  "geometry": {"coordinates":[-118.491997,34.018839],"type":"Point"}
}