{
  "type": "Feature",
  "properties": {
    "addr:full":"4601 Lakeview Canyon Rd Westlake Village CA 91361",
    "addr:housenumber":"4601",
    "addr:postcode":"91361",
    "addr:street":"Lakeview Canyon Rd",
    "iso:country":"US",
    "sg:address":"4601 Lakeview Canyon Rd",
    "sg:city":"Westlake Village",
    "sg:classifiers":[
        {
            "category":"Food & Beverages",
            "subcategory":"Liquor & Beverages",
            "type":"Retail Goods"
        }
    ],
    "sg:phone":"+1 818 889 5292",
    "sg:postcode":"91361",
    "sg:province":"CA",
    "sg:tags":[
        "grocery",
        "alcoholic"
    ],
    "wof:name":"Village Spirits Shoppe",
    "wof:placetype":"venue"
},
  "geometry": {"coordinates":[-118.819199,34.148095],"type":"Point"}
}