{
  "type": "Feature",
  "properties": {
    "addr:full":"2248 16th St Santa Monica CA 90405",
    "addr:housenumber":"2248",
    "addr:postcode":"90405",
    "addr:street":"16Th St",
    "iso:country":"US",
    "sg:address":"2248 16th St",
    "sg:city":"Santa Monica",
    "sg:classifiers":[
        {
            "category":"Professional",
            "subcategory":"Computer Services",
            "type":"Services"
        }
    ],
    "sg:phone":"+1 310 452 3450",
    "sg:postcode":"90405",
    "sg:province":"CA",
    "sg:tags":[
        "related"
    ],
    "wof:name":"Imedian",
    "wof:placetype":"venue"
},
  "geometry": {"coordinates":[-118.471752,34.014459],"type":"Point"}
}