{
  "type": "Feature",
  "properties": {
    "iso:country":"US",
    "sg:address":"4126 N Norse Way",
    "sg:city":"Long Beach",
    "sg:classifiers":[
        {
            "category":"Professional",
            "type":"Services"
        }
    ],
    "sg:phone":"+1 562 425 6336",
    "sg:postcode":"90808",
    "sg:province":"CA",
    "sg:tags":[
        "arts",
        "artist"
    ],
    "wof:name":"Mc Cracken Visions",
    "wof:placetype":"venue"
},
  "geometry": {"coordinates":[-118.141101,33.832776],"type":"Point"}
}