{
  "type": "Feature",
  "properties": {
    "addr:full":"1900 N 6th St Burbank CA 91504",
    "addr:housenumber":"1900",
    "addr:postcode":"91504",
    "addr:street":"N 6Th St",
    "iso:country":"US",
    "sg:address":"1900 N 6th St",
    "sg:city":"Burbank",
    "sg:classifiers":[
        {
            "category":"Education",
            "subcategory":"School",
            "type":"Public Place"
        }
    ],
    "sg:phone":"+1 818 558 4635",
    "sg:postcode":"91504",
    "sg:province":"CA",
    "sg:tags":[
        "high",
        "middle",
        "elementary"
    ],
    "sg:website":"www.burbank.k12.ca.us",
    "wof:name":"Burbank Unified School District",
    "wof:placetype":"venue"
},
  "geometry": {"coordinates":[-118.32199900000001,34.198601],"type":"Point"}
}