{
  "type": "Feature",
  "properties": {
    "addr:full":"25885 Trabuco Rd Lake Forest CA 92630",
    "addr:housenumber":"25885",
    "addr:postcode":"92630",
    "addr:street":"Trabuco Rd",
    "iso:country":"US",
    "sg:address":"25885 Trabuco Rd",
    "sg:city":"Lake Forest",
    "sg:classifiers":[
        {
            "category":"Professional",
            "type":"Services"
        }
    ],
    "sg:phone":"+1 949 461 9397",
    "sg:postcode":"92630",
    "sg:province":"CA",
    "wof:name":"Azz Electronics",
    "wof:placetype":"venue"
},
  "geometry": {"coordinates":[-117.67997,33.637029],"type":"Point"}
}