{
  "type": "Feature",
  "properties": {
    "iso:country":"US",
    "sg:address":"14104 Vanowen St",
    "sg:city":"Van Nuys",
    "sg:classifiers":[
        {
            "category":"Retail",
            "subcategory":"Auto Repair",
            "type":"Services"
        }
    ],
    "sg:phone":"+1 818 785 5500",
    "sg:postcode":"91405",
    "sg:province":"CA",
    "sg:tags":[
        "automobile",
        "smog"
    ],
    "wof:name":"Star Tech Automotive",
    "wof:placetype":"venue"
},
  "geometry": {"coordinates":[-118.44209600000001,34.193855],"type":"Point"}
}