{
  "type": "Feature",
  "properties": {
    "addr:full":"7961 Shady Creek Rd Dublin CA 94568",
    "addr:housenumber":"7961",
    "addr:postcode":"94568",
    "addr:street":"Shady Creek Rd",
    "iso:country":"US",
    "sg:address":"7961 Shady Creek Rd",
    "sg:city":"Dublin",
    "sg:classifiers":[
        {
            "category":"Building & Trades",
            "subcategory":"Landscaping Services",
            "type":"Services"
        }
    ],
    "sg:phone":"+1 925 828 6641",
    "sg:postcode":"94568",
    "sg:province":"CA",
    "sg:tags":[
        "landscape"
    ],
    "wof:name":"Sorensen Landscape",
    "wof:placetype":"venue"
},
  "geometry": {"coordinates":[-121.91376700000001,37.728148],"type":"Point"}
}