{
  "type": "Feature",
  "properties": {
    "iso:country":"US",
    "sg:address":"6900 Chestnut St",
    "sg:city":"Gilroy",
    "sg:classifiers":[
        {
            "category":"Shopping",
            "subcategory":"Shoes",
            "type":"Retail Goods"
        }
    ],
    "sg:phone":"+1 408 846 5911",
    "sg:postcode":"95020",
    "sg:province":"CA",
    "wof:name":"Moses Shoes",
    "wof:placetype":"venue"
},
  "geometry": {"coordinates":[-121.560115,36.999049],"type":"Point"}
}