{
  "type": "Feature",
  "properties": {
    "iso:country":"US",
    "sg:address":"44152 Redbud Trl",
    "sg:city":"Three Rivers",
    "sg:classifiers":[
        {
            "category":"Farming",
            "subcategory":"Livestock Farm",
            "type":"Manufacturing & Wholesale Goods"
        }
    ],
    "sg:phone":"+1 559 696 7434",
    "sg:postcode":"93271",
    "sg:province":"CA",
    "sg:tags":[
        "equine"
    ],
    "wof:name":"Equine Sitter",
    "wof:placetype":"venue"
},
  "geometry": {"coordinates":[-118.879885,36.40378],"type":"Point"}
}