{
  "type": "Feature",
  "properties": {
    "addr:full":"2028 Yankee Ct San Leandro CA 94579",
    "addr:housenumber":"2028",
    "addr:postcode":"94579",
    "addr:street":"Yankee Ct",
    "iso:country":"US",
    "sg:address":"2028 Yankee Ct",
    "sg:city":"San Leandro",
    "sg:classifiers":[
        {
            "category":"Utilities",
            "subcategory":"Telephone",
            "type":"Services"
        }
    ],
    "sg:phone":"+1 510 351 1903",
    "sg:postcode":"94579",
    "sg:province":"CA",
    "sg:tags":[
        "access",
        "internet"
    ],
    "wof:name":"City Online Cmmnctns",
    "wof:placetype":"venue"
},
  "geometry": {"coordinates":[-122.16524099999999,37.68884],"type":"Point"}
}