{
  "type": "Feature",
  "properties": {
    "iso:country":"US",
    "sg:address":"14349 Victory Blvd",
    "sg:city":"Van Nuys",
    "sg:classifiers":[
        {
            "category":"Education",
            "subcategory":"Special Training",
            "type":"Public Place"
        }
    ],
    "sg:phone":"+1 818 780 6131",
    "sg:postcode":"91401",
    "sg:province":"CA",
    "sg:tags":[
        "instruction",
        "music"
    ],
    "wof:name":"Iranian Music Assn",
    "wof:placetype":"venue"
},
  "geometry": {"coordinates":[-118.44564699999999,34.186737],"type":"Point"}
}