{
  "type": "Feature",
  "properties": {
    "addr:full":"3566 Spangler Ln Copperopolis CA 95228",
    "addr:housenumber":"3566",
    "addr:postcode":"95228",
    "addr:street":"Spangler Ln",
    "iso:country":"US",
    "sg:address":"3566 Spangler Ln",
    "sg:city":"Copperopolis",
    "sg:classifiers":[
        {
            "category":"Retail",
            "subcategory":"Auto Repair",
            "type":"Services"
        }
    ],
    "sg:phone":"+1 209 785 3682",
    "sg:postcode":"95228",
    "sg:province":"CA",
    "sg:tags":[
        "recreational",
        "vehicle"
    ],
    "wof:name":"Haynes RV",
    "wof:placetype":"venue"
},
  "geometry": {"coordinates":[-120.604174,37.93714],"type":"Point"}
}