{
  "type": "Feature",
  "properties": {
    "addr:full":"2758 Whitson St Selma CA 93662",
    "addr:housenumber":"2758",
    "addr:postcode":"93662",
    "addr:street":"Whitson St",
    "iso:country":"US",
    "sg:address":"2758 Whitson St",
    "sg:city":"Selma",
    "sg:classifiers":[
        {
            "category":"Insurance",
            "subcategory":"Insurance Agent",
            "type":"Services"
        },
        {
            "category":"Insurance",
            "subcategory":"Hazard Insurance",
            "type":"Services"
        }
    ],
    "sg:phone":"+1 559 891 2900",
    "sg:postcode":"93662",
    "sg:province":"CA",
    "sg:tags":[
        "auto",
        "recreational",
        "motorcycle",
        "vehicle",
        "marine",
        "boat"
    ],
    "wof:name":"Mark Chavez Insurance Services",
    "wof:placetype":"venue"
},
  "geometry": {"coordinates":[-119.62312900000001,36.574993],"type":"Point"}
}