{
  "type": "Feature",
  "properties": {
    "addr:full":"42280 Beacon Hill Palm Desert CA 92211",
    "addr:housenumber":"42280",
    "addr:postcode":"ca 92211",
    "addr:street":"Beacon Hill",
    "iso:country":"US",
    "sg:address":"42280 Beacon Hill",
    "sg:city":"Palm Desert",
    "sg:classifiers":[
        {
            "category":"Manufacturing",
            "subcategory":"Printing",
            "type":"Manufacturing & Wholesale Goods"
        }
    ],
    "sg:phone":"+1 760 568 5440",
    "sg:postcode":"92211",
    "sg:province":"CA",
    "sg:tags":[
        "printer"
    ],
    "wof:name":"Printing Solutions",
    "wof:placetype":"venue"
},
  "geometry": {"coordinates":[-116.352473,33.742692],"type":"Point"}
}