{
  "type": "Feature",
  "properties": {
    "addr:full":"8831 Palomar Ave Atascadero CA 93422",
    "addr:housenumber":"8831",
    "addr:postcode":"93422",
    "addr:street":"Palomar Ave",
    "iso:country":"US",
    "sg:address":"8831 Palomar Ave",
    "sg:city":"Atascadero",
    "sg:classifiers":[
        {
            "category":"Building & Trades",
            "subcategory":"Equipment Rental",
            "type":"Services"
        }
    ],
    "sg:phone":"+1 805 466 5566",
    "sg:postcode":"93422",
    "sg:province":"CA",
    "sg:tags":[
        "yard"
    ],
    "wof:name":"Taylor Rental Ctr",
    "wof:placetype":"venue"
},
  "geometry": {"coordinates":[-120.65340399999999,35.476131],"type":"Point"}
}