{
  "type": "Feature",
  "properties": {
    "iso:country":"US",
    "sg:address":"465 N Ogden Dr",
    "sg:city":"Los Angeles",
    "sg:classifiers":[
        {
            "category":"Wholesale",
            "subcategory":"Construction Materials",
            "type":"Manufacturing & Wholesale Goods"
        }
    ],
    "sg:phone":"+1 323 953 0646",
    "sg:postcode":"90036",
    "sg:province":"CA",
    "sg:tags":[
        "tile"
    ],
    "wof:name":"Bridge Modern Cabinet",
    "wof:placetype":"venue"
},
  "geometry": {"coordinates":[-118.359486,34.078895],"type":"Point"}
}