{
  "type": "Feature",
  "properties": {
    "addr:full":"529 E 3rd Avenue San Mateo CA 94401",
    "addr:housenumber":"529",
    "addr:postcode":"94401",
    "addr:street":"E 3Rd Avenue",
    "iso:country":"US",
    "sg:address":"529 E 3rd Avenue",
    "sg:city":"San Mateo",
    "sg:classifiers":[
        {
            "category":"Shopping",
            "subcategory":"Books",
            "type":"Retail Goods"
        }
    ],
    "sg:phone":"+1 650 375 8286",
    "sg:postcode":"94401",
    "sg:province":"CA",
    "sg:tags":[
        "bookstore"
    ],
    "wof:name":"Asian American Curriculum Project",
    "wof:placetype":"venue"
},
  "geometry": {"coordinates":[-122.320683,37.566837],"type":"Point"}
}