{
  "type": "Feature",
  "properties": {
    "iso:country":"US",
    "sg:address":"82375 Market St",
    "sg:city":"Indio",
    "sg:classifiers":[
        {
            "category":"Manufacturing",
            "subcategory":"Printing",
            "type":"Manufacturing & Wholesale Goods"
        }
    ],
    "sg:phone":"+1 760 342 3919",
    "sg:postcode":"92201",
    "sg:province":"CA",
    "sg:tags":[
        "screen"
    ],
    "wof:name":"Louies Screen Printing",
    "wof:placetype":"venue"
},
  "geometry": {"coordinates":[-116.224058,33.726574],"type":"Point"}
}