{
  "type": "Feature",
  "properties": {
    "iso:country":"US",
    "sg:address":"1831 Orange Ave Ste D",
    "sg:city":"Costa Mesa",
    "sg:classifiers":[
        {
            "category":"Professional",
            "type":"Services"
        }
    ],
    "sg:phone":"+1 714 733 1025",
    "sg:postcode":"92627",
    "sg:province":"CA",
    "wof:name":"Affirmative Bail Bonds",
    "wof:placetype":"venue"
},
  "geometry": {"coordinates":[-117.915367,33.639299],"type":"Point"}
}