{
  "type": "Feature",
  "properties": {
    "addr:full":"21011 Wallace Ave Perris CA 92570",
    "addr:housenumber":"21011",
    "addr:postcode":"92570",
    "addr:street":"Wallace Ave",
    "iso:country":"US",
    "sg:address":"21011 Wallace Ave",
    "sg:city":"Perris",
    "sg:classifiers":[
        {
            "category":"Mining & Drilling",
            "type":"Manufacturing & Wholesale Goods"
        }
    ],
    "sg:phone":"+1 951 657 4067",
    "sg:postcode":"92570",
    "sg:province":"CA",
    "sg:tags":[
        "field"
    ],
    "wof:name":"Villa Construction",
    "wof:placetype":"venue"
},
  "geometry": {"coordinates":[-117.291259,33.72048],"type":"Point"}
}