{
  "type": "Feature",
  "properties": {
    "iso:country":"US",
    "sg:address":"3015 Fremontia Dr",
    "sg:city":"San Bernardino",
    "sg:classifiers":[
        {
            "category":"Banks & Credit Unions",
            "subcategory":"Investment Brokerage",
            "type":"Services"
        }
    ],
    "sg:phone":"+1 909 238 8028",
    "sg:postcode":"92404",
    "sg:province":"CA",
    "sg:tags":[
        "advisory",
        "financial"
    ],
    "wof:name":"Kingbrat Enterprises",
    "wof:placetype":"venue"
},
  "geometry": {"coordinates":[-117.273475,34.14659],"type":"Point"}
}