{
  "type": "Feature",
  "properties": {
    "iso:country":"US",
    "sg:address":"9962 Bloomington Ave",
    "sg:city":"Bloomington",
    "sg:classifiers":[
        {
            "category":"Banks & Credit Unions",
            "subcategory":"Bank",
            "type":"Services"
        }
    ],
    "sg:phone":"+1 909 421 8687",
    "sg:postcode":"92316",
    "sg:province":"CA",
    "sg:tags":[
        "cashing",
        "check"
    ],
    "wof:name":"Cash 4 Checks",
    "wof:placetype":"venue"
},
  "geometry": {"coordinates":[-117.392229,34.074153],"type":"Point"}
}