{
  "type": "Feature",
  "properties": {
    "iso:country":"US",
    "sg:address":"11808 Cmt Sanudo",
    "sg:city":"San Diego",
    "sg:classifiers":[
        {
            "category":"Building & Trades",
            "subcategory":"Landscaping Services",
            "type":"Services"
        }
    ],
    "sg:phone":"+1 858 566 1912",
    "sg:postcode":"92131",
    "sg:province":"CA",
    "sg:tags":[
        "landscape"
    ],
    "wof:name":"Sterling Commercial Landscape",
    "wof:placetype":"venue"
},
  "geometry": {"coordinates":[-117.071273,32.904137],"type":"Point"}
}