{
  "type": "Feature",
  "properties": {
    "iso:country":"US",
    "sg:address":"44230 10th St W",
    "sg:city":"Lancaster",
    "sg:classifiers":[
        {
            "category":"Sports & Exercise",
            "subcategory":"Gym",
            "type":"Entertainment"
        }
    ],
    "sg:phone":"+1 661 951 1080",
    "sg:postcode":"93534",
    "sg:province":"CA",
    "sg:tags":[
        "club",
        "health",
        "studio",
        "gymnasium"
    ],
    "wof:name":"Slendor Lady Of Lancaster",
    "wof:placetype":"venue"
},
  "geometry": {"coordinates":[-118.147932,34.68789],"type":"Point"}
}