{
  "type": "Feature",
  "properties": {
    "iso:country":"US",
    "sg:address":"1407 Sunset Ave",
    "sg:city":"Madera",
    "sg:classifiers":[
        {
            "category":"Education",
            "subcategory":"School",
            "type":"Public Place"
        }
    ],
    "sg:phone":"+1 559 673 9286",
    "sg:postcode":"93637",
    "sg:province":"CA",
    "sg:website":"http://www.madera.k12.ca.us",
    "wof:name":"Jefferson thomas Middle School",
    "wof:placetype":"venue"
},
  "geometry": {"coordinates":[-120.074124,36.96011],"type":"Point"}
}