{
  "type": "Feature",
  "properties": {
    "iso:country":"US",
    "sg:address":"1421 Warner Ave Ste B",
    "sg:city":"Tustin",
    "sg:classifiers":[
        {
            "category":"Banks & Credit Unions",
            "subcategory":"Financial Services",
            "type":"Services"
        }
    ],
    "sg:phone":"+1 714 259 7711",
    "sg:postcode":"92780",
    "sg:province":"CA",
    "sg:tags":[
        "broker",
        "mortgage"
    ],
    "wof:name":"Orange County Mutual Fundings",
    "wof:placetype":"venue"
},
  "geometry": {"coordinates":[-117.838567,33.712152],"type":"Point"}
}