{
  "type": "Feature",
  "properties": {
    "iso:country":"US",
    "sg:address":"7041 Danyeur Rd",
    "sg:city":"Redding",
    "sg:classifiers":[
        {
            "category":"Home & Garden",
            "subcategory":"Furniture",
            "type":"Retail Goods"
        }
    ],
    "sg:phone":"+1 530 243 8041",
    "sg:postcode":"96001",
    "sg:province":"CA",
    "sg:tags":[
        "top",
        "counter"
    ],
    "wof:name":"Brothers Countertops",
    "wof:placetype":"venue"
},
  "geometry": {"coordinates":[-122.377931,40.514811],"type":"Point"}
}