{
  "type": "Feature",
  "properties": {
    "iso:country":"US",
    "sg:address":"520 S Kaweah Ave",
    "sg:city":"Exeter",
    "sg:classifiers":[
        {
            "category":"Food & Beverages",
            "subcategory":"Groceries & Convenience Stores",
            "type":"Retail Goods"
        }
    ],
    "sg:phone":"+1 559 592 2722",
    "sg:postcode":"93221",
    "sg:province":"CA",
    "sg:tags":[
        "grocer"
    ],
    "wof:name":"U-Mart",
    "wof:placetype":"venue"
},
  "geometry": {"coordinates":[-119.136198,36.292024],"type":"Point"}
}