{
  "type": "Feature",
  "properties": {
    "iso:country":"US",
    "sg:address":"5984 Bridgecross Dr",
    "sg:city":"Sacramento",
    "sg:classifiers":[
        {
            "category":"Building & Trades",
            "subcategory":"Construction",
            "type":"Services"
        }
    ],
    "sg:phone":"+1 916 267 5615",
    "sg:postcode":"95835",
    "sg:province":"CA",
    "sg:tags":[
        "altering",
        "remodeling",
        "contractor"
    ],
    "wof:name":"All Class Home Repair",
    "wof:placetype":"venue"
},
  "geometry": {"coordinates":[-121.50281699999999,38.681963],"type":"Point"}
}