{
  "type": "Feature",
  "properties": {
    "addr:full":"16531 Kellog Cir Huntington Beach CA 92647",
    "addr:postcode":"16531;92647",
    "addr:street":"Kellog Cir",
    "iso:country":"US",
    "sg:address":"16531 Kellog Cir",
    "sg:city":"Huntington Beach",
    "sg:classifiers":[
        {
            "category":"Manufacturing",
            "subcategory":"Printing",
            "type":"Manufacturing & Wholesale Goods"
        }
    ],
    "sg:phone":"+1 714 841 7620",
    "sg:postcode":"92647",
    "sg:province":"CA",
    "sg:tags":[
        "book"
    ],
    "wof:name":"Tentaio Press",
    "wof:placetype":"venue"
},
  "geometry": {"coordinates":[-118.004931,33.721557],"type":"Point"}
}