{
  "type": "Feature",
  "properties": {
    "iso:country":"US",
    "sg:address":"8982 Dahlia Dr",
    "sg:city":"Corona",
    "sg:classifiers":[
        {
            "category":"Professional",
            "subcategory":"Business Services",
            "type":"Services"
        }
    ],
    "sg:phone":"+1 951 277 3538",
    "sg:postcode":"92883",
    "sg:province":"CA",
    "sg:tags":[
        "detection",
        "paint",
        "lead"
    ],
    "wof:name":"AAA Lead Consultants",
    "wof:placetype":"venue"
},
  "geometry": {"coordinates":[-117.504029,33.780121],"type":"Point"}
}