{
  "type": "Feature",
  "properties": {
    "iso:country":"US",
    "sg:address":"606 Wilson St",
    "sg:city":"Santa Rosa",
    "sg:classifiers":[
        {
            "category":"Organizations",
            "subcategory":"Non-profit Organization",
            "type":"Services"
        }
    ],
    "sg:phone":"+1 707 579 2787",
    "sg:postcode":"95401",
    "sg:province":"CA",
    "wof:name":"ART Trails",
    "wof:placetype":"venue"
},
  "geometry": {"coordinates":[-122.72264199999999,38.440193],"type":"Point"}
}