{
  "type": "Feature",
  "properties": {
    "iso:country":"US",
    "sg:address":"2801 Courtnay Cir",
    "sg:city":"West Covina",
    "sg:classifiers":[
        {
            "category":"Professional",
            "type":"Services"
        }
    ],
    "sg:phone":"+1 626 810 7917",
    "sg:postcode":"91792",
    "sg:province":"CA",
    "wof:name":"Kc & K",
    "wof:placetype":"venue"
},
  "geometry": {"coordinates":[-117.910771,34.025633],"type":"Point"}
}