{
  "type": "Feature",
  "properties": {
    "addr:full":"4344 Rose Ln Concord CA 94518",
    "addr:housenumber":"4344",
    "addr:postcode":"94518",
    "addr:street":"Rose Ln",
    "iso:country":"US",
    "sg:address":"4344 Rose Ln",
    "sg:city":"Concord",
    "sg:classifiers":[
        {
            "category":"Building & Trades",
            "subcategory":"Cleaning & Sanitation",
            "type":"Services"
        }
    ],
    "sg:phone":"+1 925 680 7474",
    "sg:postcode":"94518",
    "sg:province":"CA",
    "sg:tags":[
        "window"
    ],
    "wof:name":"Clearview Window",
    "wof:placetype":"venue"
},
  "geometry": {"coordinates":[-122.000424,37.952104],"type":"Point"}
}