{
  "type": "Feature",
  "properties": {
    "addr:full":"320 13th St Ste 305 Oakland CA 94612",
    "addr:housenumber":"320",
    "addr:postcode":"94612",
    "addr:street":"13Th St Ste 305",
    "iso:country":"US",
    "sg:address":"320 13th St Ste 305",
    "sg:city":"Oakland",
    "sg:classifiers":[
        {
            "category":"Manufacturing",
            "subcategory":"Buildings",
            "type":"Manufacturing & Wholesale Goods"
        },
        {
            "category":"Building & Trades",
            "subcategory":"Construction",
            "type":"Services"
        }
    ],
    "sg:phone":"+1 510 875 9910",
    "sg:postcode":"94612",
    "sg:province":"CA",
    "sg:tags":[
        "home",
        "builder",
        "contractor"
    ],
    "wof:name":"New Eastern Constructions Corporation",
    "wof:placetype":"venue"
},
  "geometry": {"coordinates":[-122.26853300000001,37.802426],"type":"Point"}
}