{
  "type": "Feature",
  "properties": {
    "addr:full":"8234 3rd St Downey CA 90241",
    "addr:housenumber":"8234",
    "addr:postcode":"90241",
    "addr:street":"3Rd St",
    "iso:country":"US",
    "sg:address":"8234 3rd St",
    "sg:city":"Downey",
    "sg:classifiers":[
        {
            "category":"Banks & Credit Unions",
            "subcategory":"Financial Services",
            "type":"Services"
        }
    ],
    "sg:phone":"+1 562 862 0190",
    "sg:postcode":"90241",
    "sg:province":"CA",
    "sg:tags":[
        "broker",
        "mortgage"
    ],
    "wof:name":"California Residential Mortgage",
    "wof:placetype":"venue"
},
  "geometry": {"coordinates":[-118.132667,33.942122],"type":"Point"}
}