{
  "type": "Feature",
  "properties": {
    "iso:country":"US",
    "sg:address":"3325 N Cedar Ave",
    "sg:city":"Fresno",
    "sg:classifiers":[
        {
            "category":"Personal",
            "subcategory":"Beauty Salon",
            "type":"Services"
        }
    ],
    "sg:phone":"+1 559 227 4171",
    "sg:postcode":"93726",
    "sg:province":"CA",
    "wof:name":"Joe Vega",
    "wof:placetype":"venue"
},
  "geometry": {"coordinates":[-119.75443199999999,36.780285],"type":"Point"}
}