{
  "type": "Feature",
  "properties": {
    "iso:country":"US",
    "sg:address":"11238 Whittier Blvd",
    "sg:city":"Whittier",
    "sg:classifiers":[
        {
            "category":"Personal",
            "subcategory":"Beauty Salon",
            "type":"Services"
        }
    ],
    "sg:phone":"+1 562 695 9968",
    "sg:postcode":"90606",
    "sg:province":"CA",
    "sg:tags":[
        "hair",
        "stylist"
    ],
    "wof:name":"Fernando's Beauty Salon",
    "wof:placetype":"venue"
},
  "geometry": {"coordinates":[-118.05773499999999,33.985659],"type":"Point"}
}