{
  "type": "Feature",
  "properties": {
    "iso:country":"US",
    "sg:address":"20277 Valley Blvd",
    "sg:city":"Walnut",
    "sg:classifiers":[
        {
            "category":"Wholesale",
            "subcategory":"Medical Equipment & Supplies",
            "type":"Manufacturing & Wholesale Goods"
        }
    ],
    "sg:phone":"+1 909 468 5688",
    "sg:postcode":"91789",
    "sg:province":"CA",
    "sg:tags":[
        "optical"
    ],
    "wof:name":"Pacific Rim Optical Inc",
    "wof:placetype":"venue"
},
  "geometry": {"coordinates":[-117.86159000000001,34.008093],"type":"Point"}
}