{
  "type": "Feature",
  "properties": {
    "addr:full":"1400 Van Ness Ave San Francisco CA 94117",
    "addr:housenumber":"1400",
    "addr:postcode":"94117",
    "addr:street":"Van Ness Ave",
    "iso:country":"US",
    "sg:address":"1400 Van Ness Ave",
    "sg:city":"San Francisco",
    "sg:classifiers":[
        {
            "category":"Real Estate",
            "subcategory":"Real Estate Agent",
            "type":"Services"
        }
    ],
    "sg:phone":"+1 415 863 5289",
    "sg:postcode":"94117",
    "sg:province":"CA",
    "sg:website":"www.KatyDinner.com",
    "wof:name":"Katy Dinner",
    "wof:placetype":"venue"
},
  "geometry": {"coordinates":[-122.400003,37.795936],"type":"Point"}
}