{
  "type": "Feature",
  "properties": {
    "iso:country":"US",
    "sg:address":"146 E Las Flores Ave",
    "sg:city":"Arcadia",
    "sg:classifiers":[
        {
            "category":"Building & Trades",
            "subcategory":"Equipment Rental",
            "type":"Services"
        }
    ],
    "sg:phone":"+1 626 446 5404",
    "sg:postcode":"91006",
    "sg:province":"CA",
    "sg:tags":[
        "yard",
        "leasing",
        "store"
    ],
    "wof:name":"Ditty Camera Rentals",
    "wof:placetype":"venue"
},
  "geometry": {"coordinates":[-118.026393,34.116124],"type":"Point"}
}