{
  "type": "Feature",
  "properties": {
    "addr:full":"2105 Cleveland Ave National City CA 91950",
    "addr:housenumber":"2105",
    "addr:postcode":"91950",
    "addr:street":"Cleveland Ave",
    "iso:country":"US",
    "sg:address":"2105 Cleveland Ave",
    "sg:city":"National City",
    "sg:classifiers":[
        {
            "category":"Banks & Credit Unions",
            "subcategory":"Bank",
            "type":"Services"
        }
    ],
    "sg:phone":"+1 858 755 6495",
    "sg:postcode":"91950",
    "sg:province":"CA",
    "sg:tags":[
        "financing"
    ],
    "wof:name":"Bonita Financial Corp",
    "wof:placetype":"venue"
},
  "geometry": {"coordinates":[-117.110016,32.66064],"type":"Point"}
}