{
  "type": "Feature",
  "properties": {
    "addr:full":"4738 Laurel Canyon Blvd Valley Village CA 91607",
    "addr:housenumber":"4738",
    "addr:postcode":"91607",
    "addr:street":"Laurel Canyon Blvd",
    "iso:country":"US",
    "sg:address":"4738 Laurel Canyon Blvd",
    "sg:city":"Valley Village",
    "sg:classifiers":[
        {
            "category":"Food & Beverages",
            "subcategory":"Groceries & Convenience Stores",
            "type":"Retail Goods"
        }
    ],
    "sg:phone":"+1 818 906 5743",
    "sg:postcode":"91607",
    "sg:province":"CA",
    "sg:website":"www.gelsons.com",
    "wof:name":"Gelson's Markets",
    "wof:placetype":"venue"
},
  "geometry": {"coordinates":[-118.396004,34.156399],"type":"Point"}
}