{
  "type": "Feature",
  "properties": {
    "iso:country":"US",
    "sg:address":"University Of California-Los Angeles Wyton Dr and Charles E. Young Dr E",
    "sg:city":"Los Angeles",
    "sg:classifiers":[
        {
            "category":"Fast Food",
            "type":"Food & Drink"
        }
    ],
    "sg:phone":"+1 310 825 1177",
    "sg:postcode":"90025",
    "sg:province":"CA",
    "sg:tags":[
        "burger"
    ],
    "wof:name":"Roadside Grill",
    "wof:placetype":"venue"
},
  "geometry": {"coordinates":[-118.438468,34.073886],"type":"Point"}
}