{
  "type": "Feature",
  "properties": {
    "addr:full":"338 Pine St Willits CA 95490",
    "addr:housenumber":"338",
    "addr:postcode":"95490",
    "addr:street":"Pine St",
    "iso:country":"US",
    "sg:address":"338 Pine St",
    "sg:city":"Willits",
    "sg:classifiers":[
        {
            "category":"Shopping",
            "subcategory":"Jewelry",
            "type":"Retail Goods"
        }
    ],
    "sg:phone":"+1 707 459 2927",
    "sg:postcode":"95490",
    "sg:province":"CA",
    "sg:tags":[
        "stone",
        "metal",
        "precious",
        "performs",
        "d"
    ],
    "wof:name":"Kimberly Jewelry",
    "wof:placetype":"venue"
},
  "geometry": {"coordinates":[-123.359213,39.409253],"type":"Point"}
}