{
  "type": "Feature",
  "properties": {
    "iso:country":"US",
    "sg:address":"800 6th St",
    "sg:city":"Paso Robles",
    "sg:classifiers":[
        {
            "category":"Government",
            "subcategory":"Post Office",
            "type":"Public Place"
        }
    ],
    "sg:phone":"+1 805 237 8342",
    "sg:postcode":"93446",
    "sg:province":"CA",
    "sg:tags":[
        "postal",
        "us"
    ],
    "wof:name":"US Post Office",
    "wof:placetype":"venue"
},
  "geometry": {"coordinates":[-120.688328,35.620563],"type":"Point"}
}