{
  "type": "Feature",
  "properties": {
    "addr:full":"45973 Warm Springs Blvd Fremont CA 94539",
    "addr:housenumber":"45973",
    "addr:postcode":"94539",
    "addr:street":"Warm Springs Blvd",
    "iso:country":"US",
    "sg:address":"45973 Warm Springs Blvd",
    "sg:city":"Fremont",
    "sg:classifiers":[
        {
            "category":"Professional",
            "type":"Services"
        }
    ],
    "sg:phone":"+1 510 979 9301",
    "sg:postcode":"94539",
    "sg:province":"CA",
    "wof:name":"Gigabit Hosting",
    "wof:placetype":"venue"
},
  "geometry": {"coordinates":[-121.933515,37.49548],"type":"Point"}
}