{
  "type": "Feature",
  "properties": {
    "addr:full":"2543 Nelson Blvd Selma CA 93662",
    "addr:housenumber":"2543",
    "addr:postcode":"93662",
    "addr:street":"Nelson Blvd",
    "iso:country":"US",
    "sg:address":"2543 Nelson Blvd",
    "sg:city":"Selma",
    "sg:classifiers":[
        {
            "category":"Real Estate",
            "subcategory":"Real Estate Operator",
            "type":"Services"
        }
    ],
    "sg:phone":"+1 559 896 2397",
    "sg:postcode":"93662",
    "sg:province":"CA",
    "sg:tags":[
        "building",
        "apartment"
    ],
    "wof:name":"Huntlee House Apartments",
    "wof:placetype":"venue"
},
  "geometry": {"coordinates":[-119.62495,36.585338],"type":"Point"}
}