{
  "type": "Feature",
  "properties": {
    "iso:country":"US",
    "sg:address":"920 E Colorado Blvd",
    "sg:city":"Pasadena",
    "sg:phone":"+1 626 792 0191",
    "sg:postcode":"91106",
    "sg:province":"CA",
    "sg:tags":[
        "communications",
        "telegraph",
        "business"
    ],
    "wof:name":"Post & Package Ctr Unlimited",
    "wof:placetype":"venue"
},
  "geometry": {"coordinates":[-118.131415,34.145832],"type":"Point"}
}