{
  "type": "Feature",
  "properties": {
    "addr:full":"548 North Pl Redlands CA 92373",
    "addr:housenumber":"548",
    "addr:postcode":"92373",
    "addr:street":"North Pl",
    "iso:country":"US",
    "sg:address":"548 North Pl",
    "sg:city":"Redlands",
    "sg:classifiers":[
        {
            "category":"Farming",
            "subcategory":"Aquatic Farm",
            "type":"Manufacturing & Wholesale Goods"
        }
    ],
    "sg:phone":"+1 909 725 0430",
    "sg:postcode":"92373",
    "sg:province":"CA",
    "sg:tags":[
        "fish"
    ],
    "wof:name":"Fish Guy",
    "wof:placetype":"venue"
},
  "geometry": {"coordinates":[-117.184409,34.045278],"type":"Point"}
}