{
  "type": "Feature",
  "properties": {
    "addr:full":"551 W Alondra Gardena CA 90248",
    "addr:housenumber":"551",
    "addr:postcode":"90248",
    "addr:street":"W Alondra",
    "iso:country":"US",
    "sg:address":"551 W Alondra",
    "sg:city":"Gardena",
    "sg:classifiers":[
        {
            "category":"Home & Garden",
            "subcategory":"Garden Supply",
            "type":"Retail Goods"
        }
    ],
    "sg:phone":"+1 310 505 2444",
    "sg:postcode":"90248",
    "sg:province":"CA",
    "sg:tags":[
        "nursery",
        "gardening"
    ],
    "sg:website":"www.jnursery.com",
    "wof:name":"Jauregui Nursery",
    "wof:placetype":"venue"
},
  "geometry": {"coordinates":[-118.284285,33.88544],"type":"Point"}
}