{
  "type": "Feature",
  "properties": {
    "iso:country":"US",
    "sg:address":"810 S Lakeview Ave Ste E",
    "sg:city":"Placentia",
    "sg:classifiers":[
        {
            "category":"Building & Trades",
            "subcategory":"Construction",
            "type":"Services"
        }
    ],
    "sg:phone":"+1 714 282 8178",
    "sg:postcode":"92870",
    "sg:province":"CA",
    "sg:tags":[
        "contractor"
    ],
    "sg:website":"www.air-concepts.com",
    "wof:name":"Air Concepts",
    "wof:placetype":"venue"
},
  "geometry": {"coordinates":[-117.81850300000001,33.865804],"type":"Point"}
}