{
  "type": "Feature",
  "properties": {
    "addr:full":"15 Forest View Dr San Francisco CA 94132",
    "addr:housenumber":"15",
    "addr:postcode":"94132",
    "addr:street":"Forest View Dr",
    "iso:country":"US",
    "sg:address":"15 Forest View Dr",
    "sg:city":"San Francisco",
    "sg:classifiers":[
        {
            "category":"Professional",
            "subcategory":"Computer Services",
            "type":"Services"
        }
    ],
    "sg:phone":"+1 415 731 1111",
    "sg:postcode":"94132",
    "sg:province":"CA",
    "sg:tags":[
        "consultant",
        "designer"
    ],
    "sg:website":"www.novani.com",
    "wof:name":"Novani",
    "wof:placetype":"venue"
},
  "geometry": {"coordinates":[-122.48372500000001,37.732635],"type":"Point"}
}