{
  "type": "Feature",
  "properties": {
    "iso:country":"US",
    "sg:address":"966 Gayley Ave",
    "sg:city":"Los Angeles",
    "sg:classifiers":[
        {
            "category":"Retail",
            "subcategory":"Laundry & Dry Cleaning",
            "type":"Services"
        }
    ],
    "sg:phone":"+1 310 208 1985",
    "sg:postcode":"90024",
    "sg:province":"CA",
    "sg:tags":[
        "cleaner"
    ],
    "wof:name":"Apple Cleaners",
    "wof:placetype":"venue"
},
  "geometry": {"coordinates":[-118.447998,34.062199],"type":"Point"}
}