{
  "type": "Feature",
  "properties": {
    "iso:country":"US",
    "sg:address":"11001 Sutter Ave",
    "sg:city":"Pacoima",
    "sg:classifiers":[
        {
            "category":"Building & Trades",
            "subcategory":"Construction",
            "type":"Services"
        }
    ],
    "sg:phone":"+1 818 834 1146",
    "sg:postcode":"91331",
    "sg:province":"CA",
    "sg:tags":[
        "fence",
        "contractor"
    ],
    "wof:name":"Action Iron Works Inc",
    "wof:placetype":"venue"
},
  "geometry": {"coordinates":[-118.425268,34.270375],"type":"Point"}
}