{
  "type": "Feature",
  "properties": {
    "iso:country":"US",
    "sg:address":"4807 Hopyard Rd",
    "sg:city":"Pleasanton",
    "sg:classifiers":[
        {
            "category":"Professional",
            "subcategory":"Employment Agencies",
            "type":"Services"
        }
    ],
    "sg:phone":"+1 925 734 0900",
    "sg:postcode":"94588",
    "sg:province":"CA",
    "sg:tags":[
        "opportunity",
        "contractor"
    ],
    "wof:name":"Placement Pros",
    "wof:placetype":"venue"
},
  "geometry": {"coordinates":[-121.903572,37.69159],"type":"Point"}
}