{
  "type": "Feature",
  "properties": {
    "iso:country":"US",
    "sg:address":"1374 N Pacific St",
    "sg:city":"Oceanside",
    "sg:classifiers":[
        {
            "category":"Fast Food",
            "type":"Food & Drink"
        }
    ],
    "sg:phone":"+1 760 967 6539",
    "sg:postcode":"92054",
    "sg:province":"CA",
    "sg:tags":[
        "burger"
    ],
    "sg:website":"www.mcdonalds.com",
    "wof:name":"McDonald's",
    "wof:placetype":"venue"
},
  "geometry": {"coordinates":[-117.393997,33.206001],"type":"Point"}
}