{
  "type": "Feature",
  "properties": {
    "iso:country":"US",
    "sg:address":"10815 Rancho Bernardo Rd",
    "sg:city":"San Diego",
    "sg:classifiers":[
        {
            "category":"Insurance",
            "subcategory":"Insurance Agent",
            "type":"Services"
        }
    ],
    "sg:phone":"+1 858 451 3421",
    "sg:postcode":"92127",
    "sg:province":"CA",
    "wof:name":"American Life Brokerage Assoc",
    "wof:placetype":"venue"
},
  "geometry": {"coordinates":[-117.096502,33.021986],"type":"Point"}
}