{
  "type": "Feature",
  "properties": {
    "addr:full":"190 Reamer St Auburn CA 95603",
    "addr:housenumber":"190",
    "addr:postcode":"ca 95603",
    "addr:street":"Reamer St",
    "iso:country":"US",
    "sg:address":"190 Reamer St",
    "sg:city":"Auburn",
    "sg:classifiers":[
        {
            "category":"Social Services",
            "subcategory":"Adult Care",
            "type":"Services"
        }
    ],
    "sg:phone":"+1 530 823 8422",
    "sg:postcode":"95603",
    "sg:province":"CA",
    "sg:tags":[
        "counseling",
        "senior",
        "citizen"
    ],
    "sg:website":"http://www.ombudservices.com",
    "wof:name":"Ombusman Services Of N Ca",
    "wof:placetype":"venue"
},
  "geometry": {"coordinates":[-121.070239,38.901922],"type":"Point"}
}