{
  "type": "Feature",
  "properties": {
    "addr:full":"3705 N Clovis Ave Fresno CA 93727",
    "addr:housenumber":"3705",
    "addr:postcode":"93727",
    "addr:street":"N Clovis Ave",
    "iso:country":"US",
    "sg:address":"3705 N Clovis Ave",
    "sg:city":"Fresno",
    "sg:classifiers":[
        {
            "category":"Manufacturing",
            "subcategory":"Signs",
            "type":"Manufacturing & Wholesale Goods"
        },
        {
            "category":"Professional",
            "subcategory":"Management & Consulting",
            "type":"Services"
        }
    ],
    "sg:phone":"+1 559 294 0458",
    "sg:postcode":"93727",
    "sg:province":"CA",
    "sg:tags":[
        "marketing",
        "consultant"
    ],
    "wof:name":"Specialized Printing & Prmtns",
    "wof:placetype":"venue"
},
  "geometry": {"coordinates":[-119.700613,36.785159],"type":"Point"}
}