{
  "type": "Feature",
  "properties": {
    "addr:full":"10230 Artesia Blvd #310 Bellflower CA 90706",
    "addr:housenumber":"10230",
    "addr:postcode":"90706",
    "addr:street":"Artesia Blvd # 310",
    "iso:country":"US",
    "sg:address":"10230 Artesia Blvd #310",
    "sg:city":"Bellflower",
    "sg:classifiers":[
        {
            "category":"Health Services",
            "subcategory":"Clinic",
            "type":"Services"
        }
    ],
    "sg:phone":"+1 562 461 0600",
    "sg:postcode":"90706",
    "sg:province":"CA",
    "sg:tags":[
        "medical"
    ],
    "sg:website":"www.myabbeycare.com",
    "wof:name":"Abbey Health & Palliative Care DBA Viva Hospice",
    "wof:placetype":"venue"
},
  "geometry": {"coordinates":[-118.116491,33.872888],"type":"Point"}
}