{
  "type": "Feature",
  "properties": {
    "iso:country":"US",
    "sg:address":"5284 Kanan Rd",
    "sg:city":"Agoura Hills",
    "sg:classifiers":[
        {
            "category":"Food & Beverages",
            "subcategory":"Groceries & Convenience Stores",
            "type":"Retail Goods"
        }
    ],
    "sg:phone":"+1 818 212 4324",
    "sg:postcode":"91301",
    "sg:province":"CA",
    "wof:name":"Agoura Market de Paris",
    "wof:placetype":"venue"
},
  "geometry": {"coordinates":[-118.76058399999999,34.148214],"type":"Point"}
}