{
  "type": "Feature",
  "properties": {
    "addr:full":"5340 Alla Road Suite 205 Los Angeles CA 90066",
    "addr:postcode":"5340;90066",
    "addr:street":"Alla Road Suite 205",
    "iso:country":"US",
    "sg:address":"5340 Alla Road Suite 205",
    "sg:city":"Los Angeles",
    "sg:classifiers":[
        {
            "category":"Professional",
            "subcategory":"Computer Services",
            "type":"Services"
        }
    ],
    "sg:postcode":"90066",
    "sg:province":"CA",
    "sg:website":"http://www.davinci-selectwork.com",
    "wof:name":"Davinci Selectwork",
    "wof:placetype":"venue"
},
  "geometry": {"coordinates":[-118.42566600000001,33.977199],"type":"Point"}
}