{
  "type": "Feature",
  "properties": {
    "addr:full":"980 Camino De La Reina Suite D San Diego CA 92108",
    "addr:housenumber":"980",
    "addr:postcode":"92108",
    "addr:street":"Camino De La Reina Suite D",
    "iso:country":"US",
    "sg:address":"980 Camino De La Reina Suite D",
    "sg:city":"San Diego",
    "sg:classifiers":[
        {
            "category":"Shopping",
            "subcategory":"Mobile Phones",
            "type":"Retail Goods"
        }
    ],
    "sg:phone":"+1 619 209 5818",
    "sg:postcode":"92108",
    "sg:province":"CA",
    "sg:website":"www.VerizonWireless.com",
    "wof:name":"Verizon Wireless",
    "wof:placetype":"venue"
},
  "geometry": {"coordinates":[-117.154612,32.768413],"type":"Point"}
}