{
  "type": "Feature",
  "properties": {
    "iso:country":"US",
    "sg:address":"20629 Redwood Rd",
    "sg:city":"Castro Valley",
    "sg:classifiers":[
        {
            "category":"Building & Trades",
            "subcategory":"Landscaping Services",
            "type":"Services"
        }
    ],
    "sg:phone":"+1 510 727 6760",
    "sg:postcode":"94546",
    "sg:province":"CA",
    "sg:tags":[
        "tree"
    ],
    "wof:name":"Ed's Tree Svc",
    "wof:placetype":"venue"
},
  "geometry": {"coordinates":[-122.074041,37.696272],"type":"Point"}
}