{
  "type": "Feature",
  "properties": {
    "iso:country":"US",
    "sg:address":"143 W Center Street Promenade",
    "sg:city":"Anaheim",
    "sg:classifiers":[
        {
            "category":"Travel",
            "subcategory":"Travel Agent",
            "type":"Entertainment"
        }
    ],
    "sg:phone":"+1 714 533 8200",
    "sg:postcode":"92805",
    "sg:province":"CA",
    "sg:tags":[
        "agency"
    ],
    "wof:name":"Cruise Holidays of Anaheim",
    "wof:placetype":"venue"
},
  "geometry": {"coordinates":[-117.91421699999999,33.834148],"type":"Point"}
}