{
  "type": "Feature",
  "properties": {
    "iso:country":"US",
    "sg:address":"6001 W Sunset Blvd",
    "sg:city":"Los Angeles",
    "sg:classifiers":[
        {
            "category":"Manufacturing",
            "subcategory":"Printing",
            "type":"Manufacturing & Wholesale Goods"
        }
    ],
    "sg:phone":"+1 323 467 6048",
    "sg:postcode":"90028",
    "sg:province":"CA",
    "sg:tags":[
        "printer"
    ],
    "wof:name":"Budget Printing Ctr",
    "wof:placetype":"venue"
},
  "geometry": {"coordinates":[-118.319226,34.098115],"type":"Point"}
}