{
  "type": "Feature",
  "properties": {
    "addr:full":"60 Leveroni Ct Novato CA 94949",
    "addr:housenumber":"60",
    "addr:postcode":"94949",
    "addr:street":"Leveroni Ct",
    "iso:country":"US",
    "sg:address":"60 Leveroni Ct",
    "sg:city":"Novato",
    "sg:classifiers":[
        {
            "category":"Shopping",
            "subcategory":"Luggage & Leather Goods",
            "type":"Retail Goods"
        }
    ],
    "sg:phone":"+1 415 382 1855",
    "sg:postcode":"94949",
    "sg:province":"CA",
    "sg:tags":[
        "travel",
        "accessory"
    ],
    "sg:website":"www.travelsmith.com",
    "wof:name":"Travel Smith Outfitters",
    "wof:placetype":"venue"
},
  "geometry": {"coordinates":[-122.531881,38.07177],"type":"Point"}
}