{
  "type": "Feature",
  "properties": {
    "addr:full":"655 Palm Canyon Dr Borrego Springs CA 92004",
    "addr:housenumber":"655",
    "addr:postcode":"92004",
    "addr:street":"Palm Canyon Dr",
    "iso:country":"US",
    "sg:address":"655 Palm Canyon Dr",
    "sg:city":"Borrego Springs",
    "sg:classifiers":[
        {
            "category":"Restaurant",
            "type":"Food & Drink"
        }
    ],
    "sg:phone":"+1 760 767 1008",
    "sg:postcode":"92004",
    "sg:province":"CA",
    "wof:name":"Jilberto's Taco Shop",
    "wof:placetype":"venue"
},
  "geometry": {"coordinates":[-116.37734399999999,33.256479],"type":"Point"}
}