{
  "type": "Feature",
  "properties": {
    "addr:full":"32 Yerba Buena Ave Los Altos CA 94022",
    "addr:housenumber":"32",
    "addr:postcode":"94022",
    "addr:street":"Yerba Buena Ave",
    "iso:country":"US",
    "sg:address":"32 Yerba Buena Ave",
    "sg:city":"Los Altos",
    "sg:classifiers":[
        {
            "category":"Travel",
            "subcategory":"Travel Agent",
            "type":"Entertainment"
        }
    ],
    "sg:phone":"+1 650 941 1679",
    "sg:postcode":"94022",
    "sg:province":"CA",
    "sg:tags":[
        "operator",
        "tour"
    ],
    "wof:name":"Dream Cruises & Tours",
    "wof:placetype":"venue"
},
  "geometry": {"coordinates":[-122.115382,37.38768],"type":"Point"}
}