{
  "type": "Feature",
  "properties": {
    "iso:country":"US",
    "sg:address":"3742 Cedarwood Ct",
    "sg:city":"Rosamond",
    "sg:classifiers":[
        {
            "category":"Insurance",
            "subcategory":"Insurance Agent",
            "type":"Services"
        }
    ],
    "sg:phone":"+1 661 256 1150",
    "sg:postcode":"93560",
    "sg:province":"CA",
    "wof:name":"Rosamond Insurance",
    "wof:placetype":"venue"
},
  "geometry": {"coordinates":[-118.197909,34.855318],"type":"Point"}
}