{
  "type": "Feature",
  "properties": {
    "addr:full":"18884 Hesperian Blvd Hayward CA 94543",
    "addr:housenumber":"18884",
    "addr:postcode":"94543",
    "addr:street":"Hesperian Blvd",
    "iso:country":"US",
    "sg:address":"18884 Hesperian Blvd",
    "sg:city":"Hayward",
    "sg:classifiers":[
        {
            "category":"Shopping",
            "subcategory":"Tobacco",
            "type":"Retail Goods"
        }
    ],
    "sg:postcode":"94543",
    "sg:province":"CA",
    "sg:tags":[
        "shop"
    ],
    "wof:name":"Star Zone Smoke Shop",
    "wof:placetype":"venue"
},
  "geometry": {"coordinates":[-122.104304,37.643173],"type":"Point"}
}