{
  "type": "Feature",
  "properties": {
    "addr:full":"2612 Alcatraz Avenue Berkeley CA 94705",
    "addr:housenumber":"2612",
    "addr:postcode":"94705",
    "addr:street":"Alcatraz Avenue",
    "iso:country":"US",
    "sg:address":"2612 Alcatraz Avenue",
    "sg:city":"Berkeley",
    "sg:classifiers":[
        {
            "category":"Personal",
            "subcategory":"Beauty Salon",
            "type":"Services"
        },
        {
            "category":"Personal",
            "subcategory":"Skin Care",
            "type":"Services"
        }
    ],
    "sg:phone":"+1 510 654 6400",
    "sg:postcode":"94705",
    "sg:province":"CA",
    "wof:name":"Chez Aesthete In Rockridge",
    "wof:placetype":"venue"
},
  "geometry": {"coordinates":[-122.252876,37.851182],"type":"Point"}
}