{
  "type": "Feature",
  "properties": {
    "addr:full":"243 W Ventura Blvd Ste B Camarillo CA 93010",
    "addr:housenumber":"243",
    "addr:postcode":"93010",
    "addr:street":"W Ventura Blvd Ste B",
    "iso:country":"US",
    "sg:address":"243 W Ventura Blvd Ste B",
    "sg:city":"Camarillo",
    "sg:classifiers":[
        {
            "category":"Personal",
            "subcategory":"Nail Salon",
            "type":"Services"
        }
    ],
    "sg:phone":"+1 805 484 6687",
    "sg:postcode":"93010",
    "sg:province":"CA",
    "wof:name":"Nail Company",
    "wof:placetype":"venue"
},
  "geometry": {"coordinates":[-119.081001,34.2197],"type":"Point"}
}