{
  "type": "Feature",
  "properties": {
    "iso:country":"US",
    "sg:address":"1574 Washington Blvd",
    "sg:city":"Fremont",
    "sg:classifiers":[
        {
            "category":"Health Services",
            "subcategory":"Health Practitioner",
            "type":"Services"
        }
    ],
    "sg:phone":"+1 510 656 1047",
    "sg:postcode":"94539",
    "sg:province":"CA",
    "sg:tags":[
        "acupuncture"
    ],
    "wof:name":"Peace Acupuncture Clinic",
    "wof:placetype":"venue"
},
  "geometry": {"coordinates":[-121.935131,37.531363],"type":"Point"}
}