{
  "type": "Feature",
  "properties": {
    "iso:country":"US",
    "sg:address":"500 S 3rd St",
    "sg:city":"Burbank",
    "sg:classifiers":[
        {
            "category":"Professional",
            "subcategory":"Management & Consulting",
            "type":"Services"
        }
    ],
    "sg:phone":"+1 818 238 9321",
    "sg:postcode":"91502",
    "sg:province":"CA",
    "sg:tags":[
        "public",
        "speaking"
    ],
    "wof:name":"Bazyn Communications",
    "wof:placetype":"venue"
},
  "geometry": {"coordinates":[-118.303021,34.178816],"type":"Point"}
}