{
  "type": "Feature",
  "properties": {
    "iso:country":"US",
    "sg:address":"23639 Sunnymead Blvd",
    "sg:city":"Moreno Valley",
    "sg:classifiers":[
        {
            "category":"Restaurant",
            "type":"Food & Drink"
        }
    ],
    "sg:phone":"+1 951 243 6600",
    "sg:postcode":"92553",
    "sg:province":"CA",
    "wof:name":"Rockin Java Cafe",
    "wof:placetype":"venue"
},
  "geometry": {"coordinates":[-117.25210199999999,33.938875],"type":"Point"}
}