{
  "type": "Feature",
  "properties": {
    "iso:country":"US",
    "sg:address":"15710 Almaden Rd",
    "sg:city":"Los Gatos",
    "sg:classifiers":[
        {
            "category":"Building & Trades",
            "subcategory":"Construction",
            "type":"Services"
        }
    ],
    "sg:phone":"+1 408 852 0473",
    "sg:postcode":"95032",
    "sg:province":"CA",
    "sg:tags":[
        "contractor"
    ],
    "sg:website":"www.firefloodwaterdamage.com/",
    "wof:name":"Superb Restoration Services",
    "wof:placetype":"venue"
},
  "geometry": {"coordinates":[-121.94417799999999,37.24301],"type":"Point"}
}