{
  "type": "Feature",
  "properties": {
    "addr:full":"900 Market St Oakland CA 94607",
    "addr:housenumber":"900",
    "addr:postcode":"94607",
    "addr:street":"Market St",
    "iso:country":"US",
    "sg:address":"900 Market St",
    "sg:city":"Oakland",
    "sg:classifiers":[
        {
            "category":"Shopping",
            "subcategory":"Clothing, Apparel, & Fashions",
            "type":"Retail Goods"
        }
    ],
    "sg:phone":"+1 510 832 2011",
    "sg:postcode":"94607",
    "sg:province":"CA",
    "wof:name":"One Price Clothing Store",
    "wof:placetype":"venue"
},
  "geometry": {"coordinates":[-122.282349,37.804479],"type":"Point"}
}