{
  "type": "Feature",
  "properties": {
    "addr:full":"10630 Chapman Ave Garden Grove CA 92840",
    "addr:housenumber":"10630",
    "addr:postcode":"92840",
    "addr:street":"Chapman Ave",
    "iso:country":"US",
    "sg:address":"10630 Chapman Ave",
    "sg:city":"Garden Grove",
    "sg:classifiers":[
        {
            "category":"Retail",
            "subcategory":"Funeral Services",
            "type":"Services"
        }
    ],
    "sg:phone":"+1 714 997 1234",
    "sg:postcode":"92840",
    "sg:province":"CA",
    "sg:tags":[
        "cemetery"
    ],
    "sg:website":"www.dimondshannonmortuary.com",
    "wof:name":"Dimond & Shannon Mortuary",
    "wof:placetype":"venue"
},
  "geometry": {"coordinates":[-117.94699900000001,33.788502],"type":"Point"}
}