{
  "type": "Feature",
  "properties": {
    "addr:full":"11740 San Vicente Blvd Los Angeles CA 90049",
    "addr:housenumber":"11740",
    "addr:postcode":"90049",
    "addr:street":"San Vicente Blvd",
    "iso:country":"US",
    "sg:address":"11740 San Vicente Blvd",
    "sg:city":"Los Angeles",
    "sg:classifiers":[
        {
            "category":"Professional",
            "subcategory":"Management & Consulting",
            "type":"Services"
        }
    ],
    "sg:phone":"+1 310 207 3100",
    "sg:postcode":"90049",
    "sg:province":"CA",
    "sg:tags":[
        "consultant",
        "business"
    ],
    "wof:name":"Malibu Consulting Corp",
    "wof:placetype":"venue"
},
  "geometry": {"coordinates":[-118.465931,34.053373],"type":"Point"}
}