{
  "type": "Feature",
  "properties": {
    "iso:country":"US",
    "sg:address":"1300 W Whittier Blvd",
    "sg:city":"La Habra",
    "sg:classifiers":[
        {
            "category":"Restaurant",
            "type":"Food & Drink"
        }
    ],
    "sg:menulink":"http://www.allmenus.com/ca/anaheim-santa-ana-garden-grove/213338-taco-bell/menu/",
    "sg:phone":"+1 562 691 7331",
    "sg:postcode":"90631",
    "sg:province":"CA",
    "sg:tags":[
        "mexican"
    ],
    "wof:name":"Taco Bell",
    "wof:placetype":"venue"
},
  "geometry": {"coordinates":[-117.96065400000001,33.938874],"type":"Point"}
}