{
  "type": "Feature",
  "properties": {
    "iso:country":"US",
    "sg:address":"1733 E Robidoux St",
    "sg:city":"Wilmington",
    "sg:classifiers":[
        {
            "category":"Utilities",
            "subcategory":"Refuse",
            "type":"Services"
        }
    ],
    "sg:phone":"+1 310 830 2161",
    "sg:postcode":"90744",
    "sg:province":"CA",
    "sg:tags":[
        "garbage",
        "collection"
    ],
    "wof:name":"Adivari Inc",
    "wof:placetype":"venue"
},
  "geometry": {"coordinates":[-118.23918,33.788875],"type":"Point"}
}