{
  "type": "Feature",
  "properties": {
    "iso:country":"US",
    "sg:address":"310 E Pico Blvd",
    "sg:city":"Los Angeles",
    "sg:classifiers":[
        {
            "category":"Wholesale",
            "subcategory":"Apparel",
            "type":"Manufacturing & Wholesale Goods"
        }
    ],
    "sg:phone":"+1 213 748 7131",
    "sg:postcode":"90015",
    "sg:province":"CA",
    "sg:tags":[
        "clothing"
    ],
    "wof:name":"Studio X T C",
    "wof:placetype":"venue"
},
  "geometry": {"coordinates":[-118.257351,34.034559],"type":"Point"}
}