{
  "type": "Feature",
  "properties": {
    "iso:country":"US",
    "sg:address":"515 Marxmiller Pl",
    "sg:city":"Goleta",
    "sg:classifiers":[
        {
            "category":"Airline",
            "type":"Transportation"
        }
    ],
    "sg:phone":"+1 805 452 4139",
    "sg:postcode":"93117",
    "sg:province":"CA",
    "sg:tags":[
        "nonscheduled",
        "air"
    ],
    "wof:name":"Decant Air L L C",
    "wof:placetype":"venue"
},
  "geometry": {"coordinates":[-119.835652,34.43314],"type":"Point"}
}