{
  "type": "Feature",
  "properties": {
    "iso:country":"US",
    "sg:address":"1640 Grey Owl Cir",
    "sg:city":"Roseville",
    "sg:classifiers":[
        {
            "category":"Professional",
            "subcategory":"Business Services",
            "type":"Services"
        }
    ],
    "sg:phone":"+1 916 797 6015",
    "sg:postcode":"95661",
    "sg:province":"CA",
    "sg:tags":[
        "appraiser"
    ],
    "wof:name":"Colleen Hanamura",
    "wof:placetype":"venue"
},
  "geometry": {"coordinates":[-121.24030999999999,38.762422],"type":"Point"}
}