{
  "type": "Feature",
  "properties": {
    "addr:full":"8361 Rembrandt Dr Huntington Beach CA 92647",
    "addr:housenumber":"8361",
    "addr:postcode":"92647",
    "addr:street":"Rembrandt Dr",
    "iso:country":"US",
    "sg:address":"8361 Rembrandt Dr",
    "sg:city":"Huntington Beach",
    "sg:classifiers":[
        {
            "category":"Professional",
            "type":"Services"
        }
    ],
    "sg:phone":"+1 714 848 2486",
    "sg:postcode":"92647",
    "sg:province":"CA",
    "wof:name":"Pamela Anderson",
    "wof:placetype":"venue"
},
  "geometry": {"coordinates":[-117.982122,33.713942],"type":"Point"}
}