{
  "type": "Feature",
  "properties": {
    "addr:full":"97 Natoma St Folsom CA 95630",
    "addr:housenumber":"97",
    "addr:postcode":"95630",
    "addr:street":"Natoma St",
    "iso:country":"US",
    "sg:address":"97 Natoma St",
    "sg:city":"Folsom",
    "sg:classifiers":[
        {
            "category":"Personal",
            "subcategory":"Tattoo Parlor",
            "type":"Services"
        }
    ],
    "sg:phone":"+1 916 355 8008",
    "sg:postcode":"95630",
    "sg:province":"CA",
    "sg:tags":[
        "tattooing"
    ],
    "wof:name":"Folsom City Ink",
    "wof:placetype":"venue"
},
  "geometry": {"coordinates":[-121.162554,38.681804],"type":"Point"}
}