{
  "type": "Feature",
  "properties": {
    "addr:full":"1355 Evans Ave San Francisco CA 94124",
    "addr:housenumber":"1355",
    "addr:postcode":"94124",
    "addr:street":"Evans Ave",
    "iso:country":"US",
    "sg:address":"1355 Evans Ave",
    "sg:city":"San Francisco",
    "sg:classifiers":[
        {
            "category":"Manufacturing",
            "subcategory":"Apparel",
            "type":"Manufacturing & Wholesale Goods"
        }
    ],
    "sg:phone":"+1 916 448 1187",
    "sg:postcode":"94124",
    "sg:province":"CA",
    "sg:tags":[
        "flag",
        "banner",
        "mfg"
    ],
    "wof:name":"Sacramento Flag Works",
    "wof:placetype":"venue"
},
  "geometry": {"coordinates":[-122.382452,37.739105],"type":"Point"}
}