{
  "type": "Feature",
  "properties": {
    "iso:country":"US",
    "sg:address":"136 Taylor Ct",
    "sg:city":"Oceanside",
    "sg:classifiers":[
        {
            "category":"Shopping",
            "subcategory":"Catalog Store",
            "type":"Retail Goods"
        }
    ],
    "sg:phone":"+1 760 430 8443",
    "sg:postcode":"92058",
    "sg:province":"CA",
    "sg:tags":[
        "mail",
        "house"
    ],
    "wof:name":"Devine Creations By Trisha",
    "wof:placetype":"venue"
},
  "geometry": {"coordinates":[-117.40633800000001,33.250904],"type":"Point"}
}