{
  "type": "Feature",
  "properties": {
    "addr:full":"164 E Florence Ave Los Angeles CA 90003",
    "addr:housenumber":"164",
    "addr:postcode":"90003",
    "addr:street":"E Florence Ave",
    "iso:country":"US",
    "sg:address":"164 E Florence Ave",
    "sg:city":"Los Angeles",
    "sg:classifiers":[
        {
            "category":"Retail",
            "subcategory":"Repair Shop",
            "type":"Services"
        }
    ],
    "sg:phone":"+1 323 759 6447",
    "sg:postcode":"90003",
    "sg:province":"CA",
    "sg:tags":[
        "welding"
    ],
    "wof:name":"Hayes Welding",
    "wof:placetype":"venue"
},
  "geometry": {"coordinates":[-118.27072,33.974632],"type":"Point"}
}