{
  "type": "Feature",
  "properties": {
    "addr:full":"172 Valley Hill Dr Moraga CA 94556",
    "addr:housenumber":"172",
    "addr:postcode":"94556",
    "addr:street":"Valley Hill Dr",
    "iso:country":"US",
    "sg:address":"172 Valley Hill Dr",
    "sg:city":"Moraga",
    "sg:classifiers":[
        {
            "category":"Building & Trades",
            "subcategory":"Construction",
            "type":"Services"
        }
    ],
    "sg:phone":"+1 925 376 6807",
    "sg:postcode":"94556",
    "sg:province":"CA",
    "sg:tags":[
        "road",
        "contractor"
    ],
    "wof:name":"Polk Construction Co",
    "wof:placetype":"venue"
},
  "geometry": {"coordinates":[-122.08780899999999,37.84102],"type":"Point"}
}