{
  "type": "Feature",
  "properties": {
    "addr:full":"5730 E Los Angeles Ave Simi Valley CA 93063",
    "addr:housenumber":"5730",
    "addr:postcode":"93063",
    "addr:street":"E Los Angeles Ave",
    "iso:country":"US",
    "sg:address":"5730 E Los Angeles Ave",
    "sg:city":"Simi Valley",
    "sg:classifiers":[
        {
            "category":"Personal",
            "type":"Services"
        }
    ],
    "sg:phone":"+1 805 582 0400",
    "sg:postcode":"93063",
    "sg:province":"CA",
    "sg:tags":[
        "therapist",
        "massage"
    ],
    "sg:website":"www.body-by-design.com",
    "wof:name":"Body By Design",
    "wof:placetype":"venue"
},
  "geometry": {"coordinates":[-118.67963399999999,34.271655],"type":"Point"}
}