{
  "type": "Feature",
  "properties": {
    "addr:full":"1100 W Line St Bishop CA 93514",
    "addr:housenumber":"1100",
    "addr:postcode":"93514",
    "addr:street":"W Line St",
    "iso:country":"US",
    "sg:address":"1100 W Line St",
    "sg:city":"Bishop",
    "sg:classifiers":[
        {
            "category":"Organizations",
            "subcategory":"Religious Organization",
            "type":"Services"
        }
    ],
    "sg:phone":"+1 760 872 8136",
    "sg:postcode":"93514",
    "sg:province":"CA",
    "sg:tags":[
        "church"
    ],
    "sg:website":"www.cbcbishop.org",
    "wof:name":"Calvary Baptist Church",
    "wof:placetype":"venue"
},
  "geometry": {"coordinates":[-118.408298,37.361316],"type":"Point"}
}