{
  "type": "Feature",
  "properties": {
    "addr:full":"660 Commerce Dr Roseville CA 95678",
    "addr:housenumber":"660",
    "addr:postcode":"95678",
    "addr:street":"Commerce Dr",
    "iso:country":"US",
    "sg:address":"660 Commerce Dr",
    "sg:city":"Roseville",
    "sg:classifiers":[
        {
            "category":"Building & Trades",
            "subcategory":"Construction",
            "type":"Services"
        }
    ],
    "sg:phone":"+1 916 786 2580",
    "sg:postcode":"95678",
    "sg:province":"CA",
    "sg:tags":[
        "control",
        "erosion"
    ],
    "wof:name":"SWPP-Eze Inc",
    "wof:placetype":"venue"
},
  "geometry": {"coordinates":[-121.30224800000001,38.7279],"type":"Point"}
}