{
  "type": "Feature",
  "properties": {
    "addr:full":"13200 Gainsway Ct La Mirada CA 90638",
    "addr:housenumber":"13200",
    "addr:postcode":"90638",
    "addr:street":"Gainsway Ct",
    "iso:country":"US",
    "sg:address":"13200 Gainsway Ct",
    "sg:city":"La Mirada",
    "sg:classifiers":[
        {
            "category":"Local Transit",
            "type":"Transportation"
        }
    ],
    "sg:phone":"+1 562 500 5466",
    "sg:postcode":"90638",
    "sg:province":"CA",
    "sg:tags":[
        "passenger"
    ],
    "wof:name":"Daleryam West Army",
    "wof:placetype":"venue"
},
  "geometry": {"coordinates":[-117.979006,33.91167],"type":"Point"}
}