{
  "type": "Feature",
  "properties": {
    "addr:full":"11341 Sunrise Park Dr Rancho Cordova CA 95742",
    "addr:housenumber":"11341",
    "addr:postcode":"95742",
    "addr:street":"Sunrise Park Dr",
    "iso:country":"US",
    "sg:address":"11341 Sunrise Park Dr",
    "sg:city":"Rancho Cordova",
    "sg:classifiers":[
        {
            "category":"Home & Garden",
            "subcategory":"Carpets & Floor Coverings",
            "type":"Retail Goods"
        }
    ],
    "sg:phone":"+1 916 858 8200",
    "sg:postcode":"95742",
    "sg:province":"CA",
    "sg:tags":[
        "dealer",
        "rug"
    ],
    "sg:website":"www.aflooring.com",
    "wof:name":"Advanced Flooring Inc",
    "wof:placetype":"venue"
},
  "geometry": {"coordinates":[-121.26174399999999,38.594365],"type":"Point"}
}