{
  "type": "Feature",
  "properties": {
    "iso:country":"US",
    "sg:address":"9135 Judicial Drive",
    "sg:city":"San Diego",
    "sg:classifiers":[
        {
            "category":"Personal",
            "subcategory":"Beauty Salon",
            "type":"Services"
        }
    ],
    "sg:phone":"+1 858 558 0505",
    "sg:postcode":"92122",
    "sg:province":"CA",
    "sg:tags":[
        "hair"
    ],
    "wof:name":"Oasis Hair Salon",
    "wof:placetype":"venue"
},
  "geometry": {"coordinates":[-117.20292999999999,32.873172],"type":"Point"}
}