{
  "type": "Feature",
  "properties": {
    "iso:country":"US",
    "sg:address":"4500 Hollister Ave",
    "sg:city":"Santa Barbara",
    "sg:classifiers":[
        {
            "category":"Education",
            "subcategory":"School",
            "type":"Public Place"
        }
    ],
    "sg:phone":"+1 805 967 8399",
    "sg:postcode":"93110",
    "sg:province":"CA",
    "wof:name":"Villa Esperanza School",
    "wof:placetype":"venue"
},
  "geometry": {"coordinates":[-119.77266899999999,34.439679],"type":"Point"}
}