{
  "type": "Feature",
  "properties": {
    "iso:country":"US",
    "sg:address":"675 Balour Dr",
    "sg:city":"Encinitas",
    "sg:classifiers":[
        {
            "category":"Education",
            "subcategory":"School",
            "type":"Public Place"
        }
    ],
    "sg:phone":"+1 760 753 6241",
    "sg:postcode":"92024",
    "sg:province":"CA",
    "sg:tags":[
        "high",
        "middle"
    ],
    "wof:name":"Oak Crest Middle School",
    "wof:placetype":"venue"
},
  "geometry": {"coordinates":[-117.26799800000001,33.042702],"type":"Point"}
}