{
  "type": "Feature",
  "properties": {
    "iso:country":"US",
    "sg:address":"555 University Avenue",
    "sg:city":"Sacramento",
    "sg:classifiers":[
        {
            "category":"Health Services",
            "subcategory":"Doctor",
            "type":"Services"
        }
    ],
    "sg:phone":"+1 916 648 9912",
    "sg:postcode":"95825",
    "sg:province":"CA",
    "wof:name":"Arden Pierre MD Ph D",
    "wof:placetype":"venue"
},
  "geometry": {"coordinates":[-121.418746,38.568509],"type":"Point"}
}