{
  "type": "Feature",
  "properties": {
    "addr:full":"3419 Via Lido Newport Beach CA 92663",
    "addr:housenumber":"3419",
    "addr:postcode":"92663",
    "addr:street":"Via Lido",
    "iso:country":"US",
    "sg:address":"3419 Via Lido",
    "sg:city":"Newport Beach",
    "sg:classifiers":[
        {
            "category":"Professional",
            "subcategory":"Lawyer & Legal Services",
            "type":"Services"
        }
    ],
    "sg:phone":"+1 949 661 1651",
    "sg:postcode":"92663",
    "sg:province":"CA",
    "sg:tags":[
        "attorney"
    ],
    "wof:name":"Auto Accident Information",
    "wof:placetype":"venue"
},
  "geometry": {"coordinates":[-117.92964499999999,33.618333],"type":"Point"}
}