{
  "type": "Feature",
  "properties": {
    "iso:country":"US",
    "sg:address":"3419 Via Lido",
    "sg:city":"Newport Beach",
    "sg:classifiers":[
        {
            "category":"Professional",
            "subcategory":"Lawyer & Legal Services",
            "type":"Services"
        }
    ],
    "sg:phone":"+1 949 661 1651",
    "sg:postcode":"92663",
    "sg:province":"CA",
    "sg:tags":[
        "attorney"
    ],
    "wof:name":"Auto Accident Information",
    "wof:placetype":"venue"
},
  "geometry": {"coordinates":[-117.929645,33.618333],"type":"Point"}
}