{
  "type": "Feature",
  "properties": {
    "addr:full":"2844 21st St San Francisco CA 94110",
    "addr:housenumber":"2844",
    "addr:postcode":"94110",
    "addr:street":"21St St",
    "iso:country":"US",
    "sg:address":"2844 21st St",
    "sg:city":"San Francisco",
    "sg:classifiers":[
        {
            "category":"Building & Trades",
            "subcategory":"Plumbing",
            "type":"Services"
        }
    ],
    "sg:phone":"+1 415 826 9602",
    "sg:postcode":"94110",
    "sg:province":"CA",
    "sg:tags":[
        "plumbing",
        "heating",
        "air"
    ],
    "wof:name":"Bautista Construction Co",
    "wof:placetype":"venue"
},
  "geometry": {"coordinates":[-122.41225900000001,37.757512],"type":"Point"}
}