{
  "type": "Feature",
  "properties": {
    "iso:country":"US",
    "sg:address":"18402 Halsted St",
    "sg:city":"Northridge",
    "sg:classifiers":[
        {
            "category":"Travel",
            "subcategory":"Travel Agent",
            "type":"Entertainment"
        }
    ],
    "sg:phone":"+1 818 727 7492",
    "sg:postcode":"91325",
    "sg:province":"CA",
    "sg:tags":[
        "agency"
    ],
    "wof:name":"Virgin Travels",
    "wof:placetype":"venue"
},
  "geometry": {"coordinates":[-118.532088,34.24449],"type":"Point"}
}