{
  "type": "Feature",
  "properties": {
    "addr:full":"1645 Donlon St Ventura CA 93003",
    "addr:housenumber":"1645",
    "addr:postcode":"93003",
    "addr:street":"Donlon St",
    "iso:country":"US",
    "sg:address":"1645 Donlon St",
    "sg:city":"Ventura",
    "sg:classifiers":[
        {
            "category":"Shopping",
            "type":"Retail Goods"
        },
        {
            "category":"Manufacturing",
            "subcategory":"Tools & Machinery",
            "type":"Manufacturing & Wholesale Goods"
        }
    ],
    "sg:phone":"+1 805 339 0670",
    "sg:postcode":"93003",
    "sg:province":"CA",
    "sg:tags":[
        "limb",
        "component",
        "prosthetic",
        "artificial",
        "mfg"
    ],
    "wof:name":"Ventura Prosthetics & Orthotic",
    "wof:placetype":"venue"
},
  "geometry": {"coordinates":[-119.23586,34.260312],"type":"Point"}
}