{
  "type": "Feature",
  "properties": {
    "iso:country":"US",
    "sg:address":"8300 Fair Oaks Blvd",
    "sg:city":"Carmichael",
    "sg:classifiers":[
        {
            "category":"Real Estate",
            "subcategory":"Real Estate Services",
            "type":"Services"
        }
    ],
    "sg:phone":"+1 916 944 0571",
    "sg:postcode":"95608",
    "sg:province":"CA",
    "wof:name":"Dick Armstrong Real Estate",
    "wof:placetype":"venue"
},
  "geometry": {"coordinates":[-121.308998,38.636501],"type":"Point"}
}