{
  "type": "Feature",
  "properties": {
    "addr:full":"24747 San Fernando Rd Santa Clarita CA 91321",
    "addr:housenumber":"24747",
    "addr:postcode":"91321",
    "addr:street":"San Fernando Rd",
    "iso:country":"US",
    "sg:address":"24747 San Fernando Rd",
    "sg:city":"Santa Clarita",
    "sg:classifiers":[
        {
            "category":"Wholesale",
            "subcategory":"Computers",
            "type":"Manufacturing & Wholesale Goods"
        }
    ],
    "sg:phone":"+1 661 799 1700",
    "sg:postcode":"91321",
    "sg:province":"CA",
    "sg:tags":[
        "printer",
        "laser"
    ],
    "wof:name":"Technicon",
    "wof:placetype":"venue"
},
  "geometry": {"coordinates":[-118.53174799999999,34.385198],"type":"Point"}
}