{
  "type": "Feature",
  "properties": {
    "addr:full":"1221 Alhambra Boulevard Sacramento CA 95816",
    "addr:housenumber":"1221",
    "addr:postcode":"95816",
    "addr:street":"Alhambra Boulevard",
    "iso:country":"US",
    "sg:address":"1221 Alhambra Boulevard",
    "sg:city":"Sacramento",
    "sg:classifiers":[
        {
            "category":"Health Services",
            "subcategory":"Chiropractor",
            "type":"Services"
        }
    ],
    "sg:phone":"+1 916 451 5552",
    "sg:postcode":"95816",
    "sg:province":"CA",
    "wof:name":"Guenther William W DC-Fort Sutter Chiropractic",
    "wof:placetype":"venue"
},
  "geometry": {"coordinates":[-121.46641200000001,38.569954],"type":"Point"}
}