{
  "type": "Feature",
  "properties": {
    "addr:full":"1503 Grant Road Mountain View CA 94040",
    "addr:housenumber":"1503",
    "addr:postcode":"94040",
    "addr:street":"Grant Road",
    "iso:country":"US",
    "sg:address":"1503 Grant Road",
    "sg:city":"Mountain View",
    "sg:classifiers":[
        {
            "category":"Health Services",
            "subcategory":"Doctor",
            "type":"Services"
        }
    ],
    "sg:phone":"+1 650 691 0611",
    "sg:postcode":"94040",
    "sg:province":"CA",
    "wof:name":"Hoar Paul F MD",
    "wof:placetype":"venue"
},
  "geometry": {"coordinates":[-122.08532599999999,37.386369],"type":"Point"}
}