{
  "type": "Feature",
  "properties": {
    "addr:full":"1729 Del Valle Ave Glendale CA 91208",
    "addr:housenumber":"1729",
    "addr:postcode":"91208",
    "addr:street":"Del Valle Ave",
    "iso:country":"US",
    "sg:address":"1729 Del Valle Ave",
    "sg:city":"Glendale",
    "sg:classifiers":[
        {
            "category":"Building & Trades",
            "subcategory":"Electrical",
            "type":"Services"
        }
    ],
    "sg:phone":"+1 818 548 4260",
    "sg:postcode":"91208",
    "sg:province":"CA",
    "sg:tags":[
        "electrician"
    ],
    "wof:name":"Lombardo Electric",
    "wof:placetype":"venue"
},
  "geometry": {"coordinates":[-118.227997,34.184299],"type":"Point"}
}