{
  "type": "Feature",
  "properties": {
    "iso:country":"US",
    "sg:address":"1314 7th St",
    "sg:city":"Santa Monica",
    "sg:classifiers":[
        {
            "category":"Building & Trades",
            "subcategory":"Construction",
            "type":"Services"
        }
    ],
    "sg:phone":"+1 310 393 9608",
    "sg:postcode":"90401",
    "sg:province":"CA",
    "sg:tags":[
        "contractor"
    ],
    "wof:name":"Independent Concrete",
    "wof:placetype":"venue"
},
  "geometry": {"coordinates":[-118.49259,34.018846],"type":"Point"}
}