{
  "type": "Feature",
  "properties": {
    "addr:full":"7919 Folsom Blvd Sacramento CA 95826",
    "addr:housenumber":"7919",
    "addr:postcode":"95826",
    "addr:street":"Folsom Blvd",
    "iso:country":"US",
    "sg:address":"7919 Folsom Blvd",
    "sg:city":"Sacramento",
    "sg:classifiers":[
        {
            "category":"Professional",
            "subcategory":"Research",
            "type":"Services"
        }
    ],
    "sg:phone":"+1 916 923 1097",
    "sg:postcode":"95826",
    "sg:province":"CA",
    "sg:tags":[
        "environmental",
        "ecological"
    ],
    "sg:website":"www.entrix.com",
    "wof:name":"Entrix Inc",
    "wof:placetype":"venue"
},
  "geometry": {"coordinates":[-121.409345,38.549553],"type":"Point"}
}