{
  "type": "Feature",
  "properties": {
    "iso:country":"US",
    "sg:address":"4570 Campus Dr Ste 7",
    "sg:city":"Newport Beach",
    "sg:classifiers":[
        {
            "category":"Health Services",
            "subcategory":"Clinic",
            "type":"Services"
        }
    ],
    "sg:phone":"+1 949 630 2032",
    "sg:postcode":"92663",
    "sg:province":"CA",
    "sg:tags":[
        "loss",
        "mental",
        "weight",
        "counseling"
    ],
    "sg:website":"www.GoldliteHypnosisInstitute.com",
    "wof:name":"Goldlite Hypnosis Institute",
    "wof:placetype":"venue"
},
  "geometry": {"coordinates":[-117.865983,33.670483],"type":"Point"}
}