{
  "type": "Feature",
  "properties": {
    "iso:country":"US",
    "sg:address":"1411 5th St",
    "sg:city":"Santa Monica",
    "sg:classifiers":[
        {
            "category":"Professional",
            "subcategory":"Advertising",
            "type":"Services"
        }
    ],
    "sg:phone":"+1 310 260 9588",
    "sg:postcode":"90401",
    "sg:province":"CA",
    "sg:tags":[
        "picture"
    ],
    "wof:name":"Aspect Group",
    "wof:placetype":"venue"
},
  "geometry": {"coordinates":[-118.49270300000001,34.016039],"type":"Point"}
}