{
  "type": "Feature",
  "properties": {
    "iso:country":"US",
    "sg:address":"715 Hearst Ave",
    "sg:city":"Berkeley",
    "sg:classifiers":[
        {
            "category":"Banks & Credit Unions",
            "subcategory":"Investment Brokerage",
            "type":"Services"
        }
    ],
    "sg:phone":"+1 510 849 5900",
    "sg:postcode":"94710",
    "sg:province":"CA",
    "sg:tags":[
        "management"
    ],
    "wof:name":"Renaissance Technology",
    "wof:placetype":"venue"
},
  "geometry": {"coordinates":[-122.301298,37.868769],"type":"Point"}
}