{
  "type": "Feature",
  "properties": {
    "iso:country":"US",
    "sg:address":"14762 Adams St",
    "sg:city":"Midway City",
    "sg:classifiers":[
        {
            "category":"Real Estate",
            "subcategory":"Real Estate Services",
            "type":"Services"
        }
    ],
    "sg:phone":"+1 714 898 8123",
    "sg:postcode":"92655",
    "sg:province":"CA",
    "wof:name":"Abstract Poetic Creations",
    "wof:placetype":"venue"
},
  "geometry": {"coordinates":[-117.988475,33.746865],"type":"Point"}
}