{
  "type": "Feature",
  "properties": {
    "addr:full":"14762 Adams St Midway City CA 92655",
    "addr:housenumber":"14762",
    "addr:postcode":"92655",
    "addr:street":"Adams St",
    "iso:country":"US",
    "sg:address":"14762 Adams St",
    "sg:city":"Midway City",
    "sg:classifiers":[
        {
            "category":"Real Estate",
            "subcategory":"Real Estate Services",
            "type":"Services"
        }
    ],
    "sg:phone":"+1 714 898 8123",
    "sg:postcode":"92655",
    "sg:province":"CA",
    "wof:name":"Abstract Poetic Creations",
    "wof:placetype":"venue"
},
  "geometry": {"coordinates":[-117.98847499999999,33.746865],"type":"Point"}
}