{
  "type": "Feature",
  "properties": {
    "addr:full":"4101 Alken St Bakersfield CA 93308",
    "addr:housenumber":"4101",
    "addr:postcode":"93308",
    "addr:street":"Alken St",
    "iso:country":"US",
    "sg:address":"4101 Alken St",
    "sg:city":"Bakersfield",
    "sg:classifiers":[
        {
            "category":"Building & Trades",
            "subcategory":"Electrical",
            "type":"Services"
        }
    ],
    "sg:phone":"+1 661 589 8935",
    "sg:postcode":"93308",
    "sg:province":"CA",
    "sg:tags":[
        "electrician"
    ],
    "wof:name":"Electric Technologies",
    "wof:placetype":"venue"
},
  "geometry": {"coordinates":[-119.07991,35.397701],"type":"Point"}
}