{
  "type": "Feature",
  "properties": {
    "addr:full":"4750 Allendale Rd Vacaville CA 95688",
    "addr:housenumber":"4750",
    "addr:postcode":"95688",
    "addr:street":"Allendale Rd",
    "iso:country":"US",
    "sg:address":"4750 Allendale Rd",
    "sg:city":"Vacaville",
    "sg:classifiers":[
        {
            "category":"Building & Trades",
            "subcategory":"Construction",
            "type":"Services"
        }
    ],
    "sg:phone":"+1 707 451 3366",
    "sg:postcode":"95688",
    "sg:province":"CA",
    "sg:tags":[
        "demolition",
        "contractor"
    ],
    "wof:name":"Yelton Company Inc",
    "wof:placetype":"venue"
},
  "geometry": {"coordinates":[-121.947692,38.453179],"type":"Point"}
}