{
  "type": "Feature",
  "properties": {
    "addr:full":"3381 Stevens Creek Blvd Santa Clara CA 95014",
    "addr:housenumber":"3381",
    "addr:postcode":"95014",
    "addr:street":"Stevens Creek Blvd",
    "iso:country":"US",
    "sg:address":"3381 Stevens Creek Blvd",
    "sg:city":"Santa Clara",
    "sg:classifiers":[
        {
            "category":"Government",
            "subcategory":"Office",
            "type":"Public Place"
        }
    ],
    "sg:phone":"+1 408 247 6311",
    "sg:postcode":"95014",
    "sg:province":"CA",
    "sg:tags":[
        "recruiting",
        "army"
    ],
    "wof:name":"Santa Clara Recruiting Station",
    "wof:placetype":"venue"
},
  "geometry": {"coordinates":[-121.95810400000001,37.323257],"type":"Point"}
}