{
  "type": "Feature",
  "properties": {
    "iso:country":"US",
    "sg:address":"2200 Powell St",
    "sg:city":"Emeryville",
    "sg:classifiers":[
        {
            "category":"Professional",
            "subcategory":"Engineering",
            "type":"Services"
        }
    ],
    "sg:phone":"+1 510 428 2907",
    "sg:postcode":"94608",
    "sg:province":"CA",
    "sg:tags":[
        "engineer"
    ],
    "wof:name":"WISS Janney Elstner Assoc Inc",
    "wof:placetype":"venue"
},
  "geometry": {"coordinates":[-122.300065,37.837626],"type":"Point"}
}