{
  "type": "Feature",
  "properties": {
    "addr:full":"7901 Stoneridge Dr Pleasanton CA 94588",
    "addr:housenumber":"7901",
    "addr:postcode":"94588",
    "addr:street":"Stoneridge Dr",
    "iso:country":"US",
    "sg:address":"7901 Stoneridge Dr",
    "sg:city":"Pleasanton",
    "sg:classifiers":[
        {
            "category":"Banks & Credit Unions",
            "subcategory":"Bank",
            "type":"Services"
        }
    ],
    "sg:phone":"+1 925 598 0064",
    "sg:postcode":"94588",
    "sg:province":"CA",
    "sg:tags":[
        "loan",
        "real estate"
    ],
    "wof:name":"New Century Mortgage",
    "wof:placetype":"venue"
},
  "geometry": {"coordinates":[-121.930286,37.6888],"type":"Point"}
}