{
  "type": "Feature",
  "properties": {
    "iso:country":"US",
    "sg:address":"444 Belden St",
    "sg:city":"Gonzales",
    "sg:classifiers":[
        {
            "category":"Manufacturing",
            "subcategory":"Buildings",
            "type":"Manufacturing & Wholesale Goods"
        },
        {
            "category":"Building & Trades",
            "subcategory":"Construction",
            "type":"Services"
        }
    ],
    "sg:phone":"+1 831 675 0334",
    "sg:postcode":"93926",
    "sg:province":"CA",
    "sg:tags":[
        "consultant",
        "builder",
        "management",
        "contractor",
        "home"
    ],
    "wof:name":"Gold Mine Construction",
    "wof:placetype":"venue"
},
  "geometry": {"coordinates":[-121.444228,36.50774],"type":"Point"}
}