{
  "type": "Feature",
  "properties": {
    "iso:country":"US",
    "sg:address":"4343 W Lancaster Blvd",
    "sg:city":"Lancaster",
    "sg:classifiers":[
        {
            "category":"Banks & Credit Unions",
            "subcategory":"Bank",
            "type":"Services"
        }
    ],
    "sg:phone":"+1 661 949 1100",
    "sg:postcode":"93536",
    "sg:province":"CA",
    "sg:tags":[
        "loan",
        "real estate"
    ],
    "wof:name":"Capital Financial Svc",
    "wof:placetype":"venue"
},
  "geometry": {"coordinates":[-118.208101,34.696858],"type":"Point"}
}