{
  "type": "Feature",
  "properties": {
    "addr:full":"5027 New York Ave La Crescenta CA 91214",
    "addr:housenumber":"5027",
    "addr:postcode":"91214",
    "addr:street":"New York Ave",
    "iso:country":"US",
    "sg:address":"5027 New York Ave",
    "sg:city":"La Crescenta",
    "sg:classifiers":[
        {
            "category":"Organizations",
            "subcategory":"Religious Organization",
            "type":"Services"
        }
    ],
    "sg:phone":"+1 818 249 9163",
    "sg:postcode":"91214",
    "sg:province":"CA",
    "sg:tags":[
        "church"
    ],
    "wof:name":"New Church",
    "wof:placetype":"venue"
},
  "geometry": {"coordinates":[-118.253041,34.241433],"type":"Point"}
}