{
  "type": "Feature",
  "properties": {
    "addr:full":"2083 Main St Oakley CA 94561",
    "addr:housenumber":"2083",
    "addr:postcode":"94561",
    "addr:street":"Main St",
    "iso:country":"US",
    "sg:address":"2083 Main St",
    "sg:city":"Oakley",
    "sg:classifiers":[
        {
            "category":"Restaurant",
            "type":"Food & Drink"
        }
    ],
    "sg:phone":"+1 925 625 0292",
    "sg:postcode":"94561",
    "sg:province":"CA",
    "wof:name":"Mike's Beef 'N' Brew",
    "wof:placetype":"venue"
},
  "geometry": {"coordinates":[-121.732613,38.003712],"type":"Point"}
}