{
  "type": "Feature",
  "properties": {
    "addr:full":"17516 Doric St Granada Hills CA 91344",
    "addr:postcode":"17516;91344",
    "addr:street":"Doric St",
    "iso:country":"US",
    "sg:address":"17516 Doric St",
    "sg:city":"Granada Hills",
    "sg:classifiers":[
        {
            "category":"Wholesale",
            "subcategory":"Non-durable Goods",
            "type":"Manufacturing & Wholesale Goods"
        }
    ],
    "sg:phone":"+1 818 832 3595",
    "sg:postcode":"91344",
    "sg:province":"CA",
    "wof:name":"Uniqaseinc",
    "wof:placetype":"venue"
},
  "geometry": {"coordinates":[-118.516913,34.303282],"type":"Point"}
}