{
  "type": "Feature",
  "properties": {
    "iso:country":"US",
    "sg:address":"151 N Glendora Ave",
    "sg:city":"Glendora",
    "sg:classifiers":[
        {
            "category":"Organizations",
            "subcategory":"Religious Organization",
            "type":"Services"
        }
    ],
    "sg:phone":"+1 626 335 4612",
    "sg:postcode":"91741",
    "sg:province":"CA",
    "sg:tags":[
        "church"
    ],
    "wof:name":"Christian Science Reading Room",
    "wof:placetype":"venue"
},
  "geometry": {"coordinates":[-117.86548000000001,34.137788],"type":"Point"}
}