{
  "type": "Feature",
  "properties": {
    "addr:full":"3200 Naglee Rd Tracy CA 95304",
    "addr:housenumber":"3200",
    "addr:postcode":"95304",
    "addr:street":"Naglee Rd",
    "iso:country":"US",
    "sg:address":"3200 Naglee Rd",
    "sg:city":"Tracy",
    "sg:classifiers":[
        {
            "category":"Restaurant",
            "type":"Food & Drink"
        }
    ],
    "sg:menulink":"http://www.allmenus.com/ca/tracy/228584-hot-dog-on-a-stick/menu/",
    "sg:postcode":"95304",
    "sg:province":"CA",
    "sg:tags":[
        "american"
    ],
    "wof:name":"HOT DOG ON A STICK",
    "wof:placetype":"venue"
},
  "geometry": {"coordinates":[-121.462273,37.760122],"type":"Point"}
}