{
  "type": "Feature",
  "properties": {
    "addr:full":"7064 Corline Ct Sebastopol CA 95472",
    "addr:housenumber":"7064",
    "addr:postcode":"95472",
    "addr:street":"Corline Ct",
    "iso:country":"US",
    "sg:address":"7064 Corline Ct",
    "sg:city":"Sebastopol",
    "sg:classifiers":[
        {
            "category":"Health Services",
            "subcategory":"Doctor",
            "type":"Services"
        }
    ],
    "sg:phone":"+1 707 829 5778",
    "sg:postcode":"95472",
    "sg:province":"CA",
    "sg:tags":[
        "physician",
        "surgeon"
    ],
    "wof:name":"Cynthia S Bailey MD",
    "wof:placetype":"venue"
},
  "geometry": {"coordinates":[-122.81350399999999,38.38999],"type":"Point"}
}