{
  "type": "Feature",
  "properties": {
    "addr:full":"1538 W 135th St Gardena CA 90249",
    "addr:housenumber":"1538",
    "addr:postcode":"90249",
    "addr:street":"W 135Th St",
    "iso:country":"US",
    "sg:address":"1538 W 135th St",
    "sg:city":"Gardena",
    "sg:classifiers":[
        {
            "category":"Manufacturing",
            "subcategory":"Glass & Minerals",
            "type":"Manufacturing & Wholesale Goods"
        }
    ],
    "sg:phone":"+1 310 323 9096",
    "sg:postcode":"90249",
    "sg:province":"CA",
    "sg:tags":[
        "granite",
        "product"
    ],
    "wof:name":"South Bay Stone",
    "wof:placetype":"venue"
},
  "geometry": {"coordinates":[-118.30349099999999,33.909093],"type":"Point"}
}