{
  "type": "Feature",
  "properties": {
    "addr:full":"7717 Edgewater Dr Oakland CA 94621",
    "addr:housenumber":"7717",
    "addr:postcode":"94621",
    "addr:street":"Edgewater Dr",
    "iso:country":"US",
    "sg:address":"7717 Edgewater Dr",
    "sg:city":"Oakland",
    "sg:classifiers":[
        {
            "category":"Government",
            "subcategory":"Jail",
            "type":"Public Place"
        }
    ],
    "sg:phone":"+1 510 577 2407",
    "sg:postcode":"94621",
    "sg:province":"CA",
    "sg:tags":[
        "parole",
        "unit"
    ],
    "wof:name":"Oakland Parole Units 1-3",
    "wof:placetype":"venue"
},
  "geometry": {"coordinates":[-122.204413,37.74294],"type":"Point"}
}