{
  "type": "Feature",
  "properties": {
    "addr:full":"1145 2nd St Suite B Brentwood CA 94513",
    "addr:housenumber":"1145",
    "addr:postcode":"94513",
    "addr:street":"2Nd St Suite B",
    "iso:country":"US",
    "sg:address":"1145 2nd St Suite B",
    "sg:city":"Brentwood",
    "sg:classifiers":[
        {
            "category":"Arts & Performance",
            "subcategory":"Art Gallery",
            "type":"Entertainment"
        }
    ],
    "sg:phone":"+1 925 634 7837",
    "sg:postcode":"94513",
    "sg:province":"CA",
    "sg:website":"www.brentwoodframesnthings.com",
    "wof:name":"Brentwood Frames N Things",
    "wof:placetype":"venue"
},
  "geometry": {"coordinates":[-121.6998,37.936091],"type":"Point"}
}