{
  "type": "Feature",
  "properties": {
    "addr:full":"101 E 25th Ave San Mateo CA 94403",
    "addr:housenumber":"101",
    "addr:postcode":"94403",
    "addr:street":"E 25Th Ave",
    "iso:country":"US",
    "sg:address":"101 E 25th Ave",
    "sg:city":"San Mateo",
    "sg:classifiers":[
        {
            "category":"Autos & Motor Vehicles",
            "subcategory":"Motorcycle Sales",
            "type":"Retail Goods"
        }
    ],
    "sg:phone":"+1 650 341 5867",
    "sg:postcode":"94403",
    "sg:province":"CA",
    "sg:website":"www.honda.com",
    "wof:name":"Honda-Suzuki of San Mateo",
    "wof:placetype":"venue"
},
  "geometry": {"coordinates":[-122.30500000000001,37.5453],"type":"Point"}
}