{
  "type": "Feature",
  "properties": {
    "addr:full":"5318 Bryant Ave Oakland CA 94618",
    "addr:housenumber":"5318",
    "addr:postcode":"94618",
    "addr:street":"Bryant Ave",
    "iso:country":"US",
    "sg:address":"5318 Bryant Ave",
    "sg:city":"Oakland",
    "sg:classifiers":[
        {
            "category":"Health Services",
            "subcategory":"Clinic",
            "type":"Services"
        }
    ],
    "sg:phone":"+1 510 653 5973",
    "sg:postcode":"94618",
    "sg:province":"CA",
    "sg:tags":[
        "counseling",
        "mental"
    ],
    "wof:name":"MacLeod Kristi L Lcsw",
    "wof:placetype":"venue"
},
  "geometry": {"coordinates":[-122.25099899999999,37.8381],"type":"Point"}
}