{
  "type": "Feature",
  "properties": {
    "addr:full":"1070 East St Redding CA 96001",
    "addr:housenumber":"1070",
    "addr:postcode":"96001",
    "addr:street":"East St",
    "iso:country":"US",
    "sg:address":"1070 East St",
    "sg:city":"Redding",
    "sg:classifiers":[
        {
            "category":"Health Services",
            "subcategory":"Clinic",
            "type":"Services"
        }
    ],
    "sg:phone":"+1 530 247 0878",
    "sg:postcode":"96001",
    "sg:province":"CA",
    "sg:tags":[
        "home"
    ],
    "wof:name":"Home Helpers",
    "wof:placetype":"venue"
},
  "geometry": {"coordinates":[-122.390762,40.590045],"type":"Point"}
}