{
  "type": "Feature",
  "properties": {
    "iso:country":"US",
    "sg:address":"9010 Reseda Blvd",
    "sg:city":"Northridge",
    "sg:classifiers":[
        {
            "category":"Professional",
            "subcategory":"Advertising",
            "type":"Services"
        }
    ],
    "sg:phone":"+1 818 772 0622",
    "sg:postcode":"91324",
    "sg:province":"CA",
    "sg:tags":[
        "distribution"
    ],
    "wof:name":"ERZ Distribution",
    "wof:placetype":"venue"
},
  "geometry": {"coordinates":[-118.53601,34.233475],"type":"Point"}
}