{
  "type": "Feature",
  "properties": {
    "addr:full":"2714 W Shaw Ave Fresno CA 93711",
    "addr:housenumber":"2714",
    "addr:postcode":"93711",
    "addr:street":"W Shaw Ave",
    "iso:country":"US",
    "sg:address":"2714 W Shaw Ave",
    "sg:city":"Fresno",
    "sg:classifiers":[
        {
            "category":"Food & Beverages",
            "subcategory":"Bakery",
            "type":"Retail Goods"
        }
    ],
    "sg:phone":"+1 559 276 1170",
    "sg:postcode":"93711",
    "sg:province":"CA",
    "sg:tags":[
        "doughnut"
    ],
    "wof:name":"Foster's Donuts",
    "wof:placetype":"venue"
},
  "geometry": {"coordinates":[-119.842078,36.808322],"type":"Point"}
}