{
  "type": "Feature",
  "properties": {
    "addr:full":"3230 Broadway St Sacramento CA 95817",
    "addr:housenumber":"3230",
    "addr:postcode":"95817",
    "addr:street":"Broadway St",
    "iso:country":"US",
    "sg:address":"3230 Broadway St",
    "sg:city":"Sacramento",
    "sg:classifiers":[
        {
            "category":"Organizations",
            "subcategory":"Religious Organization",
            "type":"Services"
        }
    ],
    "sg:phone":"+1 916 454 5019",
    "sg:postcode":"95817",
    "sg:province":"CA",
    "sg:tags":[
        "church"
    ],
    "wof:name":"Samaritan Center",
    "wof:placetype":"venue"
},
  "geometry": {"coordinates":[-121.470749,38.554129],"type":"Point"}
}