{
  "type": "Feature",
  "properties": {
    "addr:full":"6352 E Nohl Ranch Rd Anaheim CA 92807",
    "addr:housenumber":"6352",
    "addr:postcode":"92807",
    "addr:street":"E Nohl Ranch Rd",
    "iso:country":"US",
    "sg:address":"6352 E Nohl Ranch Rd",
    "sg:city":"Anaheim",
    "sg:classifiers":[
        {
            "category":"Shopping",
            "subcategory":"Bicycles & Sporting Goods",
            "type":"Retail Goods"
        }
    ],
    "sg:phone":"+1 714 282 8480",
    "sg:postcode":"92807",
    "sg:province":"CA",
    "sg:tags":[
        "gun",
        "gunsmith"
    ],
    "wof:name":"Firearms Training Assoc",
    "wof:placetype":"venue"
},
  "geometry": {"coordinates":[-117.766661,33.839666],"type":"Point"}
}