{
  "type": "Feature",
  "properties": {
    "addr:full":"8730 Wilshire Blvd Beverly Hills CA 90211",
    "addr:housenumber":"8730",
    "addr:postcode":"90211",
    "addr:street":"Wilshire Blvd",
    "iso:country":"US",
    "sg:address":"8730 Wilshire Blvd",
    "sg:city":"Beverly Hills",
    "sg:classifiers":[
        {
            "category":"Professional",
            "type":"Services"
        }
    ],
    "sg:phone":"+1 310 855 0166",
    "sg:postcode":"90211",
    "sg:province":"CA",
    "wof:name":"Network Models & Talent",
    "wof:placetype":"venue"
},
  "geometry": {"coordinates":[-118.381781,34.066457],"type":"Point"}
}