{
  "type": "Feature",
  "properties": {
    "addr:full":"11959 Discovery Ct Moorpark CA 93021",
    "addr:housenumber":"11959",
    "addr:postcode":"ca 93021",
    "addr:street":"Discovery Ct",
    "iso:country":"US",
    "sg:address":"11959 Discovery Ct",
    "sg:city":"Moorpark",
    "sg:classifiers":[
        {
            "category":"Insurance",
            "subcategory":"Hazard Insurance",
            "type":"Services"
        }
    ],
    "sg:phone":"+1 805 522 3115",
    "sg:postcode":"93021",
    "sg:province":"CA",
    "sg:tags":[
        "commercial",
        "business"
    ],
    "wof:name":"Wespac Insurance Services",
    "wof:placetype":"venue"
},
  "geometry": {"coordinates":[-118.89545099999999,34.279937],"type":"Point"}
}