{
  "type": "Feature",
  "properties": {
    "addr:full":"3383 Arden Way Sacramento CA 95825",
    "addr:housenumber":"3383",
    "addr:postcode":"95825",
    "addr:street":"Arden Way",
    "iso:country":"US",
    "sg:address":"3383 Arden Way",
    "sg:city":"Sacramento",
    "sg:classifiers":[
        {
            "category":"Professional",
            "subcategory":"Management & Consulting",
            "type":"Services"
        }
    ],
    "sg:phone":"+1 916 974 6300",
    "sg:postcode":"95825",
    "sg:province":"CA",
    "sg:tags":[
        "marketing",
        "consultant"
    ],
    "wof:name":"Imperial Marketing",
    "wof:placetype":"venue"
},
  "geometry": {"coordinates":[-121.386656,38.595859],"type":"Point"}
}