{
  "type": "Feature",
  "properties": {
    "addr:full":"234 Oak St Brentwood CA 94513",
    "addr:housenumber":"234",
    "addr:postcode":"ca 94513",
    "addr:street":"Oak St",
    "iso:country":"US",
    "sg:address":"234 Oak St",
    "sg:city":"Brentwood",
    "sg:classifiers":[
        {
            "category":"Banks & Credit Unions",
            "subcategory":"Bank",
            "type":"Services"
        }
    ],
    "sg:phone":"+1 925 240 2043",
    "sg:postcode":"94513",
    "sg:province":"CA",
    "sg:tags":[
        "financing"
    ],
    "wof:name":"C U Funding",
    "wof:placetype":"venue"
},
  "geometry": {"coordinates":[-121.692819,37.933832],"type":"Point"}
}