{
  "type": "Feature",
  "properties": {
    "addr:full":"135 S E St Lompoc CA 93436",
    "addr:housenumber":"135",
    "addr:postcode":"93436",
    "addr:street":"S E St",
    "iso:country":"US",
    "sg:address":"135 S E St",
    "sg:city":"Lompoc",
    "sg:classifiers":[
        {
            "category":"Place Of Worship",
            "subcategory":"Church",
            "type":"Public Place"
        },
        {
            "category":"Place Of Worship",
            "type":"Public Place"
        }
    ],
    "sg:phone":"+1 805 736 8615",
    "sg:postcode":"93436",
    "sg:province":"CA",
    "sg:tags":[
        "lutheran",
        "america",
        "churches-lutheran",
        "churches-lutheran-evangelical"
    ],
    "sg:website":"http://bethanylutheranchurch.ctsmemberconnect.net/",
    "wof:name":"Bethany Evang Lutheran Ch Lcms",
    "wof:placetype":"venue"
},
  "geometry": {"coordinates":[-120.45407400000001,34.638371],"type":"Point"}
}