{
  "type": "Feature",
  "properties": {
    "addr:full":"75 S Milpitas Blvd Milpitas CA 95035",
    "addr:housenumber":"75",
    "addr:postcode":"95035",
    "addr:street":"S Milpitas Blvd",
    "iso:country":"US",
    "sg:address":"75 S Milpitas Blvd",
    "sg:city":"Milpitas",
    "sg:classifiers":[
        {
            "category":"Insurance",
            "subcategory":"Insurance Agent",
            "type":"Services"
        }
    ],
    "sg:phone":"+1 408 262 1004",
    "sg:postcode":"95035",
    "sg:province":"CA",
    "wof:name":"Ken Yi Farmers Insurance",
    "wof:placetype":"venue"
},
  "geometry": {"coordinates":[-121.89827200000001,37.430202],"type":"Point"}
}