{
  "type": "Feature",
  "properties": {
    "addr:full":"301 E 11th St Los Angeles CA 90015",
    "addr:housenumber":"301",
    "addr:postcode":"90015",
    "addr:street":"E 11Th St",
    "iso:country":"US",
    "sg:address":"301 E 11th St",
    "sg:city":"Los Angeles",
    "sg:classifiers":[
        {
            "category":"Shopping",
            "subcategory":"Clothing, Apparel, & Fashions",
            "type":"Retail Goods"
        }
    ],
    "sg:phone":"+1 213 742 8878",
    "sg:postcode":"90015",
    "sg:province":"CA",
    "wof:name":"Fashion One Two Three",
    "wof:placetype":"venue"
},
  "geometry": {"coordinates":[-118.255127,34.03714],"type":"Point"}
}