{
  "type": "Feature",
  "properties": {
    "addr:full":"14523 Hawthorne Blvd Lawndale CA 90260",
    "addr:housenumber":"14523",
    "addr:postcode":"ca 90260",
    "addr:street":"Hawthorne Blvd",
    "iso:country":"US",
    "sg:address":"14523 Hawthorne Blvd",
    "sg:city":"Lawndale",
    "sg:classifiers":[
        {
            "category":"Autos & Motor Vehicles",
            "subcategory":"Automobile Sales",
            "type":"Retail Goods"
        }
    ],
    "sg:phone":"+1 310 970 1097",
    "sg:postcode":"90260",
    "sg:province":"CA",
    "sg:tags":[
        "car",
        "used"
    ],
    "sg:website":"http://www.universalautoplaza.com",
    "wof:name":"Universal Auto Plaza",
    "wof:placetype":"venue"
},
  "geometry": {"coordinates":[-118.35275300000001,33.899948],"type":"Point"}
}