{
  "type": "Feature",
  "properties": {
    "addr:full":"13166 Aurora Ave Victorville CA 92392",
    "addr:housenumber":"13166",
    "addr:postcode":"92392",
    "addr:street":"Aurora Ave",
    "iso:country":"US",
    "sg:address":"13166 Aurora Ave",
    "sg:city":"Victorville",
    "sg:classifiers":[
        {
            "category":"Retail",
            "subcategory":"Repair Shop",
            "type":"Services"
        }
    ],
    "sg:phone":"+1 760 241 8005",
    "sg:postcode":"92392",
    "sg:province":"CA",
    "sg:tags":[
        "upholsterer"
    ],
    "wof:name":"A-1 Upholstery",
    "wof:placetype":"venue"
},
  "geometry": {"coordinates":[-117.34953,34.489892],"type":"Point"}
}