{
  "type": "Feature",
  "properties": {
    "iso:country":"US",
    "sg:address":"2377 Gold Meadow Way",
    "sg:city":"Gold River",
    "sg:classifiers":[
        {
            "category":"Professional",
            "subcategory":"Lawyer & Legal Services",
            "type":"Services"
        }
    ],
    "sg:phone":"+1 916 362 5558",
    "sg:postcode":"95670",
    "sg:province":"CA",
    "sg:tags":[
        "attorney"
    ],
    "wof:name":"Chang Ruthenberg & Long",
    "wof:placetype":"venue"
},
  "geometry": {"coordinates":[-121.261115,38.622],"type":"Point"}
}