{
  "type": "Feature",
  "properties": {
    "addr:full":"2886 Main St San Diego CA 92113",
    "addr:housenumber":"2886",
    "addr:postcode":"92113",
    "addr:street":"Main St",
    "iso:country":"US",
    "sg:address":"2886 Main St",
    "sg:city":"San Diego",
    "sg:classifiers":[
        {
            "category":"Autos & Motor Vehicles",
            "subcategory":"Boat Sales",
            "type":"Retail Goods"
        }
    ],
    "sg:phone":"+1 619 544 1900",
    "sg:postcode":"92113",
    "sg:province":"CA",
    "sg:tags":[
        "equipment",
        "marine",
        "supply"
    ],
    "wof:name":"Oceans West Marine & Ind Supl",
    "wof:placetype":"venue"
},
  "geometry": {"coordinates":[-117.133433,32.692875],"type":"Point"}
}