{
  "type": "Feature",
  "properties": {
    "iso:country":"US",
    "sg:address":"11129 Brockway St",
    "sg:city":"El Monte",
    "sg:classifiers":[
        {
            "category":"Organizations",
            "subcategory":"Religious Organization",
            "type":"Services"
        }
    ],
    "sg:phone":"+1 626 442 2691",
    "sg:postcode":"91731",
    "sg:province":"CA",
    "sg:tags":[
        "church"
    ],
    "wof:name":"United Pentecostal Church",
    "wof:placetype":"venue"
},
  "geometry": {"coordinates":[-118.030999,34.068465],"type":"Point"}
}