{
  "type": "Feature",
  "properties": {
    "iso:country":"US",
    "sg:address":"1511 S. Main St",
    "sg:city":"Santa Ana",
    "sg:classifiers":[
        {
            "category":"Autos & Motor Vehicles",
            "subcategory":"Auto Supplies",
            "type":"Retail Goods"
        }
    ],
    "sg:phone":"+1 714 835 3606",
    "sg:postcode":"92707",
    "sg:province":"CA",
    "sg:tags":[
        "tire"
    ],
    "sg:website":"www.7daystirecenter.com",
    "wof:name":"7 Days Tire Center",
    "wof:placetype":"venue"
},
  "geometry": {"coordinates":[-117.867499,33.72661],"type":"Point"}
}