{
  "type": "Feature",
  "properties": {
    "addr:full":"816 Calle Plano Camarillo CA 93012",
    "addr:housenumber":"816",
    "addr:postcode":"93012",
    "addr:street":"Calle Plano",
    "iso:country":"US",
    "sg:address":"816 Calle Plano",
    "sg:city":"Camarillo",
    "sg:classifiers":[
        {
            "category":"Home & Garden",
            "subcategory":"Building Materials",
            "type":"Retail Goods"
        }
    ],
    "sg:phone":"+1 805 383 0442",
    "sg:postcode":"93012",
    "sg:province":"CA",
    "sg:tags":[
        "equipment",
        "fixture",
        "lighting"
    ],
    "wof:name":"Buster Lighting Design",
    "wof:placetype":"venue"
},
  "geometry": {"coordinates":[-119.008003,34.201302],"type":"Point"}
}