{
  "type": "Feature",
  "properties": {
    "addr:full":"302 Pendleton Way Oakland CA 94621",
    "addr:housenumber":"302",
    "addr:postcode":"94621",
    "addr:street":"Pendleton Way",
    "iso:country":"US",
    "sg:address":"302 Pendleton Way",
    "sg:city":"Oakland",
    "sg:classifiers":[
        {
            "category":"Professional",
            "subcategory":"Engineering",
            "type":"Services"
        }
    ],
    "sg:phone":"+1 510 632 1734",
    "sg:postcode":"94621",
    "sg:province":"CA",
    "sg:tags":[
        "engineer"
    ],
    "wof:name":"Enercon Services Inc",
    "wof:placetype":"venue"
},
  "geometry": {"coordinates":[-122.19993100000001,37.734],"type":"Point"}
}