{
  "type": "Feature",
  "properties": {
    "iso:country":"US",
    "sg:address":"2401 Eastman Ave",
    "sg:city":"Oxnard",
    "sg:classifiers":[
        {
            "category":"Building & Trades",
            "subcategory":"Construction",
            "type":"Services"
        }
    ],
    "sg:phone":"+1 805 981 8181",
    "sg:postcode":"93030",
    "sg:province":"CA",
    "sg:tags":[
        "roofing",
        "contractor"
    ],
    "wof:name":"Webco",
    "wof:placetype":"venue"
},
  "geometry": {"coordinates":[-119.143339,34.199038],"type":"Point"}
}