{
  "type": "Feature",
  "properties": {
    "addr:full":"43155 Sierra Hwy Lancaster CA 93534",
    "addr:housenumber":"43155",
    "addr:postcode":"93534",
    "addr:street":"Sierra Hwy",
    "iso:country":"US",
    "sg:address":"43155 Sierra Hwy",
    "sg:city":"Lancaster",
    "sg:classifiers":[
        {
            "category":"Real Estate",
            "subcategory":"Real Estate Operator",
            "type":"Services"
        }
    ],
    "sg:phone":"+1 661 948 3350",
    "sg:postcode":"93534",
    "sg:province":"CA",
    "sg:tags":[
        "mobile",
        "home",
        "community"
    ],
    "wof:name":"Shady Elms Mobile Home & Rv Pk",
    "wof:placetype":"venue"
},
  "geometry": {"coordinates":[-118.131658,34.666975],"type":"Point"}
}