{
  "type": "Feature",
  "properties": {
    "addr:full":"6814 San Fernando Rd Glendale CA 91201",
    "addr:housenumber":"6814",
    "addr:postcode":"91201",
    "addr:street":"San Fernando Rd",
    "iso:country":"US",
    "sg:address":"6814 San Fernando Rd",
    "sg:city":"Glendale",
    "sg:classifiers":[
        {
            "category":"Building & Trades",
            "subcategory":"Construction",
            "type":"Services"
        }
    ],
    "sg:phone":"+1 818 558 5000",
    "sg:postcode":"91201",
    "sg:province":"CA",
    "sg:tags":[
        "resurfacing",
        "laying",
        "refinishing",
        "flooring",
        "floor"
    ],
    "wof:name":"Royal Parquet Group",
    "wof:placetype":"venue"
},
  "geometry": {"coordinates":[-118.296997,34.172199],"type":"Point"}
}