{
  "type": "Feature",
  "properties": {
    "iso:country":"US",
    "sg:address":"2361 Arden Way",
    "sg:city":"Sacramento",
    "sg:classifiers":[
        {
            "category":"Education",
            "subcategory":"Dance Studio",
            "type":"Public Place"
        }
    ],
    "sg:phone":"+1 916 448 1665",
    "sg:postcode":"95825",
    "sg:province":"CA",
    "sg:tags":[
        "instruction",
        "dancing"
    ],
    "wof:name":"Jodette's Costumes & Boutique",
    "wof:placetype":"venue"
},
  "geometry": {"coordinates":[-121.40797999999999,38.596149],"type":"Point"}
}