{
  "type": "Feature",
  "properties": {
    "addr:full":"3553 Castro Valley Blvd Castro Valley CA 94546",
    "addr:housenumber":"3553",
    "addr:postcode":"94546",
    "addr:street":"Castro Valley Blvd",
    "iso:country":"US",
    "sg:address":"3553 Castro Valley Blvd",
    "sg:city":"Castro Valley",
    "sg:classifiers":[
        {
            "category":"Insurance",
            "subcategory":"Insurance Agent",
            "type":"Services"
        }
    ],
    "sg:phone":"+1 510 886 8568",
    "sg:postcode":"94546",
    "sg:province":"CA",
    "wof:name":"Anico",
    "wof:placetype":"venue"
},
  "geometry": {"coordinates":[-122.07148599999999,37.694882],"type":"Point"}
}