{
  "type": "Feature",
  "properties": {
    "addr:full":"215 S Hickory St Escondido CA 92025",
    "addr:housenumber":"215",
    "addr:postcode":"92025",
    "addr:street":"S Hickory St",
    "iso:country":"US",
    "sg:address":"215 S Hickory St",
    "sg:city":"Escondido",
    "sg:classifiers":[
        {
            "category":"Health Services",
            "subcategory":"Doctor",
            "type":"Services"
        },
        {
            "category":"Health Services",
            "subcategory":"Clinic",
            "type":"Services"
        },
        {
            "category":"Community Center",
            "type":"Public Place"
        }
    ],
    "sg:phone":"+1 760 432 6644",
    "sg:postcode":"92025",
    "sg:province":"CA",
    "sg:tags":[
        "physician",
        "medical",
        "surgeons",
        "internal",
        "medicine",
        "surgeon"
    ],
    "wof:name":"Chiang, Larry C, Md - Escondido Internal Medicine",
    "wof:placetype":"venue"
},
  "geometry": {"coordinates":[-117.07521800000001,33.123058],"type":"Point"}
}