{
  "type": "Feature",
  "properties": {
    "addr:full":"791 Lombardi Ct Santa Rosa CA 95407",
    "addr:housenumber":"791",
    "addr:postcode":"95407",
    "addr:street":"Lombardi Ct",
    "iso:country":"US",
    "sg:address":"791 Lombardi Ct",
    "sg:city":"Santa Rosa",
    "sg:classifiers":[
        {
            "category":"Sports & Exercise",
            "subcategory":"Gym",
            "type":"Entertainment"
        }
    ],
    "sg:phone":"+1 707 542 4500",
    "sg:postcode":"95407",
    "sg:province":"CA",
    "sg:tags":[
        "club",
        "health",
        "studio",
        "gymnasium"
    ],
    "wof:name":"Fusion Fitness",
    "wof:placetype":"venue"
},
  "geometry": {"coordinates":[-122.74847200000001,38.426452],"type":"Point"}
}