{
  "type": "Feature",
  "properties": {
    "addr:full":"355 W Alondra Blvd Gardena CA 90248",
    "addr:housenumber":"355",
    "addr:postcode":"90248",
    "addr:street":"W Alondra Blvd",
    "iso:country":"US",
    "sg:address":"355 W Alondra Blvd",
    "sg:city":"Gardena",
    "sg:classifiers":[
        {
            "category":"Manufacturing",
            "subcategory":"Metals",
            "type":"Manufacturing & Wholesale Goods"
        }
    ],
    "sg:phone":"+1 310 532 0419",
    "sg:postcode":"90248",
    "sg:province":"CA",
    "sg:tags":[
        "treating",
        "heat"
    ],
    "sg:website":"www.bodycote.com",
    "wof:name":"Ticorm Inc",
    "wof:placetype":"venue"
},
  "geometry": {"coordinates":[-118.282729,33.885466],"type":"Point"}
}