{
  "type": "Feature",
  "properties": {
    "addr:full":"445 Rosewood Ave Ste L Camarillo CA 93010",
    "addr:housenumber":"445",
    "addr:postcode":"93010",
    "addr:street":"Rosewood Ave Ste L",
    "iso:country":"US",
    "sg:address":"445 Rosewood Ave Ste L",
    "sg:city":"Camarillo",
    "sg:classifiers":[
        {
            "category":"Professional",
            "subcategory":"Lawyer & Legal Services",
            "type":"Services"
        }
    ],
    "sg:phone":"+1 805 389 6626",
    "sg:postcode":"93010",
    "sg:province":"CA",
    "sg:tags":[
        "notary"
    ],
    "wof:name":"Camarillo Escrow Company",
    "wof:placetype":"venue"
},
  "geometry": {"coordinates":[-119.06199599999999,34.221298],"type":"Point"}
}