{
  "type": "Feature",
  "properties": {
    "iso:country":"US",
    "sg:address":"2991 Randolph Ave",
    "sg:city":"Costa Mesa",
    "sg:classifiers":[
        {
            "category":"Building & Trades",
            "subcategory":"Landscaping Services",
            "type":"Services"
        }
    ],
    "sg:phone":"+1 714 435 9128",
    "sg:postcode":"92626",
    "sg:province":"CA",
    "sg:tags":[
        "maintenance"
    ],
    "wof:name":"South Coast Environment",
    "wof:placetype":"venue"
},
  "geometry": {"coordinates":[-117.887893,33.677714],"type":"Point"}
}