{
  "type": "Feature",
  "properties": {
    "iso:country":"US",
    "sg:address":"43370 San Fermin Pl",
    "sg:city":"Temecula",
    "sg:classifiers":[
        {
            "category":"Building & Trades",
            "subcategory":"Electrical",
            "type":"Services"
        }
    ],
    "sg:phone":"+1 951 302 3165",
    "sg:postcode":"92592",
    "sg:province":"CA",
    "sg:tags":[
        "electrician"
    ],
    "wof:name":"D&D Electric Inc",
    "wof:placetype":"venue"
},
  "geometry": {"coordinates":[-117.11225899999999,33.490706],"type":"Point"}
}