{
  "type": "Feature",
  "properties": {
    "addr:full":"4245 Saint George Pl Riverside CA 92504",
    "addr:housenumber":"4245",
    "addr:postcode":"92504",
    "addr:street":"Saint George Pl",
    "iso:country":"US",
    "sg:address":"4245 Saint George Pl",
    "sg:city":"Riverside",
    "sg:classifiers":[
        {
            "category":"Wholesale",
            "subcategory":"Vending Machines",
            "type":"Manufacturing & Wholesale Goods"
        }
    ],
    "sg:phone":"+1 951 689 0152",
    "sg:postcode":"92504",
    "sg:province":"CA",
    "sg:tags":[
        "operator"
    ],
    "wof:name":"Pringle Vending",
    "wof:placetype":"venue"
},
  "geometry": {"coordinates":[-117.426244,33.944595],"type":"Point"}
}