{
  "type": "Feature",
  "properties": {
    "addr:full":"4646 Los Feliz Blvd Los Angeles CA 90027",
    "addr:housenumber":"4646",
    "addr:postcode":"90027",
    "addr:street":"Los Feliz Blvd",
    "iso:country":"US",
    "sg:address":"4646 Los Feliz Blvd",
    "sg:city":"Los Angeles",
    "sg:classifiers":[
        {
            "category":"Real Estate",
            "subcategory":"Real Estate Operator",
            "type":"Services"
        }
    ],
    "sg:phone":"+1 323 662 5010",
    "sg:postcode":"90027",
    "sg:province":"CA",
    "sg:tags":[
        "apartment"
    ],
    "wof:name":"Parkwood Apartments",
    "wof:placetype":"venue"
},
  "geometry": {"coordinates":[-118.291,34.111301],"type":"Point"}
}