{
  "type": "Feature",
  "properties": {
    "iso:country":"US",
    "sg:address":"267 S Los Angeles St",
    "sg:city":"Los Angeles",
    "sg:classifiers":[
        {
            "category":"Shopping",
            "subcategory":"Bicycles & Sporting Goods",
            "type":"Retail Goods"
        }
    ],
    "sg:phone":"+1 213 617 8643",
    "sg:postcode":"90012",
    "sg:province":"CA",
    "wof:name":"La Mini Bike",
    "wof:placetype":"venue"
},
  "geometry": {"coordinates":[-118.243962,34.049732],"type":"Point"}
}