{
  "type": "Feature",
  "properties": {
    "addr:full":"1415 Luning Drive San Jose CA 95118",
    "addr:housenumber":"1415",
    "addr:postcode":"95118",
    "addr:street":"Luning Drive",
    "iso:country":"US",
    "sg:address":"1415 Luning Drive",
    "sg:city":"San Jose",
    "sg:classifiers":[
        {
            "category":"Building & Trades",
            "subcategory":"Plumbing",
            "type":"Services"
        }
    ],
    "sg:phone":"+1 408 265 4151",
    "sg:postcode":"95118",
    "sg:province":"CA",
    "wof:name":"Go With the Flow",
    "wof:placetype":"venue"
},
  "geometry": {"coordinates":[-121.89113399999999,37.25476],"type":"Point"}
}