{
  "type": "Feature",
  "properties": {
    "iso:country":"US",
    "sg:address":"356 S Western Ave Ste 102",
    "sg:city":"Los Angeles",
    "sg:classifiers":[
        {
            "category":"Personal",
            "subcategory":"Beauty Salon",
            "type":"Services"
        }
    ],
    "sg:phone":"+1 213 380 3004",
    "sg:postcode":"90020",
    "sg:province":"CA",
    "sg:tags":[
        "hair"
    ],
    "wof:name":"Inestia",
    "wof:placetype":"venue"
},
  "geometry": {"coordinates":[-118.308728,34.067406],"type":"Point"}
}