{
  "type": "Feature",
  "properties": {
    "iso:country":"US",
    "sg:address":"1726 Harbison Canyon Rd",
    "sg:city":"El Cajon",
    "sg:classifiers":[
        {
            "category":"Farming",
            "subcategory":"Farm",
            "type":"Manufacturing & Wholesale Goods"
        }
    ],
    "sg:phone":"+1 619 659 8090",
    "sg:postcode":"92019",
    "sg:province":"CA",
    "sg:tags":[
        "crop",
        "general"
    ],
    "wof:name":"Pyramid Hills Springs",
    "wof:placetype":"venue"
},
  "geometry": {"coordinates":[-116.845611,32.798394],"type":"Point"}
}