{
  "type": "Feature",
  "properties": {
    "addr:full":"21916 Amethyst Rd Wildomar CA 92595",
    "addr:housenumber":"21916",
    "addr:postcode":"92595",
    "addr:street":"Amethyst Rd",
    "iso:country":"US",
    "sg:address":"21916 Amethyst Rd",
    "sg:city":"Wildomar",
    "sg:classifiers":[
        {
            "category":"Manufacturing",
            "subcategory":"Buildings",
            "type":"Manufacturing & Wholesale Goods"
        },
        {
            "category":"Building & Trades",
            "subcategory":"Construction",
            "type":"Services"
        }
    ],
    "sg:phone":"+1 951 678 6400",
    "sg:postcode":"92595",
    "sg:province":"CA",
    "sg:tags":[
        "home",
        "builder",
        "contractor"
    ],
    "wof:name":"Tak Construction Services",
    "wof:placetype":"venue"
},
  "geometry": {"coordinates":[-117.269581,33.595942],"type":"Point"}
}