{
  "type": "Feature",
  "properties": {
    "addr:full":"350 Sansome St Ste 600 San Francisco CA 94104",
    "addr:housenumber":"350",
    "addr:postcode":"94104",
    "addr:street":"Sansome St Ste 600",
    "iso:country":"US",
    "sg:address":"350 Sansome St Ste 600",
    "sg:city":"San Francisco",
    "sg:classifiers":[
        {
            "category":"Professional",
            "subcategory":"Lawyer & Legal Services",
            "type":"Services"
        }
    ],
    "sg:phone":"+1 415 788 2035",
    "sg:postcode":"94104",
    "sg:province":"CA",
    "sg:website":"www.mkinjurylaw.com",
    "wof:name":"Meisel & Krentsa Law Offices of",
    "wof:placetype":"venue"
},
  "geometry": {"coordinates":[-122.40100099999999,37.793783],"type":"Point"}
}