{
  "type": "Feature",
  "properties": {
    "addr:full":"2732 Beatrice Ln Modesto CA 95355",
    "addr:housenumber":"2732",
    "addr:postcode":"ca 95355",
    "addr:street":"Beatrice Ln",
    "iso:country":"US",
    "sg:address":"2732 Beatrice Ln",
    "sg:city":"Modesto",
    "sg:classifiers":[
        {
            "category":"Building & Trades",
            "subcategory":"Plumbing",
            "type":"Services"
        }
    ],
    "sg:phone":"+1 209 551 8577",
    "sg:postcode":"95355",
    "sg:province":"CA",
    "sg:tags":[
        "plumbing",
        "contractor"
    ],
    "wof:name":"Cool Water Plumbing",
    "wof:placetype":"venue"
},
  "geometry": {"coordinates":[-120.946848,37.667839],"type":"Point"}
}