{
  "type": "Feature",
  "properties": {
    "iso:country":"US",
    "sg:address":"121 Jefferson Dr",
    "sg:city":"Belvedere Tibrn",
    "sg:classifiers":[
        {
            "category":"Professional",
            "type":"Services"
        }
    ],
    "sg:phone":"+1 415 383 8460",
    "sg:postcode":"94920",
    "sg:province":"CA",
    "sg:tags":[
        "establishment"
    ],
    "wof:name":"Sierra Advisory Group",
    "wof:placetype":"venue"
},
  "geometry": {"coordinates":[-122.48988,37.899937],"type":"Point"}
}