{
  "type": "Feature",
  "properties": {
    "addr:full":"9773 Sierra Ave Fontana CA 92335",
    "addr:housenumber":"9773",
    "addr:postcode":"92335",
    "addr:street":"Sierra Ave",
    "iso:country":"US",
    "sg:address":"9773 Sierra Ave",
    "sg:city":"Fontana",
    "sg:classifiers":[
        {
            "category":"Real Estate",
            "subcategory":"Real Estate Agent",
            "type":"Services"
        }
    ],
    "sg:phone":"+1 909 854 8913",
    "sg:postcode":"92335",
    "sg:province":"CA",
    "wof:name":"Century 21 Achievers",
    "wof:placetype":"venue"
},
  "geometry": {"coordinates":[-117.435607,34.075293],"type":"Point"}
}