{
  "type": "Feature",
  "properties": {
    "addr:full":"5025 Meyers St Rocklin CA 95677",
    "addr:housenumber":"5025",
    "addr:postcode":"95677",
    "addr:street":"Meyers St",
    "iso:country":"US",
    "sg:address":"5025 Meyers St",
    "sg:city":"Rocklin",
    "sg:classifiers":[
        {
            "category":"Professional",
            "type":"Services"
        }
    ],
    "sg:phone":"+1 916 624 0273",
    "sg:postcode":"95677",
    "sg:province":"CA",
    "sg:tags":[
        "establishment"
    ],
    "wof:name":"Mmca RE Site",
    "wof:placetype":"venue"
},
  "geometry": {"coordinates":[-121.228977,38.791751],"type":"Point"}
}