{
  "type": "Feature",
  "properties": {
    "iso:country":"US",
    "sg:address":"1238 7th St",
    "sg:city":"Santa Monica",
    "sg:classifiers":[
        {
            "category":"Professional",
            "type":"Services"
        }
    ],
    "sg:phone":"+1 310 451 0271",
    "sg:postcode":"90401",
    "sg:province":"CA",
    "wof:name":"Airvest",
    "wof:placetype":"venue"
},
  "geometry": {"coordinates":[-118.494444,34.020525],"type":"Point"}
}