{
  "type": "Feature",
  "properties": {
    "iso:country":"US",
    "sg:address":"796 Oller St",
    "sg:city":"Mendota",
    "sg:classifiers":[
        {
            "category":"Bars & Pubs",
            "type":"Food & Drink"
        }
    ],
    "sg:phone":"+1 559 655 0320",
    "sg:postcode":"93640",
    "sg:province":"CA",
    "sg:tags":[
        "club",
        "night"
    ],
    "wof:name":"Mi Ranchito",
    "wof:placetype":"venue"
},
  "geometry": {"coordinates":[-120.379085,36.754189],"type":"Point"}
}