{
  "type": "Feature",
  "properties": {
    "addr:full":"1405 Monterey Hwy San Jose CA 95110",
    "addr:housenumber":"1405",
    "addr:postcode":"95110",
    "addr:street":"Monterey Hwy",
    "iso:country":"US",
    "sg:address":"1405 Monterey Hwy",
    "sg:city":"San Jose",
    "sg:classifiers":[
        {
            "category":"Restaurant",
            "type":"Food & Drink"
        }
    ],
    "sg:menulink":"http://www.allmenus.com/ca/san-jose/174532-wendys/menu/",
    "sg:phone":"+1 408 287 9903",
    "sg:postcode":"95110",
    "sg:province":"CA",
    "sg:tags":[
        "burger",
        "american",
        "soup"
    ],
    "wof:name":"Wendy's",
    "wof:placetype":"venue"
},
  "geometry": {"coordinates":[-121.873684,37.316044],"type":"Point"}
}