{
  "type": "Feature",
  "properties": {
    "addr:full":"5760 Cutler Ct Loomis CA 95650",
    "addr:housenumber":"5760",
    "addr:postcode":"95650",
    "addr:street":"Cutler Ct",
    "iso:country":"US",
    "sg:address":"5760 Cutler Ct",
    "sg:city":"Loomis",
    "sg:classifiers":[
        {
            "category":"Utilities",
            "subcategory":"Telephone",
            "type":"Services"
        }
    ],
    "sg:phone":"+1 916 962 3663",
    "sg:postcode":"95650",
    "sg:province":"CA",
    "sg:tags":[
        "company"
    ],
    "wof:name":"Northern Datacom",
    "wof:placetype":"venue"
},
  "geometry": {"coordinates":[-121.19967200000001,38.827066],"type":"Point"}
}