{
  "type": "Feature",
  "properties": {
    "addr:full":"1240 W Hillsdale Boulevard San Mateo CA 94403",
    "addr:housenumber":"1240",
    "addr:postcode":"94403",
    "addr:street":"W Hillsdale Boulevard",
    "iso:country":"US",
    "sg:address":"1240 W Hillsdale Boulevard",
    "sg:city":"San Mateo",
    "sg:classifiers":[
        {
            "category":"Personal",
            "subcategory":"Barber",
            "type":"Services"
        }
    ],
    "sg:phone":"+1 650 341 2705",
    "sg:postcode":"94403",
    "sg:province":"CA",
    "wof:name":"Shear Design Joaquin",
    "wof:placetype":"venue"
},
  "geometry": {"coordinates":[-122.326503,37.533158],"type":"Point"}
}