{
  "type": "Feature",
  "properties": {
    "addr:full":"1181 N Tulare Way Upland CA 91786",
    "addr:housenumber":"1181",
    "addr:postcode":"91786",
    "addr:street":"N Tulare Way",
    "iso:country":"US",
    "sg:address":"1181 N Tulare Way",
    "sg:city":"Upland",
    "sg:classifiers":[
        {
            "category":"Building & Trades",
            "subcategory":"Electrical",
            "type":"Services"
        }
    ],
    "sg:phone":"+1 909 920 1140",
    "sg:postcode":"91786",
    "sg:province":"CA",
    "sg:tags":[
        "electric",
        "contractor"
    ],
    "wof:name":"Baird Electric",
    "wof:placetype":"venue"
},
  "geometry": {"coordinates":[-117.657445,34.109853],"type":"Point"}
}