{
  "type": "Feature",
  "properties": {
    "iso:country":"US",
    "sg:address":"951 W Valley Blvd",
    "sg:city":"Alhambra",
    "sg:classifiers":[
        {
            "category":"Manufacturing",
            "subcategory":"Furniture",
            "type":"Manufacturing & Wholesale Goods"
        }
    ],
    "sg:phone":"+1 626 284 2650",
    "sg:postcode":"91803",
    "sg:province":"CA",
    "wof:name":"ICO Trading Co",
    "wof:placetype":"venue"
},
  "geometry": {"coordinates":[-118.134226,34.078004],"type":"Point"}
}