{
  "type": "Feature",
  "properties": {
    "iso:country":"US",
    "sg:address":"116 Agnes Ave",
    "sg:city":"Santa Maria",
    "sg:classifiers":[
        {
            "category":"Social Services",
            "subcategory":"Child Care",
            "type":"Services"
        }
    ],
    "sg:phone":"+1 805 922 6875",
    "sg:postcode":"93458",
    "sg:province":"CA",
    "wof:name":"Head Start",
    "wof:placetype":"venue"
},
  "geometry": {"coordinates":[-120.43594299999999,34.96402],"type":"Point"}
}