{
  "type": "Feature",
  "properties": {
    "addr:full":"6955 Sierra Ct Dublin CA 94568",
    "addr:housenumber":"6955",
    "addr:postcode":"94568",
    "addr:street":"Sierra Ct",
    "iso:country":"US",
    "sg:address":"6955 Sierra Ct",
    "sg:city":"Dublin",
    "sg:classifiers":[
        {
            "category":"Manufacturing",
            "subcategory":"Printing",
            "type":"Manufacturing & Wholesale Goods"
        }
    ],
    "sg:phone":"+1 925 556 9233",
    "sg:postcode":"94568",
    "sg:province":"CA",
    "sg:tags":[
        "commercial"
    ],
    "wof:name":"Tickets Plus Printing",
    "wof:placetype":"venue"
},
  "geometry": {"coordinates":[-121.913478,37.711473],"type":"Point"}
}