{
  "type": "Feature",
  "properties": {
    "iso:country":"US",
    "sg:address":"2244 S Santa Fe Ave",
    "sg:city":"Vista",
    "sg:classifiers":[
        {
            "category":"Wholesale",
            "subcategory":"Chemicals & Plastics",
            "type":"Manufacturing & Wholesale Goods"
        }
    ],
    "sg:phone":"+1 760 598 5949",
    "sg:postcode":"92084",
    "sg:province":"CA",
    "sg:tags":[
        "product",
        "dairy"
    ],
    "wof:name":"Reys Wholesale",
    "wof:placetype":"venue"
},
  "geometry": {"coordinates":[-117.20649,33.169812],"type":"Point"}
}