{
  "type": "Feature",
  "properties": {
    "iso:country":"US",
    "sg:address":"711 Stony Point Rd",
    "sg:city":"Santa Rosa",
    "sg:classifiers":[
        {
            "category":"Shopping",
            "subcategory":"Jewelry",
            "type":"Retail Goods"
        }
    ],
    "sg:phone":"+1 707 569 8683",
    "sg:postcode":"95407",
    "sg:province":"CA",
    "sg:tags":[
        "jeweler"
    ],
    "wof:name":"Joyeria Lucero",
    "wof:placetype":"venue"
},
  "geometry": {"coordinates":[-122.74144200000001,38.427494],"type":"Point"}
}