{
  "type": "Feature",
  "properties": {
    "iso:country":"US",
    "sg:address":"73430 Hwy 111",
    "sg:city":"Palm Desert",
    "sg:classifiers":[
        {
            "category":"Personal",
            "subcategory":"Beauty Salon",
            "type":"Services"
        }
    ],
    "sg:phone":"+1 760 773 0577",
    "sg:postcode":"92260",
    "sg:province":"CA",
    "wof:name":"Salon 111",
    "wof:placetype":"venue"
},
  "geometry": {"coordinates":[-116.383188,33.721463],"type":"Point"}
}