{
  "type": "Feature",
  "properties": {
    "addr:full":"3522 Stockton Blvd Sacramento CA 95820",
    "addr:housenumber":"3522",
    "addr:postcode":"95820",
    "addr:street":"Stockton Blvd",
    "iso:country":"US",
    "sg:address":"3522 Stockton Blvd",
    "sg:city":"Sacramento",
    "sg:classifiers":[
        {
            "category":"Manufacturing",
            "subcategory":"Printing",
            "type":"Manufacturing & Wholesale Goods"
        }
    ],
    "sg:phone":"+1 916 383 8771",
    "sg:postcode":"95820",
    "sg:province":"CA",
    "sg:tags":[
        "commercial"
    ],
    "wof:name":"Power Bomb Productions",
    "wof:placetype":"venue"
},
  "geometry": {"coordinates":[-121.45129,38.542098],"type":"Point"}
}