{
  "type": "Feature",
  "properties": {
    "addr:full":"190 Evelyn Way San Francisco CA 94127",
    "addr:housenumber":"190",
    "addr:postcode":"94127",
    "addr:street":"Evelyn Way",
    "iso:country":"US",
    "sg:address":"190 Evelyn Way",
    "sg:city":"San Francisco",
    "sg:classifiers":[
        {
            "category":"Building & Trades",
            "subcategory":"Construction",
            "type":"Services"
        }
    ],
    "sg:phone":"+1 415 571 8229",
    "sg:postcode":"94127",
    "sg:province":"CA",
    "sg:tags":[
        "painter"
    ],
    "sg:website":"www.pearlpainting.com/",
    "wof:name":"Pearl Painting",
    "wof:placetype":"venue"
},
  "geometry": {"coordinates":[-122.451201,37.742819],"type":"Point"}
}