{
  "type": "Feature",
  "properties": {
    "iso:country":"US",
    "sg:address":"15 Business Park Way",
    "sg:city":"Sacramento",
    "sg:classifiers":[
        {
            "category":"Health Services",
            "subcategory":"Doctor",
            "type":"Services"
        },
        {
            "category":"Health Services",
            "subcategory":"Health Practitioner",
            "type":"Services"
        }
    ],
    "sg:phone":"+1 916 383 8785",
    "sg:postcode":"95828",
    "sg:province":"CA",
    "sg:tags":[
        "therapy",
        "physical"
    ],
    "wof:name":"River City Physical Therapy Inc.",
    "wof:placetype":"venue"
},
  "geometry": {"coordinates":[-121.396714,38.524751],"type":"Point"}
}