{
  "type": "Feature",
  "properties": {
    "iso:country":"US",
    "sg:address":"2966 Mission Street",
    "sg:city":"San Francisco",
    "sg:classifiers":[
        {
            "category":"Food & Beverages",
            "subcategory":"Groceries & Convenience Stores",
            "type":"Retail Goods"
        }
    ],
    "sg:phone":"+1 415 648 4101",
    "sg:postcode":"94110",
    "sg:province":"CA",
    "wof:name":"Ana Dollar Store",
    "wof:placetype":"venue"
},
  "geometry": {"coordinates":[-122.418397,37.749931],"type":"Point"}
}