{
  "type": "Feature",
  "properties": {
    "iso:country":"US",
    "sg:address":"5150 Neptune Sq Apt B",
    "sg:city":"Oxnard",
    "sg:classifiers":[
        {
            "category":"Education",
            "subcategory":"Special Training",
            "type":"Public Place"
        }
    ],
    "sg:phone":"+1 951 283 8917",
    "sg:postcode":"93035",
    "sg:province":"CA",
    "sg:tags":[
        "educational"
    ],
    "wof:name":"Ll Enterprises",
    "wof:placetype":"venue"
},
  "geometry": {"coordinates":[-119.241193,34.186503],"type":"Point"}
}