{
  "type": "Feature",
  "properties": {
    "iso:country":"US",
    "sg:address":"405 Victory Ave",
    "sg:city":"S San Francisco",
    "sg:classifiers":[
        {
            "category":"Professional",
            "subcategory":"Management & Consulting",
            "type":"Services"
        }
    ],
    "sg:phone":"+1 650 871 6647",
    "sg:postcode":"94080",
    "sg:province":"CA",
    "sg:tags":[
        "party",
        "planning"
    ],
    "wof:name":"Fiesta Filipina",
    "wof:placetype":"venue"
},
  "geometry": {"coordinates":[-122.415359,37.647217],"type":"Point"}
}