{
  "type": "Feature",
  "properties": {
    "addr:full":"1891 N Belmont Rd Exeter CA 93221",
    "addr:housenumber":"1891",
    "addr:postcode":"93221",
    "addr:street":"N Belmont Rd",
    "iso:country":"US",
    "sg:address":"1891 N Belmont Rd",
    "sg:city":"Exeter",
    "sg:classifiers":[
        {
            "category":"Building & Trades",
            "subcategory":"Construction",
            "type":"Services"
        }
    ],
    "sg:phone":"+1 559 592 4059",
    "sg:postcode":"93221",
    "sg:province":"CA",
    "sg:tags":[
        "house",
        "contractor",
        "nonresidential"
    ],
    "wof:name":"Randolph Construction Co",
    "wof:placetype":"venue"
},
  "geometry": {"coordinates":[-119.153516,36.307525],"type":"Point"}
}