{
  "type": "Feature",
  "properties": {
    "iso:country":"US",
    "sg:address":"919 Ming Ave",
    "sg:city":"Bakersfield",
    "sg:classifiers":[
        {
            "category":"Building & Trades",
            "subcategory":"Construction",
            "type":"Services"
        }
    ],
    "sg:phone":"+1 661 831 6323",
    "sg:postcode":"93307",
    "sg:province":"CA",
    "sg:tags":[
        "maker",
        "cabinet"
    ],
    "wof:name":"Haskell's",
    "wof:placetype":"venue"
},
  "geometry": {"coordinates":[-119.01437799999999,35.339451],"type":"Point"}
}