{
  "type": "Feature",
  "properties": {
    "addr:full":"2980 E Capitol Expy Ste 50 San Jose CA 95148",
    "addr:housenumber":"2980",
    "addr:postcode":"95148",
    "addr:street":"E Capitol Expy Ste 50 San Jose",
    "iso:country":"US",
    "sg:address":"2980 E Capitol Expy Ste 50",
    "sg:city":"San Jose",
    "sg:classifiers":[
        {
            "category":"Freight",
            "type":"Transportation"
        },
        {
            "category":"Wholesale",
            "subcategory":"Stationery",
            "type":"Manufacturing & Wholesale Goods"
        }
    ],
    "sg:phone":"+1 408 528 0001",
    "sg:postcode":"95148",
    "sg:province":"CA",
    "sg:tags":[
        "card",
        "shipping"
    ],
    "sg:website":"www.postalannex.com",
    "wof:name":"Postal Annex",
    "wof:placetype":"venue"
},
  "geometry": {"coordinates":[-121.810913,37.328946],"type":"Point"}
}