{
  "type": "Feature",
  "properties": {
    "addr:full":"150 W Willow St Pomona CA 91768",
    "addr:housenumber":"150",
    "addr:postcode":"91768",
    "addr:street":"W Willow St",
    "iso:country":"US",
    "sg:address":"150 W Willow St",
    "sg:city":"Pomona",
    "sg:classifiers":[
        {
            "category":"Wholesale",
            "subcategory":"Groceries",
            "type":"Manufacturing & Wholesale Goods"
        }
    ],
    "sg:phone":"+1 909 622 3321",
    "sg:postcode":"91768",
    "sg:province":"CA",
    "sg:tags":[
        "grocer"
    ],
    "wof:name":"Smart & Final",
    "wof:placetype":"venue"
},
  "geometry": {"coordinates":[-117.753691,34.078985],"type":"Point"}
}