{
  "type": "Feature",
  "properties": {
    "iso:country":"US",
    "sg:address":"8005 Shetland Dr",
    "sg:city":"Bakersfield",
    "sg:classifiers":[
        {
            "category":"Wholesale",
            "subcategory":"Petroleum",
            "type":"Manufacturing & Wholesale Goods"
        }
    ],
    "sg:phone":"+1 661 837 9739",
    "sg:postcode":"93309",
    "sg:province":"CA",
    "sg:tags":[
        "crude",
        "pipeline"
    ],
    "wof:name":"McQueen Larry",
    "wof:placetype":"venue"
},
  "geometry": {"coordinates":[-119.091448,35.337273],"type":"Point"}
}