{
  "type": "Feature",
  "properties": {
    "addr:full":"491 E Main St Grass Valley CA 95945",
    "addr:housenumber":"491",
    "addr:postcode":"95945",
    "addr:street":"E Main St",
    "iso:country":"US",
    "sg:address":"491 E Main St",
    "sg:city":"Grass Valley",
    "sg:classifiers":[
        {
            "category":"Shopping",
            "subcategory":"Bicycles & Sporting Goods",
            "type":"Retail Goods"
        }
    ],
    "sg:phone":"+1 530 477 8006",
    "sg:postcode":"95945",
    "sg:province":"CA",
    "sg:tags":[
        "equipment",
        "camping"
    ],
    "wof:name":"Mountain Recreation",
    "wof:placetype":"venue"
},
  "geometry": {"coordinates":[-121.053787,39.222099],"type":"Point"}
}