{
  "type": "Feature",
  "properties": {
    "addr:full":"10250 Santa Monica Blvd Los Angeles CA 90067",
    "addr:housenumber":"10250",
    "addr:postcode":"90067",
    "addr:street":"Santa Monica Blvd",
    "iso:country":"US",
    "sg:address":"10250 Santa Monica Blvd",
    "sg:city":"Los Angeles",
    "sg:classifiers":[
        {
            "category":"Shopping",
            "subcategory":"Optician",
            "type":"Retail Goods"
        }
    ],
    "sg:phone":"+1 310 553 0486",
    "sg:postcode":"90067",
    "sg:province":"CA",
    "sg:tags":[
        "eyewear"
    ],
    "wof:name":"Occhiali Da Sole 15",
    "wof:placetype":"venue"
},
  "geometry": {"coordinates":[-118.41999800000001,34.0602],"type":"Point"}
}