{
  "type": "Feature",
  "properties": {
    "iso:country":"US",
    "sg:address":"15449 Parthenia St",
    "sg:city":"Sepulveda",
    "sg:classifiers":[
        {
            "category":"Personal",
            "subcategory":"Beauty Salon",
            "type":"Services"
        }
    ],
    "sg:phone":"+1 818 893 0153",
    "sg:postcode":"91343",
    "sg:province":"CA",
    "wof:name":"California Hair & Nails",
    "wof:placetype":"venue"
},
  "geometry": {"coordinates":[-118.468959,34.228356],"type":"Point"}
}