{
  "type": "Feature",
  "properties": {
    "iso:country":"US",
    "sg:address":"660 S Orange Grove Blvd",
    "sg:city":"Pasadena",
    "sg:classifiers":[
        {
            "category":"Wholesale",
            "subcategory":"Durable Goods & Equipment",
            "type":"Manufacturing & Wholesale Goods"
        },
        {
            "category":"Wholesale",
            "subcategory":"Chemicals & Plastics",
            "type":"Manufacturing & Wholesale Goods"
        }
    ],
    "sg:phone":"+1 626 799 9344",
    "sg:postcode":"91105",
    "sg:province":"CA",
    "sg:tags":[
        "representative",
        "manufacturer"
    ],
    "wof:name":"Whitmore & Associates Inc",
    "wof:placetype":"venue"
},
  "geometry": {"coordinates":[-118.15885400000001,34.135077],"type":"Point"}
}