{
  "type": "Feature",
  "properties": {
    "iso:country":"US",
    "sg:address":"14212 Edwards St",
    "sg:city":"Westminster",
    "sg:classifiers":[
        {
            "category":"Social Services",
            "subcategory":"Child Care",
            "type":"Services"
        },
        {
            "category":"Education",
            "subcategory":"Preschool",
            "type":"Public Place"
        },
        {
            "category":"Education",
            "subcategory":"School",
            "type":"Public Place"
        }
    ],
    "sg:phone":"+1 714 894 4924",
    "sg:postcode":"92683",
    "sg:province":"CA",
    "sg:tags":[
        "elementary",
        "day"
    ],
    "wof:name":"Child Care Creative Montessori Experience",
    "wof:placetype":"venue"
},
  "geometry": {"coordinates":[-118.01599899999999,33.755798],"type":"Point"}
}