{
  "type": "Feature",
  "properties": {
    "addr:full":"2432 Bay Rd Redwood City CA 94063",
    "addr:housenumber":"2432",
    "addr:postcode":"94063",
    "addr:street":"Bay Rd",
    "iso:country":"US",
    "sg:address":"2432 Bay Rd",
    "sg:city":"Redwood City",
    "sg:classifiers":[
        {
            "category":"Retail",
            "subcategory":"Repair Shop",
            "type":"Services"
        }
    ],
    "sg:phone":"+1 650 368 1013",
    "sg:postcode":"94063",
    "sg:province":"CA",
    "sg:tags":[
        "upholsterer"
    ],
    "wof:name":"N M Baughman",
    "wof:placetype":"venue"
},
  "geometry": {"coordinates":[-122.210082,37.484613],"type":"Point"}
}