{
  "type": "Feature",
  "properties": {
    "iso:country":"US",
    "sg:address":"2200 W Beverly Blvd",
    "sg:city":"Montebello",
    "sg:classifiers":[
        {
            "category":"Cinema",
            "subcategory":"Movie Rental",
            "type":"Entertainment"
        }
    ],
    "sg:phone":"+1 323 722 1607",
    "sg:postcode":"90640",
    "sg:province":"CA",
    "sg:tags":[
        "leasing",
        "video",
        "disc",
        "tape"
    ],
    "wof:name":"Hollywood Video",
    "wof:placetype":"venue"
},
  "geometry": {"coordinates":[-118.124953,34.021138],"type":"Point"}
}