{
  "type": "Feature",
  "properties": {
    "iso:country":"US",
    "sg:address":"107 A St",
    "sg:city":"Newport Beach",
    "sg:classifiers":[
        {
            "category":"Taxi",
            "type":"Transportation"
        }
    ],
    "sg:phone":"+1 949 209 1200",
    "sg:postcode":"92661",
    "sg:province":"CA",
    "wof:name":"For My Taxi",
    "wof:placetype":"venue"
},
  "geometry": {"coordinates":[-117.89908699999999,33.601195],"type":"Point"}
}