{
  "type": "Feature",
  "properties": {
    "iso:country":"US",
    "sg:address":"30024 Haun Rd",
    "sg:city":"Menifee",
    "sg:classifiers":[
        {
            "category":"Food Court",
            "type":"Food & Drink"
        },
        {
            "category":"Restaurant",
            "type":"Food & Drink"
        }
    ],
    "sg:phone":"+1 951 301 9249",
    "sg:postcode":"92584",
    "sg:province":"CA",
    "sg:tags":[
        "grill",
        "management",
        "bar",
        "mexican"
    ],
    "sg:website":"http://www.chipotle.com",
    "wof:name":"Chipolte Mexican Grill",
    "wof:placetype":"venue"
},
  "geometry": {"coordinates":[-117.175543,33.683371],"type":"Point"}
}