{
  "type": "Feature",
  "properties": {
    "addr:full":"24041 Amador St Hayward CA 94544",
    "addr:housenumber":"24041",
    "addr:postcode":"94544",
    "addr:street":"Amador St",
    "iso:country":"US",
    "sg:address":"24041 Amador St",
    "sg:city":"Hayward",
    "sg:classifiers":[
        {
            "category":"Government",
            "subcategory":"Office",
            "type":"Public Place"
        }
    ],
    "sg:phone":"+1 510 383 5300",
    "sg:postcode":"94544",
    "sg:province":"CA",
    "sg:tags":[
        "government-united",
        "state"
    ],
    "sg:website":"http://www.bayareaeastshore.com",
    "wof:name":"Social Services Dept",
    "wof:placetype":"venue"
},
  "geometry": {"coordinates":[-122.09505799999999,37.660587],"type":"Point"}
}