{
  "type": "Feature",
  "properties": {
    "addr:full":"780 Epperson Dr Rowland Heights CA 91748",
    "addr:housenumber":"780",
    "addr:postcode":"91748",
    "addr:street":"Epperson Dr",
    "iso:country":"US",
    "sg:address":"780 Epperson Dr",
    "sg:city":"Rowland Heights",
    "sg:classifiers":[
        {
            "category":"Wholesale",
            "subcategory":"Groceries",
            "type":"Manufacturing & Wholesale Goods"
        }
    ],
    "sg:phone":"+1 626 854 8080",
    "sg:postcode":"91748",
    "sg:province":"CA",
    "sg:tags":[
        "general"
    ],
    "wof:name":"Royal Crown Foods",
    "wof:placetype":"venue"
},
  "geometry": {"coordinates":[-117.897002,34.001994],"type":"Point"}
}