{
  "type": "Feature",
  "properties": {
    "addr:full":"9903 Santa Monica Blvd Ste 441 Beverly Hills CA 90210",
    "addr:housenumber":"9903",
    "addr:postcode":"90210",
    "addr:street":"Santa Monica Blvd Ste 441;Hills Ca",
    "iso:country":"US",
    "sg:address":"9903 Santa Monica Blvd Ste 441",
    "sg:city":"Beverly Hills",
    "sg:classifiers":[
        {
            "category":"Professional",
            "subcategory":"Lawyer & Legal Services",
            "type":"Services"
        }
    ],
    "sg:phone":"+1 310 997 0905",
    "sg:postcode":"90210",
    "sg:province":"CA",
    "sg:tags":[
        "litigation"
    ],
    "sg:website":"www.regentllp.com",
    "wof:name":"Regent Partners",
    "wof:placetype":"venue"
},
  "geometry": {"coordinates":[-118.410839,34.066741],"type":"Point"}
}