{
  "type": "Feature",
  "properties": {
    "addr:full":"20301 Ventura Blvd Ste 126 Woodland Hills CA 91364",
    "addr:housenumber":"20301",
    "addr:postcode":"91364",
    "addr:street":"Ventura Blvd Ste 126",
    "iso:country":"US",
    "sg:address":"20301 Ventura Blvd Ste 126",
    "sg:city":"Woodland Hills",
    "sg:classifiers":[
        {
            "category":"Professional",
            "subcategory":"Lawyer & Legal Services",
            "type":"Services"
        }
    ],
    "sg:phone":"+1 818 610 8699",
    "sg:postcode":"91364",
    "sg:province":"CA",
    "wof:name":"Law Offices of Sean E Judge Attys",
    "wof:placetype":"venue"
},
  "geometry": {"coordinates":[-118.574997,34.169498],"type":"Point"}
}