{
  "type": "Feature",
  "properties": {
    "iso:country":"US",
    "sg:address":"3770 Main St",
    "sg:city":"Oakley",
    "sg:classifiers":[
        {
            "category":"Autos & Motor Vehicles",
            "subcategory":"Auto Supplies",
            "type":"Retail Goods"
        },
        {
            "category":"Retail",
            "subcategory":"Auto Repair",
            "type":"Services"
        }
    ],
    "sg:phone":"+1 925 625 2765",
    "sg:postcode":"94561",
    "sg:province":"CA",
    "sg:tags":[
        "recap",
        "retread",
        "tire"
    ],
    "wof:name":"Cutino's Tire Center",
    "wof:placetype":"venue"
},
  "geometry": {"coordinates":[-121.708899,37.996447],"type":"Point"}
}