{
  "type": "Feature",
  "properties": {
    "addr:full":"21115 Longeway Rd Ste B Sonora CA 95370",
    "addr:housenumber":"21115",
    "addr:postcode":"95370",
    "addr:street":"Longeway Rd Ste B",
    "iso:country":"US",
    "sg:address":"21115 Longeway Rd Ste B",
    "sg:city":"Sonora",
    "sg:classifiers":[
        {
            "category":"Personal",
            "type":"Services"
        },
        {
            "category":"Shopping",
            "subcategory":"Computers & Home Electronics",
            "type":"Retail Goods"
        }
    ],
    "sg:phone":"+1 209 532 9662",
    "sg:postcode":"95370",
    "sg:province":"CA",
    "sg:website":"www.mountainalarminc.com",
    "wof:name":"Alarms by Mountain",
    "wof:placetype":"venue"
},
  "geometry": {"coordinates":[-120.25584000000001,38.027219],"type":"Point"}
}