{
  "type": "Feature",
  "properties": {
    "addr:full":"2131 Crossroads Pl Livermore CA 94550",
    "addr:housenumber":"2131",
    "addr:postcode":"94550",
    "addr:street":"Crossroads Pl",
    "iso:country":"US",
    "sg:address":"2131 Crossroads Pl",
    "sg:city":"Livermore",
    "sg:classifiers":[
        {
            "category":"Banks & Credit Unions",
            "subcategory":"Investment Brokerage",
            "type":"Services"
        }
    ],
    "sg:phone":"+1 925 371 7101",
    "sg:postcode":"94550",
    "sg:province":"CA",
    "wof:name":"Saber Investments",
    "wof:placetype":"venue"
},
  "geometry": {"coordinates":[-121.79594,37.65496],"type":"Point"}
}