{
  "type": "Feature",
  "properties": {
    "addr:full":"8201 Newman Avenue Suite 102 Huntington Beach CA 92647",
    "addr:housenumber":"8201",
    "addr:postcode":"92647",
    "addr:street":"Newman Avenue Suite 102",
    "iso:country":"US",
    "sg:address":"8201 Newman Avenue Suite 102",
    "sg:city":"Huntington Beach",
    "sg:classifiers":[
        {
            "category":"Health Services",
            "subcategory":"Chiropractor",
            "type":"Services"
        }
    ],
    "sg:phone":"+1 714 847 5350",
    "sg:postcode":"92647",
    "sg:province":"CA",
    "sg:website":"www.marcbock.com",
    "wof:name":"Bock Marcandre DC PHD",
    "wof:placetype":"venue"
},
  "geometry": {"coordinates":[-118.00452900000001,33.720618],"type":"Point"}
}