{
  "type": "Feature",
  "properties": {
    "addr:full":"3728 W Sunset Blvd Los Angeles CA 90026",
    "addr:housenumber":"3728",
    "addr:postcode":"90026",
    "addr:street":"W Sunset Blvd",
    "iso:country":"US",
    "sg:address":"3728 W Sunset Blvd",
    "sg:city":"Los Angeles",
    "sg:classifiers":[
        {
            "category":"Personal",
            "subcategory":"Beauty Salon",
            "type":"Services"
        }
    ],
    "sg:phone":"+1 323 661 1300",
    "sg:postcode":"90026",
    "sg:province":"CA",
    "wof:name":"R Hair & Makeup Studio",
    "wof:placetype":"venue"
},
  "geometry": {"coordinates":[-118.278538,34.090723],"type":"Point"}
}