{
  "type": "Feature",
  "properties": {
    "iso:country":"US",
    "sg:address":"9204 Valleyoak Dr",
    "sg:city":"Stockton",
    "sg:classifiers":[
        {
            "category":"Professional",
            "subcategory":"Business Services",
            "type":"Services"
        }
    ],
    "sg:phone":"+1 209 473 3721",
    "sg:postcode":"95209",
    "sg:province":"CA",
    "sg:tags":[
        "embroidery"
    ],
    "wof:name":"Marisol Embroidery",
    "wof:placetype":"venue"
},
  "geometry": {"coordinates":[-121.323399,38.034992],"type":"Point"}
}