{
  "type": "Feature",
  "properties": {
    "iso:country":"US",
    "sg:address":"2900 W Beverly Blvd Unit D",
    "sg:city":"Montebello",
    "sg:classifiers":[
        {
            "category":"Restaurant",
            "type":"Food & Drink"
        }
    ],
    "sg:phone":"+1 323 888 6082",
    "sg:postcode":"90640",
    "sg:province":"CA",
    "sg:tags":[
        "pizza"
    ],
    "wof:name":"Papa John's",
    "wof:placetype":"venue"
},
  "geometry": {"coordinates":[-118.134157,34.022963],"type":"Point"}
}