{
  "type": "Feature",
  "properties": {
    "addr:full":"199 Fremont St San Francisco CA 94105",
    "addr:housenumber":"199",
    "addr:postcode":"94105",
    "addr:street":"Fremont St",
    "iso:country":"US",
    "sg:address":"199 Fremont St",
    "sg:city":"San Francisco",
    "sg:classifiers":[
        {
            "category":"Professional",
            "subcategory":"Computer Services",
            "type":"Services"
        }
    ],
    "sg:phone":"+1 415 247 8800",
    "sg:postcode":"94105",
    "sg:province":"CA",
    "sg:tags":[
        "repair"
    ],
    "sg:website":"www.riverbed.com",
    "wof:name":"Riverbed Technology",
    "wof:placetype":"venue"
},
  "geometry": {"coordinates":[-122.394893,37.789884],"type":"Point"}
}