{
  "type": "Feature",
  "properties": {
    "iso:country":"US",
    "sg:address":"27360 Muirfield Ln",
    "sg:city":"Valencia",
    "sg:classifiers":[
        {
            "category":"Wholesale",
            "subcategory":"Medical Equipment & Supplies",
            "type":"Manufacturing & Wholesale Goods"
        },
        {
            "category":"Shopping",
            "subcategory":"Pharmacy",
            "type":"Retail Goods"
        },
        {
            "category":"Health Services",
            "subcategory":"Dentist",
            "type":"Services"
        }
    ],
    "sg:phone":"+1 661 295 0900",
    "sg:postcode":"91355",
    "sg:province":"CA",
    "sg:tags":[
        "home",
        "dental",
        "care"
    ],
    "wof:name":"Talladium Inc.",
    "wof:placetype":"venue"
},
  "geometry": {"coordinates":[-118.61346500000001,34.446423],"type":"Point"}
}