{
  "type": "Feature",
  "properties": {
    "addr:full":"27825 Smyth Dr Valencia CA 91355",
    "addr:postcode":"27825;91355",
    "addr:street":"Smyth Dr",
    "iso:country":"US",
    "sg:address":"27825 Smyth Dr",
    "sg:city":"Valencia",
    "sg:classifiers":[
        {
            "category":"Professional",
            "type":"Services"
        }
    ],
    "sg:phone":"+1 661 294 0065",
    "sg:postcode":"91355",
    "sg:province":"CA",
    "sg:tags":[
        "consultant",
        "geological"
    ],
    "wof:name":"Allan E Seward Engnrng Geology",
    "wof:placetype":"venue"
},
  "geometry": {"coordinates":[-118.56517599999999,34.440427],"type":"Point"}
}