{
  "type": "Feature",
  "properties": {
    "iso:country":"US",
    "sg:address":"442 S Alexandria Ave",
    "sg:city":"Los Angeles",
    "sg:classifiers":[
        {
            "category":"Restaurant",
            "type":"Food & Drink"
        }
    ],
    "sg:phone":"+1 213 487 2152",
    "sg:postcode":"90020",
    "sg:province":"CA",
    "sg:tags":[
        "caterer"
    ],
    "wof:name":"Your Wish Is My Command",
    "wof:placetype":"venue"
},
  "geometry": {"coordinates":[-118.297858,34.066174],"type":"Point"}
}