{
  "type": "Feature",
  "properties": {
    "addr:full":"801 Palomar St Chula Vista CA 91911",
    "addr:housenumber":"801",
    "addr:postcode":"91911",
    "addr:street":"Palomar St",
    "iso:country":"US",
    "sg:address":"801 Palomar St",
    "sg:city":"Chula Vista",
    "sg:classifiers":[
        {
            "category":"Travel",
            "subcategory":"Hotels & Motels",
            "type":"Entertainment"
        }
    ],
    "sg:phone":"+1 619 423 8889",
    "sg:postcode":"91911",
    "sg:province":"CA",
    "sg:website":"www.palomarinnchulavista.com",
    "wof:name":"Palomar Inn",
    "wof:placetype":"venue"
},
  "geometry": {"coordinates":[-117.091003,32.604301],"type":"Point"}
}