{
  "type": "Feature",
  "properties": {
    "addr:full":"321 W Torrance Blvd Carson CA 90745",
    "addr:housenumber":"321",
    "addr:postcode":"90745",
    "addr:street":"W Torrance Blvd",
    "iso:country":"US",
    "sg:address":"321 W Torrance Blvd",
    "sg:city":"Carson",
    "sg:classifiers":[
        {
            "category":"Museum",
            "type":"Entertainment"
        }
    ],
    "sg:phone":"+1 310 516 6795",
    "sg:postcode":"90745",
    "sg:province":"CA",
    "wof:name":"Internatl. Printing Museum",
    "wof:placetype":"venue"
},
  "geometry": {"coordinates":[-118.282276,33.842229],"type":"Point"}
}