{
  "type": "Feature",
  "properties": {
    "addr:full":"10652 Flower Ave Stanton CA 90680",
    "addr:housenumber":"10652",
    "addr:postcode":"ca 90680",
    "addr:street":"Flower Ave",
    "iso:country":"US",
    "sg:address":"10652 Flower Ave",
    "sg:city":"Stanton",
    "sg:classifiers":[
        {
            "category":"Home & Garden",
            "subcategory":"Building Materials",
            "type":"Retail Goods"
        }
    ],
    "sg:phone":"+1 714 229 8340",
    "sg:postcode":"90680",
    "sg:province":"CA",
    "sg:tags":[
        "supply"
    ],
    "wof:name":"Wells Pipeline Materials",
    "wof:placetype":"venue"
},
  "geometry": {"coordinates":[-117.995003,33.8083],"type":"Point"}
}