{
  "type": "Feature",
  "properties": {
    "iso:country":"US",
    "sg:address":"212 W F St",
    "sg:city":"Tehachapi",
    "sg:classifiers":[
        {
            "category":"Professional",
            "subcategory":"Accounting & Tax Preparation",
            "type":"Services"
        }
    ],
    "sg:phone":"+1 661 822 1750",
    "sg:postcode":"93561",
    "sg:province":"CA",
    "sg:tags":[
        "accountant"
    ],
    "wof:name":"D R Moats & Co",
    "wof:placetype":"venue"
},
  "geometry": {"coordinates":[-118.45077000000001,35.13133],"type":"Point"}
}