{
  "type": "Feature",
  "properties": {
    "iso:country":"US",
    "sg:address":"6323 Ave 280",
    "sg:city":"Visalia",
    "sg:classifiers":[
        {
            "category":"Wholesale",
            "subcategory":"Dairy",
            "type":"Manufacturing & Wholesale Goods"
        }
    ],
    "sg:phone":"+1 559 651 1947",
    "sg:postcode":"93277",
    "sg:province":"CA",
    "sg:tags":[
        "product"
    ],
    "wof:name":"Lucio Dairy",
    "wof:placetype":"venue"
},
  "geometry": {"coordinates":[-119.43367600000001,36.297843],"type":"Point"}
}