{
  "type": "Feature",
  "properties": {
    "iso:country":"US",
    "sg:address":"2630 Gassmann Drive",
    "sg:city":"San Jose",
    "sg:classifiers":[
        {
            "category":"Retail",
            "subcategory":"Car Wash",
            "type":"Services"
        }
    ],
    "sg:phone":"+1 408 569 7716",
    "sg:postcode":"95121",
    "sg:province":"CA",
    "wof:name":"Elite Services Waterless Mobile Carwash",
    "wof:placetype":"venue"
},
  "geometry": {"coordinates":[-121.83738200000001,37.307212],"type":"Point"}
}