{
  "type": "Feature",
  "properties": {
    "iso:country":"US",
    "sg:address":"16560 W Hobsonway",
    "sg:city":"Blythe",
    "sg:classifiers":[
        {
            "category":"Building & Trades",
            "subcategory":"Plumbing",
            "type":"Services"
        }
    ],
    "sg:phone":"+1 760 922 9950",
    "sg:postcode":"92225",
    "sg:province":"CA",
    "sg:tags":[
        "product",
        "management",
        "energy",
        "system"
    ],
    "wof:name":"Blythe Energy",
    "wof:placetype":"venue"
},
  "geometry": {"coordinates":[-114.701766,33.609801],"type":"Point"}
}