{
  "type": "Feature",
  "properties": {
    "addr:full":"136 E 4th St San Dimas CA 91773",
    "addr:housenumber":"136",
    "addr:postcode":"91773",
    "addr:street":"E 4Th St",
    "iso:country":"US",
    "sg:address":"136 E 4th St",
    "sg:city":"San Dimas",
    "sg:classifiers":[
        {
            "category":"Building & Trades",
            "subcategory":"Pest Control",
            "type":"Services"
        }
    ],
    "sg:phone":"+1 909 592 1221",
    "sg:postcode":"91773",
    "sg:province":"CA",
    "wof:name":"A-Plus Termite Control",
    "wof:placetype":"venue"
},
  "geometry": {"coordinates":[-117.805031,34.110598],"type":"Point"}
}