{
  "type": "Feature",
  "properties": {
    "iso:country":"US",
    "sg:address":"931 Washington Blvd",
    "sg:city":"Roseville",
    "sg:classifiers":[
        {
            "category":"Shopping",
            "subcategory":"Clothing, Apparel, & Fashions",
            "type":"Retail Goods"
        },
        {
            "category":"Professional",
            "subcategory":"Advertising",
            "type":"Services"
        },
        {
            "category":"Shopping",
            "subcategory":"Crafts & Fabrics",
            "type":"Retail Goods"
        },
        {
            "category":"Professional",
            "subcategory":"Printing & Photocopies",
            "type":"Services"
        }
    ],
    "sg:phone":"+1 916 774 1616",
    "sg:postcode":"95678",
    "sg:province":"CA",
    "sg:tags":[
        "product",
        "screen",
        "trophies",
        "t-shirt",
        "embroidery",
        "advertising-promotional",
        "medal",
        "plaque"
    ],
    "sg:website":"http://www.promotemeroseville.com",
    "wof:name":"Promote Me",
    "wof:placetype":"venue"
},
  "geometry": {"coordinates":[-121.292055,38.759907],"type":"Point"}
}