{
  "type": "Feature",
  "properties": {
    "addr:full":"666 W 18th St Costa Mesa CA 92627",
    "addr:housenumber":"666",
    "addr:postcode":"92627",
    "addr:street":"W 18Th St",
    "iso:country":"US",
    "sg:address":"666 W 18th St",
    "sg:city":"Costa Mesa",
    "sg:classifiers":[
        {
            "category":"Professional",
            "type":"Services"
        }
    ],
    "sg:phone":"+1 949 646 3600",
    "sg:postcode":"92627",
    "sg:province":"CA",
    "wof:name":"Diabeticare Inc",
    "wof:placetype":"venue"
},
  "geometry": {"coordinates":[-117.926541,33.639862],"type":"Point"}
}