{
  "type": "Feature",
  "properties": {
    "iso:country":"US",
    "sg:address":"11932 Earlham St",
    "sg:city":"Orange",
    "sg:classifiers":[
        {
            "category":"Education",
            "subcategory":"Special Training",
            "type":"Public Place"
        }
    ],
    "sg:phone":"+1 714 744 1464",
    "sg:postcode":"92869",
    "sg:province":"CA",
    "sg:tags":[
        "instruction",
        "driving"
    ],
    "wof:name":"A-Teen Driving Academy",
    "wof:placetype":"venue"
},
  "geometry": {"coordinates":[-117.807867,33.788081],"type":"Point"}
}