{
  "type": "Feature",
  "properties": {
    "iso:country":"US",
    "sg:address":"515 S Smith Ave",
    "sg:city":"Corona",
    "sg:classifiers":[
        {
            "category":"Health Services",
            "subcategory":"Health Practitioner",
            "type":"Services"
        }
    ],
    "sg:phone":"+1 951 898 3668",
    "sg:postcode":"92882",
    "sg:province":"CA",
    "sg:tags":[
        "acupuncture"
    ],
    "wof:name":"Corona Acupuncture",
    "wof:placetype":"venue"
},
  "geometry": {"coordinates":[-117.594154,33.879499],"type":"Point"}
}