{
  "type": "Feature",
  "properties": {
    "addr:full":"351 W Chanslor Ave Richmond CA 94801",
    "addr:housenumber":"351",
    "addr:postcode":"94801",
    "addr:street":"W Chanslor Ave",
    "iso:country":"US",
    "sg:address":"351 W Chanslor Ave",
    "sg:city":"Richmond",
    "sg:classifiers":[
        {
            "category":"Recreation",
            "type":"Entertainment"
        }
    ],
    "sg:phone":"+1 510 237 3474",
    "sg:postcode":"94801",
    "sg:province":"CA",
    "sg:tags":[
        "party",
        "fishing"
    ],
    "wof:name":"Fish On Line Reservations",
    "wof:placetype":"venue"
},
  "geometry": {"coordinates":[-122.37466499999999,37.9337],"type":"Point"}
}