{
  "type": "Feature",
  "properties": {
    "addr:full":"1690 Civic Center Dr Santa Clara CA 95050",
    "addr:housenumber":"1690",
    "addr:postcode":"95050",
    "addr:street":"Civic Center Dr",
    "iso:country":"US",
    "sg:address":"1690 Civic Center Dr",
    "sg:city":"Santa Clara",
    "sg:classifiers":[
        {
            "category":"Professional",
            "subcategory":"Business Services",
            "type":"Services"
        }
    ],
    "sg:phone":"+1 415 716 4800",
    "sg:postcode":"95050",
    "sg:province":"CA",
    "sg:tags":[
        "printing",
        "broker"
    ],
    "wof:name":"02 Enterprises Inc",
    "wof:placetype":"venue"
},
  "geometry": {"coordinates":[-121.956067,37.353381],"type":"Point"}
}