{
  "type": "Feature",
  "properties": {
    "iso:country":"US",
    "sg:address":"12707 Rives Ave",
    "sg:city":"Downey",
    "sg:classifiers":[
        {
            "category":"Building & Trades",
            "subcategory":"Pest Control",
            "type":"Services"
        }
    ],
    "sg:phone":"+1 562 940 1533",
    "sg:postcode":"90242",
    "sg:province":"CA",
    "wof:name":"Bug Masters",
    "wof:placetype":"venue"
},
  "geometry": {"coordinates":[-118.157145,33.925551],"type":"Point"}
}