{
  "type": "Feature",
  "properties": {
    "iso:country":"US",
    "sg:address":"13470 Lincoln Way",
    "sg:city":"Auburn",
    "sg:classifiers":[
        {
            "category":"Professional",
            "type":"Services"
        }
    ],
    "sg:phone":"+1 530 888 7417",
    "sg:postcode":"95603",
    "sg:province":"CA",
    "sg:tags":[
        "caterer"
    ],
    "wof:name":"Penguin's Catering",
    "wof:placetype":"venue"
},
  "geometry": {"coordinates":[-121.055791,38.927559],"type":"Point"}
}