{
  "type": "Feature",
  "properties": {
    "iso:country":"US",
    "sg:address":"2010 Hilltop Dr",
    "sg:city":"Redding",
    "sg:classifiers":[
        {
            "category":"Shopping",
            "subcategory":"Clothing, Apparel, & Fashions",
            "type":"Retail Goods"
        }
    ],
    "sg:phone":"+1 530 221 3089",
    "sg:postcode":"96002",
    "sg:province":"CA",
    "sg:tags":[
        "shop",
        "bridal"
    ],
    "wof:name":"Occasions Bridal Prom Party",
    "wof:placetype":"venue"
},
  "geometry": {"coordinates":[-122.35799799999999,40.577508],"type":"Point"}
}