{
  "type": "Feature",
  "properties": {
    "addr:full":"373 N La Cienega Blvd 2nd Fl West Hollywood CA 90048",
    "addr:housenumber":"373",
    "addr:postcode":"90048",
    "addr:street":"N La Cienega Blvd 2Nd Fl",
    "iso:country":"US",
    "sg:address":"373 N La Cienega Blvd 2nd Fl",
    "sg:city":"West Hollywood",
    "sg:classifiers":[
        {
            "category":"Personal",
            "subcategory":"Beauty Salon",
            "type":"Services"
        }
    ],
    "sg:phone":"+1 310 927 0072",
    "sg:postcode":"90048",
    "sg:province":"CA",
    "sg:tags":[
        "hair"
    ],
    "sg:website":"facebook.com/matthewg.hair",
    "wof:name":"Matthew G. Hair",
    "wof:placetype":"venue"
},
  "geometry": {"coordinates":[-118.376586,34.07806],"type":"Point"}
}