{
  "type": "Feature",
  "properties": {
    "addr:full":"4082 N Benedict Ave Fresno CA 93722",
    "addr:housenumber":"4082",
    "addr:postcode":"93722",
    "addr:street":"N Benedict Ave",
    "iso:country":"US",
    "sg:address":"4082 N Benedict Ave",
    "sg:city":"Fresno",
    "sg:classifiers":[
        {
            "category":"Building & Trades",
            "subcategory":"Construction",
            "type":"Services"
        }
    ],
    "sg:phone":"+1 559 213 0870",
    "sg:postcode":"93722",
    "sg:province":"CA",
    "sg:tags":[
        "resurfacing",
        "laying",
        "refinishing",
        "floor"
    ],
    "wof:name":"Felix's Floor Svc",
    "wof:placetype":"venue"
},
  "geometry": {"coordinates":[-119.847106,36.795052],"type":"Point"}
}