{
  "type": "Feature",
  "properties": {
    "iso:country":"US",
    "sg:address":"15359 S Hacienda Blvd",
    "sg:city":"Hacienda Heights",
    "sg:classifiers":[
        {
            "category":"Wholesale",
            "subcategory":"Jewelry",
            "type":"Manufacturing & Wholesale Goods"
        }
    ],
    "sg:phone":"+1 626 369 2648",
    "sg:postcode":"91745",
    "sg:province":"CA",
    "sg:tags":[
        "stone"
    ],
    "wof:name":"Her Fashion Jewelry",
    "wof:placetype":"venue"
},
  "geometry": {"coordinates":[-117.971025,33.986613],"type":"Point"}
}