{
  "type": "Feature",
  "properties": {
    "addr:full":"18091 Norwood Park Pl Tustin CA 92780",
    "addr:housenumber":"18091",
    "addr:postcode":"92780",
    "addr:street":"Norwood Park Pl",
    "iso:country":"US",
    "sg:address":"18091 Norwood Park Pl",
    "sg:city":"Tustin",
    "sg:classifiers":[
        {
            "category":"Arena",
            "subcategory":"Sports Club",
            "type":"Entertainment"
        }
    ],
    "sg:phone":"+1 714 730 9154",
    "sg:postcode":"92780",
    "sg:province":"CA",
    "sg:tags":[
        "manager",
        "recruiter",
        "promoter"
    ],
    "wof:name":"Best Of The Best Of Baseball",
    "wof:placetype":"venue"
},
  "geometry": {"coordinates":[-117.81661800000001,33.754014],"type":"Point"}
}