{
  "type": "Feature",
  "properties": {
    "addr:full":"1643 India St San Diego CA 92101",
    "addr:housenumber":"1643",
    "addr:postcode":"92101",
    "addr:street":"India St",
    "iso:country":"US",
    "sg:address":"1643 India St",
    "sg:city":"San Diego",
    "sg:classifiers":[
        {
            "category":"Restaurant",
            "type":"Food & Drink"
        },
        {
            "category":"Bakery",
            "type":"Food & Drink"
        }
    ],
    "sg:phone":"+1 619 233 3506",
    "sg:postcode":"92101",
    "sg:province":"CA",
    "sg:tags":[
        "italian"
    ],
    "sg:website":"www.solunto.biz/",
    "wof:name":"Panificio e Ristorante Solunto",
    "wof:placetype":"venue"
},
  "geometry": {"coordinates":[-117.16799899999999,32.72253],"type":"Point"}
}