{
  "type": "Feature",
  "properties": {
    "addr:full":"117 Via Yella Newport Beach CA 92663",
    "addr:housenumber":"117",
    "addr:postcode":"92663",
    "addr:street":"Via Yella",
    "iso:country":"US",
    "sg:address":"117 Via Yella",
    "sg:city":"Newport Beach",
    "sg:classifiers":[
        {
            "category":"Building & Trades",
            "subcategory":"Construction",
            "type":"Services"
        }
    ],
    "sg:phone":"+1 949 673 8881",
    "sg:postcode":"92663",
    "sg:province":"CA",
    "sg:tags":[
        "house"
    ],
    "wof:name":"Gerald A Fults",
    "wof:placetype":"venue"
},
  "geometry": {"coordinates":[-117.91128999999999,33.610462],"type":"Point"}
}