{
  "type": "Feature",
  "properties": {
    "addr:full":"22325 Sierra Vista Ave Gerber CA 96035",
    "addr:housenumber":"22325",
    "addr:postcode":"96035",
    "addr:street":"Sierra Vista Ave",
    "iso:country":"US",
    "sg:address":"22325 Sierra Vista Ave",
    "sg:city":"Gerber",
    "sg:classifiers":[
        {
            "category":"Farming",
            "subcategory":"Livestock Farm",
            "type":"Manufacturing & Wholesale Goods"
        }
    ],
    "sg:phone":"+1 530 385 1327",
    "sg:postcode":"96035",
    "sg:province":"CA",
    "sg:tags":[
        "beef",
        "feedlot",
        "cattle"
    ],
    "wof:name":"Carl Hale",
    "wof:placetype":"venue"
},
  "geometry": {"coordinates":[-122.20357300000001,40.043825],"type":"Point"}
}