{
  "type": "Feature",
  "properties": {
    "iso:country":"US",
    "sg:address":"1422 Navellier Street",
    "sg:city":"El Cerrito",
    "sg:classifiers":[
        {
            "category":"Education",
            "subcategory":"Preschool",
            "type":"Public Place"
        },
        {
            "category":"Education",
            "subcategory":"School",
            "type":"Public Place"
        }
    ],
    "sg:phone":"+1 510 234 5918",
    "sg:postcode":"94530",
    "sg:province":"CA",
    "sg:tags":[
        "elementary"
    ],
    "wof:name":"Peter Pan Company-Op Nursery",
    "wof:placetype":"venue"
},
  "geometry": {"coordinates":[-122.304001,37.922298],"type":"Point"}
}