{
  "type": "Feature",
  "properties": {
    "addr:full":"23720 Lucas Dr Quail Valley CA 92587",
    "addr:housenumber":"23720",
    "addr:postcode":"92587",
    "addr:street":"Lucas Dr Quail",
    "iso:country":"US",
    "sg:address":"23720 Lucas Dr",
    "sg:city":"Quail Valley",
    "sg:classifiers":[
        {
            "category":"Building & Trades",
            "subcategory":"Construction",
            "type":"Services"
        }
    ],
    "sg:phone":"+1 951 244 0609",
    "sg:postcode":"92587",
    "sg:province":"CA",
    "sg:tags":[
        "fence",
        "contractor"
    ],
    "wof:name":"Steven Peters Fencing",
    "wof:placetype":"venue"
},
  "geometry": {"coordinates":[-117.24677200000001,33.709311],"type":"Point"}
}