{
  "type": "Feature",
  "properties": {
    "iso:country":"US",
    "sg:address":"1925 F St",
    "sg:city":"Sacramento",
    "sg:classifiers":[
        {
            "category":"Professional",
            "subcategory":"Computer Services",
            "type":"Services"
        }
    ],
    "sg:phone":"+1 916 447 9753",
    "sg:postcode":"95811",
    "sg:province":"CA",
    "sg:tags":[
        "stereo",
        "installation"
    ],
    "sg:website":"www.raysautostereo.com",
    "wof:name":"Ray's Auto Stereo",
    "wof:placetype":"venue"
},
  "geometry": {"coordinates":[-121.478172,38.581346],"type":"Point"}
}