{
  "type": "Feature",
  "properties": {
    "addr:full":"400 Sunrise Ave Roseville CA 95661",
    "addr:housenumber":"400",
    "addr:postcode":"95661",
    "addr:street":"Sunrise Ave",
    "iso:country":"US",
    "sg:address":"400 Sunrise Ave",
    "sg:city":"Roseville",
    "sg:classifiers":[
        {
            "category":"Restaurant",
            "type":"Food & Drink"
        },
        {
            "category":"Recreation",
            "subcategory":"Barbecue",
            "type":"Entertainment"
        },
        {
            "category":"Home & Garden",
            "subcategory":"Furniture",
            "type":"Retail Goods"
        }
    ],
    "sg:phone":"+1 916 847 2051",
    "sg:postcode":"95661",
    "sg:province":"CA",
    "sg:tags":[
        "grill",
        "outdoor",
        "supply",
        "house",
        "steak",
        "patio"
    ],
    "wof:name":"America's Barbecue Islands",
    "wof:placetype":"venue"
},
  "geometry": {"coordinates":[-121.272034,38.740175],"type":"Point"}
}