{
  "type": "Feature",
  "properties": {
    "iso:country":"US",
    "sg:address":"1135 E Wooley Rd",
    "sg:city":"Oxnard",
    "sg:classifiers":[
        {
            "category":"Professional",
            "subcategory":"Research",
            "type":"Services"
        }
    ],
    "sg:phone":"+1 805 247 1069",
    "sg:postcode":"93030",
    "sg:province":"CA",
    "sg:tags":[
        "environmental",
        "ecological"
    ],
    "wof:name":"Diversified Minerals Inc",
    "wof:placetype":"venue"
},
  "geometry": {"coordinates":[-119.166387,34.189938],"type":"Point"}
}