{
  "type": "Feature",
  "properties": {
    "iso:country":"US",
    "sg:address":"3615 Loosmore St",
    "sg:city":"Los Angeles",
    "sg:classifiers":[
        {
            "category":"Professional",
            "subcategory":"Art Services",
            "type":"Services"
        }
    ],
    "sg:phone":"+1 323 225 1795",
    "sg:postcode":"90065",
    "sg:province":"CA",
    "sg:tags":[
        "graphic",
        "designer"
    ],
    "wof:name":"Halo Group",
    "wof:placetype":"venue"
},
  "geometry": {"coordinates":[-118.221189,34.098376],"type":"Point"}
}