{
  "type": "Feature",
  "properties": {
    "addr:full":"100 S Wilson Ave Pasadena CA 91106",
    "addr:housenumber":"100",
    "addr:postcode":"91106",
    "addr:street":"S Wilson Ave",
    "iso:country":"US",
    "sg:address":"100 S Wilson Ave",
    "sg:city":"Pasadena",
    "sg:classifiers":[
        {
            "category":"Professional",
            "subcategory":"Engineering",
            "type":"Services"
        }
    ],
    "sg:phone":"+1 626 796 9319",
    "sg:postcode":"91106",
    "sg:province":"CA",
    "sg:tags":[
        "engineer"
    ],
    "wof:name":"Spears Engineering Co",
    "wof:placetype":"venue"
},
  "geometry": {"coordinates":[-118.12802600000001,34.14386],"type":"Point"}
}