{
  "type": "Feature",
  "properties": {
    "addr:full":"1990 10th St Redding CA 96001",
    "addr:housenumber":"1990",
    "addr:postcode":"96001",
    "addr:street":"10Th St",
    "iso:country":"US",
    "sg:address":"1990 10th St",
    "sg:city":"Redding",
    "sg:classifiers":[
        {
            "category":"Shopping",
            "subcategory":"Crafts & Fabrics",
            "type":"Retail Goods"
        }
    ],
    "sg:phone":"+1 530 246 0114",
    "sg:postcode":"96001",
    "sg:province":"CA",
    "sg:tags":[
        "sewing"
    ],
    "wof:name":"Sew Sew Beautiful",
    "wof:placetype":"venue"
},
  "geometry": {"coordinates":[-122.40276900000001,40.587653],"type":"Point"}
}