{
  "type": "Feature",
  "properties": {
    "addr:full":"7424 Deering Ave Canoga Park CA 91303",
    "addr:housenumber":"7424",
    "addr:postcode":"91303",
    "addr:street":"Deering Ave",
    "iso:country":"US",
    "sg:address":"7424 Deering Ave",
    "sg:city":"Canoga Park",
    "sg:classifiers":[
        {
            "category":"Retail",
            "subcategory":"Auto Repair",
            "type":"Services"
        }
    ],
    "sg:phone":"+1 818 348 2450",
    "sg:postcode":"91303",
    "sg:province":"CA",
    "sg:tags":[
        "body",
        "shop",
        "painting",
        "automobile"
    ],
    "wof:name":"Hamrick Body & Paint Shop",
    "wof:placetype":"venue"
},
  "geometry": {"coordinates":[-118.59699999999999,34.2057],"type":"Point"}
}