{
  "type": "Feature",
  "properties": {
    "iso:country":"US",
    "sg:address":"6635 Alhambra Ave",
    "sg:city":"Martinez",
    "sg:classifiers":[
        {
            "category":"Restaurant",
            "type":"Food & Drink"
        }
    ],
    "sg:phone":"+1 925 943 5771",
    "sg:postcode":"94553",
    "sg:province":"CA",
    "wof:name":"Macao Kitchen",
    "wof:placetype":"venue"
},
  "geometry": {"coordinates":[-122.093607,37.959341],"type":"Point"}
}