{
  "type": "Feature",
  "properties": {
    "iso:country":"US",
    "sg:address":"22690 Cactus Ave",
    "sg:city":"Moreno Valley",
    "sg:classifiers":[
        {
            "category":"Social Services",
            "type":"Services"
        }
    ],
    "sg:phone":"+1 951 413 5625",
    "sg:postcode":"92555",
    "sg:province":"CA",
    "sg:tags":[
        "training",
        "center"
    ],
    "wof:name":"Public Social Services",
    "wof:placetype":"venue"
},
  "geometry": {"coordinates":[-117.26747400000001,33.910241],"type":"Point"}
}