{
  "type": "Feature",
  "properties": {
    "iso:country":"US",
    "sg:address":"1457 E Washington Boulevard",
    "sg:city":"Los Angeles",
    "sg:classifiers":[
        {
            "category":"Shopping",
            "subcategory":"Crafts & Fabrics",
            "type":"Retail Goods"
        }
    ],
    "sg:phone":"+1 213 747 2673",
    "sg:postcode":"90021",
    "sg:province":"CA",
    "sg:tags":[
        "store"
    ],
    "wof:name":"Security Textiles",
    "wof:placetype":"venue"
},
  "geometry": {"coordinates":[-118.246551,34.022468],"type":"Point"}
}