{
  "type": "Feature",
  "properties": {
    "addr:full":"3030 Skyway Dr Santa Maria CA 93455",
    "addr:housenumber":"3030",
    "addr:postcode":"93455",
    "addr:street":"Skyway Dr",
    "iso:country":"US",
    "sg:address":"3030 Skyway Dr",
    "sg:city":"Santa Maria",
    "sg:classifiers":[
        {
            "category":"Home & Garden",
            "subcategory":"Furniture",
            "type":"Retail Goods"
        }
    ],
    "sg:phone":"+1 805 925 4400",
    "sg:postcode":"93455",
    "sg:province":"CA",
    "sg:tags":[
        "top",
        "counter"
    ],
    "wof:name":"Primo Custom Counter Tops",
    "wof:placetype":"venue"
},
  "geometry": {"coordinates":[-120.45235099999999,34.905524],"type":"Point"}
}