{
  "type": "Feature",
  "properties": {
    "iso:country":"US",
    "sg:address":"14320 Ocean Gate Ave",
    "sg:city":"Hawthorne",
    "sg:classifiers":[
        {
            "category":"Shopping",
            "subcategory":"Clothing, Apparel, & Fashions",
            "type":"Retail Goods"
        }
    ],
    "sg:phone":"+1 310 644 7282",
    "sg:postcode":"90250",
    "sg:province":"CA",
    "sg:tags":[
        "accessory",
        "clothing",
        "women's"
    ],
    "wof:name":"Pretty Woman",
    "wof:placetype":"venue"
},
  "geometry": {"coordinates":[-118.366997,33.901501],"type":"Point"}
}