{
  "type": "Feature",
  "properties": {
    "iso:country":"US",
    "sg:address":"13553 Roscoe Blvd",
    "sg:city":"Panorama City",
    "sg:classifiers":[
        {
            "category":"Personal",
            "subcategory":"Beauty Salon",
            "type":"Services"
        }
    ],
    "sg:phone":"+1 818 997 9595",
    "sg:postcode":"91402",
    "sg:province":"CA",
    "sg:tags":[
        "hair"
    ],
    "wof:name":"Chol Beauty Salon",
    "wof:placetype":"venue"
},
  "geometry": {"coordinates":[-118.42800099999999,34.2215],"type":"Point"}
}