{
  "type": "Feature",
  "properties": {
    "iso:country":"US",
    "sg:address":"7911 Winnetka Ave",
    "sg:city":"Winnetka",
    "sg:classifiers":[
        {
            "category":"Social Services",
            "subcategory":"Child Care",
            "type":"Services"
        },
        {
            "category":"Education",
            "subcategory":"Preschool",
            "type":"Public Place"
        },
        {
            "category":"Education",
            "subcategory":"School",
            "type":"Public Place"
        }
    ],
    "sg:phone":"+1 818 882 3242",
    "sg:postcode":"91306",
    "sg:province":"CA",
    "sg:tags":[
        "kindergarten",
        "k-",
        "high",
        "middle",
        "nursery",
        "private",
        "interest",
        "elementary",
        "religious",
        "day"
    ],
    "sg:website":"www.wvca.org",
    "wof:name":"West Valley Christian Academy",
    "wof:placetype":"venue"
},
  "geometry": {"coordinates":[-118.570999,34.214199],"type":"Point"}
}