{
  "type": "Feature",
  "properties": {
    "addr:full":"915 Yosemite Ave Modesto CA 95354",
    "addr:housenumber":"915",
    "addr:postcode":"ca 95354",
    "addr:street":"Yosemite Ave",
    "iso:country":"US",
    "sg:address":"915 Yosemite Ave",
    "sg:city":"Modesto",
    "sg:classifiers":[
        {
            "category":"Restaurant",
            "type":"Food & Drink"
        }
    ],
    "sg:phone":"+1 209 523 3627",
    "sg:postcode":"95354",
    "sg:province":"CA",
    "sg:tags":[
        "barbeque"
    ],
    "wof:name":"King's BBQ Grill",
    "wof:placetype":"venue"
},
  "geometry": {"coordinates":[-121.00830000000001,37.624257],"type":"Point"}
}