{
  "type": "Feature",
  "properties": {
    "addr:full":"156 N Clark Dr Beverly Hills CA 90211",
    "addr:housenumber":"156",
    "addr:postcode":"90211",
    "addr:street":"N Clark Dr",
    "iso:country":"US",
    "sg:address":"156 N Clark Dr",
    "sg:city":"Beverly Hills",
    "sg:classifiers":[
        {
            "category":"Retail",
            "subcategory":"Auto Repair",
            "type":"Services"
        }
    ],
    "sg:phone":"+1 310 360 9455",
    "sg:postcode":"90211",
    "sg:province":"CA",
    "sg:tags":[
        "automobile",
        "co",
        "drive",
        "transporter"
    ],
    "wof:name":"Metro City Towing",
    "wof:placetype":"venue"
},
  "geometry": {"coordinates":[-118.38462,34.068579],"type":"Point"}
}