{
  "type": "Feature",
  "properties": {
    "addr:full":"1242 Park St Alameda CA 94501",
    "addr:housenumber":"1242",
    "addr:postcode":"94501",
    "addr:street":"Park St",
    "iso:country":"US",
    "sg:address":"1242 Park St",
    "sg:city":"Alameda",
    "sg:classifiers":[
        {
            "category":"Health Services",
            "subcategory":"Clinic",
            "type":"Services"
        }
    ],
    "sg:phone":"+1 510 521 3500",
    "sg:postcode":"94501",
    "sg:province":"CA",
    "sg:tags":[
        "counseling",
        "mental"
    ],
    "wof:name":"Donelan Joan A PHD California Counseling Associats",
    "wof:placetype":"venue"
},
  "geometry": {"coordinates":[-122.24400300000001,37.7621],"type":"Point"}
}