{
  "type": "Feature",
  "properties": {
    "addr:full":"895 Napa Ave Ste B5 Morro Bay CA 93442",
    "addr:housenumber":"895",
    "addr:postcode":"93442",
    "addr:street":"Napa Ave Ste B5",
    "iso:country":"US",
    "sg:address":"895 Napa Ave Ste B5",
    "sg:city":"Morro Bay",
    "sg:classifiers":[
        {
            "category":"Personal",
            "subcategory":"Beauty Salon",
            "type":"Services"
        }
    ],
    "sg:phone":"+1 805 771 9900",
    "sg:postcode":"93442",
    "sg:province":"CA",
    "sg:tags":[
        "hair"
    ],
    "sg:website":"kramsaydesigns.webs.com",
    "wof:name":"Equanimity Eco Salon . Studio",
    "wof:placetype":"venue"
},
  "geometry": {"coordinates":[-120.84802999999999,35.366589],"type":"Point"}
}