{
  "type": "Feature",
  "properties": {
    "addr:full":"324 State St Santa Barbara CA 93101",
    "addr:housenumber":"324",
    "addr:postcode":"93101",
    "addr:street":"State St",
    "iso:country":"US",
    "sg:address":"324 State St",
    "sg:city":"Santa Barbara",
    "sg:classifiers":[
        {
            "category":"Recreation",
            "type":"Entertainment"
        }
    ],
    "sg:phone":"+1 805 965 7175",
    "sg:postcode":"93101",
    "sg:province":"CA",
    "sg:tags":[
        "instruction",
        "yoga"
    ],
    "wof:name":"Ashtanga Yoga Shala",
    "wof:placetype":"venue"
},
  "geometry": {"coordinates":[-119.694103,34.415844],"type":"Point"}
}