{
  "type": "Feature",
  "properties": {
    "iso:country":"US",
    "sg:address":"1068 Ranchero Way",
    "sg:city":"San Jose",
    "sg:classifiers":[
        {
            "category":"Building & Trades",
            "subcategory":"Construction",
            "type":"Services"
        }
    ],
    "sg:phone":"+1 408 234 3729",
    "sg:postcode":"95117",
    "sg:province":"CA",
    "sg:tags":[
        "handyman"
    ],
    "wof:name":"P C Works",
    "wof:placetype":"venue"
},
  "geometry": {"coordinates":[-121.973494,37.304534],"type":"Point"}
}