{
  "type": "Feature",
  "properties": {
    "iso:country":"US",
    "sg:address":"1300 University Dr",
    "sg:city":"Menlo Park",
    "sg:classifiers":[
        {
            "category":"Health Services",
            "subcategory":"Health Practitioner",
            "type":"Services"
        }
    ],
    "sg:phone":"+1 650 473 6858",
    "sg:postcode":"94025",
    "sg:province":"CA",
    "sg:tags":[
        "psychologist"
    ],
    "wof:name":"Judith Wilson PHD",
    "wof:placetype":"venue"
},
  "geometry": {"coordinates":[-122.190611,37.452246],"type":"Point"}
}