{
  "type": "Feature",
  "properties": {
    "addr:full":"1860 Quail Meadows Cir Vacaville CA 95687",
    "addr:housenumber":"1860",
    "addr:postcode":"95687",
    "addr:street":"Quail Meadows Cir",
    "iso:country":"US",
    "sg:address":"1860 Quail Meadows Cir",
    "sg:city":"Vacaville",
    "sg:classifiers":[
        {
            "category":"Professional",
            "subcategory":"Computer Services",
            "type":"Services"
        }
    ],
    "sg:phone":"+1 707 447 5000",
    "sg:postcode":"95687",
    "sg:province":"CA",
    "sg:tags":[
        "internet"
    ],
    "wof:name":"P Trader Network",
    "wof:placetype":"venue"
},
  "geometry": {"coordinates":[-121.972775,38.334306],"type":"Point"}
}