{
  "type": "Feature",
  "properties": {
    "addr:full":"323 Coburn St Quincy CA 95971",
    "addr:housenumber":"323",
    "addr:postcode":"95971",
    "addr:street":"Coburn St",
    "iso:country":"US",
    "sg:address":"323 Coburn St",
    "sg:city":"Quincy",
    "sg:classifiers":[
        {
            "category":"Building & Trades",
            "subcategory":"Construction",
            "type":"Services"
        }
    ],
    "sg:phone":"+1 530 283 4444",
    "sg:postcode":"95971",
    "sg:province":"CA",
    "sg:tags":[
        "contractor"
    ],
    "wof:name":"Murray Co",
    "wof:placetype":"venue"
},
  "geometry": {"coordinates":[-120.946952,39.931729],"type":"Point"}
}