{
  "type": "Feature",
  "properties": {
    "iso:country":"US",
    "sg:address":"1134 Pine St",
    "sg:city":"Redding",
    "sg:classifiers":[
        {
            "category":"Restaurant",
            "type":"Food & Drink"
        }
    ],
    "sg:phone":"+1 530 243 2014",
    "sg:postcode":"96001",
    "sg:province":"CA",
    "wof:name":"Subway Sandwiches & Salads",
    "wof:placetype":"venue"
},
  "geometry": {"coordinates":[-122.391314,40.588929],"type":"Point"}
}