{
  "type": "Feature",
  "properties": {
    "iso:country":"US",
    "sg:address":"3899 W Davis Ave",
    "sg:city":"Riverdale",
    "sg:classifiers":[
        {
            "category":"Farming",
            "subcategory":"Livestock Farm",
            "type":"Manufacturing & Wholesale Goods"
        },
        {
            "category":"Farming",
            "subcategory":"Farm & Veterinary Services",
            "type":"Manufacturing & Wholesale Goods"
        }
    ],
    "sg:phone":"+1 559 867 3545",
    "sg:postcode":"93656",
    "sg:province":"CA",
    "sg:tags":[
        "breeder"
    ],
    "wof:name":"Genes Golden Inc",
    "wof:placetype":"venue"
},
  "geometry": {"coordinates":[-119.855136,36.474427],"type":"Point"}
}