{
  "type": "Feature",
  "properties": {
    "iso:country":"US",
    "sg:address":"165 22nd St",
    "sg:city":"Richmond",
    "sg:classifiers":[
        {
            "category":"Organizations",
            "subcategory":"Non-profit Organization",
            "type":"Services"
        }
    ],
    "sg:phone":"+1 510 233 2141",
    "sg:postcode":"94801",
    "sg:province":"CA",
    "sg:tags":[
        "religious"
    ],
    "sg:website":"www.gripcommunity.org",
    "wof:name":"Greater Richmond Interfaith Program",
    "wof:placetype":"venue"
},
  "geometry": {"coordinates":[-122.348884,37.933423],"type":"Point"}
}