{
  "type": "Feature",
  "properties": {
    "iso:country":"US",
    "sg:address":"9551 Domer Rd",
    "sg:city":"Santee",
    "sg:classifiers":[
        {
            "category":"Home & Garden",
            "subcategory":"Household Appliances",
            "type":"Retail Goods"
        }
    ],
    "sg:phone":"+1 619 280 0044",
    "sg:postcode":"92071",
    "sg:province":"CA",
    "sg:tags":[
        "appliances-small"
    ],
    "wof:name":"Abz Appliance Svc",
    "wof:placetype":"venue"
},
  "geometry": {"coordinates":[-116.997326,32.851006],"type":"Point"}
}