{
  "type": "Feature",
  "properties": {
    "addr:full":"2100 Del Paso Boulevard Sacramento CA 95815",
    "addr:housenumber":"2100",
    "addr:postcode":"95815",
    "addr:street":"Del Paso Boulevard",
    "iso:country":"US",
    "sg:address":"2100 Del Paso Boulevard",
    "sg:city":"Sacramento",
    "sg:classifiers":[
        {
            "category":"Shopping",
            "subcategory":"Florist",
            "type":"Retail Goods"
        }
    ],
    "sg:phone":"+1 916 925 8588",
    "sg:postcode":"95815",
    "sg:province":"CA",
    "wof:name":"Gene's Flowers",
    "wof:placetype":"venue"
},
  "geometry": {"coordinates":[-121.451803,38.609458],"type":"Point"}
}