{
  "type": "Feature",
  "properties": {
    "addr:full":"2050 Pioneer Court Suite 200 San Mateo CA 94403",
    "addr:housenumber":"2050",
    "addr:postcode":"94403",
    "addr:street":"Pioneer Court Suite 200",
    "iso:country":"US",
    "sg:address":"2050 Pioneer Court Suite 200",
    "sg:city":"San Mateo",
    "sg:classifiers":[
        {
            "category":"Banks & Credit Unions",
            "subcategory":"Financial Services",
            "type":"Services"
        }
    ],
    "sg:phone":"+1 650 520 0915",
    "sg:postcode":"94403",
    "sg:province":"CA",
    "sg:tags":[
        "broker",
        "mortgage"
    ],
    "sg:website":"sanmateomortgageblog.com",
    "wof:name":"Chris Williamson - Mortgage California",
    "wof:placetype":"venue"
},
  "geometry": {"coordinates":[-122.31208100000001,37.546239],"type":"Point"}
}