{
  "type": "Feature",
  "properties": {
    "iso:country":"US",
    "sg:address":"2 Clark Dr",
    "sg:city":"San Mateo",
    "sg:classifiers":[
        {
            "category":"Real Estate",
            "subcategory":"Real Estate Operator",
            "type":"Services"
        }
    ],
    "sg:phone":"+1 650 342 5434",
    "sg:postcode":"94401",
    "sg:province":"CA",
    "sg:tags":[
        "apartment"
    ],
    "wof:name":"Two Clark Drive Apartments",
    "wof:placetype":"venue"
},
  "geometry": {"coordinates":[-122.34102799999999,37.570665],"type":"Point"}
}