{
  "type": "Feature",
  "properties": {
    "addr:full":"4891 Convoy St San Diego CA 92111",
    "addr:housenumber":"4891",
    "addr:postcode":"92111",
    "addr:street":"Convoy St",
    "iso:country":"US",
    "sg:address":"4891 Convoy St",
    "sg:city":"San Diego",
    "sg:classifiers":[
        {
            "category":"Shopping",
            "subcategory":"Bicycles & Sporting Goods",
            "type":"Retail Goods"
        }
    ],
    "sg:phone":"+1 858 571 2020",
    "sg:postcode":"92111",
    "sg:province":"CA",
    "sg:tags":[
        "antique",
        "gun",
        "gunsmith"
    ],
    "sg:website":"www.socalgun.com",
    "wof:name":"Southern California Gun",
    "wof:placetype":"venue"
},
  "geometry": {"coordinates":[-117.153204,32.82931],"type":"Point"}
}