{
  "type": "Feature",
  "properties": {
    "iso:country":"US",
    "sg:address":"10748 Carmenita Rd",
    "sg:city":"Whittier",
    "sg:classifiers":[
        {
            "category":"Health Services",
            "subcategory":"Nursing And Care Facility",
            "type":"Services"
        }
    ],
    "sg:phone":"+1 562 944 5575",
    "sg:postcode":"90605",
    "sg:province":"CA",
    "sg:tags":[
        "home",
        "convalescent"
    ],
    "wof:name":"Mercedes Diaz Homes Facilities",
    "wof:placetype":"venue"
},
  "geometry": {"coordinates":[-118.046414,33.935645],"type":"Point"}
}