{
  "type": "Feature",
  "properties": {
    "addr:full":"1188 Sunny Ct San Jose CA 95116",
    "addr:housenumber":"1188",
    "addr:postcode":"95116",
    "addr:street":"Sunny Ct",
    "iso:country":"US",
    "sg:address":"1188 Sunny Ct",
    "sg:city":"San Jose",
    "sg:classifiers":[
        {
            "category":"Professional",
            "type":"Services"
        }
    ],
    "sg:phone":"+1 408 288 8119",
    "sg:postcode":"95116",
    "sg:province":"CA",
    "wof:name":"Nguyen Sewing",
    "wof:placetype":"venue"
},
  "geometry": {"coordinates":[-121.859572,37.341274],"type":"Point"}
}