{
  "type": "Feature",
  "properties": {
    "iso:country":"US",
    "sg:address":"9387 Ruffin Ct",
    "sg:city":"San Diego",
    "sg:classifiers":[
        {
            "category":"Professional",
            "subcategory":"Accounting & Tax Preparation",
            "type":"Services"
        }
    ],
    "sg:phone":"+1 858 576 9331",
    "sg:postcode":"92123",
    "sg:province":"CA",
    "sg:tags":[
        "accountant"
    ],
    "wof:name":"Rose P Regas CPA",
    "wof:placetype":"venue"
},
  "geometry": {"coordinates":[-117.12381000000001,32.828643],"type":"Point"}
}