{
  "type": "Feature",
  "properties": {
    "addr:full":"12883 6th Ave Hanford CA 93230",
    "addr:housenumber":"12883",
    "addr:postcode":"ca 93230",
    "addr:street":"6Th Ave",
    "iso:country":"US",
    "sg:address":"12883 6th Ave",
    "sg:city":"Hanford",
    "sg:classifiers":[
        {
            "category":"Building & Trades",
            "subcategory":"Electrical",
            "type":"Services"
        }
    ],
    "sg:phone":"+1 559 582 8693",
    "sg:postcode":"93230",
    "sg:province":"CA",
    "sg:tags":[
        "electrical",
        "contractor"
    ],
    "wof:name":"Stan Vierra Electric",
    "wof:placetype":"venue"
},
  "geometry": {"coordinates":[-119.565051,36.285794],"type":"Point"}
}