{
  "type": "Feature",
  "properties": {
    "addr:full":"2118 Bullrush Ln Cardiff By The Sea CA 92007",
    "addr:housenumber":"2118",
    "addr:postcode":"92007",
    "addr:street":"Bullrush Ln",
    "iso:country":"US",
    "sg:address":"2118 Bullrush Ln",
    "sg:city":"Cardiff By The Sea",
    "sg:classifiers":[
        {
            "category":"Professional",
            "subcategory":"Management & Consulting",
            "type":"Services"
        }
    ],
    "sg:phone":"+1 760 944 9513",
    "sg:postcode":"92007",
    "sg:province":"CA",
    "sg:tags":[
        "public",
        "relations"
    ],
    "wof:name":"Home Sales Office",
    "wof:placetype":"venue"
},
  "geometry": {"coordinates":[-117.270788,33.018677],"type":"Point"}
}