{
  "type": "Feature",
  "properties": {
    "addr:full":"6218 Bakman Ave North Hollywood CA 91606",
    "addr:housenumber":"6218",
    "addr:postcode":"91606",
    "addr:street":"Bakman Ave",
    "iso:country":"US",
    "sg:address":"6218 Bakman Ave",
    "sg:city":"North Hollywood",
    "sg:classifiers":[
        {
            "category":"Insurance",
            "subcategory":"Insurance Agent",
            "type":"Services"
        }
    ],
    "sg:phone":"+1 818 508 5453",
    "sg:postcode":"91606",
    "sg:province":"CA",
    "wof:name":"Vernon J Bridges",
    "wof:placetype":"venue"
},
  "geometry": {"coordinates":[-118.377877,34.184533],"type":"Point"}
}