{
  "type": "Feature",
  "properties": {
    "addr:full":"11050 Woodley Ave Granada Hills CA 91344",
    "addr:housenumber":"11050",
    "addr:postcode":"91344",
    "addr:street":"Woodley Ave",
    "iso:country":"US",
    "sg:address":"11050 Woodley Ave",
    "sg:city":"Granada Hills",
    "sg:classifiers":[
        {
            "category":"Retail",
            "subcategory":"Auto Repair",
            "type":"Services"
        }
    ],
    "sg:phone":"+1 818 368 0244",
    "sg:postcode":"91344",
    "sg:province":"CA",
    "sg:tags":[
        "repairing",
        "automobile"
    ],
    "wof:name":"J P Automotive",
    "wof:placetype":"venue"
},
  "geometry": {"coordinates":[-118.48465299999999,34.270912],"type":"Point"}
}