{
  "type": "Feature",
  "properties": {
    "iso:country":"US",
    "sg:address":"2155 N Winery Ave",
    "sg:city":"Fresno",
    "sg:classifiers":[
        {
            "category":"Real Estate",
            "subcategory":"Real Estate Operator",
            "type":"Services"
        }
    ],
    "sg:phone":"+1 559 255 8386",
    "sg:postcode":"93703",
    "sg:province":"CA",
    "sg:tags":[
        "apartment"
    ],
    "wof:name":"Sunset Gardens Apartments",
    "wof:placetype":"venue"
},
  "geometry": {"coordinates":[-119.731831,36.768569],"type":"Point"}
}