{
  "type": "Feature",
  "properties": {
    "addr:full":"943 Market St San Francisco CA 94103",
    "addr:housenumber":"943",
    "addr:postcode":"94103",
    "addr:street":"Market St",
    "iso:country":"US",
    "sg:address":"943 Market St",
    "sg:city":"San Francisco",
    "sg:classifiers":[
        {
            "category":"Shopping",
            "subcategory":"Computers & Home Electronics",
            "type":"Retail Goods"
        }
    ],
    "sg:phone":"+1 415 541 9055",
    "sg:postcode":"94103",
    "sg:province":"CA",
    "sg:tags":[
        "equipment",
        "electronic",
        "supply"
    ],
    "wof:name":"Next Generation Electronics",
    "wof:placetype":"venue"
},
  "geometry": {"coordinates":[-122.40801399999999,37.783911],"type":"Point"}
}