{
  "type": "Feature",
  "properties": {
    "iso:country":"US",
    "sg:address":"9674 Telstar Ave Ste J",
    "sg:city":"El Monte",
    "sg:classifiers":[
        {
            "category":"Shopping",
            "subcategory":"Mobile Phones",
            "type":"Retail Goods"
        }
    ],
    "sg:phone":"+1 626 350 9819",
    "sg:postcode":"91731",
    "sg:province":"CA",
    "wof:name":"Day Deal Inc",
    "wof:placetype":"venue"
},
  "geometry": {"coordinates":[-118.058998,34.069901],"type":"Point"}
}