{
  "type": "Feature",
  "properties": {
    "iso:country":"US",
    "sg:address":"520 Palisades Dr",
    "sg:city":"Pacific Plsds",
    "sg:classifiers":[
        {
            "category":"Personal",
            "subcategory":"Beauty Salon",
            "type":"Services"
        }
    ],
    "sg:phone":"+1 310 230 0056",
    "sg:postcode":"90272",
    "sg:province":"CA",
    "sg:tags":[
        "manicuring"
    ],
    "wof:name":"Lovely Nail Boutique",
    "wof:placetype":"venue"
},
  "geometry": {"coordinates":[-118.552832,34.051909],"type":"Point"}
}