{
  "type": "Feature",
  "properties": {
    "addr:full":"1970 Placentia Ave Costa Mesa CA 92627",
    "addr:postcode":"1970;92627",
    "addr:street":"Placentia Ave",
    "iso:country":"US",
    "sg:address":"1970 Placentia Ave",
    "sg:city":"Costa Mesa",
    "sg:classifiers":[
        {
            "category":"Professional",
            "subcategory":"Art Services",
            "type":"Services"
        }
    ],
    "sg:phone":"+1 949 574 8558",
    "sg:postcode":"92627",
    "sg:province":"CA",
    "sg:tags":[
        "graphic",
        "designer"
    ],
    "sg:website":"www.khourygraphics.com",
    "wof:name":"Khoury Graphics Group",
    "wof:placetype":"venue"
},
  "geometry": {"coordinates":[-117.931967,33.64619],"type":"Point"}
}