{
  "type": "Feature",
  "properties": {
    "addr:full":"660 S Main St Willits CA 95490",
    "addr:housenumber":"660",
    "addr:postcode":"95490",
    "addr:street":"S Main St",
    "iso:country":"US",
    "sg:address":"660 S Main St",
    "sg:city":"Willits",
    "sg:classifiers":[
        {
            "category":"Social Services",
            "type":"Services"
        }
    ],
    "sg:phone":"+1 707 459 0370",
    "sg:postcode":"95490",
    "sg:province":"CA",
    "sg:tags":[
        "counselor",
        "marriage",
        "family"
    ],
    "wof:name":"Bruce Crawford",
    "wof:placetype":"venue"
},
  "geometry": {"coordinates":[-123.35242599999999,39.405292],"type":"Point"}
}