{
  "type": "Feature",
  "properties": {
    "iso:country":"US",
    "sg:address":"16010 Tyrol Dr",
    "sg:city":"Fontana",
    "sg:classifiers":[
        {
            "category":"Building & Trades",
            "subcategory":"Construction",
            "type":"Services"
        }
    ],
    "sg:phone":"+1 909 355 5193",
    "sg:postcode":"92337",
    "sg:province":"CA",
    "sg:tags":[
        "roofing",
        "contractor"
    ],
    "wof:name":"Green Diamond Roofing Co",
    "wof:placetype":"venue"
},
  "geometry": {"coordinates":[-117.45575100000001,34.058393],"type":"Point"}
}