{
  "type": "Feature",
  "properties": {
    "iso:country":"US",
    "sg:address":"1380 Oakville Rd",
    "sg:city":"Oakville",
    "sg:classifiers":[
        {
            "category":"Farming",
            "subcategory":"Vineyard",
            "type":"Manufacturing & Wholesale Goods"
        }
    ],
    "sg:phone":"+1 707 944 0126",
    "sg:postcode":"94558",
    "sg:province":"CA",
    "wof:name":"Oakville Experimental Vineyard",
    "wof:placetype":"venue"
},
  "geometry": {"coordinates":[-122.407055,38.429409],"type":"Point"}
}