{
  "type": "Feature",
  "properties": {
    "iso:country":"US",
    "sg:address":"213 E Laurel St",
    "sg:city":"Fort Bragg",
    "sg:classifiers":[
        {
            "category":"Recreation",
            "type":"Entertainment"
        }
    ],
    "sg:phone":"+1 707 964 9446",
    "sg:postcode":"95437",
    "sg:province":"CA",
    "sg:tags":[
        "center"
    ],
    "sg:website":"www.mcrpd.us",
    "wof:name":"Fort Bragg Recreation Ctr",
    "wof:placetype":"venue"
},
  "geometry": {"coordinates":[-123.804424,39.445567],"type":"Point"}
}