{
  "type": "Feature",
  "properties": {
    "iso:country":"US",
    "sg:address":"2720 Maple Ave",
    "sg:city":"Los Angeles",
    "sg:classifiers":[
        {
            "category":"Autos & Motor Vehicles",
            "subcategory":"Auto Supplies",
            "type":"Retail Goods"
        }
    ],
    "sg:phone":"+1 213 746 6251",
    "sg:postcode":"90011",
    "sg:province":"CA",
    "sg:tags":[
        "automobile",
        "parts"
    ],
    "wof:name":"Main Auto Electric Parts",
    "wof:placetype":"venue"
},
  "geometry": {"coordinates":[-118.266302,34.021944],"type":"Point"}
}