{
  "type": "Feature",
  "properties": {
    "addr:full":"3420 E Vernon Avenue Los Angeles CA 90058",
    "addr:housenumber":"3420",
    "addr:postcode":"90058",
    "addr:street":"E Vernon Avenue",
    "iso:country":"US",
    "sg:address":"3420 E Vernon Avenue",
    "sg:city":"Los Angeles",
    "sg:classifiers":[
        {
            "category":"Food & Beverages",
            "subcategory":"Groceries & Convenience Stores",
            "type":"Retail Goods"
        }
    ],
    "sg:phone":"+1 323 973 4000",
    "sg:postcode":"90058",
    "sg:province":"CA",
    "wof:name":"West Trading Golden",
    "wof:placetype":"venue"
},
  "geometry": {"coordinates":[-118.21041099999999,34.005546],"type":"Point"}
}