{
  "type": "Feature",
  "properties": {
    "iso:country":"US",
    "sg:address":"555 Knowles Dr",
    "sg:city":"Los Gatos",
    "sg:classifiers":[
        {
            "category":"Health Services",
            "subcategory":"Doctor",
            "type":"Services"
        }
    ],
    "sg:phone":"+1 408 378 7240",
    "sg:postcode":"95032",
    "sg:province":"CA",
    "sg:tags":[
        "physician",
        "surgeon"
    ],
    "sg:website":"www.spinal-surgeons.com",
    "wof:name":"Thomas A Kula Inc",
    "wof:placetype":"venue"
},
  "geometry": {"coordinates":[-121.96385100000001,37.261666],"type":"Point"}
}