{
  "type": "Feature",
  "properties": {
    "addr:full":"3945 Branson Dr San Mateo CA 94403",
    "addr:housenumber":"3945",
    "addr:postcode":"94403",
    "addr:street":"Branson Dr",
    "iso:country":"US",
    "sg:address":"3945 Branson Dr",
    "sg:city":"San Mateo",
    "sg:classifiers":[
        {
            "category":"Building & Trades",
            "subcategory":"Landscaping Services",
            "type":"Services"
        }
    ],
    "sg:phone":"+1 650 572 8222",
    "sg:postcode":"94403",
    "sg:province":"CA",
    "sg:tags":[
        "landscape",
        "contractor"
    ],
    "wof:name":"Superior Landscaping Service",
    "wof:placetype":"venue"
},
  "geometry": {"coordinates":[-122.28316599999999,37.538438],"type":"Point"}
}