{
  "type": "Feature",
  "properties": {
    "iso:country":"US",
    "sg:address":"3945 Branson Dr",
    "sg:city":"San Mateo",
    "sg:classifiers":[
        {
            "category":"Building & Trades",
            "subcategory":"Landscaping Services",
            "type":"Services"
        }
    ],
    "sg:phone":"+1 650 572 8222",
    "sg:postcode":"94403",
    "sg:province":"CA",
    "sg:tags":[
        "landscape",
        "contractor"
    ],
    "wof:name":"Superior Landscaping Service",
    "wof:placetype":"venue"
},
  "geometry": {"coordinates":[-122.283166,37.538438],"type":"Point"}
}