{
  "type": "Feature",
  "properties": {
    "iso:country":"US",
    "sg:address":"45800 Challenger Way # 72",
    "sg:city":"Lancaster",
    "sg:classifiers":[
        {
            "category":"Shopping",
            "subcategory":"Pets & Pet Supplies",
            "type":"Retail Goods"
        }
    ],
    "sg:phone":"+1 661 944 1954",
    "sg:postcode":"93535",
    "sg:province":"CA",
    "sg:tags":[
        "furnishing",
        "dog",
        "store",
        "cat"
    ],
    "wof:name":"Flying South Inc",
    "wof:placetype":"venue"
},
  "geometry": {"coordinates":[-118.112405,34.715736],"type":"Point"}
}