{
  "type": "Feature",
  "properties": {
    "addr:full":"2750 Marsh St Los Angeles CA 90039",
    "addr:housenumber":"2750",
    "addr:postcode":"90039",
    "addr:street":"Marsh St",
    "iso:country":"US",
    "sg:address":"2750 Marsh St",
    "sg:city":"Los Angeles",
    "sg:classifiers":[
        {
            "category":"Organizations",
            "subcategory":"Religious Organization",
            "type":"Services"
        }
    ],
    "sg:phone":"+1 818 663 1924",
    "sg:postcode":"90039",
    "sg:province":"CA",
    "sg:tags":[
        "church"
    ],
    "wof:name":"L A Second Chinese Church",
    "wof:placetype":"venue"
},
  "geometry": {"coordinates":[-118.248786,34.103882],"type":"Point"}
}