{
  "type": "Feature",
  "properties": {
    "iso:country":"US",
    "sg:address":"15324 S Broadway St",
    "sg:city":"Gardena",
    "sg:classifiers":[
        {
            "category":"Wholesale",
            "subcategory":"Chemicals & Plastics",
            "type":"Manufacturing & Wholesale Goods"
        }
    ],
    "sg:phone":"+1 310 327 9805",
    "sg:postcode":"90248",
    "sg:province":"CA",
    "wof:name":"California Research",
    "wof:placetype":"venue"
},
  "geometry": {"coordinates":[-118.278568,33.892165],"type":"Point"}
}