{
  "type": "Feature",
  "properties": {
    "addr:full":"2664 Mercantile Dr Ste A Rancho Cordova CA 95742",
    "addr:housenumber":"2664",
    "addr:postcode":"95742",
    "addr:street":"Mercantile Dr Ste A",
    "iso:country":"US",
    "sg:address":"2664 Mercantile Dr Ste A",
    "sg:city":"Rancho Cordova",
    "sg:classifiers":[
        {
            "category":"Building & Trades",
            "subcategory":"Construction",
            "type":"Services"
        }
    ],
    "sg:phone":"+1 916 635 0331",
    "sg:postcode":"95742",
    "sg:province":"CA",
    "sg:tags":[
        "contractor"
    ],
    "wof:name":"Hartin & Hume Inc",
    "wof:placetype":"venue"
},
  "geometry": {"coordinates":[-121.260002,38.6077],"type":"Point"}
}