{
  "type": "Feature",
  "properties": {
    "addr:full":"7099 Baker Ln Sebastopol CA 95472",
    "addr:housenumber":"7099",
    "addr:postcode":"95472",
    "addr:street":"Baker Ln",
    "iso:country":"US",
    "sg:address":"7099 Baker Ln",
    "sg:city":"Sebastopol",
    "sg:classifiers":[
        {
            "category":"Building & Trades",
            "subcategory":"Landscaping Services",
            "type":"Services"
        }
    ],
    "sg:phone":"+1 707 823 8881",
    "sg:postcode":"95472",
    "sg:province":"CA",
    "sg:tags":[
        "landscape",
        "contractor"
    ],
    "wof:name":"Ogasawara Landscaping",
    "wof:placetype":"venue"
},
  "geometry": {"coordinates":[-122.813002,38.372014],"type":"Point"}
}