{
  "type": "Feature",
  "properties": {
    "addr:full":"1004 Industrial Way Lodi CA 95240",
    "addr:housenumber":"1004",
    "addr:postcode":"95240",
    "addr:street":"Industrial Way",
    "iso:country":"US",
    "sg:address":"1004 Industrial Way",
    "sg:city":"Lodi",
    "sg:classifiers":[
        {
            "category":"Building & Trades",
            "subcategory":"Construction",
            "type":"Services"
        }
    ],
    "sg:phone":"+1 209 366 2486",
    "sg:postcode":"95240",
    "sg:province":"CA",
    "sg:tags":[
        "contractor"
    ],
    "wof:name":"O & A Construction",
    "wof:placetype":"venue"
},
  "geometry": {"coordinates":[-121.254451,38.12541],"type":"Point"}
}