{
  "type": "Feature",
  "properties": {
    "addr:full":"678 Hamann Dr San Jose CA 95117",
    "addr:housenumber":"678",
    "addr:postcode":"95117",
    "addr:street":"Hamann Dr",
    "iso:country":"US",
    "sg:address":"678 Hamann Dr",
    "sg:city":"San Jose",
    "sg:classifiers":[
        {
            "category":"Education",
            "subcategory":"Special Training",
            "type":"Public Place"
        }
    ],
    "sg:phone":"+1 408 249 3623",
    "sg:postcode":"95117",
    "sg:province":"CA",
    "sg:tags":[
        "etiquette",
        "school"
    ],
    "wof:name":"Gal Plays Music",
    "wof:placetype":"venue"
},
  "geometry": {"coordinates":[-121.964922,37.315582],"type":"Point"}
}