{
  "type": "Feature",
  "properties": {
    "iso:country":"US",
    "sg:address":"1277 Cypress Avenue",
    "sg:city":"Los Angeles",
    "sg:classifiers":[
        {
            "category":"Shopping",
            "subcategory":"Beauty & Cosmetics",
            "type":"Retail Goods"
        }
    ],
    "sg:phone":"+1 323 227 9234",
    "sg:postcode":"90065",
    "sg:province":"CA",
    "sg:tags":[
        "supply"
    ],
    "wof:name":"Nore's Beauty Salon",
    "wof:placetype":"venue"
},
  "geometry": {"coordinates":[-118.229584,34.096211],"type":"Point"}
}