{
  "type": "Feature",
  "properties": {
    "iso:country":"US",
    "sg:address":"1810 Gateway Drive",
    "sg:city":"Foster City",
    "sg:classifiers":[
        {
            "category":"Health Services",
            "subcategory":"Health Practitioner",
            "type":"Services"
        }
    ],
    "sg:phone":"+1 650 345 2739",
    "sg:postcode":"94404",
    "sg:province":"CA",
    "sg:tags":[
        "therapy",
        "physical"
    ],
    "wof:name":"Matoso Dave Pt",
    "wof:placetype":"venue"
},
  "geometry": {"coordinates":[-122.281295,37.555815],"type":"Point"}
}