{
  "type": "Feature",
  "properties": {
    "addr:full":"20210 Haynes St Winnetka CA 91306",
    "addr:housenumber":"20210",
    "addr:postcode":"91306",
    "addr:street":"Haynes St",
    "iso:country":"US",
    "sg:address":"20210 Haynes St",
    "sg:city":"Winnetka",
    "sg:classifiers":[
        {
            "category":"Professional",
            "type":"Services"
        }
    ],
    "sg:phone":"+1 818 347 1614",
    "sg:postcode":"91306",
    "sg:province":"CA",
    "wof:name":"Hru Co",
    "wof:placetype":"venue"
},
  "geometry": {"coordinates":[-118.573762,34.190985],"type":"Point"}
}