{
  "type": "Feature",
  "properties": {
    "addr:full":"5000 N. Parkway Calabasas Suite 114 Calabasas CA 91302",
    "addr:housenumber":"5000;suite 114",
    "addr:postcode":"91302",
    "addr:street":"N. Parkway",
    "iso:country":"US",
    "sg:address":"5000 N. Parkway Calabasas Suite 114",
    "sg:city":"Calabasas",
    "sg:classifiers":[
        {
            "category":"Banks & Credit Unions",
            "subcategory":"Investment Brokerage",
            "type":"Services"
        }
    ],
    "sg:phone":"+1 877 705 0202",
    "sg:postcode":"91302",
    "sg:province":"CA",
    "sg:tags":[
        "investing"
    ],
    "sg:website":"www.getmypaymentslower.com",
    "wof:name":"Get Payments Lower",
    "wof:placetype":"venue"
},
  "geometry": {"coordinates":[-118.65273999999999,34.155501],"type":"Point"}
}