{
  "type": "Feature",
  "properties": {
    "addr:full":"2424 Riviera Dr Chula Vista CA 91915",
    "addr:housenumber":"2424",
    "addr:postcode":"91915",
    "addr:street":"Riviera Dr",
    "iso:country":"US",
    "sg:address":"2424 Riviera Dr",
    "sg:city":"Chula Vista",
    "sg:classifiers":[
        {
            "category":"Wholesale",
            "subcategory":"Machinery & Supplies",
            "type":"Manufacturing & Wholesale Goods"
        }
    ],
    "sg:phone":"+1 619 482 1905",
    "sg:postcode":"91915",
    "sg:province":"CA",
    "sg:tags":[
        "salon",
        "beauty"
    ],
    "wof:name":"Premiere Nail Care Supply",
    "wof:placetype":"venue"
},
  "geometry": {"coordinates":[-116.954132,32.634551],"type":"Point"}
}