{
  "type": "Feature",
  "properties": {
    "addr:full":"1640 E 1st St Santa Ana CA 92701",
    "addr:housenumber":"1640",
    "addr:postcode":"92701",
    "addr:street":"E 1St St",
    "iso:country":"US",
    "sg:address":"1640 E 1st St",
    "sg:city":"Santa Ana",
    "sg:classifiers":[
        {
            "category":"Personal",
            "subcategory":"Beauty Salon",
            "type":"Services"
        }
    ],
    "sg:phone":"+1 714 973 8922",
    "sg:postcode":"92701",
    "sg:province":"CA",
    "sg:tags":[
        "manicuring"
    ],
    "wof:name":"Super Nails",
    "wof:placetype":"venue"
},
  "geometry": {"coordinates":[-117.84665800000001,33.745386],"type":"Point"}
}