{
  "type": "Feature",
  "properties": {
    "iso:country":"US",
    "sg:address":"24074 N Ray Rd",
    "sg:city":"Lodi",
    "sg:phone":"+1 209 368 3105",
    "sg:postcode":"95242",
    "sg:province":"CA",
    "sg:tags":[
        "farm",
        "field",
        "crop"
    ],
    "wof:name":"Ron Zapara",
    "wof:placetype":"venue"
},
  "geometry": {"coordinates":[-121.372696,38.207876],"type":"Point"}
}