{
  "type": "Feature",
  "properties": {
    "addr:full":"363 Ave Arboles San Jose CA 95123",
    "addr:housenumber":"363",
    "addr:postcode":"95123",
    "addr:street":"Ave Arboles",
    "iso:country":"US",
    "sg:address":"363 Ave Arboles",
    "sg:city":"San Jose",
    "sg:phone":"+1 408 629 0313",
    "sg:postcode":"95123",
    "sg:province":"CA",
    "sg:tags":[
        "scale"
    ],
    "wof:name":"Scale Service Co",
    "wof:placetype":"venue"
},
  "geometry": {"coordinates":[-121.83167899999999,37.256382],"type":"Point"}
}