{
  "type": "Feature",
  "properties": {
    "iso:country":"US",
    "sg:address":"4831 John Muir Rd",
    "sg:city":"Martinez",
    "sg:classifiers":[
        {
            "category":"Professional",
            "subcategory":"Business Services",
            "type":"Services"
        }
    ],
    "sg:phone":"+1 925 228 1212",
    "sg:postcode":"94553",
    "sg:province":"CA",
    "sg:tags":[
        "consultant",
        "coach"
    ],
    "wof:name":"New Hope Credit Consulting",
    "wof:placetype":"venue"
},
  "geometry": {"coordinates":[-122.11416699999999,37.987611],"type":"Point"}
}