{
  "type": "Feature",
  "properties": {
    "iso:country":"US",
    "sg:address":"5323 Babcock Ave",
    "sg:city":"Valley Village",
    "sg:classifiers":[
        {
            "category":"Wholesale",
            "subcategory":"Non-durable Goods",
            "type":"Manufacturing & Wholesale Goods"
        }
    ],
    "sg:phone":"+1 818 762 7680",
    "sg:postcode":"91607",
    "sg:province":"CA",
    "sg:tags":[
        "advertising",
        "specialty"
    ],
    "wof:name":"Action Ad Specialties Inc",
    "wof:placetype":"venue"
},
  "geometry": {"coordinates":[-118.40646,34.166187],"type":"Point"}
}