{
  "type": "Feature",
  "properties": {
    "addr:full":"4720 Cloyne St Oxnard CA 93033",
    "addr:postcode":"4720;93033",
    "addr:street":"Cloyne St",
    "iso:country":"US",
    "sg:address":"4720 Cloyne St",
    "sg:city":"Oxnard",
    "sg:classifiers":[
        {
            "category":"Real Estate",
            "subcategory":"Real Estate Operator",
            "type":"Services"
        }
    ],
    "sg:phone":"+1 805 488 1116",
    "sg:postcode":"93033",
    "sg:province":"CA",
    "sg:tags":[
        "apartment"
    ],
    "wof:name":"Pleasant Valley Apartments",
    "wof:placetype":"venue"
},
  "geometry": {"coordinates":[-119.173035,34.157711],"type":"Point"}
}