{
  "type": "Feature",
  "properties": {
    "addr:full":"939 Oakland Rd San Jose CA 95112",
    "addr:housenumber":"939",
    "addr:postcode":"95112",
    "addr:street":"Oakland Rd",
    "iso:country":"US",
    "sg:address":"939 Oakland Rd",
    "sg:city":"San Jose",
    "sg:classifiers":[
        {
            "category":"Bars & Pubs",
            "type":"Food & Drink"
        }
    ],
    "sg:phone":"+1 408 292 3372",
    "sg:postcode":"95112",
    "sg:province":"CA",
    "sg:tags":[
        "nightlife"
    ],
    "wof:name":"Mexicali Club",
    "wof:placetype":"venue"
},
  "geometry": {"coordinates":[-121.89099899999999,37.3605],"type":"Point"}
}