{
  "type": "Feature",
  "properties": {
    "iso:country":"US",
    "sg:address":"1465 Eureka Rd Ste 100",
    "sg:city":"Roseville",
    "sg:classifiers":[
        {
            "category":"Professional",
            "type":"Services"
        },
        {
            "category":"Restaurant",
            "type":"Food & Drink"
        }
    ],
    "sg:phone":"+1 916 788 1122",
    "sg:postcode":"95661",
    "sg:province":"CA",
    "sg:tags":[
        "grill",
        "bar",
        "caterer"
    ],
    "wof:name":"Utopia Grill",
    "wof:placetype":"venue"
},
  "geometry": {"coordinates":[-121.252601,38.753717],"type":"Point"}
}