{
  "type": "Feature",
  "properties": {
    "addr:full":"23635 el Toro Rd El Toro CA 92630",
    "addr:housenumber":"23635",
    "addr:postcode":"92630",
    "addr:street":"El Toro Rd",
    "iso:country":"US",
    "sg:address":"23635 el Toro Rd",
    "sg:city":"El Toro",
    "sg:classifiers":[
        {
            "category":"Restaurant",
            "type":"Food & Drink"
        }
    ],
    "sg:phone":"+1 949 770 1136",
    "sg:postcode":"92630",
    "sg:province":"CA",
    "wof:name":"Mariscos Rio Balsas",
    "wof:placetype":"venue"
},
  "geometry": {"coordinates":[-117.702455,33.619044],"type":"Point"}
}