{
  "type": "Feature",
  "properties": {
    "iso:country":"US",
    "sg:address":"Grand Ave 1800DataCenter.com",
    "sg:city":"Sanda Ana",
    "sg:classifiers":[
        {
            "category":"Professional",
            "subcategory":"Computer Services",
            "type":"Services"
        }
    ],
    "sg:phone":"+1 949 209 9785",
    "sg:province":"CA",
    "sg:tags":[
        "cloud-computing-data-center-call-center-web-hosting-virtualization-colocation-managed-hosting-irvine-orangecounty-california-949-714-sas-pci-compliant"
    ],
    "sg:website":"http://1800DataCenter.com",
    "wof:name":"1800DataCenter.com",
    "wof:placetype":"venue"
},
  "geometry": {"coordinates":[-117.86660000000001,33.749739],"type":"Point"}
}