{
  "type": "Feature",
  "properties": {
    "addr:full":"220 Cannery St San Pedro CA 90731",
    "addr:housenumber":"220",
    "addr:postcode":"90731",
    "addr:street":"Cannery St",
    "iso:country":"US",
    "sg:address":"220 Cannery St",
    "sg:city":"San Pedro",
    "sg:classifiers":[
        {
            "category":"Wholesale",
            "subcategory":"Chemicals & Plastics",
            "type":"Manufacturing & Wholesale Goods"
        }
    ],
    "sg:phone":"+1 310 519 0343",
    "sg:postcode":"90731",
    "sg:province":"CA",
    "wof:name":"Nalfleet Inc",
    "wof:placetype":"venue"
},
  "geometry": {"coordinates":[-118.26778400000001,33.739431],"type":"Point"}
}