{
  "type": "Feature",
  "properties": {
    "addr:full":"10476 W Linne Rd Tracy CA 95377",
    "addr:housenumber":"10476",
    "addr:postcode":"95377",
    "addr:street":"W Linne Rd",
    "iso:country":"US",
    "sg:address":"10476 W Linne Rd",
    "sg:city":"Tracy",
    "sg:classifiers":[
        {
            "category":"Food & Beverages",
            "subcategory":"Groceries & Convenience Stores",
            "type":"Retail Goods"
        }
    ],
    "sg:phone":"+1 209 835 3684",
    "sg:postcode":"95377",
    "sg:province":"CA",
    "sg:tags":[
        "grocer"
    ],
    "wof:name":"Country Market",
    "wof:placetype":"venue"
},
  "geometry": {"coordinates":[-121.425352,37.696023],"type":"Point"}
}