{
  "type": "Feature",
  "properties": {
    "addr:full":"127 W Valley Blvd Rialto CA 92376",
    "addr:housenumber":"127",
    "addr:postcode":"92376",
    "addr:street":"W Valley Blvd",
    "iso:country":"US",
    "sg:address":"127 W Valley Blvd",
    "sg:city":"Rialto",
    "sg:classifiers":[
        {
            "category":"Restaurant",
            "type":"Food & Drink"
        }
    ],
    "sg:menulink":"http://www.allmenus.com/ca/san-bernardino/104551-hometown-buffet/menu/",
    "sg:phone":"+1 909 421 9688",
    "sg:postcode":"92376",
    "sg:province":"CA",
    "sg:tags":[
        "new",
        "american"
    ],
    "wof:name":"Hometown Buffet",
    "wof:placetype":"venue"
},
  "geometry": {"coordinates":[-117.371309,34.069895],"type":"Point"}
}