{
  "type": "Feature",
  "properties": {
    "iso:country":"US",
    "sg:address":"5959 Topanga Canyon Blvd",
    "sg:city":"Woodland Hills",
    "sg:classifiers":[
        {
            "category":"Building & Trades",
            "subcategory":"Construction",
            "type":"Services"
        }
    ],
    "sg:phone":"+1 818 704 7294",
    "sg:postcode":"91367",
    "sg:province":"CA",
    "sg:tags":[
        "general",
        "contractor"
    ],
    "wof:name":"Perry Stone Construction",
    "wof:placetype":"venue"
},
  "geometry": {"coordinates":[-118.6049,34.177219],"type":"Point"}
}