{
  "type": "Feature",
  "properties": {
    "addr:full":"437 Rogers Ave Watsonville CA 95076",
    "addr:housenumber":"437",
    "addr:postcode":"95076",
    "addr:street":"Rogers Ave",
    "iso:country":"US",
    "sg:address":"437 Rogers Ave",
    "sg:city":"Watsonville",
    "sg:classifiers":[
        {
            "category":"Organizations",
            "subcategory":"Religious Organization",
            "type":"Services"
        }
    ],
    "sg:phone":"+1 831 724 5338",
    "sg:postcode":"95076",
    "sg:province":"CA",
    "sg:tags":[
        "place",
        "worship",
        "church"
    ],
    "wof:name":"All Saints Episcopal Church",
    "wof:placetype":"venue"
},
  "geometry": {"coordinates":[-121.756372,36.92702],"type":"Point"}
}