{
  "type": "Feature",
  "properties": {
    "addr:full":"126 Wood Rd Camarillo CA 93010",
    "addr:housenumber":"126",
    "addr:postcode":"93010",
    "addr:street":"Wood Rd",
    "iso:country":"US",
    "sg:address":"126 Wood Rd",
    "sg:city":"Camarillo",
    "sg:classifiers":[
        {
            "category":"Manufacturing",
            "subcategory":"Tools & Machinery",
            "type":"Manufacturing & Wholesale Goods"
        }
    ],
    "sg:phone":"+1 805 987 5995",
    "sg:postcode":"93010",
    "sg:province":"CA",
    "sg:tags":[
        "machine",
        "shop"
    ],
    "wof:name":"C & S Precision Machining",
    "wof:placetype":"venue"
},
  "geometry": {"coordinates":[-119.095967,34.218806],"type":"Point"}
}