{
  "type": "Feature",
  "properties": {
    "iso:country":"US",
    "sg:address":"6040 Sonoma Hwy",
    "sg:city":"Santa Rosa",
    "sg:classifiers":[
        {
            "category":"Building & Trades",
            "subcategory":"Cleaning & Sanitation",
            "type":"Services"
        }
    ],
    "sg:phone":"+1 707 539 3696",
    "sg:postcode":"95409",
    "sg:province":"CA",
    "sg:tags":[
        "window"
    ],
    "wof:name":"C J's Window Washing Svc",
    "wof:placetype":"venue"
},
  "geometry": {"coordinates":[-122.622792,38.45346],"type":"Point"}
}