{
  "type": "Feature",
  "properties": {
    "addr:full":"13530 Fellows Ave Sylmar CA 91342",
    "addr:housenumber":"13530",
    "addr:postcode":"91342",
    "addr:street":"Fellows Ave",
    "iso:country":"US",
    "sg:address":"13530 Fellows Ave",
    "sg:city":"Sylmar",
    "sg:classifiers":[
        {
            "category":"Building & Trades",
            "subcategory":"Electrical",
            "type":"Services"
        }
    ],
    "sg:phone":"+1 818 362 2754",
    "sg:postcode":"91342",
    "sg:province":"CA",
    "sg:tags":[
        "electric",
        "contractor"
    ],
    "wof:name":"AMR Electric",
    "wof:placetype":"venue"
},
  "geometry": {"coordinates":[-118.459886,34.317931],"type":"Point"}
}