{
  "type": "Feature",
  "properties": {
    "addr:full":"22304 Main St Hayward CA 94541",
    "addr:housenumber":"22304",
    "addr:postcode":"94541",
    "addr:street":"Main St",
    "iso:country":"US",
    "sg:address":"22304 Main St",
    "sg:city":"Hayward",
    "sg:classifiers":[
        {
            "category":"Health Services",
            "subcategory":"Doctor",
            "type":"Services"
        }
    ],
    "sg:phone":"+1 510 886 5400",
    "sg:postcode":"94541",
    "sg:province":"CA",
    "sg:tags":[
        "surgeon",
        "oral",
        "dentist"
    ],
    "wof:name":"Hemanes Glenn J DDS",
    "wof:placetype":"venue"
},
  "geometry": {"coordinates":[-122.084999,37.6754],"type":"Point"}
}