{
  "type": "Feature",
  "properties": {
    "iso:country":"US",
    "sg:address":"7210 Vineyard Dr",
    "sg:city":"Paso Robles",
    "sg:classifiers":[
        {
            "category":"Building & Trades",
            "subcategory":"Construction",
            "type":"Services"
        }
    ],
    "sg:phone":"+1 805 238 2500",
    "sg:postcode":"93446",
    "sg:province":"CA",
    "sg:tags":[
        "excavation",
        "paving",
        "contractor"
    ],
    "wof:name":"Roadrunner Construction",
    "wof:placetype":"venue"
},
  "geometry": {"coordinates":[-120.820986,35.590019],"type":"Point"}
}