{
  "type": "Feature",
  "properties": {
    "iso:country":"US",
    "sg:address":"703 Market St",
    "sg:city":"San Francisco",
    "sg:classifiers":[
        {
            "category":"Real Estate",
            "subcategory":"Real Estate Agent",
            "type":"Services"
        }
    ],
    "sg:phone":"+1 415 433 5111",
    "sg:postcode":"94103",
    "sg:province":"CA",
    "wof:name":"Bohan Co",
    "wof:placetype":"venue"
},
  "geometry": {"coordinates":[-122.404513,37.78667],"type":"Point"}
}