{
  "type": "Feature",
  "properties": {
    "addr:full":"10701 Wilshire Blvd Apt 1905 Los Angeles CA 90024",
    "addr:housenumber":"10701",
    "addr:postcode":"90024",
    "addr:street":"Wilshire Blvd Apt 1905",
    "iso:country":"US",
    "sg:address":"10701 Wilshire Blvd Apt 1905",
    "sg:city":"Los Angeles",
    "sg:classifiers":[
        {
            "category":"Health Services",
            "subcategory":"Doctor",
            "type":"Services"
        }
    ],
    "sg:phone":"+1 310 441 5588",
    "sg:postcode":"90024",
    "sg:province":"CA",
    "wof:name":"Pourzand Parisa MD",
    "wof:placetype":"venue"
},
  "geometry": {"coordinates":[-118.435765,34.097401],"type":"Point"}
}