{
  "type": "Feature",
  "properties": {
    "iso:country":"US",
    "sg:address":"120 N Akers St",
    "sg:city":"Visalia",
    "sg:classifiers":[
        {
            "category":"Retail",
            "subcategory":"Veterinary Services",
            "type":"Services"
        }
    ],
    "sg:phone":"+1 559 732 8651",
    "sg:postcode":"93291",
    "sg:province":"CA",
    "sg:tags":[
        "medicine",
        "surgery"
    ],
    "wof:name":"Diamond Veterinary Med Hosp",
    "wof:placetype":"venue"
},
  "geometry": {"coordinates":[-119.349601,36.328156],"type":"Point"}
}