{
  "type": "Feature",
  "properties": {
    "addr:full":"18148 Sherman Way Reseda CA 91335",
    "addr:housenumber":"18148",
    "addr:postcode":"91335",
    "addr:street":"Sherman Way",
    "iso:country":"US",
    "sg:address":"18148 Sherman Way",
    "sg:city":"Reseda",
    "sg:classifiers":[
        {
            "category":"Professional",
            "subcategory":"Art Services",
            "type":"Services"
        }
    ],
    "sg:phone":"+1 818 343 9170",
    "sg:postcode":"91335",
    "sg:province":"CA",
    "sg:tags":[
        "photographer"
    ],
    "sg:website":"www.siskinphoto.com",
    "wof:name":"Siskin Photography",
    "wof:placetype":"venue"
},
  "geometry": {"coordinates":[-118.53080799999999,34.200932],"type":"Point"}
}