{
  "type": "Feature",
  "properties": {
    "iso:country":"US",
    "sg:address":"730 Quebec Way",
    "sg:city":"Rio Linda",
    "sg:classifiers":[
        {
            "category":"Professional",
            "subcategory":"Business Services",
            "type":"Services"
        }
    ],
    "sg:phone":"+1 916 991 6726",
    "sg:postcode":"95673",
    "sg:province":"CA",
    "sg:tags":[
        "drafting"
    ],
    "wof:name":"MAS & Assoc",
    "wof:placetype":"venue"
},
  "geometry": {"coordinates":[-121.449009,38.696775],"type":"Point"}
}