{
  "type": "Feature",
  "properties": {
    "addr:full":"2701 W Alameda Ave Burbank CA 91505",
    "addr:housenumber":"2701",
    "addr:postcode":"91505",
    "addr:street":"W Alameda Ave",
    "iso:country":"US",
    "sg:address":"2701 W Alameda Ave",
    "sg:city":"Burbank",
    "sg:classifiers":[
        {
            "category":"Health Services",
            "subcategory":"Doctor",
            "type":"Services"
        }
    ],
    "sg:phone":"+1 818 848 6550",
    "sg:postcode":"91505",
    "sg:province":"CA",
    "sg:tags":[
        "physician",
        "surgeon"
    ],
    "wof:name":"Laser Bare",
    "wof:placetype":"venue"
},
  "geometry": {"coordinates":[-118.331034,34.157236],"type":"Point"}
}