{
  "type": "Feature",
  "properties": {
    "addr:full":"848 Battery St San Francisco CA 94111",
    "addr:housenumber":"848",
    "addr:postcode":"94111",
    "addr:street":"Battery St",
    "iso:country":"US",
    "sg:address":"848 Battery St",
    "sg:city":"San Francisco",
    "sg:classifiers":[
        {
            "category":"Communications",
            "subcategory":"Television Station",
            "type":"Services"
        }
    ],
    "sg:phone":"+1 408 286 1111",
    "sg:postcode":"94111",
    "sg:province":"CA",
    "sg:tags":[
        "broadcasting",
        "co"
    ],
    "wof:name":"NBC Kntv",
    "wof:placetype":"venue"
},
  "geometry": {"coordinates":[-122.401242,37.799063],"type":"Point"}
}