{
  "type": "Feature",
  "properties": {
    "iso:country":"US",
    "sg:address":"1003 W Beverly Blvd",
    "sg:city":"Montebello",
    "sg:classifiers":[
        {
            "category":"Health Services",
            "subcategory":"Medical Lab",
            "type":"Services"
        }
    ],
    "sg:phone":"+1 323 722 2123",
    "sg:postcode":"90640",
    "sg:province":"CA",
    "sg:tags":[
        "laboratory"
    ],
    "wof:name":"Montebello Dental Ceramics",
    "wof:placetype":"venue"
},
  "geometry": {"coordinates":[-118.109755,34.017846],"type":"Point"}
}