{
  "type": "Feature",
  "properties": {
    "addr:full":"7607 Carson Blvd Long Beach CA 90808",
    "addr:housenumber":"7607",
    "addr:postcode":"90808",
    "addr:street":"Carson Blvd",
    "iso:country":"US",
    "sg:address":"7607 Carson Blvd",
    "sg:city":"Long Beach",
    "sg:classifiers":[
        {
            "category":"Home & Garden",
            "subcategory":"Carpets & Floor Coverings",
            "type":"Retail Goods"
        }
    ],
    "sg:phone":"+1 562 429 5644",
    "sg:postcode":"90808",
    "sg:province":"CA",
    "sg:tags":[
        "mattress"
    ],
    "wof:name":"Mattress Gallery No 82",
    "wof:placetype":"venue"
},
  "geometry": {"coordinates":[-118.084,33.8255],"type":"Point"}
}