{
  "type": "Feature",
  "properties": {
    "iso:country":"US",
    "sg:address":"5227 Lakewood Blvd",
    "sg:city":"Lakewood",
    "sg:classifiers":[
        {
            "category":"Shopping",
            "subcategory":"Department Store",
            "type":"Retail Goods"
        }
    ],
    "sg:phone":"+1 562 529 7947",
    "sg:postcode":"90712",
    "sg:province":"CA",
    "sg:tags":[
        "shop"
    ],
    "sg:website":"www.biglots.com",
    "wof:name":"Big Lots",
    "wof:placetype":"venue"
},
  "geometry": {"coordinates":[-118.14299800000001,33.852901],"type":"Point"}
}