{
  "type": "Feature",
  "properties": {
    "iso:country":"US",
    "sg:address":"259 N Almont Dr",
    "sg:city":"Beverly Hills",
    "sg:classifiers":[
        {
            "category":"Building & Trades",
            "subcategory":"Construction",
            "type":"Services"
        }
    ],
    "sg:phone":"+1 323 405 7498",
    "sg:postcode":"90211",
    "sg:province":"CA",
    "sg:tags":[
        "contractor"
    ],
    "sg:website":"retrofitterLA.com",
    "wof:name":"Doheny Construction",
    "wof:placetype":"venue"
},
  "geometry": {"coordinates":[-118.38771699999999,34.070669],"type":"Point"}
}