{
  "type": "Feature",
  "properties": {
    "iso:country":"US",
    "sg:address":"1005 S Fairfax Ave",
    "sg:city":"Los Angeles",
    "sg:classifiers":[
        {
            "category":"Restaurant",
            "type":"Food & Drink"
        }
    ],
    "sg:menulink":"http://www.allmenus.com/ca/los-angeles/170858-carls-jr/menu/",
    "sg:phone":"+1 323 935 4122",
    "sg:postcode":"90019",
    "sg:province":"CA",
    "sg:tags":[
        "burger",
        "american"
    ],
    "wof:name":"Carl's Jr.",
    "wof:placetype":"venue"
},
  "geometry": {"coordinates":[-118.363906,34.058006],"type":"Point"}
}