{
  "type": "Feature",
  "properties": {
    "iso:country":"US",
    "sg:address":"1900 Saipan Ave",
    "sg:city":"Firebaugh",
    "sg:classifiers":[
        {
            "category":"Place Of Worship",
            "type":"Public Place"
        }
    ],
    "sg:phone":"+1 559 659 2943",
    "sg:postcode":"93622",
    "sg:province":"CA",
    "sg:tags":[
        "church"
    ],
    "wof:name":"St. Josephs Church",
    "wof:placetype":"venue"
},
  "geometry": {"coordinates":[-120.444542,36.852821],"type":"Point"}
}