{
  "type": "Feature",
  "properties": {
    "addr:full":"881 S 4th St Grover Beach CA 93433",
    "addr:housenumber":"881",
    "addr:postcode":"93433",
    "addr:street":"S 4Th St",
    "iso:country":"US",
    "sg:address":"881 S 4th St",
    "sg:city":"Grover Beach",
    "sg:classifiers":[
        {
            "category":"Retail",
            "subcategory":"Auto Repair",
            "type":"Services"
        }
    ],
    "sg:phone":"+1 805 474 0431",
    "sg:postcode":"93433",
    "sg:province":"CA",
    "sg:tags":[
        "repairing",
        "automobile"
    ],
    "wof:name":"M & S Automotive Specialists",
    "wof:placetype":"venue"
},
  "geometry": {"coordinates":[-120.625061,35.113348],"type":"Point"}
}