{
  "type": "Feature",
  "properties": {
    "iso:country":"US",
    "sg:address":"408 S Beach Blvd Ste 213",
    "sg:city":"Anaheim",
    "sg:classifiers":[
        {
            "category":"Health Services",
            "subcategory":"Doctor",
            "type":"Services"
        }
    ],
    "sg:phone":"+1 714 821 8479",
    "sg:postcode":"92804",
    "sg:province":"CA",
    "wof:name":"Samuel B Yoo MD",
    "wof:placetype":"venue"
},
  "geometry": {"coordinates":[-117.993073,33.827467],"type":"Point"}
}