{
  "type": "Feature",
  "properties": {
    "iso:country":"US",
    "sg:address":"22505 Mission Blvd",
    "sg:city":"Hayward",
    "sg:classifiers":[
        {
            "category":"Shopping",
            "type":"Retail Goods"
        }
    ],
    "sg:phone":"+1 510 538 5500",
    "sg:postcode":"94541",
    "sg:province":"CA",
    "sg:tags":[
        "telephone",
        "cellular"
    ],
    "wof:name":"Cellular Warehouse",
    "wof:placetype":"venue"
},
  "geometry": {"coordinates":[-122.08504499999999,37.673173],"type":"Point"}
}