{
  "type": "Feature",
  "properties": {
    "iso:country":"US",
    "sg:address":"1352 Oregon St",
    "sg:city":"Redding",
    "sg:classifiers":[
        {
            "category":"Social Services",
            "type":"Services"
        }
    ],
    "sg:phone":"+1 530 244 2808",
    "sg:postcode":"96001",
    "sg:province":"CA",
    "sg:tags":[
        "counselor",
        "marriage",
        "family"
    ],
    "wof:name":"Center For Integrative Psycho",
    "wof:placetype":"venue"
},
  "geometry": {"coordinates":[-122.395092,40.584955],"type":"Point"}
}