{
  "type": "Feature",
  "properties": {
    "iso:country":"US",
    "sg:address":"478 8th St",
    "sg:city":"Oakland",
    "sg:classifiers":[
        {
            "category":"Parking",
            "type":"Transportation"
        }
    ],
    "sg:phone":"+1 510 763 1175",
    "sg:postcode":"94607",
    "sg:province":"CA",
    "sg:tags":[
        "attendant"
    ],
    "wof:name":"Central Parking System",
    "wof:placetype":"venue"
},
  "geometry": {"coordinates":[-122.27496,37.800724],"type":"Point"}
}