{
  "type": "Feature",
  "properties": {
    "iso:country":"US",
    "sg:address":"821 N Humboldt St",
    "sg:city":"San Mateo",
    "sg:classifiers":[
        {
            "category":"Professional",
            "subcategory":"Computer Services",
            "type":"Services"
        }
    ],
    "sg:phone":"+1 650 579 0203",
    "sg:postcode":"94401",
    "sg:province":"CA",
    "sg:tags":[
        "programing",
        "custom"
    ],
    "wof:name":"Jim Salois Corp",
    "wof:placetype":"venue"
},
  "geometry": {"coordinates":[-122.329725,37.581668],"type":"Point"}
}