{
  "type": "Feature",
  "properties": {
    "iso:country":"US",
    "sg:address":"916 N Mountain Ave",
    "sg:city":"Upland",
    "sg:classifiers":[
        {
            "category":"Personal",
            "subcategory":"Beauty Salon",
            "type":"Services"
        }
    ],
    "sg:phone":"+1 909 931 0201",
    "sg:postcode":"91786",
    "sg:province":"CA",
    "wof:name":"Strandz Salon",
    "wof:placetype":"venue"
},
  "geometry": {"coordinates":[-117.670141,34.105871],"type":"Point"}
}