{
  "type": "Feature",
  "properties": {
    "iso:country":"US",
    "sg:address":"11232 Calabash Ave",
    "sg:city":"Fontana",
    "sg:classifiers":[
        {
            "category":"Manufacturing",
            "subcategory":"Wood Products",
            "type":"Manufacturing & Wholesale Goods"
        }
    ],
    "sg:phone":"+1 909 823 9207",
    "sg:postcode":"92337",
    "sg:province":"CA",
    "sg:tags":[
        "pallet",
        "skid"
    ],
    "wof:name":"Express Pallets",
    "wof:placetype":"venue"
},
  "geometry": {"coordinates":[-117.50209,34.048131],"type":"Point"}
}