{
  "type": "Feature",
  "properties": {
    "iso:country":"US",
    "sg:address":"2831 Countryside Dr",
    "sg:city":"Turlock",
    "sg:classifiers":[
        {
            "category":"Coffee & Tea",
            "type":"Food & Drink"
        },
        {
            "category":"Shopping",
            "subcategory":"Music",
            "type":"Retail Goods"
        },
        {
            "category":"Shopping",
            "subcategory":"Books",
            "type":"Retail Goods"
        }
    ],
    "sg:phone":"+1 209 632 5000",
    "sg:postcode":"95380",
    "sg:province":"CA",
    "sg:tags":[
        "bookstore",
        "dvd's"
    ],
    "sg:website":"www.borders.com",
    "wof:name":"Borders",
    "wof:placetype":"venue"
},
  "geometry": {"coordinates":[-120.88244899999999,37.518691],"type":"Point"}
}