{
  "type": "Feature",
  "properties": {
    "addr:full":"550 D St Chula Vista CA 91910",
    "addr:housenumber":"550",
    "addr:postcode":"91910",
    "addr:street":"D St",
    "iso:country":"US",
    "sg:address":"550 D St",
    "sg:city":"Chula Vista",
    "sg:classifiers":[
        {
            "category":"Building & Trades",
            "subcategory":"Construction",
            "type":"Services"
        }
    ],
    "sg:phone":"+1 619 498 0914",
    "sg:postcode":"91910",
    "sg:province":"CA",
    "sg:tags":[
        "contractor"
    ],
    "wof:name":"Jesse Ruble Roofing",
    "wof:placetype":"venue"
},
  "geometry": {"coordinates":[-117.092502,32.645386],"type":"Point"}
}