{
  "type": "Feature",
  "properties": {
    "iso:country":"US",
    "sg:address":"13395 Estelle St",
    "sg:city":"Corona",
    "sg:classifiers":[
        {
            "category":"Professional",
            "type":"Services"
        }
    ],
    "sg:phone":"+1 951 735 8101",
    "sg:postcode":"92879",
    "sg:province":"CA",
    "wof:name":"Gregor Co Inc",
    "wof:placetype":"venue"
},
  "geometry": {"coordinates":[-117.51507100000001,33.88292],"type":"Point"}
}