{
  "type": "Feature",
  "properties": {
    "addr:full":"7300 S Main Street Los Angeles CA 90003",
    "addr:housenumber":"7300",
    "addr:postcode":"90003",
    "addr:street":"S Main Street",
    "iso:country":"US",
    "sg:address":"7300 S Main Street",
    "sg:city":"Los Angeles",
    "sg:classifiers":[
        {
            "category":"Government",
            "subcategory":"Office",
            "type":"Public Place"
        }
    ],
    "sg:phone":"+1 323 751 8630",
    "sg:postcode":"90003",
    "sg:province":"CA",
    "sg:tags":[
        "smog",
        "check"
    ],
    "wof:name":"Main Smog Test Center",
    "wof:placetype":"venue"
},
  "geometry": {"coordinates":[-118.27405400000001,33.973608],"type":"Point"}
}