{
  "type": "Feature",
  "properties": {
    "addr:full":"10861 Beach Blvd Stanton CA 90680",
    "addr:housenumber":"10861",
    "addr:postcode":"ca 90680",
    "addr:street":"Beach Blvd",
    "iso:country":"US",
    "sg:address":"10861 Beach Blvd",
    "sg:city":"Stanton",
    "sg:classifiers":[
        {
            "category":"Travel",
            "subcategory":"Travel Agent",
            "type":"Entertainment"
        }
    ],
    "sg:phone":"+1 714 527 2666",
    "sg:postcode":"90680",
    "sg:province":"CA",
    "sg:tags":[
        "agency"
    ],
    "wof:name":"Aero Paris Travel",
    "wof:placetype":"venue"
},
  "geometry": {"coordinates":[-117.99303,33.80383],"type":"Point"}
}