{
  "type": "Feature",
  "properties": {
    "iso:country":"US",
    "sg:address":"1226 de la Torre St",
    "sg:city":"Salinas",
    "sg:classifiers":[
        {
            "category":"Travel",
            "subcategory":"Hotels & Motels",
            "type":"Entertainment"
        }
    ],
    "sg:phone":"+1 831 759 9900",
    "sg:postcode":"93905",
    "sg:province":"CA",
    "sg:website":"http://www.daysinn.com",
    "wof:name":"Days Inn",
    "wof:placetype":"venue"
},
  "geometry": {"coordinates":[-121.622145,36.660359],"type":"Point"}
}