{
  "type": "Feature",
  "properties": {
    "addr:full":"1101 S Prairie Ave Inglewood CA 90301",
    "addr:housenumber":"1101",
    "addr:postcode":"90301",
    "addr:street":"S Prairie Ave",
    "iso:country":"US",
    "sg:address":"1101 S Prairie Ave",
    "sg:city":"Inglewood",
    "sg:phone":"+1 310 672 1137",
    "sg:postcode":"90301",
    "sg:province":"CA",
    "wof:name":"Chu's Garden",
    "wof:placetype":"venue"
},
  "geometry": {"coordinates":[-118.343971,33.964556],"type":"Point"}
}