{
  "type": "Feature",
  "properties": {
    "iso:country":"US",
    "sg:address":"1375 E Main St",
    "sg:city":"El Cajon",
    "sg:classifiers":[
        {
            "category":"Autos & Motor Vehicles",
            "subcategory":"Automobile Sales",
            "type":"Retail Goods"
        }
    ],
    "sg:phone":"+1 619 442 6135",
    "sg:postcode":"92021",
    "sg:province":"CA",
    "sg:tags":[
        "car",
        "dealer"
    ],
    "wof:name":"East County Auto Ctr",
    "wof:placetype":"venue"
},
  "geometry": {"coordinates":[-116.932666,32.797956],"type":"Point"}
}