{
  "type": "Feature",
  "properties": {
    "addr:full":"12740 Vigilante Rd Lakeside CA 92040",
    "addr:housenumber":"12740",
    "addr:postcode":"92040",
    "addr:street":"Vigilante Rd",
    "iso:country":"US",
    "sg:address":"12740 Vigilante Rd",
    "sg:city":"Lakeside",
    "sg:classifiers":[
        {
            "category":"Building & Trades",
            "subcategory":"Construction",
            "type":"Services"
        }
    ],
    "sg:phone":"+1 619 443 7867",
    "sg:postcode":"92040",
    "sg:province":"CA",
    "sg:tags":[
        "pumping",
        "contractor"
    ],
    "wof:name":"Atlas Pumping Svc",
    "wof:placetype":"venue"
},
  "geometry": {"coordinates":[-116.935301,32.904148],"type":"Point"}
}