{
  "type": "Feature",
  "properties": {
    "iso:country":"US",
    "sg:address":"600 N Mountain Ave",
    "sg:city":"Upland",
    "sg:classifiers":[
        {
            "category":"Health Services",
            "subcategory":"Doctor",
            "type":"Services"
        }
    ],
    "sg:phone":"+1 909 931 7947",
    "sg:postcode":"91786",
    "sg:province":"CA",
    "sg:tags":[
        "physician",
        "surgeon"
    ],
    "wof:name":"Sumil K Saini MD",
    "wof:placetype":"venue"
},
  "geometry": {"coordinates":[-117.67011,34.103004],"type":"Point"}
}