{
  "type": "Feature",
  "properties": {
    "addr:full":"8218 Sorensen Ave Santa Fe Springs CA 90670",
    "addr:housenumber":"8218",
    "addr:postcode":"90670",
    "addr:street":"Sorensen Ave",
    "iso:country":"US",
    "sg:address":"8218 Sorensen Ave",
    "sg:city":"Santa Fe Springs",
    "sg:phone":"+1 562 693 1001",
    "sg:postcode":"90670",
    "sg:province":"CA",
    "sg:tags":[
        "equipment",
        "commercial"
    ],
    "wof:name":"Choice Concepts",
    "wof:placetype":"venue"
},
  "geometry": {"coordinates":[-118.060012,33.968647],"type":"Point"}
}