{
  "type": "Feature",
  "properties": {
    "iso:country":"US",
    "sg:address":"216 N Golden State Blvd",
    "sg:city":"Turlock",
    "sg:classifiers":[
        {
            "category":"Autos & Motor Vehicles",
            "subcategory":"Fuel & Gas Station",
            "type":"Retail Goods"
        }
    ],
    "sg:phone":"+1 209 632 7433",
    "sg:postcode":"95380",
    "sg:province":"CA",
    "sg:tags":[
        "oil"
    ],
    "wof:name":"Beacon Oil Co",
    "wof:placetype":"venue"
},
  "geometry": {"coordinates":[-120.84751300000001,37.496226],"type":"Point"}
}