{
  "type": "Feature",
  "properties": {
    "iso:country":"US",
    "sg:address":"2226 6th St",
    "sg:city":"Berkeley",
    "sg:classifiers":[
        {
            "category":"Professional",
            "subcategory":"Management & Consulting",
            "type":"Services"
        }
    ],
    "sg:phone":"+1 707 328 1887",
    "sg:postcode":"94710",
    "sg:province":"CA",
    "sg:tags":[
        "counselor",
        "public",
        "relations"
    ],
    "sg:website":"www.crmsonoma.com",
    "wof:name":"Communication Resource Mgmt",
    "wof:placetype":"venue"
},
  "geometry": {"coordinates":[-122.296514,37.86397],"type":"Point"}
}