{
  "type": "Feature",
  "properties": {
    "iso:country":"US",
    "sg:address":"1625 State St",
    "sg:city":"Santa Barbara",
    "sg:classifiers":[
        {
            "category":"Health Services",
            "subcategory":"Chiropractor",
            "type":"Services"
        }
    ],
    "sg:phone":"+1 805 569 5002",
    "sg:postcode":"93101",
    "sg:province":"CA",
    "wof:name":"Center For Accident & Work",
    "wof:placetype":"venue"
},
  "geometry": {"coordinates":[-119.710639,34.427742],"type":"Point"}
}