{
  "type": "Feature",
  "properties": {
    "addr:full":"2630 Humboldt St Los Angeles CA 90031",
    "addr:housenumber":"2630",
    "addr:postcode":"90031",
    "addr:street":"Humboldt St",
    "iso:country":"US",
    "sg:address":"2630 Humboldt St",
    "sg:city":"Los Angeles",
    "sg:classifiers":[
        {
            "category":"Manufacturing",
            "subcategory":"Apparel",
            "type":"Manufacturing & Wholesale Goods"
        }
    ],
    "sg:phone":"+1 323 221 9202",
    "sg:postcode":"90031",
    "sg:province":"CA",
    "sg:tags":[
        "sewing",
        "contractor"
    ],
    "wof:name":"Southern Apparel Corp",
    "wof:placetype":"venue"
},
  "geometry": {"coordinates":[-118.21768299999999,34.080276],"type":"Point"}
}