{
  "type": "Feature",
  "properties": {
    "addr:full":"1480 Alamitos Ave Long Beach CA 90813",
    "addr:housenumber":"1480",
    "addr:postcode":"90813",
    "addr:street":"Alamitos Ave",
    "iso:country":"US",
    "sg:address":"1480 Alamitos Ave",
    "sg:city":"Long Beach",
    "sg:classifiers":[
        {
            "category":"Professional",
            "type":"Services"
        }
    ],
    "sg:phone":"+1 562 218 6471",
    "sg:postcode":"90813",
    "sg:province":"CA",
    "sg:tags":[
        "establishment"
    ],
    "wof:name":"Afco",
    "wof:placetype":"venue"
},
  "geometry": {"coordinates":[-118.17701599999999,33.785172],"type":"Point"}
}