{
  "type": "Feature",
  "properties": {
    "iso:country":"US",
    "sg:address":"686 Sutton Way",
    "sg:city":"Grass Valley",
    "sg:classifiers":[
        {
            "category":"Restaurant",
            "type":"Food & Drink"
        }
    ],
    "sg:menulink":"http://www.allmenus.com/ca/grass-valley/75134-round-table-pizza/menu/",
    "sg:phone":"+1 530 273 6155",
    "sg:postcode":"95945",
    "sg:province":"CA",
    "sg:tags":[
        "american",
        "pizza"
    ],
    "wof:name":"Round Table Pizza",
    "wof:placetype":"venue"
},
  "geometry": {"coordinates":[-121.03398300000001,39.227397],"type":"Point"}
}