{
  "type": "Feature",
  "properties": {
    "iso:country":"US",
    "sg:address":"685 Wallis Ave",
    "sg:city":"Gustine",
    "sg:classifiers":[
        {
            "category":"Education",
            "subcategory":"School",
            "type":"Public Place"
        }
    ],
    "sg:phone":"+1 209 854 6404",
    "sg:postcode":"95322",
    "sg:province":"CA",
    "wof:name":"Gustine Middle School",
    "wof:placetype":"venue"
},
  "geometry": {"coordinates":[-121.000613,37.251278],"type":"Point"}
}