{
  "type": "Feature",
  "properties": {
    "addr:full":"7636 Miramar Rd San Diego CA 92126",
    "addr:housenumber":"7636",
    "addr:postcode":"92126",
    "addr:street":"Miramar Rd",
    "iso:country":"US",
    "sg:address":"7636 Miramar Rd",
    "sg:city":"San Diego",
    "sg:classifiers":[
        {
            "category":"Manufacturing",
            "subcategory":"Tools & Machinery",
            "type":"Manufacturing & Wholesale Goods"
        }
    ],
    "sg:phone":"+1 858 693 9000",
    "sg:postcode":"92126",
    "sg:province":"CA",
    "sg:tags":[
        "equipment",
        "pump",
        "pumping"
    ],
    "wof:name":"Race Mate Alternators",
    "wof:placetype":"venue"
},
  "geometry": {"coordinates":[-117.15303900000001,32.883866],"type":"Point"}
}