{
  "type": "Feature",
  "properties": {
    "iso:country":"US",
    "sg:address":"1717 Oakdale Rd Frnt",
    "sg:city":"Modesto",
    "sg:classifiers":[
        {
            "category":"Shopping",
            "subcategory":"Department Store",
            "type":"Retail Goods"
        }
    ],
    "sg:phone":"+1 209 527 5780",
    "sg:postcode":"95355",
    "sg:province":"CA",
    "wof:name":"Food Maxx",
    "wof:placetype":"venue"
},
  "geometry": {"coordinates":[-120.957629,37.668605],"type":"Point"}
}