{
  "type": "Feature",
  "properties": {
    "iso:country":"US",
    "sg:address":"5620 Kearny Mesa Rd",
    "sg:city":"San Diego",
    "sg:classifiers":[
        {
            "category":"Manufacturing",
            "subcategory":"Glass & Minerals",
            "type":"Manufacturing & Wholesale Goods"
        }
    ],
    "sg:phone":"+1 858 654 4070",
    "sg:postcode":"92111",
    "sg:province":"CA",
    "sg:tags":[
        "tempered",
        "mfg"
    ],
    "wof:name":"Downey Glass",
    "wof:placetype":"venue"
},
  "geometry": {"coordinates":[-117.13767900000001,32.836944],"type":"Point"}
}