{
  "type": "Feature",
  "properties": {
    "addr:full":"6406 Mc Abee Rd San Jose CA 95120",
    "addr:housenumber":"6406",
    "addr:postcode":"95120",
    "addr:street":"Mc Abee Rd",
    "iso:country":"US",
    "sg:address":"6406 Mc Abee Rd",
    "sg:city":"San Jose",
    "sg:classifiers":[
        {
            "category":"Manufacturing",
            "subcategory":"Metals",
            "type":"Manufacturing & Wholesale Goods"
        }
    ],
    "sg:phone":"+1 408 838 2179",
    "sg:postcode":"95120",
    "sg:province":"CA",
    "sg:tags":[
        "hanging"
    ],
    "wof:name":"Nuarts Production",
    "wof:placetype":"venue"
},
  "geometry": {"coordinates":[-121.87648,37.225103],"type":"Point"}
}