{
  "type": "Feature",
  "properties": {
    "iso:country":"US",
    "sg:address":"1143 Firestone Blvd",
    "sg:city":"Los Angeles",
    "sg:classifiers":[
        {
            "category":"Autos & Motor Vehicles",
            "subcategory":"Automobile Sales",
            "type":"Retail Goods"
        }
    ],
    "sg:phone":"+1 323 589 7933",
    "sg:postcode":"90001",
    "sg:province":"CA",
    "sg:tags":[
        "car",
        "dealer"
    ],
    "wof:name":"Las Torres Auto Sales",
    "wof:placetype":"venue"
},
  "geometry": {"coordinates":[-118.255683,33.960244],"type":"Point"}
}