{
  "type": "Feature",
  "properties": {
    "addr:full":"459 Fulton St San Francisco CA 94102",
    "addr:housenumber":"459",
    "addr:postcode":"94102",
    "addr:street":"Fulton St",
    "iso:country":"US",
    "sg:address":"459 Fulton St",
    "sg:city":"San Francisco",
    "sg:classifiers":[
        {
            "category":"Professional",
            "subcategory":"Lawyer & Legal Services",
            "type":"Services"
        }
    ],
    "sg:phone":"+1 415 241 0444",
    "sg:postcode":"94102",
    "sg:province":"CA",
    "sg:tags":[
        "attorney"
    ],
    "wof:name":"Linda Votaw Law Offices",
    "wof:placetype":"venue"
},
  "geometry": {"coordinates":[-122.424217,37.778587],"type":"Point"}
}