{
  "type": "Feature",
  "properties": {
    "addr:full":"3153 Marine Ave Gardena CA 90249",
    "addr:housenumber":"3153",
    "addr:postcode":"90249",
    "addr:street":"Marine Ave",
    "iso:country":"US",
    "sg:address":"3153 Marine Ave",
    "sg:city":"Gardena",
    "sg:classifiers":[
        {
            "category":"Education",
            "subcategory":"Preschool",
            "type":"Public Place"
        },
        {
            "category":"Education",
            "subcategory":"School",
            "type":"Public Place"
        }
    ],
    "sg:phone":"+1 310 219 1815",
    "sg:postcode":"90249",
    "sg:province":"CA",
    "sg:tags":[
        "elementary"
    ],
    "wof:name":"Kum Ran Church Pre-School",
    "wof:placetype":"venue"
},
  "geometry": {"coordinates":[-118.328003,33.8946],"type":"Point"}
}