{
  "type": "Feature",
  "properties": {
    "addr:full":"Riviera Palm Springs 1600 North Indian Canyon Road Palm Springs CA 92262",
    "addr:housenumber":"1600",
    "addr:postcode":"92262",
    "addr:street":"Riviera;North Indian Canyon Road",
    "iso:country":"US",
    "sg:address":"Riviera Palm Springs 1600 North Indian Canyon Road",
    "sg:city":"Palm Springs",
    "sg:classifiers":[
        {
            "category":"Bars & Pubs",
            "subcategory":"Lounge",
            "type":"Food & Drink"
        }
    ],
    "sg:phone":"+1 760 327 8311",
    "sg:postcode":"92262",
    "sg:province":"CA",
    "sg:website":"www.psriviera.com/starlite_loung...",
    "wof:name":"Starlite Lounge",
    "wof:placetype":"venue"
},
  "geometry": {"coordinates":[-116.543982,33.84606],"type":"Point"}
}