{
  "type": "Feature",
  "properties": {
    "addr:full":"15958 Arminta St Van Nuys CA 91406",
    "addr:housenumber":"15958",
    "addr:postcode":"91406",
    "addr:street":"Arminta St",
    "iso:country":"US",
    "sg:address":"15958 Arminta St",
    "sg:city":"Van Nuys",
    "sg:classifiers":[
        {
            "category":"Manufacturing",
            "subcategory":"Tools & Machinery",
            "type":"Manufacturing & Wholesale Goods"
        }
    ],
    "sg:phone":"+1 818 989 2324",
    "sg:postcode":"91406",
    "sg:province":"CA",
    "sg:tags":[
        "equipment",
        "welding",
        "supply"
    ],
    "sg:website":"www.edsyn.com",
    "wof:name":"Edsyn Inc",
    "wof:placetype":"venue"
},
  "geometry": {"coordinates":[-118.48332000000001,34.213804],"type":"Point"}
}