{
  "type": "Feature",
  "properties": {
    "iso:country":"US",
    "sg:address":"2080 Llano Rd",
    "sg:city":"Santa Rosa",
    "sg:classifiers":[
        {
            "category":"Retail",
            "subcategory":"Auto Repair",
            "type":"Services"
        }
    ],
    "sg:phone":"+1 707 575 9620",
    "sg:postcode":"95407",
    "sg:province":"CA",
    "sg:tags":[
        "body",
        "automobile",
        "painting"
    ],
    "wof:name":"Randy Hanson Auto Body & Paint",
    "wof:placetype":"venue"
},
  "geometry": {"coordinates":[-122.788468,38.401934],"type":"Point"}
}