{
  "type": "Feature",
  "properties": {
    "addr:full":"14975 Hilton Dr Fontana CA 92336",
    "addr:housenumber":"14975",
    "addr:postcode":"92336",
    "addr:street":"Hilton Dr",
    "iso:country":"US",
    "sg:address":"14975 Hilton Dr",
    "sg:city":"Fontana",
    "sg:classifiers":[
        {
            "category":"Autos & Motor Vehicles",
            "subcategory":"Automobile Sales",
            "type":"Retail Goods"
        }
    ],
    "sg:phone":"+1 909 434 0800",
    "sg:postcode":"92336",
    "sg:province":"CA",
    "sg:tags":[
        "salvage"
    ],
    "wof:name":"California Recyclers",
    "wof:placetype":"venue"
},
  "geometry": {"coordinates":[-117.477616,34.108436],"type":"Point"}
}