{
  "type": "Feature",
  "properties": {
    "iso:country":"US",
    "sg:address":"622 E Hill St",
    "sg:city":"Long Beach",
    "sg:classifiers":[
        {
            "category":"Social Services",
            "subcategory":"Child Care",
            "type":"Services"
        }
    ],
    "sg:phone":"+1 562 599 0633",
    "sg:postcode":"90806",
    "sg:province":"CA",
    "sg:tags":[
        "day"
    ],
    "wof:name":"Comprehensive Child",
    "wof:placetype":"venue"
},
  "geometry": {"coordinates":[-118.184998,33.797001],"type":"Point"}
}