{
  "type": "Feature",
  "properties": {
    "addr:full":"11 Mareblu Ste 220 Aliso Viejo CA 92656",
    "addr:housenumber":"11",
    "addr:postcode":"92656",
    "addr:street":"Mareblu Ste 220",
    "iso:country":"US",
    "sg:address":"11 Mareblu Ste 220",
    "sg:city":"Aliso Viejo",
    "sg:classifiers":[
        {
            "category":"Professional",
            "subcategory":"Lawyer & Legal Services",
            "type":"Services"
        }
    ],
    "sg:phone":"+1 949 643 7000",
    "sg:postcode":"92656",
    "sg:province":"CA",
    "sg:tags":[
        "notary"
    ],
    "wof:name":"Sign On the X Inc",
    "wof:placetype":"venue"
},
  "geometry": {"coordinates":[-117.703121,33.572899],"type":"Point"}
}