{
  "type": "Feature",
  "properties": {
    "addr:full":"19737 Ventura Blvd Woodland Hills CA 91364",
    "addr:housenumber":"19737",
    "addr:postcode":"91364",
    "addr:street":"Ventura Blvd",
    "iso:country":"US",
    "sg:address":"19737 Ventura Blvd",
    "sg:city":"Woodland Hills",
    "sg:classifiers":[
        {
            "category":"Education",
            "subcategory":"Special Training",
            "type":"Public Place"
        }
    ],
    "sg:phone":"+1 818 887 6000",
    "sg:postcode":"91364",
    "sg:province":"CA",
    "sg:tags":[
        "tutoring"
    ],
    "wof:name":"Ivy Bound Educational Ctr",
    "wof:placetype":"venue"
},
  "geometry": {"coordinates":[-118.56364000000001,34.172544],"type":"Point"}
}