{
  "type": "Feature",
  "properties": {
    "iso:country":"US",
    "sg:address":"14551 Red Hill Ave",
    "sg:city":"Tustin",
    "sg:classifiers":[
        {
            "category":"Bakery",
            "type":"Food & Drink"
        }
    ],
    "sg:phone":"+1 714 838 0566",
    "sg:postcode":"92780",
    "sg:province":"CA",
    "wof:name":"Bosco Bakery",
    "wof:placetype":"venue"
},
  "geometry": {"coordinates":[-117.820999,33.727402],"type":"Point"}
}