{
  "type": "Feature",
  "properties": {
    "addr:full":"31383 State Rte 120 Groveland CA 95321",
    "addr:housenumber":"31383",
    "addr:postcode":"95321",
    "addr:street":"State Rte 120",
    "iso:country":"US",
    "sg:address":"31383 State Rte 120",
    "sg:city":"Groveland",
    "sg:classifiers":[
        {
            "category":"Travel",
            "subcategory":"Campground",
            "type":"Entertainment"
        }
    ],
    "sg:phone":"+1 209 962 0121",
    "sg:postcode":"95321",
    "sg:province":"CA",
    "wof:name":"Yosemite Lakes",
    "wof:placetype":"venue"
},
  "geometry": {"coordinates":[-119.884978,37.813465],"type":"Point"}
}