{
  "type": "Feature",
  "properties": {
    "addr:full":"18662 Macarthur Blvd Irvine CA 92612",
    "addr:housenumber":"18662",
    "addr:postcode":"92612",
    "addr:street":"Macarthur Blvd",
    "iso:country":"US",
    "sg:address":"18662 Macarthur Blvd",
    "sg:city":"Irvine",
    "sg:classifiers":[
        {
            "category":"Manufacturing",
            "subcategory":"Tools & Machinery",
            "type":"Manufacturing & Wholesale Goods"
        }
    ],
    "sg:phone":"+1 949 660 8886",
    "sg:postcode":"92612",
    "sg:province":"CA",
    "sg:tags":[
        "mfg",
        "industrial",
        "general"
    ],
    "wof:name":"Finn Power International",
    "wof:placetype":"venue"
},
  "geometry": {"coordinates":[-117.861842,33.67542],"type":"Point"}
}