{
  "type": "Feature",
  "properties": {
    "addr:full":"341 Castro St Mountain View CA 94041",
    "addr:housenumber":"341",
    "addr:postcode":"94041",
    "addr:street":"Castro St",
    "iso:country":"US",
    "sg:address":"341 Castro St",
    "sg:city":"Mountain View",
    "sg:classifiers":[
        {
            "category":"Health Services",
            "subcategory":"Clinic",
            "type":"Services"
        }
    ],
    "sg:phone":"+1 650 940 1688",
    "sg:postcode":"94041",
    "sg:province":"CA",
    "sg:website":"www.qistar.com",
    "wof:name":"Unison Health Connection",
    "wof:placetype":"venue"
},
  "geometry": {"coordinates":[-122.080151,37.391864],"type":"Point"}
}