{
  "type": "Feature",
  "properties": {
    "iso:country":"US",
    "sg:address":"10712 Wilmington Ave",
    "sg:city":"Los Angeles",
    "sg:classifiers":[
        {
            "category":"Social Services",
            "subcategory":"Child Care",
            "type":"Services"
        }
    ],
    "sg:phone":"+1 323 564 0628",
    "sg:postcode":"90059",
    "sg:province":"CA",
    "wof:name":"Kedren Preschool",
    "wof:placetype":"venue"
},
  "geometry": {"coordinates":[-118.238947,33.938786],"type":"Point"}
}