{
  "type": "Feature",
  "properties": {
    "iso:country":"US",
    "sg:address":"119 S 13th St",
    "sg:city":"San Jose",
    "sg:classifiers":[
        {
            "category":"Health Services",
            "subcategory":"Clinic",
            "type":"Services"
        }
    ],
    "sg:phone":"+1 408 362 9918",
    "sg:postcode":"95112",
    "sg:province":"CA",
    "sg:tags":[
        "home"
    ],
    "wof:name":"Frevedel Homecare Healthcare",
    "wof:placetype":"venue"
},
  "geometry": {"coordinates":[-121.875879,37.339056],"type":"Point"}
}