{
  "type": "Feature",
  "properties": {
    "addr:full":"1230 Stockton St San Francisco CA 94133",
    "addr:housenumber":"1230",
    "addr:postcode":"94133",
    "addr:street":"Stockton St",
    "iso:country":"US",
    "sg:address":"1230 Stockton St",
    "sg:city":"San Francisco",
    "sg:classifiers":[
        {
            "category":"Food & Beverages",
            "subcategory":"Specialty",
            "type":"Retail Goods"
        }
    ],
    "sg:phone":"+1 415 397 2288",
    "sg:postcode":"94133",
    "sg:province":"CA",
    "sg:tags":[
        "herb"
    ],
    "wof:name":"Chung Chou City",
    "wof:placetype":"venue"
},
  "geometry": {"coordinates":[-122.40854400000001,37.79763],"type":"Point"}
}