{
  "type": "Feature",
  "properties": {
    "addr:full":"1425 N Avalon Blvd Wilmington CA 90744",
    "addr:housenumber":"1425",
    "addr:postcode":"90744",
    "addr:street":"N Avalon Blvd",
    "iso:country":"US",
    "sg:address":"1425 N Avalon Blvd",
    "sg:city":"Wilmington",
    "sg:classifiers":[
        {
            "category":"Education",
            "subcategory":"School",
            "type":"Public Place"
        }
    ],
    "sg:phone":"+1 310 549 2112",
    "sg:postcode":"90744",
    "sg:province":"CA",
    "sg:tags":[
        "high",
        "middle",
        "elementary"
    ],
    "sg:website":"www.lausd.k12.ca.us",
    "wof:name":"Avalon High School",
    "wof:placetype":"venue"
},
  "geometry": {"coordinates":[-118.26300000000001,33.791698],"type":"Point"}
}