{
  "type": "Feature",
  "properties": {
    "iso:country":"US",
    "sg:address":"334 Main St",
    "sg:city":"Livingston",
    "sg:classifiers":[
        {
            "category":"Shopping",
            "subcategory":"Jewelry",
            "type":"Retail Goods"
        }
    ],
    "sg:phone":"+1 209 394 4947",
    "sg:postcode":"95334",
    "sg:province":"CA",
    "sg:tags":[
        "repair"
    ],
    "wof:name":"Millans Jewelry",
    "wof:placetype":"venue"
},
  "geometry": {"coordinates":[-120.72332,37.386861],"type":"Point"}
}