{
  "type": "Feature",
  "properties": {
    "iso:country":"US",
    "sg:address":"5869 Lone Tree Way",
    "sg:city":"Antioch",
    "sg:classifiers":[
        {
            "category":"Shopping",
            "subcategory":"Clothing, Apparel, & Fashions",
            "type":"Retail Goods"
        },
        {
            "category":"Shopping",
            "subcategory":"Baby Store",
            "type":"Retail Goods"
        }
    ],
    "sg:phone":"+1 925 706 1036",
    "sg:postcode":"94531",
    "sg:province":"CA",
    "sg:tags":[
        "infant",
        "men's",
        "women's",
        "children's",
        "maternity",
        "wear",
        "apparel",
        "girls'",
        "clothing",
        "boys'",
        "clothes"
    ],
    "sg:website":"http://www.oldnavy.com",
    "wof:name":"Old Navy",
    "wof:placetype":"venue"
},
  "geometry": {"coordinates":[-121.734386,37.96169],"type":"Point"}
}