{
  "type": "Feature",
  "properties": {
    "iso:country":"US",
    "sg:address":"2009 E El Segundo Blvd",
    "sg:city":"Compton",
    "sg:classifiers":[
        {
            "category":"Place Of Worship",
            "subcategory":"Church",
            "type":"Public Place"
        },
        {
            "category":"Place Of Worship",
            "type":"Public Place"
        },
        {
            "category":"Organizations",
            "subcategory":"Religious Organization",
            "type":"Services"
        }
    ],
    "sg:phone":"+1 310 638 8908",
    "sg:postcode":"90222",
    "sg:province":"CA",
    "sg:tags":[
        "churches-interdenominational",
        "churches-jehovah's",
        "churches-various",
        "witness",
        "denomination"
    ],
    "sg:website":"http://www.watchtower.org",
    "wof:name":"Christian Congregation Of Jehova's Witnesses",
    "wof:placetype":"venue"
},
  "geometry": {"coordinates":[-118.236395,33.91626],"type":"Point"}
}