{
  "type": "Feature",
  "properties": {
    "iso:country":"US",
    "sg:address":"3435 Wilshire Blvd",
    "sg:city":"Los Angeles",
    "sg:classifiers":[
        {
            "category":"Banks & Credit Unions",
            "subcategory":"Investment Brokerage",
            "type":"Services"
        }
    ],
    "sg:phone":"+1 323 933 7000",
    "sg:postcode":"90010",
    "sg:province":"CA",
    "sg:tags":[
        "commodity"
    ],
    "wof:name":"Calport Resources Inc",
    "wof:placetype":"venue"
},
  "geometry": {"coordinates":[-118.2989,34.061826],"type":"Point"}
}