{
  "type": "Feature",
  "properties": {
    "iso:country":"US",
    "sg:address":"6086 Brockton Ave",
    "sg:city":"Riverside",
    "sg:classifiers":[
        {
            "category":"Health Services",
            "subcategory":"Doctor",
            "type":"Services"
        }
    ],
    "sg:phone":"+1 951 683 8655",
    "sg:postcode":"92506",
    "sg:province":"CA",
    "sg:tags":[
        "dentist"
    ],
    "wof:name":"William A Taylor Inc",
    "wof:placetype":"venue"
},
  "geometry": {"coordinates":[-117.396679,33.96076],"type":"Point"}
}