{
  "type": "Feature",
  "properties": {
    "iso:country":"US",
    "sg:address":"59 Soda Bay Rd # R6",
    "sg:city":"Lakeport",
    "sg:classifiers":[
        {
            "category":"Building & Trades",
            "subcategory":"Construction",
            "type":"Services"
        }
    ],
    "sg:phone":"+1 707 263 0586",
    "sg:postcode":"95453",
    "sg:province":"CA",
    "sg:tags":[
        "contractor",
        "fence-sales"
    ],
    "wof:name":"Precision Vinyl Components",
    "wof:placetype":"venue"
},
  "geometry": {"coordinates":[-122.910443,39.015123],"type":"Point"}
}