{
  "type": "Feature",
  "properties": {
    "addr:full":"1605 School St Moraga CA 94556",
    "addr:housenumber":"1605",
    "addr:postcode":"94556",
    "addr:street":"School St",
    "iso:country":"US",
    "sg:address":"1605 School St",
    "sg:city":"Moraga",
    "sg:classifiers":[
        {
            "category":"Professional",
            "subcategory":"Business Services",
            "type":"Services"
        }
    ],
    "sg:phone":"+1 925 631 1989",
    "sg:postcode":"94556",
    "sg:province":"CA",
    "sg:tags":[
        "consultant",
        "coach"
    ],
    "wof:name":"Advanced Geological Services",
    "wof:placetype":"venue"
},
  "geometry": {"coordinates":[-122.132785,37.832829],"type":"Point"}
}