{
  "type": "Feature",
  "properties": {
    "addr:full":"9720 Rd 29 Madera CA 93637",
    "addr:housenumber":"9720",
    "addr:postcode":"93637",
    "addr:street":"Rd 29",
    "iso:country":"US",
    "sg:address":"9720 Rd 29",
    "sg:city":"Madera",
    "sg:classifiers":[
        {
            "category":"Farming",
            "subcategory":"Crops",
            "type":"Manufacturing & Wholesale Goods"
        }
    ],
    "sg:phone":"+1 559 673 1120",
    "sg:postcode":"93637",
    "sg:province":"CA",
    "sg:tags":[
        "grove",
        "nut",
        "tree"
    ],
    "wof:name":"Joe Clements",
    "wof:placetype":"venue"
},
  "geometry": {"coordinates":[-120.019481,36.905803],"type":"Point"}
}