{
  "type": "Feature",
  "properties": {
    "iso:country":"US",
    "sg:address":"3165 Horizon Dr",
    "sg:city":"Santa Ynez",
    "sg:classifiers":[
        {
            "category":"Retail",
            "subcategory":"Animal Services",
            "type":"Services"
        }
    ],
    "sg:phone":"+1 805 693 8277",
    "sg:postcode":"93460",
    "sg:province":"CA",
    "wof:name":"Two Tone Ranch",
    "wof:placetype":"venue"
},
  "geometry": {"coordinates":[-120.096841,34.609459],"type":"Point"}
}