{
  "type": "Feature",
  "properties": {
    "addr:full":"1459 Humboldt Rd Chico CA 95928",
    "addr:housenumber":"1459",
    "addr:postcode":"95928",
    "addr:street":"Humboldt Rd",
    "iso:country":"US",
    "sg:address":"1459 Humboldt Rd",
    "sg:city":"Chico",
    "sg:classifiers":[
        {
            "category":"Communications",
            "subcategory":"Radio Station",
            "type":"Services"
        }
    ],
    "sg:phone":"+1 530 342 1536",
    "sg:postcode":"95928",
    "sg:province":"CA",
    "sg:tags":[
        "broadcast"
    ],
    "wof:name":"K F M F F M 93 9",
    "wof:placetype":"venue"
},
  "geometry": {"coordinates":[-121.807238,39.737166],"type":"Point"}
}