{
  "type": "Feature",
  "properties": {
    "iso:country":"US",
    "sg:address":"627 N Escondido Blvd",
    "sg:city":"Escondido",
    "sg:classifiers":[
        {
            "category":"Restaurant",
            "type":"Food & Drink"
        }
    ],
    "sg:menulink":"http://www.allmenus.com/ca/oceanside-escondido/213455-taco-bell/menu/",
    "sg:phone":"+1 760 745 0995",
    "sg:postcode":"92025",
    "sg:province":"CA",
    "sg:tags":[
        "mexican"
    ],
    "wof:name":"Taco Bell",
    "wof:placetype":"venue"
},
  "geometry": {"coordinates":[-117.089049,33.126802],"type":"Point"}
}