{
  "type": "Feature",
  "properties": {
    "addr:full":"14615 Sherman Way Van Nuys CA 91405",
    "addr:housenumber":"14615",
    "addr:postcode":"91405",
    "addr:street":"Sherman Way",
    "iso:country":"US",
    "sg:address":"14615 Sherman Way",
    "sg:city":"Van Nuys",
    "sg:classifiers":[
        {
            "category":"Organizations",
            "subcategory":"Religious Organization",
            "type":"Services"
        }
    ],
    "sg:phone":"+1 818 787 8380",
    "sg:postcode":"91405",
    "sg:province":"CA",
    "sg:tags":[
        "church"
    ],
    "wof:name":"Seventh-Day Adventist Church",
    "wof:placetype":"venue"
},
  "geometry": {"coordinates":[-118.450198,34.201266],"type":"Point"}
}