{
  "type": "Feature",
  "properties": {
    "iso:country":"US",
    "sg:address":"10163 Folsom Blvd",
    "sg:city":"Rancho Cordova",
    "sg:classifiers":[
        {
            "category":"Personal",
            "subcategory":"Shoe Repair & Shine",
            "type":"Services"
        }
    ],
    "sg:phone":"+1 916 366 8744",
    "sg:postcode":"95670",
    "sg:province":"CA",
    "sg:tags":[
        "repairing",
        "boot"
    ],
    "wof:name":"Jim's Shoe & Luggage Repair",
    "wof:placetype":"venue"
},
  "geometry": {"coordinates":[-121.31016700000001,38.585549],"type":"Point"}
}