{
  "type": "Feature",
  "properties": {
    "iso:country":"US",
    "sg:address":"8606 W Schulte Rd",
    "sg:city":"Tracy",
    "sg:classifiers":[
        {
            "category":"Wholesale",
            "subcategory":"Groceries",
            "type":"Manufacturing & Wholesale Goods"
        }
    ],
    "sg:phone":"+1 209 835 4213",
    "sg:postcode":"95304",
    "sg:province":"CA",
    "sg:tags":[
        "tomato",
        "farm",
        "grocer",
        "lima",
        "bean"
    ],
    "wof:name":"Alvarez Farms Inc",
    "wof:placetype":"venue"
},
  "geometry": {"coordinates":[-121.405694,37.725135],"type":"Point"}
}