{
  "type": "Feature",
  "properties": {
    "addr:full":"2585 E Vineyard Ave Oxnard CA 93036",
    "addr:housenumber":"2585",
    "addr:postcode":"93036",
    "addr:street":"E Vineyard Ave",
    "iso:country":"US",
    "sg:address":"2585 E Vineyard Ave",
    "sg:city":"Oxnard",
    "sg:classifiers":[
        {
            "category":"Food & Beverages",
            "subcategory":"Groceries & Convenience Stores",
            "type":"Retail Goods"
        }
    ],
    "sg:phone":"+1 805 988 9409",
    "sg:postcode":"93036",
    "sg:province":"CA",
    "sg:tags":[
        "market"
    ],
    "wof:name":"China's Market",
    "wof:placetype":"venue"
},
  "geometry": {"coordinates":[-119.173625,34.231417],"type":"Point"}
}