{
  "type": "Feature",
  "properties": {
    "iso:country":"US",
    "sg:address":"2830 I St",
    "sg:city":"Sacramento",
    "sg:classifiers":[
        {
            "category":"Professional",
            "subcategory":"Management & Consulting",
            "type":"Services"
        }
    ],
    "sg:phone":"+1 916 443 7256",
    "sg:postcode":"95816",
    "sg:province":"CA",
    "sg:tags":[
        "counselor",
        "public",
        "relations"
    ],
    "wof:name":"Vitali-Gage Communications Inc",
    "wof:placetype":"venue"
},
  "geometry": {"coordinates":[-121.46774499999999,38.574606],"type":"Point"}
}