{
  "type": "Feature",
  "properties": {
    "addr:full":"17293 Darwin Ave Hesperia CA 92345",
    "addr:housenumber":"17293",
    "addr:postcode":"92345",
    "addr:street":"Darwin Ave",
    "iso:country":"US",
    "sg:address":"17293 Darwin Ave",
    "sg:city":"Hesperia",
    "sg:classifiers":[
        {
            "category":"Manufacturing",
            "subcategory":"Metals",
            "type":"Manufacturing & Wholesale Goods"
        }
    ],
    "sg:phone":"+1 760 956 1050",
    "sg:postcode":"92345",
    "sg:province":"CA",
    "sg:tags":[
        "stampings"
    ],
    "wof:name":"Rons Metal Spinning",
    "wof:placetype":"venue"
},
  "geometry": {"coordinates":[-117.285444,34.45289],"type":"Point"}
}