{
  "type": "Feature",
  "properties": {
    "addr:full":"525 B St Ste 1500 San Diego CA 92101",
    "addr:housenumber":"525",
    "addr:postcode":"92101",
    "addr:street":"B St Ste 1500",
    "iso:country":"US",
    "sg:address":"525 B St Ste 1500",
    "sg:city":"San Diego",
    "sg:classifiers":[
        {
            "category":"Professional",
            "subcategory":"Lawyer & Legal Services",
            "type":"Services"
        }
    ],
    "sg:phone":"+1 619 858 4706",
    "sg:postcode":"92101",
    "sg:province":"CA",
    "sg:tags":[
        "personal",
        "injury"
    ],
    "wof:name":"Law Offices of William Van Order",
    "wof:placetype":"venue"
},
  "geometry": {"coordinates":[-117.160004,32.7178],"type":"Point"}
}