{
  "type": "Feature",
  "properties": {
    "iso:country":"US",
    "sg:address":"5196 Golden Rd",
    "sg:city":"Pleasanton",
    "sg:classifiers":[
        {
            "category":"Real Estate",
            "subcategory":"Real Estate Operator",
            "type":"Services"
        }
    ],
    "sg:phone":"+1 925 846 9689",
    "sg:postcode":"94566",
    "sg:province":"CA",
    "sg:tags":[
        "apartment"
    ],
    "wof:name":"Del Prado Apartments",
    "wof:placetype":"venue"
},
  "geometry": {"coordinates":[-121.886281,37.667818],"type":"Point"}
}