{
  "type": "Feature",
  "properties": {
    "addr:full":"5953 Chesbro Ave San Jose CA 95123",
    "addr:postcode":"5953;95123",
    "addr:street":"Chesbro Ave",
    "iso:country":"US",
    "sg:address":"5953 Chesbro Ave",
    "sg:city":"San Jose",
    "sg:classifiers":[
        {
            "category":"Professional",
            "type":"Services"
        }
    ],
    "sg:phone":"+1 408 578 6227",
    "sg:postcode":"95123",
    "sg:province":"CA",
    "wof:name":"Just Screenin It",
    "wof:placetype":"venue"
},
  "geometry": {"coordinates":[-121.84492400000001,37.241694],"type":"Point"}
}