{
  "type": "Feature",
  "properties": {
    "addr:full":"14002 Anson Ave Santa Fe Springs CA 90670",
    "addr:housenumber":"14002",
    "addr:postcode":"90670",
    "addr:street":"Anson Ave",
    "iso:country":"US",
    "sg:address":"14002 Anson Ave",
    "sg:city":"Santa Fe Springs",
    "sg:classifiers":[
        {
            "category":"Manufacturing",
            "subcategory":"Tools & Machinery",
            "type":"Manufacturing & Wholesale Goods"
        }
    ],
    "sg:phone":"+1 562 921 1274",
    "sg:postcode":"90670",
    "sg:province":"CA",
    "sg:tags":[
        "machine",
        "shop"
    ],
    "wof:name":"Aero Grinding",
    "wof:placetype":"venue"
},
  "geometry": {"coordinates":[-118.03544100000001,33.90307],"type":"Point"}
}