{
  "type": "Feature",
  "properties": {
    "iso:country":"US",
    "sg:address":"1114 22nd St",
    "sg:city":"Manhattan Beach",
    "sg:classifiers":[
        {
            "category":"Manufacturing",
            "subcategory":"Printing",
            "type":"Manufacturing & Wholesale Goods"
        }
    ],
    "sg:phone":"+1 310 546 2288",
    "sg:postcode":"90266",
    "sg:province":"CA",
    "sg:tags":[
        "printer"
    ],
    "sg:website":"www.manhattanrepro.com",
    "wof:name":"Manhattan Repro",
    "wof:placetype":"venue"
},
  "geometry": {"coordinates":[-118.39512000000001,33.893215],"type":"Point"}
}