{
  "type": "Feature",
  "properties": {
    "iso:country":"US",
    "sg:address":"2332 Amapola Dr",
    "sg:city":"Davis",
    "sg:classifiers":[
        {
            "category":"Manufacturing",
            "subcategory":"Jewelry",
            "type":"Manufacturing & Wholesale Goods"
        }
    ],
    "sg:phone":"+1 916 421 3316",
    "sg:postcode":"95616",
    "sg:province":"CA",
    "sg:tags":[
        "jeweler"
    ],
    "sg:website":"www.carnelian.com",
    "wof:name":"Esperanza Station",
    "wof:placetype":"venue"
},
  "geometry": {"coordinates":[-121.745712,38.565538],"type":"Point"}
}