{
  "type": "Feature",
  "properties": {
    "iso:country":"US",
    "sg:address":"1632 Crenshaw Blvd",
    "sg:city":"Torrance",
    "sg:classifiers":[
        {
            "category":"Restaurant",
            "type":"Food & Drink"
        }
    ],
    "sg:phone":"+1 310 618 8979",
    "sg:postcode":"90501",
    "sg:province":"CA",
    "sg:tags":[
        "fast"
    ],
    "wof:name":"Steve's Char Burgers No 1",
    "wof:placetype":"venue"
},
  "geometry": {"coordinates":[-118.329002,33.831799],"type":"Point"}
}