{
  "type": "Feature",
  "properties": {
    "addr:full":"634 N Main St Los Angeles CA 90012",
    "addr:housenumber":"634",
    "addr:postcode":"90012",
    "addr:street":"N Main St",
    "iso:country":"US",
    "sg:address":"634 N Main St",
    "sg:city":"Los Angeles",
    "sg:classifiers":[
        {
            "category":"Wholesale",
            "subcategory":"Non-durable Goods",
            "type":"Manufacturing & Wholesale Goods"
        }
    ],
    "sg:phone":"+1 213 625 1754",
    "sg:postcode":"90012",
    "sg:province":"CA",
    "wof:name":"Artes Andinas",
    "wof:placetype":"venue"
},
  "geometry": {"coordinates":[-118.23832400000001,34.057473],"type":"Point"}
}