{
  "type": "Feature",
  "properties": {
    "addr:full":"2235 State Rte 46 Wasco CA 93280",
    "addr:housenumber":"2235",
    "addr:postcode":"ca 93280",
    "addr:street":"State Rte 46",
    "iso:country":"US",
    "sg:address":"2235 State Rte 46",
    "sg:city":"Wasco",
    "sg:classifiers":[
        {
            "category":"Professional",
            "subcategory":"Accounting & Tax Preparation",
            "type":"Services"
        }
    ],
    "sg:phone":"+1 661 758 1191",
    "sg:postcode":"93280",
    "sg:province":"CA",
    "sg:tags":[
        "accountant"
    ],
    "sg:website":"www.albert-cpa.com",
    "wof:name":"Albert & Assoc LLP",
    "wof:placetype":"venue"
},
  "geometry": {"coordinates":[-119.350431,35.601476],"type":"Point"}
}