{
  "type": "Feature",
  "properties": {
    "addr:full":"149 E Yosemite Ave Madera CA 93638",
    "addr:housenumber":"149",
    "addr:postcode":"93638",
    "addr:street":"E Yosemite Ave",
    "iso:country":"US",
    "sg:address":"149 E Yosemite Ave",
    "sg:city":"Madera",
    "sg:classifiers":[
        {
            "category":"Shopping",
            "subcategory":"Clothing, Apparel, & Fashions",
            "type":"Retail Goods"
        }
    ],
    "sg:phone":"+1 559 674 4633",
    "sg:postcode":"93638",
    "sg:province":"CA",
    "sg:tags":[
        "furnishing"
    ],
    "wof:name":"William Carol Fashions Unltd",
    "wof:placetype":"venue"
},
  "geometry": {"coordinates":[-120.058977,36.962323],"type":"Point"}
}