{
  "type": "Feature",
  "properties": {
    "addr:full":"4949 Rhoads Ave Santa Barbara CA 93111",
    "addr:housenumber":"4949",
    "addr:postcode":"93111",
    "addr:street":"Rhoads Ave",
    "iso:country":"US",
    "sg:address":"4949 Rhoads Ave",
    "sg:city":"Santa Barbara",
    "sg:classifiers":[
        {
            "category":"Communications",
            "type":"Services"
        }
    ],
    "sg:phone":"+1 805 683 6759",
    "sg:postcode":"93111",
    "sg:province":"CA",
    "sg:tags":[
        "internet"
    ],
    "wof:name":"DWHS",
    "wof:placetype":"venue"
},
  "geometry": {"coordinates":[-119.795371,34.428182],"type":"Point"}
}