{
  "type": "Feature",
  "properties": {
    "addr:full":"825 N Euclid Anaheim CA 92801",
    "addr:housenumber":"825",
    "addr:postcode":"92801",
    "addr:street":"N Euclid",
    "iso:country":"US",
    "sg:address":"825 N Euclid",
    "sg:city":"Anaheim",
    "sg:classifiers":[
        {
            "category":"Restaurant",
            "type":"Food & Drink"
        }
    ],
    "sg:postcode":"92801",
    "sg:province":"CA",
    "sg:tags":[
        "seafood",
        "mexican"
    ],
    "wof:name":"Sahuaros Birrieria & Seafood",
    "wof:placetype":"venue"
},
  "geometry": {"coordinates":[-117.94217500000001,33.843611],"type":"Point"}
}