{
  "type": "Feature",
  "properties": {
    "addr:full":"3563 6th Avenue San Diego CA 92103",
    "addr:housenumber":"3563",
    "addr:postcode":"92103",
    "addr:street":"6Th Avenue",
    "iso:country":"US",
    "sg:address":"3563 6th Avenue",
    "sg:city":"San Diego",
    "sg:classifiers":[
        {
            "category":"Real Estate",
            "subcategory":"Real Estate Operator",
            "type":"Services"
        }
    ],
    "sg:phone":"+1 619 542 0377",
    "sg:postcode":"92103",
    "sg:province":"CA",
    "sg:tags":[
        "apartment"
    ],
    "wof:name":"Park Tower Apartments",
    "wof:placetype":"venue"
},
  "geometry": {"coordinates":[-117.159463,32.742864],"type":"Point"}
}