{
  "type": "Feature",
  "properties": {
    "addr:full":"1012 2nd St Encinitas CA 92024",
    "addr:housenumber":"1012",
    "addr:postcode":"92024",
    "addr:street":"2Nd St",
    "iso:country":"US",
    "sg:address":"1012 2nd St",
    "sg:city":"Encinitas",
    "sg:classifiers":[
        {
            "category":"Real Estate",
            "subcategory":"Architect",
            "type":"Services"
        }
    ],
    "sg:phone":"+1 760 479 1822",
    "sg:postcode":"92024",
    "sg:province":"CA",
    "wof:name":"Moser Gibb Architects",
    "wof:placetype":"venue"
},
  "geometry": {"coordinates":[-117.293876,33.038668],"type":"Point"}
}