{
  "type": "Feature",
  "properties": {
    "addr:full":"33051 Arizona St Union City CA 94587",
    "addr:housenumber":"33051",
    "addr:postcode":"94587",
    "addr:street":"Arizona St",
    "iso:country":"US",
    "sg:address":"33051 Arizona St",
    "sg:city":"Union City",
    "sg:classifiers":[
        {
            "category":"Social Services",
            "subcategory":"Adult Care",
            "type":"Services"
        }
    ],
    "sg:phone":"+1 510 675 9841",
    "sg:postcode":"94587",
    "sg:province":"CA",
    "sg:tags":[
        "home",
        "residential"
    ],
    "wof:name":"All Time Care Home",
    "wof:placetype":"venue"
},
  "geometry": {"coordinates":[-122.045407,37.590545],"type":"Point"}
}