{
  "type": "Feature",
  "properties": {
    "addr:full":"3056 Iris Ave San Diego CA 92154",
    "addr:housenumber":"3056",
    "addr:postcode":"92154",
    "addr:street":"Iris Ave",
    "iso:country":"US",
    "sg:address":"3056 Iris Ave",
    "sg:city":"San Diego",
    "sg:classifiers":[
        {
            "category":"Shopping",
            "subcategory":"Optician",
            "type":"Retail Goods"
        }
    ],
    "sg:phone":"+1 619 690 0631",
    "sg:postcode":"92154",
    "sg:province":"CA",
    "sg:tags":[
        "eyewear"
    ],
    "wof:name":"Prisma Optical",
    "wof:placetype":"venue"
},
  "geometry": {"coordinates":[-117.06789000000001,32.569138],"type":"Point"}
}