{
  "type": "Feature",
  "properties": {
    "addr:full":"21764 el Puma Cir Sonora CA 95370",
    "addr:housenumber":"21764",
    "addr:postcode":"95370",
    "addr:street":"El Puma Cir",
    "iso:country":"US",
    "sg:address":"21764 el Puma Cir",
    "sg:city":"Sonora",
    "sg:classifiers":[
        {
            "category":"Banks & Credit Unions",
            "subcategory":"Investment Brokerage",
            "type":"Services"
        }
    ],
    "sg:phone":"+1 209 533 9547",
    "sg:postcode":"95370",
    "sg:province":"CA",
    "sg:tags":[
        "commodity",
        "contract"
    ],
    "wof:name":"M J M Investments",
    "wof:placetype":"venue"
},
  "geometry": {"coordinates":[-120.305537,38.01413],"type":"Point"}
}