{
  "type": "Feature",
  "properties": {
    "addr:full":"653 S Spring St Los Angeles CA 90013",
    "addr:housenumber":"653",
    "addr:postcode":"90013",
    "addr:street":"S Spring St",
    "iso:country":"US",
    "sg:address":"653 S Spring St",
    "sg:city":"Los Angeles",
    "sg:classifiers":[
        {
            "category":"Juice Bar",
            "subcategory":"None",
            "type":"Food & Drink"
        },
        {
            "category":"Restaurant",
            "type":"Food & Drink"
        }
    ],
    "sg:phone":"+1 213 627 4111",
    "sg:postcode":"90013",
    "sg:province":"CA",
    "sg:tags":[
        "smoothy",
        "mexican"
    ],
    "sg:website":"www.raspadoxpress.com",
    "wof:name":"Raspado Xpress",
    "wof:placetype":"venue"
},
  "geometry": {"coordinates":[-118.25167,34.04521],"type":"Point"}
}