{
  "type": "Feature",
  "properties": {
    "iso:country":"US",
    "sg:address":"1316 Chestnut St",
    "sg:city":"San Carlos",
    "sg:classifiers":[
        {
            "category":"Professional",
            "subcategory":"Business Services",
            "type":"Services"
        }
    ],
    "sg:phone":"+1 650 592 1868",
    "sg:postcode":"94070",
    "sg:province":"CA",
    "sg:tags":[
        "drafting"
    ],
    "wof:name":"Anderson Illustration",
    "wof:placetype":"venue"
},
  "geometry": {"coordinates":[-122.254261,37.494087],"type":"Point"}
}