{
  "type": "Feature",
  "properties": {
    "addr:full":"7038 Bellaire Ave North Hollywood CA 91605",
    "addr:housenumber":"7038",
    "addr:postcode":"91605",
    "addr:street":"Bellaire Ave",
    "iso:country":"US",
    "sg:address":"7038 Bellaire Ave",
    "sg:city":"North Hollywood",
    "sg:classifiers":[
        {
            "category":"Freight",
            "type":"Transportation"
        }
    ],
    "sg:phone":"+1 818 765 4896",
    "sg:postcode":"91605",
    "sg:province":"CA",
    "sg:tags":[
        "trucking"
    ],
    "wof:name":"Ayvazyan Stepan",
    "wof:placetype":"venue"
},
  "geometry": {"coordinates":[-118.409347,34.198658],"type":"Point"}
}