{
  "type": "Feature",
  "properties": {
    "addr:full":"19104 Bailey Rd Tehachapi CA 93561",
    "addr:housenumber":"19104",
    "addr:postcode":"93561",
    "addr:street":"Bailey Rd",
    "iso:country":"US",
    "sg:address":"19104 Bailey Rd",
    "sg:city":"Tehachapi",
    "sg:classifiers":[
        {
            "category":"Real Estate",
            "subcategory":"Real Estate Agent",
            "type":"Services"
        }
    ],
    "sg:phone":"+1 661 822 4195",
    "sg:postcode":"93561",
    "sg:province":"CA",
    "wof:name":"Jim Mann Real Estate",
    "wof:placetype":"venue"
},
  "geometry": {"coordinates":[-118.59315599999999,35.104925],"type":"Point"}
}