{
  "type": "Feature",
  "properties": {
    "iso:country":"US",
    "sg:address":"1335 Crowley Ln",
    "sg:city":"Fairfield",
    "sg:classifiers":[
        {
            "category":"Real Estate",
            "subcategory":"Real Estate Operator",
            "type":"Services"
        }
    ],
    "sg:phone":"+1 707 425 3439",
    "sg:postcode":"94533",
    "sg:province":"CA",
    "sg:tags":[
        "apartment"
    ],
    "wof:name":"Siesta Garden Apartments",
    "wof:placetype":"venue"
},
  "geometry": {"coordinates":[-122.051492,38.247542],"type":"Point"}
}