{
  "type": "Feature",
  "properties": {
    "iso:country":"US",
    "sg:address":"4431 Corporate Center Dr Ste 131",
    "sg:city":"Los Alamitos",
    "sg:classifiers":[
        {
            "category":"Professional",
            "subcategory":"Advertising",
            "type":"Services"
        },
        {
            "category":"Professional",
            "subcategory":"Art Services",
            "type":"Services"
        },
        {
            "category":"Professional",
            "subcategory":"Printing & Photocopies",
            "type":"Services"
        }
    ],
    "sg:phone":"+1 714 527 5424",
    "sg:postcode":"90720",
    "sg:province":"CA",
    "sg:tags":[
        "marketing",
        "graphic",
        "design"
    ],
    "sg:website":"www.iconographyStudios.net",
    "wof:name":"Iconography Studios",
    "wof:placetype":"venue"
},
  "geometry": {"coordinates":[-118.055603,33.808271],"type":"Point"}
}