{
  "type": "Feature",
  "properties": {
    "addr:full":"25386 Via Palacio Valencia CA 91355",
    "addr:housenumber":"25386",
    "addr:postcode":"91355",
    "addr:street":"Via Palacio",
    "iso:country":"US",
    "sg:address":"25386 Via Palacio",
    "sg:city":"Valencia",
    "sg:classifiers":[
        {
            "category":"Social Services",
            "type":"Services"
        }
    ],
    "sg:phone":"+1 661 288 0368",
    "sg:postcode":"91355",
    "sg:province":"CA",
    "sg:tags":[
        "youth",
        "organization",
        "center"
    ],
    "wof:name":"American Youth Soccer",
    "wof:placetype":"venue"
},
  "geometry": {"coordinates":[-118.546542,34.394271],"type":"Point"}
}