{
  "type": "Feature",
  "properties": {
    "addr:full":"2830 Glenn Ave Los Angeles CA 90023",
    "addr:housenumber":"2830",
    "addr:postcode":"90023",
    "addr:street":"Glenn Ave",
    "iso:country":"US",
    "sg:address":"2830 Glenn Ave",
    "sg:city":"Los Angeles",
    "sg:classifiers":[
        {
            "category":"Communications",
            "type":"Services"
        }
    ],
    "sg:phone":"+1 323 980 9347",
    "sg:postcode":"90023",
    "sg:province":"CA",
    "sg:tags":[
        "communication"
    ],
    "wof:name":"Califone Communications",
    "wof:placetype":"venue"
},
  "geometry": {"coordinates":[-118.21566,34.023708],"type":"Point"}
}