{
  "type": "Feature",
  "properties": {
    "iso:country":"US",
    "sg:address":"2112 Danville Blvd",
    "sg:city":"Alamo",
    "sg:classifiers":[
        {
            "category":"Manufacturing",
            "subcategory":"Printing",
            "type":"Manufacturing & Wholesale Goods"
        }
    ],
    "sg:phone":"+1 925 932 5408",
    "sg:postcode":"94507",
    "sg:province":"CA",
    "sg:tags":[
        "lithographic",
        "commercial"
    ],
    "wof:name":"Intaglio Press",
    "wof:placetype":"venue"
},
  "geometry": {"coordinates":[-122.032686,37.850795],"type":"Point"}
}