{
  "type": "Feature",
  "properties": {
    "addr:full":"2200 Sharon Rd. Menlo Park, Ca 94025",
    "wof:categories":[
        "education_and_religion:education=school"
    ],
    "wof:name":"La Entrada Middle School",
    "wof:placetype":"venue"
},
  "geometry": {"coordinates":[-122.20061993871403,37.42863734133243],"type":"Point"}
}