{
  "type": "Feature",
  "properties": {
    "iso:country":"US",
    "sg:address":"5720 Roseville Rd",
    "sg:city":"Sacramento",
    "sg:classifiers":[
        {
            "category":"Retail",
            "subcategory":"Auto Repair",
            "type":"Services"
        }
    ],
    "sg:phone":"+1 916 339 1290",
    "sg:postcode":"95842",
    "sg:province":"CA",
    "sg:tags":[
        "road"
    ],
    "wof:name":"A 1 Mobile Auto Svc",
    "wof:placetype":"venue"
},
  "geometry": {"coordinates":[-121.36604,38.673859],"type":"Point"}
}