{
  "type": "Feature",
  "properties": {
    "addr:full":"177 Front St Danville CA 94526",
    "addr:housenumber":"177",
    "addr:postcode":"94526",
    "addr:street":"Front St",
    "iso:country":"US",
    "sg:address":"177 Front St",
    "sg:city":"Danville",
    "sg:classifiers":[
        {
            "category":"Professional",
            "subcategory":"Accounting & Tax Preparation",
            "type":"Services"
        }
    ],
    "sg:phone":"+1 925 838 0400",
    "sg:postcode":"94526",
    "sg:province":"CA",
    "sg:tags":[
        "accountant"
    ],
    "wof:name":"Collis & Ramos",
    "wof:placetype":"venue"
},
  "geometry": {"coordinates":[-121.996285,37.819565],"type":"Point"}
}