{
  "type": "Feature",
  "properties": {
    "addr:full":"4915 W 142nd St Hawthorne CA 90250",
    "addr:housenumber":"4915",
    "addr:postcode":"90250",
    "addr:street":"W 142Nd St",
    "iso:country":"US",
    "sg:address":"4915 W 142nd St",
    "sg:city":"Hawthorne",
    "sg:classifiers":[
        {
            "category":"Building & Trades",
            "subcategory":"Plumbing",
            "type":"Services"
        }
    ],
    "sg:phone":"+1 310 200 0258",
    "sg:postcode":"90250",
    "sg:province":"CA",
    "sg:tags":[
        "plumbing",
        "contractor"
    ],
    "wof:name":"Holmstedt Plumbing",
    "wof:placetype":"venue"
},
  "geometry": {"coordinates":[-118.364602,33.902875],"type":"Point"}
}