{
  "type": "Feature",
  "properties": {
    "iso:country":"US",
    "sg:address":"920 Via Cartago",
    "sg:city":"Riverside",
    "sg:classifiers":[
        {
            "category":"Shopping",
            "subcategory":"Computers & Home Electronics",
            "type":"Retail Goods"
        }
    ],
    "sg:phone":"+1 951 682 8662",
    "sg:postcode":"92507",
    "sg:province":"CA",
    "sg:tags":[
        "parts",
        "supply"
    ],
    "wof:name":"Insight Computing Svc Inc",
    "wof:placetype":"venue"
},
  "geometry": {"coordinates":[-117.331102,33.951272],"type":"Point"}
}