{
  "type": "Feature",
  "properties": {
    "addr:full":"15615 Alton Pkwy Ste 260 Irvine CA 92618",
    "addr:housenumber":"15615",
    "addr:postcode":"92618",
    "addr:street":"Alton Pkwy Ste 260",
    "iso:country":"US",
    "sg:address":"15615 Alton Pkwy Ste 260",
    "sg:city":"Irvine",
    "sg:classifiers":[
        {
            "category":"Professional",
            "subcategory":"Accounting & Tax Preparation",
            "type":"Services"
        }
    ],
    "sg:phone":"+1 949 752 1322",
    "sg:postcode":"92618",
    "sg:province":"CA",
    "sg:tags":[
        "accountant"
    ],
    "wof:name":"Klopfstein & Kapur Llp",
    "wof:placetype":"venue"
},
  "geometry": {"coordinates":[-117.752731,33.655843],"type":"Point"}
}