{
  "type": "Feature",
  "properties": {
    "iso:country":"US",
    "sg:address":"189 Great Mall Dr",
    "sg:city":"Milpitas",
    "sg:classifiers":[
        {
            "category":"Manufacturing",
            "subcategory":"Printing",
            "type":"Manufacturing & Wholesale Goods"
        }
    ],
    "sg:phone":"+1 408 935 8171",
    "sg:postcode":"95035",
    "sg:province":"CA",
    "sg:tags":[
        "periodical"
    ],
    "wof:name":"Voga",
    "wof:placetype":"venue"
},
  "geometry": {"coordinates":[-121.90057,37.419294],"type":"Point"}
}