{
  "type": "Feature",
  "properties": {
    "iso:country":"US",
    "sg:address":"117 Drake Ct",
    "sg:city":"Vallejo",
    "sg:classifiers":[
        {
            "category":"Shopping",
            "subcategory":"Clothing, Apparel, & Fashions",
            "type":"Retail Goods"
        }
    ],
    "sg:phone":"+1 707 333 9083",
    "sg:postcode":"94591",
    "sg:province":"CA",
    "sg:tags":[
        "handbag"
    ],
    "wof:name":"Styles International",
    "wof:placetype":"venue"
},
  "geometry": {"coordinates":[-122.208134,38.072057],"type":"Point"}
}