{
  "type": "Feature",
  "properties": {
    "addr:full":"18376 Gothard St Huntington Beach CA 92647",
    "addr:housenumber":"18376",
    "addr:postcode":"92647",
    "addr:street":"Gothard St",
    "iso:country":"US",
    "sg:address":"18376 Gothard St",
    "sg:city":"Huntington Beach",
    "sg:classifiers":[
        {
            "category":"Wholesale",
            "subcategory":"Durable Goods & Equipment",
            "type":"Manufacturing & Wholesale Goods"
        }
    ],
    "sg:phone":"+1 714 596 5644",
    "sg:postcode":"92647",
    "sg:province":"CA",
    "sg:tags":[
        "professional"
    ],
    "wof:name":"CTS",
    "wof:placetype":"venue"
},
  "geometry": {"coordinates":[-117.99973199999999,33.694804],"type":"Point"}
}