{
  "type": "Feature",
  "properties": {
    "addr:full":"960 Baker St Bakersfield CA 93305",
    "addr:housenumber":"960",
    "addr:postcode":"93305",
    "addr:street":"Baker St",
    "iso:country":"US",
    "sg:address":"960 Baker St",
    "sg:city":"Bakersfield",
    "sg:classifiers":[
        {
            "category":"Personal",
            "subcategory":"Shoe Repair & Shine",
            "type":"Services"
        }
    ],
    "sg:phone":"+1 661 324 3287",
    "sg:postcode":"93305",
    "sg:province":"CA",
    "sg:tags":[
        "repairing",
        "boot"
    ],
    "wof:name":"Williams Shoe Svc",
    "wof:placetype":"venue"
},
  "geometry": {"coordinates":[-118.992442,35.378231],"type":"Point"}
}