{
  "type": "Feature",
  "properties": {
    "iso:country":"US",
    "sg:address":"2515 S Western Ave",
    "sg:city":"San Pedro",
    "sg:classifiers":[
        {
            "category":"Health Services",
            "subcategory":"Doctor",
            "type":"Services"
        }
    ],
    "sg:phone":"+1 310 832 2657",
    "sg:postcode":"90732",
    "sg:province":"CA",
    "sg:tags":[
        "dentist"
    ],
    "wof:name":"Susan A Sheets DDS",
    "wof:placetype":"venue"
},
  "geometry": {"coordinates":[-118.314219,33.721912],"type":"Point"}
}