{
  "type": "Feature",
  "properties": {
    "addr:full":"500 S Glenn Alan Ave West Covina CA 91791",
    "addr:housenumber":"500",
    "addr:postcode":"91791",
    "addr:street":"S Glenn Alan Ave",
    "iso:country":"US",
    "sg:address":"500 S Glenn Alan Ave",
    "sg:city":"West Covina",
    "sg:classifiers":[
        {
            "category":"Government",
            "subcategory":"Office",
            "type":"Public Place"
        }
    ],
    "sg:phone":"+1 626 332 5697",
    "sg:postcode":"91791",
    "sg:province":"CA",
    "sg:tags":[
        "national",
        "security"
    ],
    "wof:name":"USS Prince William Assoc",
    "wof:placetype":"venue"
},
  "geometry": {"coordinates":[-117.903886,34.065982],"type":"Point"}
}