{
  "type": "Feature",
  "properties": {
    "iso:country":"US",
    "sg:address":"180 E Sunnyoaks Avenue Bldg 5B",
    "sg:city":"Campbell",
    "sg:classifiers":[
        {
            "category":"Shopping",
            "subcategory":"Antiques",
            "type":"Retail Goods"
        }
    ],
    "sg:phone":"+1 408 395 0696",
    "sg:postcode":"95008",
    "sg:province":"CA",
    "wof:name":"Los Gatos Refinishing",
    "wof:placetype":"venue"
},
  "geometry": {"coordinates":[-121.95185499999999,37.271925],"type":"Point"}
}