{
  "type": "Feature",
  "properties": {
    "addr:full":"2156 The Alameda San Jose CA 95126",
    "addr:housenumber":"2156",
    "addr:postcode":"95126",
    "addr:street":"The Alameda",
    "iso:country":"US",
    "sg:address":"2156 The Alameda",
    "sg:city":"San Jose",
    "sg:classifiers":[
        {
            "category":"Real Estate",
            "subcategory":"Real Estate Agent",
            "type":"Services"
        }
    ],
    "sg:phone":"+1 408 615 7733",
    "sg:postcode":"95126",
    "sg:province":"CA",
    "wof:name":"J D Properties",
    "wof:placetype":"venue"
},
  "geometry": {"coordinates":[-121.931293,37.344335],"type":"Point"}
}