{
  "type": "Feature",
  "properties": {
    "addr:full":"175 W 5th St San Bernardino CA 92410",
    "addr:housenumber":"175",
    "addr:postcode":"92410",
    "addr:street":"W 5Th St",
    "iso:country":"US",
    "sg:address":"175 W 5th St",
    "sg:city":"San Bernardino",
    "sg:classifiers":[
        {
            "category":"Government",
            "subcategory":"Office",
            "type":"Public Place"
        }
    ],
    "sg:phone":"+1 909 387 5869",
    "sg:postcode":"92410",
    "sg:province":"CA",
    "sg:tags":[
        "conservation"
    ],
    "wof:name":"Lafco",
    "wof:placetype":"venue"
},
  "geometry": {"coordinates":[-117.28592500000001,34.108253],"type":"Point"}
}