{
  "type": "Feature",
  "properties": {
    "iso:country":"US",
    "sg:address":"210 N Beechwood Ave",
    "sg:city":"Rialto",
    "sg:classifiers":[
        {
            "category":"Wholesale",
            "subcategory":"Computers",
            "type":"Manufacturing & Wholesale Goods"
        }
    ],
    "sg:phone":"+1 909 877 5662",
    "sg:postcode":"92376",
    "sg:province":"CA",
    "sg:tags":[
        "equipment"
    ],
    "wof:name":"Belnap Construction Groups",
    "wof:placetype":"venue"
},
  "geometry": {"coordinates":[-117.389038,34.101958],"type":"Point"}
}