{
  "type": "Feature",
  "properties": {
    "iso:country":"US",
    "sg:address":"53 Depot Rd",
    "sg:city":"Goleta",
    "sg:classifiers":[
        {
            "category":"Retail",
            "subcategory":"Auto Repair",
            "type":"Services"
        }
    ],
    "sg:phone":"+1 805 964 0100",
    "sg:postcode":"93117",
    "sg:province":"CA",
    "sg:tags":[
        "repairing",
        "automobile"
    ],
    "wof:name":"Smitty's-Goleta",
    "wof:placetype":"venue"
},
  "geometry": {"coordinates":[-119.821242,34.439049],"type":"Point"}
}