{
  "type": "Feature",
  "properties": {
    "addr:full":"11601 Pendleton St Sun Valley CA 91352",
    "addr:housenumber":"11601",
    "addr:postcode":"91352",
    "addr:street":"Pendleton St",
    "iso:country":"US",
    "sg:address":"11601 Pendleton St",
    "sg:city":"Sun Valley",
    "sg:classifiers":[
        {
            "category":"Wholesale",
            "subcategory":"Apparel",
            "type":"Manufacturing & Wholesale Goods"
        }
    ],
    "sg:phone":"+1 818 767 7717",
    "sg:postcode":"91352",
    "sg:province":"CA",
    "sg:tags":[
        "piece"
    ],
    "wof:name":"Crown Bed Linens",
    "wof:placetype":"venue"
},
  "geometry": {"coordinates":[-118.386807,34.228511],"type":"Point"}
}