{
  "type": "Feature",
  "properties": {
    "addr:full":"835 W Ave L Lancaster CA 93534",
    "addr:housenumber":"835",
    "addr:postcode":"93534",
    "addr:street":"W Ave L",
    "iso:country":"US",
    "sg:address":"835 W Ave L",
    "sg:city":"Lancaster",
    "sg:classifiers":[
        {
            "category":"Real Estate",
            "subcategory":"Real Estate Operator",
            "type":"Services"
        }
    ],
    "sg:phone":"+1 661 948 5008",
    "sg:postcode":"93534",
    "sg:province":"CA",
    "sg:tags":[
        "apartment"
    ],
    "wof:name":"Montecito Apartments",
    "wof:placetype":"venue"
},
  "geometry": {"coordinates":[-118.147085,34.660359],"type":"Point"}
}