{
  "type": "Feature",
  "properties": {
    "addr:full":"15880 Rose Ave Los Gatos CA 95030",
    "addr:housenumber":"15880",
    "addr:postcode":"95030",
    "addr:street":"Rose Ave",
    "iso:country":"US",
    "sg:address":"15880 Rose Ave",
    "sg:city":"Los Gatos",
    "sg:classifiers":[
        {
            "category":"Professional",
            "subcategory":"Management & Consulting",
            "type":"Services"
        }
    ],
    "sg:phone":"+1 408 354 1964",
    "sg:postcode":"95030",
    "sg:province":"CA",
    "sg:tags":[
        "consultant",
        "resource",
        "human"
    ],
    "sg:website":"www.careercompany.com",
    "wof:name":"Career Co",
    "wof:placetype":"venue"
},
  "geometry": {"coordinates":[-121.984066,37.236542],"type":"Point"}
}