{
  "type": "Feature",
  "properties": {
    "addr:full":"119 Ready Rd Walnut Creek CA 94598",
    "addr:housenumber":"119",
    "addr:postcode":"94598",
    "addr:street":"Ready Rd",
    "iso:country":"US",
    "sg:address":"119 Ready Rd",
    "sg:city":"Walnut Creek",
    "sg:classifiers":[
        {
            "category":"Professional",
            "subcategory":"Business Services",
            "type":"Services"
        }
    ],
    "sg:phone":"+1 925 938 4642",
    "sg:postcode":"94598",
    "sg:province":"CA",
    "sg:tags":[
        "lecture",
        "bureau",
        "seminar"
    ],
    "wof:name":"Lynne Leach Presents",
    "wof:placetype":"venue"
},
  "geometry": {"coordinates":[-122.036227,37.926398],"type":"Point"}
}