{
  "type": "Feature",
  "properties": {
    "addr:full":"16255 Ventura Blvd Encino CA 91436",
    "addr:housenumber":"16255",
    "addr:postcode":"91436",
    "addr:street":"Ventura Blvd",
    "iso:country":"US",
    "sg:address":"16255 Ventura Blvd",
    "sg:city":"Encino",
    "sg:phone":"+1 818 379 8700",
    "sg:postcode":"91436",
    "sg:province":"CA",
    "sg:website":"http://www.ezehealthcoverage.com",
    "wof:name":"Ezehealthcoverage",
    "wof:placetype":"venue"
},
  "geometry": {"coordinates":[-118.487071,34.156831],"type":"Point"}
}