{
  "type": "Feature",
  "properties": {
    "addr:full":"1605 Chapin Rd Montebello CA 90640",
    "addr:housenumber":"1605",
    "addr:postcode":"90640",
    "addr:street":"Chapin Rd",
    "iso:country":"US",
    "sg:address":"1605 Chapin Rd",
    "sg:city":"Montebello",
    "sg:classifiers":[
        {
            "category":"Freight",
            "type":"Transportation"
        }
    ],
    "sg:phone":"+1 323 889 8000",
    "sg:postcode":"90640",
    "sg:province":"CA",
    "sg:tags":[
        "trucking"
    ],
    "wof:name":"Container Connection",
    "wof:placetype":"venue"
},
  "geometry": {"coordinates":[-118.11866499999999,33.98129],"type":"Point"}
}