{
  "type": "Feature",
  "properties": {
    "addr:full":"6780 Miramar Rd Ste 111 San Diego CA 92121",
    "addr:housenumber":"6780",
    "addr:postcode":"92121",
    "addr:street":"Miramar Rd Ste 111",
    "iso:country":"US",
    "sg:address":"6780 Miramar Rd Ste 111",
    "sg:city":"San Diego",
    "sg:classifiers":[
        {
            "category":"Shopping",
            "subcategory":"Pharmacy",
            "type":"Retail Goods"
        }
    ],
    "sg:phone":"+1 858 653 5274",
    "sg:postcode":"92121",
    "sg:province":"CA",
    "sg:tags":[
        "drugstore"
    ],
    "wof:name":"Downey 1432",
    "wof:placetype":"venue"
},
  "geometry": {"coordinates":[-117.168584,32.878319],"type":"Point"}
}