{
  "type": "Feature",
  "properties": {
    "iso:country":"US",
    "sg:address":"1720 S Hutchins St",
    "sg:city":"Lodi",
    "sg:classifiers":[
        {
            "category":"Real Estate",
            "subcategory":"Real Estate Operator",
            "type":"Services"
        }
    ],
    "sg:phone":"+1 209 334 9345",
    "sg:postcode":"95240",
    "sg:province":"CA",
    "sg:tags":[
        "apartment"
    ],
    "wof:name":"Tokay Villa Apartments",
    "wof:placetype":"venue"
},
  "geometry": {"coordinates":[-121.27883,38.108493],"type":"Point"}
}