{
  "type": "Feature",
  "properties": {
    "iso:country":"US",
    "sg:address":"6518 Summer Breeze Ln",
    "sg:city":"Bakersfield",
    "sg:classifiers":[
        {
            "category":"Shopping",
            "subcategory":"Department Store",
            "type":"Retail Goods"
        }
    ],
    "sg:phone":"+1 661 832 1498",
    "sg:postcode":"93313",
    "sg:province":"CA",
    "sg:tags":[
        "variety"
    ],
    "wof:name":"One Dollar Mart & More",
    "wof:placetype":"venue"
},
  "geometry": {"coordinates":[-119.043876,35.29522],"type":"Point"}
}