{
  "type": "Feature",
  "properties": {
    "iso:country":"US",
    "sg:address":"2348 Bean Creek Rd",
    "sg:city":"Scotts Valley",
    "sg:classifiers":[
        {
            "category":"Wholesale",
            "subcategory":"Medical Equipment & Supplies",
            "type":"Manufacturing & Wholesale Goods"
        }
    ],
    "sg:phone":"+1 831 234 4892",
    "sg:postcode":"95066",
    "sg:province":"CA",
    "sg:tags":[
        "hospital"
    ],
    "wof:name":"ATP Biosciences",
    "wof:placetype":"venue"
},
  "geometry": {"coordinates":[-122.011741,37.079556],"type":"Point"}
}