{
  "type": "Feature",
  "properties": {
    "iso:country":"US",
    "sg:address":"1220 E 60th St",
    "sg:city":"Long Beach",
    "sg:classifiers":[
        {
            "category":"Professional",
            "subcategory":"Accounting & Tax Preparation",
            "type":"Services"
        }
    ],
    "sg:phone":"+1 562 708 7535",
    "sg:postcode":"90805",
    "sg:province":"CA",
    "sg:tags":[
        "return",
        "filing"
    ],
    "wof:name":"Best Income Tax & Accounting",
    "wof:placetype":"venue"
},
  "geometry": {"coordinates":[-118.176486,33.864104],"type":"Point"}
}