{
  "type": "Feature",
  "properties": {
    "addr:full":"601 W Main St Santa Maria CA 93458",
    "addr:housenumber":"601",
    "addr:postcode":"93458",
    "addr:street":"W Main St",
    "iso:country":"US",
    "sg:address":"601 W Main St",
    "sg:city":"Santa Maria",
    "sg:classifiers":[
        {
            "category":"Banks & Credit Unions",
            "subcategory":"Bank",
            "type":"Services"
        }
    ],
    "sg:phone":"+1 805 925 9102",
    "sg:postcode":"93458",
    "sg:province":"CA",
    "sg:tags":[
        "money",
        "transfer"
    ],
    "wof:name":"Envios Flores",
    "wof:placetype":"venue"
},
  "geometry": {"coordinates":[-120.44255099999999,34.953255],"type":"Point"}
}