{
  "type": "Feature",
  "properties": {
    "iso:country":"US",
    "sg:address":"3890 Grand Ave",
    "sg:city":"Chino",
    "sg:classifiers":[
        {
            "category":"Restaurant",
            "type":"Food & Drink"
        }
    ],
    "sg:phone":"+1 909 465 1595",
    "sg:postcode":"91710",
    "sg:province":"CA",
    "sg:tags":[
        "lunch",
        "american",
        "brunch",
        "breakfast"
    ],
    "sg:website":"http://www.mimiscafe.com/",
    "wof:name":"Mimi's Cafe",
    "wof:placetype":"venue"
},
  "geometry": {"coordinates":[-117.71964800000001,33.99909],"type":"Point"}
}