{
  "type": "Feature",
  "properties": {
    "addr:full":"3002 El Camino Real Santa Clara CA 95051",
    "addr:housenumber":"3002",
    "addr:postcode":"95051",
    "addr:street":"El Camino Real",
    "iso:country":"US",
    "sg:address":"3002 El Camino Real",
    "sg:city":"Santa Clara",
    "sg:classifiers":[
        {
            "category":"Personal",
            "subcategory":"Nail Salon",
            "type":"Services"
        }
    ],
    "sg:phone":"+1 408 248 9333",
    "sg:postcode":"95051",
    "sg:province":"CA",
    "wof:name":"Today Nails",
    "wof:placetype":"venue"
},
  "geometry": {"coordinates":[-121.980704,37.352411],"type":"Point"}
}