{
  "type": "Feature",
  "properties": {
    "addr:full":"590 Maureen Ln Pleasant Hill CA 94523",
    "addr:housenumber":"590",
    "addr:postcode":"94523",
    "addr:street":"Maureen Ln",
    "iso:country":"US",
    "sg:address":"590 Maureen Ln",
    "sg:city":"Pleasant Hill",
    "sg:classifiers":[
        {
            "category":"Social Services",
            "subcategory":"Adult Care",
            "type":"Services"
        }
    ],
    "sg:phone":"+1 925 827 0997",
    "sg:postcode":"94523",
    "sg:province":"CA",
    "sg:tags":[
        "home",
        "residential"
    ],
    "wof:name":"Sequoia Care Homes",
    "wof:placetype":"venue"
},
  "geometry": {"coordinates":[-122.079465,37.950769],"type":"Point"}
}