{
  "type": "Feature",
  "properties": {
    "addr:full":"621 E Glenoaks Blvd Glendale CA 91207",
    "addr:housenumber":"621",
    "addr:postcode":"91207",
    "addr:street":"E Glenoaks Blvd",
    "iso:country":"US",
    "sg:address":"621 E Glenoaks Blvd",
    "sg:city":"Glendale",
    "sg:classifiers":[
        {
            "category":"Restaurant",
            "type":"Food & Drink"
        }
    ],
    "sg:phone":"+1 818 247 4021",
    "sg:postcode":"91207",
    "sg:province":"CA",
    "sg:tags":[
        "delicatessen",
        "sandwich"
    ],
    "wof:name":"Glenoaks Deli Gourmet Grocery",
    "wof:placetype":"venue"
},
  "geometry": {"coordinates":[-118.248797,34.15842],"type":"Point"}
}