{
  "type": "Feature",
  "properties": {
    "addr:full":"796 I Ave Coronado CA 92118",
    "addr:housenumber":"796",
    "addr:postcode":"92118",
    "addr:street":"I Ave",
    "iso:country":"US",
    "sg:address":"796 I Ave",
    "sg:city":"Coronado",
    "sg:classifiers":[
        {
            "category":"Banks & Credit Unions",
            "subcategory":"Financial Services",
            "type":"Services"
        }
    ],
    "sg:phone":"+1 619 435 6130",
    "sg:postcode":"92118",
    "sg:province":"CA",
    "sg:tags":[
        "trust",
        "management"
    ],
    "wof:name":"Lighter Family Trust",
    "wof:placetype":"venue"
},
  "geometry": {"coordinates":[-117.184169,32.693012],"type":"Point"}
}