{
  "type": "Feature",
  "properties": {
    "iso:country":"US",
    "sg:address":"380 Tennant Ave",
    "sg:city":"Morgan Hill",
    "sg:classifiers":[
        {
            "category":"Recreation",
            "type":"Entertainment"
        }
    ],
    "sg:phone":"+1 408 779 4797",
    "sg:postcode":"95037",
    "sg:province":"CA",
    "sg:tags":[
        "martial",
        "arts",
        "instruction"
    ],
    "wof:name":"King's Martial Arts",
    "wof:placetype":"venue"
},
  "geometry": {"coordinates":[-121.63633900000001,37.115446],"type":"Point"}
}