{
  "type": "Feature",
  "properties": {
    "addr:full":"4615 N 1st St Fresno CA 93726",
    "addr:housenumber":"4615",
    "addr:postcode":"93726",
    "addr:street":"N 1St St",
    "iso:country":"US",
    "sg:address":"4615 N 1st St",
    "sg:city":"Fresno",
    "sg:classifiers":[
        {
            "category":"Health Services",
            "subcategory":"Doctor",
            "type":"Services"
        }
    ],
    "sg:phone":"+1 559 243 1115",
    "sg:postcode":"93726",
    "sg:province":"CA",
    "sg:tags":[
        "dentist"
    ],
    "wof:name":"Frank J Woo DDS",
    "wof:placetype":"venue"
},
  "geometry": {"coordinates":[-119.772361,36.80319],"type":"Point"}
}