{
  "type": "Feature",
  "properties": {
    "addr:full":"2116 Allston Way Berkeley CA 94704",
    "addr:housenumber":"2116",
    "addr:postcode":"94704",
    "addr:street":"Allston Way",
    "iso:country":"US",
    "sg:address":"2116 Allston Way",
    "sg:city":"Berkeley",
    "sg:classifiers":[
        {
            "category":"Real Estate",
            "subcategory":"Real Estate Operator",
            "type":"Services"
        }
    ],
    "sg:phone":"+1 510 849 2000",
    "sg:postcode":"94704",
    "sg:province":"CA",
    "sg:tags":[
        "apartment"
    ],
    "sg:website":"www.berkeleyapt.com/",
    "wof:name":"Berkeley Apartments - Gaia",
    "wof:placetype":"venue"
},
  "geometry": {"coordinates":[-122.26722700000001,37.869448],"type":"Point"}
}