{
  "type": "Feature",
  "properties": {
    "iso:country":"US",
    "sg:address":"1880 Pleasant Valley Ave # E",
    "sg:city":"Oakland",
    "sg:classifiers":[
        {
            "category":"Building & Trades",
            "subcategory":"Cleaning & Sanitation",
            "type":"Services"
        }
    ],
    "sg:phone":"+1 925 846 1556",
    "sg:postcode":"94611",
    "sg:province":"CA",
    "sg:tags":[
        "home"
    ],
    "wof:name":"Dana's Housekeeping Personnel Service Llc",
    "wof:placetype":"venue"
},
  "geometry": {"coordinates":[-122.248001,37.830502],"type":"Point"}
}