{
  "type": "Feature",
  "properties": {
    "addr:full":"Bush St & Stockton St San Francisco CA 94199",
    "addr:postcode":"94199",
    "addr:street":"Bush St & Stockton St",
    "iso:country":"US",
    "sg:address":"Bush St & Stockton St",
    "sg:city":"San Francisco",
    "sg:classifiers":[
        {
            "category":"Retail",
            "subcategory":"Laundry & Dry Cleaning",
            "type":"Services"
        }
    ],
    "sg:postcode":"94199",
    "sg:province":"CA",
    "wof:name":"Laundromat",
    "wof:placetype":"venue"
},
  "geometry": {"coordinates":[-122.407123,37.79041],"type":"Point"}
}