{
  "type": "Feature",
  "properties": {
    "iso:country":"US",
    "sg:address":"32981 9th St",
    "sg:city":"Winchester",
    "sg:classifiers":[
        {
            "category":"Wholesale",
            "subcategory":"Auto Parts",
            "type":"Manufacturing & Wholesale Goods"
        }
    ],
    "sg:phone":"+1 951 926 9636",
    "sg:postcode":"92596",
    "sg:province":"CA",
    "sg:tags":[
        "transmission"
    ],
    "wof:name":"Kraftswerk",
    "wof:placetype":"venue"
},
  "geometry": {"coordinates":[-117.085916,33.712663],"type":"Point"}
}