{
  "type": "Feature",
  "properties": {
    "addr:full":"1055 N Ashford Ave Rialto CA 92376",
    "addr:housenumber":"1055",
    "addr:postcode":"92376",
    "addr:street":"N Ashford Ave",
    "iso:country":"US",
    "sg:address":"1055 N Ashford Ave",
    "sg:city":"Rialto",
    "sg:classifiers":[
        {
            "category":"Communications",
            "type":"Services"
        }
    ],
    "sg:phone":"+1 909 434 4393",
    "sg:postcode":"92376",
    "sg:province":"CA",
    "wof:name":"Porticom Communications",
    "wof:placetype":"venue"
},
  "geometry": {"coordinates":[-117.404454,34.118609],"type":"Point"}
}