{
  "type": "Feature",
  "properties": {
    "addr:full":"495 S Fairview Ave Goleta CA 93117",
    "addr:housenumber":"495",
    "addr:postcode":"93117",
    "addr:street":"S Fairview Ave",
    "iso:country":"US",
    "sg:address":"495 S Fairview Ave",
    "sg:city":"Goleta",
    "sg:classifiers":[
        {
            "category":"Retail",
            "subcategory":"Repair Shop",
            "type":"Services"
        }
    ],
    "sg:phone":"+1 805 692 1300",
    "sg:postcode":"93117",
    "sg:province":"CA",
    "sg:tags":[
        "engine",
        "aircraft"
    ],
    "wof:name":"GE",
    "wof:placetype":"venue"
},
  "geometry": {"coordinates":[-119.830471,34.426263],"type":"Point"}
}