{
  "type": "Feature",
  "properties": {
    "addr:full":"15126 S Western Ave Gardena CA 90249",
    "addr:housenumber":"15126",
    "addr:postcode":"90249",
    "addr:street":"S Western Ave",
    "iso:country":"US",
    "sg:address":"15126 S Western Ave",
    "sg:city":"Gardena",
    "sg:classifiers":[
        {
            "category":"Restaurant",
            "type":"Food & Drink"
        }
    ],
    "sg:phone":"+1 310 512 6688",
    "sg:postcode":"90249",
    "sg:province":"CA",
    "sg:tags":[
        "seafood"
    ],
    "wof:name":"The Best Crabhouse",
    "wof:placetype":"venue"
},
  "geometry": {"coordinates":[-118.309118,33.893724],"type":"Point"}
}