{
  "type": "Feature",
  "properties": {
    "iso:country":"US",
    "sg:address":"1605 Pacific Coast Hwy",
    "sg:city":"Harbor City",
    "sg:classifiers":[
        {
            "category":"Food & Beverages",
            "subcategory":"Bakery",
            "type":"Retail Goods"
        }
    ],
    "sg:phone":"+1 310 530 8311",
    "sg:postcode":"90710",
    "sg:province":"CA",
    "sg:tags":[
        "doughnut"
    ],
    "wof:name":"Danny's Donut",
    "wof:placetype":"venue"
},
  "geometry": {"coordinates":[-118.307423,33.789543],"type":"Point"}
}