{
  "type": "Feature",
  "properties": {
    "iso:country":"US",
    "sg:address":"21 W Laurel Dr",
    "sg:city":"Salinas",
    "sg:classifiers":[
        {
            "category":"Farming",
            "subcategory":"Farm & Veterinary Services",
            "type":"Manufacturing & Wholesale Goods"
        }
    ],
    "sg:phone":"+1 831 442 1500",
    "sg:postcode":"93906",
    "sg:province":"CA",
    "sg:tags":[
        "harvesting"
    ],
    "wof:name":"B C Harvesting",
    "wof:placetype":"venue"
},
  "geometry": {"coordinates":[-121.65283700000001,36.699144],"type":"Point"}
}