{
  "type": "Feature",
  "properties": {
    "addr:full":"239 S Pacific Ave San Pedro CA 90731",
    "addr:housenumber":"239",
    "addr:postcode":"90731",
    "addr:street":"S Pacific Ave",
    "iso:country":"US",
    "sg:address":"239 S Pacific Ave",
    "sg:city":"San Pedro",
    "sg:classifiers":[
        {
            "category":"Personal",
            "subcategory":"Beauty Salon",
            "type":"Services"
        }
    ],
    "sg:phone":"+1 310 833 4675",
    "sg:postcode":"90731",
    "sg:province":"CA",
    "wof:name":"Rocio's Beauty Salon",
    "wof:placetype":"venue"
},
  "geometry": {"coordinates":[-118.287963,33.741703],"type":"Point"}
}