{
  "type": "Feature",
  "properties": {
    "addr:full":"1107 el Camino Real Arroyo Grande CA 93420",
    "addr:housenumber":"1107",
    "addr:postcode":"93420",
    "addr:street":"El Camino Real",
    "iso:country":"US",
    "sg:address":"1107 el Camino Real",
    "sg:city":"Arroyo Grande",
    "sg:classifiers":[
        {
            "category":"Building & Trades",
            "subcategory":"Landscaping Services",
            "type":"Services"
        }
    ],
    "sg:phone":"+1 805 473 1311",
    "sg:postcode":"93420",
    "sg:province":"CA",
    "sg:tags":[
        "landscape",
        "contractor"
    ],
    "wof:name":"Grass Tech",
    "wof:placetype":"venue"
},
  "geometry": {"coordinates":[-120.597487,35.125468],"type":"Point"}
}