{
  "type": "Feature",
  "properties": {
    "addr:full":"349 E 10th St Lincoln CA 95648",
    "addr:housenumber":"349",
    "addr:postcode":"95648",
    "addr:street":"E 10Th St",
    "iso:country":"US",
    "sg:address":"349 E 10th St",
    "sg:city":"Lincoln",
    "sg:classifiers":[
        {
            "category":"Organizations",
            "subcategory":"Religious Organization",
            "type":"Services"
        }
    ],
    "sg:phone":"+1 916 645 1724",
    "sg:postcode":"95648",
    "sg:province":"CA",
    "sg:website":"http://www.pcg.org",
    "wof:name":"The Pentecostal Church Of God Extension Fund",
    "wof:placetype":"venue"
},
  "geometry": {"coordinates":[-121.281323,38.898634],"type":"Point"}
}