{
  "type": "Feature",
  "properties": {
    "iso:country":"US",
    "sg:address":"Masonic and Oak Between Baker & Stanyan and Oak & Fell",
    "sg:city":"San Francisco",
    "sg:classifiers":[
        {
            "category":"Park",
            "type":"Public Place"
        }
    ],
    "sg:postcode":"94117",
    "sg:province":"CA",
    "sg:website":"www.panhandlepark.blogspot.com",
    "wof:name":"The Panhandle",
    "wof:placetype":"venue"
},
  "geometry": {"coordinates":[-122.445725,37.772105],"type":"Point"}
}