{
  "type": "Feature",
  "properties": {
    "addr:full":"1444 Shattuck Ave Berkeley CA 94709",
    "addr:housenumber":"1444",
    "addr:postcode":"94709",
    "addr:street":"Shattuck Ave",
    "iso:country":"US",
    "sg:address":"1444 Shattuck Ave",
    "sg:city":"Berkeley",
    "sg:classifiers":[
        {
            "category":"Food & Beverages",
            "subcategory":"Groceries & Convenience Stores",
            "type":"Retail Goods"
        }
    ],
    "sg:phone":"+1 510 526 3086",
    "sg:postcode":"94709",
    "sg:province":"CA",
    "sg:website":"www.safeway.com",
    "wof:name":"Safeway",
    "wof:placetype":"venue"
},
  "geometry": {"coordinates":[-122.269436,37.880749],"type":"Point"}
}