{
  "type": "Feature",
  "properties": {
    "addr:full":"34125 Powerhouse Rd Auberry CA 93602",
    "addr:postcode":"34125;93602",
    "addr:street":"Powerhouse Rd",
    "iso:country":"US",
    "sg:address":"34125 Powerhouse Rd",
    "sg:city":"Auberry",
    "sg:classifiers":[
        {
            "category":"Organizations",
            "subcategory":"Religious Organization",
            "type":"Services"
        }
    ],
    "sg:phone":"+1 559 855 8880",
    "sg:postcode":"93602",
    "sg:province":"CA",
    "sg:tags":[
        "church"
    ],
    "wof:name":"Auberry Seventh-Day Adventist",
    "wof:placetype":"venue"
},
  "geometry": {"coordinates":[-118.95590300000001,37.034211],"type":"Point"}
}