{
  "type": "Feature",
  "properties": {
    "iso:country":"US",
    "sg:address":"8425 Rovana Cir",
    "sg:city":"Sacramento",
    "sg:classifiers":[
        {
            "category":"Wholesale",
            "subcategory":"Furniture",
            "type":"Manufacturing & Wholesale Goods"
        }
    ],
    "sg:phone":"+1 916 387 6612",
    "sg:postcode":"95828",
    "sg:province":"CA",
    "wof:name":"West Coast Installation",
    "wof:placetype":"venue"
},
  "geometry": {"coordinates":[-121.392402,38.507102],"type":"Point"}
}