{
  "type": "Feature",
  "properties": {
    "addr:full":"15706 Pomerado Rd Poway CA 92064",
    "addr:housenumber":"15706",
    "addr:postcode":"ca 92064",
    "addr:street":"Pomerado Rd",
    "iso:country":"US",
    "sg:address":"15706 Pomerado Rd",
    "sg:city":"Poway",
    "sg:classifiers":[
        {
            "category":"Health Services",
            "subcategory":"Doctor",
            "type":"Services"
        }
    ],
    "sg:phone":"+1 858 674 4462",
    "sg:postcode":"92064",
    "sg:province":"CA",
    "sg:tags":[
        "physician",
        "surgeon"
    ],
    "wof:name":"Robert F Lasting MD",
    "wof:placetype":"venue"
},
  "geometry": {"coordinates":[-117.05801599999999,33.003716],"type":"Point"}
}