{
  "type": "Feature",
  "properties": {
    "addr:full":"2033 N Main St Walnut Creek CA 94596",
    "addr:housenumber":"2033",
    "addr:postcode":"94596",
    "addr:street":"N Main St",
    "iso:country":"US",
    "sg:address":"2033 N Main St",
    "sg:city":"Walnut Creek",
    "sg:classifiers":[
        {
            "category":"Professional",
            "subcategory":"Lawyer & Legal Services",
            "type":"Services"
        }
    ],
    "sg:phone":"+1 925 416 8800",
    "sg:postcode":"94596",
    "sg:province":"CA",
    "sg:tags":[
        "attorney"
    ],
    "wof:name":"Pandell Novich & Borsuk",
    "wof:placetype":"venue"
},
  "geometry": {"coordinates":[-122.06485600000001,37.907506],"type":"Point"}
}