{
  "type": "Feature",
  "properties": {
    "addr:full":"730 W Chapman Ave Orange CA 92868",
    "addr:housenumber":"730",
    "addr:postcode":"92868",
    "addr:street":"W Chapman Ave",
    "iso:country":"US",
    "sg:address":"730 W Chapman Ave",
    "sg:city":"Orange",
    "sg:classifiers":[
        {
            "category":"Autos & Motor Vehicles",
            "subcategory":"Automobile Sales",
            "type":"Retail Goods"
        }
    ],
    "sg:phone":"+1 714 288 9131",
    "sg:postcode":"92868",
    "sg:province":"CA",
    "sg:tags":[
        "car",
        "dealer"
    ],
    "wof:name":"Best Deal Auto Brokers",
    "wof:placetype":"venue"
},
  "geometry": {"coordinates":[-117.86179,33.787948],"type":"Point"}
}