{
  "type": "Feature",
  "properties": {
    "addr:full":"2300 Alessandro Dr Ventura CA 93001",
    "addr:housenumber":"2300",
    "addr:postcode":"93001",
    "addr:street":"Alessandro Dr",
    "iso:country":"US",
    "sg:address":"2300 Alessandro Dr",
    "sg:city":"Ventura",
    "sg:classifiers":[
        {
            "category":"Insurance",
            "subcategory":"Insurance Agent",
            "type":"Services"
        }
    ],
    "sg:phone":"+1 805 652 6400",
    "sg:postcode":"93001",
    "sg:province":"CA",
    "wof:name":"Infinity Insurance Co",
    "wof:placetype":"venue"
},
  "geometry": {"coordinates":[-119.267357,34.265298],"type":"Point"}
}