{
  "type": "Feature",
  "properties": {
    "iso:country":"US",
    "sg:address":"1112 College Ave",
    "sg:city":"Santa Rosa",
    "sg:classifiers":[
        {
            "category":"Health Services",
            "subcategory":"Health Practitioner",
            "type":"Services"
        }
    ],
    "sg:phone":"+1 707 576 0128",
    "sg:postcode":"95404",
    "sg:province":"CA",
    "sg:tags":[
        "hypnotist"
    ],
    "wof:name":"Hypnosis Care Ctr",
    "wof:placetype":"venue"
},
  "geometry": {"coordinates":[-122.707441,38.445287],"type":"Point"}
}