{
  "type": "Feature",
  "properties": {
    "iso:country":"US",
    "sg:address":"1322 el Camino Real",
    "sg:city":"Belmont",
    "sg:classifiers":[
        {
            "category":"Personal",
            "subcategory":"Beauty Salon",
            "type":"Services"
        }
    ],
    "sg:phone":"+1 650 593 1912",
    "sg:postcode":"94002",
    "sg:province":"CA",
    "wof:name":"Cathy Green For Hair",
    "wof:placetype":"venue"
},
  "geometry": {"coordinates":[-122.273729,37.518488],"type":"Point"}
}