{
  "type": "Feature",
  "properties": {
    "addr:full":"2043 Gill Port Ln Walnut Creek CA 94598",
    "addr:housenumber":"2043",
    "addr:postcode":"94598",
    "addr:street":"Gill Port Ln",
    "iso:country":"US",
    "sg:address":"2043 Gill Port Ln",
    "sg:city":"Walnut Creek",
    "sg:classifiers":[
        {
            "category":"Manufacturing",
            "subcategory":"Rubber & Plastics",
            "type":"Manufacturing & Wholesale Goods"
        }
    ],
    "sg:phone":"+1 925 256 0481",
    "sg:postcode":"94598",
    "sg:province":"CA",
    "sg:tags":[
        "product",
        "fabricated",
        "mfg"
    ],
    "wof:name":"Neoprene Concepts Internatl",
    "wof:placetype":"venue"
},
  "geometry": {"coordinates":[-122.04239699999999,37.932013],"type":"Point"}
}