{
  "type": "Feature",
  "properties": {
    "addr:full":"997 Brandon Ave Simi Valley CA 93065",
    "addr:housenumber":"997",
    "addr:postcode":"93065",
    "addr:street":"Brandon Ave",
    "iso:country":"US",
    "sg:address":"997 Brandon Ave",
    "sg:city":"Simi Valley",
    "sg:classifiers":[
        {
            "category":"Building & Trades",
            "subcategory":"Construction",
            "type":"Services"
        }
    ],
    "sg:phone":"+1 805 522 2407",
    "sg:postcode":"93065",
    "sg:province":"CA",
    "sg:tags":[
        "residential",
        "contractor",
        "commercial",
        "general"
    ],
    "wof:name":"Carlito Construction Inc",
    "wof:placetype":"venue"
},
  "geometry": {"coordinates":[-118.752314,34.257188],"type":"Point"}
}