{
  "type": "Feature",
  "properties": {
    "addr:full":"417 Menker Ave San Jose CA 95128",
    "addr:housenumber":"417",
    "addr:postcode":"95128",
    "addr:street":"Menker Ave",
    "iso:country":"US",
    "sg:address":"417 Menker Ave",
    "sg:city":"San Jose",
    "sg:classifiers":[
        {
            "category":"Education",
            "subcategory":"Special Training",
            "type":"Public Place"
        }
    ],
    "sg:phone":"+1 408 289 9469",
    "sg:postcode":"95128",
    "sg:province":"CA",
    "sg:tags":[
        "instruction",
        "music"
    ],
    "wof:name":"Andrade's Music Studio",
    "wof:placetype":"venue"
},
  "geometry": {"coordinates":[-121.921736,37.321882],"type":"Point"}
}