{
  "type": "Feature",
  "properties": {
    "addr:full":"425 E Pico Blvd Los Angeles CA 90015",
    "addr:housenumber":"425",
    "addr:postcode":"90015",
    "addr:street":"E Pico Blvd",
    "iso:country":"US",
    "sg:address":"425 E Pico Blvd",
    "sg:city":"Los Angeles",
    "sg:classifiers":[
        {
            "category":"Wholesale",
            "subcategory":"Apparel",
            "type":"Manufacturing & Wholesale Goods"
        }
    ],
    "sg:phone":"+1 213 749 8906",
    "sg:postcode":"90015",
    "sg:province":"CA",
    "sg:tags":[
        "infant",
        "wear"
    ],
    "wof:name":"Pinnochio",
    "wof:placetype":"venue"
},
  "geometry": {"coordinates":[-118.256134,34.034045],"type":"Point"}
}