{
  "type": "Feature",
  "properties": {
    "addr:full":"20301 Ventura Blvd Woodland Hills CA 91364",
    "addr:housenumber":"20301",
    "addr:postcode":"91364",
    "addr:street":"Ventura Blvd",
    "iso:country":"US",
    "sg:address":"20301 Ventura Blvd",
    "sg:city":"Woodland Hills",
    "sg:classifiers":[
        {
            "category":"Travel",
            "subcategory":"Travel Agent",
            "type":"Entertainment"
        }
    ],
    "sg:phone":"+1 818 349 7676",
    "sg:postcode":"91364",
    "sg:province":"CA",
    "sg:tags":[
        "agency"
    ],
    "wof:name":"Born To Travel",
    "wof:placetype":"venue"
},
  "geometry": {"coordinates":[-118.57745300000001,34.168591],"type":"Point"}
}