{
  "type": "Feature",
  "properties": {
    "iso:country":"US",
    "sg:address":"6180 Elenor St",
    "sg:city":"Riverside",
    "sg:classifiers":[
        {
            "category":"Building & Trades",
            "subcategory":"Construction",
            "type":"Services"
        }
    ],
    "sg:phone":"+1 951 784 1329",
    "sg:postcode":"92506",
    "sg:province":"CA",
    "sg:tags":[
        "roofing",
        "contractor"
    ],
    "wof:name":"Western Roofing",
    "wof:placetype":"venue"
},
  "geometry": {"coordinates":[-117.390553,33.959649],"type":"Point"}
}