{
  "type": "Feature",
  "properties": {
    "addr:full":"350 N Valencia Blvd Woodlake CA 93286",
    "addr:housenumber":"350",
    "addr:postcode":"93286",
    "addr:street":"N Valencia Blvd",
    "iso:country":"US",
    "sg:address":"350 N Valencia Blvd",
    "sg:city":"Woodlake",
    "sg:classifiers":[
        {
            "category":"Government",
            "subcategory":"Court House",
            "type":"Public Place"
        }
    ],
    "sg:phone":"+1 559 564 8969",
    "sg:postcode":"93286",
    "sg:province":"CA",
    "sg:tags":[
        "state",
        "system"
    ],
    "wof:name":"Tulare Cnty Justice Court/Wood",
    "wof:placetype":"venue"
},
  "geometry": {"coordinates":[-119.098851,36.418241],"type":"Point"}
}