{
  "type": "Feature",
  "properties": {
    "iso:country":"US",
    "sg:address":"13130 Penny Ln",
    "sg:city":"Yucaipa",
    "sg:classifiers":[
        {
            "category":"Professional",
            "subcategory":"Detective & Security Services",
            "type":"Services"
        }
    ],
    "sg:phone":"+1 951 233 0378",
    "sg:postcode":"92399",
    "sg:province":"CA",
    "sg:tags":[
        "guard",
        "patrol"
    ],
    "wof:name":"Light Walker Security",
    "wof:placetype":"venue"
},
  "geometry": {"coordinates":[-117.03998199999999,34.015328],"type":"Point"}
}