{
  "type": "Feature",
  "properties": {
    "iso:country":"US",
    "sg:address":"1941 Wave Pl",
    "sg:city":"San Jose",
    "sg:classifiers":[
        {
            "category":"Travel",
            "subcategory":"Travel Agent",
            "type":"Entertainment"
        }
    ],
    "sg:phone":"+1 408 254 1587",
    "sg:postcode":"95133",
    "sg:province":"CA",
    "sg:tags":[
        "agency"
    ],
    "wof:name":"Blue Sky Travel",
    "wof:placetype":"venue"
},
  "geometry": {"coordinates":[-121.866862,37.375784],"type":"Point"}
}