{
  "type": "Feature",
  "properties": {
    "addr:full":"1236 Balsam Way Vacaville CA 95687",
    "addr:housenumber":"1236",
    "addr:postcode":"95687",
    "addr:street":"Balsam Way",
    "iso:country":"US",
    "sg:address":"1236 Balsam Way",
    "sg:city":"Vacaville",
    "sg:classifiers":[
        {
            "category":"Professional",
            "type":"Services"
        }
    ],
    "sg:phone":"+1 707 447 4263",
    "sg:postcode":"95687",
    "sg:province":"CA",
    "wof:name":"Jobmatch Inc",
    "wof:placetype":"venue"
},
  "geometry": {"coordinates":[-121.988179,38.340202],"type":"Point"}
}