{
  "type": "Feature",
  "properties": {
    "addr:full":"2319 Merced Ave South El Monte CA 91733",
    "addr:housenumber":"2319",
    "addr:postcode":"91733",
    "addr:street":"Merced Ave",
    "iso:country":"US",
    "sg:address":"2319 Merced Ave",
    "sg:city":"South El Monte",
    "sg:classifiers":[
        {
            "category":"Wholesale",
            "subcategory":"Non-durable Goods",
            "type":"Manufacturing & Wholesale Goods"
        }
    ],
    "sg:phone":"+1 626 350 8271",
    "sg:postcode":"91733",
    "sg:province":"CA",
    "wof:name":"Chen C Fang",
    "wof:placetype":"venue"
},
  "geometry": {"coordinates":[-118.051354,34.052567],"type":"Point"}
}