{
  "type": "Feature",
  "properties": {
    "addr:full":"871 Shadowgrove St Brea CA 92821",
    "addr:housenumber":"871",
    "addr:postcode":"92821",
    "addr:street":"Shadowgrove St",
    "iso:country":"US",
    "sg:address":"871 Shadowgrove St",
    "sg:city":"Brea",
    "sg:classifiers":[
        {
            "category":"Autos & Motor Vehicles",
            "subcategory":"Automobile Sales",
            "type":"Retail Goods"
        }
    ],
    "sg:phone":"+1 714 529 3208",
    "sg:postcode":"92821",
    "sg:province":"CA",
    "sg:tags":[
        "dealers-used",
        "used",
        "cars-wholesale",
        "car"
    ],
    "wof:name":"J&J Automotive",
    "wof:placetype":"venue"
},
  "geometry": {"coordinates":[-117.909592,33.936055],"type":"Point"}
}