{
  "type": "Feature",
  "properties": {
    "addr:full":"9017 Arrow Rte Rancho Cucamonga CA 91730",
    "addr:housenumber":"9017",
    "addr:postcode":"91730",
    "addr:street":"Arrow Rte",
    "iso:country":"US",
    "sg:address":"9017 Arrow Rte",
    "sg:city":"Rancho Cucamonga",
    "sg:classifiers":[
        {
            "category":"Home & Garden",
            "subcategory":"Building Materials",
            "type":"Retail Goods"
        }
    ],
    "sg:phone":"+1 909 945 9891",
    "sg:postcode":"91730",
    "sg:province":"CA",
    "sg:tags":[
        "door"
    ],
    "sg:website":"www.randrgaragedoor.com",
    "wof:name":"R & R Garage Door Svc",
    "wof:placetype":"venue"
},
  "geometry": {"coordinates":[-117.609497,34.099283],"type":"Point"}
}