{
  "type": "Feature",
  "properties": {
    "addr:full":"8518 Bennington Way Sacramento CA 95826",
    "addr:housenumber":"8518",
    "addr:postcode":"95826",
    "addr:street":"Bennington Way",
    "iso:country":"US",
    "sg:address":"8518 Bennington Way",
    "sg:city":"Sacramento",
    "sg:classifiers":[
        {
            "category":"Manufacturing",
            "subcategory":"Printing",
            "type":"Manufacturing & Wholesale Goods"
        }
    ],
    "sg:phone":"+1 916 383 8963",
    "sg:postcode":"95826",
    "sg:province":"CA",
    "sg:tags":[
        "book"
    ],
    "wof:name":"Simien & Simien",
    "wof:placetype":"venue"
},
  "geometry": {"coordinates":[-121.391735,38.554639],"type":"Point"}
}