{
  "type": "Feature",
  "properties": {
    "addr:full":"1394 Heckman Way San Jose CA 95129",
    "addr:housenumber":"1394",
    "addr:postcode":"95129",
    "addr:street":"Heckman Way",
    "iso:country":"US",
    "sg:address":"1394 Heckman Way",
    "sg:city":"San Jose",
    "sg:classifiers":[
        {
            "category":"Health Services",
            "subcategory":"Health Practitioner",
            "type":"Services"
        }
    ],
    "sg:phone":"+1 408 257 8347",
    "sg:postcode":"95129",
    "sg:province":"CA",
    "sg:tags":[
        "nutritionist"
    ],
    "wof:name":"Vitan",
    "wof:placetype":"venue"
},
  "geometry": {"coordinates":[-122.005352,37.297606],"type":"Point"}
}