{
  "type": "Feature",
  "properties": {
    "addr:full":"1920 Shadowridge Dr # 109 Vista CA 92081",
    "addr:housenumber":"1920",
    "addr:postcode":"92081",
    "addr:street":"Shadowridge Dr # 109",
    "iso:country":"US",
    "sg:address":"1920 Shadowridge Dr # 109",
    "sg:city":"Vista",
    "sg:classifiers":[
        {
            "category":"Insurance",
            "subcategory":"Insurance Agent",
            "type":"Services"
        },
        {
            "category":"Insurance",
            "subcategory":"Hazard Insurance",
            "type":"Services"
        },
        {
            "category":"Insurance",
            "subcategory":"Health Insurance",
            "type":"Services"
        }
    ],
    "sg:phone":"+1 760 727 9876",
    "sg:postcode":"92081",
    "sg:province":"CA",
    "sg:tags":[
        "employee",
        "auto",
        "benefit",
        "commercial",
        "business"
    ],
    "sg:website":"http://www.farmersagent.com/scrouch",
    "wof:name":"Farmers Insurance",
    "wof:placetype":"venue"
},
  "geometry": {"coordinates":[-117.24918599999999,33.157582],"type":"Point"}
}