{
  "type": "Feature",
  "properties": {
    "addr:full":"1665 S Rancho Santa Fe Rd San Marcos CA 92078",
    "addr:housenumber":"1665",
    "addr:postcode":"92078",
    "addr:street":"S Rancho Santa Fe Rd",
    "iso:country":"US",
    "sg:address":"1665 S Rancho Santa Fe Rd",
    "sg:city":"San Marcos",
    "sg:classifiers":[
        {
            "category":"Recreation",
            "type":"Entertainment"
        }
    ],
    "sg:phone":"+1 760 942 3319",
    "sg:postcode":"92078",
    "sg:province":"CA",
    "sg:tags":[
        "course",
        "golf"
    ],
    "wof:name":"Moonlight Glassing Co",
    "wof:placetype":"venue"
},
  "geometry": {"coordinates":[-117.22404899999999,33.11821],"type":"Point"}
}