{
  "type": "Feature",
  "properties": {
    "iso:country":"US",
    "sg:address":"436 San Mateo Ave",
    "sg:city":"San Bruno",
    "sg:classifiers":[
        {
            "category":"Restaurant",
            "type":"Food & Drink"
        }
    ],
    "sg:menulink":"http://www.allmenus.com/ca/south-san-francisco/209881-mings-chinese-restaurant/menu/",
    "sg:phone":"+1 650 588 2375",
    "sg:postcode":"94066",
    "sg:province":"CA",
    "sg:tags":[
        "asian",
        "chinese"
    ],
    "wof:name":"Ming's Chinese Restaurant",
    "wof:placetype":"venue"
},
  "geometry": {"coordinates":[-122.41098700000001,37.622425],"type":"Point"}
}