{
  "type": "Feature",
  "properties": {
    "iso:country":"US",
    "sg:address":"4007 30th St",
    "sg:city":"San Diego",
    "sg:classifiers":[
        {
            "category":"Food & Beverages",
            "subcategory":"Bakery",
            "type":"Retail Goods"
        }
    ],
    "sg:phone":"+1 619 584 2148",
    "sg:postcode":"92104",
    "sg:province":"CA",
    "sg:tags":[
        "doughnut"
    ],
    "wof:name":"Donut Factory",
    "wof:placetype":"venue"
},
  "geometry": {"coordinates":[-117.130083,32.752095],"type":"Point"}
}