{
  "type": "Feature",
  "properties": {
    "addr:full":"1926 Petrel Pl Ventura CA 93003",
    "addr:housenumber":"1926",
    "addr:postcode":"93003",
    "addr:street":"Petrel Pl",
    "iso:country":"US",
    "sg:address":"1926 Petrel Pl",
    "sg:city":"Ventura",
    "sg:classifiers":[
        {
            "category":"Professional",
            "type":"Services"
        }
    ],
    "sg:phone":"+1 805 658 6891",
    "sg:postcode":"93003",
    "sg:province":"CA",
    "wof:name":"Ida Way Burkes",
    "wof:placetype":"venue"
},
  "geometry": {"coordinates":[-119.20119800000001,34.259141],"type":"Point"}
}