{
  "type": "Feature",
  "properties": {
    "iso:country":"US",
    "sg:address":"430 Orange St",
    "sg:city":"Oakland",
    "sg:classifiers":[
        {
            "category":"Manufacturing",
            "subcategory":"Retail Goods",
            "type":"Manufacturing & Wholesale Goods"
        }
    ],
    "sg:phone":"+1 510 444 0650",
    "sg:postcode":"94610",
    "sg:province":"CA",
    "sg:tags":[
        "product",
        "mfg"
    ],
    "wof:name":"Mannequin Madness",
    "wof:placetype":"venue"
},
  "geometry": {"coordinates":[-122.25409000000001,37.818135],"type":"Point"}
}