{
  "type": "Feature",
  "properties": {
    "addr:full":"SOMA San Francisco CA 94105",
    "addr:postcode":"94105",
    "iso:country":"US",
    "sg:address":"SOMA",
    "sg:city":"San Francisco",
    "sg:classifiers":[
        {
            "category":"Professional",
            "subcategory":"Art Services",
            "type":"Services"
        }
    ],
    "sg:phone":"+1 415 216 7447",
    "sg:postcode":"94105",
    "sg:province":"CA",
    "sg:tags":[
        "graphic",
        "design"
    ],
    "sg:website":"www.chantal.ws",
    "wof:name":"Chantal Design Solutions",
    "wof:placetype":"venue"
},
  "geometry": {"coordinates":[-122.40054000000001,37.777453],"type":"Point"}
}