{
  "type": "Feature",
  "properties": {
    "iso:country":"US",
    "sg:address":"1191 E Walnut St Ste 104",
    "sg:city":"Pasadena",
    "sg:classifiers":[
        {
            "category":"Health Services",
            "subcategory":"Clinic",
            "type":"Services"
        }
    ],
    "sg:phone":"+1 818 568 6982",
    "sg:postcode":"91106",
    "sg:province":"CA",
    "sg:tags":[
        "counseling",
        "mental"
    ],
    "sg:website":"www.bodymindpsych.com",
    "wof:name":"Chris Tickner, PhDc, MFT",
    "wof:placetype":"venue"
},
  "geometry": {"coordinates":[-118.125923,34.149841],"type":"Point"}
}