{
  "type": "Feature",
  "properties": {
    "iso:country":"US",
    "sg:address":"1712 W Belmont Ave",
    "sg:city":"Fresno",
    "sg:classifiers":[
        {
            "category":"Retail",
            "subcategory":"Repair Shop",
            "type":"Services"
        }
    ],
    "sg:phone":"+1 559 252 6142",
    "sg:postcode":"93728",
    "sg:province":"CA",
    "sg:tags":[
        "lock",
        "locksmith"
    ],
    "wof:name":"A-1 Key Svc",
    "wof:placetype":"venue"
},
  "geometry": {"coordinates":[-119.832407,36.750304],"type":"Point"}
}