{
  "type": "Feature",
  "properties": {
    "iso:country":"US",
    "sg:address":"914 E Success Dr",
    "sg:city":"Porterville",
    "sg:classifiers":[
        {
            "category":"Home & Garden",
            "subcategory":"Carpets & Floor Coverings",
            "type":"Retail Goods"
        }
    ],
    "sg:phone":"+1 559 781 2092",
    "sg:postcode":"93257",
    "sg:province":"CA",
    "sg:tags":[
        "dealer",
        "rug"
    ],
    "wof:name":"Holbrooks Sales",
    "wof:placetype":"venue"
},
  "geometry": {"coordinates":[-118.996608,36.05895],"type":"Point"}
}