{
  "type": "Feature",
  "properties": {
    "addr:full":"4080 Attawa Ave Sacramento CA 95822",
    "addr:housenumber":"4080",
    "addr:postcode":"95822",
    "addr:street":"Attawa Ave",
    "iso:country":"US",
    "sg:address":"4080 Attawa Ave",
    "sg:city":"Sacramento",
    "sg:classifiers":[
        {
            "category":"Building & Trades",
            "subcategory":"Landscaping Services",
            "type":"Services"
        }
    ],
    "sg:phone":"+1 916 451 6499",
    "sg:postcode":"95822",
    "sg:province":"CA",
    "sg:tags":[
        "landscape",
        "contractor"
    ],
    "wof:name":"Stathos Landscape Maintenance",
    "wof:placetype":"venue"
},
  "geometry": {"coordinates":[-121.48537,38.538238],"type":"Point"}
}