{
  "type": "Feature",
  "properties": {
    "iso:country":"US",
    "sg:address":"28200 Highway 189",
    "sg:city":"Lake Arrowhead",
    "sg:classifiers":[
        {
            "category":"Banks & Credit Unions",
            "subcategory":"Bank",
            "type":"Services"
        }
    ],
    "sg:phone":"+1 909 337 5302",
    "sg:postcode":"92352",
    "sg:province":"CA",
    "wof:name":"Bank of America",
    "wof:placetype":"venue"
},
  "geometry": {"coordinates":[-117.189915,34.249443],"type":"Point"}
}