{
  "type": "Feature",
  "properties": {
    "iso:country":"US",
    "sg:address":"1110 Colorado Blvd",
    "sg:city":"Los Angeles",
    "sg:classifiers":[
        {
            "category":"Personal",
            "subcategory":"Beauty Salon",
            "type":"Services"
        },
        {
            "category":"Personal",
            "subcategory":"Day Spa",
            "type":"Services"
        }
    ],
    "sg:phone":"+1 323 257 1623",
    "sg:postcode":"90041",
    "sg:province":"CA",
    "sg:tags":[
        "hair"
    ],
    "sg:website":"www.bellamiasalonandspa.com",
    "wof:name":"Bella Mia Salon And Spa",
    "wof:placetype":"venue"
},
  "geometry": {"coordinates":[-118.190101,34.137182],"type":"Point"}
}