{
  "type": "Feature",
  "properties": {
    "addr:full":"31111 Lodge Rd Auberry CA 93602",
    "addr:housenumber":"31111",
    "addr:postcode":"93602",
    "addr:street":"Lodge Rd",
    "iso:country":"US",
    "sg:address":"31111 Lodge Rd",
    "sg:city":"Auberry",
    "sg:classifiers":[
        {
            "category":"Professional",
            "subcategory":"Engineering",
            "type":"Services"
        }
    ],
    "sg:phone":"+1 559 855 8811",
    "sg:postcode":"93602",
    "sg:province":"CA",
    "sg:tags":[
        "general",
        "contractor"
    ],
    "wof:name":"Mountain Movers Inc",
    "wof:placetype":"venue"
},
  "geometry": {"coordinates":[-119.49067700000001,37.043961],"type":"Point"}
}