{
  "type": "Feature",
  "properties": {
    "iso:country":"US",
    "sg:address":"841 E Washington Ave",
    "sg:city":"Santa Ana",
    "sg:classifiers":[
        {
            "category":"Building & Trades",
            "subcategory":"Construction",
            "type":"Services"
        }
    ],
    "sg:phone":"+1 714 564 1130",
    "sg:postcode":"92701",
    "sg:province":"CA",
    "sg:tags":[
        "heavy",
        "foundation",
        "civil",
        "air",
        "contractor",
        "structure"
    ],
    "wof:name":"Macro-Z-Technology",
    "wof:placetype":"venue"
},
  "geometry": {"coordinates":[-117.85900100000001,33.755699],"type":"Point"}
}