{
  "type": "Feature",
  "properties": {
    "iso:country":"US",
    "sg:address":"6301 Bellaire Ave",
    "sg:city":"North Hollywood",
    "sg:classifiers":[
        {
            "category":"Wholesale",
            "subcategory":"Non-durable Goods",
            "type":"Manufacturing & Wholesale Goods"
        }
    ],
    "sg:phone":"+1 818 762 9886",
    "sg:postcode":"91606",
    "sg:province":"CA",
    "wof:name":"Sterling Distributors",
    "wof:placetype":"venue"
},
  "geometry": {"coordinates":[-118.409494,34.184662],"type":"Point"}
}