{
  "type": "Feature",
  "properties": {
    "iso:country":"US",
    "sg:address":"1121 E Colorado St",
    "sg:city":"Glendale",
    "sg:classifiers":[
        {
            "category":"Professional",
            "subcategory":"Computer Services",
            "type":"Services"
        }
    ],
    "sg:phone":"+1 818 545 8165",
    "sg:postcode":"91205",
    "sg:province":"CA",
    "sg:tags":[
        "graphics"
    ],
    "wof:name":"Synphony In Color",
    "wof:placetype":"venue"
},
  "geometry": {"coordinates":[-118.239981,34.142717],"type":"Point"}
}