{
  "type": "Feature",
  "properties": {
    "addr:full":"23639 Breezy Meadow Ct Moreno Valley CA 92557",
    "addr:housenumber":"23639",
    "addr:postcode":"92557",
    "addr:street":"Breezy Meadow Ct",
    "iso:country":"US",
    "sg:address":"23639 Breezy Meadow Ct",
    "sg:city":"Moreno Valley",
    "sg:classifiers":[
        {
            "category":"Professional",
            "type":"Services"
        }
    ],
    "sg:phone":"+1 951 242 0868",
    "sg:postcode":"92557",
    "sg:province":"CA",
    "wof:name":"Heart & Sole Transportati",
    "wof:placetype":"venue"
},
  "geometry": {"coordinates":[-117.25199600000001,33.961362],"type":"Point"}
}