{
  "type": "Feature",
  "properties": {
    "addr:full":"474 W Arrow Hwy San Dimas CA 91773",
    "addr:housenumber":"474",
    "addr:postcode":"91773",
    "addr:street":"W Arrow Hwy",
    "iso:country":"US",
    "sg:address":"474 W Arrow Hwy",
    "sg:city":"San Dimas",
    "sg:classifiers":[
        {
            "category":"Manufacturing",
            "subcategory":"Motor Vehicles & Parts",
            "type":"Manufacturing & Wholesale Goods"
        }
    ],
    "sg:phone":"+1 909 592 8807",
    "sg:postcode":"91773",
    "sg:province":"CA",
    "sg:tags":[
        "mfg"
    ],
    "wof:name":"California Horsepower & Prfmce",
    "wof:placetype":"venue"
},
  "geometry": {"coordinates":[-117.81407,34.102853],"type":"Point"}
}