{
  "type": "Feature",
  "properties": {
    "iso:country":"US",
    "sg:address":"4124 W Barnhart Rd",
    "sg:city":"Turlock",
    "sg:classifiers":[
        {
            "category":"Real Estate",
            "subcategory":"Real Estate Operator",
            "type":"Services"
        }
    ],
    "sg:phone":"+1 209 632 2478",
    "sg:postcode":"95382",
    "sg:province":"CA",
    "sg:tags":[
        "mobile",
        "home",
        "community"
    ],
    "wof:name":"Countryside Mobile Home Estate",
    "wof:placetype":"venue"
},
  "geometry": {"coordinates":[-120.899057,37.543949],"type":"Point"}
}