{
  "type": "Feature",
  "properties": {
    "iso:country":"US",
    "sg:address":"2605 Sherwood Ave",
    "sg:city":"Modesto",
    "sg:classifiers":[
        {
            "category":"Building & Trades",
            "subcategory":"Pest Control",
            "type":"Services"
        }
    ],
    "sg:phone":"+1 209 522 1475",
    "sg:postcode":"95350",
    "sg:province":"CA",
    "wof:name":"Harmon Pest Control",
    "wof:placetype":"venue"
},
  "geometry": {"coordinates":[-120.998723,37.679124],"type":"Point"}
}