{
  "type": "Feature",
  "properties": {
    "iso:country":"US",
    "sg:address":"950 Clement St",
    "sg:city":"San Francisco",
    "sg:classifiers":[
        {
            "category":"Education",
            "subcategory":"School",
            "type":"Public Place"
        }
    ],
    "sg:phone":"+1 415 221 1218",
    "sg:postcode":"94118",
    "sg:province":"CA",
    "wof:name":"Olympia Institute",
    "wof:placetype":"venue"
},
  "geometry": {"coordinates":[-122.469345,37.782802],"type":"Point"}
}