{
  "type": "Feature",
  "properties": {
    "iso:country":"US",
    "sg:address":"3928 N Blackstone Ave",
    "sg:city":"Fresno",
    "sg:classifiers":[
        {
            "category":"Retail",
            "subcategory":"Auto Repair",
            "type":"Services"
        }
    ],
    "sg:phone":"+1 559 225 8473",
    "sg:postcode":"93726",
    "sg:province":"CA",
    "sg:tags":[
        "wheel",
        "axle",
        "alignment"
    ],
    "wof:name":"Fresno Custom Wheels & Tires",
    "wof:placetype":"venue"
},
  "geometry": {"coordinates":[-119.790426,36.789934],"type":"Point"}
}