{
  "type": "Feature",
  "properties": {
    "iso:country":"US",
    "sg:address":"11625 Venture Dr",
    "sg:city":"Mira Loma",
    "sg:classifiers":[
        {
            "category":"Wholesale",
            "subcategory":"Books, Periodicals, & Newspapers",
            "type":"Manufacturing & Wholesale Goods"
        }
    ],
    "sg:phone":"+1 951 361 4000",
    "sg:postcode":"91752",
    "sg:province":"CA",
    "sg:tags":[
        "distributor"
    ],
    "wof:name":"Borders Group Inc",
    "wof:placetype":"venue"
},
  "geometry": {"coordinates":[-117.538431,34.029793],"type":"Point"}
}