{
  "type": "Feature",
  "properties": {
    "addr:full":"909 Electric Ave Seal Beach CA 90740",
    "addr:housenumber":"909",
    "addr:postcode":"90740",
    "addr:street":"Electric Ave",
    "iso:country":"US",
    "sg:address":"909 Electric Ave",
    "sg:city":"Seal Beach",
    "sg:classifiers":[
        {
            "category":"Professional",
            "subcategory":"Engineering",
            "type":"Services"
        }
    ],
    "sg:phone":"+1 562 493 0158",
    "sg:postcode":"90740",
    "sg:province":"CA",
    "sg:tags":[
        "engineer"
    ],
    "sg:website":"www.dtsweb.com",
    "wof:name":"Diversified Technical Systems",
    "wof:placetype":"venue"
},
  "geometry": {"coordinates":[-118.102946,33.742342],"type":"Point"}
}