{
  "type": "Feature",
  "properties": {
    "addr:full":"817 16th St Santa Monica CA 90403",
    "addr:housenumber":"817",
    "addr:postcode":"90403",
    "addr:street":"16Th St",
    "iso:country":"US",
    "sg:address":"817 16th St",
    "sg:city":"Santa Monica",
    "sg:classifiers":[
        {
            "category":"Professional",
            "type":"Services"
        }
    ],
    "sg:phone":"+1 310 453 2764",
    "sg:postcode":"90403",
    "sg:province":"CA",
    "wof:name":"Vibe Master Inc",
    "wof:placetype":"venue"
},
  "geometry": {"coordinates":[-118.49190400000001,34.032666],"type":"Point"}
}