{
  "type": "Feature",
  "properties": {
    "iso:country":"US",
    "sg:address":"817 16th St",
    "sg:city":"Santa Monica",
    "sg:classifiers":[
        {
            "category":"Professional",
            "type":"Services"
        }
    ],
    "sg:phone":"+1 310 453 2764",
    "sg:postcode":"90403",
    "sg:province":"CA",
    "wof:name":"Vibe Master Inc",
    "wof:placetype":"venue"
},
  "geometry": {"coordinates":[-118.491904,34.032666],"type":"Point"}
}