{
  "type": "Feature",
  "properties": {
    "iso:country":"US",
    "sg:address":"6000 J Street",
    "sg:city":"Sacramento",
    "sg:classifiers":[
        {
            "category":"Arts & Performance",
            "subcategory":"Arts Center",
            "type":"Entertainment"
        }
    ],
    "sg:phone":"+1 916 278 4323",
    "sg:postcode":"95819",
    "sg:province":"CA",
    "sg:tags":[
        "performing"
    ],
    "wof:name":"California State University Sacramento Playwright's Theatre",
    "wof:placetype":"venue"
},
  "geometry": {"coordinates":[-121.427525,38.566911],"type":"Point"}
}