{
  "type": "Feature",
  "properties": {
    "addr:full":"17620 Bellflower Blvd B103 Bellflower CA 90706",
    "addr:housenumber":"17620",
    "addr:postcode":"90706",
    "addr:street":"Bellflower Blvd B103",
    "iso:country":"US",
    "sg:address":"17620 Bellflower Blvd B103",
    "sg:city":"Bellflower",
    "sg:classifiers":[
        {
            "category":"Professional",
            "subcategory":"Lawyer & Legal Services",
            "type":"Services"
        }
    ],
    "sg:phone":"+1 562 804 6118",
    "sg:postcode":"90706",
    "sg:province":"CA",
    "sg:tags":[
        "consultant",
        "naturalization",
        "immigration"
    ],
    "wof:name":"Southern Cal Immigration Ctr",
    "wof:placetype":"venue"
},
  "geometry": {"coordinates":[-118.125157,33.872845],"type":"Point"}
}