{
  "type": "Feature",
  "properties": {
    "addr:full":"388 E Alma Ave San Jose CA 95112",
    "addr:housenumber":"388",
    "addr:postcode":"95112",
    "addr:street":"E Alma Ave",
    "iso:country":"US",
    "sg:address":"388 E Alma Ave",
    "sg:city":"San Jose",
    "sg:classifiers":[
        {
            "category":"Wholesale",
            "subcategory":"Scrap",
            "type":"Manufacturing & Wholesale Goods"
        }
    ],
    "sg:phone":"+1 408 297 1022",
    "sg:postcode":"95112",
    "sg:province":"CA",
    "sg:tags":[
        "waste"
    ],
    "wof:name":"Recycled Fibers Of California",
    "wof:placetype":"venue"
},
  "geometry": {"coordinates":[-121.86826499999999,37.318517],"type":"Point"}
}