{
  "type": "Feature",
  "properties": {
    "iso:country":"US",
    "sg:address":"388 E Alma Ave",
    "sg:city":"San Jose",
    "sg:classifiers":[
        {
            "category":"Wholesale",
            "subcategory":"Scrap",
            "type":"Manufacturing & Wholesale Goods"
        }
    ],
    "sg:phone":"+1 408 297 1022",
    "sg:postcode":"95112",
    "sg:province":"CA",
    "sg:tags":[
        "waste"
    ],
    "wof:name":"Recycled Fibers Of California",
    "wof:placetype":"venue"
},
  "geometry": {"coordinates":[-121.86826499999999,37.318517],"type":"Point"}
}