{
  "type": "Feature",
  "properties": {
    "iso:country":"US",
    "sg:address":"3028 Martin Luther King Jr Blvd",
    "sg:city":"Lynwood",
    "sg:classifiers":[
        {
            "category":"Banks & Credit Unions",
            "subcategory":"Bank",
            "type":"Services"
        }
    ],
    "sg:phone":"+1 310 639 7545",
    "sg:postcode":"90262",
    "sg:province":"CA",
    "sg:tags":[
        "cashing",
        "check"
    ],
    "wof:name":"Century Check Cashing",
    "wof:placetype":"venue"
},
  "geometry": {"coordinates":[-118.21932200000001,33.937371],"type":"Point"}
}