{
  "type": "Feature",
  "properties": {
    "iso:country":"US",
    "sg:address":"1221 E Bremer Ave",
    "sg:city":"Fresno",
    "sg:classifiers":[
        {
            "category":"Professional",
            "subcategory":"Computer Services",
            "type":"Services"
        }
    ],
    "sg:phone":"+1 559 237 2955",
    "sg:postcode":"93728",
    "sg:province":"CA",
    "sg:tags":[
        "consultant",
        "designer"
    ],
    "wof:name":"Master Mind Ind Solutions",
    "wof:placetype":"venue"
},
  "geometry": {"coordinates":[-119.796241,36.753027],"type":"Point"}
}