{
  "type": "Feature",
  "properties": {
    "iso:country":"US",
    "sg:address":"22737 Hamlin St",
    "sg:city":"Canoga Park",
    "sg:classifiers":[
        {
            "category":"Building & Trades",
            "subcategory":"Construction",
            "type":"Services"
        }
    ],
    "sg:phone":"+1 818 884 5263",
    "sg:postcode":"91307",
    "sg:province":"CA",
    "sg:tags":[
        "general",
        "contractor"
    ],
    "wof:name":"Tobon Construction",
    "wof:placetype":"venue"
},
  "geometry": {"coordinates":[-118.622681,34.188991],"type":"Point"}
}