{
  "type": "Feature",
  "properties": {
    "iso:country":"US",
    "sg:address":"16299 Foothill Blvd",
    "sg:city":"Fontana",
    "sg:classifiers":[
        {
            "category":"Home & Garden",
            "subcategory":"Home Furnishings",
            "type":"Retail Goods"
        }
    ],
    "sg:phone":"+1 909 429 8140",
    "sg:postcode":"92335",
    "sg:province":"CA",
    "sg:tags":[
        "mirror"
    ],
    "wof:name":"Survivor Glass",
    "wof:placetype":"venue"
},
  "geometry": {"coordinates":[-117.453643,34.106566],"type":"Point"}
}