{
  "type": "Feature",
  "properties": {
    "addr:full":"708 N Bellah Ave Lindsay CA 93247",
    "addr:housenumber":"708",
    "addr:postcode":"93247",
    "addr:street":"N Bellah Ave",
    "iso:country":"US",
    "sg:address":"708 N Bellah Ave",
    "sg:city":"Lindsay",
    "sg:classifiers":[
        {
            "category":"Farming",
            "subcategory":"Farm & Veterinary Services",
            "type":"Manufacturing & Wholesale Goods"
        }
    ],
    "sg:phone":"+1 559 562 6555",
    "sg:postcode":"93247",
    "sg:province":"CA",
    "sg:tags":[
        "crop",
        "harvesting"
    ],
    "wof:name":"Tapia & Tapia Farm Services",
    "wof:placetype":"venue"
},
  "geometry": {"coordinates":[-119.086912,36.21241],"type":"Point"}
}