{
  "type": "Feature",
  "properties": {
    "iso:country":"US",
    "sg:address":"5113 Kipp Way",
    "sg:city":"Carmichael",
    "sg:classifiers":[
        {
            "category":"Home & Garden",
            "subcategory":"Carpets & Floor Coverings",
            "type":"Retail Goods"
        }
    ],
    "sg:phone":"+1 916 604 2232",
    "sg:postcode":"95608",
    "sg:province":"CA",
    "sg:tags":[
        "distributor",
        "rug",
        "carpeting",
        "manufacturer"
    ],
    "wof:name":"Next Level Carpet Care",
    "wof:placetype":"venue"
},
  "geometry": {"coordinates":[-121.312231,38.657514],"type":"Point"}
}