{
  "type": "Feature",
  "properties": {
    "addr:full":"1045 E Harvard Rd Burbank CA 91501",
    "addr:housenumber":"1045",
    "addr:postcode":"91501",
    "addr:street":"E Harvard Rd",
    "iso:country":"US",
    "sg:address":"1045 E Harvard Rd",
    "sg:city":"Burbank",
    "sg:classifiers":[
        {
            "category":"Manufacturing",
            "subcategory":"Wood Products",
            "type":"Manufacturing & Wholesale Goods"
        }
    ],
    "sg:phone":"+1 818 563 4122",
    "sg:postcode":"91501",
    "sg:province":"CA",
    "sg:tags":[
        "mfg"
    ],
    "wof:name":"Abbys Treasures Inc",
    "wof:placetype":"venue"
},
  "geometry": {"coordinates":[-118.30295,34.196178],"type":"Point"}
}