{
  "type": "Feature",
  "properties": {
    "addr:full":"613 N Oceanbluff Ave San Dimas CA 91773",
    "addr:housenumber":"613",
    "addr:postcode":"91773",
    "addr:street":"N Oceanbluff Ave",
    "iso:country":"US",
    "sg:address":"613 N Oceanbluff Ave",
    "sg:city":"San Dimas",
    "sg:classifiers":[
        {
            "category":"Professional",
            "subcategory":"Business Services",
            "type":"Services"
        }
    ],
    "sg:phone":"+1 909 599 5990",
    "sg:postcode":"91773",
    "sg:province":"CA",
    "wof:name":"Allied Home Inspection Svcs",
    "wof:placetype":"venue"
},
  "geometry": {"coordinates":[-117.80021499999999,34.113018],"type":"Point"}
}