{
  "type": "Feature",
  "properties": {
    "addr:full":"434 W Florence Ave Inglewood CA 90301",
    "addr:housenumber":"434",
    "addr:postcode":"90301",
    "addr:street":"W Florence Ave",
    "iso:country":"US",
    "sg:address":"434 W Florence Ave",
    "sg:city":"Inglewood",
    "sg:classifiers":[
        {
            "category":"Retail",
            "subcategory":"Auto Repair",
            "type":"Services"
        }
    ],
    "sg:phone":"+1 310 671 1199",
    "sg:postcode":"90301",
    "sg:province":"CA",
    "sg:website":"www.aegautomotive.com",
    "wof:name":"AEG Automotive Group",
    "wof:placetype":"venue"
},
  "geometry": {"coordinates":[-118.36255199999999,33.965476],"type":"Point"}
}