{
  "type": "Feature",
  "properties": {
    "iso:country":"US",
    "sg:address":"1778 Conway St",
    "sg:city":"Milpitas",
    "sg:classifiers":[
        {
            "category":"Professional",
            "subcategory":"Computer Services",
            "type":"Services"
        }
    ],
    "sg:phone":"+1 650 846 5761",
    "sg:postcode":"95035",
    "sg:province":"CA",
    "sg:tags":[
        "internet"
    ],
    "wof:name":"LINKTONET.NET",
    "wof:placetype":"venue"
},
  "geometry": {"coordinates":[-121.902056,37.457332],"type":"Point"}
}