{
  "type": "Feature",
  "properties": {
    "addr:full":"465 Reservation Rd Marina CA 93933",
    "addr:housenumber":"465",
    "addr:postcode":"93933",
    "addr:street":"Reservation Rd",
    "iso:country":"US",
    "sg:address":"465 Reservation Rd",
    "sg:city":"Marina",
    "sg:classifiers":[
        {
            "category":"Communications",
            "subcategory":"Film & Video Production",
            "type":"Services"
        }
    ],
    "sg:phone":"+1 831 372 6077",
    "sg:postcode":"93933",
    "sg:province":"CA",
    "sg:tags":[
        "services-commercial"
    ],
    "wof:name":"Monterey Bay Video Production Co.",
    "wof:placetype":"venue"
},
  "geometry": {"coordinates":[-121.780624,36.678521],"type":"Point"}
}