{
  "type": "Feature",
  "properties": {
    "iso:country":"US",
    "sg:address":"1000 Piner Rd",
    "sg:city":"Santa Rosa",
    "sg:classifiers":[
        {
            "category":"Retail",
            "subcategory":"Auto Repair",
            "type":"Services"
        }
    ],
    "sg:phone":"+1 707 544 6988",
    "sg:postcode":"95403",
    "sg:province":"CA",
    "sg:tags":[
        "machine",
        "automobile",
        "shop"
    ],
    "wof:name":"JNW Engine & Machine",
    "wof:placetype":"venue"
},
  "geometry": {"coordinates":[-122.739615,38.471478],"type":"Point"}
}