{
  "type": "Feature",
  "properties": {
    "addr:full":"380 W Aten Rd Imperial CA 92251",
    "addr:housenumber":"380",
    "addr:postcode":"92251",
    "addr:street":"W Aten Rd",
    "iso:country":"US",
    "sg:address":"380 W Aten Rd",
    "sg:city":"Imperial",
    "sg:classifiers":[
        {
            "category":"Education",
            "subcategory":"College",
            "type":"Public Place"
        }
    ],
    "sg:phone":"+1 760 352 8320",
    "sg:postcode":"92251",
    "sg:province":"CA",
    "sg:tags":[
        "academic",
        "school"
    ],
    "wof:name":"Imperial Valley College",
    "wof:placetype":"venue"
},
  "geometry": {"coordinates":[-115.570131,32.825683],"type":"Point"}
}