{
  "type": "Feature",
  "properties": {
    "addr:full":"805 1st St Gilroy CA 95020",
    "addr:housenumber":"805",
    "addr:postcode":"95020",
    "addr:street":"1St St",
    "iso:country":"US",
    "sg:address":"805 1st St",
    "sg:city":"Gilroy",
    "sg:classifiers":[
        {
            "category":"Banks & Credit Unions",
            "subcategory":"Bank",
            "type":"Services"
        }
    ],
    "sg:phone":"+1 408 842 6416",
    "sg:postcode":"95020",
    "sg:province":"CA",
    "wof:name":"Union Bank Of CA",
    "wof:placetype":"venue"
},
  "geometry": {"coordinates":[-121.584085,37.013496],"type":"Point"}
}