{
  "type": "Feature",
  "properties": {
    "addr:full":"2051 Solar Dr Suite 150 Oxnard CA 93036",
    "addr:housenumber":"2051",
    "addr:postcode":"93036",
    "addr:street":"Solar Dr Suite 150",
    "iso:country":"US",
    "sg:address":"2051 Solar Dr Suite 150",
    "sg:city":"Oxnard",
    "sg:classifiers":[
        {
            "category":"Education",
            "subcategory":"Special Training",
            "type":"Public Place"
        },
        {
            "category":"Education",
            "subcategory":"Vocational School",
            "type":"Public Place"
        },
        {
            "category":"Education",
            "subcategory":"University",
            "type":"Public Place"
        },
        {
            "category":"Education",
            "subcategory":"School",
            "type":"Public Place"
        }
    ],
    "sg:phone":"+1 888 332 7176",
    "sg:postcode":"93036",
    "sg:province":"CA",
    "sg:tags":[
        "educational",
        "industrial",
        "business",
        "technical",
        "trade",
        "college"
    ],
    "sg:website":"http://national.citysearch.com/profile/external/698665/oxnard_ca/itt_technical_institute.html?publisher=yellowpages&reference_id=1&placement=ypwebsitemip",
    "wof:name":"ITT TECHNICAL INSTITUTE",
    "wof:placetype":"venue"
},
  "geometry": {"coordinates":[-119.144909,34.220183],"type":"Point"}
}