{
  "type": "Feature",
  "properties": {
    "addr:full":"32180 Auberry Rd Auberry CA 93602",
    "addr:postcode":"32180;93602",
    "addr:street":"Auberry Rd",
    "iso:country":"US",
    "sg:address":"32180 Auberry Rd",
    "sg:city":"Auberry",
    "sg:classifiers":[
        {
            "category":"Manufacturing",
            "subcategory":"Lumber",
            "type":"Manufacturing & Wholesale Goods"
        }
    ],
    "sg:phone":"+1 559 855 8913",
    "sg:postcode":"93602",
    "sg:province":"CA",
    "sg:tags":[
        "logging"
    ],
    "wof:name":"Sierra Forest Products",
    "wof:placetype":"venue"
},
  "geometry": {"coordinates":[-119.49427799999999,37.064346],"type":"Point"}
}