{
  "type": "Feature",
  "properties": {
    "iso:country":"US",
    "sg:address":"32180 Auberry Rd",
    "sg:city":"Auberry",
    "sg:classifiers":[
        {
            "category":"Manufacturing",
            "subcategory":"Lumber",
            "type":"Manufacturing & Wholesale Goods"
        }
    ],
    "sg:phone":"+1 559 855 8913",
    "sg:postcode":"93602",
    "sg:province":"CA",
    "sg:tags":[
        "logging"
    ],
    "wof:name":"Sierra Forest Products",
    "wof:placetype":"venue"
},
  "geometry": {"coordinates":[-119.494278,37.064346],"type":"Point"}
}