{
  "type": "Feature",
  "properties": {
    "addr:full":"6402 Platt Ave West Hills CA 91307",
    "addr:housenumber":"6402",
    "addr:postcode":"91307",
    "addr:street":"Platt Ave",
    "iso:country":"US",
    "sg:address":"6402 Platt Ave",
    "sg:city":"West Hills",
    "sg:classifiers":[
        {
            "category":"Retail",
            "subcategory":"Veterinary Services",
            "type":"Services"
        }
    ],
    "sg:phone":"+1 818 888 8111",
    "sg:postcode":"91307",
    "sg:province":"CA",
    "sg:tags":[
        "veterinarian"
    ],
    "sg:website":"www.westhillsanimalhospital.net",
    "wof:name":"West Hills Animal Hospital",
    "wof:placetype":"venue"
},
  "geometry": {"coordinates":[-118.64273300000001,34.186825],"type":"Point"}
}