{
  "type": "Feature",
  "properties": {
    "addr:full":"2068 Walsh Ave Santa Clara CA 95050",
    "addr:housenumber":"2068",
    "addr:postcode":"95050",
    "addr:street":"Walsh Ave",
    "iso:country":"US",
    "sg:address":"2068 Walsh Ave",
    "sg:city":"Santa Clara",
    "sg:classifiers":[
        {
            "category":"Banks & Credit Unions",
            "subcategory":"Bank",
            "type":"Services"
        }
    ],
    "sg:phone":"+1 408 970 3410",
    "sg:postcode":"95050",
    "sg:province":"CA",
    "sg:tags":[
        "loan",
        "real estate"
    ],
    "wof:name":"Ebid Mortgage",
    "wof:placetype":"venue"
},
  "geometry": {"coordinates":[-121.96066399999999,37.36939],"type":"Point"}
}