{
  "type": "Feature",
  "properties": {
    "addr:full":"9430 Washington Blvd Culver City CA 90232",
    "addr:housenumber":"9430",
    "addr:postcode":"90232",
    "addr:street":"Washington Blvd",
    "iso:country":"US",
    "sg:address":"9430 Washington Blvd",
    "sg:city":"Culver City",
    "sg:classifiers":[
        {
            "category":"Communications",
            "subcategory":"Film & Video Production",
            "type":"Services"
        }
    ],
    "sg:phone":"+1 310 202 3513",
    "sg:postcode":"90232",
    "sg:province":"CA",
    "sg:tags":[
        "motion"
    ],
    "wof:name":"MGM",
    "wof:placetype":"venue"
},
  "geometry": {"coordinates":[-118.39397,34.023604],"type":"Point"}
}