{
  "type": "Feature",
  "properties": {
    "iso:country":"US",
    "sg:address":"737 N Burke St",
    "sg:city":"Visalia",
    "sg:classifiers":[
        {
            "category":"Wholesale",
            "subcategory":"Electrical",
            "type":"Manufacturing & Wholesale Goods"
        }
    ],
    "sg:phone":"+1 559 625 0333",
    "sg:postcode":"93292",
    "sg:province":"CA",
    "sg:tags":[
        "equipment",
        "electric",
        "supply"
    ],
    "sg:website":"www.medallionsupply.com",
    "wof:name":"Medallion Supply Inc",
    "wof:placetype":"venue"
},
  "geometry": {"coordinates":[-119.283433,36.337638],"type":"Point"}
}