{
  "type": "Feature",
  "properties": {
    "iso:country":"US",
    "sg:address":"3399 Adams St",
    "sg:city":"Riverside",
    "sg:classifiers":[
        {
            "category":"Autos & Motor Vehicles",
            "subcategory":"Fuel & Gas Station",
            "type":"Retail Goods"
        }
    ],
    "sg:phone":"+1 951 687 2249",
    "sg:postcode":"92504",
    "sg:province":"CA",
    "sg:tags":[
        "oil"
    ],
    "wof:name":"Mohamed's Mobil Svc",
    "wof:placetype":"venue"
},
  "geometry": {"coordinates":[-117.41833099999999,33.925733],"type":"Point"}
}