{
  "type": "Feature",
  "properties": {
    "iso:country":"US",
    "sg:address":"426 E California St",
    "sg:city":"Ontario",
    "sg:classifiers":[
        {
            "category":"Banks & Credit Unions",
            "subcategory":"Bank",
            "type":"Services"
        }
    ],
    "sg:phone":"+1 909 986 7266",
    "sg:postcode":"91761",
    "sg:province":"CA",
    "sg:tags":[
        "cashing",
        "check"
    ],
    "wof:name":"Check Exchange",
    "wof:placetype":"venue"
},
  "geometry": {"coordinates":[-117.646325,34.055697],"type":"Point"}
}