{
  "type": "Feature",
  "properties": {
    "addr:full":"11520 Jefferson Blvd Culver City CA 90230",
    "addr:housenumber":"11520",
    "addr:postcode":"90230",
    "addr:street":"Jefferson Blvd",
    "iso:country":"US",
    "sg:address":"11520 Jefferson Blvd",
    "sg:city":"Culver City",
    "sg:classifiers":[
        {
            "category":"Real Estate",
            "subcategory":"Real Estate Agent",
            "type":"Services"
        }
    ],
    "sg:phone":"+1 310 915 9595",
    "sg:postcode":"90230",
    "sg:province":"CA",
    "sg:tags":[
        "management",
        "property"
    ],
    "wof:name":"Harris Properties",
    "wof:placetype":"venue"
},
  "geometry": {"coordinates":[-118.398003,33.988499],"type":"Point"}
}