{
  "type": "Feature",
  "properties": {
    "iso:country":"US",
    "sg:address":"416 Rutgers Dr",
    "sg:city":"Santa Maria",
    "sg:classifiers":[
        {
            "category":"Wholesale",
            "subcategory":"Home Furnishings",
            "type":"Manufacturing & Wholesale Goods"
        }
    ],
    "sg:phone":"+1 805 934 1440",
    "sg:postcode":"93455",
    "sg:province":"CA",
    "wof:name":"Penots Draperies",
    "wof:placetype":"venue"
},
  "geometry": {"coordinates":[-120.429574,34.88459],"type":"Point"}
}