{
  "type": "Feature",
  "properties": {
    "addr:full":"8620 Delmonico Ave Canoga Park CA 91304",
    "addr:housenumber":"8620",
    "addr:postcode":"91304",
    "addr:street":"Delmonico Ave",
    "iso:country":"US",
    "sg:address":"8620 Delmonico Ave",
    "sg:city":"Canoga Park",
    "sg:classifiers":[
        {
            "category":"Professional",
            "type":"Services"
        }
    ],
    "sg:phone":"+1 818 992 5203",
    "sg:postcode":"91304",
    "sg:province":"CA",
    "wof:name":"Unique Promoz",
    "wof:placetype":"venue"
},
  "geometry": {"coordinates":[-118.61361100000001,34.228607],"type":"Point"}
}