{
  "type": "Feature",
  "properties": {
    "iso:country":"US",
    "sg:address":"3250 Cherry Ave",
    "sg:city":"Long Beach",
    "sg:classifiers":[
        {
            "category":"Mining & Drilling",
            "type":"Manufacturing & Wholesale Goods"
        }
    ],
    "sg:phone":"+1 562 424 8647",
    "sg:postcode":"90807",
    "sg:province":"CA",
    "sg:tags":[
        "oil",
        "well"
    ],
    "wof:name":"Gammaloy Limited",
    "wof:placetype":"venue"
},
  "geometry": {"coordinates":[-118.167555,33.816973],"type":"Point"}
}