{
  "type": "Feature",
  "properties": {
    "iso:country":"US",
    "sg:address":"900 S Westmoreland Ave",
    "sg:city":"Los Angeles",
    "sg:classifiers":[
        {
            "category":"Professional",
            "subcategory":"Employment Agencies",
            "type":"Services"
        }
    ],
    "sg:phone":"+1 213 675 5152",
    "sg:postcode":"90006",
    "sg:province":"CA",
    "sg:tags":[
        "opportunity"
    ],
    "wof:name":"Hanmi Empolyement Agency",
    "wof:placetype":"venue"
},
  "geometry": {"coordinates":[-118.289072,34.054995],"type":"Point"}
}