{
  "type": "Feature",
  "properties": {
    "iso:country":"US",
    "sg:address":"251 S Melrose Dr",
    "sg:city":"Vista",
    "sg:classifiers":[
        {
            "category":"Coffee & Tea",
            "type":"Food & Drink"
        }
    ],
    "sg:phone":"+1 760 806 8110",
    "sg:postcode":"92081",
    "sg:province":"CA",
    "sg:website":"www.starbucks.com",
    "wof:name":"Starbucks",
    "wof:placetype":"venue"
},
  "geometry": {"coordinates":[-117.25369000000001,33.193401],"type":"Point"}
}