{
  "type": "Feature",
  "properties": {
    "addr:full":"607 N June St Los Angeles CA 90004",
    "addr:housenumber":"607",
    "addr:postcode":"90004",
    "addr:street":"N June St",
    "iso:country":"US",
    "sg:address":"607 N June St",
    "sg:city":"Los Angeles",
    "sg:classifiers":[
        {
            "category":"Professional",
            "subcategory":"Lawyer & Legal Services",
            "type":"Services"
        }
    ],
    "sg:phone":"+1 213 430 7274",
    "sg:postcode":"90004",
    "sg:province":"CA",
    "wof:name":"OMelveny & Myers LLP",
    "wof:placetype":"venue"
},
  "geometry": {"coordinates":[-118.334242,34.083381],"type":"Point"}
}