{
  "type": "Feature",
  "properties": {
    "addr:full":"2125 Arizona Ave Santa Monica CA 90404",
    "addr:housenumber":"2125",
    "addr:postcode":"90404",
    "addr:street":"Arizona Ave",
    "iso:country":"US",
    "sg:address":"2125 Arizona Ave",
    "sg:city":"Santa Monica",
    "sg:classifiers":[
        {
            "category":"Insurance",
            "subcategory":"Insurance Agent",
            "type":"Services"
        }
    ],
    "sg:phone":"+1 310 586 9700",
    "sg:postcode":"90404",
    "sg:province":"CA",
    "sg:tags":[
        "accident"
    ],
    "wof:name":"Sue Hartenbaum Insurance Svc",
    "wof:placetype":"venue"
},
  "geometry": {"coordinates":[-118.480076,34.031263],"type":"Point"}
}