{
  "type": "Feature",
  "properties": {
    "iso:country":"US",
    "sg:address":"1141 Owsley Ave",
    "sg:city":"San Jose",
    "sg:classifiers":[
        {
            "category":"Banks & Credit Unions",
            "subcategory":"Financial Services",
            "type":"Services"
        }
    ],
    "sg:phone":"+1 408 971 7073",
    "sg:postcode":"95122",
    "sg:province":"CA",
    "sg:tags":[
        "broker",
        "mortgage"
    ],
    "wof:name":"Crown Service Company",
    "wof:placetype":"venue"
},
  "geometry": {"coordinates":[-121.852997,37.3311],"type":"Point"}
}