{
  "type": "Feature",
  "properties": {
    "iso:country":"US",
    "sg:address":"6111 5th St",
    "sg:city":"Los Angeles",
    "sg:classifiers":[
        {
            "category":"Personal",
            "subcategory":"Beauty Salon",
            "type":"Services"
        }
    ],
    "sg:phone":"+1 323 938 6895",
    "sg:postcode":"90048",
    "sg:province":"CA",
    "sg:tags":[
        "hair"
    ],
    "sg:website":"www.mothershipsalon.com",
    "wof:name":"MotherShip Salon",
    "wof:placetype":"venue"
},
  "geometry": {"coordinates":[-118.361477,34.067421],"type":"Point"}
}