{
  "type": "Feature",
  "properties": {
    "addr:full":"3750 Gleason Ave San Jose CA 95130",
    "addr:housenumber":"3750",
    "addr:postcode":"95130",
    "addr:street":"Gleason Ave",
    "iso:country":"US",
    "sg:address":"3750 Gleason Ave",
    "sg:city":"San Jose",
    "sg:classifiers":[
        {
            "category":"Education",
            "subcategory":"School",
            "type":"Public Place"
        }
    ],
    "sg:phone":"+1 408 874 3700",
    "sg:postcode":"95130",
    "sg:province":"CA",
    "sg:tags":[
        "elementary"
    ],
    "sg:website":"www.moreland.k12.ca.us",
    "wof:name":"Payne Elementary School",
    "wof:placetype":"venue"
},
  "geometry": {"coordinates":[-121.968002,37.297501],"type":"Point"}
}