{
  "type": "Feature",
  "properties": {
    "iso:country":"US",
    "sg:address":"2345 S Grove Ave",
    "sg:city":"Ontario",
    "sg:classifiers":[
        {
            "category":"Restaurant",
            "type":"Food & Drink"
        }
    ],
    "sg:phone":"+1 909 947 3322",
    "sg:postcode":"91761",
    "sg:province":"CA",
    "wof:name":"Royal Cut",
    "wof:placetype":"venue"
},
  "geometry": {"coordinates":[-117.628386,34.033493],"type":"Point"}
}