{
  "type": "Feature",
  "properties": {
    "iso:country":"US",
    "sg:address":"Los Angeles Equestrian Center 480 Riverside Dr",
    "sg:city":"Burbank",
    "sg:classifiers":[
        {
            "category":"Sports & Exercise",
            "subcategory":"Stables",
            "type":"Entertainment"
        }
    ],
    "sg:phone":"+1 818 569 3666",
    "sg:postcode":"91506",
    "sg:province":"CA",
    "sg:tags":[
        "riding",
        "horseback"
    ],
    "sg:website":"www.traditionaleq.com",
    "wof:name":"Traditional Equitation School",
    "wof:placetype":"venue"
},
  "geometry": {"coordinates":[-118.310244,34.160713],"type":"Point"}
}