{
  "type": "Feature",
  "properties": {
    "iso:country":"US",
    "sg:address":"8880 Benson Ave",
    "sg:city":"Montclair",
    "sg:classifiers":[
        {
            "category":"Organizations",
            "subcategory":"Professional Association",
            "type":"Services"
        }
    ],
    "sg:phone":"+1 909 931 4413",
    "sg:postcode":"91763",
    "sg:province":"CA",
    "wof:name":"National Association",
    "wof:placetype":"venue"
},
  "geometry": {"coordinates":[-117.680932,34.093907],"type":"Point"}
}