{
  "type": "Feature",
  "properties": {
    "iso:country":"US",
    "sg:address":"3650 Wade St",
    "sg:city":"Los Angeles",
    "sg:classifiers":[
        {
            "category":"Professional",
            "type":"Services"
        }
    ],
    "sg:phone":"+1 310 390 5263",
    "sg:postcode":"90066",
    "sg:province":"CA",
    "wof:name":"Steven Odere",
    "wof:placetype":"venue"
},
  "geometry": {"coordinates":[-118.440681,34.005282],"type":"Point"}
}