{
  "type": "Feature",
  "properties": {
    "iso:country":"US",
    "sg:address":"3319 Sacramento Street",
    "sg:city":"San Francisco",
    "sg:classifiers":[
        {
            "category":"Arts & Performance",
            "subcategory":"Art Gallery",
            "type":"Entertainment"
        },
        {
            "category":"Shopping",
            "subcategory":"Florist",
            "type":"Retail Goods"
        }
    ],
    "sg:phone":"+1 415 567 2443",
    "sg:postcode":"94118",
    "sg:province":"CA",
    "sg:website":"www.beautifulorchids.com",
    "wof:name":"Beautiful Orchids",
    "wof:placetype":"venue"
},
  "geometry": {"coordinates":[-122.447998,37.7887],"type":"Point"}
}