{
  "type": "Feature",
  "properties": {
    "iso:country":"US",
    "sg:address":"1360 Howell Creek Rd",
    "sg:city":"Ukiah",
    "sg:classifiers":[
        {
            "category":"Building & Trades",
            "subcategory":"Construction",
            "type":"Services"
        }
    ],
    "sg:phone":"+1 707 463 0377",
    "sg:postcode":"95482",
    "sg:province":"CA",
    "sg:tags":[
        "wallcoverings-installation",
        "wallpaper",
        "painting",
        "contractor"
    ],
    "wof:name":"Dave Mondragon Painting",
    "wof:placetype":"venue"
},
  "geometry": {"coordinates":[-123.16889999999999,39.110272],"type":"Point"}
}