{
  "type": "Feature",
  "properties": {
    "iso:country":"US",
    "sg:address":"6009 Rosemead Blvd",
    "sg:city":"Pico Rivera",
    "sg:classifiers":[
        {
            "category":"Cinema",
            "subcategory":"Movie Rental",
            "type":"Entertainment"
        }
    ],
    "sg:phone":"+1 562 948 3633",
    "sg:postcode":"90660",
    "sg:province":"CA",
    "sg:tags":[
        "leasing",
        "video",
        "disc",
        "tape"
    ],
    "wof:name":"Video Guild",
    "wof:placetype":"venue"
},
  "geometry": {"coordinates":[-118.092343,33.990044],"type":"Point"}
}