{
  "type": "Feature",
  "properties": {
    "addr:full":"8155 Lankershim Blvd North Hollywood CA 91605",
    "addr:housenumber":"8155",
    "addr:postcode":"91605",
    "addr:street":"Lankershim Blvd",
    "iso:country":"US",
    "sg:address":"8155 Lankershim Blvd",
    "sg:city":"North Hollywood",
    "sg:classifiers":[
        {
            "category":"Home & Garden",
            "subcategory":"Building Materials",
            "type":"Retail Goods"
        }
    ],
    "sg:phone":"+1 818 767 5694",
    "sg:postcode":"91605",
    "sg:province":"CA",
    "sg:tags":[
        "glass",
        "window",
        "plate"
    ],
    "wof:name":"Pilkington North America",
    "wof:placetype":"venue"
},
  "geometry": {"coordinates":[-118.387856,34.216511],"type":"Point"}
}