{
  "type": "Feature",
  "properties": {
    "iso:country":"US",
    "sg:address":"3636 1st Ave",
    "sg:city":"San Diego",
    "sg:classifiers":[
        {
            "category":"Health Services",
            "subcategory":"Health Practitioner",
            "type":"Services"
        }
    ],
    "sg:phone":"+1 619 296 9781",
    "sg:postcode":"92103",
    "sg:province":"CA",
    "sg:tags":[
        "psychologist"
    ],
    "wof:name":"Patricia B Lindquist PHD",
    "wof:placetype":"venue"
},
  "geometry": {"coordinates":[-117.163933,32.74445],"type":"Point"}
}