{
  "type": "Feature",
  "properties": {
    "addr:full":"2355 Chestnut St San Francisco CA 94123",
    "addr:housenumber":"2355",
    "addr:postcode":"94123",
    "addr:street":"Chestnut St",
    "iso:country":"US",
    "sg:address":"2355 Chestnut St",
    "sg:city":"San Francisco",
    "sg:classifiers":[
        {
            "category":"Restaurant",
            "type":"Food & Drink"
        }
    ],
    "sg:menulink":"http://www.allmenus.com/ca/san-francisco/61879-a-16/menu/",
    "sg:phone":"+1 415 771 2216",
    "sg:postcode":"94123",
    "sg:province":"CA",
    "sg:tags":[
        "italian"
    ],
    "wof:name":"A 16",
    "wof:placetype":"venue"
},
  "geometry": {"coordinates":[-122.44212899999999,37.800101],"type":"Point"}
}