{
  "type": "Feature",
  "properties": {
    "iso:country":"US",
    "sg:address":"334 Beach Rd",
    "sg:city":"Alameda",
    "sg:classifiers":[
        {
            "category":"Real Estate",
            "subcategory":"Real Estate Agent",
            "type":"Services"
        }
    ],
    "sg:phone":"+1 510 521 2108",
    "sg:postcode":"94502",
    "sg:province":"CA",
    "sg:tags":[
        "management",
        "property"
    ],
    "wof:name":"The Property Shop Management",
    "wof:placetype":"venue"
},
  "geometry": {"coordinates":[-122.23200199999999,37.732498],"type":"Point"}
}