{
  "type": "Feature",
  "properties": {
    "addr:full":"6843 Mission St Daly City CA 94014",
    "addr:housenumber":"6843",
    "addr:postcode":"94014",
    "addr:street":"Mission St",
    "iso:country":"US",
    "sg:address":"6843 Mission St",
    "sg:city":"Daly City",
    "sg:classifiers":[
        {
            "category":"Wholesale",
            "subcategory":"Drugs",
            "type":"Manufacturing & Wholesale Goods"
        }
    ],
    "sg:phone":"+1 650 992 9490",
    "sg:postcode":"94014",
    "sg:province":"CA",
    "wof:name":"Sav On Pharmacies",
    "wof:placetype":"venue"
},
  "geometry": {"coordinates":[-122.464225,37.697911],"type":"Point"}
}