{
  "type": "Feature",
  "properties": {
    "iso:country":"US",
    "sg:address":"101 Lincoln Centre Dr",
    "sg:city":"San Mateo",
    "sg:classifiers":[
        {
            "category":"Manufacturing",
            "subcategory":"Tools & Machinery",
            "type":"Manufacturing & Wholesale Goods"
        }
    ],
    "sg:phone":"+1 650 570 6667",
    "sg:postcode":"94404",
    "sg:province":"CA",
    "sg:tags":[
        "analytical",
        "instrument",
        "chemical",
        "preparation",
        "mfg"
    ],
    "wof:name":"Applied Biosystems Group",
    "wof:placetype":"venue"
},
  "geometry": {"coordinates":[-122.27019,37.56854],"type":"Point"}
}