{
  "type": "Feature",
  "properties": {
    "iso:country":"US",
    "sg:address":"33 Dearborn Pl",
    "sg:city":"Goleta",
    "sg:classifiers":[
        {
            "category":"Manufacturing",
            "subcategory":"Printing",
            "type":"Manufacturing & Wholesale Goods"
        }
    ],
    "sg:phone":"+1 805 967 1193",
    "sg:postcode":"93117",
    "sg:province":"CA",
    "sg:tags":[
        "multimedia"
    ],
    "wof:name":"JLP Media",
    "wof:placetype":"venue"
},
  "geometry": {"coordinates":[-119.815716,34.438929],"type":"Point"}
}