{
  "type": "Feature",
  "properties": {
    "addr:full":"385 Paraiso Dr Danville CA 94526",
    "addr:housenumber":"385",
    "addr:postcode":"94526",
    "addr:street":"Paraiso Dr",
    "iso:country":"US",
    "sg:address":"385 Paraiso Dr",
    "sg:city":"Danville",
    "sg:classifiers":[
        {
            "category":"Home & Garden",
            "subcategory":"Building Materials",
            "type":"Retail Goods"
        }
    ],
    "sg:phone":"+1 925 362 9617",
    "sg:postcode":"94526",
    "sg:province":"CA",
    "sg:tags":[
        "windows"
    ],
    "wof:name":"Giannini Archtectural",
    "wof:placetype":"venue"
},
  "geometry": {"coordinates":[-121.972859,37.805814],"type":"Point"}
}