{
  "type": "Feature",
  "properties": {
    "addr:full":"171 E Sycamore Ave Arcadia CA 91006",
    "addr:housenumber":"171",
    "addr:postcode":"91006",
    "addr:street":"E Sycamore Ave",
    "iso:country":"US",
    "sg:address":"171 E Sycamore Ave",
    "sg:city":"Arcadia",
    "sg:classifiers":[
        {
            "category":"Education",
            "subcategory":"School",
            "type":"Public Place"
        }
    ],
    "sg:phone":"+1 626 821 8363",
    "sg:postcode":"91006",
    "sg:province":"CA",
    "sg:tags":[
        "high"
    ],
    "sg:website":"http://www.ausd.k12.ca.us",
    "wof:name":"Foothills Middle School",
    "wof:placetype":"venue"
},
  "geometry": {"coordinates":[-118.026061,34.152854],"type":"Point"}
}