{
  "type": "Feature",
  "properties": {
    "iso:country":"US",
    "sg:address":"628 O St",
    "sg:city":"Fresno",
    "sg:classifiers":[
        {
            "category":"Restaurant",
            "type":"Food & Drink"
        }
    ],
    "sg:phone":"+1 559 277 1715",
    "sg:postcode":"93721",
    "sg:province":"CA",
    "wof:name":"Italian Garden Restaurant",
    "wof:placetype":"venue"
},
  "geometry": {"coordinates":[-119.781374,36.734286],"type":"Point"}
}