{
  "type": "Feature",
  "properties": {
    "iso:country":"US",
    "sg:address":"2015 Mt Diablo Blvd",
    "sg:city":"Walnut Creek",
    "sg:classifiers":[
        {
            "category":"Health Services",
            "subcategory":"Nursing And Care Facility",
            "type":"Services"
        }
    ],
    "sg:phone":"+1 925 256 8708",
    "sg:postcode":"94596",
    "sg:province":"CA",
    "sg:tags":[
        "home",
        "convalescent"
    ],
    "sg:website":"www.edenvilla.com",
    "wof:name":"Eden Villa",
    "wof:placetype":"venue"
},
  "geometry": {"coordinates":[-122.067797,37.897127],"type":"Point"}
}