{
  "type": "Feature",
  "properties": {
    "iso:country":"US",
    "sg:address":"8757 Santa Monica Blvd",
    "sg:city":"West Hollywood",
    "sg:classifiers":[
        {
            "category":"Restaurant",
            "type":"Food & Drink"
        }
    ],
    "sg:postcode":"90069",
    "sg:province":"CA",
    "sg:tags":[
        "flavor",
        "local"
    ],
    "sg:website":"www.hauntingfactory.com/",
    "wof:name":"Vampyr Inn's Bloody Ball Haunted House",
    "wof:placetype":"venue"
},
  "geometry": {"coordinates":[-118.381692,34.086616],"type":"Point"}
}