{
  "type": "Feature",
  "properties": {
    "addr:full":"259 N McDowell Blvd Petaluma CA 94954",
    "addr:housenumber":"259",
    "addr:postcode":"94954",
    "addr:street":"N Mcdowell Blvd",
    "iso:country":"US",
    "sg:address":"259 N McDowell Blvd",
    "sg:city":"Petaluma",
    "sg:classifiers":[
        {
            "category":"Shopping",
            "type":"Retail Goods"
        }
    ],
    "sg:phone":"+1 707 778 8700",
    "sg:postcode":"94954",
    "sg:province":"CA",
    "sg:tags":[
        "telephone",
        "cellular"
    ],
    "wof:name":"Cellular World Inc",
    "wof:placetype":"venue"
},
  "geometry": {"coordinates":[-122.629665,38.251294],"type":"Point"}
}