{
  "type": "Feature",
  "properties": {
    "iso:country":"US",
    "sg:address":"1505 N Thorn St",
    "sg:city":"Ridgecrest",
    "sg:classifiers":[
        {
            "category":"Manufacturing",
            "subcategory":"Signs",
            "type":"Manufacturing & Wholesale Goods"
        },
        {
            "category":"Building & Trades",
            "subcategory":"Construction",
            "type":"Services"
        }
    ],
    "sg:phone":"+1 760 377 4519",
    "sg:postcode":"93555",
    "sg:province":"CA",
    "sg:tags":[
        "mfg",
        "specialty",
        "contractor"
    ],
    "wof:name":"A To Z Custom Signs",
    "wof:placetype":"venue"
},
  "geometry": {"coordinates":[-117.754213,35.648274],"type":"Point"}
}