{
  "type": "Feature",
  "properties": {
    "addr:full":"200 Glenwood Cir Monterey CA 93940",
    "addr:housenumber":"200",
    "addr:postcode":"93940",
    "addr:street":"Glenwood Cir",
    "iso:country":"US",
    "sg:address":"200 Glenwood Cir",
    "sg:city":"Monterey",
    "sg:classifiers":[
        {
            "category":"Social Services",
            "subcategory":"Adult Care",
            "type":"Services"
        },
        {
            "category":"Real Estate",
            "subcategory":"Real Estate Operator",
            "type":"Services"
        }
    ],
    "sg:phone":"+1 831 373 6126",
    "sg:postcode":"93940",
    "sg:province":"CA",
    "sg:tags":[
        "retirement",
        "for",
        "residential",
        "hotel",
        "elderly",
        "home"
    ],
    "sg:website":"www.classicresidence.com",
    "wof:name":"Park Lane A Classic Residence",
    "wof:placetype":"venue"
},
  "geometry": {"coordinates":[-121.891351,36.584133],"type":"Point"}
}