{
  "type": "Feature",
  "properties": {
    "iso:country":"US",
    "sg:address":"401 W Columbus St",
    "sg:city":"Bakersfield",
    "sg:classifiers":[
        {
            "category":"Real Estate",
            "subcategory":"Real Estate Operator",
            "type":"Services"
        }
    ],
    "sg:phone":"+1 661 325 4047",
    "sg:postcode":"93301",
    "sg:province":"CA",
    "sg:tags":[
        "building",
        "apartment"
    ],
    "wof:name":"Aimco",
    "wof:placetype":"venue"
},
  "geometry": {"coordinates":[-119.007978,35.397774],"type":"Point"}
}