{
  "type": "Feature",
  "properties": {
    "iso:country":"US",
    "sg:address":"1519 S Broadway",
    "sg:city":"Santa Maria",
    "sg:classifiers":[
        {
            "category":"Banks & Credit Unions",
            "subcategory":"Bank",
            "type":"Services"
        }
    ],
    "sg:phone":"+1 805 928 3838",
    "sg:postcode":"93454",
    "sg:province":"CA",
    "sg:tags":[
        "loan",
        "real estate"
    ],
    "sg:website":"www.yourdreamhome.com",
    "wof:name":"Casa De Sus Suenos Realty",
    "wof:placetype":"venue"
},
  "geometry": {"coordinates":[-120.43619,34.933635],"type":"Point"}
}