{
  "type": "Feature",
  "properties": {
    "addr:full":"1670 Alvarado St San Leandro CA 94577",
    "addr:housenumber":"1670",
    "addr:postcode":"94577",
    "addr:street":"Alvarado St",
    "iso:country":"US",
    "sg:address":"1670 Alvarado St",
    "sg:city":"San Leandro",
    "sg:classifiers":[
        {
            "category":"Home & Garden",
            "subcategory":"Garden Supply",
            "type":"Retail Goods"
        }
    ],
    "sg:phone":"+1 510 351 1516",
    "sg:postcode":"94577",
    "sg:province":"CA",
    "sg:tags":[
        "nursery",
        "gardening"
    ],
    "wof:name":"Plant Domain",
    "wof:placetype":"venue"
},
  "geometry": {"coordinates":[-122.160729,37.718769],"type":"Point"}
}