{
  "type": "Feature",
  "properties": {
    "iso:country":"US",
    "sg:address":"2806 64th St",
    "sg:city":"Sacramento",
    "sg:classifiers":[
        {
            "category":"Professional",
            "subcategory":"Art Services",
            "type":"Services"
        }
    ],
    "sg:phone":"+1 916 201 1489",
    "sg:postcode":"95817",
    "sg:province":"CA",
    "sg:tags":[
        "graphic",
        "designer"
    ],
    "wof:name":"Skinnydork Designs",
    "wof:placetype":"venue"
},
  "geometry": {"coordinates":[-121.429703,38.548217],"type":"Point"}
}