{
  "type": "Feature",
  "properties": {
    "addr:full":"3400 Standish Ave Santa Rosa CA 95407",
    "addr:postcode":"3400;95407",
    "addr:street":"Standish Ave",
    "iso:country":"US",
    "sg:address":"3400 Standish Ave",
    "sg:city":"Santa Rosa",
    "sg:classifiers":[
        {
            "category":"Wholesale",
            "subcategory":"Scrap",
            "type":"Manufacturing & Wholesale Goods"
        }
    ],
    "sg:phone":"+1 707 585 0291",
    "sg:postcode":"95407",
    "sg:province":"CA",
    "sg:tags":[
        "recycling",
        "center"
    ],
    "sg:website":"www.wastemanagement.com",
    "wof:name":"Waste Management Inc",
    "wof:placetype":"venue"
},
  "geometry": {"coordinates":[-122.723038,38.393226],"type":"Point"}
}