{
  "type": "Feature",
  "properties": {
    "iso:country":"US",
    "sg:address":"2424 Del Monte Street",
    "sg:city":"West Sacramento",
    "sg:classifiers":[
        {
            "category":"Food & Beverages",
            "subcategory":"Liquor & Beverages",
            "type":"Retail Goods"
        }
    ],
    "sg:phone":"+1 916 371 8164",
    "sg:postcode":"95691",
    "sg:province":"CA",
    "sg:tags":[
        "beer",
        "spirit",
        "wine"
    ],
    "wof:name":"Capital Beverage Company",
    "wof:placetype":"venue"
},
  "geometry": {"coordinates":[-121.54134999999999,38.569805],"type":"Point"}
}