{
  "type": "Feature",
  "properties": {
    "iso:country":"US",
    "sg:address":"461 Valencia St",
    "sg:city":"San Francisco",
    "sg:classifiers":[
        {
            "category":"Arts & Performance",
            "subcategory":"Art Gallery",
            "type":"Entertainment"
        }
    ],
    "sg:phone":"+1 415 441 8680",
    "sg:postcode":"94103",
    "sg:province":"CA",
    "sg:website":"www.artzone461.com",
    "wof:name":"ArtZone 461 Gallery",
    "wof:placetype":"venue"
},
  "geometry": {"coordinates":[-122.421628,37.765511],"type":"Point"}
}