{
  "type": "Feature",
  "properties": {
    "iso:country":"US",
    "sg:address":"2820 Willow Ave",
    "sg:city":"Clovis",
    "sg:classifiers":[
        {
            "category":"Organizations",
            "subcategory":"Religious Organization",
            "type":"Services"
        }
    ],
    "sg:phone":"+1 559 347 3000",
    "sg:postcode":"93612",
    "sg:province":"CA",
    "sg:tags":[
        "church"
    ],
    "wof:name":"Adventist Book Ctr",
    "wof:placetype":"venue"
},
  "geometry": {"coordinates":[-119.727399,36.798],"type":"Point"}
}