{
  "type": "Feature",
  "properties": {
    "addr:full":"388 Adams Ave Pomona CA 91767",
    "addr:housenumber":"388",
    "addr:postcode":"91767",
    "addr:street":"Adams Ave",
    "iso:country":"US",
    "sg:address":"388 Adams Ave",
    "sg:city":"Pomona",
    "sg:classifiers":[
        {
            "category":"Professional",
            "type":"Services"
        }
    ],
    "sg:phone":"+1 909 629 6052",
    "sg:postcode":"91767",
    "sg:province":"CA",
    "wof:name":"Luna Treasures",
    "wof:placetype":"venue"
},
  "geometry": {"coordinates":[-117.745024,34.075296],"type":"Point"}
}