{
  "type": "Feature",
  "properties": {
    "iso:country":"US",
    "sg:address":"980 9th St",
    "sg:city":"Sacramento",
    "sg:classifiers":[
        {
            "category":"Banks & Credit Unions",
            "subcategory":"Investment Brokerage",
            "type":"Services"
        }
    ],
    "sg:phone":"+1 916 449 9652",
    "sg:postcode":"95814",
    "sg:province":"CA",
    "sg:tags":[
        "security"
    ],
    "wof:name":"Beal M R & Co A VA Ltd Partnr",
    "wof:placetype":"venue"
},
  "geometry": {"coordinates":[-121.494581,38.581584],"type":"Point"}
}