{
  "type": "Feature",
  "properties": {
    "iso:country":"US",
    "sg:address":"9081 Watson St",
    "sg:city":"Cypress",
    "sg:classifiers":[
        {
            "category":"Professional",
            "subcategory":"Advertising",
            "type":"Services"
        }
    ],
    "sg:phone":"+1 714 827 7990",
    "sg:postcode":"90630",
    "sg:province":"CA",
    "sg:tags":[
        "promotion",
        "sale"
    ],
    "wof:name":"Socal Promotions Inc",
    "wof:placetype":"venue"
},
  "geometry": {"coordinates":[-118.03919500000001,33.830953],"type":"Point"}
}