{
  "type": "Feature",
  "properties": {
    "iso:country":"US",
    "sg:address":"1001 Manhattan Beach Blvd",
    "sg:city":"Manhattan Beach",
    "sg:classifiers":[
        {
            "category":"Real Estate",
            "subcategory":"Real Estate Services",
            "type":"Services"
        }
    ],
    "sg:phone":"+1 888 773 7573",
    "sg:postcode":"90266",
    "sg:province":"CA",
    "sg:tags":[
        "management",
        "property"
    ],
    "sg:website":"www.firstlightpropertymanagement...",
    "wof:name":"First Light Property Management, Inc",
    "wof:placetype":"venue"
},
  "geometry": {"coordinates":[-118.397671,33.887636],"type":"Point"}
}