{
  "type": "Feature",
  "properties": {
    "iso:country":"US",
    "sg:address":"1230 E Clinton Ave",
    "sg:city":"Fresno",
    "sg:classifiers":[
        {
            "category":"Retail",
            "subcategory":"Auto Repair",
            "type":"Services"
        }
    ],
    "sg:phone":"+1 559 307 8742",
    "sg:postcode":"93704",
    "sg:province":"CA",
    "sg:tags":[
        "wrecker"
    ],
    "wof:name":"Brent Towing",
    "wof:placetype":"venue"
},
  "geometry": {"coordinates":[-119.795575,36.772174],"type":"Point"}
}