{
  "type": "Feature",
  "properties": {
    "iso:country":"US",
    "sg:address":"5675 Telegraph Rd",
    "sg:city":"Los Angeles",
    "sg:classifiers":[
        {
            "category":"Shopping",
            "subcategory":"Clothing, Apparel, & Fashions",
            "type":"Retail Goods"
        }
    ],
    "sg:phone":"+1 323 726 1987",
    "sg:postcode":"90040",
    "sg:province":"CA",
    "sg:tags":[
        "sportswear"
    ],
    "wof:name":"Pacific Sunwear",
    "wof:placetype":"venue"
},
  "geometry": {"coordinates":[-118.15422599999999,34.00607],"type":"Point"}
}