{
  "type": "Feature",
  "properties": {
    "iso:country":"US",
    "sg:address":"2201 Ingalls Street",
    "sg:city":"San Francisco",
    "sg:classifiers":[
        {
            "category":"Retail",
            "subcategory":"Auto Repair",
            "type":"Services"
        }
    ],
    "sg:phone":"+1 415 822 4874",
    "sg:postcode":"94124",
    "sg:province":"CA",
    "wof:name":"Suarez Auto Repair",
    "wof:placetype":"venue"
},
  "geometry": {"coordinates":[-122.387001,37.725101],"type":"Point"}
}