{
  "type": "Feature",
  "properties": {
    "addr:full":"1421 Sacramento St Vallejo CA 94590",
    "addr:housenumber":"1421",
    "addr:postcode":"94590",
    "addr:street":"Sacramento St",
    "iso:country":"US",
    "sg:address":"1421 Sacramento St",
    "sg:city":"Vallejo",
    "sg:classifiers":[
        {
            "category":"Shopping",
            "subcategory":"Clothing, Apparel, & Fashions",
            "type":"Retail Goods"
        }
    ],
    "sg:phone":"+1 707 558 9757",
    "sg:postcode":"94590",
    "sg:province":"CA",
    "sg:tags":[
        "alterations-clothing",
        "accessory",
        "women's"
    ],
    "wof:name":"Paulas Stitch Shoppe",
    "wof:placetype":"venue"
},
  "geometry": {"coordinates":[-122.25808000000001,38.110543],"type":"Point"}
}