{
  "type": "Feature",
  "properties": {
    "addr:full":"5035 Brookdale Cir Fairfield CA 94534",
    "addr:housenumber":"5035",
    "addr:postcode":"94534",
    "addr:street":"Brookdale Cir",
    "iso:country":"US",
    "sg:address":"5035 Brookdale Cir",
    "sg:city":"Fairfield",
    "sg:classifiers":[
        {
            "category":"Shopping",
            "subcategory":"Bicycles & Sporting Goods",
            "type":"Retail Goods"
        }
    ],
    "sg:phone":"+1 707 427 1595",
    "sg:postcode":"94534",
    "sg:province":"CA",
    "wof:name":"Rod's Sports Towel",
    "wof:placetype":"venue"
},
  "geometry": {"coordinates":[-122.144684,38.188222],"type":"Point"}
}