{
  "type": "Feature",
  "properties": {
    "addr:full":"305 W 6th St Oxnard CA 93030",
    "addr:housenumber":"305",
    "addr:postcode":"93030",
    "addr:street":"W 6Th St",
    "iso:country":"US",
    "sg:address":"305 W 6th St",
    "sg:city":"Oxnard",
    "sg:classifiers":[
        {
            "category":"Restaurant",
            "type":"Food & Drink"
        }
    ],
    "sg:phone":"+1 805 483 3524",
    "sg:postcode":"93030",
    "sg:province":"CA",
    "wof:name":"LA Placita Restaurant",
    "wof:placetype":"venue"
},
  "geometry": {"coordinates":[-119.18044,34.196449],"type":"Point"}
}