{
  "type": "Feature",
  "properties": {
    "iso:country":"US",
    "sg:address":"3909 Park Dr",
    "sg:city":"El Dorado Hills",
    "sg:classifiers":[
        {
            "category":"Restaurant",
            "type":"Food & Drink"
        }
    ],
    "sg:phone":"+1 916 933 8555",
    "sg:postcode":"95762",
    "sg:province":"CA",
    "sg:tags":[
        "rest",
        "italian"
    ],
    "sg:website":"www.masqueristorante.com",
    "wof:name":"Masque Ristorante",
    "wof:placetype":"venue"
},
  "geometry": {"coordinates":[-121.073765,38.659739],"type":"Point"}
}