{
  "type": "Feature",
  "properties": {
    "addr:full":"2811 San Carlos Avenue San Carlos CA 94070",
    "addr:housenumber":"2811",
    "addr:postcode":"94070",
    "addr:street":"San Carlos Avenue",
    "iso:country":"US",
    "sg:address":"2811 San Carlos Avenue",
    "sg:city":"San Carlos",
    "sg:classifiers":[
        {
            "category":"Place Of Worship",
            "subcategory":"Church",
            "type":"Public Place"
        }
    ],
    "sg:phone":"+1 650 593 3654",
    "sg:postcode":"94070",
    "sg:province":"CA",
    "sg:website":"www.genchurchsc.com",
    "wof:name":"Generations Church",
    "wof:placetype":"venue"
},
  "geometry": {"coordinates":[-122.28563699999999,37.506749],"type":"Point"}
}