{
  "type": "Feature",
  "properties": {
    "iso:country":"US",
    "sg:address":"585 Fitzgerald Ave",
    "sg:city":"San Martin",
    "sg:classifiers":[
        {
            "category":"Farming",
            "subcategory":"Farm",
            "type":"Manufacturing & Wholesale Goods"
        }
    ],
    "sg:phone":"+1 408 842 9755",
    "sg:postcode":"95046",
    "sg:province":"CA",
    "sg:tags":[
        "crop",
        "general"
    ],
    "wof:name":"LJB Farms",
    "wof:placetype":"venue"
},
  "geometry": {"coordinates":[-121.59830100000001,37.055195],"type":"Point"}
}