{
  "type": "Feature",
  "properties": {
    "addr:full":"1533 Baker St Costa Mesa CA 92626",
    "addr:housenumber":"1533",
    "addr:postcode":"92626",
    "addr:street":"Baker St",
    "iso:country":"US",
    "sg:address":"1533 Baker St",
    "sg:city":"Costa Mesa",
    "sg:classifiers":[
        {
            "category":"Shopping",
            "subcategory":"Hobbies, Toys, & Games",
            "type":"Retail Goods"
        }
    ],
    "sg:phone":"+1 714 556 7692",
    "sg:postcode":"92626",
    "sg:province":"CA",
    "sg:tags":[
        "craft",
        "supply"
    ],
    "wof:name":"Americraft",
    "wof:placetype":"venue"
},
  "geometry": {"coordinates":[-117.91989,33.679995],"type":"Point"}
}