{
  "type": "Feature",
  "properties": {
    "addr:full":"23172 Alcalde Dr Laguna Hills CA 92653",
    "addr:housenumber":"23172",
    "addr:postcode":"92653",
    "addr:street":"Alcalde Dr",
    "iso:country":"US",
    "sg:address":"23172 Alcalde Dr",
    "sg:city":"Laguna Hills",
    "sg:classifiers":[
        {
            "category":"Wholesale",
            "subcategory":"Furniture",
            "type":"Manufacturing & Wholesale Goods"
        }
    ],
    "sg:phone":"+1 949 916 0522",
    "sg:postcode":"92653",
    "sg:province":"CA",
    "wof:name":"Laguna West Designs",
    "wof:placetype":"venue"
},
  "geometry": {"coordinates":[-117.72514200000001,33.62309],"type":"Point"}
}