{
  "type": "Feature",
  "properties": {
    "iso:country":"US",
    "sg:address":"1194 Maple Ln",
    "sg:city":"Calistoga",
    "sg:classifiers":[
        {
            "category":"Building & Trades",
            "subcategory":"Landscaping Services",
            "type":"Services"
        }
    ],
    "sg:phone":"+1 707 942 6284",
    "sg:postcode":"94515",
    "sg:province":"CA",
    "sg:tags":[
        "tree"
    ],
    "wof:name":"Arnold Tree Service",
    "wof:placetype":"venue"
},
  "geometry": {"coordinates":[-122.53837300000001,38.561194],"type":"Point"}
}