{
  "type": "Feature",
  "properties": {
    "addr:full":"27452 Via Caudaloso Mission Viejo CA 92692",
    "addr:housenumber":"27452",
    "addr:postcode":"92692",
    "addr:street":"Via Caudaloso",
    "iso:country":"US",
    "sg:address":"27452 Via Caudaloso",
    "sg:city":"Mission Viejo",
    "sg:classifiers":[
        {
            "category":"Professional",
            "type":"Services"
        }
    ],
    "sg:phone":"+1 949 768 3323",
    "sg:postcode":"92692",
    "sg:province":"CA",
    "wof:name":"Bernice C Colopy",
    "wof:placetype":"venue"
},
  "geometry": {"coordinates":[-117.652299,33.605707],"type":"Point"}
}