{
  "type": "Feature",
  "properties": {
    "iso:country":"US",
    "sg:address":"1858 Manchester Dr",
    "sg:city":"Redding",
    "sg:classifiers":[
        {
            "category":"Freight",
            "type":"Transportation"
        }
    ],
    "sg:phone":"+1 530 222 3082",
    "sg:postcode":"96002",
    "sg:province":"CA",
    "sg:tags":[
        "operator",
        "local",
        "trucking"
    ],
    "wof:name":"S Denison Trucking",
    "wof:placetype":"venue"
},
  "geometry": {"coordinates":[-122.336788,40.574215],"type":"Point"}
}