{
  "type": "Feature",
  "properties": {
    "iso:country":"US",
    "sg:address":"1991 E Florida Ave",
    "sg:city":"Hemet",
    "sg:classifiers":[
        {
            "category":"Personal",
            "subcategory":"Barber",
            "type":"Services"
        }
    ],
    "sg:phone":"+1 951 658 1059",
    "sg:postcode":"92544",
    "sg:province":"CA",
    "wof:name":"Chuck Leake",
    "wof:placetype":"venue"
},
  "geometry": {"coordinates":[-116.95128200000001,33.747635],"type":"Point"}
}