{
  "type": "Feature",
  "properties": {
    "addr:full":"2255 S Broadway Santa Maria CA 93454",
    "addr:housenumber":"2255",
    "addr:postcode":"93454",
    "addr:street":"S Broadway",
    "iso:country":"US",
    "sg:address":"2255 S Broadway",
    "sg:city":"Santa Maria",
    "sg:classifiers":[
        {
            "category":"Wholesale",
            "subcategory":"Fruits & Vegetables",
            "type":"Manufacturing & Wholesale Goods"
        }
    ],
    "sg:phone":"+1 805 925 3385",
    "sg:postcode":"93454",
    "sg:province":"CA",
    "wof:name":"Valley Produce",
    "wof:placetype":"venue"
},
  "geometry": {"coordinates":[-120.43617999999999,34.919651],"type":"Point"}
}