{
  "type": "Feature",
  "properties": {
    "iso:country":"US",
    "sg:address":"584 Castro St Ste 508",
    "sg:city":"San Francisco",
    "sg:classifiers":[
        {
            "category":"Professional",
            "type":"Services"
        }
    ],
    "sg:phone":"+1 415 287 3402",
    "sg:postcode":"94114",
    "sg:province":"CA",
    "wof:name":"San Francisco Apostille Service",
    "wof:placetype":"venue"
},
  "geometry": {"coordinates":[-122.435031,37.759536],"type":"Point"}
}