{
  "type": "Feature",
  "properties": {
    "iso:country":"US",
    "sg:address":"506 la Tierra Dr",
    "sg:city":"Angwin",
    "sg:classifiers":[
        {
            "category":"Shopping",
            "subcategory":"Hobbies, Toys, & Games",
            "type":"Retail Goods"
        },
        {
            "category":"Recreation",
            "subcategory":"Gun Range",
            "type":"Entertainment"
        }
    ],
    "sg:phone":"+1 707 965 3668",
    "sg:postcode":"94508",
    "sg:province":"CA",
    "sg:tags":[
        "safety",
        "instruction",
        "marksmanship",
        "gunsmith"
    ],
    "wof:name":"Dowswells Firearms",
    "wof:placetype":"venue"
},
  "geometry": {"coordinates":[-122.455848,38.557674],"type":"Point"}
}