{
  "type": "Feature",
  "properties": {
    "addr:full":"21910 Sherman Way Canoga Park CA 91303",
    "addr:housenumber":"21910",
    "addr:postcode":"91303",
    "addr:street":"Sherman Way",
    "iso:country":"US",
    "sg:address":"21910 Sherman Way",
    "sg:city":"Canoga Park",
    "sg:classifiers":[
        {
            "category":"Shopping",
            "subcategory":"Department Store",
            "type":"Retail Goods"
        }
    ],
    "sg:phone":"+1 818 348 7288",
    "sg:postcode":"91303",
    "sg:province":"CA",
    "sg:tags":[
        "shop"
    ],
    "wof:name":"Big Lots",
    "wof:placetype":"venue"
},
  "geometry": {"coordinates":[-118.605727,34.200939],"type":"Point"}
}