{
  "type": "Feature",
  "properties": {
    "iso:country":"US",
    "sg:address":"9147 Olive St",
    "sg:city":"Temple City",
    "sg:classifiers":[
        {
            "category":"Building & Trades",
            "subcategory":"Construction",
            "type":"Services"
        }
    ],
    "sg:phone":"+1 626 286 7625",
    "sg:postcode":"91780",
    "sg:province":"CA",
    "sg:tags":[
        "painter"
    ],
    "wof:name":"Wendell Booher",
    "wof:placetype":"venue"
},
  "geometry": {"coordinates":[-118.06805199999999,34.09672],"type":"Point"}
}