{
  "type": "Feature",
  "properties": {
    "iso:country":"US",
    "sg:address":"3180 S Hacienda Blvd",
    "sg:city":"Hacienda Heights",
    "sg:classifiers":[
        {
            "category":"Real Estate",
            "subcategory":"Real Estate Agent",
            "type":"Services"
        }
    ],
    "sg:phone":"+1 626 855 2530",
    "sg:postcode":"91745",
    "sg:province":"CA",
    "wof:name":"Caldwell Realty-Hacienda Hts",
    "wof:placetype":"venue"
},
  "geometry": {"coordinates":[-117.972723,33.980795],"type":"Point"}
}