{
  "type": "Feature",
  "properties": {
    "iso:country":"US",
    "sg:address":"501 S Fairfax Ave",
    "sg:city":"Los Angeles",
    "sg:classifiers":[
        {
            "category":"Professional",
            "subcategory":"Research",
            "type":"Services"
        }
    ],
    "sg:phone":"+1 323 857 1570",
    "sg:postcode":"90036",
    "sg:province":"CA",
    "sg:tags":[
        "development",
        "marketing",
        "product"
    ],
    "wof:name":"Beverly Dairy Products",
    "wof:placetype":"venue"
},
  "geometry": {"coordinates":[-118.361391,34.066674],"type":"Point"}
}