{
  "type": "Feature",
  "properties": {
    "addr:full":"20101 Valley Blvd Walnut CA 91789",
    "addr:housenumber":"20101",
    "addr:postcode":"91789",
    "addr:street":"Valley Blvd",
    "iso:country":"US",
    "sg:address":"20101 Valley Blvd",
    "sg:city":"Walnut",
    "sg:classifiers":[
        {
            "category":"Home & Garden",
            "subcategory":"Carpets & Floor Coverings",
            "type":"Retail Goods"
        }
    ],
    "sg:phone":"+1 909 595 2456",
    "sg:postcode":"91789",
    "sg:province":"CA",
    "sg:tags":[
        "installation",
        "rug"
    ],
    "sg:website":"http://www.lacarpetandkitchen.com",
    "wof:name":"LA Carpet & Kitchen",
    "wof:placetype":"venue"
},
  "geometry": {"coordinates":[-117.86521500000001,34.006276],"type":"Point"}
}