{
  "type": "Feature",
  "properties": {
    "addr:full":"77 8th St Oakland CA 94607",
    "addr:housenumber":"77",
    "addr:postcode":"94607",
    "addr:street":"8Th St",
    "iso:country":"US",
    "sg:address":"77 8th St",
    "sg:city":"Oakland",
    "sg:classifiers":[
        {
            "category":"Professional",
            "subcategory":"Advertising",
            "type":"Services"
        }
    ],
    "sg:phone":"+1 510 836 2405",
    "sg:postcode":"94607",
    "sg:province":"CA",
    "sg:tags":[
        "distribution"
    ],
    "wof:name":"RNK Distribution",
    "wof:placetype":"venue"
},
  "geometry": {"coordinates":[-122.264729,37.796511],"type":"Point"}
}