{
  "type": "Feature",
  "properties": {
    "addr:full":"28529 Sugar Pine Way Santa Clarita CA 91390",
    "addr:housenumber":"28529",
    "addr:postcode":"91390",
    "addr:street":"Sugar Pine Way",
    "iso:country":"US",
    "sg:address":"28529 Sugar Pine Way",
    "sg:city":"Santa Clarita",
    "sg:classifiers":[
        {
            "category":"Building & Trades",
            "subcategory":"Landscaping Services",
            "type":"Services"
        }
    ],
    "sg:phone":"+1 661 296 1692",
    "sg:postcode":"91390",
    "sg:province":"CA",
    "sg:tags":[
        "landscape"
    ],
    "wof:name":"Taylor Made Grdening Ldscp Svc",
    "wof:placetype":"venue"
},
  "geometry": {"coordinates":[-118.535118,34.469821],"type":"Point"}
}