{
  "type": "Feature",
  "properties": {
    "addr:full":"68785 Ramon Rd Cathedral City CA 92234",
    "addr:housenumber":"68785",
    "addr:postcode":"92234",
    "addr:street":"Ramon Rd",
    "iso:country":"US",
    "sg:address":"68785 Ramon Rd",
    "sg:city":"Cathedral City",
    "sg:classifiers":[
        {
            "category":"Restaurant",
            "type":"Food & Drink"
        }
    ],
    "sg:menulink":"http://www.allmenus.com/ca/cathedral-city-palm-desert/164272-wienerschnitzel/menu/",
    "sg:phone":"+1 760 770 5620",
    "sg:postcode":"92234",
    "sg:province":"CA",
    "sg:tags":[
        "sandwich",
        "dog",
        "burger",
        "hot",
        "wrap",
        "american"
    ],
    "wof:name":"Wienerschnitzel",
    "wof:placetype":"venue"
},
  "geometry": {"coordinates":[-116.461842,33.815664],"type":"Point"}
}