{
  "type": "Feature",
  "properties": {
    "iso:country":"US",
    "sg:address":"2531 Heide Ct",
    "sg:city":"El Sobrante",
    "sg:classifiers":[
        {
            "category":"Banks & Credit Unions",
            "subcategory":"Financial Services",
            "type":"Services"
        }
    ],
    "sg:phone":"+1 510 243 0575",
    "sg:postcode":"94803",
    "sg:province":"CA",
    "sg:tags":[
        "broker",
        "mortgage"
    ],
    "wof:name":"Godiva Loan Associates",
    "wof:placetype":"venue"
},
  "geometry": {"coordinates":[-122.266746,37.951627],"type":"Point"}
}