{
  "type": "Feature",
  "properties": {
    "addr:full":"1821 Hyperion Avenue Los Angeles CA 90027",
    "addr:housenumber":"1821",
    "addr:postcode":"90027",
    "addr:street":"Hyperion Avenue",
    "iso:country":"US",
    "sg:address":"1821 Hyperion Avenue",
    "sg:city":"Los Angeles",
    "sg:classifiers":[
        {
            "category":"Retail",
            "subcategory":"Auto Repair",
            "type":"Services"
        }
    ],
    "sg:phone":"+1 323 665 6275",
    "sg:postcode":"90027",
    "sg:province":"CA",
    "sg:tags":[
        "body",
        "shop"
    ],
    "wof:name":"Elite Body Works",
    "wof:placetype":"venue"
},
  "geometry": {"coordinates":[-118.27636099999999,34.096055],"type":"Point"}
}