{
  "type": "Feature",
  "properties": {
    "iso:country":"US",
    "sg:address":"1134 D St",
    "sg:city":"Ramona",
    "sg:classifiers":[
        {
            "category":"Retail",
            "subcategory":"Veterinary Services",
            "type":"Services"
        }
    ],
    "sg:phone":"+1 760 789 7090",
    "sg:postcode":"92065",
    "sg:province":"CA",
    "wof:name":"Adobe Animal Hospital",
    "wof:placetype":"venue"
},
  "geometry": {"coordinates":[-116.87049399999999,33.039627],"type":"Point"}
}