{
  "type": "Feature",
  "properties": {
    "iso:country":"US",
    "sg:address":"3030 Bonita Rd",
    "sg:city":"National City",
    "sg:classifiers":[
        {
            "category":"Health Services",
            "subcategory":"Clinic",
            "type":"Services"
        }
    ],
    "sg:phone":"+1 619 479 2971",
    "sg:postcode":"91910",
    "sg:province":"CA",
    "sg:tags":[
        "wellness",
        "program"
    ],
    "wof:name":"Comfort & Wellness",
    "wof:placetype":"venue"
},
  "geometry": {"coordinates":[-117.057897,32.647711],"type":"Point"}
}