{
  "type": "Feature",
  "properties": {
    "addr:full":"Rosecrans St & Avenida de Portugal San Diego CA 92106",
    "addr:postcode":"92106",
    "addr:street":"Rosecrans St & Avenida De Portugal",
    "iso:country":"US",
    "sg:address":"Rosecrans St & Avenida de Portugal",
    "sg:city":"San Diego",
    "sg:classifiers":[
        {
            "category":"Restaurant",
            "type":"Food & Drink"
        }
    ],
    "sg:postcode":"92106",
    "sg:province":"CA",
    "sg:tags":[
        "flavor",
        "local"
    ],
    "wof:name":"Jeff Pastorino Memorial Bench",
    "wof:placetype":"venue"
},
  "geometry": {"coordinates":[-117.231453,32.721966],"type":"Point"}
}