{
  "type": "Feature",
  "properties": {
    "addr:full":"142 W 232nd Pl Carson CA 90745",
    "addr:housenumber":"142",
    "addr:postcode":"90745",
    "addr:street":"W 232Nd Pl",
    "iso:country":"US",
    "sg:address":"142 W 232nd Pl",
    "sg:city":"Carson",
    "sg:classifiers":[
        {
            "category":"Insurance",
            "subcategory":"Insurance Agent",
            "type":"Services"
        }
    ],
    "sg:phone":"+1 310 835 2001",
    "sg:postcode":"90745",
    "sg:province":"CA",
    "wof:name":"Primerica Financial Svc",
    "wof:placetype":"venue"
},
  "geometry": {"coordinates":[-118.27996899999999,33.814761],"type":"Point"}
}