{
  "type": "Feature",
  "properties": {
    "addr:full":"3700 San Pablo Ave Hercules CA 94547",
    "addr:housenumber":"3700",
    "addr:postcode":"94547",
    "addr:street":"San Pablo Ave",
    "iso:country":"US",
    "sg:address":"3700 San Pablo Ave",
    "sg:city":"Hercules",
    "sg:classifiers":[
        {
            "category":"Banks & Credit Unions",
            "subcategory":"Bank",
            "type":"Services"
        }
    ],
    "sg:phone":"+1 510 592 0920",
    "sg:postcode":"94547",
    "sg:province":"CA",
    "wof:name":"Flagbank Bank",
    "wof:placetype":"venue"
},
  "geometry": {"coordinates":[-122.27512299999999,38.012542],"type":"Point"}
}