{
  "type": "Feature",
  "properties": {
    "addr:full":"4247 Appian Way El Sobrante CA 94803",
    "addr:housenumber":"4247",
    "addr:postcode":"94803",
    "addr:street":"Appian Way",
    "iso:country":"US",
    "sg:address":"4247 Appian Way",
    "sg:city":"El Sobrante",
    "sg:classifiers":[
        {
            "category":"Banks & Credit Unions",
            "subcategory":"Bank",
            "type":"Services"
        }
    ],
    "sg:phone":"+1 510 262 0189",
    "sg:postcode":"94803",
    "sg:province":"CA",
    "sg:tags":[
        "cashing",
        "check"
    ],
    "wof:name":"Low Fee Check Cashing",
    "wof:placetype":"venue"
},
  "geometry": {"coordinates":[-122.309414,37.966587],"type":"Point"}
}