{
  "type": "Feature",
  "properties": {
    "iso:country":"US",
    "sg:address":"1072 S De Anza Boulevard Suite A206",
    "sg:city":"San Jose",
    "sg:classifiers":[
        {
            "category":"Banks & Credit Unions",
            "subcategory":"Investment Brokerage",
            "type":"Services"
        }
    ],
    "sg:phone":"+1 408 996 1118",
    "sg:postcode":"95129",
    "sg:province":"CA",
    "sg:tags":[
        "investing"
    ],
    "sg:website":"www.infi.biz",
    "wof:name":"Integral Financial",
    "wof:placetype":"venue"
},
  "geometry": {"coordinates":[-122.032149,37.307026],"type":"Point"}
}