{
  "type": "Feature",
  "properties": {
    "iso:country":"US",
    "sg:address":"7760 Fay Ave Ste Q",
    "sg:city":"La Jolla",
    "sg:classifiers":[
        {
            "category":"Personal",
            "subcategory":"Skin Care",
            "type":"Services"
        }
    ],
    "sg:phone":"+1 858 456 9404",
    "sg:postcode":"92037",
    "sg:province":"CA",
    "wof:name":"Irina Skin Care of La Jolla",
    "wof:placetype":"venue"
},
  "geometry": {"coordinates":[-117.275002,32.844299],"type":"Point"}
}