{
  "type": "Feature",
  "properties": {
    "iso:country":"US",
    "sg:address":"108 N Laurel Ave",
    "sg:city":"Ontario",
    "sg:classifiers":[
        {
            "category":"Personal",
            "subcategory":"Beauty Salon",
            "type":"Services"
        }
    ],
    "sg:phone":"+1 909 460 9244",
    "sg:postcode":"91762",
    "sg:province":"CA",
    "wof:name":"XICA Beauty Salon",
    "wof:placetype":"venue"
},
  "geometry": {"coordinates":[-117.65232899999999,34.064483],"type":"Point"}
}