{
  "type": "Feature",
  "properties": {
    "addr:full":"407 W Pacific Coast Hwy Wilmington CA 90744",
    "addr:housenumber":"407",
    "addr:postcode":"90744",
    "addr:street":"W Pacific Coast Hwy",
    "iso:country":"US",
    "sg:address":"407 W Pacific Coast Hwy",
    "sg:city":"Wilmington",
    "sg:classifiers":[
        {
            "category":"Personal",
            "subcategory":"Nail Salon",
            "type":"Services"
        }
    ],
    "sg:phone":"+1 310 513 9829",
    "sg:postcode":"90744",
    "sg:province":"CA",
    "wof:name":"The Beauty Nails & Hari",
    "wof:placetype":"venue"
},
  "geometry": {"coordinates":[-118.266998,33.790798],"type":"Point"}
}