{
  "type": "Feature",
  "properties": {
    "addr:full":"1929 Adams St San Bernardino CA 92407",
    "addr:housenumber":"1929",
    "addr:postcode":"92407",
    "addr:street":"Adams St",
    "iso:country":"US",
    "sg:address":"1929 Adams St",
    "sg:city":"San Bernardino",
    "sg:classifiers":[
        {
            "category":"Building & Trades",
            "subcategory":"Landscaping Services",
            "type":"Services"
        }
    ],
    "sg:phone":"+1 909 496 1026",
    "sg:postcode":"92407",
    "sg:province":"CA",
    "sg:tags":[
        "lawn",
        "maintenance",
        "grounds"
    ],
    "wof:name":"Taufa Landscape & Concrete",
    "wof:placetype":"venue"
},
  "geometry": {"coordinates":[-117.334304,34.137805],"type":"Point"}
}