{
  "type": "Feature",
  "properties": {
    "addr:full":"2183 Vista Way Ste B Oceanside CA 92054",
    "addr:housenumber":"2183",
    "addr:postcode":"92054",
    "addr:street":"Vista Way Ste B",
    "iso:country":"US",
    "sg:address":"2183 Vista Way Ste B",
    "sg:city":"Oceanside",
    "sg:classifiers":[
        {
            "category":"Restaurant",
            "type":"Food & Drink"
        }
    ],
    "sg:phone":"+1 760 757 4992",
    "sg:postcode":"92054",
    "sg:province":"CA",
    "sg:tags":[
        "pizza"
    ],
    "sg:website":"brooklynboyzpizza.com",
    "wof:name":"Brooklyn Boyz Pizza",
    "wof:placetype":"venue"
},
  "geometry": {"coordinates":[-117.340745,33.182539],"type":"Point"}
}