{
  "type": "Feature",
  "properties": {
    "addr:full":"2015 E Hammond Ave Fresno CA 93703",
    "addr:housenumber":"2015",
    "addr:postcode":"93703",
    "addr:street":"E Hammond Ave",
    "iso:country":"US",
    "sg:address":"2015 E Hammond Ave",
    "sg:city":"Fresno",
    "sg:classifiers":[
        {
            "category":"Retail",
            "subcategory":"Repair Shop",
            "type":"Services"
        }
    ],
    "sg:phone":"+1 559 495 1270",
    "sg:postcode":"93703",
    "sg:province":"CA",
    "sg:tags":[
        "related"
    ],
    "wof:name":"Valencia Repair",
    "wof:placetype":"venue"
},
  "geometry": {"coordinates":[-119.78710700000001,36.758707],"type":"Point"}
}