{
  "type": "Feature",
  "properties": {
    "addr:full":"3411 MacArthur Blvd Oakland CA 94602",
    "addr:housenumber":"3411",
    "addr:postcode":"94602",
    "addr:street":"Macarthur Blvd",
    "iso:country":"US",
    "sg:address":"3411 MacArthur Blvd",
    "sg:city":"Oakland",
    "sg:classifiers":[
        {
            "category":"Bars & Pubs",
            "subcategory":"Lounge",
            "type":"Food & Drink"
        }
    ],
    "sg:phone":"+1 510 531 3411",
    "sg:postcode":"94602",
    "sg:province":"CA",
    "wof:name":"Lounge 3411",
    "wof:placetype":"venue"
},
  "geometry": {"coordinates":[-122.201082,37.794218],"type":"Point"}
}