{
  "type": "Feature",
  "properties": {
    "addr:full":"1050 N Batavia St Ste B Orange CA 92867",
    "addr:housenumber":"1050",
    "addr:postcode":"92867",
    "addr:street":"N Batavia St Ste B",
    "iso:country":"US",
    "sg:address":"1050 N Batavia St Ste B",
    "sg:city":"Orange",
    "sg:classifiers":[
        {
            "category":"Shopping",
            "subcategory":"Shoes",
            "type":"Retail Goods"
        }
    ],
    "sg:phone":"+1 714 628 2963",
    "sg:postcode":"92867",
    "sg:province":"CA",
    "sg:tags":[
        "store"
    ],
    "wof:name":"Ellie Shoes",
    "wof:placetype":"venue"
},
  "geometry": {"coordinates":[-117.86199999999999,33.805099],"type":"Point"}
}