{
  "type": "Feature",
  "properties": {
    "addr:full":"7901 S Central Ave Los Angeles CA 90001",
    "addr:housenumber":"7901",
    "addr:postcode":"90001",
    "addr:street":"S Central Ave",
    "iso:country":"US",
    "sg:address":"7901 S Central Ave",
    "sg:city":"Los Angeles",
    "sg:classifiers":[
        {
            "category":"Shopping",
            "subcategory":"Bicycles & Sporting Goods",
            "type":"Retail Goods"
        }
    ],
    "sg:phone":"+1 323 588 9894",
    "sg:postcode":"90001",
    "sg:province":"CA",
    "sg:tags":[
        "bike"
    ],
    "wof:name":"Mother's Bike Shop",
    "wof:placetype":"venue"
},
  "geometry": {"coordinates":[-118.25599699999999,33.967499],"type":"Point"}
}