{
  "type": "Feature",
  "properties": {
    "addr:full":"289 Orange Dr Vacaville CA 95687",
    "addr:housenumber":"289",
    "addr:postcode":"95687",
    "addr:street":"Orange Dr",
    "iso:country":"US",
    "sg:address":"289 Orange Dr",
    "sg:city":"Vacaville",
    "sg:classifiers":[
        {
            "category":"Restaurant",
            "type":"Food & Drink"
        }
    ],
    "sg:menulink":"http://www.allmenus.com/ca/vacaville/171132-carls-jr/menu/",
    "sg:phone":"+1 707 452 1499",
    "sg:postcode":"95687",
    "sg:province":"CA",
    "sg:tags":[
        "burger",
        "american"
    ],
    "wof:name":"Carl's Jr.",
    "wof:placetype":"venue"
},
  "geometry": {"coordinates":[-121.956374,38.369137],"type":"Point"}
}