{
  "type": "Feature",
  "properties": {
    "addr:full":"234 Canada Larga Rd Ventura CA 93001",
    "addr:housenumber":"234",
    "addr:postcode":"93001",
    "addr:street":"Canada Larga Rd",
    "iso:country":"US",
    "sg:address":"234 Canada Larga Rd",
    "sg:city":"Ventura",
    "sg:classifiers":[
        {
            "category":"Farming",
            "subcategory":"Crops",
            "type":"Manufacturing & Wholesale Goods"
        }
    ],
    "sg:phone":"+1 805 643 2942",
    "sg:postcode":"93001",
    "sg:province":"CA",
    "sg:tags":[
        "farm"
    ],
    "wof:name":"Alan Walbridge",
    "wof:placetype":"venue"
},
  "geometry": {"coordinates":[-119.286687,34.341948],"type":"Point"}
}