{
  "type": "Feature",
  "properties": {
    "addr:full":"7751 Sunset Avenue Fair Oaks CA 95628",
    "addr:housenumber":"7751",
    "addr:postcode":"95628",
    "addr:street":"Sunset Avenue",
    "iso:country":"US",
    "sg:address":"7751 Sunset Avenue",
    "sg:city":"Fair Oaks",
    "sg:classifiers":[
        {
            "category":"Retail",
            "subcategory":"Veterinary Services",
            "type":"Services"
        },
        {
            "category":"Retail",
            "subcategory":"Pet Boarding",
            "type":"Services"
        }
    ],
    "sg:phone":"+1 916 967 7768",
    "sg:postcode":"95628",
    "sg:province":"CA",
    "sg:tags":[
        "veterinarian",
        "boarding/pet",
        "sitting"
    ],
    "wof:name":"Marsh Kathleen Vmd",
    "wof:placetype":"venue"
},
  "geometry": {"coordinates":[-121.27977799999999,38.65286],"type":"Point"}
}