{
  "type": "Feature",
  "properties": {
    "iso:country":"US",
    "sg:address":"988 San Antonio Ave",
    "sg:city":"Palo Alto",
    "sg:classifiers":[
        {
            "category":"Shopping",
            "subcategory":"Pharmacy",
            "type":"Retail Goods"
        }
    ],
    "sg:phone":"+1 650 856 4874",
    "sg:postcode":"94303",
    "sg:province":"CA",
    "sg:tags":[
        "pharmaceutical",
        "consultant"
    ],
    "sg:website":"www.validationsystems.com",
    "wof:name":"Validation Systems Inc",
    "wof:placetype":"venue"
},
  "geometry": {"coordinates":[-122.101252,37.424426],"type":"Point"}
}