{
  "type": "Feature",
  "properties": {
    "addr:full":"54325 McKinley Grove Rd Shaver Lake CA 93664",
    "addr:postcode":"54325;93664",
    "addr:street":"Mckinley Grove Rd",
    "iso:country":"US",
    "sg:address":"54325 McKinley Grove Rd",
    "sg:city":"Shaver Lake",
    "sg:classifiers":[
        {
            "category":"Professional",
            "type":"Services"
        }
    ],
    "sg:phone":"+1 559 841 2136",
    "sg:postcode":"93664",
    "sg:province":"CA",
    "sg:tags":[
        "establishment"
    ],
    "wof:name":"MDW Glenn Work Ctr",
    "wof:placetype":"venue"
},
  "geometry": {"coordinates":[-119.153955,37.066135],"type":"Point"}
}