{
  "type": "Feature",
  "properties": {
    "iso:country":"US",
    "sg:address":"831 S Filbert St",
    "sg:city":"Stockton",
    "sg:classifiers":[
        {
            "category":"Building & Trades",
            "subcategory":"Construction",
            "type":"Services"
        }
    ],
    "sg:phone":"+1 209 929 6503",
    "sg:postcode":"95205",
    "sg:province":"CA",
    "sg:tags":[
        "painting",
        "painter",
        "contractor"
    ],
    "wof:name":"Colors Painting & Design",
    "wof:placetype":"venue"
},
  "geometry": {"coordinates":[-121.251042,37.952549],"type":"Point"}
}