{
  "type": "Feature",
  "properties": {
    "iso:country":"US",
    "sg:address":"1333 Noriega St",
    "sg:city":"San Francisco",
    "sg:classifiers":[
        {
            "category":"Building & Trades",
            "subcategory":"Plumbing",
            "type":"Services"
        }
    ],
    "sg:phone":"+1 415 566 3222",
    "sg:postcode":"94122",
    "sg:province":"CA",
    "sg:tags":[
        "conditioning",
        "air",
        "system",
        "contractor"
    ],
    "wof:name":"Noriega Heating & Sheet Metal",
    "wof:placetype":"venue"
},
  "geometry": {"coordinates":[-122.478336,37.754086],"type":"Point"}
}