{
  "type": "Feature",
  "properties": {
    "addr:full":"2016 del Paso Blvd Sacramento CA 95815",
    "addr:housenumber":"2016",
    "addr:postcode":"95815",
    "addr:street":"Del Paso Blvd",
    "iso:country":"US",
    "sg:address":"2016 del Paso Blvd",
    "sg:city":"Sacramento",
    "sg:classifiers":[
        {
            "category":"Shopping",
            "subcategory":"Clothing, Apparel, & Fashions",
            "type":"Retail Goods"
        }
    ],
    "sg:phone":"+1 916 924 3008",
    "sg:postcode":"95815",
    "sg:province":"CA",
    "wof:name":"Holly & Family Fashion Store",
    "wof:placetype":"venue"
},
  "geometry": {"coordinates":[-121.452533,38.609201],"type":"Point"}
}