{
  "type": "Feature",
  "properties": {
    "iso:country":"US",
    "sg:address":"23472 Thornewood Dr",
    "sg:city":"Los Angeles",
    "sg:classifiers":[
        {
            "category":"Building & Trades",
            "subcategory":"Electrical",
            "type":"Services"
        }
    ],
    "sg:phone":"+1 818 244 9660",
    "sg:postcode":"91321",
    "sg:province":"CA",
    "sg:tags":[
        "electrician"
    ],
    "wof:name":"Cayson Industrial Electric",
    "wof:placetype":"venue"
},
  "geometry": {"coordinates":[-118.544107,34.364116],"type":"Point"}
}