{
  "type": "Feature",
  "properties": {
    "addr:full":"9250 Wilshire Boulevard Beverly Hills CA 90212",
    "addr:housenumber":"9250",
    "addr:postcode":"90212",
    "addr:street":"Wilshire Boulevard",
    "iso:country":"US",
    "sg:address":"9250 Wilshire Boulevard",
    "sg:city":"Beverly Hills",
    "sg:classifiers":[
        {
            "category":"Professional",
            "subcategory":"Employment Agencies",
            "type":"Services"
        }
    ],
    "sg:phone":"+1 310 278 0511",
    "sg:postcode":"90212",
    "sg:province":"CA",
    "wof:name":"Star Personnel Services.",
    "wof:placetype":"venue"
},
  "geometry": {"coordinates":[-118.393602,34.067103],"type":"Point"}
}