{
  "type": "Feature",
  "properties": {
    "iso:country":"US",
    "sg:address":"159 Branding Iron Way",
    "sg:city":"Galt",
    "sg:classifiers":[
        {
            "category":"Professional",
            "subcategory":"Computer Services",
            "type":"Services"
        }
    ],
    "sg:phone":"+1 209 745 8927",
    "sg:postcode":"95632",
    "sg:province":"CA",
    "sg:tags":[
        "repair"
    ],
    "wof:name":"WSE Systems",
    "wof:placetype":"venue"
},
  "geometry": {"coordinates":[-121.310841,38.250737],"type":"Point"}
}