{
  "type": "Feature",
  "properties": {
    "iso:country":"US",
    "sg:address":"268 W Olive Ave",
    "sg:city":"Porterville",
    "sg:classifiers":[
        {
            "category":"Autos & Motor Vehicles",
            "subcategory":"Automobile Sales",
            "type":"Retail Goods"
        }
    ],
    "sg:phone":"+1 559 782 8619",
    "sg:postcode":"93257",
    "sg:province":"CA",
    "sg:tags":[
        "car",
        "dealer"
    ],
    "wof:name":"Wes's Used Car",
    "wof:placetype":"venue"
},
  "geometry": {"coordinates":[-119.02229,36.065345],"type":"Point"}
}