{
  "type": "Feature",
  "properties": {
    "addr:full":"1509 S Robertson Blvd Los Angeles CA 90035",
    "addr:housenumber":"1509",
    "addr:postcode":"90035",
    "addr:street":"S Robertson Blvd",
    "iso:country":"US",
    "sg:address":"1509 S Robertson Blvd",
    "sg:city":"Los Angeles",
    "sg:classifiers":[
        {
            "category":"Restaurant",
            "type":"Food & Drink"
        }
    ],
    "sg:phone":"+1 310 407 0404",
    "sg:postcode":"90035",
    "sg:province":"CA",
    "sg:tags":[
        "kosher",
        "vegetarian"
    ],
    "sg:website":"www.nanacaferestaurant.com",
    "wof:name":"Nana Restaurant Cafe",
    "wof:placetype":"venue"
},
  "geometry": {"coordinates":[-118.384142,34.051857],"type":"Point"}
}