{
  "type": "Feature",
  "properties": {
    "iso:country":"US",
    "sg:address":"1900 S Van Ness Ave",
    "sg:city":"Fresno",
    "sg:classifiers":[
        {
            "category":"Building & Trades",
            "subcategory":"Pest Control",
            "type":"Services"
        }
    ],
    "sg:phone":"+1 559 266 3066",
    "sg:postcode":"93721",
    "sg:province":"CA",
    "wof:name":"Spider Guy Inc",
    "wof:placetype":"venue"
},
  "geometry": {"coordinates":[-119.779016,36.72262],"type":"Point"}
}