{
  "type": "Feature",
  "properties": {
    "addr:full":"1102 P St Newman CA 95360",
    "addr:housenumber":"1102 p",
    "addr:postcode":"95360",
    "addr:street":"St",
    "iso:country":"US",
    "sg:address":"1102 P St",
    "sg:city":"Newman",
    "sg:classifiers":[
        {
            "category":"Place Of Worship",
            "subcategory":"Church",
            "type":"Public Place"
        },
        {
            "category":"Place Of Worship",
            "type":"Public Place"
        }
    ],
    "sg:phone":"+1 209 862 3438",
    "sg:postcode":"95360",
    "sg:province":"CA",
    "sg:tags":[
        "lutheran",
        "america",
        "churches-lutheran",
        "churches-lutheran-evangelical"
    ],
    "wof:name":"James Saint Lutheran Church",
    "wof:placetype":"venue"
},
  "geometry": {"coordinates":[-121.025159,37.318063],"type":"Point"}
}