{
  "type": "Feature",
  "properties": {
    "addr:full":"9255 Winnetka Ave Chatsworth CA 91311",
    "addr:housenumber":"9255",
    "addr:postcode":"91311",
    "addr:street":"Winnetka Ave",
    "iso:country":"US",
    "sg:address":"9255 Winnetka Ave",
    "sg:city":"Chatsworth",
    "sg:classifiers":[
        {
            "category":"Restaurant",
            "type":"Food & Drink"
        }
    ],
    "sg:phone":"+1 818 885 6519",
    "sg:postcode":"91311",
    "sg:province":"CA",
    "sg:tags":[
        "grill",
        "style",
        "bar",
        "american",
        "family"
    ],
    "sg:website":"http://www.applebees.com",
    "wof:name":"Applebee's",
    "wof:placetype":"venue"
},
  "geometry": {"coordinates":[-118.571083,34.237638],"type":"Point"}
}