{
  "type": "Feature",
  "properties": {
    "iso:country":"US",
    "sg:address":"4085 Cameron Park Dr",
    "sg:city":"Cameron Park",
    "sg:classifiers":[
        {
            "category":"Restaurant",
            "type":"Food & Drink"
        }
    ],
    "sg:phone":"+1 530 672 2593",
    "sg:postcode":"95682",
    "sg:province":"CA",
    "wof:name":"Sizzler",
    "wof:placetype":"venue"
},
  "geometry": {"coordinates":[-120.96906199999999,38.656883],"type":"Point"}
}