{
  "type": "Feature",
  "properties": {
    "addr:full":"9301 Tampa Ave Northridge CA 91324",
    "addr:housenumber":"9301",
    "addr:postcode":"91324",
    "addr:street":"Tampa Ave",
    "iso:country":"US",
    "sg:address":"9301 Tampa Ave",
    "sg:city":"Northridge",
    "sg:classifiers":[
        {
            "category":"Shopping",
            "subcategory":"Department Store",
            "type":"Retail Goods"
        }
    ],
    "sg:phone":"+1 818 885 1464",
    "sg:postcode":"91324",
    "sg:province":"CA",
    "wof:name":"JC Penney",
    "wof:placetype":"venue"
},
  "geometry": {"coordinates":[-118.55357100000001,34.242742],"type":"Point"}
}