{
  "type": "Feature",
  "properties": {
    "iso:country":"US",
    "sg:address":"845 Promontory Dr W",
    "sg:city":"Newport Beach",
    "sg:classifiers":[
        {
            "category":"Wholesale",
            "subcategory":"Chemicals & Plastics",
            "type":"Manufacturing & Wholesale Goods"
        }
    ],
    "sg:phone":"+1 949 673 7000",
    "sg:postcode":"92660",
    "sg:province":"CA",
    "sg:tags":[
        "business"
    ],
    "wof:name":"Exceltech Inc",
    "wof:placetype":"venue"
},
  "geometry": {"coordinates":[-117.898672,33.614343],"type":"Point"}
}