{
  "type": "Feature",
  "properties": {
    "addr:full":"1801 N Loop Rd Alameda CA 94502",
    "addr:housenumber":"1801",
    "addr:postcode":"94502",
    "addr:street":"N Loop Rd",
    "iso:country":"US",
    "sg:address":"1801 N Loop Rd",
    "sg:city":"Alameda",
    "sg:classifiers":[
        {
            "category":"Education",
            "subcategory":"School",
            "type":"Public Place"
        }
    ],
    "sg:phone":"+1 510 522 0200",
    "sg:postcode":"94502",
    "sg:province":"CA",
    "sg:tags":[
        "interest",
        "religious",
        "private",
        "k-"
    ],
    "wof:name":"Christian Chinese School",
    "wof:placetype":"venue"
},
  "geometry": {"coordinates":[-122.24015799999999,37.727711],"type":"Point"}
}