{
  "type": "Feature",
  "properties": {
    "iso:country":"US",
    "sg:address":"3140 N Argyle Ave",
    "sg:city":"Fresno",
    "sg:classifiers":[
        {
            "category":"Professional",
            "subcategory":"Management & Consulting",
            "type":"Services"
        }
    ],
    "sg:phone":"+1 559 294 7791",
    "sg:postcode":"93727",
    "sg:province":"CA",
    "sg:tags":[
        "consultant",
        "safety"
    ],
    "wof:name":"Life Quest Of California",
    "wof:placetype":"venue"
},
  "geometry": {"coordinates":[-119.694218,36.772701],"type":"Point"}
}