{
  "type": "Feature",
  "properties": {
    "iso:country":"US",
    "sg:address":"32036 Live Oak Canyon Rd",
    "sg:city":"Redlands",
    "sg:classifiers":[
        {
            "category":"Wholesale",
            "subcategory":"Toys & Hobbies",
            "type":"Manufacturing & Wholesale Goods"
        }
    ],
    "sg:phone":"+1 909 795 4279",
    "sg:postcode":"92373",
    "sg:province":"CA",
    "sg:tags":[
        "wholesaler"
    ],
    "wof:name":"Sierra Nursery",
    "wof:placetype":"venue"
},
  "geometry": {"coordinates":[-117.09819400000001,34.015333],"type":"Point"}
}