{
  "type": "Feature",
  "properties": {
    "addr:full":"477 Devlin Rd Napa CA 94558",
    "addr:housenumber":"477",
    "addr:postcode":"94558",
    "addr:street":"Devlin Rd",
    "iso:country":"US",
    "sg:address":"477 Devlin Rd",
    "sg:city":"Napa",
    "sg:classifiers":[
        {
            "category":"Health Services",
            "subcategory":"Doctor",
            "type":"Services"
        }
    ],
    "sg:phone":"+1 707 253 8084",
    "sg:postcode":"94558",
    "sg:province":"CA",
    "sg:tags":[
        "physician",
        "surgeon"
    ],
    "wof:name":"Job Care",
    "wof:placetype":"venue"
},
  "geometry": {"coordinates":[-122.266638,38.238573],"type":"Point"}
}