{
  "type": "Feature",
  "properties": {
    "addr:full":"19622 Stevens Creek Blvd Cupertino CA 95014",
    "addr:housenumber":"19622",
    "addr:postcode":"95014",
    "addr:street":"Stevens Creek Blvd",
    "iso:country":"US",
    "sg:address":"19622 Stevens Creek Blvd",
    "sg:city":"Cupertino",
    "sg:classifiers":[
        {
            "category":"Coffee & Tea",
            "type":"Food & Drink"
        }
    ],
    "sg:phone":"+1 408 446 3185",
    "sg:postcode":"95014",
    "sg:province":"CA",
    "sg:website":"itsagrind.com",
    "wof:name":"It's A Grind",
    "wof:placetype":"venue"
},
  "geometry": {"coordinates":[-122.016537,37.322837],"type":"Point"}
}