{
  "type": "Feature",
  "properties": {
    "addr:full":"3584 Sturgis Rd Oxnard CA 93030",
    "addr:housenumber":"3584",
    "addr:postcode":"93030",
    "addr:street":"Sturgis Rd",
    "iso:country":"US",
    "sg:address":"3584 Sturgis Rd",
    "sg:city":"Oxnard",
    "sg:classifiers":[
        {
            "category":"Professional",
            "type":"Services"
        }
    ],
    "sg:phone":"+1 805 485 8217",
    "sg:postcode":"93030",
    "sg:province":"CA",
    "sg:tags":[
        "establishment"
    ],
    "wof:name":"Chase Production Co",
    "wof:placetype":"venue"
},
  "geometry": {"coordinates":[-119.115848,34.20171],"type":"Point"}
}