{
  "type": "Feature",
  "properties": {
    "addr:full":"607 E Main St Ventura CA 93001",
    "addr:housenumber":"607",
    "addr:postcode":"93001",
    "addr:street":"E Main St",
    "iso:country":"US",
    "sg:address":"607 E Main St",
    "sg:city":"Ventura",
    "sg:classifiers":[
        {
            "category":"Coffee & Tea",
            "type":"Food & Drink"
        }
    ],
    "sg:menulink":"http://www.allmenus.com/ca/ventura/118602-starbucks-coffee/menu/",
    "sg:phone":"+1 805 648 2489",
    "sg:postcode":"93001",
    "sg:province":"CA",
    "sg:tags":[
        "american"
    ],
    "wof:name":"Starbucks Coffee",
    "wof:placetype":"venue"
},
  "geometry": {"coordinates":[-119.291284,34.281098],"type":"Point"}
}