{
  "type": "Feature",
  "properties": {
    "iso:country":"US",
    "sg:address":"10247 Glenoaks Blvd",
    "sg:city":"Pacoima",
    "sg:classifiers":[
        {
            "category":"Building & Trades",
            "subcategory":"Construction",
            "type":"Services"
        },
        {
            "category":"Military Area",
            "subcategory":"Armory",
            "type":"Public Place"
        }
    ],
    "sg:phone":"+1 818 448 4710",
    "sg:postcode":"91331",
    "sg:province":"CA",
    "sg:tags":[
        "repair",
        "fence-sales",
        "fence",
        "contractor"
    ],
    "wof:name":"All Bending Metal Fences",
    "wof:placetype":"venue"
},
  "geometry": {"coordinates":[-118.39471,34.256609],"type":"Point"}
}