{
  "type": "Feature",
  "properties": {
    "iso:country":"US",
    "sg:address":"2480 N 1st St",
    "sg:city":"San Jose",
    "sg:classifiers":[
        {
            "category":"Utilities",
            "subcategory":"Telephone",
            "type":"Services"
        }
    ],
    "sg:phone":"+1 408 382 1400",
    "sg:postcode":"95131",
    "sg:province":"CA",
    "sg:tags":[
        "internet"
    ],
    "wof:name":"123signup AMS",
    "wof:placetype":"venue"
},
  "geometry": {"coordinates":[-121.923358,37.380075],"type":"Point"}
}