{
  "type": "Feature",
  "properties": {
    "addr:full":"1849 Solano Ave Berkeley CA 94707",
    "addr:housenumber":"1849",
    "addr:postcode":"94707",
    "addr:street":"Solano Ave",
    "iso:country":"US",
    "sg:address":"1849 Solano Ave",
    "sg:city":"Berkeley",
    "sg:classifiers":[
        {
            "category":"Retail",
            "subcategory":"Laundry & Dry Cleaning",
            "type":"Services"
        },
        {
            "category":"Home & Garden",
            "subcategory":"Home Furnishings",
            "type":"Retail Goods"
        },
        {
            "category":"Building & Trades",
            "subcategory":"Cleaning & Sanitation",
            "type":"Services"
        },
        {
            "category":"Home & Garden",
            "subcategory":"Carpets & Floor Coverings",
            "type":"Retail Goods"
        }
    ],
    "sg:phone":"+1 510 528 7847",
    "sg:postcode":"94707",
    "sg:province":"CA",
    "sg:tags":[
        "cleaner",
        "decor",
        "rug"
    ],
    "sg:website":"www.solanorugs.com",
    "wof:name":"Solano Oriental Rug Gallery",
    "wof:placetype":"venue"
},
  "geometry": {"coordinates":[-122.278645,37.891524],"type":"Point"}
}