{
  "type": "Feature",
  "properties": {
    "iso:country":"US",
    "sg:address":"833 Santa Paula St",
    "sg:city":"Fillmore",
    "sg:classifiers":[
        {
            "category":"Farming",
            "subcategory":"Farm & Veterinary Services",
            "type":"Manufacturing & Wholesale Goods"
        }
    ],
    "sg:phone":"+1 805 524 2676",
    "sg:postcode":"93015",
    "sg:province":"CA",
    "sg:tags":[
        "management"
    ],
    "wof:name":"Edmonds' Ranch Management",
    "wof:placetype":"venue"
},
  "geometry": {"coordinates":[-118.937602,34.378419],"type":"Point"}
}