{
  "type": "Feature",
  "properties": {
    "addr:full":"2334 Marshall Ave Simi Valley CA 93063",
    "addr:housenumber":"2334",
    "addr:postcode":"93063",
    "addr:street":"Marshall Ave",
    "iso:country":"US",
    "sg:address":"2334 Marshall Ave",
    "sg:city":"Simi Valley",
    "sg:classifiers":[
        {
            "category":"Freight",
            "type":"Transportation"
        }
    ],
    "sg:phone":"+1 805 583 4929",
    "sg:postcode":"93063",
    "sg:province":"CA",
    "sg:tags":[
        "operator",
        "local",
        "trucking"
    ],
    "wof:name":"Juan",
    "wof:placetype":"venue"
},
  "geometry": {"coordinates":[-118.702718,34.275216],"type":"Point"}
}