{
  "type": "Feature",
  "properties": {
    "addr:full":"1370 2nd St Los Osos CA 93402",
    "addr:housenumber":"1370",
    "addr:postcode":"93402",
    "addr:street":"2Nd St",
    "iso:country":"US",
    "sg:address":"1370 2nd St",
    "sg:city":"Los Osos",
    "sg:classifiers":[
        {
            "category":"Travel",
            "subcategory":"Hotels & Motels",
            "type":"Entertainment"
        }
    ],
    "sg:phone":"+1 805 528 8888",
    "sg:postcode":"93402",
    "sg:province":"CA",
    "sg:website":"www.baywoodinn.com",
    "wof:name":"Baywood Bed & Breakfast Inn",
    "wof:placetype":"venue"
},
  "geometry": {"coordinates":[-120.84090399999999,35.32729],"type":"Point"}
}