{
  "type": "Feature",
  "properties": {
    "iso:country":"US",
    "sg:address":"142 E Bonita Ave",
    "sg:city":"San Dimas",
    "sg:classifiers":[
        {
            "category":"Retail",
            "subcategory":"Auto Repair",
            "type":"Services"
        }
    ],
    "sg:phone":"+1 909 388 6620",
    "sg:postcode":"91773",
    "sg:province":"CA",
    "sg:tags":[
        "body",
        "automobile",
        "painting"
    ],
    "wof:name":"Jim's Complete Automotive Rcnd",
    "wof:placetype":"venue"
},
  "geometry": {"coordinates":[-117.805672,34.106593],"type":"Point"}
}