{
  "type": "Feature",
  "properties": {
    "addr:full":"25 County Center Dr Oroville CA 95965",
    "addr:housenumber":"25",
    "addr:postcode":"95965",
    "addr:street":"County Center Dr",
    "iso:country":"US",
    "sg:address":"25 County Center Dr",
    "sg:city":"Oroville",
    "sg:classifiers":[
        {
            "category":"Government",
            "subcategory":"Office",
            "type":"Public Place"
        }
    ],
    "sg:phone":"+1 530 538 7631",
    "sg:postcode":"95965",
    "sg:province":"CA",
    "wof:name":"Butte County Adm Ofc",
    "wof:placetype":"venue"
},
  "geometry": {"coordinates":[-121.570694,39.525115],"type":"Point"}
}