{
  "type": "Feature",
  "properties": {
    "iso:country":"US",
    "sg:address":"3450 Wilshire Blvd",
    "sg:city":"Los Angeles",
    "sg:classifiers":[
        {
            "category":"Insurance",
            "subcategory":"Health Insurance",
            "type":"Services"
        }
    ],
    "sg:phone":"+1 213 380 5922",
    "sg:postcode":"90010",
    "sg:province":"CA",
    "sg:tags":[
        "market"
    ],
    "wof:name":"Kang Bu Group",
    "wof:placetype":"venue"
},
  "geometry": {"coordinates":[-118.299004,34.061798],"type":"Point"}
}