{
  "type": "Feature",
  "properties": {
    "iso:country":"US",
    "sg:address":"33804 Rd 613",
    "sg:city":"Raymond",
    "sg:classifiers":[
        {
            "category":"Wholesale",
            "subcategory":"Hardware",
            "type":"Manufacturing & Wholesale Goods"
        }
    ],
    "sg:phone":"+1 559 689 3533",
    "sg:postcode":"93653",
    "sg:province":"CA",
    "wof:name":"Plammer's Plus",
    "wof:placetype":"venue"
},
  "geometry": {"coordinates":[-119.925015,37.241954],"type":"Point"}
}