{
  "type": "Feature",
  "properties": {
    "iso:country":"US",
    "sg:address":"1120 W Mahalo Place",
    "sg:city":"Compton",
    "sg:classifiers":[
        {
            "category":"Bakery",
            "type":"Food & Drink"
        }
    ],
    "sg:phone":"+1 310 608 1881",
    "sg:postcode":"90220",
    "sg:province":"CA",
    "wof:name":"Bay Cities Italian Bakery",
    "wof:placetype":"venue"
},
  "geometry": {"coordinates":[-118.242791,33.871423],"type":"Point"}
}