{
  "type": "Feature",
  "properties": {
    "iso:country":"US",
    "sg:address":"191 E Jefferson Blvd",
    "sg:city":"Los Angeles",
    "sg:classifiers":[
        {
            "category":"Wholesale",
            "subcategory":"Apparel",
            "type":"Manufacturing & Wholesale Goods"
        }
    ],
    "sg:phone":"+1 323 238 0325",
    "sg:postcode":"90011",
    "sg:province":"CA",
    "sg:tags":[
        "clothing"
    ],
    "wof:name":"Kopac Merchandising Inc",
    "wof:placetype":"venue"
},
  "geometry": {"coordinates":[-118.270335,34.017783],"type":"Point"}
}