{
  "type": "Feature",
  "properties": {
    "iso:country":"US",
    "sg:address":"1290 N Johnson Ave",
    "sg:city":"El Cajon",
    "sg:classifiers":[
        {
            "category":"Wholesale",
            "subcategory":"Sporting Goods",
            "type":"Manufacturing & Wholesale Goods"
        }
    ],
    "sg:phone":"+1 619 593 0872",
    "sg:postcode":"92020",
    "sg:province":"CA",
    "sg:tags":[
        "supply"
    ],
    "wof:name":"Awr Sports LLC",
    "wof:placetype":"venue"
},
  "geometry": {"coordinates":[-116.97107800000001,32.81337],"type":"Point"}
}