{
  "type": "Feature",
  "properties": {
    "iso:country":"US",
    "sg:address":"1028 W Burbank Blvd",
    "sg:city":"Burbank",
    "sg:classifiers":[
        {
            "category":"Autos & Motor Vehicles",
            "subcategory":"Motorcycle Sales",
            "type":"Retail Goods"
        }
    ],
    "sg:phone":"+1 818 559 9610",
    "sg:postcode":"91506",
    "sg:province":"CA",
    "wof:name":"Jet World Dan Fitzgerald",
    "wof:placetype":"venue"
},
  "geometry": {"coordinates":[-118.322998,34.183899],"type":"Point"}
}