{
  "type": "Feature",
  "properties": {
    "addr:full":"246 Broadway San Diego CA 92101",
    "addr:housenumber":"246",
    "addr:postcode":"92101",
    "addr:street":"Broadway",
    "iso:country":"US",
    "sg:address":"246 Broadway",
    "sg:city":"San Diego",
    "sg:classifiers":[
        {
            "category":"Airline",
            "type":"Transportation"
        }
    ],
    "sg:phone":"+1 619 231 0990",
    "sg:postcode":"92101",
    "sg:province":"CA",
    "sg:tags":[
        "company"
    ],
    "wof:name":"Aero Mexico Airlines",
    "wof:placetype":"venue"
},
  "geometry": {"coordinates":[-117.16237700000001,32.71578],"type":"Point"}
}