{
  "type": "Feature",
  "properties": {
    "iso:country":"US",
    "sg:address":"5460 Douglas Blvd",
    "sg:city":"Granite Bay",
    "sg:classifiers":[
        {
            "category":"Retail",
            "subcategory":"Auto Repair",
            "type":"Services"
        }
    ],
    "sg:phone":"+1 916 791 2949",
    "sg:postcode":"95746",
    "sg:province":"CA",
    "sg:tags":[
        "repairing",
        "automobile"
    ],
    "wof:name":"German Specialty Cars",
    "wof:placetype":"venue"
},
  "geometry": {"coordinates":[-121.200504,38.744112],"type":"Point"}
}