{
  "type": "Feature",
  "properties": {
    "iso:country":"US",
    "sg:address":"536 N Cedros Ave",
    "sg:city":"Solana Beach",
    "sg:classifiers":[
        {
            "category":"Building & Trades",
            "subcategory":"Construction",
            "type":"Services"
        }
    ],
    "sg:phone":"+1 858 794 9910",
    "sg:postcode":"92075",
    "sg:province":"CA",
    "sg:tags":[
        "contractor"
    ],
    "wof:name":"Endurance Masonry",
    "wof:placetype":"venue"
},
  "geometry": {"coordinates":[-117.27251099999999,32.997576],"type":"Point"}
}