{
  "type": "Feature",
  "properties": {
    "addr:full":"155 Valley View Ave San Jose CA 95127",
    "addr:housenumber":"155",
    "addr:postcode":"95127",
    "addr:street":"Valley View Ave",
    "iso:country":"US",
    "sg:address":"155 Valley View Ave",
    "sg:city":"San Jose",
    "sg:classifiers":[
        {
            "category":"Professional",
            "subcategory":"Advertising",
            "type":"Services"
        }
    ],
    "sg:phone":"+1 408 254 1234",
    "sg:postcode":"95127",
    "sg:province":"CA",
    "sg:tags":[
        "guide"
    ],
    "wof:name":"What 2 Do Guide",
    "wof:placetype":"venue"
},
  "geometry": {"coordinates":[-121.82329300000001,37.380937],"type":"Point"}
}