{
  "type": "Feature",
  "properties": {
    "iso:country":"US",
    "sg:address":"41350 Christy St",
    "sg:city":"Fremont",
    "sg:classifiers":[
        {
            "category":"Restaurant",
            "type":"Food & Drink"
        }
    ],
    "sg:phone":"+1 510 490 8040",
    "sg:postcode":"94538",
    "sg:province":"CA",
    "sg:tags":[
        "delicatessen"
    ],
    "wof:name":"Service Cafe",
    "wof:placetype":"venue"
},
  "geometry": {"coordinates":[-121.982596,37.514594],"type":"Point"}
}