{
  "type": "Feature",
  "properties": {
    "addr:full":"1700 Market St Oakland CA 94607",
    "addr:housenumber":"1700",
    "addr:postcode":"94607",
    "addr:street":"Market St",
    "iso:country":"US",
    "sg:address":"1700 Market St",
    "sg:city":"Oakland",
    "sg:classifiers":[
        {
            "category":"Education",
            "subcategory":"School",
            "type":"Public Place"
        }
    ],
    "sg:phone":"+1 510 879 1290",
    "sg:postcode":"94607",
    "sg:province":"CA",
    "sg:tags":[
        "high",
        "middle",
        "elementary"
    ],
    "sg:website":"www.ousd.k12.ca.us",
    "wof:name":"Oakland Public Schools",
    "wof:placetype":"venue"
},
  "geometry": {"coordinates":[-122.279815,37.81032],"type":"Point"}
}