{
  "type": "Feature",
  "properties": {
    "iso:country":"US",
    "sg:address":"1419 Solano Ave",
    "sg:city":"Albany",
    "sg:classifiers":[
        {
            "category":"Real Estate",
            "subcategory":"Real Estate Agent",
            "type":"Services"
        }
    ],
    "sg:phone":"+1 510 558 8378",
    "sg:postcode":"94706",
    "sg:province":"CA",
    "sg:website":"www.alohabay.net",
    "wof:name":"Aloha Bay Realty",
    "wof:placetype":"venue"
},
  "geometry": {"coordinates":[-122.289756,37.89078],"type":"Point"}
}