{
  "type": "Feature",
  "properties": {
    "iso:country":"US",
    "sg:address":"6801 Hollywood Blvd Ste 119",
    "sg:city":"Los Angeles",
    "sg:classifiers":[
        {
            "category":"Shopping",
            "subcategory":"Optician",
            "type":"Retail Goods"
        },
        {
            "category":"Shopping",
            "subcategory":"Clothing, Apparel, & Fashions",
            "type":"Retail Goods"
        }
    ],
    "sg:phone":"+1 323 962 5716",
    "sg:postcode":"90028",
    "sg:province":"CA",
    "sg:tags":[
        "eyewear",
        "accessory"
    ],
    "wof:name":"Sun's Up",
    "wof:placetype":"venue"
},
  "geometry": {"coordinates":[-118.243425,34.052187],"type":"Point"}
}