{
  "type": "Feature",
  "properties": {
    "addr:full":"330 Euclid Ave Oakland CA 94610",
    "addr:housenumber":"330",
    "addr:postcode":"94610",
    "addr:street":"Euclid Ave",
    "iso:country":"US",
    "sg:address":"330 Euclid Ave",
    "sg:city":"Oakland",
    "sg:classifiers":[
        {
            "category":"Social Services",
            "subcategory":"Child Care",
            "type":"Services"
        }
    ],
    "sg:phone":"+1 510 763 7528",
    "sg:postcode":"94610",
    "sg:province":"CA",
    "sg:tags":[
        "kindergarten",
        "academic",
        "school"
    ],
    "wof:name":"Gan Avraham",
    "wof:placetype":"venue"
},
  "geometry": {"coordinates":[-122.252672,37.813804],"type":"Point"}
}