{
  "type": "Feature",
  "properties": {
    "addr:full":"6632 E Parlier Ave Fowler CA 93625",
    "addr:housenumber":"6632",
    "addr:postcode":"93625",
    "addr:street":"E Parlier Ave",
    "iso:country":"US",
    "sg:address":"6632 E Parlier Ave",
    "sg:city":"Fowler",
    "sg:classifiers":[
        {
            "category":"Freight",
            "type":"Transportation"
        }
    ],
    "sg:phone":"+1 559 834 5969",
    "sg:postcode":"93625",
    "sg:province":"CA",
    "sg:tags":[
        "hauler",
        "contract"
    ],
    "wof:name":"W O Saxton Trucking",
    "wof:placetype":"venue"
},
  "geometry": {"coordinates":[-119.67692,36.612772],"type":"Point"}
}