{
  "type": "Feature",
  "properties": {
    "addr:full":"426 S Mills Rd Ventura CA 93003",
    "addr:housenumber":"426",
    "addr:postcode":"93003",
    "addr:street":"S Mills Rd",
    "iso:country":"US",
    "sg:address":"426 S Mills Rd",
    "sg:city":"Ventura",
    "sg:classifiers":[
        {
            "category":"Place Of Worship",
            "type":"Public Place"
        }
    ],
    "sg:phone":"+1 805 642 3244",
    "sg:postcode":"93003",
    "sg:province":"CA",
    "sg:tags":[
        "church"
    ],
    "sg:website":"http://www.fbcventura.org",
    "wof:name":"Coastline Bible Church",
    "wof:placetype":"venue"
},
  "geometry": {"coordinates":[-119.246737,34.268412],"type":"Point"}
}