{
  "type": "Feature",
  "properties": {
    "iso:country":"US",
    "sg:address":"1093 Broxton Ave",
    "sg:city":"Los Angeles",
    "sg:classifiers":[
        {
            "category":"Personal",
            "type":"Services"
        }
    ],
    "sg:phone":"+1 310 208 7923",
    "sg:postcode":"90024",
    "sg:province":"CA",
    "sg:tags":[
        "sewing",
        "alteration"
    ],
    "wof:name":"Vittorio Tailor Shop",
    "wof:placetype":"venue"
},
  "geometry": {"coordinates":[-118.445999,34.060699],"type":"Point"}
}