{
  "type": "Feature",
  "properties": {
    "iso:country":"US",
    "sg:address":"1615 Bonanza St",
    "sg:city":"Walnut Creek",
    "sg:classifiers":[
        {
            "category":"Professional",
            "subcategory":"Accounting & Tax Preparation",
            "type":"Services"
        }
    ],
    "sg:phone":"+1 925 935 1028",
    "sg:postcode":"94596",
    "sg:province":"CA",
    "sg:tags":[
        "accountant"
    ],
    "wof:name":"Jewell & Langasdale",
    "wof:placetype":"venue"
},
  "geometry": {"coordinates":[-122.063345,37.899256],"type":"Point"}
}