{
  "type": "Feature",
  "properties": {
    "iso:country":"US",
    "sg:address":"540 S Topanga Canyon Blvd",
    "sg:city":"Topanga",
    "sg:classifiers":[
        {
            "category":"Real Estate",
            "subcategory":"Real Estate Agent",
            "type":"Services"
        }
    ],
    "sg:phone":"+1 310 663 9039",
    "sg:postcode":"90290",
    "sg:province":"CA",
    "sg:website":"www.topangacynhomes.com",
    "wof:name":"Prudential Malibu Realty",
    "wof:placetype":"venue"
},
  "geometry": {"coordinates":[-118.59906100000001,34.08375],"type":"Point"}
}