{
  "type": "Feature",
  "properties": {
    "addr:full":"9135 Alabama Ave Chatsworth CA 91311",
    "addr:housenumber":"9135",
    "addr:postcode":"91311",
    "addr:street":"Alabama Ave",
    "iso:country":"US",
    "sg:address":"9135 Alabama Ave",
    "sg:city":"Chatsworth",
    "sg:classifiers":[
        {
            "category":"Wholesale",
            "subcategory":"Non-durable Goods",
            "type":"Manufacturing & Wholesale Goods"
        }
    ],
    "sg:phone":"+1 818 772 4600",
    "sg:postcode":"91311",
    "sg:province":"CA",
    "sg:tags":[
        "leather"
    ],
    "wof:name":"Cinema Leathers Inc",
    "wof:placetype":"venue"
},
  "geometry": {"coordinates":[-118.59985500000001,34.238455],"type":"Point"}
}