{
  "type": "Feature",
  "properties": {
    "iso:country":"US",
    "sg:address":"20739 Lycoming St",
    "sg:city":"Walnut",
    "sg:classifiers":[
        {
            "category":"Real Estate",
            "subcategory":"Real Estate Operator",
            "type":"Services"
        }
    ],
    "sg:phone":"+1 909 595 2753",
    "sg:postcode":"91789",
    "sg:province":"CA",
    "sg:tags":[
        "mobile",
        "home",
        "community"
    ],
    "wof:name":"Walnut Creek Mobile Estates",
    "wof:placetype":"venue"
},
  "geometry": {"coordinates":[-117.855133,34.002974],"type":"Point"}
}