{
  "type": "Feature",
  "properties": {
    "iso:country":"US",
    "sg:address":"982 Park Row",
    "sg:city":"Salinas",
    "sg:classifiers":[
        {
            "category":"Personal",
            "subcategory":"Beauty Salon",
            "type":"Services"
        }
    ],
    "sg:phone":"+1 831 424 7073",
    "sg:postcode":"93901",
    "sg:province":"CA",
    "wof:name":"Kelly R Borzini",
    "wof:placetype":"venue"
},
  "geometry": {"coordinates":[-121.659525,36.663237],"type":"Point"}
}