{
  "type": "Feature",
  "properties": {
    "addr:full":"33156 Condor Dr Union City CA 94587",
    "addr:postcode":"33156;94587",
    "addr:street":"Condor Dr",
    "iso:country":"US",
    "sg:address":"33156 Condor Dr",
    "sg:city":"Union City",
    "sg:classifiers":[
        {
            "category":"Freight",
            "type":"Transportation"
        }
    ],
    "sg:phone":"+1 510 487 6356",
    "sg:postcode":"94587",
    "sg:province":"CA",
    "wof:name":"Randhawa Transport",
    "wof:placetype":"venue"
},
  "geometry": {"coordinates":[-122.041706,37.591536],"type":"Point"}
}