{
  "type": "Feature",
  "properties": {
    "addr:full":"10619 Sierra Dr Grass Valley CA 95945",
    "addr:housenumber":"10619",
    "addr:postcode":"95945",
    "addr:street":"Sierra Dr",
    "iso:country":"US",
    "sg:address":"10619 Sierra Dr",
    "sg:city":"Grass Valley",
    "sg:classifiers":[
        {
            "category":"Social Services",
            "subcategory":"Adult Care",
            "type":"Services"
        }
    ],
    "sg:phone":"+1 530 273 7820",
    "sg:postcode":"95945",
    "sg:province":"CA",
    "sg:tags":[
        "home",
        "residential"
    ],
    "wof:name":"Mountain View Wecare Home",
    "wof:placetype":"venue"
},
  "geometry": {"coordinates":[-121.076166,39.233024],"type":"Point"}
}