{
  "type": "Feature",
  "properties": {
    "iso:country":"US",
    "sg:address":"875 Westbourne Drive",
    "sg:city":"West Hollywood",
    "sg:classifiers":[
        {
            "category":"Shopping",
            "subcategory":"Used Merchandise",
            "type":"Retail Goods"
        }
    ],
    "sg:phone":"+1 310 358 0102",
    "sg:postcode":"90069",
    "sg:province":"CA",
    "sg:tags":[
        "vintage",
        "consignment"
    ],
    "wof:name":"The Paper Bag Princess",
    "wof:placetype":"venue"
},
  "geometry": {"coordinates":[-118.379648,34.086385],"type":"Point"}
}