{
  "type": "Feature",
  "properties": {
    "addr:full":"156 16th Ave San Francisco CA 94118",
    "addr:housenumber":"156",
    "addr:postcode":"94118",
    "addr:street":"16Th Ave",
    "iso:country":"US",
    "sg:address":"156 16th Ave",
    "sg:city":"San Francisco",
    "sg:classifiers":[
        {
            "category":"Social Services",
            "type":"Services"
        }
    ],
    "sg:phone":"+1 415 387 6434",
    "sg:postcode":"94118",
    "sg:province":"CA",
    "sg:tags":[
        "worker"
    ],
    "wof:name":"Charlotte Prozan",
    "wof:placetype":"venue"
},
  "geometry": {"coordinates":[-122.475356,37.785387],"type":"Point"}
}