{
  "type": "Feature",
  "properties": {
    "addr:full":"2190 Addison Ave East Palo Alto CA 94303",
    "addr:housenumber":"2190",
    "addr:postcode":"94303",
    "addr:street":"Addison Ave",
    "iso:country":"US",
    "sg:address":"2190 Addison Ave",
    "sg:city":"East Palo Alto",
    "sg:classifiers":[
        {
            "category":"Utilities",
            "subcategory":"Water",
            "type":"Services"
        }
    ],
    "sg:phone":"+1 650 322 6903",
    "sg:postcode":"94303",
    "sg:province":"CA",
    "sg:tags":[
        "company",
        "sewage"
    ],
    "wof:name":"Palo Alto Park Mutual Water Co",
    "wof:placetype":"venue"
},
  "geometry": {"coordinates":[-122.14841699999999,37.465464],"type":"Point"}
}