{
  "type": "Feature",
  "properties": {
    "addr:full":"1401 N Shoreline Blvd Mountain View CA 94043",
    "addr:housenumber":"1401",
    "addr:postcode":"94043",
    "addr:street":"N Shoreline Blvd",
    "iso:country":"US",
    "sg:address":"1401 N Shoreline Blvd",
    "sg:city":"Mountain View",
    "sg:classifiers":[
        {
            "category":"Museum",
            "type":"Entertainment"
        }
    ],
    "sg:phone":"+1 650 810 1010",
    "sg:postcode":"94043",
    "sg:province":"CA",
    "sg:website":"www.computerhistory.org",
    "wof:name":"Computer History Museum",
    "wof:placetype":"venue"
},
  "geometry": {"coordinates":[-122.078003,37.415001],"type":"Point"}
}