{
  "type": "Feature",
  "properties": {
    "iso:country":"US",
    "sg:address":"11205 Imperial Hwy",
    "sg:city":"Norwalk",
    "sg:classifiers":[
        {
            "category":"Building & Trades",
            "subcategory":"Electrical",
            "type":"Services"
        }
    ],
    "sg:phone":"+1 562 863 5829",
    "sg:postcode":"90650",
    "sg:province":"CA",
    "sg:tags":[
        "electric",
        "contractor"
    ],
    "sg:website":"www.downeyelectric.com",
    "wof:name":"Downey Electric",
    "wof:placetype":"venue"
},
  "geometry": {"coordinates":[-118.092964,33.916958],"type":"Point"}
}