{
  "type": "Feature",
  "properties": {
    "iso:country":"US",
    "sg:address":"8547 Melvin Ave",
    "sg:city":"Northridge",
    "sg:classifiers":[
        {
            "category":"Health Services",
            "subcategory":"Clinic",
            "type":"Services"
        }
    ],
    "sg:phone":"+1 818 727 1597",
    "sg:postcode":"91324",
    "sg:province":"CA",
    "sg:tags":[
        "home"
    ],
    "wof:name":"My Sunshine Board & Care Hm",
    "wof:placetype":"venue"
},
  "geometry": {"coordinates":[-118.560033,34.22668],"type":"Point"}
}