{
  "type": "Feature",
  "properties": {
    "iso:country":"US",
    "sg:address":"14411 Palmdale Rd",
    "sg:city":"Victorville",
    "sg:classifiers":[
        {
            "category":"Building & Trades",
            "subcategory":"Construction",
            "type":"Services"
        }
    ],
    "sg:phone":"+1 760 843 8118",
    "sg:postcode":"92392",
    "sg:province":"CA",
    "sg:tags":[
        "equipment",
        "supply",
        "drywall",
        "contractor"
    ],
    "wof:name":"Advanced Drywall",
    "wof:placetype":"venue"
},
  "geometry": {"coordinates":[-117.34854900000001,34.50671],"type":"Point"}
}