{
  "type": "Feature",
  "properties": {
    "addr:full":"9295 Rock Springs Rd Newcastle CA 95658",
    "addr:housenumber":"9295",
    "addr:postcode":"95658",
    "addr:street":"Rock Springs Rd",
    "iso:country":"US",
    "sg:address":"9295 Rock Springs Rd",
    "sg:city":"Newcastle",
    "sg:classifiers":[
        {
            "category":"Transit Center",
            "subcategory":"Freight",
            "type":"Transportation"
        },
        {
            "category":"Freight",
            "type":"Transportation"
        }
    ],
    "sg:phone":"+1 916 663 2033",
    "sg:postcode":"95658",
    "sg:province":"CA",
    "sg:tags":[
        "trucking-motor",
        "trucking"
    ],
    "wof:name":"Storm Trucking",
    "wof:placetype":"venue"
},
  "geometry": {"coordinates":[-121.129516,38.840069],"type":"Point"}
}