{
  "type": "Feature",
  "properties": {
    "iso:country":"US",
    "sg:address":"2052 S Willow Ave",
    "sg:city":"Fresno",
    "sg:classifiers":[
        {
            "category":"Education",
            "subcategory":"School",
            "type":"Public Place"
        }
    ],
    "sg:phone":"+1 559 251 8982",
    "sg:postcode":"93727",
    "sg:province":"CA",
    "sg:tags":[
        "academic",
        "special"
    ],
    "wof:name":"Fresno County Office-Education",
    "wof:placetype":"venue"
},
  "geometry": {"coordinates":[-119.727536,36.723765],"type":"Point"}
}