{
  "type": "Feature",
  "properties": {
    "iso:country":"US",
    "sg:address":"1212 Arcane St",
    "sg:city":"Simi Valley",
    "sg:classifiers":[
        {
            "category":"Building & Trades",
            "subcategory":"Landscaping Services",
            "type":"Services"
        }
    ],
    "sg:phone":"+1 805 579 7333",
    "sg:postcode":"93065",
    "sg:province":"CA",
    "sg:tags":[
        "tree"
    ],
    "wof:name":"Austin Reed's Tree Care",
    "wof:placetype":"venue"
},
  "geometry": {"coordinates":[-118.774903,34.260833],"type":"Point"}
}