{
  "type": "Feature",
  "properties": {
    "iso:country":"US",
    "sg:address":"300 Hutchison St",
    "sg:city":"Barstow",
    "sg:classifiers":[
        {
            "category":"Place Of Worship",
            "type":"Public Place"
        }
    ],
    "sg:phone":"+1 760 253 7616",
    "sg:postcode":"92311",
    "sg:province":"CA",
    "sg:tags":[
        "church"
    ],
    "wof:name":"Zion Aphostolic Church",
    "wof:placetype":"venue"
},
  "geometry": {"coordinates":[-117.02446,34.90136],"type":"Point"}
}