{
  "type": "Feature",
  "properties": {
    "addr:full":"4157 S Central Ave Los Angeles CA 90011",
    "addr:housenumber":"4157",
    "addr:postcode":"90011",
    "addr:street":"S Central Ave",
    "iso:country":"US",
    "sg:address":"4157 S Central Ave",
    "sg:city":"Los Angeles",
    "sg:classifiers":[
        {
            "category":"Shopping",
            "subcategory":"Clothing, Apparel, & Fashions",
            "type":"Retail Goods"
        }
    ],
    "sg:phone":"+1 323 846 8033",
    "sg:postcode":"90011",
    "sg:province":"CA",
    "wof:name":"D & G Fashion",
    "wof:placetype":"venue"
},
  "geometry": {"coordinates":[-118.25656499999999,34.007647],"type":"Point"}
}