{
  "type": "Feature",
  "properties": {
    "iso:country":"US",
    "sg:address":"240 Sunday Dr",
    "sg:city":"Berry Creek",
    "sg:classifiers":[
        {
            "category":"Shopping",
            "type":"Retail Goods"
        }
    ],
    "sg:phone":"+1 530 589 9000",
    "sg:postcode":"95916",
    "sg:province":"CA",
    "sg:tags":[
        "awning",
        "canopy"
    ],
    "wof:name":"Rontimco Com",
    "wof:placetype":"venue"
},
  "geometry": {"coordinates":[-121.45835099999999,39.606352],"type":"Point"}
}