{
  "type": "Feature",
  "properties": {
    "iso:country":"US",
    "sg:address":"414 S Los Angeles St",
    "sg:city":"Los Angeles",
    "sg:classifiers":[
        {
            "category":"Wholesale",
            "subcategory":"Jewelry",
            "type":"Manufacturing & Wholesale Goods"
        }
    ],
    "sg:phone":"+1 213 687 3098",
    "sg:postcode":"90013",
    "sg:province":"CA",
    "sg:tags":[
        "stone"
    ],
    "wof:name":"Pacific Waves",
    "wof:placetype":"venue"
},
  "geometry": {"coordinates":[-118.24659,34.046906],"type":"Point"}
}