{
  "type": "Feature",
  "properties": {
    "addr:full":"25141 Sweet Grass Dr Moreno Valley CA 92553",
    "addr:housenumber":"25141",
    "addr:postcode":"92553",
    "addr:street":"Sweet Grass Dr",
    "iso:country":"US",
    "sg:address":"25141 Sweet Grass Dr",
    "sg:city":"Moreno Valley",
    "sg:classifiers":[
        {
            "category":"Manufacturing",
            "subcategory":"Tools & Machinery",
            "type":"Manufacturing & Wholesale Goods"
        }
    ],
    "sg:phone":"+1 951 334 8584",
    "sg:postcode":"92553",
    "sg:province":"CA",
    "sg:tags":[
        "measuring",
        "instrument",
        "electrical",
        "mfg"
    ],
    "wof:name":"Elite Professional Networks",
    "wof:placetype":"venue"
},
  "geometry": {"coordinates":[-117.22269300000001,33.922271],"type":"Point"}
}