{
  "type": "Feature",
  "properties": {
    "addr:full":"17171 Foothill Blvd Fontana CA 92335",
    "addr:housenumber":"17171",
    "addr:postcode":"92335",
    "addr:street":"Foothill Blvd",
    "iso:country":"US",
    "sg:address":"17171 Foothill Blvd",
    "sg:city":"Fontana",
    "sg:classifiers":[
        {
            "category":"Health Services",
            "subcategory":"Doctor",
            "type":"Services"
        }
    ],
    "sg:phone":"+1 909 356 5757",
    "sg:postcode":"92335",
    "sg:province":"CA",
    "sg:tags":[
        "physician",
        "surgeon"
    ],
    "wof:name":"Inland Healthcare Group",
    "wof:placetype":"venue"
},
  "geometry": {"coordinates":[-117.428538,34.106574],"type":"Point"}
}