{
  "type": "Feature",
  "properties": {
    "iso:country":"US",
    "sg:address":"110 Calistoga Rd",
    "sg:city":"Santa Rosa",
    "sg:classifiers":[
        {
            "category":"Shopping",
            "subcategory":"Jewelry",
            "type":"Retail Goods"
        }
    ],
    "sg:phone":"+1 707 539 7452",
    "sg:postcode":"95409",
    "sg:province":"CA",
    "sg:tags":[
        "designer"
    ],
    "wof:name":"Pasdera Custom Jewelers",
    "wof:placetype":"venue"
},
  "geometry": {"coordinates":[-122.653402,38.465939],"type":"Point"}
}