{
  "type": "Feature",
  "properties": {
    "addr:full":"762 S Broadway Los Angeles CA 90014",
    "addr:housenumber":"762",
    "addr:postcode":"90014",
    "addr:street":"S Broadway",
    "iso:country":"US",
    "sg:address":"762 S Broadway",
    "sg:city":"Los Angeles",
    "sg:classifiers":[
        {
            "category":"Shopping",
            "subcategory":"Jewelry",
            "type":"Retail Goods"
        }
    ],
    "sg:phone":"+1 213 688 7710",
    "sg:postcode":"90014",
    "sg:province":"CA",
    "sg:website":"www.lindasjewelry.com",
    "wof:name":"Linda's Jewelry",
    "wof:placetype":"venue"
},
  "geometry": {"coordinates":[-118.25455599999999,34.043909],"type":"Point"}
}