{
  "type": "Feature",
  "properties": {
    "addr:full":"1260 57th Ave Unit B Oakland CA 94621",
    "addr:housenumber":"1260",
    "addr:postcode":"94621",
    "addr:street":"57Th Ave Unit B",
    "iso:country":"US",
    "sg:address":"1260 57th Ave Unit B",
    "sg:city":"Oakland",
    "sg:classifiers":[
        {
            "category":"Manufacturing",
            "subcategory":"Apparel",
            "type":"Manufacturing & Wholesale Goods"
        }
    ],
    "sg:phone":"+1 510 432 9211",
    "sg:postcode":"94621",
    "sg:province":"CA",
    "sg:tags":[
        "clothing-men's-wholesale",
        "manufacturer"
    ],
    "sg:website":"http://www.calclothings.com",
    "wof:name":"California Clothing Collection",
    "wof:placetype":"venue"
},
  "geometry": {"coordinates":[-122.20406199999999,37.76448],"type":"Point"}
}