{
  "type": "Feature",
  "properties": {
    "addr:full":"2484 Shattuck Ave Berkeley CA 94704",
    "addr:housenumber":"2484",
    "addr:postcode":"94704",
    "addr:street":"Shattuck Ave",
    "iso:country":"US",
    "sg:address":"2484 Shattuck Ave",
    "sg:city":"Berkeley",
    "sg:classifiers":[
        {
            "category":"Health Services",
            "subcategory":"Health Practitioner",
            "type":"Services"
        }
    ],
    "sg:phone":"+1 510 339 3260",
    "sg:postcode":"94704",
    "sg:province":"CA",
    "sg:tags":[
        "psychotherapist"
    ],
    "wof:name":"Cindy Sachs",
    "wof:placetype":"venue"
},
  "geometry": {"coordinates":[-122.267601,37.864612],"type":"Point"}
}