{
  "type": "Feature",
  "properties": {
    "addr:full":"2080 Harbison Dr Vacaville CA 95687",
    "addr:housenumber":"2080",
    "addr:postcode":"95687",
    "addr:street":"Harbison Dr",
    "iso:country":"US",
    "sg:address":"2080 Harbison Dr",
    "sg:city":"Vacaville",
    "sg:classifiers":[
        {
            "category":"Shopping",
            "type":"Retail Goods"
        }
    ],
    "sg:phone":"+1 707 446 1502",
    "sg:postcode":"95687",
    "sg:province":"CA",
    "sg:tags":[
        "telephone",
        "cellular"
    ],
    "wof:name":"Radio Shack",
    "wof:placetype":"venue"
},
  "geometry": {"coordinates":[-121.964376,38.363033],"type":"Point"}
}