{
  "type": "Feature",
  "properties": {
    "iso:country":"US",
    "sg:address":"44236 10th St W",
    "sg:city":"Lancaster",
    "sg:classifiers":[
        {
            "category":"Utilities",
            "subcategory":"Mobile Phone",
            "type":"Services"
        },
        {
            "category":"Communications",
            "type":"Services"
        }
    ],
    "sg:phone":"+1 661 942 0180",
    "sg:postcode":"93534",
    "sg:province":"CA",
    "sg:tags":[
        "telephone",
        "cellular"
    ],
    "wof:name":"Wireless Quick Svc",
    "wof:placetype":"venue"
},
  "geometry": {"coordinates":[-118.147989,34.686034],"type":"Point"}
}