{
  "type": "Feature",
  "properties": {
    "addr:full":"2511 E Cesar E Chavez Ave Los Angeles CA 90033",
    "addr:housenumber":"2511",
    "addr:postcode":"90033",
    "addr:street":"E Cesar E Chavez Ave",
    "iso:country":"US",
    "sg:address":"2511 E Cesar E Chavez Ave",
    "sg:city":"Los Angeles",
    "sg:classifiers":[
        {
            "category":"Travel",
            "subcategory":"Travel Agent",
            "type":"Entertainment"
        }
    ],
    "sg:phone":"+1 323 265 3096",
    "sg:postcode":"90033",
    "sg:province":"CA",
    "sg:tags":[
        "agency"
    ],
    "wof:name":"Link Group Inc",
    "wof:placetype":"venue"
},
  "geometry": {"coordinates":[-118.205298,34.045792],"type":"Point"}
}