{
  "type": "Feature",
  "properties": {
    "addr:full":"4566 Salida Blvd Salida CA 95368",
    "addr:housenumber":"4566",
    "addr:postcode":"95368",
    "addr:street":"Salida Blvd",
    "iso:country":"US",
    "sg:address":"4566 Salida Blvd",
    "sg:city":"Salida",
    "sg:classifiers":[
        {
            "category":"Retail",
            "subcategory":"Veterinary Services",
            "type":"Services"
        }
    ],
    "sg:phone":"+1 209 545 9590",
    "sg:postcode":"95368",
    "sg:province":"CA",
    "sg:tags":[
        "hospital",
        "animal"
    ],
    "wof:name":"Salida Veterinary Hospital",
    "wof:placetype":"venue"
},
  "geometry": {"coordinates":[-121.07824100000001,37.70382],"type":"Point"}
}