{
  "type": "Feature",
  "properties": {
    "iso:country":"US",
    "sg:address":"703 W Anaheim St",
    "sg:city":"Wilmington",
    "sg:classifiers":[
        {
            "category":"Shopping",
            "subcategory":"Discount & Variety Stores",
            "type":"Retail Goods"
        }
    ],
    "sg:phone":"+1 310 830 9840",
    "sg:postcode":"90744",
    "sg:province":"CA",
    "wof:name":"Wilmington Discount",
    "wof:placetype":"venue"
},
  "geometry": {"coordinates":[-118.269891,33.779568],"type":"Point"}
}