{
  "type": "Feature",
  "properties": {
    "iso:country":"US",
    "sg:address":"2908 E Whitmore Ave Ste H",
    "sg:city":"Ceres",
    "sg:classifiers":[
        {
            "category":"Professional",
            "subcategory":"Lawyer & Legal Services",
            "type":"Services"
        },
        {
            "category":"Professional",
            "subcategory":"Printing & Photocopies",
            "type":"Services"
        }
    ],
    "sg:phone":"+1 209 537 9040",
    "sg:postcode":"95307",
    "sg:province":"CA",
    "sg:tags":[
        "notary"
    ],
    "wof:name":"Ups Store the",
    "wof:placetype":"venue"
},
  "geometry": {"coordinates":[-120.94000200000001,37.5947],"type":"Point"}
}