{
  "type": "Feature",
  "properties": {
    "addr:full":"763 Parma Way Los Altos CA 94024",
    "addr:housenumber":"763",
    "addr:postcode":"94024",
    "addr:street":"Parma Way",
    "iso:country":"US",
    "sg:address":"763 Parma Way",
    "sg:city":"Los Altos",
    "sg:classifiers":[
        {
            "category":"Professional",
            "subcategory":"Computer Services",
            "type":"Services"
        }
    ],
    "sg:phone":"+1 650 947 7755",
    "sg:postcode":"94024",
    "sg:province":"CA",
    "sg:tags":[
        "communications",
        "datum",
        "system"
    ],
    "wof:name":"Criterion Network Svc",
    "wof:placetype":"venue"
},
  "geometry": {"coordinates":[-122.098816,37.369909],"type":"Point"}
}