{
  "type": "Feature",
  "properties": {
    "iso:country":"US",
    "sg:address":"409 Alberto Way",
    "sg:city":"Los Gatos",
    "sg:classifiers":[
        {
            "category":"Professional",
            "subcategory":"Art Services",
            "type":"Services"
        }
    ],
    "sg:phone":"+1 408 354 1555",
    "sg:postcode":"95032",
    "sg:province":"CA",
    "sg:tags":[
        "artist"
    ],
    "wof:name":"Susan Jaekel Illustrations",
    "wof:placetype":"venue"
},
  "geometry": {"coordinates":[-121.972317,37.226275],"type":"Point"}
}