{
  "type": "Feature",
  "properties": {
    "iso:country":"US",
    "sg:address":"1901 E Shields Ave",
    "sg:city":"Fresno",
    "sg:classifiers":[
        {
            "category":"Health Services",
            "subcategory":"Doctor",
            "type":"Services"
        }
    ],
    "sg:phone":"+1 559 226 2626",
    "sg:postcode":"93726",
    "sg:province":"CA",
    "sg:tags":[
        "dentist"
    ],
    "wof:name":"Smile Care",
    "wof:placetype":"venue"
},
  "geometry": {"coordinates":[-119.78784400000001,36.779736],"type":"Point"}
}