{
  "type": "Feature",
  "properties": {
    "addr:full":"4765 J St Sacramento CA 95819",
    "addr:housenumber":"4765",
    "addr:postcode":"95819",
    "addr:street":"J St",
    "iso:country":"US",
    "sg:address":"4765 J St",
    "sg:city":"Sacramento",
    "sg:classifiers":[
        {
            "category":"Home & Garden",
            "subcategory":"Furniture",
            "type":"Retail Goods"
        }
    ],
    "sg:phone":"+1 916 457 7400",
    "sg:postcode":"95819",
    "sg:province":"CA",
    "sg:tags":[
        "store"
    ],
    "wof:name":"Room & Company",
    "wof:placetype":"venue"
},
  "geometry": {"coordinates":[-121.444,38.5672],"type":"Point"}
}