{
  "type": "Feature",
  "properties": {
    "addr:full":"21323 Hawthorne Boulevard Los Angeles CA 90001",
    "addr:housenumber":"21323",
    "addr:postcode":"90001",
    "addr:street":"Hawthorne Boulevard",
    "iso:country":"US",
    "sg:address":"21323 Hawthorne Boulevard",
    "sg:city":"Los Angeles",
    "sg:classifiers":[
        {
            "category":"Banks & Credit Unions",
            "subcategory":"Bank",
            "type":"Services"
        }
    ],
    "sg:phone":"+1 310 540 9615",
    "sg:postcode":"90001",
    "sg:province":"CA",
    "wof:name":"Wells Fargo Bank Na",
    "wof:placetype":"venue"
},
  "geometry": {"coordinates":[-118.248999,33.974767],"type":"Point"}
}