{
  "type": "Feature",
  "properties": {
    "addr:full":"900 Rock Ave San Jose CA 95131",
    "addr:housenumber":"900",
    "addr:postcode":"95131",
    "addr:street":"Rock Ave",
    "iso:country":"US",
    "sg:address":"900 Rock Ave",
    "sg:city":"San Jose",
    "sg:classifiers":[
        {
            "category":"Professional",
            "subcategory":"Printing & Photocopies",
            "type":"Services"
        }
    ],
    "sg:phone":"+1 408 456 6999",
    "sg:postcode":"95131",
    "sg:province":"CA",
    "sg:website":"www.diamondpress.biz",
    "wof:name":"Diamond Press & Printing",
    "wof:placetype":"venue"
},
  "geometry": {"coordinates":[-121.90586999999999,37.390756],"type":"Point"}
}