{
  "type": "Feature",
  "properties": {
    "iso:country":"US",
    "sg:address":"1754 S Grande Vista Ave",
    "sg:city":"Los Angeles",
    "sg:classifiers":[
        {
            "category":"Retail",
            "subcategory":"Auto Repair",
            "type":"Services"
        }
    ],
    "sg:phone":"+1 323 268 1137",
    "sg:postcode":"90023",
    "sg:province":"CA",
    "sg:tags":[
        "truck"
    ],
    "wof:name":"A & F Truck Repair",
    "wof:placetype":"venue"
},
  "geometry": {"coordinates":[-118.208115,34.01507],"type":"Point"}
}