{
  "type": "Feature",
  "properties": {
    "iso:country":"US",
    "sg:address":"12052 Hesperia Rd",
    "sg:city":"Hesperia",
    "sg:classifiers":[
        {
            "category":"Recreation",
            "type":"Entertainment"
        }
    ],
    "sg:phone":"+1 760 956 3432",
    "sg:postcode":"92345",
    "sg:province":"CA",
    "sg:tags":[
        "martial",
        "arts",
        "instruction"
    ],
    "wof:name":"Kim's Hapkido",
    "wof:placetype":"venue"
},
  "geometry": {"coordinates":[-117.292059,34.470887],"type":"Point"}
}