{
  "type": "Feature",
  "properties": {
    "addr:full":"12052 Hesperia Rd Hesperia CA 92345",
    "addr:housenumber":"12052",
    "addr:postcode":"92345",
    "addr:street":"Hesperia Rd",
    "iso:country":"US",
    "sg:address":"12052 Hesperia Rd",
    "sg:city":"Hesperia",
    "sg:classifiers":[
        {
            "category":"Recreation",
            "type":"Entertainment"
        }
    ],
    "sg:phone":"+1 760 956 3432",
    "sg:postcode":"92345",
    "sg:province":"CA",
    "sg:tags":[
        "martial",
        "arts",
        "instruction"
    ],
    "wof:name":"Kim's Hapkido",
    "wof:placetype":"venue"
},
  "geometry": {"coordinates":[-117.29205899999999,34.470887],"type":"Point"}
}