{
  "type": "Feature",
  "properties": {
    "addr:full":"12843 State Hwy 99 Red Bluff CA 96080",
    "addr:housenumber":"12843",
    "addr:postcode":"96080",
    "addr:street":"State Hwy 99",
    "iso:country":"US",
    "sg:address":"12843 State Hwy 99",
    "sg:city":"Red Bluff",
    "sg:classifiers":[
        {
            "category":"Farming",
            "subcategory":"Orchard",
            "type":"Manufacturing & Wholesale Goods"
        }
    ],
    "sg:phone":"+1 530 529 1269",
    "sg:postcode":"96080",
    "sg:province":"CA",
    "sg:tags":[
        "grove",
        "nut",
        "fruit",
        "tree"
    ],
    "wof:name":"Pierce Orchard",
    "wof:placetype":"venue"
},
  "geometry": {"coordinates":[-122.156977,40.167186],"type":"Point"}
}