{
  "type": "Feature",
  "properties": {
    "iso:country":"US",
    "sg:address":"1245 Oakmead Pkwy",
    "sg:city":"Sunnyvale",
    "sg:classifiers":[
        {
            "category":"Wholesale",
            "subcategory":"Computers",
            "type":"Manufacturing & Wholesale Goods"
        }
    ],
    "sg:phone":"+1 408 523 6000",
    "sg:postcode":"94085",
    "sg:province":"CA",
    "wof:name":"Ambex Venture Group",
    "wof:placetype":"venue"
},
  "geometry": {"coordinates":[-121.99299600000001,37.387001],"type":"Point"}
}