{
  "type": "Feature",
  "properties": {
    "iso:country":"US",
    "sg:address":"1437 Freedom Blvd",
    "sg:city":"Watsonville",
    "sg:classifiers":[
        {
            "category":"Utilities",
            "subcategory":"Mobile Phone",
            "type":"Services"
        }
    ],
    "sg:phone":"+1 831 722 4411",
    "sg:postcode":"95076",
    "sg:province":"CA",
    "sg:tags":[
        "communication",
        "radiotelephone"
    ],
    "wof:name":"Mucho Cellular",
    "wof:placetype":"venue"
},
  "geometry": {"coordinates":[-121.76488999999999,36.926625],"type":"Point"}
}