{
  "type": "Feature",
  "properties": {
    "iso:country":"US",
    "sg:address":"114 N Palm Ave",
    "sg:city":"Santa Paula",
    "sg:classifiers":[
        {
            "category":"Real Estate",
            "subcategory":"Real Estate Agent",
            "type":"Services"
        }
    ],
    "sg:phone":"+1 805 933 6600",
    "sg:postcode":"93060",
    "sg:province":"CA",
    "wof:name":"Re/Max Gold Coast Realtors",
    "wof:placetype":"venue"
},
  "geometry": {"coordinates":[-119.071682,34.350243],"type":"Point"}
}