{
  "type": "Feature",
  "properties": {
    "addr:full":"14450 Griffith St San Leandro CA 94577",
    "addr:housenumber":"14450",
    "addr:postcode":"94577",
    "addr:street":"Griffith St",
    "iso:country":"US",
    "sg:address":"14450 Griffith St",
    "sg:city":"San Leandro",
    "sg:classifiers":[
        {
            "category":"Wholesale",
            "subcategory":"Machinery & Supplies",
            "type":"Manufacturing & Wholesale Goods"
        }
    ],
    "sg:phone":"+1 510 483 9917",
    "sg:postcode":"94577",
    "sg:province":"CA",
    "sg:tags":[
        "construction",
        "fastener",
        "industrial",
        "suppl",
        "threaded"
    ],
    "wof:name":"Fastenal Company",
    "wof:placetype":"venue"
},
  "geometry": {"coordinates":[-122.169527,37.696313],"type":"Point"}
}