{
  "type": "Feature",
  "properties": {
    "iso:country":"US",
    "sg:address":"1030 N Columbia Ave",
    "sg:city":"Claremont",
    "sg:classifiers":[
        {
            "category":"Education",
            "subcategory":"College",
            "type":"Public Place"
        }
    ],
    "sg:phone":"+1 909 621 8149",
    "sg:postcode":"91711",
    "sg:province":"CA",
    "sg:tags":[
        "academic",
        "school"
    ],
    "wof:name":"Scripps College",
    "wof:placetype":"venue"
},
  "geometry": {"coordinates":[-117.711431,34.104365],"type":"Point"}
}