{
  "type": "Feature",
  "properties": {
    "addr:full":"542 S Pacific St San Marcos CA 92078",
    "addr:housenumber":"542",
    "addr:postcode":"92078",
    "addr:street":"S Pacific St",
    "iso:country":"US",
    "sg:address":"542 S Pacific St",
    "sg:city":"San Marcos",
    "sg:classifiers":[
        {
            "category":"Organizations",
            "subcategory":"Religious Organization",
            "type":"Services"
        }
    ],
    "sg:phone":"+1 760 510 1777",
    "sg:postcode":"92078",
    "sg:province":"CA",
    "sg:tags":[
        "church"
    ],
    "wof:name":"Faith Tabernacle Apostolic Inc",
    "wof:placetype":"venue"
},
  "geometry": {"coordinates":[-117.19741,33.133524],"type":"Point"}
}