{
  "type": "Feature",
  "properties": {
    "addr:full":"2581 Nut Tree Rd (Suite A) Vacaville CA 95687",
    "addr:housenumber":"2581",
    "addr:postcode":"95687",
    "addr:street":"Nut Tree Rd Suite A",
    "iso:country":"US",
    "sg:address":"2581 Nut Tree Rd (Suite A)",
    "sg:city":"Vacaville",
    "sg:classifiers":[
        {
            "category":"Health Services",
            "subcategory":"Dentist",
            "type":"Services"
        }
    ],
    "sg:phone":"+1 707 448 9211",
    "sg:postcode":"95687",
    "sg:province":"CA",
    "sg:tags":[
        "dentists-cosmetic",
        "dentistry"
    ],
    "sg:website":"http://www.dentalmakeovers.com",
    "wof:name":"Dr. Randy Johnson's Center for Contemporary Dentistry",
    "wof:placetype":"venue"
},
  "geometry": {"coordinates":[-121.953211,38.334317],"type":"Point"}
}