{
  "type": "Feature",
  "properties": {
    "iso:country":"US",
    "sg:address":"5820 Mission St",
    "sg:city":"San Francisco",
    "sg:classifiers":[
        {
            "category":"Restaurant",
            "type":"Food & Drink"
        }
    ],
    "sg:phone":"+1 415 333 7869",
    "sg:postcode":"94112",
    "sg:province":"CA",
    "wof:name":"Ly Luck Chinese Restaurant",
    "wof:placetype":"venue"
},
  "geometry": {"coordinates":[-122.451639,37.709259],"type":"Point"}
}