{
  "type": "Feature",
  "properties": {
    "addr:full":"1693 Branham Lane San Jose CA 95118",
    "addr:housenumber":"1693",
    "addr:postcode":"95118",
    "addr:street":"Branham Lane",
    "iso:country":"US",
    "sg:address":"1693 Branham Lane",
    "sg:city":"San Jose",
    "sg:classifiers":[
        {
            "category":"Retail",
            "subcategory":"Laundry & Dry Cleaning",
            "type":"Services"
        }
    ],
    "sg:phone":"+1 408 448 1882",
    "sg:postcode":"95118",
    "sg:province":"CA",
    "wof:name":"Holiday Cleaners",
    "wof:placetype":"venue"
},
  "geometry": {"coordinates":[-121.905159,37.251193],"type":"Point"}
}