{
  "type": "Feature",
  "properties": {
    "addr:full":"3444 Camino Del Rio N San Diego CA 92108",
    "addr:housenumber":"3444",
    "addr:postcode":"92108",
    "addr:street":"Camino Del Rio N",
    "iso:country":"US",
    "sg:address":"3444 Camino Del Rio N",
    "sg:city":"San Diego",
    "sg:classifiers":[
        {
            "category":"Professional",
            "subcategory":"Lawyer & Legal Services",
            "type":"Services"
        }
    ],
    "sg:phone":"+1 619 284 8811",
    "sg:postcode":"92108",
    "sg:province":"CA",
    "wof:name":"John A Attorney",
    "wof:placetype":"venue"
},
  "geometry": {"coordinates":[-117.121189,32.777543],"type":"Point"}
}