{
  "type": "Feature",
  "properties": {
    "iso:country":"US",
    "sg:address":"981 Fremont Street",
    "sg:city":"Santa Clara",
    "sg:classifiers":[
        {
            "category":"Professional",
            "subcategory":"Lawyer & Legal Services",
            "type":"Services"
        }
    ],
    "sg:phone":"+1 408 984 8555",
    "sg:postcode":"95050",
    "sg:province":"CA",
    "wof:name":"Johnson David Attorney At Law",
    "wof:placetype":"venue"
},
  "geometry": {"coordinates":[-121.945278,37.351661],"type":"Point"}
}