{
  "type": "Feature",
  "properties": {
    "iso:country":"US",
    "sg:address":"2590 N 1st St",
    "sg:city":"San Jose",
    "sg:classifiers":[
        {
            "category":"Utilities",
            "subcategory":"Mobile Phone",
            "type":"Services"
        }
    ],
    "sg:phone":"+1 408 243 7710",
    "sg:postcode":"95131",
    "sg:province":"CA",
    "sg:tags":[
        "communication",
        "radiotelephone"
    ],
    "wof:name":"Verizon",
    "wof:placetype":"venue"
},
  "geometry": {"coordinates":[-121.925324,37.382753],"type":"Point"}
}