{
  "type": "Feature",
  "properties": {
    "addr:full":"290 N Benson Ave Upland CA 91786",
    "addr:housenumber":"290",
    "addr:postcode":"91786",
    "addr:street":"N Benson Ave",
    "iso:country":"US",
    "sg:address":"290 N Benson Ave",
    "sg:city":"Upland",
    "sg:classifiers":[
        {
            "category":"Wholesale",
            "subcategory":"Office Equipment",
            "type":"Manufacturing & Wholesale Goods"
        },
        {
            "category":"Shopping",
            "subcategory":"Computers & Home Electronics",
            "type":"Retail Goods"
        }
    ],
    "sg:phone":"+1 909 982 0161",
    "sg:postcode":"91786",
    "sg:province":"CA",
    "sg:tags":[
        "scanning",
        "printer",
        "plotting",
        "supply"
    ],
    "wof:name":"Akhil International",
    "wof:placetype":"venue"
},
  "geometry": {"coordinates":[-117.68092300000001,34.097375],"type":"Point"}
}