{
  "type": "Feature",
  "properties": {
    "iso:country":"US",
    "sg:address":"1206 W Flint St",
    "sg:city":"Lake Elsinore",
    "sg:classifiers":[
        {
            "category":"Autos & Motor Vehicles",
            "subcategory":"Auto Supplies",
            "type":"Retail Goods"
        },
        {
            "category":"Retail",
            "subcategory":"Auto Repair",
            "type":"Services"
        }
    ],
    "sg:phone":"+1 951 245 7522",
    "sg:postcode":"92530",
    "sg:province":"CA",
    "sg:tags":[
        "tire"
    ],
    "wof:name":"Value Automotive",
    "wof:placetype":"venue"
},
  "geometry": {"coordinates":[-117.337997,33.678902],"type":"Point"}
}