{
  "type": "Feature",
  "properties": {
    "addr:full":"50 S San Mateo Dr San Mateo CA 94401",
    "addr:housenumber":"50",
    "addr:postcode":"94401",
    "addr:street":"S San Mateo Dr",
    "iso:country":"US",
    "sg:address":"50 S San Mateo Dr",
    "sg:city":"San Mateo",
    "sg:classifiers":[
        {
            "category":"Health Services",
            "subcategory":"Doctor",
            "type":"Services"
        }
    ],
    "sg:phone":"+1 650 342 4145",
    "sg:postcode":"94401",
    "sg:province":"CA",
    "wof:name":"Glasgow Tiffany MD",
    "wof:placetype":"venue"
},
  "geometry": {"coordinates":[-122.325996,37.566601],"type":"Point"}
}