{
  "type": "Feature",
  "properties": {
    "addr:full":"285 Richfield Dr San Jose CA 95129",
    "addr:housenumber":"285",
    "addr:postcode":"95129",
    "addr:street":"Richfield Dr",
    "iso:country":"US",
    "sg:address":"285 Richfield Dr",
    "sg:city":"San Jose",
    "sg:classifiers":[
        {
            "category":"Real Estate",
            "subcategory":"Real Estate Operator",
            "type":"Services"
        }
    ],
    "sg:phone":"+1 408 246 5656",
    "sg:postcode":"95129",
    "sg:province":"CA",
    "sg:tags":[
        "apartment"
    ],
    "wof:name":"Florentine Villa Apartments",
    "wof:placetype":"venue"
},
  "geometry": {"coordinates":[-121.98400100000001,37.3204],"type":"Point"}
}