{
  "type": "Feature",
  "properties": {
    "addr:full":"4 West 4th Avenue Suite 206 San Mateo CA 94402",
    "addr:housenumber":"4",
    "addr:postcode":"94402",
    "addr:street":"West 4Th Avenue Suite 206",
    "iso:country":"US",
    "sg:address":"4 West 4th Avenue Suite 206",
    "sg:city":"San Mateo",
    "sg:classifiers":[
        {
            "category":"Professional",
            "subcategory":"Computer Services",
            "type":"Services"
        }
    ],
    "sg:postcode":"94402",
    "sg:province":"CA",
    "sg:tags":[
        "radio",
        "music",
        "social"
    ],
    "sg:website":"http://www.jelli.com",
    "wof:name":"Jelli",
    "wof:placetype":"venue"
},
  "geometry": {"coordinates":[-122.326888,37.561139],"type":"Point"}
}