{
  "type": "Feature",
  "properties": {
    "addr:full":"2797 Castro Valley Blvd Castro Valley CA 94546",
    "addr:housenumber":"2797",
    "addr:postcode":"94546",
    "addr:street":"Castro Valley Blvd",
    "iso:country":"US",
    "sg:address":"2797 Castro Valley Blvd",
    "sg:city":"Castro Valley",
    "sg:classifiers":[
        {
            "category":"Personal",
            "subcategory":"Beauty Salon",
            "type":"Services"
        }
    ],
    "sg:phone":"+1 510 581 7053",
    "sg:postcode":"94546",
    "sg:province":"CA",
    "sg:tags":[
        "care",
        "skin"
    ],
    "wof:name":"Evelyne's Results Skin Care",
    "wof:placetype":"venue"
},
  "geometry": {"coordinates":[-122.084,37.695],"type":"Point"}
}