{
  "type": "Feature",
  "properties": {
    "iso:country":"US",
    "sg:address":"7329 Gabbiano Ln",
    "sg:city":"Carlsbad",
    "sg:classifiers":[
        {
            "category":"Autos & Motor Vehicles",
            "subcategory":"Auto Supplies",
            "type":"Retail Goods"
        }
    ],
    "sg:phone":"+1 760 476 0112",
    "sg:postcode":"92011",
    "sg:province":"CA",
    "sg:tags":[
        "automobile",
        "part",
        "accessory"
    ],
    "wof:name":"Advance Auto Center",
    "wof:placetype":"venue"
},
  "geometry": {"coordinates":[-117.30226999999999,33.095719],"type":"Point"}
}