{
  "type": "Feature",
  "properties": {
    "addr:full":"307 N Montgomery St Ojai CA 93023",
    "addr:housenumber":"307",
    "addr:postcode":"93023",
    "addr:street":"N Montgomery St",
    "iso:country":"US",
    "sg:address":"307 N Montgomery St",
    "sg:city":"Ojai",
    "sg:classifiers":[
        {
            "category":"Professional",
            "subcategory":"Business Services",
            "type":"Services"
        },
        {
            "category":"Wholesale",
            "subcategory":"Books, Periodicals, & Newspapers",
            "type":"Manufacturing & Wholesale Goods"
        }
    ],
    "sg:phone":"+1 805 646 8179",
    "sg:postcode":"93023",
    "sg:province":"CA",
    "sg:tags":[
        "consultant",
        "publishing",
        "representative",
        "publisher"
    ],
    "wof:name":"William Samuel Foundation",
    "wof:placetype":"venue"
},
  "geometry": {"coordinates":[-119.242949,34.449993],"type":"Point"}
}