{
  "type": "Feature",
  "properties": {
    "iso:country":"US",
    "sg:address":"2065 W Shaw Ave",
    "sg:city":"Fresno",
    "sg:classifiers":[
        {
            "category":"Wholesale",
            "subcategory":"Machinery & Supplies",
            "type":"Manufacturing & Wholesale Goods"
        }
    ],
    "sg:phone":"+1 559 225 9783",
    "sg:postcode":"93711",
    "sg:province":"CA",
    "sg:tags":[
        "salon",
        "beauty"
    ],
    "sg:website":"www.sallybeauty.com",
    "wof:name":"Sally Beauty Supply",
    "wof:placetype":"venue"
},
  "geometry": {"coordinates":[-119.828958,36.808193],"type":"Point"}
}