{
  "type": "Feature",
  "properties": {
    "addr:full":"17230 Ballinger St Northridge CA 91325",
    "addr:housenumber":"17230",
    "addr:postcode":"91325",
    "addr:street":"Ballinger St",
    "iso:country":"US",
    "sg:address":"17230 Ballinger St",
    "sg:city":"Northridge",
    "sg:classifiers":[
        {
            "category":"Wholesale",
            "subcategory":"Durable Goods & Equipment",
            "type":"Manufacturing & Wholesale Goods"
        }
    ],
    "sg:phone":"+1 818 998 6789",
    "sg:postcode":"91325",
    "sg:province":"CA",
    "sg:tags":[
        "slide",
        "rule"
    ],
    "wof:name":"Arth-O-Graf",
    "wof:placetype":"venue"
},
  "geometry": {"coordinates":[-118.510665,34.243606],"type":"Point"}
}