{
  "type": "Feature",
  "properties": {
    "iso:country":"US",
    "sg:address":"755 N Waterman Ave",
    "sg:city":"San Bernardino",
    "sg:classifiers":[
        {
            "category":"Wholesale",
            "subcategory":"Auto Parts",
            "type":"Manufacturing & Wholesale Goods"
        }
    ],
    "sg:phone":"+1 909 884 5211",
    "sg:postcode":"92410",
    "sg:province":"CA",
    "sg:tags":[
        "automobile",
        "wrecking"
    ],
    "wof:name":"American Auto Wrecking",
    "wof:placetype":"venue"
},
  "geometry": {"coordinates":[-117.278789,34.115815],"type":"Point"}
}