{
  "type": "Feature",
  "properties": {
    "addr:full":"11380 Cam Playa Cancun San Diego CA 92124",
    "addr:housenumber":"11380",
    "addr:postcode":"92124",
    "addr:street":"Cam Playa Cancun",
    "iso:country":"US",
    "sg:address":"11380 Cam Playa Cancun",
    "sg:city":"San Diego",
    "sg:classifiers":[
        {
            "category":"Banks & Credit Unions",
            "subcategory":"Financial Services",
            "type":"Services"
        }
    ],
    "sg:phone":"+1 858 277 6758",
    "sg:postcode":"92124",
    "sg:province":"CA",
    "sg:tags":[
        "trust",
        "management"
    ],
    "wof:name":"Berlin Virginia E Trust",
    "wof:placetype":"venue"
},
  "geometry": {"coordinates":[-117.082988,32.839287],"type":"Point"}
}