{
  "type": "Feature",
  "properties": {
    "addr:full":"14818 Huston St Sherman Oaks CA 91403",
    "addr:postcode":"14818;91403",
    "addr:street":"Huston St",
    "iso:country":"US",
    "sg:address":"14818 Huston St",
    "sg:city":"Sherman Oaks",
    "sg:classifiers":[
        {
            "category":"Professional",
            "type":"Services"
        }
    ],
    "sg:phone":"+1 818 986 2238",
    "sg:postcode":"91403",
    "sg:province":"CA",
    "wof:name":"Nifni",
    "wof:placetype":"venue"
},
  "geometry": {"coordinates":[-118.457041,34.159335],"type":"Point"}
}