{
  "type": "Feature",
  "properties": {
    "iso:country":"US",
    "sg:address":"426 N Minnesota Ave",
    "sg:city":"Glendora",
    "sg:classifiers":[
        {
            "category":"Professional",
            "type":"Services"
        }
    ],
    "sg:phone":"+1 626 937 2038",
    "sg:postcode":"91741",
    "sg:province":"CA",
    "wof:name":"Landview Visual Communica",
    "wof:placetype":"venue"
},
  "geometry": {"coordinates":[-117.861395,34.141569],"type":"Point"}
}