{
  "type": "Feature",
  "properties": {
    "iso:country":"US",
    "sg:address":"2627 Mission St",
    "sg:city":"San Marino",
    "sg:classifiers":[
        {
            "category":"Building & Trades",
            "subcategory":"Construction",
            "type":"Services"
        }
    ],
    "sg:phone":"+1 626 799 8447",
    "sg:postcode":"91108",
    "sg:province":"CA",
    "sg:tags":[
        "interior",
        "design"
    ],
    "wof:name":"Santana Interior",
    "wof:placetype":"venue"
},
  "geometry": {"coordinates":[-118.13745299999999,34.116176],"type":"Point"}
}