{
  "type": "Feature",
  "properties": {
    "addr:full":"732 Brannan St San Francisco CA 94103",
    "addr:housenumber":"732",
    "addr:postcode":"94103",
    "addr:street":"Brannan St",
    "iso:country":"US",
    "sg:address":"732 Brannan St",
    "sg:city":"San Francisco",
    "sg:classifiers":[
        {
            "category":"Government",
            "subcategory":"Court House",
            "type":"Public Place"
        }
    ],
    "sg:phone":"+1 415 551 9595",
    "sg:postcode":"94103",
    "sg:province":"CA",
    "sg:tags":[
        "city",
        "counsel"
    ],
    "wof:name":"District Attorney-Special Oper",
    "wof:placetype":"venue"
},
  "geometry": {"coordinates":[-122.401765,37.774354],"type":"Point"}
}