{
  "type": "Feature",
  "properties": {
    "iso:country":"US",
    "sg:address":"11425 Cull Canyon Rd",
    "sg:city":"Castro Valley",
    "sg:classifiers":[
        {
            "category":"Retail",
            "subcategory":"Animal Services",
            "type":"Services"
        }
    ],
    "sg:phone":"+1 510 889 8097",
    "sg:postcode":"94552",
    "sg:province":"CA",
    "wof:name":"Cull Cyn Rnch Boarding Stables",
    "wof:placetype":"venue"
},
  "geometry": {"coordinates":[-122.05553,37.745675],"type":"Point"}
}