{
  "type": "Feature",
  "properties": {
    "addr:full":"4716 Golden Ridge Dr Corona CA 92880",
    "addr:housenumber":"4716",
    "addr:postcode":"92880",
    "addr:street":"Golden Ridge Dr",
    "iso:country":"US",
    "sg:address":"4716 Golden Ridge Dr",
    "sg:city":"Corona",
    "sg:classifiers":[
        {
            "category":"Retail",
            "subcategory":"Repair Shop",
            "type":"Services"
        }
    ],
    "sg:phone":"+1 951 735 6234",
    "sg:postcode":"92880",
    "sg:province":"CA",
    "sg:tags":[
        "welding"
    ],
    "wof:name":"Red Hawk Weld Repair",
    "wof:placetype":"venue"
},
  "geometry": {"coordinates":[-117.66336200000001,33.883734],"type":"Point"}
}