{
  "type": "Feature",
  "properties": {
    "iso:country":"US",
    "sg:address":"1123 Carlton Ave",
    "sg:city":"Menlo Park",
    "sg:classifiers":[
        {
            "category":"Organizations",
            "subcategory":"Religious Organization",
            "type":"Services"
        }
    ],
    "sg:phone":"+1 650 322 2700",
    "sg:postcode":"94025",
    "sg:province":"CA",
    "wof:name":"Most Worshipful Sons-Light",
    "wof:placetype":"venue"
},
  "geometry": {"coordinates":[-122.156075,37.472605],"type":"Point"}
}