{
  "type": "Feature",
  "properties": {
    "addr:full":"415 E Broadway Glendale CA 91205",
    "addr:housenumber":"415",
    "addr:postcode":"91205",
    "addr:street":"E Broadway",
    "iso:country":"US",
    "sg:address":"415 E Broadway",
    "sg:city":"Glendale",
    "sg:classifiers":[
        {
            "category":"Professional",
            "subcategory":"Lawyer & Legal Services",
            "type":"Services"
        }
    ],
    "sg:phone":"+1 818 550 1264",
    "sg:postcode":"91205",
    "sg:province":"CA",
    "sg:tags":[
        "attorney"
    ],
    "wof:name":"Mason Yost",
    "wof:placetype":"venue"
},
  "geometry": {"coordinates":[-118.250873,34.146408],"type":"Point"}
}