{
  "type": "Feature",
  "properties": {
    "addr:full":"10648 Painter Ave Santa Fe Springs CA 90670",
    "addr:housenumber":"10648",
    "addr:postcode":"90670",
    "addr:street":"Painter Ave",
    "iso:country":"US",
    "sg:address":"10648 Painter Ave",
    "sg:city":"Santa Fe Springs",
    "sg:classifiers":[
        {
            "category":"Real Estate",
            "subcategory":"Real Estate Agent",
            "type":"Services"
        }
    ],
    "sg:phone":"+1 562 777 0404",
    "sg:postcode":"90670",
    "sg:province":"CA",
    "wof:name":"Time Realty",
    "wof:placetype":"venue"
},
  "geometry": {"coordinates":[-118.051288,33.939587],"type":"Point"}
}