{
  "type": "Feature",
  "properties": {
    "iso:country":"US",
    "sg:address":"1130 W Main St",
    "sg:city":"Santa Maria",
    "sg:classifiers":[
        {
            "category":"Retail",
            "subcategory":"Auto Repair",
            "type":"Services"
        }
    ],
    "sg:phone":"+1 805 928 5238",
    "sg:postcode":"93458",
    "sg:province":"CA",
    "sg:tags":[
        "carburetor"
    ],
    "wof:name":"Lopez Carburetors",
    "wof:placetype":"venue"
},
  "geometry": {"coordinates":[-120.453107,34.953168],"type":"Point"}
}