{
  "type": "Feature",
  "properties": {
    "iso:country":"US",
    "sg:address":"414 Rainbow Ln",
    "sg:city":"Mammoth Lakes",
    "sg:classifiers":[
        {
            "category":"Real Estate",
            "subcategory":"Real Estate Operator",
            "type":"Services"
        }
    ],
    "sg:phone":"+1 760 934 8270",
    "sg:postcode":"93546",
    "sg:province":"CA",
    "sg:tags":[
        "condominium"
    ],
    "wof:name":"Snowbird Condominiums",
    "wof:placetype":"venue"
},
  "geometry": {"coordinates":[-119.000811,37.645228],"type":"Point"}
}