{
  "type": "Feature",
  "properties": {
    "iso:country":"US",
    "sg:address":"1400 N Harbor Blvd Ste 130-130",
    "sg:city":"Fullerton",
    "sg:classifiers":[
        {
            "category":"Professional",
            "subcategory":"Art Services",
            "type":"Services"
        }
    ],
    "sg:phone":"+1 714 255 9000",
    "sg:postcode":"92835",
    "sg:province":"CA",
    "sg:tags":[
        "photographer"
    ],
    "sg:website":"www.shutterbooth.com",
    "wof:name":"ShutterBooth",
    "wof:placetype":"venue"
},
  "geometry": {"coordinates":[-117.92511399999999,33.883704],"type":"Point"}
}