{
  "type": "Feature",
  "properties": {
    "addr:full":"519 Encinitas Blvd Encinitas CA 92024",
    "addr:housenumber":"519",
    "addr:postcode":"92024",
    "addr:street":"Encinitas Blvd",
    "iso:country":"US",
    "sg:address":"519 Encinitas Blvd",
    "sg:city":"Encinitas",
    "sg:classifiers":[
        {
            "category":"Mining & Drilling",
            "type":"Manufacturing & Wholesale Goods"
        }
    ],
    "sg:phone":"+1 760 436 9877",
    "sg:postcode":"92024",
    "sg:province":"CA",
    "sg:tags":[
        "crude",
        "production",
        "gas"
    ],
    "wof:name":"Intermarket Trading Co LLC",
    "wof:placetype":"venue"
},
  "geometry": {"coordinates":[-117.280332,33.046838],"type":"Point"}
}