{
  "type": "Feature",
  "properties": {
    "iso:country":"US",
    "sg:address":"3514 W Burbank Blvd",
    "sg:city":"Burbank",
    "sg:classifiers":[
        {
            "category":"Retail",
            "subcategory":"Auto Repair",
            "type":"Services"
        }
    ],
    "sg:phone":"+1 818 846 2648",
    "sg:postcode":"91505",
    "sg:province":"CA",
    "sg:tags":[
        "muffler",
        "exhaust",
        "system"
    ],
    "wof:name":"Midas Auto Service Experts",
    "wof:placetype":"venue"
},
  "geometry": {"coordinates":[-118.348769,34.174872],"type":"Point"}
}