{
  "type": "Feature",
  "properties": {
    "iso:country":"US",
    "sg:address":"5921 Garrapatos Rd",
    "sg:city":"Carmel",
    "sg:classifiers":[
        {
            "category":"Personal",
            "type":"Services"
        }
    ],
    "sg:phone":"+1 831 625 3523",
    "sg:postcode":"93923",
    "sg:province":"CA",
    "sg:tags":[
        "consultant",
        "planning",
        "wedding"
    ],
    "wof:name":"Elegant Events",
    "wof:placetype":"venue"
},
  "geometry": {"coordinates":[-121.86788799999999,36.401696],"type":"Point"}
}