{
  "type": "Feature",
  "properties": {
    "addr:full":"2931 N Main St Walnut Creek CA 94597",
    "addr:housenumber":"2931",
    "addr:postcode":"94597",
    "addr:street":"N Main St",
    "iso:country":"US",
    "sg:address":"2931 N Main St",
    "sg:city":"Walnut Creek",
    "sg:classifiers":[
        {
            "category":"Shopping",
            "type":"Retail Goods"
        }
    ],
    "sg:phone":"+1 925 938 1466",
    "sg:postcode":"94597",
    "sg:province":"CA",
    "sg:tags":[
        "trophy",
        "medal",
        "award"
    ],
    "wof:name":"Cal-West Trophy & Awards",
    "wof:placetype":"venue"
},
  "geometry": {"coordinates":[-122.061841,37.928035],"type":"Point"}
}