{
  "type": "Feature",
  "properties": {
    "addr:full":"3083 Gold Canal Dr Rancho Cordova CA 95670",
    "addr:housenumber":"3083",
    "addr:postcode":"95670",
    "addr:street":"Gold Canal Dr",
    "iso:country":"US",
    "sg:address":"3083 Gold Canal Dr",
    "sg:city":"Rancho Cordova",
    "sg:classifiers":[
        {
            "category":"Shopping",
            "subcategory":"Computers & Home Electronics",
            "type":"Retail Goods"
        }
    ],
    "sg:phone":"+1 916 638 2322",
    "sg:postcode":"95670",
    "sg:province":"CA",
    "sg:tags":[
        "equipment",
        "dealer"
    ],
    "sg:website":"www.logicaldesign.com",
    "wof:name":"Logical Design",
    "wof:placetype":"venue"
},
  "geometry": {"coordinates":[-121.268528,38.592251],"type":"Point"}
}