{
  "type": "Feature",
  "properties": {
    "iso:country":"US",
    "sg:address":"36667 Road 144",
    "sg:city":"Visalia",
    "sg:classifiers":[
        {
            "category":"Manufacturing",
            "subcategory":"Food",
            "type":"Manufacturing & Wholesale Goods"
        }
    ],
    "sg:phone":"+1 559 734 7950",
    "sg:postcode":"93292",
    "sg:province":"CA",
    "sg:tags":[
        "product"
    ],
    "wof:name":"Kenneth Pennington",
    "wof:placetype":"venue"
},
  "geometry": {"coordinates":[-119.250761,36.451527],"type":"Point"}
}