{
  "type": "Feature",
  "properties": {
    "addr:full":"1048 Hermosa Ave Hermosa Beach CA 90254",
    "addr:housenumber":"1048",
    "addr:postcode":"90254",
    "addr:street":"Hermosa Ave",
    "iso:country":"US",
    "sg:address":"1048 Hermosa Ave",
    "sg:city":"Hermosa Beach",
    "sg:classifiers":[
        {
            "category":"Retail",
            "subcategory":"Laundry & Dry Cleaning",
            "type":"Services"
        }
    ],
    "sg:phone":"+1 310 374 7869",
    "sg:postcode":"90254",
    "sg:province":"CA",
    "sg:tags":[
        "cleaners"
    ],
    "wof:name":"Rose Cleaners",
    "wof:placetype":"venue"
},
  "geometry": {"coordinates":[-118.399601,33.860966],"type":"Point"}
}