{
  "type": "Feature",
  "properties": {
    "iso:country":"US",
    "sg:address":"1414 Jefferson St",
    "sg:city":"Delano",
    "sg:classifiers":[
        {
            "category":"Real Estate",
            "subcategory":"Real Estate Services",
            "type":"Services"
        }
    ],
    "sg:phone":"+1 661 720 2760",
    "sg:postcode":"93215",
    "sg:province":"CA",
    "sg:tags":[
        "company",
        "title"
    ],
    "wof:name":"Alliance Title Co",
    "wof:placetype":"venue"
},
  "geometry": {"coordinates":[-119.245732,35.775682],"type":"Point"}
}