{
  "type": "Feature",
  "properties": {
    "addr:full":"1720 Pacific Ave Venice CA 90291",
    "addr:housenumber":"1720",
    "addr:postcode":"90291",
    "addr:street":"Pacific Ave",
    "iso:country":"US",
    "sg:address":"1720 Pacific Ave",
    "sg:city":"Venice",
    "sg:classifiers":[
        {
            "category":"Real Estate",
            "subcategory":"Real Estate Operator",
            "type":"Services"
        }
    ],
    "sg:phone":"+1 310 399 3377",
    "sg:postcode":"90291",
    "sg:province":"CA",
    "sg:tags":[
        "apartment"
    ],
    "wof:name":"Windward Village Apartments",
    "wof:placetype":"venue"
},
  "geometry": {"coordinates":[-118.47184300000001,33.9874],"type":"Point"}
}