{
  "type": "Feature",
  "properties": {
    "iso:country":"US",
    "sg:address":"1176 20th St",
    "sg:city":"Oroville",
    "sg:classifiers":[
        {
            "category":"Professional",
            "subcategory":"Business Services",
            "type":"Services"
        }
    ],
    "sg:phone":"+1 530 533 9234",
    "sg:postcode":"95965",
    "sg:province":"CA",
    "sg:tags":[
        "interior",
        "consultant",
        "design",
        "decorator"
    ],
    "wof:name":"Lasting Memories",
    "wof:placetype":"venue"
},
  "geometry": {"coordinates":[-121.60910199999999,39.500749],"type":"Point"}
}