{
  "type": "Feature",
  "properties": {
    "addr:full":"1821 W Avenue I Lancaster CA 93534",
    "addr:housenumber":"1821",
    "addr:postcode":"93534",
    "addr:street":"W Avenue I",
    "iso:country":"US",
    "sg:address":"1821 W Avenue I",
    "sg:city":"Lancaster",
    "sg:classifiers":[
        {
            "category":"Banks & Credit Unions",
            "subcategory":"Financial Services",
            "type":"Services"
        }
    ],
    "sg:phone":"+1 661 942 9373",
    "sg:postcode":"93534",
    "sg:province":"CA",
    "sg:tags":[
        "cashing",
        "loan",
        "payday",
        "alternative",
        "check"
    ],
    "sg:website":"http://www.acecashexpress.com",
    "wof:name":"ACE Cash Express",
    "wof:placetype":"venue"
},
  "geometry": {"coordinates":[-118.164181,34.704041],"type":"Point"}
}