{
  "type": "Feature",
  "properties": {
    "addr:full":"440 Harcourt Ave Seaside CA 93955",
    "addr:housenumber":"440",
    "addr:postcode":"93955",
    "addr:street":"Harcourt Ave",
    "iso:country":"US",
    "sg:address":"440 Harcourt Ave",
    "sg:city":"Seaside",
    "sg:classifiers":[
        {
            "category":"Government",
            "subcategory":"Office",
            "type":"Public Place"
        }
    ],
    "sg:phone":"+1 831 899 6202",
    "sg:postcode":"93955",
    "sg:province":"CA",
    "sg:tags":[
        "city"
    ],
    "wof:name":"City Clerk",
    "wof:placetype":"venue"
},
  "geometry": {"coordinates":[-121.854196,36.604114],"type":"Point"}
}