{
  "type": "Feature",
  "properties": {
    "addr:full":"4333 Meadow Dr Santa Maria CA 93455",
    "addr:housenumber":"4333",
    "addr:postcode":"93455",
    "addr:street":"Meadow Dr",
    "iso:country":"US",
    "sg:address":"4333 Meadow Dr",
    "sg:city":"Santa Maria",
    "sg:classifiers":[
        {
            "category":"Local Transit",
            "type":"Transportation"
        }
    ],
    "sg:phone":"+1 805 937 5466",
    "sg:postcode":"93455",
    "sg:province":"CA",
    "sg:tags":[
        "limousine"
    ],
    "sg:website":"www.goldcoastlimos.com",
    "wof:name":"Gold Coast Limousines",
    "wof:placetype":"venue"
},
  "geometry": {"coordinates":[-120.414299,34.878759],"type":"Point"}
}