{
  "type": "Feature",
  "properties": {
    "addr:full":"3001 Red Hill Ave Costa Mesa CA 92626",
    "addr:housenumber":"3001",
    "addr:postcode":"92626",
    "addr:street":"Red Hill Ave",
    "iso:country":"US",
    "sg:address":"3001 Red Hill Ave",
    "sg:city":"Costa Mesa",
    "sg:classifiers":[
        {
            "category":"Professional",
            "type":"Services"
        }
    ],
    "sg:phone":"+1 714 241 1091",
    "sg:postcode":"92626",
    "sg:province":"CA",
    "sg:tags":[
        "caterer"
    ],
    "sg:website":"www.cremedelacremefoods.com",
    "wof:name":"Creme De La Creme",
    "wof:placetype":"venue"
},
  "geometry": {"coordinates":[-117.879492,33.673494],"type":"Point"}
}