{
  "type": "Feature",
  "properties": {
    "addr:full":"2475 Burnt Oak Dr Santa Rosa CA 95401",
    "addr:housenumber":"2475",
    "addr:postcode":"95401",
    "addr:street":"Burnt Oak Dr",
    "iso:country":"US",
    "sg:address":"2475 Burnt Oak Dr",
    "sg:city":"Santa Rosa",
    "sg:classifiers":[
        {
            "category":"Professional",
            "type":"Services"
        }
    ],
    "sg:phone":"+1 707 569 8716",
    "sg:postcode":"95401",
    "sg:province":"CA",
    "sg:tags":[
        "consultant",
        "geological"
    ],
    "wof:name":"Michael J Dwyer",
    "wof:placetype":"venue"
},
  "geometry": {"coordinates":[-122.76829600000001,38.437028],"type":"Point"}
}