{
  "type": "Feature",
  "properties": {
    "iso:country":"US",
    "sg:address":"1000 Torrance Blvd",
    "sg:city":"Redondo Beach",
    "sg:classifiers":[
        {
            "category":"Retail",
            "subcategory":"Laundry & Dry Cleaning",
            "type":"Services"
        }
    ],
    "sg:phone":"+1 310 316 0156",
    "sg:postcode":"90277",
    "sg:province":"CA",
    "wof:name":"Shoreline Dry Cleaner and Tailor",
    "wof:placetype":"venue"
},
  "geometry": {"coordinates":[-118.376244,33.83877],"type":"Point"}
}