{
  "type": "Feature",
  "properties": {
    "addr:full":"26411 Via de Anza San Juan Capistrano CA 92675",
    "addr:housenumber":"26411",
    "addr:postcode":"92675",
    "addr:street":"Via De Anza",
    "iso:country":"US",
    "sg:address":"26411 Via de Anza",
    "sg:city":"San Juan Capistrano",
    "sg:classifiers":[
        {
            "category":"Freight",
            "type":"Transportation"
        }
    ],
    "sg:phone":"+1 949 493 7301",
    "sg:postcode":"92675",
    "sg:province":"CA",
    "sg:tags":[
        "special",
        "general"
    ],
    "wof:name":"San Juan Capistrano Self Stor",
    "wof:placetype":"venue"
},
  "geometry": {"coordinates":[-117.670631,33.48313],"type":"Point"}
}