{
  "type": "Feature",
  "properties": {
    "addr:full":"424 Hayes Street San Francisco CA 94102",
    "addr:housenumber":"424",
    "addr:postcode":"94102",
    "addr:street":"Hayes Street",
    "iso:country":"US",
    "sg:address":"424 Hayes Street",
    "sg:city":"San Francisco",
    "sg:classifiers":[
        {
            "category":"Food & Beverages",
            "subcategory":"Groceries & Convenience Stores",
            "type":"Retail Goods"
        }
    ],
    "sg:phone":"+1 415 863 1372",
    "sg:postcode":"94102",
    "sg:province":"CA",
    "wof:name":"Anna's Market",
    "wof:placetype":"venue"
},
  "geometry": {"coordinates":[-122.424004,37.776901],"type":"Point"}
}