{
  "type": "Feature",
  "properties": {
    "iso:country":"US",
    "sg:address":"1201 lafayette",
    "sg:city":"Alameda",
    "sg:classifiers":[
        {
            "category":"Retail",
            "subcategory":"Animal Services",
            "type":"Services"
        }
    ],
    "sg:phone":"+1 510 520 5988",
    "sg:postcode":"94501",
    "sg:province":"CA",
    "sg:tags":[
        "pet"
    ],
    "sg:website":"www.alamedanailsandtails.com",
    "wof:name":"Nails and Tails",
    "wof:placetype":"venue"
},
  "geometry": {"coordinates":[-122.25493400000001,37.767401],"type":"Point"}
}