{
  "type": "Feature",
  "properties": {
    "addr:full":"11990 Kemper Rd Auburn CA 95603",
    "addr:housenumber":"11990",
    "addr:postcode":"ca 95603",
    "addr:street":"Kemper Rd",
    "iso:country":"US",
    "sg:address":"11990 Kemper Rd",
    "sg:city":"Auburn",
    "sg:classifiers":[
        {
            "category":"Insurance",
            "subcategory":"Insurance Agent",
            "type":"Services"
        }
    ],
    "sg:phone":"+1 530 823 5225",
    "sg:postcode":"95603",
    "sg:province":"CA",
    "sg:website":"www.acjbinsurance.com",
    "wof:name":"Jack Bradbury Insurance Svc",
    "wof:placetype":"venue"
},
  "geometry": {"coordinates":[-121.09080299999999,38.932321],"type":"Point"}
}