{
  "type": "Feature",
  "properties": {
    "iso:country":"US",
    "sg:address":"21375 Roscoe Blvd",
    "sg:city":"Canoga Park",
    "sg:classifiers":[
        {
            "category":"Social Services",
            "type":"Services"
        }
    ],
    "sg:phone":"+1 818 883 6321",
    "sg:postcode":"91304",
    "sg:province":"CA",
    "sg:tags":[
        "organization",
        "welfare"
    ],
    "wof:name":"Salvation Army",
    "wof:placetype":"venue"
},
  "geometry": {"coordinates":[-118.597234,34.219795],"type":"Point"}
}