{
  "type": "Feature",
  "properties": {
    "addr:full":"650 S Lincoln Ave Corona CA 92882",
    "addr:housenumber":"650",
    "addr:postcode":"92882",
    "addr:street":"S Lincoln Ave",
    "iso:country":"US",
    "sg:address":"650 S Lincoln Ave",
    "sg:city":"Corona",
    "sg:classifiers":[
        {
            "category":"Retail",
            "subcategory":"Self-service Laundry",
            "type":"Services"
        }
    ],
    "sg:phone":"+1 951 270 0659",
    "sg:postcode":"92882",
    "sg:province":"CA",
    "wof:name":"Home Laundromat",
    "wof:placetype":"venue"
},
  "geometry": {"coordinates":[-117.583371,33.876723],"type":"Point"}
}