{
  "type": "Feature",
  "properties": {
    "iso:country":"US",
    "sg:address":"13292 Courtland Ter",
    "sg:city":"San Diego",
    "sg:classifiers":[
        {
            "category":"Building & Trades",
            "subcategory":"Construction",
            "type":"Services"
        }
    ],
    "sg:phone":"+1 858 259 9606",
    "sg:postcode":"92130",
    "sg:province":"CA",
    "sg:tags":[
        "equipment",
        "installation"
    ],
    "wof:name":"Hitech Home",
    "wof:placetype":"venue"
},
  "geometry": {"coordinates":[-117.238404,32.957617],"type":"Point"}
}