{
  "type": "Feature",
  "properties": {
    "iso:country":"US",
    "sg:address":"128 Dunstable Way",
    "sg:city":"Folsom",
    "sg:classifiers":[
        {
            "category":"Professional",
            "subcategory":"Computer Services",
            "type":"Services"
        }
    ],
    "sg:phone":"+1 916 983 9685",
    "sg:postcode":"95630",
    "sg:province":"CA",
    "sg:tags":[
        "consultant",
        "designer"
    ],
    "wof:name":"Intel Corp",
    "wof:placetype":"venue"
},
  "geometry": {"coordinates":[-121.126753,38.668453],"type":"Point"}
}