{
  "type": "Feature",
  "properties": {
    "addr:full":"128 Dunstable Way Folsom CA 95630",
    "addr:housenumber":"128",
    "addr:postcode":"95630",
    "addr:street":"Dunstable Way",
    "iso:country":"US",
    "sg:address":"128 Dunstable Way",
    "sg:city":"Folsom",
    "sg:classifiers":[
        {
            "category":"Professional",
            "subcategory":"Computer Services",
            "type":"Services"
        }
    ],
    "sg:phone":"+1 916 983 9685",
    "sg:postcode":"95630",
    "sg:province":"CA",
    "sg:tags":[
        "consultant",
        "designer"
    ],
    "wof:name":"Intel Corp",
    "wof:placetype":"venue"
},
  "geometry": {"coordinates":[-121.12675299999999,38.668453],"type":"Point"}
}