{
  "type": "Feature",
  "properties": {
    "iso:country":"US",
    "sg:address":"1224 Grant Ave",
    "sg:city":"Novato",
    "sg:classifiers":[
        {
            "category":"Retail",
            "subcategory":"Laundry & Dry Cleaning",
            "type":"Services"
        }
    ],
    "sg:phone":"+1 415 892 2925",
    "sg:postcode":"94945",
    "sg:province":"CA",
    "wof:name":"Washette",
    "wof:placetype":"venue"
},
  "geometry": {"coordinates":[-122.57335399999999,38.108228],"type":"Point"}
}