{
  "type": "Feature",
  "properties": {
    "iso:country":"US",
    "sg:address":"21515 Hawthorne Blvd Ste 200",
    "sg:city":"Torrance",
    "sg:classifiers":[
        {
            "category":"Professional",
            "subcategory":"Lawyer & Legal Services",
            "type":"Services"
        }
    ],
    "sg:phone":"+1 310 316 2500",
    "sg:postcode":"90503",
    "sg:province":"CA",
    "wof:name":"Wilson Christopher & Associates",
    "wof:placetype":"venue"
},
  "geometry": {"coordinates":[-118.35311,33.832922],"type":"Point"}
}