{
  "type": "Feature",
  "properties": {
    "iso:country":"US",
    "sg:address":"4425 Arch St",
    "sg:city":"San Diego",
    "sg:classifiers":[
        {
            "category":"Shopping",
            "subcategory":"Florist",
            "type":"Retail Goods"
        }
    ],
    "sg:phone":"+1 619 743 1332",
    "sg:postcode":"92116",
    "sg:province":"CA",
    "wof:name":"Flowers From The Ground Up",
    "wof:placetype":"venue"
},
  "geometry": {"coordinates":[-117.153264,32.75848],"type":"Point"}
}