{
  "type": "Feature",
  "properties": {
    "iso:country":"US",
    "sg:address":"16669 Selby Dr",
    "sg:city":"San Leandro",
    "sg:classifiers":[
        {
            "category":"Personal",
            "subcategory":"Beauty Salon",
            "type":"Services"
        }
    ],
    "sg:phone":"+1 510 755 4489",
    "sg:postcode":"94578",
    "sg:province":"CA",
    "wof:name":"Hair Garden",
    "wof:placetype":"venue"
},
  "geometry": {"coordinates":[-122.099784,37.703106],"type":"Point"}
}