{
  "type": "Feature",
  "properties": {
    "iso:country":"US",
    "sg:address":"22420 Skyline Dr",
    "sg:city":"Yorba Linda",
    "sg:classifiers":[
        {
            "category":"Building & Trades",
            "subcategory":"Plumbing",
            "type":"Services"
        }
    ],
    "sg:phone":"+1 714 694 0418",
    "sg:postcode":"92887",
    "sg:province":"CA",
    "sg:tags":[
        "product",
        "management",
        "energy",
        "system"
    ],
    "wof:name":"Advanced Energy Solutions",
    "wof:placetype":"venue"
},
  "geometry": {"coordinates":[-117.741821,33.88874],"type":"Point"}
}