{
  "type": "Feature",
  "properties": {
    "iso:country":"US",
    "sg:address":"473 N San Pedro St",
    "sg:city":"San Jose",
    "sg:classifiers":[
        {
            "category":"Organizations",
            "subcategory":"Non-profit Organization",
            "type":"Services"
        }
    ],
    "sg:phone":"+1 408 297 1182",
    "sg:postcode":"95110",
    "sg:province":"CA",
    "sg:tags":[
        "information",
        "alcoholism",
        "treatment"
    ],
    "wof:name":"New Life Support Homes",
    "wof:placetype":"venue"
},
  "geometry": {"coordinates":[-121.899335,37.343771],"type":"Point"}
}