{
  "type": "Feature",
  "properties": {
    "addr:full":"15982 Quantico Rd Apple Valley CA 92307",
    "addr:housenumber":"15982",
    "addr:postcode":"92307",
    "addr:street":"Quantico Rd",
    "iso:country":"US",
    "sg:address":"15982 Quantico Rd",
    "sg:city":"Apple Valley",
    "sg:classifiers":[
        {
            "category":"Health Services",
            "subcategory":"Clinic",
            "type":"Services"
        }
    ],
    "sg:phone":"+1 760 242 9756",
    "sg:postcode":"92307",
    "sg:province":"CA",
    "wof:name":"Gambro Healthcare",
    "wof:placetype":"venue"
},
  "geometry": {"coordinates":[-117.270878,34.541809],"type":"Point"}
}