{
  "type": "Feature",
  "properties": {
    "addr:full":"840 Hilgard Ave Los Angeles CA 90024",
    "addr:housenumber":"840",
    "addr:postcode":"90024",
    "addr:street":"Hilgard Ave",
    "iso:country":"US",
    "sg:address":"840 Hilgard Ave",
    "sg:city":"Los Angeles",
    "sg:classifiers":[
        {
            "category":"Organizations",
            "subcategory":"Community Association",
            "type":"Services"
        }
    ],
    "sg:phone":"+1 310 208 6544",
    "sg:postcode":"90024",
    "sg:province":"CA",
    "sg:tags":[
        "sorority",
        "fraternity"
    ],
    "wof:name":"Hillside University Ctr",
    "wof:placetype":"venue"
},
  "geometry": {"coordinates":[-118.440551,34.065078],"type":"Point"}
}