{
  "type": "Feature",
  "properties": {
    "addr:full":"550 Shepherd Ave Apt 4 Hayward CA 94544",
    "addr:housenumber":"550;4",
    "addr:postcode":"94544",
    "addr:street":"Shepherd Ave Apt",
    "iso:country":"US",
    "sg:address":"550 Shepherd Ave Apt 4",
    "sg:city":"Hayward",
    "sg:classifiers":[
        {
            "category":"Recreation",
            "type":"Entertainment"
        }
    ],
    "sg:phone":"+1 510 586 7715",
    "sg:postcode":"94544",
    "sg:province":"CA",
    "sg:tags":[
        "entertainers-family",
        "business"
    ],
    "wof:name":"Islamic-Entertainment",
    "wof:placetype":"venue"
},
  "geometry": {"coordinates":[-122.07320300000001,37.63749],"type":"Point"}
}