{
  "type": "Feature",
  "properties": {
    "iso:country":"US",
    "sg:address":"28545 Felix Valdez Ave",
    "sg:city":"Temecula",
    "sg:classifiers":[
        {
            "category":"Restaurant",
            "type":"Food & Drink"
        }
    ],
    "sg:phone":"+1 951 694 6355",
    "sg:postcode":"92590",
    "sg:province":"CA",
    "sg:tags":[
        "caterer"
    ],
    "wof:name":"Dreamakers Custom Catering",
    "wof:placetype":"venue"
},
  "geometry": {"coordinates":[-117.153457,33.494902],"type":"Point"}
}