{
  "type": "Feature",
  "properties": {
    "addr:full":"13562 Newport Ave Tustin CA 92780",
    "addr:housenumber":"13562",
    "addr:postcode":"92780",
    "addr:street":"Newport Ave",
    "iso:country":"US",
    "sg:address":"13562 Newport Ave",
    "sg:city":"Tustin",
    "sg:classifiers":[
        {
            "category":"Shopping",
            "subcategory":"Clothing, Apparel, & Fashions",
            "type":"Retail Goods"
        }
    ],
    "sg:phone":"+1 714 544 0974",
    "sg:postcode":"92780",
    "sg:province":"CA",
    "sg:tags":[
        "tailor",
        "alteration",
        "sewing"
    ],
    "wof:name":"Angelo's Professional Tailoring",
    "wof:placetype":"venue"
},
  "geometry": {"coordinates":[-117.817001,33.743198],"type":"Point"}
}