{
  "type": "Feature",
  "properties": {
    "addr:full":"1859 E Summerfield Ct Oakley CA 94561",
    "addr:housenumber":"1859",
    "addr:postcode":"94561",
    "addr:street":"E Summerfield Ct",
    "iso:country":"US",
    "sg:address":"1859 E Summerfield Ct",
    "sg:city":"Oakley",
    "sg:classifiers":[
        {
            "category":"Utilities",
            "subcategory":"Fuel Oil & Lpg",
            "type":"Services"
        }
    ],
    "sg:phone":"+1 925 625 8946",
    "sg:postcode":"94561",
    "sg:province":"CA",
    "sg:tags":[
        "development",
        "exploration",
        "gas"
    ],
    "wof:name":"Basa, Nerfe",
    "wof:placetype":"venue"
},
  "geometry": {"coordinates":[-121.726776,38.00246],"type":"Point"}
}