{
  "type": "Feature",
  "properties": {
    "iso:country":"US",
    "sg:address":"4888 Ronson Ct",
    "sg:city":"San Diego",
    "sg:classifiers":[
        {
            "category":"Wholesale",
            "subcategory":"Apparel",
            "type":"Manufacturing & Wholesale Goods"
        }
    ],
    "sg:phone":"+1 858 292 7071",
    "sg:postcode":"92111",
    "sg:province":"CA",
    "sg:tags":[
        "clothing",
        "furnishing",
        "mfg"
    ],
    "wof:name":"Dijon Bleu",
    "wof:placetype":"venue"
},
  "geometry": {"coordinates":[-117.146035,32.829321],"type":"Point"}
}