{
  "type": "Feature",
  "properties": {
    "addr:full":"3540 Wilshire Blvd Los Angeles CA 90010",
    "addr:housenumber":"3540",
    "addr:postcode":"90010",
    "addr:street":"Wilshire Blvd",
    "iso:country":"US",
    "sg:address":"3540 Wilshire Blvd",
    "sg:city":"Los Angeles",
    "sg:classifiers":[
        {
            "category":"Shopping",
            "subcategory":"Clothing, Apparel, & Fashions",
            "type":"Retail Goods"
        }
    ],
    "sg:phone":"+1 213 385 1812",
    "sg:postcode":"90010",
    "sg:province":"CA",
    "sg:tags":[
        "woman",
        "store",
        "accessory"
    ],
    "wof:name":"Maritere's of Wilshire",
    "wof:placetype":"venue"
},
  "geometry": {"coordinates":[-118.302002,34.061699],"type":"Point"}
}