{
  "type": "Feature",
  "properties": {
    "iso:country":"US",
    "sg:address":"1500 Webster St",
    "sg:city":"Fairfield",
    "sg:classifiers":[
        {
            "category":"Professional",
            "subcategory":"Lawyer & Legal Services",
            "type":"Services"
        }
    ],
    "sg:phone":"+1 707 421 2476",
    "sg:postcode":"94533",
    "sg:province":"CA",
    "sg:tags":[
        "attorney"
    ],
    "wof:name":"Daniel Long Law Office",
    "wof:placetype":"venue"
},
  "geometry": {"coordinates":[-122.046595,38.255319],"type":"Point"}
}