{
  "type": "Feature",
  "properties": {
    "addr:full":"298 Valencia St San Francisco CA 94103",
    "addr:housenumber":"298",
    "addr:postcode":"94103",
    "addr:street":"Valencia St",
    "iso:country":"US",
    "sg:address":"298 Valencia St",
    "sg:city":"San Francisco",
    "sg:classifiers":[
        {
            "category":"Shopping",
            "subcategory":"Books",
            "type":"Retail Goods"
        }
    ],
    "sg:phone":"+1 415 255 1081",
    "sg:postcode":"94103",
    "sg:province":"CA",
    "sg:tags":[
        "dealer"
    ],
    "sg:website":"www.socialistaction.org",
    "wof:name":"Socialist Action",
    "wof:placetype":"venue"
},
  "geometry": {"coordinates":[-122.422258,37.768754],"type":"Point"}
}