{
  "type": "Feature",
  "properties": {
    "iso:country":"US",
    "sg:address":"2002 Pinercrest Dr",
    "sg:city":"Santa Rosa",
    "sg:classifiers":[
        {
            "category":"Insurance",
            "subcategory":"Insurance Agent",
            "type":"Services"
        }
    ],
    "sg:phone":"+1 707 578 3130",
    "sg:postcode":"95403",
    "sg:province":"CA",
    "wof:name":"Gordon KOOP Soaring Capital",
    "wof:placetype":"venue"
},
  "geometry": {"coordinates":[-122.754009,38.469374],"type":"Point"}
}