{
  "type": "Feature",
  "properties": {
    "addr:full":"11100 Heather Ln Montague CA 96064",
    "addr:housenumber":"11100",
    "addr:postcode":"96064",
    "addr:street":"Heather Ln",
    "iso:country":"US",
    "sg:address":"11100 Heather Ln",
    "sg:city":"Montague",
    "sg:classifiers":[
        {
            "category":"Organizations",
            "subcategory":"Religious Organization",
            "type":"Services"
        }
    ],
    "sg:phone":"+1 530 459 3341",
    "sg:postcode":"96064",
    "sg:province":"CA",
    "sg:tags":[
        "science",
        "christian",
        "practitioner"
    ],
    "wof:name":"Janet Marie Danse",
    "wof:placetype":"venue"
},
  "geometry": {"coordinates":[-122.400154,41.936841],"type":"Point"}
}