{
  "type": "Feature",
  "properties": {
    "addr:full":"2400 W Coast Hwy Newport Beach CA 92663",
    "addr:housenumber":"2400",
    "addr:postcode":"92663",
    "addr:street":"W Coast Hwy",
    "iso:country":"US",
    "sg:address":"2400 W Coast Hwy",
    "sg:city":"Newport Beach",
    "sg:classifiers":[
        {
            "category":"Banks & Credit Unions",
            "subcategory":"Bank",
            "type":"Services"
        }
    ],
    "sg:phone":"+1 949 631 1038",
    "sg:postcode":"92663",
    "sg:province":"CA",
    "sg:tags":[
        "personal",
        "institution"
    ],
    "wof:name":"Schmitz Enterprises",
    "wof:placetype":"venue"
},
  "geometry": {"coordinates":[-117.913735,33.616115],"type":"Point"}
}