{
  "type": "Feature",
  "properties": {
    "iso:country":"US",
    "sg:address":"8961 W Sunset Blvd Unit 1A",
    "sg:city":"West Hollywood",
    "sg:classifiers":[
        {
            "category":"Personal",
            "subcategory":"Nail Salon",
            "type":"Services"
        }
    ],
    "sg:phone":"+1 310 246 0030",
    "sg:postcode":"90069",
    "sg:province":"CA",
    "sg:website":"www.nailsbydesignspa.com",
    "wof:name":"Nails by Design",
    "wof:placetype":"venue"
},
  "geometry": {"coordinates":[-118.387,34.090862],"type":"Point"}
}