{
  "type": "Feature",
  "properties": {
    "addr:full":"3599 Mission St San Francisco CA 94110",
    "addr:housenumber":"3599",
    "addr:postcode":"94110",
    "addr:street":"Mission St",
    "iso:country":"US",
    "sg:address":"3599 Mission St",
    "sg:city":"San Francisco",
    "sg:classifiers":[
        {
            "category":"Wholesale",
            "subcategory":"Farm Supplies",
            "type":"Manufacturing & Wholesale Goods"
        }
    ],
    "sg:phone":"+1 415 648 5673",
    "sg:postcode":"94110",
    "sg:province":"CA",
    "sg:tags":[
        "shop",
        "raw",
        "product",
        "material",
        "beauty"
    ],
    "wof:name":"Other Place",
    "wof:placetype":"venue"
},
  "geometry": {"coordinates":[-122.423687,37.739596],"type":"Point"}
}