{
  "type": "Feature",
  "properties": {
    "iso:country":"US",
    "sg:address":"3243 Amber Dr",
    "sg:city":"Paso Robles",
    "sg:classifiers":[
        {
            "category":"Real Estate",
            "subcategory":"Real Estate Agent",
            "type":"Services"
        }
    ],
    "sg:phone":"+1 805 434 1978",
    "sg:postcode":"93446",
    "sg:province":"CA",
    "sg:tags":[
        "inspection"
    ],
    "wof:name":"Professional Home Inspection",
    "wof:placetype":"venue"
},
  "geometry": {"coordinates":[-120.70308900000001,35.572906],"type":"Point"}
}