{
  "type": "Feature",
  "properties": {
    "iso:country":"US",
    "sg:address":"10021 Gierson Ave",
    "sg:city":"Chatsworth",
    "sg:classifiers":[
        {
            "category":"Building & Trades",
            "subcategory":"Cleaning & Sanitation",
            "type":"Services"
        }
    ],
    "sg:phone":"+1 818 709 7091",
    "sg:postcode":"91311",
    "sg:province":"CA",
    "sg:tags":[
        "butler",
        "maid"
    ],
    "wof:name":"Maid For You",
    "wof:placetype":"venue"
},
  "geometry": {"coordinates":[-118.611507,34.252143],"type":"Point"}
}