{
  "type": "Feature",
  "properties": {
    "addr:full":"982 N Ave Palmas Palm Springs CA 92262",
    "addr:housenumber":"982",
    "addr:postcode":"92262",
    "addr:street":"N Ave",
    "iso:country":"US",
    "sg:address":"982 N Ave Palmas",
    "sg:city":"Palm Springs",
    "sg:classifiers":[
        {
            "category":"Building & Trades",
            "subcategory":"Construction",
            "type":"Services"
        }
    ],
    "sg:phone":"+1 760 328 7360",
    "sg:postcode":"92262",
    "sg:province":"CA",
    "sg:tags":[
        "contractor"
    ],
    "wof:name":"Landau Development",
    "wof:placetype":"venue"
},
  "geometry": {"coordinates":[-116.54224000000001,33.836619],"type":"Point"}
}