{
  "type": "Feature",
  "properties": {
    "addr:full":"3232 Dora Verdugo Dr Glendale CA 91208",
    "addr:housenumber":"3232",
    "addr:postcode":"91208",
    "addr:street":"Dora Verdugo Dr",
    "iso:country":"US",
    "sg:address":"3232 Dora Verdugo Dr",
    "sg:city":"Glendale",
    "sg:classifiers":[
        {
            "category":"Wholesale",
            "subcategory":"Non-durable Goods",
            "type":"Manufacturing & Wholesale Goods"
        }
    ],
    "sg:phone":"+1 818 957 1280",
    "sg:postcode":"91208",
    "sg:province":"CA",
    "wof:name":"Vlas Export Import Inc",
    "wof:placetype":"venue"
},
  "geometry": {"coordinates":[-118.23974800000001,34.197224],"type":"Point"}
}