{
  "type": "Feature",
  "properties": {
    "iso:country":"US",
    "sg:address":"7477 Watt Ave",
    "sg:city":"Sacramento",
    "sg:classifiers":[
        {
            "category":"Deli",
            "type":"Food & Drink"
        },
        {
            "category":"Bakery",
            "type":"Food & Drink"
        },
        {
            "category":"Food & Beverages",
            "subcategory":"Groceries & Convenience Stores",
            "type":"Retail Goods"
        }
    ],
    "sg:phone":"+1 916 332 2635",
    "sg:postcode":"95814",
    "sg:province":"CA",
    "wof:name":"Raley's Supermarkets & Drug Centers",
    "wof:placetype":"venue"
},
  "geometry": {"coordinates":[-121.491997,38.577599],"type":"Point"}
}