{
  "type": "Feature",
  "properties": {
    "addr:full":"9420 Topanga Canyon Blvd Chatsworth CA 91311",
    "addr:housenumber":"9420",
    "addr:postcode":"91311",
    "addr:street":"Topanga Canyon Blvd",
    "iso:country":"US",
    "sg:address":"9420 Topanga Canyon Blvd",
    "sg:city":"Chatsworth",
    "sg:classifiers":[
        {
            "category":"Insurance",
            "subcategory":"Insurance Agent",
            "type":"Services"
        }
    ],
    "sg:phone":"+1 818 885 0111",
    "sg:postcode":"91311",
    "sg:province":"CA",
    "sg:website":"www.niains.com",
    "wof:name":"Lorch Insurance Inc",
    "wof:placetype":"venue"
},
  "geometry": {"coordinates":[-118.60593,34.239781],"type":"Point"}
}