{
  "type": "Feature",
  "properties": {
    "iso:country":"US",
    "sg:address":"30245 Agoura Rd",
    "sg:city":"Agoura Hills",
    "sg:classifiers":[
        {
            "category":"Autos & Motor Vehicles",
            "subcategory":"Fuel & Gas Station",
            "type":"Retail Goods"
        }
    ],
    "sg:phone":"+1 818 889 6829",
    "sg:postcode":"91301",
    "sg:province":"CA",
    "sg:tags":[
        "oil"
    ],
    "wof:name":"Jin's Agoura Shell",
    "wof:placetype":"venue"
},
  "geometry": {"coordinates":[-118.78783,34.144708],"type":"Point"}
}