{
  "type": "Feature",
  "properties": {
    "addr:full":"2715 Claremont Blvd Berkeley CA 94705",
    "addr:housenumber":"2715",
    "addr:postcode":"94705",
    "addr:street":"Claremont Blvd",
    "iso:country":"US",
    "sg:address":"2715 Claremont Blvd",
    "sg:city":"Berkeley",
    "sg:classifiers":[
        {
            "category":"Professional",
            "type":"Services"
        }
    ],
    "sg:phone":"+1 510 549 3801",
    "sg:postcode":"94705",
    "sg:province":"CA",
    "sg:tags":[
        "editorial"
    ],
    "wof:name":"Printed Page Productions",
    "wof:placetype":"venue"
},
  "geometry": {"coordinates":[-122.24701899999999,37.862327],"type":"Point"}
}