{
  "type": "Feature",
  "properties": {
    "addr:full":"40671 Village Dr Big Bear Lake CA 92314",
    "addr:housenumber":"40671",
    "addr:postcode":"92314",
    "addr:street":"Village Dr",
    "iso:country":"US",
    "sg:address":"40671 Village Dr",
    "sg:city":"Big Bear Lake",
    "sg:classifiers":[
        {
            "category":"Organizations",
            "subcategory":"Community Association",
            "type":"Services"
        }
    ],
    "sg:phone":"+1 909 878 2700",
    "sg:postcode":"92314",
    "sg:province":"CA",
    "sg:tags":[
        "club"
    ],
    "wof:name":"Club At Big Bear",
    "wof:placetype":"venue"
},
  "geometry": {"coordinates":[-116.91456100000001,34.239947],"type":"Point"}
}