{
  "type": "Feature",
  "properties": {
    "iso:country":"US",
    "sg:address":"2990 Glenrose Ave",
    "sg:city":"Altadena",
    "sg:classifiers":[
        {
            "category":"Personal",
            "subcategory":"Beauty Salon",
            "type":"Services"
        }
    ],
    "sg:phone":"+1 626 398 1748",
    "sg:postcode":"91001",
    "sg:province":"CA",
    "wof:name":"M J's Hair Salon",
    "wof:placetype":"venue"
},
  "geometry": {"coordinates":[-118.150916,34.194858],"type":"Point"}
}