{
  "type": "Feature",
  "properties": {
    "iso:country":"US",
    "sg:address":"526 Soquel Ave Ste D",
    "sg:city":"Santa Cruz",
    "sg:classifiers":[
        {
            "category":"Health Services",
            "subcategory":"Chiropractor",
            "type":"Services"
        }
    ],
    "sg:phone":"+1 831 457 9363",
    "sg:postcode":"95062",
    "sg:province":"CA",
    "wof:name":"Zeff Janet DC Ccsp Ccn",
    "wof:placetype":"venue"
},
  "geometry": {"coordinates":[-122.01799800000001,36.975399],"type":"Point"}
}