{
  "type": "Feature",
  "properties": {
    "addr:full":"1009 Martis Lndg Truckee CA 96161",
    "addr:housenumber":"1009",
    "addr:postcode":"96161",
    "addr:street":"Martis Lndg",
    "iso:country":"US",
    "sg:address":"1009 Martis Lndg",
    "sg:city":"Truckee",
    "sg:classifiers":[
        {
            "category":"Real Estate",
            "subcategory":"Real Estate Services",
            "type":"Services"
        },
        {
            "category":"Real Estate",
            "subcategory":"Real Estate Agent",
            "type":"Services"
        }
    ],
    "sg:phone":"+1 530 562 0603",
    "sg:postcode":"96161",
    "sg:province":"CA",
    "sg:tags":[
        "buyer",
        "broker"
    ],
    "wof:name":"Northstar Real Estate",
    "wof:placetype":"venue"
},
  "geometry": {"coordinates":[-120.123345,39.283009],"type":"Point"}
}