{
  "type": "Feature",
  "properties": {
    "iso:country":"US",
    "sg:address":"2186 Geary Blvd",
    "sg:city":"San Francisco",
    "sg:classifiers":[
        {
            "category":"Health Services",
            "subcategory":"Doctor",
            "type":"Services"
        }
    ],
    "sg:phone":"+1 415 749 6900",
    "sg:postcode":"94115",
    "sg:province":"CA",
    "sg:tags":[
        "physician",
        "surgeon"
    ],
    "wof:name":"Frank Farrell MD",
    "wof:placetype":"venue"
},
  "geometry": {"coordinates":[-122.43811700000001,37.783837],"type":"Point"}
}