{
  "type": "Feature",
  "properties": {
    "addr:full":"115 N School St Lodi CA 95240",
    "addr:housenumber":"115",
    "addr:postcode":"95240",
    "addr:street":"N School St",
    "iso:country":"US",
    "sg:address":"115 N School St",
    "sg:city":"Lodi",
    "sg:classifiers":[
        {
            "category":"Professional",
            "subcategory":"Lawyer & Legal Services",
            "type":"Services"
        }
    ],
    "sg:phone":"+1 209 333 2398",
    "sg:postcode":"95240",
    "sg:province":"CA",
    "sg:tags":[
        "attorney"
    ],
    "wof:name":"Kurt H Siebert",
    "wof:placetype":"venue"
},
  "geometry": {"coordinates":[-121.2736,38.135929],"type":"Point"}
}