{
  "type": "Feature",
  "properties": {
    "addr:full":"41444 Collegian Way Hemet CA 92544",
    "addr:postcode":"41444;92544",
    "addr:street":"Collegian Way",
    "iso:country":"US",
    "sg:address":"41444 Collegian Way",
    "sg:city":"Hemet",
    "sg:classifiers":[
        {
            "category":"Professional",
            "type":"Services"
        }
    ],
    "sg:phone":"+1 951 766 0568",
    "sg:postcode":"92544",
    "sg:province":"CA",
    "wof:name":"Western Works",
    "wof:placetype":"venue"
},
  "geometry": {"coordinates":[-116.93949499999999,33.734634],"type":"Point"}
}