{
  "type": "Feature",
  "properties": {
    "addr:full":"8935 Towne Centre Dr San Diego CA 92122",
    "addr:housenumber":"8935",
    "addr:postcode":"92122",
    "addr:street":"Towne Centre Dr",
    "iso:country":"US",
    "sg:address":"8935 Towne Centre Dr",
    "sg:city":"San Diego",
    "sg:classifiers":[
        {
            "category":"Food & Beverages",
            "subcategory":"Specialty",
            "type":"Retail Goods"
        },
        {
            "category":"Wholesale",
            "subcategory":"Groceries",
            "type":"Manufacturing & Wholesale Goods"
        }
    ],
    "sg:phone":"+1 858 320 0050",
    "sg:postcode":"92122",
    "sg:province":"CA",
    "sg:tags":[
        "gourmet",
        "shop"
    ],
    "wof:name":"French Accent LLC",
    "wof:placetype":"venue"
},
  "geometry": {"coordinates":[-117.206942,32.868305],"type":"Point"}
}