{
  "type": "Feature",
  "properties": {
    "addr:full":"611 56th St Oakland CA 94609",
    "addr:housenumber":"611",
    "addr:postcode":"94609",
    "addr:street":"56Th St",
    "iso:country":"US",
    "sg:address":"611 56th St",
    "sg:city":"Oakland",
    "sg:classifiers":[
        {
            "category":"Manufacturing",
            "subcategory":"Printing",
            "type":"Manufacturing & Wholesale Goods"
        }
    ],
    "sg:phone":"+1 510 601 9710",
    "sg:postcode":"94609",
    "sg:province":"CA",
    "sg:tags":[
        "multimedia"
    ],
    "wof:name":"Viridian",
    "wof:placetype":"venue"
},
  "geometry": {"coordinates":[-122.267173,37.840872],"type":"Point"}
}