{
  "type": "Feature",
  "properties": {
    "iso:country":"US",
    "sg:address":"4370 Contractors Cmn",
    "sg:city":"Livermore",
    "sg:classifiers":[
        {
            "category":"Building & Trades",
            "subcategory":"Construction",
            "type":"Services"
        }
    ],
    "sg:phone":"+1 925 961 1004",
    "sg:postcode":"94551",
    "sg:province":"CA",
    "sg:tags":[
        "wallcoverings-installation",
        "wallpaper",
        "painting",
        "contractor"
    ],
    "wof:name":"Champlin Mike Painting",
    "wof:placetype":"venue"
},
  "geometry": {"coordinates":[-121.737167,37.694279],"type":"Point"}
}