{
  "type": "Feature",
  "properties": {
    "addr:full":"4595 Ben Hur Rd Mariposa CA 95338",
    "addr:housenumber":"4595",
    "addr:postcode":"95338",
    "addr:street":"Ben Hur Rd",
    "iso:country":"US",
    "sg:address":"4595 Ben Hur Rd",
    "sg:city":"Mariposa",
    "sg:classifiers":[
        {
            "category":"Wholesale",
            "subcategory":"Hardware",
            "type":"Manufacturing & Wholesale Goods"
        }
    ],
    "sg:phone":"+1 209 742 7473",
    "sg:postcode":"95338",
    "sg:province":"CA",
    "sg:tags":[
        "plumbing"
    ],
    "wof:name":"Mariposa Pipe",
    "wof:placetype":"venue"
},
  "geometry": {"coordinates":[-119.946141,37.456191],"type":"Point"}
}