{
  "type": "Feature",
  "properties": {
    "addr:full":"4000 Shoreline Ct Ste 400 South San Francisco CA 94080",
    "addr:housenumber":"4000",
    "addr:postcode":"94080",
    "addr:street":"Shoreline Ct Ste 400",
    "iso:country":"US",
    "sg:address":"4000 Shoreline Ct Ste 400",
    "sg:city":"South San Francisco",
    "sg:classifiers":[
        {
            "category":"Communications",
            "subcategory":"Newspaper",
            "type":"Services"
        }
    ],
    "sg:phone":"+1 650 872 1642",
    "sg:postcode":"94080",
    "sg:province":"CA",
    "sg:tags":[
        "print",
        "medium"
    ],
    "sg:website":"www.maclife.com",
    "wof:name":"MacLife",
    "wof:placetype":"venue"
},
  "geometry": {"coordinates":[-122.472718,37.767439],"type":"Point"}
}