{
  "type": "Feature",
  "properties": {
    "iso:country":"US",
    "sg:address":"8337 Telegraph Rd Ste 110",
    "sg:city":"Pico Rivera",
    "sg:classifiers":[
        {
            "category":"Health Services",
            "subcategory":"Health Practitioner",
            "type":"Services"
        }
    ],
    "sg:phone":"+1 562 927 0816",
    "sg:postcode":"90660",
    "sg:province":"CA",
    "sg:tags":[
        "acupuncture"
    ],
    "wof:name":"Newx Acupuncture Clinic",
    "wof:placetype":"venue"
},
  "geometry": {"coordinates":[-118.112999,33.964199],"type":"Point"}
}