{
  "type": "Feature",
  "properties": {
    "iso:country":"US",
    "sg:address":"19250 Van Ness Ave",
    "sg:city":"Torrance",
    "sg:classifiers":[
        {
            "category":"Freight",
            "type":"Transportation"
        }
    ],
    "sg:phone":"+1 310 782 1515",
    "sg:postcode":"90504",
    "sg:province":"CA",
    "sg:tags":[
        "forwarding"
    ],
    "wof:name":"T K K Freight Forwarders",
    "wof:placetype":"venue"
},
  "geometry": {"coordinates":[-118.317685,33.856707],"type":"Point"}
}