{
  "type": "Feature",
  "properties": {
    "addr:full":"30413 Paynes Creek Loop Paynes Creek CA 96075",
    "addr:postcode":"30413;96075",
    "addr:street":"Paynes Creek Loop",
    "iso:country":"US",
    "sg:address":"30413 Paynes Creek Loop",
    "sg:city":"Paynes Creek",
    "sg:classifiers":[
        {
            "category":"Retail",
            "subcategory":"Veterinary Services",
            "type":"Services"
        }
    ],
    "sg:phone":"+1 530 597 2360",
    "sg:postcode":"96075",
    "sg:province":"CA",
    "wof:name":"Equine Radiographics",
    "wof:placetype":"venue"
},
  "geometry": {"coordinates":[-121.872005,40.345805],"type":"Point"}
}