{
  "type": "Feature",
  "properties": {
    "iso:country":"US",
    "sg:address":"280 Main St",
    "sg:city":"Weed",
    "sg:classifiers":[
        {
            "category":"Shopping",
            "subcategory":"Florist",
            "type":"Retail Goods"
        }
    ],
    "sg:phone":"+1 530 938 3959",
    "sg:postcode":"96094",
    "sg:province":"CA",
    "wof:name":"Michelle's Lilies & Lattes",
    "wof:placetype":"venue"
},
  "geometry": {"coordinates":[-122.38427,41.42466],"type":"Point"}
}