{
  "type": "Feature",
  "properties": {
    "addr:full":"1334 N Avalon Blvd Wilmington CA 90744",
    "addr:housenumber":"1334",
    "addr:postcode":"90744",
    "addr:street":"N Avalon Blvd",
    "iso:country":"US",
    "sg:address":"1334 N Avalon Blvd",
    "sg:city":"Wilmington",
    "sg:classifiers":[
        {
            "category":"Travel",
            "subcategory":"Travel Agent",
            "type":"Entertainment"
        }
    ],
    "sg:phone":"+1 310 518 3122",
    "sg:postcode":"90744",
    "sg:province":"CA",
    "sg:tags":[
        "agency"
    ],
    "wof:name":"Relax Vacation",
    "wof:placetype":"venue"
},
  "geometry": {"coordinates":[-118.26307300000001,33.788956],"type":"Point"}
}