{
  "type": "Feature",
  "properties": {
    "iso:country":"US",
    "sg:address":"32554 Pacific Coast Hwy",
    "sg:city":"Malibu",
    "sg:classifiers":[
        {
            "category":"Professional",
            "type":"Services"
        }
    ],
    "sg:phone":"+1 805 388 5552",
    "sg:postcode":"90265",
    "sg:province":"CA",
    "wof:name":"Beach Access",
    "wof:placetype":"venue"
},
  "geometry": {"coordinates":[-118.882239,34.039981],"type":"Point"}
}