{
  "type": "Feature",
  "properties": {
    "addr:full":"31760 Holland Rd Winchester CA 92596",
    "addr:housenumber":"31760",
    "addr:postcode":"92596",
    "addr:street":"Holland Rd",
    "iso:country":"US",
    "sg:address":"31760 Holland Rd",
    "sg:city":"Winchester",
    "sg:classifiers":[
        {
            "category":"Retail",
            "subcategory":"Animal Services",
            "type":"Services"
        }
    ],
    "sg:phone":"+1 951 926 1194",
    "sg:postcode":"92596",
    "sg:province":"CA",
    "wof:name":"Movieland Animals",
    "wof:placetype":"venue"
},
  "geometry": {"coordinates":[-117.103466,33.671344],"type":"Point"}
}