{
  "type": "Feature",
  "properties": {
    "iso:country":"US",
    "sg:address":"142 Horton Plaza",
    "sg:city":"San Diego",
    "sg:classifiers":[
        {
            "category":"Shopping Center",
            "type":"Public Place"
        }
    ],
    "sg:phone":"+1 619 231 1464",
    "sg:postcode":"92101",
    "sg:province":"CA",
    "wof:name":"Brookstone Company",
    "wof:placetype":"venue"
},
  "geometry": {"coordinates":[-117.16301,32.713244],"type":"Point"}
}