{
  "type": "Feature",
  "properties": {
    "iso:country":"US",
    "sg:address":"5202 W Whitesbridge Ave",
    "sg:city":"Fresno",
    "sg:classifiers":[
        {
            "category":"Farming",
            "subcategory":"Vineyard",
            "type":"Manufacturing & Wholesale Goods"
        }
    ],
    "sg:phone":"+1 559 264 9484",
    "sg:postcode":"93706",
    "sg:province":"CA",
    "sg:tags":[
        "grape"
    ],
    "wof:name":"Goto Itsumi",
    "wof:placetype":"venue"
},
  "geometry": {"coordinates":[-119.889149,36.735533],"type":"Point"}
}