{
  "type": "Feature",
  "properties": {
    "iso:country":"US",
    "sg:address":"16818 Redwood St",
    "sg:city":"Fountain Valley",
    "sg:classifiers":[
        {
            "category":"Building & Trades",
            "subcategory":"Plumbing",
            "type":"Services"
        }
    ],
    "sg:phone":"+1 714 968 0665",
    "sg:postcode":"92708",
    "sg:province":"CA",
    "sg:tags":[
        "contractor"
    ],
    "wof:name":"Specialty Cooling",
    "wof:placetype":"venue"
},
  "geometry": {"coordinates":[-117.959278,33.718774],"type":"Point"}
}