{
  "type": "Feature",
  "properties": {
    "iso:country":"US",
    "sg:address":"1836 Port Manleigh Pl",
    "sg:city":"Newport Beach",
    "sg:classifiers":[
        {
            "category":"Shopping",
            "subcategory":"Jewelry",
            "type":"Retail Goods"
        }
    ],
    "sg:phone":"+1 949 719 1919",
    "sg:postcode":"92660",
    "sg:province":"CA",
    "sg:tags":[
        "jeweler"
    ],
    "wof:name":"Charlotte",
    "wof:placetype":"venue"
},
  "geometry": {"coordinates":[-117.857404,33.620215],"type":"Point"}
}