{
  "type": "Feature",
  "properties": {
    "iso:country":"US",
    "sg:address":"10716 Washington Blvd",
    "sg:city":"Culver City",
    "sg:classifiers":[
        {
            "category":"Banks & Credit Unions",
            "subcategory":"Bank",
            "type":"Services"
        }
    ],
    "sg:phone":"+1 310 204 2115",
    "sg:postcode":"90232",
    "sg:province":"CA",
    "sg:tags":[
        "cashing",
        "check"
    ],
    "wof:name":"Community Check Cashing",
    "wof:placetype":"venue"
},
  "geometry": {"coordinates":[-118.406584,34.015839],"type":"Point"}
}