{
  "type": "Feature",
  "properties": {
    "addr:full":"3645 Main St Chula Vista CA 91911",
    "addr:housenumber":"3645",
    "addr:postcode":"91911",
    "addr:street":"Main St",
    "iso:country":"US",
    "sg:address":"3645 Main St",
    "sg:city":"Chula Vista",
    "sg:classifiers":[
        {
            "category":"Retail",
            "subcategory":"Auto Repair",
            "type":"Services"
        }
    ],
    "sg:phone":"+1 619 425 5151",
    "sg:postcode":"91911",
    "sg:province":"CA",
    "sg:tags":[
        "repairing",
        "automobile"
    ],
    "wof:name":"P B Auto",
    "wof:placetype":"venue"
},
  "geometry": {"coordinates":[-117.05750500000001,32.594651],"type":"Point"}
}