{
  "type": "Feature",
  "properties": {
    "iso:country":"US",
    "sg:address":"73962 Alessandro Dr",
    "sg:city":"Palm Desert",
    "sg:classifiers":[
        {
            "category":"Building & Trades",
            "subcategory":"Construction",
            "type":"Services"
        }
    ],
    "sg:phone":"+1 760 902 9207",
    "sg:postcode":"92260",
    "sg:province":"CA",
    "sg:tags":[
        "handyman"
    ],
    "sg:website":"www.rmk-services.com",
    "wof:name":"RMK Services",
    "wof:placetype":"venue"
},
  "geometry": {"coordinates":[-116.37442900000001,33.722065],"type":"Point"}
}