{
  "type": "Feature",
  "properties": {
    "iso:country":"US",
    "sg:address":"30301 Sherwood Rd",
    "sg:city":"Fort Bragg",
    "sg:classifiers":[
        {
            "category":"Shopping",
            "subcategory":"Catalog Store",
            "type":"Retail Goods"
        }
    ],
    "sg:phone":"+1 707 964 2922",
    "sg:postcode":"95437",
    "sg:province":"CA",
    "sg:tags":[
        "food",
        "mail",
        "order",
        "culture"
    ],
    "wof:name":"Gem Cultures",
    "wof:placetype":"venue"
},
  "geometry": {"coordinates":[-123.760595,39.444927],"type":"Point"}
}