{
  "type": "Feature",
  "properties": {
    "iso:country":"US",
    "sg:address":"500 N Atlantic Blvd A-121",
    "sg:city":"Monterey Park",
    "sg:classifiers":[
        {
            "category":"Juice Bar",
            "subcategory":"None",
            "type":"Food & Drink"
        },
        {
            "category":"Ice Cream",
            "type":"Food & Drink"
        }
    ],
    "sg:phone":"+1 626 926 6329",
    "sg:postcode":"91754",
    "sg:province":"CA",
    "sg:tags":[
        "smoothy",
        "frozen",
        "yogurt"
    ],
    "sg:website":"www.yogenfruz.com",
    "wof:name":"Yogen Fruz",
    "wof:placetype":"venue"
},
  "geometry": {"coordinates":[-118.13440199999999,34.069032],"type":"Point"}
}