{
  "type": "Feature",
  "properties": {
    "addr:full":"2001 Union St Ste 680 San Francisco CA 94123",
    "addr:housenumber":"2001",
    "addr:postcode":"94123",
    "addr:street":"Union St Ste 680",
    "iso:country":"US",
    "sg:address":"2001 Union St Ste 680",
    "sg:city":"San Francisco",
    "sg:classifiers":[
        {
            "category":"Health Services",
            "subcategory":"Doctor",
            "type":"Services"
        }
    ],
    "sg:phone":"+1 415 776 4040",
    "sg:postcode":"94123",
    "sg:province":"CA",
    "sg:tags":[
        "surgeon",
        "oral"
    ],
    "wof:name":"Steve S. Lim, DMD",
    "wof:placetype":"venue"
},
  "geometry": {"coordinates":[-122.432486,37.797184],"type":"Point"}
}