{
  "type": "Feature",
  "properties": {
    "addr:full":"940 Broxton Ave  Los Angeles CA 90024",
    "addr:housenumber":"940",
    "addr:postcode":"90024",
    "addr:street":"Broxton Ave",
    "iso:country":"US",
    "sg:address":"940 Broxton Ave ",
    "sg:city":"Los Angeles",
    "sg:classifiers":[
        {
            "category":"Cafe",
            "type":"Food & Drink"
        },
        {
            "category":"Food & Beverages",
            "subcategory":"Bakery",
            "type":"Retail Goods"
        }
    ],
    "sg:menulink":"http://www.allmenus.com/ca/los-angeles/283991-gypsy-cafe/menu/",
    "sg:phone":"+1 310 824 2119",
    "sg:postcode":"90024",
    "sg:province":"CA",
    "sg:tags":[
        "middle",
        "eastern"
    ],
    "wof:name":"Gypsy Cafe",
    "wof:placetype":"venue"
},
  "geometry": {"coordinates":[-118.44703,34.062809],"type":"Point"}
}