{
  "type": "Feature",
  "properties": {
    "iso:country":"US",
    "sg:address":"20578 3rd St",
    "sg:city":"Saratoga",
    "sg:classifiers":[
        {
            "category":"Professional",
            "subcategory":"Computer Services",
            "type":"Services"
        }
    ],
    "sg:phone":"+1 408 867 1798",
    "sg:postcode":"95070",
    "sg:province":"CA",
    "sg:tags":[
        "internet"
    ],
    "wof:name":"Platinum Dining",
    "wof:placetype":"venue"
},
  "geometry": {"coordinates":[-122.033587,37.257081],"type":"Point"}
}