{
  "type": "Feature",
  "properties": {
    "addr:full":"510 Tamalpais Dr Corte Madera CA 94925",
    "addr:housenumber":"510",
    "addr:postcode":"94925",
    "addr:street":"Tamalpais Dr",
    "iso:country":"US",
    "sg:address":"510 Tamalpais Dr",
    "sg:city":"Corte Madera",
    "sg:classifiers":[
        {
            "category":"Restaurant",
            "type":"Food & Drink"
        }
    ],
    "sg:phone":"+1 415 924 1223",
    "sg:postcode":"94925",
    "sg:province":"CA",
    "sg:tags":[
        "eating"
    ],
    "wof:name":"Tim Tub Thai Restaurant",
    "wof:placetype":"venue"
},
  "geometry": {"coordinates":[-122.52647899999999,37.9256],"type":"Point"}
}