{
  "type": "Feature",
  "properties": {
    "iso:country":"US",
    "sg:address":"4860 Ruffner St",
    "sg:city":"San Diego",
    "sg:classifiers":[
        {
            "category":"Building & Trades",
            "subcategory":"Cleaning & Sanitation",
            "type":"Services"
        }
    ],
    "sg:phone":"+1 858 627 7130",
    "sg:postcode":"92111",
    "sg:province":"CA",
    "sg:tags":[
        "maintenance"
    ],
    "wof:name":"Maintenance Unit",
    "wof:placetype":"venue"
},
  "geometry": {"coordinates":[-117.158725,32.829687],"type":"Point"}
}