{
  "type": "Feature",
  "properties": {
    "addr:full":"7410 Greenhaven Dr Sacramento CA 95831",
    "addr:housenumber":"7410",
    "addr:postcode":"95831",
    "addr:street":"Greenhaven Dr",
    "iso:country":"US",
    "sg:address":"7410 Greenhaven Dr",
    "sg:city":"Sacramento",
    "sg:classifiers":[
        {
            "category":"Banks & Credit Unions",
            "subcategory":"Investment Brokerage",
            "type":"Services"
        }
    ],
    "sg:phone":"+1 916 391 9567",
    "sg:postcode":"95831",
    "sg:province":"CA",
    "sg:tags":[
        "advisory",
        "financial"
    ],
    "wof:name":"Pacific Gold Financial",
    "wof:placetype":"venue"
},
  "geometry": {"coordinates":[-121.51740599999999,38.487632],"type":"Point"}
}