{
  "type": "Feature",
  "properties": {
    "iso:country":"US",
    "sg:address":"1814 Flower St",
    "sg:city":"Glendale",
    "sg:classifiers":[
        {
            "category":"Manufacturing",
            "subcategory":"Printing",
            "type":"Manufacturing & Wholesale Goods"
        }
    ],
    "sg:phone":"+1 818 244 8558",
    "sg:postcode":"91201",
    "sg:province":"CA",
    "sg:tags":[
        "publisher",
        "software"
    ],
    "wof:name":"Us Hightech Systems",
    "wof:placetype":"venue"
},
  "geometry": {"coordinates":[-118.297836,34.167449],"type":"Point"}
}