{
  "type": "Feature",
  "properties": {
    "iso:country":"US",
    "name:eng_x_preferred":[
        "SF Anchorage 9 Berth W8"
    ],
    "wof:name":"SF Anchorage 9 Berth W8",
    "wof:placetype":"venue"
},
  "geometry": {"coordinates":[-122.334866667,37.69985],"type":"Point"}
}