{
  "type": "Feature",
  "properties": {
    "addr:full":"300 Pasteur Dr Stanford CA 94305",
    "addr:housenumber":"300",
    "addr:postcode":"94305",
    "addr:street":"Pasteur Dr",
    "iso:country":"US",
    "sg:address":"300 Pasteur Dr",
    "sg:city":"Stanford",
    "sg:classifiers":[
        {
            "category":"Health Services",
            "subcategory":"Doctor",
            "type":"Services"
        }
    ],
    "sg:phone":"+1 650 723 4000",
    "sg:postcode":"94305",
    "sg:province":"CA",
    "sg:tags":[
        "physician",
        "pediatrics",
        "family",
        "cardiology",
        "practice",
        "surgeons",
        "orthopedics",
        "internal",
        "medicine",
        "surgeon",
        "surgery-general",
        "pathology"
    ],
    "wof:name":"Calore, Briana, Md - Stanford School Of Medicine",
    "wof:placetype":"venue"
},
  "geometry": {"coordinates":[-122.177429,37.433331],"type":"Point"}
}