{
  "type": "Feature",
  "properties": {
    "iso:country":"US",
    "sg:address":"112 Cardoza",
    "sg:city":"Hercules",
    "sg:classifiers":[
        {
            "category":"Shopping",
            "type":"Retail Goods"
        }
    ],
    "sg:phone":"+1 510 964 0506",
    "sg:postcode":"94547",
    "sg:province":"CA",
    "sg:tags":[
        "pet",
        "food",
        "supply"
    ],
    "wof:name":"Adams Precision Design Inc",
    "wof:placetype":"venue"
},
  "geometry": {"coordinates":[-122.29280199999999,38.011781],"type":"Point"}
}