{
  "type": "Feature",
  "properties": {
    "addr:full":"12200 Thatcher Ct Poway CA 92064",
    "addr:housenumber":"12200",
    "addr:postcode":"ca 92064",
    "addr:street":"Thatcher Ct",
    "iso:country":"US",
    "sg:address":"12200 Thatcher Ct",
    "sg:city":"Poway",
    "sg:classifiers":[
        {
            "category":"Manufacturing",
            "subcategory":"Tools & Machinery",
            "type":"Manufacturing & Wholesale Goods"
        }
    ],
    "sg:phone":"+1 858 486 8787",
    "sg:postcode":"92064",
    "sg:province":"CA",
    "sg:tags":[
        "equipment",
        "system",
        "automation"
    ],
    "sg:website":"www.jdstechnologies.com",
    "wof:name":"JDS Technologies",
    "wof:placetype":"venue"
},
  "geometry": {"coordinates":[-117.041574,32.939119],"type":"Point"}
}