{
  "type": "Feature",
  "properties": {
    "iso:country":"US",
    "sg:address":"555 Jean St",
    "sg:city":"Oakland",
    "sg:classifiers":[
        {
            "category":"Personal",
            "type":"Services"
        }
    ],
    "sg:phone":"+1 510 333 4446",
    "sg:postcode":"94606",
    "sg:province":"CA",
    "sg:tags":[
        "home"
    ],
    "sg:website":"www.sosimpleorg.com",
    "wof:name":"Simplfied Profesional Organizing",
    "wof:placetype":"venue"
},
  "geometry": {"coordinates":[-122.248516,37.817173],"type":"Point"}
}