{
  "type": "Feature",
  "properties": {
    "iso:country":"US",
    "sg:address":"9932 Basilica Ct",
    "sg:city":"Cypress",
    "sg:classifiers":[
        {
            "category":"Wholesale",
            "subcategory":"Auto Parts",
            "type":"Manufacturing & Wholesale Goods"
        }
    ],
    "sg:phone":"+1 714 826 7773",
    "sg:postcode":"90630",
    "sg:province":"CA",
    "sg:tags":[
        "automobile",
        "supply"
    ],
    "wof:name":"Ysk Inc",
    "wof:placetype":"venue"
},
  "geometry": {"coordinates":[-118.047935,33.817669],"type":"Point"}
}