{
  "type": "Feature",
  "properties": {
    "iso:country":"US",
    "sg:address":"516 Burchett St",
    "sg:city":"Glendale",
    "sg:classifiers":[
        {
            "category":"Health Services",
            "subcategory":"Nursing And Care Facility",
            "type":"Services"
        }
    ],
    "sg:phone":"+1 818 247 0420",
    "sg:postcode":"91203",
    "sg:province":"CA",
    "sg:tags":[
        "home",
        "retirement",
        "community"
    ],
    "sg:website":"www.scphs.com",
    "wof:name":"So Ca Presbyterian Homes",
    "wof:placetype":"venue"
},
  "geometry": {"coordinates":[-118.266413,34.157167],"type":"Point"}
}