{
  "type": "Feature",
  "properties": {
    "addr:full":"2434 Webb Ave Alameda CA 94501",
    "addr:housenumber":"2434",
    "addr:postcode":"94501",
    "addr:street":"Webb Ave",
    "iso:country":"US",
    "sg:address":"2434 Webb Ave",
    "sg:city":"Alameda",
    "sg:classifiers":[
        {
            "category":"Farming",
            "subcategory":"Fish & Marine Products",
            "type":"Manufacturing & Wholesale Goods"
        },
        {
            "category":"Shopping",
            "subcategory":"Gifts & Souvenirs",
            "type":"Retail Goods"
        }
    ],
    "sg:phone":"+1 510 521 2385",
    "sg:postcode":"94501",
    "sg:province":"CA",
    "sg:tags":[
        "picture",
        "framing",
        "shop"
    ],
    "wof:name":"Urban Forest",
    "wof:placetype":"venue"
},
  "geometry": {"coordinates":[-122.24079,37.765585],"type":"Point"}
}