{
  "type": "Feature",
  "properties": {
    "addr:full":"4678 Fargo Ave San Diego CA 92117",
    "addr:housenumber":"4678",
    "addr:postcode":"92117",
    "addr:street":"Fargo Ave",
    "iso:country":"US",
    "sg:address":"4678 Fargo Ave",
    "sg:city":"San Diego",
    "sg:classifiers":[
        {
            "category":"Shopping",
            "subcategory":"Beauty & Cosmetics",
            "type":"Retail Goods"
        }
    ],
    "sg:phone":"+1 858 336 7309",
    "sg:postcode":"92117",
    "sg:province":"CA",
    "sg:tags":[
        "supply"
    ],
    "wof:name":"Red Wine Therapy",
    "wof:placetype":"venue"
},
  "geometry": {"coordinates":[-117.225281,32.833719],"type":"Point"}
}