{
  "type": "Feature",
  "properties": {
    "iso:country":"US",
    "sg:address":"4328 Bell Ave",
    "sg:city":"Bell",
    "sg:classifiers":[
        {
            "category":"Building & Trades",
            "subcategory":"Plumbing",
            "type":"Services"
        }
    ],
    "sg:phone":"+1 323 560 8933",
    "sg:postcode":"90201",
    "sg:province":"CA",
    "wof:name":"A & B Construction Inc.",
    "wof:placetype":"venue"
},
  "geometry": {"coordinates":[-118.190315,33.974576],"type":"Point"}
}