{
  "type": "Feature",
  "properties": {
    "addr:full":"Sawtelle & Wilshire Los Angeles CA 90001",
    "addr:postcode":"90001",
    "iso:country":"US",
    "sg:address":"Sawtelle & Wilshire",
    "sg:city":"Los Angeles",
    "sg:classifiers":[
        {
            "category":"Arts & Performance",
            "subcategory":"Arts Center",
            "type":"Entertainment"
        }
    ],
    "sg:phone":"+1 310 479 3003",
    "sg:postcode":"90001",
    "sg:province":"CA",
    "sg:tags":[
        "performing"
    ],
    "wof:name":"Wadsworth Theatre",
    "wof:placetype":"venue"
},
  "geometry": {"coordinates":[-118.248999,33.974767],"type":"Point"}
}