{
  "type": "Feature",
  "properties": {
    "iso:country":"US",
    "sg:address":"3013 W Florida Ave",
    "sg:city":"Hemet",
    "sg:classifiers":[
        {
            "category":"Banks & Credit Unions",
            "subcategory":"Bank",
            "type":"Services"
        }
    ],
    "sg:phone":"+1 951 766 6600",
    "sg:postcode":"92545",
    "sg:province":"CA",
    "sg:website":"www.guarantygroup.com",
    "wof:name":"Guaranty Bank",
    "wof:placetype":"venue"
},
  "geometry": {"coordinates":[-117.00276700000001,33.747318],"type":"Point"}
}