{
  "type": "Feature",
  "properties": {
    "iso:country":"US",
    "sg:address":"7080 Donlon Way Ste 200",
    "sg:city":"Dublin",
    "sg:classifiers":[
        {
            "category":"Insurance",
            "subcategory":"Hazard Insurance",
            "type":"Services"
        },
        {
            "category":"Insurance",
            "subcategory":"Life Insurance",
            "type":"Services"
        }
    ],
    "sg:phone":"+1 925 828 4884",
    "sg:postcode":"94568",
    "sg:province":"CA",
    "sg:tags":[
        "commercial",
        "group",
        "business"
    ],
    "sg:website":"http://www.luso-american.org",
    "wof:name":"Luso-American Life Insurance Society",
    "wof:placetype":"venue"
},
  "geometry": {"coordinates":[-121.93921899999999,37.702695],"type":"Point"}
}