{
  "type": "Feature",
  "properties": {
    "addr:full":"16417 Tulsa St Granada Hills CA 91344",
    "addr:housenumber":"16417",
    "addr:postcode":"91344",
    "addr:street":"Tulsa St",
    "iso:country":"US",
    "sg:address":"16417 Tulsa St",
    "sg:city":"Granada Hills",
    "sg:classifiers":[
        {
            "category":"Wholesale",
            "subcategory":"Groceries",
            "type":"Manufacturing & Wholesale Goods"
        }
    ],
    "sg:phone":"+1 818 360 9122",
    "sg:postcode":"91344",
    "sg:province":"CA",
    "wof:name":"Top Quality",
    "wof:placetype":"venue"
},
  "geometry": {"coordinates":[-118.489701,34.268394],"type":"Point"}
}