{
  "type": "Feature",
  "properties": {
    "iso:country":"US",
    "sg:address":"105 Vernon St",
    "sg:city":"Roseville",
    "sg:classifiers":[
        {
            "category":"Home & Garden",
            "subcategory":"Furniture",
            "type":"Retail Goods"
        }
    ],
    "sg:phone":"+1 916 773 2722",
    "sg:postcode":"95678",
    "sg:province":"CA",
    "wof:name":"Room Decor & More",
    "wof:placetype":"venue"
},
  "geometry": {"coordinates":[-121.28276099999999,38.749878],"type":"Point"}
}