{
  "type": "Feature",
  "properties": {
    "addr:full":"2944 Taraval St San Francisco CA 94116",
    "addr:housenumber":"2944",
    "addr:postcode":"94116",
    "addr:street":"Taraval St",
    "iso:country":"US",
    "sg:address":"2944 Taraval St",
    "sg:city":"San Francisco",
    "sg:classifiers":[
        {
            "category":"Building & Trades",
            "subcategory":"Construction",
            "type":"Services"
        }
    ],
    "sg:phone":"+1 415 566 4638",
    "sg:postcode":"94116",
    "sg:province":"CA",
    "sg:tags":[
        "resurfacing",
        "laying",
        "refinishing",
        "floor"
    ],
    "wof:name":"Golden Crown Hardwood Floor",
    "wof:placetype":"venue"
},
  "geometry": {"coordinates":[-122.49781299999999,37.742152],"type":"Point"}
}