{
  "type": "Feature",
  "properties": {
    "addr:full":"388 Bryce Canyon Rd San Rafael CA 94903",
    "addr:housenumber":"388",
    "addr:postcode":"94903",
    "addr:street":"Bryce Canyon Rd",
    "iso:country":"US",
    "sg:address":"388 Bryce Canyon Rd",
    "sg:city":"San Rafael",
    "sg:classifiers":[
        {
            "category":"Health Services",
            "subcategory":"Clinic",
            "type":"Services"
        }
    ],
    "sg:phone":"+1 415 472 0735",
    "sg:postcode":"94903",
    "sg:province":"CA",
    "sg:tags":[
        "information",
        "disability",
        "learning"
    ],
    "wof:name":"Institute Of Abundant Living",
    "wof:placetype":"venue"
},
  "geometry": {"coordinates":[-122.52911,38.01435],"type":"Point"}
}