{
  "type": "Feature",
  "properties": {
    "iso:country":"US",
    "sg:address":"6591 Reflection Dr",
    "sg:city":"San Diego",
    "sg:classifiers":[
        {
            "category":"Travel",
            "subcategory":"Hotels & Motels",
            "type":"Entertainment"
        }
    ],
    "sg:phone":"+1 619 284 1638",
    "sg:postcode":"92124",
    "sg:province":"CA",
    "wof:name":"Coast To Coast Corporate Housing",
    "wof:placetype":"venue"
},
  "geometry": {"coordinates":[-117.107375,32.794782],"type":"Point"}
}