{
  "type": "Feature",
  "properties": {
    "addr:full":"308 Main St Nevada City CA 95959",
    "addr:housenumber":"308",
    "addr:postcode":"95959",
    "addr:street":"Main St",
    "iso:country":"US",
    "sg:address":"308 Main St",
    "sg:city":"Nevada City",
    "sg:classifiers":[
        {
            "category":"Insurance",
            "subcategory":"Insurance Agent",
            "type":"Services"
        }
    ],
    "sg:phone":"+1 530 265 2046",
    "sg:postcode":"95959",
    "sg:province":"CA",
    "wof:name":"Interwest Insurance Svc",
    "wof:placetype":"venue"
},
  "geometry": {"coordinates":[-121.017775,39.263821],"type":"Point"}
}