{
  "type": "Feature",
  "properties": {
    "iso:country":"US",
    "sg:address":"341 Rose Ave",
    "sg:city":"Danville",
    "sg:classifiers":[
        {
            "category":"Home & Garden",
            "subcategory":"Furniture",
            "type":"Retail Goods"
        }
    ],
    "sg:phone":"+1 925 362 4505",
    "sg:postcode":"94526",
    "sg:province":"CA",
    "sg:tags":[
        "builder",
        "custom"
    ],
    "wof:name":"Nonnu",
    "wof:placetype":"venue"
},
  "geometry": {"coordinates":[-122.001198,37.823906],"type":"Point"}
}