{
  "type": "Feature",
  "properties": {
    "addr:full":"1731 Edgewood Dr Lodi CA 95240",
    "addr:housenumber":"1731",
    "addr:postcode":"95240",
    "addr:street":"Edgewood Dr",
    "iso:country":"US",
    "sg:address":"1731 Edgewood Dr",
    "sg:city":"Lodi",
    "sg:classifiers":[
        {
            "category":"Building & Trades",
            "subcategory":"Construction",
            "type":"Services"
        }
    ],
    "sg:phone":"+1 209 481 6172",
    "sg:postcode":"95240",
    "sg:province":"CA",
    "sg:tags":[
        "contractor"
    ],
    "wof:name":"Jim Dwyer Installation",
    "wof:placetype":"venue"
},
  "geometry": {"coordinates":[-121.287094,38.150757],"type":"Point"}
}