{
  "type": "Feature",
  "properties": {
    "iso:country":"US",
    "sg:address":"1125 N 7th St",
    "sg:city":"San Jose",
    "sg:classifiers":[
        {
            "category":"Organizations",
            "subcategory":"Non-profit Organization",
            "type":"Services"
        }
    ],
    "sg:phone":"+1 408 947 6920",
    "sg:postcode":"95112",
    "sg:province":"CA",
    "sg:website":"www.spartanbookstore.com",
    "wof:name":"Spartan Shops Inc",
    "wof:placetype":"venue"
},
  "geometry": {"coordinates":[-121.90106900000001,37.361706],"type":"Point"}
}