{
  "type": "Feature",
  "properties": {
    "iso:country":"US",
    "sg:address":"206 16th Ave",
    "sg:city":"Santa Cruz",
    "sg:classifiers":[
        {
            "category":"Freight",
            "type":"Transportation"
        }
    ],
    "sg:phone":"+1 831 239 4726",
    "sg:postcode":"95062",
    "sg:province":"CA",
    "wof:name":"Richard Buchanan Transport",
    "wof:placetype":"venue"
},
  "geometry": {"coordinates":[-121.99115,36.960147],"type":"Point"}
}