{
  "type": "Feature",
  "properties": {
    "addr:full":"6680 Rancho Adobe Dr Sacramento CA 95828",
    "addr:housenumber":"6680",
    "addr:postcode":"95828",
    "addr:street":"Rancho Adobe Dr",
    "iso:country":"US",
    "sg:address":"6680 Rancho Adobe Dr",
    "sg:city":"Sacramento",
    "sg:classifiers":[
        {
            "category":"Utilities",
            "subcategory":"Mobile Phone",
            "type":"Services"
        }
    ],
    "sg:phone":"+1 916 801 3200",
    "sg:postcode":"95828",
    "sg:province":"CA",
    "sg:tags":[
        "telephone",
        "cellular"
    ],
    "wof:name":"V-Phone Digital/Wireless",
    "wof:placetype":"venue"
},
  "geometry": {"coordinates":[-121.42169800000001,38.505454],"type":"Point"}
}