{
  "type": "Feature",
  "properties": {
    "iso:country":"US",
    "sg:address":"945 Montcrest Dr",
    "sg:city":"Redding",
    "sg:classifiers":[
        {
            "category":"Autos & Motor Vehicles",
            "subcategory":"Automobile Sales",
            "type":"Retail Goods"
        }
    ],
    "sg:phone":"+1 530 221 4887",
    "sg:postcode":"96003",
    "sg:province":"CA",
    "sg:tags":[
        "car",
        "used"
    ],
    "wof:name":"Brandon Paul Blanco",
    "wof:placetype":"venue"
},
  "geometry": {"coordinates":[-122.355805,40.598642],"type":"Point"}
}