{
  "type": "Feature",
  "properties": {
    "iso:country":"US",
    "sg:address":"17835 Ventura Blvd",
    "sg:city":"Encino",
    "sg:classifiers":[
        {
            "category":"Professional",
            "subcategory":"Business Services",
            "type":"Services"
        }
    ],
    "sg:phone":"+1 818 705 1911",
    "sg:postcode":"91316",
    "sg:province":"CA",
    "sg:tags":[
        "development"
    ],
    "sg:website":"www.hellerdev.com",
    "wof:name":"Heller Development",
    "wof:placetype":"venue"
},
  "geometry": {"coordinates":[-118.52149,34.163373],"type":"Point"}
}