{
  "type": "Feature",
  "properties": {
    "iso:country":"US",
    "sg:address":"923 Key Route Blvd",
    "sg:city":"Albany",
    "sg:classifiers":[
        {
            "category":"Professional",
            "subcategory":"Accounting & Tax Preparation",
            "type":"Services"
        }
    ],
    "sg:phone":"+1 510 681 6887",
    "sg:postcode":"94706",
    "sg:province":"CA",
    "sg:tags":[
        "return",
        "preparation-business"
    ],
    "wof:name":"Jackson Hewitt Inc.",
    "wof:placetype":"venue"
},
  "geometry": {"coordinates":[-122.292801,37.890272],"type":"Point"}
}