{
  "type": "Feature",
  "properties": {
    "addr:full":"123 N Palm Canyon Dr Palm Springs CA 92262",
    "addr:housenumber":"123",
    "addr:postcode":"92262",
    "addr:street":"N Palm Canyon Dr",
    "iso:country":"US",
    "sg:address":"123 N Palm Canyon Dr",
    "sg:city":"Palm Springs",
    "sg:classifiers":[
        {
            "category":"Restaurant",
            "type":"Food & Drink"
        }
    ],
    "sg:menulink":"http://www.allmenus.com/ca/palm-springs/69090-california-pizza-kitchen/menu/",
    "sg:phone":"+1 760 322 6075",
    "sg:postcode":"92262",
    "sg:province":"CA",
    "sg:tags":[
        "sandwich",
        "salad",
        "soup",
        "american",
        "pasta",
        "californian",
        "pizza"
    ],
    "wof:name":"California Pizza Kitchen",
    "wof:placetype":"venue"
},
  "geometry": {"coordinates":[-116.548202,33.825161],"type":"Point"}
}