{
  "type": "Feature",
  "properties": {
    "addr:full":"1625 Church St Redlands CA 92374",
    "addr:housenumber":"1625",
    "addr:postcode":"92374",
    "addr:street":"Church St",
    "iso:country":"US",
    "sg:address":"1625 Church St",
    "sg:city":"Redlands",
    "sg:classifiers":[
        {
            "category":"Freight",
            "type":"Transportation"
        }
    ],
    "sg:phone":"+1 951 235 1729",
    "sg:postcode":"92374",
    "sg:province":"CA",
    "sg:tags":[
        "trucking"
    ],
    "wof:name":"M & M",
    "wof:placetype":"venue"
},
  "geometry": {"coordinates":[-117.173686,34.07782],"type":"Point"}
}