{
  "type": "Feature",
  "properties": {
    "addr:full":"223 San Anselmo Ave San Anselmo CA 94960",
    "addr:housenumber":"223",
    "addr:postcode":"94960",
    "addr:street":"San Anselmo Ave",
    "iso:country":"US",
    "sg:address":"223 San Anselmo Ave",
    "sg:city":"San Anselmo",
    "sg:classifiers":[
        {
            "category":"Building & Trades",
            "subcategory":"Equipment Rental",
            "type":"Services"
        }
    ],
    "sg:phone":"+1 415 257 4200",
    "sg:postcode":"94960",
    "sg:province":"CA",
    "sg:tags":[
        "leasing"
    ],
    "wof:name":"Allegiant Interfund Inc",
    "wof:placetype":"venue"
},
  "geometry": {"coordinates":[-122.561904,37.972257],"type":"Point"}
}