{
  "type": "Feature",
  "properties": {
    "addr:full":"2828 Fletcher Dr Los Angeles CA 90039",
    "addr:housenumber":"2828",
    "addr:postcode":"90039",
    "addr:street":"Fletcher Dr",
    "iso:country":"US",
    "sg:address":"2828 Fletcher Dr",
    "sg:city":"Los Angeles",
    "sg:classifiers":[
        {
            "category":"Retail",
            "subcategory":"Auto Repair",
            "type":"Services"
        }
    ],
    "sg:phone":"+1 323 660 0900",
    "sg:postcode":"90039",
    "sg:province":"CA",
    "sg:tags":[
        "body",
        "automobile",
        "painting"
    ],
    "wof:name":"Mega Co",
    "wof:placetype":"venue"
},
  "geometry": {"coordinates":[-118.249818,34.111683],"type":"Point"}
}