{
  "type": "Feature",
  "properties": {
    "iso:country":"US",
    "sg:address":"9926 Horn Rd",
    "sg:city":"Sacramento",
    "sg:classifiers":[
        {
            "category":"Wholesale",
            "subcategory":"Construction Materials",
            "type":"Manufacturing & Wholesale Goods"
        },
        {
            "category":"Building & Trades",
            "subcategory":"Construction",
            "type":"Services"
        }
    ],
    "sg:phone":"+1 916 366 8453",
    "sg:postcode":"95827",
    "sg:province":"CA",
    "sg:tags":[
        "tile",
        "dealer"
    ],
    "wof:name":"Western Design Tile Inc",
    "wof:placetype":"venue"
},
  "geometry": {"coordinates":[-121.324932,38.575855],"type":"Point"}
}