{
  "type": "Feature",
  "properties": {
    "addr:full":"1800 Gravenstein Hwy N Sebastopol CA 95472",
    "addr:housenumber":"1800",
    "addr:postcode":"95472",
    "addr:street":"Gravenstein Hwy N",
    "iso:country":"US",
    "sg:address":"1800 Gravenstein Hwy N",
    "sg:city":"Sebastopol",
    "sg:classifiers":[
        {
            "category":"Health Services",
            "subcategory":"Clinic",
            "type":"Services"
        },
        {
            "category":"Social Services",
            "subcategory":"Child Care",
            "type":"Services"
        },
        {
            "category":"Education",
            "subcategory":"School",
            "type":"Public Place"
        }
    ],
    "sg:phone":"+1 707 823 7300",
    "sg:postcode":"95472",
    "sg:province":"CA",
    "sg:tags":[
        "planning",
        "information",
        "family",
        "agency",
        "private",
        "foster",
        "adoption",
        "k-"
    ],
    "sg:website":"http://www.tlc4kids.org",
    "wof:name":"TLC Child & Family Services",
    "wof:placetype":"venue"
},
  "geometry": {"coordinates":[-122.846092,38.422081],"type":"Point"}
}