{
  "type": "Feature",
  "properties": {
    "iso:country":"US",
    "sg:address":"2185 Main St",
    "sg:city":"Oakley",
    "sg:classifiers":[
        {
            "category":"Restaurant",
            "type":"Food & Drink"
        }
    ],
    "sg:menulink":"http://www.allmenus.com/ca/east-contra-costa/178752-jack-in-the-box/menu/",
    "sg:phone":"+1 925 625 5931",
    "sg:postcode":"94561",
    "sg:province":"CA",
    "sg:tags":[
        "burger",
        "american"
    ],
    "wof:name":"Jack in the Box",
    "wof:placetype":"venue"
},
  "geometry": {"coordinates":[-121.732359,38.002162],"type":"Point"}
}