{
  "type": "Feature",
  "properties": {
    "iso:country":"US",
    "sg:address":"6211 Yarrow Dr",
    "sg:city":"Carlsbad",
    "sg:classifiers":[
        {
            "category":"Home & Garden",
            "subcategory":"Furniture",
            "type":"Retail Goods"
        }
    ],
    "sg:phone":"+1 760 602 0669",
    "sg:postcode":"92011",
    "sg:province":"CA",
    "sg:tags":[
        "store"
    ],
    "sg:website":"www.ligne-roset.com",
    "wof:name":"Ligne Roset",
    "wof:placetype":"venue"
},
  "geometry": {"coordinates":[-117.273906,33.122422],"type":"Point"}
}