{
  "type": "Feature",
  "properties": {
    "addr:full":"1320 Oak Leaf Cir Oakdale CA 95361",
    "addr:housenumber":"1320",
    "addr:postcode":"95361",
    "addr:street":"Oak Leaf Cir",
    "iso:country":"US",
    "sg:address":"1320 Oak Leaf Cir",
    "sg:city":"Oakdale",
    "sg:classifiers":[
        {
            "category":"Building & Trades",
            "subcategory":"Cleaning & Sanitation",
            "type":"Services"
        }
    ],
    "sg:phone":"+1 209 847 2248",
    "sg:postcode":"95361",
    "sg:province":"CA",
    "sg:tags":[
        "house"
    ],
    "wof:name":"Custom Maids House Cleaning",
    "wof:placetype":"venue"
},
  "geometry": {"coordinates":[-120.83283900000001,37.76704],"type":"Point"}
}