{
  "type": "Feature",
  "properties": {
    "iso:country":"US",
    "sg:address":"742 Coyote Rd",
    "sg:city":"Santa Barbara",
    "sg:classifiers":[
        {
            "category":"Restaurant",
            "type":"Food & Drink"
        }
    ],
    "sg:phone":"+1 805 563 2725",
    "sg:postcode":"93108",
    "sg:province":"CA",
    "sg:tags":[
        "eating"
    ],
    "wof:name":"Ambrosia Catering",
    "wof:placetype":"venue"
},
  "geometry": {"coordinates":[-119.670686,34.449185],"type":"Point"}
}