{
  "type": "Feature",
  "properties": {
    "addr:full":"801 2nd St Santa Monica CA 90403",
    "addr:housenumber":"801",
    "addr:postcode":"90403",
    "addr:street":"2Nd St",
    "iso:country":"US",
    "sg:address":"801 2nd St",
    "sg:city":"Santa Monica",
    "sg:classifiers":[
        {
            "category":"Real Estate",
            "subcategory":"Real Estate Operator",
            "type":"Services"
        }
    ],
    "sg:phone":"+1 310 395 3027",
    "sg:postcode":"90403",
    "sg:province":"CA",
    "sg:tags":[
        "apartment"
    ],
    "wof:name":"B B & K Monica Inc",
    "wof:placetype":"venue"
},
  "geometry": {"coordinates":[-118.50493299999999,34.021668],"type":"Point"}
}