{
  "type": "Feature",
  "properties": {
    "iso:country":"US",
    "sg:address":"1615 Bridgeway",
    "sg:city":"Sausalito",
    "sg:classifiers":[
        {
            "category":"Retail",
            "subcategory":"Repair Shop",
            "type":"Services"
        }
    ],
    "sg:phone":"+1 415 331 5731",
    "sg:postcode":"94965",
    "sg:province":"CA",
    "sg:tags":[
        "upholsterer"
    ],
    "wof:name":"Golden Gate Interiors",
    "wof:placetype":"venue"
},
  "geometry": {"coordinates":[-122.489342,37.861131],"type":"Point"}
}