{
  "type": "Feature",
  "properties": {
    "addr:full":"3385 Scott Blvd Santa Clara CA 95050",
    "addr:housenumber":"3385",
    "addr:postcode":"95050",
    "addr:street":"Scott Blvd",
    "iso:country":"US",
    "sg:address":"3385 Scott Blvd",
    "sg:city":"Santa Clara",
    "sg:classifiers":[
        {
            "category":"Wholesale",
            "subcategory":"Electrical",
            "type":"Manufacturing & Wholesale Goods"
        }
    ],
    "sg:phone":"+1 408 727 6600",
    "sg:postcode":"95050",
    "sg:province":"CA",
    "sg:tags":[
        "equipment",
        "testing",
        "electronic"
    ],
    "sg:website":"www.catc.com",
    "wof:name":"Lecroy Corp Protocol Solutions",
    "wof:placetype":"venue"
},
  "geometry": {"coordinates":[-121.98563799999999,37.380645],"type":"Point"}
}