{
  "type": "Feature",
  "properties": {
    "addr:full":"13858 Chase St Panorama City CA 91402",
    "addr:housenumber":"13858",
    "addr:postcode":"91402",
    "addr:street":"Chase St",
    "iso:country":"US",
    "sg:address":"13858 Chase St",
    "sg:city":"Panorama City",
    "sg:classifiers":[
        {
            "category":"Bars & Pubs",
            "type":"Food & Drink"
        }
    ],
    "sg:phone":"+1 818 894 1817",
    "sg:postcode":"91402",
    "sg:province":"CA",
    "sg:tags":[
        "lounge",
        "cocktail"
    ],
    "wof:name":"Sand Trap",
    "wof:placetype":"venue"
},
  "geometry": {"coordinates":[-118.43502700000001,34.227548],"type":"Point"}
}