{
  "type": "Feature",
  "properties": {
    "addr:full":"1665 S Imperial Ave El Centro CA 92243",
    "addr:housenumber":"1665",
    "addr:postcode":"92243",
    "addr:street":"S Imperial Ave",
    "iso:country":"US",
    "sg:address":"1665 S Imperial Ave",
    "sg:city":"El Centro",
    "sg:classifiers":[
        {
            "category":"Health Services",
            "subcategory":"Podiatrist",
            "type":"Services"
        }
    ],
    "sg:phone":"+1 760 352 6062",
    "sg:postcode":"92243",
    "sg:province":"CA",
    "wof:name":"Federico R Hernandez DPM",
    "wof:placetype":"venue"
},
  "geometry": {"coordinates":[-115.56952800000001,32.77876],"type":"Point"}
}