{
  "type": "Feature",
  "properties": {
    "addr:full":"1361 Cassins St Carlsbad CA 92011",
    "addr:housenumber":"1361",
    "addr:postcode":"92011",
    "addr:street":"Cassins St",
    "iso:country":"US",
    "sg:address":"1361 Cassins St",
    "sg:city":"Carlsbad",
    "sg:classifiers":[
        {
            "category":"Banks & Credit Unions",
            "subcategory":"Investment Brokerage",
            "type":"Services"
        }
    ],
    "sg:phone":"+1 760 918 0710",
    "sg:postcode":"92011",
    "sg:province":"CA",
    "sg:tags":[
        "advisory",
        "financial"
    ],
    "wof:name":"Chase Manhattan Auto",
    "wof:placetype":"venue"
},
  "geometry": {"coordinates":[-117.29329199999999,33.098199],"type":"Point"}
}