{
  "type": "Feature",
  "properties": {
    "iso:country":"US",
    "sg:address":"2571 California Park Dr",
    "sg:city":"Chico",
    "sg:classifiers":[
        {
            "category":"Professional",
            "subcategory":"Lawyer & Legal Services",
            "type":"Services"
        }
    ],
    "sg:phone":"+1 530 899 9755",
    "sg:postcode":"95928",
    "sg:province":"CA",
    "sg:tags":[
        "attorney"
    ],
    "wof:name":"O'Laughlin & Paris LLP",
    "wof:placetype":"venue"
},
  "geometry": {"coordinates":[-121.791203,39.753834],"type":"Point"}
}