{
  "type": "Feature",
  "properties": {
    "iso:country":"US",
    "sg:address":"19354 Londelius St",
    "sg:city":"Northridge",
    "sg:classifiers":[
        {
            "category":"Shopping",
            "subcategory":"Catalog Store",
            "type":"Retail Goods"
        }
    ],
    "sg:phone":"+1 818 341 0997",
    "sg:postcode":"91324",
    "sg:province":"CA",
    "sg:tags":[
        "mail",
        "order"
    ],
    "wof:name":"In-Excess Productions Inc",
    "wof:placetype":"venue"
},
  "geometry": {"coordinates":[-118.55694800000001,34.229793],"type":"Point"}
}