{
  "type": "Feature",
  "properties": {
    "addr:full":"955 S E St San Bernardino CA 92408",
    "addr:housenumber":"955",
    "addr:postcode":"92408",
    "addr:street":"S E St",
    "iso:country":"US",
    "sg:address":"955 S E St",
    "sg:city":"San Bernardino",
    "sg:classifiers":[
        {
            "category":"Personal",
            "subcategory":"Beauty Salon",
            "type":"Services"
        }
    ],
    "sg:phone":"+1 909 888 2234",
    "sg:postcode":"92408",
    "sg:province":"CA",
    "wof:name":"Supercuts",
    "wof:placetype":"venue"
},
  "geometry": {"coordinates":[-117.293997,34.08266],"type":"Point"}
}