{
  "type": "Feature",
  "properties": {
    "addr:full":"3850 Wilshire Boulevard Los Angeles CA 90010",
    "addr:housenumber":"3850",
    "addr:postcode":"90010",
    "addr:street":"Wilshire Boulevard",
    "iso:country":"US",
    "sg:address":"3850 Wilshire Boulevard",
    "sg:city":"Los Angeles",
    "sg:classifiers":[
        {
            "category":"Arts & Performance",
            "subcategory":"Art Gallery",
            "type":"Entertainment"
        }
    ],
    "sg:phone":"+1 213 389 8188",
    "sg:postcode":"90010",
    "sg:province":"CA",
    "wof:name":"Dsl Andrew Shire Art Gallery",
    "wof:placetype":"venue"
},
  "geometry": {"coordinates":[-118.31068999999999,34.061661],"type":"Point"}
}