{
  "type": "Feature",
  "properties": {
    "addr:full":"9654 la Porte Rd Brownsville CA 95919",
    "addr:housenumber":"9654",
    "addr:postcode":"95919",
    "addr:street":"La Porte Rd",
    "iso:country":"US",
    "sg:address":"9654 la Porte Rd",
    "sg:city":"Brownsville",
    "sg:classifiers":[
        {
            "category":"Manufacturing",
            "subcategory":"Buildings",
            "type":"Manufacturing & Wholesale Goods"
        },
        {
            "category":"Building & Trades",
            "subcategory":"Construction",
            "type":"Services"
        }
    ],
    "sg:phone":"+1 530 675 0191",
    "sg:postcode":"95919",
    "sg:province":"CA",
    "sg:tags":[
        "home",
        "builder",
        "contractor"
    ],
    "wof:name":"Roy Construction Co",
    "wof:placetype":"venue"
},
  "geometry": {"coordinates":[-121.24379500000001,39.483402],"type":"Point"}
}