{
  "type": "Feature",
  "properties": {
    "iso:country":"US",
    "sg:address":"24012 Ave de la Carlota",
    "sg:city":"Laguna Hills",
    "sg:classifiers":[
        {
            "category":"Shopping",
            "subcategory":"Clothing, Apparel, & Fashions",
            "type":"Retail Goods"
        }
    ],
    "sg:phone":"+1 949 457 8196",
    "sg:postcode":"92653",
    "sg:province":"CA",
    "sg:tags":[
        "furnishing"
    ],
    "sg:website":"www.menswearhouse.com",
    "wof:name":"Men's Wearhouse",
    "wof:placetype":"venue"
},
  "geometry": {"coordinates":[-117.70715300000001,33.613366],"type":"Point"}
}