{
  "type": "Feature",
  "properties": {
    "iso:country":"US",
    "sg:address":"1841 W Lincoln Ave Ste D",
    "sg:city":"Anaheim",
    "sg:classifiers":[
        {
            "category":"Food & Beverages",
            "subcategory":"Liquor & Beverages",
            "type":"Retail Goods"
        }
    ],
    "sg:phone":"+1 714 758 0705",
    "sg:postcode":"92801",
    "sg:province":"CA",
    "sg:tags":[
        "beer",
        "spirit",
        "wine"
    ],
    "wof:name":"Walkers's Liquor & Deli",
    "wof:placetype":"venue"
},
  "geometry": {"coordinates":[-117.94699900000001,33.8326],"type":"Point"}
}