{
  "type": "Feature",
  "properties": {
    "addr:full":"17 Wood Ct San Anselmo CA 94960",
    "addr:housenumber":"17",
    "addr:postcode":"94960",
    "addr:street":"Wood Ct",
    "iso:country":"US",
    "sg:address":"17 Wood Ct",
    "sg:city":"San Anselmo",
    "sg:classifiers":[
        {
            "category":"Health Services",
            "subcategory":"Doctor",
            "type":"Services"
        }
    ],
    "sg:phone":"+1 415 459 9200",
    "sg:postcode":"94960",
    "sg:province":"CA",
    "sg:tags":[
        "physician",
        "surgeon"
    ],
    "wof:name":"Catherine Fehrmann MD",
    "wof:placetype":"venue"
},
  "geometry": {"coordinates":[-122.570182,37.987926],"type":"Point"}
}