{
  "type": "Feature",
  "properties": {
    "iso:country":"US",
    "sg:address":"4635 Elverta Rd",
    "sg:city":"Antelope",
    "sg:classifiers":[
        {
            "category":"Education",
            "subcategory":"School",
            "type":"Public Place"
        }
    ],
    "sg:phone":"+1 916 726 1400",
    "sg:postcode":"95843",
    "sg:province":"CA",
    "sg:tags":[
        "high"
    ],
    "wof:name":"Antelope High School",
    "wof:placetype":"venue"
},
  "geometry": {"coordinates":[-121.358425,38.711517],"type":"Point"}
}