{
  "type": "Feature",
  "properties": {
    "addr:full":"1230 Western St Fairfield CA 94533",
    "addr:housenumber":"1230",
    "addr:postcode":"94533",
    "addr:street":"Western St",
    "iso:country":"US",
    "sg:address":"1230 Western St",
    "sg:city":"Fairfield",
    "sg:classifiers":[
        {
            "category":"Real Estate",
            "subcategory":"Real Estate Operator",
            "type":"Services"
        }
    ],
    "sg:phone":"+1 707 427 0223",
    "sg:postcode":"94533",
    "sg:province":"CA",
    "sg:tags":[
        "building",
        "apartment"
    ],
    "wof:name":"Branson Rentals",
    "wof:placetype":"venue"
},
  "geometry": {"coordinates":[-122.008104,38.27404],"type":"Point"}
}