{
  "type": "Feature",
  "properties": {
    "addr:full":"1221 E Cypress Ave Redding CA 96002",
    "addr:housenumber":"1221",
    "addr:postcode":"96002",
    "addr:street":"E Cypress Ave",
    "iso:country":"US",
    "sg:address":"1221 E Cypress Ave",
    "sg:city":"Redding",
    "sg:classifiers":[
        {
            "category":"Real Estate",
            "subcategory":"Real Estate Operator",
            "type":"Services"
        }
    ],
    "sg:phone":"+1 530 222 0448",
    "sg:postcode":"96002",
    "sg:province":"CA",
    "sg:tags":[
        "mobile",
        "home",
        "community"
    ],
    "wof:name":"Starlite Mobile Estates",
    "wof:placetype":"venue"
},
  "geometry": {"coordinates":[-122.350354,40.570992],"type":"Point"}
}