{
  "type": "Feature",
  "properties": {
    "addr:full":"145 Town and Country Dr Danville CA 94526",
    "addr:housenumber":"145",
    "addr:postcode":"94526",
    "addr:street":"Town And Country Dr",
    "iso:country":"US",
    "sg:address":"145 Town and Country Dr",
    "sg:city":"Danville",
    "sg:classifiers":[
        {
            "category":"Building & Trades",
            "subcategory":"Landscaping Services",
            "type":"Services"
        }
    ],
    "sg:phone":"+1 925 735 7407",
    "sg:postcode":"94526",
    "sg:province":"CA",
    "wof:name":"Eastrock Lanscape",
    "wof:placetype":"venue"
},
  "geometry": {"coordinates":[-122.000664,37.81356],"type":"Point"}
}