{
  "type": "Feature",
  "properties": {
    "addr:full":"16624 Chatsworth St Granada Hills CA 91344",
    "addr:housenumber":"16624",
    "addr:postcode":"91344",
    "addr:street":"Chatsworth St",
    "iso:country":"US",
    "sg:address":"16624 Chatsworth St",
    "sg:city":"Granada Hills",
    "sg:classifiers":[
        {
            "category":"Shopping",
            "type":"Retail Goods"
        }
    ],
    "sg:phone":"+1 818 363 8060",
    "sg:postcode":"91344",
    "sg:province":"CA",
    "sg:tags":[
        "telephone",
        "cellular"
    ],
    "wof:name":"Direct Communications",
    "wof:placetype":"venue"
},
  "geometry": {"coordinates":[-118.49746,34.264666],"type":"Point"}
}