{
  "type": "Feature",
  "properties": {
    "iso:country":"US",
    "sg:address":"17202 Norwalk Blvd",
    "sg:city":"Cerritos",
    "sg:classifiers":[
        {
            "category":"Restaurant",
            "type":"Food & Drink"
        },
        {
            "category":"Food & Beverages",
            "subcategory":"Groceries & Convenience Stores",
            "type":"Retail Goods"
        }
    ],
    "sg:phone":"+1 562 207 4421",
    "sg:postcode":"90703",
    "sg:province":"CA",
    "sg:tags":[
        "filipino"
    ],
    "sg:website":"www.seafoodcity.com",
    "wof:name":"Seafood City",
    "wof:placetype":"venue"
},
  "geometry": {"coordinates":[-118.072581,33.874038],"type":"Point"}
}