{
  "type": "Feature",
  "properties": {
    "addr:full":"1809 West Boulevard Los Angeles CA 90019",
    "addr:housenumber":"1809",
    "addr:postcode":"90019",
    "addr:street":"West Boulevard",
    "iso:country":"US",
    "sg:address":"1809 West Boulevard",
    "sg:city":"Los Angeles",
    "sg:classifiers":[
        {
            "category":"Social Services",
            "subcategory":"Child Care",
            "type":"Services"
        }
    ],
    "sg:phone":"+1 323 954 8099",
    "sg:postcode":"90019",
    "sg:province":"CA",
    "sg:tags":[
        "day"
    ],
    "wof:name":"Head Start At First Presbyterian Church",
    "wof:placetype":"venue"
},
  "geometry": {"coordinates":[-118.336923,34.04027],"type":"Point"}
}