{
  "type": "Feature",
  "properties": {
    "iso:country":"US",
    "sg:address":"1570 W Branch St",
    "sg:city":"Arroyo Grande",
    "sg:classifiers":[
        {
            "category":"Restaurant",
            "type":"Food & Drink"
        }
    ],
    "sg:phone":"+1 805 481 6204",
    "sg:postcode":"93420",
    "sg:province":"CA",
    "sg:tags":[
        "pizza"
    ],
    "wof:name":"Little Caesars Pizza",
    "wof:placetype":"venue"
},
  "geometry": {"coordinates":[-120.60176,35.129144],"type":"Point"}
}