{
  "type": "Feature",
  "properties": {
    "addr:full":"2716 Telegraph Ave Berkeley CA 94705",
    "addr:housenumber":"2716",
    "addr:postcode":"94705",
    "addr:street":"Telegraph Ave",
    "iso:country":"US",
    "sg:address":"2716 Telegraph Ave",
    "sg:city":"Berkeley",
    "sg:classifiers":[
        {
            "category":"Real Estate",
            "subcategory":"Real Estate Agent",
            "type":"Services"
        }
    ],
    "sg:phone":"+1 510 548 1210",
    "sg:postcode":"94705",
    "sg:province":"CA",
    "sg:tags":[
        "appraisers-business",
        "industrial",
        "commercial",
        "appraiser"
    ],
    "sg:website":"www.yovino.com",
    "wof:name":"Yovino Young Inc",
    "wof:placetype":"venue"
},
  "geometry": {"coordinates":[-122.25935,37.860824],"type":"Point"}
}