{
  "type": "Feature",
  "properties": {
    "addr:full":"660 Leslie St Ukiah CA 95482",
    "addr:housenumber":"660",
    "addr:postcode":"ca 95482",
    "addr:street":"Leslie St",
    "iso:country":"US",
    "sg:address":"660 Leslie St",
    "sg:city":"Ukiah",
    "sg:classifiers":[
        {
            "category":"Real Estate",
            "subcategory":"Real Estate Operator",
            "type":"Services"
        }
    ],
    "sg:phone":"+1 707 462 3153",
    "sg:postcode":"95482",
    "sg:province":"CA",
    "sg:tags":[
        "mobile",
        "home",
        "community"
    ],
    "wof:name":"Rancho Del Rey Mobile Home Prk",
    "wof:placetype":"venue"
},
  "geometry": {"coordinates":[-123.20124199999999,39.146183],"type":"Point"}
}