{
  "type": "Feature",
  "properties": {
    "addr:full":"25574 Rye Canyon Rd Ste B Santa Clarita CA 91355",
    "addr:postcode":"25574;91355",
    "addr:street":"Rye Canyon Rd Ste B",
    "iso:country":"US",
    "sg:address":"25574 Rye Canyon Rd Ste B",
    "sg:city":"Santa Clarita",
    "sg:classifiers":[
        {
            "category":"Recreation",
            "subcategory":"Boat Charter",
            "type":"Entertainment"
        }
    ],
    "sg:phone":"+1 661 702 1420",
    "sg:postcode":"91355",
    "sg:province":"CA",
    "sg:tags":[
        "boating"
    ],
    "sg:website":"www.pyramid-enterprises.com",
    "wof:name":"Pyramid Enterprises",
    "wof:placetype":"venue"
},
  "geometry": {"coordinates":[-118.584102,34.434319],"type":"Point"}
}