{
  "type": "Feature",
  "properties": {
    "iso:country":"US",
    "sg:address":"15333 Pioneer Blvd",
    "sg:city":"Norwalk",
    "sg:classifiers":[
        {
            "category":"Building & Trades",
            "subcategory":"Cleaning & Sanitation",
            "type":"Services"
        }
    ],
    "sg:phone":"+1 562 726 6444",
    "sg:postcode":"90650",
    "sg:province":"CA",
    "sg:tags":[
        "carpet"
    ],
    "wof:name":"Garrett's Carpet Cleaning & Janitorial Services",
    "wof:placetype":"venue"
},
  "geometry": {"coordinates":[-118.26252,33.89175],"type":"Point"}
}