{
  "type": "Feature",
  "properties": {
    "addr:full":"4624 W 116th St Hawthorne CA 90250",
    "addr:housenumber":"4624",
    "addr:postcode":"90250",
    "addr:street":"W 116Th St",
    "iso:country":"US",
    "sg:address":"4624 W 116th St",
    "sg:city":"Hawthorne",
    "sg:classifiers":[
        {
            "category":"Restaurant",
            "type":"Food & Drink"
        }
    ],
    "sg:phone":"+1 310 644 6200",
    "sg:postcode":"90250",
    "sg:province":"CA",
    "sg:tags":[
        "caterer"
    ],
    "wof:name":"Four Hearts Staffing Svc",
    "wof:placetype":"venue"
},
  "geometry": {"coordinates":[-118.35761599999999,33.929044],"type":"Point"}
}