{
  "type": "Feature",
  "properties": {
    "addr:full":"526 E Redondo Beach Blvd Gardena CA 90248",
    "addr:housenumber":"526",
    "addr:postcode":"90248",
    "addr:street":"E Redondo Beach Blvd",
    "iso:country":"US",
    "sg:address":"526 E Redondo Beach Blvd",
    "sg:city":"Gardena",
    "sg:classifiers":[
        {
            "category":"Building & Trades",
            "subcategory":"Cleaning & Sanitation",
            "type":"Services"
        }
    ],
    "sg:phone":"+1 310 769 4902",
    "sg:postcode":"90248",
    "sg:province":"CA",
    "sg:tags":[
        "house"
    ],
    "wof:name":"A-1 Enviro Clean",
    "wof:placetype":"venue"
},
  "geometry": {"coordinates":[-118.266829,33.893113],"type":"Point"}
}