{
  "type": "Feature",
  "properties": {
    "addr:full":"211 Limerick Ln Healdsburg CA 95448",
    "addr:housenumber":"211",
    "addr:postcode":"95448",
    "addr:street":"Limerick Ln",
    "iso:country":"US",
    "sg:address":"211 Limerick Ln",
    "sg:city":"Healdsburg",
    "sg:classifiers":[
        {
            "category":"Wholesale",
            "subcategory":"Plants",
            "type":"Manufacturing & Wholesale Goods"
        }
    ],
    "sg:phone":"+1 707 433 5091",
    "sg:postcode":"95448",
    "sg:province":"CA",
    "sg:tags":[
        "nursery",
        "tree"
    ],
    "wof:name":"Vine & Branches WHOL Nursery",
    "wof:placetype":"venue"
},
  "geometry": {"coordinates":[-122.84808,38.588125],"type":"Point"}
}