{
  "type": "Feature",
  "properties": {
    "addr:full":"451 College Ave Santa Rosa CA 95401",
    "addr:housenumber":"451",
    "addr:postcode":"95401",
    "addr:street":"College Ave",
    "iso:country":"US",
    "sg:address":"451 College Ave",
    "sg:city":"Santa Rosa",
    "sg:classifiers":[
        {
            "category":"Professional",
            "type":"Services"
        }
    ],
    "sg:phone":"+1 707 591 9799",
    "sg:postcode":"95401",
    "sg:province":"CA",
    "wof:name":"Jeff Malmuth & Co",
    "wof:placetype":"venue"
},
  "geometry": {"coordinates":[-122.718879,38.445752],"type":"Point"}
}