{
  "type": "Feature",
  "properties": {
    "addr:full":"1880 Hanlon Way Pittsburg CA 94565",
    "addr:housenumber":"1880",
    "addr:postcode":"94565",
    "addr:street":"Hanlon Way",
    "iso:country":"US",
    "sg:address":"1880 Hanlon Way",
    "sg:city":"Pittsburg",
    "sg:classifiers":[
        {
            "category":"Education",
            "subcategory":"School",
            "type":"Public Place"
        }
    ],
    "sg:phone":"+1 925 709 2000",
    "sg:postcode":"94565",
    "sg:province":"CA",
    "wof:name":"Willow Cove Elementary School",
    "wof:placetype":"venue"
},
  "geometry": {"coordinates":[-121.925962,38.023181],"type":"Point"}
}