{
  "type": "Feature",
  "properties": {
    "addr:full":"710 Post St San Francisco CA 94109",
    "addr:housenumber":"710",
    "addr:postcode":"94109",
    "addr:street":"Post St",
    "iso:country":"US",
    "sg:address":"710 Post St",
    "sg:city":"San Francisco",
    "sg:classifiers":[
        {
            "category":"Personal",
            "subcategory":"Massage",
            "type":"Services"
        }
    ],
    "sg:phone":"+1 415 929 6822",
    "sg:postcode":"94109",
    "sg:province":"CA",
    "wof:name":"Hawaiian Village Day Spa & Massage",
    "wof:placetype":"venue"
},
  "geometry": {"coordinates":[-122.41366499999999,37.787715],"type":"Point"}
}