{
  "type": "Feature",
  "properties": {
    "iso:country":"US",
    "sg:address":"27 Aaron Dr",
    "sg:city":"Novato",
    "sg:classifiers":[
        {
            "category":"Manufacturing",
            "subcategory":"Tools & Machinery",
            "type":"Manufacturing & Wholesale Goods"
        }
    ],
    "sg:phone":"+1 415 382 8853",
    "sg:postcode":"94949",
    "sg:province":"CA",
    "sg:tags":[
        "equipment",
        "professional",
        "calibration",
        "re",
        "certification"
    ],
    "wof:name":"Instrument Control Company",
    "wof:placetype":"venue"
},
  "geometry": {"coordinates":[-122.560394,38.071643],"type":"Point"}
}