{
  "type": "Feature",
  "properties": {
    "iso:country":"US",
    "sg:address":"603 S Mansfield Ave",
    "sg:city":"Los Angeles",
    "sg:classifiers":[
        {
            "category":"Shopping",
            "subcategory":"Used Merchandise",
            "type":"Retail Goods"
        }
    ],
    "sg:phone":"+1 213 487 6767",
    "sg:postcode":"90036",
    "sg:province":"CA",
    "wof:name":"Hidden Treasures Antiques Etc",
    "wof:placetype":"venue"
},
  "geometry": {"coordinates":[-118.340833,34.062901],"type":"Point"}
}