{
  "type": "Feature",
  "properties": {
    "iso:country":"US",
    "sg:address":"3100 E Slauson Ave",
    "sg:city":"Vernon",
    "sg:classifiers":[
        {
            "category":"Manufacturing",
            "subcategory":"Metals",
            "type":"Manufacturing & Wholesale Goods"
        }
    ],
    "sg:phone":"+1 323 277 3211",
    "sg:postcode":"90058",
    "sg:province":"CA",
    "sg:tags":[
        "brass",
        "product"
    ],
    "wof:name":"Productmax USA",
    "wof:placetype":"venue"
},
  "geometry": {"coordinates":[-118.21088899999999,33.989197],"type":"Point"}
}