{
  "type": "Feature",
  "properties": {
    "iso:country":"US",
    "sg:address":"100 Blue Ravine Rd",
    "sg:city":"Folsom",
    "sg:classifiers":[
        {
            "category":"Manufacturing",
            "subcategory":"Printing",
            "type":"Manufacturing & Wholesale Goods"
        }
    ],
    "sg:phone":"+1 916 363 8191",
    "sg:postcode":"95630",
    "sg:province":"CA",
    "sg:tags":[
        "publishes",
        "monthly",
        "newspaper"
    ],
    "wof:name":"California Computer News",
    "wof:placetype":"venue"
},
  "geometry": {"coordinates":[-121.187153,38.651236],"type":"Point"}
}