{
  "type": "Feature",
  "properties": {
    "iso:country":"US",
    "sg:address":"331 15th St",
    "sg:city":"Oakland",
    "sg:classifiers":[
        {
            "category":"Personal",
            "subcategory":"Beauty Salon",
            "type":"Services"
        }
    ],
    "sg:phone":"+1 510 763 2769",
    "sg:postcode":"94612",
    "sg:province":"CA",
    "wof:name":"Simply Raw Hair Studio",
    "wof:placetype":"venue"
},
  "geometry": {"coordinates":[-122.267609,37.803996],"type":"Point"}
}