{
  "type": "Feature",
  "properties": {
    "iso:country":"US",
    "sg:address":"145 S Glenoaks Blvd",
    "sg:city":"Burbank",
    "sg:classifiers":[
        {
            "category":"Shopping",
            "subcategory":"Department Store",
            "type":"Retail Goods"
        }
    ],
    "sg:phone":"+1 818 261 3901",
    "sg:postcode":"91502",
    "sg:province":"CA",
    "sg:tags":[
        "shop"
    ],
    "wof:name":"Discount Copier Svc",
    "wof:placetype":"venue"
},
  "geometry": {"coordinates":[-118.305635,34.182726],"type":"Point"}
}