{
  "type": "Feature",
  "properties": {
    "addr:full":"Twin Pines Park Senior & Community Center 1223 Ralston Ave Belmont CA 94002",
    "addr:housenumber":"1223",
    "addr:postcode":"94002",
    "addr:street":"Ralston Ave",
    "iso:country":"US",
    "sg:address":"Twin Pines Park Senior & Community Center 1223 Ralston Ave",
    "sg:city":"Belmont",
    "sg:classifiers":[
        {
            "category":"Education",
            "subcategory":"Special Training",
            "type":"Public Place"
        }
    ],
    "sg:postcode":"94002",
    "sg:province":"CA",
    "sg:tags":[
        "adult"
    ],
    "sg:website":"scbtoastmasters.com",
    "wof:name":"San Carlos Belmont Toastmasters",
    "wof:placetype":"venue"
},
  "geometry": {"coordinates":[-122.279387,37.516832],"type":"Point"}
}