{
  "type": "Feature",
  "properties": {
    "addr:full":"32978 Auberry Rd Auberry CA 93602",
    "addr:postcode":"32978;93602",
    "addr:street":"Auberry Rd",
    "iso:country":"US",
    "sg:address":"32978 Auberry Rd",
    "sg:city":"Auberry",
    "sg:classifiers":[
        {
            "category":"Insurance",
            "subcategory":"Hazard Insurance",
            "type":"Services"
        }
    ],
    "sg:phone":"+1 559 855 6600",
    "sg:postcode":"93602",
    "sg:province":"CA",
    "sg:tags":[
        "bond"
    ],
    "wof:name":"West-Pac General Agency",
    "wof:placetype":"venue"
},
  "geometry": {"coordinates":[-119.486198,37.074721],"type":"Point"}
}