{
  "type": "Feature",
  "properties": {
    "addr:full":"9972 Garden Grove Blvd Garden Grove CA 92844",
    "addr:housenumber":"9972",
    "addr:postcode":"92844",
    "addr:street":"Garden Grove Blvd",
    "iso:country":"US",
    "sg:address":"9972 Garden Grove Blvd",
    "sg:city":"Garden Grove",
    "sg:classifiers":[
        {
            "category":"Wholesale",
            "subcategory":"Electrical",
            "type":"Manufacturing & Wholesale Goods"
        }
    ],
    "sg:phone":"+1 714 537 8952",
    "sg:postcode":"92844",
    "sg:province":"CA",
    "sg:tags":[
        "electronic"
    ],
    "wof:name":"Rstv",
    "wof:placetype":"venue"
},
  "geometry": {"coordinates":[-117.958459,33.773948],"type":"Point"}
}