{
  "type": "Feature",
  "properties": {
    "iso:country":"US",
    "sg:address":"11305 Rancho Bernardo Rd",
    "sg:city":"San Diego",
    "sg:classifiers":[
        {
            "category":"Professional",
            "subcategory":"Engineering",
            "type":"Services"
        }
    ],
    "sg:phone":"+1 858 674 6559",
    "sg:postcode":"92127",
    "sg:province":"CA",
    "sg:tags":[
        "engineer"
    ],
    "wof:name":"Geosyntec Consultants",
    "wof:placetype":"venue"
},
  "geometry": {"coordinates":[-117.085334,33.024362],"type":"Point"}
}