{
  "type": "Feature",
  "properties": {
    "addr:full":"125 Altena St San Rafael CA 94901",
    "addr:housenumber":"125",
    "addr:postcode":"94901",
    "addr:street":"Altena St",
    "iso:country":"US",
    "sg:address":"125 Altena St",
    "sg:city":"San Rafael",
    "sg:classifiers":[
        {
            "category":"Professional",
            "subcategory":"Business Services",
            "type":"Services"
        }
    ],
    "sg:phone":"+1 415 459 7180",
    "sg:postcode":"94901",
    "sg:province":"CA",
    "sg:tags":[
        "recording",
        "studio"
    ],
    "wof:name":"Reeltime Duplication",
    "wof:placetype":"venue"
},
  "geometry": {"coordinates":[-122.509314,37.955455],"type":"Point"}
}