{
  "type": "Feature",
  "properties": {
    "iso:country":"US",
    "sg:address":"125 Altena St",
    "sg:city":"San Rafael",
    "sg:classifiers":[
        {
            "category":"Professional",
            "subcategory":"Business Services",
            "type":"Services"
        }
    ],
    "sg:phone":"+1 415 459 7180",
    "sg:postcode":"94901",
    "sg:province":"CA",
    "sg:tags":[
        "recording",
        "studio"
    ],
    "wof:name":"Reeltime Duplication",
    "wof:placetype":"venue"
},
  "geometry": {"coordinates":[-122.509314,37.955455],"type":"Point"}
}