{
  "type": "Feature",
  "properties": {
    "iso:country":"US",
    "sg:address":"825 College Blvd. suite 102#134",
    "sg:city":"Oceanside",
    "sg:classifiers":[
        {
            "category":"Arts & Performance",
            "subcategory":"Arts Center",
            "type":"Entertainment"
        },
        {
            "category":"Building & Trades",
            "subcategory":"Construction",
            "type":"Services"
        },
        {
            "category":"Wholesale",
            "subcategory":"Home Furnishings",
            "type":"Manufacturing & Wholesale Goods"
        }
    ],
    "sg:phone":"+1 760 390 9417",
    "sg:postcode":"92057",
    "sg:province":"CA",
    "sg:tags":[
        "blind",
        "hand",
        "design",
        "shade",
        "interior",
        "decorating",
        "painting"
    ],
    "sg:website":"http://casabonitainteriors.com",
    "wof:name":"Casa Bonita Interiors",
    "wof:placetype":"venue"
},
  "geometry": {"coordinates":[-117.291411,33.238998],"type":"Point"}
}