{
  "type": "Feature",
  "properties": {
    "addr:full":"10097 Jay Jay Pl Grass Valley CA 95949",
    "addr:housenumber":"10097",
    "addr:postcode":"95949",
    "addr:street":"Jay Jay Pl",
    "iso:country":"US",
    "sg:address":"10097 Jay Jay Pl",
    "sg:city":"Grass Valley",
    "sg:classifiers":[
        {
            "category":"Shopping",
            "subcategory":"Computers & Home Electronics",
            "type":"Retail Goods"
        }
    ],
    "sg:phone":"+1 530 272 5455",
    "sg:postcode":"95949",
    "sg:province":"CA",
    "sg:tags":[
        "software"
    ],
    "sg:website":"www.snsd.com",
    "wof:name":"Sierra Nevada Software Dev",
    "wof:placetype":"venue"
},
  "geometry": {"coordinates":[-121.057599,39.159449],"type":"Point"}
}