{
  "type": "Feature",
  "properties": {
    "iso:country":"US",
    "sg:address":"40245 Hobby Horse Rd",
    "sg:city":"Temecula",
    "sg:classifiers":[
        {
            "category":"Utilities",
            "subcategory":"Water",
            "type":"Services"
        }
    ],
    "sg:phone":"+1 951 767 1198",
    "sg:postcode":"92592",
    "sg:province":"CA",
    "sg:tags":[
        "supply"
    ],
    "wof:name":"Rancho Water Welldrilling",
    "wof:placetype":"venue"
},
  "geometry": {"coordinates":[-116.957566,33.5764],"type":"Point"}
}