{
  "type": "Feature",
  "properties": {
    "iso:country":"US",
    "sg:address":"12821 Carmenita Rd",
    "sg:city":"Santa Fe Springs",
    "sg:classifiers":[
        {
            "category":"Manufacturing",
            "subcategory":"Tools & Machinery",
            "type":"Manufacturing & Wholesale Goods"
        }
    ],
    "sg:phone":"+1 562 404 9900",
    "sg:postcode":"90670",
    "sg:province":"CA",
    "sg:tags":[
        "industry",
        "aerospace"
    ],
    "wof:name":"TMX Aerospace",
    "wof:placetype":"venue"
},
  "geometry": {"coordinates":[-118.046668,33.914438],"type":"Point"}
}