{
  "type": "Feature",
  "properties": {
    "iso:country":"US",
    "sg:address":"727 W 7th St",
    "sg:city":"Los Angeles",
    "sg:classifiers":[
        {
            "category":"Professional",
            "subcategory":"Printing & Photocopies",
            "type":"Services"
        }
    ],
    "sg:phone":"+1 213 489 2221",
    "sg:postcode":"90017",
    "sg:province":"CA",
    "sg:tags":[
        "duplicating",
        "copying"
    ],
    "wof:name":"Dolphin Document Solutions",
    "wof:placetype":"venue"
},
  "geometry": {"coordinates":[-118.258481,34.048563],"type":"Point"}
}