{
  "type": "Feature",
  "properties": {
    "addr:full":"9197 Central Ave Montclair CA 91763",
    "addr:housenumber":"9197",
    "addr:postcode":"91763",
    "addr:street":"Central Ave",
    "iso:country":"US",
    "sg:address":"9197 Central Ave",
    "sg:city":"Montclair",
    "sg:classifiers":[
        {
            "category":"Personal",
            "subcategory":"Beauty Salon",
            "type":"Services"
        }
    ],
    "sg:phone":"+1 909 626 8428",
    "sg:postcode":"91763",
    "sg:province":"CA",
    "sg:tags":[
        "manicuring"
    ],
    "wof:name":"Montclair Nail",
    "wof:placetype":"venue"
},
  "geometry": {"coordinates":[-117.689505,34.08689],"type":"Point"}
}