{
  "type": "Feature",
  "properties": {
    "addr:full":"1370 Willow Road Menlo Park CA 94025",
    "addr:housenumber":"1370",
    "addr:postcode":"94025",
    "addr:street":"Willow Road",
    "iso:country":"US",
    "sg:address":"1370 Willow Road",
    "sg:city":"Menlo Park",
    "sg:classifiers":[
        {
            "category":"Professional",
            "subcategory":"Computer Services",
            "type":"Services"
        }
    ],
    "sg:postcode":"94025",
    "sg:province":"CA",
    "sg:tags":[
        "video",
        "chat",
        "facebook",
        "real-time"
    ],
    "sg:website":"http://www.vchatter.com",
    "wof:name":"vChatter",
    "wof:placetype":"venue"
},
  "geometry": {"coordinates":[-122.15283100000001,37.476189],"type":"Point"}
}