{
  "type": "Feature",
  "properties": {
    "addr:full":"428 Missouri St San Francisco CA 94107",
    "addr:housenumber":"428",
    "addr:postcode":"94107",
    "addr:street":"Missouri St",
    "iso:country":"US",
    "sg:address":"428 Missouri St",
    "sg:city":"San Francisco",
    "sg:classifiers":[
        {
            "category":"Professional",
            "subcategory":"Art Services",
            "type":"Services"
        }
    ],
    "sg:phone":"+1 415 550 8175",
    "sg:postcode":"94107",
    "sg:province":"CA",
    "sg:tags":[
        "commercial",
        "design"
    ],
    "wof:name":"Rose De Heer Design",
    "wof:placetype":"venue"
},
  "geometry": {"coordinates":[-122.39638600000001,37.760384],"type":"Point"}
}