{
  "type": "Feature",
  "properties": {
    "addr:full":"26 Corporate Plaza Dr Newport Beach CA 92660",
    "addr:housenumber":"26",
    "addr:postcode":"92660",
    "addr:street":"Plaza Dr",
    "iso:country":"US",
    "sg:address":"26 Corporate Plaza Dr",
    "sg:city":"Newport Beach",
    "sg:classifiers":[
        {
            "category":"Travel",
            "subcategory":"Travel Agent",
            "type":"Entertainment"
        }
    ],
    "sg:phone":"+1 949 717 3333",
    "sg:postcode":"92660",
    "sg:province":"CA",
    "sg:tags":[
        "tours",
        "promoter"
    ],
    "sg:website":"www.gptours.com",
    "wof:name":"Grand Prix Tours",
    "wof:placetype":"venue"
},
  "geometry": {"coordinates":[-117.87515399999999,33.6074],"type":"Point"}
}