{
  "type": "Feature",
  "properties": {
    "addr:full":"111 W Evelyn Avenue Suite 210 Sunnyvale CA 94086",
    "addr:housenumber":"111",
    "addr:postcode":"94086",
    "addr:street":"W Evelyn Avenue Suite 210",
    "iso:country":"US",
    "sg:address":"111 W Evelyn Avenue Suite 210",
    "sg:city":"Sunnyvale",
    "sg:classifiers":[
        {
            "category":"Wholesale",
            "subcategory":"Computers",
            "type":"Manufacturing & Wholesale Goods"
        }
    ],
    "sg:phone":"+1 408 739 5400",
    "sg:postcode":"94086",
    "sg:province":"CA",
    "wof:name":"Mobius Micro",
    "wof:placetype":"venue"
},
  "geometry": {"coordinates":[-122.028976,37.377354],"type":"Point"}
}