{
  "type": "Feature",
  "properties": {
    "iso:country":"US",
    "sg:address":"201 S Douglas St",
    "sg:city":"El Segundo",
    "sg:classifiers":[
        {
            "category":"Building & Trades",
            "subcategory":"Construction",
            "type":"Services"
        }
    ],
    "sg:phone":"+1 310 978 2098",
    "sg:postcode":"90245",
    "sg:province":"CA",
    "sg:tags":[
        "contractor"
    ],
    "wof:name":"Prestige Building Services",
    "wof:placetype":"venue"
},
  "geometry": {"coordinates":[-118.383003,33.9146],"type":"Point"}
}