{
  "type": "Feature",
  "properties": {
    "iso:country":"US",
    "sg:address":"921 W Artesia Blvd",
    "sg:city":"Compton",
    "sg:classifiers":[
        {
            "category":"Freight",
            "type":"Transportation"
        }
    ],
    "sg:phone":"+1 310 928 0389",
    "sg:postcode":"90220",
    "sg:province":"CA",
    "wof:name":"Katco",
    "wof:placetype":"venue"
},
  "geometry": {"coordinates":[-118.237299,33.874301],"type":"Point"}
}