{
  "type": "Feature",
  "properties": {
    "addr:full":"921 W Artesia Blvd Compton CA 90220",
    "addr:housenumber":"921",
    "addr:postcode":"90220",
    "addr:street":"W Artesia Blvd",
    "iso:country":"US",
    "sg:address":"921 W Artesia Blvd",
    "sg:city":"Compton",
    "sg:classifiers":[
        {
            "category":"Freight",
            "type":"Transportation"
        }
    ],
    "sg:phone":"+1 310 928 0389",
    "sg:postcode":"90220",
    "sg:province":"CA",
    "wof:name":"Katco",
    "wof:placetype":"venue"
},
  "geometry": {"coordinates":[-118.23729899999999,33.874301],"type":"Point"}
}