{
  "type": "Feature",
  "properties": {
    "iso:country":"US",
    "sg:address":"2850 Boles St",
    "sg:city":"Madera",
    "sg:classifiers":[
        {
            "category":"Farming",
            "subcategory":"Farm",
            "type":"Manufacturing & Wholesale Goods"
        }
    ],
    "sg:phone":"+1 559 673 6246",
    "sg:postcode":"93637",
    "sg:province":"CA",
    "sg:tags":[
        "crop",
        "general"
    ],
    "wof:name":"Cantu Labor",
    "wof:placetype":"venue"
},
  "geometry": {"coordinates":[-120.095133,36.989936],"type":"Point"}
}