{
  "type": "Feature",
  "properties": {
    "addr:full":"1586 Bush St San Francisco CA 94109",
    "addr:housenumber":"1586",
    "addr:postcode":"94109",
    "addr:street":"Bush St",
    "iso:country":"US",
    "sg:address":"1586 Bush St",
    "sg:city":"San Francisco",
    "sg:classifiers":[
        {
            "category":"Arts & Performance",
            "subcategory":"Art Gallery",
            "type":"Entertainment"
        }
    ],
    "sg:phone":"+1 415 203 4479",
    "sg:postcode":"94109",
    "sg:province":"CA",
    "wof:name":"Campusfork",
    "wof:placetype":"venue"
},
  "geometry": {"coordinates":[-122.423304,37.78851],"type":"Point"}
}