{
  "type": "Feature",
  "properties": {
    "iso:country":"US",
    "sg:address":"93 Sugar Pine Dr",
    "sg:city":"Mammoth Lakes",
    "sg:classifiers":[
        {
            "category":"Shopping",
            "subcategory":"Florist",
            "type":"Retail Goods"
        }
    ],
    "sg:phone":"+1 760 924 5010",
    "sg:postcode":"93546",
    "sg:province":"CA",
    "wof:name":"Celebrations",
    "wof:placetype":"venue"
},
  "geometry": {"coordinates":[-118.989268,37.640667],"type":"Point"}
}