{
  "type": "Feature",
  "properties": {
    "addr:full":"1805 Darwin Ave Ceres CA 95307",
    "addr:housenumber":"1805",
    "addr:postcode":"95307",
    "addr:street":"Darwin Ave",
    "iso:country":"US",
    "sg:address":"1805 Darwin Ave",
    "sg:city":"Ceres",
    "sg:classifiers":[
        {
            "category":"Building & Trades",
            "subcategory":"Construction",
            "type":"Services"
        }
    ],
    "sg:phone":"+1 209 538 8699",
    "sg:postcode":"95307",
    "sg:province":"CA",
    "sg:tags":[
        "woodworker"
    ],
    "wof:name":"Thomson Woodcarving",
    "wof:placetype":"venue"
},
  "geometry": {"coordinates":[-120.944675,37.603893],"type":"Point"}
}