{
  "type": "Feature",
  "properties": {
    "addr:full":"2400 19th Ave Kingsburg CA 93631",
    "addr:housenumber":"2400",
    "addr:postcode":"93631",
    "addr:street":"19Th Ave",
    "iso:country":"US",
    "sg:address":"2400 19th Ave",
    "sg:city":"Kingsburg",
    "sg:classifiers":[
        {
            "category":"Organizations",
            "subcategory":"Religious Organization",
            "type":"Services"
        }
    ],
    "sg:phone":"+1 559 897 5102",
    "sg:postcode":"93631",
    "sg:province":"CA",
    "sg:tags":[
        "church"
    ],
    "wof:name":"Evangelical Free Church",
    "wof:placetype":"venue"
},
  "geometry": {"coordinates":[-119.546617,36.524362],"type":"Point"}
}