{
  "type": "Feature",
  "properties": {
    "addr:full":"115 W California Blvd Pasadena CA 91105",
    "addr:housenumber":"115",
    "addr:postcode":"91105",
    "addr:street":"W California Blvd",
    "iso:country":"US",
    "sg:address":"115 W California Blvd",
    "sg:city":"Pasadena",
    "sg:classifiers":[
        {
            "category":"Banks & Credit Unions",
            "subcategory":"Investment Brokerage",
            "type":"Services"
        }
    ],
    "sg:phone":"+1 818 445 7510",
    "sg:postcode":"91105",
    "sg:province":"CA",
    "sg:tags":[
        "advisory"
    ],
    "wof:name":"Los Robles Investments",
    "wof:placetype":"venue"
},
  "geometry": {"coordinates":[-118.152766,34.13578],"type":"Point"}
}