{
  "type": "Feature",
  "properties": {
    "iso:country":"US",
    "sg:address":"21208 Nordhoff St",
    "sg:city":"Chatsworth",
    "sg:classifiers":[
        {
            "category":"Wholesale",
            "subcategory":"Electrical",
            "type":"Manufacturing & Wholesale Goods"
        }
    ],
    "sg:phone":"+1 818 700 2991",
    "sg:postcode":"91311",
    "sg:province":"CA",
    "sg:tags":[
        "specializing",
        "electronic",
        "parts",
        "component"
    ],
    "wof:name":"Acort Industries Inc",
    "wof:placetype":"venue"
},
  "geometry": {"coordinates":[-118.596002,34.23538],"type":"Point"}
}