{
  "type": "Feature",
  "properties": {
    "iso:country":"US",
    "sg:address":"15464 Valley Blvd",
    "sg:city":"City Of Industry",
    "sg:classifiers":[
        {
            "category":"Home & Garden",
            "subcategory":"Furniture",
            "type":"Retail Goods"
        }
    ],
    "sg:phone":"+1 626 336 6084",
    "sg:postcode":"91746",
    "sg:province":"CA",
    "sg:tags":[
        "bedding"
    ],
    "wof:name":"Comfortex Inc",
    "wof:placetype":"venue"
},
  "geometry": {"coordinates":[-117.96388399999999,34.0269],"type":"Point"}
}