{
  "type": "Feature",
  "properties": {
    "addr:full":"6811 Lena Ave Canoga Park CA 91307",
    "addr:postcode":"6811;91307",
    "addr:street":"Lena Ave",
    "iso:country":"US",
    "sg:address":"6811 Lena Ave",
    "sg:city":"Canoga Park",
    "sg:classifiers":[
        {
            "category":"Building & Trades",
            "subcategory":"Construction",
            "type":"Services"
        }
    ],
    "sg:phone":"+1 818 713 1692",
    "sg:postcode":"91307",
    "sg:province":"CA",
    "sg:tags":[
        "nonresidential"
    ],
    "wof:name":"Mieure Construction",
    "wof:placetype":"venue"
},
  "geometry": {"coordinates":[-118.627259,34.194518],"type":"Point"}
}