{
  "type": "Feature",
  "properties": {
    "addr:full":"17734 Chatsworth St Granada Hills CA 91344",
    "addr:housenumber":"17734",
    "addr:postcode":"91344",
    "addr:street":"Chatsworth St",
    "iso:country":"US",
    "sg:address":"17734 Chatsworth St",
    "sg:city":"Granada Hills",
    "sg:classifiers":[
        {
            "category":"Retail",
            "subcategory":"Auto Repair",
            "type":"Services"
        }
    ],
    "sg:phone":"+1 818 366 8027",
    "sg:postcode":"91344",
    "sg:province":"CA",
    "sg:tags":[
        "body",
        "truck"
    ],
    "wof:name":"LA Alignments",
    "wof:placetype":"venue"
},
  "geometry": {"coordinates":[-118.521041,34.264815],"type":"Point"}
}