{
  "type": "Feature",
  "properties": {
    "iso:country":"US",
    "sg:address":"11849 Firestone Blvd",
    "sg:city":"Norwalk",
    "sg:classifiers":[
        {
            "category":"Social Services",
            "type":"Services"
        }
    ],
    "sg:phone":"+1 562 406 2240",
    "sg:postcode":"90650",
    "sg:province":"CA",
    "sg:tags":[
        "organization",
        "welfare"
    ],
    "wof:name":"SPA7 Children's Council",
    "wof:placetype":"venue"
},
  "geometry": {"coordinates":[-118.08039100000001,33.912191],"type":"Point"}
}