{
  "type": "Feature",
  "properties": {
    "addr:full":"114 6th Ave City Of Industry CA 91746",
    "addr:housenumber":"114",
    "addr:postcode":"91746",
    "addr:street":"6Th Ave",
    "iso:country":"US",
    "sg:address":"114 6th Ave",
    "sg:city":"City Of Industry",
    "sg:classifiers":[
        {
            "category":"Building & Trades",
            "subcategory":"Plumbing",
            "type":"Services"
        }
    ],
    "sg:phone":"+1 626 330 7786",
    "sg:postcode":"91746",
    "sg:province":"CA",
    "sg:tags":[
        "conditioning",
        "air",
        "system",
        "contractor"
    ],
    "wof:name":"WSI",
    "wof:placetype":"venue"
},
  "geometry": {"coordinates":[-117.981149,34.034397],"type":"Point"}
}