{
  "type": "Feature",
  "properties": {
    "iso:country":"US",
    "sg:address":"12246 Coast Dr",
    "sg:city":"Whittier",
    "sg:classifiers":[
        {
            "category":"Retail",
            "subcategory":"Auto Repair",
            "type":"Services"
        }
    ],
    "sg:phone":"+1 562 699 4961",
    "sg:postcode":"90601",
    "sg:province":"CA",
    "sg:tags":[
        "van",
        "conversion",
        "truck",
        "accessory"
    ],
    "wof:name":"Bedliner Kingdom",
    "wof:placetype":"venue"
},
  "geometry": {"coordinates":[-118.039115,34.028673],"type":"Point"}
}