{
  "type": "Feature",
  "properties": {
    "iso:country":"US",
    "sg:address":"15455 San Fernando Mission Blvd",
    "sg:city":"Mission Hills",
    "sg:classifiers":[
        {
            "category":"Real Estate",
            "subcategory":"Real Estate Agent",
            "type":"Services"
        }
    ],
    "sg:phone":"+1 818 361 6620",
    "sg:postcode":"91345",
    "sg:province":"CA",
    "wof:name":"Tanner Realty",
    "wof:placetype":"venue"
},
  "geometry": {"coordinates":[-118.468243,34.271954],"type":"Point"}
}