{
  "type": "Feature",
  "properties": {
    "iso:country":"US",
    "sg:address":"1220 E Washington St",
    "sg:city":"Colton",
    "sg:classifiers":[
        {
            "category":"Professional",
            "subcategory":"Accounting & Tax Preparation",
            "type":"Services"
        }
    ],
    "sg:phone":"+1 909 777 3101",
    "sg:postcode":"92324",
    "sg:province":"CA",
    "sg:tags":[
        "return",
        "filing"
    ],
    "wof:name":"H & R Block Tax Svc",
    "wof:placetype":"venue"
},
  "geometry": {"coordinates":[-117.307076,34.047281],"type":"Point"}
}