{
  "type": "Feature",
  "properties": {
    "addr:full":"4024 Ibis St San Diego CA 92103",
    "addr:housenumber":"4024",
    "addr:postcode":"92103",
    "addr:street":"Ibis St",
    "iso:country":"US",
    "sg:address":"4024 Ibis St",
    "sg:city":"San Diego",
    "sg:classifiers":[
        {
            "category":"Social Services",
            "type":"Services"
        }
    ],
    "sg:phone":"+1 619 574 0110",
    "sg:postcode":"92103",
    "sg:province":"CA",
    "sg:tags":[
        "counselor",
        "marriage",
        "family"
    ],
    "wof:name":"Trina Day",
    "wof:placetype":"venue"
},
  "geometry": {"coordinates":[-117.173286,32.750375],"type":"Point"}
}