{
  "type": "Feature",
  "properties": {
    "iso:country":"US",
    "sg:address":"2009 W Martin Luther King Jr Blvd",
    "sg:city":"Los Angeles",
    "sg:classifiers":[
        {
            "category":"Education",
            "subcategory":"School",
            "type":"Public Place"
        }
    ],
    "sg:phone":"+1 323 290 2335",
    "sg:postcode":"90062",
    "sg:province":"CA",
    "wof:name":"CLAS Elementary School",
    "wof:placetype":"venue"
},
  "geometry": {"coordinates":[-118.315299,34.097713],"type":"Point"}
}