{
  "type": "Feature",
  "properties": {
    "addr:full":"711 1st St Gilroy CA 95020",
    "addr:housenumber":"711",
    "addr:postcode":"95020",
    "addr:street":"1St St",
    "iso:country":"US",
    "sg:address":"711 1st St",
    "sg:city":"Gilroy",
    "sg:classifiers":[
        {
            "category":"Restaurant",
            "type":"Food & Drink"
        }
    ],
    "sg:menulink":"http://www.allmenus.com/ca/gilroy/164315-wienerschnitzel/menu/",
    "sg:phone":"+1 408 846 6361",
    "sg:postcode":"95020",
    "sg:province":"CA",
    "sg:tags":[
        "sandwich",
        "dog",
        "burger",
        "hot",
        "wrap",
        "american"
    ],
    "wof:name":"Wienerschnitzel",
    "wof:placetype":"venue"
},
  "geometry": {"coordinates":[-121.58220799999999,37.013573],"type":"Point"}
}