{
  "type": "Feature",
  "properties": {
    "iso:country":"US",
    "sg:address":"2641 Santa Ana Ave",
    "sg:city":"Costa Mesa",
    "sg:classifiers":[
        {
            "category":"Shopping",
            "subcategory":"Bicycles & Sporting Goods",
            "type":"Retail Goods"
        }
    ],
    "sg:phone":"+1 949 515 5848",
    "sg:postcode":"92627",
    "sg:province":"CA",
    "wof:name":"Sewer Skateboards",
    "wof:placetype":"venue"
},
  "geometry": {"coordinates":[-117.889301,33.659299],"type":"Point"}
}