{
  "type": "Feature",
  "properties": {
    "addr:full":"277 Mountain Crest Rd Duarte CA 91010",
    "addr:housenumber":"277",
    "addr:postcode":"91010",
    "addr:street":"Mountain Crest Rd",
    "iso:country":"US",
    "sg:address":"277 Mountain Crest Rd",
    "sg:city":"Duarte",
    "sg:classifiers":[
        {
            "category":"Retail",
            "subcategory":"Repair Shop",
            "type":"Services"
        }
    ],
    "sg:phone":"+1 626 303 7020",
    "sg:postcode":"91010",
    "sg:province":"CA",
    "sg:tags":[
        "instrument"
    ],
    "wof:name":"Advanced Instrument Svc",
    "wof:placetype":"venue"
},
  "geometry": {"coordinates":[-117.937637,34.15034],"type":"Point"}
}