{
  "type": "Feature",
  "properties": {
    "addr:full":"16850 Willow Glen Rd Ste C Brownsville CA 95919",
    "addr:housenumber":"16850",
    "addr:postcode":"95919",
    "addr:street":"Willow Glen Rd Ste C",
    "iso:country":"US",
    "sg:address":"16850 Willow Glen Rd Ste C",
    "sg:city":"Brownsville",
    "sg:classifiers":[
        {
            "category":"Shopping",
            "subcategory":"Stationery & Office Supplies",
            "type":"Retail Goods"
        },
        {
            "category":"Shopping",
            "subcategory":"Gifts & Souvenirs",
            "type":"Retail Goods"
        },
        {
            "category":"Manufacturing",
            "subcategory":"Jewelry",
            "type":"Manufacturing & Wholesale Goods"
        }
    ],
    "sg:phone":"+1 530 675 0105",
    "sg:postcode":"95919",
    "sg:province":"CA",
    "sg:tags":[
        "shop",
        "novelty",
        "store"
    ],
    "wof:name":"Weebees",
    "wof:placetype":"venue"
},
  "geometry": {"coordinates":[-121.28295900000001,39.458605],"type":"Point"}
}