{
  "type": "Feature",
  "properties": {
    "addr:full":"11251 S Mariposa Ave Los Angeles CA 90044",
    "addr:housenumber":"11251",
    "addr:postcode":"90044",
    "addr:street":"S Mariposa Ave",
    "iso:country":"US",
    "sg:address":"11251 S Mariposa Ave",
    "sg:city":"Los Angeles",
    "sg:classifiers":[
        {
            "category":"Professional",
            "type":"Services"
        }
    ],
    "sg:phone":"+1 323 777 5526",
    "sg:postcode":"90044",
    "sg:province":"CA",
    "wof:name":"McFarland Latrice",
    "wof:placetype":"venue"
},
  "geometry": {"coordinates":[-118.299121,33.932027],"type":"Point"}
}