{
  "type": "Feature",
  "properties": {
    "iso:country":"US",
    "sg:address":"2950 Ralston Ave",
    "sg:city":"Hillsborough",
    "sg:classifiers":[
        {
            "category":"Manufacturing",
            "subcategory":"Printing",
            "type":"Manufacturing & Wholesale Goods"
        }
    ],
    "sg:phone":"+1 650 579 5512",
    "sg:postcode":"94010",
    "sg:province":"CA",
    "sg:tags":[
        "newspaper",
        "publishing"
    ],
    "wof:name":"Tonga USA Today",
    "wof:placetype":"venue"
},
  "geometry": {"coordinates":[-122.365022,37.561148],"type":"Point"}
}