{
  "type": "Feature",
  "properties": {
    "addr:full":"7927 Garden Grove Blvd Garden Grove CA 92841",
    "addr:housenumber":"7927",
    "addr:postcode":"92841",
    "addr:street":"Garden Grove Blvd",
    "iso:country":"US",
    "sg:address":"7927 Garden Grove Blvd",
    "sg:city":"Garden Grove",
    "sg:classifiers":[
        {
            "category":"Professional",
            "subcategory":"Accounting & Tax Preparation",
            "type":"Services"
        }
    ],
    "sg:phone":"+1 714 895 6516",
    "sg:postcode":"92841",
    "sg:province":"CA",
    "sg:tags":[
        "accountant"
    ],
    "wof:name":"Hsu Patrick T CPA",
    "wof:placetype":"venue"
},
  "geometry": {"coordinates":[-117.99099699999999,33.773998],"type":"Point"}
}