{
  "type": "Feature",
  "properties": {
    "addr:full":"2531 Village Ln Cambria CA 93428",
    "addr:housenumber":"2531",
    "addr:postcode":"93428",
    "addr:street":"Village Ln",
    "iso:country":"US",
    "sg:address":"2531 Village Ln",
    "sg:city":"Cambria",
    "sg:classifiers":[
        {
            "category":"Arts & Performance",
            "subcategory":"Art Gallery",
            "type":"Entertainment"
        }
    ],
    "sg:phone":"+1 805 927 9416",
    "sg:postcode":"93428",
    "sg:province":"CA",
    "wof:name":"Delapp Terry Gallery",
    "wof:placetype":"venue"
},
  "geometry": {"coordinates":[-121.078003,35.563702],"type":"Point"}
}