{
  "type": "Feature",
  "properties": {
    "addr:full":"1230 Warren Dr Santa Cruz CA 95060",
    "addr:housenumber":"1230",
    "addr:postcode":"95060",
    "addr:street":"Warren Dr",
    "iso:country":"US",
    "sg:address":"1230 Warren Dr",
    "sg:city":"Santa Cruz",
    "sg:classifiers":[
        {
            "category":"Travel",
            "subcategory":"Travel Agent",
            "type":"Entertainment"
        }
    ],
    "sg:phone":"+1 831 460 9898",
    "sg:postcode":"95060",
    "sg:province":"CA",
    "sg:tags":[
        "agency"
    ],
    "wof:name":"Travel Outpost",
    "wof:placetype":"venue"
},
  "geometry": {"coordinates":[-122.138398,37.038429],"type":"Point"}
}