{
  "type": "Feature",
  "properties": {
    "addr:full":"1561 Via Entrada del Lago San Marcos CA 92078",
    "addr:housenumber":"1561",
    "addr:postcode":"92078",
    "addr:street":"Via Entrada Del Lago",
    "iso:country":"US",
    "sg:address":"1561 Via Entrada del Lago",
    "sg:city":"San Marcos",
    "sg:classifiers":[
        {
            "category":"Real Estate",
            "subcategory":"Architect",
            "type":"Services"
        }
    ],
    "sg:phone":"+1 760 591 0733",
    "sg:postcode":"92078",
    "sg:province":"CA",
    "sg:tags":[
        "estimate",
        "construction"
    ],
    "wof:name":"C P & M",
    "wof:placetype":"venue"
},
  "geometry": {"coordinates":[-117.209323,33.122159],"type":"Point"}
}