{
  "type": "Feature",
  "properties": {
    "iso:country":"US",
    "sg:address":"1095 Barona Rd",
    "sg:city":"Lakeside",
    "sg:classifiers":[
        {
            "category":"Social Services",
            "subcategory":"Child Care",
            "type":"Services"
        }
    ],
    "sg:phone":"+1 619 443 6040",
    "sg:postcode":"92040",
    "sg:province":"CA",
    "wof:name":"Barona Childcare Ctr",
    "wof:placetype":"venue"
},
  "geometry": {"coordinates":[-116.87548200000001,32.932694],"type":"Point"}
}