{
  "type": "Feature",
  "properties": {
    "addr:full":"6426 Valley View St Joshua Tree CA 92252",
    "addr:housenumber":"6426",
    "addr:postcode":"92252",
    "addr:street":"Valley View St",
    "iso:country":"US",
    "sg:address":"6426 Valley View St",
    "sg:city":"Joshua Tree",
    "sg:classifiers":[
        {
            "category":"Real Estate",
            "subcategory":"Developer",
            "type":"Services"
        }
    ],
    "sg:phone":"+1 760 366 2212",
    "sg:postcode":"92252",
    "sg:province":"CA",
    "sg:tags":[
        "mobile",
        "home"
    ],
    "sg:website":"www.lazyhmhp.com",
    "wof:name":"Lazy H Mobile Park",
    "wof:placetype":"venue"
},
  "geometry": {"coordinates":[-116.310845,34.136411],"type":"Point"}
}