{
  "type": "Feature",
  "properties": {
    "iso:country":"US",
    "sg:address":"6840 Via del Oro",
    "sg:city":"San Jose",
    "sg:classifiers":[
        {
            "category":"Professional",
            "type":"Services"
        }
    ],
    "sg:phone":"+1 408 238 7177",
    "sg:postcode":"95119",
    "sg:province":"CA",
    "wof:name":"3 Mak LLC",
    "wof:placetype":"venue"
},
  "geometry": {"coordinates":[-121.77802699999999,37.232039],"type":"Point"}
}