{
  "type": "Feature",
  "properties": {
    "iso:country":"US",
    "sg:address":"4101 E Maple Tree Dr",
    "sg:city":"Anaheim",
    "sg:classifiers":[
        {
            "category":"Professional",
            "subcategory":"Business Services",
            "type":"Services"
        }
    ],
    "sg:phone":"+1 714 283 1061",
    "sg:postcode":"92807",
    "sg:province":"CA",
    "sg:tags":[
        "telemarketing"
    ],
    "wof:name":"Ray B Harmon Inc",
    "wof:placetype":"venue"
},
  "geometry": {"coordinates":[-117.827212,33.839785],"type":"Point"}
}