{
  "type": "Feature",
  "properties": {
    "iso:country":"US",
    "sg:address":"3816 Don Pedro Rd",
    "sg:city":"Ceres",
    "sg:classifiers":[
        {
            "category":"Building & Trades",
            "subcategory":"Construction",
            "type":"Services"
        }
    ],
    "sg:phone":"+1 209 538 1811",
    "sg:postcode":"95307",
    "sg:province":"CA",
    "sg:tags":[
        "concrete",
        "protection",
        "repair",
        "contractor"
    ],
    "wof:name":"Concrete Restoration",
    "wof:placetype":"venue"
},
  "geometry": {"coordinates":[-120.924352,37.583831],"type":"Point"}
}