{
  "type": "Feature",
  "properties": {
    "addr:full":"959 Garnet Avenue San Diego CA 92109",
    "addr:housenumber":"959",
    "addr:postcode":"92109",
    "addr:street":"Garnet Avenue",
    "iso:country":"US",
    "sg:address":"959 Garnet Avenue",
    "sg:city":"San Diego",
    "sg:classifiers":[
        {
            "category":"Shopping",
            "subcategory":"Clothing, Apparel, & Fashions",
            "type":"Retail Goods"
        }
    ],
    "sg:phone":"+1 858 483 1513",
    "sg:postcode":"92109",
    "sg:province":"CA",
    "sg:tags":[
        "accessory",
        "clothing",
        "women's"
    ],
    "wof:name":"Gloss Boutique",
    "wof:placetype":"venue"
},
  "geometry": {"coordinates":[-117.252291,32.797255],"type":"Point"}
}