{
  "type": "Feature",
  "properties": {
    "iso:country":"US",
    "sg:address":"2120 Grove St",
    "sg:city":"Sonoma",
    "sg:classifiers":[
        {
            "category":"Farming",
            "subcategory":"Farm",
            "type":"Manufacturing & Wholesale Goods"
        }
    ],
    "sg:phone":"+1 707 933 1437",
    "sg:postcode":"95476",
    "sg:province":"CA",
    "sg:tags":[
        "crop",
        "general"
    ],
    "wof:name":"Willow Creek Farms",
    "wof:placetype":"venue"
},
  "geometry": {"coordinates":[-122.518314,38.291971],"type":"Point"}
}