{
  "type": "Feature",
  "properties": {
    "addr:full":"6290 Warehouse Way Sacramento CA 95826",
    "addr:housenumber":"6290",
    "addr:postcode":"95826",
    "addr:street":"Warehouse Way",
    "iso:country":"US",
    "sg:address":"6290 Warehouse Way",
    "sg:city":"Sacramento",
    "sg:classifiers":[
        {
            "category":"Autos & Motor Vehicles",
            "subcategory":"Auto Supplies",
            "type":"Retail Goods"
        },
        {
            "category":"Retail",
            "subcategory":"Auto Repair",
            "type":"Services"
        }
    ],
    "sg:phone":"+1 916 381 0161",
    "sg:postcode":"95826",
    "sg:province":"CA",
    "sg:tags":[
        "body",
        "lettering",
        "automobile",
        "truck",
        "painting",
        "repairing"
    ],
    "wof:name":"Kearney's Painting Inc",
    "wof:placetype":"venue"
},
  "geometry": {"coordinates":[-121.382538,38.532411],"type":"Point"}
}