{
  "type": "Feature",
  "properties": {
    "addr:full":"4422 W Slauson Ave Los Angeles CA 90043",
    "addr:housenumber":"4422",
    "addr:postcode":"90043",
    "addr:street":"W Slauson Ave",
    "iso:country":"US",
    "sg:address":"4422 W Slauson Ave",
    "sg:city":"Los Angeles",
    "sg:classifiers":[
        {
            "category":"Retail",
            "subcategory":"Laundry & Dry Cleaning",
            "type":"Services"
        }
    ],
    "sg:phone":"+1 323 294 2255",
    "sg:postcode":"90043",
    "sg:province":"CA",
    "sg:website":"www.virginias-losangeles.com/",
    "wof:name":"Virginia's Cleaners",
    "wof:placetype":"venue"
},
  "geometry": {"coordinates":[-118.35248799999999,33.988889],"type":"Point"}
}