{
  "type": "Feature",
  "properties": {
    "addr:full":"1900 Powell St Oakland CA 94608",
    "addr:housenumber":"1900",
    "addr:postcode":"94608",
    "addr:street":"Powell St",
    "iso:country":"US",
    "sg:address":"1900 Powell St",
    "sg:city":"Oakland",
    "sg:classifiers":[
        {
            "category":"Shopping",
            "subcategory":"Computers & Home Electronics",
            "type":"Retail Goods"
        }
    ],
    "sg:phone":"+1 510 596 0780",
    "sg:postcode":"94608",
    "sg:province":"CA",
    "sg:tags":[
        "software"
    ],
    "sg:website":"www.idbs.com",
    "wof:name":"I D Business Solutions",
    "wof:placetype":"venue"
},
  "geometry": {"coordinates":[-122.297955,37.837907],"type":"Point"}
}