{
  "type": "Feature",
  "properties": {
    "iso:country":"US",
    "sg:address":"2800 Jefferson St",
    "sg:city":"Napa",
    "sg:classifiers":[
        {
            "category":"Real Estate",
            "subcategory":"Real Estate Agent",
            "type":"Services"
        }
    ],
    "sg:phone":"+1 707 254 1403",
    "sg:postcode":"94558",
    "sg:province":"CA",
    "wof:name":"Associated Brokers Realty",
    "wof:placetype":"venue"
},
  "geometry": {"coordinates":[-122.297809,38.315636],"type":"Point"}
}