{
  "type": "Feature",
  "properties": {
    "addr:full":"2420 Sand Creek Rd # 204 Brentwood CA 94513",
    "addr:housenumber":"2420",
    "addr:postcode":"ca 94513",
    "addr:street":"Sand Creek Rd # 204",
    "iso:country":"US",
    "sg:address":"2420 Sand Creek Rd # 204",
    "sg:city":"Brentwood",
    "sg:classifiers":[
        {
            "category":"Professional",
            "subcategory":"Management & Consulting",
            "type":"Services"
        }
    ],
    "sg:phone":"+1 510 610 2219",
    "sg:postcode":"94513",
    "sg:province":"CA",
    "sg:tags":[
        "consultant"
    ],
    "wof:name":"Spruce Property Management",
    "wof:placetype":"venue"
},
  "geometry": {"coordinates":[-121.73654399999999,37.943501],"type":"Point"}
}