{
  "type": "Feature",
  "properties": {
    "iso:country":"US",
    "sg:address":"4956 W Century Blvd, Ste 10-B",
    "sg:city":"Inglewood",
    "sg:classifiers":[
        {
            "category":"Restaurant",
            "type":"Food & Drink"
        },
        {
            "category":"Food & Beverages",
            "subcategory":"Ethnic Foods",
            "type":"Retail Goods"
        }
    ],
    "sg:phone":"+1 310 330 8338",
    "sg:postcode":"90304",
    "sg:province":"CA",
    "sg:tags":[
        "hawaiian",
        "barbeque"
    ],
    "sg:website":"www.bigislandbbq.com",
    "wof:name":"Big Island Hawaiian BBQ",
    "wof:placetype":"venue"
},
  "geometry": {"coordinates":[-118.36549,33.945122],"type":"Point"}
}