{
  "type": "Feature",
  "properties": {
    "iso:country":"US",
    "sg:address":"500 9th St Ste K1",
    "sg:city":"Modesto",
    "sg:classifiers":[
        {
            "category":"Personal",
            "type":"Services"
        },
        {
            "category":"Restaurant",
            "type":"Food & Drink"
        },
        {
            "category":"Retail",
            "subcategory":"Event Space",
            "type":"Services"
        }
    ],
    "sg:phone":"+1 209 526 7000",
    "sg:postcode":"95354",
    "sg:province":"CA",
    "sg:tags":[
        "mexican",
        "facility",
        "hall",
        "planning",
        "reception",
        "party",
        "meeting",
        "banquet"
    ],
    "wof:name":"El Sol Restaurant",
    "wof:placetype":"venue"
},
  "geometry": {"coordinates":[-120.99556,37.634972],"type":"Point"}
}