{
  "type": "Feature",
  "properties": {
    "iso:country":"US",
    "sg:address":"6008 Mission Gorge Rd",
    "sg:city":"San Diego",
    "sg:classifiers":[
        {
            "category":"Retail",
            "subcategory":"Auto Repair",
            "type":"Services"
        }
    ],
    "sg:phone":"+1 619 640 4300",
    "sg:postcode":"92120",
    "sg:province":"CA",
    "sg:tags":[
        "transmission"
    ],
    "wof:name":"Dr Trans Transmissions",
    "wof:placetype":"venue"
},
  "geometry": {"coordinates":[-117.09788399999999,32.784258],"type":"Point"}
}