{
  "type": "Feature",
  "properties": {
    "addr:full":"541 Blarney Cir Vacaville CA 95688",
    "addr:housenumber":"541",
    "addr:postcode":"95688",
    "addr:street":"Blarney Cir",
    "iso:country":"US",
    "sg:address":"541 Blarney Cir",
    "sg:city":"Vacaville",
    "sg:classifiers":[
        {
            "category":"Education",
            "subcategory":"School",
            "type":"Public Place"
        }
    ],
    "sg:phone":"+1 530 400 2596",
    "sg:postcode":"95688",
    "sg:province":"CA",
    "wof:name":"Crescent Elementary",
    "wof:placetype":"venue"
},
  "geometry": {"coordinates":[-121.972324,38.391763],"type":"Point"}
}