{
  "type": "Feature",
  "properties": {
    "addr:full":"1025 Yosemite Blvd Modesto CA 95354",
    "addr:housenumber":"1025",
    "addr:postcode":"ca 95354",
    "addr:street":"Yosemite Blvd",
    "iso:country":"US",
    "sg:address":"1025 Yosemite Blvd",
    "sg:city":"Modesto",
    "sg:classifiers":[
        {
            "category":"Retail",
            "subcategory":"Auto Repair",
            "type":"Services"
        }
    ],
    "sg:phone":"+1 209 525 3934",
    "sg:postcode":"95354",
    "sg:province":"CA",
    "sg:tags":[
        "repairing",
        "automobile"
    ],
    "wof:name":"Johnson Auto Repair",
    "wof:placetype":"venue"
},
  "geometry": {"coordinates":[-120.976767,37.638285],"type":"Point"}
}