{
  "type": "Feature",
  "properties": {
    "iso:country":"US",
    "sg:address":"6500 Wilshire Blvd",
    "sg:city":"Los Angeles",
    "sg:classifiers":[
        {
            "category":"Professional",
            "subcategory":"Advertising",
            "type":"Services"
        }
    ],
    "sg:phone":"+1 323 966 5911",
    "sg:postcode":"90048",
    "sg:province":"CA",
    "sg:tags":[
        "counselor"
    ],
    "wof:name":"B H Direct",
    "wof:placetype":"venue"
},
  "geometry": {"coordinates":[-118.370091,34.06385],"type":"Point"}
}