{
  "type": "Feature",
  "properties": {
    "iso:country":"US",
    "sg:address":"14111 Freeway Dr",
    "sg:city":"Santa Fe Springs",
    "sg:classifiers":[
        {
            "category":"Communications",
            "subcategory":"Newspaper",
            "type":"Services"
        }
    ],
    "sg:phone":"+1 714 940 9902",
    "sg:postcode":"90670",
    "sg:province":"CA",
    "sg:tags":[
        "print",
        "medium"
    ],
    "wof:name":"Harold Kirshner Financial & Insurance S Ervices",
    "wof:placetype":"venue"
},
  "geometry": {"coordinates":[-118.030998,33.885502],"type":"Point"}
}