{
  "type": "Feature",
  "properties": {
    "addr:full":"2244 Fairview Road Costa Mesa CA 92627",
    "addr:housenumber":"2244",
    "addr:postcode":"92627",
    "addr:street":"Fairview Road",
    "iso:country":"US",
    "sg:address":"2244 Fairview Road",
    "sg:city":"Costa Mesa",
    "sg:classifiers":[
        {
            "category":"Professional",
            "type":"Services"
        }
    ],
    "sg:phone":"+1 949 722 8910",
    "sg:postcode":"92627",
    "sg:province":"CA",
    "sg:tags":[
        "caterer"
    ],
    "wof:name":"Lett-Uce Cater To You",
    "wof:placetype":"venue"
},
  "geometry": {"coordinates":[-117.907551,33.656291],"type":"Point"}
}