{
  "type": "Feature",
  "properties": {
    "addr:full":"5499 Choctaw Ct Chino CA 91710",
    "addr:housenumber":"5499",
    "addr:postcode":"91710",
    "addr:street":"Choctaw Ct",
    "iso:country":"US",
    "sg:address":"5499 Choctaw Ct",
    "sg:city":"Chino",
    "sg:classifiers":[
        {
            "category":"Professional",
            "subcategory":"Business Services",
            "type":"Services"
        }
    ],
    "sg:phone":"+1 909 489 4564",
    "sg:postcode":"91710",
    "sg:province":"CA",
    "sg:tags":[
        "pool",
        "swimming"
    ],
    "wof:name":"Clearwater Pool Care",
    "wof:placetype":"venue"
},
  "geometry": {"coordinates":[-117.685621,34.035707],"type":"Point"}
}