{
  "type": "Feature",
  "properties": {
    "addr:full":"2211 E Palmdale Blvd Palmdale CA 93550",
    "addr:housenumber":"2211",
    "addr:postcode":"ca 93550",
    "addr:street":"E Palmdale Blvd",
    "iso:country":"US",
    "sg:address":"2211 E Palmdale Blvd",
    "sg:city":"Palmdale",
    "sg:classifiers":[
        {
            "category":"Restaurant",
            "type":"Food & Drink"
        }
    ],
    "sg:phone":"+1 661 273 3082",
    "sg:postcode":"93550",
    "sg:province":"CA",
    "wof:name":"Country Cafe",
    "wof:placetype":"venue"
},
  "geometry": {"coordinates":[-118.089428,34.580186],"type":"Point"}
}