{
  "type": "Feature",
  "properties": {
    "iso:country":"US",
    "sg:address":"1043 S Main St",
    "sg:city":"Manteca",
    "sg:classifiers":[
        {
            "category":"Sports & Exercise",
            "subcategory":"Gym",
            "type":"Entertainment"
        }
    ],
    "sg:phone":"+1 209 239 9006",
    "sg:postcode":"95337",
    "sg:province":"CA",
    "sg:tags":[
        "club",
        "health",
        "studio",
        "gymnasium"
    ],
    "wof:name":"Slender Lady Of Manteca",
    "wof:placetype":"venue"
},
  "geometry": {"coordinates":[-121.216154,37.788348],"type":"Point"}
}