{
  "type": "Feature",
  "properties": {
    "addr:full":"7711 Otis Ave Cudahy CA 90201",
    "addr:housenumber":"7711",
    "addr:postcode":"90201",
    "addr:street":"Otis Ave",
    "iso:country":"US",
    "sg:address":"7711 Otis Ave",
    "sg:city":"Cudahy",
    "sg:classifiers":[
        {
            "category":"Personal",
            "subcategory":"Beauty Salon",
            "type":"Services"
        }
    ],
    "sg:phone":"+1 323 773 2169",
    "sg:postcode":"90201",
    "sg:province":"CA",
    "wof:name":"Alfredo's Beauty Salon & Gifts",
    "wof:placetype":"venue"
},
  "geometry": {"coordinates":[-118.194717,33.965374],"type":"Point"}
}