{
  "type": "Feature",
  "properties": {
    "iso:country":"US",
    "sg:address":"7556 Cosgrove Way",
    "sg:city":"Sacramento",
    "sg:phone":"+1 916 395 3788",
    "sg:postcode":"95822",
    "sg:province":"CA",
    "wof:name":"Mitchells Care Home",
    "wof:placetype":"venue"
},
  "geometry": {"coordinates":[-121.493568,38.483463],"type":"Point"}
}