{
  "type": "Feature",
  "properties": {
    "addr:full":"3725 Mt Diablo Blvd Lafayette CA 94549",
    "addr:housenumber":"3725",
    "addr:postcode":"94549",
    "addr:street":"Mt Diablo Blvd",
    "iso:country":"US",
    "sg:address":"3725 Mt Diablo Blvd",
    "sg:city":"Lafayette",
    "sg:classifiers":[
        {
            "category":"Real Estate",
            "subcategory":"Real Estate Agent",
            "type":"Services"
        }
    ],
    "sg:phone":"+1 925 283 7866",
    "sg:postcode":"94549",
    "sg:province":"CA",
    "sg:website":"www.ucbhomes.com",
    "wof:name":"United California Brokers",
    "wof:placetype":"venue"
},
  "geometry": {"coordinates":[-122.132188,37.889095],"type":"Point"}
}