{
  "type": "Feature",
  "properties": {
    "addr:full":"2002 Harrison Ave Eureka CA 95501",
    "addr:housenumber":"2002",
    "addr:postcode":"95501",
    "addr:street":"Harrison Ave",
    "iso:country":"US",
    "sg:address":"2002 Harrison Ave",
    "sg:city":"Eureka",
    "sg:classifiers":[
        {
            "category":"Professional",
            "subcategory":"Research",
            "type":"Services"
        }
    ],
    "sg:phone":"+1 707 445 1114",
    "sg:postcode":"95501",
    "sg:province":"CA",
    "sg:tags":[
        "laboratory"
    ],
    "wof:name":"Redwood Toxicology Laboratory",
    "wof:placetype":"venue"
},
  "geometry": {"coordinates":[-124.13968,40.789441],"type":"Point"}
}