{
  "type": "Feature",
  "properties": {
    "iso:country":"US",
    "sg:address":"14517 Gilmore St",
    "sg:city":"Van Nuys",
    "sg:classifiers":[
        {
            "category":"Shopping",
            "subcategory":"Books",
            "type":"Retail Goods"
        }
    ],
    "sg:phone":"+1 818 781 9741",
    "sg:postcode":"91411",
    "sg:province":"CA",
    "sg:tags":[
        "dealer"
    ],
    "wof:name":"Spiritual Light",
    "wof:placetype":"venue"
},
  "geometry": {"coordinates":[-118.450604,34.187724],"type":"Point"}
}