{
  "type": "Feature",
  "properties": {
    "addr:full":"1750 Howe Ave Sacramento CA 95825",
    "addr:housenumber":"1750",
    "addr:postcode":"95825",
    "addr:street":"Howe Ave",
    "iso:country":"US",
    "sg:address":"1750 Howe Ave",
    "sg:city":"Sacramento",
    "sg:classifiers":[
        {
            "category":"Building & Trades",
            "subcategory":"Equipment Rental",
            "type":"Services"
        }
    ],
    "sg:phone":"+1 916 923 6003",
    "sg:postcode":"95825",
    "sg:province":"CA",
    "wof:name":"GE",
    "wof:placetype":"venue"
},
  "geometry": {"coordinates":[-121.41521899999999,38.597182],"type":"Point"}
}