{
  "type": "Feature",
  "properties": {
    "addr:full":"8323 Willis Ave Panorama City CA 91402",
    "addr:housenumber":"8323",
    "addr:postcode":"91402",
    "addr:street":"Willis Ave",
    "iso:country":"US",
    "sg:address":"8323 Willis Ave",
    "sg:city":"Panorama City",
    "sg:classifiers":[
        {
            "category":"Building & Trades",
            "subcategory":"Cleaning & Sanitation",
            "type":"Services"
        }
    ],
    "sg:phone":"+1 818 891 1258",
    "sg:postcode":"91402",
    "sg:province":"CA",
    "sg:tags":[
        "house"
    ],
    "wof:name":"Linda's Cleaning Svc",
    "wof:placetype":"venue"
},
  "geometry": {"coordinates":[-118.45536300000001,34.224369],"type":"Point"}
}