{
  "type": "Feature",
  "properties": {
    "iso:country":"US",
    "sg:address":"126 E 18th St",
    "sg:city":"Merced",
    "sg:classifiers":[
        {
            "category":"Building & Trades",
            "subcategory":"Landscaping Services",
            "type":"Services"
        },
        {
            "category":"Health Services",
            "subcategory":"Nursing And Care Facility",
            "type":"Services"
        },
        {
            "category":"Social Services",
            "subcategory":"Adult Care",
            "type":"Services"
        },
        {
            "category":"Social Services",
            "subcategory":"Retirement Home",
            "type":"Services"
        }
    ],
    "sg:phone":"+1 209 726 0580",
    "sg:postcode":"95340",
    "sg:province":"CA",
    "sg:tags":[
        "nurses-home",
        "convalescent",
        "aged",
        "homes-institutional",
        "residential"
    ],
    "sg:website":"http://www.scslmerced.org",
    "wof:name":"Sierra Creek Senior Living",
    "wof:placetype":"venue"
},
  "geometry": {"coordinates":[-120.47312599999999,37.298896],"type":"Point"}
}