{
  "type": "Feature",
  "properties": {
    "addr:full":"8037 Allport Ave Santa Fe Springs CA 90670",
    "addr:postcode":"8037;90670",
    "addr:street":"Allport Ave",
    "iso:country":"US",
    "sg:address":"8037 Allport Ave",
    "sg:city":"Santa Fe Springs",
    "sg:classifiers":[
        {
            "category":"Retail",
            "subcategory":"Auto Repair",
            "type":"Services"
        }
    ],
    "sg:phone":"+1 562 698 9191",
    "sg:postcode":"90670",
    "sg:province":"CA",
    "sg:tags":[
        "automobile",
        "smog",
        "check"
    ],
    "wof:name":"Smarty Smog",
    "wof:placetype":"venue"
},
  "geometry": {"coordinates":[-118.064003,33.969898],"type":"Point"}
}