{
  "type": "Feature",
  "properties": {
    "iso:country":"US",
    "sg:address":"12711 Newport Ave",
    "sg:city":"Tustin",
    "sg:classifiers":[
        {
            "category":"Real Estate",
            "subcategory":"Real Estate Agent",
            "type":"Services"
        }
    ],
    "sg:phone":"+1 714 508 3609",
    "sg:postcode":"92780",
    "sg:province":"CA",
    "sg:tags":[
        "consultant"
    ],
    "wof:name":"Del Valle Realtors",
    "wof:placetype":"venue"
},
  "geometry": {"coordinates":[-117.808001,33.752473],"type":"Point"}
}