{
  "type": "Feature",
  "properties": {
    "iso:country":"US",
    "sg:address":"951 W Mabel Ave",
    "sg:city":"Monterey Park",
    "sg:classifiers":[
        {
            "category":"Professional",
            "type":"Services"
        }
    ],
    "sg:phone":"+1 626 284 6852",
    "sg:postcode":"91754",
    "sg:province":"CA",
    "wof:name":"Art Gallery",
    "wof:placetype":"venue"
},
  "geometry": {"coordinates":[-118.135175,34.061593],"type":"Point"}
}