{
  "type": "Feature",
  "properties": {
    "iso:country":"US",
    "sg:address":"8049 Gold Pheasant Ct",
    "sg:city":"Elverta",
    "sg:classifiers":[
        {
            "category":"Retail",
            "subcategory":"Auto Repair",
            "type":"Services"
        }
    ],
    "sg:phone":"+1 916 992 1015",
    "sg:postcode":"95626",
    "sg:province":"CA",
    "sg:tags":[
        "wrecker"
    ],
    "wof:name":"C H Towing",
    "wof:placetype":"venue"
},
  "geometry": {"coordinates":[-121.41613700000001,38.716087],"type":"Point"}
}