{
  "type": "Feature",
  "properties": {
    "addr:full":"1430 W Pacific Coast Hwy Wilmington CA 90744",
    "addr:housenumber":"1430",
    "addr:postcode":"90744",
    "addr:street":"W Pacific Coast Hwy",
    "iso:country":"US",
    "sg:address":"1430 W Pacific Coast Hwy",
    "sg:city":"Wilmington",
    "sg:classifiers":[
        {
            "category":"Wholesale",
            "subcategory":"Petroleum",
            "type":"Manufacturing & Wholesale Goods"
        }
    ],
    "sg:phone":"+1 310 952 1002",
    "sg:postcode":"90744",
    "sg:province":"CA",
    "sg:tags":[
        "bulk",
        "station"
    ],
    "wof:name":"Lux Oil 1002",
    "wof:placetype":"venue"
},
  "geometry": {"coordinates":[-118.284181,33.790731],"type":"Point"}
}