{
  "type": "Feature",
  "properties": {
    "addr:full":"29798 Haun Rd Ste 201 Sun City CA 92586",
    "addr:housenumber":"29798",
    "addr:postcode":"92586",
    "addr:street":"Haun Rd Ste 201",
    "iso:country":"US",
    "sg:address":"29798 Haun Rd Ste 201",
    "sg:city":"Sun City",
    "sg:classifiers":[
        {
            "category":"Community Center",
            "type":"Public Place"
        }
    ],
    "sg:phone":"+1 800 610 0271",
    "sg:postcode":"92586",
    "sg:province":"CA",
    "sg:tags":[
        "medical"
    ],
    "sg:website":"www.localstdtesting.com",
    "wof:name":"Sun City Local HIV / STD Testing",
    "wof:placetype":"venue"
},
  "geometry": {"coordinates":[-117.174857,33.68757],"type":"Point"}
}