{
  "type": "Feature",
  "properties": {
    "addr:full":"2630 J St Sacramento CA 95816",
    "addr:housenumber":"2630",
    "addr:postcode":"95816",
    "addr:street":"J St",
    "iso:country":"US",
    "sg:address":"2630 J St",
    "sg:city":"Sacramento",
    "sg:classifiers":[
        {
            "category":"Professional",
            "subcategory":"Lawyer & Legal Services",
            "type":"Services"
        }
    ],
    "sg:phone":"+1 916 442 6739",
    "sg:postcode":"95816",
    "sg:province":"CA",
    "sg:website":"www.ernestalongadr.com",
    "wof:name":"Ernest A Long ADR",
    "wof:placetype":"venue"
},
  "geometry": {"coordinates":[-121.471491,38.574311],"type":"Point"}
}