{
  "type": "Feature",
  "properties": {
    "iso:country":"US",
    "sg:address":"1155 S 12th Ave",
    "sg:city":"Hanford",
    "sg:classifiers":[
        {
            "category":"Transit Center",
            "subcategory":"Freight",
            "type":"Transportation"
        },
        {
            "category":"Freight",
            "type":"Transportation"
        }
    ],
    "sg:phone":"+1 559 583 6490",
    "sg:postcode":"93230",
    "sg:province":"CA",
    "sg:tags":[
        "local",
        "trucking-motor",
        "trucking"
    ],
    "wof:name":"Util Transport",
    "wof:placetype":"venue"
},
  "geometry": {"coordinates":[-119.672944,36.312133],"type":"Point"}
}