{
  "type": "Feature",
  "properties": {
    "iso:country":"US",
    "sg:address":"1120 Price St",
    "sg:city":"Pomona",
    "sg:classifiers":[
        {
            "category":"Banks & Credit Unions",
            "subcategory":"Financial Services",
            "type":"Services"
        }
    ],
    "sg:phone":"+1 909 620 3877",
    "sg:postcode":"91767",
    "sg:province":"CA",
    "sg:tags":[
        "international",
        "trade"
    ],
    "wof:name":"Potef Compupter & Trading",
    "wof:placetype":"venue"
},
  "geometry": {"coordinates":[-117.727216,34.060204],"type":"Point"}
}