{
  "type": "Feature",
  "properties": {
    "iso:country":"US",
    "sg:address":"1163 N Mount Vernon Ave",
    "sg:city":"Colton",
    "sg:classifiers":[
        {
            "category":"Insurance",
            "subcategory":"Insurance Agent",
            "type":"Services"
        }
    ],
    "sg:phone":"+1 909 783 2900",
    "sg:postcode":"92324",
    "sg:province":"CA",
    "wof:name":"Adriana's Insurance",
    "wof:placetype":"venue"
},
  "geometry": {"coordinates":[-117.31394899999999,34.079034],"type":"Point"}
}