{
  "type": "Feature",
  "properties": {
    "addr:full":"1901 Boonville Rd Ukiah CA 95482",
    "addr:housenumber":"1901",
    "addr:postcode":"ca 95482",
    "addr:street":"Boonville Rd",
    "iso:country":"US",
    "sg:address":"1901 Boonville Rd",
    "sg:city":"Ukiah",
    "sg:classifiers":[
        {
            "category":"Travel",
            "subcategory":"Hotels & Motels",
            "type":"Entertainment"
        }
    ],
    "sg:phone":"+1 707 468 9039",
    "sg:postcode":"95482",
    "sg:province":"CA",
    "sg:tags":[
        "breakfast",
        "operation",
        "bed",
        "accommodation"
    ],
    "wof:name":"Robinson Creek Inn & Flower FA",
    "wof:placetype":"venue"
},
  "geometry": {"coordinates":[-123.21978300000001,39.092364],"type":"Point"}
}