{
  "type": "Feature",
  "properties": {
    "addr:full":"1364 W 139th St Gardena CA 90247",
    "addr:housenumber":"1364",
    "addr:postcode":"90247",
    "addr:street":"W 139Th St",
    "iso:country":"US",
    "sg:address":"1364 W 139th St",
    "sg:city":"Gardena",
    "sg:classifiers":[
        {
            "category":"Real Estate",
            "subcategory":"Real Estate Operator",
            "type":"Services"
        }
    ],
    "sg:phone":"+1 310 538 5265",
    "sg:postcode":"90247",
    "sg:province":"CA",
    "sg:tags":[
        "condominium"
    ],
    "wof:name":"White Oak Village",
    "wof:placetype":"venue"
},
  "geometry": {"coordinates":[-118.299541,33.905465],"type":"Point"}
}