{
  "type": "Feature",
  "properties": {
    "iso:country":"US",
    "sg:address":"427 9th Avenue",
    "sg:city":"San Diego",
    "sg:classifiers":[
        {
            "category":"Banks & Credit Unions",
            "subcategory":"Financial Services",
            "type":"Services"
        }
    ],
    "sg:phone":"+1 619 398 3500",
    "sg:postcode":"92101",
    "sg:province":"CA",
    "sg:tags":[
        "broker",
        "mortgage"
    ],
    "sg:website":"www.westendmortgage.com",
    "wof:name":"Westend Mortgage",
    "wof:placetype":"venue"
},
  "geometry": {"coordinates":[-117.156469,32.709665],"type":"Point"}
}