{
  "type": "Feature",
  "properties": {
    "addr:full":"1620 5th Ave San Diego CA 92101",
    "addr:housenumber":"1620",
    "addr:postcode":"92101",
    "addr:street":"5Th Ave",
    "iso:country":"US",
    "sg:address":"1620 5th Ave",
    "sg:city":"San Diego",
    "sg:classifiers":[
        {
            "category":"Professional",
            "subcategory":"Management & Consulting",
            "type":"Services"
        }
    ],
    "sg:phone":"+1 619 239 1523",
    "sg:postcode":"92101",
    "sg:province":"CA",
    "sg:tags":[
        "counselor",
        "public",
        "relations"
    ],
    "sg:website":"www.marstonandmarston.com",
    "wof:name":"Marston & Marston",
    "wof:placetype":"venue"
},
  "geometry": {"coordinates":[-117.160217,32.72235],"type":"Point"}
}