{
  "type": "Feature",
  "properties": {
    "iso:country":"US",
    "sg:address":"8476 Yarrow Ln",
    "sg:city":"Riverside",
    "sg:classifiers":[
        {
            "category":"Professional",
            "subcategory":"Business Services",
            "type":"Services"
        }
    ],
    "sg:phone":"+1 951 750 9888",
    "sg:postcode":"92508",
    "sg:province":"CA",
    "sg:tags":[
        "notary",
        "public"
    ],
    "wof:name":"Local And Global Notary",
    "wof:placetype":"venue"
},
  "geometry": {"coordinates":[-117.297314,33.896644],"type":"Point"}
}