{
  "type": "Feature",
  "properties": {
    "addr:full":"2 Embarcadero Ctr Street Level San Francisco CA 94111",
    "addr:housenumber":"2",
    "addr:postcode":"94111",
    "addr:street":"Embarcadero Ctr Street Level",
    "iso:country":"US",
    "sg:address":"2 Embarcadero Ctr Street Level",
    "sg:city":"San Francisco",
    "sg:classifiers":[
        {
            "category":"Food & Beverages",
            "subcategory":"Liquor & Beverages",
            "type":"Retail Goods"
        },
        {
            "category":"Bars & Pubs",
            "subcategory":"Wine Bar",
            "type":"Food & Drink"
        }
    ],
    "sg:phone":"+1 415 391 0758",
    "sg:postcode":"94111",
    "sg:province":"CA",
    "sg:tags":[
        "beer",
        "spirit"
    ],
    "sg:website":"www.winebarsf.com",
    "wof:name":"Wine Bar & Shop",
    "wof:placetype":"venue"
},
  "geometry": {"coordinates":[-122.399111,37.795169],"type":"Point"}
}