{
  "type": "Feature",
  "properties": {
    "addr:full":"Walnut Blvd Brentwood CA 94513",
    "addr:postcode":"ca 94513",
    "addr:street":"Walnut Blvd",
    "iso:country":"US",
    "sg:address":"Walnut Blvd",
    "sg:city":"Brentwood",
    "sg:classifiers":[
        {
            "category":"Building & Trades",
            "subcategory":"Construction",
            "type":"Services"
        }
    ],
    "sg:phone":"+1 925 634 3067",
    "sg:postcode":"94513",
    "sg:province":"CA",
    "sg:tags":[
        "interior",
        "design"
    ],
    "wof:name":"Moffatt's Interiors Ifda",
    "wof:placetype":"venue"
},
  "geometry": {"coordinates":[-121.704002,37.930099],"type":"Point"}
}