{
  "type": "Feature",
  "properties": {
    "addr:full":"1660 Stanley Dr Ripon CA 95366",
    "addr:housenumber":"1660",
    "addr:postcode":"ca 95366",
    "addr:street":"Stanley Dr",
    "iso:country":"US",
    "sg:address":"1660 Stanley Dr",
    "sg:city":"Ripon",
    "sg:classifiers":[
        {
            "category":"Education",
            "subcategory":"School",
            "type":"Public Place"
        }
    ],
    "sg:phone":"+1 209 599 7113",
    "sg:postcode":"95366",
    "sg:province":"CA",
    "sg:website":"www.edserv.sjcoe.k12.ca.us",
    "wof:name":"Weston Elementary School",
    "wof:placetype":"venue"
},
  "geometry": {"coordinates":[-121.143416,37.733624],"type":"Point"}
}