{
  "type": "Feature",
  "properties": {
    "addr:full":"1233 W Ave P Palmdale CA 93551",
    "addr:housenumber":"1233",
    "addr:postcode":"93551",
    "addr:street":"W Ave P Palmdale",
    "iso:country":"US",
    "sg:address":"1233 W Ave P",
    "sg:city":"Palmdale",
    "sg:classifiers":[
        {
            "category":"Shopping",
            "type":"Retail Goods"
        },
        {
            "category":"Manufacturing",
            "subcategory":"Chemicals & Compounds",
            "type":"Manufacturing & Wholesale Goods"
        }
    ],
    "sg:phone":"+1 661 224 1334",
    "sg:postcode":"93551",
    "sg:province":"CA",
    "sg:tags":[
        "preparation",
        "toilet",
        "mfg",
        "perfume"
    ],
    "wof:name":"Luxury Perfumes",
    "wof:placetype":"venue"
},
  "geometry": {"coordinates":[-118.15138,34.601777],"type":"Point"}
}