{
  "type": "Feature",
  "properties": {
    "addr:full":"4401 Brookdale Ave Oakland CA 94619",
    "addr:housenumber":"4401",
    "addr:postcode":"94619",
    "addr:street":"Brookdale Ave",
    "iso:country":"US",
    "sg:address":"4401 Brookdale Ave",
    "sg:city":"Oakland",
    "sg:classifiers":[
        {
            "category":"Communications",
            "subcategory":"Film & Video Production",
            "type":"Services"
        }
    ],
    "sg:phone":"+1 510 536 6362",
    "sg:postcode":"94619",
    "sg:province":"CA",
    "sg:tags":[
        "tv",
        "services-commercial",
        "companies-film",
        "radio"
    ],
    "wof:name":"Bluelight Productions",
    "wof:placetype":"venue"
},
  "geometry": {"coordinates":[-122.203209,37.781719],"type":"Point"}
}