{
  "type": "Feature",
  "properties": {
    "addr:full":"112 Angus Ave W San Bruno CA 94066",
    "addr:housenumber":"112",
    "addr:postcode":"94066",
    "addr:street":"Angus Ave W",
    "iso:country":"US",
    "sg:address":"112 Angus Ave W",
    "sg:city":"San Bruno",
    "sg:classifiers":[
        {
            "category":"Taxi",
            "type":"Transportation"
        }
    ],
    "sg:phone":"+1 650 588 8099",
    "sg:postcode":"94066",
    "sg:province":"CA",
    "wof:name":"Yellow Cab",
    "wof:placetype":"venue"
},
  "geometry": {"coordinates":[-122.409865,37.626737],"type":"Point"}
}