{
  "type": "Feature",
  "properties": {
    "iso:country":"US",
    "sg:address":"1060 Minnesota Ave",
    "sg:city":"San Jose",
    "sg:classifiers":[
        {
            "category":"Government",
            "subcategory":"Office",
            "type":"Public Place"
        }
    ],
    "sg:phone":"+1 408 280 7264",
    "sg:postcode":"95125",
    "sg:province":"CA",
    "sg:tags":[
        "county"
    ],
    "wof:name":"NAMI Of Santa Clara County",
    "wof:placetype":"venue"
},
  "geometry": {"coordinates":[-121.89677,37.303862],"type":"Point"}
}