{
  "type": "Feature",
  "properties": {
    "iso:country":"US",
    "sg:address":"7011 Stewart and Gray Rd",
    "sg:city":"Downey",
    "sg:classifiers":[
        {
            "category":"Food & Beverages",
            "subcategory":"Dairy",
            "type":"Retail Goods"
        }
    ],
    "sg:phone":"+1 562 622 3602",
    "sg:postcode":"90241",
    "sg:province":"CA",
    "sg:tags":[
        "product"
    ],
    "wof:name":"Roxy's Dairy",
    "wof:placetype":"venue"
},
  "geometry": {"coordinates":[-118.159688,33.943226],"type":"Point"}
}