{
  "type": "Feature",
  "properties": {
    "addr:full":"8261 Sepulveda Blvd Panorama City CA 91402",
    "addr:housenumber":"8261",
    "addr:postcode":"91402",
    "addr:street":"Sepulveda Blvd",
    "iso:country":"US",
    "sg:address":"8261 Sepulveda Blvd",
    "sg:city":"Panorama City",
    "sg:classifiers":[
        {
            "category":"Restaurant",
            "type":"Food & Drink"
        }
    ],
    "sg:menulink":"http://www.allmenus.com/ca/san-fernando-valley/123908-quiznos-sub/menu/",
    "sg:phone":"+1 818 830 1355",
    "sg:postcode":"91402",
    "sg:province":"CA",
    "sg:tags":[
        "wrap",
        "american",
        "sandwich"
    ],
    "wof:name":"Quiznos Sub",
    "wof:placetype":"venue"
},
  "geometry": {"coordinates":[-118.467709,34.221129],"type":"Point"}
}