{
  "type": "Feature",
  "properties": {
    "iso:country":"US",
    "sg:address":"6333 South Alameda St",
    "sg:city":"Los Angeles",
    "sg:classifiers":[
        {
            "category":"Autos & Motor Vehicles",
            "subcategory":"Automobile Sales",
            "type":"Retail Goods"
        }
    ],
    "sg:phone":"+1 800 800 6425",
    "sg:postcode":"90001",
    "sg:province":"CA",
    "sg:tags":[
        "car"
    ],
    "sg:website":"www.alexanderbmw.com/",
    "wof:name":"Alexander BMW",
    "wof:placetype":"venue"
},
  "geometry": {"coordinates":[-118.236378,33.982203],"type":"Point"}
}