{
  "type": "Feature",
  "properties": {
    "addr:full":"2379 Maggio Cir Lodi CA 95240",
    "addr:housenumber":"2379",
    "addr:postcode":"95240",
    "addr:street":"Maggio Cir",
    "iso:country":"US",
    "sg:address":"2379 Maggio Cir",
    "sg:city":"Lodi",
    "sg:classifiers":[
        {
            "category":"Retail",
            "subcategory":"Car Wash",
            "type":"Services"
        }
    ],
    "sg:phone":"+1 209 369 2833",
    "sg:postcode":"95240",
    "sg:province":"CA",
    "sg:tags":[
        "automobile",
        "detail",
        "clean"
    ],
    "wof:name":"Every Detail",
    "wof:placetype":"venue"
},
  "geometry": {"coordinates":[-121.27103,38.104486],"type":"Point"}
}