{
  "type": "Feature",
  "properties": {
    "iso:country":"US",
    "sg:address":"17912 Mitchell S",
    "sg:city":"Irvine",
    "sg:classifiers":[
        {
            "category":"Professional",
            "type":"Services"
        }
    ],
    "sg:phone":"+1 949 724 9913",
    "sg:postcode":"92614",
    "sg:province":"CA",
    "sg:tags":[
        "establishment"
    ],
    "wof:name":"Frimmer & Assoc",
    "wof:placetype":"venue"
},
  "geometry": {"coordinates":[-117.863823,33.692535],"type":"Point"}
}