{
  "type": "Feature",
  "properties": {
    "addr:full":"10741 Sherman Way Sun Valley CA 91352",
    "addr:housenumber":"10741",
    "addr:postcode":"91352",
    "addr:street":"Sherman Way",
    "iso:country":"US",
    "sg:address":"10741 Sherman Way",
    "sg:city":"Sun Valley",
    "sg:classifiers":[
        {
            "category":"Wholesale",
            "subcategory":"Drugs",
            "type":"Manufacturing & Wholesale Goods"
        }
    ],
    "sg:phone":"+1 818 255 5533",
    "sg:postcode":"91352",
    "sg:province":"CA",
    "sg:tags":[
        "cosmetic"
    ],
    "wof:name":"Delicate Cosmetics Inc",
    "wof:placetype":"venue"
},
  "geometry": {"coordinates":[-118.364953,34.20127],"type":"Point"}
}