{
  "type": "Feature",
  "properties": {
    "addr:full":"953 Feller Ave San Jose CA 95127",
    "addr:housenumber":"953",
    "addr:postcode":"95127",
    "addr:street":"Feller Ave",
    "iso:country":"US",
    "sg:address":"953 Feller Ave",
    "sg:city":"San Jose",
    "sg:classifiers":[
        {
            "category":"Professional",
            "type":"Services"
        }
    ],
    "sg:phone":"+1 408 251 7428",
    "sg:postcode":"95127",
    "sg:province":"CA",
    "wof:name":"Souza W & D",
    "wof:placetype":"venue"
},
  "geometry": {"coordinates":[-121.80796100000001,37.367857],"type":"Point"}
}