{
  "type": "Feature",
  "properties": {
    "iso:country":"US",
    "sg:address":"234 Main St",
    "sg:city":"Pleasanton",
    "sg:classifiers":[
        {
            "category":"Wholesale",
            "subcategory":"Hardware",
            "type":"Manufacturing & Wholesale Goods"
        },
        {
            "category":"Wholesale",
            "subcategory":"Durable Goods & Equipment",
            "type":"Manufacturing & Wholesale Goods"
        }
    ],
    "sg:phone":"+1 925 426 1358",
    "sg:postcode":"94566",
    "sg:province":"CA",
    "sg:tags":[
        "lock",
        "locksmith"
    ],
    "wof:name":"B & S Key Word Systems",
    "wof:placetype":"venue"
},
  "geometry": {"coordinates":[-121.876784,37.658698],"type":"Point"}
}