{
  "type": "Feature",
  "properties": {
    "addr:full":"9910 Long Beach Boulevard Lynwood CA 90262",
    "addr:housenumber":"9910",
    "addr:postcode":"90262",
    "addr:street":"Long Beach Boulevard",
    "iso:country":"US",
    "sg:address":"9910 Long Beach Boulevard",
    "sg:city":"Lynwood",
    "sg:classifiers":[
        {
            "category":"Restaurant",
            "type":"Food & Drink"
        }
    ],
    "sg:phone":"+1 323 564 3916",
    "sg:postcode":"90262",
    "sg:province":"CA",
    "sg:tags":[
        "chinese"
    ],
    "wof:name":"China Wok Express",
    "wof:placetype":"venue"
},
  "geometry": {"coordinates":[-118.216138,33.945268],"type":"Point"}
}