{
  "type": "Feature",
  "properties": {
    "addr:full":"2053 Inman Way San Jose CA 95122",
    "addr:housenumber":"2053",
    "addr:postcode":"95122",
    "addr:street":"Inman Way",
    "iso:country":"US",
    "sg:address":"2053 Inman Way",
    "sg:city":"San Jose",
    "sg:classifiers":[
        {
            "category":"Retail",
            "subcategory":"Repair Shop",
            "type":"Services"
        }
    ],
    "sg:phone":"+1 408 923 3456",
    "sg:postcode":"95122",
    "sg:province":"CA",
    "sg:tags":[
        "equipment",
        "conditioning",
        "air"
    ],
    "wof:name":"Capella Heating & Air Cond",
    "wof:placetype":"venue"
},
  "geometry": {"coordinates":[-121.827065,37.328208],"type":"Point"}
}