{
  "type": "Feature",
  "properties": {
    "iso:country":"US",
    "sg:address":"6117 Banner Dr",
    "sg:city":"San Jose",
    "sg:classifiers":[
        {
            "category":"Shopping",
            "subcategory":"Catalog Store",
            "type":"Retail Goods"
        }
    ],
    "sg:phone":"+1 408 362 1418",
    "sg:postcode":"95123",
    "sg:province":"CA",
    "sg:tags":[
        "mail",
        "order"
    ],
    "wof:name":"Collectvs Books",
    "wof:placetype":"venue"
},
  "geometry": {"coordinates":[-121.822167,37.235831],"type":"Point"}
}