{
  "type": "Feature",
  "properties": {
    "addr:full":"16408 Felice Dr San Diego CA 92128",
    "addr:housenumber":"16408",
    "addr:postcode":"92128",
    "addr:street":"Felice Dr",
    "iso:country":"US",
    "sg:address":"16408 Felice Dr",
    "sg:city":"San Diego",
    "sg:classifiers":[
        {
            "category":"Government",
            "subcategory":"Office",
            "type":"Public Place"
        }
    ],
    "sg:phone":"+1 858 487 9387",
    "sg:postcode":"92128",
    "sg:province":"CA",
    "sg:tags":[
        "program",
        "manpower"
    ],
    "wof:name":"Corporate Management Ventures",
    "wof:placetype":"venue"
},
  "geometry": {"coordinates":[-117.06117,33.01391],"type":"Point"}
}