{
  "type": "Feature",
  "properties": {
    "iso:country":"US",
    "sg:address":"355 W 82nd St",
    "sg:city":"Los Angeles",
    "sg:classifiers":[
        {
            "category":"Retail",
            "subcategory":"Auto Repair",
            "type":"Services"
        }
    ],
    "sg:phone":"+1 323 759 6174",
    "sg:postcode":"90003",
    "sg:province":"CA",
    "sg:tags":[
        "general"
    ],
    "wof:name":"Ramses Auto Dismantler",
    "wof:placetype":"venue"
},
  "geometry": {"coordinates":[-118.279428,33.965132],"type":"Point"}
}