{
  "type": "Feature",
  "properties": {
    "addr:full":"14022 Ramona Blvd Baldwin Park CA 91706",
    "addr:housenumber":"14022",
    "addr:postcode":"91706",
    "addr:street":"Ramona Blvd",
    "iso:country":"US",
    "sg:address":"14022 Ramona Blvd",
    "sg:city":"Baldwin Park",
    "sg:classifiers":[
        {
            "category":"Real Estate",
            "subcategory":"Real Estate Agent",
            "type":"Services"
        }
    ],
    "sg:phone":"+1 626 337 3275",
    "sg:postcode":"91706",
    "sg:province":"CA",
    "wof:name":"Las Brisas Realty",
    "wof:placetype":"venue"
},
  "geometry": {"coordinates":[-117.966725,34.084703],"type":"Point"}
}