{
  "type": "Feature",
  "properties": {
    "addr:full":"662 23rd St Richmond CA 94804",
    "addr:housenumber":"662",
    "addr:postcode":"94804",
    "addr:street":"23Rd St",
    "iso:country":"US",
    "sg:address":"662 23rd St",
    "sg:city":"Richmond",
    "sg:classifiers":[
        {
            "category":"Food & Beverages",
            "subcategory":"Liquor & Beverages",
            "type":"Retail Goods"
        }
    ],
    "sg:phone":"+1 510 236 2201",
    "sg:postcode":"94804",
    "sg:province":"CA",
    "sg:tags":[
        "beer",
        "spirit",
        "wine"
    ],
    "wof:name":"Hand's Liquors & Delicatessen",
    "wof:placetype":"venue"
},
  "geometry": {"coordinates":[-122.34699999999999,37.942101],"type":"Point"}
}