{
  "type": "Feature",
  "properties": {
    "addr:full":"208 del Cabo San Clemente CA 92673",
    "addr:housenumber":"208",
    "addr:postcode":"92673",
    "addr:street":"Del Cabo",
    "iso:country":"US",
    "sg:address":"208 del Cabo",
    "sg:city":"San Clemente",
    "sg:classifiers":[
        {
            "category":"Manufacturing",
            "subcategory":"Metals",
            "type":"Manufacturing & Wholesale Goods"
        }
    ],
    "sg:phone":"+1 949 465 6719",
    "sg:postcode":"92673",
    "sg:province":"CA",
    "sg:tags":[
        "ornamental",
        "work"
    ],
    "wof:name":"Final Touch Iron Design",
    "wof:placetype":"venue"
},
  "geometry": {"coordinates":[-117.641756,33.468884],"type":"Point"}
}