{
  "type": "Feature",
  "properties": {
    "addr:full":"3400 Boulder St Pleasanton CA 94566",
    "addr:housenumber":"3400",
    "addr:postcode":"94566",
    "addr:street":"Boulder St",
    "iso:country":"US",
    "sg:address":"3400 Boulder St",
    "sg:city":"Pleasanton",
    "sg:classifiers":[
        {
            "category":"Wholesale",
            "subcategory":"Construction Materials",
            "type":"Manufacturing & Wholesale Goods"
        },
        {
            "category":"Manufacturing",
            "subcategory":"Building Materials",
            "type":"Manufacturing & Wholesale Goods"
        }
    ],
    "sg:phone":"+1 925 846 3226",
    "sg:postcode":"94566",
    "sg:province":"CA",
    "sg:tags":[
        "mixed",
        "concrete-ready",
        "cement"
    ],
    "wof:name":"Pleasanton Ready Mix",
    "wof:placetype":"venue"
},
  "geometry": {"coordinates":[-121.860023,37.673321],"type":"Point"}
}