{
  "type": "Feature",
  "properties": {
    "iso:country":"US",
    "sg:address":"30 Anguido Ct",
    "sg:city":"Burlingame",
    "sg:classifiers":[
        {
            "category":"Manufacturing",
            "subcategory":"Tools & Machinery",
            "type":"Manufacturing & Wholesale Goods"
        }
    ],
    "sg:phone":"+1 650 571 5870",
    "sg:postcode":"94010",
    "sg:province":"CA",
    "sg:tags":[
        "instrument",
        "industry",
        "for"
    ],
    "wof:name":"Lamdagen LLC",
    "wof:placetype":"venue"
},
  "geometry": {"coordinates":[-122.34260500000001,37.53664],"type":"Point"}
}