{
  "type": "Feature",
  "properties": {
    "addr:full":"3585 W Beechwood Ave Fresno CA 93711",
    "addr:housenumber":"3585",
    "addr:postcode":"93711",
    "addr:street":"W Beechwood Ave",
    "iso:country":"US",
    "sg:address":"3585 W Beechwood Ave",
    "sg:city":"Fresno",
    "sg:classifiers":[
        {
            "category":"Professional",
            "type":"Services"
        }
    ],
    "sg:phone":"+1 559 431 1680",
    "sg:postcode":"93711",
    "sg:province":"CA",
    "wof:name":"CMS",
    "wof:placetype":"venue"
},
  "geometry": {"coordinates":[-119.857088,36.838243],"type":"Point"}
}