{
  "type": "Feature",
  "properties": {
    "iso:country":"US",
    "sg:address":"3748 W 139th St",
    "sg:city":"Hawthorne",
    "sg:classifiers":[
        {
            "category":"Professional",
            "type":"Services"
        }
    ],
    "sg:phone":"+1 310 973 0929",
    "sg:postcode":"90250",
    "sg:province":"CA",
    "wof:name":"Wendy Flores",
    "wof:placetype":"venue"
},
  "geometry": {"coordinates":[-118.337557,33.905485],"type":"Point"}
}