{
  "type": "Feature",
  "properties": {
    "addr:full":"1459 18th St Suite 245 San Francisco CA 94107",
    "addr:housenumber":"1459",
    "addr:postcode":"94107",
    "addr:street":"18Th St Suite 245",
    "iso:country":"US",
    "sg:address":"1459 18th St Suite 245",
    "sg:city":"San Francisco",
    "sg:classifiers":[
        {
            "category":"Professional",
            "subcategory":"Management & Consulting",
            "type":"Services"
        }
    ],
    "sg:phone":"+1 415 717 9858",
    "sg:postcode":"94107",
    "sg:province":"CA",
    "sg:tags":[
        "consulting-jobs",
        "consultant-jobs",
        "consultants",
        "advisors",
        "independent-consulting",
        "independent-consultants"
    ],
    "sg:website":"http://www.ParetoCentral.com",
    "wof:name":"ParetoCentral.com",
    "wof:placetype":"venue"
},
  "geometry": {"coordinates":[-122.397035,37.762481],"type":"Point"}
}