{
  "type": "Feature",
  "properties": {
    "iso:country":"US",
    "sg:address":"902 14th St",
    "sg:city":"Arcata",
    "sg:classifiers":[
        {
            "category":"Organizations",
            "subcategory":"Non-profit Organization",
            "type":"Services"
        }
    ],
    "sg:phone":"+1 707 826 7986",
    "sg:postcode":"95521",
    "sg:province":"CA",
    "sg:tags":[
        "medical",
        "management"
    ],
    "wof:name":"Leslie Pennington",
    "wof:placetype":"venue"
},
  "geometry": {"coordinates":[-124.086382,40.873238],"type":"Point"}
}