{
  "type": "Feature",
  "properties": {
    "addr:full":"640 Hegenberger Rd Oakland CA 94621",
    "addr:housenumber":"640",
    "addr:postcode":"94621",
    "addr:street":"Hegenberger Rd",
    "iso:country":"US",
    "sg:address":"640 Hegenberger Rd",
    "sg:city":"Oakland",
    "sg:classifiers":[
        {
            "category":"Fast Food",
            "type":"Food & Drink"
        }
    ],
    "sg:phone":"+1 510 632 9225",
    "sg:postcode":"94621",
    "sg:province":"CA",
    "sg:website":"www.mcdonalds.com",
    "wof:name":"McDonald's",
    "wof:placetype":"venue"
},
  "geometry": {"coordinates":[-122.19611500000001,37.748443],"type":"Point"}
}