{
  "type": "Feature",
  "properties": {
    "addr:full":"10641 Pullman Ct Rancho Cucamonga CA 91730",
    "addr:housenumber":"10641",
    "addr:postcode":"91730",
    "addr:street":"Pullman Ct",
    "iso:country":"US",
    "sg:address":"10641 Pullman Ct",
    "sg:city":"Rancho Cucamonga",
    "sg:classifiers":[
        {
            "category":"Manufacturing",
            "subcategory":"Tools & Machinery",
            "type":"Manufacturing & Wholesale Goods"
        }
    ],
    "sg:phone":"+1 909 989 4478",
    "sg:postcode":"91730",
    "sg:province":"CA",
    "sg:tags":[
        "machine",
        "shop"
    ],
    "wof:name":"Garcia Molds & Engineering",
    "wof:placetype":"venue"
},
  "geometry": {"coordinates":[-117.57208,34.097801],"type":"Point"}
}