{
  "type": "Feature",
  "properties": {
    "iso:country":"US",
    "sg:address":"3251 20th Ave",
    "sg:city":"San Francisco",
    "sg:classifiers":[
        {
            "category":"Restaurant",
            "type":"Food & Drink"
        }
    ],
    "sg:menulink":"http://www.allmenus.com/ca/san-francisco/228587-hot-dog-on-a-stick/menu/",
    "sg:phone":"0",
    "sg:postcode":"94132",
    "sg:province":"CA",
    "sg:tags":[
        "american"
    ],
    "wof:name":"HOT DOG ON A STICK",
    "wof:placetype":"venue"
},
  "geometry": {"coordinates":[-122.47560300000001,37.728458],"type":"Point"}
}