{
  "type": "Feature",
  "properties": {
    "iso:country":"US",
    "sg:address":"933 7th St",
    "sg:city":"Wasco",
    "sg:classifiers":[
        {
            "category":"Personal",
            "subcategory":"Beauty Salon",
            "type":"Services"
        }
    ],
    "sg:phone":"+1 661 758 3837",
    "sg:postcode":"93280",
    "sg:province":"CA",
    "wof:name":"Cecilia's Impressions",
    "wof:placetype":"venue"
},
  "geometry": {"coordinates":[-119.33549499999999,35.594177],"type":"Point"}
}