{
  "type": "Feature",
  "properties": {
    "iso:country":"US",
    "sg:address":"21201 Victory Blvd",
    "sg:city":"Canoga Park",
    "sg:classifiers":[
        {
            "category":"Health Services",
            "subcategory":"Doctor",
            "type":"Services"
        }
    ],
    "sg:phone":"+1 818 702 9339",
    "sg:postcode":"91303",
    "sg:province":"CA",
    "sg:tags":[
        "physician",
        "surgeon"
    ],
    "wof:name":"Natalie Krah MD",
    "wof:placetype":"venue"
},
  "geometry": {"coordinates":[-118.596165,34.188419],"type":"Point"}
}