{
  "type": "Feature",
  "properties": {
    "addr:full":"108 S Indian Canyon Dr Palm Springs CA 92262",
    "addr:housenumber":"108",
    "addr:postcode":"92262",
    "addr:street":"S Indian Canyon Dr",
    "iso:country":"US",
    "sg:address":"108 S Indian Canyon Dr",
    "sg:city":"Palm Springs",
    "sg:classifiers":[
        {
            "category":"Shopping",
            "subcategory":"Clothing, Apparel, & Fashions",
            "type":"Retail Goods"
        }
    ],
    "sg:phone":"+1 760 325 4330",
    "sg:postcode":"92262",
    "sg:province":"CA",
    "sg:tags":[
        "accessory"
    ],
    "wof:name":"Wardrobe the",
    "wof:placetype":"venue"
},
  "geometry": {"coordinates":[-116.545998,33.822201],"type":"Point"}
}