{
  "type": "Feature",
  "properties": {
    "iso:country":"US",
    "sg:address":"12300 Valpico Rd",
    "sg:city":"Tracy",
    "sg:classifiers":[
        {
            "category":"Utilities",
            "subcategory":"Telephone",
            "type":"Services"
        }
    ],
    "sg:phone":"+1 209 832 4637",
    "sg:postcode":"95377",
    "sg:province":"CA",
    "sg:tags":[
        "communications"
    ],
    "wof:name":"Foyer Telephone",
    "wof:placetype":"venue"
},
  "geometry": {"coordinates":[-121.452864,37.710575],"type":"Point"}
}