{
  "type": "Feature",
  "properties": {
    "iso:country":"US",
    "sg:address":"12777 Big Sky Pl",
    "sg:city":"Auburn",
    "sg:classifiers":[
        {
            "category":"Manufacturing",
            "subcategory":"Chemicals & Compounds",
            "type":"Manufacturing & Wholesale Goods"
        }
    ],
    "sg:phone":"+1 530 269 2343",
    "sg:postcode":"95602",
    "sg:province":"CA",
    "sg:tags":[
        "synthetic",
        "rubber",
        "mfg"
    ],
    "wof:name":"Eagle Nest Homes",
    "wof:placetype":"venue"
},
  "geometry": {"coordinates":[-121.102376,39.008511],"type":"Point"}
}