{
  "type": "Feature",
  "properties": {
    "addr:full":"12777 Big Sky Pl Auburn CA 95602",
    "addr:housenumber":"12777",
    "addr:postcode":"ca 95602",
    "addr:street":"Big;Pl",
    "iso:country":"US",
    "sg:address":"12777 Big Sky Pl",
    "sg:city":"Auburn",
    "sg:classifiers":[
        {
            "category":"Manufacturing",
            "subcategory":"Chemicals & Compounds",
            "type":"Manufacturing & Wholesale Goods"
        }
    ],
    "sg:phone":"+1 530 269 2343",
    "sg:postcode":"95602",
    "sg:province":"CA",
    "sg:tags":[
        "synthetic",
        "rubber",
        "mfg"
    ],
    "wof:name":"Eagle Nest Homes",
    "wof:placetype":"venue"
},
  "geometry": {"coordinates":[-121.10237600000001,39.008511],"type":"Point"}
}