{
  "type": "Feature",
  "properties": {
    "addr:full":"2105 S Bascom Ave Campbell CA 95008",
    "addr:housenumber":"2105",
    "addr:postcode":"95008",
    "addr:street":"S Bascom Ave",
    "iso:country":"US",
    "sg:address":"2105 S Bascom Ave",
    "sg:city":"Campbell",
    "sg:classifiers":[
        {
            "category":"Real Estate",
            "subcategory":"Real Estate Agent",
            "type":"Services"
        }
    ],
    "sg:phone":"+1 408 866 7171",
    "sg:postcode":"95008",
    "sg:province":"CA",
    "sg:website":"www.robroham.com",
    "wof:name":"Rob Roham",
    "wof:placetype":"venue"
},
  "geometry": {"coordinates":[-121.93182,37.285791],"type":"Point"}
}