{
  "type": "Feature",
  "properties": {
    "iso:country":"US",
    "sg:address":"246 Dorchester Ln",
    "sg:city":"Alamo",
    "sg:classifiers":[
        {
            "category":"Professional",
            "type":"Services"
        }
    ],
    "sg:phone":"+1 925 939 9911",
    "sg:postcode":"94507",
    "sg:province":"CA",
    "wof:name":"Sharon Meyer",
    "wof:placetype":"venue"
},
  "geometry": {"coordinates":[-122.006111,37.87824],"type":"Point"}
}