{
  "type": "Feature",
  "properties": {
    "iso:country":"US",
    "sg:address":"14724 Aviation Blvd",
    "sg:city":"Lawndale",
    "sg:classifiers":[
        {
            "category":"Manufacturing",
            "subcategory":"Motor Vehicles & Parts",
            "type":"Manufacturing & Wholesale Goods"
        }
    ],
    "sg:phone":"+1 310 536 0551",
    "sg:postcode":"90260",
    "sg:province":"CA",
    "sg:tags":[
        "equipment",
        "railroad",
        "mfg"
    ],
    "wof:name":"Bombardier Transportation",
    "wof:placetype":"venue"
},
  "geometry": {"coordinates":[-118.378664,33.898735],"type":"Point"}
}