{
  "type": "Feature",
  "properties": {
    "iso:country":"US",
    "sg:address":"25262 el Paseo",
    "sg:city":"Mission Viejo",
    "sg:classifiers":[
        {
            "category":"Shopping",
            "subcategory":"Computers & Home Electronics",
            "type":"Retail Goods"
        }
    ],
    "sg:phone":"+1 949 582 8288",
    "sg:postcode":"92691",
    "sg:province":"CA",
    "wof:name":"Comp U S A 267",
    "wof:placetype":"venue"
},
  "geometry": {"coordinates":[-117.673794,33.590365],"type":"Point"}
}