{
  "type": "Feature",
  "properties": {
    "iso:country":"US",
    "sg:address":"1020 Huntington Dr",
    "sg:city":"San Marino",
    "sg:classifiers":[
        {
            "category":"Real Estate",
            "subcategory":"Real Estate Services",
            "type":"Services"
        }
    ],
    "sg:phone":"+1 626 282 8443",
    "sg:postcode":"91108",
    "sg:province":"CA",
    "sg:tags":[
        "management",
        "property"
    ],
    "wof:name":"Casner Consolidates",
    "wof:placetype":"venue"
},
  "geometry": {"coordinates":[-118.12400100000001,34.113201],"type":"Point"}
}