{
  "type": "Feature",
  "properties": {
    "addr:full":"5029 Evanwood Ave Agoura Hills CA 91377",
    "addr:housenumber":"5029",
    "addr:postcode":"91377",
    "addr:street":"Evanwood Ave",
    "iso:country":"US",
    "sg:address":"5029 Evanwood Ave",
    "sg:city":"Agoura Hills",
    "sg:classifiers":[
        {
            "category":"Wholesale",
            "subcategory":"Computers",
            "type":"Manufacturing & Wholesale Goods"
        }
    ],
    "sg:phone":"+1 818 991 9498",
    "sg:postcode":"91377",
    "sg:province":"CA",
    "wof:name":"Cross-Country Trading Co Inc",
    "wof:placetype":"venue"
},
  "geometry": {"coordinates":[-118.783349,34.181135],"type":"Point"}
}