{
  "type": "Feature",
  "properties": {
    "addr:full":"6592 N Garden Ave Fresno CA 93710",
    "addr:housenumber":"6592",
    "addr:postcode":"93710",
    "addr:street":"N Garden Ave",
    "iso:country":"US",
    "sg:address":"6592 N Garden Ave",
    "sg:city":"Fresno",
    "sg:classifiers":[
        {
            "category":"Real Estate",
            "subcategory":"Real Estate Agent",
            "type":"Services"
        }
    ],
    "sg:phone":"+1 559 292 3400",
    "sg:postcode":"93710",
    "sg:province":"CA",
    "wof:name":"J A Salerno & Assoc",
    "wof:placetype":"venue"
},
  "geometry": {"coordinates":[-119.73422100000001,36.832131],"type":"Point"}
}