{
  "type": "Feature",
  "properties": {
    "iso:country":"US",
    "sg:address":"1330 N Linwood Ave",
    "sg:city":"Santa Ana",
    "sg:classifiers":[
        {
            "category":"Freight",
            "type":"Transportation"
        }
    ],
    "sg:phone":"+1 714 728 8009",
    "sg:postcode":"92701",
    "sg:province":"CA",
    "sg:tags":[
        "trucking"
    ],
    "wof:name":"Tomas Moreno & Sons Trucking",
    "wof:placetype":"venue"
},
  "geometry": {"coordinates":[-117.848823,33.757096],"type":"Point"}
}