{
  "type": "Feature",
  "properties": {
    "iso:country":"US",
    "sg:address":"23928 Lyons Ave Ste 204",
    "sg:city":"Newhall",
    "sg:classifiers":[
        {
            "category":"Health Services",
            "subcategory":"Doctor",
            "type":"Services"
        }
    ],
    "sg:phone":"+1 661 288 1358",
    "sg:postcode":"91321",
    "sg:province":"CA",
    "sg:tags":[
        "psychiatrist"
    ],
    "wof:name":"Barte Ophelia G MD",
    "wof:placetype":"venue"
},
  "geometry": {"coordinates":[-118.55300099999999,34.379002],"type":"Point"}
}