{
  "type": "Feature",
  "properties": {
    "iso:country":"US",
    "sg:address":"3129 E Tulare Ave",
    "sg:city":"Fresno",
    "sg:classifiers":[
        {
            "category":"Restaurant",
            "type":"Food & Drink"
        }
    ],
    "sg:phone":"+1 559 497 0980",
    "sg:postcode":"93702",
    "sg:province":"CA",
    "wof:name":"Subway Sandwiches & Salads",
    "wof:placetype":"venue"
},
  "geometry": {"coordinates":[-119.77132,36.743235],"type":"Point"}
}