{
  "type": "Feature",
  "properties": {
    "addr:full":"11731 Sterling Ave Riverside CA 92503",
    "addr:housenumber":"11731",
    "addr:postcode":"92503",
    "addr:street":"Sterling Ave",
    "iso:country":"US",
    "sg:address":"11731 Sterling Ave",
    "sg:city":"Riverside",
    "sg:classifiers":[
        {
            "category":"Home & Garden",
            "subcategory":"Carpets & Floor Coverings",
            "type":"Retail Goods"
        }
    ],
    "sg:phone":"+1 951 352 2530",
    "sg:postcode":"92503",
    "sg:province":"CA",
    "sg:tags":[
        "dealer",
        "rug"
    ],
    "wof:name":"Carpet Warehouse",
    "wof:placetype":"venue"
},
  "geometry": {"coordinates":[-117.48623499999999,33.895207],"type":"Point"}
}