{
  "type": "Feature",
  "properties": {
    "addr:full":"594 Fisher St Rio Vista CA 94571",
    "addr:housenumber":"594",
    "addr:postcode":"94571",
    "addr:street":"Fisher St",
    "iso:country":"US",
    "sg:address":"594 Fisher St",
    "sg:city":"Rio Vista",
    "sg:classifiers":[
        {
            "category":"Building & Trades",
            "subcategory":"Construction",
            "type":"Services"
        }
    ],
    "sg:phone":"+1 510 724 2995",
    "sg:postcode":"94571",
    "sg:province":"CA",
    "sg:tags":[
        "roofing",
        "contractor"
    ],
    "wof:name":"Jim's Roofing Co",
    "wof:placetype":"venue"
},
  "geometry": {"coordinates":[-121.69370499999999,38.170913],"type":"Point"}
}