{
  "type": "Feature",
  "properties": {
    "iso:country":"US",
    "sg:address":"1226 S Main St",
    "sg:city":"Santa Ana",
    "sg:classifiers":[
        {
            "category":"Retail",
            "subcategory":"Auto Repair",
            "type":"Services"
        },
        {
            "category":"Ice Cream",
            "type":"Food & Drink"
        }
    ],
    "sg:phone":"+1 714 836 4009",
    "sg:postcode":"92707",
    "sg:province":"CA",
    "sg:tags":[
        "frozen",
        "yogurt"
    ],
    "wof:name":"Santa Ana F B O Inc",
    "wof:placetype":"venue"
},
  "geometry": {"coordinates":[-117.86799600000001,33.732201],"type":"Point"}
}