{
  "type": "Feature",
  "properties": {
    "addr:full":"2910 E Heaton Ave Fresno CA 93721",
    "addr:housenumber":"2910",
    "addr:postcode":"93721",
    "addr:street":"E Heaton Ave",
    "iso:country":"US",
    "sg:address":"2910 E Heaton Ave",
    "sg:city":"Fresno",
    "sg:classifiers":[
        {
            "category":"Manufacturing",
            "subcategory":"Paper Products",
            "type":"Manufacturing & Wholesale Goods"
        }
    ],
    "sg:phone":"+1 559 485 9761",
    "sg:postcode":"93721",
    "sg:province":"CA",
    "sg:tags":[
        "mill",
        "asphalt",
        "mfg"
    ],
    "wof:name":"Penny Newman Grain Co",
    "wof:placetype":"venue"
},
  "geometry": {"coordinates":[-119.77508899999999,36.726799],"type":"Point"}
}