{
  "type": "Feature",
  "properties": {
    "iso:country":"US",
    "sg:address":"510 4th St",
    "sg:city":"Davis",
    "sg:classifiers":[
        {
            "category":"Professional",
            "subcategory":"Lawyer & Legal Services",
            "type":"Services"
        }
    ],
    "sg:phone":"+1 530 758 1990",
    "sg:postcode":"95616",
    "sg:province":"CA",
    "sg:tags":[
        "attorney"
    ],
    "wof:name":"Stanley H Wells Law Offices",
    "wof:placetype":"venue"
},
  "geometry": {"coordinates":[-121.741888,38.545717],"type":"Point"}
}