{
  "type": "Feature",
  "properties": {
    "iso:country":"US",
    "sg:address":"5231 Marathon St",
    "sg:city":"Los Angeles",
    "sg:classifiers":[
        {
            "category":"Freight",
            "type":"Transportation"
        }
    ],
    "sg:phone":"+1 323 493 7963",
    "sg:postcode":"90038",
    "sg:province":"CA",
    "sg:tags":[
        "operator",
        "local",
        "trucking"
    ],
    "wof:name":"Henean Trucking",
    "wof:placetype":"venue"
},
  "geometry": {"coordinates":[-118.312172,34.084979],"type":"Point"}
}