{
  "type": "Feature",
  "properties": {
    "addr:full":"377 Needles Hwy Needles CA 92363",
    "addr:housenumber":"377",
    "addr:postcode":"92363",
    "addr:street":"Needles Hwy",
    "iso:country":"US",
    "sg:address":"377 Needles Hwy",
    "sg:city":"Needles",
    "sg:classifiers":[
        {
            "category":"Professional",
            "subcategory":"Business Services",
            "type":"Services"
        }
    ],
    "sg:phone":"+1 760 326 2015",
    "sg:postcode":"92363",
    "sg:province":"CA",
    "sg:tags":[
        "information",
        "referral"
    ],
    "wof:name":"Laughlin Information Ctr",
    "wof:placetype":"venue"
},
  "geometry": {"coordinates":[-114.60783000000001,34.84831],"type":"Point"}
}