{
  "type": "Feature",
  "properties": {
    "iso:country":"US",
    "sg:address":"230 Sequoia Ave",
    "sg:city":"Walnut Creek",
    "sg:classifiers":[
        {
            "category":"Building & Trades",
            "subcategory":"Construction",
            "type":"Services"
        },
        {
            "category":"Home & Garden",
            "subcategory":"Furniture",
            "type":"Retail Goods"
        }
    ],
    "sg:phone":"+1 925 932 0420",
    "sg:postcode":"94595",
    "sg:province":"CA",
    "sg:tags":[
        "maker",
        "cabinet"
    ],
    "wof:name":"Temple Norm Special Effects",
    "wof:placetype":"venue"
},
  "geometry": {"coordinates":[-122.073573,37.884467],"type":"Point"}
}