{
  "type": "Feature",
  "properties": {
    "iso:country":"US",
    "sg:address":"364 Ferguson Dr",
    "sg:city":"Mountain View",
    "sg:classifiers":[
        {
            "category":"Utilities",
            "subcategory":"Telephone",
            "type":"Services"
        }
    ],
    "sg:phone":"+1 650 318 8100",
    "sg:postcode":"94043",
    "sg:province":"CA",
    "sg:tags":[
        "communications"
    ],
    "wof:name":"Genuity Managed Services LLC",
    "wof:placetype":"venue"
},
  "geometry": {"coordinates":[-122.05731,37.38831],"type":"Point"}
}