{
  "type": "Feature",
  "properties": {
    "iso:country":"US",
    "sg:address":"508 W Mission Ave",
    "sg:city":"Escondido",
    "sg:classifiers":[
        {
            "category":"Professional",
            "subcategory":"Management & Consulting",
            "type":"Services"
        }
    ],
    "sg:phone":"+1 760 743 5408",
    "sg:postcode":"92025",
    "sg:province":"CA",
    "sg:tags":[
        "consultant",
        "energy",
        "conservation"
    ],
    "sg:website":"www.title-24.com",
    "wof:name":"Haynal & Co",
    "wof:placetype":"venue"
},
  "geometry": {"coordinates":[-117.092244,33.128299],"type":"Point"}
}