{
  "type": "Feature",
  "properties": {
    "iso:country":"US",
    "sg:address":"220 McKinley St",
    "sg:city":"Calexico",
    "sg:classifiers":[
        {
            "category":"Wholesale",
            "subcategory":"Groceries",
            "type":"Manufacturing & Wholesale Goods"
        }
    ],
    "sg:phone":"+1 760 357 0577",
    "sg:postcode":"92231",
    "sg:province":"CA",
    "sg:tags":[
        "grocer"
    ],
    "wof:name":"California Super Market",
    "wof:placetype":"venue"
},
  "geometry": {"coordinates":[-115.501392,32.676039],"type":"Point"}
}