{
  "type": "Feature",
  "properties": {
    "addr:full":"1411 E 31st St Oakland CA 94602",
    "addr:housenumber":"1411",
    "addr:postcode":"94602",
    "addr:street":"E 31St St",
    "iso:country":"US",
    "sg:address":"1411 E 31st St",
    "sg:city":"Oakland",
    "sg:classifiers":[
        {
            "category":"Health Services",
            "subcategory":"Doctor",
            "type":"Services"
        }
    ],
    "sg:phone":"+1 510 437 4268",
    "sg:postcode":"94602",
    "sg:province":"CA",
    "sg:tags":[
        "physician",
        "surgeon"
    ],
    "sg:website":"www.hghed.com",
    "wof:name":"East Bay Academic Physicians",
    "wof:placetype":"venue"
},
  "geometry": {"coordinates":[-122.23182300000001,37.799282],"type":"Point"}
}