{
  "type": "Feature",
  "properties": {
    "iso:country":"US",
    "sg:address":"760 Stony Point Rd",
    "sg:city":"Santa Rosa",
    "sg:classifiers":[
        {
            "category":"Coffee & Tea",
            "type":"Food & Drink"
        }
    ],
    "sg:menulink":"http://www.allmenus.com/ca/santa-rosa/116667-starbucks-coffee/menu/",
    "sg:phone":"+1 707 546 5046",
    "sg:postcode":"95407",
    "sg:province":"CA",
    "sg:tags":[
        "american"
    ],
    "wof:name":"Starbucks Coffee",
    "wof:placetype":"venue"
},
  "geometry": {"coordinates":[-122.74135099999999,38.42765],"type":"Point"}
}