{
  "type": "Feature",
  "properties": {
    "addr:full":"1355 N Hacienda Blvd La Puente CA 91744",
    "addr:housenumber":"1355",
    "addr:postcode":"91744",
    "addr:street":"N Hacienda Blvd",
    "iso:country":"US",
    "sg:address":"1355 N Hacienda Blvd",
    "sg:city":"La Puente",
    "sg:classifiers":[
        {
            "category":"Health Services",
            "subcategory":"Doctor",
            "type":"Services"
        }
    ],
    "sg:phone":"+1 626 917 1719",
    "sg:postcode":"91744",
    "sg:province":"CA",
    "sg:tags":[
        "physician",
        "surgeon"
    ],
    "wof:name":"LA Puente Dialysis Ctr",
    "wof:placetype":"venue"
},
  "geometry": {"coordinates":[-117.94936199999999,34.043285],"type":"Point"}
}