{
  "type": "Feature",
  "properties": {
    "addr:full":"11111 Santa Monica Blvd Los Angeles CA 90025",
    "addr:housenumber":"11111",
    "addr:postcode":"90025",
    "addr:street":"Santa Monica Blvd",
    "iso:country":"US",
    "sg:address":"11111 Santa Monica Blvd",
    "sg:city":"Los Angeles",
    "sg:classifiers":[
        {
            "category":"Banks & Credit Unions",
            "subcategory":"Investment Brokerage",
            "type":"Services"
        }
    ],
    "sg:phone":"+1 310 231 6100",
    "sg:postcode":"90025",
    "sg:province":"CA",
    "sg:tags":[
        "investing"
    ],
    "wof:name":"Causeway Capital Management",
    "wof:placetype":"venue"
},
  "geometry": {"coordinates":[-118.444,34.047699],"type":"Point"}
}