{
  "type": "Feature",
  "properties": {
    "addr:full":"14960 Rosemary Dr Fontana CA 92335",
    "addr:housenumber":"14960",
    "addr:postcode":"92335",
    "addr:street":"Rosemary Dr",
    "iso:country":"US",
    "sg:address":"14960 Rosemary Dr",
    "sg:city":"Fontana",
    "sg:classifiers":[
        {
            "category":"Freight",
            "type":"Transportation"
        }
    ],
    "sg:phone":"+1 909 429 1254",
    "sg:postcode":"92335",
    "sg:province":"CA",
    "wof:name":"Farias Brothers Transport",
    "wof:placetype":"venue"
},
  "geometry": {"coordinates":[-117.476879,34.073444],"type":"Point"}
}