{
  "type": "Feature",
  "properties": {
    "iso:country":"US",
    "sg:address":"7236 Reseda Blvd",
    "sg:city":"Reseda",
    "sg:classifiers":[
        {
            "category":"Autos & Motor Vehicles",
            "subcategory":"Auto Supplies",
            "type":"Retail Goods"
        },
        {
            "category":"Retail",
            "subcategory":"Auto Repair",
            "type":"Services"
        }
    ],
    "sg:phone":"+1 818 708 0042",
    "sg:postcode":"91335",
    "sg:province":"CA",
    "sg:tags":[
        "lettering",
        "automobile",
        "body",
        "truck",
        "painting",
        "repairing"
    ],
    "wof:name":"Independent Auto Collision Repair",
    "wof:placetype":"venue"
},
  "geometry": {"coordinates":[-118.53604900000001,34.202342],"type":"Point"}
}