{
  "type": "Feature",
  "properties": {
    "iso:country":"US",
    "sg:address":"225 9th Ave",
    "sg:city":"La Puente",
    "sg:classifiers":[
        {
            "category":"Building & Trades",
            "subcategory":"Construction",
            "type":"Services"
        }
    ],
    "sg:phone":"+1 626 333 3962",
    "sg:postcode":"91746",
    "sg:province":"CA",
    "sg:tags":[
        "maker",
        "cabinet"
    ],
    "wof:name":"R Kenson Cabinet",
    "wof:placetype":"venue"
},
  "geometry": {"coordinates":[-117.970305,34.027599],"type":"Point"}
}