{
  "type": "Feature",
  "properties": {
    "iso:country":"US",
    "sg:address":"346 N Tehama St",
    "sg:city":"Willows",
    "sg:classifiers":[
        {
            "category":"Building & Trades",
            "subcategory":"Plumbing",
            "type":"Services"
        }
    ],
    "sg:phone":"+1 530 934 3261",
    "sg:postcode":"95988",
    "sg:province":"CA",
    "sg:tags":[
        "conditioning",
        "air",
        "system",
        "contractor"
    ],
    "wof:name":"Sinclair Heating & Air Cond",
    "wof:placetype":"venue"
},
  "geometry": {"coordinates":[-122.193788,39.523724],"type":"Point"}
}