{
  "type": "Feature",
  "properties": {
    "iso:country":"US",
    "sg:address":"1736 Redwood Hwy",
    "sg:city":"Corte Madera",
    "sg:classifiers":[
        {
            "category":"Restaurant",
            "type":"Food & Drink"
        }
    ],
    "sg:phone":"+1 415 945 0777",
    "sg:postcode":"94925",
    "sg:province":"CA",
    "wof:name":"Cheesecake Factory",
    "wof:placetype":"venue"
},
  "geometry": {"coordinates":[-122.516075,37.933856],"type":"Point"}
}