{
  "type": "Feature",
  "properties": {
    "iso:country":"US",
    "sg:address":"775 Sunrise Ave",
    "sg:city":"Roseville",
    "sg:classifiers":[
        {
            "category":"Real Estate",
            "subcategory":"Developer",
            "type":"Services"
        },
        {
            "category":"Real Estate",
            "subcategory":"Real Estate Agent",
            "type":"Services"
        }
    ],
    "sg:phone":"+1 916 773 1812",
    "sg:postcode":"95661",
    "sg:province":"CA",
    "wof:name":"Summit Brokerage",
    "wof:placetype":"venue"
},
  "geometry": {"coordinates":[-121.27196499999999,38.733814],"type":"Point"}
}