{
  "type": "Feature",
  "properties": {
    "iso:country":"US",
    "sg:address":"24413 Valley St",
    "sg:city":"Newhall",
    "sg:classifiers":[
        {
            "category":"Real Estate",
            "subcategory":"Real Estate Services",
            "type":"Services"
        },
        {
            "category":"Insurance",
            "subcategory":"Title Insurance",
            "type":"Services"
        }
    ],
    "sg:phone":"+1 661 287 3322",
    "sg:postcode":"91321",
    "sg:province":"CA",
    "wof:name":"Southland Title",
    "wof:placetype":"venue"
},
  "geometry": {"coordinates":[-118.539737,34.371665],"type":"Point"}
}