{
  "type": "Feature",
  "properties": {
    "iso:country":"US",
    "sg:address":"671 W Tefft St",
    "sg:city":"Nipomo",
    "sg:classifiers":[
        {
            "category":"Sports & Exercise",
            "subcategory":"Gym",
            "type":"Entertainment"
        }
    ],
    "sg:phone":"+1 805 929 3555",
    "sg:postcode":"93444",
    "sg:province":"CA",
    "sg:tags":[
        "club",
        "health",
        "studio",
        "gymnasium"
    ],
    "wof:name":"Slender Lady",
    "wof:placetype":"venue"
},
  "geometry": {"coordinates":[-120.487023,35.0353],"type":"Point"}
}