{
  "type": "Feature",
  "properties": {
    "iso:country":"US",
    "sg:address":"1221 E Yorba Linda Blvd",
    "sg:city":"Placentia",
    "sg:classifiers":[
        {
            "category":"Professional",
            "subcategory":"Employment Agencies",
            "type":"Services"
        }
    ],
    "sg:phone":"+1 714 996 1989",
    "sg:postcode":"92870",
    "sg:province":"CA",
    "wof:name":"Maranatha Personnel Service",
    "wof:placetype":"venue"
},
  "geometry": {"coordinates":[-117.843002,33.8853],"type":"Point"}
}