{
  "type": "Feature",
  "properties": {
    "addr:full":"840 13th St Paso Robles CA 93446",
    "addr:housenumber":"840",
    "addr:postcode":"93446",
    "addr:street":"13Th St",
    "iso:country":"US",
    "sg:address":"840 13th St",
    "sg:city":"Paso Robles",
    "sg:classifiers":[
        {
            "category":"Government",
            "subcategory":"Office",
            "type":"Public Place"
        }
    ],
    "sg:phone":"+1 805 226 0207",
    "sg:postcode":"93446",
    "sg:province":"CA",
    "sg:tags":[
        "force",
        "armed",
        "recruiting"
    ],
    "wof:name":"US Army Recruiting",
    "wof:placetype":"venue"
},
  "geometry": {"coordinates":[-120.68955,35.627773],"type":"Point"}
}