{
  "type": "Feature",
  "properties": {
    "addr:full":"2633 W Rumble Rd Modesto CA 95350",
    "addr:housenumber":"2633",
    "addr:postcode":"ca 95350",
    "addr:street":"W Rumble Rd",
    "iso:country":"US",
    "sg:address":"2633 W Rumble Rd",
    "sg:city":"Modesto",
    "sg:classifiers":[
        {
            "category":"Health Services",
            "subcategory":"Nursing And Care Facility",
            "type":"Services"
        }
    ],
    "sg:phone":"+1 209 577 1001",
    "sg:postcode":"95350",
    "sg:province":"CA",
    "sg:tags":[
        "home",
        "skilled",
        "convalescent"
    ],
    "sg:website":"www.englishoaks.com",
    "wof:name":"English Oaks Convalescent & RE",
    "wof:placetype":"venue"
},
  "geometry": {"coordinates":[-121.048142,37.682242],"type":"Point"}
}