{
  "type": "Feature",
  "properties": {
    "iso:country":"US",
    "sg:address":"278 N Wilshire Ave",
    "sg:city":"Anaheim",
    "sg:classifiers":[
        {
            "category":"Professional",
            "subcategory":"Research",
            "type":"Services"
        }
    ],
    "sg:phone":"+1 714 535 0433",
    "sg:postcode":"92801",
    "sg:province":"CA",
    "sg:tags":[
        "organization",
        "noncommercial"
    ],
    "wof:name":"Coalition Fod Educatnl Rights",
    "wof:placetype":"venue"
},
  "geometry": {"coordinates":[-117.933902,33.834054],"type":"Point"}
}