{
  "type": "Feature",
  "properties": {
    "iso:country":"US",
    "sg:address":"1650 Forest Ave",
    "sg:city":"Chico",
    "sg:classifiers":[
        {
            "category":"Professional",
            "subcategory":"Business Services",
            "type":"Services"
        }
    ],
    "sg:phone":"+1 530 566 1607",
    "sg:postcode":"95928",
    "sg:province":"CA",
    "sg:tags":[
        "pool",
        "swimming"
    ],
    "wof:name":"Pools Plus",
    "wof:placetype":"venue"
},
  "geometry": {"coordinates":[-121.80153300000001,39.733686],"type":"Point"}
}