{
  "type": "Feature",
  "properties": {
    "iso:country":"US",
    "sg:address":"42652 Rd 812",
    "sg:city":"Raymond",
    "sg:classifiers":[
        {
            "category":"Farming",
            "subcategory":"Livestock Farm",
            "type":"Manufacturing & Wholesale Goods"
        }
    ],
    "sg:phone":"+1 209 966 2576",
    "sg:postcode":"93653",
    "sg:province":"CA",
    "sg:tags":[
        "ranch",
        "cattle"
    ],
    "wof:name":"Jean Werly",
    "wof:placetype":"venue"
},
  "geometry": {"coordinates":[-119.80878199999999,37.362374],"type":"Point"}
}