{
  "type": "Feature",
  "properties": {
    "addr:full":"15811 W Harding Rd Turlock CA 95380",
    "addr:housenumber":"15811",
    "addr:postcode":"95380",
    "addr:street":"W Harding Rd",
    "iso:country":"US",
    "sg:address":"15811 W Harding Rd",
    "sg:city":"Turlock",
    "sg:classifiers":[
        {
            "category":"Farming",
            "subcategory":"Crops",
            "type":"Manufacturing & Wholesale Goods"
        }
    ],
    "sg:phone":"+1 209 634 8036",
    "sg:postcode":"95380",
    "sg:province":"CA",
    "sg:tags":[
        "grove",
        "nut",
        "tree"
    ],
    "wof:name":"Victor Bertolini",
    "wof:placetype":"venue"
},
  "geometry": {"coordinates":[-120.772187,37.463105],"type":"Point"}
}