{
  "type": "Feature",
  "properties": {
    "addr:full":"1010 Stern Ln Foster City CA 94404",
    "addr:housenumber":"1010",
    "addr:postcode":"94404",
    "addr:street":"Stern Ln",
    "iso:country":"US",
    "sg:address":"1010 Stern Ln",
    "sg:city":"Foster City",
    "sg:classifiers":[
        {
            "category":"Wholesale",
            "subcategory":"Durable Goods & Equipment",
            "type":"Manufacturing & Wholesale Goods"
        }
    ],
    "sg:phone":"+1 650 349 5732",
    "sg:postcode":"94404",
    "sg:province":"CA",
    "sg:tags":[
        "exporter"
    ],
    "wof:name":"Traphil International Inc",
    "wof:placetype":"venue"
},
  "geometry": {"coordinates":[-122.256917,37.548276],"type":"Point"}
}