{
  "type": "Feature",
  "properties": {
    "iso:country":"US",
    "sg:address":"1061 State St",
    "sg:city":"Soledad",
    "sg:classifiers":[
        {
            "category":"Health Services",
            "subcategory":"Doctor",
            "type":"Services"
        }
    ],
    "sg:phone":"+1 831 678 1237",
    "sg:postcode":"93960",
    "sg:province":"CA",
    "sg:tags":[
        "tattoo"
    ],
    "wof:name":"Mystical Tattoos",
    "wof:placetype":"venue"
},
  "geometry": {"coordinates":[-121.323218,36.423557],"type":"Point"}
}