{
  "type": "Feature",
  "properties": {
    "addr:full":"60995 Pierce St Thermal CA 92274",
    "addr:housenumber":"60995",
    "addr:postcode":"92274",
    "addr:street":"Pierce St",
    "iso:country":"US",
    "sg:address":"60995 Pierce St",
    "sg:city":"Thermal",
    "sg:classifiers":[
        {
            "category":"Home & Garden",
            "subcategory":"Garden Supply",
            "type":"Retail Goods"
        }
    ],
    "sg:phone":"+1 760 399 1487",
    "sg:postcode":"92274",
    "sg:province":"CA",
    "sg:tags":[
        "fertilizer"
    ],
    "wof:name":"Helena Chemical Co",
    "wof:placetype":"venue"
},
  "geometry": {"coordinates":[-116.112408,33.605871],"type":"Point"}
}