{
  "type": "Feature",
  "properties": {
    "addr:full":"6382 Thornhill Dr Oakland CA 94611",
    "addr:housenumber":"6382",
    "addr:postcode":"94611",
    "addr:street":"Thornhill Dr",
    "iso:country":"US",
    "sg:address":"6382 Thornhill Dr",
    "sg:city":"Oakland",
    "sg:classifiers":[
        {
            "category":"Social Services",
            "subcategory":"Adult Care",
            "type":"Services"
        }
    ],
    "sg:phone":"+1 510 685 8195",
    "sg:postcode":"94611",
    "sg:province":"CA",
    "sg:tags":[
        "home",
        "convalescent",
        "nursing",
        "residential"
    ],
    "wof:name":"Dehaven, Cain Enterprises",
    "wof:placetype":"venue"
},
  "geometry": {"coordinates":[-122.206937,37.841728],"type":"Point"}
}