{
  "type": "Feature",
  "properties": {
    "addr:full":"1840 Woolsey St Berkeley CA 94703",
    "addr:housenumber":"1840",
    "addr:postcode":"94703",
    "addr:street":"Woolsey St",
    "iso:country":"US",
    "sg:address":"1840 Woolsey St",
    "sg:city":"Berkeley",
    "sg:classifiers":[
        {
            "category":"Professional",
            "subcategory":"Lawyer & Legal Services",
            "type":"Services"
        }
    ],
    "sg:phone":"+1 510 845 9788",
    "sg:postcode":"94703",
    "sg:province":"CA",
    "sg:tags":[
        "attorney"
    ],
    "wof:name":"Larry Hildes",
    "wof:placetype":"venue"
},
  "geometry": {"coordinates":[-122.27126800000001,37.851452],"type":"Point"}
}