{
  "type": "Feature",
  "properties": {
    "iso:country":"US",
    "sg:address":"801 Miller St",
    "sg:city":"Bakersfield",
    "sg:classifiers":[
        {
            "category":"Wholesale",
            "subcategory":"Hardware",
            "type":"Manufacturing & Wholesale Goods"
        }
    ],
    "sg:phone":"+1 661 861 9095",
    "sg:postcode":"93305",
    "sg:province":"CA",
    "sg:tags":[
        "plumbing",
        "fixture",
        "supply"
    ],
    "sg:website":"www.slakeybrothers.com",
    "wof:name":"Slakey Brothers Inc",
    "wof:placetype":"venue"
},
  "geometry": {"coordinates":[-118.983605,35.374687],"type":"Point"}
}