{
  "type": "Feature",
  "properties": {
    "iso:country":"US",
    "sg:address":"2419 Pearl St",
    "sg:city":"Santa Monica",
    "sg:classifiers":[
        {
            "category":"Freight",
            "type":"Transportation"
        }
    ],
    "sg:phone":"+1 310 450 7061",
    "sg:postcode":"90405",
    "sg:province":"CA",
    "sg:tags":[
        "operator",
        "trucking"
    ],
    "wof:name":"Gail Marie Trucking",
    "wof:placetype":"venue"
},
  "geometry": {"coordinates":[-118.46136199999999,34.020023],"type":"Point"}
}