{
  "type": "Feature",
  "properties": {
    "iso:country":"US",
    "sg:address":"158 E Blithedale Ave",
    "sg:city":"Mill Valley",
    "sg:classifiers":[
        {
            "category":"Personal",
            "type":"Services"
        }
    ],
    "sg:phone":"+1 415 381 3457",
    "sg:postcode":"94941",
    "sg:province":"CA",
    "sg:tags":[
        "therapist",
        "massage"
    ],
    "wof:name":"Lavenne Yves Orthopedic Massag",
    "wof:placetype":"venue"
},
  "geometry": {"coordinates":[-122.543739,37.905036],"type":"Point"}
}