{
  "type": "Feature",
  "properties": {
    "addr:full":"528 W Leadora Ave Glendora CA 91741",
    "addr:housenumber":"528",
    "addr:postcode":"91741",
    "addr:street":"W Leadora Ave",
    "iso:country":"US",
    "sg:address":"528 W Leadora Ave",
    "sg:city":"Glendora",
    "sg:classifiers":[
        {
            "category":"Building & Trades",
            "subcategory":"Electrical",
            "type":"Services"
        }
    ],
    "sg:phone":"+1 626 963 4234",
    "sg:postcode":"91741",
    "sg:province":"CA",
    "sg:tags":[
        "industrial",
        "electrician",
        "contractors-commercial",
        "electric"
    ],
    "wof:name":"Myers' Electric Co",
    "wof:placetype":"venue"
},
  "geometry": {"coordinates":[-117.873214,34.143312],"type":"Point"}
}