{
  "type": "Feature",
  "properties": {
    "addr:full":"2120 S el Camino Real San Clemente CA 92672",
    "addr:housenumber":"2120",
    "addr:postcode":"92672",
    "addr:street":"S El Camino Real",
    "iso:country":"US",
    "sg:address":"2120 S el Camino Real",
    "sg:city":"San Clemente",
    "sg:classifiers":[
        {
            "category":"Shopping",
            "subcategory":"Used Merchandise",
            "type":"Retail Goods"
        }
    ],
    "sg:phone":"+1 949 366 0473",
    "sg:postcode":"92672",
    "sg:province":"CA",
    "wof:name":"Hard Times Clothing",
    "wof:placetype":"venue"
},
  "geometry": {"coordinates":[-117.601304,33.415831],"type":"Point"}
}