{
  "type": "Feature",
  "properties": {
    "addr:full":"8784 19th St Alta Loma CA 91701",
    "addr:housenumber":"8784",
    "addr:postcode":"91701",
    "addr:street":"19Th St",
    "iso:country":"US",
    "sg:address":"8784 19th St",
    "sg:city":"Alta Loma",
    "sg:classifiers":[
        {
            "category":"Shopping",
            "type":"Retail Goods"
        }
    ],
    "sg:phone":"+1 909 948 1226",
    "sg:postcode":"91701",
    "sg:province":"CA",
    "sg:tags":[
        "telephone",
        "cellular"
    ],
    "wof:name":"Celltech",
    "wof:placetype":"venue"
},
  "geometry": {"coordinates":[-117.61531600000001,34.132698],"type":"Point"}
}