{
  "type": "Feature",
  "properties": {
    "addr:full":"3431 Portola Dr Santa Cruz CA 95062",
    "addr:housenumber":"3431",
    "addr:postcode":"95062",
    "addr:street":"Portola Dr",
    "iso:country":"US",
    "sg:address":"3431 Portola Dr",
    "sg:city":"Santa Cruz",
    "sg:classifiers":[
        {
            "category":"Shopping",
            "subcategory":"Florist",
            "type":"Retail Goods"
        }
    ],
    "sg:phone":"+1 831 465 9096",
    "sg:postcode":"95062",
    "sg:province":"CA",
    "wof:name":"Pleasure Point Flowers",
    "wof:placetype":"venue"
},
  "geometry": {"coordinates":[-121.971001,36.9636],"type":"Point"}
}