{
  "type": "Feature",
  "properties": {
    "iso:country":"US",
    "sg:address":"2834 Carma Ct",
    "sg:city":"Riverside",
    "sg:classifiers":[
        {
            "category":"Banks & Credit Unions",
            "subcategory":"Investment Brokerage",
            "type":"Services"
        }
    ],
    "sg:phone":"+1 951 359 4346",
    "sg:postcode":"92503",
    "sg:province":"CA",
    "sg:tags":[
        "advisory",
        "financial"
    ],
    "wof:name":"Millennium Co",
    "wof:placetype":"venue"
},
  "geometry": {"coordinates":[-117.425276,33.912842],"type":"Point"}
}