{
  "type": "Feature",
  "properties": {
    "addr:full":"2056 Pacific Ave Long Beach CA 90806",
    "addr:housenumber":"2056",
    "addr:postcode":"90806",
    "addr:street":"Pacific Ave",
    "iso:country":"US",
    "sg:address":"2056 Pacific Ave",
    "sg:city":"Long Beach",
    "sg:classifiers":[
        {
            "category":"Shopping",
            "subcategory":"Clothing, Apparel, & Fashions",
            "type":"Retail Goods"
        }
    ],
    "sg:phone":"+1 562 218 1182",
    "sg:postcode":"90806",
    "sg:province":"CA",
    "sg:tags":[
        "children's",
        "clothing"
    ],
    "wof:name":"Kids & Discount Outlet",
    "wof:placetype":"venue"
},
  "geometry": {"coordinates":[-118.194,33.794498],"type":"Point"}
}