{
  "type": "Feature",
  "properties": {
    "iso:country":"US",
    "sg:address":"40 Philadelphia Dr",
    "sg:city":"Paradise",
    "sg:classifiers":[
        {
            "category":"Health Services",
            "subcategory":"Clinic",
            "type":"Services"
        }
    ],
    "sg:phone":"+1 530 877 3746",
    "sg:postcode":"95973",
    "sg:province":"CA",
    "wof:name":"Edson Kathryn Health Insurance",
    "wof:placetype":"venue"
},
  "geometry": {"coordinates":[-121.875236,39.771958],"type":"Point"}
}