{
  "type": "Feature",
  "properties": {
    "iso:country":"US",
    "sg:address":"6107 Freeport Blvd",
    "sg:city":"Sacramento",
    "sg:classifiers":[
        {
            "category":"Real Estate",
            "subcategory":"Developer",
            "type":"Services"
        }
    ],
    "sg:phone":"+1 916 424 9695",
    "sg:postcode":"95822",
    "sg:province":"CA",
    "sg:tags":[
        "helicopter",
        "charter",
        "rental"
    ],
    "wof:name":"Sacramento Executive Helicopters Inc",
    "wof:placetype":"venue"
},
  "geometry": {"coordinates":[-121.498794,38.51365],"type":"Point"}
}