{
  "type": "Feature",
  "properties": {
    "addr:full":"1726 Costa Ave San Pablo CA 94806",
    "addr:housenumber":"1726",
    "addr:postcode":"94806",
    "addr:street":"Costa Ave",
    "iso:country":"US",
    "sg:address":"1726 Costa Ave",
    "sg:city":"San Pablo",
    "sg:classifiers":[
        {
            "category":"Personal",
            "subcategory":"Beauty Salon",
            "type":"Services"
        }
    ],
    "sg:phone":"+1 510 235 5560",
    "sg:postcode":"94806",
    "sg:province":"CA",
    "wof:name":"For All Beauty",
    "wof:placetype":"venue"
},
  "geometry": {"coordinates":[-122.352512,37.950246],"type":"Point"}
}