{
  "type": "Feature",
  "properties": {
    "addr:full":"1237 Jacklin Rd Milpitas CA 95035",
    "addr:housenumber":"1237",
    "addr:postcode":"95035",
    "addr:street":"Jacklin Rd",
    "iso:country":"US",
    "sg:address":"1237 Jacklin Rd",
    "sg:city":"Milpitas",
    "sg:classifiers":[
        {
            "category":"Shopping",
            "subcategory":"Music",
            "type":"Retail Goods"
        },
        {
            "category":"Cinema",
            "subcategory":"Movie Rental",
            "type":"Entertainment"
        }
    ],
    "sg:phone":"+1 408 946 9778",
    "sg:postcode":"95035",
    "sg:province":"CA",
    "sg:tags":[
        "video",
        "disc",
        "tape",
        "cassette"
    ],
    "wof:name":"People's Video",
    "wof:placetype":"venue"
},
  "geometry": {"coordinates":[-121.88916500000001,37.447393],"type":"Point"}
}