{
  "type": "Feature",
  "properties": {
    "iso:country":"US",
    "sg:address":"3400 S Sepulveda Boulevard",
    "sg:city":"Los Angeles",
    "sg:classifiers":[
        {
            "category":"Shopping",
            "subcategory":"Department Store",
            "type":"Retail Goods"
        }
    ],
    "sg:phone":"+1 310 546 5525",
    "sg:postcode":"90034",
    "sg:province":"CA",
    "wof:name":"MacY's",
    "wof:placetype":"venue"
},
  "geometry": {"coordinates":[-118.423241,34.020401],"type":"Point"}
}