{
  "type": "Feature",
  "properties": {
    "iso:country":"US",
    "sg:address":"8541 Jasmine Crest Ct",
    "sg:city":"Elk Grove",
    "sg:classifiers":[
        {
            "category":"Manufacturing",
            "subcategory":"Textiles",
            "type":"Manufacturing & Wholesale Goods"
        }
    ],
    "sg:phone":"+1 916 685 4031",
    "sg:postcode":"95624",
    "sg:province":"CA",
    "sg:tags":[
        "mill",
        "fabric"
    ],
    "wof:name":"Rocky Beckner",
    "wof:placetype":"venue"
},
  "geometry": {"coordinates":[-121.387979,38.418707],"type":"Point"}
}