{
  "type": "Feature",
  "properties": {
    "addr:full":"5720 Stoneridge Mall Rd Pleasanton CA 94588",
    "addr:housenumber":"5720",
    "addr:postcode":"94588",
    "addr:street":"Stoneridge Mall Rd",
    "iso:country":"US",
    "sg:address":"5720 Stoneridge Mall Rd",
    "sg:city":"Pleasanton",
    "sg:classifiers":[
        {
            "category":"Health Services",
            "subcategory":"Doctor",
            "type":"Services"
        }
    ],
    "sg:phone":"+1 925 847 5229",
    "sg:postcode":"94588",
    "sg:province":"CA",
    "sg:tags":[
        "physician",
        "surgeon"
    ],
    "wof:name":"Kaiser Permanente Medical Ctr",
    "wof:placetype":"venue"
},
  "geometry": {"coordinates":[-121.93131200000001,37.693476],"type":"Point"}
}