{
  "type": "Feature",
  "properties": {
    "addr:full":"1324 Putnam St Antioch CA 94509",
    "addr:housenumber":"1324",
    "addr:postcode":"ca 94509",
    "addr:street":"Putnam St",
    "iso:country":"US",
    "sg:address":"1324 Putnam St",
    "sg:city":"Antioch",
    "sg:classifiers":[
        {
            "category":"Social Services",
            "subcategory":"Child Care",
            "type":"Services"
        }
    ],
    "sg:phone":"+1 925 706 2403",
    "sg:postcode":"94509",
    "sg:province":"CA",
    "sg:tags":[
        "kindergarten",
        "academic",
        "school"
    ],
    "wof:name":"Sonshine Home Christian Prschl",
    "wof:placetype":"venue"
},
  "geometry": {"coordinates":[-121.829705,37.989688],"type":"Point"}
}