{
  "type": "Feature",
  "properties": {
    "addr:full":"211 N El Camino Real Encinitas CA 92024",
    "addr:housenumber":"211",
    "addr:postcode":"92024",
    "addr:street":"N El Camino Real",
    "iso:country":"US",
    "sg:address":"211 N El Camino Real",
    "sg:city":"Encinitas",
    "sg:classifiers":[
        {
            "category":"Home & Garden",
            "subcategory":"Carpets & Floor Coverings",
            "type":"Retail Goods"
        }
    ],
    "sg:phone":"+1 760 634 3640",
    "sg:postcode":"92024",
    "sg:province":"CA",
    "sg:tags":[
        "mattress"
    ],
    "wof:name":"Mattress Discounters",
    "wof:placetype":"venue"
},
  "geometry": {"coordinates":[-117.260002,33.050098],"type":"Point"}
}