{
  "type": "Feature",
  "properties": {
    "iso:country":"US",
    "sg:address":"San Francisco Airport",
    "sg:city":"San Francisco",
    "sg:classifiers":[
        {
            "category":"Shopping",
            "subcategory":"Luggage & Leather Goods",
            "type":"Retail Goods"
        }
    ],
    "sg:phone":"+1 650 821 1030",
    "sg:postcode":"94128",
    "sg:province":"CA",
    "sg:website":"www.rdgtravel.com",
    "wof:name":"Pacific Outfitters",
    "wof:placetype":"venue"
},
  "geometry": {"coordinates":[-122.389979,37.615223],"type":"Point"}
}