{
  "type": "Feature",
  "properties": {
    "iso:country":"US",
    "sg:address":"4909 Date Avenue",
    "sg:city":"Sacramento",
    "sg:classifiers":[
        {
            "category":"Real Estate",
            "subcategory":"Real Estate Operator",
            "type":"Services"
        }
    ],
    "sg:phone":"+1 916 344 4877",
    "sg:postcode":"95841",
    "sg:province":"CA",
    "sg:tags":[
        "apartment"
    ],
    "wof:name":"Date Tree Apartments",
    "wof:placetype":"venue"
},
  "geometry": {"coordinates":[-121.355198,38.654099],"type":"Point"}
}