{
  "type": "Feature",
  "properties": {
    "iso:country":"US",
    "sg:address":"3550 Santoro Rd",
    "sg:city":"San Diego",
    "sg:classifiers":[
        {
            "category":"Shopping",
            "subcategory":"Bicycles & Sporting Goods",
            "type":"Retail Goods"
        }
    ],
    "sg:phone":"+1 858 509 1242",
    "sg:postcode":"92130",
    "sg:province":"CA",
    "sg:tags":[
        "tackle",
        "fishing"
    ],
    "wof:name":"Executive Tackle",
    "wof:placetype":"venue"
},
  "geometry": {"coordinates":[-117.239418,32.957849],"type":"Point"}
}