{
  "type": "Feature",
  "properties": {
    "iso:country":"US",
    "sg:address":"8322 Beverly Blvd",
    "sg:city":"Los Angeles",
    "sg:classifiers":[
        {
            "category":"Professional",
            "subcategory":"Management & Consulting",
            "type":"Services"
        }
    ],
    "sg:phone":"+1 323 651 0889",
    "sg:postcode":"90048",
    "sg:province":"CA",
    "sg:tags":[
        "fuel"
    ],
    "wof:name":"Mark Holder Management",
    "wof:placetype":"venue"
},
  "geometry": {"coordinates":[-118.370377,34.075991],"type":"Point"}
}