{
  "type": "Feature",
  "properties": {
    "addr:full":"859 California Drive Burlingame CA 94010",
    "addr:housenumber":"859",
    "addr:postcode":"94010",
    "addr:street":"California Drive",
    "iso:country":"US",
    "sg:address":"859 California Drive",
    "sg:city":"Burlingame",
    "sg:classifiers":[
        {
            "category":"Shopping",
            "subcategory":"Florist",
            "type":"Retail Goods"
        }
    ],
    "sg:phone":"+1 650 347 6865",
    "sg:postcode":"94010",
    "sg:province":"CA",
    "wof:name":"Flower Boutique",
    "wof:placetype":"venue"
},
  "geometry": {"coordinates":[-122.355678,37.584088],"type":"Point"}
}