{
  "type": "Feature",
  "properties": {
    "addr:full":"1031 Bradshawe Ave Monterey Park CA 91754",
    "addr:housenumber":"1031",
    "addr:postcode":"91754",
    "addr:street":"Bradshawe Ave",
    "iso:country":"US",
    "sg:address":"1031 Bradshawe Ave",
    "sg:city":"Monterey Park",
    "sg:classifiers":[
        {
            "category":"Building & Trades",
            "subcategory":"Construction",
            "type":"Services"
        }
    ],
    "sg:phone":"+1 626 307 7323",
    "sg:postcode":"91754",
    "sg:province":"CA",
    "sg:tags":[
        "contractor"
    ],
    "wof:name":"Action Prof Design & Cnstr",
    "wof:placetype":"venue"
},
  "geometry": {"coordinates":[-118.134979,34.047831],"type":"Point"}
}