{
  "type": "Feature",
  "properties": {
    "iso:country":"US",
    "sg:address":"1031 Bradshawe Ave",
    "sg:city":"Monterey Park",
    "sg:classifiers":[
        {
            "category":"Building & Trades",
            "subcategory":"Construction",
            "type":"Services"
        }
    ],
    "sg:phone":"+1 626 307 7323",
    "sg:postcode":"91754",
    "sg:province":"CA",
    "sg:tags":[
        "contractor"
    ],
    "wof:name":"Action Prof Design & Cnstr",
    "wof:placetype":"venue"
},
  "geometry": {"coordinates":[-118.134979,34.047831],"type":"Point"}
}