{
  "type": "Feature",
  "properties": {
    "addr:full":"5409 Central Ave Ste 12 Newark CA 94560",
    "addr:housenumber":"5409;12",
    "addr:postcode":"94560",
    "addr:street":"Central Ave Ste",
    "iso:country":"US",
    "sg:address":"5409 Central Ave Ste 12",
    "sg:city":"Newark",
    "sg:classifiers":[
        {
            "category":"Food & Beverages",
            "subcategory":"Groceries & Convenience Stores",
            "type":"Retail Goods"
        }
    ],
    "sg:phone":"+1 510 713 9234",
    "sg:postcode":"94560",
    "sg:province":"CA",
    "wof:name":"Central Liquor & Food Inc",
    "wof:placetype":"venue"
},
  "geometry": {"coordinates":[-122.01733400000001,37.539268],"type":"Point"}
}