{
  "type": "Feature",
  "properties": {
    "addr:full":"6150 Quail Valley Ct Riverside CA 92507",
    "addr:housenumber":"6150",
    "addr:postcode":"92507",
    "addr:street":"Quail Valley Ct",
    "iso:country":"US",
    "sg:address":"6150 Quail Valley Ct",
    "sg:city":"Riverside",
    "sg:classifiers":[
        {
            "category":"Building & Trades",
            "subcategory":"Construction",
            "type":"Services"
        }
    ],
    "sg:phone":"+1 951 656 7500",
    "sg:postcode":"92507",
    "sg:province":"CA",
    "sg:tags":[
        "contractor"
    ],
    "wof:name":"D & M Builders",
    "wof:placetype":"venue"
},
  "geometry": {"coordinates":[-117.295162,33.940247],"type":"Point"}
}