{
  "type": "Feature",
  "properties": {
    "iso:country":"US",
    "sg:address":"4305 Bannister Rd.",
    "sg:city":"Fair Oaks",
    "sg:classifiers":[
        {
            "category":"Education",
            "subcategory":"Preschool",
            "type":"Public Place"
        }
    ],
    "sg:phone":"+1 916 844 0016",
    "sg:postcode":"95628",
    "sg:province":"CA",
    "sg:website":"www.lotuschildmontessori.com",
    "wof:name":"Lotus Child Montessori",
    "wof:placetype":"venue"
},
  "geometry": {"coordinates":[-121.287808,38.642831],"type":"Point"}
}