{
  "type": "Feature",
  "properties": {
    "iso:country":"US",
    "sg:address":"3420 W Lincoln Ave",
    "sg:city":"Anaheim",
    "sg:classifiers":[
        {
            "category":"Shopping",
            "subcategory":"Department Store",
            "type":"Retail Goods"
        }
    ],
    "sg:phone":"+1 714 995 3999",
    "sg:postcode":"92801",
    "sg:province":"CA",
    "sg:tags":[
        "shop"
    ],
    "wof:name":"99 Cents Only",
    "wof:placetype":"venue"
},
  "geometry": {"coordinates":[-118.009604,33.831835],"type":"Point"}
}