{
  "type": "Feature",
  "properties": {
    "addr:full":"2386 Mountain View Dr Concord CA 94520",
    "addr:housenumber":"2386",
    "addr:postcode":"94520",
    "addr:street":"Mountain View Dr",
    "iso:country":"US",
    "sg:address":"2386 Mountain View Dr",
    "sg:city":"Concord",
    "sg:classifiers":[
        {
            "category":"Building & Trades",
            "subcategory":"Construction",
            "type":"Services"
        }
    ],
    "sg:phone":"+1 925 687 4601",
    "sg:postcode":"94520",
    "sg:province":"CA",
    "sg:tags":[
        "painter"
    ],
    "wof:name":"Painless Painting",
    "wof:placetype":"venue"
},
  "geometry": {"coordinates":[-122.036389,37.987757],"type":"Point"}
}