{
  "type": "Feature",
  "properties": {
    "addr:full":"1645 Saratoga Ave San Jose CA 95129",
    "addr:housenumber":"1645",
    "addr:postcode":"95129",
    "addr:street":"Saratoga Ave",
    "iso:country":"US",
    "sg:address":"1645 Saratoga Ave",
    "sg:city":"San Jose",
    "sg:classifiers":[
        {
            "category":"Ice Cream",
            "type":"Food & Drink"
        }
    ],
    "sg:phone":"+1 408 725 9120",
    "sg:postcode":"95129",
    "sg:province":"CA",
    "sg:tags":[
        "frozen",
        "yogurt"
    ],
    "sg:website":"www.pinkberry.com",
    "wof:name":"Pinkberry",
    "wof:placetype":"venue"
},
  "geometry": {"coordinates":[-121.99074400000001,37.292972],"type":"Point"}
}