{
  "type": "Feature",
  "properties": {
    "iso:country":"US",
    "sg:address":"1530 Chapala St",
    "sg:city":"Santa Barbara",
    "sg:classifiers":[
        {
            "category":"Professional",
            "subcategory":"Lawyer & Legal Services",
            "type":"Services"
        }
    ],
    "sg:phone":"+1 805 966 3434",
    "sg:postcode":"93101",
    "sg:province":"CA",
    "sg:tags":[
        "attorney"
    ],
    "wof:name":"Kenneth E Falstrom Law Offices",
    "wof:placetype":"venue"
},
  "geometry": {"coordinates":[-119.710333,34.42579],"type":"Point"}
}