{
  "type": "Feature",
  "properties": {
    "iso:country":"US",
    "sg:address":"1401 S Victoria Ave",
    "sg:city":"Ventura",
    "sg:classifiers":[
        {
            "category":"Restaurant",
            "type":"Food & Drink"
        }
    ],
    "sg:menulink":"http://www.allmenus.com/ca/ventura/174578-wendys/menu/",
    "sg:phone":"+1 805 642 8790",
    "sg:postcode":"93003",
    "sg:province":"CA",
    "sg:tags":[
        "burger",
        "american",
        "soup"
    ],
    "wof:name":"Wendy's",
    "wof:placetype":"venue"
},
  "geometry": {"coordinates":[-119.212772,34.261685],"type":"Point"}
}