{
  "type": "Feature",
  "properties": {
    "addr:full":"3690 33rd Ave Sacramento CA 95824",
    "addr:housenumber":"3690",
    "addr:postcode":"95824",
    "addr:street":"33Rd Ave",
    "iso:country":"US",
    "sg:address":"3690 33rd Ave",
    "sg:city":"Sacramento",
    "sg:classifiers":[
        {
            "category":"Building & Trades",
            "subcategory":"Construction",
            "type":"Services"
        }
    ],
    "sg:phone":"+1 916 427 3702",
    "sg:postcode":"95824",
    "sg:province":"CA",
    "sg:tags":[
        "concrete",
        "staining",
        "contractor"
    ],
    "wof:name":"S & K Concrete Inc.",
    "wof:placetype":"venue"
},
  "geometry": {"coordinates":[-121.46712599999999,38.522506],"type":"Point"}
}