{
  "type": "Feature",
  "properties": {
    "addr:full":"230 S California Ave Palo Alto CA 94306",
    "addr:housenumber":"230",
    "addr:postcode":"94306",
    "addr:street":"S California Ave",
    "iso:country":"US",
    "sg:address":"230 S California Ave",
    "sg:city":"Palo Alto",
    "sg:classifiers":[
        {
            "category":"Banks & Credit Unions",
            "subcategory":"Financial Services",
            "type":"Services"
        }
    ],
    "sg:phone":"+1 650 327 8780",
    "sg:postcode":"94306",
    "sg:province":"CA",
    "sg:tags":[
        "international",
        "trade"
    ],
    "sg:website":"www.rikinternational.com",
    "wof:name":"Rik Intl Ind Trade",
    "wof:placetype":"venue"
},
  "geometry": {"coordinates":[-122.14377500000001,37.427743],"type":"Point"}
}