{
  "type": "Feature",
  "properties": {
    "addr:full":"330 W Pico Blvd Los Angeles CA 90015",
    "addr:housenumber":"330",
    "addr:postcode":"90015",
    "addr:street":"W Pico Blvd",
    "iso:country":"US",
    "sg:address":"330 W Pico Blvd",
    "sg:city":"Los Angeles",
    "sg:phone":"+1 213 747 2668",
    "sg:postcode":"90015",
    "sg:province":"CA",
    "sg:tags":[
        "fixture",
        "mannequin"
    ],
    "wof:name":"Full Mannequin Co",
    "wof:placetype":"venue"
},
  "geometry": {"coordinates":[-118.264321,34.038808],"type":"Point"}
}