{
  "type": "Feature",
  "properties": {
    "iso:country":"US",
    "sg:address":"1880 Santa Barbara St",
    "sg:city":"San Luis Obispo",
    "sg:classifiers":[
        {
            "category":"Insurance",
            "subcategory":"Insurance Agent",
            "type":"Services"
        }
    ],
    "sg:phone":"+1 805 544 5311",
    "sg:postcode":"93401",
    "sg:province":"CA",
    "wof:name":"Colonial Supplemental Ins",
    "wof:placetype":"venue"
},
  "geometry": {"coordinates":[-120.656147,35.274621],"type":"Point"}
}