{
  "type": "Feature",
  "properties": {
    "addr:full":"881 W Lambert Rd La Habra CA 90631",
    "addr:housenumber":"881",
    "addr:postcode":"90631",
    "addr:street":"W Lambert Rd",
    "iso:country":"US",
    "sg:address":"881 W Lambert Rd",
    "sg:city":"La Habra",
    "sg:classifiers":[
        {
            "category":"Retail",
            "subcategory":"Auto Repair",
            "type":"Services"
        }
    ],
    "sg:phone":"+1 562 690 4582",
    "sg:postcode":"90631",
    "sg:province":"CA",
    "sg:tags":[
        "automobile",
        "restoration",
        "classic"
    ],
    "wof:name":"Retro Rods",
    "wof:placetype":"venue"
},
  "geometry": {"coordinates":[-117.95683,33.924658],"type":"Point"}
}