{
  "type": "Feature",
  "properties": {
    "iso:country":"US",
    "sg:address":"299 N Euclid Ave Ste 100",
    "sg:city":"Pasadena",
    "sg:classifiers":[
        {
            "category":"Education",
            "subcategory":"University",
            "type":"Public Place"
        }
    ],
    "sg:phone":"+1 626 793 9661",
    "sg:postcode":"91101",
    "sg:province":"CA",
    "sg:tags":[
        "college"
    ],
    "wof:name":"University of Phoenix Pasadena",
    "wof:placetype":"venue"
},
  "geometry": {"coordinates":[-118.142998,34.150501],"type":"Point"}
}