{
  "type": "Feature",
  "properties": {
    "iso:country":"US",
    "sg:address":"1292 N Main St",
    "sg:city":"Salinas",
    "sg:classifiers":[
        {
            "category":"Food & Beverages",
            "subcategory":"Bakery",
            "type":"Retail Goods"
        }
    ],
    "sg:phone":"+1 831 449 3354",
    "sg:postcode":"93906",
    "sg:province":"CA",
    "sg:tags":[
        "baker",
        "restaurant"
    ],
    "wof:name":"Cake Express",
    "wof:placetype":"venue"
},
  "geometry": {"coordinates":[-121.65224000000001,36.701436],"type":"Point"}
}