{
  "type": "Feature",
  "properties": {
    "iso:country":"US",
    "sg:address":"13845 Alton Pkwy",
    "sg:city":"Irvine",
    "sg:classifiers":[
        {
            "category":"Professional",
            "subcategory":"Business Services",
            "type":"Services"
        }
    ],
    "sg:phone":"+1 949 457 2300",
    "sg:postcode":"92618",
    "sg:province":"CA",
    "sg:tags":[
        "specialty",
        "mfg"
    ],
    "wof:name":"Graffiti Signs & Graphics",
    "wof:placetype":"venue"
},
  "geometry": {"coordinates":[-117.708819,33.662236],"type":"Point"}
}