{
  "type": "Feature",
  "properties": {
    "addr:full":"3080 Landess Ave San Jose CA 95132",
    "addr:housenumber":"3080",
    "addr:postcode":"95132",
    "addr:street":"Landess Ave",
    "iso:country":"US",
    "sg:address":"3080 Landess Ave",
    "sg:city":"San Jose",
    "sg:classifiers":[
        {
            "category":"Restaurant",
            "type":"Food & Drink"
        }
    ],
    "sg:phone":"+1 408 946 5888",
    "sg:postcode":"95132",
    "sg:province":"CA",
    "wof:name":"My Chinese Restaurant",
    "wof:placetype":"venue"
},
  "geometry": {"coordinates":[-121.877636,37.415262],"type":"Point"}
}