{
  "type": "Feature",
  "properties": {
    "iso:country":"US",
    "sg:address":"2424 W Ball Rd Ste E",
    "sg:city":"Anaheim",
    "sg:classifiers":[
        {
            "category":"Manufacturing",
            "subcategory":"Soap",
            "type":"Manufacturing & Wholesale Goods"
        }
    ],
    "sg:phone":"+1 714 236 9811",
    "sg:postcode":"92804",
    "sg:province":"CA",
    "sg:tags":[
        "perfume-wholesale",
        "manufacturer"
    ],
    "wof:name":"Perfumes Ilusion",
    "wof:placetype":"venue"
},
  "geometry": {"coordinates":[-117.969122,33.817666],"type":"Point"}
}