{
  "type": "Feature",
  "properties": {
    "addr:full":"1313 S Brand Blvd Glendale CA 91204",
    "addr:housenumber":"1313",
    "addr:postcode":"91204",
    "addr:street":"S Brand Blvd",
    "iso:country":"US",
    "sg:address":"1313 S Brand Blvd",
    "sg:city":"Glendale",
    "sg:classifiers":[
        {
            "category":"Retail",
            "subcategory":"Auto Rental",
            "type":"Services"
        }
    ],
    "sg:phone":"+1 818 242 4235",
    "sg:postcode":"91204",
    "sg:province":"CA",
    "sg:tags":[
        "truck",
        "trailer",
        "liquid",
        "utility"
    ],
    "wof:name":"U-Haul",
    "wof:placetype":"venue"
},
  "geometry": {"coordinates":[-118.255027,34.128829],"type":"Point"}
}