{
  "type": "Feature",
  "properties": {
    "addr:full":"7660 Beverly Blvd Los Angeles CA 90036",
    "addr:housenumber":"7660",
    "addr:postcode":"90036",
    "addr:street":"Beverly Blvd",
    "iso:country":"US",
    "sg:address":"7660 Beverly Blvd",
    "sg:city":"Los Angeles",
    "sg:classifiers":[
        {
            "category":"Food & Beverages",
            "subcategory":"Specialty",
            "type":"Retail Goods"
        }
    ],
    "sg:phone":"+1 323 931 4139",
    "sg:postcode":"90036",
    "sg:province":"CA",
    "sg:tags":[
        "herb"
    ],
    "wof:name":"Dragon Herbs",
    "wof:placetype":"venue"
},
  "geometry": {"coordinates":[-118.35735099999999,34.076122],"type":"Point"}
}