{
  "type": "Feature",
  "properties": {
    "iso:country":"US",
    "sg:address":"7660 Beverly Blvd",
    "sg:city":"Los Angeles",
    "sg:classifiers":[
        {
            "category":"Food & Beverages",
            "subcategory":"Specialty",
            "type":"Retail Goods"
        }
    ],
    "sg:phone":"+1 323 931 4139",
    "sg:postcode":"90036",
    "sg:province":"CA",
    "sg:tags":[
        "herb"
    ],
    "wof:name":"Dragon Herbs",
    "wof:placetype":"venue"
},
  "geometry": {"coordinates":[-118.357351,34.076122],"type":"Point"}
}