{
  "type": "Feature",
  "properties": {
    "addr:full":"9575 Las Tunas Dr Temple City CA 91780",
    "addr:housenumber":"9575",
    "addr:postcode":"91780",
    "addr:street":"Las Tunas Dr",
    "iso:country":"US",
    "sg:address":"9575 Las Tunas Dr",
    "sg:city":"Temple City",
    "sg:classifiers":[
        {
            "category":"Personal",
            "subcategory":"Beauty Salon",
            "type":"Services"
        }
    ],
    "sg:phone":"+1 626 614 8140",
    "sg:postcode":"91780",
    "sg:province":"CA",
    "sg:tags":[
        "manicuring"
    ],
    "wof:name":"Kerri Womack",
    "wof:placetype":"venue"
},
  "geometry": {"coordinates":[-118.061582,34.106661],"type":"Point"}
}