{
  "type": "Feature",
  "properties": {
    "addr:full":"5333 Mission Center Rd Ste 356 San Diego CA 92108",
    "addr:housenumber":"5333",
    "addr:postcode":"92108",
    "addr:street":"Mission Center Rd Ste 356",
    "iso:country":"US",
    "sg:address":"5333 Mission Center Rd Ste 356",
    "sg:city":"San Diego",
    "sg:classifiers":[
        {
            "category":"Professional",
            "subcategory":"Employment Agencies",
            "type":"Services"
        }
    ],
    "sg:phone":"+1 619 299 9159",
    "sg:postcode":"92108",
    "sg:province":"CA",
    "wof:name":"Intelistaf Healthcare",
    "wof:placetype":"venue"
},
  "geometry": {"coordinates":[-117.154703,32.771106],"type":"Point"}
}