{
  "type": "Feature",
  "properties": {
    "iso:country":"US",
    "sg:address":"118 1st St",
    "sg:city":"Watsonville",
    "sg:classifiers":[
        {
            "category":"Organizations",
            "subcategory":"Religious Organization",
            "type":"Services"
        }
    ],
    "sg:phone":"+1 831 724 6222",
    "sg:postcode":"95076",
    "sg:province":"CA",
    "sg:tags":[
        "churches-presbyterian-usa",
        "church"
    ],
    "wof:name":"Westview Presbyterian Church",
    "wof:placetype":"venue"
},
  "geometry": {"coordinates":[-121.75585,36.906379],"type":"Point"}
}