{
  "type": "Feature",
  "properties": {
    "iso:country":"US",
    "sg:address":"320 Santa Fe Dr Ste 108",
    "sg:city":"Encinitas",
    "sg:classifiers":[
        {
            "category":"Health Services",
            "subcategory":"Doctor",
            "type":"Services"
        }
    ],
    "sg:phone":"+1 760 942 1390",
    "sg:postcode":"92024",
    "sg:province":"CA",
    "wof:name":"Rosenberg Jay MD",
    "wof:placetype":"venue"
},
  "geometry": {"coordinates":[-117.28536,33.637079],"type":"Point"}
}