{
  "type": "Feature",
  "properties": {
    "addr:full":"1400 Appalachian Pl Chula Vista CA 91915",
    "addr:housenumber":"1400",
    "addr:postcode":"91915",
    "addr:street":"Appalachian Pl",
    "iso:country":"US",
    "sg:address":"1400 Appalachian Pl",
    "sg:city":"Chula Vista",
    "sg:classifiers":[
        {
            "category":"Wholesale",
            "subcategory":"Durable Goods & Equipment",
            "type":"Manufacturing & Wholesale Goods"
        }
    ],
    "sg:phone":"+1 619 421 2340",
    "sg:postcode":"91915",
    "sg:province":"CA",
    "sg:tags":[
        "importer"
    ],
    "wof:name":"Ivy International",
    "wof:placetype":"venue"
},
  "geometry": {"coordinates":[-116.94896799999999,32.633516],"type":"Point"}
}