{
  "type": "Feature",
  "properties": {
    "iso:country":"US",
    "sg:address":"6134 Nancy Ridge Dr",
    "sg:city":"San Diego",
    "sg:classifiers":[
        {
            "category":"Utilities",
            "subcategory":"Telephone",
            "type":"Services"
        }
    ],
    "sg:phone":"+1 858 456 3551",
    "sg:postcode":"92121",
    "sg:province":"CA",
    "sg:tags":[
        "distance",
        "local",
        "telecommunication",
        "long"
    ],
    "wof:name":"UStelepacific Corp",
    "wof:placetype":"venue"
},
  "geometry": {"coordinates":[-117.184243,32.888209],"type":"Point"}
}