{
  "type": "Feature",
  "properties": {
    "iso:country":"US",
    "sg:address":"305 E Commercial St",
    "sg:city":"Willits",
    "sg:classifiers":[
        {
            "category":"Home & Garden",
            "subcategory":"Building Materials",
            "type":"Retail Goods"
        }
    ],
    "sg:phone":"+1 707 459 4631",
    "sg:postcode":"95490",
    "sg:province":"CA",
    "sg:website":"www.mendomill.com",
    "wof:name":"Mendo Mill & Lumber Co",
    "wof:placetype":"venue"
},
  "geometry": {"coordinates":[-123.34807,39.412479],"type":"Point"}
}