{
  "type": "Feature",
  "properties": {
    "iso:country":"US",
    "sg:address":"400 Chesapeake",
    "sg:city":"Redwood City",
    "sg:classifiers":[
        {
            "category":"Professional",
            "subcategory":"Research",
            "type":"Services"
        }
    ],
    "sg:phone":"+1 650 363 2400",
    "sg:postcode":"94063",
    "sg:province":"CA",
    "sg:website":"http://www.avinger.com",
    "wof:name":"Avinger",
    "wof:placetype":"venue"
},
  "geometry": {"coordinates":[-122.215084,37.502423],"type":"Point"}
}