{
  "type": "Feature",
  "properties": {
    "iso:country":"US",
    "sg:address":"12623 Centurian St",
    "sg:city":"White Water",
    "sg:classifiers":[
        {
            "category":"Building & Trades",
            "subcategory":"Construction",
            "type":"Services"
        }
    ],
    "sg:phone":"+1 760 322 0254",
    "sg:postcode":"92282",
    "sg:province":"CA",
    "sg:tags":[
        "concrete",
        "cutting",
        "breaking",
        "sawing"
    ],
    "wof:name":"Spartan Concrete & Asphalt",
    "wof:placetype":"venue"
},
  "geometry": {"coordinates":[-116.725392,33.934076],"type":"Point"}
}