{
  "type": "Feature",
  "properties": {
    "addr:full":"9999 Valley Ford Rd Petaluma CA 94952",
    "addr:housenumber":"9999",
    "addr:postcode":"94952",
    "addr:street":"Valley Ford Rd",
    "iso:country":"US",
    "sg:address":"9999 Valley Ford Rd",
    "sg:city":"Petaluma",
    "sg:classifiers":[
        {
            "category":"Farming",
            "subcategory":"Farm",
            "type":"Manufacturing & Wholesale Goods"
        }
    ],
    "sg:phone":"+1 707 763 0993",
    "sg:postcode":"94952",
    "sg:province":"CA",
    "sg:website":"http://www.bellwethercheese.com",
    "wof:name":"Bellwether Farms",
    "wof:placetype":"venue"
},
  "geometry": {"coordinates":[-122.828221,38.300237],"type":"Point"}
}