{
  "type": "Feature",
  "properties": {
    "addr:full":"5011 Alterra Way Sacramento CA 95835",
    "addr:postcode":"5011;95835",
    "addr:street":"Alterra Way",
    "iso:country":"US",
    "sg:address":"5011 Alterra Way",
    "sg:city":"Sacramento",
    "sg:classifiers":[
        {
            "category":"Insurance",
            "subcategory":"Insurance Agent",
            "type":"Services"
        }
    ],
    "sg:phone":"+1 916 928 1316",
    "sg:postcode":"95835",
    "sg:province":"CA",
    "wof:name":"Commerce West Insurance",
    "wof:placetype":"venue"
},
  "geometry": {"coordinates":[-121.493881,38.665053],"type":"Point"}
}