{
  "type": "Feature",
  "properties": {
    "addr:full":"1035 Underhills Rd Oakland CA 94610",
    "addr:housenumber":"1035",
    "addr:postcode":"94610",
    "addr:street":"Underhills Rd",
    "iso:country":"US",
    "sg:address":"1035 Underhills Rd",
    "sg:city":"Oakland",
    "sg:classifiers":[
        {
            "category":"Manufacturing",
            "subcategory":"Buildings",
            "type":"Manufacturing & Wholesale Goods"
        },
        {
            "category":"Building & Trades",
            "subcategory":"Construction",
            "type":"Services"
        }
    ],
    "sg:phone":"+1 510 485 2255",
    "sg:postcode":"94610",
    "sg:province":"CA",
    "sg:tags":[
        "home",
        "builder",
        "contractor"
    ],
    "wof:name":"Winzeler Construction",
    "wof:placetype":"venue"
},
  "geometry": {"coordinates":[-122.228163,37.809003],"type":"Point"}
}