{
  "type": "Feature",
  "properties": {
    "addr:full":"724 Grand Teton Way Chico CA 95973",
    "addr:housenumber":"724",
    "addr:postcode":"95973",
    "addr:street":"Grand Teton Way",
    "iso:country":"US",
    "sg:address":"724 Grand Teton Way",
    "sg:city":"Chico",
    "sg:classifiers":[
        {
            "category":"Professional",
            "type":"Services"
        }
    ],
    "sg:phone":"+1 530 894 7099",
    "sg:postcode":"95973",
    "sg:province":"CA",
    "wof:name":"Chicoans Agnst Substance Abuse",
    "wof:placetype":"venue"
},
  "geometry": {"coordinates":[-121.858923,39.7713],"type":"Point"}
}