{
  "type": "Feature",
  "properties": {
    "addr:full":"2157 W Manchester Avenue Los Angeles CA 90047",
    "addr:housenumber":"2157",
    "addr:postcode":"90047",
    "addr:street":"W Manchester Avenue",
    "iso:country":"US",
    "sg:address":"2157 W Manchester Avenue",
    "sg:city":"Los Angeles",
    "sg:classifiers":[
        {
            "category":"Retail",
            "subcategory":"Auto Repair",
            "type":"Services"
        }
    ],
    "sg:phone":"+1 213 752 3232",
    "sg:postcode":"90047",
    "sg:province":"CA",
    "sg:website":"LosAngelesCA.JiffyLube.com",
    "wof:name":"Jiffy Lube",
    "wof:placetype":"venue"
},
  "geometry": {"coordinates":[-118.317538,33.960274],"type":"Point"}
}