{
  "type": "Feature",
  "properties": {
    "addr:full":"2016 Jefferson St Napa CA 94559",
    "addr:housenumber":"2016",
    "addr:postcode":"94559",
    "addr:street":"Jefferson St",
    "iso:country":"US",
    "sg:address":"2016 Jefferson St",
    "sg:city":"Napa",
    "sg:classifiers":[
        {
            "category":"Health Services",
            "subcategory":"Doctor",
            "type":"Services"
        }
    ],
    "sg:phone":"+1 707 255 1172",
    "sg:postcode":"94559",
    "sg:province":"CA",
    "sg:tags":[
        "dentist"
    ],
    "wof:name":"Vineyard Dental",
    "wof:placetype":"venue"
},
  "geometry": {"coordinates":[-122.29490300000001,38.305828],"type":"Point"}
}