{
  "type": "Feature",
  "properties": {
    "iso:country":"US",
    "sg:address":"10552 Santana St",
    "sg:city":"Santee",
    "sg:classifiers":[
        {
            "category":"Shopping",
            "subcategory":"Hobbies, Toys, & Games",
            "type":"Retail Goods"
        }
    ],
    "sg:phone":"+1 619 258 5628",
    "sg:postcode":"92071",
    "sg:province":"CA",
    "wof:name":"Pats Passion",
    "wof:placetype":"venue"
},
  "geometry": {"coordinates":[-116.963201,32.867029],"type":"Point"}
}