{
  "type": "Feature",
  "properties": {
    "addr:full":"1280 Scott Blvd Santa Clara CA 95050",
    "addr:housenumber":"1280",
    "addr:postcode":"95050",
    "addr:street":"Scott Blvd",
    "iso:country":"US",
    "sg:address":"1280 Scott Blvd",
    "sg:city":"Santa Clara",
    "sg:classifiers":[
        {
            "category":"Professional",
            "subcategory":"Lawyer & Legal Services",
            "type":"Services"
        }
    ],
    "sg:phone":"+1 408 244 7853",
    "sg:postcode":"95050",
    "sg:province":"CA",
    "sg:tags":[
        "attorney"
    ],
    "wof:name":"Aryeh Korthamar",
    "wof:placetype":"venue"
},
  "geometry": {"coordinates":[-121.959391,37.348762],"type":"Point"}
}