{
  "type": "Feature",
  "properties": {
    "iso:country":"US",
    "sg:address":"3150 Central Expy",
    "sg:city":"Santa Clara",
    "sg:classifiers":[
        {
            "category":"Manufacturing",
            "subcategory":"Tools & Machinery",
            "type":"Manufacturing & Wholesale Goods"
        }
    ],
    "sg:phone":"+1 408 727 3240",
    "sg:postcode":"95051",
    "sg:province":"CA",
    "sg:tags":[
        "laser",
        "scientific",
        "mfg"
    ],
    "wof:name":"Continuum",
    "wof:placetype":"venue"
},
  "geometry": {"coordinates":[-121.986501,37.37766],"type":"Point"}
}