{
  "type": "Feature",
  "properties": {
    "addr:full":"308 Broad St Nevada City CA 95959",
    "addr:housenumber":"308",
    "addr:postcode":"95959",
    "addr:street":"Broad St",
    "iso:country":"US",
    "sg:address":"308 Broad St",
    "sg:city":"Nevada City",
    "sg:classifiers":[
        {
            "category":"Shopping",
            "subcategory":"Gifts & Souvenirs",
            "type":"Retail Goods"
        }
    ],
    "sg:phone":"+1 530 265 6478",
    "sg:postcode":"95959",
    "sg:province":"CA",
    "sg:tags":[
        "novelty",
        "jewelry",
        "accessory"
    ],
    "wof:name":"Golden Eagle",
    "wof:placetype":"venue"
},
  "geometry": {"coordinates":[-121.019791,39.262957],"type":"Point"}
}