{
  "type": "Feature",
  "properties": {
    "iso:country":"US",
    "sg:address":"4475 Seminole Way",
    "sg:city":"Pleasanton",
    "sg:classifiers":[
        {
            "category":"Wholesale",
            "subcategory":"Non-durable Goods",
            "type":"Manufacturing & Wholesale Goods"
        }
    ],
    "sg:phone":"+1 925 461 4904",
    "sg:postcode":"94588",
    "sg:province":"CA",
    "wof:name":"Gabbis Gifts",
    "wof:placetype":"venue"
},
  "geometry": {"coordinates":[-121.87945499999999,37.691642],"type":"Point"}
}