{
  "type": "Feature",
  "properties": {
    "addr:full":"6200 W Manchester Ave Los Angeles CA 90045",
    "addr:housenumber":"6200",
    "addr:postcode":"90045",
    "addr:street":"W Manchester Ave",
    "iso:country":"US",
    "sg:address":"6200 W Manchester Ave",
    "sg:city":"Los Angeles",
    "sg:classifiers":[
        {
            "category":"Food & Beverages",
            "subcategory":"Liquor & Beverages",
            "type":"Retail Goods"
        }
    ],
    "sg:phone":"+1 310 410 0333",
    "sg:postcode":"90045",
    "sg:province":"CA",
    "sg:tags":[
        "wine"
    ],
    "wof:name":"A & A Liquors",
    "wof:placetype":"venue"
},
  "geometry": {"coordinates":[-118.396213,33.959793],"type":"Point"}
}