{
  "type": "Feature",
  "properties": {
    "iso:country":"US",
    "sg:address":"717 N Shoreline Blvd",
    "sg:city":"Mountain View",
    "sg:classifiers":[
        {
            "category":"Communications",
            "type":"Services"
        }
    ],
    "sg:phone":"+1 650 605 0290",
    "sg:postcode":"94043",
    "sg:province":"CA",
    "sg:tags":[
        "web",
        "design"
    ],
    "sg:website":"www.onlinefocus.com",
    "wof:name":"Online Focus",
    "wof:placetype":"venue"
},
  "geometry": {"coordinates":[-122.078003,37.403702],"type":"Point"}
}