{
  "type": "Feature",
  "properties": {
    "addr:full":"3055 Wilshire Blvd Ste 510 Los Angeles CA 90010",
    "addr:housenumber":"3055",
    "addr:postcode":"90010",
    "addr:street":"Wilshire Blvd Ste 510",
    "iso:country":"US",
    "sg:address":"3055 Wilshire Blvd Ste 510",
    "sg:city":"Los Angeles",
    "sg:classifiers":[
        {
            "category":"Professional",
            "subcategory":"Lawyer & Legal Services",
            "type":"Services"
        }
    ],
    "sg:phone":"+1 213 487 8660",
    "sg:postcode":"90010",
    "sg:province":"CA",
    "wof:name":"AMCC INC",
    "wof:placetype":"venue"
},
  "geometry": {"coordinates":[-118.28810900000001,34.199713],"type":"Point"}
}