{
  "type": "Feature",
  "properties": {
    "addr:full":"2220 Cordelia Rd Fairfield CA 94534",
    "addr:housenumber":"2220",
    "addr:postcode":"94534",
    "addr:street":"Cordelia Rd",
    "iso:country":"US",
    "sg:address":"2220 Cordelia Rd",
    "sg:city":"Fairfield",
    "sg:classifiers":[
        {
            "category":"Professional",
            "subcategory":"Art Services",
            "type":"Services"
        },
        {
            "category":"Professional",
            "subcategory":"Business Services",
            "type":"Services"
        },
        {
            "category":"Shopping",
            "type":"Retail Goods"
        },
        {
            "category":"Retail",
            "subcategory":"Storage",
            "type":"Services"
        },
        {
            "category":"Shopping",
            "subcategory":"Used Merchandise",
            "type":"Retail Goods"
        }
    ],
    "sg:phone":"+1 707 425 7900",
    "sg:postcode":"94534",
    "sg:province":"CA",
    "sg:tags":[
        "designer",
        "merchandising",
        "producer",
        "household",
        "commercial",
        "importer",
        "display",
        "ribbon"
    ],
    "wof:name":"Lee Display West Inc.",
    "wof:placetype":"venue"
},
  "geometry": {"coordinates":[-122.065434,38.230602],"type":"Point"}
}