{
  "type": "Feature",
  "properties": {
    "iso:country":"US",
    "sg:address":"6171 W Century Blvd",
    "sg:city":"Los Angeles",
    "sg:classifiers":[
        {
            "category":"Professional",
            "subcategory":"Business Services",
            "type":"Services"
        }
    ],
    "sg:phone":"+1 310 337 3066",
    "sg:postcode":"90045",
    "sg:province":"CA",
    "sg:tags":[
        "information",
        "referral"
    ],
    "wof:name":"Strategic Information Svc",
    "wof:placetype":"venue"
},
  "geometry": {"coordinates":[-118.392084,33.945637],"type":"Point"}
}