{
  "type": "Feature",
  "properties": {
    "addr:full":"16307 Arthur St Cerritos CA 90703",
    "addr:housenumber":"16307",
    "addr:postcode":"ca 90703",
    "addr:street":"Arthur St",
    "iso:country":"US",
    "sg:address":"16307 Arthur St",
    "sg:city":"Cerritos",
    "sg:classifiers":[
        {
            "category":"Shopping",
            "subcategory":"Clothing, Apparel, & Fashions",
            "type":"Retail Goods"
        }
    ],
    "sg:phone":"+1 562 407 3300",
    "sg:postcode":"90703",
    "sg:province":"CA",
    "sg:tags":[
        "wig",
        "toupee",
        "hairpiece"
    ],
    "wof:name":"Tocco Hair Collection",
    "wof:placetype":"venue"
},
  "geometry": {"coordinates":[-118.061339,33.883875],"type":"Point"}
}