{
  "type": "Feature",
  "properties": {
    "iso:country":"US",
    "sg:address":"37126 State Rte 299 E",
    "sg:city":"Burney",
    "sg:classifiers":[
        {
            "category":"Personal",
            "type":"Services"
        }
    ],
    "sg:phone":"+1 530 335 2229",
    "sg:postcode":"96013",
    "sg:province":"CA",
    "sg:tags":[
        "program",
        "physical",
        "exercise",
        "fitness"
    ],
    "wof:name":"Totally Fit Workout Ctr",
    "wof:placetype":"venue"
},
  "geometry": {"coordinates":[-121.664312,40.882097],"type":"Point"}
}