{
  "type": "Feature",
  "properties": {
    "addr:full":"24446 Hampton Dr Valencia CA 91355",
    "addr:housenumber":"24446",
    "addr:postcode":"91355",
    "addr:street":"Hampton Dr",
    "iso:country":"US",
    "sg:address":"24446 Hampton Dr",
    "sg:city":"Valencia",
    "sg:classifiers":[
        {
            "category":"Professional",
            "subcategory":"Management & Consulting",
            "type":"Services"
        }
    ],
    "sg:phone":"+1 661 255 5659",
    "sg:postcode":"91355",
    "sg:province":"CA",
    "sg:tags":[
        "consultant"
    ],
    "wof:name":"Burke, Christman",
    "wof:placetype":"venue"
},
  "geometry": {"coordinates":[-118.56346000000001,34.403752],"type":"Point"}
}