{
  "type": "Feature",
  "properties": {
    "addr:full":"11320 Dismantle Ct Rancho Cordova CA 95742",
    "addr:housenumber":"11320",
    "addr:postcode":"95742",
    "addr:street":"Dismantle Ct",
    "iso:country":"US",
    "sg:address":"11320 Dismantle Ct",
    "sg:city":"Rancho Cordova",
    "sg:classifiers":[
        {
            "category":"Personal",
            "type":"Services"
        }
    ],
    "sg:phone":"+1 916 635 5600",
    "sg:postcode":"95742",
    "sg:province":"CA",
    "sg:tags":[
        "local"
    ],
    "wof:name":"Sims Metal Management",
    "wof:placetype":"venue"
},
  "geometry": {"coordinates":[-121.260454,38.571574],"type":"Point"}
}