{
  "type": "Feature",
  "properties": {
    "iso:country":"US",
    "sg:address":"1689 Arden Way",
    "sg:city":"Sacramento",
    "sg:classifiers":[
        {
            "category":"Shopping",
            "subcategory":"Clothing, Apparel, & Fashions",
            "type":"Retail Goods"
        }
    ],
    "sg:phone":"+1 916 649 2064",
    "sg:postcode":"95815",
    "sg:province":"CA",
    "wof:name":"Wet Seal",
    "wof:placetype":"venue"
},
  "geometry": {"coordinates":[-121.425477,38.598953],"type":"Point"}
}