{
  "type": "Feature",
  "properties": {
    "addr:full":"12650 Brookprinter Pl Poway CA 92064",
    "addr:housenumber":"12650",
    "addr:postcode":"ca 92064",
    "addr:street":"Brookprinter Pl",
    "iso:country":"US",
    "sg:address":"12650 Brookprinter Pl",
    "sg:city":"Poway",
    "sg:classifiers":[
        {
            "category":"Wholesale",
            "subcategory":"Groceries",
            "type":"Manufacturing & Wholesale Goods"
        }
    ],
    "sg:phone":"+1 858 486 4777",
    "sg:postcode":"92064",
    "sg:province":"CA",
    "wof:name":"G & A Snack Distributing Inc",
    "wof:placetype":"venue"
},
  "geometry": {"coordinates":[-117.047191,32.943203],"type":"Point"}
}