{
  "type": "Feature",
  "properties": {
    "addr:full":"175 E Stetson Ave Hemet CA 92543",
    "addr:housenumber":"175",
    "addr:postcode":"92543",
    "addr:street":"E Stetson Ave",
    "iso:country":"US",
    "sg:address":"175 E Stetson Ave",
    "sg:city":"Hemet",
    "sg:classifiers":[
        {
            "category":"Food & Beverages",
            "subcategory":"Liquor & Beverages",
            "type":"Retail Goods"
        }
    ],
    "sg:phone":"+1 951 925 8115",
    "sg:postcode":"92543",
    "sg:province":"CA",
    "wof:name":"Frank's Liquor",
    "wof:placetype":"venue"
},
  "geometry": {"coordinates":[-116.970089,33.729324],"type":"Point"}
}