{
  "type": "Feature",
  "properties": {
    "addr:full":"5729 Sonoma Dr Pleasanton CA 94566",
    "addr:housenumber":"5729",
    "addr:postcode":"94566",
    "addr:street":"Sonoma Dr",
    "iso:country":"US",
    "sg:address":"5729 Sonoma Dr",
    "sg:city":"Pleasanton",
    "sg:classifiers":[
        {
            "category":"Wholesale",
            "subcategory":"Construction Materials",
            "type":"Manufacturing & Wholesale Goods"
        }
    ],
    "sg:phone":"+1 925 485 6141",
    "sg:postcode":"94566",
    "sg:province":"CA",
    "sg:tags":[
        "gate",
        "accessory"
    ],
    "sg:website":"http://www.adautogate.com",
    "wof:name":"A & D Automatic Gate and Access Co.",
    "wof:placetype":"venue"
},
  "geometry": {"coordinates":[-121.878516,37.648062],"type":"Point"}
}