{
  "type": "Feature",
  "properties": {
    "iso:country":"US",
    "sg:address":"180 Harbor Dr",
    "sg:city":"Sausalito",
    "sg:classifiers":[
        {
            "category":"Real Estate",
            "subcategory":"Architect",
            "type":"Services"
        }
    ],
    "sg:phone":"+1 415 331 3383",
    "sg:postcode":"94965",
    "sg:province":"CA",
    "sg:tags":[
        "residential",
        "designer",
        "illustrator",
        "architectural"
    ],
    "wof:name":"Healthy Home Designs",
    "wof:placetype":"venue"
},
  "geometry": {"coordinates":[-122.499534,37.867867],"type":"Point"}
}