{
  "type": "Feature",
  "properties": {
    "addr:full":"1898 W Imola Ave Napa CA 94559",
    "addr:housenumber":"1898",
    "addr:postcode":"94559",
    "addr:street":"W Imola Ave",
    "iso:country":"US",
    "sg:address":"1898 W Imola Ave",
    "sg:city":"Napa",
    "sg:classifiers":[
        {
            "category":"Retail",
            "subcategory":"Auto Repair",
            "type":"Services"
        }
    ],
    "sg:phone":"+1 707 252 8194",
    "sg:postcode":"94559",
    "sg:province":"CA",
    "sg:tags":[
        "repairing",
        "automobile"
    ],
    "wof:name":"Silverado Service Ctr",
    "wof:placetype":"venue"
},
  "geometry": {"coordinates":[-122.294984,38.282053],"type":"Point"}
}