{
  "type": "Feature",
  "properties": {
    "iso:country":"US",
    "sg:address":"3200 Pomona Blvd",
    "sg:city":"Pomona",
    "sg:classifiers":[
        {
            "category":"Shopping",
            "subcategory":"Jewelry",
            "type":"Retail Goods"
        }
    ],
    "sg:phone":"+1 909 594 5432",
    "sg:postcode":"91768",
    "sg:province":"CA",
    "wof:name":"Treasure Chest",
    "wof:placetype":"venue"
},
  "geometry": {"coordinates":[-117.807999,34.0495],"type":"Point"}
}