{
  "type": "Feature",
  "properties": {
    "addr:full":"4757 Double Tree Ln Placerville CA 95667",
    "addr:housenumber":"4757",
    "addr:postcode":"95667",
    "addr:street":"Double Tree Ln",
    "iso:country":"US",
    "sg:address":"4757 Double Tree Ln",
    "sg:city":"Placerville",
    "sg:classifiers":[
        {
            "category":"Bars & Pubs",
            "type":"Food & Drink"
        },
        {
            "category":"Restaurant",
            "type":"Food & Drink"
        },
        {
            "category":"Bars & Pubs",
            "subcategory":"Lounge",
            "type":"Food & Drink"
        }
    ],
    "sg:phone":"+1 530 626 1689",
    "sg:postcode":"95667",
    "sg:province":"CA",
    "sg:tags":[
        "cocktail"
    ],
    "wof:name":"Stadium Club",
    "wof:placetype":"venue"
},
  "geometry": {"coordinates":[-120.65312,38.687624],"type":"Point"}
}