{
  "type": "Feature",
  "properties": {
    "addr:full":"419 E 17th Street Costa Mesa CA 92627",
    "addr:housenumber":"419",
    "addr:postcode":"92627",
    "addr:street":"E 17Th Street",
    "iso:country":"US",
    "sg:address":"419 E 17th Street",
    "sg:city":"Costa Mesa",
    "sg:classifiers":[
        {
            "category":"Professional",
            "subcategory":"Accounting & Tax Preparation",
            "type":"Services"
        }
    ],
    "sg:phone":"+1 949 646 4330",
    "sg:postcode":"92627",
    "sg:province":"CA",
    "sg:tags":[
        "accountant"
    ],
    "wof:name":"Lefmann Richard S CPA",
    "wof:placetype":"venue"
},
  "geometry": {"coordinates":[-117.911418,33.630365],"type":"Point"}
}