{
  "type": "Feature",
  "properties": {
    "addr:full":"1350 Churn Creek Rd Redding CA 96003",
    "addr:housenumber":"1350",
    "addr:postcode":"96003",
    "addr:street":"Churn Creek Rd",
    "iso:country":"US",
    "sg:address":"1350 Churn Creek Rd",
    "sg:city":"Redding",
    "sg:classifiers":[
        {
            "category":"Health Services",
            "subcategory":"Doctor",
            "type":"Services"
        }
    ],
    "sg:phone":"+1 530 224 9700",
    "sg:postcode":"96003",
    "sg:province":"CA",
    "wof:name":"Western Dental Services Inc",
    "wof:placetype":"venue"
},
  "geometry": {"coordinates":[-122.350882,40.587398],"type":"Point"}
}