{
  "type": "Feature",
  "properties": {
    "iso:country":"US",
    "sg:address":"3100 Telegraph Ave",
    "sg:city":"Berkeley",
    "sg:classifiers":[
        {
            "category":"Organizations",
            "subcategory":"Religious Organization",
            "type":"Services"
        }
    ],
    "sg:phone":"+1 510 848 8821",
    "sg:postcode":"94705",
    "sg:province":"CA",
    "sg:tags":[
        "church"
    ],
    "wof:name":"Bethlehem Lutheran Church Mo Synod",
    "wof:placetype":"venue"
},
  "geometry": {"coordinates":[-122.26004399999999,37.853893],"type":"Point"}
}