{
  "type": "Feature",
  "properties": {
    "addr:full":"13881 Campo Rd Jamul CA 91935",
    "addr:housenumber":"13881",
    "addr:postcode":"91935",
    "addr:street":"Campo Rd",
    "iso:country":"US",
    "sg:address":"13881 Campo Rd",
    "sg:city":"Jamul",
    "sg:classifiers":[
        {
            "category":"Sports & Exercise",
            "subcategory":"Gym",
            "type":"Entertainment"
        }
    ],
    "sg:phone":"+1 619 669 6682",
    "sg:postcode":"91935",
    "sg:province":"CA",
    "sg:tags":[
        "club",
        "health",
        "studio",
        "gymnasium"
    ],
    "wof:name":"Curves For Women",
    "wof:placetype":"venue"
},
  "geometry": {"coordinates":[-116.876743,32.717051],"type":"Point"}
}