{
  "type": "Feature",
  "properties": {
    "addr:full":"7623 Pekoe Way Sacramento CA 95828",
    "addr:postcode":"7623;95828",
    "addr:street":"Pekoe Way",
    "iso:country":"US",
    "sg:address":"7623 Pekoe Way",
    "sg:city":"Sacramento",
    "sg:classifiers":[
        {
            "category":"Real Estate",
            "subcategory":"Real Estate Services",
            "type":"Services"
        },
        {
            "category":"Real Estate",
            "subcategory":"Real Estate Agent",
            "type":"Services"
        }
    ],
    "sg:phone":"+1 916 803 0211",
    "sg:postcode":"95828",
    "sg:province":"CA",
    "sg:tags":[
        "buyer",
        "broker"
    ],
    "wof:name":"Connect Realty.Com",
    "wof:placetype":"venue"
},
  "geometry": {"coordinates":[-121.38189300000001,38.481064],"type":"Point"}
}