{
  "type": "Feature",
  "properties": {
    "addr:full":"44752 Beech Ave Lancaster CA 93534",
    "addr:housenumber":"44752",
    "addr:postcode":"93534",
    "addr:street":"Beech Ave",
    "iso:country":"US",
    "sg:address":"44752 Beech Ave",
    "sg:city":"Lancaster",
    "sg:classifiers":[
        {
            "category":"Shopping",
            "subcategory":"Used Merchandise",
            "type":"Retail Goods"
        }
    ],
    "sg:phone":"+1 661 729 3751",
    "sg:postcode":"93534",
    "sg:province":"CA",
    "sg:tags":[
        "shop",
        "consignment"
    ],
    "wof:name":"Expression Boutique",
    "wof:placetype":"venue"
},
  "geometry": {"coordinates":[-118.137743,34.695476],"type":"Point"}
}