{
  "type": "Feature",
  "properties": {
    "addr:full":"740 Ventura Blvd Ste 406 Camarillo CA 93010",
    "addr:housenumber":"740",
    "addr:postcode":"93010",
    "addr:street":"Ventura Blvd Ste 406",
    "iso:country":"US",
    "sg:address":"740 Ventura Blvd Ste 406",
    "sg:city":"Camarillo",
    "sg:classifiers":[
        {
            "category":"Shopping",
            "subcategory":"Discount & Variety Stores",
            "type":"Retail Goods"
        }
    ],
    "sg:phone":"+1 805 388 3024",
    "sg:postcode":"93010",
    "sg:province":"CA",
    "sg:tags":[
        "outlet"
    ],
    "sg:website":"www.fossil.com",
    "wof:name":"Fossil",
    "wof:placetype":"venue"
},
  "geometry": {"coordinates":[-119.061032,34.217976],"type":"Point"}
}