{
  "type": "Feature",
  "properties": {
    "addr:full":"2302 Martin St Ste 475 Irvine CA 92618",
    "addr:housenumber":"2302",
    "addr:postcode":"92618",
    "addr:street":"Martin St Ste 475",
    "iso:country":"US",
    "sg:address":"2302 Martin St Ste 475",
    "sg:city":"Irvine",
    "sg:classifiers":[
        {
            "category":"Professional",
            "subcategory":"Lawyer & Legal Services",
            "type":"Services"
        }
    ],
    "sg:phone":"+1 877 648 6718",
    "sg:postcode":"92618",
    "sg:province":"CA",
    "sg:tags":[
        "notary"
    ],
    "wof:name":"AAA Emergency Notary",
    "wof:placetype":"venue"
},
  "geometry": {"coordinates":[-117.858617,33.67201],"type":"Point"}
}