{
  "type": "Feature",
  "properties": {
    "iso:country":"US",
    "sg:address":"9211 Bolsa Ave Ste 106 - 107",
    "sg:city":"Westminster",
    "sg:classifiers":[
        {
            "category":"Restaurant",
            "type":"Food & Drink"
        }
    ],
    "sg:phone":"+1 714 893 1976",
    "sg:postcode":"92683",
    "sg:province":"CA",
    "sg:tags":[
        "dim",
        "sum",
        "seafood"
    ],
    "sg:website":"www.seafoodcove.com",
    "wof:name":"Seafood Cove #2",
    "wof:placetype":"venue"
},
  "geometry": {"coordinates":[-117.968067,33.745041],"type":"Point"}
}