{
  "type": "Feature",
  "properties": {
    "addr:full":"700 Long Beach Blvd Long Beach CA 90813",
    "addr:housenumber":"700",
    "addr:postcode":"90813",
    "addr:street":"Long Beach Blvd",
    "iso:country":"US",
    "sg:address":"700 Long Beach Blvd",
    "sg:city":"Long Beach",
    "sg:classifiers":[
        {
            "category":"Restaurant",
            "type":"Food & Drink"
        }
    ],
    "sg:phone":"+1 562 432 7502",
    "sg:postcode":"90813",
    "sg:province":"CA",
    "wof:name":"Carl's Jr Restaurants",
    "wof:placetype":"venue"
},
  "geometry": {"coordinates":[-118.189003,33.7757],"type":"Point"}
}