{
  "type": "Feature",
  "properties": {
    "iso:country":"US",
    "sg:address":"21350 Hawthorne Blvd",
    "sg:city":"Torrance",
    "sg:classifiers":[
        {
            "category":"Health Services",
            "subcategory":"Dentist",
            "type":"Services"
        }
    ],
    "sg:phone":"+1 310 543 3533",
    "sg:postcode":"90503",
    "sg:province":"CA",
    "wof:name":"Allied Dental Care",
    "wof:placetype":"venue"
},
  "geometry": {"coordinates":[-118.352942,33.834341],"type":"Point"}
}