{
  "type": "Feature",
  "properties": {
    "iso:country":"US",
    "sg:address":"4 Dahlia Way",
    "sg:city":"Chico",
    "sg:classifiers":[
        {
            "category":"Farming",
            "subcategory":"Farm & Veterinary Services",
            "type":"Manufacturing & Wholesale Goods"
        }
    ],
    "sg:phone":"+1 530 342 5000",
    "sg:postcode":"95926",
    "sg:province":"CA",
    "sg:tags":[
        "preparation",
        "soil",
        "crop"
    ],
    "wof:name":"Reimer Pest & Weed C",
    "wof:placetype":"venue"
},
  "geometry": {"coordinates":[-121.862526,39.743579],"type":"Point"}
}