{
  "type": "Feature",
  "properties": {
    "addr:full":"1999 Harrison St Suite 2600 Oakland CA 94612",
    "addr:housenumber":"1999",
    "addr:postcode":"94612",
    "addr:street":"Harrison St Suite 2600",
    "iso:country":"US",
    "sg:address":"1999 Harrison St Suite 2600",
    "sg:city":"Oakland",
    "sg:classifiers":[
        {
            "category":"Professional",
            "subcategory":"Lawyer & Legal Services",
            "type":"Services"
        }
    ],
    "sg:phone":"+1 510 433 2600",
    "sg:postcode":"94612",
    "sg:province":"CA",
    "sg:tags":[
        "litigation",
        "attorney",
        "tort"
    ],
    "wof:name":"Sebransky , Lori A. - Lombardi, Loper &",
    "wof:placetype":"venue"
},
  "geometry": {"coordinates":[-122.264397,37.80806],"type":"Point"}
}