{
  "type": "Feature",
  "properties": {
    "addr:full":"214 Beethoven Ln Los Gatos CA 95032",
    "addr:housenumber":"214",
    "addr:postcode":"95032",
    "addr:street":"Beethoven Ln",
    "iso:country":"US",
    "sg:address":"214 Beethoven Ln",
    "sg:city":"Los Gatos",
    "sg:classifiers":[
        {
            "category":"Building & Trades",
            "subcategory":"Construction",
            "type":"Services"
        }
    ],
    "sg:phone":"+1 408 358 3800",
    "sg:postcode":"95032",
    "sg:province":"CA",
    "sg:tags":[
        "contractor"
    ],
    "wof:name":"Classics At Beethoven Lane",
    "wof:placetype":"venue"
},
  "geometry": {"coordinates":[-121.953446,37.257565],"type":"Point"}
}