{
  "type": "Feature",
  "properties": {
    "iso:country":"US",
    "sg:address":"84 Martens Blvd",
    "sg:city":"San Rafael",
    "sg:classifiers":[
        {
            "category":"Building & Trades",
            "subcategory":"Cleaning & Sanitation",
            "type":"Services"
        }
    ],
    "sg:phone":"+1 415 457 5228",
    "sg:postcode":"94901",
    "sg:province":"CA",
    "sg:tags":[
        "janitor"
    ],
    "wof:name":"Bucket & Broom Assoc",
    "wof:placetype":"venue"
},
  "geometry": {"coordinates":[-122.530053,37.966127],"type":"Point"}
}