{
  "type": "Feature",
  "properties": {
    "iso:country":"US",
    "sg:address":"2462 Flagstone Dr",
    "sg:city":"Napa",
    "sg:classifiers":[
        {
            "category":"Professional",
            "type":"Services"
        }
    ],
    "sg:phone":"+1 707 255 5716",
    "sg:postcode":"94558",
    "sg:province":"CA",
    "wof:name":"Peopleidea",
    "wof:placetype":"venue"
},
  "geometry": {"coordinates":[-122.333802,38.332218],"type":"Point"}
}