{
  "type": "Feature",
  "properties": {
    "addr:full":"2462 Flagstone Dr Napa CA 94558",
    "addr:housenumber":"2462",
    "addr:postcode":"94558",
    "addr:street":"Flagstone Dr",
    "iso:country":"US",
    "sg:address":"2462 Flagstone Dr",
    "sg:city":"Napa",
    "sg:classifiers":[
        {
            "category":"Professional",
            "type":"Services"
        }
    ],
    "sg:phone":"+1 707 255 5716",
    "sg:postcode":"94558",
    "sg:province":"CA",
    "wof:name":"Peopleidea",
    "wof:placetype":"venue"
},
  "geometry": {"coordinates":[-122.33380200000001,38.332218],"type":"Point"}
}