{
  "type": "Feature",
  "properties": {
    "iso:country":"US",
    "sg:address":"16296 Merrill Ave",
    "sg:city":"Fontana",
    "sg:classifiers":[
        {
            "category":"Real Estate",
            "subcategory":"Real Estate Operator",
            "type":"Services"
        }
    ],
    "sg:phone":"+1 909 350 1552",
    "sg:postcode":"92335",
    "sg:province":"CA",
    "sg:tags":[
        "apartment"
    ],
    "wof:name":"Las Brisas Apartments",
    "wof:placetype":"venue"
},
  "geometry": {"coordinates":[-117.45124800000001,34.092157],"type":"Point"}
}