{
  "type": "Feature",
  "properties": {
    "addr:full":"675 S Glenwood Pl Burbank CA 91506",
    "addr:housenumber":"675",
    "addr:postcode":"91506",
    "addr:street":"S Glenwood Pl",
    "iso:country":"US",
    "sg:address":"675 S Glenwood Pl",
    "sg:city":"Burbank",
    "sg:classifiers":[
        {
            "category":"Building & Trades",
            "subcategory":"Plumbing",
            "type":"Services"
        }
    ],
    "sg:phone":"+1 818 240 1492",
    "sg:postcode":"91506",
    "sg:province":"CA",
    "sg:website":"www.earthquakestore.com",
    "wof:name":"Earthquake Store",
    "wof:placetype":"venue"
},
  "geometry": {"coordinates":[-118.31413499999999,34.165818],"type":"Point"}
}