{
  "type": "Feature",
  "properties": {
    "addr:full":"465 California Street San Francisco CA 94104",
    "addr:housenumber":"465",
    "addr:postcode":"94104",
    "addr:street":"California Street",
    "iso:country":"US",
    "sg:address":"465 California Street",
    "sg:city":"San Francisco",
    "sg:classifiers":[
        {
            "category":"Professional",
            "subcategory":"Lawyer & Legal Services",
            "type":"Services"
        }
    ],
    "sg:phone":"+1 415 362 4405",
    "sg:postcode":"94104",
    "sg:province":"CA",
    "wof:name":"Burton John Atty At Law",
    "wof:placetype":"venue"
},
  "geometry": {"coordinates":[-122.402,37.792999],"type":"Point"}
}