{
  "type": "Feature",
  "properties": {
    "iso:country":"US",
    "sg:address":"5655 College Ave",
    "sg:city":"Oakland",
    "sg:classifiers":[
        {
            "category":"Cafe",
            "type":"Food & Drink"
        }
    ],
    "sg:menulink":"http://www.allmenus.com/ca/oakland/22415-oliveto-cafe--restaurant/menu/",
    "sg:phone":"+1 510 547 4381",
    "sg:postcode":"94618",
    "sg:province":"CA",
    "sg:tags":[
        "italian"
    ],
    "wof:name":"Oliveto Cafe & Restaurant",
    "wof:placetype":"venue"
},
  "geometry": {"coordinates":[-122.251723,37.844191],"type":"Point"}
}