{
  "type": "Feature",
  "properties": {
    "addr:full":"8240 Winnetka Ave Winnetka CA 91306",
    "addr:housenumber":"8240",
    "addr:postcode":"91306",
    "addr:street":"Winnetka Ave",
    "iso:country":"US",
    "sg:address":"8240 Winnetka Ave",
    "sg:city":"Winnetka",
    "sg:classifiers":[
        {
            "category":"Professional",
            "subcategory":"Research",
            "type":"Services"
        }
    ],
    "sg:phone":"+1 818 886 2066",
    "sg:postcode":"91306",
    "sg:province":"CA",
    "sg:tags":[
        "environmental",
        "ecological"
    ],
    "wof:name":"E A Environmental",
    "wof:placetype":"venue"
},
  "geometry": {"coordinates":[-118.570958,34.219304],"type":"Point"}
}