{
  "type": "Feature",
  "properties": {
    "addr:full":"17510 Pioneer Blvd Ste 202 Artesia CA 90701",
    "addr:housenumber":"17510",
    "addr:postcode":"90701",
    "addr:street":"Pioneer Blvd Ste 202",
    "iso:country":"US",
    "sg:address":"17510 Pioneer Blvd Ste 202",
    "sg:city":"Artesia",
    "sg:classifiers":[
        {
            "category":"Health Services",
            "subcategory":"Health Practitioner",
            "type":"Services"
        }
    ],
    "sg:phone":"+1 562 860 0975",
    "sg:postcode":"90701",
    "sg:province":"CA",
    "sg:tags":[
        "acupuncture"
    ],
    "wof:name":"Yoon's Acupuncture",
    "wof:placetype":"venue"
},
  "geometry": {"coordinates":[-118.08200100000001,33.872002],"type":"Point"}
}