{
  "type": "Feature",
  "properties": {
    "addr:full":"6918 Valjean Ave Van Nuys CA 91406",
    "addr:housenumber":"6918",
    "addr:postcode":"91406",
    "addr:street":"Valjean Ave",
    "iso:country":"US",
    "sg:address":"6918 Valjean Ave",
    "sg:city":"Van Nuys",
    "sg:classifiers":[
        {
            "category":"Retail",
            "subcategory":"Repair Shop",
            "type":"Services"
        }
    ],
    "sg:phone":"+1 818 908 5858",
    "sg:postcode":"91406",
    "sg:province":"CA",
    "sg:tags":[
        "refrigeration"
    ],
    "wof:name":"Geary Pacific Corp",
    "wof:placetype":"venue"
},
  "geometry": {"coordinates":[-118.48576199999999,34.195368],"type":"Point"}
}