{
  "type": "Feature",
  "properties": {
    "addr:full":"2749 Sumac Rd Fallbrook CA 92028",
    "addr:housenumber":"2749",
    "addr:postcode":"92028",
    "addr:street":"Sumac Rd",
    "iso:country":"US",
    "sg:address":"2749 Sumac Rd",
    "sg:city":"Fallbrook",
    "sg:classifiers":[
        {
            "category":"Real Estate",
            "subcategory":"Real Estate Agent",
            "type":"Services"
        }
    ],
    "sg:phone":"+1 760 731 3342",
    "sg:postcode":"92028",
    "sg:province":"CA",
    "wof:name":"Thomas R Metier",
    "wof:placetype":"venue"
},
  "geometry": {"coordinates":[-117.170204,33.336315],"type":"Point"}
}