{
  "type": "Feature",
  "properties": {
    "addr:full":"1817 2nd St Livermore CA 94550",
    "addr:housenumber":"1817",
    "addr:postcode":"94550",
    "addr:street":"2Nd St",
    "iso:country":"US",
    "sg:address":"1817 2nd St",
    "sg:city":"Livermore",
    "sg:phone":"+1 925 455 1104",
    "sg:postcode":"94550",
    "sg:province":"CA",
    "wof:name":"St Vincent De Paul Society",
    "wof:placetype":"venue"
},
  "geometry": {"coordinates":[-121.77315400000001,37.679505],"type":"Point"}
}