{
  "type": "Feature",
  "properties": {
    "iso:country":"US",
    "sg:address":"5494 Judith St",
    "sg:city":"San Jose",
    "sg:classifiers":[
        {
            "category":"Building & Trades",
            "subcategory":"Construction",
            "type":"Services"
        }
    ],
    "sg:phone":"+1 408 629 3110",
    "sg:postcode":"95123",
    "sg:province":"CA",
    "sg:tags":[
        "dry wall",
        "contractor"
    ],
    "wof:name":"J & V Drywall",
    "wof:placetype":"venue"
},
  "geometry": {"coordinates":[-121.825853,37.255366],"type":"Point"}
}