{
  "type": "Feature",
  "properties": {
    "iso:country":"US",
    "sg:address":"3307 Sacramento St",
    "sg:city":"San Francisco",
    "sg:classifiers":[
        {
            "category":"Shopping",
            "subcategory":"Clothing, Apparel, & Fashions",
            "type":"Retail Goods"
        }
    ],
    "sg:phone":"+1 415 440 7599",
    "sg:postcode":"94118",
    "sg:province":"CA",
    "sg:tags":[
        "infant",
        "wear"
    ],
    "wof:name":"Brooks Shoes For Kids",
    "wof:placetype":"venue"
},
  "geometry": {"coordinates":[-122.448563,37.787916],"type":"Point"}
}