{
  "type": "Feature",
  "properties": {
    "addr:full":"420 W 7th St Los Angeles CA 90014",
    "addr:housenumber":"420",
    "addr:postcode":"90014",
    "addr:street":"W 7Th St",
    "iso:country":"US",
    "sg:address":"420 W 7th St",
    "sg:city":"Los Angeles",
    "sg:classifiers":[
        {
            "category":"Shopping",
            "subcategory":"Jewelry",
            "type":"Retail Goods"
        },
        {
            "category":"Wholesale",
            "subcategory":"Jewelry",
            "type":"Manufacturing & Wholesale Goods"
        }
    ],
    "sg:phone":"+1 213 629 3566",
    "sg:postcode":"90014",
    "sg:province":"CA",
    "sg:tags":[
        "stone",
        "jeweler"
    ],
    "wof:name":"D & J Jewelry",
    "wof:placetype":"venue"
},
  "geometry": {"coordinates":[-118.255557,34.046532],"type":"Point"}
}