{
  "type": "Feature",
  "properties": {
    "iso:country":"US",
    "sg:address":"783 California Dr",
    "sg:city":"Burlingame",
    "sg:classifiers":[
        {
            "category":"Home & Garden",
            "subcategory":"Furniture",
            "type":"Retail Goods"
        }
    ],
    "sg:phone":"+1 650 375 1212",
    "sg:postcode":"94010",
    "sg:province":"CA",
    "sg:website":"www.tribecahome.com",
    "wof:name":"Tribeca",
    "wof:placetype":"venue"
},
  "geometry": {"coordinates":[-122.351663,37.582403],"type":"Point"}
}