{
  "type": "Feature",
  "properties": {
    "iso:country":"US",
    "sg:address":"1939 Harrison St",
    "sg:city":"Oakland",
    "sg:classifiers":[
        {
            "category":"Manufacturing",
            "subcategory":"Printing",
            "type":"Manufacturing & Wholesale Goods"
        }
    ],
    "sg:phone":"+1 510 272 4747",
    "sg:postcode":"94612",
    "sg:province":"CA",
    "sg:tags":[
        "newspaper"
    ],
    "wof:name":"Inter-City Express",
    "wof:placetype":"venue"
},
  "geometry": {"coordinates":[-122.264605,37.808071],"type":"Point"}
}