{
  "type": "Feature",
  "properties": {
    "iso:country":"US",
    "sg:address":"4700 Teller Ave",
    "sg:city":"Newport Beach",
    "sg:classifiers":[
        {
            "category":"Professional",
            "subcategory":"Lawyer & Legal Services",
            "type":"Services"
        }
    ],
    "sg:phone":"+1 949 863 9297",
    "sg:postcode":"92660",
    "sg:province":"CA",
    "sg:tags":[
        "attorney"
    ],
    "sg:website":"www.4injurylawyer.com",
    "wof:name":"Criminal Defense Professionals",
    "wof:placetype":"venue"
},
  "geometry": {"coordinates":[-117.856965,33.666508],"type":"Point"}
}