{
  "type": "Feature",
  "properties": {
    "iso:country":"US",
    "sg:address":"4730 Crystal Springs Drive",
    "sg:city":"Los Angeles",
    "sg:classifiers":[
        {
            "category":"Sports & Exercise",
            "subcategory":"Golf",
            "type":"Entertainment"
        }
    ],
    "sg:phone":"+1 323 664 2255",
    "sg:postcode":"90027",
    "sg:province":"CA",
    "wof:name":"Griffith Park Golf Shop",
    "wof:placetype":"venue"
},
  "geometry": {"coordinates":[-118.284401,34.146501],"type":"Point"}
}