{
  "type": "Feature",
  "properties": {
    "addr:full":"1211 Grant Ave Novato CA 94945",
    "addr:housenumber":"1211",
    "addr:postcode":"94945",
    "addr:street":"Grant Ave",
    "iso:country":"US",
    "sg:address":"1211 Grant Ave",
    "sg:city":"Novato",
    "sg:classifiers":[
        {
            "category":"Shopping",
            "subcategory":"Music",
            "type":"Retail Goods"
        }
    ],
    "sg:phone":"+1 415 897 2892",
    "sg:postcode":"94945",
    "sg:province":"CA",
    "sg:tags":[
        "compact",
        "record",
        "disc",
        "tape"
    ],
    "wof:name":"Watts Music",
    "wof:placetype":"venue"
},
  "geometry": {"coordinates":[-122.573532,38.10811],"type":"Point"}
}