{
  "type": "Feature",
  "properties": {
    "addr:full":"4157 Long Beach Ave Vernon CA 90058",
    "addr:housenumber":"4157",
    "addr:postcode":"90058",
    "addr:street":"Long Beach Ave",
    "iso:country":"US",
    "sg:address":"4157 Long Beach Ave",
    "sg:city":"Vernon",
    "sg:classifiers":[
        {
            "category":"Restaurant",
            "type":"Food & Drink"
        }
    ],
    "sg:phone":"+1 323 235 5610",
    "sg:postcode":"90058",
    "sg:province":"CA",
    "sg:tags":[
        "style",
        "family"
    ],
    "wof:name":"Ilobasqueno Restaurant",
    "wof:placetype":"venue"
},
  "geometry": {"coordinates":[-118.24324900000001,34.006942],"type":"Point"}
}