{
  "type": "Feature",
  "properties": {
    "addr:full":"55 Second Street Suite 400 San Francisco CA 94105",
    "addr:housenumber":"55",
    "addr:postcode":"94105",
    "addr:street":"Second Street Suite 400",
    "iso:country":"US",
    "sg:address":"55 Second Street Suite 400",
    "sg:city":"San Francisco",
    "sg:classifiers":[
        {
            "category":"Professional",
            "subcategory":"Computer Services",
            "type":"Services"
        }
    ],
    "sg:phone":"+1 415 404 6094",
    "sg:postcode":"94105",
    "sg:province":"CA",
    "sg:tags":[
        "hi5",
        "socialnetworking",
        "musicnetwork",
        "youyu"
    ],
    "sg:website":"http://hi5.com",
    "wof:name":"hi5",
    "wof:placetype":"venue"
},
  "geometry": {"coordinates":[-122.39563099999999,37.789595],"type":"Point"}
}