{
  "type": "Feature",
  "properties": {
    "iso:country":"US",
    "sg:address":"3185 W Olympic Blvd",
    "sg:city":"Los Angeles",
    "sg:classifiers":[
        {
            "category":"Restaurant",
            "type":"Food & Drink"
        }
    ],
    "sg:phone":"+1 213 382 3815",
    "sg:postcode":"90006",
    "sg:province":"CA",
    "sg:tags":[
        "korean"
    ],
    "wof:name":"Yu Chun Chic Naeng Myun",
    "wof:placetype":"venue"
},
  "geometry": {"coordinates":[-118.306,34.0527],"type":"Point"}
}