{
  "type": "Feature",
  "properties": {
    "addr:full":"3907 Stockton Blvd Sacramento CA 95820",
    "addr:housenumber":"3907",
    "addr:postcode":"95820",
    "addr:street":"Stockton Blvd",
    "iso:country":"US",
    "sg:address":"3907 Stockton Blvd",
    "sg:city":"Sacramento",
    "sg:classifiers":[
        {
            "category":"Autos & Motor Vehicles",
            "subcategory":"Fuel & Gas Station",
            "type":"Retail Goods"
        }
    ],
    "sg:phone":"+1 916 376 7581",
    "sg:postcode":"95820",
    "sg:province":"CA",
    "wof:name":"Shop",
    "wof:placetype":"venue"
},
  "geometry": {"coordinates":[-121.44947999999999,38.539384],"type":"Point"}
}