{
  "type": "Feature",
  "properties": {
    "addr:full":"39500 Comptche Ukiah Rd Mendocino CA 95460",
    "addr:postcode":"39500;95460",
    "addr:street":"Ukiah Rd",
    "iso:country":"US",
    "sg:address":"39500 Comptche Ukiah Rd",
    "sg:city":"Mendocino",
    "sg:classifiers":[
        {
            "category":"Retail",
            "subcategory":"Repair Shop",
            "type":"Services"
        }
    ],
    "sg:phone":"+1 707 937 6061",
    "sg:postcode":"95460",
    "sg:province":"CA",
    "sg:tags":[
        "welding"
    ],
    "wof:name":"Noah's Arc Welding",
    "wof:placetype":"venue"
},
  "geometry": {"coordinates":[-123.708326,39.276158],"type":"Point"}
}