{
  "type": "Feature",
  "properties": {
    "addr:full":"23586 Calabasas Rd Ste 204 Calabasas CA 91302",
    "addr:housenumber":"23586",
    "addr:postcode":"91302",
    "addr:street":"Calabasas Rd Ste 204",
    "iso:country":"US",
    "sg:address":"23586 Calabasas Rd Ste 204",
    "sg:city":"Calabasas",
    "sg:classifiers":[
        {
            "category":"Professional",
            "subcategory":"Employment Agencies",
            "type":"Services"
        }
    ],
    "sg:phone":"+1 818 444 0103",
    "sg:postcode":"91302",
    "sg:province":"CA",
    "sg:tags":[
        "opportunity"
    ],
    "sg:website":"www.equisdifference.com",
    "wof:name":"Equis",
    "wof:placetype":"venue"
},
  "geometry": {"coordinates":[-118.64075200000001,34.156705],"type":"Point"}
}