{
  "type": "Feature",
  "properties": {
    "addr:full":"121 N La Cienega Blvd Ste 114 Los Angeles CA 90048",
    "addr:housenumber":"121",
    "addr:postcode":"90048",
    "addr:street":"N La Cienega Blvd Ste 114",
    "iso:country":"US",
    "sg:address":"121 N La Cienega Blvd Ste 114",
    "sg:city":"Los Angeles",
    "sg:classifiers":[
        {
            "category":"Restaurant",
            "type":"Food & Drink"
        }
    ],
    "sg:postcode":"90048",
    "sg:province":"CA",
    "sg:tags":[
        "mexican"
    ],
    "wof:name":"Chipolte",
    "wof:placetype":"venue"
},
  "geometry": {"coordinates":[-118.377562,34.075004],"type":"Point"}
}