{
  "type": "Feature",
  "properties": {
    "addr:full":"2280 Hutton Rd Nipomo CA 93444",
    "addr:housenumber":"2280",
    "addr:postcode":"93444",
    "addr:street":"Hutton Rd",
    "iso:country":"US",
    "sg:address":"2280 Hutton Rd",
    "sg:city":"Nipomo",
    "sg:classifiers":[
        {
            "category":"Freight",
            "type":"Transportation"
        }
    ],
    "sg:phone":"+1 805 928 2577",
    "sg:postcode":"93444",
    "sg:province":"CA",
    "sg:tags":[
        "trucking"
    ],
    "wof:name":"ECR Inc",
    "wof:placetype":"venue"
},
  "geometry": {"coordinates":[-120.43732300000001,35.000236],"type":"Point"}
}