{
  "type": "Feature",
  "properties": {
    "addr:full":"166 N Le Doux Rd Beverly Hills CA 90211",
    "addr:housenumber":"166",
    "addr:postcode":"90211",
    "addr:street":"N Le Doux Rd",
    "iso:country":"US",
    "sg:address":"166 N Le Doux Rd",
    "sg:city":"Beverly Hills",
    "sg:classifiers":[
        {
            "category":"Manufacturing",
            "subcategory":"Tools & Machinery",
            "type":"Manufacturing & Wholesale Goods"
        }
    ],
    "sg:phone":"+1 310 659 3898",
    "sg:postcode":"90211",
    "sg:province":"CA",
    "sg:tags":[
        "filter"
    ],
    "wof:name":"Sol-Gor Scientific",
    "wof:placetype":"venue"
},
  "geometry": {"coordinates":[-118.37721000000001,34.06672],"type":"Point"}
}