{
  "type": "Feature",
  "properties": {
    "addr:full":"328 Camaritas Way Danville CA 94526",
    "addr:housenumber":"328",
    "addr:postcode":"94526",
    "addr:street":"Camaritas Way",
    "iso:country":"US",
    "sg:address":"328 Camaritas Way",
    "sg:city":"Danville",
    "sg:classifiers":[
        {
            "category":"Professional",
            "subcategory":"Management & Consulting",
            "type":"Services"
        },
        {
            "category":"Professional",
            "subcategory":"Engineering",
            "type":"Services"
        }
    ],
    "sg:phone":"+1 925 422 0910",
    "sg:postcode":"94526",
    "sg:province":"CA",
    "sg:tags":[
        "environmental",
        "ecological",
        "engineer",
        "consultant"
    ],
    "wof:name":"Jeffrey I Daniels",
    "wof:placetype":"venue"
},
  "geometry": {"coordinates":[-121.965565,37.798329],"type":"Point"}
}