{
  "type": "Feature",
  "properties": {
    "iso:country":"US",
    "sg:address":"11939 Rancho Bernardo Rd",
    "sg:city":"San Diego",
    "sg:classifiers":[
        {
            "category":"Personal",
            "subcategory":"Beauty Salon",
            "type":"Services"
        }
    ],
    "sg:phone":"+1 858 675 3520",
    "sg:postcode":"92128",
    "sg:province":"CA",
    "sg:tags":[
        "manicuring"
    ],
    "wof:name":"Nails By Judy",
    "wof:placetype":"venue"
},
  "geometry": {"coordinates":[-117.072226,33.022798],"type":"Point"}
}