{
  "type": "Feature",
  "properties": {
    "iso:country":"US",
    "sg:address":"2223 Fulton St Fl 4",
    "sg:city":"Berkeley",
    "sg:classifiers":[
        {
            "category":"Health Services",
            "subcategory":"Clinic",
            "type":"Services"
        }
    ],
    "sg:phone":"+1 510 642 5507",
    "sg:postcode":"94720",
    "sg:province":"CA",
    "sg:tags":[
        "welfare"
    ],
    "wof:name":"Labor Occupational Health Program",
    "wof:placetype":"venue"
},
  "geometry": {"coordinates":[-122.266041,37.868363],"type":"Point"}
}