{
  "type": "Feature",
  "properties": {
    "iso:country":"US",
    "sg:address":"24000 Alicia Pkwy Ste 10",
    "sg:city":"Mission Viejo",
    "sg:classifiers":[
        {
            "category":"Personal",
            "subcategory":"Hair Removal",
            "type":"Services"
        }
    ],
    "sg:phone":"+1 949 436 5786",
    "sg:postcode":"92691",
    "sg:province":"CA",
    "sg:website":"www.prettythreading.com",
    "wof:name":"Pretty threading",
    "wof:placetype":"venue"
},
  "geometry": {"coordinates":[-117.679413,33.613558],"type":"Point"}
}