{
  "type": "Feature",
  "properties": {
    "addr:full":"346 Pollasky Ave Clovis CA 93612",
    "addr:housenumber":"346",
    "addr:postcode":"93612",
    "addr:street":"Pollasky Ave",
    "iso:country":"US",
    "sg:address":"346 Pollasky Ave",
    "sg:city":"Clovis",
    "sg:classifiers":[
        {
            "category":"Personal",
            "subcategory":"Beauty Salon",
            "type":"Services"
        }
    ],
    "sg:phone":"+1 559 298 1492",
    "sg:postcode":"93612",
    "sg:province":"CA",
    "wof:name":"Resurface Skincare By Jennifer",
    "wof:placetype":"venue"
},
  "geometry": {"coordinates":[-119.70206899999999,36.825873],"type":"Point"}
}