{
  "type": "Feature",
  "properties": {
    "iso:country":"US",
    "sg:address":"27823 Coldsprings Pl",
    "sg:city":"Valencia",
    "sg:classifiers":[
        {
            "category":"Home & Garden",
            "subcategory":"Building Materials",
            "type":"Retail Goods"
        },
        {
            "category":"Building & Trades",
            "subcategory":"Construction",
            "type":"Services"
        }
    ],
    "sg:phone":"+1 661 212 2269",
    "sg:postcode":"91354",
    "sg:province":"CA",
    "sg:tags":[
        "concrete",
        "staining",
        "contractor"
    ],
    "wof:name":"Custom Concrete Coatings",
    "wof:placetype":"venue"
},
  "geometry": {"coordinates":[-118.547197,34.451526],"type":"Point"}
}