{
  "type": "Feature",
  "properties": {
    "addr:full":"541 W Manchester Blvd Ste 104 Inglewood CA 90301",
    "addr:housenumber":"541",
    "addr:postcode":"90301",
    "addr:street":"W Manchester Blvd Ste 104",
    "iso:country":"US",
    "sg:address":"541 W Manchester Blvd Ste 104",
    "sg:city":"Inglewood",
    "sg:classifiers":[
        {
            "category":"Wholesale",
            "subcategory":"Medical Equipment & Supplies",
            "type":"Manufacturing & Wholesale Goods"
        },
        {
            "category":"Shopping",
            "subcategory":"Pharmacy",
            "type":"Retail Goods"
        }
    ],
    "sg:phone":"+1 310 330 3933",
    "sg:postcode":"90301",
    "sg:province":"CA",
    "sg:tags":[
        "home",
        "health",
        "care"
    ],
    "wof:name":"Horizon Medical & Hospital",
    "wof:placetype":"venue"
},
  "geometry": {"coordinates":[-118.364878,33.961693],"type":"Point"}
}