{
  "type": "Feature",
  "properties": {
    "addr:full":"576 Toro Canyon Rd. Montecito CA 93108",
    "addr:housenumber":"576",
    "addr:postcode":"93108",
    "addr:street":"Toro Canyon Rd.",
    "iso:country":"US",
    "sg:address":"576 Toro Canyon Rd.",
    "sg:city":"Montecito",
    "sg:classifiers":[
        {
            "category":"Park",
            "type":"Public Place"
        },
        {
            "category":"Recreation",
            "subcategory":"Playground",
            "type":"Entertainment"
        },
        {
            "category":"Recreation",
            "type":"Entertainment"
        }
    ],
    "sg:phone":"+1 805 969 3315",
    "sg:postcode":"93108",
    "sg:province":"CA",
    "sg:tags":[
        "hiking"
    ],
    "sg:website":"www.sbparks.org",
    "wof:name":"Toro Canyon Park",
    "wof:placetype":"venue"
},
  "geometry": {"coordinates":[-119.571225,34.434518],"type":"Point"}
}