{
  "type": "Feature",
  "properties": {
    "iso:country":"US",
    "sg:address":"514 15th St",
    "sg:city":"Modesto",
    "sg:classifiers":[
        {
            "category":"Professional",
            "type":"Services"
        },
        {
            "category":"Health Services",
            "subcategory":"Doctor",
            "type":"Services"
        }
    ],
    "sg:phone":"+1 209 577 3146",
    "sg:postcode":"95354",
    "sg:province":"CA",
    "sg:tags":[
        "dentist"
    ],
    "wof:name":"Dental Hygiene Resources",
    "wof:placetype":"venue"
},
  "geometry": {"coordinates":[-120.990757,37.640145],"type":"Point"}
}