{
  "type": "Feature",
  "properties": {
    "addr:full":"1265 Pacific Ave Santa Rosa CA 95404",
    "addr:housenumber":"1265",
    "addr:postcode":"95404",
    "addr:street":"Pacific Ave",
    "iso:country":"US",
    "sg:address":"1265 Pacific Ave",
    "sg:city":"Santa Rosa",
    "sg:classifiers":[
        {
            "category":"Real Estate",
            "subcategory":"Real Estate Operator",
            "type":"Services"
        }
    ],
    "sg:phone":"+1 707 579 0787",
    "sg:postcode":"95404",
    "sg:province":"CA",
    "sg:tags":[
        "apartment"
    ],
    "wof:name":"Pacific Garden Apartments",
    "wof:placetype":"venue"
},
  "geometry": {"coordinates":[-122.70742,38.45318],"type":"Point"}
}