{
  "type": "Feature",
  "properties": {
    "iso:country":"US",
    "sg:address":"1240 Goodrich Blvd",
    "sg:city":"Los Angeles",
    "sg:classifiers":[
        {
            "category":"Manufacturing",
            "subcategory":"Retail Goods",
            "type":"Manufacturing & Wholesale Goods"
        }
    ],
    "sg:phone":"+1 323 838 0600",
    "sg:postcode":"90022",
    "sg:province":"CA",
    "sg:tags":[
        "manufacturer"
    ],
    "wof:name":"JRM Industries Inc",
    "wof:placetype":"venue"
},
  "geometry": {"coordinates":[-118.15648,34.014615],"type":"Point"}
}