{
  "type": "Feature",
  "properties": {
    "iso:country":"US",
    "sg:address":"1614 Sage Ave",
    "sg:city":"Los Osos",
    "sg:classifiers":[
        {
            "category":"Wholesale",
            "subcategory":"Plants",
            "type":"Manufacturing & Wholesale Goods"
        }
    ],
    "sg:phone":"+1 805 528 0181",
    "sg:postcode":"93402",
    "sg:province":"CA",
    "sg:tags":[
        "supply",
        "beverage",
        "alcoholic"
    ],
    "wof:name":"Orchids Of Los Osos",
    "wof:placetype":"venue"
},
  "geometry": {"coordinates":[-120.817072,35.319596],"type":"Point"}
}