{
  "type": "Feature",
  "properties": {
    "addr:full":"24812 Dana Dr Dana Point CA 92629",
    "addr:housenumber":"24812",
    "addr:postcode":"92629",
    "addr:street":"Dana Dr",
    "iso:country":"US",
    "sg:address":"24812 Dana Dr",
    "sg:city":"Dana Point",
    "sg:classifiers":[
        {
            "category":"Building & Trades",
            "subcategory":"Construction",
            "type":"Services"
        }
    ],
    "sg:phone":"+1 949 240 0293",
    "sg:postcode":"92629",
    "sg:province":"CA",
    "sg:tags":[
        "house"
    ],
    "wof:name":"Mark Stodder Construction",
    "wof:placetype":"venue"
},
  "geometry": {"coordinates":[-117.696225,33.457962],"type":"Point"}
}