{
  "type": "Feature",
  "properties": {
    "addr:full":"875 Fremont Ave San Leandro CA 94577",
    "addr:housenumber":"875",
    "addr:postcode":"94577",
    "addr:street":"Fremont Ave",
    "iso:country":"US",
    "sg:address":"875 Fremont Ave",
    "sg:city":"San Leandro",
    "sg:classifiers":[
        {
            "category":"Professional",
            "type":"Services"
        }
    ],
    "sg:phone":"+1 510 618 2400",
    "sg:postcode":"94577",
    "sg:province":"CA",
    "wof:name":"Torres Team Inc",
    "wof:placetype":"venue"
},
  "geometry": {"coordinates":[-122.150609,37.703413],"type":"Point"}
}