{
  "type": "Feature",
  "properties": {
    "addr:full":"2717 E 7th St Long Beach CA 90804",
    "addr:housenumber":"2717",
    "addr:postcode":"90804",
    "addr:street":"E 7Th St",
    "iso:country":"US",
    "sg:address":"2717 E 7th St",
    "sg:city":"Long Beach",
    "sg:classifiers":[
        {
            "category":"Social Services",
            "subcategory":"Child Care",
            "type":"Services"
        }
    ],
    "sg:phone":"+1 562 856 9315",
    "sg:postcode":"90804",
    "sg:province":"CA",
    "wof:name":"Robinson Family Day Care",
    "wof:placetype":"venue"
},
  "geometry": {"coordinates":[-118.15907900000001,33.775409],"type":"Point"}
}