{
  "type": "Feature",
  "properties": {
    "iso:country":"US",
    "sg:address":"15463 Fairfield Ranch Rd ",
    "sg:city":"Chino Hills",
    "sg:classifiers":[
        {
            "category":"Restaurant",
            "type":"Food & Drink"
        }
    ],
    "sg:menulink":"http://www.allmenus.com/ca/ontario/292657-first-class-pizza-chino-hills/menu/",
    "sg:phone":"+1 909 393 3530",
    "sg:postcode":"91709",
    "sg:province":"CA",
    "sg:tags":[
        "pizza"
    ],
    "wof:name":"First Class Pizza Chino Hills",
    "wof:placetype":"venue"
},
  "geometry": {"coordinates":[-117.690107,33.971735],"type":"Point"}
}