{
  "type": "Feature",
  "properties": {
    "iso:country":"US",
    "sg:address":"614 Walnut St",
    "sg:city":"Red Bluff",
    "sg:classifiers":[
        {
            "category":"Autos & Motor Vehicles",
            "subcategory":"Auto Supplies",
            "type":"Retail Goods"
        }
    ],
    "sg:phone":"+1 530 529 1612",
    "sg:postcode":"96080",
    "sg:province":"CA",
    "sg:tags":[
        "tire"
    ],
    "wof:name":"Bob's Tire Ctr",
    "wof:placetype":"venue"
},
  "geometry": {"coordinates":[-122.238893,40.176825],"type":"Point"}
}