{
  "type": "Feature",
  "properties": {
    "addr:full":"2601 Spring St Redwood City CA 94063",
    "addr:housenumber":"2601",
    "addr:postcode":"94063",
    "addr:street":"Spring St",
    "iso:country":"US",
    "sg:address":"2601 Spring St",
    "sg:city":"Redwood City",
    "sg:classifiers":[
        {
            "category":"Professional",
            "subcategory":"Research",
            "type":"Services"
        }
    ],
    "sg:phone":"+1 650 367 9600",
    "sg:postcode":"94063",
    "sg:province":"CA",
    "sg:tags":[
        "biotechnology",
        "product"
    ],
    "wof:name":"Agilent Technologies Inc",
    "wof:placetype":"venue"
},
  "geometry": {"coordinates":[-122.207685,37.482245],"type":"Point"}
}