{
  "type": "Feature",
  "properties": {
    "iso:country":"US",
    "sg:address":"26624 Shadow Wood Dr",
    "sg:city":"Rancho Pls Vrds",
    "sg:classifiers":[
        {
            "category":"Professional",
            "subcategory":"Research",
            "type":"Services"
        }
    ],
    "sg:phone":"+1 310 375 1558",
    "sg:postcode":"90275",
    "sg:province":"CA",
    "sg:tags":[
        "educational"
    ],
    "wof:name":"St Joseph Sciences Inc",
    "wof:placetype":"venue"
},
  "geometry": {"coordinates":[-118.370788,33.782659],"type":"Point"}
}