{
  "type": "Feature",
  "properties": {
    "iso:country":"US",
    "sg:address":"252 Washington Blvd",
    "sg:city":"Fremont",
    "sg:classifiers":[
        {
            "category":"Personal",
            "subcategory":"Beauty Salon",
            "type":"Services"
        }
    ],
    "sg:phone":"+1 510 490 1904",
    "sg:postcode":"94539",
    "sg:province":"CA",
    "wof:name":"Jendra's Irma",
    "wof:placetype":"venue"
},
  "geometry": {"coordinates":[-121.921964,37.533101],"type":"Point"}
}