{
  "type": "Feature",
  "properties": {
    "addr:full":"10744 Foothill Blvd Rancho Cucamonga CA 91730",
    "addr:housenumber":"10744",
    "addr:postcode":"91730",
    "addr:street":"Foothill Blvd",
    "iso:country":"US",
    "sg:address":"10744 Foothill Blvd",
    "sg:city":"Rancho Cucamonga",
    "sg:classifiers":[
        {
            "category":"Shopping",
            "subcategory":"Department Store",
            "type":"Retail Goods"
        }
    ],
    "sg:phone":"+1 909 466 9811",
    "sg:postcode":"91730",
    "sg:province":"CA",
    "wof:name":"Ross Dress For Less",
    "wof:placetype":"venue"
},
  "geometry": {"coordinates":[-117.567864,34.106572],"type":"Point"}
}