{
  "type": "Feature",
  "properties": {
    "addr:full":"947 Burman Dr San Jose CA 95111",
    "addr:housenumber":"947",
    "addr:postcode":"95111",
    "addr:street":"Burman Dr",
    "iso:country":"US",
    "sg:address":"947 Burman Dr",
    "sg:city":"San Jose",
    "sg:classifiers":[
        {
            "category":"Shopping",
            "subcategory":"Florist",
            "type":"Retail Goods"
        }
    ],
    "sg:phone":"+1 408 972 8112",
    "sg:postcode":"95111",
    "sg:province":"CA",
    "wof:name":"Oanhs Florist",
    "wof:placetype":"venue"
},
  "geometry": {"coordinates":[-121.815371,37.284906],"type":"Point"}
}