{
  "type": "Feature",
  "properties": {
    "iso:country":"US",
    "sg:address":"9833 Garvey Ave",
    "sg:city":"El Monte",
    "sg:classifiers":[
        {
            "category":"Autos & Motor Vehicles",
            "subcategory":"Automobile Sales",
            "type":"Retail Goods"
        },
        {
            "category":"Wholesale",
            "subcategory":"Motor Vehicles",
            "type":"Manufacturing & Wholesale Goods"
        }
    ],
    "sg:phone":"+1 626 350 3266",
    "sg:postcode":"91733",
    "sg:province":"CA",
    "sg:tags":[
        "car",
        "dealer"
    ],
    "wof:name":"Al Auto Wholesale",
    "wof:placetype":"venue"
},
  "geometry": {"coordinates":[-118.05560800000001,34.062785],"type":"Point"}
}