{
  "type": "Feature",
  "properties": {
    "iso:country":"US",
    "sg:address":"507 N Granada Ave",
    "sg:city":"Alhambra",
    "sg:classifiers":[
        {
            "category":"Government",
            "subcategory":"Office",
            "type":"Public Place"
        }
    ],
    "sg:phone":"+1 626 289 0223",
    "sg:postcode":"91801",
    "sg:province":"CA",
    "sg:tags":[
        "administrative",
        "program",
        "health"
    ],
    "wof:name":"St Joseph Center",
    "wof:placetype":"venue"
},
  "geometry": {"coordinates":[-118.120969,34.10388],"type":"Point"}
}