{
  "type": "Feature",
  "properties": {
    "addr:full":"1900 Saturn Ct Ceres CA 95307",
    "addr:housenumber":"1900",
    "addr:postcode":"95307",
    "addr:street":"Saturn Ct",
    "iso:country":"US",
    "sg:address":"1900 Saturn Ct",
    "sg:city":"Ceres",
    "sg:classifiers":[
        {
            "category":"Building & Trades",
            "subcategory":"Landscaping Services",
            "type":"Services"
        }
    ],
    "sg:phone":"+1 209 538 0621",
    "sg:postcode":"95307",
    "sg:province":"CA",
    "sg:tags":[
        "landscape"
    ],
    "wof:name":"Plush Gardens Landscape Maint",
    "wof:placetype":"venue"
},
  "geometry": {"coordinates":[-120.933121,37.60129],"type":"Point"}
}