{
  "type": "Feature",
  "properties": {
    "addr:full":"7 Raffles Ct Petaluma CA 94954",
    "addr:housenumber":"7",
    "addr:postcode":"94954",
    "addr:street":"Raffles Ct",
    "iso:country":"US",
    "sg:address":"7 Raffles Ct",
    "sg:city":"Petaluma",
    "sg:classifiers":[
        {
            "category":"Professional",
            "subcategory":"Computer Services",
            "type":"Services"
        }
    ],
    "sg:phone":"+1 707 781 7200",
    "sg:postcode":"94954",
    "sg:province":"CA",
    "sg:tags":[
        "hardware",
        "provider",
        "internet",
        "software"
    ],
    "wof:name":"Databright Management Systems",
    "wof:placetype":"venue"
},
  "geometry": {"coordinates":[-122.591866,38.24502],"type":"Point"}
}