{
  "type": "Feature",
  "properties": {
    "addr:full":"224 W 8th Ave Chico CA 95926",
    "addr:housenumber":"224",
    "addr:postcode":"95926",
    "addr:street":"W 8Th Ave",
    "iso:country":"US",
    "sg:address":"224 W 8th Ave",
    "sg:city":"Chico",
    "sg:classifiers":[
        {
            "category":"Manufacturing",
            "subcategory":"Metals",
            "type":"Manufacturing & Wholesale Goods"
        }
    ],
    "sg:phone":"+1 530 895 1762",
    "sg:postcode":"95926",
    "sg:province":"CA",
    "sg:tags":[
        "blade"
    ],
    "wof:name":"Fanno Saw Works",
    "wof:placetype":"venue"
},
  "geometry": {"coordinates":[-121.85266,39.744479],"type":"Point"}
}