{
  "type": "Feature",
  "properties": {
    "iso:country":"US",
    "sg:address":"Inside Image USA Salon 1645 Hollenbeck Ave.",
    "sg:city":"Sunnyvale",
    "sg:classifiers":[
        {
            "category":"Personal",
            "subcategory":"Beauty Salon",
            "type":"Services"
        },
        {
            "category":"Personal",
            "subcategory":"Nail Salon",
            "type":"Services"
        }
    ],
    "sg:phone":"+1 408 398 4892",
    "sg:postcode":"94087",
    "sg:province":"CA",
    "sg:tags":[
        "hair"
    ],
    "sg:website":"www.charshairdesign.com",
    "wof:name":"Char's Hair Design +",
    "wof:placetype":"venue"
},
  "geometry": {"coordinates":[-122.04154,37.339933],"type":"Point"}
}