{
  "type": "Feature",
  "properties": {
    "iso:country":"US",
    "sg:address":"564 Briarwood Ct",
    "sg:city":"Los Banos",
    "sg:classifiers":[
        {
            "category":"Retail",
            "subcategory":"Repair Shop",
            "type":"Services"
        }
    ],
    "sg:phone":"+1 209 826 3791",
    "sg:postcode":"93635",
    "sg:province":"CA",
    "sg:tags":[
        "lock",
        "locksmith"
    ],
    "wof:name":"Kirkland's Key & Locks",
    "wof:placetype":"venue"
},
  "geometry": {"coordinates":[-120.840527,37.079897],"type":"Point"}
}