{
  "type": "Feature",
  "properties": {
    "iso:country":"US",
    "sg:address":"10028 Adams Ave",
    "sg:city":"Huntington Beach",
    "sg:classifiers":[
        {
            "category":"Health Services",
            "subcategory":"Dentist",
            "type":"Services"
        }
    ],
    "sg:phone":"+1 714 962 4070",
    "sg:postcode":"92646",
    "sg:province":"CA",
    "sg:website":"www.swaroopdental.com",
    "wof:name":"Swaroop Dental",
    "wof:placetype":"venue"
},
  "geometry": {"coordinates":[-117.947205,33.672513],"type":"Point"}
}