{
  "type": "Feature",
  "properties": {
    "addr:full":"950 Paintbrush Dr Madera CA 93637",
    "addr:housenumber":"950",
    "addr:postcode":"93637",
    "addr:street":"Paintbrush Dr",
    "iso:country":"US",
    "sg:address":"950 Paintbrush Dr",
    "sg:city":"Madera",
    "sg:classifiers":[
        {
            "category":"Manufacturing",
            "subcategory":"Metals",
            "type":"Manufacturing & Wholesale Goods"
        }
    ],
    "sg:phone":"+1 559 674 0489",
    "sg:postcode":"93637",
    "sg:province":"CA",
    "sg:tags":[
        "hardware",
        "tool",
        "store",
        "mfg"
    ],
    "sg:website":"http://www.snapon.com",
    "wof:name":"Snap-On Tools",
    "wof:placetype":"venue"
},
  "geometry": {"coordinates":[-120.097849,36.964035],"type":"Point"}
}