{
  "type": "Feature",
  "properties": {
    "addr:full":"1575 Lander Ave Turlock CA 95380",
    "addr:housenumber":"1575",
    "addr:postcode":"95380",
    "addr:street":"Lander Ave",
    "iso:country":"US",
    "sg:address":"1575 Lander Ave",
    "sg:city":"Turlock",
    "sg:classifiers":[
        {
            "category":"Building & Trades",
            "subcategory":"Plumbing",
            "type":"Services"
        }
    ],
    "sg:phone":"+1 209 632 7596",
    "sg:postcode":"95380",
    "sg:province":"CA",
    "sg:tags":[
        "conditioning",
        "air",
        "system",
        "contractor"
    ],
    "wof:name":"Wally Falke's Air Cond Inc",
    "wof:placetype":"venue"
},
  "geometry": {"coordinates":[-120.84904899999999,37.478401],"type":"Point"}
}