{
  "type": "Feature",
  "properties": {
    "addr:full":"201 S Lake Ave Pasadena CA 91101",
    "addr:housenumber":"201",
    "addr:postcode":"91101",
    "addr:street":"S Lake Ave",
    "iso:country":"US",
    "sg:address":"201 S Lake Ave",
    "sg:city":"Pasadena",
    "sg:classifiers":[
        {
            "category":"Professional",
            "subcategory":"Lawyer & Legal Services",
            "type":"Services"
        }
    ],
    "sg:phone":"+1 626 583 8000",
    "sg:postcode":"91101",
    "sg:province":"CA",
    "wof:name":"Hawekotte Angela Atty",
    "wof:placetype":"venue"
},
  "geometry": {"coordinates":[-118.13200399999999,34.142399],"type":"Point"}
}