{
  "type": "Feature",
  "properties": {
    "addr:full":"1401 Satinwood Ct Riverside CA 92501",
    "addr:housenumber":"1401",
    "addr:postcode":"92501",
    "addr:street":"Satinwood Ct",
    "iso:country":"US",
    "sg:address":"1401 Satinwood Ct",
    "sg:city":"Riverside",
    "sg:classifiers":[
        {
            "category":"Real Estate",
            "subcategory":"Real Estate Operator",
            "type":"Services"
        }
    ],
    "sg:phone":"+1 951 787 0649",
    "sg:postcode":"92501",
    "sg:province":"CA",
    "sg:tags":[
        "apartment"
    ],
    "wof:name":"Breezewood Apartments",
    "wof:placetype":"venue"
},
  "geometry": {"coordinates":[-117.365148,34.003399],"type":"Point"}
}