{
  "type": "Feature",
  "properties": {
    "addr:full":"902 Alice Ave Ukiah CA 95482",
    "addr:housenumber":"902",
    "addr:postcode":"ca 95482",
    "addr:street":"Alice Ave",
    "iso:country":"US",
    "sg:address":"902 Alice Ave",
    "sg:city":"Ukiah",
    "sg:classifiers":[
        {
            "category":"Freight",
            "type":"Transportation"
        }
    ],
    "sg:phone":"+1 707 462 2511",
    "sg:postcode":"95482",
    "sg:province":"CA",
    "sg:tags":[
        "operator",
        "trucking"
    ],
    "wof:name":"Tony Engels Trucking",
    "wof:placetype":"venue"
},
  "geometry": {"coordinates":[-123.211516,39.139471],"type":"Point"}
}