{
  "type": "Feature",
  "properties": {
    "addr:full":"270 Commerce St Lodi CA 95240",
    "addr:housenumber":"270",
    "addr:postcode":"95240",
    "addr:street":"Commerce St",
    "iso:country":"US",
    "sg:address":"270 Commerce St",
    "sg:city":"Lodi",
    "sg:classifiers":[
        {
            "category":"Manufacturing",
            "subcategory":"Tools & Machinery",
            "type":"Manufacturing & Wholesale Goods"
        }
    ],
    "sg:phone":"+1 209 333 2473",
    "sg:postcode":"95240",
    "sg:province":"CA",
    "sg:tags":[
        "machine",
        "shop"
    ],
    "wof:name":"Lin-Don Machining",
    "wof:placetype":"venue"
},
  "geometry": {"coordinates":[-121.249234,38.131002],"type":"Point"}
}