{
  "type": "Feature",
  "properties": {
    "iso:country":"US",
    "sg:address":"621 W Ave J",
    "sg:city":"Lancaster",
    "sg:classifiers":[
        {
            "category":"Autos & Motor Vehicles",
            "subcategory":"Auto Supplies",
            "type":"Retail Goods"
        }
    ],
    "sg:phone":"+1 661 945 8628",
    "sg:postcode":"93534",
    "sg:province":"CA",
    "sg:tags":[
        "automobile",
        "parts"
    ],
    "wof:name":"Don's Auto Parts",
    "wof:placetype":"venue"
},
  "geometry": {"coordinates":[-118.138825,34.689458],"type":"Point"}
}