{
  "type": "Feature",
  "properties": {
    "addr:full":"32889 Sky Blue Water Trl Palm Springs CA 92234",
    "addr:housenumber":"32889",
    "addr:postcode":"92234",
    "addr:street":"Sky Blue Water Trl",
    "iso:country":"US",
    "sg:address":"32889 Sky Blue Water Trl",
    "sg:city":"Palm Springs",
    "sg:classifiers":[
        {
            "category":"Retail",
            "subcategory":"Repair Shop",
            "type":"Services"
        }
    ],
    "sg:phone":"+1 760 328 9672",
    "sg:postcode":"92234",
    "sg:province":"CA",
    "wof:name":"Inland Empire Equipment",
    "wof:placetype":"venue"
},
  "geometry": {"coordinates":[-116.47018199999999,33.81159],"type":"Point"}
}