{
  "type": "Feature",
  "properties": {
    "addr:full":"130 Crestview Ct Watsonville CA 95076",
    "addr:housenumber":"130",
    "addr:postcode":"95076",
    "addr:street":"Crestview Ct",
    "iso:country":"US",
    "sg:address":"130 Crestview Ct",
    "sg:city":"Watsonville",
    "sg:classifiers":[
        {
            "category":"Building & Trades",
            "subcategory":"Cleaning & Sanitation",
            "type":"Services"
        }
    ],
    "sg:phone":"+1 831 761 1560",
    "sg:postcode":"95076",
    "sg:province":"CA",
    "sg:tags":[
        "janitor"
    ],
    "wof:name":"3 Great K's Auto Detailing",
    "wof:placetype":"venue"
},
  "geometry": {"coordinates":[-121.760732,36.926506],"type":"Point"}
}