{
  "type": "Feature",
  "properties": {
    "iso:country":"US",
    "sg:address":"180 W Highland Ave",
    "sg:city":"San Bernardino",
    "sg:classifiers":[
        {
            "category":"Real Estate",
            "subcategory":"Real Estate Agent",
            "type":"Services"
        }
    ],
    "sg:phone":"+1 909 886 7851",
    "sg:postcode":"92405",
    "sg:province":"CA",
    "wof:name":"Shidler Development Inc",
    "wof:placetype":"venue"
},
  "geometry": {"coordinates":[-117.287408,34.136028],"type":"Point"}
}