{
  "type": "Feature",
  "properties": {
    "iso:country":"US",
    "sg:address":"898 Douglas Blvd",
    "sg:city":"Roseville",
    "sg:classifiers":[
        {
            "category":"Wholesale",
            "subcategory":"Machinery & Supplies",
            "type":"Manufacturing & Wholesale Goods"
        }
    ],
    "sg:phone":"+1 916 774 4430",
    "sg:postcode":"95678",
    "sg:province":"CA",
    "sg:tags":[
        "industrial"
    ],
    "wof:name":"P & H Representatives Inc",
    "wof:placetype":"venue"
},
  "geometry": {"coordinates":[-121.280758,38.743851],"type":"Point"}
}