{
  "type": "Feature",
  "properties": {
    "addr:full":"898 Douglas Blvd Roseville CA 95678",
    "addr:housenumber":"898",
    "addr:postcode":"95678",
    "addr:street":"Douglas Blvd",
    "iso:country":"US",
    "sg:address":"898 Douglas Blvd",
    "sg:city":"Roseville",
    "sg:classifiers":[
        {
            "category":"Wholesale",
            "subcategory":"Machinery & Supplies",
            "type":"Manufacturing & Wholesale Goods"
        }
    ],
    "sg:phone":"+1 916 774 4430",
    "sg:postcode":"95678",
    "sg:province":"CA",
    "sg:tags":[
        "industrial"
    ],
    "wof:name":"P & H Representatives Inc",
    "wof:placetype":"venue"
},
  "geometry": {"coordinates":[-121.28075800000001,38.743851],"type":"Point"}
}