{
  "type": "Feature",
  "properties": {
    "iso:country":"US",
    "sg:address":"23639 Hawthorne Blvd",
    "sg:city":"Torrance",
    "sg:classifiers":[
        {
            "category":"Building & Trades",
            "subcategory":"Landscaping Services",
            "type":"Services"
        }
    ],
    "sg:phone":"+1 310 373 3347",
    "sg:postcode":"90505",
    "sg:province":"CA",
    "sg:tags":[
        "designer",
        "landscape"
    ],
    "wof:name":"Martin Design Associates",
    "wof:placetype":"venue"
},
  "geometry": {"coordinates":[-118.35109,33.809418],"type":"Point"}
}