{
  "type": "Feature",
  "properties": {
    "addr:full":"3535 J St San Diego CA 92102",
    "addr:housenumber":"3535",
    "addr:postcode":"92102",
    "addr:street":"J St",
    "iso:country":"US",
    "sg:address":"3535 J St",
    "sg:city":"San Diego",
    "sg:classifiers":[
        {
            "category":"Manufacturing",
            "subcategory":"Jewelry",
            "type":"Manufacturing & Wholesale Goods"
        }
    ],
    "sg:phone":"+1 619 233 3521",
    "sg:postcode":"92102",
    "sg:province":"CA",
    "sg:tags":[
        "costume",
        "mfg"
    ],
    "wof:name":"Telma",
    "wof:placetype":"venue"
},
  "geometry": {"coordinates":[-117.117251,32.70941],"type":"Point"}
}