{
  "type": "Feature",
  "properties": {
    "iso:country":"US",
    "sg:address":"1180 Industrial St",
    "sg:city":"Redding",
    "sg:classifiers":[
        {
            "category":"Wholesale",
            "subcategory":"Durable Goods & Equipment",
            "type":"Manufacturing & Wholesale Goods"
        }
    ],
    "sg:phone":"+1 530 223 2492",
    "sg:postcode":"96002",
    "sg:province":"CA",
    "sg:tags":[
        "fire",
        "extinguisher",
        "business"
    ],
    "wof:name":"Shasta Fire Equipment Co",
    "wof:placetype":"venue"
},
  "geometry": {"coordinates":[-122.351994,40.574814],"type":"Point"}
}