{
  "type": "Feature",
  "properties": {
    "addr:full":"11712 Moorpark St Studio City CA 91604",
    "addr:housenumber":"11712",
    "addr:postcode":"91604",
    "addr:street":"Moorpark St",
    "iso:country":"US",
    "sg:address":"11712 Moorpark St",
    "sg:city":"Studio City",
    "sg:classifiers":[
        {
            "category":"Professional",
            "type":"Services"
        }
    ],
    "sg:phone":"+1 818 752 0267",
    "sg:postcode":"91604",
    "sg:province":"CA",
    "wof:name":"Emori USA Corporation",
    "wof:placetype":"venue"
},
  "geometry": {"coordinates":[-118.388465,34.150292],"type":"Point"}
}