{
  "type": "Feature",
  "properties": {
    "iso:country":"US",
    "sg:address":"100 Breen Rd",
    "sg:city":"San Jn Bautista",
    "sg:classifiers":[
        {
            "category":"Wholesale",
            "subcategory":"Farm Supplies",
            "type":"Manufacturing & Wholesale Goods"
        },
        {
            "category":"Farming",
            "subcategory":"Farm",
            "type":"Manufacturing & Wholesale Goods"
        }
    ],
    "sg:phone":"+1 831 623 4216",
    "sg:postcode":"95045",
    "sg:province":"CA",
    "sg:tags":[
        "bulb",
        "seed"
    ],
    "wof:name":"Nong Woo Seed America  Inc",
    "wof:placetype":"venue"
},
  "geometry": {"coordinates":[-121.52446,36.841279],"type":"Point"}
}