{
  "type": "Feature",
  "properties": {
    "iso:country":"US",
    "sg:address":"2202 Signal Pl",
    "sg:city":"San Pedro",
    "sg:classifiers":[
        {
            "category":"Wholesale",
            "subcategory":"Seafood",
            "type":"Manufacturing & Wholesale Goods"
        }
    ],
    "sg:phone":"+1 310 832 1195",
    "sg:postcode":"90731",
    "sg:province":"CA",
    "sg:tags":[
        "fish"
    ],
    "wof:name":"H E Barnett Inc",
    "wof:placetype":"venue"
},
  "geometry": {"coordinates":[-118.273928,33.726044],"type":"Point"}
}