{
  "type": "Feature",
  "properties": {
    "addr:full":"2000 Van Ness Avenue San Francisco CA 94109",
    "addr:housenumber":"2000",
    "addr:postcode":"94109",
    "addr:street":"Van Ness Avenue",
    "iso:country":"US",
    "sg:address":"2000 Van Ness Avenue",
    "sg:city":"San Francisco",
    "sg:classifiers":[
        {
            "category":"Health Services",
            "subcategory":"Doctor",
            "type":"Services"
        }
    ],
    "sg:phone":"+1 415 931 9881",
    "sg:postcode":"94109",
    "sg:province":"CA",
    "sg:website":"www.rosanelli.com",
    "wof:name":"Rosanelli Thomas MD",
    "wof:placetype":"venue"
},
  "geometry": {"coordinates":[-122.422967,37.793991],"type":"Point"}
}