{
  "type": "Feature",
  "properties": {
    "iso:country":"US",
    "sg:address":"6904 Miramar Rd Ste 102",
    "sg:city":"San Diego",
    "sg:classifiers":[
        {
            "category":"Personal",
            "type":"Services"
        },
        {
            "category":"Education",
            "subcategory":"Dance Studio",
            "type":"Public Place"
        }
    ],
    "sg:phone":"+1 858 472 9835",
    "sg:postcode":"92121",
    "sg:province":"CA",
    "sg:tags":[
        "party",
        "planning",
        "event"
    ],
    "sg:website":"www.sexysilhouettesbysara.com",
    "wof:name":"Sexy Silhouettes By Sara: San Diego Premier Pole Dancing School",
    "wof:placetype":"venue"
},
  "geometry": {"coordinates":[-117.167478,32.879192],"type":"Point"}
}