{
  "type": "Feature",
  "properties": {
    "addr:full":"667 Montclair Dr Santa Rosa CA 95409",
    "addr:housenumber":"667",
    "addr:postcode":"95409",
    "addr:street":"Montclair Dr",
    "iso:country":"US",
    "sg:address":"667 Montclair Dr",
    "sg:city":"Santa Rosa",
    "sg:classifiers":[
        {
            "category":"Insurance",
            "subcategory":"Insurance Agent",
            "type":"Services"
        }
    ],
    "sg:phone":"+1 707 537 2256",
    "sg:postcode":"95409",
    "sg:province":"CA",
    "wof:name":"Loveland Insurance Services",
    "wof:placetype":"venue"
},
  "geometry": {"coordinates":[-122.652626,38.475969],"type":"Point"}
}