{
  "type": "Feature",
  "properties": {
    "addr:full":"3633 Concord Blvd Concord CA 94519",
    "addr:housenumber":"3633",
    "addr:postcode":"94519",
    "addr:street":"Concord Blvd",
    "iso:country":"US",
    "sg:address":"3633 Concord Blvd",
    "sg:city":"Concord",
    "sg:classifiers":[
        {
            "category":"Home & Garden",
            "subcategory":"Hardware",
            "type":"Retail Goods"
        }
    ],
    "sg:phone":"+1 415 531 8665",
    "sg:postcode":"94519",
    "sg:province":"CA",
    "sg:tags":[
        "machine",
        "tool",
        "mfg",
        "accessory"
    ],
    "wof:name":"Snap-On Tools",
    "wof:placetype":"venue"
},
  "geometry": {"coordinates":[-122.00973500000001,37.977761],"type":"Point"}
}