{
  "type": "Feature",
  "properties": {
    "iso:country":"US",
    "sg:address":"44 N Lassen St",
    "sg:city":"Susanville",
    "sg:classifiers":[
        {
            "category":"Sports & Exercise",
            "subcategory":"Gym",
            "type":"Entertainment"
        }
    ],
    "sg:phone":"+1 530 257 2882",
    "sg:postcode":"96130",
    "sg:province":"CA",
    "sg:tags":[
        "club",
        "health",
        "studio",
        "gymnasium"
    ],
    "wof:name":"Divas Health & Fitness",
    "wof:placetype":"venue"
},
  "geometry": {"coordinates":[-120.661705,40.419219],"type":"Point"}
}