{
  "type": "Feature",
  "properties": {
    "iso:country":"US",
    "sg:address":"4138 Napier St",
    "sg:city":"San Diego",
    "sg:classifiers":[
        {
            "category":"Professional",
            "type":"Services"
        }
    ],
    "sg:phone":"+1 619 275 0696",
    "sg:postcode":"92110",
    "sg:province":"CA",
    "sg:tags":[
        "arts",
        "artist"
    ],
    "wof:name":"Bay Park Press",
    "wof:placetype":"venue"
},
  "geometry": {"coordinates":[-117.206377,32.782327],"type":"Point"}
}