{
  "type": "Feature",
  "properties": {
    "addr:full":"611 S Hill St Los Angeles CA 90014",
    "addr:housenumber":"611",
    "addr:postcode":"90014",
    "addr:street":"S Hill St",
    "iso:country":"US",
    "sg:address":"611 S Hill St",
    "sg:city":"Los Angeles",
    "sg:classifiers":[
        {
            "category":"Manufacturing",
            "subcategory":"Jewelry",
            "type":"Manufacturing & Wholesale Goods"
        }
    ],
    "sg:phone":"+1 213 689 9680",
    "sg:postcode":"90014",
    "sg:province":"CA",
    "sg:tags":[
        "precious",
        "metal",
        "mfg"
    ],
    "wof:name":"Vartanyan Serkis",
    "wof:placetype":"venue"
},
  "geometry": {"coordinates":[-118.254394,34.046101],"type":"Point"}
}