{
  "type": "Feature",
  "properties": {
    "addr:full":"571 Hillsdale Ave Santa Clara CA 95051",
    "addr:housenumber":"571",
    "addr:postcode":"95051",
    "addr:street":"Hillsdale Ave",
    "iso:country":"US",
    "sg:address":"571 Hillsdale Ave",
    "sg:city":"Santa Clara",
    "sg:phone":"+1 408 244 9485",
    "sg:postcode":"95051",
    "sg:province":"CA",
    "sg:tags":[
        "shelving"
    ],
    "wof:name":"Indoff Inc",
    "wof:placetype":"venue"
},
  "geometry": {"coordinates":[-121.997922,37.331527],"type":"Point"}
}