{
  "type": "Feature",
  "properties": {
    "addr:full":"816 Hurlingame Ave Redwood City CA 94063",
    "addr:housenumber":"816",
    "addr:postcode":"94063",
    "addr:street":"Hurlingame Ave",
    "iso:country":"US",
    "sg:address":"816 Hurlingame Ave",
    "sg:city":"Redwood City",
    "sg:classifiers":[
        {
            "category":"Retail",
            "subcategory":"Repair Shop",
            "type":"Services"
        }
    ],
    "sg:phone":"+1 650 369 2234",
    "sg:postcode":"94063",
    "sg:province":"CA",
    "sg:tags":[
        "lighting",
        "fixture"
    ],
    "wof:name":"Archbold Electric",
    "wof:placetype":"venue"
},
  "geometry": {"coordinates":[-122.206587,37.483613],"type":"Point"}
}