{
  "type": "Feature",
  "properties": {
    "addr:full":"455 Hyde St San Francisco CA 94109",
    "addr:housenumber":"455",
    "addr:postcode":"94109",
    "addr:street":"Hyde St",
    "iso:country":"US",
    "sg:address":"455 Hyde St",
    "sg:city":"San Francisco",
    "sg:classifiers":[
        {
            "category":"Local Transit",
            "type":"Transportation"
        }
    ],
    "sg:phone":"+1 415 309 7066",
    "sg:postcode":"94109",
    "sg:province":"CA",
    "sg:tags":[
        "limousine"
    ],
    "wof:name":"Worldwide Personal Service",
    "wof:placetype":"venue"
},
  "geometry": {"coordinates":[-122.416252,37.784853],"type":"Point"}
}