{
  "type": "Feature",
  "properties": {
    "addr:full":"1250 N Berkeley Ave Turlock CA 95380",
    "addr:housenumber":"1250",
    "addr:postcode":"95380",
    "addr:street":"N Berkeley Ave",
    "iso:country":"US",
    "sg:address":"1250 N Berkeley Ave",
    "sg:city":"Turlock",
    "sg:classifiers":[
        {
            "category":"Professional",
            "subcategory":"Computer Services",
            "type":"Services"
        }
    ],
    "sg:phone":"+1 209 632 8256",
    "sg:postcode":"95380",
    "sg:province":"CA",
    "sg:tags":[
        "internet"
    ],
    "wof:name":"English Document Co",
    "wof:placetype":"venue"
},
  "geometry": {"coordinates":[-120.83063900000001,37.504521],"type":"Point"}
}