{
  "type": "Feature",
  "properties": {
    "iso:country":"US",
    "sg:address":"5300 E Olympic Blvd",
    "sg:city":"Los Angeles",
    "sg:classifiers":[
        {
            "category":"Restaurant",
            "type":"Food & Drink"
        }
    ],
    "sg:phone":"+1 323 260 4700",
    "sg:postcode":"90022",
    "sg:province":"CA",
    "sg:tags":[
        "mexican"
    ],
    "sg:website":"telacu.com/site/en/home/tamayo-r...",
    "wof:name":"Tamayo Restaurant",
    "wof:placetype":"venue"
},
  "geometry": {"coordinates":[-118.15799699999999,34.016201],"type":"Point"}
}