{
  "type": "Feature",
  "properties": {
    "iso:country":"US",
    "sg:address":"42 County Center Dr",
    "sg:city":"Oroville",
    "sg:classifiers":[
        {
            "category":"Government",
            "subcategory":"Office",
            "type":"Public Place"
        }
    ],
    "sg:phone":"+1 530 538 7269",
    "sg:postcode":"95965",
    "sg:province":"CA",
    "sg:tags":[
        "county",
        "resource"
    ],
    "wof:name":"District Attorney-Welfare Frd",
    "wof:placetype":"venue"
},
  "geometry": {"coordinates":[-121.570803,39.528493],"type":"Point"}
}