{
  "type": "Feature",
  "properties": {
    "addr:full":"30237 Floto St La Grange CA 95386",
    "addr:postcode":"30237;95386",
    "addr:street":"Floto St",
    "iso:country":"US",
    "sg:address":"30237 Floto St",
    "sg:city":"La Grange",
    "sg:classifiers":[
        {
            "category":"Education",
            "subcategory":"School",
            "type":"Public Place"
        }
    ],
    "sg:phone":"+1 209 853 2132",
    "sg:postcode":"95386",
    "sg:province":"CA",
    "wof:name":"LA Grange Elementary School",
    "wof:placetype":"venue"
},
  "geometry": {"coordinates":[-120.460142,37.661803],"type":"Point"}
}