{
  "type": "Feature",
  "properties": {
    "iso:country":"US",
    "sg:address":"1433 Burlingame Ave",
    "sg:city":"Burlingame",
    "sg:classifiers":[
        {
            "category":"Shopping",
            "subcategory":"Clothing, Apparel, & Fashions",
            "type":"Retail Goods"
        }
    ],
    "sg:phone":"+1 650 375 1933",
    "sg:postcode":"94010",
    "sg:province":"CA",
    "sg:tags":[
        "accessory",
        "clothing",
        "women's"
    ],
    "sg:website":"www.lesdeuxcopines.com",
    "wof:name":"Les Deux Copines",
    "wof:placetype":"venue"
},
  "geometry": {"coordinates":[-122.348618,37.577048],"type":"Point"}
}