{
  "type": "Feature",
  "properties": {
    "iso:country":"US",
    "sg:address":"319 Union Ave",
    "sg:city":"Pomona",
    "sg:classifiers":[
        {
            "category":"Building & Trades",
            "subcategory":"Plumbing",
            "type":"Services"
        }
    ],
    "sg:phone":"+1 909 984 1498",
    "sg:postcode":"91768",
    "sg:province":"CA",
    "sg:tags":[
        "plumbing",
        "contractor"
    ],
    "wof:name":"Roto-Rooter Plumbing & Drain",
    "wof:placetype":"venue"
},
  "geometry": {"coordinates":[-117.783244,34.059824],"type":"Point"}
}