{
  "type": "Feature",
  "properties": {
    "iso:country":"US",
    "sg:address":"9605 Rush St",
    "sg:city":"South El Monte",
    "sg:classifiers":[
        {
            "category":"Shopping",
            "subcategory":"Clothing, Apparel, & Fashions",
            "type":"Retail Goods"
        }
    ],
    "sg:phone":"+1 626 453 3598",
    "sg:postcode":"91733",
    "sg:province":"CA",
    "wof:name":"888 Star Fashion Inc",
    "wof:placetype":"venue"
},
  "geometry": {"coordinates":[-118.055697,34.051894],"type":"Point"}
}