{
  "type": "Feature",
  "properties": {
    "addr:full":"12950 Tranquility Ln Nevada City CA 95959",
    "addr:housenumber":"12950",
    "addr:postcode":"95959",
    "addr:street":"Tranquility Ln",
    "iso:country":"US",
    "sg:address":"12950 Tranquility Ln",
    "sg:city":"Nevada City",
    "sg:classifiers":[
        {
            "category":"Freight",
            "type":"Transportation"
        }
    ],
    "sg:phone":"+1 530 272 6741",
    "sg:postcode":"95959",
    "sg:province":"CA",
    "sg:tags":[
        "operator",
        "trucking"
    ],
    "wof:name":"3-D Logging",
    "wof:placetype":"venue"
},
  "geometry": {"coordinates":[-120.988918,39.231223],"type":"Point"}
}