{
  "type": "Feature",
  "properties": {
    "iso:country":"US",
    "sg:address":"351 Jack London Ave",
    "sg:city":"Alameda",
    "sg:classifiers":[
        {
            "category":"Place Of Worship",
            "subcategory":"Church",
            "type":"Public Place"
        }
    ],
    "sg:phone":"+1 510 520 5444",
    "sg:postcode":"94501",
    "sg:province":"CA",
    "sg:website":"www.thebridgepointchurch.com",
    "wof:name":"Bridge Point Church",
    "wof:placetype":"venue"
},
  "geometry": {"coordinates":[-122.285971,37.781757],"type":"Point"}
}