{
  "type": "Feature",
  "properties": {
    "addr:full":"139 N Western Ave Los Angeles CA 90004",
    "addr:housenumber":"139",
    "addr:postcode":"90004",
    "addr:street":"N Western Ave",
    "iso:country":"US",
    "sg:address":"139 N Western Ave",
    "sg:city":"Los Angeles",
    "sg:classifiers":[
        {
            "category":"Travel",
            "subcategory":"Travel Agent",
            "type":"Entertainment"
        }
    ],
    "sg:phone":"+1 323 960 0500",
    "sg:postcode":"90004",
    "sg:province":"CA",
    "sg:tags":[
        "agency"
    ],
    "wof:name":"Yes Travel",
    "wof:placetype":"venue"
},
  "geometry": {"coordinates":[-118.309214,34.074266],"type":"Point"}
}