{
  "type": "Feature",
  "properties": {
    "iso:country":"US",
    "sg:address":"651 St Marys Rd",
    "sg:city":"Lafayette",
    "sg:classifiers":[
        {
            "category":"Real Estate",
            "subcategory":"Real Estate Services",
            "type":"Services"
        },
        {
            "category":"Real Estate",
            "subcategory":"Real Estate Agent",
            "type":"Services"
        }
    ],
    "sg:phone":"+1 925 299 0079",
    "sg:postcode":"94549",
    "sg:province":"CA",
    "sg:tags":[
        "buyer",
        "broker"
    ],
    "wof:name":"Bryant Contractors & Real Esta",
    "wof:placetype":"venue"
},
  "geometry": {"coordinates":[-122.09799099999999,37.873123],"type":"Point"}
}