{
  "type": "Feature",
  "properties": {
    "addr:full":"83477 62nd Ave Thermal CA 92274",
    "addr:housenumber":"83477",
    "addr:postcode":"92274",
    "addr:street":"62Nd Ave",
    "iso:country":"US",
    "sg:address":"83477 62nd Ave",
    "sg:city":"Thermal",
    "sg:classifiers":[
        {
            "category":"Building & Trades",
            "subcategory":"Construction",
            "type":"Services"
        }
    ],
    "sg:phone":"+1 760 399 5194",
    "sg:postcode":"92274",
    "sg:province":"CA",
    "sg:tags":[
        "pipe",
        "line",
        "contractor"
    ],
    "wof:name":"Desert Pipeline Inc",
    "wof:placetype":"venue"
},
  "geometry": {"coordinates":[-116.215091,33.598242],"type":"Point"}
}