{
  "type": "Feature",
  "properties": {
    "addr:full":"20702 Lake Forest Dr Lake Forest CA 92630",
    "addr:housenumber":"20702",
    "addr:postcode":"92630",
    "addr:street":"Lake Forest Dr",
    "iso:country":"US",
    "sg:address":"20702 Lake Forest Dr",
    "sg:city":"Lake Forest",
    "sg:classifiers":[
        {
            "category":"Bars & Pubs",
            "subcategory":"Sports Bar",
            "type":"Food & Drink"
        },
        {
            "category":"Restaurant",
            "type":"Food & Drink"
        }
    ],
    "sg:phone":"+1 949 215 4081",
    "sg:postcode":"92630",
    "sg:province":"CA",
    "sg:tags":[
        "mexican"
    ],
    "sg:website":"www.loscaboscantinaandgrill.com",
    "wof:name":"Los Cabos Cantina",
    "wof:placetype":"venue"
},
  "geometry": {"coordinates":[-117.667241,33.661335],"type":"Point"}
}