{
  "type": "Feature",
  "properties": {
    "addr:full":"503 Majestic Way San Leandro CA 94578",
    "addr:housenumber":"503",
    "addr:postcode":"94578",
    "addr:street":"Majestic Way",
    "iso:country":"US",
    "sg:address":"503 Majestic Way",
    "sg:city":"San Leandro",
    "sg:classifiers":[
        {
            "category":"Retail",
            "subcategory":"Animal Services",
            "type":"Services"
        }
    ],
    "sg:phone":"+1 510 483 9866",
    "sg:postcode":"94578",
    "sg:province":"CA",
    "wof:name":"Adventurous Dog Training",
    "wof:placetype":"venue"
},
  "geometry": {"coordinates":[-122.142628,37.698765],"type":"Point"}
}