{
  "type": "Feature",
  "properties": {
    "iso:country":"US",
    "sg:address":"955 Opal St",
    "sg:city":"San Diego",
    "sg:classifiers":[
        {
            "category":"Shopping",
            "subcategory":"Catalog Store",
            "type":"Retail Goods"
        }
    ],
    "sg:phone":"+1 858 273 4562",
    "sg:postcode":"92109",
    "sg:province":"CA",
    "sg:tags":[
        "e"
    ],
    "wof:name":"Kenmark",
    "wof:placetype":"venue"
},
  "geometry": {"coordinates":[-117.25524,32.80658],"type":"Point"}
}