{
  "type": "Feature",
  "properties": {
    "iso:country":"US",
    "sg:address":"27625 Baseline St",
    "sg:city":"Highland",
    "sg:classifiers":[
        {
            "category":"Restaurant",
            "type":"Food & Drink"
        }
    ],
    "sg:menulink":"http://www.allmenus.com/ca/san-bernardino/175038-popeyes-chicken--biscuits/menu/",
    "sg:phone":"+1 909 864 3700",
    "sg:postcode":"92346",
    "sg:province":"CA",
    "sg:tags":[
        "american",
        "wing"
    ],
    "wof:name":"Popeyes Chicken & Biscuits",
    "wof:placetype":"venue"
},
  "geometry": {"coordinates":[-117.202567,34.12123],"type":"Point"}
}