{
  "type": "Feature",
  "properties": {
    "iso:country":"US",
    "sg:address":"950 Scott Ct",
    "sg:city":"Campbell",
    "sg:classifiers":[
        {
            "category":"Wholesale",
            "subcategory":"Plants",
            "type":"Manufacturing & Wholesale Goods"
        }
    ],
    "sg:phone":"+1 408 866 2549",
    "sg:postcode":"95008",
    "sg:province":"CA",
    "sg:tags":[
        "nursery",
        "tree"
    ],
    "wof:name":"Angus Mc Fong Home Garden",
    "wof:placetype":"venue"
},
  "geometry": {"coordinates":[-121.96575900000001,37.268298],"type":"Point"}
}