{
  "type": "Feature",
  "properties": {
    "iso:country":"US",
    "sg:address":"526 S Main St",
    "sg:city":"Yreka",
    "sg:classifiers":[
        {
            "category":"Travel",
            "subcategory":"Hotels & Motels",
            "type":"Entertainment"
        }
    ],
    "sg:phone":"+1 530 842 4404",
    "sg:postcode":"96097",
    "sg:province":"CA",
    "wof:name":"Economy Inn",
    "wof:placetype":"venue"
},
  "geometry": {"coordinates":[-122.637264,41.727543],"type":"Point"}
}