{
  "type": "Feature",
  "properties": {
    "iso:country":"US",
    "sg:address":"2089 E 14th St",
    "sg:city":"San Leandro",
    "sg:classifiers":[
        {
            "category":"Shopping",
            "subcategory":"Clothing, Apparel, & Fashions",
            "type":"Retail Goods"
        }
    ],
    "sg:phone":"+1 510 351 9412",
    "sg:postcode":"94577",
    "sg:province":"CA",
    "wof:name":"Fashion City",
    "wof:placetype":"venue"
},
  "geometry": {"coordinates":[-122.148312,37.719603],"type":"Point"}
}