{
  "type": "Feature",
  "properties": {
    "addr:full":"2837 Highland Ave National City CA 91950",
    "addr:housenumber":"2837",
    "addr:postcode":"91950",
    "addr:street":"Highland Ave",
    "iso:country":"US",
    "sg:address":"2837 Highland Ave",
    "sg:city":"National City",
    "sg:classifiers":[
        {
            "category":"Government",
            "subcategory":"Office",
            "type":"Public Place"
        },
        {
            "category":"Health Services",
            "subcategory":"Clinic",
            "type":"Services"
        }
    ],
    "sg:phone":"+1 619 477 4451",
    "sg:postcode":"91950",
    "sg:province":"CA",
    "sg:tags":[
        "community"
    ],
    "sg:website":"www.operationsamahan.org",
    "wof:name":"Operation Samahan Health",
    "wof:placetype":"venue"
},
  "geometry": {"coordinates":[-117.09134899999999,32.659487],"type":"Point"}
}