{
  "type": "Feature",
  "properties": {
    "iso:country":"US",
    "sg:address":"1750 Ladera Vista Dr",
    "sg:city":"Fullerton",
    "sg:classifiers":[
        {
            "category":"Real Estate",
            "subcategory":"Real Estate Operator",
            "type":"Services"
        }
    ],
    "sg:phone":"+1 714 870 0650",
    "sg:postcode":"92831",
    "sg:province":"CA",
    "sg:tags":[
        "builder",
        "dwelling",
        "operative"
    ],
    "wof:name":"Breuer-Harrison Inc",
    "wof:placetype":"venue"
},
  "geometry": {"coordinates":[-117.895399,33.889323],"type":"Point"}
}