{
  "type": "Feature",
  "properties": {
    "iso:country":"US",
    "sg:address":"1191 Riley St",
    "sg:city":"Folsom",
    "sg:classifiers":[
        {
            "category":"Autos & Motor Vehicles",
            "subcategory":"Auto Supplies",
            "type":"Retail Goods"
        },
        {
            "category":"Wholesale",
            "subcategory":"Auto Parts",
            "type":"Manufacturing & Wholesale Goods"
        }
    ],
    "sg:phone":"+1 916 983 9884",
    "sg:postcode":"95630",
    "sg:province":"CA",
    "sg:tags":[
        "body",
        "automobile",
        "truck",
        "equipment",
        "accessory"
    ],
    "sg:website":"http://www.oreillyauto.com?utm_source=yellowpages&utm_medium=iyp&utm_campaign=3030",
    "wof:name":"Kragen O'ReillyAuto Parts",
    "wof:placetype":"venue"
},
  "geometry": {"coordinates":[-121.16253399999999,38.669893],"type":"Point"}
}