{
  "type": "Feature",
  "properties": {
    "addr:full":"4225 Prado Rd Corona CA 92880",
    "addr:housenumber":"4225",
    "addr:postcode":"92880",
    "addr:street":"Prado Rd",
    "iso:country":"US",
    "sg:address":"4225 Prado Rd",
    "sg:city":"Corona",
    "sg:classifiers":[
        {
            "category":"Home & Garden",
            "subcategory":"Furniture",
            "type":"Retail Goods"
        }
    ],
    "sg:phone":"+1 951 272 1221",
    "sg:postcode":"92880",
    "sg:province":"CA",
    "wof:name":"West Coast Patio",
    "wof:placetype":"venue"
},
  "geometry": {"coordinates":[-117.650634,33.881667],"type":"Point"}
}