{
  "type": "Feature",
  "properties": {
    "addr:full":"22630 Hickory Nut Ln Diamond Bar CA 91765",
    "addr:housenumber":"22630",
    "addr:postcode":"91765",
    "addr:street":"Hickory Nut Ln",
    "iso:country":"US",
    "sg:address":"22630 Hickory Nut Ln",
    "sg:city":"Diamond Bar",
    "sg:classifiers":[
        {
            "category":"Shopping",
            "subcategory":"Florist",
            "type":"Retail Goods"
        }
    ],
    "sg:phone":"+1 909 861 3138",
    "sg:postcode":"91765",
    "sg:province":"CA",
    "wof:name":"Flowers By Sharron",
    "wof:placetype":"venue"
},
  "geometry": {"coordinates":[-117.820711,33.994026],"type":"Point"}
}