{
  "type": "Feature",
  "properties": {
    "addr:full":"252 S Reeves Dr 9 Beverly Hills CA 90212",
    "addr:housenumber":"252;9",
    "addr:postcode":"90212",
    "addr:street":"S Reeves Dr;Hills Ca",
    "iso:country":"US",
    "sg:address":"252 S Reeves Dr 9",
    "sg:city":"Beverly Hills",
    "sg:classifiers":[
        {
            "category":"Building & Trades",
            "subcategory":"Construction",
            "type":"Services"
        }
    ],
    "sg:phone":"+1 310 271 8518",
    "sg:postcode":"90212",
    "sg:province":"CA",
    "sg:tags":[
        "interior",
        "design"
    ],
    "wof:name":"Joseph Cabanillas Interior Design",
    "wof:placetype":"venue"
},
  "geometry": {"coordinates":[-118.397689,34.063052],"type":"Point"}
}