{
  "type": "Feature",
  "properties": {
    "addr:full":"13121 Perris Blvd Moreno Valley CA 92553",
    "addr:housenumber":"13121",
    "addr:postcode":"92553",
    "addr:street":"Perris Blvd",
    "iso:country":"US",
    "sg:address":"13121 Perris Blvd",
    "sg:city":"Moreno Valley",
    "sg:classifiers":[
        {
            "category":"Food & Beverages",
            "subcategory":"Liquor & Beverages",
            "type":"Retail Goods"
        }
    ],
    "sg:phone":"+1 951 924 8577",
    "sg:postcode":"92553",
    "sg:province":"CA",
    "wof:name":"Frank's Liquors",
    "wof:placetype":"venue"
},
  "geometry": {"coordinates":[-117.22634600000001,33.931786],"type":"Point"}
}