{
  "type": "Feature",
  "properties": {
    "addr:full":"7452 Asman Avenue West Hills CA 91307",
    "addr:housenumber":"7452",
    "addr:postcode":"91307",
    "addr:street":"Asman Avenue",
    "iso:country":"US",
    "sg:address":"7452 Asman Avenue",
    "sg:city":"West Hills",
    "sg:classifiers":[
        {
            "category":"Education",
            "subcategory":"Special Training",
            "type":"Public Place"
        }
    ],
    "sg:phone":"+1 866 414 2030",
    "sg:postcode":"91307",
    "sg:province":"CA",
    "sg:tags":[
        "tutoring"
    ],
    "sg:website":"www.tutoringinla.com",
    "wof:name":"Tutoring in Los Angeles",
    "wof:placetype":"venue"
},
  "geometry": {"coordinates":[-118.616559,34.206159],"type":"Point"}
}