{
  "type": "Feature",
  "properties": {
    "iso:country":"US",
    "sg:address":"536 E Hobsonway",
    "sg:city":"Blythe",
    "sg:classifiers":[
        {
            "category":"Insurance",
            "subcategory":"Insurance Agent",
            "type":"Services"
        }
    ],
    "sg:phone":"+1 760 921 2012",
    "sg:postcode":"92225",
    "sg:province":"CA",
    "wof:name":"Gene Araujo Payless Auto",
    "wof:placetype":"venue"
},
  "geometry": {"coordinates":[-114.59080299999999,33.61038],"type":"Point"}
}