{
  "type": "Feature",
  "properties": {
    "iso:country":"US",
    "sg:address":"931 Buena Vista Way",
    "sg:city":"Chula Vista",
    "sg:classifiers":[
        {
            "category":"Building & Trades",
            "subcategory":"Cleaning & Sanitation",
            "type":"Services"
        }
    ],
    "sg:phone":"+1 619 216 9070",
    "sg:postcode":"91910",
    "sg:province":"CA",
    "sg:tags":[
        "carpet"
    ],
    "wof:name":"Sunset Carpet Cleaning",
    "wof:placetype":"venue"
},
  "geometry": {"coordinates":[-117.001999,32.638599],"type":"Point"}
}