{
  "type": "Feature",
  "properties": {
    "addr:full":"829 Wilshire Blvd Santa Monica CA 90401",
    "addr:housenumber":"829",
    "addr:postcode":"90401",
    "addr:street":"Wilshire Blvd",
    "iso:country":"US",
    "sg:address":"829 Wilshire Blvd",
    "sg:city":"Santa Monica",
    "sg:classifiers":[
        {
            "category":"Restaurant",
            "type":"Food & Drink"
        }
    ],
    "sg:phone":"+1 310 576 0560",
    "sg:postcode":"90401",
    "sg:province":"CA",
    "sg:tags":[
        "shop",
        "coffee"
    ],
    "wof:name":"Coffee Bean & Tea Leaf",
    "wof:placetype":"venue"
},
  "geometry": {"coordinates":[-118.49367100000001,34.022952],"type":"Point"}
}