{
  "type": "Feature",
  "properties": {
    "addr:full":"1547 Pacific Ave Santa Cruz CA 95060",
    "addr:housenumber":"1547",
    "addr:postcode":"95060",
    "addr:street":"Pacific Ave",
    "iso:country":"US",
    "sg:address":"1547 Pacific Ave",
    "sg:city":"Santa Cruz",
    "sg:classifiers":[
        {
            "category":"Shopping",
            "type":"Retail Goods"
        }
    ],
    "sg:phone":"+1 831 425 2787",
    "sg:postcode":"95060",
    "sg:province":"CA",
    "sg:tags":[
        "art",
        "gallery",
        "dealer"
    ],
    "wof:name":"Artforms",
    "wof:placetype":"venue"
},
  "geometry": {"coordinates":[-122.026872,36.976167],"type":"Point"}
}