{
  "type": "Feature",
  "properties": {
    "addr:full":"24909 Pico Canyon Rd Stevenson Ranch CA 91381",
    "addr:housenumber":"24909",
    "addr:postcode":"91381",
    "addr:street":"Pico Canyon Rd",
    "iso:country":"US",
    "sg:address":"24909 Pico Canyon Rd",
    "sg:city":"Stevenson Ranch",
    "sg:classifiers":[
        {
            "category":"Restaurant",
            "type":"Food & Drink"
        }
    ],
    "sg:menulink":"http://www.allmenus.com/ca/newhall/165791-del-taco/menu/",
    "sg:phone":"+1 661 255 6098",
    "sg:postcode":"91381",
    "sg:province":"CA",
    "sg:tags":[
        "american",
        "mexican",
        "tex-mex"
    ],
    "wof:name":"Del Taco",
    "wof:placetype":"venue"
},
  "geometry": {"coordinates":[-118.571838,34.381705],"type":"Point"}
}