{
  "type": "Feature",
  "properties": {
    "addr:full":"2111 University Avenue Berkeley CA 94704",
    "addr:housenumber":"2111",
    "addr:postcode":"94704",
    "addr:street":"University Avenue",
    "iso:country":"US",
    "sg:address":"2111 University Avenue",
    "sg:city":"Berkeley",
    "sg:classifiers":[
        {
            "category":"Professional",
            "subcategory":"Printing & Photocopies",
            "type":"Services"
        }
    ],
    "sg:phone":"+1 510 540 5959",
    "sg:postcode":"94704",
    "sg:province":"CA",
    "sg:website":"www.krishnacopy.com",
    "wof:name":"Krishna Copy Center",
    "wof:placetype":"venue"
},
  "geometry": {"coordinates":[-122.267977,37.872338],"type":"Point"}
}