{
  "type": "Feature",
  "properties": {
    "addr:full":"1180 Silverado Trl Napa CA 94559",
    "addr:housenumber":"1180",
    "addr:postcode":"94559",
    "addr:street":"Silverado Trl",
    "iso:country":"US",
    "sg:address":"1180 Silverado Trl",
    "sg:city":"Napa",
    "sg:classifiers":[
        {
            "category":"Personal",
            "subcategory":"Beauty Salon",
            "type":"Services"
        }
    ],
    "sg:phone":"+1 707 253 0883",
    "sg:postcode":"94559",
    "sg:province":"CA",
    "wof:name":"Glow Skin & Body Care",
    "wof:placetype":"venue"
},
  "geometry": {"coordinates":[-122.276898,38.303162],"type":"Point"}
}