{
  "type": "Feature",
  "properties": {
    "addr:full":"1475 S Harbor Blvd Fullerton CA 92832",
    "addr:housenumber":"1475",
    "addr:postcode":"92832",
    "addr:street":"S Harbor Blvd",
    "iso:country":"US",
    "sg:address":"1475 S Harbor Blvd",
    "sg:city":"Fullerton",
    "sg:classifiers":[
        {
            "category":"Shopping",
            "subcategory":"Jewelry",
            "type":"Retail Goods"
        }
    ],
    "sg:phone":"+1 714 992 4020",
    "sg:postcode":"92832",
    "sg:province":"CA",
    "sg:tags":[
        "repair"
    ],
    "wof:name":"An Watch Company",
    "wof:placetype":"venue"
},
  "geometry": {"coordinates":[-117.92436499999999,33.856091],"type":"Point"}
}