{
  "type": "Feature",
  "properties": {
    "iso:country":"US",
    "sg:address":"1330 Lincoln Avenue",
    "sg:city":"San Jose",
    "sg:classifiers":[
        {
            "category":"Shopping",
            "subcategory":"Antiques",
            "type":"Retail Goods"
        }
    ],
    "sg:phone":"+1 408 295 3500",
    "sg:postcode":"95125",
    "sg:province":"CA",
    "wof:name":"Whatnots and Dodads",
    "wof:placetype":"venue"
},
  "geometry": {"coordinates":[-121.89801199999999,37.304418],"type":"Point"}
}