{
  "type": "Feature",
  "properties": {
    "iso:country":"US",
    "sg:address":"1709 W Pico Blvd",
    "sg:city":"Los Angeles",
    "sg:classifiers":[
        {
            "category":"Personal",
            "subcategory":"Beauty Salon",
            "type":"Services"
        }
    ],
    "sg:phone":"+1 213 387 7609",
    "sg:postcode":"90015",
    "sg:province":"CA",
    "wof:name":"Sharon Beauty Salon",
    "wof:placetype":"venue"
},
  "geometry": {"coordinates":[-118.278813,34.045575],"type":"Point"}
}