{
  "type": "Feature",
  "properties": {
    "iso:country":"US",
    "sg:address":"5050 Palo Verde St",
    "sg:city":"Montclair",
    "sg:classifiers":[
        {
            "category":"Health Services",
            "subcategory":"Clinic",
            "type":"Services"
        },
        {
            "category":"Health Services",
            "subcategory":"Nursing And Care Facility",
            "type":"Services"
        },
        {
            "category":"Health Services",
            "subcategory":"Health Practitioner",
            "type":"Services"
        },
        {
            "category":"Community Center",
            "type":"Public Place"
        }
    ],
    "sg:phone":"+1 909 398 1520",
    "sg:postcode":"91763",
    "sg:province":"CA",
    "sg:tags":[
        "home",
        "medical",
        "eldercare-home",
        "welfare"
    ],
    "wof:name":"Tha Home Health Care Inc",
    "wof:placetype":"venue"
},
  "geometry": {"coordinates":[-117.69506699999999,34.081436],"type":"Point"}
}