{
  "type": "Feature",
  "properties": {
    "addr:full":"1060 Danbeck Ave Santa Rosa CA 95404",
    "addr:housenumber":"1060",
    "addr:postcode":"95404",
    "addr:street":"Danbeck Ave",
    "iso:country":"US",
    "sg:address":"1060 Danbeck Ave",
    "sg:city":"Santa Rosa",
    "sg:classifiers":[
        {
            "category":"Shopping",
            "subcategory":"Jewelry",
            "type":"Retail Goods"
        }
    ],
    "sg:phone":"+1 707 528 0715",
    "sg:postcode":"95404",
    "sg:province":"CA",
    "wof:name":"Sacred Fires",
    "wof:placetype":"venue"
},
  "geometry": {"coordinates":[-122.708679,38.46128],"type":"Point"}
}