{
  "type": "Feature",
  "properties": {
    "iso:country":"US",
    "sg:address":"4000 Fara Biundo Dr Apt 70",
    "sg:city":"Modesto",
    "sg:classifiers":[
        {
            "category":"Building & Trades",
            "subcategory":"Landscaping Services",
            "type":"Services"
        }
    ],
    "sg:phone":"+1 209 551 9000",
    "sg:postcode":"95355",
    "sg:province":"CA",
    "sg:tags":[
        "gardener"
    ],
    "wof:name":"ED GANJEH LAWN & GARDENING SERVICE",
    "wof:placetype":"venue"
},
  "geometry": {"coordinates":[-120.92049400000001,37.663633],"type":"Point"}
}