{
  "type": "Feature",
  "properties": {
    "addr:full":"5655 E La Palma Ave Anaheim CA 92807",
    "addr:housenumber":"5655",
    "addr:postcode":"92807",
    "addr:street":"E La Palma Ave",
    "iso:country":"US",
    "sg:address":"5655 E La Palma Ave",
    "sg:city":"Anaheim",
    "sg:classifiers":[
        {
            "category":"Restaurant",
            "type":"Food & Drink"
        }
    ],
    "sg:phone":"+1 714 693 9888",
    "sg:postcode":"92807",
    "sg:province":"CA",
    "sg:tags":[
        "chinese"
    ],
    "wof:name":"First China Kitchen",
    "wof:placetype":"venue"
},
  "geometry": {"coordinates":[-117.791875,33.859764],"type":"Point"}
}