{
  "type": "Feature",
  "properties": {
    "iso:country":"US",
    "sg:address":"1520 Goodyear Ave",
    "sg:city":"Ventura",
    "sg:classifiers":[
        {
            "category":"Home & Garden",
            "subcategory":"Furniture",
            "type":"Retail Goods"
        }
    ],
    "sg:phone":"+1 805 642 4037",
    "sg:postcode":"93003",
    "sg:province":"CA",
    "wof:name":"Coastal Peak",
    "wof:placetype":"venue"
},
  "geometry": {"coordinates":[-119.232465,34.257417],"type":"Point"}
}