{
  "type": "Feature",
  "properties": {
    "iso:country":"US",
    "sg:address":"900 N Glenoaks Blvd",
    "sg:city":"Burbank",
    "sg:classifiers":[
        {
            "category":"Organizations",
            "subcategory":"Professional Association",
            "type":"Services"
        }
    ],
    "sg:phone":"+1 818 848 4746",
    "sg:postcode":"91502",
    "sg:province":"CA",
    "wof:name":"Syrian Aramenian Boy Scout",
    "wof:placetype":"venue"
},
  "geometry": {"coordinates":[-118.315043,34.18961],"type":"Point"}
}