{
  "type": "Feature",
  "properties": {
    "addr:full":"2175 Hancock St San Diego CA 92110",
    "addr:housenumber":"2175",
    "addr:postcode":"92110",
    "addr:street":"Hancock St",
    "iso:country":"US",
    "sg:address":"2175 Hancock St",
    "sg:city":"San Diego",
    "sg:classifiers":[
        {
            "category":"Retail",
            "subcategory":"Auto Repair",
            "type":"Services"
        }
    ],
    "sg:phone":"+1 619 260 1167",
    "sg:postcode":"92110",
    "sg:province":"CA",
    "sg:tags":[
        "body",
        "automobile",
        "painting"
    ],
    "wof:name":"S E Inc",
    "wof:placetype":"venue"
},
  "geometry": {"coordinates":[-117.18937699999999,32.744733],"type":"Point"}
}