{
  "type": "Feature",
  "properties": {
    "addr:full":"8475 East Rd Redwood Valley CA 95470",
    "addr:housenumber":"8475",
    "addr:postcode":"95470",
    "addr:street":"East Rd",
    "iso:country":"US",
    "sg:address":"8475 East Rd",
    "sg:city":"Redwood Valley",
    "sg:classifiers":[
        {
            "category":"Retail",
            "subcategory":"Veterinary Services",
            "type":"Services"
        }
    ],
    "sg:phone":"+1 707 468 8387",
    "sg:postcode":"95470",
    "sg:province":"CA",
    "sg:tags":[
        "veterinarian"
    ],
    "wof:name":"Michelsen & WITT",
    "wof:placetype":"venue"
},
  "geometry": {"coordinates":[-123.203778,39.263096],"type":"Point"}
}