{
  "type": "Feature",
  "properties": {
    "addr:full":"9311 Mission Gorge Rd Santee CA 92071",
    "addr:housenumber":"9311",
    "addr:postcode":"92071",
    "addr:street":"Mission Gorge Rd",
    "iso:country":"US",
    "sg:address":"9311 Mission Gorge Rd",
    "sg:city":"Santee",
    "sg:classifiers":[
        {
            "category":"Professional",
            "subcategory":"Accounting & Tax Preparation",
            "type":"Services"
        }
    ],
    "sg:phone":"+1 619 448 9403",
    "sg:postcode":"92071",
    "sg:province":"CA",
    "sg:tags":[
        "return",
        "filing"
    ],
    "wof:name":"Jackson Hewitt Tax Svc",
    "wof:placetype":"venue"
},
  "geometry": {"coordinates":[-116.99468899999999,32.838597],"type":"Point"}
}