{
  "type": "Feature",
  "properties": {
    "addr:full":"23941 Ave 95 Terra Bella CA 93270",
    "addr:housenumber":"23941;95",
    "addr:postcode":"93270",
    "addr:street":"Ave",
    "iso:country":"US",
    "sg:address":"23941 Ave 95",
    "sg:city":"Terra Bella",
    "sg:classifiers":[
        {
            "category":"Organizations",
            "subcategory":"Community Association",
            "type":"Services"
        }
    ],
    "sg:phone":"+1 559 535 4454",
    "sg:postcode":"93270",
    "sg:province":"CA",
    "sg:tags":[
        "military"
    ],
    "wof:name":"Veterans Memorial Building",
    "wof:placetype":"venue"
},
  "geometry": {"coordinates":[-119.037238,35.962331],"type":"Point"}
}