{
  "type": "Feature",
  "properties": {
    "addr:full":"17226 Norwalk Blvd Cerritos CA 90703",
    "addr:housenumber":"17226",
    "addr:postcode":"ca 90703",
    "addr:street":"Norwalk Blvd",
    "iso:country":"US",
    "sg:address":"17226 Norwalk Blvd",
    "sg:city":"Cerritos",
    "sg:classifiers":[
        {
            "category":"Personal",
            "subcategory":"Beauty Salon",
            "type":"Services"
        }
    ],
    "sg:phone":"+1 562 402 1444",
    "sg:postcode":"90703",
    "sg:province":"CA",
    "sg:tags":[
        "barber"
    ],
    "sg:website":"www.supercuts.com",
    "wof:name":"Supercuts",
    "wof:placetype":"venue"
},
  "geometry": {"coordinates":[-118.072998,33.874199],"type":"Point"}
}