{
  "type": "Feature",
  "properties": {
    "addr:full":"1091 Lincoln Avenue San Jose CA 95125",
    "addr:housenumber":"1091",
    "addr:postcode":"95125",
    "addr:street":"Lincoln Avenue",
    "iso:country":"US",
    "sg:address":"1091 Lincoln Avenue",
    "sg:city":"San Jose",
    "sg:classifiers":[
        {
            "category":"Professional",
            "subcategory":"Lawyer & Legal Services",
            "type":"Services"
        }
    ],
    "sg:phone":"+1 408 293 0344",
    "sg:postcode":"95125",
    "sg:province":"CA",
    "wof:name":"Law Offices of Daniel E Hanley",
    "wof:placetype":"venue"
},
  "geometry": {"coordinates":[-121.901234,37.308943],"type":"Point"}
}