{
  "type": "Feature",
  "properties": {
    "addr:full":"350 N Lantana St Camarillo CA 93010",
    "addr:housenumber":"350",
    "addr:postcode":"93010",
    "addr:street":"N Lantana St",
    "iso:country":"US",
    "sg:address":"350 N Lantana St",
    "sg:city":"Camarillo",
    "sg:classifiers":[
        {
            "category":"Restaurant",
            "type":"Food & Drink"
        }
    ],
    "sg:phone":"+1 805 987 4979",
    "sg:postcode":"93010",
    "sg:province":"CA",
    "wof:name":"Crab House Restaurant",
    "wof:placetype":"venue"
},
  "geometry": {"coordinates":[-119.055029,34.219629],"type":"Point"}
}