{
  "type": "Feature",
  "properties": {
    "iso:country":"US",
    "sg:address":"6080 Lone Pine Rd",
    "sg:city":"Sebastopol",
    "sg:classifiers":[
        {
            "category":"Building & Trades",
            "subcategory":"Construction",
            "type":"Services"
        }
    ],
    "sg:phone":"+1 707 823 0639",
    "sg:postcode":"95472",
    "sg:province":"CA",
    "sg:tags":[
        "equipment",
        "supply",
        "drywall",
        "contractor"
    ],
    "wof:name":"Ed Springles Drywall",
    "wof:placetype":"venue"
},
  "geometry": {"coordinates":[-122.794573,38.365701],"type":"Point"}
}