{
  "type": "Feature",
  "properties": {
    "iso:country":"US",
    "sg:address":"2351 Dawson Ave",
    "sg:city":"Signal Hill",
    "sg:classifiers":[
        {
            "category":"Park",
            "type":"Public Place"
        }
    ],
    "sg:phone":"+1 562 989 7330",
    "sg:postcode":"90755",
    "sg:province":"CA",
    "sg:website":"www.ci.signal-hill.ca.us/communi...",
    "wof:name":"Hilltop Park",
    "wof:placetype":"venue"
},
  "geometry": {"coordinates":[-118.164923,33.799989],"type":"Point"}
}