{
  "type": "Feature",
  "properties": {
    "iso:country":"US",
    "sg:address":"2333 Lake Ave Ste E",
    "sg:city":"Altadena",
    "sg:classifiers":[
        {
            "category":"Retail",
            "subcategory":"Event Space",
            "type":"Services"
        }
    ],
    "sg:phone":"+1 626 797 1769",
    "sg:postcode":"91001",
    "sg:province":"CA",
    "sg:tags":[
        "venue"
    ],
    "wof:name":"Dc 36",
    "wof:placetype":"venue"
},
  "geometry": {"coordinates":[-118.131658,34.185916],"type":"Point"}
}