{
  "type": "Feature",
  "properties": {
    "addr:full":"745 Camden Ave Campbell CA 95008",
    "addr:housenumber":"745",
    "addr:postcode":"95008",
    "addr:street":"Camden Ave",
    "iso:country":"US",
    "sg:address":"745 Camden Ave",
    "sg:city":"Campbell",
    "sg:classifiers":[
        {
            "category":"Building & Trades",
            "subcategory":"Cleaning & Sanitation",
            "type":"Services"
        }
    ],
    "sg:phone":"+1 408 371 3303",
    "sg:postcode":"95008",
    "sg:province":"CA",
    "sg:tags":[
        "processing",
        "cryogenic"
    ],
    "wof:name":"VBS Industries",
    "wof:placetype":"venue"
},
  "geometry": {"coordinates":[-121.95021699999999,37.27636],"type":"Point"}
}