{
  "type": "Feature",
  "properties": {
    "iso:country":"US",
    "sg:address":"1175 University Avenue",
    "sg:city":"Berkeley",
    "sg:classifiers":[
        {
            "category":"Travel",
            "subcategory":"Hotels & Motels",
            "type":"Entertainment"
        },
        {
            "category":"Retail",
            "subcategory":"Event Space",
            "type":"Services"
        }
    ],
    "sg:phone":"+1 510 548 1700",
    "sg:postcode":"94702",
    "sg:province":"CA",
    "sg:tags":[
        "venue"
    ],
    "sg:website":"www.holidayinnexpress.com",
    "wof:name":"Holiday Inn Express Hotel & Suites Berkeley",
    "wof:placetype":"venue"
},
  "geometry": {"coordinates":[-122.290464,37.869827],"type":"Point"}
}