{
  "type": "Feature",
  "properties": {
    "iso:country":"US",
    "sg:address":"1275 4th St",
    "sg:city":"Santa Rosa",
    "sg:classifiers":[
        {
            "category":"Professional",
            "subcategory":"Business Services",
            "type":"Services"
        }
    ],
    "sg:phone":"+1 707 523 4901",
    "sg:postcode":"95404",
    "sg:province":"CA",
    "sg:tags":[
        "interior",
        "consultant",
        "design",
        "decorator"
    ],
    "wof:name":"Acocella Interiors",
    "wof:placetype":"venue"
},
  "geometry": {"coordinates":[-122.70506,38.444796],"type":"Point"}
}