{
  "type": "Feature",
  "properties": {
    "addr:full":"Canoga Park Ofc Canoga Park CA 91303",
    "addr:postcode":"91303",
    "iso:country":"US",
    "sg:address":"Canoga Park Ofc",
    "sg:city":"Canoga Park",
    "sg:classifiers":[
        {
            "category":"Health Services",
            "subcategory":"Doctor",
            "type":"Services"
        }
    ],
    "sg:phone":"+1 818 348 6200",
    "sg:postcode":"91303",
    "sg:province":"CA",
    "sg:tags":[
        "obstetrician",
        "gynecologist"
    ],
    "wof:name":"Eder Jerome M MD",
    "wof:placetype":"venue"
},
  "geometry": {"coordinates":[-118.59899900000001,34.1978],"type":"Point"}
}