{
  "type": "Feature",
  "properties": {
    "iso:country":"US",
    "sg:address":"3191 W Temple Ave",
    "sg:city":"Pomona",
    "sg:classifiers":[
        {
            "category":"Professional",
            "subcategory":"Computer Services",
            "type":"Services"
        }
    ],
    "sg:phone":"+1 909 594 5452",
    "sg:postcode":"91768",
    "sg:province":"CA",
    "sg:tags":[
        "consultant"
    ],
    "sg:website":"www.atitechnologies.com",
    "wof:name":"AGI Technologies",
    "wof:placetype":"venue"
},
  "geometry": {"coordinates":[-117.802819,34.045365],"type":"Point"}
}