{
  "type": "Feature",
  "properties": {
    "iso:country":"US",
    "sg:address":"855 3rd Ave",
    "sg:city":"Chula Vista",
    "sg:classifiers":[
        {
            "category":"Health Services",
            "subcategory":"Doctor",
            "type":"Services"
        }
    ],
    "sg:phone":"+1 619 691 0388",
    "sg:postcode":"91911",
    "sg:province":"CA",
    "sg:tags":[
        "physician",
        "surgeon"
    ],
    "wof:name":"Georges M Argoud MD",
    "wof:placetype":"venue"
},
  "geometry": {"coordinates":[-117.072913,32.623657],"type":"Point"}
}