{
  "type": "Feature",
  "properties": {
    "iso:country":"US",
    "sg:address":"1713 S California Ave",
    "sg:city":"Monrovia",
    "sg:classifiers":[
        {
            "category":"Manufacturing",
            "subcategory":"Metals",
            "type":"Manufacturing & Wholesale Goods"
        }
    ],
    "sg:phone":"+1 626 305 3014",
    "sg:postcode":"91016",
    "sg:province":"CA",
    "sg:tags":[
        "plating"
    ],
    "wof:name":"Atotech USA Inc",
    "wof:placetype":"venue"
},
  "geometry": {"coordinates":[-117.995104,34.132605],"type":"Point"}
}