{
  "type": "Feature",
  "properties": {
    "iso:country":"US",
    "sg:address":"2500 5th St",
    "sg:city":"Norco",
    "sg:classifiers":[
        {
            "category":"Social Services",
            "type":"Services"
        }
    ],
    "sg:phone":"+1 951 737 7010",
    "sg:postcode":"92860",
    "sg:province":"CA",
    "sg:tags":[
        "organization",
        "welfare"
    ],
    "wof:name":"Hospitality Place",
    "wof:placetype":"venue"
},
  "geometry": {"coordinates":[-117.567998,33.931191],"type":"Point"}
}