{
  "type": "Feature",
  "properties": {
    "addr:full":"13447 Ventura Blvd Sherman Oaks CA 91423",
    "addr:housenumber":"13447",
    "addr:postcode":"91423",
    "addr:street":"Ventura Blvd",
    "iso:country":"US",
    "sg:address":"13447 Ventura Blvd",
    "sg:city":"Sherman Oaks",
    "sg:classifiers":[
        {
            "category":"Restaurant",
            "type":"Food & Drink"
        }
    ],
    "sg:phone":"+1 818 906 7274",
    "sg:postcode":"91423",
    "sg:province":"CA",
    "sg:tags":[
        "sushi",
        "bar",
        "japanese"
    ],
    "wof:name":"Bizen Restaurant",
    "wof:placetype":"venue"
},
  "geometry": {"coordinates":[-118.42600299999999,34.147099],"type":"Point"}
}