{
  "type": "Feature",
  "properties": {
    "iso:country":"US",
    "sg:address":"8445 N Star Way",
    "sg:city":"Orangevale",
    "sg:classifiers":[
        {
            "category":"Shopping",
            "subcategory":"Jewelry",
            "type":"Retail Goods"
        }
    ],
    "sg:phone":"+1 916 705 6004",
    "sg:postcode":"95662",
    "sg:province":"CA",
    "sg:tags":[
        "designer"
    ],
    "wof:name":"Jayne Doe Design",
    "wof:placetype":"venue"
},
  "geometry": {"coordinates":[-121.244894,38.680204],"type":"Point"}
}