{
  "type": "Feature",
  "properties": {
    "addr:full":"42541 6th St E Lancaster CA 93535",
    "addr:housenumber":"42541",
    "addr:postcode":"93535",
    "addr:street":"6Th St E",
    "iso:country":"US",
    "sg:address":"42541 6th St E",
    "sg:city":"Lancaster",
    "sg:classifiers":[
        {
            "category":"Building & Trades",
            "subcategory":"Construction",
            "type":"Services"
        }
    ],
    "sg:phone":"+1 661 974 7967",
    "sg:postcode":"93535",
    "sg:province":"CA",
    "sg:tags":[
        "excavating",
        "contractor"
    ],
    "wof:name":"Seeber Excavation & Hauling",
    "wof:placetype":"venue"
},
  "geometry": {"coordinates":[-118.118968,34.654206],"type":"Point"}
}