{
  "type": "Feature",
  "properties": {
    "addr:full":"3069 Olcott St Santa Clara CA 95054",
    "addr:housenumber":"3069",
    "addr:postcode":"95054",
    "addr:street":"Olcott St",
    "iso:country":"US",
    "sg:address":"3069 Olcott St",
    "sg:city":"Santa Clara",
    "sg:classifiers":[
        {
            "category":"Manufacturing",
            "subcategory":"Electronics",
            "type":"Manufacturing & Wholesale Goods"
        }
    ],
    "sg:phone":"+1 408 727 3028",
    "sg:postcode":"95054",
    "sg:province":"CA",
    "sg:tags":[
        "devices",
        "mfg"
    ],
    "wof:name":"Genesis Associates",
    "wof:placetype":"venue"
},
  "geometry": {"coordinates":[-121.96735099999999,37.377883],"type":"Point"}
}