{
  "type": "Feature",
  "properties": {
    "addr:full":"6320 W 84th Pl Los Angeles CA 90045",
    "addr:housenumber":"6320",
    "addr:postcode":"90045",
    "addr:street":"W 84Th Pl",
    "iso:country":"US",
    "sg:address":"6320 W 84th Pl",
    "sg:city":"Los Angeles",
    "sg:classifiers":[
        {
            "category":"Social Services",
            "type":"Services"
        }
    ],
    "sg:phone":"+1 310 568 9095",
    "sg:postcode":"90045",
    "sg:province":"CA",
    "sg:tags":[
        "counseling"
    ],
    "wof:name":"Breunig & Assoc",
    "wof:placetype":"venue"
},
  "geometry": {"coordinates":[-118.400217,33.962052],"type":"Point"}
}