{
  "type": "Feature",
  "properties": {
    "iso:country":"US",
    "sg:address":"8500 Wilshire Boulevard",
    "sg:city":"Beverly Hills",
    "sg:classifiers":[
        {
            "category":"Health Services",
            "subcategory":"Dentist",
            "type":"Services"
        }
    ],
    "sg:phone":"+1 310 358 5593",
    "sg:postcode":"90211",
    "sg:province":"CA",
    "sg:tags":[
        "orthodontist"
    ],
    "wof:name":"Zimring Jerry F DDS MSD",
    "wof:placetype":"venue"
},
  "geometry": {"coordinates":[-118.376245,34.065231],"type":"Point"}
}