{
  "type": "Feature",
  "properties": {
    "addr:full":"5434 La Palma Ave La Palma CA 90623",
    "addr:housenumber":"5434",
    "addr:postcode":"90623",
    "addr:street":"La Palma Ave",
    "iso:country":"US",
    "sg:address":"5434 La Palma Ave",
    "sg:city":"La Palma",
    "sg:classifiers":[
        {
            "category":"Shopping",
            "subcategory":"Beauty & Cosmetics",
            "type":"Retail Goods"
        }
    ],
    "sg:phone":"+1 714 220 2944",
    "sg:postcode":"90623",
    "sg:province":"CA",
    "sg:tags":[
        "supply"
    ],
    "wof:name":"Infiniti Beauty Salon & Supply",
    "wof:placetype":"venue"
},
  "geometry": {"coordinates":[-118.03800200000001,33.846199],"type":"Point"}
}