{
  "type": "Feature",
  "properties": {
    "iso:country":"US",
    "sg:address":"1603 Aviation Blvd",
    "sg:city":"Redondo Beach",
    "sg:classifiers":[
        {
            "category":"Real Estate",
            "subcategory":"Real Estate Agent",
            "type":"Services"
        }
    ],
    "sg:phone":"+1 310 374 5224",
    "sg:postcode":"90278",
    "sg:province":"CA",
    "sg:tags":[
        "appraiser"
    ],
    "wof:name":"Accurate Appraisal Svc",
    "wof:placetype":"venue"
},
  "geometry": {"coordinates":[-118.382616,33.869794],"type":"Point"}
}