{
  "type": "Feature",
  "properties": {
    "iso:country":"US",
    "sg:address":"14020 Marquardt Ave",
    "sg:city":"Santa Fe Springs",
    "sg:classifiers":[
        {
            "category":"Building & Trades",
            "subcategory":"Construction",
            "type":"Services"
        }
    ],
    "sg:phone":"+1 562 926 2232",
    "sg:postcode":"90670",
    "sg:province":"CA",
    "sg:tags":[
        "contractor"
    ],
    "wof:name":"Quinn Building Construction",
    "wof:placetype":"venue"
},
  "geometry": {"coordinates":[-118.03800200000001,33.903301],"type":"Point"}
}