{
  "type": "Feature",
  "properties": {
    "addr:full":"1257 Apple Ave Wrightwood CA 92397",
    "addr:housenumber":"1257",
    "addr:postcode":"92397",
    "addr:street":"Apple Ave",
    "iso:country":"US",
    "sg:address":"1257 Apple Ave",
    "sg:city":"Wrightwood",
    "sg:classifiers":[
        {
            "category":"Shopping",
            "subcategory":"Clothing, Apparel, & Fashions",
            "type":"Retail Goods"
        }
    ],
    "sg:phone":"+1 760 249 3010",
    "sg:postcode":"92397",
    "sg:province":"CA",
    "wof:name":"Off Melrose",
    "wof:placetype":"venue"
},
  "geometry": {"coordinates":[-117.63506700000001,34.35991],"type":"Point"}
}