{
  "type": "Feature",
  "properties": {
    "addr:full":"11306 Mountain View Ave Loma Linda CA 92354",
    "addr:housenumber":"11306",
    "addr:postcode":"92354",
    "addr:street":"Mountain View Ave",
    "iso:country":"US",
    "sg:address":"11306 Mountain View Ave",
    "sg:city":"Loma Linda",
    "sg:classifiers":[
        {
            "category":"Sports & Exercise",
            "subcategory":"Gym",
            "type":"Entertainment"
        }
    ],
    "sg:phone":"+1 909 478 9499",
    "sg:postcode":"92354",
    "sg:province":"CA",
    "sg:tags":[
        "club",
        "health",
        "studio",
        "gymnasium"
    ],
    "wof:name":"Curves For Women",
    "wof:placetype":"venue"
},
  "geometry": {"coordinates":[-117.243707,34.044952],"type":"Point"}
}