{
  "type": "Feature",
  "properties": {
    "addr:full":"Torrey Pines High School 3710 Del Mar Heights Rd San Diego CA 92130",
    "addr:housenumber":"3710",
    "addr:postcode":"92130",
    "addr:street":"Del Mar Heights Rd",
    "iso:country":"US",
    "sg:address":"Torrey Pines High School 3710 Del Mar Heights Rd",
    "sg:city":"San Diego",
    "sg:classifiers":[
        {
            "category":"Place Of Worship",
            "subcategory":"Church",
            "type":"Public Place"
        }
    ],
    "sg:phone":"+1 858 997 4676",
    "sg:postcode":"92130",
    "sg:province":"CA",
    "sg:website":"www.ElevateSanDiego.com",
    "wof:name":"Elevate Church",
    "wof:placetype":"venue"
},
  "geometry": {"coordinates":[-117.225798,32.956409],"type":"Point"}
}