{
  "type": "Feature",
  "properties": {
    "iso:country":"US",
    "sg:address":"330 Skyway Dr",
    "sg:city":"Camarillo",
    "sg:classifiers":[
        {
            "category":"Arts & Performance",
            "subcategory":"Theater",
            "type":"Entertainment"
        }
    ],
    "sg:phone":"+1 805 388 5716",
    "sg:postcode":"93010",
    "sg:province":"CA",
    "wof:name":"Camarillo Community Theatre",
    "wof:placetype":"venue"
},
  "geometry": {"coordinates":[-119.076632,34.206266],"type":"Point"}
}