{
  "type": "Feature",
  "properties": {
    "addr:full":"15219 W Sunset Blvd Pacific Plsds CA 90272",
    "addr:housenumber":"15219",
    "addr:postcode":"90272",
    "addr:street":"W Sunset Blvd",
    "iso:country":"US",
    "sg:address":"15219 W Sunset Blvd",
    "sg:city":"Pacific Plsds",
    "sg:classifiers":[
        {
            "category":"Insurance",
            "subcategory":"Insurance Agent",
            "type":"Services"
        }
    ],
    "sg:phone":"+1 310 454 7788",
    "sg:postcode":"90272",
    "sg:province":"CA",
    "wof:name":"Dennis Sokol Insurance",
    "wof:placetype":"venue"
},
  "geometry": {"coordinates":[-118.524762,34.046569],"type":"Point"}
}