{
  "type": "Feature",
  "properties": {
    "addr:full":"215 N Maple Ave Fresno CA 93702",
    "addr:housenumber":"215",
    "addr:postcode":"93702",
    "addr:street":"N Maple Ave",
    "iso:country":"US",
    "sg:address":"215 N Maple Ave",
    "sg:city":"Fresno",
    "sg:classifiers":[
        {
            "category":"Food & Beverages",
            "subcategory":"Specialty",
            "type":"Retail Goods"
        }
    ],
    "sg:phone":"+1 559 454 0961",
    "sg:postcode":"93702",
    "sg:province":"CA",
    "wof:name":"Natural Family Center",
    "wof:placetype":"venue"
},
  "geometry": {"coordinates":[-119.74550000000001,36.745652],"type":"Point"}
}