{
  "type": "Feature",
  "properties": {
    "iso:country":"US",
    "sg:address":"8840 Beverly Blvd",
    "sg:city":"Los Angeles",
    "sg:classifiers":[
        {
            "category":"Shopping",
            "subcategory":"Jewelry",
            "type":"Retail Goods"
        }
    ],
    "sg:phone":"+1 310 271 2761",
    "sg:postcode":"90048",
    "sg:province":"CA",
    "wof:name":"Ageless Jewels",
    "wof:placetype":"venue"
},
  "geometry": {"coordinates":[-118.386002,34.077202],"type":"Point"}
}