{
  "type": "Feature",
  "properties": {
    "iso:country":"US",
    "sg:address":"1 Irvine Park Road",
    "sg:city":"Orange",
    "sg:classifiers":[
        {
            "category":"Museum",
            "subcategory":"Zoo",
            "type":"Entertainment"
        }
    ],
    "sg:phone":"+1 714 973 6847",
    "sg:postcode":"92862",
    "sg:province":"CA",
    "sg:website":"www.oczoo.com",
    "wof:name":"Orange County Zoo",
    "wof:placetype":"venue"
},
  "geometry": {"coordinates":[-117.758003,33.796398],"type":"Point"}
}