{
  "type": "Feature",
  "properties": {
    "iso:country":"US",
    "sg:address":"307 Healdsburg Ave",
    "sg:city":"Healdsburg",
    "sg:classifiers":[
        {
            "category":"Shopping",
            "subcategory":"Clothing, Apparel, & Fashions",
            "type":"Retail Goods"
        }
    ],
    "sg:phone":"+1 707 433 8189",
    "sg:postcode":"95448",
    "sg:province":"CA",
    "wof:name":"Clutch",
    "wof:placetype":"venue"
},
  "geometry": {"coordinates":[-122.870115,38.608606],"type":"Point"}
}