{
  "type": "Feature",
  "properties": {
    "addr:full":"996 Saratoga Ave San Jose CA 95129",
    "addr:housenumber":"996",
    "addr:postcode":"95129",
    "addr:street":"Saratoga Ave",
    "iso:country":"US",
    "sg:address":"996 Saratoga Ave",
    "sg:city":"San Jose",
    "sg:classifiers":[
        {
            "category":"Health Services",
            "subcategory":"Clinic",
            "type":"Services"
        }
    ],
    "sg:phone":"+1 408 244 9925",
    "sg:postcode":"95129",
    "sg:province":"CA",
    "sg:tags":[
        "cannabis"
    ],
    "wof:name":"Patient to Patient",
    "wof:placetype":"venue"
},
  "geometry": {"coordinates":[-121.97674000000001,37.308503],"type":"Point"}
}