{
  "type": "Feature",
  "properties": {
    "addr:full":"140 Brookwood Rd Orinda CA 94563",
    "addr:housenumber":"140",
    "addr:postcode":"94563",
    "addr:street":"Brookwood Rd",
    "iso:country":"US",
    "sg:address":"140 Brookwood Rd",
    "sg:city":"Orinda",
    "sg:classifiers":[
        {
            "category":"Health Services",
            "subcategory":"Doctor",
            "type":"Services"
        }
    ],
    "sg:phone":"+1 925 254 9090",
    "sg:postcode":"94563",
    "sg:province":"CA",
    "sg:tags":[
        "medicine",
        "internal"
    ],
    "wof:name":"Sears Mary MD Dr",
    "wof:placetype":"venue"
},
  "geometry": {"coordinates":[-122.181999,37.875999],"type":"Point"}
}