{
  "type": "Feature",
  "properties": {
    "addr:full":"901 E E St Wilmington CA 90744",
    "addr:housenumber":"901",
    "addr:postcode":"90744",
    "addr:street":"E E St",
    "iso:country":"US",
    "sg:address":"901 E E St",
    "sg:city":"Wilmington",
    "sg:classifiers":[
        {
            "category":"Freight",
            "type":"Transportation"
        }
    ],
    "sg:phone":"+1 310 233 7300",
    "sg:postcode":"90744",
    "sg:province":"CA",
    "sg:tags":[
        "warehouse",
        "storage"
    ],
    "wof:name":"Union Ice",
    "wof:placetype":"venue"
},
  "geometry": {"coordinates":[-118.25037,33.776154],"type":"Point"}
}