{
  "type": "Feature",
  "properties": {
    "addr:full":"525 N Garfield Ave Monterey Park CA 91754",
    "addr:housenumber":"525",
    "addr:postcode":"91754",
    "addr:street":"N Garfield Ave",
    "iso:country":"US",
    "sg:address":"525 N Garfield Ave",
    "sg:city":"Monterey Park",
    "sg:classifiers":[
        {
            "category":"Professional",
            "subcategory":"Management & Consulting",
            "type":"Services"
        }
    ],
    "sg:phone":"+1 626 573 2222",
    "sg:postcode":"91754",
    "sg:province":"CA",
    "sg:tags":[
        "facility",
        "hospital",
        "skilled",
        "nursing",
        "care"
    ],
    "wof:name":"Garfield Medical Center",
    "wof:placetype":"venue"
},
  "geometry": {"coordinates":[-118.123001,34.068199],"type":"Point"}
}