{
  "type": "Feature",
  "properties": {
    "addr:full":"160 Glendale Blvd Los Angeles CA 90026",
    "addr:housenumber":"160",
    "addr:postcode":"90026",
    "addr:street":"Glendale Blvd",
    "iso:country":"US",
    "sg:address":"160 Glendale Blvd",
    "sg:city":"Los Angeles",
    "sg:classifiers":[
        {
            "category":"Manufacturing",
            "subcategory":"Apparel",
            "type":"Manufacturing & Wholesale Goods"
        }
    ],
    "sg:phone":"+1 213 250 0869",
    "sg:postcode":"90026",
    "sg:province":"CA",
    "sg:tags":[
        "sewing",
        "contractor"
    ],
    "wof:name":"SCL Fashion Inc",
    "wof:placetype":"venue"
},
  "geometry": {"coordinates":[-118.259755,34.063612],"type":"Point"}
}