{
  "type": "Feature",
  "properties": {
    "addr:full":"11920 Amargosa Rd Victorville CA 92392",
    "addr:housenumber":"11920",
    "addr:postcode":"92392",
    "addr:street":"Amargosa Rd",
    "iso:country":"US",
    "sg:address":"11920 Amargosa Rd",
    "sg:city":"Victorville",
    "sg:classifiers":[
        {
            "category":"Restaurant",
            "type":"Food & Drink"
        }
    ],
    "sg:menulink":"http://www.allmenus.com/ca/barstow-victorville/104988-carinos-italian-grill/menu/",
    "sg:phone":"+1 760 949 2248",
    "sg:postcode":"92392",
    "sg:province":"CA",
    "sg:tags":[
        "american",
        "italian"
    ],
    "wof:name":"Carino's Italian Grill",
    "wof:placetype":"venue"
},
  "geometry": {"coordinates":[-117.35004000000001,34.466961],"type":"Point"}
}