{
  "type": "Feature",
  "properties": {
    "addr:full":"1601 Sawtelle Blvd Ste 101 Los Angeles CA 90025",
    "addr:housenumber":"1601",
    "addr:postcode":"90025",
    "addr:street":"Sawtelle Blvd Ste 101",
    "iso:country":"US",
    "sg:address":"1601 Sawtelle Blvd Ste 101",
    "sg:city":"Los Angeles",
    "sg:classifiers":[
        {
            "category":"Restaurant",
            "type":"Food & Drink"
        }
    ],
    "sg:phone":"+1 310 445 0070",
    "sg:postcode":"90025",
    "sg:province":"CA",
    "sg:tags":[
        "mexican"
    ],
    "wof:name":"El Rebozo Mexican Restaurant",
    "wof:placetype":"venue"
},
  "geometry": {"coordinates":[-118.44899700000001,34.0471],"type":"Point"}
}