{
  "type": "Feature",
  "properties": {
    "addr:full":"8525 O'Toole Ct Gilroy CA 95020",
    "addr:housenumber":"8525",
    "addr:postcode":"95020",
    "addr:street":"O'Toole Ct",
    "iso:country":"US",
    "sg:address":"8525 O'Toole Ct",
    "sg:city":"Gilroy",
    "sg:classifiers":[
        {
            "category":"Professional",
            "subcategory":"Computer Services",
            "type":"Services"
        }
    ],
    "sg:phone":"+1 408 848 1091",
    "sg:postcode":"95020",
    "sg:province":"CA",
    "sg:tags":[
        "programing",
        "custom"
    ],
    "wof:name":"Sun Microsystems",
    "wof:placetype":"venue"
},
  "geometry": {"coordinates":[-121.57411999999999,36.987239],"type":"Point"}
}