{
  "type": "Feature",
  "properties": {
    "addr:full":"2685 Sherwin Ave Ventura CA 93003",
    "addr:housenumber":"2685",
    "addr:postcode":"93003",
    "addr:street":"Sherwin Ave",
    "iso:country":"US",
    "sg:address":"2685 Sherwin Ave",
    "sg:city":"Ventura",
    "sg:classifiers":[
        {
            "category":"Freight",
            "type":"Transportation"
        }
    ],
    "sg:phone":"+1 805 642 7090",
    "sg:postcode":"93003",
    "sg:province":"CA",
    "sg:tags":[
        "carrier",
        "motor"
    ],
    "wof:name":"Yellow Transportation Inc",
    "wof:placetype":"venue"
},
  "geometry": {"coordinates":[-119.198736,34.249609],"type":"Point"}
}