{
  "type": "Feature",
  "properties": {
    "addr:full":"665 Eddy St San Francisco CA 94109",
    "addr:housenumber":"665",
    "addr:postcode":"94109",
    "addr:street":"Eddy St",
    "iso:country":"US",
    "sg:address":"665 Eddy St",
    "sg:city":"San Francisco",
    "sg:classifiers":[
        {
            "category":"Personal",
            "subcategory":"Beauty Salon",
            "type":"Services"
        },
        {
            "category":"Personal",
            "subcategory":"Hair Removal",
            "type":"Services"
        }
    ],
    "sg:phone":"+1 415 678 9852",
    "sg:postcode":"94109",
    "sg:province":"CA",
    "wof:name":"African Professional Hair",
    "wof:placetype":"venue"
},
  "geometry": {"coordinates":[-122.41862399999999,37.782887],"type":"Point"}
}