{
  "type": "Feature",
  "properties": {
    "iso:country":"US",
    "sg:address":"15706 Whittwood Ln",
    "sg:city":"Whittier",
    "sg:classifiers":[
        {
            "category":"Sports & Exercise",
            "subcategory":"Bicycle Rental",
            "type":"Entertainment"
        }
    ],
    "sg:phone":"+1 562 943 8786",
    "sg:postcode":"90603",
    "sg:province":"CA",
    "sg:tags":[
        "wear"
    ],
    "wof:name":"Beach Bums Board Shop",
    "wof:placetype":"venue"
},
  "geometry": {"coordinates":[-117.994782,33.943709],"type":"Point"}
}