{
  "type": "Feature",
  "properties": {
    "iso:country":"US",
    "sg:address":"1470 Mendocino Ave",
    "sg:city":"Santa Rosa",
    "sg:classifiers":[
        {
            "category":"Home & Garden",
            "subcategory":"Household Appliances",
            "type":"Retail Goods"
        }
    ],
    "sg:phone":"+1 707 568 3220",
    "sg:postcode":"95401",
    "sg:province":"CA",
    "sg:tags":[
        "cleaners",
        "vacuum"
    ],
    "wof:name":"Place That Sells Vacuums",
    "wof:placetype":"venue"
},
  "geometry": {"coordinates":[-122.717315,38.453763],"type":"Point"}
}