{
  "type": "Feature",
  "properties": {
    "addr:full":"3518 S Garden St Visalia CA 93277",
    "addr:housenumber":"3518",
    "addr:postcode":"93277",
    "addr:street":"S Garden St",
    "iso:country":"US",
    "sg:address":"3518 S Garden St",
    "sg:city":"Visalia",
    "sg:classifiers":[
        {
            "category":"Food & Beverages",
            "subcategory":"Candy",
            "type":"Retail Goods"
        }
    ],
    "sg:phone":"+1 559 901 4313",
    "sg:postcode":"93277",
    "sg:province":"CA",
    "sg:tags":[
        "confectionery"
    ],
    "wof:name":"Sports Nut Inc",
    "wof:placetype":"venue"
},
  "geometry": {"coordinates":[-119.28926800000001,36.298691],"type":"Point"}
}