{
  "type": "Feature",
  "properties": {
    "addr:full":"6025 E Cll Cedro Anaheim CA 92807",
    "addr:housenumber":"6025",
    "addr:postcode":"92807",
    "addr:street":"E Cll",
    "iso:country":"US",
    "sg:address":"6025 E Cll Cedro",
    "sg:city":"Anaheim",
    "sg:classifiers":[
        {
            "category":"Building & Trades",
            "subcategory":"Construction",
            "type":"Services"
        }
    ],
    "sg:phone":"+1 714 998 9680",
    "sg:postcode":"92807",
    "sg:province":"CA",
    "sg:tags":[
        "coping",
        "plastering",
        "tiling",
        "pool",
        "swimming"
    ],
    "wof:name":"Perfect Pool & Spa Svc",
    "wof:placetype":"venue"
},
  "geometry": {"coordinates":[-117.781524,33.853924],"type":"Point"}
}