{
  "type": "Feature",
  "properties": {
    "addr:full":"3434 Atlantic Ave Long Beach CA 90807",
    "addr:housenumber":"3434",
    "addr:postcode":"90807",
    "addr:street":"Atlantic Ave",
    "iso:country":"US",
    "sg:address":"3434 Atlantic Ave",
    "sg:city":"Long Beach",
    "sg:classifiers":[
        {
            "category":"Shopping",
            "subcategory":"Antiques",
            "type":"Retail Goods"
        },
        {
            "category":"Home & Garden",
            "subcategory":"Furniture",
            "type":"Retail Goods"
        }
    ],
    "sg:phone":"+1 562 424 9252",
    "sg:postcode":"90807",
    "sg:province":"CA",
    "sg:tags":[
        "store"
    ],
    "wof:name":"Finders Keepers",
    "wof:placetype":"venue"
},
  "geometry": {"coordinates":[-118.18499799999999,33.819801],"type":"Point"}
}