{
  "type": "Feature",
  "properties": {
    "addr:full":"528 N Civic Dr Walnut Creek CA 94597",
    "addr:housenumber":"528",
    "addr:postcode":"94597",
    "addr:street":"N Civic Dr",
    "iso:country":"US",
    "sg:address":"528 N Civic Dr",
    "sg:city":"Walnut Creek",
    "sg:classifiers":[
        {
            "category":"Professional",
            "subcategory":"Management & Consulting",
            "type":"Services"
        }
    ],
    "sg:phone":"+1 925 938 5408",
    "sg:postcode":"94597",
    "sg:province":"CA",
    "sg:tags":[
        "business"
    ],
    "wof:name":"Austin Travel Corp",
    "wof:placetype":"venue"
},
  "geometry": {"coordinates":[-122.05911500000001,37.916847],"type":"Point"}
}