{
  "type": "Feature",
  "properties": {
    "iso:country":"US",
    "sg:address":"12921 Fern St",
    "sg:city":"Garden Grove",
    "sg:classifiers":[
        {
            "category":"Autos & Motor Vehicles",
            "subcategory":"Automobile Sales",
            "type":"Retail Goods"
        }
    ],
    "sg:phone":"+1 714 373 0011",
    "sg:postcode":"92841",
    "sg:province":"CA",
    "sg:tags":[
        "car",
        "dealer"
    ],
    "wof:name":"Daehan Motors",
    "wof:placetype":"venue"
},
  "geometry": {"coordinates":[-117.988387,33.774618],"type":"Point"}
}