{
  "type": "Feature",
  "properties": {
    "iso:country":"US",
    "sg:address":"9980 State Hwy 1",
    "sg:city":"Olema",
    "sg:classifiers":[
        {
            "category":"Shopping",
            "type":"Retail Goods"
        }
    ],
    "sg:phone":"+1 415 663 8948",
    "sg:postcode":"94950",
    "sg:province":"CA",
    "sg:tags":[
        "art",
        "gallery",
        "dealer"
    ],
    "wof:name":"Xquisit Art",
    "wof:placetype":"venue"
},
  "geometry": {"coordinates":[-122.76014499999999,38.049951],"type":"Point"}
}