{
  "type": "Feature",
  "properties": {
    "iso:country":"US",
    "sg:address":"965 S Meridian Ave",
    "sg:city":"Alhambra",
    "sg:classifiers":[
        {
            "category":"Shopping",
            "subcategory":"Music",
            "type":"Retail Goods"
        }
    ],
    "sg:phone":"+1 626 308 9190",
    "sg:postcode":"91803",
    "sg:province":"CA",
    "sg:tags":[
        "video",
        "disc",
        "tape",
        "cassette"
    ],
    "wof:name":"LANDMARK Media Corp",
    "wof:placetype":"venue"
},
  "geometry": {"coordinates":[-118.153917,34.083129],"type":"Point"}
}