{
  "type": "Feature",
  "properties": {
    "addr:full":"2223 Wellington Ave Santa Ana CA 92701",
    "addr:housenumber":"2223",
    "addr:postcode":"92701",
    "addr:street":"Wellington Ave",
    "iso:country":"US",
    "sg:address":"2223 Wellington Ave",
    "sg:city":"Santa Ana",
    "sg:classifiers":[
        {
            "category":"Insurance",
            "subcategory":"Hazard Insurance",
            "type":"Services"
        }
    ],
    "sg:phone":"+1 714 558 6200",
    "sg:postcode":"92701",
    "sg:province":"CA",
    "sg:tags":[
        "fund"
    ],
    "wof:name":"Retirement Office",
    "wof:placetype":"venue"
},
  "geometry": {"coordinates":[-117.834722,33.755285],"type":"Point"}
}