{
  "type": "Feature",
  "properties": {
    "iso:country":"US",
    "sg:address":"12401 Woodruff Ave",
    "sg:city":"Downey",
    "sg:classifiers":[
        {
            "category":"Wholesale",
            "subcategory":"Electrical",
            "type":"Manufacturing & Wholesale Goods"
        }
    ],
    "sg:phone":"+1 562 401 9337",
    "sg:postcode":"90241",
    "sg:province":"CA",
    "sg:tags":[
        "equipment",
        "electronic",
        "supply"
    ],
    "wof:name":"Mc O Electronics",
    "wof:placetype":"venue"
},
  "geometry": {"coordinates":[-118.116721,33.91808],"type":"Point"}
}