{
  "type": "Feature",
  "properties": {
    "iso:country":"US",
    "sg:address":"1300 Gardena Ave",
    "sg:city":"Glendale",
    "sg:classifiers":[
        {
            "category":"Building & Trades",
            "subcategory":"Plumbing",
            "type":"Services"
        }
    ],
    "sg:phone":"+1 323 255 0111",
    "sg:postcode":"91204",
    "sg:province":"CA",
    "sg:tags":[
        "contractor"
    ],
    "wof:name":"Patton & Maloney Plumbing",
    "wof:placetype":"venue"
},
  "geometry": {"coordinates":[-118.261002,34.128201],"type":"Point"}
}