{
  "type": "Feature",
  "properties": {
    "addr:full":"3849 E Foothill Blvd Pasadena CA 91107",
    "addr:housenumber":"3849",
    "addr:postcode":"91107",
    "addr:street":"E Foothill Blvd",
    "iso:country":"US",
    "sg:address":"3849 E Foothill Blvd",
    "sg:city":"Pasadena",
    "sg:classifiers":[
        {
            "category":"Shopping",
            "subcategory":"Beauty & Cosmetics",
            "type":"Retail Goods"
        }
    ],
    "sg:phone":"+1 626 351 4776",
    "sg:postcode":"91107",
    "sg:province":"CA",
    "sg:tags":[
        "supply"
    ],
    "wof:name":"Han's Beauty Store",
    "wof:placetype":"venue"
},
  "geometry": {"coordinates":[-118.070999,34.150398],"type":"Point"}
}