{
  "type": "Feature",
  "properties": {
    "addr:full":"1765 Pentecost Way San Diego CA 92105",
    "addr:housenumber":"1765",
    "addr:postcode":"92105",
    "addr:street":"Pentecost Way",
    "iso:country":"US",
    "sg:address":"1765 Pentecost Way",
    "sg:city":"San Diego",
    "sg:classifiers":[
        {
            "category":"Organizations",
            "subcategory":"Religious Organization",
            "type":"Services"
        }
    ],
    "sg:phone":"+1 619 264 1721",
    "sg:postcode":"92105",
    "sg:province":"CA",
    "wof:name":"Tabernacle Christian Academy",
    "wof:placetype":"venue"
},
  "geometry": {"coordinates":[-117.081001,32.7239],"type":"Point"}
}