{
  "type": "Feature",
  "properties": {
    "addr:full":"740 Heinz Ave Berkeley CA 94710",
    "addr:housenumber":"740",
    "addr:postcode":"94710",
    "addr:street":"Heinz Ave",
    "iso:country":"US",
    "sg:address":"740 Heinz Ave",
    "sg:city":"Berkeley",
    "sg:classifiers":[
        {
            "category":"Manufacturing",
            "subcategory":"Lumber",
            "type":"Manufacturing & Wholesale Goods"
        }
    ],
    "sg:phone":"+1 510 845 1246",
    "sg:postcode":"94710",
    "sg:province":"CA",
    "sg:tags":[
        "wooden",
        "mfg",
        "furniture"
    ],
    "wof:name":"Frances Todd Inc",
    "wof:placetype":"venue"
},
  "geometry": {"coordinates":[-122.295542,37.85276],"type":"Point"}
}