{
  "type": "Feature",
  "properties": {
    "addr:full":"31789 State Hwy 79 S Temecula CA 92592",
    "addr:housenumber":"31789",
    "addr:postcode":"92592",
    "addr:street":"State Hwy 79 S",
    "iso:country":"US",
    "sg:address":"31789 State Hwy 79 S",
    "sg:city":"Temecula",
    "sg:classifiers":[
        {
            "category":"Shopping",
            "subcategory":"Clothing, Apparel, & Fashions",
            "type":"Retail Goods"
        }
    ],
    "sg:phone":"+1 951 694 6677",
    "sg:postcode":"92592",
    "sg:province":"CA",
    "wof:name":"Basic 21 Rideshop",
    "wof:placetype":"venue"
},
  "geometry": {"coordinates":[-117.105598,33.47925],"type":"Point"}
}