{
  "type": "Feature",
  "properties": {
    "addr:full":"14015 S Vermont Ave Gardena CA 90247",
    "addr:housenumber":"14015",
    "addr:postcode":"90247",
    "addr:street":"S Vermont Ave",
    "iso:country":"US",
    "sg:address":"14015 S Vermont Ave",
    "sg:city":"Gardena",
    "sg:classifiers":[
        {
            "category":"Food & Beverages",
            "subcategory":"Groceries & Convenience Stores",
            "type":"Retail Goods"
        }
    ],
    "sg:phone":"+1 310 324 5575",
    "sg:postcode":"90247",
    "sg:province":"CA",
    "wof:name":"Quigley's Mkt",
    "wof:placetype":"venue"
},
  "geometry": {"coordinates":[-118.292,33.904099],"type":"Point"}
}