{
  "type": "Feature",
  "properties": {
    "addr:full":"1127 W Indianapolis Ave Fresno CA 93705",
    "addr:housenumber":"1127",
    "addr:postcode":"93705",
    "addr:street":"W Indianapolis Ave",
    "iso:country":"US",
    "sg:address":"1127 W Indianapolis Ave",
    "sg:city":"Fresno",
    "sg:classifiers":[
        {
            "category":"Health Services",
            "subcategory":"Health Practitioner",
            "type":"Services"
        }
    ],
    "sg:phone":"+1 559 225 6917",
    "sg:postcode":"93705",
    "sg:province":"CA",
    "sg:tags":[
        "acupuncture"
    ],
    "wof:name":"Mag's Healing Touch Shiatsu",
    "wof:placetype":"venue"
},
  "geometry": {"coordinates":[-119.82548199999999,36.799431],"type":"Point"}
}