{
  "type": "Feature",
  "properties": {
    "iso:country":"US",
    "sg:address":"1815 Hawthorne Blvd",
    "sg:city":"Redondo Beach",
    "sg:classifiers":[
        {
            "category":"Shopping",
            "subcategory":"Photographic Equipment",
            "type":"Retail Goods"
        }
    ],
    "sg:phone":"+1 310 542 4098",
    "sg:postcode":"90278",
    "sg:province":"CA",
    "sg:tags":[
        "supply"
    ],
    "wof:name":"Kits Cameras",
    "wof:placetype":"venue"
},
  "geometry": {"coordinates":[-118.352524,33.870239],"type":"Point"}
}