{
  "type": "Feature",
  "properties": {
    "addr:full":"4868 Petrified Forest Rd Calistoga CA 94515",
    "addr:housenumber":"4868",
    "addr:postcode":"94515",
    "addr:street":"Petrified Forest Rd",
    "iso:country":"US",
    "sg:address":"4868 Petrified Forest Rd",
    "sg:city":"Calistoga",
    "sg:classifiers":[
        {
            "category":"Personal",
            "type":"Services"
        },
        {
            "category":"Real Estate",
            "subcategory":"Architect",
            "type":"Services"
        }
    ],
    "sg:phone":"+1 707 942 6540",
    "sg:postcode":"94515",
    "sg:province":"CA",
    "sg:tags":[
        "local"
    ],
    "sg:website":"www.pmarchitect.com",
    "wof:name":"Patrick Mervin + Associates Architects, AIA",
    "wof:placetype":"venue"
},
  "geometry": {"coordinates":[-122.63400300000001,38.559299],"type":"Point"}
}