{
  "type": "Feature",
  "properties": {
    "addr:full":"819 Cleveland Ave Escondido CA 92026",
    "addr:housenumber":"819",
    "addr:postcode":"92026",
    "addr:street":"Cleveland Ave",
    "iso:country":"US",
    "sg:address":"819 Cleveland Ave",
    "sg:city":"Escondido",
    "sg:classifiers":[
        {
            "category":"Building & Trades",
            "subcategory":"Electrical",
            "type":"Services"
        }
    ],
    "sg:phone":"+1 760 735 2587",
    "sg:postcode":"92026",
    "sg:province":"CA",
    "sg:tags":[
        "electrical",
        "contractor"
    ],
    "wof:name":"Digitalcomm Communications",
    "wof:placetype":"venue"
},
  "geometry": {"coordinates":[-117.08107,33.171553],"type":"Point"}
}