{
  "type": "Feature",
  "properties": {
    "addr:full":"8 Francisco Vista Ct Belvedere Tibrn CA 94920",
    "addr:postcode":"94920",
    "addr:street":"Francisco Vista Ct",
    "iso:country":"US",
    "sg:address":"8 Francisco Vista Ct",
    "sg:city":"Belvedere Tibrn",
    "sg:classifiers":[
        {
            "category":"Personal",
            "subcategory":"Hair Removal",
            "type":"Services"
        }
    ],
    "sg:phone":"+1 415 986 9500",
    "sg:postcode":"94920",
    "sg:province":"CA",
    "sg:tags":[
        "removing"
    ],
    "wof:name":"Sona Med Spa",
    "wof:placetype":"venue"
},
  "geometry": {"coordinates":[-122.478528,37.892936],"type":"Point"}
}