{
  "type": "Feature",
  "properties": {
    "addr:full":"1985 Wilcox Ave Monterey Park CA 91755",
    "addr:housenumber":"1985",
    "addr:postcode":"91755",
    "addr:street":"Wilcox Ave",
    "iso:country":"US",
    "sg:address":"1985 Wilcox Ave",
    "sg:city":"Monterey Park",
    "sg:classifiers":[
        {
            "category":"Manufacturing",
            "subcategory":"Jewelry",
            "type":"Manufacturing & Wholesale Goods"
        }
    ],
    "sg:phone":"+1 323 722 8757",
    "sg:postcode":"91755",
    "sg:province":"CA",
    "sg:tags":[
        "precious",
        "metal",
        "mfg"
    ],
    "wof:name":"Jls Enterprises",
    "wof:placetype":"venue"
},
  "geometry": {"coordinates":[-118.128135,34.041079],"type":"Point"}
}