{
  "type": "Feature",
  "properties": {
    "addr:full":"775 Lincoln Ave San Jose CA 95126",
    "addr:housenumber":"775",
    "addr:postcode":"95126",
    "addr:street":"Lincoln Ave",
    "iso:country":"US",
    "sg:address":"775 Lincoln Ave",
    "sg:city":"San Jose",
    "sg:classifiers":[
        {
            "category":"Wholesale",
            "subcategory":"Scrap",
            "type":"Manufacturing & Wholesale Goods"
        }
    ],
    "sg:phone":"+1 408 292 3333",
    "sg:postcode":"95126",
    "sg:province":"CA",
    "sg:tags":[
        "recycling",
        "center"
    ],
    "sg:website":"ranchtownrecycling.com/",
    "wof:name":"Ranch Town Recycling Center Inc",
    "wof:placetype":"venue"
},
  "geometry": {"coordinates":[-121.906963,37.315467],"type":"Point"}
}