{
  "type": "Feature",
  "properties": {
    "addr:full":"31555 Rustic Oak Dr Westlake Village CA 91361",
    "addr:housenumber":"31555",
    "addr:postcode":"91361",
    "addr:street":"Rustic Oak Dr",
    "iso:country":"US",
    "sg:address":"31555 Rustic Oak Dr",
    "sg:city":"Westlake Village",
    "sg:classifiers":[
        {
            "category":"Travel",
            "subcategory":"Travel Agent",
            "type":"Entertainment"
        }
    ],
    "sg:phone":"+1 818 575 9580",
    "sg:postcode":"91361",
    "sg:province":"CA",
    "sg:tags":[
        "operator",
        "tour"
    ],
    "wof:name":"Twilight Tours",
    "wof:placetype":"venue"
},
  "geometry": {"coordinates":[-118.810019,34.141923],"type":"Point"}
}