{
  "type": "Feature",
  "properties": {
    "addr:full":"20695 S Western Ave Torrance CA 90501",
    "addr:housenumber":"20695",
    "addr:postcode":"90501",
    "addr:street":"S Western Ave",
    "iso:country":"US",
    "sg:address":"20695 S Western Ave",
    "sg:city":"Torrance",
    "sg:classifiers":[
        {
            "category":"Travel",
            "subcategory":"Travel Agent",
            "type":"Entertainment"
        }
    ],
    "sg:phone":"+1 310 324 9261",
    "sg:postcode":"90501",
    "sg:province":"CA",
    "sg:tags":[
        "agency",
        "bureau"
    ],
    "wof:name":"Global International Svc Inc",
    "wof:placetype":"venue"
},
  "geometry": {"coordinates":[-118.309332,33.843366],"type":"Point"}
}