{
  "type": "Feature",
  "properties": {
    "iso:country":"US",
    "sg:address":"7581 Chapman Ave",
    "sg:city":"Garden Grove",
    "sg:classifiers":[
        {
            "category":"Retail",
            "subcategory":"Storage",
            "type":"Services"
        }
    ],
    "sg:phone":"+1 714 799 9338",
    "sg:postcode":"92841",
    "sg:province":"CA",
    "sg:tags":[
        "self"
    ],
    "wof:name":"Chapman Rv Storage",
    "wof:placetype":"venue"
},
  "geometry": {"coordinates":[-117.99900100000001,33.788399],"type":"Point"}
}