{
  "type": "Feature",
  "properties": {
    "iso:country":"US",
    "sg:address":"9160 Santa Barbara Rd",
    "sg:city":"Atascadero",
    "sg:classifiers":[
        {
            "category":"Professional",
            "subcategory":"Business Services",
            "type":"Services"
        }
    ],
    "sg:phone":"+1 805 462 1393",
    "sg:postcode":"93422",
    "sg:province":"CA",
    "sg:tags":[
        "barricade"
    ],
    "wof:name":"Baiba's Safety Svc Inc",
    "wof:placetype":"venue"
},
  "geometry": {"coordinates":[-120.636737,35.445558],"type":"Point"}
}