{
  "type": "Feature",
  "properties": {
    "iso:country":"US",
    "sg:address":"411 Palm St",
    "sg:city":"Santa Cruz",
    "sg:classifiers":[
        {
            "category":"Professional",
            "type":"Services"
        }
    ],
    "sg:phone":"+1 831 426 2136",
    "sg:postcode":"95060",
    "sg:province":"CA",
    "sg:tags":[
        "establishment"
    ],
    "wof:name":"Ersilis Galli",
    "wof:placetype":"venue"
},
  "geometry": {"coordinates":[-122.038687,36.962654],"type":"Point"}
}