{
  "type": "Feature",
  "properties": {
    "addr:full":"815 Tucker Rd Tehachapi CA 93561",
    "addr:housenumber":"815",
    "addr:postcode":"93561",
    "addr:street":"Tucker Rd",
    "iso:country":"US",
    "sg:address":"815 Tucker Rd",
    "sg:city":"Tehachapi",
    "sg:classifiers":[
        {
            "category":"Personal",
            "subcategory":"Beauty Salon",
            "type":"Services"
        }
    ],
    "sg:phone":"+1 661 822 9529",
    "sg:postcode":"93561",
    "sg:province":"CA",
    "wof:name":"Holiday Hair & Nails",
    "wof:placetype":"venue"
},
  "geometry": {"coordinates":[-118.46785199999999,35.11807],"type":"Point"}
}