{
  "type": "Feature",
  "properties": {
    "addr:full":"7600 Eathart Road Oakland CA 94614",
    "addr:housenumber":"7600",
    "addr:postcode":"94614",
    "addr:street":"Eathart Road",
    "iso:country":"US",
    "sg:address":"7600 Eathart Road",
    "sg:city":"Oakland",
    "sg:classifiers":[
        {
            "category":"Retail",
            "subcategory":"Auto Rental",
            "type":"Services"
        }
    ],
    "sg:phone":"+1 866 434 2226",
    "sg:postcode":"94614",
    "sg:province":"CA",
    "sg:tags":[
        "car"
    ],
    "sg:website":"www.dollar.com",
    "wof:name":"Dollar Rent A Car - Oakland Int'l Airport",
    "wof:placetype":"venue"
},
  "geometry": {"coordinates":[-122.216455,37.737231],"type":"Point"}
}