{
  "type": "Feature",
  "properties": {
    "addr:full":"4360 Melrose Ave Los Angeles CA 90029",
    "addr:housenumber":"4360",
    "addr:postcode":"90029",
    "addr:street":"Melrose Ave",
    "iso:country":"US",
    "sg:address":"4360 Melrose Ave",
    "sg:city":"Los Angeles",
    "sg:classifiers":[
        {
            "category":"Communications",
            "subcategory":"Film & Video Production",
            "type":"Services"
        }
    ],
    "sg:phone":"+1 323 664 8791",
    "sg:postcode":"90029",
    "sg:province":"CA",
    "sg:tags":[
        "taping"
    ],
    "wof:name":"Salvavision Production Distr",
    "wof:placetype":"venue"
},
  "geometry": {"coordinates":[-118.294066,34.083588],"type":"Point"}
}