{
  "type": "Feature",
  "properties": {
    "addr:full":"12155 Kirkham Rd Poway CA 92064",
    "addr:housenumber":"12155",
    "addr:postcode":"ca 92064",
    "addr:street":"Kirkham Rd",
    "iso:country":"US",
    "sg:address":"12155 Kirkham Rd",
    "sg:city":"Poway",
    "sg:classifiers":[
        {
            "category":"Wholesale",
            "subcategory":"Groceries",
            "type":"Manufacturing & Wholesale Goods"
        }
    ],
    "sg:phone":"+1 858 679 9962",
    "sg:postcode":"92064",
    "sg:province":"CA",
    "sg:tags":[
        "confectionery",
        "candy"
    ],
    "sg:website":"www.maredy.com",
    "wof:name":"Maredy Corp",
    "wof:placetype":"venue"
},
  "geometry": {"coordinates":[-117.049938,32.936827],"type":"Point"}
}