{
  "type": "Feature",
  "properties": {
    "iso:country":"US",
    "sg:address":"6314 de Woody St",
    "sg:city":"Laton",
    "sg:classifiers":[
        {
            "category":"Home & Garden",
            "subcategory":"Hardware",
            "type":"Retail Goods"
        }
    ],
    "sg:phone":"+1 559 923 4846",
    "sg:postcode":"93242",
    "sg:province":"CA",
    "wof:name":"Singleton Hardware & Supply",
    "wof:placetype":"venue"
},
  "geometry": {"coordinates":[-119.68387,36.43506],"type":"Point"}
}