{
  "type": "Feature",
  "properties": {
    "addr:full":"250 Hamilton Ave Palo Alto CA 94301",
    "addr:housenumber":"250",
    "addr:postcode":"94301",
    "addr:street":"Hamilton Ave",
    "iso:country":"US",
    "sg:address":"250 Hamilton Ave",
    "sg:city":"Palo Alto",
    "sg:classifiers":[
        {
            "category":"Government",
            "subcategory":"Office",
            "type":"Public Place"
        }
    ],
    "sg:phone":"+1 650 329 2428",
    "sg:postcode":"94301",
    "sg:province":"CA",
    "sg:tags":[
        "city",
        "planning",
        "dev"
    ],
    "wof:name":"Community Development Block",
    "wof:placetype":"venue"
},
  "geometry": {"coordinates":[-122.16032,37.44508],"type":"Point"}
}