{
  "type": "Feature",
  "properties": {
    "iso:country":"US",
    "sg:address":"1127 Broad St",
    "sg:city":"San Luis Obispo",
    "sg:classifiers":[
        {
            "category":"Food & Beverages",
            "subcategory":"Bakery",
            "type":"Retail Goods"
        }
    ],
    "sg:phone":"+1 805 541 5134",
    "sg:postcode":"93401",
    "sg:province":"CA",
    "sg:tags":[
        "bagel"
    ],
    "wof:name":"Boston Bagel Co",
    "wof:placetype":"venue"
},
  "geometry": {"coordinates":[-120.664388,35.278634],"type":"Point"}
}