{
  "type": "Feature",
  "properties": {
    "addr:full":"3416 Henderson Cir Santa Rosa CA 95404",
    "addr:housenumber":"3416",
    "addr:postcode":"95404",
    "addr:street":"Henderson Cir",
    "iso:country":"US",
    "sg:address":"3416 Henderson Cir",
    "sg:city":"Santa Rosa",
    "sg:classifiers":[
        {
            "category":"Professional",
            "subcategory":"Business Services",
            "type":"Services"
        }
    ],
    "sg:phone":"+1 707 528 4200",
    "sg:postcode":"95404",
    "sg:province":"CA",
    "wof:name":"Expressions Design Co",
    "wof:placetype":"venue"
},
  "geometry": {"coordinates":[-122.713992,38.473008],"type":"Point"}
}