{
  "type": "Feature",
  "properties": {
    "addr:full":"40037 State Hwy 41 Oakhurst CA 93644",
    "addr:housenumber":"40037",
    "addr:postcode":"93644",
    "addr:street":"State Hwy 41",
    "iso:country":"US",
    "sg:address":"40037 State Hwy 41",
    "sg:city":"Oakhurst",
    "sg:classifiers":[
        {
            "category":"Shopping",
            "subcategory":"Computers & Home Electronics",
            "type":"Retail Goods"
        }
    ],
    "sg:phone":"+1 559 683 4862",
    "sg:postcode":"93644",
    "sg:province":"CA",
    "sg:tags":[
        "parts",
        "supply"
    ],
    "wof:name":"National Computer Software",
    "wof:placetype":"venue"
},
  "geometry": {"coordinates":[-119.656468,37.330079],"type":"Point"}
}