{
  "type": "Feature",
  "properties": {
    "addr:full":"3530 Wilshire Boulevard Los Angeles CA 90010",
    "addr:housenumber":"3530",
    "addr:postcode":"90010",
    "addr:street":"Wilshire Boulevard",
    "iso:country":"US",
    "sg:address":"3530 Wilshire Boulevard",
    "sg:city":"Los Angeles",
    "sg:classifiers":[
        {
            "category":"Professional",
            "subcategory":"Accounting & Tax Preparation",
            "type":"Services"
        }
    ],
    "sg:phone":"+1 213 380 8866",
    "sg:postcode":"90010",
    "sg:province":"CA",
    "sg:tags":[
        "accountant"
    ],
    "wof:name":"Lee John H CPA",
    "wof:placetype":"venue"
},
  "geometry": {"coordinates":[-118.30036800000001,34.06176],"type":"Point"}
}