{
  "type": "Feature",
  "properties": {
    "iso:country":"US",
    "sg:address":"6141 Randolph St",
    "sg:city":"Los Angeles",
    "sg:classifiers":[
        {
            "category":"Wholesale",
            "subcategory":"Groceries",
            "type":"Manufacturing & Wholesale Goods"
        }
    ],
    "sg:phone":"+1 323 721 6127",
    "sg:postcode":"90040",
    "sg:province":"CA",
    "sg:tags":[
        "food",
        "product"
    ],
    "wof:name":"Cordialsa USA",
    "wof:placetype":"venue"
},
  "geometry": {"coordinates":[-118.154252,33.97852],"type":"Point"}
}