{
  "type": "Feature",
  "properties": {
    "addr:full":"7998 Hollywood Blvd West Hollywood CA 90046",
    "addr:housenumber":"7998",
    "addr:postcode":"90046",
    "addr:street":"Hollywood Blvd",
    "iso:country":"US",
    "sg:address":"7998 Hollywood Blvd",
    "sg:city":"West Hollywood",
    "sg:classifiers":[
        {
            "category":"Shopping",
            "subcategory":"Clothing, Apparel, & Fashions",
            "type":"Retail Goods"
        }
    ],
    "sg:phone":"+1 323 650 0376",
    "sg:postcode":"90046",
    "sg:province":"CA",
    "sg:tags":[
        "alteration"
    ],
    "wof:name":"Cayirar Gele",
    "wof:placetype":"venue"
},
  "geometry": {"coordinates":[-118.36156699999999,34.10131],"type":"Point"}
}