{
  "type": "Feature",
  "properties": {
    "iso:country":"US",
    "sg:address":"7549 Convoy Ct",
    "sg:city":"San Diego",
    "sg:classifiers":[
        {
            "category":"Retail",
            "subcategory":"Auto Repair",
            "type":"Services"
        }
    ],
    "sg:phone":"+1 858 974 3685",
    "sg:postcode":"92111",
    "sg:province":"CA",
    "sg:tags":[
        "automobile",
        "diagnostic"
    ],
    "wof:name":"QLD Information Corp",
    "wof:placetype":"venue"
},
  "geometry": {"coordinates":[-117.155017,32.834665],"type":"Point"}
}