{
  "type": "Feature",
  "properties": {
    "iso:country":"US",
    "sg:address":"2251 Buena Vista Ave",
    "sg:city":"San Leandro",
    "sg:classifiers":[
        {
            "category":"Communications",
            "type":"Services"
        },
        {
            "category":"Professional",
            "subcategory":"Computer Services",
            "type":"Services"
        }
    ],
    "sg:phone":"+1 510 962 4760",
    "sg:postcode":"94577",
    "sg:province":"CA",
    "sg:tags":[
        "repair",
        "design",
        "web"
    ],
    "sg:website":"www.boundarycross.com",
    "wof:name":"Boundary Cross Online Solutions LLC.",
    "wof:placetype":"venue"
},
  "geometry": {"coordinates":[-122.149845,37.71653],"type":"Point"}
}