{
  "type": "Feature",
  "properties": {
    "addr:full":"73851 Hwy 111 Palm Desert CA 92260",
    "addr:housenumber":"73851",
    "addr:postcode":"ca 92260",
    "addr:street":"Hwy 111",
    "iso:country":"US",
    "sg:address":"73851 Hwy 111",
    "sg:city":"Palm Desert",
    "sg:classifiers":[
        {
            "category":"Shopping",
            "subcategory":"Crafts & Fabrics",
            "type":"Retail Goods"
        }
    ],
    "sg:phone":"+1 760 568 2005",
    "sg:postcode":"92260",
    "sg:province":"CA",
    "sg:tags":[
        "sewing"
    ],
    "wof:name":"Needlepoint Joint",
    "wof:placetype":"venue"
},
  "geometry": {"coordinates":[-116.37427599999999,33.721216],"type":"Point"}
}