{
  "type": "Feature",
  "properties": {
    "iso:country":"US",
    "sg:address":"40 Birch St",
    "sg:city":"Redwood City",
    "sg:classifiers":[
        {
            "category":"Professional",
            "subcategory":"Accounting & Tax Preparation",
            "type":"Services"
        }
    ],
    "sg:phone":"+1 650 369 1040",
    "sg:postcode":"94062",
    "sg:province":"CA",
    "sg:tags":[
        "bookkeeping",
        "general"
    ],
    "wof:name":"Padgett Business Svc",
    "wof:placetype":"venue"
},
  "geometry": {"coordinates":[-122.240357,37.488097],"type":"Point"}
}