{
  "type": "Feature",
  "properties": {
    "iso:country":"US",
    "sg:address":"1696 Laurel St",
    "sg:city":"San Carlos",
    "sg:classifiers":[
        {
            "category":"Home & Garden",
            "subcategory":"Hardware",
            "type":"Retail Goods"
        }
    ],
    "sg:phone":"+1 650 593 5277",
    "sg:postcode":"94070",
    "sg:province":"CA",
    "wof:name":"White Oaks Hardware",
    "wof:placetype":"venue"
},
  "geometry": {"coordinates":[-122.247435,37.494973],"type":"Point"}
}