{
  "type": "Feature",
  "properties": {
    "addr:full":"3260 Beard Rd Napa CA 94558",
    "addr:housenumber":"3260",
    "addr:postcode":"94558",
    "addr:street":"Beard Rd",
    "iso:country":"US",
    "sg:address":"3260 Beard Rd",
    "sg:city":"Napa",
    "sg:classifiers":[
        {
            "category":"Health Services",
            "subcategory":"Doctor",
            "type":"Services"
        }
    ],
    "sg:phone":"+1 707 255 6212",
    "sg:postcode":"94558",
    "sg:province":"CA",
    "sg:tags":[
        "physician",
        "surgeon"
    ],
    "wof:name":"Eye Specialists",
    "wof:placetype":"venue"
},
  "geometry": {"coordinates":[-122.295546,38.322249],"type":"Point"}
}