{
  "type": "Feature",
  "properties": {
    "addr:full":"8216 Lankershim Blvd North Hollywood CA 91605",
    "addr:housenumber":"8216",
    "addr:postcode":"91605",
    "addr:street":"Lankershim Blvd",
    "iso:country":"US",
    "sg:address":"8216 Lankershim Blvd",
    "sg:city":"North Hollywood",
    "sg:classifiers":[
        {
            "category":"Manufacturing",
            "subcategory":"Tools & Machinery",
            "type":"Manufacturing & Wholesale Goods"
        }
    ],
    "sg:phone":"+1 818 767 3117",
    "sg:postcode":"91605",
    "sg:province":"CA",
    "sg:tags":[
        "machine",
        "copying",
        "supply"
    ],
    "wof:name":"Strictly Wholesale",
    "wof:placetype":"venue"
},
  "geometry": {"coordinates":[-118.387704,34.222258],"type":"Point"}
}