{
  "type": "Feature",
  "properties": {
    "addr:full":"1396 Park Ave Emeryville CA 94608",
    "addr:housenumber":"1396",
    "addr:postcode":"94608",
    "addr:street":"Park Ave",
    "iso:country":"US",
    "sg:address":"1396 Park Ave",
    "sg:city":"Emeryville",
    "sg:classifiers":[
        {
            "category":"Professional",
            "type":"Services"
        }
    ],
    "sg:phone":"+1 510 594 1300",
    "sg:postcode":"94608",
    "sg:province":"CA",
    "sg:website":"www.wag.com",
    "wof:name":"Walcott-Ayers Group",
    "wof:placetype":"venue"
},
  "geometry": {"coordinates":[-122.287003,37.8311],"type":"Point"}
}