{
  "type": "Feature",
  "properties": {
    "addr:full":"5923 Severin Dr La Mesa CA 91942",
    "addr:housenumber":"5923",
    "addr:postcode":"91942",
    "addr:street":"Severin Dr",
    "iso:country":"US",
    "sg:address":"5923 Severin Dr",
    "sg:city":"La Mesa",
    "sg:classifiers":[
        {
            "category":"Shopping",
            "subcategory":"Jewelry",
            "type":"Retail Goods"
        }
    ],
    "sg:phone":"+1 619 463 8322",
    "sg:postcode":"91942",
    "sg:province":"CA",
    "sg:tags":[
        "jeweler"
    ],
    "sg:website":"www.htimwilliamsjewelers.com",
    "wof:name":"H Tim Williams Jewelers",
    "wof:placetype":"venue"
},
  "geometry": {"coordinates":[-116.999093,32.787194],"type":"Point"}
}