{
  "type": "Feature",
  "properties": {
    "addr:full":"3821 Smith St Union City CA 94587",
    "addr:housenumber":"3821",
    "addr:postcode":"94587",
    "addr:street":"Smith St",
    "iso:country":"US",
    "sg:address":"3821 Smith St",
    "sg:city":"Union City",
    "sg:classifiers":[
        {
            "category":"Restaurant",
            "type":"Food & Drink"
        }
    ],
    "sg:phone":"+1 510 477 8868",
    "sg:postcode":"94587",
    "sg:province":"CA",
    "wof:name":"Dragon House",
    "wof:placetype":"venue"
},
  "geometry": {"coordinates":[-122.077474,37.596541],"type":"Point"}
}