{
  "type": "Feature",
  "properties": {
    "addr:full":"8606 Commerce Ave San Diego CA 92121",
    "addr:housenumber":"8606",
    "addr:postcode":"92121",
    "addr:street":"Commerce Ave",
    "iso:country":"US",
    "sg:address":"8606 Commerce Ave",
    "sg:city":"San Diego",
    "sg:classifiers":[
        {
            "category":"Manufacturing",
            "subcategory":"Tools & Machinery",
            "type":"Manufacturing & Wholesale Goods"
        }
    ],
    "sg:phone":"+1 858 578 6815",
    "sg:postcode":"92121",
    "sg:province":"CA",
    "sg:tags":[
        "generator"
    ],
    "wof:name":"M Engineering",
    "wof:placetype":"venue"
},
  "geometry": {"coordinates":[-117.167736,32.881279],"type":"Point"}
}