{
  "type": "Feature",
  "properties": {
    "addr:full":"234 Panorama Dr Bishop CA 93514",
    "addr:housenumber":"234",
    "addr:postcode":"93514",
    "addr:street":"Panorama Dr",
    "iso:country":"US",
    "sg:address":"234 Panorama Dr",
    "sg:city":"Bishop",
    "sg:classifiers":[
        {
            "category":"Building & Trades",
            "subcategory":"Landscaping Services",
            "type":"Services"
        }
    ],
    "sg:phone":"+1 760 873 7210",
    "sg:postcode":"93514",
    "sg:province":"CA",
    "sg:tags":[
        "lawn",
        "maintenance",
        "grounds"
    ],
    "wof:name":"Sonlight Outdoor Maintenance",
    "wof:placetype":"venue"
},
  "geometry": {"coordinates":[-118.385745,37.283532],"type":"Point"}
}