{
  "type": "Feature",
  "properties": {
    "iso:country":"US",
    "sg:address":"9938 Bolsa Ave Ste 112",
    "sg:city":"Westminster",
    "sg:classifiers":[
        {
            "category":"Shopping",
            "subcategory":"Computers & Home Electronics",
            "type":"Retail Goods"
        }
    ],
    "sg:phone":"+1 714 531 0808",
    "sg:postcode":"92683",
    "sg:province":"CA",
    "wof:name":"Tektronic Auto & Video",
    "wof:placetype":"venue"
},
  "geometry": {"coordinates":[-117.956001,33.7449],"type":"Point"}
}