{
  "type": "Feature",
  "properties": {
    "addr:full":"10417 Boulder St Nevada City CA 95959",
    "addr:housenumber":"10417",
    "addr:postcode":"95959",
    "addr:street":"Boulder St",
    "iso:country":"US",
    "sg:address":"10417 Boulder St",
    "sg:city":"Nevada City",
    "sg:classifiers":[
        {
            "category":"Professional",
            "type":"Services"
        }
    ],
    "sg:phone":"+1 530 478 1953",
    "sg:postcode":"95959",
    "sg:province":"CA",
    "wof:name":"Bruce Kristal",
    "wof:placetype":"venue"
},
  "geometry": {"coordinates":[-121.008809,39.262428],"type":"Point"}
}