{
  "type": "Feature",
  "properties": {
    "addr:full":"37710 Leta Dr Calimesa CA 92320",
    "addr:postcode":"37710;92320",
    "addr:street":"Leta Dr",
    "iso:country":"US",
    "sg:address":"37710 Leta Dr",
    "sg:city":"Calimesa",
    "sg:classifiers":[
        {
            "category":"Wholesale",
            "subcategory":"Poultry",
            "type":"Manufacturing & Wholesale Goods"
        }
    ],
    "sg:phone":"+1 909 795 1410",
    "sg:postcode":"92320",
    "sg:province":"CA",
    "sg:tags":[
        "eggs"
    ],
    "wof:name":"California Egg Exchange",
    "wof:placetype":"venue"
},
  "geometry": {"coordinates":[-117.01013399999999,33.995895],"type":"Point"}
}