{
  "type": "Feature",
  "properties": {
    "iso:country":"US",
    "sg:address":"6614 Florin Rd",
    "sg:city":"Sacramento",
    "sg:classifiers":[
        {
            "category":"Personal",
            "subcategory":"Beauty Salon",
            "type":"Services"
        }
    ],
    "sg:phone":"+1 916 395 7757",
    "sg:postcode":"95828",
    "sg:province":"CA",
    "sg:tags":[
        "manicuring"
    ],
    "wof:name":"Mary's Nail",
    "wof:placetype":"venue"
},
  "geometry": {"coordinates":[-121.41966600000001,38.495946],"type":"Point"}
}