{
  "type": "Feature",
  "properties": {
    "addr:full":"840 Verbena Ave Chico CA 95926",
    "addr:housenumber":"840",
    "addr:postcode":"95926",
    "addr:street":"Verbena Ave",
    "iso:country":"US",
    "sg:address":"840 Verbena Ave",
    "sg:city":"Chico",
    "sg:classifiers":[
        {
            "category":"Building & Trades",
            "subcategory":"Construction",
            "type":"Services"
        }
    ],
    "sg:phone":"+1 530 893 2520",
    "sg:postcode":"95926",
    "sg:province":"CA",
    "sg:tags":[
        "contractor"
    ],
    "wof:name":"D R Finish-Woodworking",
    "wof:placetype":"venue"
},
  "geometry": {"coordinates":[-121.817953,39.75127],"type":"Point"}
}