{
  "type": "Feature",
  "properties": {
    "iso:country":"US",
    "sg:address":"905 Newport Center Dr",
    "sg:city":"Newport Beach",
    "sg:classifiers":[
        {
            "category":"Shopping",
            "subcategory":"Jewelry",
            "type":"Retail Goods"
        }
    ],
    "sg:phone":"+1 949 760 3656",
    "sg:postcode":"92660",
    "sg:province":"CA",
    "sg:tags":[
        "jeweler"
    ],
    "wof:name":"Bronson Collection",
    "wof:placetype":"venue"
},
  "geometry": {"coordinates":[-117.878067,33.614387],"type":"Point"}
}