{
  "type": "Feature",
  "properties": {
    "iso:country":"US",
    "sg:address":"660 Kirkland Dr",
    "sg:city":"Sunnyvale",
    "sg:classifiers":[
        {
            "category":"Taxi",
            "type":"Transportation"
        }
    ],
    "sg:phone":"+1 408 735 1877",
    "sg:postcode":"94087",
    "sg:province":"CA",
    "sg:tags":[
        "taxicab"
    ],
    "wof:name":"Singh Jaswant",
    "wof:placetype":"venue"
},
  "geometry": {"coordinates":[-122.03971,37.340749],"type":"Point"}
}