{
  "type": "Feature",
  "properties": {
    "addr:full":"550 Continental Blvd Ste 110 El Segundo CA 90245",
    "addr:housenumber":"550",
    "addr:postcode":"90245",
    "addr:street":"Continental Blvd Ste 110",
    "iso:country":"US",
    "sg:address":"550 Continental Blvd Ste 110",
    "sg:city":"El Segundo",
    "sg:classifiers":[
        {
            "category":"Professional",
            "subcategory":"Art Services",
            "type":"Services"
        },
        {
            "category":"Professional",
            "subcategory":"Computer Services",
            "type":"Services"
        }
    ],
    "sg:phone":"+1 310 648 8414",
    "sg:postcode":"90245",
    "sg:province":"CA",
    "sg:tags":[
        "repair",
        "graphic",
        "design"
    ],
    "wof:name":"Executive Technology Services, Inc",
    "wof:placetype":"venue"
},
  "geometry": {"coordinates":[-118.390388,33.922108],"type":"Point"}
}