{
  "type": "Feature",
  "properties": {
    "iso:country":"US",
    "sg:address":"526 E 11th Street",
    "sg:city":"Los Angeles",
    "sg:classifiers":[
        {
            "category":"Shopping",
            "subcategory":"Clothing, Apparel, & Fashions",
            "type":"Retail Goods"
        }
    ],
    "sg:phone":"+1 213 746 9906",
    "sg:postcode":"90015",
    "sg:province":"CA",
    "sg:tags":[
        "clothing",
        "women's"
    ],
    "wof:name":"4 U Design",
    "wof:placetype":"venue"
},
  "geometry": {"coordinates":[-118.253691,34.036064],"type":"Point"}
}