{
  "type": "Feature",
  "properties": {
    "addr:full":"2500 Marina Point Ln Elk Grove CA 95758",
    "addr:housenumber":"2500",
    "addr:postcode":"95758",
    "addr:street":"Marina Point Ln",
    "iso:country":"US",
    "sg:address":"2500 Marina Point Ln",
    "sg:city":"Elk Grove",
    "sg:classifiers":[
        {
            "category":"Wholesale",
            "subcategory":"Durable Goods & Equipment",
            "type":"Manufacturing & Wholesale Goods"
        }
    ],
    "sg:phone":"+1 916 826 4218",
    "sg:postcode":"95758",
    "sg:province":"CA",
    "sg:tags":[
        "importer"
    ],
    "wof:name":"A Plus Import",
    "wof:placetype":"venue"
},
  "geometry": {"coordinates":[-121.47536700000001,38.41093],"type":"Point"}
}