{
  "type": "Feature",
  "properties": {
    "iso:country":"US",
    "sg:address":"2252 Honolulu Ave",
    "sg:city":"Montrose",
    "sg:classifiers":[
        {
            "category":"Home & Garden",
            "subcategory":"Household Appliances",
            "type":"Retail Goods"
        }
    ],
    "sg:phone":"+1 818 249 2466",
    "sg:postcode":"91020",
    "sg:province":"CA",
    "sg:tags":[
        "machine",
        "sewing"
    ],
    "sg:website":"www.mayhallssewingcenter.com",
    "wof:name":"Mayhall's Sewing & Vacuum Ctr",
    "wof:placetype":"venue"
},
  "geometry": {"coordinates":[-118.227976,34.205393],"type":"Point"}
}