{
  "type": "Feature",
  "properties": {
    "addr:full":"104 S Santa Cruz Ave Modesto CA 95354",
    "addr:housenumber":"104",
    "addr:postcode":"ca 95354",
    "addr:street":"S Santa Cruz Ave",
    "iso:country":"US",
    "sg:address":"104 S Santa Cruz Ave",
    "sg:city":"Modesto",
    "sg:classifiers":[
        {
            "category":"Shopping",
            "subcategory":"Used Merchandise",
            "type":"Retail Goods"
        }
    ],
    "sg:phone":"+1 209 579 9016",
    "sg:postcode":"95354",
    "sg:province":"CA",
    "sg:tags":[
        "shop",
        "thrift"
    ],
    "wof:name":"Rogers Thrift Shop",
    "wof:placetype":"venue"
},
  "geometry": {"coordinates":[-120.974684,37.636883],"type":"Point"}
}