{
  "type": "Feature",
  "properties": {
    "addr:full":"16530 Green Valley Truck Trl Ramona CA 92065",
    "addr:housenumber":"16530",
    "addr:postcode":"92065",
    "addr:street":"Green Valley Truck Trl",
    "iso:country":"US",
    "sg:address":"16530 Green Valley Truck Trl",
    "sg:city":"Ramona",
    "sg:classifiers":[
        {
            "category":"Professional",
            "subcategory":"Business Services",
            "type":"Services"
        }
    ],
    "sg:phone":"+1 760 788 6764",
    "sg:postcode":"92065",
    "sg:province":"CA",
    "sg:tags":[
        "painter",
        "sign"
    ],
    "wof:name":"Hal Snyder Signwriter",
    "wof:placetype":"venue"
},
  "geometry": {"coordinates":[-116.97262600000001,33.036662],"type":"Point"}
}