{
  "type": "Feature",
  "properties": {
    "iso:country":"US",
    "sg:address":"16530 Green Valley Truck Trl",
    "sg:city":"Ramona",
    "sg:classifiers":[
        {
            "category":"Professional",
            "subcategory":"Business Services",
            "type":"Services"
        }
    ],
    "sg:phone":"+1 760 788 6764",
    "sg:postcode":"92065",
    "sg:province":"CA",
    "sg:tags":[
        "painter",
        "sign"
    ],
    "wof:name":"Hal Snyder Signwriter",
    "wof:placetype":"venue"
},
  "geometry": {"coordinates":[-116.972626,33.036662],"type":"Point"}
}