{
  "type": "Feature",
  "properties": {
    "iso:country":"US",
    "sg:address":"421 Entrada Dr",
    "sg:city":"Santa Monica",
    "sg:classifiers":[
        {
            "category":"Education",
            "subcategory":"School",
            "type":"Public Place"
        }
    ],
    "sg:phone":"+1 310 454 7510",
    "sg:postcode":"90402",
    "sg:province":"CA",
    "wof:name":"Canyon Elementary School",
    "wof:placetype":"venue"
},
  "geometry": {"coordinates":[-118.513195,34.030668],"type":"Point"}
}