{
  "type": "Feature",
  "properties": {
    "iso:country":"US",
    "sg:address":"1519 N Gaffey St",
    "sg:city":"San Pedro",
    "sg:classifiers":[
        {
            "category":"Food & Beverages",
            "subcategory":"Groceries & Convenience Stores",
            "type":"Retail Goods"
        }
    ],
    "sg:phone":"+1 310 547 3757",
    "sg:postcode":"90731",
    "sg:province":"CA",
    "wof:name":"7-Eleven Food Stores",
    "wof:placetype":"venue"
},
  "geometry": {"coordinates":[-118.292999,33.758202],"type":"Point"}
}