{
  "type": "Feature",
  "properties": {
    "addr:full":"13125 Adenmoor Ave Downey CA 90242",
    "addr:postcode":"13125;90242",
    "addr:street":"Adenmoor Ave",
    "iso:country":"US",
    "sg:address":"13125 Adenmoor Ave",
    "sg:city":"Downey",
    "sg:classifiers":[
        {
            "category":"Retail",
            "subcategory":"Auto Repair",
            "type":"Services"
        }
    ],
    "sg:phone":"+1 562 440 2437",
    "sg:postcode":"90242",
    "sg:province":"CA",
    "sg:tags":[
        "repairing",
        "automobile"
    ],
    "wof:name":"Fix A Dent",
    "wof:placetype":"venue"
},
  "geometry": {"coordinates":[-118.123707,33.912074],"type":"Point"}
}