{
  "type": "Feature",
  "properties": {
    "iso:country":"US",
    "sg:address":"Valley Fair Mall 2855 Stevens Creek Blvd",
    "sg:city":"Santa Clara",
    "sg:classifiers":[
        {
            "category":"Shopping",
            "subcategory":"Clothing, Apparel, & Fashions",
            "type":"Retail Goods"
        }
    ],
    "sg:phone":"+1 408 249 5002",
    "sg:postcode":"95050",
    "sg:province":"CA",
    "sg:tags":[
        "clothing",
        "women's"
    ],
    "wof:name":"Charlotte Russe",
    "wof:placetype":"venue"
},
  "geometry": {"coordinates":[-121.947529,37.349242],"type":"Point"}
}