{
  "type": "Feature",
  "properties": {
    "iso:country":"US",
    "sg:address":"3037 Edinger Ave Ste B",
    "sg:city":"Tustin",
    "sg:classifiers":[
        {
            "category":"Autos & Motor Vehicles",
            "subcategory":"Auto Supplies",
            "type":"Retail Goods"
        }
    ],
    "sg:phone":"+1 949 733 8468",
    "sg:postcode":"92780",
    "sg:province":"CA",
    "sg:tags":[
        "glass"
    ],
    "sg:website":"www.houseoftints.com",
    "wof:name":"House of Tints",
    "wof:placetype":"venue"
},
  "geometry": {"coordinates":[-117.80647999999999,33.706987],"type":"Point"}
}