{
  "type": "Feature",
  "properties": {
    "addr:full":"23915 Fairlands Rd Hayward CA 94541",
    "addr:postcode":"23915;94541",
    "addr:street":"Fairlands Rd",
    "iso:country":"US",
    "sg:address":"23915 Fairlands Rd",
    "sg:city":"Hayward",
    "sg:classifiers":[
        {
            "category":"Food & Beverages",
            "subcategory":"Specialty",
            "type":"Retail Goods"
        }
    ],
    "sg:phone":"+1 510 582 6030",
    "sg:postcode":"94541",
    "sg:province":"CA",
    "sg:tags":[
        "health",
        "diet"
    ],
    "wof:name":"Pamela Kesler",
    "wof:placetype":"venue"
},
  "geometry": {"coordinates":[-122.060051,37.678173],"type":"Point"}
}