{
  "type": "Feature",
  "properties": {
    "addr:full":"183 Ryland St San Jose CA 95110",
    "addr:housenumber":"183",
    "addr:postcode":"95110",
    "addr:street":"Ryland St",
    "iso:country":"US",
    "sg:address":"183 Ryland St",
    "sg:city":"San Jose",
    "sg:classifiers":[
        {
            "category":"Retail",
            "subcategory":"Auto Repair",
            "type":"Services"
        }
    ],
    "sg:phone":"+1 408 971 1090",
    "sg:postcode":"95110",
    "sg:province":"CA",
    "sg:tags":[
        "transmission"
    ],
    "wof:name":"San Jose Import & Domestic",
    "wof:placetype":"venue"
},
  "geometry": {"coordinates":[-121.898393,37.341745],"type":"Point"}
}