{
  "type": "Feature",
  "properties": {
    "iso:country":"US",
    "sg:address":"6033 W Century Blvd",
    "sg:city":"Los Angeles",
    "sg:classifiers":[
        {
            "category":"Travel",
            "subcategory":"Hotels & Motels",
            "type":"Entertainment"
        },
        {
            "category":"Landmark",
            "subcategory":"Tourist Information",
            "type":"Public Place"
        }
    ],
    "sg:phone":"+1 310 417 3460",
    "sg:postcode":"90045",
    "sg:province":"CA",
    "sg:tags":[
        "tour"
    ],
    "wof:name":"Troy Tours",
    "wof:placetype":"venue"
},
  "geometry": {"coordinates":[-118.389668,33.946125],"type":"Point"}
}