{
  "type": "Feature",
  "properties": {
    "addr:full":"2511 W Beverly Blvd Montebello CA 90640",
    "addr:housenumber":"2511",
    "addr:postcode":"90640",
    "addr:street":"W Beverly Blvd",
    "iso:country":"US",
    "sg:address":"2511 W Beverly Blvd",
    "sg:city":"Montebello",
    "sg:classifiers":[
        {
            "category":"Professional",
            "type":"Services"
        }
    ],
    "sg:phone":"+1 323 725 1908",
    "sg:postcode":"90640",
    "sg:province":"CA",
    "wof:name":"Community Resurgence & Dev In",
    "wof:placetype":"venue"
},
  "geometry": {"coordinates":[-118.130261,34.020746],"type":"Point"}
}