{
  "type": "Feature",
  "properties": {
    "iso:country":"US",
    "sg:address":"404 S Figueroa St Ste 605",
    "sg:city":"Los Angeles",
    "sg:classifiers":[
        {
            "category":"Restaurant",
            "type":"Food & Drink"
        }
    ],
    "sg:phone":"+1 213 683 8866",
    "sg:postcode":"90071",
    "sg:province":"CA",
    "sg:tags":[
        "chinese"
    ],
    "wof:name":"Mandarin West",
    "wof:placetype":"venue"
},
  "geometry": {"coordinates":[-118.256021,34.053184],"type":"Point"}
}