{
  "type": "Feature",
  "properties": {
    "addr:full":"43104 Grimmer Ter Fremont CA 94538",
    "addr:postcode":"43104;94538",
    "addr:street":"Grimmer Ter",
    "iso:country":"US",
    "sg:address":"43104 Grimmer Ter",
    "sg:city":"Fremont",
    "sg:classifiers":[
        {
            "category":"Shopping",
            "subcategory":"Clothing, Apparel, & Fashions",
            "type":"Retail Goods"
        }
    ],
    "sg:phone":"+1 510 396 2791",
    "sg:postcode":"94538",
    "sg:province":"CA",
    "sg:tags":[
        "shop",
        "bridal"
    ],
    "wof:name":"Bridal Boutique",
    "wof:placetype":"venue"
},
  "geometry": {"coordinates":[-121.96465000000001,37.514024],"type":"Point"}
}