{
  "type": "Feature",
  "properties": {
    "addr:full":"105 Seminary Dr Mill Valley CA 94941",
    "addr:housenumber":"105",
    "addr:postcode":"94941",
    "addr:street":"Seminary Dr",
    "iso:country":"US",
    "sg:address":"105 Seminary Dr",
    "sg:city":"Mill Valley",
    "sg:classifiers":[
        {
            "category":"Manufacturing",
            "subcategory":"Jewelry",
            "type":"Manufacturing & Wholesale Goods"
        }
    ],
    "sg:phone":"+1 415 420 4456",
    "sg:postcode":"94941",
    "sg:province":"CA",
    "sg:tags":[
        "precious",
        "metal",
        "mfg"
    ],
    "wof:name":"Krystals By Kim",
    "wof:placetype":"venue"
},
  "geometry": {"coordinates":[-122.510187,37.888335],"type":"Point"}
}