{
  "type": "Feature",
  "properties": {
    "addr:full":"23746 Main St Carson CA 90745",
    "addr:housenumber":"23746",
    "addr:postcode":"90745",
    "addr:street":"Main St",
    "iso:country":"US",
    "sg:address":"23746 Main St",
    "sg:city":"Carson",
    "sg:classifiers":[
        {
            "category":"Manufacturing",
            "subcategory":"Printing",
            "type":"Manufacturing & Wholesale Goods"
        }
    ],
    "sg:phone":"+1 310 830 6033",
    "sg:postcode":"90745",
    "sg:province":"CA",
    "sg:tags":[
        "publisher"
    ],
    "wof:name":"Ang Peryodiko",
    "wof:placetype":"venue"
},
  "geometry": {"coordinates":[-118.275406,33.812036],"type":"Point"}
}