{
  "type": "Feature",
  "properties": {
    "iso:country":"US",
    "sg:address":"6121 Hollis Street #4",
    "sg:city":"Emeryville",
    "sg:classifiers":[
        {
            "category":"Professional",
            "subcategory":"Computer Services",
            "type":"Services"
        }
    ],
    "sg:phone":"+1 510 653 6800",
    "sg:postcode":"94608",
    "sg:province":"CA",
    "sg:tags":[
        "social-customer-suite",
        "social-customers",
        "social-success",
        "community",
        "social-crm",
        "customer-network",
        "online-communities",
        "customer-communities"
    ],
    "sg:website":"http://www.lithium.com/",
    "wof:name":"Lithium Technologies",
    "wof:placetype":"venue"
},
  "geometry": {"coordinates":[-122.29035399999999,37.842843],"type":"Point"}
}