{
  "type": "Feature",
  "properties": {
    "iso:country":"US",
    "sg:address":"18277 Parthenia St",
    "sg:city":"Northridge",
    "sg:classifiers":[
        {
            "category":"Home & Garden",
            "subcategory":"Furniture",
            "type":"Retail Goods"
        }
    ],
    "sg:phone":"+1 818 885 5004",
    "sg:postcode":"91325",
    "sg:province":"CA",
    "sg:tags":[
        "equipment",
        "kitchen",
        "cabinet"
    ],
    "wof:name":"Hi Q Cabinets",
    "wof:placetype":"venue"
},
  "geometry": {"coordinates":[-118.528668,34.228733],"type":"Point"}
}