{
  "type": "Feature",
  "properties": {
    "addr:full":"24807 Ave Tibbitts Valencia CA 91355",
    "addr:housenumber":"24807",
    "addr:postcode":"91355",
    "addr:street":"Ave",
    "iso:country":"US",
    "sg:address":"24807 Ave Tibbitts",
    "sg:city":"Valencia",
    "sg:classifiers":[
        {
            "category":"Professional",
            "type":"Services"
        }
    ],
    "sg:phone":"+1 661 296 0353",
    "sg:postcode":"91355",
    "sg:province":"CA",
    "wof:name":"Forever Foundation Inc",
    "wof:placetype":"venue"
},
  "geometry": {"coordinates":[-118.568324,34.433293],"type":"Point"}
}