{
  "type": "Feature",
  "properties": {
    "iso:country":"US",
    "sg:address":"22030 Main St",
    "sg:city":"Carson",
    "sg:classifiers":[
        {
            "category":"Health Services",
            "subcategory":"Health Practitioner",
            "type":"Services"
        }
    ],
    "sg:phone":"+1 310 835 9689",
    "sg:postcode":"90745",
    "sg:province":"CA",
    "sg:tags":[
        "therapist",
        "physical"
    ],
    "wof:name":"Surelief Care Inc",
    "wof:placetype":"venue"
},
  "geometry": {"coordinates":[-118.275344,33.81798],"type":"Point"}
}