{
  "type": "Feature",
  "properties": {
    "iso:country":"US",
    "sg:address":"2416 San Ramon Valley Blvd",
    "sg:city":"San Ramon",
    "sg:classifiers":[
        {
            "category":"Cafe",
            "type":"Food & Drink"
        }
    ],
    "sg:menulink":"http://www.allmenus.com/ca/central-contra-costa/21269-cafe-esin/menu/",
    "sg:phone":"+1 925 314 0974",
    "sg:postcode":"94583",
    "sg:province":"CA",
    "sg:tags":[
        "american",
        "mediterranean"
    ],
    "wof:name":"Cafe Esin",
    "wof:placetype":"venue"
},
  "geometry": {"coordinates":[-121.97777600000001,37.775508],"type":"Point"}
}