{
  "type": "Feature",
  "properties": {
    "iso:country":"US",
    "sg:address":"8014 Poplin Dr",
    "sg:city":"Santee",
    "sg:phone":"+1 619 562 0772",
    "sg:postcode":"92071",
    "sg:province":"CA",
    "sg:tags":[
        "communications",
        "telegraph"
    ],
    "wof:name":"At Matinees of Madness",
    "wof:placetype":"venue"
},
  "geometry": {"coordinates":[-117.023793,32.829393],"type":"Point"}
}