{
  "type": "Feature",
  "properties": {
    "addr:full":"1228 S Main St Lakeport CA 95453",
    "addr:housenumber":"1228",
    "addr:postcode":"95453",
    "addr:street":"S Main St",
    "iso:country":"US",
    "sg:address":"1228 S Main St",
    "sg:city":"Lakeport",
    "sg:classifiers":[
        {
            "category":"Real Estate",
            "subcategory":"Real Estate Agent",
            "type":"Services"
        }
    ],
    "sg:phone":"+1 707 263 5411",
    "sg:postcode":"95453",
    "sg:province":"CA",
    "sg:tags":[
        "consultant"
    ],
    "wof:name":"First West Co",
    "wof:placetype":"venue"
},
  "geometry": {"coordinates":[-122.915668,39.03419],"type":"Point"}
}