{
  "type": "Feature",
  "properties": {
    "iso:country":"US",
    "sg:address":"36 Caselli Ave",
    "sg:city":"San Francisco",
    "sg:classifiers":[
        {
            "category":"Professional",
            "subcategory":"Computer Services",
            "type":"Services"
        }
    ],
    "sg:phone":"+1 415 503 1649",
    "sg:postcode":"94114",
    "sg:province":"CA",
    "sg:tags":[
        "productivity",
        "time-management-tips",
        "email-management",
        "getting-organized",
        "managing-stress",
        "online-courses",
        "virtual-worlds",
        "motivational-speakers",
        "teamwork",
        "document-collaboration",
        "emerging-technology"
    ],
    "sg:website":"http://www.people-onthego.com",
    "wof:name":"People-OnTheGo",
    "wof:placetype":"venue"
},
  "geometry": {"coordinates":[-122.441046,37.759769],"type":"Point"}
}