{
  "type": "Feature",
  "properties": {
    "iso:country":"US",
    "sg:address":"4011 Freeport Boulevard",
    "sg:city":"Sacramento",
    "sg:classifiers":[
        {
            "category":"Autos & Motor Vehicles",
            "subcategory":"Fuel & Gas Station",
            "type":"Retail Goods"
        }
    ],
    "sg:phone":"+1 916 454 4470",
    "sg:postcode":"95822",
    "sg:province":"CA",
    "sg:website":"www.valero.com/products/pages/ga...",
    "wof:name":"Freeport Valero Minimart",
    "wof:placetype":"venue"
},
  "geometry": {"coordinates":[-121.492779,38.537833],"type":"Point"}
}