{
  "type": "Feature",
  "properties": {
    "iso:country":"US",
    "sg:address":"164 N Bascom Ave",
    "sg:city":"San Jose",
    "sg:classifiers":[
        {
            "category":"Insurance",
            "subcategory":"Insurance Agent",
            "type":"Services"
        }
    ],
    "sg:phone":"+1 408 918 0877",
    "sg:postcode":"95128",
    "sg:province":"CA",
    "wof:name":"State Farm Insurance",
    "wof:placetype":"venue"
},
  "geometry": {"coordinates":[-121.93191,37.326881],"type":"Point"}
}