{
  "type": "Feature",
  "properties": {
    "addr:full":"410 Washington St Calistoga CA 94515",
    "addr:housenumber":"410",
    "addr:postcode":"94515",
    "addr:street":"Washington St",
    "iso:country":"US",
    "sg:address":"410 Washington St",
    "sg:city":"Calistoga",
    "sg:classifiers":[
        {
            "category":"Organizations",
            "subcategory":"Professional Association",
            "type":"Services"
        }
    ],
    "sg:phone":"+1 707 942 6732",
    "sg:postcode":"94515",
    "sg:province":"CA",
    "wof:name":"Calistoga Baseball Assn",
    "wof:placetype":"venue"
},
  "geometry": {"coordinates":[-122.57345599999999,38.577115],"type":"Point"}
}