{
  "type": "Feature",
  "properties": {
    "iso:country":"US",
    "sg:address":"2003 Woolsey St",
    "sg:city":"Berkeley",
    "sg:classifiers":[
        {
            "category":"Organizations",
            "subcategory":"Religious Organization",
            "type":"Services"
        }
    ],
    "sg:phone":"+1 510 848 2093",
    "sg:postcode":"94703",
    "sg:province":"CA",
    "sg:tags":[
        "church"
    ],
    "wof:name":"All Nations Church Of Christ",
    "wof:placetype":"venue"
},
  "geometry": {"coordinates":[-122.267231,37.852318],"type":"Point"}
}