{
  "type": "Feature",
  "properties": {
    "iso:country":"US",
    "sg:address":"8427 N Millbrook Ave",
    "sg:city":"Fresno",
    "sg:classifiers":[
        {
            "category":"Health Services",
            "subcategory":"Health Practitioner",
            "type":"Services"
        }
    ],
    "sg:phone":"+1 559 432 8010",
    "sg:postcode":"93720",
    "sg:province":"CA",
    "sg:tags":[
        "pathologist",
        "speech"
    ],
    "wof:name":"Center For Communication",
    "wof:placetype":"venue"
},
  "geometry": {"coordinates":[-119.765835,36.85866],"type":"Point"}
}