{
  "type": "Feature",
  "properties": {
    "addr:full":"40455 Carrigan Rd Murrieta CA 92562",
    "addr:housenumber":"40455",
    "addr:postcode":"92562",
    "addr:street":"Carrigan Rd",
    "iso:country":"US",
    "sg:address":"40455 Carrigan Rd",
    "sg:city":"Murrieta",
    "sg:classifiers":[
        {
            "category":"Building & Trades",
            "subcategory":"Equipment Rental",
            "type":"Services"
        }
    ],
    "sg:phone":"+1 951 698 9312",
    "sg:postcode":"92562",
    "sg:province":"CA",
    "sg:tags":[
        "contractors'"
    ],
    "wof:name":"Fd&R Coleman Equipment Rentals",
    "wof:placetype":"venue"
},
  "geometry": {"coordinates":[-117.187079,33.561761],"type":"Point"}
}