{
  "type": "Feature",
  "properties": {
    "iso:country":"US",
    "sg:address":"7991 Milwheel Ct",
    "sg:city":"Sacramento",
    "sg:classifiers":[
        {
            "category":"Building & Trades",
            "subcategory":"Cleaning & Sanitation",
            "type":"Services"
        }
    ],
    "sg:phone":"+1 916 626 4116",
    "sg:postcode":"95829",
    "sg:province":"CA",
    "sg:tags":[
        "window"
    ],
    "wof:name":"Express Window Cleaning",
    "wof:placetype":"venue"
},
  "geometry": {"coordinates":[-121.333474,38.466199],"type":"Point"}
}