{
  "type": "Feature",
  "properties": {
    "iso:country":"US",
    "sg:address":"201 Filbert Street",
    "sg:city":"San Francisco",
    "sg:classifiers":[
        {
            "category":"Real Estate",
            "subcategory":"Real Estate Services",
            "type":"Services"
        }
    ],
    "sg:phone":"+1 415 391 1313",
    "sg:postcode":"94133",
    "sg:province":"CA",
    "sg:tags":[
        "management",
        "property"
    ],
    "sg:website":"www.gersonbakar.com",
    "wof:name":"Gerson Bakar & Associates",
    "wof:placetype":"venue"
},
  "geometry": {"coordinates":[-122.402974,37.802147],"type":"Point"}
}