{
  "type": "Feature",
  "properties": {
    "iso:country":"US",
    "sg:address":"5642 Fox Hills Ave",
    "sg:city":"Buena Park",
    "sg:classifiers":[
        {
            "category":"Building & Trades",
            "subcategory":"Construction",
            "type":"Services"
        }
    ],
    "sg:phone":"+1 714 522 6121",
    "sg:postcode":"90621",
    "sg:province":"CA",
    "sg:tags":[
        "contractor"
    ],
    "wof:name":"Double Eagle Enterprise",
    "wof:placetype":"venue"
},
  "geometry": {"coordinates":[-117.98896499999999,33.879358],"type":"Point"}
}