{
  "type": "Feature",
  "properties": {
    "addr:full":"Tanforan Mall South San Francisco CA 94080",
    "addr:postcode":"94080",
    "iso:country":"US",
    "sg:address":"Tanforan Mall",
    "sg:city":"South San Francisco",
    "sg:classifiers":[
        {
            "category":"Health Services",
            "subcategory":"Dentist",
            "type":"Services"
        }
    ],
    "sg:phone":"+1 650 952 7315",
    "sg:postcode":"94080",
    "sg:province":"CA",
    "wof:name":"Dental Health Center",
    "wof:placetype":"venue"
},
  "geometry": {"coordinates":[-122.434438,37.656679],"type":"Point"}
}