{
  "type": "Feature",
  "properties": {
    "addr:full":"1177 E Mission Rd Fallbrook CA 92028",
    "addr:housenumber":"1177",
    "addr:postcode":"92028",
    "addr:street":"E Mission Rd",
    "iso:country":"US",
    "sg:address":"1177 E Mission Rd",
    "sg:city":"Fallbrook",
    "sg:classifiers":[
        {
            "category":"Autos & Motor Vehicles",
            "subcategory":"Motorcycle Sales",
            "type":"Retail Goods"
        }
    ],
    "sg:phone":"+1 760 731 5920",
    "sg:postcode":"92028",
    "sg:province":"CA",
    "sg:tags":[
        "scooters-parts",
        "supply"
    ],
    "sg:website":"www.rolldesign.com",
    "wof:name":"Roll Design",
    "wof:placetype":"venue"
},
  "geometry": {"coordinates":[-117.237999,33.3876],"type":"Point"}
}