{
  "type": "Feature",
  "properties": {
    "addr:full":"44081 Old Warm Springs Blvd Fremont CA 94538",
    "addr:housenumber":"44081",
    "addr:postcode":"94538",
    "addr:street":"Old Warm Springs Blvd",
    "iso:country":"US",
    "sg:address":"44081 Old Warm Springs Blvd",
    "sg:city":"Fremont",
    "sg:classifiers":[
        {
            "category":"Professional",
            "subcategory":"Research",
            "type":"Services"
        }
    ],
    "sg:phone":"+1 510 659 1527",
    "sg:postcode":"94538",
    "sg:province":"CA",
    "sg:tags":[
        "laboratory"
    ],
    "wof:name":"Intellect Labs",
    "wof:placetype":"venue"
},
  "geometry": {"coordinates":[-121.949364,37.509033],"type":"Point"}
}