{
  "type": "Feature",
  "properties": {
    "addr:full":"6570 N Bungalow Ln Fresno CA 93704",
    "addr:housenumber":"6570",
    "addr:postcode":"93704",
    "addr:street":"N Bungalow Ln",
    "iso:country":"US",
    "sg:address":"6570 N Bungalow Ln",
    "sg:city":"Fresno",
    "sg:classifiers":[
        {
            "category":"Shopping",
            "subcategory":"Gifts & Souvenirs",
            "type":"Retail Goods"
        }
    ],
    "sg:phone":"+1 559 261 0908",
    "sg:postcode":"93704",
    "sg:province":"CA",
    "sg:tags":[
        "shop"
    ],
    "wof:name":"Rainbow Of Gifts",
    "wof:placetype":"venue"
},
  "geometry": {"coordinates":[-119.79805500000001,36.832449],"type":"Point"}
}