{
  "type": "Feature",
  "properties": {
    "addr:full":"750 US Hwy 101 Crescent City CA 95531",
    "addr:housenumber":"750",
    "addr:postcode":"95531",
    "addr:street":"Us Hwy 101 Crescent",
    "iso:country":"US",
    "sg:address":"750 US Hwy 101",
    "sg:city":"Crescent City",
    "sg:classifiers":[
        {
            "category":"Travel",
            "subcategory":"Campground",
            "type":"Entertainment"
        }
    ],
    "sg:phone":"+1 707 464 9482",
    "sg:postcode":"95531",
    "sg:province":"CA",
    "wof:name":"Bayside Rv Park",
    "wof:placetype":"venue"
},
  "geometry": {"coordinates":[-124.197298,41.757061],"type":"Point"}
}