{
  "type": "Feature",
  "properties": {
    "iso:country":"US",
    "sg:address":"2199 Fulton St",
    "sg:city":"San Francisco",
    "sg:classifiers":[
        {
            "category":"Education",
            "subcategory":"University",
            "type":"Public Place"
        }
    ],
    "sg:phone":"+1 415 422 6304",
    "sg:postcode":"94118",
    "sg:province":"CA",
    "sg:tags":[
        "college"
    ],
    "sg:website":"www.law.usfca.edu/",
    "wof:name":"University of San Francisco School of Law",
    "wof:placetype":"venue"
},
  "geometry": {"coordinates":[-122.452974,37.774971],"type":"Point"}
}