{
  "type": "Feature",
  "properties": {
    "addr:full":"7604 Fay Ave La Jolla CA 92037",
    "addr:housenumber":"7604",
    "addr:postcode":"92037",
    "addr:street":"Fay Ave",
    "iso:country":"US",
    "sg:address":"7604 Fay Ave",
    "sg:city":"La Jolla",
    "sg:classifiers":[
        {
            "category":"Personal",
            "subcategory":"Beauty Salon",
            "type":"Services"
        },
        {
            "category":"Personal",
            "subcategory":"Skin Care",
            "type":"Services"
        }
    ],
    "sg:phone":"+1 858 551 8605",
    "sg:postcode":"92037",
    "sg:province":"CA",
    "sg:tags":[
        "hair"
    ],
    "sg:website":"salonmaxfield.com",
    "wof:name":"Salon Maxfield",
    "wof:placetype":"venue"
},
  "geometry": {"coordinates":[-117.274396,32.842279],"type":"Point"}
}