{
  "type": "Feature",
  "properties": {
    "addr:full":"1630 W 3rd St Los Angeles CA 90017",
    "addr:housenumber":"1630",
    "addr:postcode":"90017",
    "addr:street":"W 3Rd St",
    "iso:country":"US",
    "sg:address":"1630 W 3rd St",
    "sg:city":"Los Angeles",
    "sg:classifiers":[
        {
            "category":"Building & Trades",
            "subcategory":"Landscaping Services",
            "type":"Services"
        }
    ],
    "sg:phone":"+1 213 989 0478",
    "sg:postcode":"90017",
    "sg:province":"CA",
    "sg:tags":[
        "lawn",
        "maintenance",
        "grounds"
    ],
    "wof:name":"Rose",
    "wof:placetype":"venue"
},
  "geometry": {"coordinates":[-118.266426,34.060096],"type":"Point"}
}