{
  "type": "Feature",
  "properties": {
    "iso:country":"US",
    "sg:address":"5865 E Naples Plz",
    "sg:city":"Long Beach",
    "sg:classifiers":[
        {
            "category":"Health Services",
            "subcategory":"Doctor",
            "type":"Services"
        }
    ],
    "sg:phone":"+1 562 434 4481",
    "sg:postcode":"90803",
    "sg:province":"CA",
    "sg:tags":[
        "clinic"
    ],
    "wof:name":"Naples Medical Group",
    "wof:placetype":"venue"
},
  "geometry": {"coordinates":[-118.119824,33.756084],"type":"Point"}
}