{
  "type": "Feature",
  "properties": {
    "iso:country":"US",
    "sg:address":"234 E Colorado Blvd Ste 720",
    "sg:city":"Pasadena",
    "sg:classifiers":[
        {
            "category":"Professional",
            "subcategory":"Lawyer & Legal Services",
            "type":"Services"
        }
    ],
    "sg:phone":"+1 626 683 8395",
    "sg:postcode":"91101",
    "sg:province":"CA",
    "sg:tags":[
        "divorce",
        "law",
        "family"
    ],
    "wof:name":"Tam Anthony Law Offices of",
    "wof:placetype":"venue"
},
  "geometry": {"coordinates":[-118.146004,34.145802],"type":"Point"}
}