{
  "type": "Feature",
  "properties": {
    "addr:full":"1 W Campbell Ave Campbell CA 95008",
    "addr:housenumber":"1",
    "addr:postcode":"95008",
    "addr:street":"W Campbell Ave",
    "iso:country":"US",
    "sg:address":"1 W Campbell Ave",
    "sg:city":"Campbell",
    "sg:classifiers":[
        {
            "category":"Professional",
            "type":"Services"
        }
    ],
    "sg:phone":"+1 408 866 6989",
    "sg:postcode":"95008",
    "sg:province":"CA",
    "wof:name":"Bosnian AM Asn Sclar Sanjse",
    "wof:placetype":"venue"
},
  "geometry": {"coordinates":[-121.9499,37.28702],"type":"Point"}
}