{
  "type": "Feature",
  "properties": {
    "addr:full":"1247 Camino Del Mar Del Mar CA 92014",
    "addr:housenumber":"1247",
    "addr:postcode":"92014",
    "addr:street":"Camino Del Mar",
    "iso:country":"US",
    "sg:address":"1247 Camino Del Mar",
    "sg:city":"Del Mar",
    "sg:classifiers":[
        {
            "category":"Restaurant",
            "type":"Food & Drink"
        }
    ],
    "sg:phone":"+1 858 755 0076",
    "sg:postcode":"92014",
    "sg:province":"CA",
    "sg:tags":[
        "new",
        "american"
    ],
    "sg:website":"www.zelsdelmar.com/index.html",
    "wof:name":"Zel's Del Mar",
    "wof:placetype":"venue"
},
  "geometry": {"coordinates":[-117.26423800000001,32.957428],"type":"Point"}
}