{
  "type": "Feature",
  "properties": {
    "addr:full":"17106 Avalon Blvd. Carson CA 90746",
    "addr:housenumber":"17106",
    "addr:postcode":"90746",
    "addr:street":"Avalon Blvd.",
    "iso:country":"US",
    "sg:address":"17106 Avalon Blvd.",
    "sg:city":"Carson",
    "sg:classifiers":[
        {
            "category":"Retail",
            "subcategory":"Storage",
            "type":"Services"
        }
    ],
    "sg:phone":"+1 310 817 6425",
    "sg:postcode":"90746",
    "sg:province":"CA",
    "sg:tags":[
        "self"
    ],
    "sg:website":"www.avalonselfstorage.com/",
    "wof:name":"Avalon Self Storage",
    "wof:placetype":"venue"
},
  "geometry": {"coordinates":[-118.264252,33.876931],"type":"Point"}
}