{
  "type": "Feature",
  "properties": {
    "addr:full":"15030 Broaden Ln Riverside CA 92508",
    "addr:housenumber":"15030",
    "addr:postcode":"92508",
    "addr:street":"Broaden Ln",
    "iso:country":"US",
    "sg:address":"15030 Broaden Ln",
    "sg:city":"Riverside",
    "sg:classifiers":[
        {
            "category":"Building & Trades",
            "subcategory":"Construction",
            "type":"Services"
        }
    ],
    "sg:phone":"+1 951 780 4640",
    "sg:postcode":"92508",
    "sg:province":"CA",
    "sg:tags":[
        "pipe",
        "line",
        "contractor"
    ],
    "wof:name":"R W Jacobson-General Engnrng",
    "wof:placetype":"venue"
},
  "geometry": {"coordinates":[-117.350821,33.899988],"type":"Point"}
}