{
  "type": "Feature",
  "properties": {
    "iso:country":"US",
    "sg:address":"714 E Manchester Blvd",
    "sg:city":"Inglewood",
    "sg:classifiers":[
        {
            "category":"Education",
            "subcategory":"Dance Studio",
            "type":"Public Place"
        }
    ],
    "sg:phone":"+1 310 672 2221",
    "sg:postcode":"90301",
    "sg:province":"CA",
    "sg:tags":[
        "instruction",
        "dancing"
    ],
    "wof:name":"Dance Forum",
    "wof:placetype":"venue"
},
  "geometry": {"coordinates":[-118.345598,33.959653],"type":"Point"}
}