{
  "type": "Feature",
  "properties": {
    "iso:country":"US",
    "sg:address":"8819 Etiwanda Ave",
    "sg:city":"Northridge",
    "sg:classifiers":[
        {
            "category":"Organizations",
            "subcategory":"Political Organization",
            "type":"Services"
        }
    ],
    "sg:phone":"+1 818 349 4370",
    "sg:postcode":"91325",
    "sg:province":"CA",
    "wof:name":"Old Northridge Community Cncl",
    "wof:placetype":"venue"
},
  "geometry": {"coordinates":[-118.532412,34.23166],"type":"Point"}
}