{
  "type": "Feature",
  "properties": {
    "addr:full":"8819 Etiwanda Ave Northridge CA 91325",
    "addr:housenumber":"8819",
    "addr:postcode":"91325",
    "addr:street":"Etiwanda Ave",
    "iso:country":"US",
    "sg:address":"8819 Etiwanda Ave",
    "sg:city":"Northridge",
    "sg:classifiers":[
        {
            "category":"Organizations",
            "subcategory":"Political Organization",
            "type":"Services"
        }
    ],
    "sg:phone":"+1 818 349 4370",
    "sg:postcode":"91325",
    "sg:province":"CA",
    "wof:name":"Old Northridge Community Cncl",
    "wof:placetype":"venue"
},
  "geometry": {"coordinates":[-118.53241199999999,34.23166],"type":"Point"}
}