{
  "type": "Feature",
  "properties": {
    "iso:country":"US",
    "sg:address":"24476 Ave 14",
    "sg:city":"Madera",
    "sg:classifiers":[
        {
            "category":"Wholesale",
            "subcategory":"Machinery & Supplies",
            "type":"Manufacturing & Wholesale Goods"
        }
    ],
    "sg:phone":"+1 559 674 8715",
    "sg:postcode":"93637",
    "sg:province":"CA",
    "sg:tags":[
        "tractor"
    ],
    "wof:name":"Madera Tractor & Implement Co",
    "wof:placetype":"venue"
},
  "geometry": {"coordinates":[-120.103049,36.952726],"type":"Point"}
}