{
  "type": "Feature",
  "properties": {
    "iso:country":"US",
    "sg:address":"3445 Midway Dr",
    "sg:city":"San Diego",
    "sg:classifiers":[
        {
            "category":"Shopping",
            "subcategory":"Pharmacy",
            "type":"Retail Goods"
        }
    ],
    "sg:phone":"+1 619 223 2566",
    "sg:postcode":"92110",
    "sg:province":"CA",
    "wof:name":"Save Mart",
    "wof:placetype":"venue"
},
  "geometry": {"coordinates":[-117.21293900000001,32.750662],"type":"Point"}
}