{
  "type": "Feature",
  "properties": {
    "iso:country":"US",
    "sg:address":"2015 W Redondo Beach Blvd",
    "sg:city":"Gardena",
    "sg:classifiers":[
        {
            "category":"Banks & Credit Unions",
            "subcategory":"Bank",
            "type":"Services"
        }
    ],
    "sg:phone":"+1 310 715 1211",
    "sg:postcode":"90247",
    "sg:province":"CA",
    "sg:tags":[
        "loan",
        "real estate"
    ],
    "wof:name":"People's Home Loan & Realty",
    "wof:placetype":"venue"
},
  "geometry": {"coordinates":[-118.313791,33.887194],"type":"Point"}
}