{
  "type": "Feature",
  "properties": {
    "iso:country":"US",
    "sg:address":"9812 Old Winery Pl Ste 1",
    "sg:city":"Sacramento",
    "sg:classifiers":[
        {
            "category":"Travel",
            "subcategory":"Travel Agent",
            "type":"Entertainment"
        },
        {
            "category":"Landmark",
            "subcategory":"Tourist Information",
            "type":"Public Place"
        }
    ],
    "sg:phone":"+1 916 361 2051",
    "sg:postcode":"95827",
    "sg:province":"CA",
    "sg:tags":[
        "agency",
        "services-commercial",
        "promoter",
        "tour",
        "tours-operators"
    ],
    "sg:website":"www.sportsleisure.com",
    "wof:name":"Sports Leisure Vacations",
    "wof:placetype":"venue"
},
  "geometry": {"coordinates":[-121.33014,38.573981],"type":"Point"}
}