{
  "type": "Feature",
  "properties": {
    "addr:full":"388 N Lindley Dr Porterville CA 93257",
    "addr:housenumber":"388",
    "addr:postcode":"93257",
    "addr:street":"N Lindley Dr",
    "iso:country":"US",
    "sg:address":"388 N Lindley Dr",
    "sg:city":"Porterville",
    "sg:classifiers":[
        {
            "category":"Building & Trades",
            "subcategory":"Landscaping Services",
            "type":"Services"
        }
    ],
    "sg:phone":"+1 559 358 5090",
    "sg:postcode":"93257",
    "sg:province":"CA",
    "wof:name":"Jt AG Services",
    "wof:placetype":"venue"
},
  "geometry": {"coordinates":[-119.031667,36.071972],"type":"Point"}
}