{
  "type": "Feature",
  "properties": {
    "addr:full":"140 W Amerige Ave Fullerton CA 92832",
    "addr:housenumber":"140",
    "addr:postcode":"92832",
    "addr:street":"W Amerige Ave",
    "iso:country":"US",
    "sg:address":"140 W Amerige Ave",
    "sg:city":"Fullerton",
    "sg:classifiers":[
        {
            "category":"Professional",
            "subcategory":"Management & Consulting",
            "type":"Services"
        }
    ],
    "sg:phone":"+1 714 348 7242",
    "sg:postcode":"92832",
    "sg:province":"CA",
    "sg:tags":[
        "consultant",
        "safety"
    ],
    "wof:name":"Benson & Assoc Loss Control",
    "wof:placetype":"venue"
},
  "geometry": {"coordinates":[-117.92578899999999,33.8713],"type":"Point"}
}