{
  "type": "Feature",
  "properties": {
    "addr:full":"295 N 10th Street San Jose CA 95112",
    "addr:housenumber":"295",
    "addr:postcode":"95112",
    "addr:street":"N 10Th Street",
    "iso:country":"US",
    "sg:address":"295 N 10th Street",
    "sg:city":"San Jose",
    "sg:classifiers":[
        {
            "category":"Real Estate",
            "subcategory":"Real Estate Services",
            "type":"Services"
        },
        {
            "category":"Real Estate",
            "subcategory":"Real Estate Operator",
            "type":"Services"
        }
    ],
    "sg:phone":"+1 408 297 6205",
    "sg:postcode":"95112",
    "sg:province":"CA",
    "sg:tags":[
        "apartment",
        "property",
        "management"
    ],
    "wof:name":"Pisciotta and Richie Enterprises",
    "wof:placetype":"venue"
},
  "geometry": {"coordinates":[-121.884306,37.344877],"type":"Point"}
}