{
  "type": "Feature",
  "properties": {
    "addr:full":"1043 E 2nd Ave Escondido CA 92025",
    "addr:housenumber":"1043",
    "addr:postcode":"92025",
    "addr:street":"E 2Nd Ave",
    "iso:country":"US",
    "sg:address":"1043 E 2nd Ave",
    "sg:city":"Escondido",
    "sg:classifiers":[
        {
            "category":"Building & Trades",
            "subcategory":"Landscaping Services",
            "type":"Services"
        }
    ],
    "sg:phone":"+1 760 738 4982",
    "sg:postcode":"92025",
    "sg:province":"CA",
    "sg:tags":[
        "landscape"
    ],
    "wof:name":"J Rivera Landscape",
    "wof:placetype":"venue"
},
  "geometry": {"coordinates":[-117.067126,33.125504],"type":"Point"}
}