{
  "type": "Feature",
  "properties": {
    "addr:full":"740 W Lambert Rd La Habra CA 90631",
    "addr:housenumber":"740",
    "addr:postcode":"90631",
    "addr:street":"W Lambert Rd",
    "iso:country":"US",
    "sg:address":"740 W Lambert Rd",
    "sg:city":"La Habra",
    "sg:classifiers":[
        {
            "category":"Autos & Motor Vehicles",
            "subcategory":"Auto Supplies",
            "type":"Retail Goods"
        },
        {
            "category":"Wholesale",
            "subcategory":"Auto Parts",
            "type":"Manufacturing & Wholesale Goods"
        }
    ],
    "sg:phone":"+1 562 690 4490",
    "sg:postcode":"90631",
    "sg:province":"CA",
    "sg:tags":[
        "alternator",
        "automotive",
        "generator"
    ],
    "wof:name":"Car-Go Alternator Starter Sup",
    "wof:placetype":"venue"
},
  "geometry": {"coordinates":[-117.95501299999999,33.92447],"type":"Point"}
}