{
  "type": "Feature",
  "properties": {
    "addr:full":"7967 Auburn Blvd Citrus Heights CA 95610",
    "addr:housenumber":"7967",
    "addr:postcode":"95610",
    "addr:street":"Auburn Blvd",
    "iso:country":"US",
    "sg:address":"7967 Auburn Blvd",
    "sg:city":"Citrus Heights",
    "sg:classifiers":[
        {
            "category":"Restaurant",
            "type":"Food & Drink"
        }
    ],
    "sg:phone":"+1 916 726 2200",
    "sg:postcode":"95610",
    "sg:province":"CA",
    "sg:tags":[
        "caterer"
    ],
    "wof:name":"Smokin' Joe's Bbq",
    "wof:placetype":"venue"
},
  "geometry": {"coordinates":[-121.290486,38.710648],"type":"Point"}
}