{
  "type": "Feature",
  "properties": {
    "addr:full":"903 E Valley Blvd San Gabriel CA 91776",
    "addr:housenumber":"903",
    "addr:postcode":"91776",
    "addr:street":"E Valley Blvd",
    "iso:country":"US",
    "sg:address":"903 E Valley Blvd",
    "sg:city":"San Gabriel",
    "sg:classifiers":[
        {
            "category":"Professional",
            "subcategory":"Accounting & Tax Preparation",
            "type":"Services"
        }
    ],
    "sg:phone":"+1 626 572 4843",
    "sg:postcode":"91776",
    "sg:province":"CA",
    "sg:tags":[
        "accountant"
    ],
    "sg:website":"www.honghlee.com",
    "wof:name":"Hong H Lee & Associates",
    "wof:placetype":"venue"
},
  "geometry": {"coordinates":[-118.087997,34.080299],"type":"Point"}
}