{
  "type": "Feature",
  "properties": {
    "iso:country":"US",
    "sg:address":"2455 N Garey Ave",
    "sg:city":"Pomona",
    "sg:classifiers":[
        {
            "category":"Autos & Motor Vehicles",
            "subcategory":"Fuel & Gas Station",
            "type":"Retail Goods"
        }
    ],
    "sg:phone":"+1 909 593 4376",
    "sg:postcode":"91767",
    "sg:province":"CA",
    "sg:tags":[
        "oil"
    ],
    "wof:name":"Sina A & A",
    "wof:placetype":"venue"
},
  "geometry": {"coordinates":[-117.748829,34.091303],"type":"Point"}
}