{
  "type": "Feature",
  "properties": {
    "iso:country":"US",
    "sg:address":"2409 S Vineyard Ave",
    "sg:city":"Ontario",
    "sg:classifiers":[
        {
            "category":"Real Estate",
            "subcategory":"Real Estate Agent",
            "type":"Services"
        }
    ],
    "sg:phone":"+1 909 908 9474",
    "sg:postcode":"91761",
    "sg:province":"CA",
    "wof:name":"Avila Gerardo",
    "wof:placetype":"venue"
},
  "geometry": {"coordinates":[-117.61092499999999,34.030898],"type":"Point"}
}