{
  "type": "Feature",
  "properties": {
    "addr:full":"1209 W Anaheim St Wilmington CA 90744",
    "addr:housenumber":"1209",
    "addr:postcode":"90744",
    "addr:street":"W Anaheim St",
    "iso:country":"US",
    "sg:address":"1209 W Anaheim St",
    "sg:city":"Wilmington",
    "sg:classifiers":[
        {
            "category":"Wholesale",
            "subcategory":"Electrical",
            "type":"Manufacturing & Wholesale Goods"
        }
    ],
    "sg:phone":"+1 310 549 0942",
    "sg:postcode":"90744",
    "sg:province":"CA",
    "sg:tags":[
        "electronic"
    ],
    "wof:name":"Jose Villalpando",
    "wof:placetype":"venue"
},
  "geometry": {"coordinates":[-118.278154,33.779118],"type":"Point"}
}