{
  "type": "Feature",
  "properties": {
    "addr:full":"20261 Beatty Ridge Road Los Gatos CA 95033",
    "addr:housenumber":"20261",
    "addr:postcode":"95033",
    "addr:street":"Beatty Ridge Road",
    "iso:country":"US",
    "sg:address":"20261 Beatty Ridge Road",
    "sg:city":"Los Gatos",
    "sg:classifiers":[
        {
            "category":"Professional",
            "subcategory":"Lawyer & Legal Services",
            "type":"Services"
        }
    ],
    "sg:phone":"+1 408 399 5195",
    "sg:postcode":"95033",
    "sg:province":"CA",
    "wof:name":"The Tod Company",
    "wof:placetype":"venue"
},
  "geometry": {"coordinates":[-122.07338300000001,37.201782],"type":"Point"}
}