{
  "type": "Feature",
  "properties": {
    "addr:full":"300 Broadway St Chico CA 95928",
    "addr:housenumber":"300",
    "addr:postcode":"95928",
    "addr:street":"Broadway St",
    "iso:country":"US",
    "sg:address":"300 Broadway St",
    "sg:city":"Chico",
    "sg:classifiers":[
        {
            "category":"Real Estate",
            "subcategory":"Real Estate Agent",
            "type":"Services"
        }
    ],
    "sg:phone":"+1 530 342 8321",
    "sg:postcode":"95928",
    "sg:province":"CA",
    "sg:website":"www.robbfairchildrealtor.com",
    "wof:name":"Robb Fairchild Realtor",
    "wof:placetype":"venue"
},
  "geometry": {"coordinates":[-121.83969999999999,39.728355],"type":"Point"}
}