{
  "type": "Feature",
  "properties": {
    "addr:full":"1948 S Broadway Santa Maria CA 93454",
    "addr:housenumber":"1948",
    "addr:postcode":"93454",
    "addr:street":"S Broadway",
    "iso:country":"US",
    "sg:address":"1948 S Broadway",
    "sg:city":"Santa Maria",
    "sg:classifiers":[
        {
            "category":"Food & Beverages",
            "subcategory":"Groceries & Convenience Stores",
            "type":"Retail Goods"
        }
    ],
    "sg:phone":"+1 805 922 0109",
    "sg:postcode":"93454",
    "sg:province":"CA",
    "sg:tags":[
        "grocer"
    ],
    "wof:name":"Santa Maria Grocery Outlet",
    "wof:placetype":"venue"
},
  "geometry": {"coordinates":[-120.435849,34.925021],"type":"Point"}
}