{
  "type": "Feature",
  "properties": {
    "iso:country":"US",
    "sg:address":"401 W Radio Rd Ste B-24",
    "sg:city":"Palm Springs",
    "sg:classifiers":[
        {
            "category":"Retail",
            "subcategory":"Auto Repair",
            "type":"Services"
        }
    ],
    "sg:phone":"+1 760 325 3592",
    "sg:postcode":"92262",
    "sg:province":"CA",
    "wof:name":"David Daniel Smith Automotive Inc",
    "wof:placetype":"venue"
},
  "geometry": {"coordinates":[-116.55170200000001,33.861505],"type":"Point"}
}