{
  "type": "Feature",
  "properties": {
    "addr:full":"1 Daniel Burnham Ct San Francisco CA 94109",
    "addr:housenumber":"1",
    "addr:postcode":"94109",
    "addr:street":"Daniel Burnham Ct",
    "iso:country":"US",
    "sg:address":"1 Daniel Burnham Ct",
    "sg:city":"San Francisco",
    "sg:classifiers":[
        {
            "category":"Utilities",
            "subcategory":"Mobile Phone",
            "type":"Services"
        }
    ],
    "sg:phone":"+1 415 351 1700",
    "sg:postcode":"94109",
    "sg:province":"CA",
    "sg:tags":[
        "communication",
        "radiotelephone",
        "merchandise"
    ],
    "wof:name":"Verizon",
    "wof:placetype":"venue"
},
  "geometry": {"coordinates":[-122.42330699999999,37.786868],"type":"Point"}
}