{
  "type": "Feature",
  "properties": {
    "addr:full":"180 Webb St Montague CA 96064",
    "addr:housenumber":"180",
    "addr:postcode":"96064",
    "addr:street":"Webb St",
    "iso:country":"US",
    "sg:address":"180 Webb St",
    "sg:city":"Montague",
    "sg:classifiers":[
        {
            "category":"Shopping",
            "subcategory":"Bicycles & Sporting Goods",
            "type":"Retail Goods"
        }
    ],
    "sg:phone":"+1 530 459 3102",
    "sg:postcode":"96064",
    "sg:province":"CA",
    "sg:tags":[
        "saddlery",
        "harness"
    ],
    "wof:name":"Dale's Feed & Saddle Shop",
    "wof:placetype":"venue"
},
  "geometry": {"coordinates":[-122.525948,41.727536],"type":"Point"}
}