{
  "type": "Feature",
  "properties": {
    "addr:full":"17004 Columbia River Dr Sonora CA 95370",
    "addr:housenumber":"17004",
    "addr:postcode":"95370",
    "addr:street":"Columbia River Dr",
    "iso:country":"US",
    "sg:address":"17004 Columbia River Dr",
    "sg:city":"Sonora",
    "sg:classifiers":[
        {
            "category":"Building & Trades",
            "subcategory":"Construction",
            "type":"Services"
        }
    ],
    "sg:phone":"+1 209 536 9776",
    "sg:postcode":"95370",
    "sg:province":"CA",
    "sg:tags":[
        "painter"
    ],
    "wof:name":"Cascade Painting",
    "wof:placetype":"venue"
},
  "geometry": {"coordinates":[-120.268997,38.011002],"type":"Point"}
}