{
  "type": "Feature",
  "properties": {
    "addr:full":"28312 Industrial Blvd Hayward CA 94545",
    "addr:housenumber":"28312",
    "addr:postcode":"94545",
    "addr:street":"Industrial Blvd",
    "iso:country":"US",
    "sg:address":"28312 Industrial Blvd",
    "sg:city":"Hayward",
    "sg:classifiers":[
        {
            "category":"Building & Trades",
            "subcategory":"Construction",
            "type":"Services"
        }
    ],
    "sg:phone":"+1 510 781 0350",
    "sg:postcode":"94545",
    "sg:province":"CA",
    "sg:tags":[
        "contractor"
    ],
    "wof:name":"X L R 8",
    "wof:placetype":"venue"
},
  "geometry": {"coordinates":[-122.090176,37.616752],"type":"Point"}
}