{
  "type": "Feature",
  "properties": {
    "iso:country":"US",
    "sg:address":"250 41st St",
    "sg:city":"Oakland",
    "sg:classifiers":[
        {
            "category":"Education",
            "subcategory":"School",
            "type":"Public Place"
        }
    ],
    "sg:phone":"+1 510 547 4747",
    "sg:postcode":"94611",
    "sg:province":"CA",
    "sg:tags":[
        "elementary"
    ],
    "sg:website":"www.archwayschool.org",
    "wof:name":"Archway School",
    "wof:placetype":"venue"
},
  "geometry": {"coordinates":[-122.254997,37.828098],"type":"Point"}
}