{
  "type": "Feature",
  "properties": {
    "iso:country":"US",
    "sg:address":"4601 W Telephone Rd",
    "sg:city":"Ventura",
    "sg:classifiers":[
        {
            "category":"Health Services",
            "subcategory":"Medical Lab",
            "type":"Services"
        }
    ],
    "sg:phone":"+1 805 644 7300",
    "sg:postcode":"93003",
    "sg:province":"CA",
    "sg:tags":[
        "x",
        "laboratory"
    ],
    "sg:website":"www.radnet.com",
    "wof:name":"Ventura Coast Imaging Ctr",
    "wof:placetype":"venue"
},
  "geometry": {"coordinates":[-119.22608099999999,34.263443],"type":"Point"}
}