{
  "type": "Feature",
  "properties": {
    "iso:country":"US",
    "sg:address":"225 Wilson St",
    "sg:city":"Petaluma",
    "sg:classifiers":[
        {
            "category":"Personal",
            "subcategory":"Beauty Salon",
            "type":"Services"
        }
    ],
    "sg:phone":"+1 707 763 8330",
    "sg:postcode":"94952",
    "sg:province":"CA",
    "wof:name":"Wilson Street Hair Design",
    "wof:placetype":"venue"
},
  "geometry": {"coordinates":[-122.633568,38.238252],"type":"Point"}
}