{
  "type": "Feature",
  "properties": {
    "addr:full":"672 S Van Ness San Francisco CA 94110",
    "addr:housenumber":"672",
    "addr:postcode":"94110",
    "addr:street":"S Van Ness",
    "iso:country":"US",
    "sg:address":"672 S Van Ness",
    "sg:city":"San Francisco",
    "sg:classifiers":[
        {
            "category":"Education",
            "subcategory":"Dance Studio",
            "type":"Public Place"
        }
    ],
    "sg:phone":"+1 415 681 8140",
    "sg:postcode":"94110",
    "sg:province":"CA",
    "sg:website":"www.dancefitSF.com",
    "wof:name":"Symbolic Dance & Fitness",
    "wof:placetype":"venue"
},
  "geometry": {"coordinates":[-122.417254,37.7624],"type":"Point"}
}