{
  "type": "Feature",
  "properties": {
    "addr:full":"1729 W 17th St Santa Ana CA 92706",
    "addr:housenumber":"1729",
    "addr:postcode":"92706",
    "addr:street":"W 17Th St",
    "iso:country":"US",
    "sg:address":"1729 W 17th St",
    "sg:city":"Santa Ana",
    "sg:classifiers":[
        {
            "category":"Health Services",
            "subcategory":"Medical Lab",
            "type":"Services"
        }
    ],
    "sg:phone":"+1 714 834 8385",
    "sg:postcode":"92706",
    "sg:province":"CA",
    "sg:tags":[
        "laboratory"
    ],
    "wof:name":"Health Care Agency",
    "wof:placetype":"venue"
},
  "geometry": {"coordinates":[-117.89264300000001,33.760083],"type":"Point"}
}