{
  "type": "Feature",
  "properties": {
    "iso:country":"US",
    "sg:address":"25191 de Salle St",
    "sg:city":"Laguna Hills",
    "sg:classifiers":[
        {
            "category":"Building & Trades",
            "subcategory":"Construction",
            "type":"Services"
        }
    ],
    "sg:phone":"+1 949 768 5382",
    "sg:postcode":"92653",
    "sg:province":"CA",
    "sg:tags":[
        "house"
    ],
    "wof:name":"Benda Construction",
    "wof:placetype":"venue"
},
  "geometry": {"coordinates":[-117.686175,33.597364],"type":"Point"}
}