{
  "type": "Feature",
  "properties": {
    "iso:country":"US",
    "sg:address":"25190 Hancock Ave",
    "sg:city":"Murrieta",
    "sg:classifiers":[
        {
            "category":"Building & Trades",
            "subcategory":"Construction",
            "type":"Services"
        }
    ],
    "sg:phone":"+1 951 677 3033",
    "sg:postcode":"92562",
    "sg:province":"CA",
    "sg:tags":[
        "general",
        "contractor"
    ],
    "wof:name":"Sundt Construction",
    "wof:placetype":"venue"
},
  "geometry": {"coordinates":[-117.18238700000001,33.567442],"type":"Point"}
}