{
  "type": "Feature",
  "properties": {
    "iso:country":"US",
    "sg:address":"128 E Covina Blvd",
    "sg:city":"Covina",
    "sg:classifiers":[
        {
            "category":"Restaurant",
            "type":"Food & Drink"
        }
    ],
    "sg:phone":"+1 626 430 9096",
    "sg:postcode":"91722",
    "sg:province":"CA",
    "wof:name":"El Pueblo Restaurant",
    "wof:placetype":"venue"
},
  "geometry": {"coordinates":[-117.889668,34.099325],"type":"Point"}
}