{
  "type": "Feature",
  "properties": {
    "iso:country":"US",
    "sg:address":"2425 Merced St",
    "sg:city":"Fresno",
    "sg:classifiers":[
        {
            "category":"Restaurant",
            "type":"Food & Drink"
        }
    ],
    "sg:menulink":"http://www.allmenus.com/ca/fresno/59908-subway/menu/",
    "sg:phone":"+1 559 233 0600",
    "sg:postcode":"93721",
    "sg:province":"CA",
    "sg:tags":[
        "american",
        "sandwich"
    ],
    "wof:name":"Subway",
    "wof:placetype":"venue"
},
  "geometry": {"coordinates":[-119.789047,36.740022],"type":"Point"}
}