{
  "type": "Feature",
  "properties": {
    "iso:country":"US",
    "sg:address":"1300 Hurlbut Ave",
    "sg:city":"Sebastopol",
    "sg:classifiers":[
        {
            "category":"Building & Trades",
            "subcategory":"Landscaping Services",
            "type":"Services"
        }
    ],
    "sg:phone":"+1 707 823 3912",
    "sg:postcode":"95472",
    "sg:province":"CA",
    "sg:tags":[
        "landscape"
    ],
    "wof:name":"Landscape Restoration",
    "wof:placetype":"venue"
},
  "geometry": {"coordinates":[-122.838546,38.418801],"type":"Point"}
}