{
  "type": "Feature",
  "properties": {
    "addr:full":"1300 Hurlbut Ave Sebastopol CA 95472",
    "addr:housenumber":"1300",
    "addr:postcode":"95472",
    "addr:street":"Hurlbut Ave",
    "iso:country":"US",
    "sg:address":"1300 Hurlbut Ave",
    "sg:city":"Sebastopol",
    "sg:classifiers":[
        {
            "category":"Building & Trades",
            "subcategory":"Landscaping Services",
            "type":"Services"
        }
    ],
    "sg:phone":"+1 707 823 3912",
    "sg:postcode":"95472",
    "sg:province":"CA",
    "sg:tags":[
        "landscape"
    ],
    "wof:name":"Landscape Restoration",
    "wof:placetype":"venue"
},
  "geometry": {"coordinates":[-122.83854599999999,38.418801],"type":"Point"}
}