{
  "type": "Feature",
  "properties": {
    "iso:country":"US",
    "sg:address":"303 W Lincoln Ave Suite 105",
    "sg:city":"Anaheim",
    "sg:classifiers":[
        {
            "category":"Health Services",
            "subcategory":"Clinic",
            "type":"Services"
        }
    ],
    "sg:phone":"+1 714 922 4100",
    "sg:postcode":"92805",
    "sg:province":"CA",
    "sg:tags":[
        "medical"
    ],
    "sg:website":"www.plannedparenthoodosbc.org",
    "wof:name":"Planned Parenthood",
    "wof:placetype":"venue"
},
  "geometry": {"coordinates":[-117.917948,33.835289],"type":"Point"}
}