{
  "type": "Feature",
  "properties": {
    "addr:full":"580 2nd St Ste 260 Oakland CA 94607",
    "addr:housenumber":"580",
    "addr:postcode":"94607",
    "addr:street":"2Nd St Ste 260",
    "iso:country":"US",
    "sg:address":"580 2nd St Ste 260",
    "sg:city":"Oakland",
    "sg:classifiers":[
        {
            "category":"Industrial Area",
            "type":"Public Place"
        }
    ],
    "sg:phone":"+1 510 839 4000",
    "sg:postcode":"94607",
    "sg:province":"CA",
    "sg:tags":[
        "development"
    ],
    "wof:name":"Mv Broadway",
    "wof:placetype":"venue"
},
  "geometry": {"coordinates":[-122.27947899999999,37.797297],"type":"Point"}
}