{
  "type": "Feature",
  "properties": {
    "iso:country":"US",
    "sg:address":"9240 Excelsior Ave",
    "sg:city":"Hanford",
    "sg:phone":"+1 559 584 5751",
    "sg:postcode":"93230",
    "sg:province":"CA",
    "sg:tags":[
        "farm",
        "general"
    ],
    "wof:name":"Tos Farms Inc",
    "wof:placetype":"venue"
},
  "geometry": {"coordinates":[-119.622862,36.401296],"type":"Point"}
}