{
  "type": "Feature",
  "properties": {
    "addr:full":"12512 Knott St Garden Grove CA 92841",
    "addr:housenumber":"12512",
    "addr:postcode":"92841",
    "addr:street":"Knott St",
    "iso:country":"US",
    "sg:address":"12512 Knott St",
    "sg:city":"Garden Grove",
    "sg:classifiers":[
        {
            "category":"Food & Beverages",
            "subcategory":"Groceries & Convenience Stores",
            "type":"Retail Goods"
        }
    ],
    "sg:phone":"+1 714 898 4075",
    "sg:postcode":"92841",
    "sg:province":"CA",
    "wof:name":"Circle K",
    "wof:placetype":"venue"
},
  "geometry": {"coordinates":[-118.011076,33.780571],"type":"Point"}
}