{
  "type": "Feature",
  "properties": {
    "addr:full":"2005 Desire Ave Rowland Heights CA 91748",
    "addr:housenumber":"2005",
    "addr:postcode":"91748",
    "addr:street":"Desire Ave",
    "iso:country":"US",
    "sg:address":"2005 Desire Ave",
    "sg:city":"Rowland Heights",
    "sg:classifiers":[
        {
            "category":"Building & Trades",
            "subcategory":"Landscaping Services",
            "type":"Services"
        }
    ],
    "sg:phone":"+1 626 965 8445",
    "sg:postcode":"91748",
    "sg:province":"CA",
    "sg:tags":[
        "landscape",
        "contractor"
    ],
    "wof:name":"Calpak Landscape",
    "wof:placetype":"venue"
},
  "geometry": {"coordinates":[-117.89457299999999,33.982305],"type":"Point"}
}