{
  "type": "Feature",
  "properties": {
    "iso:country":"US",
    "sg:address":"3110 Wagner Heights Rd",
    "sg:city":"Stockton",
    "sg:classifiers":[
        {
            "category":"Health Services",
            "subcategory":"Nursing And Care Facility",
            "type":"Services"
        }
    ],
    "sg:phone":"+1 209 956 3444",
    "sg:postcode":"95209",
    "sg:province":"CA",
    "sg:tags":[
        "home",
        "convalescent"
    ],
    "sg:website":"www.oconnorwoods.com",
    "wof:name":"Meadowood",
    "wof:placetype":"venue"
},
  "geometry": {"coordinates":[-121.355709,38.031982],"type":"Point"}
}