{
  "type": "Feature",
  "properties": {
    "iso:country":"US",
    "sg:address":"11150 Sepulveda Blvd",
    "sg:city":"Mission Hills",
    "sg:classifiers":[
        {
            "category":"Social Services",
            "subcategory":"Child Care",
            "type":"Services"
        }
    ],
    "sg:phone":"+1 818 365 3665",
    "sg:postcode":"91345",
    "sg:province":"CA",
    "wof:name":"Walden Environment",
    "wof:placetype":"venue"
},
  "geometry": {"coordinates":[-118.46776,34.273894],"type":"Point"}
}