{
  "type": "Feature",
  "properties": {
    "iso:country":"US",
    "sg:address":"1591 N Cuyamaca St",
    "sg:city":"El Cajon",
    "sg:classifiers":[
        {
            "category":"Home & Garden",
            "subcategory":"Garden Supply",
            "type":"Retail Goods"
        }
    ],
    "sg:phone":"+1 619 749 6777",
    "sg:postcode":"92090",
    "sg:province":"CA",
    "sg:tags":[
        "nursery",
        "gardening"
    ],
    "sg:website":"www.growalot.com",
    "wof:name":"GROWaLOT",
    "wof:placetype":"venue"
},
  "geometry": {"coordinates":[-116.97962800000001,32.816764],"type":"Point"}
}