{
  "type": "Feature",
  "properties": {
    "iso:country":"US",
    "sg:address":"9532 McLennan Ave",
    "sg:city":"North Hills",
    "sg:classifiers":[
        {
            "category":"Freight",
            "type":"Transportation"
        }
    ],
    "sg:phone":"+1 818 339 7733",
    "sg:postcode":"91343",
    "sg:province":"CA",
    "wof:name":"Jacks Transport",
    "wof:placetype":"venue"
},
  "geometry": {"coordinates":[-118.50113,34.244332],"type":"Point"}
}