{
  "type": "Feature",
  "properties": {
    "iso:country":"US",
    "sg:address":"3000 T St Ste 102",
    "sg:city":"Sacramento",
    "sg:classifiers":[
        {
            "category":"Professional",
            "subcategory":"Lawyer & Legal Services",
            "type":"Services"
        }
    ],
    "sg:phone":"+1 916 455 4030",
    "sg:postcode":"95816",
    "sg:province":"CA",
    "wof:name":"Vera Julia E Law Offices Of",
    "wof:placetype":"venue"
},
  "geometry": {"coordinates":[-121.47074600000001,38.561848],"type":"Point"}
}