{
  "type": "Feature",
  "properties": {
    "addr:full":"766 E Colorado Blvd Pasadena CA 91101",
    "addr:housenumber":"766",
    "addr:postcode":"91101",
    "addr:street":"E Colorado Blvd",
    "iso:country":"US",
    "sg:address":"766 E Colorado Blvd",
    "sg:city":"Pasadena",
    "sg:classifiers":[
        {
            "category":"Real Estate",
            "subcategory":"Architect",
            "type":"Services"
        }
    ],
    "sg:phone":"+1 626 585 1332",
    "sg:postcode":"91101",
    "sg:province":"CA",
    "wof:name":"Hafco & Associates",
    "wof:placetype":"venue"
},
  "geometry": {"coordinates":[-118.13400300000001,34.145802],"type":"Point"}
}