{
  "type": "Feature",
  "properties": {
    "iso:country":"US",
    "sg:address":"400 N Adams St",
    "sg:city":"Dixon",
    "sg:classifiers":[
        {
            "category":"Autos & Motor Vehicles",
            "subcategory":"Auto Supplies",
            "type":"Retail Goods"
        }
    ],
    "sg:phone":"+1 707 678 0446",
    "sg:postcode":"95620",
    "sg:province":"CA",
    "sg:tags":[
        "automobile",
        "stereo",
        "radio"
    ],
    "wof:name":"Stereophonics",
    "wof:placetype":"venue"
},
  "geometry": {"coordinates":[-121.826191,38.449528],"type":"Point"}
}