{
  "type": "Feature",
  "properties": {
    "addr:full":"2569 Chino Hills Pkwy Chino Hills CA 91709",
    "addr:housenumber":"2569",
    "addr:postcode":"91709",
    "addr:street":"Chino Hills Pkwy",
    "iso:country":"US",
    "sg:address":"2569 Chino Hills Pkwy",
    "sg:city":"Chino Hills",
    "sg:classifiers":[
        {
            "category":"Banks & Credit Unions",
            "subcategory":"Bank",
            "type":"Services"
        }
    ],
    "sg:phone":"+1 909 393 3580",
    "sg:postcode":"91709",
    "sg:province":"CA",
    "wof:name":"Union Bank Of CA",
    "wof:placetype":"venue"
},
  "geometry": {"coordinates":[-117.749078,33.985599],"type":"Point"}
}