{
  "type": "Feature",
  "properties": {
    "addr:full":"9844 Wilshire Blvd Beverly Hills CA 90212",
    "addr:housenumber":"9844",
    "addr:postcode":"90212",
    "addr:street":"Wilshire Blvd",
    "iso:country":"US",
    "sg:address":"9844 Wilshire Blvd",
    "sg:city":"Beverly Hills",
    "sg:classifiers":[
        {
            "category":"Coffee & Tea",
            "type":"Food & Drink"
        }
    ],
    "sg:menulink":"http://www.allmenus.com/ca/los-angeles/117469-starbucks-coffee/menu/",
    "sg:phone":"+1 310 552 3133",
    "sg:postcode":"90212",
    "sg:province":"CA",
    "sg:tags":[
        "american"
    ],
    "wof:name":"Starbucks Coffee",
    "wof:placetype":"venue"
},
  "geometry": {"coordinates":[-118.410235,34.06675],"type":"Point"}
}