{
  "type": "Feature",
  "properties": {
    "iso:country":"US",
    "sg:address":"3301 E 19th St",
    "sg:city":"Long Beach",
    "sg:classifiers":[
        {
            "category":"Wholesale",
            "subcategory":"Construction Materials",
            "type":"Manufacturing & Wholesale Goods"
        }
    ],
    "sg:phone":"+1 562 594 0069",
    "sg:postcode":"90755",
    "sg:province":"CA",
    "sg:tags":[
        "house"
    ],
    "wof:name":"Peterson & Jones",
    "wof:placetype":"venue"
},
  "geometry": {"coordinates":[-118.15133,33.791672],"type":"Point"}
}