{
  "type": "Feature",
  "properties": {
    "iso:country":"US",
    "sg:address":"631 S Melrose Dr",
    "sg:city":"Vista",
    "sg:classifiers":[
        {
            "category":"Personal",
            "subcategory":"Massage",
            "type":"Services"
        },
        {
            "category":"Personal",
            "subcategory":"Beauty Salon",
            "type":"Services"
        }
    ],
    "sg:phone":"+1 760 295 2436",
    "sg:postcode":"92081",
    "sg:province":"CA",
    "sg:tags":[
        "hair"
    ],
    "sg:website":"salonpoise.com",
    "wof:name":"Salon Poise",
    "wof:placetype":"venue"
},
  "geometry": {"coordinates":[-117.253366,33.185617],"type":"Point"}
}