{
  "type": "Feature",
  "properties": {
    "addr:full":"1620 26th St Santa Monica CA 90404",
    "addr:housenumber":"1620",
    "addr:postcode":"90404",
    "addr:street":"26Th St",
    "iso:country":"US",
    "sg:address":"1620 26th St",
    "sg:city":"Santa Monica",
    "sg:classifiers":[
        {
            "category":"Utilities",
            "subcategory":"Electric",
            "type":"Services"
        }
    ],
    "sg:phone":"+1 310 656 9800",
    "sg:postcode":"90404",
    "sg:province":"CA",
    "sg:tags":[
        "company"
    ],
    "wof:name":"Quiet Energy",
    "wof:placetype":"venue"
},
  "geometry": {"coordinates":[-118.470589,34.030017],"type":"Point"}
}