{
  "type": "Feature",
  "properties": {
    "iso:country":"US",
    "sg:address":"1785 E Capitol Expy",
    "sg:city":"San Jose",
    "sg:classifiers":[
        {
            "category":"Real Estate",
            "subcategory":"Real Estate Agent",
            "type":"Services"
        }
    ],
    "sg:phone":"+1 408 223 5536",
    "sg:postcode":"95121",
    "sg:province":"CA",
    "wof:name":"Millennium 2000 Real Estate",
    "wof:placetype":"venue"
},
  "geometry": {"coordinates":[-121.809415,37.308818],"type":"Point"}
}