{
  "type": "Feature",
  "properties": {
    "iso:country":"US",
    "sg:address":"2061 Freeway Dr Ste C",
    "sg:city":"Woodland",
    "sg:classifiers":[
        {
            "category":"Home & Garden",
            "subcategory":"Building Materials",
            "type":"Retail Goods"
        },
        {
            "category":"Manufacturing",
            "subcategory":"Building Materials",
            "type":"Manufacturing & Wholesale Goods"
        }
    ],
    "sg:phone":"+1 530 661 1697",
    "sg:postcode":"95776",
    "sg:province":"CA",
    "sg:tags":[
        "solid",
        "top",
        "counter",
        "surface"
    ],
    "wof:name":"We're Tops Countertops",
    "wof:placetype":"venue"
},
  "geometry": {"coordinates":[-121.726758,38.675742],"type":"Point"}
}