{
  "type": "Feature",
  "properties": {
    "iso:country":"US",
    "sg:address":"960 3rd St",
    "sg:city":"Fillmore",
    "sg:classifiers":[
        {
            "category":"Wholesale",
            "subcategory":"Fruits & Vegetables",
            "type":"Manufacturing & Wholesale Goods"
        }
    ],
    "sg:phone":"+1 805 524 0411",
    "sg:postcode":"93015",
    "sg:province":"CA",
    "sg:tags":[
        "shipper"
    ],
    "sg:website":"www.vpoa.net",
    "wof:name":"Villa Park Orchards Assn",
    "wof:placetype":"venue"
},
  "geometry": {"coordinates":[-118.925828,34.404826],"type":"Point"}
}