{
  "type": "Feature",
  "properties": {
    "iso:country":"US",
    "sg:address":"506 Tamalpais Dr",
    "sg:city":"Corte Madera",
    "sg:classifiers":[
        {
            "category":"Travel",
            "subcategory":"Travel Agent",
            "type":"Entertainment"
        }
    ],
    "sg:phone":"+1 415 924 5850",
    "sg:postcode":"94925",
    "sg:province":"CA",
    "sg:tags":[
        "agency"
    ],
    "wof:name":"Cruise Experts",
    "wof:placetype":"venue"
},
  "geometry": {"coordinates":[-122.52647,37.925599],"type":"Point"}
}