{
  "type": "Feature",
  "properties": {
    "iso:country":"US",
    "sg:address":"1640 W 190th St",
    "sg:city":"Torrance",
    "sg:classifiers":[
        {
            "category":"Shopping",
            "subcategory":"Music",
            "type":"Retail Goods"
        }
    ],
    "sg:phone":"+1 310 974 1010",
    "sg:postcode":"90501",
    "sg:province":"CA",
    "sg:tags":[
        "dvd's"
    ],
    "wof:name":"Denon Electronics",
    "wof:placetype":"venue"
},
  "geometry": {"coordinates":[-118.30901299999999,33.858212],"type":"Point"}
}