{
  "type": "Feature",
  "properties": {
    "iso:country":"US",
    "sg:address":"10671 Story Ln",
    "sg:city":"San Jose",
    "sg:classifiers":[
        {
            "category":"Arts & Performance",
            "subcategory":"Theater",
            "type":"Entertainment"
        }
    ],
    "sg:phone":"+1 408 259 4242",
    "sg:postcode":"95127",
    "sg:province":"CA",
    "sg:tags":[
        "bureau"
    ],
    "wof:name":"Anderson Sports & Entrtn",
    "wof:placetype":"venue"
},
  "geometry": {"coordinates":[-121.803257,37.358425],"type":"Point"}
}