{
  "type": "Feature",
  "properties": {
    "iso:country":"US",
    "sg:address":"16635 Oldham St",
    "sg:city":"Encino",
    "sg:classifiers":[
        {
            "category":"Professional",
            "subcategory":"Accounting & Tax Preparation",
            "type":"Services"
        }
    ],
    "sg:phone":"+1 818 789 4451",
    "sg:postcode":"91436",
    "sg:province":"CA",
    "sg:tags":[
        "clothing",
        "family"
    ],
    "wof:name":"Outpost Productions",
    "wof:placetype":"venue"
},
  "geometry": {"coordinates":[-118.49555100000001,34.14232],"type":"Point"}
}