{
  "type": "Feature",
  "properties": {
    "addr:full":"4163 Tokay Dr Napa CA 94558",
    "addr:housenumber":"4163",
    "addr:postcode":"94558",
    "addr:street":"Tokay Dr",
    "iso:country":"US",
    "sg:address":"4163 Tokay Dr",
    "sg:city":"Napa",
    "sg:classifiers":[
        {
            "category":"Building & Trades",
            "subcategory":"Landscaping Services",
            "type":"Services"
        }
    ],
    "sg:phone":"+1 707 226 8098",
    "sg:postcode":"94558",
    "sg:province":"CA",
    "sg:tags":[
        "lawn",
        "maintenance",
        "grounds"
    ],
    "wof:name":"Sierra Landscape Svc",
    "wof:placetype":"venue"
},
  "geometry": {"coordinates":[-122.32881399999999,38.328766],"type":"Point"}
}