{
  "type": "Feature",
  "properties": {
    "iso:country":"US",
    "sg:address":"4415 Los Serranos Blvd",
    "sg:city":"Chino Hills",
    "sg:classifiers":[
        {
            "category":"Professional",
            "type":"Services"
        }
    ],
    "sg:phone":"+1 909 393 1421",
    "sg:postcode":"91709",
    "sg:province":"CA",
    "wof:name":"Antonio Edeza",
    "wof:placetype":"venue"
},
  "geometry": {"coordinates":[-117.70731600000001,33.970645],"type":"Point"}
}