{
  "type": "Feature",
  "properties": {
    "iso:country":"US",
    "sg:address":"13615 Colony Ave",
    "sg:city":"San Martin",
    "sg:classifiers":[
        {
            "category":"Real Estate",
            "subcategory":"Real Estate Agent",
            "type":"Services"
        }
    ],
    "sg:phone":"+1 408 683 0510",
    "sg:postcode":"95046",
    "sg:province":"CA",
    "wof:name":"Roy Gullo Properties",
    "wof:placetype":"venue"
},
  "geometry": {"coordinates":[-121.616058,37.087933],"type":"Point"}
}