{
  "type": "Feature",
  "properties": {
    "addr:full":"531 E Campbell Ave Campbell CA 95008",
    "addr:housenumber":"531",
    "addr:postcode":"95008",
    "addr:street":"E Campbell Ave",
    "iso:country":"US",
    "sg:address":"531 E Campbell Ave",
    "sg:city":"Campbell",
    "sg:classifiers":[
        {
            "category":"Shopping",
            "subcategory":"Clothing, Apparel, & Fashions",
            "type":"Retail Goods"
        },
        {
            "category":"Personal",
            "subcategory":"Tanning Parlor",
            "type":"Services"
        }
    ],
    "sg:phone":"+1 408 866 2253",
    "sg:postcode":"95008",
    "sg:province":"CA",
    "sg:tags":[
        "clothing",
        "women's"
    ],
    "sg:website":"www.bronzetts.com",
    "wof:name":"Bronze Rage",
    "wof:placetype":"venue"
},
  "geometry": {"coordinates":[-121.94047,37.287062],"type":"Point"}
}