{
  "type": "Feature",
  "properties": {
    "iso:country":"US",
    "sg:address":"185 Branham Ln",
    "sg:city":"San Jose",
    "sg:classifiers":[
        {
            "category":"Personal",
            "subcategory":"Nail Salon",
            "type":"Services"
        }
    ],
    "sg:phone":"+1 408 229 8028",
    "sg:postcode":"95136",
    "sg:province":"CA",
    "wof:name":"Annie's Design Nail Salon",
    "wof:placetype":"venue"
},
  "geometry": {"coordinates":[-121.83397100000001,37.2672],"type":"Point"}
}