{
  "type": "Feature",
  "properties": {
    "iso:country":"US",
    "sg:address":"958 San Leandro Ave",
    "sg:city":"Mountain View",
    "sg:classifiers":[
        {
            "category":"Restaurant",
            "type":"Food & Drink"
        }
    ],
    "sg:phone":"+1 650 940 4200",
    "sg:postcode":"94043",
    "sg:province":"CA",
    "wof:name":"Mc Donald's",
    "wof:placetype":"venue"
},
  "geometry": {"coordinates":[-122.07062999999999,37.407242],"type":"Point"}
}