{
  "type": "Feature",
  "properties": {
    "addr:full":"1312 S Trotwood Ave San Pedro CA 90732",
    "addr:housenumber":"1312",
    "addr:postcode":"90732",
    "addr:street":"S Trotwood Ave",
    "iso:country":"US",
    "sg:address":"1312 S Trotwood Ave",
    "sg:city":"San Pedro",
    "sg:classifiers":[
        {
            "category":"Food & Beverages",
            "subcategory":"Meat & Fish",
            "type":"Retail Goods"
        }
    ],
    "sg:phone":"+1 310 547 5184",
    "sg:postcode":"90732",
    "sg:province":"CA",
    "sg:tags":[
        "seafood"
    ],
    "wof:name":"Seafood Express",
    "wof:placetype":"venue"
},
  "geometry": {"coordinates":[-118.314536,33.732267],"type":"Point"}
}