{
  "type": "Feature",
  "properties": {
    "iso:country":"US",
    "sg:address":"646 Williams Rd",
    "sg:city":"Salinas",
    "sg:classifiers":[
        {
            "category":"Autos & Motor Vehicles",
            "subcategory":"Fuel & Gas Station",
            "type":"Retail Goods"
        }
    ],
    "sg:phone":"+1 831 753 1695",
    "sg:postcode":"93905",
    "sg:province":"CA",
    "wof:name":"Valero-Mountain Valley",
    "wof:placetype":"venue"
},
  "geometry": {"coordinates":[-121.60614099999999,36.680161],"type":"Point"}
}