{
  "type": "Feature",
  "properties": {
    "addr:full":"7700 Imperial Hwy Downey CA 90242",
    "addr:housenumber":"7700",
    "addr:postcode":"90242",
    "addr:street":"Imperial Hwy",
    "iso:country":"US",
    "sg:address":"7700 Imperial Hwy",
    "sg:city":"Downey",
    "sg:classifiers":[
        {
            "category":"Shopping",
            "type":"Retail Goods"
        }
    ],
    "sg:phone":"+1 562 803 3322",
    "sg:postcode":"90242",
    "sg:province":"CA",
    "sg:tags":[
        "limb",
        "artificial"
    ],
    "sg:website":"www.hanger.com",
    "wof:name":"Hanger Prosthetics & Orthotics",
    "wof:placetype":"venue"
},
  "geometry": {"coordinates":[-118.158468,33.927225],"type":"Point"}
}