{
  "type": "Feature",
  "properties": {
    "addr:full":"2955 Kathleen St Riverside CA 92506",
    "addr:housenumber":"2955",
    "addr:postcode":"92506",
    "addr:street":"Kathleen St",
    "iso:country":"US",
    "sg:address":"2955 Kathleen St",
    "sg:city":"Riverside",
    "sg:classifiers":[
        {
            "category":"Professional",
            "type":"Services"
        }
    ],
    "sg:phone":"+1 951 779 0199",
    "sg:postcode":"92506",
    "sg:province":"CA",
    "wof:name":"Customer Service Unlimited",
    "wof:placetype":"venue"
},
  "geometry": {"coordinates":[-117.384084,33.941048],"type":"Point"}
}