{
  "type": "Feature",
  "properties": {
    "iso:country":"US",
    "sg:address":"8327 Fair Oaks Blvd",
    "sg:city":"Carmichael",
    "sg:classifiers":[
        {
            "category":"Real Estate",
            "subcategory":"Real Estate Operator",
            "type":"Services"
        }
    ],
    "sg:phone":"+1 916 944 2555",
    "sg:postcode":"95608",
    "sg:province":"CA",
    "sg:tags":[
        "apartment"
    ],
    "wof:name":"Hill Crest",
    "wof:placetype":"venue"
},
  "geometry": {"coordinates":[-121.30884500000001,38.636686],"type":"Point"}
}