{
  "type": "Feature",
  "properties": {
    "addr:full":"73622 Sun Ln Palm Desert CA 92260",
    "addr:housenumber":"73622",
    "addr:postcode":"ca 92260",
    "addr:street":"Sun Ln",
    "iso:country":"US",
    "sg:address":"73622 Sun Ln",
    "sg:city":"Palm Desert",
    "sg:classifiers":[
        {
            "category":"Building & Trades",
            "subcategory":"Electrical",
            "type":"Services"
        }
    ],
    "sg:phone":"+1 760 341 8018",
    "sg:postcode":"92260",
    "sg:province":"CA",
    "sg:tags":[
        "electrician"
    ],
    "wof:name":"Donco Electric Inc",
    "wof:placetype":"venue"
},
  "geometry": {"coordinates":[-116.380084,33.701788],"type":"Point"}
}