{
  "type": "Feature",
  "properties": {
    "iso:country":"US",
    "sg:address":"5301 Pirrone Rd",
    "sg:city":"Salida",
    "sg:classifiers":[
        {
            "category":"Professional",
            "subcategory":"Management & Consulting",
            "type":"Services"
        }
    ],
    "sg:phone":"+1 209 545 9889",
    "sg:postcode":"95368",
    "sg:province":"CA",
    "sg:tags":[
        "consultant",
        "construction"
    ],
    "wof:name":"Riverside Builders",
    "wof:placetype":"venue"
},
  "geometry": {"coordinates":[-121.097673,37.720652],"type":"Point"}
}