{
  "type": "Feature",
  "properties": {
    "iso:country":"US",
    "sg:address":"9425 Telegraph Rd",
    "sg:city":"Pico Rivera",
    "sg:classifiers":[
        {
            "category":"Banks & Credit Unions",
            "subcategory":"Financial Services",
            "type":"Services"
        }
    ],
    "sg:phone":"+1 562 222 2282",
    "sg:postcode":"90660",
    "sg:province":"CA",
    "sg:tags":[
        "broker",
        "mortgage"
    ],
    "wof:name":"Infinity Mortgage Services",
    "wof:placetype":"venue"
},
  "geometry": {"coordinates":[-118.085999,33.985802],"type":"Point"}
}