{
  "type": "Feature",
  "properties": {
    "addr:full":"230 16th Pl Costa Mesa CA 92627",
    "addr:housenumber":"230",
    "addr:postcode":"92627",
    "addr:street":"16Th Pl",
    "iso:country":"US",
    "sg:address":"230 16th Pl",
    "sg:city":"Costa Mesa",
    "sg:classifiers":[
        {
            "category":"Shopping",
            "subcategory":"Catalog Store",
            "type":"Retail Goods"
        }
    ],
    "sg:phone":"+1 949 646 8946",
    "sg:postcode":"92627",
    "sg:province":"CA",
    "sg:tags":[
        "e"
    ],
    "sg:website":"www.pricecooler.com",
    "wof:name":"PRICECOOLER.COM",
    "wof:placetype":"venue"
},
  "geometry": {"coordinates":[-117.920024,33.63295],"type":"Point"}
}