{
  "type": "Feature",
  "properties": {
    "iso:country":"US",
    "sg:address":"757 N Twin Oaks Valley Rd",
    "sg:city":"San Marcos",
    "sg:classifiers":[
        {
            "category":"Manufacturing",
            "subcategory":"Retail Goods",
            "type":"Manufacturing & Wholesale Goods"
        }
    ],
    "sg:phone":"+1 760 591 3911",
    "sg:postcode":"92069",
    "sg:province":"CA",
    "sg:tags":[
        "mfg",
        "shades",
        "onyx",
        "lamp",
        "parts",
        "silk",
        "marble"
    ],
    "wof:name":"Burdock",
    "wof:placetype":"venue"
},
  "geometry": {"coordinates":[-117.161655,33.150931],"type":"Point"}
}