{
  "type": "Feature",
  "properties": {
    "addr:full":"2127 S Vasco Rd Livermore CA 94550",
    "addr:housenumber":"2127",
    "addr:postcode":"94550",
    "addr:street":"S Vasco Rd",
    "iso:country":"US",
    "sg:address":"2127 S Vasco Rd",
    "sg:city":"Livermore",
    "sg:classifiers":[
        {
            "category":"Building & Trades",
            "subcategory":"Construction",
            "type":"Services"
        }
    ],
    "sg:phone":"+1 925 454 8845",
    "sg:postcode":"94550",
    "sg:province":"CA",
    "sg:tags":[
        "front",
        "store",
        "contractor"
    ],
    "wof:name":"F & M Storefront",
    "wof:placetype":"venue"
},
  "geometry": {"coordinates":[-121.71900599999999,37.677965],"type":"Point"}
}