{
  "type": "Feature",
  "properties": {
    "iso:country":"US",
    "sg:address":"2925 Root Ave",
    "sg:city":"Carmichael",
    "sg:classifiers":[
        {
            "category":"Social Services",
            "subcategory":"Child Care",
            "type":"Services"
        }
    ],
    "sg:phone":"+1 916 487 8411",
    "sg:postcode":"95608",
    "sg:province":"CA",
    "sg:tags":[
        "day"
    ],
    "wof:name":"Wee Tymes Playschool Inc",
    "wof:placetype":"venue"
},
  "geometry": {"coordinates":[-121.350792,38.618177],"type":"Point"}
}