{
  "type": "Feature",
  "properties": {
    "addr:full":"2163 Abbott St San Diego CA 92107",
    "addr:housenumber":"2163",
    "addr:postcode":"92107",
    "addr:street":"Abbott St",
    "iso:country":"US",
    "sg:address":"2163 Abbott St",
    "sg:city":"San Diego",
    "sg:classifiers":[
        {
            "category":"Food & Beverages",
            "subcategory":"Bakery",
            "type":"Retail Goods"
        }
    ],
    "sg:phone":"+1 619 224 2358",
    "sg:postcode":"92107",
    "sg:province":"CA",
    "sg:tags":[
        "baker"
    ],
    "wof:name":"Point Loma Bakery",
    "wof:placetype":"venue"
},
  "geometry": {"coordinates":[-117.249241,32.751932],"type":"Point"}
}