{
  "type": "Feature",
  "properties": {
    "iso:country":"US",
    "sg:address":"8665 Gibbs Dr",
    "sg:city":"San Diego",
    "sg:classifiers":[
        {
            "category":"Insurance",
            "subcategory":"Insurance Agent",
            "type":"Services"
        }
    ],
    "sg:phone":"+1 858 715 8800",
    "sg:postcode":"92123",
    "sg:province":"CA",
    "wof:name":"Tristar Risk Management Inc",
    "wof:placetype":"venue"
},
  "geometry": {"coordinates":[-117.143726,32.810346],"type":"Point"}
}