{
  "type": "Feature",
  "properties": {
    "iso:country":"US",
    "sg:address":"1926 H St 95814",
    "sg:city":"Sacramento",
    "sg:classifiers":[
        {
            "category":"Retail",
            "subcategory":"Photofinishing",
            "type":"Services"
        },
        {
            "category":"Professional",
            "subcategory":"Printing & Photocopies",
            "type":"Services"
        }
    ],
    "sg:phone":"+1 800 464 6861",
    "sg:postcode":"95811",
    "sg:province":"CA",
    "sg:tags":[
        "laboratory",
        "laboratories-commercial",
        "finishing-custom",
        "photo"
    ],
    "wof:name":"C Fg. Photo Lab",
    "wof:placetype":"venue"
},
  "geometry": {"coordinates":[-121.479556,38.579056],"type":"Point"}
}