{
  "type": "Feature",
  "properties": {
    "iso:country":"US",
    "sg:address":"87 E Green St",
    "sg:city":"Pasadena",
    "sg:classifiers":[
        {
            "category":"Professional",
            "subcategory":"Employment Agencies",
            "type":"Services"
        }
    ],
    "sg:phone":"+1 626 844 3562",
    "sg:postcode":"91105",
    "sg:province":"CA",
    "sg:tags":[
        "temporary"
    ],
    "wof:name":"Express Employment",
    "wof:placetype":"venue"
},
  "geometry": {"coordinates":[-118.148719,34.144501],"type":"Point"}
}