{
  "type": "Feature",
  "properties": {
    "iso:country":"US",
    "sg:address":"30812 E Kings Canyon Rd",
    "sg:city":"Squaw Valley",
    "sg:classifiers":[
        {
            "category":"Food & Beverages",
            "subcategory":"Groceries & Convenience Stores",
            "type":"Retail Goods"
        }
    ],
    "sg:phone":"+1 559 332 2880",
    "sg:postcode":"93675",
    "sg:province":"CA",
    "wof:name":"Squaw Valley Trading Ctr",
    "wof:placetype":"venue"
},
  "geometry": {"coordinates":[-119.23677,36.743252],"type":"Point"}
}