{
  "type": "Feature",
  "properties": {
    "iso:country":"US",
    "sg:address":"12643 Sherman Way",
    "sg:city":"North Hollywood",
    "sg:classifiers":[
        {
            "category":"Wholesale",
            "subcategory":"Plants",
            "type":"Manufacturing & Wholesale Goods"
        }
    ],
    "sg:phone":"+1 818 764 4623",
    "sg:postcode":"91605",
    "sg:province":"CA",
    "sg:tags":[
        "florist"
    ],
    "wof:name":"Tip Top Designs",
    "wof:placetype":"venue"
},
  "geometry": {"coordinates":[-118.406899,34.20127],"type":"Point"}
}