{
  "type": "Feature",
  "properties": {
    "iso:country":"US",
    "sg:address":"8443 Hidden Valley Rd",
    "sg:city":"Mountain Ranch",
    "sg:classifiers":[
        {
            "category":"Wholesale",
            "subcategory":"Hardware",
            "type":"Manufacturing & Wholesale Goods"
        }
    ],
    "sg:phone":"+1 209 754 5121",
    "sg:postcode":"95246",
    "sg:province":"CA",
    "sg:tags":[
        "equipment",
        "jail"
    ],
    "sg:website":"www.goldmedalsafetypadding.com",
    "wof:name":"Marathon Engineering",
    "wof:placetype":"venue"
},
  "geometry": {"coordinates":[-120.52488700000001,38.216176],"type":"Point"}
}