{
  "type": "Feature",
  "properties": {
    "addr:full":"251 Stonewood St K-5 Downey CA 90241",
    "addr:housenumber":"251;k-5",
    "addr:postcode":"90241",
    "addr:street":"Stonewood St",
    "iso:country":"US",
    "sg:address":"251 Stonewood St K-5",
    "sg:city":"Downey",
    "sg:classifiers":[
        {
            "category":"Retail",
            "subcategory":"Repair Shop",
            "type":"Services"
        }
    ],
    "sg:phone":"+1 562 861 4818",
    "sg:postcode":"90241",
    "sg:province":"CA",
    "sg:tags":[
        "watch"
    ],
    "wof:name":"Watch Doc",
    "wof:placetype":"venue"
},
  "geometry": {"coordinates":[-118.119984,33.935768],"type":"Point"}
}