{
  "type": "Feature",
  "properties": {
    "addr:full":"1601 W Redondo Beach Boulevard Suite 103 Gardena CA 90247",
    "addr:housenumber":"1601",
    "addr:postcode":"90247",
    "addr:street":"W Redondo Beach Boulevard Suite 103",
    "iso:country":"US",
    "sg:address":"1601 W Redondo Beach Boulevard Suite 103",
    "sg:city":"Gardena",
    "sg:classifiers":[
        {
            "category":"Shopping",
            "subcategory":"Pets & Pet Supplies",
            "type":"Retail Goods"
        }
    ],
    "sg:phone":"+1 310 327 1001",
    "sg:postcode":"90247",
    "sg:province":"CA",
    "sg:tags":[
        "groomers"
    ],
    "wof:name":"Beach Dog Grooming",
    "wof:placetype":"venue"
},
  "geometry": {"coordinates":[-118.292928,33.892455],"type":"Point"}
}