{
  "type": "Feature",
  "properties": {
    "addr:full":"419 6th St Marysville CA 95901",
    "addr:housenumber":"419",
    "addr:postcode":"95901",
    "addr:street":"6Th St",
    "iso:country":"US",
    "sg:address":"419 6th St",
    "sg:city":"Marysville",
    "sg:classifiers":[
        {
            "category":"Insurance",
            "subcategory":"Insurance Agent",
            "type":"Services"
        }
    ],
    "sg:phone":"+1 530 742 3243",
    "sg:postcode":"95901",
    "sg:province":"CA",
    "sg:website":"www.galliganinsurance.com",
    "wof:name":"Robert Galligan & Assoc Inc",
    "wof:placetype":"venue"
},
  "geometry": {"coordinates":[-121.590693,39.141318],"type":"Point"}
}