{
  "type": "Feature",
  "properties": {
    "iso:country":"US",
    "sg:address":"18887 River Ranch Rd",
    "sg:city":"Anderson",
    "sg:classifiers":[
        {
            "category":"Manufacturing",
            "subcategory":"Lumber",
            "type":"Manufacturing & Wholesale Goods"
        }
    ],
    "sg:phone":"+1 530 243 4990",
    "sg:postcode":"96007",
    "sg:province":"CA",
    "sg:tags":[
        "logging"
    ],
    "wof:name":"Isringhausen Logging & Eqp",
    "wof:placetype":"venue"
},
  "geometry": {"coordinates":[-122.35509500000001,40.487887],"type":"Point"}
}