{
  "type": "Feature",
  "properties": {
    "iso:country":"US",
    "sg:address":"4296 Alamo St",
    "sg:city":"Simi Valley",
    "sg:classifiers":[
        {
            "category":"Professional",
            "subcategory":"Management & Consulting",
            "type":"Services"
        }
    ],
    "sg:phone":"+1 805 581 2391",
    "sg:postcode":"93063",
    "sg:province":"CA",
    "wof:name":"Mechanical Drafting Service",
    "wof:placetype":"venue"
},
  "geometry": {"coordinates":[-118.710801,34.286215],"type":"Point"}
}