{
  "type": "Feature",
  "properties": {
    "iso:country":"US",
    "sg:address":"620 Lighthouse Ave",
    "sg:city":"Pacific Grove",
    "sg:classifiers":[
        {
            "category":"Real Estate",
            "subcategory":"Real Estate Agent",
            "type":"Services"
        }
    ],
    "sg:phone":"+1 831 655 5100",
    "sg:postcode":"93950",
    "sg:province":"CA",
    "sg:tags":[
        "consultant"
    ],
    "wof:name":"Gregory P Beardsley",
    "wof:placetype":"venue"
},
  "geometry": {"coordinates":[-121.919257,36.621807],"type":"Point"}
}