{
  "type": "Feature",
  "properties": {
    "addr:full":"689 Calderon Ave Mountain View CA 94041",
    "addr:housenumber":"689",
    "addr:postcode":"94041",
    "addr:street":"Calderon Ave",
    "iso:country":"US",
    "sg:address":"689 Calderon Ave",
    "sg:city":"Mountain View",
    "sg:classifiers":[
        {
            "category":"Food & Beverages",
            "subcategory":"Groceries & Convenience Stores",
            "type":"Retail Goods"
        }
    ],
    "sg:phone":"+1 650 968 1070",
    "sg:postcode":"94041",
    "sg:province":"CA",
    "wof:name":"Sav Mor Food Store",
    "wof:placetype":"venue"
},
  "geometry": {"coordinates":[-122.074997,37.3853],"type":"Point"}
}