{
  "type": "Feature",
  "properties": {
    "iso:country":"US",
    "sg:address":"2233 Huntington Dr",
    "sg:city":"San Marino",
    "sg:classifiers":[
        {
            "category":"Banks & Credit Unions",
            "subcategory":"Bank",
            "type":"Services"
        }
    ],
    "sg:phone":"+1 626 440 9430",
    "sg:postcode":"91108",
    "sg:province":"CA",
    "sg:tags":[
        "loan"
    ],
    "sg:website":"www.kennedycorp.com",
    "wof:name":"Kennedy Capital",
    "wof:placetype":"venue"
},
  "geometry": {"coordinates":[-118.104962,34.122381],"type":"Point"}
}