{
  "type": "Feature",
  "properties": {
    "iso:country":"US",
    "sg:address":"19211 State Rte 65",
    "sg:city":"Bakersfield",
    "sg:classifiers":[
        {
            "category":"Recreation",
            "type":"Entertainment"
        }
    ],
    "sg:phone":"+1 661 393 9071",
    "sg:postcode":"93308",
    "sg:province":"CA",
    "sg:tags":[
        "range",
        "practice",
        "golf"
    ],
    "wof:name":"# 1 Golf Driving Range",
    "wof:placetype":"venue"
},
  "geometry": {"coordinates":[-119.07467,35.448993],"type":"Point"}
}