{
  "type": "Feature",
  "properties": {
    "addr:full":"1170 Camino Vallecito Lafayette CA 94549",
    "addr:housenumber":"1170",
    "addr:postcode":"94549",
    "addr:street":"Camino Vallecito",
    "iso:country":"US",
    "sg:address":"1170 Camino Vallecito",
    "sg:city":"Lafayette",
    "sg:classifiers":[
        {
            "category":"Building & Trades",
            "subcategory":"Plumbing",
            "type":"Services"
        }
    ],
    "sg:phone":"+1 925 383 8506",
    "sg:postcode":"94549",
    "sg:province":"CA",
    "sg:tags":[
        "plumber",
        "industrial",
        "contractors-commercial"
    ],
    "wof:name":"Stefano S Plumbing & Drain",
    "wof:placetype":"venue"
},
  "geometry": {"coordinates":[-122.147845,37.901262],"type":"Point"}
}