{
  "type": "Feature",
  "properties": {
    "addr:full":"900 S Broadway Los Angeles CA 90015",
    "addr:housenumber":"900",
    "addr:postcode":"90015",
    "addr:street":"S Broadway",
    "iso:country":"US",
    "sg:address":"900 S Broadway",
    "sg:city":"Los Angeles",
    "sg:classifiers":[
        {
            "category":"Manufacturing",
            "subcategory":"Jewelry",
            "type":"Manufacturing & Wholesale Goods"
        }
    ],
    "sg:phone":"+1 213 489 6627",
    "sg:postcode":"90015",
    "sg:province":"CA",
    "wof:name":"Chain & Charm Jewelry Mfg",
    "wof:placetype":"venue"
},
  "geometry": {"coordinates":[-118.257402,34.040901],"type":"Point"}
}