{
  "type": "Feature",
  "properties": {
    "iso:country":"US",
    "sg:address":"20200 Redwood Rd",
    "sg:city":"Castro Valley",
    "sg:classifiers":[
        {
            "category":"Real Estate",
            "subcategory":"Real Estate Agent",
            "type":"Services"
        }
    ],
    "sg:phone":"+1 510 490 4300",
    "sg:postcode":"94546",
    "sg:province":"CA",
    "wof:name":"Leavitt Realty",
    "wof:placetype":"venue"
},
  "geometry": {"coordinates":[-122.073994,37.698115],"type":"Point"}
}