{
  "type": "Feature",
  "properties": {
    "addr:full":"2695 Fordham St. East Palo Alto, Ca 94303",
    "wof:categories":[
        "education_and_religion:education=school"
    ],
    "wof:name":"Costano Elementary School",
    "wof:placetype":"venue"
},
  "geometry": {"coordinates":[-122.13688954478711,37.47837108236676],"type":"Point"}
}