{
  "type": "Feature",
  "properties": {
    "addr:full":"2625 Townsgate Rd Westlake Village CA 91361",
    "addr:housenumber":"2625",
    "addr:postcode":"91361",
    "addr:street":"Townsgate Rd",
    "iso:country":"US",
    "sg:address":"2625 Townsgate Rd",
    "sg:city":"Westlake Village",
    "sg:classifiers":[
        {
            "category":"Wholesale",
            "subcategory":"Toys & Hobbies",
            "type":"Manufacturing & Wholesale Goods"
        }
    ],
    "sg:phone":"+1 805 267 1292",
    "sg:postcode":"91361",
    "sg:province":"CA",
    "sg:tags":[
        "doll"
    ],
    "wof:name":"Lonely Hearts Club",
    "wof:placetype":"venue"
},
  "geometry": {"coordinates":[-118.82841000000001,34.155766],"type":"Point"}
}