{
  "type": "Feature",
  "properties": {
    "addr:full":"125 Spring Hill Dr Grass Valley CA 95945",
    "addr:housenumber":"125",
    "addr:postcode":"95945",
    "addr:street":"Spring Hill Dr",
    "iso:country":"US",
    "sg:address":"125 Spring Hill Dr",
    "sg:city":"Grass Valley",
    "sg:classifiers":[
        {
            "category":"Retail",
            "subcategory":"Auto Repair",
            "type":"Services"
        }
    ],
    "sg:phone":"+1 530 477 0140",
    "sg:postcode":"95945",
    "sg:province":"CA",
    "sg:tags":[
        "repairing",
        "automobile",
        "customizing"
    ],
    "wof:name":"Geared Up Drivetrain",
    "wof:placetype":"venue"
},
  "geometry": {"coordinates":[-121.04291499999999,39.225202],"type":"Point"}
}