{
  "type": "Feature",
  "properties": {
    "addr:full":"24310 Moulton Pkwy Laguna Woods CA 92637",
    "addr:housenumber":"24310",
    "addr:postcode":"92637",
    "addr:street":"Moulton Pkwy",
    "iso:country":"US",
    "sg:address":"24310 Moulton Pkwy",
    "sg:city":"Laguna Woods",
    "sg:classifiers":[
        {
            "category":"Personal",
            "subcategory":"Beauty Salon",
            "type":"Services"
        }
    ],
    "sg:phone":"+1 949 581 6791",
    "sg:postcode":"92637",
    "sg:province":"CA",
    "wof:name":"Dee",
    "wof:placetype":"venue"
},
  "geometry": {"coordinates":[-117.72234,33.607504],"type":"Point"}
}