{
  "type": "Feature",
  "properties": {
    "addr:full":"776 Jackson St San Francisco CA 94133",
    "addr:housenumber":"776",
    "addr:postcode":"94133",
    "addr:street":"Jackson St",
    "iso:country":"US",
    "sg:address":"776 Jackson St",
    "sg:city":"San Francisco",
    "sg:classifiers":[
        {
            "category":"Food & Beverages",
            "subcategory":"Specialty",
            "type":"Retail Goods"
        }
    ],
    "sg:phone":"+1 415 362 1888",
    "sg:postcode":"94133",
    "sg:province":"CA",
    "sg:tags":[
        "herb"
    ],
    "wof:name":"Hue An Co",
    "wof:placetype":"venue"
},
  "geometry": {"coordinates":[-122.408209,37.795906],"type":"Point"}
}