{
  "type": "Feature",
  "properties": {
    "addr:full":"1036 W Robinhood Dr Stockton CA 95207",
    "addr:housenumber":"1036",
    "addr:postcode":"95207",
    "addr:street":"W Robinhood Dr",
    "iso:country":"US",
    "sg:address":"1036 W Robinhood Dr",
    "sg:city":"Stockton",
    "sg:classifiers":[
        {
            "category":"Professional",
            "subcategory":"Advertising",
            "type":"Services"
        }
    ],
    "sg:phone":"+1 209 473 3920",
    "sg:postcode":"95207",
    "sg:province":"CA",
    "sg:tags":[
        "counselor"
    ],
    "wof:name":"Palmer Advertising",
    "wof:placetype":"venue"
},
  "geometry": {"coordinates":[-121.318274,37.999985],"type":"Point"}
}