{
  "type": "Feature",
  "properties": {
    "addr:full":"7888 Broadway Lemon Grove CA 91945",
    "addr:housenumber":"7888",
    "addr:postcode":"91945",
    "addr:street":"Broadway",
    "iso:country":"US",
    "sg:address":"7888 Broadway",
    "sg:city":"Lemon Grove",
    "sg:classifiers":[
        {
            "category":"Banks & Credit Unions",
            "subcategory":"Financial Services",
            "type":"Services"
        }
    ],
    "sg:phone":"+1 619 303 3772",
    "sg:postcode":"91945",
    "sg:province":"CA",
    "sg:tags":[
        "broker",
        "mortgage"
    ],
    "sg:website":"www.hsmfinancial.com",
    "wof:name":"HSM Financial",
    "wof:placetype":"venue"
},
  "geometry": {"coordinates":[-117.02889999999999,32.742795],"type":"Point"}
}