{
  "type": "Feature",
  "properties": {
    "addr:full":"3139 Braemar Dr Santa Barbara CA 93109",
    "addr:housenumber":"3139",
    "addr:postcode":"93109",
    "addr:street":"Braemar Dr",
    "iso:country":"US",
    "sg:address":"3139 Braemar Dr",
    "sg:city":"Santa Barbara",
    "sg:classifiers":[
        {
            "category":"Wholesale",
            "subcategory":"Plants",
            "type":"Manufacturing & Wholesale Goods"
        }
    ],
    "sg:phone":"+1 805 563 8097",
    "sg:postcode":"93109",
    "sg:province":"CA",
    "sg:tags":[
        "nursery",
        "tree"
    ],
    "wof:name":"Rancho Encino",
    "wof:placetype":"venue"
},
  "geometry": {"coordinates":[-119.746481,34.407142],"type":"Point"}
}