{
  "type": "Feature",
  "properties": {
    "iso:country":"US",
    "sg:address":"1565 S Harbor Blvd",
    "sg:city":"Fullerton",
    "sg:classifiers":[
        {
            "category":"Communications",
            "subcategory":"Television Station",
            "type":"Services"
        }
    ],
    "sg:phone":"+1 877 278 1493",
    "sg:postcode":"92832",
    "sg:province":"CA",
    "sg:tags":[
        "repair",
        "satellite",
        "cable",
        "tv",
        "system",
        "equipment"
    ],
    "wof:name":"Time Warner Cable SoCal",
    "wof:placetype":"venue"
},
  "geometry": {"coordinates":[-117.924352,33.855729],"type":"Point"}
}