{
  "type": "Feature",
  "properties": {
    "addr:full":"114 S Riverside Ave Rialto CA 92376",
    "addr:housenumber":"114",
    "addr:postcode":"92376",
    "addr:street":"S Riverside Ave",
    "iso:country":"US",
    "sg:address":"114 S Riverside Ave",
    "sg:city":"Rialto",
    "sg:classifiers":[
        {
            "category":"Shopping",
            "subcategory":"Florist",
            "type":"Retail Goods"
        }
    ],
    "sg:phone":"+1 909 875 3360",
    "sg:postcode":"92376",
    "sg:province":"CA",
    "wof:name":"Rialto Flower & Gift Shop",
    "wof:placetype":"venue"
},
  "geometry": {"coordinates":[-117.370574,34.099155],"type":"Point"}
}