{
  "type": "Feature",
  "properties": {
    "addr:full":"617 14th Street Sacramento CA 95814",
    "addr:housenumber":"617",
    "addr:postcode":"95814",
    "addr:street":"14Th Street",
    "iso:country":"US",
    "sg:address":"617 14th Street",
    "sg:city":"Sacramento",
    "sg:classifiers":[
        {
            "category":"Banks & Credit Unions",
            "subcategory":"Financial Services",
            "type":"Services"
        }
    ],
    "sg:phone":"+1 916 444 7511",
    "sg:postcode":"95814",
    "sg:province":"CA",
    "sg:tags":[
        "broker",
        "mortgage"
    ],
    "wof:name":"Sierra Pacific Mortgage-Eric Golden",
    "wof:placetype":"venue"
},
  "geometry": {"coordinates":[-121.486169,38.582423],"type":"Point"}
}