{
  "type": "Feature",
  "properties": {
    "iso:country":"US",
    "sg:address":"17459 Lilac St",
    "sg:city":"Hesperia",
    "sg:classifiers":[
        {
            "category":"Retail",
            "subcategory":"Repair Shop",
            "type":"Services"
        },
        {
            "category":"Manufacturing",
            "subcategory":"Motor Vehicles & Parts",
            "type":"Manufacturing & Wholesale Goods"
        }
    ],
    "sg:phone":"+1 760 949 3907",
    "sg:postcode":"92345",
    "sg:province":"CA",
    "sg:tags":[
        "mfg",
        "racing",
        "welding"
    ],
    "wof:name":"C and D Fabworks",
    "wof:placetype":"venue"
},
  "geometry": {"coordinates":[-117.28638100000001,34.451267],"type":"Point"}
}