{
  "type": "Feature",
  "properties": {
    "addr:full":"15261 Hesperian Blvd San Leandro CA 94578",
    "addr:housenumber":"15261",
    "addr:postcode":"94578",
    "addr:street":"Hesperian Blvd",
    "iso:country":"US",
    "sg:address":"15261 Hesperian Blvd",
    "sg:city":"San Leandro",
    "sg:classifiers":[
        {
            "category":"Banks & Credit Unions",
            "subcategory":"Investment Brokerage",
            "type":"Services"
        }
    ],
    "sg:phone":"+1 510 317 2380",
    "sg:postcode":"94578",
    "sg:province":"CA",
    "sg:tags":[
        "advisory",
        "financial"
    ],
    "wof:name":"Financial Network Investment",
    "wof:placetype":"venue"
},
  "geometry": {"coordinates":[-122.13002400000001,37.696939],"type":"Point"}
}