{
  "type": "Feature",
  "properties": {
    "iso:country":"US",
    "sg:address":"3651 Frei Rd",
    "sg:city":"Sebastopol",
    "sg:classifiers":[
        {
            "category":"Restaurant",
            "type":"Food & Drink"
        }
    ],
    "sg:phone":"+1 707 829 3374",
    "sg:postcode":"95472",
    "sg:province":"CA",
    "wof:name":"Quailhill Vineyard",
    "wof:placetype":"venue"
},
  "geometry": {"coordinates":[-122.84892499999999,38.439291],"type":"Point"}
}