{
  "type": "Feature",
  "properties": {
    "iso:country":"US",
    "sg:address":"2934 Westminster Ave",
    "sg:city":"Seal Beach",
    "sg:classifiers":[
        {
            "category":"Restaurant",
            "type":"Food & Drink"
        }
    ],
    "sg:menulink":"http://www.allmenus.com/ca/north-coast/73892-dominos-pizza/menu/",
    "sg:phone":"+1 562 493 2212",
    "sg:postcode":"90740",
    "sg:province":"CA",
    "sg:tags":[
        "american",
        "wing",
        "pizza"
    ],
    "wof:name":"Domino's Pizza",
    "wof:placetype":"venue"
},
  "geometry": {"coordinates":[-118.07926399999999,33.759495],"type":"Point"}
}