{
  "type": "Feature",
  "properties": {
    "addr:full":"2552 E Colorado Blvd Pasadena CA 91107",
    "addr:housenumber":"2552",
    "addr:postcode":"91107",
    "addr:street":"E Colorado Blvd",
    "iso:country":"US",
    "sg:address":"2552 E Colorado Blvd",
    "sg:city":"Pasadena",
    "sg:classifiers":[
        {
            "category":"Shopping",
            "subcategory":"Used Merchandise",
            "type":"Retail Goods"
        }
    ],
    "sg:phone":"+1 626 440 1880",
    "sg:postcode":"91107",
    "sg:province":"CA",
    "wof:name":"Time Recyclers",
    "wof:placetype":"venue"
},
  "geometry": {"coordinates":[-118.09818199999999,34.146031],"type":"Point"}
}