{
  "type": "Feature",
  "properties": {
    "iso:country":"US",
    "sg:address":"740 Ventura Blvd",
    "sg:city":"Camarillo",
    "sg:classifiers":[
        {
            "category":"Wholesale",
            "subcategory":"Sporting Goods",
            "type":"Manufacturing & Wholesale Goods"
        }
    ],
    "sg:phone":"+1 805 383 3115",
    "sg:postcode":"93010",
    "sg:province":"CA",
    "wof:name":"Just Sports",
    "wof:placetype":"venue"
},
  "geometry": {"coordinates":[-119.058465,34.217809],"type":"Point"}
}