{
  "type": "Feature",
  "properties": {
    "addr:full":"5701 Lindero Canyon Rd Westlake Village CA 91362",
    "addr:housenumber":"5701",
    "addr:postcode":"91362",
    "addr:street":"Lindero Canyon Rd",
    "iso:country":"US",
    "sg:address":"5701 Lindero Canyon Rd",
    "sg:city":"Westlake Village",
    "sg:classifiers":[
        {
            "category":"Wholesale",
            "subcategory":"Office Equipment",
            "type":"Manufacturing & Wholesale Goods"
        }
    ],
    "sg:phone":"+1 818 991 3400",
    "sg:postcode":"91362",
    "sg:province":"CA",
    "sg:tags":[
        "credit",
        "system",
        "card"
    ],
    "sg:website":"www.bankcardusams.org",
    "wof:name":"Cardservice",
    "wof:placetype":"venue"
},
  "geometry": {"coordinates":[-118.798332,34.153464],"type":"Point"}
}