{
  "type": "Feature",
  "properties": {
    "addr:full":"31117 Mission Blvd Hayward CA 94544",
    "addr:housenumber":"31117",
    "addr:postcode":"94544",
    "addr:street":"Mission Blvd",
    "iso:country":"US",
    "sg:address":"31117 Mission Blvd",
    "sg:city":"Hayward",
    "sg:classifiers":[
        {
            "category":"Shopping",
            "subcategory":"Jewelry",
            "type":"Retail Goods"
        }
    ],
    "sg:phone":"+1 510 441 7123",
    "sg:postcode":"94544",
    "sg:province":"CA",
    "wof:name":"Bc Jewelry",
    "wof:placetype":"venue"
},
  "geometry": {"coordinates":[-122.03600299999999,37.6199],"type":"Point"}
}