{
  "type": "Feature",
  "properties": {
    "addr:full":"1379 B St Hayward CA 94541",
    "addr:housenumber":"1379",
    "addr:postcode":"94541",
    "addr:street":"B St",
    "iso:country":"US",
    "sg:address":"1379 B St",
    "sg:city":"Hayward",
    "sg:classifiers":[
        {
            "category":"Health Services",
            "subcategory":"Medical Lab",
            "type":"Services"
        }
    ],
    "sg:phone":"+1 510 885 1813",
    "sg:postcode":"94541",
    "sg:province":"CA",
    "sg:tags":[
        "laboratory"
    ],
    "wof:name":"E & E Dental Design",
    "wof:placetype":"venue"
},
  "geometry": {"coordinates":[-122.07702399999999,37.676683],"type":"Point"}
}