{
  "type": "Feature",
  "properties": {
    "addr:full":"13334 Ramona Blvd Baldwin Park CA 91706",
    "addr:housenumber":"13334",
    "addr:postcode":"91706",
    "addr:street":"Ramona Blvd",
    "iso:country":"US",
    "sg:address":"13334 Ramona Blvd",
    "sg:city":"Baldwin Park",
    "sg:classifiers":[
        {
            "category":"Retail",
            "subcategory":"Repair Shop",
            "type":"Services"
        }
    ],
    "sg:phone":"+1 626 480 8333",
    "sg:postcode":"91706",
    "sg:province":"CA",
    "sg:tags":[
        "lock",
        "locksmith"
    ],
    "wof:name":"Ace Locksmith",
    "wof:placetype":"venue"
},
  "geometry": {"coordinates":[-117.98279599999999,34.081083],"type":"Point"}
}