{
  "type": "Feature",
  "properties": {
    "addr:full":"9731 Somerset Blvd Bellflower CA 90706",
    "addr:housenumber":"9731",
    "addr:postcode":"90706",
    "addr:street":"Somerset Blvd",
    "iso:country":"US",
    "sg:address":"9731 Somerset Blvd",
    "sg:city":"Bellflower",
    "sg:classifiers":[
        {
            "category":"Shopping",
            "type":"Retail Goods"
        }
    ],
    "sg:phone":"+1 562 804 9747",
    "sg:postcode":"90706",
    "sg:province":"CA",
    "sg:tags":[
        "miscellaneous",
        "store",
        "merchandise-wholesale"
    ],
    "wof:name":"M R Distribution",
    "wof:placetype":"venue"
},
  "geometry": {"coordinates":[-118.12719300000001,33.896568],"type":"Point"}
}