{
  "type": "Feature",
  "properties": {
    "addr:full":"6185 Orchard Station Rd Sebastopol CA 95472",
    "addr:housenumber":"6185",
    "addr:postcode":"95472",
    "addr:street":"Orchard Station Rd",
    "iso:country":"US",
    "sg:address":"6185 Orchard Station Rd",
    "sg:city":"Sebastopol",
    "sg:classifiers":[
        {
            "category":"Manufacturing",
            "subcategory":"Food",
            "type":"Manufacturing & Wholesale Goods"
        },
        {
            "category":"Farming",
            "subcategory":"Farm",
            "type":"Manufacturing & Wholesale Goods"
        }
    ],
    "sg:phone":"+1 707 824 9932",
    "sg:postcode":"95472",
    "sg:province":"CA",
    "sg:tags":[
        "corn",
        "product"
    ],
    "wof:name":"Jayne Delawter",
    "wof:placetype":"venue"
},
  "geometry": {"coordinates":[-122.77385,38.329109],"type":"Point"}
}