{
  "type": "Feature",
  "properties": {
    "iso:country":"US",
    "sg:address":"2455 Fourth Ave",
    "sg:city":"San Diego",
    "sg:classifiers":[
        {
            "category":"Banks & Credit Unions",
            "subcategory":"Financial Services",
            "type":"Services"
        }
    ],
    "sg:phone":"+1 619 519 8262",
    "sg:postcode":"92101",
    "sg:province":"CA",
    "sg:tags":[
        "broker",
        "mortgage"
    ],
    "sg:website":"metrosandiegohomeloans.com",
    "wof:name":"Dominic Silvestri",
    "wof:placetype":"venue"
},
  "geometry": {"coordinates":[-117.161186,32.730926],"type":"Point"}
}