{
  "type": "Feature",
  "properties": {
    "addr:full":"7203 Balboa Blvd Van Nuys CA 91406",
    "addr:housenumber":"7203",
    "addr:postcode":"91406",
    "addr:street":"Balboa Blvd",
    "iso:country":"US",
    "sg:address":"7203 Balboa Blvd",
    "sg:city":"Van Nuys",
    "sg:classifiers":[
        {
            "category":"Health Services",
            "subcategory":"Chiropractor",
            "type":"Services"
        }
    ],
    "sg:phone":"+1 818 901 0388",
    "sg:postcode":"91406",
    "sg:province":"CA",
    "wof:name":"Family Chiropractic Clinic",
    "wof:placetype":"venue"
},
  "geometry": {"coordinates":[-118.501199,34.201238],"type":"Point"}
}