{
  "type": "Feature",
  "properties": {
    "iso:country":"US",
    "sg:address":"6335 Nancy Ridge Dr",
    "sg:city":"San Diego",
    "sg:classifiers":[
        {
            "category":"Shopping",
            "subcategory":"Computers & Home Electronics",
            "type":"Retail Goods"
        }
    ],
    "sg:phone":"+1 858 558 0867",
    "sg:postcode":"92121",
    "sg:province":"CA",
    "sg:tags":[
        "software"
    ],
    "wof:name":"Intelligent Modeler",
    "wof:placetype":"venue"
},
  "geometry": {"coordinates":[-117.187217,32.888696],"type":"Point"}
}