{
  "type": "Feature",
  "properties": {
    "addr:full":"222 N Linwood St Visalia CA 93291",
    "addr:housenumber":"222",
    "addr:postcode":"93291",
    "addr:street":"N Linwood St",
    "iso:country":"US",
    "sg:address":"222 N Linwood St",
    "sg:city":"Visalia",
    "sg:classifiers":[
        {
            "category":"Retail",
            "subcategory":"Auto Repair",
            "type":"Services"
        }
    ],
    "sg:phone":"+1 559 308 1936",
    "sg:postcode":"93291",
    "sg:province":"CA",
    "sg:tags":[
        "automobile",
        "customizing"
    ],
    "wof:name":"Shop",
    "wof:placetype":"venue"
},
  "geometry": {"coordinates":[-119.34161400000001,36.3322],"type":"Point"}
}