{
  "type": "Feature",
  "properties": {
    "iso:country":"US",
    "sg:address":"722 E Lomita Ave",
    "sg:city":"Glendale",
    "sg:classifiers":[
        {
            "category":"Utilities",
            "subcategory":"Refuse",
            "type":"Services"
        }
    ],
    "sg:phone":"+1 818 246 4711",
    "sg:postcode":"91205",
    "sg:province":"CA",
    "sg:tags":[
        "system"
    ],
    "wof:name":"Tma Recycling Center",
    "wof:placetype":"venue"
},
  "geometry": {"coordinates":[-118.245592,34.140767],"type":"Point"}
}