{
  "type": "Feature",
  "properties": {
    "iso:country":"US",
    "sg:address":"73 52nd St",
    "sg:city":"Sacramento",
    "sg:classifiers":[
        {
            "category":"Shopping",
            "subcategory":"Pets & Pet Supplies",
            "type":"Retail Goods"
        }
    ],
    "sg:phone":"+1 916 456 1935",
    "sg:postcode":"95819",
    "sg:province":"CA",
    "sg:tags":[
        "furnishing",
        "dog",
        "store",
        "cat"
    ],
    "wof:name":"East Sacramento Pet Pals",
    "wof:placetype":"venue"
},
  "geometry": {"coordinates":[-121.43634,38.575947],"type":"Point"}
}