{
  "type": "Feature",
  "properties": {
    "iso:country":"US",
    "sg:address":"3045 Solano Ave",
    "sg:city":"Napa",
    "sg:classifiers":[
        {
            "category":"Professional",
            "subcategory":"Accounting & Tax Preparation",
            "type":"Services"
        }
    ],
    "sg:phone":"+1 707 257 7960",
    "sg:postcode":"94558",
    "sg:province":"CA",
    "sg:tags":[
        "return",
        "filing"
    ],
    "wof:name":"Judith Lewis Tax Office",
    "wof:placetype":"venue"
},
  "geometry": {"coordinates":[-122.307413,38.314806],"type":"Point"}
}