{
  "type": "Feature",
  "properties": {
    "addr:full":"1701 San Pablo Ave Berkeley CA 94702",
    "addr:housenumber":"1701",
    "addr:postcode":"94702",
    "addr:street":"San Pablo Ave",
    "iso:country":"US",
    "sg:address":"1701 San Pablo Ave",
    "sg:city":"Berkeley",
    "sg:classifiers":[
        {
            "category":"Education",
            "subcategory":"School",
            "type":"Public Place"
        }
    ],
    "sg:phone":"+1 510 644 6130",
    "sg:postcode":"94702",
    "sg:province":"CA",
    "sg:website":"bas.berkeley.net",
    "wof:name":"Berkeley Adult School",
    "wof:placetype":"venue"
},
  "geometry": {"coordinates":[-122.29346,37.873417],"type":"Point"}
}