{
  "type": "Feature",
  "properties": {
    "addr:full":"522 E Main St Ventura CA 93001",
    "addr:housenumber":"522",
    "addr:postcode":"93001",
    "addr:street":"E Main St",
    "iso:country":"US",
    "sg:address":"522 E Main St",
    "sg:city":"Ventura",
    "sg:classifiers":[
        {
            "category":"Shopping",
            "subcategory":"Clothing, Apparel, & Fashions",
            "type":"Retail Goods"
        }
    ],
    "sg:phone":"+1 805 643 1313",
    "sg:postcode":"93001",
    "sg:province":"CA",
    "sg:tags":[
        "item",
        "boutique"
    ],
    "wof:name":"Heart's Delight",
    "wof:placetype":"venue"
},
  "geometry": {"coordinates":[-119.291838,34.280746],"type":"Point"}
}