{
  "type": "Feature",
  "properties": {
    "addr:full":"4064 Avalon Blvd Los Angeles CA 90011",
    "addr:housenumber":"4064",
    "addr:postcode":"90011",
    "addr:street":"Avalon Blvd",
    "iso:country":"US",
    "sg:address":"4064 Avalon Blvd",
    "sg:city":"Los Angeles",
    "sg:classifiers":[
        {
            "category":"Retail",
            "subcategory":"Auto Repair",
            "type":"Services"
        }
    ],
    "sg:phone":"+1 323 232 0244",
    "sg:postcode":"90011",
    "sg:province":"CA",
    "wof:name":"San Miguel Auto Service",
    "wof:placetype":"venue"
},
  "geometry": {"coordinates":[-118.264999,34.009998],"type":"Point"}
}