{
  "type": "Feature",
  "properties": {
    "addr:full":"9583 Foothill Blvd Rancho Cucamonga CA 91730",
    "addr:housenumber":"9583",
    "addr:postcode":"91730",
    "addr:street":"Foothill Blvd",
    "iso:country":"US",
    "sg:address":"9583 Foothill Blvd",
    "sg:city":"Rancho Cucamonga",
    "sg:classifiers":[
        {
            "category":"Wholesale",
            "subcategory":"Non-durable Goods",
            "type":"Manufacturing & Wholesale Goods"
        }
    ],
    "sg:phone":"+1 909 980 4888",
    "sg:postcode":"91730",
    "sg:province":"CA",
    "sg:tags":[
        "oriental"
    ],
    "wof:name":"Tropical Seafood & Meat Market",
    "wof:placetype":"venue"
},
  "geometry": {"coordinates":[-117.59686000000001,34.106533],"type":"Point"}
}