{
  "type": "Feature",
  "properties": {
    "addr:full":"8451 Melrose Avenue West Hollywood CA 90069",
    "addr:housenumber":"8451",
    "addr:postcode":"90069",
    "addr:street":"Melrose Avenue",
    "iso:country":"US",
    "sg:address":"8451 Melrose Avenue",
    "sg:city":"West Hollywood",
    "sg:classifiers":[
        {
            "category":"Shopping",
            "subcategory":"Antiques",
            "type":"Retail Goods"
        }
    ],
    "sg:phone":"+1 323 655 9888",
    "sg:postcode":"90069",
    "sg:province":"CA",
    "wof:name":"Art Resources",
    "wof:placetype":"venue"
},
  "geometry": {"coordinates":[-118.37509900000001,34.082511],"type":"Point"}
}