{
  "type": "Feature",
  "properties": {
    "iso:country":"US",
    "sg:address":"60 Rancho Rd",
    "sg:city":"Thousand Oaks",
    "sg:classifiers":[
        {
            "category":"Professional",
            "type":"Services"
        }
    ],
    "sg:phone":"+1 805 557 0205",
    "sg:postcode":"91362",
    "sg:province":"CA",
    "wof:name":"Ocean West Framing",
    "wof:placetype":"venue"
},
  "geometry": {"coordinates":[-118.857828,34.179054],"type":"Point"}
}