{
  "type": "Feature",
  "properties": {
    "iso:country":"US",
    "sg:address":"1885 N Tustin St",
    "sg:city":"Orange",
    "sg:classifiers":[
        {
            "category":"Wholesale",
            "subcategory":"Fruits & Vegetables",
            "type":"Manufacturing & Wholesale Goods"
        }
    ],
    "sg:phone":"+1 714 974 1830",
    "sg:postcode":"92865",
    "sg:province":"CA",
    "sg:tags":[
        "veggie"
    ],
    "wof:name":"Produce World",
    "wof:placetype":"venue"
},
  "geometry": {"coordinates":[-117.835999,33.818401],"type":"Point"}
}