{
  "type": "Feature",
  "properties": {
    "iso:country":"US",
    "sg:address":"415 N Pine St",
    "sg:city":"Nevada City",
    "sg:classifiers":[
        {
            "category":"Organizations",
            "subcategory":"Community Association",
            "type":"Services"
        }
    ],
    "sg:phone":"+1 530 265 8396",
    "sg:postcode":"95959",
    "sg:province":"CA",
    "sg:tags":[
        "military"
    ],
    "wof:name":"Veterans Of Foreign Wars",
    "wof:placetype":"venue"
},
  "geometry": {"coordinates":[-121.019637,39.264601],"type":"Point"}
}