{
  "type": "Feature",
  "properties": {
    "addr:full":"15781 Maidstone St Westminster CA 92683",
    "addr:housenumber":"15781",
    "addr:postcode":"92683",
    "addr:street":"Maidstone St",
    "iso:country":"US",
    "sg:address":"15781 Maidstone St",
    "sg:city":"Westminster",
    "sg:classifiers":[
        {
            "category":"Building & Trades",
            "subcategory":"Construction",
            "type":"Services"
        }
    ],
    "sg:phone":"+1 714 493 9041",
    "sg:postcode":"92683",
    "sg:province":"CA",
    "sg:tags":[
        "air",
        "heating",
        "conditioning/hvac"
    ],
    "wof:name":"Stephan's Refrigeration",
    "wof:placetype":"venue"
},
  "geometry": {"coordinates":[-117.950917,33.733122],"type":"Point"}
}