{
  "type": "Feature",
  "properties": {
    "iso:country":"US",
    "sg:address":"151 Callan Ave",
    "sg:city":"San Leandro",
    "sg:classifiers":[
        {
            "category":"Professional",
            "subcategory":"Accounting & Tax Preparation",
            "type":"Services"
        }
    ],
    "sg:phone":"+1 510 895 8310",
    "sg:postcode":"94577",
    "sg:province":"CA",
    "sg:tags":[
        "accountant"
    ],
    "wof:name":"Friedrich Martin G CPA",
    "wof:placetype":"venue"
},
  "geometry": {"coordinates":[-122.155114,37.726078],"type":"Point"}
}