{
  "type": "Feature",
  "properties": {
    "addr:full":"4885 Ronson Ct San Diego CA 92111",
    "addr:housenumber":"4885",
    "addr:postcode":"92111",
    "addr:street":"Ronson Ct",
    "iso:country":"US",
    "sg:address":"4885 Ronson Ct",
    "sg:city":"San Diego",
    "sg:classifiers":[
        {
            "category":"Restaurant",
            "type":"Food & Drink"
        }
    ],
    "sg:phone":"+1 858 569 0808",
    "sg:postcode":"92111",
    "sg:province":"CA",
    "sg:tags":[
        "delicatessen"
    ],
    "wof:name":"Dutch's Place",
    "wof:placetype":"venue"
},
  "geometry": {"coordinates":[-117.14588500000001,32.829408],"type":"Point"}
}