{
  "type": "Feature",
  "properties": {
    "iso:country":"US",
    "sg:address":"527 Munroe St",
    "sg:city":"Sacramento",
    "sg:classifiers":[
        {
            "category":"Personal",
            "subcategory":"Beauty Salon",
            "type":"Services"
        }
    ],
    "sg:phone":"+1 916 483 6878",
    "sg:postcode":"95825",
    "sg:province":"CA",
    "sg:tags":[
        "nail",
        "manicuring"
    ],
    "wof:name":"Ultimate Nails",
    "wof:placetype":"venue"
},
  "geometry": {"coordinates":[-121.401523,38.575142],"type":"Point"}
}