{
  "type": "Feature",
  "properties": {
    "iso:country":"US",
    "sg:address":"1477 Retherford St",
    "sg:city":"Tulare",
    "sg:classifiers":[
        {
            "category":"Shopping",
            "subcategory":"Clothing, Apparel, & Fashions",
            "type":"Retail Goods"
        }
    ],
    "sg:phone":"+1 559 688 3608",
    "sg:postcode":"93274",
    "sg:province":"CA",
    "sg:tags":[
        "designer"
    ],
    "sg:website":"www.liz.com",
    "wof:name":"Liz Claiborne Inc",
    "wof:placetype":"venue"
},
  "geometry": {"coordinates":[-119.335439,36.23123],"type":"Point"}
}