{
  "type": "Feature",
  "properties": {
    "iso:country":"US",
    "sg:address":"1408 Industrial Park Ave",
    "sg:city":"Redlands",
    "sg:classifiers":[
        {
            "category":"Retail",
            "subcategory":"Auto Rental",
            "type":"Services"
        }
    ],
    "sg:phone":"+1 909 792 8397",
    "sg:postcode":"92374",
    "sg:province":"CA",
    "sg:tags":[
        "renting",
        "automobile"
    ],
    "wof:name":"Avis Rent A Car",
    "wof:placetype":"venue"
},
  "geometry": {"coordinates":[-117.204024,34.064535],"type":"Point"}
}