{
  "type": "Feature",
  "properties": {
    "iso:country":"US",
    "sg:address":"9581 W Pico Blvd",
    "sg:city":"Los Angeles",
    "sg:classifiers":[
        {
            "category":"Education",
            "subcategory":"Special Training",
            "type":"Public Place"
        }
    ],
    "sg:phone":"+1 310 557 1711",
    "sg:postcode":"90035",
    "sg:province":"CA",
    "sg:tags":[
        "school",
        "language"
    ],
    "sg:website":"www.bhisl.com",
    "wof:name":"Beverly Hills Intl School",
    "wof:placetype":"venue"
},
  "geometry": {"coordinates":[-118.397903,34.055237],"type":"Point"}
}