{
  "type": "Feature",
  "properties": {
    "addr:full":"1339 S Winchester Blvd San Jose CA 95128",
    "addr:housenumber":"1339",
    "addr:postcode":"95128",
    "addr:street":"S Winchester Blvd",
    "iso:country":"US",
    "sg:address":"1339 S Winchester Blvd",
    "sg:city":"San Jose",
    "sg:classifiers":[
        {
            "category":"Restaurant",
            "type":"Food & Drink"
        }
    ],
    "sg:phone":"+1 408 374 1516",
    "sg:postcode":"95128",
    "sg:province":"CA",
    "wof:name":"Blimpie Subs & Salads",
    "wof:placetype":"venue"
},
  "geometry": {"coordinates":[-121.94999900000001,37.297586],"type":"Point"}
}