{
  "type": "Feature",
  "properties": {
    "iso:country":"US",
    "sg:address":"1609 Doncarol Ave",
    "sg:city":"El Cajon",
    "sg:classifiers":[
        {
            "category":"Building & Trades",
            "subcategory":"Electrical",
            "type":"Services"
        }
    ],
    "sg:phone":"+1 619 698 7565",
    "sg:postcode":"92019",
    "sg:province":"CA",
    "sg:tags":[
        "telecommunication",
        "contractor"
    ],
    "wof:name":"A Phone Man",
    "wof:placetype":"venue"
},
  "geometry": {"coordinates":[-116.923027,32.790631],"type":"Point"}
}