{
  "type": "Feature",
  "properties": {
    "addr:full":"160 W Ann St Los Angeles CA 90012",
    "addr:housenumber":"160",
    "addr:postcode":"90012",
    "addr:street":"W Ann St",
    "iso:country":"US",
    "sg:address":"160 W Ann St",
    "sg:city":"Los Angeles",
    "sg:classifiers":[
        {
            "category":"Home & Garden",
            "subcategory":"Home Furnishings",
            "type":"Retail Goods"
        }
    ],
    "sg:phone":"+1 323 225 8234",
    "sg:postcode":"90012",
    "sg:province":"CA",
    "sg:tags":[
        "bedspread"
    ],
    "wof:name":"Comphy Co",
    "wof:placetype":"venue"
},
  "geometry": {"coordinates":[-118.231725,34.065084],"type":"Point"}
}