{
  "type": "Feature",
  "properties": {
    "addr:full":"150 S Anza St El Cajon CA 92020",
    "addr:housenumber":"150",
    "addr:postcode":"92020",
    "addr:street":"S Anza St",
    "iso:country":"US",
    "sg:address":"150 S Anza St",
    "sg:city":"El Cajon",
    "sg:classifiers":[
        {
            "category":"Real Estate",
            "subcategory":"Real Estate Operator",
            "type":"Services"
        }
    ],
    "sg:phone":"+1 619 447 3543",
    "sg:postcode":"92020",
    "sg:province":"CA",
    "sg:tags":[
        "mobile",
        "home",
        "community"
    ],
    "wof:name":"Horseshoe Trailer Villas",
    "wof:placetype":"venue"
},
  "geometry": {"coordinates":[-116.948277,32.794782],"type":"Point"}
}