{
  "type": "Feature",
  "properties": {
    "addr:full":"1415 L St Ste 740 Sacramento CA 95814",
    "addr:housenumber":"1415",
    "addr:postcode":"95814",
    "addr:street":"L St Ste 740",
    "iso:country":"US",
    "sg:address":"1415 L St Ste 740",
    "sg:city":"Sacramento",
    "sg:classifiers":[
        {
            "category":"Banks & Credit Unions",
            "subcategory":"Bank",
            "type":"Services"
        }
    ],
    "sg:phone":"+1 916 321 6714",
    "sg:postcode":"95814",
    "sg:province":"CA",
    "wof:name":"Union Bank",
    "wof:placetype":"venue"
},
  "geometry": {"coordinates":[-121.488586,38.576692],"type":"Point"}
}