{
  "type": "Feature",
  "properties": {
    "addr:full":"2100 Main Street Huntington Beach CA 92648",
    "addr:housenumber":"2100",
    "addr:postcode":"92648",
    "addr:street":"Main Street",
    "iso:country":"US",
    "sg:address":"2100 Main Street",
    "sg:city":"Huntington Beach",
    "sg:classifiers":[
        {
            "category":"Professional",
            "subcategory":"Lawyer & Legal Services",
            "type":"Services"
        }
    ],
    "sg:phone":"+1 714 960 0858",
    "sg:postcode":"92648",
    "sg:province":"CA",
    "wof:name":"Sellberg Jeffrey B Atty",
    "wof:placetype":"venue"
},
  "geometry": {"coordinates":[-118.001447,33.678875],"type":"Point"}
}