{
  "type": "Feature",
  "properties": {
    "iso:country":"US",
    "sg:address":"3615 N. San Fernando Blvd",
    "sg:city":"Burbank",
    "sg:classifiers":[
        {
            "category":"Home & Garden",
            "subcategory":"Household Appliances",
            "type":"Retail Goods"
        },
        {
            "category":"Building & Trades",
            "subcategory":"Construction",
            "type":"Services"
        }
    ],
    "sg:phone":"+1 818 968 3627",
    "sg:postcode":"91505",
    "sg:province":"CA",
    "sg:tags":[
        "repair",
        "contractor"
    ],
    "sg:website":"hvaccontractorburbank.com#cid=yelp",
    "wof:name":"S&E Heating & Air",
    "wof:placetype":"venue"
},
  "geometry": {"coordinates":[-118.350677,34.206253],"type":"Point"}
}