{
  "type": "Feature",
  "properties": {
    "iso:country":"US",
    "sg:address":"2100 W Orangewood Ave Ste 210",
    "sg:city":"Orange",
    "sg:classifiers":[
        {
            "category":"Real Estate",
            "subcategory":"Real Estate Services",
            "type":"Services"
        },
        {
            "category":"Banks & Credit Unions",
            "subcategory":"Financial Services",
            "type":"Services"
        }
    ],
    "sg:phone":"+1 714 385 2286",
    "sg:postcode":"92868",
    "sg:province":"CA",
    "sg:tags":[
        "loan",
        "broker",
        "mortgage"
    ],
    "sg:website":"www.mark1mortgage.com",
    "wof:name":"Mark 1 Mortgage",
    "wof:placetype":"venue"
},
  "geometry": {"coordinates":[-117.875,33.7957],"type":"Point"}
}