{
  "type": "Feature",
  "properties": {
    "addr:full":"401 N Harbor Blvd La Habra CA 90631",
    "addr:housenumber":"401",
    "addr:postcode":"90631",
    "addr:street":"N Harbor Blvd",
    "iso:country":"US",
    "sg:address":"401 N Harbor Blvd",
    "sg:city":"La Habra",
    "sg:classifiers":[
        {
            "category":"Professional",
            "subcategory":"Accounting & Tax Preparation",
            "type":"Services"
        }
    ],
    "sg:phone":"+1 562 694 8050",
    "sg:postcode":"90631",
    "sg:province":"CA",
    "sg:tags":[
        "accountant"
    ],
    "wof:name":"Paul M Morishita CPA",
    "wof:placetype":"venue"
},
  "geometry": {"coordinates":[-117.93312299999999,33.933805],"type":"Point"}
}