{
  "type": "Feature",
  "properties": {
    "addr:full":"10122 Topanga Canyon Blvd Chatsworth CA 91311",
    "addr:housenumber":"10122",
    "addr:postcode":"91311",
    "addr:street":"Topanga Canyon Blvd",
    "iso:country":"US",
    "sg:address":"10122 Topanga Canyon Blvd",
    "sg:city":"Chatsworth",
    "sg:classifiers":[
        {
            "category":"Food & Beverages",
            "subcategory":"Farmers Market",
            "type":"Retail Goods"
        },
        {
            "category":"Farming",
            "subcategory":"Farm",
            "type":"Manufacturing & Wholesale Goods"
        }
    ],
    "sg:phone":"+1 818 886 8171",
    "sg:postcode":"91311",
    "sg:province":"CA",
    "sg:tags":[
        "vegetable",
        "fruit"
    ],
    "wof:name":"Farm Brothers",
    "wof:placetype":"venue"
},
  "geometry": {"coordinates":[-118.60606799999999,34.253977],"type":"Point"}
}