{
  "type": "Feature",
  "properties": {
    "iso:country":"US",
    "sg:address":"7475 Starward Dr",
    "sg:city":"Dublin",
    "sg:classifiers":[
        {
            "category":"Utilities",
            "subcategory":"Telephone",
            "type":"Services"
        },
        {
            "category":"Professional",
            "subcategory":"Computer Services",
            "type":"Services"
        }
    ],
    "sg:phone":"+1 925 828 0664",
    "sg:postcode":"94568",
    "sg:province":"CA",
    "sg:tags":[
        "communications",
        "internet"
    ],
    "wof:name":"Nothing But Net",
    "wof:placetype":"venue"
},
  "geometry": {"coordinates":[-121.933516,37.707963],"type":"Point"}
}