{
  "type": "Feature",
  "properties": {
    "iso:country":"US",
    "sg:address":"4773 Tyler St Suite 2H",
    "sg:city":"Riverside",
    "sg:classifiers":[
        {
            "category":"Personal",
            "subcategory":"Beauty Salon",
            "type":"Services"
        }
    ],
    "sg:phone":"+1 951 689 7926",
    "sg:postcode":"92503",
    "sg:province":"CA",
    "wof:name":"Rosa Hair Salon",
    "wof:placetype":"venue"
},
  "geometry": {"coordinates":[-117.473894,33.927617],"type":"Point"}
}