{
  "type": "Feature",
  "properties": {
    "addr:full":"30110 Crown Valley Pkwy Laguna Niguel CA 92677",
    "addr:housenumber":"30110",
    "addr:postcode":"92677",
    "addr:street":"Crown Valley Pkwy",
    "iso:country":"US",
    "sg:address":"30110 Crown Valley Pkwy",
    "sg:city":"Laguna Niguel",
    "sg:classifiers":[
        {
            "category":"Banks & Credit Unions",
            "subcategory":"Investment Brokerage",
            "type":"Services"
        }
    ],
    "sg:phone":"+1 949 249 8248",
    "sg:postcode":"92677",
    "sg:province":"CA",
    "sg:tags":[
        "security"
    ],
    "sg:website":"www.edwardjones.com",
    "wof:name":"Edward Jones Co",
    "wof:placetype":"venue"
},
  "geometry": {"coordinates":[-117.714488,33.523902],"type":"Point"}
}