{
  "type": "Feature",
  "properties": {
    "iso:country":"US",
    "sg:address":"1111 E Howell Ave",
    "sg:city":"Anaheim",
    "sg:classifiers":[
        {
            "category":"Home & Garden",
            "subcategory":"Building Materials",
            "type":"Retail Goods"
        }
    ],
    "sg:phone":"+1 714 939 2014",
    "sg:postcode":"92805",
    "sg:province":"CA",
    "sg:tags":[
        "supply"
    ],
    "wof:name":"Westside Building Material Corp",
    "wof:placetype":"venue"
},
  "geometry": {"coordinates":[-117.897003,33.806999],"type":"Point"}
}