{
  "type": "Feature",
  "properties": {
    "addr:full":"2805 Belgrave Ave Huntington Park CA 90255",
    "addr:housenumber":"2805",
    "addr:postcode":"90255",
    "addr:street":"Belgrave Ave;Park",
    "iso:country":"US",
    "sg:address":"2805 Belgrave Ave",
    "sg:city":"Huntington Park",
    "sg:classifiers":[
        {
            "category":"Organizations",
            "subcategory":"Religious Organization",
            "type":"Services"
        }
    ],
    "sg:phone":"+1 323 588 1611",
    "sg:postcode":"90255",
    "sg:province":"CA",
    "sg:tags":[
        "church"
    ],
    "wof:name":"Iberoamerica Assembly Of God",
    "wof:placetype":"venue"
},
  "geometry": {"coordinates":[-118.219373,33.987268],"type":"Point"}
}