{
  "type": "Feature",
  "properties": {
    "iso:country":"US",
    "sg:address":"118 W Hazel St",
    "sg:city":"Inglewood",
    "sg:classifiers":[
        {
            "category":"Freight",
            "type":"Transportation"
        }
    ],
    "sg:phone":"+1 310 672 8887",
    "sg:postcode":"90302",
    "sg:province":"CA",
    "sg:tags":[
        "arrangement"
    ],
    "wof:name":"Dimex Consulting",
    "wof:placetype":"venue"
},
  "geometry": {"coordinates":[-118.356766,33.967765],"type":"Point"}
}