{
  "type": "Feature",
  "properties": {
    "addr:full":"5522 West Pico Blvd Los Angeles CA 90019",
    "addr:housenumber":"5522",
    "addr:postcode":"90019",
    "addr:street":"West Pico Blvd",
    "iso:country":"US",
    "sg:address":"5522 West Pico Blvd",
    "sg:city":"Los Angeles",
    "sg:classifiers":[
        {
            "category":"Organizations",
            "subcategory":"Non-profit Organization",
            "type":"Services"
        }
    ],
    "sg:phone":"+1 323 933 2229",
    "sg:postcode":"90019",
    "sg:province":"CA",
    "sg:tags":[
        "service/non-profit",
        "community"
    ],
    "sg:website":"www.baby2baby.org/",
    "wof:name":"Baby2Baby",
    "wof:placetype":"venue"
},
  "geometry": {"coordinates":[-118.35869099999999,34.049341],"type":"Point"}
}