{
  "type": "Feature",
  "properties": {
    "iso:country":"US",
    "sg:address":"2350 Buhne St",
    "sg:city":"Eureka",
    "sg:classifiers":[
        {
            "category":"Health Services",
            "subcategory":"Doctor",
            "type":"Services"
        }
    ],
    "sg:phone":"+1 707 443 4593",
    "sg:postcode":"95501",
    "sg:province":"CA",
    "sg:tags":[
        "physician",
        "surgeon"
    ],
    "sg:website":"www.redmed.com",
    "wof:name":"Redwood Family Practice",
    "wof:placetype":"venue"
},
  "geometry": {"coordinates":[-124.143241,40.785856],"type":"Point"}
}