{
  "type": "Feature",
  "properties": {
    "iso:country":"US",
    "sg:address":"3090 Bristol St Ste 160",
    "sg:city":"Costa Mesa",
    "sg:classifiers":[
        {
            "category":"Building & Trades",
            "subcategory":"Construction",
            "type":"Services"
        }
    ],
    "sg:phone":"+1 714 708 7500",
    "sg:postcode":"92626",
    "sg:province":"CA",
    "sg:tags":[
        "interior",
        "design"
    ],
    "wof:name":"Triomphe Design",
    "wof:placetype":"venue"
},
  "geometry": {"coordinates":[-117.885323,33.685493],"type":"Point"}
}