{
  "type": "Feature",
  "properties": {
    "iso:country":"US",
    "sg:address":"15816 Amar Rd",
    "sg:city":"City Of Industry",
    "sg:classifiers":[
        {
            "category":"Retail",
            "subcategory":"Repair Shop",
            "type":"Services"
        }
    ],
    "sg:phone":"+1 626 968 5551",
    "sg:postcode":"91744",
    "sg:province":"CA",
    "sg:tags":[
        "scooter",
        "motorcycle",
        "motor"
    ],
    "wof:name":"Cycle Barn",
    "wof:placetype":"venue"
},
  "geometry": {"coordinates":[-117.938438,34.036304],"type":"Point"}
}