{
  "type": "Feature",
  "properties": {
    "iso:country":"US",
    "sg:address":"8410 Fruitland Ave",
    "sg:city":"Winton",
    "sg:classifiers":[
        {
            "category":"Farming",
            "subcategory":"Farm",
            "type":"Manufacturing & Wholesale Goods"
        }
    ],
    "sg:phone":"+1 209 358 4927",
    "sg:postcode":"95388",
    "sg:province":"CA",
    "sg:tags":[
        "crop",
        "general"
    ],
    "wof:name":"Arnold Farms",
    "wof:placetype":"venue"
},
  "geometry": {"coordinates":[-120.63504500000001,37.367651],"type":"Point"}
}