{
  "type": "Feature",
  "properties": {
    "iso:country":"US",
    "sg:address":"9621 Mission Gorge Rd",
    "sg:city":"Santee",
    "sg:classifiers":[
        {
            "category":"Shopping",
            "subcategory":"Jewelry",
            "type":"Retail Goods"
        }
    ],
    "sg:phone":"+1 619 562 8004",
    "sg:postcode":"92071",
    "sg:province":"CA",
    "wof:name":"Michael's Jewelers",
    "wof:placetype":"venue"
},
  "geometry": {"coordinates":[-116.987999,32.838699],"type":"Point"}
}