{
  "type": "Feature",
  "properties": {
    "addr:full":"1977 N Grand Ave Sierra Vista AZ 85635",
    "addr:housenumber":"1977",
    "addr:postcode":"85635",
    "addr:street":"N Grand Ave",
    "iso:country":"US",
    "sg:address":"1977 N Grand Ave",
    "sg:city":"Sierra Vista",
    "sg:classifiers":[
        {
            "category":"Building & Trades",
            "subcategory":"Locksmith",
            "type":"Services"
        }
    ],
    "sg:phone":"+1 866 236 7115",
    "sg:postcode":"85635",
    "sg:province":"AZ",
    "sg:tags":[
        "key"
    ],
    "wof:name":"A 1 Emergency Locksmith",
    "wof:placetype":"venue"
},
  "geometry": {"coordinates":[-118.144801,34.096311],"type":"Point"}
}