{
  "type": "Feature",
  "properties": {
    "addr:full":"3455 Homestead Rd Santa Clara CA 95051",
    "addr:housenumber":"3455",
    "addr:postcode":"95051",
    "addr:street":"Homestead Rd",
    "iso:country":"US",
    "sg:address":"3455 Homestead Rd",
    "sg:city":"Santa Clara",
    "sg:classifiers":[
        {
            "category":"Real Estate",
            "subcategory":"Real Estate Operator",
            "type":"Services"
        }
    ],
    "sg:phone":"+1 408 243 3898",
    "sg:postcode":"95051",
    "sg:province":"CA",
    "sg:tags":[
        "apartment"
    ],
    "wof:name":"Vista Point Apartments",
    "wof:placetype":"venue"
},
  "geometry": {"coordinates":[-121.991997,37.337898],"type":"Point"}
}