{
  "type": "Feature",
  "properties": {
    "iso:country":"US",
    "sg:address":"3924 W Rosecrans Ave",
    "sg:city":"Hawthorne",
    "sg:classifiers":[
        {
            "category":"Personal",
            "subcategory":"Beauty Salon",
            "type":"Services"
        }
    ],
    "sg:phone":"+1 310 644 7786",
    "sg:postcode":"90250",
    "sg:province":"CA",
    "wof:name":"Solomon's",
    "wof:placetype":"venue"
},
  "geometry": {"coordinates":[-118.343326,33.901847],"type":"Point"}
}