{
  "type": "Feature",
  "properties": {
    "iso:country":"US",
    "sg:address":"642 Martin Ave",
    "sg:city":"Rohnert Park",
    "sg:classifiers":[
        {
            "category":"Wholesale",
            "subcategory":"Vending Machines",
            "type":"Manufacturing & Wholesale Goods"
        }
    ],
    "sg:phone":"+1 707 584 9119",
    "sg:postcode":"94928",
    "sg:province":"CA",
    "sg:website":"www.tdrowe.com",
    "wof:name":"T D Rowe Corp",
    "wof:placetype":"venue"
},
  "geometry": {"coordinates":[-122.724047,38.351841],"type":"Point"}
}