{
  "type": "Feature",
  "properties": {
    "iso:country":"US",
    "sg:address":"2501 S El Camino Real",
    "sg:city":"San Mateo",
    "sg:classifiers":[
        {
            "category":"Restaurant",
            "type":"Food & Drink"
        }
    ],
    "sg:menulink":"http://www.allmenus.com/ca/san-mateo/163912-togos-eatery/menu/",
    "sg:phone":"+1 650 570 7741",
    "sg:postcode":"94403",
    "sg:province":"CA",
    "sg:tags":[
        "wrap",
        "american",
        "sandwich"
    ],
    "wof:name":"Togo's Eatery",
    "wof:placetype":"venue"
},
  "geometry": {"coordinates":[-122.305615,37.544506],"type":"Point"}
}