{
  "type": "Feature",
  "properties": {
    "iso:country":"US",
    "sg:address":"6300 Garfield Ave Ste 150",
    "sg:city":"Sacramento",
    "sg:classifiers":[
        {
            "category":"Health Services",
            "subcategory":"Dentist",
            "type":"Services"
        }
    ],
    "sg:phone":"+1 916 344 1000",
    "sg:postcode":"95841",
    "sg:province":"CA",
    "sg:tags":[
        "orthodontist",
        "pediatric"
    ],
    "sg:website":"www.kidscaredentalgroup.com",
    "wof:name":"Kids Care Dental Group",
    "wof:placetype":"venue"
},
  "geometry": {"coordinates":[-121.333943,38.67978],"type":"Point"}
}