{
  "type": "Feature",
  "properties": {
    "addr:full":"660 4th St #409 San Francisco CA 94107",
    "addr:housenumber":"660",
    "addr:postcode":"94107",
    "addr:street":"4Th St # 409",
    "iso:country":"US",
    "sg:address":"660 4th St #409",
    "sg:city":"San Francisco",
    "sg:classifiers":[
        {
            "category":"Real Estate",
            "subcategory":"Real Estate Services",
            "type":"Services"
        }
    ],
    "sg:phone":"+1 415 517 7440",
    "sg:postcode":"94107",
    "sg:province":"CA",
    "sg:website":"www.BayShellRealty.com",
    "wof:name":"Roya Behjan",
    "wof:placetype":"venue"
},
  "geometry": {"coordinates":[-122.395606,37.777455],"type":"Point"}
}