{
  "type": "Feature",
  "properties": {
    "addr:full":"5900 Wilshire Blvd Los Angeles CA 90036",
    "addr:housenumber":"5900",
    "addr:postcode":"90036",
    "addr:street":"Wilshire Blvd",
    "iso:country":"US",
    "sg:address":"5900 Wilshire Blvd",
    "sg:city":"Los Angeles",
    "sg:classifiers":[
        {
            "category":"Communications",
            "subcategory":"Newspaper",
            "type":"Services"
        }
    ],
    "sg:phone":"+1 323 801 0100",
    "sg:postcode":"90036",
    "sg:province":"CA",
    "sg:tags":[
        "magazine"
    ],
    "wof:name":"Los Angeles Magazine",
    "wof:placetype":"venue"
},
  "geometry": {"coordinates":[-118.358002,34.0625],"type":"Point"}
}