{
  "type": "Feature",
  "properties": {
    "iso:country":"US",
    "sg:address":"3709 W 190th St",
    "sg:city":"Torrance",
    "sg:classifiers":[
        {
            "category":"Food & Beverages",
            "subcategory":"Liquor & Beverages",
            "type":"Retail Goods"
        }
    ],
    "sg:phone":"+1 310 323 1697",
    "sg:postcode":"90504",
    "sg:province":"CA",
    "sg:tags":[
        "beer",
        "spirit",
        "wine"
    ],
    "wof:name":"A B C Liquors",
    "wof:placetype":"venue"
},
  "geometry": {"coordinates":[-118.336998,33.8582],"type":"Point"}
}