{
  "type": "Feature",
  "properties": {
    "addr:full":"614 S Buena Vista St Hemet CA 92543",
    "addr:housenumber":"614",
    "addr:postcode":"92543",
    "addr:street":"S Buena Vista St",
    "iso:country":"US",
    "sg:address":"614 S Buena Vista St",
    "sg:city":"Hemet",
    "sg:classifiers":[
        {
            "category":"Retail",
            "subcategory":"Laundry & Dry Cleaning",
            "type":"Services"
        }
    ],
    "sg:phone":"+1 951 925 3113",
    "sg:postcode":"92543",
    "sg:province":"CA",
    "sg:tags":[
        "cleaner",
        "rug",
        "carpet"
    ],
    "wof:name":"Milton Carpet And Upholstery Cleaning",
    "wof:placetype":"venue"
},
  "geometry": {"coordinates":[-116.967258,33.738213],"type":"Point"}
}