{
  "type": "Feature",
  "properties": {
    "addr:full":"1210 Wible Rd Bakersfield CA 93304",
    "addr:housenumber":"1210",
    "addr:postcode":"93304",
    "addr:street":"Wible Rd",
    "iso:country":"US",
    "sg:address":"1210 Wible Rd",
    "sg:city":"Bakersfield",
    "sg:classifiers":[
        {
            "category":"Shopping",
            "subcategory":"Clothing, Apparel, & Fashions",
            "type":"Retail Goods"
        }
    ],
    "sg:phone":"+1 661 831 5400",
    "sg:postcode":"93304",
    "sg:province":"CA",
    "sg:tags":[
        "shop",
        "bridal"
    ],
    "wof:name":"David's Bridal",
    "wof:placetype":"venue"
},
  "geometry": {"coordinates":[-119.038882,35.341173],"type":"Point"}
}