{
  "type": "Feature",
  "properties": {
    "addr:full":"595 Price Ave Redwood City CA 94063",
    "addr:housenumber":"595",
    "addr:postcode":"94063",
    "addr:street":"Price Ave",
    "iso:country":"US",
    "sg:address":"595 Price Ave",
    "sg:city":"Redwood City",
    "sg:classifiers":[
        {
            "category":"Professional",
            "type":"Services"
        }
    ],
    "sg:phone":"+1 650 678 9769",
    "sg:postcode":"94063",
    "sg:province":"CA",
    "wof:name":"Talking Playhouse",
    "wof:placetype":"venue"
},
  "geometry": {"coordinates":[-122.231004,37.493351],"type":"Point"}
}