{
  "type": "Feature",
  "properties": {
    "addr:full":"400 Capitol Mall Ste 3000 Sacramento CA 95814",
    "addr:housenumber":"400",
    "addr:postcode":"95814",
    "addr:street":"Capitol Mall Ste 3000",
    "iso:country":"US",
    "sg:address":"400 Capitol Mall Ste 3000",
    "sg:city":"Sacramento",
    "sg:classifiers":[
        {
            "category":"Structure",
            "subcategory":"Office Building",
            "type":"Public Place"
        }
    ],
    "sg:phone":"+1 916 446 4469",
    "sg:postcode":"95814",
    "sg:province":"CA",
    "sg:tags":[
        "park"
    ],
    "wof:name":"Diepenbrock Harrison",
    "wof:placetype":"venue"
},
  "geometry": {"coordinates":[-121.502922,38.579029],"type":"Point"}
}