{
  "type": "Feature",
  "properties": {
    "addr:full":"359 Main St Trinidad CA 95570",
    "addr:housenumber":"359",
    "addr:postcode":"95570",
    "addr:street":"Main St",
    "iso:country":"US",
    "sg:address":"359 Main St",
    "sg:city":"Trinidad",
    "sg:classifiers":[
        {
            "category":"Personal",
            "subcategory":"Beauty Salon",
            "type":"Services"
        }
    ],
    "sg:phone":"+1 707 677 0357",
    "sg:postcode":"95570",
    "sg:province":"CA",
    "wof:name":"Sandcastle Hair Gallery",
    "wof:placetype":"venue"
},
  "geometry": {"coordinates":[-124.142571,41.060985],"type":"Point"}
}