{
  "type": "Feature",
  "properties": {
    "addr:full":"12411 Euclid St Ste A Garden Grove CA 92840",
    "addr:housenumber":"12411",
    "addr:postcode":"92840",
    "addr:street":"Euclid St Ste A",
    "iso:country":"US",
    "sg:address":"12411 Euclid St Ste A",
    "sg:city":"Garden Grove",
    "sg:classifiers":[
        {
            "category":"Health Services",
            "subcategory":"Clinic",
            "type":"Services"
        }
    ],
    "sg:phone":"+1 714 390 2039",
    "sg:postcode":"92840",
    "sg:province":"CA",
    "sg:tags":[
        "medical"
    ],
    "sg:website":"www.loveatfirstsight4d.com/",
    "wof:name":"Love at First Sight",
    "wof:placetype":"venue"
},
  "geometry": {"coordinates":[-117.94147,33.782388],"type":"Point"}
}