{
  "type": "Feature",
  "properties": {
    "iso:country":"US",
    "sg:address":"479 N McKinley St",
    "sg:city":"Corona",
    "sg:classifiers":[
        {
            "category":"Banks & Credit Unions",
            "subcategory":"Bank",
            "type":"Services"
        }
    ],
    "sg:phone":"+1 951 372 2990",
    "sg:postcode":"92879",
    "sg:province":"CA",
    "sg:tags":[
        "loan"
    ],
    "wof:name":"Banco Popular",
    "wof:placetype":"venue"
},
  "geometry": {"coordinates":[-117.52054,33.88972],"type":"Point"}
}