{
  "type": "Feature",
  "properties": {
    "addr:full":"10528 Pioneer Blvd Santa Fe Springs CA 90670",
    "addr:housenumber":"10528",
    "addr:postcode":"90670",
    "addr:street":"Pioneer Blvd",
    "iso:country":"US",
    "sg:address":"10528 Pioneer Blvd",
    "sg:city":"Santa Fe Springs",
    "sg:classifiers":[
        {
            "category":"Retail",
            "subcategory":"Auto Repair",
            "type":"Services"
        }
    ],
    "sg:phone":"+1 562 946 7733",
    "sg:postcode":"90670",
    "sg:province":"CA",
    "wof:name":"Digital Audio",
    "wof:placetype":"venue"
},
  "geometry": {"coordinates":[-118.16047,33.938522],"type":"Point"}
}