{
  "type": "Feature",
  "properties": {
    "iso:country":"US",
    "sg:address":"461 Valencia St",
    "sg:city":"San Francisco",
    "sg:classifiers":[
        {
            "category":"Shopping",
            "subcategory":"Bicycles & Sporting Goods",
            "type":"Retail Goods"
        }
    ],
    "sg:phone":"+1 415 552 8300",
    "sg:postcode":"94103",
    "sg:province":"CA",
    "sg:tags":[
        "equipment",
        "golf",
        "supply"
    ],
    "wof:name":"Mission Lights",
    "wof:placetype":"venue"
},
  "geometry": {"coordinates":[-122.42182,37.765032],"type":"Point"}
}