{
  "type": "Feature",
  "properties": {
    "iso:country":"US",
    "sg:address":"1505 11th St",
    "sg:city":"Santa Monica",
    "sg:classifiers":[
        {
            "category":"Communications",
            "subcategory":"Film & Video Production",
            "type":"Services"
        }
    ],
    "sg:phone":"+1 310 451 0333",
    "sg:postcode":"90401",
    "sg:province":"CA",
    "sg:tags":[
        "taping"
    ],
    "sg:website":"www.santamonicavideo.com",
    "wof:name":"Santa Monica Video",
    "wof:placetype":"venue"
},
  "geometry": {"coordinates":[-118.485412,34.019247],"type":"Point"}
}