{
  "type": "Feature",
  "properties": {
    "iso:country":"US",
    "sg:address":"1914 Spring St",
    "sg:city":"Redwood City",
    "sg:classifiers":[
        {
            "category":"Building & Trades",
            "subcategory":"Landscaping Services",
            "type":"Services"
        }
    ],
    "sg:phone":"+1 650 367 4900",
    "sg:postcode":"94063",
    "sg:province":"CA",
    "sg:tags":[
        "tree"
    ],
    "wof:name":"Econo Tree Svc Inc",
    "wof:placetype":"venue"
},
  "geometry": {"coordinates":[-122.215179,37.483751],"type":"Point"}
}