{
  "type": "Feature",
  "properties": {
    "addr:full":"6711 S Sherbourne Dr Los Angeles CA 90056",
    "addr:housenumber":"6711",
    "addr:postcode":"90056",
    "addr:street":"S Sherbourne Dr",
    "iso:country":"US",
    "sg:address":"6711 S Sherbourne Dr",
    "sg:city":"Los Angeles",
    "sg:classifiers":[
        {
            "category":"Professional",
            "type":"Services"
        }
    ],
    "sg:phone":"+1 310 645 9506",
    "sg:postcode":"90056",
    "sg:province":"CA",
    "wof:name":"Cdrom On Line Inc",
    "wof:placetype":"venue"
},
  "geometry": {"coordinates":[-118.380549,33.97916],"type":"Point"}
}