{
  "type": "Feature",
  "properties": {
    "iso:country":"US",
    "sg:address":"7252 N Lake Blvd",
    "sg:city":"Tahoe Vista",
    "sg:classifiers":[
        {
            "category":"Real Estate",
            "subcategory":"Architect",
            "type":"Services"
        }
    ],
    "sg:phone":"+1 530 546 3126",
    "sg:postcode":"96148",
    "sg:province":"CA",
    "sg:tags":[
        "home",
        "planning",
        "design"
    ],
    "wof:name":"Munsterman Group",
    "wof:placetype":"venue"
},
  "geometry": {"coordinates":[-120.042108,39.23853],"type":"Point"}
}