{
  "type": "Feature",
  "properties": {
    "addr:full":"73338 Hwy 111 Palm Desert CA 92260",
    "addr:housenumber":"73338",
    "addr:postcode":"ca 92260",
    "addr:street":"Hwy 111",
    "iso:country":"US",
    "sg:address":"73338 Hwy 111",
    "sg:city":"Palm Desert",
    "sg:classifiers":[
        {
            "category":"Personal",
            "type":"Services"
        },
        {
            "category":"Professional",
            "subcategory":"Management & Consulting",
            "type":"Services"
        }
    ],
    "sg:phone":"+1 760 674 1675",
    "sg:postcode":"92260",
    "sg:province":"CA",
    "sg:tags":[
        "party",
        "planning"
    ],
    "wof:name":"Little Tea Spot A",
    "wof:placetype":"venue"
},
  "geometry": {"coordinates":[-116.38421700000001,33.721463],"type":"Point"}
}