{
  "type": "Feature",
  "properties": {
    "iso:country":"US",
    "sg:address":"470 Chadbourne Rd",
    "sg:city":"Fairfield",
    "sg:classifiers":[
        {
            "category":"Government",
            "subcategory":"Office",
            "type":"Public Place"
        }
    ],
    "sg:phone":"+1 707 438 1773",
    "sg:postcode":"94534",
    "sg:province":"CA",
    "sg:tags":[
        "county",
        "program",
        "health"
    ],
    "wof:name":"Solano County Health & Social",
    "wof:placetype":"venue"
},
  "geometry": {"coordinates":[-122.083732,38.233779],"type":"Point"}
}