{
  "type": "Feature",
  "properties": {
    "addr:full":"1849 E Gibson Rd Woodland CA 95776",
    "addr:housenumber":"1849",
    "addr:postcode":"95776",
    "addr:street":"E Gibson Rd",
    "iso:country":"US",
    "sg:address":"1849 E Gibson Rd",
    "sg:city":"Woodland",
    "sg:classifiers":[
        {
            "category":"Restaurant",
            "type":"Food & Drink"
        },
        {
            "category":"Food & Beverages",
            "subcategory":"Groceries & Convenience Stores",
            "type":"Retail Goods"
        }
    ],
    "sg:phone":"+1 530 662 2490",
    "sg:postcode":"95776",
    "sg:province":"CA",
    "sg:tags":[
        "american",
        "latin",
        "mexican"
    ],
    "wof:name":"Iguana's Mexican Grill",
    "wof:placetype":"venue"
},
  "geometry": {"coordinates":[-121.741052,38.6628],"type":"Point"}
}