{
  "type": "Feature",
  "properties": {
    "iso:country":"US",
    "sg:address":"12118 Bloomfield Ave",
    "sg:city":"Santa Fe Springs",
    "sg:classifiers":[
        {
            "category":"Building & Trades",
            "subcategory":"Construction",
            "type":"Services"
        }
    ],
    "sg:phone":"+1 562 462 0004",
    "sg:postcode":"90670",
    "sg:province":"CA",
    "sg:tags":[
        "contractor"
    ],
    "wof:name":"Safeguard Fencing",
    "wof:placetype":"venue"
},
  "geometry": {"coordinates":[-118.063918,33.921586],"type":"Point"}
}