{
  "type": "Feature",
  "properties": {
    "iso:country":"US",
    "sg:address":"79 Shorebreaker Dr",
    "sg:city":"Laguna Niguel",
    "sg:classifiers":[
        {
            "category":"Manufacturing",
            "subcategory":"Printing",
            "type":"Manufacturing & Wholesale Goods"
        }
    ],
    "sg:phone":"+1 949 240 6172",
    "sg:postcode":"92677",
    "sg:province":"CA",
    "sg:tags":[
        "publisher",
        "software"
    ],
    "wof:name":"Eroket Com",
    "wof:placetype":"venue"
},
  "geometry": {"coordinates":[-117.699449,33.4944],"type":"Point"}
}