{
  "type": "Feature",
  "properties": {
    "addr:full":"1003 E Bellevue Rd Atwater CA 95301",
    "addr:housenumber":"1003",
    "addr:postcode":"95301",
    "addr:street":"E Bellevue Rd",
    "iso:country":"US",
    "sg:address":"1003 E Bellevue Rd",
    "sg:city":"Atwater",
    "sg:classifiers":[
        {
            "category":"Real Estate",
            "subcategory":"Real Estate Operator",
            "type":"Services"
        }
    ],
    "sg:phone":"+1 209 356 0476",
    "sg:postcode":"95301",
    "sg:province":"CA",
    "sg:tags":[
        "apartment"
    ],
    "wof:name":"Maxwell Enterprises",
    "wof:placetype":"venue"
},
  "geometry": {"coordinates":[-120.58711700000001,37.360489],"type":"Point"}
}