{
  "type": "Feature",
  "properties": {
    "iso:country":"US",
    "sg:address":"11140 Fair Oaks Boulevard",
    "sg:city":"Fair Oaks",
    "sg:classifiers":[
        {
            "category":"Professional",
            "subcategory":"Lawyer & Legal Services",
            "type":"Services"
        }
    ],
    "sg:phone":"+1 916 859 4910",
    "sg:postcode":"95628",
    "sg:province":"CA",
    "wof:name":"Brown and Associates Plc",
    "wof:placetype":"venue"
},
  "geometry": {"coordinates":[-121.264258,38.654433],"type":"Point"}
}