{
  "type": "Feature",
  "properties": {
    "iso:country":"US",
    "sg:address":"148 E Younger Ave",
    "sg:city":"San Jose",
    "sg:classifiers":[
        {
            "category":"Personal",
            "subcategory":"Beauty Salon",
            "type":"Services"
        }
    ],
    "sg:phone":"+1 408 293 9094",
    "sg:postcode":"95112",
    "sg:province":"CA",
    "wof:name":"Beaute Den",
    "wof:placetype":"venue"
},
  "geometry": {"coordinates":[-121.902603,37.356148],"type":"Point"}
}