{
  "type": "Feature",
  "properties": {
    "addr:full":"112 E 4th St Santa Ana CA 92701",
    "addr:housenumber":"112",
    "addr:postcode":"92701",
    "addr:street":"E 4Th St",
    "iso:country":"US",
    "sg:address":"112 E 4th St",
    "sg:city":"Santa Ana",
    "sg:classifiers":[
        {
            "category":"Shopping",
            "subcategory":"Shoes",
            "type":"Retail Goods"
        }
    ],
    "sg:phone":"+1 714 542 4483",
    "sg:postcode":"92701",
    "sg:province":"CA",
    "sg:tags":[
        "store"
    ],
    "wof:name":"La Zapateria Mexico",
    "wof:placetype":"venue"
},
  "geometry": {"coordinates":[-117.86747699999999,33.74786],"type":"Point"}
}