{
  "type": "Feature",
  "properties": {
    "iso:country":"US",
    "sg:address":"10222 San Diego Mission Rd",
    "sg:city":"San Diego",
    "sg:classifiers":[
        {
            "category":"Home & Garden",
            "subcategory":"Building Materials",
            "type":"Retail Goods"
        }
    ],
    "sg:phone":"+1 619 516 5267",
    "sg:postcode":"92108",
    "sg:province":"CA",
    "wof:name":"San Diego Habitat For Humanity",
    "wof:placetype":"venue"
},
  "geometry": {"coordinates":[-117.11280499999999,32.785769],"type":"Point"}
}