{
  "type": "Feature",
  "properties": {
    "addr:full":"850 G St Arcata CA 95521",
    "addr:housenumber":"850",
    "addr:postcode":"95521",
    "addr:street":"G St",
    "iso:country":"US",
    "sg:address":"850 G St",
    "sg:city":"Arcata",
    "sg:classifiers":[
        {
            "category":"Professional",
            "subcategory":"Research",
            "type":"Services"
        }
    ],
    "sg:phone":"+1 707 822 9607",
    "sg:postcode":"95521",
    "sg:province":"CA",
    "sg:tags":[
        "environmental",
        "ecological"
    ],
    "wof:name":"Stillwater Ecosystem Watershed",
    "wof:placetype":"venue"
},
  "geometry": {"coordinates":[-124.085809,40.868371],"type":"Point"}
}