{
  "type": "Feature",
  "properties": {
    "iso:country":"US",
    "sg:address":"660 Dennett St",
    "sg:city":"Pacific Grove",
    "sg:classifiers":[
        {
            "category":"Travel",
            "subcategory":"Hotels & Motels",
            "type":"Entertainment"
        }
    ],
    "sg:phone":"+1 831 373 8777",
    "sg:postcode":"93950",
    "sg:province":"CA",
    "sg:tags":[
        "operation"
    ],
    "sg:website":"www.hojomonterey.com",
    "wof:name":"Howard Johnson",
    "wof:placetype":"venue"
},
  "geometry": {"coordinates":[-121.933706,36.619544],"type":"Point"}
}