{
  "type": "Feature",
  "properties": {
    "iso:country":"US",
    "sg:address":"525 N Brand Blvd",
    "sg:city":"Glendale",
    "sg:classifiers":[
        {
            "category":"Real Estate",
            "subcategory":"Real Estate Services",
            "type":"Services"
        }
    ],
    "sg:phone":"+1 818 291 9145",
    "sg:postcode":"91203",
    "sg:province":"CA",
    "wof:name":"Stewart Title of California",
    "wof:placetype":"venue"
},
  "geometry": {"coordinates":[-118.254997,34.1534],"type":"Point"}
}