{
  "type": "Feature",
  "properties": {
    "iso:country":"US",
    "sg:address":"Westfield Mall 865 Market St",
    "sg:city":"San Francisco",
    "sg:classifiers":[
        {
            "category":"Shopping",
            "subcategory":"Beauty & Cosmetics",
            "type":"Retail Goods"
        }
    ],
    "sg:postcode":"94199",
    "sg:province":"CA",
    "sg:tags":[
        "supply"
    ],
    "sg:website":"www.premierdeadsea.com",
    "wof:name":"Dead Sea Premier Kiosk",
    "wof:placetype":"venue"
},
  "geometry": {"coordinates":[-122.407285,37.784634],"type":"Point"}
}