{
  "type": "Feature",
  "properties": {
    "iso:country":"US",
    "sg:address":"30381 Benecia Ave",
    "sg:city":"Laguna Niguel",
    "sg:classifiers":[
        {
            "category":"Real Estate",
            "subcategory":"Architect",
            "type":"Services"
        }
    ],
    "sg:phone":"+1 949 363 1622",
    "sg:postcode":"92677",
    "sg:province":"CA",
    "wof:name":"Michael Martin Architect",
    "wof:placetype":"venue"
},
  "geometry": {"coordinates":[-117.712111,33.521985],"type":"Point"}
}