{
  "type": "Feature",
  "properties": {
    "iso:country":"US",
    "sg:address":"6295 Leland Wy",
    "sg:city":"Los Angeles",
    "sg:classifiers":[
        {
            "category":"Wholesale",
            "subcategory":"Computers",
            "type":"Manufacturing & Wholesale Goods"
        }
    ],
    "sg:phone":"+1 216 365 8320",
    "sg:postcode":"90028",
    "sg:province":"CA",
    "wof:name":"Magic Data Recovery",
    "wof:placetype":"venue"
},
  "geometry": {"coordinates":[-118.326572,34.097069],"type":"Point"}
}