{
  "type": "Feature",
  "properties": {
    "iso:country":"US",
    "sg:address":"12280 Saratoga Sunnyvale R",
    "sg:city":"Saratoga",
    "sg:classifiers":[
        {
            "category":"Building & Trades",
            "subcategory":"Construction",
            "type":"Services"
        }
    ],
    "sg:phone":"+1 408 252 3615",
    "sg:postcode":"95070",
    "sg:province":"CA",
    "sg:tags":[
        "contractor"
    ],
    "wof:name":"Kosich Construction Company.",
    "wof:placetype":"venue"
},
  "geometry": {"coordinates":[-122.03227800000001,37.289757],"type":"Point"}
}