{
  "type": "Feature",
  "properties": {
    "addr:full":"3900 Sylvan Ave Modesto CA 95355",
    "addr:housenumber":"3900",
    "addr:postcode":"ca 95355",
    "addr:street":"Sylvan Ave",
    "iso:country":"US",
    "sg:address":"3900 Sylvan Ave",
    "sg:city":"Modesto",
    "sg:classifiers":[
        {
            "category":"Recreation",
            "subcategory":"Dog Park",
            "type":"Entertainment"
        },
        {
            "category":"Animal Shelter",
            "type":"Public Place"
        },
        {
            "category":"Retail",
            "subcategory":"Pet Boarding",
            "type":"Services"
        }
    ],
    "sg:phone":"+1 209 551 5070",
    "sg:postcode":"95355",
    "sg:province":"CA",
    "sg:tags":[
        "care",
        "day",
        "kennel"
    ],
    "wof:name":"Country View Kennels",
    "wof:placetype":"venue"
},
  "geometry": {"coordinates":[-120.923563,37.689064],"type":"Point"}
}