{
  "type": "Feature",
  "properties": {
    "iso:country":"US",
    "sg:address":"4225 Oceanside Blvd",
    "sg:city":"Oceanside",
    "sg:classifiers":[
        {
            "category":"Recreation",
            "type":"Entertainment"
        }
    ],
    "sg:phone":"+1 760 805 4621",
    "sg:postcode":"92056",
    "sg:province":"CA",
    "sg:tags":[
        "amusement"
    ],
    "wof:name":"Just 4 Fun Athletic Camps",
    "wof:placetype":"venue"
},
  "geometry": {"coordinates":[-117.283112,33.207702],"type":"Point"}
}