{
  "type": "Feature",
  "properties": {
    "iso:country":"US",
    "sg:address":"927 W Esplanade Ave",
    "sg:city":"San Jacinto",
    "sg:classifiers":[
        {
            "category":"Recreation",
            "type":"Entertainment"
        }
    ],
    "sg:phone":"+1 951 654 2820",
    "sg:postcode":"92582",
    "sg:province":"CA",
    "sg:tags":[
        "range",
        "baseball",
        "batting"
    ],
    "wof:name":"Batting Box",
    "wof:placetype":"venue"
},
  "geometry": {"coordinates":[-116.976512,33.772997],"type":"Point"}
}