{
  "type": "Feature",
  "properties": {
    "addr:full":"1438 Hawthorne Ter Berkeley CA 94708",
    "addr:housenumber":"1438",
    "addr:postcode":"94708",
    "addr:street":"Hawthorne Ter",
    "iso:country":"US",
    "sg:address":"1438 Hawthorne Ter",
    "sg:city":"Berkeley",
    "sg:classifiers":[
        {
            "category":"Organizations",
            "subcategory":"Non-profit Organization",
            "type":"Services"
        }
    ],
    "sg:phone":"+1 510 841 8326",
    "sg:postcode":"94708",
    "sg:province":"CA",
    "sg:tags":[
        "charity",
        "foundations-educational",
        "philanthropic",
        "research"
    ],
    "wof:name":"Ellis-Leland Family Foundation",
    "wof:placetype":"venue"
},
  "geometry": {"coordinates":[-122.262423,37.88249],"type":"Point"}
}