{
  "type": "Feature",
  "properties": {
    "addr:full":"5556 S.Centinela Avenue Los Angeles CA 90066",
    "addr:housenumber":"5556",
    "addr:postcode":"90066",
    "addr:street":"S.Centinela Avenue",
    "iso:country":"US",
    "sg:address":"5556 S.Centinela Avenue",
    "sg:city":"Los Angeles",
    "sg:classifiers":[
        {
            "category":"Autos & Motor Vehicles",
            "subcategory":"Automobile Sales",
            "type":"Retail Goods"
        }
    ],
    "sg:phone":"+1 310 577 5777",
    "sg:postcode":"90066",
    "sg:province":"CA",
    "sg:tags":[
        "limo"
    ],
    "sg:website":"www.calimoservice.com",
    "wof:name":"Ca Limo Service",
    "wof:placetype":"venue"
},
  "geometry": {"coordinates":[-118.40941599999999,33.98193],"type":"Point"}
}