{
  "type": "Feature",
  "properties": {
    "iso:country":"US",
    "sg:address":"987 W Foothill Blvd",
    "sg:city":"Upland",
    "sg:classifiers":[
        {
            "category":"Shopping",
            "type":"Retail Goods"
        }
    ],
    "sg:phone":"+1 909 920 9445",
    "sg:postcode":"91786",
    "sg:province":"CA",
    "sg:tags":[
        "merchandise"
    ],
    "wof:name":"Light It Up Smoke Shop",
    "wof:placetype":"venue"
},
  "geometry": {"coordinates":[-117.66119500000001,34.107057],"type":"Point"}
}