{
  "type": "Feature",
  "properties": {
    "addr:full":"1625 The Alameda Suite 100 San Jose CA 95126",
    "addr:housenumber":"1625",
    "addr:postcode":"95126",
    "addr:street":"The Alameda Suite 100",
    "iso:country":"US",
    "sg:address":"1625 The Alameda Suite 100",
    "sg:city":"San Jose",
    "sg:classifiers":[
        {
            "category":"Banks & Credit Unions",
            "subcategory":"Bank",
            "type":"Services"
        }
    ],
    "sg:phone":"+1 408 999 0242",
    "sg:postcode":"95126",
    "sg:province":"CA",
    "wof:name":"Bank of Walnut Creek",
    "wof:placetype":"venue"
},
  "geometry": {"coordinates":[-121.917126,37.335665],"type":"Point"}
}