{
  "type": "Feature",
  "properties": {
    "iso:country":"US",
    "sg:address":"840 S Imperial Ave",
    "sg:city":"Calexico",
    "sg:classifiers":[
        {
            "category":"Shopping",
            "subcategory":"Florist",
            "type":"Retail Goods"
        }
    ],
    "sg:phone":"+1 760 768 0569",
    "sg:postcode":"92231",
    "sg:province":"CA",
    "wof:name":"Flowers By Annette",
    "wof:placetype":"venue"
},
  "geometry": {"coordinates":[-115.498592,32.674921],"type":"Point"}
}