{
  "type": "Feature",
  "properties": {
    "addr:full":"1411 E 31st St Ste 411 Oakland CA 94602",
    "addr:housenumber":"1411",
    "addr:postcode":"94602",
    "addr:street":"E 31St St Ste 411",
    "iso:country":"US",
    "sg:address":"1411 E 31st St Ste 411",
    "sg:city":"Oakland",
    "sg:classifiers":[
        {
            "category":"Shopping",
            "subcategory":"Gifts & Souvenirs",
            "type":"Retail Goods"
        }
    ],
    "sg:phone":"+1 510 437 4615",
    "sg:postcode":"94602",
    "sg:province":"CA",
    "sg:tags":[
        "shop"
    ],
    "wof:name":"Gift Gallery",
    "wof:placetype":"venue"
},
  "geometry": {"coordinates":[-122.231177,37.799242],"type":"Point"}
}