{
  "type": "Feature",
  "properties": {
    "iso:country":"US",
    "sg:address":"3451 Airway Dr",
    "sg:city":"Santa Rosa",
    "sg:classifiers":[
        {
            "category":"Retail",
            "subcategory":"Repair Shop",
            "type":"Services"
        }
    ],
    "sg:phone":"+1 707 526 6675",
    "sg:postcode":"95403",
    "sg:province":"CA",
    "sg:tags":[
        "upholsterer"
    ],
    "wof:name":"Pabros Upholstery & Detail",
    "wof:placetype":"venue"
},
  "geometry": {"coordinates":[-122.738175,38.474792],"type":"Point"}
}