{
  "type": "Feature",
  "properties": {
    "addr:full":"3950 Doubles Dr Santa Rosa CA 95407",
    "addr:postcode":"3950;95407",
    "addr:street":"Doubles Dr",
    "iso:country":"US",
    "sg:address":"3950 Doubles Dr",
    "sg:city":"Santa Rosa",
    "sg:classifiers":[
        {
            "category":"Organizations",
            "subcategory":"Religious Organization",
            "type":"Services"
        }
    ],
    "sg:phone":"+1 707 542 0791",
    "sg:postcode":"95407",
    "sg:province":"CA",
    "sg:tags":[
        "church"
    ],
    "wof:name":"West Santa Rosa Baptist Church",
    "wof:placetype":"venue"
},
  "geometry": {"coordinates":[-122.762258,38.424289],"type":"Point"}
}