{
  "type": "Feature",
  "properties": {
    "iso:country":"US",
    "sg:address":"2909 Dinwiddie Way",
    "sg:city":"Elk Grove",
    "sg:classifiers":[
        {
            "category":"Professional",
            "type":"Services"
        }
    ],
    "sg:phone":"+1 916 683 6424",
    "sg:postcode":"95758",
    "sg:province":"CA",
    "wof:name":"Killer Beads",
    "wof:placetype":"venue"
},
  "geometry": {"coordinates":[-121.47905,38.427363],"type":"Point"}
}