{
  "type": "Feature",
  "properties": {
    "iso:country":"US",
    "sg:address":"1590 Moffett St",
    "sg:city":"Salinas",
    "sg:classifiers":[
        {
            "category":"Government",
            "subcategory":"Office",
            "type":"Public Place"
        }
    ],
    "sg:phone":"+1 831 759 6900",
    "sg:postcode":"93905",
    "sg:province":"CA",
    "wof:name":"Monterey County Info Tech",
    "wof:placetype":"venue"
},
  "geometry": {"coordinates":[-121.61750499999999,36.661262],"type":"Point"}
}