{
  "type": "Feature",
  "properties": {
    "addr:full":"6522 Pacific Boulevard Huntington Park CA 90255",
    "addr:housenumber":"6522",
    "addr:postcode":"90255",
    "addr:street":"Pacific Boulevard;Park",
    "iso:country":"US",
    "sg:address":"6522 Pacific Boulevard",
    "sg:city":"Huntington Park",
    "sg:classifiers":[
        {
            "category":"Health Services",
            "subcategory":"Chiropractor",
            "type":"Services"
        }
    ],
    "sg:phone":"+1 323 589 8804",
    "sg:postcode":"90255",
    "sg:province":"CA",
    "wof:name":"Ams Chiropractic and Rehabilitation",
    "wof:placetype":"venue"
},
  "geometry": {"coordinates":[-118.225251,33.979995],"type":"Point"}
}