{
  "type": "Feature",
  "properties": {
    "iso:country":"US",
    "sg:address":"4126 Hitch Blvd",
    "sg:city":"Moorpark",
    "sg:classifiers":[
        {
            "category":"Building & Trades",
            "subcategory":"Construction",
            "type":"Services"
        }
    ],
    "sg:phone":"+1 805 517 1196",
    "sg:postcode":"93021",
    "sg:province":"CA",
    "sg:tags":[
        "ceiling"
    ],
    "wof:name":"ECL Acoustics",
    "wof:placetype":"venue"
},
  "geometry": {"coordinates":[-118.915243,34.266743],"type":"Point"}
}