{
  "type": "Feature",
  "properties": {
    "addr:full":"2475 4th St Berkeley CA 94710",
    "addr:housenumber":"2475",
    "addr:postcode":"94710",
    "addr:street":"4Th St",
    "iso:country":"US",
    "sg:address":"2475 4th St",
    "sg:city":"Berkeley",
    "sg:classifiers":[
        {
            "category":"Manufacturing",
            "subcategory":"Tools & Machinery",
            "type":"Manufacturing & Wholesale Goods"
        },
        {
            "category":"Professional",
            "subcategory":"Computer Services",
            "type":"Services"
        }
    ],
    "sg:phone":"+1 510 843 3587",
    "sg:postcode":"94710",
    "sg:province":"CA",
    "sg:tags":[
        "magnetometer",
        "electronics",
        "mfg"
    ],
    "sg:website":"www.georgeassociates.com",
    "wof:name":"George Associates",
    "wof:placetype":"venue"
},
  "geometry": {"coordinates":[-122.29766100000001,37.860899],"type":"Point"}
}