{
  "type": "Feature",
  "properties": {
    "addr:full":"280 28th St Oakland CA 94611",
    "addr:housenumber":"280",
    "addr:postcode":"94611",
    "addr:street":"28Th St",
    "iso:country":"US",
    "sg:address":"280 28th St",
    "sg:city":"Oakland",
    "sg:classifiers":[
        {
            "category":"Shopping",
            "subcategory":"Computers & Home Electronics",
            "type":"Retail Goods"
        }
    ],
    "sg:phone":"+1 510 268 0153",
    "sg:postcode":"94611",
    "sg:province":"CA",
    "wof:name":"Satellite Senior Homes",
    "wof:placetype":"venue"
},
  "geometry": {"coordinates":[-122.262426,37.816267],"type":"Point"}
}