{
  "type": "Feature",
  "properties": {
    "iso:country":"US",
    "sg:address":"1751 N Sunrise Way Ste F1",
    "sg:city":"Palm Springs",
    "sg:classifiers":[
        {
            "category":"Restaurant",
            "type":"Food & Drink"
        }
    ],
    "sg:phone":"+1 760 323 9244",
    "sg:postcode":"92262",
    "sg:province":"CA",
    "sg:tags":[
        "pizza"
    ],
    "sg:website":"rockyspizzapalmsprings.com",
    "wof:name":"Rocky's Pizza",
    "wof:placetype":"venue"
},
  "geometry": {"coordinates":[-116.549677,33.82336],"type":"Point"}
}