{
  "type": "Feature",
  "properties": {
    "iso:country":"US",
    "sg:address":"859 Diablo Ave",
    "sg:city":"Novato",
    "sg:classifiers":[
        {
            "category":"Insurance",
            "subcategory":"Hazard Insurance",
            "type":"Services"
        }
    ],
    "sg:phone":"+1 415 493 2500",
    "sg:postcode":"94947",
    "sg:province":"CA",
    "sg:tags":[
        "commercial",
        "business"
    ],
    "sg:website":"http://www.fp-ins.com",
    "wof:name":"Farallone Pacific Insurance Services",
    "wof:placetype":"venue"
},
  "geometry": {"coordinates":[-122.57356900000001,38.102853],"type":"Point"}
}