{
  "type": "Feature",
  "properties": {
    "addr:full":"183 E Glenarm St Ste 102 Pasadena CA 91105",
    "addr:housenumber":"183",
    "addr:postcode":"91105",
    "addr:street":"E Glenarm St Ste 102",
    "iso:country":"US",
    "sg:address":"183 E Glenarm St Ste 102",
    "sg:city":"Pasadena",
    "sg:classifiers":[
        {
            "category":"Education",
            "subcategory":"Special Training",
            "type":"Public Place"
        }
    ],
    "sg:phone":"+1 626 799 3909",
    "sg:postcode":"91105",
    "sg:province":"CA",
    "sg:tags":[
        "tutoring"
    ],
    "wof:name":"Campus Kids",
    "wof:placetype":"venue"
},
  "geometry": {"coordinates":[-118.146004,34.127602],"type":"Point"}
}