{
  "type": "Feature",
  "properties": {
    "addr:full":"1761 W Romneya Dr Ste F Anaheim CA 92801",
    "addr:housenumber":"1761",
    "addr:postcode":"92801",
    "addr:street":"W Romneya Dr Ste F",
    "iso:country":"US",
    "sg:address":"1761 W Romneya Dr Ste F",
    "sg:city":"Anaheim",
    "sg:classifiers":[
        {
            "category":"Health Services",
            "subcategory":"Doctor",
            "type":"Services"
        },
        {
            "category":"Health Services",
            "subcategory":"Dentist",
            "type":"Services"
        }
    ],
    "sg:phone":"+1 714 635 1170",
    "sg:postcode":"92801",
    "sg:province":"CA",
    "sg:tags":[
        "surgeon",
        "oral",
        "pediatric"
    ],
    "wof:name":"Okawachi David DDS",
    "wof:placetype":"venue"
},
  "geometry": {"coordinates":[-117.94405399999999,33.851654],"type":"Point"}
}