{
  "type": "Feature",
  "properties": {
    "addr:full":"445 W 11th St Tracy CA 95376",
    "addr:housenumber":"445",
    "addr:postcode":"95376",
    "addr:street":"W 11Th St",
    "iso:country":"US",
    "sg:address":"445 W 11th St",
    "sg:city":"Tracy",
    "sg:classifiers":[
        {
            "category":"Banks & Credit Unions",
            "subcategory":"Bank",
            "type":"Services"
        }
    ],
    "sg:phone":"+1 209 834 0100",
    "sg:postcode":"95376",
    "sg:province":"CA",
    "sg:tags":[
        "loan",
        "real estate"
    ],
    "wof:name":"Partner's Mortgage",
    "wof:placetype":"venue"
},
  "geometry": {"coordinates":[-121.433042,37.739711],"type":"Point"}
}