{
  "type": "Feature",
  "properties": {
    "iso:country":"US",
    "sg:address":"620 E Bidwell St",
    "sg:city":"Folsom",
    "sg:classifiers":[
        {
            "category":"Travel",
            "subcategory":"Travel Agent",
            "type":"Entertainment"
        }
    ],
    "sg:phone":"+1 916 983 7900",
    "sg:postcode":"95630",
    "sg:province":"CA",
    "sg:tags":[
        "agency"
    ],
    "wof:name":"Folsom Travel",
    "wof:placetype":"venue"
},
  "geometry": {"coordinates":[-121.156891,38.670319],"type":"Point"}
}