{
  "type": "Feature",
  "properties": {
    "addr:full":"99 S E St Santa Rosa CA 95404",
    "addr:housenumber":"99",
    "addr:postcode":"ca 95404",
    "addr:street":"S E St",
    "iso:country":"US",
    "sg:address":"99 S E St",
    "sg:city":"Santa Rosa",
    "sg:classifiers":[
        {
            "category":"Government",
            "subcategory":"Court House",
            "type":"Public Place"
        }
    ],
    "sg:phone":"+1 707 575 5035",
    "sg:postcode":"95404",
    "sg:province":"CA",
    "sg:tags":[
        "federal",
        "judicial"
    ],
    "wof:name":"U S Bankruptcy Court",
    "wof:placetype":"venue"
},
  "geometry": {"coordinates":[-122.70782,38.437947],"type":"Point"}
}