{
  "type": "Feature",
  "properties": {
    "addr:full":"481 Pso Refugio Milpitas CA 95035",
    "addr:housenumber":"481",
    "addr:postcode":"95035",
    "addr:street":"Pso Refugio",
    "iso:country":"US",
    "sg:address":"481 Pso Refugio",
    "sg:city":"Milpitas",
    "sg:classifiers":[
        {
            "category":"Professional",
            "subcategory":"Business Services",
            "type":"Services"
        }
    ],
    "sg:phone":"+1 408 309 2877",
    "sg:postcode":"95035",
    "sg:province":"CA",
    "wof:name":"Trenh & Assoc",
    "wof:placetype":"venue"
},
  "geometry": {"coordinates":[-121.89883,37.437649],"type":"Point"}
}