{
  "type": "Feature",
  "properties": {
    "iso:country":"US",
    "sg:address":"1744 W Chapman Ave",
    "sg:city":"Orange",
    "sg:classifiers":[
        {
            "category":"Professional",
            "type":"Services"
        }
    ],
    "sg:phone":"+1 714 978 8007",
    "sg:postcode":"92868",
    "sg:province":"CA",
    "wof:name":"Spa Source",
    "wof:placetype":"venue"
},
  "geometry": {"coordinates":[-117.873346,33.787884],"type":"Point"}
}