{
  "type": "Feature",
  "properties": {
    "iso:country":"US",
    "sg:address":"644 East Katella Ave",
    "sg:city":"Orange",
    "sg:classifiers":[
        {
            "category":"Shopping",
            "subcategory":"Clothing, Apparel, & Fashions",
            "type":"Retail Goods"
        },
        {
            "category":"Animal Shelter",
            "type":"Public Place"
        }
    ],
    "sg:phone":"+1 714 997 8440",
    "sg:postcode":"92825",
    "sg:province":"CA",
    "sg:tags":[
        "lingerie",
        "clothing",
        "adult",
        "women's"
    ],
    "sg:website":"stringsbyjudith.com",
    "wof:name":"Strings by Judith",
    "wof:placetype":"venue"
},
  "geometry": {"coordinates":[-117.846687,33.809056],"type":"Point"}
}