{
  "type": "Feature",
  "properties": {
    "iso:country":"US",
    "sg:address":"860 Bancroft Rd",
    "sg:city":"Walnut Creek",
    "sg:classifiers":[
        {
            "category":"Shopping",
            "subcategory":"Used Merchandise",
            "type":"Retail Goods"
        }
    ],
    "sg:phone":"+1 925 934 5161",
    "sg:postcode":"94598",
    "sg:province":"CA",
    "sg:tags":[
        "shop",
        "consignment"
    ],
    "wof:name":"Kids Clothesline",
    "wof:placetype":"venue"
},
  "geometry": {"coordinates":[-122.044955,37.932094],"type":"Point"}
}