{
  "type": "Feature",
  "properties": {
    "addr:full":"41415 Tejon Pass Rd Gorman CA 93243",
    "addr:housenumber":"41415",
    "addr:postcode":"93243",
    "addr:street":"Tejon Pass Rd",
    "iso:country":"US",
    "sg:address":"41415 Tejon Pass Rd",
    "sg:city":"Gorman",
    "sg:classifiers":[
        {
            "category":"Shopping",
            "subcategory":"Clothing, Apparel, & Fashions",
            "type":"Retail Goods"
        }
    ],
    "sg:phone":"+1 661 248 2418",
    "sg:postcode":"93243",
    "sg:province":"CA",
    "wof:name":"Alpaca Store",
    "wof:placetype":"venue"
},
  "geometry": {"coordinates":[-118.88076,34.80699],"type":"Point"}
}