{
  "type": "Feature",
  "properties": {
    "iso:country":"US",
    "sg:address":"2630 Greenrock Rd",
    "sg:city":"Milpitas",
    "sg:classifiers":[
        {
            "category":"Professional",
            "subcategory":"Business Services",
            "type":"Services"
        }
    ],
    "sg:phone":"+1 408 263 5933",
    "sg:postcode":"95035",
    "sg:province":"CA",
    "sg:tags":[
        "packaging"
    ],
    "wof:name":"Advanced Packaging Integration",
    "wof:placetype":"venue"
},
  "geometry": {"coordinates":[-121.860715,37.425971],"type":"Point"}
}