{
  "type": "Feature",
  "properties": {
    "iso:country":"US",
    "sg:address":"13664 Geranium St",
    "sg:city":"Chino",
    "sg:classifiers":[
        {
            "category":"Personal",
            "type":"Services"
        }
    ],
    "sg:phone":"+1 909 262 4789",
    "sg:postcode":"91710",
    "sg:province":"CA",
    "sg:tags":[
        "assistant"
    ],
    "wof:name":"Elite Meetings Internatio",
    "wof:placetype":"venue"
},
  "geometry": {"coordinates":[-117.70875599999999,34.004812],"type":"Point"}
}