{
  "type": "Feature",
  "properties": {
    "iso:country":"US",
    "sg:address":"7615 State St",
    "sg:city":"Huntington Park",
    "sg:classifiers":[
        {
            "category":"Professional",
            "type":"Services"
        }
    ],
    "sg:phone":"+1 323 588 2182",
    "sg:postcode":"90255",
    "sg:province":"CA",
    "sg:tags":[
        "establishment"
    ],
    "wof:name":"Velasco N",
    "wof:placetype":"venue"
},
  "geometry": {"coordinates":[-118.210153,33.96878],"type":"Point"}
}