{
  "type": "Feature",
  "properties": {
    "iso:country":"US",
    "sg:address":"236 8th St STE A",
    "sg:city":"San Francisco",
    "sg:classifiers":[
        {
            "category":"Professional",
            "subcategory":"Computer Services",
            "type":"Services"
        }
    ],
    "sg:postcode":"94103",
    "sg:province":"CA",
    "sg:tags":[
        "social",
        "food",
        "web-2-0",
        "consumer-web"
    ],
    "sg:website":"http://www.foodia.com",
    "wof:name":"Foodia",
    "wof:placetype":"venue"
},
  "geometry": {"coordinates":[-122.410696,37.775408],"type":"Point"}
}