{
  "type": "Feature",
  "properties": {
    "iso:country":"US",
    "sg:address":"1331 E Katella Ave",
    "sg:city":"Orange",
    "sg:classifiers":[
        {
            "category":"Shopping",
            "subcategory":"Gifts & Souvenirs",
            "type":"Retail Goods"
        }
    ],
    "sg:phone":"+1 714 978 1773",
    "sg:postcode":"92867",
    "sg:province":"CA",
    "wof:name":"City Gifts",
    "wof:placetype":"venue"
},
  "geometry": {"coordinates":[-117.836027,33.809256],"type":"Point"}
}