{
  "type": "Feature",
  "properties": {
    "iso:country":"US",
    "sg:address":"4570 Putah Creek Rd",
    "sg:city":"Winters",
    "sg:classifiers":[
        {
            "category":"Home & Garden",
            "subcategory":"Garden Supply",
            "type":"Retail Goods"
        }
    ],
    "sg:phone":"+1 530 795 0859",
    "sg:postcode":"95694",
    "sg:province":"CA",
    "sg:tags":[
        "nurseryman"
    ],
    "sg:website":"www.martinezorchards.com",
    "wof:name":"Martinez Orchards Inc",
    "wof:placetype":"venue"
},
  "geometry": {"coordinates":[-121.953575,38.524836],"type":"Point"}
}