{
  "type": "Feature",
  "properties": {
    "addr:full":"880 Tioga Ave Seaside CA 93955",
    "addr:housenumber":"880",
    "addr:postcode":"93955",
    "addr:street":"Tioga Ave",
    "iso:country":"US",
    "sg:address":"880 Tioga Ave",
    "sg:city":"Seaside",
    "sg:classifiers":[
        {
            "category":"Personal",
            "type":"Services"
        },
        {
            "category":"Arena",
            "subcategory":"Sports Club",
            "type":"Entertainment"
        }
    ],
    "sg:phone":"+1 831 920 1495",
    "sg:postcode":"93955",
    "sg:province":"CA",
    "sg:tags":[
        "trainer",
        "consultant",
        "physical",
        "health",
        "fitness"
    ],
    "wof:name":"Fit Athletics",
    "wof:placetype":"venue"
},
  "geometry": {"coordinates":[-121.844978,36.616119],"type":"Point"}
}