{
  "type": "Feature",
  "properties": {
    "addr:full":"1140 Peachy Canyon Rd Paso Robles CA 93446",
    "addr:housenumber":"1140",
    "addr:postcode":"93446",
    "addr:street":"Peachy Canyon Rd",
    "iso:country":"US",
    "sg:address":"1140 Peachy Canyon Rd",
    "sg:city":"Paso Robles",
    "sg:classifiers":[
        {
            "category":"Building & Trades",
            "subcategory":"Plumbing",
            "type":"Services"
        }
    ],
    "sg:phone":"+1 805 237 0142",
    "sg:postcode":"93446",
    "sg:province":"CA",
    "sg:tags":[
        "conditioning",
        "air",
        "system",
        "contractor"
    ],
    "wof:name":"Bergin's Heating & Air Cond",
    "wof:placetype":"venue"
},
  "geometry": {"coordinates":[-120.70851500000001,35.622897],"type":"Point"}
}