{
  "type": "Feature",
  "properties": {
    "iso:country":"US",
    "sg:address":"14566 7th St",
    "sg:city":"Victorville",
    "sg:classifiers":[
        {
            "category":"Health Services",
            "subcategory":"Health Practitioner",
            "type":"Services"
        }
    ],
    "sg:phone":"+1 760 843 0895",
    "sg:postcode":"92395",
    "sg:province":"CA",
    "sg:tags":[
        "therapist",
        "physical"
    ],
    "wof:name":"Comprehensive Physical Therapy",
    "wof:placetype":"venue"
},
  "geometry": {"coordinates":[-117.313721,34.515824],"type":"Point"}
}