{
  "type": "Feature",
  "properties": {
    "addr:full":"900 Golden Wheel Park Dr San Jose CA 95112",
    "addr:housenumber":"900",
    "addr:postcode":"95112",
    "addr:street":"Golden Wheel Park Dr",
    "iso:country":"US",
    "sg:address":"900 Golden Wheel Park Dr",
    "sg:city":"San Jose",
    "sg:classifiers":[
        {
            "category":"Professional",
            "type":"Services"
        },
        {
            "category":"Personal",
            "type":"Services"
        },
        {
            "category":"Professional",
            "subcategory":"Business Services",
            "type":"Services"
        }
    ],
    "sg:phone":"+1 510 512 3217",
    "sg:postcode":"95112",
    "sg:province":"CA",
    "sg:tags":[
        "chef",
        "delivery",
        "food",
        "caterer"
    ],
    "wof:name":"Chef Deepak Bhardwaj",
    "wof:placetype":"venue"
},
  "geometry": {"coordinates":[-121.892216,37.374727],"type":"Point"}
}