{
  "type": "Feature",
  "properties": {
    "iso:country":"US",
    "sg:address":"2103 S el Camino Real",
    "sg:city":"Oceanside",
    "sg:classifiers":[
        {
            "category":"Banks & Credit Unions",
            "subcategory":"Bank",
            "type":"Services"
        }
    ],
    "sg:phone":"+1 760 721 9775",
    "sg:postcode":"92054",
    "sg:province":"CA",
    "sg:tags":[
        "broker",
        "mortgage"
    ],
    "wof:name":"buyers Only",
    "wof:placetype":"venue"
},
  "geometry": {"coordinates":[-117.328416,33.187014],"type":"Point"}
}