{
  "type": "Feature",
  "properties": {
    "addr:full":"11130 Whitman Ave Granada Hills CA 91344",
    "addr:housenumber":"11130",
    "addr:postcode":"91344",
    "addr:street":"Whitman Ave",
    "iso:country":"US",
    "sg:address":"11130 Whitman Ave",
    "sg:city":"Granada Hills",
    "sg:classifiers":[
        {
            "category":"Shopping",
            "subcategory":"Music",
            "type":"Retail Goods"
        }
    ],
    "sg:phone":"+1 818 831 9528",
    "sg:postcode":"91344",
    "sg:province":"CA",
    "wof:name":"Pulpo Records",
    "wof:placetype":"venue"
},
  "geometry": {"coordinates":[-118.477833,34.273749],"type":"Point"}
}