{
  "type": "Feature",
  "properties": {
    "addr:full":"337 W Felicita Ave Escondido CA 92025",
    "addr:housenumber":"337",
    "addr:postcode":"92025",
    "addr:street":"W Felicita Ave",
    "iso:country":"US",
    "sg:address":"337 W Felicita Ave",
    "sg:city":"Escondido",
    "sg:classifiers":[
        {
            "category":"Food & Beverages",
            "subcategory":"Specialty",
            "type":"Retail Goods"
        }
    ],
    "sg:phone":"+1 760 489 7074",
    "sg:postcode":"92025",
    "sg:province":"CA",
    "sg:tags":[
        "water",
        "bulk",
        "company"
    ],
    "wof:name":"Felicita Water Store",
    "wof:placetype":"venue"
},
  "geometry": {"coordinates":[-117.07451500000001,33.10384],"type":"Point"}
}