{
  "type": "Feature",
  "properties": {
    "addr:full":"1220 Crossman Ave Ste 110 Sunnyvale CA 94089",
    "addr:housenumber":"1220",
    "addr:postcode":"94089",
    "addr:street":"Crossman Ave Ste 110",
    "iso:country":"US",
    "sg:address":"1220 Crossman Ave Ste 110",
    "sg:city":"Sunnyvale",
    "sg:classifiers":[
        {
            "category":"Food & Beverages",
            "subcategory":"Bakery",
            "type":"Retail Goods"
        }
    ],
    "sg:phone":"+1 408 744 1945",
    "sg:postcode":"94089",
    "sg:province":"CA",
    "sg:tags":[
        "sandwich"
    ],
    "wof:name":"Cafe Melange",
    "wof:placetype":"venue"
},
  "geometry": {"coordinates":[-122.011404,37.407351],"type":"Point"}
}