{
  "type": "Feature",
  "properties": {
    "iso:country":"US",
    "sg:address":"107 Park Shadow Ct",
    "sg:city":"Baldwin Park",
    "sg:classifiers":[
        {
            "category":"Wholesale",
            "subcategory":"Durable Goods & Equipment",
            "type":"Manufacturing & Wholesale Goods"
        }
    ],
    "sg:phone":"+1 626 813 3758",
    "sg:postcode":"91706",
    "sg:province":"CA",
    "sg:tags":[
        "importer"
    ],
    "wof:name":"J & K Group Inc",
    "wof:placetype":"venue"
},
  "geometry": {"coordinates":[-117.962835,34.087883],"type":"Point"}
}