{
  "type": "Feature",
  "properties": {
    "iso:country":"US",
    "sg:address":"4533 E Home Ave",
    "sg:city":"Fresno",
    "sg:classifiers":[
        {
            "category":"Autos & Motor Vehicles",
            "subcategory":"Auto Supplies",
            "type":"Retail Goods"
        },
        {
            "category":"Retail",
            "subcategory":"Auto Repair",
            "type":"Services"
        }
    ],
    "sg:phone":"+1 559 456 2494",
    "sg:postcode":"93703",
    "sg:province":"CA",
    "sg:tags":[
        "transmission"
    ],
    "wof:name":"Triple Tech Transmissions",
    "wof:placetype":"venue"
},
  "geometry": {"coordinates":[-119.74791,36.763198],"type":"Point"}
}