{
  "type": "Feature",
  "properties": {
    "iso:country":"US",
    "sg:address":"1045 Blaine St",
    "sg:city":"Los Angeles",
    "sg:classifiers":[
        {
            "category":"Autos & Motor Vehicles",
            "subcategory":"Fuel & Gas Station",
            "type":"Retail Goods"
        },
        {
            "category":"Restaurant",
            "type":"Food & Drink"
        }
    ],
    "sg:phone":"+1 213 748 2121",
    "sg:postcode":"90015",
    "sg:province":"CA",
    "wof:name":"Mr Sippee",
    "wof:placetype":"venue"
},
  "geometry": {"coordinates":[-118.271004,34.046101],"type":"Point"}
}