{
  "type": "Feature",
  "properties": {
    "iso:country":"US",
    "sg:address":"900 S San Tomas Aquino Rd",
    "sg:city":"Campbell",
    "sg:classifiers":[
        {
            "category":"Food & Beverages",
            "subcategory":"Groceries & Convenience Stores",
            "type":"Retail Goods"
        }
    ],
    "sg:phone":"+1 408 866 1662",
    "sg:postcode":"95008",
    "sg:province":"CA",
    "wof:name":"Farm Milk Dairy",
    "wof:placetype":"venue"
},
  "geometry": {"coordinates":[-121.97199999999999,37.273899],"type":"Point"}
}