{
  "type": "Feature",
  "properties": {
    "addr:full":"6777 N Cedar Ave Fresno CA 93710",
    "addr:housenumber":"6777",
    "addr:postcode":"93710",
    "addr:street":"N Cedar Ave",
    "iso:country":"US",
    "sg:address":"6777 N Cedar Ave",
    "sg:city":"Fresno",
    "sg:classifiers":[
        {
            "category":"Restaurant",
            "type":"Food & Drink"
        }
    ],
    "sg:phone":"+1 559 223 2837",
    "sg:postcode":"93710",
    "sg:province":"CA",
    "sg:tags":[
        "pizza"
    ],
    "wof:name":"Bad Buds Noble Roman's Pizza",
    "wof:placetype":"venue"
},
  "geometry": {"coordinates":[-119.754305,36.836962],"type":"Point"}
}