{
  "type": "Feature",
  "properties": {
    "iso:country":"US",
    "sg:address":"14011 Ventura Blvd",
    "sg:city":"Sherman Oaks",
    "sg:classifiers":[
        {
            "category":"Professional",
            "subcategory":"Lawyer & Legal Services",
            "type":"Services"
        }
    ],
    "sg:phone":"+1 805 523 9450",
    "sg:postcode":"91423",
    "sg:province":"CA",
    "sg:tags":[
        "attorney"
    ],
    "wof:name":"Jason Rowe Law Offices",
    "wof:placetype":"venue"
},
  "geometry": {"coordinates":[-118.43764,34.149139],"type":"Point"}
}