{
  "type": "Feature",
  "properties": {
    "iso:country":"US",
    "sg:address":"333 Eliseo Dr",
    "sg:city":"Greenbrae",
    "sg:classifiers":[
        {
            "category":"Real Estate",
            "subcategory":"Real Estate Operator",
            "type":"Services"
        }
    ],
    "sg:phone":"+1 415 461 5839",
    "sg:postcode":"94904",
    "sg:province":"CA",
    "sg:tags":[
        "property",
        "lessor"
    ],
    "wof:name":"B and H Motors Inc",
    "wof:placetype":"venue"
},
  "geometry": {"coordinates":[-122.514168,37.951861],"type":"Point"}
}