{
  "type": "Feature",
  "properties": {
    "addr:full":"14701 Myford Rd Tustin CA 92780",
    "addr:housenumber":"14701",
    "addr:postcode":"92780",
    "addr:street":"Myford Rd",
    "iso:country":"US",
    "sg:address":"14701 Myford Rd",
    "sg:city":"Tustin",
    "sg:classifiers":[
        {
            "category":"Professional",
            "subcategory":"Computer Services",
            "type":"Services"
        }
    ],
    "sg:phone":"+1 714 544 2679",
    "sg:postcode":"92780",
    "sg:province":"CA",
    "sg:tags":[
        "repair"
    ],
    "wof:name":"A American Toner Supply & Repair",
    "wof:placetype":"venue"
},
  "geometry": {"coordinates":[-117.804237,33.712204],"type":"Point"}
}