{
  "type": "Feature",
  "properties": {
    "addr:full":"116 Garcia Ave San Leandro CA 94577",
    "addr:housenumber":"116",
    "addr:postcode":"94577",
    "addr:street":"Garcia Ave",
    "iso:country":"US",
    "sg:address":"116 Garcia Ave",
    "sg:city":"San Leandro",
    "sg:classifiers":[
        {
            "category":"Personal",
            "type":"Services"
        }
    ],
    "sg:phone":"+1 510 569 1610",
    "sg:postcode":"94577",
    "sg:province":"CA",
    "sg:tags":[
        "sewing",
        "alteration"
    ],
    "wof:name":"Maria's Alterations",
    "wof:placetype":"venue"
},
  "geometry": {"coordinates":[-122.16300200000001,37.7342],"type":"Point"}
}