{
  "type": "Feature",
  "properties": {
    "iso:country":"US",
    "sg:address":"1540 W Gaylord St",
    "sg:city":"Long Beach",
    "sg:classifiers":[
        {
            "category":"Professional",
            "type":"Services"
        }
    ],
    "sg:phone":"+1 562 432 4229",
    "sg:postcode":"90813",
    "sg:province":"CA",
    "sg:tags":[
        "sculptor"
    ],
    "wof:name":"Alvarez Wax Models",
    "wof:placetype":"venue"
},
  "geometry": {"coordinates":[-118.213245,33.786368],"type":"Point"}
}