{
  "type": "Feature",
  "properties": {
    "addr:full":"4151 23rd Ave Sacramento CA 95820",
    "addr:housenumber":"4151",
    "addr:postcode":"95820",
    "addr:street":"23Rd Ave",
    "iso:country":"US",
    "sg:address":"4151 23rd Ave",
    "sg:city":"Sacramento",
    "sg:classifiers":[
        {
            "category":"Utilities",
            "subcategory":"Mobile Phone",
            "type":"Services"
        }
    ],
    "sg:phone":"+1 916 731 8786",
    "sg:postcode":"95820",
    "sg:province":"CA",
    "sg:tags":[
        "telephone",
        "cellular"
    ],
    "wof:name":"Wireless proz",
    "wof:placetype":"venue"
},
  "geometry": {"coordinates":[-121.458223,38.53219],"type":"Point"}
}