{
  "type": "Feature",
  "properties": {
    "iso:country":"US",
    "sg:address":"13019 Stagg St",
    "sg:city":"North Hollywood",
    "sg:classifiers":[
        {
            "category":"Shopping",
            "subcategory":"Crafts & Fabrics",
            "type":"Retail Goods"
        }
    ],
    "sg:phone":"+1 818 765 2994",
    "sg:postcode":"91605",
    "sg:province":"CA",
    "sg:tags":[
        "sewing"
    ],
    "wof:name":"Fabrics Unlimited",
    "wof:placetype":"venue"
},
  "geometry": {"coordinates":[-118.416397,34.210166],"type":"Point"}
}