{
  "type": "Feature",
  "properties": {
    "addr:full":"98 Clarksville Rd Folsom CA 95630",
    "addr:housenumber":"98",
    "addr:postcode":"95630",
    "addr:street":"Clarksville Rd",
    "iso:country":"US",
    "sg:address":"98 Clarksville Rd",
    "sg:city":"Folsom",
    "sg:classifiers":[
        {
            "category":"Home & Garden",
            "subcategory":"Carpets & Floor Coverings",
            "type":"Retail Goods"
        }
    ],
    "sg:phone":"+1 916 984 6683",
    "sg:postcode":"95630",
    "sg:province":"CA",
    "sg:tags":[
        "installation",
        "rug"
    ],
    "wof:name":"Eldorado S & G Carpet",
    "wof:placetype":"venue"
},
  "geometry": {"coordinates":[-121.128418,38.658249],"type":"Point"}
}