{
  "type": "Feature",
  "properties": {
    "iso:country":"US",
    "sg:address":"1534 W 25th St",
    "sg:city":"San Pedro",
    "sg:classifiers":[
        {
            "category":"Health Services",
            "subcategory":"Chiropractor",
            "type":"Services"
        }
    ],
    "sg:phone":"+1 310 547 3000",
    "sg:postcode":"90732",
    "sg:province":"CA",
    "wof:name":"Crittle Chiropractic Ctr",
    "wof:placetype":"venue"
},
  "geometry": {"coordinates":[-118.311494,33.721956],"type":"Point"}
}