{
  "type": "Feature",
  "properties": {
    "addr:full":"914 W Grand Ave Oakland CA 94607",
    "addr:housenumber":"914",
    "addr:postcode":"94607",
    "addr:street":"W Grand Ave",
    "iso:country":"US",
    "sg:address":"914 W Grand Ave",
    "sg:city":"Oakland",
    "sg:classifiers":[
        {
            "category":"Autos & Motor Vehicles",
            "subcategory":"Auto Supplies",
            "type":"Retail Goods"
        },
        {
            "category":"Retail",
            "subcategory":"Auto Repair",
            "type":"Services"
        }
    ],
    "sg:phone":"+1 510 268 8814",
    "sg:postcode":"94607",
    "sg:province":"CA",
    "sg:tags":[
        "recap",
        "retread",
        "tire"
    ],
    "wof:name":"West Oakland Tires & Repairs",
    "wof:placetype":"venue"
},
  "geometry": {"coordinates":[-122.279222,37.814858],"type":"Point"}
}