{
  "type": "Feature",
  "properties": {
    "addr:full":"2178 Queens Ln San Mateo CA 94402",
    "addr:housenumber":"2178",
    "addr:postcode":"94402",
    "addr:street":"Queens Ln",
    "iso:country":"US",
    "sg:address":"2178 Queens Ln",
    "sg:city":"San Mateo",
    "sg:classifiers":[
        {
            "category":"Building & Trades",
            "subcategory":"Landscaping Services",
            "type":"Services"
        }
    ],
    "sg:phone":"+1 650 345 7295",
    "sg:postcode":"94402",
    "sg:province":"CA",
    "wof:name":"Lanusse Jean Gardening",
    "wof:placetype":"venue"
},
  "geometry": {"coordinates":[-122.33242799999999,37.517262],"type":"Point"}
}