{
  "type": "Feature",
  "properties": {
    "addr:full":"554 E Hillcrest Dr Thousand Oaks CA 91360",
    "addr:housenumber":"554",
    "addr:postcode":"91360",
    "addr:street":"E Hillcrest Dr",
    "iso:country":"US",
    "sg:address":"554 E Hillcrest Dr",
    "sg:city":"Thousand Oaks",
    "sg:classifiers":[
        {
            "category":"Personal",
            "subcategory":"Beauty Salon",
            "type":"Services"
        }
    ],
    "sg:phone":"+1 805 777 3448",
    "sg:postcode":"91360",
    "sg:province":"CA",
    "wof:name":"Regis Salons",
    "wof:placetype":"venue"
},
  "geometry": {"coordinates":[-118.867198,34.181368],"type":"Point"}
}