{
  "type": "Feature",
  "properties": {
    "iso:country":"US",
    "sg:address":"29169 Heathercliff Rd",
    "sg:city":"Malibu",
    "sg:classifiers":[
        {
            "category":"Professional",
            "subcategory":"Management & Consulting",
            "type":"Services"
        }
    ],
    "sg:phone":"+1 310 589 2084",
    "sg:postcode":"90265",
    "sg:province":"CA",
    "sg:tags":[
        "food",
        "safety",
        "sanitation"
    ],
    "sg:website":"www.evercleanservices.com",
    "wof:name":"Everclean Services",
    "wof:placetype":"venue"
},
  "geometry": {"coordinates":[-118.808898,34.021581],"type":"Point"}
}