{
  "type": "Feature",
  "properties": {
    "addr:full":"2175 S Mallul Dr Ofc Anaheim CA 92802",
    "addr:housenumber":"2175",
    "addr:postcode":"92802",
    "addr:street":"S Mallul Dr",
    "iso:country":"US",
    "sg:address":"2175 S Mallul Dr Ofc",
    "sg:city":"Anaheim",
    "sg:classifiers":[
        {
            "category":"Real Estate",
            "subcategory":"Real Estate Operator",
            "type":"Services"
        }
    ],
    "sg:phone":"+1 714 971 5991",
    "sg:postcode":"92802",
    "sg:province":"CA",
    "sg:tags":[
        "apartment"
    ],
    "wof:name":"Caribbean Cove Apartments",
    "wof:placetype":"venue"
},
  "geometry": {"coordinates":[-117.916,33.7939],"type":"Point"}
}