{
  "type": "Feature",
  "properties": {
    "iso:country":"US",
    "sg:address":"1010 S San Gabriel Blvd",
    "sg:city":"San Gabriel",
    "sg:classifiers":[
        {
            "category":"Wholesale",
            "subcategory":"Apparel",
            "type":"Manufacturing & Wholesale Goods"
        },
        {
            "category":"Professional",
            "subcategory":"Business Services",
            "type":"Services"
        }
    ],
    "sg:phone":"+1 626 286 1086",
    "sg:postcode":"91776",
    "sg:province":"CA",
    "sg:tags":[
        "piece",
        "embroidery",
        "sewing"
    ],
    "wof:name":"Good Looking Embroidery Co",
    "wof:placetype":"venue"
},
  "geometry": {"coordinates":[-118.090805,34.088049],"type":"Point"}
}