{
  "type": "Feature",
  "properties": {
    "addr:full":"9018 Balboa Blvd Northridge CA 91325",
    "addr:housenumber":"9018",
    "addr:postcode":"91325",
    "addr:street":"Balboa Blvd",
    "iso:country":"US",
    "sg:address":"9018 Balboa Blvd",
    "sg:city":"Northridge",
    "sg:classifiers":[
        {
            "category":"Manufacturing",
            "subcategory":"Printing",
            "type":"Manufacturing & Wholesale Goods"
        }
    ],
    "sg:phone":"+1 818 734 9741",
    "sg:postcode":"91325",
    "sg:province":"CA",
    "sg:tags":[
        "publisher"
    ],
    "wof:name":"Albert Lund Publishing",
    "wof:placetype":"venue"
},
  "geometry": {"coordinates":[-118.50248000000001,34.233175],"type":"Point"}
}