{
  "type": "Feature",
  "properties": {
    "iso:country":"US",
    "sg:address":"115 S Waterman Ave",
    "sg:city":"San Bernardino",
    "sg:classifiers":[
        {
            "category":"Insurance",
            "subcategory":"Hazard Insurance",
            "type":"Services"
        }
    ],
    "sg:phone":"+1 909 887 4219",
    "sg:postcode":"92408",
    "sg:province":"CA",
    "sg:tags":[
        "fidelity",
        "bond"
    ],
    "wof:name":"Greenwood Bail Bonds",
    "wof:placetype":"venue"
},
  "geometry": {"coordinates":[-117.278689,34.096206],"type":"Point"}
}