{
  "type": "Feature",
  "properties": {
    "iso:country":"US",
    "sg:address":"765 E 9th St",
    "sg:city":"San Bernardino",
    "sg:classifiers":[
        {
            "category":"Professional",
            "subcategory":"Management & Consulting",
            "type":"Services"
        }
    ],
    "sg:phone":"+1 909 381 6158",
    "sg:postcode":"92410",
    "sg:province":"CA",
    "sg:tags":[
        "marketing",
        "consultant"
    ],
    "wof:name":"Atwell Enterprise",
    "wof:placetype":"venue"
},
  "geometry": {"coordinates":[-117.270045,34.115715],"type":"Point"}
}