{
  "type": "Feature",
  "properties": {
    "iso:country":"US",
    "sg:address":"1238 Parkside Dr",
    "sg:city":"Mckinleyville",
    "sg:classifiers":[
        {
            "category":"Building & Trades",
            "subcategory":"Landscaping Services",
            "type":"Services"
        }
    ],
    "sg:phone":"+1 707 839 1308",
    "sg:postcode":"95519",
    "sg:province":"CA",
    "sg:tags":[
        "landscape",
        "contractor"
    ],
    "wof:name":"Jim Mc Laughlin Landscape",
    "wof:placetype":"venue"
},
  "geometry": {"coordinates":[-124.109666,40.951781],"type":"Point"}
}