{
  "type": "Feature",
  "properties": {
    "iso:country":"US",
    "sg:address":"7 Whatney",
    "sg:city":"Irvine",
    "sg:classifiers":[
        {
            "category":"Place Of Worship",
            "subcategory":"Church",
            "type":"Public Place"
        }
    ],
    "sg:phone":"+1 949 458 2424",
    "sg:postcode":"92618",
    "sg:province":"CA",
    "sg:website":"www.ourterranova.com",
    "wof:name":"TerraNova Church",
    "wof:placetype":"venue"
},
  "geometry": {"coordinates":[-117.720308,33.636425],"type":"Point"}
}