{
  "type": "Feature",
  "properties": {
    "addr:full":"203 W State St Redlands CA 92374",
    "addr:housenumber":"203",
    "addr:postcode":"92374",
    "addr:street":"W State St",
    "iso:country":"US",
    "sg:address":"203 W State St",
    "sg:city":"Redlands",
    "sg:classifiers":[
        {
            "category":"Utilities",
            "subcategory":"Telephone",
            "type":"Services"
        }
    ],
    "sg:phone":"+1 951 545 7251",
    "sg:postcode":"92374",
    "sg:province":"CA",
    "sg:tags":[
        "hosting",
        "internet"
    ],
    "wof:name":"Webhost2com",
    "wof:placetype":"venue"
},
  "geometry": {"coordinates":[-117.18693,34.056466],"type":"Point"}
}