{
  "type": "Feature",
  "properties": {
    "addr:full":"7001 Olive Dr Bakersfield CA 93308",
    "addr:housenumber":"7001",
    "addr:postcode":"93308",
    "addr:street":"Olive Dr",
    "iso:country":"US",
    "sg:address":"7001 Olive Dr",
    "sg:city":"Bakersfield",
    "sg:classifiers":[
        {
            "category":"Building & Trades",
            "subcategory":"Construction",
            "type":"Services"
        }
    ],
    "sg:phone":"+1 661 399 8366",
    "sg:postcode":"93308",
    "sg:province":"CA",
    "sg:tags":[
        "house"
    ],
    "wof:name":"Ed Sauer Construction",
    "wof:placetype":"venue"
},
  "geometry": {"coordinates":[-119.081118,35.41241],"type":"Point"}
}