{
  "type": "Feature",
  "properties": {
    "addr:full":"35 Clement St San Francisco CA 94118",
    "addr:housenumber":"35",
    "addr:postcode":"94118",
    "addr:street":"Clement St",
    "iso:country":"US",
    "sg:address":"35 Clement St",
    "sg:city":"San Francisco",
    "sg:classifiers":[
        {
            "category":"Sports & Exercise",
            "subcategory":"Gym",
            "type":"Entertainment"
        }
    ],
    "sg:phone":"+1 415 221 7246",
    "sg:postcode":"94118",
    "sg:province":"CA",
    "wof:name":"Dynamic Balance",
    "wof:placetype":"venue"
},
  "geometry": {"coordinates":[-122.459397,37.783042],"type":"Point"}
}