{
  "type": "Feature",
  "properties": {
    "addr:full":"8612 Bandera St Los Angeles CA 90002",
    "addr:housenumber":"8612",
    "addr:postcode":"90002",
    "addr:street":"Bandera St",
    "iso:country":"US",
    "sg:address":"8612 Bandera St",
    "sg:city":"Los Angeles",
    "sg:classifiers":[
        {
            "category":"Manufacturing",
            "subcategory":"Metals",
            "type":"Manufacturing & Wholesale Goods"
        }
    ],
    "sg:phone":"+1 323 583 4423",
    "sg:postcode":"90002",
    "sg:province":"CA",
    "sg:tags":[
        "metalwork",
        "architectural",
        "mfg"
    ],
    "wof:name":"Marios Iron Works",
    "wof:placetype":"venue"
},
  "geometry": {"coordinates":[-118.23958399999999,33.959478],"type":"Point"}
}