{
  "type": "Feature",
  "properties": {
    "iso:country":"US",
    "sg:address":"230 E 17th St",
    "sg:city":"Costa Mesa",
    "sg:classifiers":[
        {
            "category":"Health Services",
            "subcategory":"Chiropractor",
            "type":"Services"
        }
    ],
    "sg:phone":"+1 949 645 6963",
    "sg:postcode":"92627",
    "sg:province":"CA",
    "wof:name":"Mark M Kosker DC",
    "wof:placetype":"venue"
},
  "geometry": {"coordinates":[-117.917905,33.635013],"type":"Point"}
}