{
  "type": "Feature",
  "properties": {
    "addr:full":"2100 Auto Center Dr Oxnard CA 93030",
    "addr:housenumber":"2100",
    "addr:postcode":"93030",
    "addr:street":"Auto Center Dr",
    "iso:country":"US",
    "sg:address":"2100 Auto Center Dr",
    "sg:city":"Oxnard",
    "sg:classifiers":[
        {
            "category":"Freight",
            "type":"Transportation"
        }
    ],
    "sg:phone":"+1 805 983 1978",
    "sg:postcode":"93030",
    "sg:province":"CA",
    "sg:tags":[
        "commercial",
        "storage"
    ],
    "wof:name":"Golden State Self Storage",
    "wof:placetype":"venue"
},
  "geometry": {"coordinates":[-119.14814200000001,34.226593],"type":"Point"}
}