{
  "type": "Feature",
  "properties": {
    "addr:full":"1723 17th Ave San Francisco CA 94122",
    "addr:housenumber":"1723",
    "addr:postcode":"94122",
    "addr:street":"17Th Ave",
    "iso:country":"US",
    "sg:address":"1723 17th Ave",
    "sg:city":"San Francisco",
    "sg:classifiers":[
        {
            "category":"Local Transit",
            "type":"Transportation"
        }
    ],
    "sg:phone":"+1 415 665 7773",
    "sg:postcode":"94122",
    "sg:province":"CA",
    "sg:tags":[
        "limousine"
    ],
    "wof:name":"Tokyo Limousine Service Inc",
    "wof:placetype":"venue"
},
  "geometry": {"coordinates":[-122.474433,37.754749],"type":"Point"}
}