{
  "type": "Feature",
  "properties": {
    "iso:country":"US",
    "sg:address":"25542 Marguerite Pkwy",
    "sg:city":"Mission Viejo",
    "sg:classifiers":[
        {
            "category":"Restaurant",
            "type":"Food & Drink"
        }
    ],
    "sg:phone":"+1 949 770 7888",
    "sg:postcode":"92692",
    "sg:province":"CA",
    "wof:name":"Del Taco",
    "wof:placetype":"venue"
},
  "geometry": {"coordinates":[-117.659477,33.591473],"type":"Point"}
}