{
  "type": "Feature",
  "properties": {
    "iso:country":"US",
    "sg:address":"100 Medical Plz",
    "sg:city":"Los Angeles",
    "sg:classifiers":[
        {
            "category":"Health Services",
            "subcategory":"Doctor",
            "type":"Services"
        }
    ],
    "sg:phone":"+1 310 794 6399",
    "sg:postcode":"90001",
    "sg:province":"CA",
    "wof:name":"Tobinick Edward MD",
    "wof:placetype":"venue"
},
  "geometry": {"coordinates":[-118.24900100000001,33.9748],"type":"Point"}
}