{
  "type": "Feature",
  "properties": {
    "addr:full":"120 23rd St Costa Mesa CA 92627",
    "addr:housenumber":"120",
    "addr:postcode":"92627",
    "addr:street":"23Rd St",
    "iso:country":"US",
    "sg:address":"120 23rd St",
    "sg:city":"Costa Mesa",
    "sg:classifiers":[
        {
            "category":"Utilities",
            "subcategory":"Telephone",
            "type":"Services"
        }
    ],
    "sg:phone":"+1 714 321 2149",
    "sg:postcode":"92627",
    "sg:province":"CA",
    "sg:tags":[
        "communications"
    ],
    "wof:name":"Desktop Doc",
    "wof:placetype":"venue"
},
  "geometry": {"coordinates":[-117.905396,33.654472],"type":"Point"}
}