{
  "type": "Feature",
  "properties": {
    "addr:full":"3972 Barranca Pkwy Ste J Irvine CA 92606",
    "addr:housenumber":"3972",
    "addr:postcode":"92606",
    "addr:street":"Barranca Pkwy Ste J",
    "iso:country":"US",
    "sg:address":"3972 Barranca Pkwy Ste J",
    "sg:city":"Irvine",
    "sg:classifiers":[
        {
            "category":"Autos & Motor Vehicles",
            "subcategory":"Automobile Sales",
            "type":"Retail Goods"
        }
    ],
    "sg:phone":"+1 714 335 5984",
    "sg:postcode":"92606",
    "sg:province":"CA",
    "sg:tags":[
        "limo"
    ],
    "sg:website":"www.saturnlimousines.com#cid=yelp",
    "wof:name":"Saturn Limousine",
    "wof:placetype":"venue"
},
  "geometry": {"coordinates":[-117.81053799999999,33.68489],"type":"Point"}
}