{
  "type": "Feature",
  "properties": {
    "iso:country":"US",
    "sg:address":"808 N Azusa Ave",
    "sg:city":"West Covina",
    "sg:classifiers":[
        {
            "category":"Real Estate",
            "subcategory":"Real Estate Operator",
            "type":"Services"
        }
    ],
    "sg:phone":"+1 626 966 2644",
    "sg:postcode":"91791",
    "sg:province":"CA",
    "sg:tags":[
        "building",
        "apartment"
    ],
    "wof:name":"West Covina Keys",
    "wof:placetype":"venue"
},
  "geometry": {"coordinates":[-117.907767,34.084595],"type":"Point"}
}