{
  "type": "Feature",
  "properties": {
    "iso:country":"US",
    "sg:address":"182 E Merrill Ave",
    "sg:city":"Rialto",
    "sg:classifiers":[
        {
            "category":"Professional",
            "subcategory":"Business Services",
            "type":"Services"
        }
    ],
    "sg:phone":"+1 951 354 2341",
    "sg:postcode":"92376",
    "sg:province":"CA",
    "sg:tags":[
        "interior",
        "consultant",
        "design",
        "decorator"
    ],
    "wof:name":"Decor & You",
    "wof:placetype":"venue"
},
  "geometry": {"coordinates":[-117.36763500000001,34.09238],"type":"Point"}
}