{
  "type": "Feature",
  "properties": {
    "addr:full":"12921 166th St Cerritos CA 90703",
    "addr:housenumber":"12921",
    "addr:postcode":"ca 90703",
    "addr:street":"166Th St",
    "iso:country":"US",
    "sg:address":"12921 166th St",
    "sg:city":"Cerritos",
    "sg:classifiers":[
        {
            "category":"Professional",
            "subcategory":"Printing & Photocopies",
            "type":"Services"
        }
    ],
    "sg:phone":"+1 562 921 0202",
    "sg:postcode":"90703",
    "sg:province":"CA",
    "sg:tags":[
        "duplicating",
        "copying"
    ],
    "sg:website":"www.ibedigital.com",
    "wof:name":"International Business Equip",
    "wof:placetype":"venue"
},
  "geometry": {"coordinates":[-118.057107,33.880557],"type":"Point"}
}