{
  "type": "Feature",
  "properties": {
    "iso:country":"US",
    "sg:address":"6285 E Spring St",
    "sg:city":"Long Beach",
    "sg:classifiers":[
        {
            "category":"Insurance",
            "subcategory":"Insurance Agent",
            "type":"Services"
        }
    ],
    "sg:phone":"+1 562 420 7104",
    "sg:postcode":"90808",
    "sg:province":"CA",
    "sg:tags":[
        "accident"
    ],
    "wof:name":"DSR Insurance Svc",
    "wof:placetype":"venue"
},
  "geometry": {"coordinates":[-118.108665,33.810557],"type":"Point"}
}