{
  "type": "Feature",
  "properties": {
    "addr:full":"3977 Durock Rd Cameron Park CA 95682",
    "addr:housenumber":"3977",
    "addr:postcode":"95682",
    "addr:street":"Durock Rd;Park",
    "iso:country":"US",
    "sg:address":"3977 Durock Rd",
    "sg:city":"Cameron Park",
    "sg:classifiers":[
        {
            "category":"Shopping",
            "subcategory":"Gifts & Souvenirs",
            "type":"Retail Goods"
        }
    ],
    "sg:phone":"+1 530 677 2221",
    "sg:postcode":"95682",
    "sg:province":"CA",
    "sg:tags":[
        "shop"
    ],
    "wof:name":"Musical Moments & Collectibles",
    "wof:placetype":"venue"
},
  "geometry": {"coordinates":[-120.942916,38.660343],"type":"Point"}
}