{
  "type": "Feature",
  "properties": {
    "addr:full":"950 Sebastopol Rd Santa Rosa CA 95407",
    "addr:housenumber":"950",
    "addr:postcode":"95407",
    "addr:street":"Sebastopol Rd",
    "iso:country":"US",
    "sg:address":"950 Sebastopol Rd",
    "sg:city":"Santa Rosa",
    "sg:classifiers":[
        {
            "category":"Social Services",
            "subcategory":"Child Care",
            "type":"Services"
        }
    ],
    "sg:phone":"+1 707 545 4541",
    "sg:postcode":"95407",
    "sg:province":"CA",
    "sg:tags":[
        "kindergarten",
        "academic",
        "school"
    ],
    "wof:name":"Apples & Bananas Preschool",
    "wof:placetype":"venue"
},
  "geometry": {"coordinates":[-122.73159200000001,38.42903],"type":"Point"}
}