{
  "type": "Feature",
  "properties": {
    "addr:full":"503 5th Ave Alameda CA 94501",
    "addr:housenumber":"503",
    "addr:postcode":"94501",
    "addr:street":"5Th Ave",
    "iso:country":"US",
    "sg:address":"503 5th Ave",
    "sg:city":"Alameda",
    "sg:classifiers":[
        {
            "category":"Restaurant",
            "type":"Food & Drink"
        }
    ],
    "sg:phone":"+1 619 233 3166",
    "sg:postcode":"94501",
    "sg:province":"CA",
    "sg:tags":[
        "caribbean"
    ],
    "wof:name":"Cesar's Caribbean Tapas and Mojito Bar",
    "wof:placetype":"venue"
},
  "geometry": {"coordinates":[-122.282218,37.777381],"type":"Point"}
}