{
  "type": "Feature",
  "properties": {
    "addr:full":"11232 el Camino Real San Diego CA 92130",
    "addr:housenumber":"11232",
    "addr:postcode":"92130",
    "addr:street":"El Camino Real",
    "iso:country":"US",
    "sg:address":"11232 el Camino Real",
    "sg:city":"San Diego",
    "sg:classifiers":[
        {
            "category":"Professional",
            "subcategory":"Business Services",
            "type":"Services"
        }
    ],
    "sg:phone":"+1 858 314 1300",
    "sg:postcode":"92130",
    "sg:province":"CA",
    "sg:tags":[
        "broker"
    ],
    "wof:name":"Page Olson Business Brokers",
    "wof:placetype":"venue"
},
  "geometry": {"coordinates":[-117.230799,32.923382],"type":"Point"}
}