{
  "type": "Feature",
  "properties": {
    "iso:country":"US",
    "sg:address":"2406 Saint Elmo Dr",
    "sg:city":"San Bernardino",
    "sg:classifiers":[
        {
            "category":"Real Estate",
            "subcategory":"Real Estate Agent",
            "type":"Services"
        }
    ],
    "sg:phone":"+1 909 806 4008",
    "sg:postcode":"92410",
    "sg:province":"CA",
    "wof:name":"Best Properties Management",
    "wof:placetype":"venue"
},
  "geometry": {"coordinates":[-117.342855,34.109822],"type":"Point"}
}