{
  "type": "Feature",
  "properties": {
    "iso:country":"US",
    "sg:address":"1039 Green Street",
    "sg:city":"San Francisco",
    "sg:classifiers":[
        {
            "category":"Professional",
            "subcategory":"Lawyer & Legal Services",
            "type":"Services"
        }
    ],
    "sg:phone":"+1 415 765 9000",
    "sg:postcode":"94133",
    "sg:province":"CA",
    "wof:name":"Murphy Bartholomew",
    "wof:placetype":"venue"
},
  "geometry": {"coordinates":[-122.416526,37.798501],"type":"Point"}
}