{
  "type": "Feature",
  "properties": {
    "addr:full":"580 River St Santa Cruz CA 95060",
    "addr:housenumber":"580",
    "addr:postcode":"95060",
    "addr:street":"River St",
    "iso:country":"US",
    "sg:address":"580 River St",
    "sg:city":"Santa Cruz",
    "sg:classifiers":[
        {
            "category":"Food & Beverages",
            "subcategory":"Specialty",
            "type":"Retail Goods"
        }
    ],
    "sg:phone":"+1 831 459 7500",
    "sg:postcode":"95060",
    "sg:province":"CA",
    "sg:tags":[
        "vitamin"
    ],
    "wof:name":"General Nutrition Ctr",
    "wof:placetype":"venue"
},
  "geometry": {"coordinates":[-122.029573,36.982343],"type":"Point"}
}