{
  "type": "Feature",
  "properties": {
    "iso:country":"US",
    "sg:address":"23451 Madison St",
    "sg:city":"Torrance",
    "sg:classifiers":[
        {
            "category":"Health Services",
            "subcategory":"Doctor",
            "type":"Services"
        }
    ],
    "sg:phone":"+1 310 375 5437",
    "sg:postcode":"90505",
    "sg:province":"CA",
    "sg:tags":[
        "dentist"
    ],
    "wof:name":"Evangeline Shitabata DDS",
    "wof:placetype":"venue"
},
  "geometry": {"coordinates":[-118.34812,33.811127],"type":"Point"}
}