{
  "type": "Feature",
  "properties": {
    "iso:country":"US",
    "sg:address":"18520 Murphy Springs Ct",
    "sg:city":"Morgan Hill",
    "sg:classifiers":[
        {
            "category":"Professional",
            "subcategory":"Computer Services",
            "type":"Services"
        }
    ],
    "sg:phone":"+1 408 778 8316",
    "sg:postcode":"95037",
    "sg:province":"CA",
    "wof:name":"Rescuecom Of Northern Calif",
    "wof:placetype":"venue"
},
  "geometry": {"coordinates":[-121.671347,37.141428],"type":"Point"}
}