{
  "type": "Feature",
  "properties": {
    "addr:full":"21064 Country Park Rd Salinas CA 93908",
    "addr:housenumber":"21064",
    "addr:postcode":"93908",
    "addr:street":"Country Park Rd",
    "iso:country":"US",
    "sg:address":"21064 Country Park Rd",
    "sg:city":"Salinas",
    "sg:classifiers":[
        {
            "category":"Building & Trades",
            "subcategory":"Cleaning & Sanitation",
            "type":"Services"
        }
    ],
    "sg:phone":"+1 831 455 0465",
    "sg:postcode":"93908",
    "sg:province":"CA",
    "sg:tags":[
        "janitor"
    ],
    "wof:name":"R & O Cleaning",
    "wof:placetype":"venue"
},
  "geometry": {"coordinates":[-121.671947,36.620672],"type":"Point"}
}