{
  "type": "Feature",
  "properties": {
    "iso:country":"US",
    "sg:address":"6316 27th St",
    "sg:city":"Sacramento",
    "sg:classifiers":[
        {
            "category":"Utilities",
            "subcategory":"Mobile Phone",
            "type":"Services"
        }
    ],
    "sg:phone":"+1 916 395 5530",
    "sg:postcode":"95822",
    "sg:province":"CA",
    "sg:tags":[
        "telephone",
        "cellular"
    ],
    "wof:name":"Sacramento PCS",
    "wof:placetype":"venue"
},
  "geometry": {"coordinates":[-121.477505,38.51371],"type":"Point"}
}