{
  "type": "Feature",
  "properties": {
    "addr:full":"10566 Hole Ave Riverside CA 92505",
    "addr:housenumber":"10566",
    "addr:postcode":"92505",
    "addr:street":"Hole Ave",
    "iso:country":"US",
    "sg:address":"10566 Hole Ave",
    "sg:city":"Riverside",
    "sg:classifiers":[
        {
            "category":"Real Estate",
            "subcategory":"Real Estate Operator",
            "type":"Services"
        }
    ],
    "sg:phone":"+1 951 689 0555",
    "sg:postcode":"92505",
    "sg:province":"CA",
    "sg:tags":[
        "apartment"
    ],
    "wof:name":"River Glen Apartments",
    "wof:placetype":"venue"
},
  "geometry": {"coordinates":[-117.473057,33.916571],"type":"Point"}
}