{
  "type": "Feature",
  "properties": {
    "addr:full":"3520 Avondale Cir Carlsbad CA 92008",
    "addr:housenumber":"3520",
    "addr:postcode":"92008",
    "addr:street":"Avondale Cir",
    "iso:country":"US",
    "sg:address":"3520 Avondale Cir",
    "sg:city":"Carlsbad",
    "sg:classifiers":[
        {
            "category":"Manufacturing",
            "subcategory":"Toys & Sporting Goods",
            "type":"Manufacturing & Wholesale Goods"
        }
    ],
    "sg:phone":"+1 760 803 4935",
    "sg:postcode":"92008",
    "sg:province":"CA",
    "sg:tags":[
        "athletic",
        "equipment"
    ],
    "wof:name":"Par 3 Soccer",
    "wof:placetype":"venue"
},
  "geometry": {"coordinates":[-117.324584,33.164179],"type":"Point"}
}