{
  "type": "Feature",
  "properties": {
    "iso:country":"US",
    "sg:address":"25 Hillcrest Rd",
    "sg:city":"Berkeley",
    "sg:classifiers":[
        {
            "category":"Banks & Credit Unions",
            "subcategory":"Investment Brokerage",
            "type":"Services"
        }
    ],
    "sg:phone":"+1 510 654 8418",
    "sg:postcode":"94705",
    "sg:province":"CA",
    "sg:tags":[
        "trust"
    ],
    "wof:name":"Majorie Sperber Living Trust D",
    "wof:placetype":"venue"
},
  "geometry": {"coordinates":[-122.248363,37.852713],"type":"Point"}
}