{
  "type": "Feature",
  "properties": {
    "addr:full":"170 Grand Ave Pacific Grove CA 93950",
    "addr:housenumber":"170",
    "addr:postcode":"93950",
    "addr:street":"Grand Ave",
    "iso:country":"US",
    "sg:address":"170 Grand Ave",
    "sg:city":"Pacific Grove",
    "sg:classifiers":[
        {
            "category":"Professional",
            "type":"Services"
        }
    ],
    "sg:phone":"+1 831 375 1146",
    "sg:postcode":"93950",
    "sg:province":"CA",
    "sg:tags":[
        "arts",
        "artist"
    ],
    "wof:name":"Red Mill Studio & Gallery",
    "wof:placetype":"venue"
},
  "geometry": {"coordinates":[-121.917171,36.62122],"type":"Point"}
}