{
  "type": "Feature",
  "properties": {
    "addr:full":"1450 Frazee Rd Ste 210 San Diego CA 92108",
    "addr:housenumber":"1450",
    "addr:postcode":"92108",
    "addr:street":"Frazee Rd Ste 210",
    "iso:country":"US",
    "sg:address":"1450 Frazee Rd Ste 210",
    "sg:city":"San Diego",
    "sg:classifiers":[
        {
            "category":"Real Estate",
            "subcategory":"Real Estate Agent",
            "type":"Services"
        }
    ],
    "sg:phone":"+1 619 209 5500",
    "sg:postcode":"92108",
    "sg:province":"CA",
    "sg:website":"www.teamaguilar.com",
    "wof:name":"Team Aguilar Real Estate - AXIA",
    "wof:placetype":"venue"
},
  "geometry": {"coordinates":[-117.159153,32.773174],"type":"Point"}
}