{
  "type": "Feature",
  "properties": {
    "iso:country":"US",
    "sg:address":"1434 10th St",
    "sg:city":"Santa Monica",
    "sg:classifiers":[
        {
            "category":"Local Transit",
            "type":"Transportation"
        }
    ],
    "sg:phone":"+1 310 395 6174",
    "sg:postcode":"90401",
    "sg:province":"CA",
    "sg:tags":[
        "limousine"
    ],
    "wof:name":"Standout Limousine",
    "wof:placetype":"venue"
},
  "geometry": {"coordinates":[-118.488416,34.020095],"type":"Point"}
}