{
  "type": "Feature",
  "properties": {
    "addr:full":"27206 Calaroga Ave Hayward CA 94545",
    "addr:housenumber":"27206",
    "addr:postcode":"94545",
    "addr:street":"Calaroga Ave",
    "iso:country":"US",
    "sg:address":"27206 Calaroga Ave",
    "sg:city":"Hayward",
    "sg:classifiers":[
        {
            "category":"Health Services",
            "subcategory":"Doctor",
            "type":"Services"
        }
    ],
    "sg:phone":"+1 510 887 1777",
    "sg:postcode":"94545",
    "sg:province":"CA",
    "sg:tags":[
        "physician",
        "surgeon"
    ],
    "wof:name":"Gastroenterology Specialists",
    "wof:placetype":"venue"
},
  "geometry": {"coordinates":[-122.08981799999999,37.633513],"type":"Point"}
}