{
  "type": "Feature",
  "properties": {
    "iso:country":"US",
    "sg:address":"18751 Libra Cir",
    "sg:city":"Huntington Beach",
    "sg:classifiers":[
        {
            "category":"Wholesale",
            "subcategory":"Hardware",
            "type":"Manufacturing & Wholesale Goods"
        }
    ],
    "sg:phone":"+1 714 962 8816",
    "sg:postcode":"92646",
    "sg:province":"CA",
    "sg:tags":[
        "plumbing"
    ],
    "wof:name":"Easy Soft Water Products",
    "wof:placetype":"venue"
},
  "geometry": {"coordinates":[-117.987325,33.690959],"type":"Point"}
}