{
  "type": "Feature",
  "properties": {
    "addr:full":"350 Townsend St San Francisco CA 94107",
    "addr:housenumber":"350",
    "addr:postcode":"94107",
    "addr:street":"Townsend St",
    "iso:country":"US",
    "sg:address":"350 Townsend St",
    "sg:city":"San Francisco",
    "sg:classifiers":[
        {
            "category":"Professional",
            "subcategory":"Detective & Security Services",
            "type":"Services"
        }
    ],
    "sg:phone":"+1 415 284 1160",
    "sg:postcode":"94107",
    "sg:province":"CA",
    "sg:tags":[
        "investigator"
    ],
    "wof:name":"Elder Angels",
    "wof:placetype":"venue"
},
  "geometry": {"coordinates":[-122.397206,37.775332],"type":"Point"}
}