{
  "type": "Feature",
  "properties": {
    "addr:full":"161 Fashion Ln Tustin CA 92780",
    "addr:housenumber":"161",
    "addr:postcode":"92780",
    "addr:street":"Fashion Ln",
    "iso:country":"US",
    "sg:address":"161 Fashion Ln",
    "sg:city":"Tustin",
    "sg:classifiers":[
        {
            "category":"Education",
            "subcategory":"Dance Studio",
            "type":"Public Place"
        }
    ],
    "sg:phone":"+1 714 505 2800",
    "sg:postcode":"92780",
    "sg:province":"CA",
    "sg:tags":[
        "instruction",
        "dancing"
    ],
    "wof:name":"Fire Dance Grill Corp Office",
    "wof:placetype":"venue"
},
  "geometry": {"coordinates":[-117.817014,33.746423],"type":"Point"}
}