{
  "type": "Feature",
  "properties": {
    "iso:country":"US",
    "sg:address":"195 Glen Cove Marina Rd E",
    "sg:city":"Vallejo",
    "sg:classifiers":[
        {
            "category":"Health Services",
            "subcategory":"Doctor",
            "type":"Services"
        }
    ],
    "sg:phone":"+1 707 649 8000",
    "sg:postcode":"94591",
    "sg:province":"CA",
    "sg:tags":[
        "dentist"
    ],
    "wof:name":"Wah K Mark DDS",
    "wof:placetype":"venue"
},
  "geometry": {"coordinates":[-122.21259000000001,38.070902],"type":"Point"}
}