{
  "type": "Feature",
  "properties": {
    "addr:full":"2519 San Pablo Ave Oakland CA 94620",
    "addr:housenumber":"2519",
    "addr:postcode":"94620",
    "addr:street":"San Pablo Ave",
    "iso:country":"US",
    "sg:address":"2519 San Pablo Ave",
    "sg:city":"Oakland",
    "sg:classifiers":[
        {
            "category":"Arts & Performance",
            "subcategory":"Music",
            "type":"Entertainment"
        }
    ],
    "sg:postcode":"94620",
    "sg:province":"CA",
    "sg:tags":[
        "venue"
    ],
    "wof:name":"Ghost Town Gallery",
    "wof:placetype":"venue"
},
  "geometry": {"coordinates":[-122.275092,37.816027],"type":"Point"}
}