{
  "type": "Feature",
  "properties": {
    "iso:country":"US",
    "sg:address":"2395 Evergreen Street",
    "sg:city":"Sacramento",
    "sg:classifiers":[
        {
            "category":"Retail",
            "subcategory":"Auto Repair",
            "type":"Services"
        }
    ],
    "sg:phone":"+1 916 921 2280",
    "sg:postcode":"95815",
    "sg:province":"CA",
    "wof:name":"Ken's All Foreign Auto",
    "wof:placetype":"venue"
},
  "geometry": {"coordinates":[-121.44400899999999,38.609165],"type":"Point"}
}