{
  "type": "Feature",
  "properties": {
    "addr:full":"3240 Wilshire Blvd Ste 105 Los Angeles CA 90010",
    "addr:housenumber":"3240",
    "addr:postcode":"90010",
    "addr:street":"Wilshire Blvd Ste 105",
    "iso:country":"US",
    "sg:address":"3240 Wilshire Blvd Ste 105",
    "sg:city":"Los Angeles",
    "sg:classifiers":[
        {
            "category":"Personal",
            "subcategory":"Beauty Salon",
            "type":"Services"
        }
    ],
    "sg:phone":"+1 213 388 6262",
    "sg:postcode":"90010",
    "sg:province":"CA",
    "sg:tags":[
        "hair"
    ],
    "wof:name":"Lee Ka Ja",
    "wof:placetype":"venue"
},
  "geometry": {"coordinates":[-118.292534,34.060765],"type":"Point"}
}