{
  "type": "Feature",
  "properties": {
    "iso:country":"US",
    "sg:address":"14972 Crystal Cir",
    "sg:city":"Irvine",
    "sg:classifiers":[
        {
            "category":"Shopping",
            "subcategory":"Jewelry",
            "type":"Retail Goods"
        }
    ],
    "sg:phone":"+1 949 559 4116",
    "sg:postcode":"92604",
    "sg:province":"CA",
    "wof:name":"Queenbead",
    "wof:placetype":"venue"
},
  "geometry": {"coordinates":[-117.79057,33.698416],"type":"Point"}
}