{
  "type": "Feature",
  "properties": {
    "addr:full":"26544 Carmel Rancho Blvd Carmel CA 93923",
    "addr:housenumber":"26544",
    "addr:postcode":"93923",
    "addr:street":"Carmel Rancho Blvd",
    "iso:country":"US",
    "sg:address":"26544 Carmel Rancho Blvd",
    "sg:city":"Carmel",
    "sg:classifiers":[
        {
            "category":"Professional",
            "subcategory":"Printing & Photocopies",
            "type":"Services"
        }
    ],
    "sg:phone":"+1 831 622 9024",
    "sg:postcode":"93923",
    "sg:province":"CA",
    "wof:name":"Biztech Shipping and Copy C",
    "wof:placetype":"venue"
},
  "geometry": {"coordinates":[-121.904999,36.5387],"type":"Point"}
}