{
  "type": "Feature",
  "properties": {
    "addr:full":"1495 Sperring Rd Sonoma CA 95476",
    "addr:housenumber":"1495",
    "addr:postcode":"95476",
    "addr:street":"Sperring Rd",
    "iso:country":"US",
    "sg:address":"1495 Sperring Rd",
    "sg:city":"Sonoma",
    "sg:classifiers":[
        {
            "category":"Manufacturing",
            "subcategory":"Tools & Machinery",
            "type":"Manufacturing & Wholesale Goods"
        }
    ],
    "sg:phone":"+1 707 996 7932",
    "sg:postcode":"95476",
    "sg:province":"CA",
    "sg:tags":[
        "industrial",
        "mfg"
    ],
    "wof:name":"R&R Trk & Tractor Svc",
    "wof:placetype":"venue"
},
  "geometry": {"coordinates":[-122.498998,38.276959],"type":"Point"}
}