{
  "type": "Feature",
  "properties": {
    "iso:country":"US",
    "sg:address":"18219 Valley Blvd",
    "sg:city":"Bloomington",
    "sg:classifiers":[
        {
            "category":"Real Estate",
            "subcategory":"Real Estate Operator",
            "type":"Services"
        }
    ],
    "sg:phone":"+1 909 877 5243",
    "sg:postcode":"92316",
    "sg:province":"CA",
    "sg:tags":[
        "mobile",
        "home",
        "site",
        "community"
    ],
    "wof:name":"Bloomington Mobile Home Park",
    "wof:placetype":"venue"
},
  "geometry": {"coordinates":[-117.40928099999999,34.070367],"type":"Point"}
}