{
  "type": "Feature",
  "properties": {
    "addr:full":"1661 Soquel Dr Santa Cruz CA 95065",
    "addr:housenumber":"1661",
    "addr:postcode":"95065",
    "addr:street":"Soquel Dr",
    "iso:country":"US",
    "sg:address":"1661 Soquel Dr",
    "sg:city":"Santa Cruz",
    "sg:classifiers":[
        {
            "category":"Health Services",
            "subcategory":"Doctor",
            "type":"Services"
        }
    ],
    "sg:phone":"+1 831 476 7676",
    "sg:postcode":"95065",
    "sg:province":"CA",
    "sg:tags":[
        "physician",
        "surgeon"
    ],
    "sg:website":"www.harbormedicalgroup.yourmd.com",
    "wof:name":"Harbor Medical Group Inc",
    "wof:placetype":"venue"
},
  "geometry": {"coordinates":[-121.98206399999999,36.988938],"type":"Point"}
}