{
  "type": "Feature",
  "properties": {
    "iso:country":"US",
    "sg:address":"291 Lomita Ave",
    "sg:city":"San Bruno",
    "sg:classifiers":[
        {
            "category":"Building & Trades",
            "subcategory":"Construction",
            "type":"Services"
        }
    ],
    "sg:phone":"+1 650 583 1209",
    "sg:postcode":"94066",
    "sg:province":"CA",
    "sg:tags":[
        "contractor"
    ],
    "wof:name":"Navarrete Augusto Contractor",
    "wof:placetype":"venue"
},
  "geometry": {"coordinates":[-122.40799699999999,37.613602],"type":"Point"}
}