{
  "type": "Feature",
  "properties": {
    "addr:full":"900 N Broadway Santa Ana CA 92701",
    "addr:housenumber":"900",
    "addr:postcode":"92701",
    "addr:street":"N Broadway",
    "iso:country":"US",
    "sg:address":"900 N Broadway",
    "sg:city":"Santa Ana",
    "sg:classifiers":[
        {
            "category":"Professional",
            "subcategory":"Management & Consulting",
            "type":"Services"
        }
    ],
    "sg:phone":"+1 714 571 0382",
    "sg:postcode":"92701",
    "sg:province":"CA",
    "sg:tags":[
        "international",
        "business"
    ],
    "wof:name":"JETRO Santa Ana Shizuo",
    "wof:placetype":"venue"
},
  "geometry": {"coordinates":[-117.869778,33.751898],"type":"Point"}
}