{
  "type": "Feature",
  "properties": {
    "addr:full":"1906 E Valley Pkwy Escondido CA 92027",
    "addr:housenumber":"1906",
    "addr:postcode":"92027",
    "addr:street":"E Valley Pkwy",
    "iso:country":"US",
    "sg:address":"1906 E Valley Pkwy",
    "sg:city":"Escondido",
    "sg:classifiers":[
        {
            "category":"Retail",
            "subcategory":"Laundry & Dry Cleaning",
            "type":"Services"
        }
    ],
    "sg:phone":"+1 760 739 9868",
    "sg:postcode":"92027",
    "sg:province":"CA",
    "wof:name":"Continental Cleaners",
    "wof:placetype":"venue"
},
  "geometry": {"coordinates":[-117.360013,33.136833],"type":"Point"}
}