{
  "type": "Feature",
  "properties": {
    "addr:full":"13600 Sundowner Trl Lucerne Valley CA 92356",
    "addr:housenumber":"13600",
    "addr:postcode":"92356",
    "addr:street":"Sundowner Trl",
    "iso:country":"US",
    "sg:address":"13600 Sundowner Trl",
    "sg:city":"Lucerne Valley",
    "sg:classifiers":[
        {
            "category":"Retail",
            "subcategory":"Animal Services",
            "type":"Services"
        }
    ],
    "sg:phone":"+1 760 248 6107",
    "sg:postcode":"92356",
    "sg:province":"CA",
    "wof:name":"Thunderbird Ranch",
    "wof:placetype":"venue"
},
  "geometry": {"coordinates":[-117.037684,34.498083],"type":"Point"}
}