{
  "type": "Feature",
  "properties": {
    "addr:full":"3000 3rd St San Francisco CA 94107",
    "addr:housenumber":"3000",
    "addr:postcode":"94107",
    "addr:street":"3Rd St",
    "iso:country":"US",
    "sg:address":"3000 3rd St",
    "sg:city":"San Francisco",
    "sg:classifiers":[
        {
            "category":"Professional",
            "type":"Services"
        }
    ],
    "sg:phone":"+1 415 550 7273",
    "sg:postcode":"94107",
    "sg:province":"CA",
    "sg:tags":[
        "establishment"
    ],
    "wof:name":"Grabber San Francisco",
    "wof:placetype":"venue"
},
  "geometry": {"coordinates":[-122.387585,37.750263],"type":"Point"}
}