{
  "type": "Feature",
  "properties": {
    "addr:full":"837 5th St Santa Rosa CA 95404",
    "addr:housenumber":"837",
    "addr:postcode":"ca 95404",
    "addr:street":"5Th St",
    "iso:country":"US",
    "sg:address":"837 5th St",
    "sg:city":"Santa Rosa",
    "sg:classifiers":[
        {
            "category":"Professional",
            "type":"Services"
        }
    ],
    "sg:phone":"+1 707 546 8412",
    "sg:postcode":"95404",
    "sg:province":"CA",
    "wof:name":"Robert Sanoff",
    "wof:placetype":"venue"
},
  "geometry": {"coordinates":[-122.710296,38.443221],"type":"Point"}
}