{
  "type": "Feature",
  "properties": {
    "iso:country":"US",
    "sg:address":"7556 Fay Ave Ste E",
    "sg:city":"La Jolla",
    "sg:classifiers":[
        {
            "category":"Personal",
            "subcategory":"Skin Care",
            "type":"Services"
        }
    ],
    "sg:phone":"+1 858 456 2889",
    "sg:postcode":"92037",
    "sg:province":"CA",
    "sg:website":"www.beautymarkshop.com",
    "wof:name":"Beautymarkshop, Inc",
    "wof:placetype":"venue"
},
  "geometry": {"coordinates":[-117.274452,32.841324],"type":"Point"}
}