{
  "type": "Feature",
  "properties": {
    "addr:full":"724 Lyrelake Ct Sunnyvale CA 94089",
    "addr:housenumber":"724",
    "addr:postcode":"94089",
    "addr:street":"Lyrelake Ct",
    "iso:country":"US",
    "sg:address":"724 Lyrelake Ct",
    "sg:city":"Sunnyvale",
    "sg:classifiers":[
        {
            "category":"Professional",
            "type":"Services"
        }
    ],
    "sg:phone":"+1 408 745 9105",
    "sg:postcode":"94089",
    "sg:province":"CA",
    "wof:name":"Handy Hand Svc",
    "wof:placetype":"venue"
},
  "geometry": {"coordinates":[-122.00488,37.397113],"type":"Point"}
}