{
  "type": "Feature",
  "properties": {
    "iso:country":"US",
    "sg:address":"125 E Bristol Ln",
    "sg:city":"Orange",
    "sg:classifiers":[
        {
            "category":"Manufacturing",
            "subcategory":"Signs",
            "type":"Manufacturing & Wholesale Goods"
        }
    ],
    "sg:phone":"+1 714 283 8550",
    "sg:postcode":"92865",
    "sg:province":"CA",
    "wof:name":"Action Signs",
    "wof:placetype":"venue"
},
  "geometry": {"coordinates":[-117.85119,33.826839],"type":"Point"}
}