{
  "type": "Feature",
  "properties": {
    "iso:country":"US",
    "sg:address":"16133 Hollis St",
    "sg:city":"Hacienda Heights",
    "sg:classifiers":[
        {
            "category":"Professional",
            "type":"Services"
        }
    ],
    "sg:phone":"+1 626 333 9201",
    "sg:postcode":"91745",
    "sg:province":"CA",
    "wof:name":"Felix Wang",
    "wof:placetype":"venue"
},
  "geometry": {"coordinates":[-117.95661800000001,33.999228],"type":"Point"}
}