{
  "type": "Feature",
  "properties": {
    "addr:full":"1263 N Virgil Avenue Los Angeles CA 90029",
    "addr:housenumber":"1263",
    "addr:postcode":"90029",
    "addr:street":"N Virgil Avenue",
    "iso:country":"US",
    "sg:address":"1263 N Virgil Avenue",
    "sg:city":"Los Angeles",
    "sg:classifiers":[
        {
            "category":"Building & Trades",
            "subcategory":"Pest Control",
            "type":"Services"
        }
    ],
    "sg:phone":"+1 323 663 2023",
    "sg:postcode":"90029",
    "sg:province":"CA",
    "wof:name":"Guarantee Pest Control",
    "wof:placetype":"venue"
},
  "geometry": {"coordinates":[-118.286744,34.095558],"type":"Point"}
}