{
  "type": "Feature",
  "properties": {
    "iso:country":"US",
    "sg:address":"706 S Hill St",
    "sg:city":"Los Angeles",
    "sg:classifiers":[
        {
            "category":"Manufacturing",
            "subcategory":"Jewelry",
            "type":"Manufacturing & Wholesale Goods"
        }
    ],
    "sg:phone":"+1 213 627 8309",
    "sg:postcode":"90014",
    "sg:province":"CA",
    "sg:tags":[
        "mfg"
    ],
    "wof:name":"Exclusive Jewelry Designs",
    "wof:placetype":"venue"
},
  "geometry": {"coordinates":[-118.255658,34.044511],"type":"Point"}
}