{
  "type": "Feature",
  "properties": {
    "iso:country":"US",
    "sg:address":"13 E Plymouth St",
    "sg:city":"Long Beach",
    "sg:classifiers":[
        {
            "category":"Real Estate",
            "subcategory":"Real Estate Operator",
            "type":"Services"
        }
    ],
    "sg:phone":"+1 562 423 9177",
    "sg:postcode":"90805",
    "sg:province":"CA",
    "sg:tags":[
        "condominium"
    ],
    "wof:name":"Plymouth Rock Condo",
    "wof:placetype":"venue"
},
  "geometry": {"coordinates":[-118.193929,33.853375],"type":"Point"}
}