{
  "type": "Feature",
  "properties": {
    "iso:country":"US",
    "sg:address":"1734 N Verdugo Rd",
    "sg:city":"Glendale",
    "sg:classifiers":[
        {
            "category":"Shopping",
            "subcategory":"Antiques",
            "type":"Retail Goods"
        }
    ],
    "sg:phone":"+1 818 243 2720",
    "sg:postcode":"91208",
    "sg:province":"CA",
    "wof:name":"Dkw Enterprise",
    "wof:placetype":"venue"
},
  "geometry": {"coordinates":[-118.22640199999999,34.173321],"type":"Point"}
}