{
  "type": "Feature",
  "properties": {
    "iso:country":"US",
    "sg:address":"30551 Red Mountain Rd",
    "sg:city":"Hemet",
    "sg:classifiers":[
        {
            "category":"Retail",
            "subcategory":"Repair Shop",
            "type":"Services"
        }
    ],
    "sg:phone":"+1 951 767 2206",
    "sg:postcode":"92544",
    "sg:province":"CA",
    "sg:tags":[
        "upholsterer"
    ],
    "wof:name":"M D Swindell Upholstery",
    "wof:placetype":"venue"
},
  "geometry": {"coordinates":[-116.901917,33.617825],"type":"Point"}
}