{
  "type": "Feature",
  "properties": {
    "iso:country":"US",
    "sg:address":"400 Montgomery Street",
    "sg:city":"San Francisco",
    "sg:classifiers":[
        {
            "category":"Professional",
            "subcategory":"Lawyer & Legal Services",
            "type":"Services"
        }
    ],
    "sg:phone":"+1 415 399 0800",
    "sg:postcode":"94104",
    "sg:province":"CA",
    "wof:name":"Mazzocone Michael A Atty",
    "wof:placetype":"venue"
},
  "geometry": {"coordinates":[-122.40300000000001,37.7929],"type":"Point"}
}