{
  "type": "Feature",
  "properties": {
    "addr:full":"6952 Trabuco Rd Irvine CA 92618",
    "addr:housenumber":"6952",
    "addr:postcode":"92618",
    "addr:street":"Trabuco Rd",
    "iso:country":"US",
    "sg:address":"6952 Trabuco Rd",
    "sg:city":"Irvine",
    "sg:classifiers":[
        {
            "category":"Retail",
            "subcategory":"Auto Repair",
            "type":"Services"
        }
    ],
    "sg:phone":"+1 949 551 2030",
    "sg:postcode":"92618",
    "sg:province":"CA",
    "sg:tags":[
        "recreational",
        "vehicle"
    ],
    "wof:name":"Giant Rv",
    "wof:placetype":"venue"
},
  "geometry": {"coordinates":[-117.718846,33.680299],"type":"Point"}
}