{
  "type": "Feature",
  "properties": {
    "addr:full":"3324 Castle Heights Avenue Ofc Los Angeles CA 90034",
    "addr:housenumber":"3324",
    "addr:postcode":"90034",
    "addr:street":"Castle Heights Avenue",
    "iso:country":"US",
    "sg:address":"3324 Castle Heights Avenue Ofc",
    "sg:city":"Los Angeles",
    "sg:classifiers":[
        {
            "category":"Real Estate",
            "subcategory":"Real Estate Operator",
            "type":"Services"
        }
    ],
    "sg:phone":"+1 310 280 0692",
    "sg:postcode":"90034",
    "sg:province":"CA",
    "sg:tags":[
        "apartment"
    ],
    "wof:name":"Waterstone & At Chevrot Hills",
    "wof:placetype":"venue"
},
  "geometry": {"coordinates":[-118.40000499999999,34.031005],"type":"Point"}
}