{
  "type": "Feature",
  "properties": {
    "iso:country":"US",
    "sg:address":"3961 Sepulveda Blvd",
    "sg:city":"Culver City",
    "sg:classifiers":[
        {
            "category":"Professional",
            "subcategory":"Accounting & Tax Preparation",
            "type":"Services"
        }
    ],
    "sg:phone":"+1 310 398 5414",
    "sg:postcode":"90230",
    "sg:province":"CA",
    "sg:tags":[
        "return",
        "filing"
    ],
    "wof:name":"Financial Management System",
    "wof:placetype":"venue"
},
  "geometry": {"coordinates":[-118.415304,34.010471],"type":"Point"}
}