{
  "type": "Feature",
  "properties": {
    "addr:full":"591 Camino De La Reina Ste 100 San Diego CA 92108",
    "addr:housenumber":"591",
    "addr:postcode":"92108",
    "addr:street":"Camino De La Reina Ste 100",
    "iso:country":"US",
    "sg:address":"591 Camino De La Reina Ste 100",
    "sg:city":"San Diego",
    "sg:classifiers":[
        {
            "category":"Real Estate",
            "subcategory":"Real Estate Services",
            "type":"Services"
        }
    ],
    "sg:phone":"+1 858 232 5976",
    "sg:postcode":"92108",
    "sg:province":"CA",
    "sg:website":"www.corinthiantitle.com",
    "wof:name":"Greg Ives- Corinthian Title",
    "wof:placetype":"venue"
},
  "geometry": {"coordinates":[-117.161432,32.765674],"type":"Point"}
}