{
  "type": "Feature",
  "properties": {
    "addr:full":"2601 Colorado Ave Santa Monica CA 90404",
    "addr:housenumber":"2601",
    "addr:postcode":"90404",
    "addr:street":"Colorado Ave",
    "iso:country":"US",
    "sg:address":"2601 Colorado Ave",
    "sg:city":"Santa Monica",
    "sg:classifiers":[
        {
            "category":"Professional",
            "type":"Services"
        }
    ],
    "sg:phone":"+1 310 230 6561",
    "sg:postcode":"90404",
    "sg:province":"CA",
    "wof:name":"Play It Inc",
    "wof:placetype":"venue"
},
  "geometry": {"coordinates":[-118.470665,34.031028],"type":"Point"}
}