{
  "type": "Feature",
  "properties": {
    "iso:country":"US",
    "sg:address":"10554 Progress Way",
    "sg:city":"Cypress",
    "sg:classifiers":[
        {
            "category":"Professional",
            "subcategory":"Lawyer & Legal Services",
            "type":"Services"
        }
    ],
    "sg:phone":"+1 714 821 1910",
    "sg:postcode":"90630",
    "sg:province":"CA",
    "sg:tags":[
        "laboratory",
        "attorney",
        "testing",
        "bureau"
    ],
    "sg:website":"http://www.centralmedlab.com/",
    "wof:name":"Central Medical Laboratory",
    "wof:placetype":"venue"
},
  "geometry": {"coordinates":[-118.035601,33.809175],"type":"Point"}
}