{
  "type": "Feature",
  "properties": {
    "addr:full":"6839 Buckingham Blvd Berkeley CA 94705",
    "addr:housenumber":"6839",
    "addr:postcode":"94705",
    "addr:street":"Buckingham Blvd",
    "iso:country":"US",
    "sg:address":"6839 Buckingham Blvd",
    "sg:city":"Berkeley",
    "sg:classifiers":[
        {
            "category":"Real Estate",
            "subcategory":"Real Estate Agent",
            "type":"Services"
        }
    ],
    "sg:phone":"+1 510 845 3388",
    "sg:postcode":"94705",
    "sg:province":"CA",
    "wof:name":"Bergman Properties",
    "wof:placetype":"venue"
},
  "geometry": {"coordinates":[-122.224975,37.857763],"type":"Point"}
}