{
  "type": "Feature",
  "properties": {
    "addr:full":"19738 Bassett St Winnetka CA 91306",
    "addr:housenumber":"19738",
    "addr:postcode":"91306",
    "addr:street":"Bassett St",
    "iso:country":"US",
    "sg:address":"19738 Bassett St",
    "sg:city":"Winnetka",
    "sg:classifiers":[
        {
            "category":"Manufacturing",
            "subcategory":"Printing",
            "type":"Manufacturing & Wholesale Goods"
        }
    ],
    "sg:phone":"+1 818 887 3658",
    "sg:postcode":"91306",
    "sg:province":"CA",
    "sg:tags":[
        "publishing"
    ],
    "wof:name":"Chunks O Music",
    "wof:placetype":"venue"
},
  "geometry": {"coordinates":[-118.564554,34.195945],"type":"Point"}
}