{
  "type": "Feature",
  "properties": {
    "iso:country":"US",
    "sg:address":"1948 W Collins Ave",
    "sg:city":"Orange",
    "sg:phone":"+1 714 639 9981",
    "sg:postcode":"92867",
    "sg:province":"CA",
    "sg:website":"http://www.countyair.com",
    "wof:name":"County Heating And Air Conditioning Inc.",
    "wof:placetype":"venue"
},
  "geometry": {"coordinates":[-117.873446,33.802441],"type":"Point"}
}