{
  "type": "Feature",
  "properties": {
    "addr:full":"19800 Hawthorne Blvd Torrance CA 90503",
    "addr:housenumber":"19800",
    "addr:postcode":"90503",
    "addr:street":"Hawthorne Blvd",
    "iso:country":"US",
    "sg:address":"19800 Hawthorne Blvd",
    "sg:city":"Torrance",
    "sg:classifiers":[
        {
            "category":"Shopping",
            "subcategory":"Gifts & Souvenirs",
            "type":"Retail Goods"
        }
    ],
    "sg:phone":"+1 310 406 3004",
    "sg:postcode":"90503",
    "sg:province":"CA",
    "sg:tags":[
        "shop"
    ],
    "wof:name":"Tuesday Morning",
    "wof:placetype":"venue"
},
  "geometry": {"coordinates":[-118.353593,33.851489],"type":"Point"}
}