{
  "type": "Feature",
  "properties": {
    "addr:full":"2302 Rim Rd Duarte CA 91008",
    "addr:housenumber":"2302",
    "addr:postcode":"91008",
    "addr:street":"Rim Rd",
    "iso:country":"US",
    "sg:address":"2302 Rim Rd",
    "sg:city":"Duarte",
    "sg:classifiers":[
        {
            "category":"Building & Trades",
            "subcategory":"Electrical",
            "type":"Services"
        }
    ],
    "sg:phone":"+1 626 358 0118",
    "sg:postcode":"91008",
    "sg:province":"CA",
    "wof:name":"Bmh Electric",
    "wof:placetype":"venue"
},
  "geometry": {"coordinates":[-117.953255,34.152408],"type":"Point"}
}