{
  "type": "Feature",
  "properties": {
    "iso:country":"US",
    "sg:address":"4516 N Washington Rd",
    "sg:city":"Turlock",
    "sg:classifiers":[
        {
            "category":"Retail",
            "subcategory":"Auto Repair",
            "type":"Services"
        }
    ],
    "sg:phone":"+1 209 678 0832",
    "sg:postcode":"95380",
    "sg:province":"CA",
    "sg:tags":[
        "automobile",
        "restoration",
        "classic"
    ],
    "wof:name":"H & H Restorations",
    "wof:placetype":"venue"
},
  "geometry": {"coordinates":[-120.902777,37.531351],"type":"Point"}
}