{
  "type": "Feature",
  "properties": {
    "addr:full":"5225 Lindley Ave Tarzana CA 91356",
    "addr:housenumber":"5225",
    "addr:postcode":"91356",
    "addr:street":"Lindley Ave",
    "iso:country":"US",
    "sg:address":"5225 Lindley Ave",
    "sg:city":"Tarzana",
    "sg:classifiers":[
        {
            "category":"Personal",
            "subcategory":"Beauty Salon",
            "type":"Services"
        }
    ],
    "sg:phone":"+1 818 996 8366",
    "sg:postcode":"91356",
    "sg:province":"CA",
    "sg:tags":[
        "manicuring"
    ],
    "wof:name":"Number One Nails Salon",
    "wof:placetype":"venue"
},
  "geometry": {"coordinates":[-118.527232,34.165506],"type":"Point"}
}