{
  "type": "Feature",
  "properties": {
    "iso:country":"US",
    "sg:address":"1421 S 4th St",
    "sg:city":"Alhambra",
    "sg:classifiers":[
        {
            "category":"Building & Trades",
            "subcategory":"Plumbing",
            "type":"Services"
        }
    ],
    "sg:phone":"+1 626 282 4540",
    "sg:postcode":"91803",
    "sg:province":"CA",
    "sg:tags":[
        "plumbing",
        "contractor"
    ],
    "wof:name":"A-1 Apache Plumbing",
    "wof:placetype":"venue"
},
  "geometry": {"coordinates":[-118.126837,34.076241],"type":"Point"}
}