{
  "type": "Feature",
  "properties": {
    "addr:full":"1421 S 4th St Alhambra CA 91803",
    "addr:housenumber":"1421",
    "addr:postcode":"91803",
    "addr:street":"S 4Th St",
    "iso:country":"US",
    "sg:address":"1421 S 4th St",
    "sg:city":"Alhambra",
    "sg:classifiers":[
        {
            "category":"Building & Trades",
            "subcategory":"Plumbing",
            "type":"Services"
        }
    ],
    "sg:phone":"+1 626 282 4540",
    "sg:postcode":"91803",
    "sg:province":"CA",
    "sg:tags":[
        "plumbing",
        "contractor"
    ],
    "wof:name":"A-1 Apache Plumbing",
    "wof:placetype":"venue"
},
  "geometry": {"coordinates":[-118.12683699999999,34.076241],"type":"Point"}
}