{
  "type": "Feature",
  "properties": {
    "addr:full":"9850 Genesee Ave San Diego CA 92122",
    "addr:housenumber":"9850",
    "addr:postcode":"92122",
    "addr:street":"Genesee Ave",
    "iso:country":"US",
    "sg:address":"9850 Genesee Ave",
    "sg:city":"San Diego",
    "sg:classifiers":[
        {
            "category":"Health Services",
            "subcategory":"Medical Lab",
            "type":"Services"
        }
    ],
    "sg:phone":"+1 858 453 5235",
    "sg:postcode":"92122",
    "sg:province":"CA",
    "sg:tags":[
        "laboratory"
    ],
    "wof:name":"Laboratory Corporation America",
    "wof:placetype":"venue"
},
  "geometry": {"coordinates":[-117.21871299999999,32.881072],"type":"Point"}
}