{
  "type": "Feature",
  "properties": {
    "iso:country":"US",
    "sg:address":"1400 5th Ave",
    "sg:city":"San Rafael",
    "sg:classifiers":[
        {
            "category":"Government",
            "subcategory":"Police Station",
            "type":"Public Place"
        }
    ],
    "sg:phone":"+1 415 485 3000",
    "sg:postcode":"94901",
    "sg:province":"CA",
    "sg:tags":[
        "department"
    ],
    "sg:website":"www.srpd.org",
    "wof:name":"San Rafael Police Dept",
    "wof:placetype":"venue"
},
  "geometry": {"coordinates":[-122.533096,37.974638],"type":"Point"}
}