{
  "type": "Feature",
  "properties": {
    "addr:full":"348 Shaw Rd S San Francisco CA 94080",
    "addr:housenumber":"348",
    "addr:postcode":"94080",
    "addr:street":"Shaw Rd S",
    "iso:country":"US",
    "sg:address":"348 Shaw Rd",
    "sg:city":"S San Francisco",
    "sg:classifiers":[
        {
            "category":"Freight",
            "type":"Transportation"
        }
    ],
    "sg:phone":"+1 650 583 1128",
    "sg:postcode":"94080",
    "sg:province":"CA",
    "sg:tags":[
        "warehouse",
        "self",
        "storage"
    ],
    "wof:name":"M & T Storage Co",
    "wof:placetype":"venue"
},
  "geometry": {"coordinates":[-122.405783,37.636252],"type":"Point"}
}