{
  "type": "Feature",
  "properties": {
    "addr:full":"1820 Diesel Dr Ste 40 Sacramento CA 95838",
    "addr:housenumber":"1820",
    "addr:postcode":"95838",
    "addr:street":"Diesel Dr Ste 40",
    "iso:country":"US",
    "sg:address":"1820 Diesel Dr Ste 40",
    "sg:city":"Sacramento",
    "sg:classifiers":[
        {
            "category":"Shopping",
            "subcategory":"Stationery & Office Supplies",
            "type":"Retail Goods"
        },
        {
            "category":"Manufacturing",
            "subcategory":"Paper Products",
            "type":"Manufacturing & Wholesale Goods"
        }
    ],
    "sg:phone":"+1 916 923 2971",
    "sg:postcode":"95838",
    "sg:province":"CA",
    "sg:tags":[
        "marking",
        "products-wholesale",
        "coding",
        "equipment",
        "manufacturer"
    ],
    "sg:website":"http://www.allmarkingproducts.com",
    "wof:name":"Marking Products Inc.",
    "wof:placetype":"venue"
},
  "geometry": {"coordinates":[-121.423506,38.64911],"type":"Point"}
}