{
  "type": "Feature",
  "properties": {
    "iso:country":"US",
    "sg:address":"9364 W Ave G",
    "sg:city":"Lancaster",
    "sg:classifiers":[
        {
            "category":"Building & Trades",
            "subcategory":"Landscaping Services",
            "type":"Services"
        }
    ],
    "sg:phone":"+1 661 942 4683",
    "sg:postcode":"93536",
    "sg:province":"CA",
    "wof:name":"Reca Landscape Maintenance",
    "wof:placetype":"venue"
},
  "geometry": {"coordinates":[-118.294912,34.732752],"type":"Point"}
}