{
  "type": "Feature",
  "properties": {
    "iso:country":"US",
    "sg:address":"1094 Dwight Way",
    "sg:city":"Berkeley",
    "sg:classifiers":[
        {
            "category":"Professional",
            "subcategory":"Art Services",
            "type":"Services"
        }
    ],
    "sg:phone":"+1 510 524 2907",
    "sg:postcode":"94710",
    "sg:province":"CA",
    "sg:tags":[
        "interior",
        "designer",
        "decorator"
    ],
    "wof:name":"Jean Flynn Interior Decorating",
    "wof:placetype":"venue"
},
  "geometry": {"coordinates":[-122.28966800000001,37.861073],"type":"Point"}
}