{
  "type": "Feature",
  "properties": {
    "addr:full":"1074 Cherry Ave San Jose CA 95125",
    "addr:housenumber":"1074",
    "addr:postcode":"95125",
    "addr:street":"Cherry Ave",
    "iso:country":"US",
    "sg:address":"1074 Cherry Ave",
    "sg:city":"San Jose",
    "sg:classifiers":[
        {
            "category":"Professional",
            "subcategory":"Management & Consulting",
            "type":"Services"
        }
    ],
    "sg:phone":"+1 408 977 3129",
    "sg:postcode":"95125",
    "sg:province":"CA",
    "wof:name":"DHooghe Dries Consulting",
    "wof:placetype":"venue"
},
  "geometry": {"coordinates":[-121.907822,37.308008],"type":"Point"}
}