{
  "type": "Feature",
  "properties": {
    "iso:country":"US",
    "sg:address":"3077 State St",
    "sg:city":"Carlsbad",
    "sg:classifiers":[
        {
            "category":"Professional",
            "type":"Services"
        }
    ],
    "sg:phone":"+1 760 729 1596",
    "sg:postcode":"92008",
    "sg:province":"CA",
    "wof:name":"Animecafe Corporation",
    "wof:placetype":"venue"
},
  "geometry": {"coordinates":[-117.348172,33.158852],"type":"Point"}
}