{
  "type": "Feature",
  "properties": {
    "addr:full":"3077 State St Carlsbad CA 92008",
    "addr:housenumber":"3077",
    "addr:postcode":"92008",
    "addr:street":"State St",
    "iso:country":"US",
    "sg:address":"3077 State St",
    "sg:city":"Carlsbad",
    "sg:classifiers":[
        {
            "category":"Professional",
            "type":"Services"
        }
    ],
    "sg:phone":"+1 760 729 1596",
    "sg:postcode":"92008",
    "sg:province":"CA",
    "wof:name":"Animecafe Corporation",
    "wof:placetype":"venue"
},
  "geometry": {"coordinates":[-117.34817200000001,33.158852],"type":"Point"}
}