{
  "type": "Feature",
  "properties": {
    "iso:country":"US",
    "sg:address":"222 W 6th St",
    "sg:city":"San Pedro",
    "sg:classifiers":[
        {
            "category":"Professional",
            "subcategory":"Computer Services",
            "type":"Services"
        }
    ],
    "sg:phone":"+1 310 831 0611",
    "sg:postcode":"90731",
    "sg:province":"CA",
    "sg:tags":[
        "design",
        "integrated",
        "system"
    ],
    "sg:website":"www.litg.com",
    "wof:name":"Northrop Grumman Corp",
    "wof:placetype":"venue"
},
  "geometry": {"coordinates":[-118.28135399999999,33.738734],"type":"Point"}
}