{
  "type": "Feature",
  "properties": {
    "iso:country":"US",
    "sg:address":"10700 Idaho Ave",
    "sg:city":"Hanford",
    "sg:classifiers":[
        {
            "category":"Wholesale",
            "subcategory":"Auto Parts",
            "type":"Manufacturing & Wholesale Goods"
        }
    ],
    "sg:phone":"+1 559 583 2800",
    "sg:postcode":"93230",
    "sg:province":"CA",
    "sg:tags":[
        "tire"
    ],
    "wof:name":"Pirelli Armstrong Tire Co",
    "wof:placetype":"venue"
},
  "geometry": {"coordinates":[-119.64881800000001,36.269418],"type":"Point"}
}