{
  "type": "Feature",
  "properties": {
    "addr:full":"Bay St and Eagle St Alameda CA 94501",
    "addr:postcode":"94501",
    "addr:street":"St;Eagle St",
    "iso:country":"US",
    "sg:address":"Bay St and Eagle St",
    "sg:city":"Alameda",
    "sg:classifiers":[
        {
            "category":"Park",
            "type":"Public Place"
        }
    ],
    "sg:postcode":"94501",
    "sg:province":"CA",
    "wof:name":"Bay-Eagle Community Garden",
    "wof:placetype":"venue"
},
  "geometry": {"coordinates":[-122.264369,37.777888],"type":"Point"}
}