{
  "type": "Feature",
  "properties": {
    "iso:country":"US",
    "sg:address":"12422 Central Ave",
    "sg:city":"Chino",
    "sg:classifiers":[
        {
            "category":"Home & Garden",
            "subcategory":"Carpets & Floor Coverings",
            "type":"Retail Goods"
        }
    ],
    "sg:phone":"+1 909 464 1300",
    "sg:postcode":"91710",
    "sg:province":"CA",
    "sg:tags":[
        "dealer",
        "rug"
    ],
    "wof:name":"Budget Floor Design",
    "wof:placetype":"venue"
},
  "geometry": {"coordinates":[-117.689459,34.026744],"type":"Point"}
}