{
  "type": "Feature",
  "properties": {
    "iso:country":"US",
    "sg:address":"17 7th St",
    "sg:city":"Hermosa Beach",
    "sg:classifiers":[
        {
            "category":"Health Services",
            "subcategory":"Hospital",
            "type":"Services"
        }
    ],
    "sg:phone":"+1 310 379 3366",
    "sg:postcode":"90254",
    "sg:province":"CA",
    "sg:tags":[
        "mental"
    ],
    "wof:name":"Behavior Frontiers",
    "wof:placetype":"venue"
},
  "geometry": {"coordinates":[-118.399072,33.858587],"type":"Point"}
}