{
  "type": "Feature",
  "properties": {
    "addr:full":"200 Larkin St San Francisco CA 94102",
    "addr:housenumber":"200",
    "addr:postcode":"94102",
    "addr:street":"Larkin St",
    "iso:country":"US",
    "sg:address":"200 Larkin St",
    "sg:city":"San Francisco",
    "sg:classifiers":[
        {
            "category":"Cafe",
            "type":"Food & Drink"
        }
    ],
    "sg:menulink":"http://www.allmenus.com/ca/san-francisco/276223-cafe-asia/menu/",
    "sg:phone":"+1 415 581 3630",
    "sg:postcode":"94102",
    "sg:province":"CA",
    "sg:tags":[
        "thai",
        "vietnamese",
        "japanese",
        "chinese",
        "asian"
    ],
    "wof:name":"Cafe Asia",
    "wof:placetype":"venue"
},
  "geometry": {"coordinates":[-122.41672699999999,37.779561],"type":"Point"}
}