{
  "type": "Feature",
  "properties": {
    "addr:full":"1506 E 1st St Los Angeles CA 90033",
    "addr:housenumber":"1506",
    "addr:postcode":"90033",
    "addr:street":"E 1St St",
    "iso:country":"US",
    "sg:address":"1506 E 1st St",
    "sg:city":"Los Angeles",
    "sg:classifiers":[
        {
            "category":"Food & Beverages",
            "subcategory":"Bakery",
            "type":"Retail Goods"
        }
    ],
    "sg:phone":"+1 323 780 9640",
    "sg:postcode":"90033",
    "sg:province":"CA",
    "sg:tags":[
        "baker"
    ],
    "wof:name":"San Rafael Bakery",
    "wof:placetype":"venue"
},
  "geometry": {"coordinates":[-118.222939,34.047355],"type":"Point"}
}