{
  "type": "Feature",
  "properties": {
    "iso:country":"US",
    "sg:address":"930 S Andreasen Dr",
    "sg:city":"Escondido",
    "sg:classifiers":[
        {
            "category":"Building & Trades",
            "subcategory":"Electrical",
            "type":"Services"
        }
    ],
    "sg:phone":"+1 951 719 1447",
    "sg:postcode":"92029",
    "sg:province":"CA",
    "sg:tags":[
        "electric",
        "contractor"
    ],
    "wof:name":"Elzinga & Volkers Electrical",
    "wof:placetype":"venue"
},
  "geometry": {"coordinates":[-117.11548500000001,33.112855],"type":"Point"}
}