{
  "type": "Feature",
  "properties": {
    "addr:full":"6161 Hart Ave Temple City CA 91780",
    "addr:housenumber":"6161",
    "addr:postcode":"91780",
    "addr:street":"Hart Ave",
    "iso:country":"US",
    "sg:address":"6161 Hart Ave",
    "sg:city":"Temple City",
    "sg:classifiers":[
        {
            "category":"Building & Trades",
            "subcategory":"Construction",
            "type":"Services"
        }
    ],
    "sg:phone":"+1 626 287 4417",
    "sg:postcode":"91780",
    "sg:province":"CA",
    "sg:tags":[
        "residential"
    ],
    "wof:name":"Dale A Shaffer",
    "wof:placetype":"venue"
},
  "geometry": {"coordinates":[-118.07093999999999,34.112279],"type":"Point"}
}