{
  "type": "Feature",
  "properties": {
    "iso:country":"US",
    "sg:address":"14548 Baseline Ave",
    "sg:city":"Fontana",
    "sg:classifiers":[
        {
            "category":"Personal",
            "subcategory":"Beauty Salon",
            "type":"Services"
        }
    ],
    "sg:phone":"+1 909 355 3316",
    "sg:postcode":"92336",
    "sg:province":"CA",
    "wof:name":"Hair Charisma",
    "wof:placetype":"venue"
},
  "geometry": {"coordinates":[-117.48523299999999,34.121506],"type":"Point"}
}