{
  "type": "Feature",
  "properties": {
    "addr:full":"1525 Union Ave Fairfield CA 94533",
    "addr:housenumber":"1525",
    "addr:postcode":"94533",
    "addr:street":"Union Ave",
    "iso:country":"US",
    "sg:address":"1525 Union Ave",
    "sg:city":"Fairfield",
    "sg:classifiers":[
        {
            "category":"Organizations",
            "subcategory":"Non-profit Organization",
            "type":"Services"
        }
    ],
    "sg:phone":"+1 707 435 1804",
    "sg:postcode":"94533",
    "sg:province":"CA",
    "sg:tags":[
        "information",
        "alcoholism",
        "treatment"
    ],
    "wof:name":"Archway Recovery Svc",
    "wof:placetype":"venue"
},
  "geometry": {"coordinates":[-122.040499,38.257814],"type":"Point"}
}