{
  "type": "Feature",
  "properties": {
    "iso:country":"US",
    "sg:address":"1306 W Francisquito Ave",
    "sg:city":"West Covina",
    "sg:classifiers":[
        {
            "category":"Shopping",
            "subcategory":"Discount & Variety Stores",
            "type":"Retail Goods"
        }
    ],
    "sg:phone":"+1 626 918 5898",
    "sg:postcode":"91744",
    "sg:province":"CA",
    "sg:tags":[
        "merchandise",
        "general"
    ],
    "wof:name":"Mega Bargains 98 Plus",
    "wof:placetype":"venue"
},
  "geometry": {"coordinates":[-117.95294,34.052839],"type":"Point"}
}