{
  "type": "Feature",
  "properties": {
    "iso:country":"US",
    "sg:address":"1005 E Colorado Blvd Ste 209",
    "sg:city":"Pasadena",
    "sg:classifiers":[
        {
            "category":"Communications",
            "type":"Services"
        }
    ],
    "sg:phone":"+1 626 795 1885",
    "sg:postcode":"91106",
    "sg:province":"CA",
    "sg:tags":[
        "web",
        "design"
    ],
    "sg:website":"www.visibletheory.com",
    "wof:name":"Visible Theory",
    "wof:placetype":"venue"
},
  "geometry": {"coordinates":[-118.129329,34.145904],"type":"Point"}
}