{
  "type": "Feature",
  "properties": {
    "addr:full":"1102 S B St San Mateo CA 94401",
    "addr:housenumber":"1102",
    "addr:postcode":"94401",
    "addr:street":"S B St",
    "iso:country":"US",
    "sg:address":"1102 S B St",
    "sg:city":"San Mateo",
    "sg:classifiers":[
        {
            "category":"Food & Beverages",
            "subcategory":"Specialty",
            "type":"Retail Goods"
        }
    ],
    "sg:phone":"+1 650 341 9484",
    "sg:postcode":"94401",
    "sg:province":"CA",
    "sg:tags":[
        "vitamin"
    ],
    "wof:name":"Nutrition For Life Business",
    "wof:placetype":"venue"
},
  "geometry": {"coordinates":[-122.315037,37.558884],"type":"Point"}
}