{
  "type": "Feature",
  "properties": {
    "addr:full":"446 N Glassell St Orange CA 92866",
    "addr:housenumber":"446",
    "addr:postcode":"92866",
    "addr:street":"N Glassell St",
    "iso:country":"US",
    "sg:address":"446 N Glassell St",
    "sg:city":"Orange",
    "sg:classifiers":[
        {
            "category":"Personal",
            "subcategory":"Barber",
            "type":"Services"
        }
    ],
    "sg:phone":"+1 714 771 0411",
    "sg:postcode":"92866",
    "sg:province":"CA",
    "wof:name":"Ray's Barber Shop",
    "wof:placetype":"venue"
},
  "geometry": {"coordinates":[-117.852997,33.793701],"type":"Point"}
}