{
  "type": "Feature",
  "properties": {
    "addr:full":"1352 W Artesia Blvd Gardena CA 90248",
    "addr:housenumber":"1352",
    "addr:postcode":"90248",
    "addr:street":"W Artesia Blvd",
    "iso:country":"US",
    "sg:address":"1352 W Artesia Blvd",
    "sg:city":"Gardena",
    "sg:classifiers":[
        {
            "category":"Banks & Credit Unions",
            "subcategory":"Bank",
            "type":"Services"
        }
    ],
    "sg:phone":"+1 310 217 7051",
    "sg:postcode":"90248",
    "sg:province":"CA",
    "sg:tags":[
        "state"
    ],
    "wof:name":"La Federal Credit Union",
    "wof:placetype":"venue"
},
  "geometry": {"coordinates":[-118.297093,33.872696],"type":"Point"}
}