{
  "type": "Feature",
  "properties": {
    "addr:full":"2548 Empire Grade Santa Cruz CA 95060",
    "addr:housenumber":"2548",
    "addr:postcode":"95060",
    "addr:street":"Empire Grade",
    "iso:country":"US",
    "sg:address":"2548 Empire Grade",
    "sg:city":"Santa Cruz",
    "sg:classifiers":[
        {
            "category":"Professional",
            "subcategory":"Research",
            "type":"Services"
        }
    ],
    "sg:phone":"+1 831 426 0148",
    "sg:postcode":"95060",
    "sg:province":"CA",
    "sg:tags":[
        "environmental",
        "ecological"
    ],
    "sg:website":"www.indoorair2002.org",
    "wof:name":"Indoor Air 2002",
    "wof:placetype":"venue"
},
  "geometry": {"coordinates":[-122.075614,37.009331],"type":"Point"}
}