{
  "type": "Feature",
  "properties": {
    "addr:full":"4949 Great America Pkwy Santa Clara CA 95054",
    "addr:housenumber":"4949",
    "addr:postcode":"95054",
    "addr:street":"Great America Pkwy",
    "iso:country":"US",
    "sg:address":"4949 Great America Pkwy",
    "sg:city":"Santa Clara",
    "sg:classifiers":[
        {
            "category":"Restaurant",
            "type":"Food & Drink"
        }
    ],
    "sg:phone":"+1 408 562 6731",
    "sg:postcode":"95054",
    "sg:province":"CA",
    "sg:tags":[
        "new",
        "american"
    ],
    "sg:website":"www.hiltonsantaclara.com/dining/",
    "wof:name":"La Fontana",
    "wof:placetype":"venue"
},
  "geometry": {"coordinates":[-121.977997,37.4025],"type":"Point"}
}