{
  "type": "Feature",
  "properties": {
    "addr:full":"966 S Vermont Ave Los Angeles CA 90006",
    "addr:housenumber":"966",
    "addr:postcode":"90006",
    "addr:street":"S Vermont Ave",
    "iso:country":"US",
    "sg:address":"966 S Vermont Ave",
    "sg:city":"Los Angeles",
    "sg:classifiers":[
        {
            "category":"Restaurant",
            "type":"Food & Drink"
        }
    ],
    "sg:phone":"+1 213 387 8833",
    "sg:postcode":"90006",
    "sg:province":"CA",
    "sg:tags":[
        "chinese"
    ],
    "sg:website":"www.dragonchineserestaurantla.com",
    "wof:name":"The Dragon Restaurant",
    "wof:placetype":"venue"
},
  "geometry": {"coordinates":[-118.292,34.0536],"type":"Point"}
}