{
  "type": "Feature",
  "properties": {
    "iso:country":"US",
    "sg:address":"428 J Street Bsmt",
    "sg:city":"Sacramento",
    "sg:classifiers":[
        {
            "category":"Professional",
            "subcategory":"Lawyer & Legal Services",
            "type":"Services"
        }
    ],
    "sg:phone":"+1 916 443 0217",
    "sg:postcode":"95814",
    "sg:province":"CA",
    "wof:name":"Bigelow Michael B Atty",
    "wof:placetype":"venue"
},
  "geometry": {"coordinates":[-121.501014,38.582355],"type":"Point"}
}