{
  "type": "Feature",
  "properties": {
    "addr:full":"1559 Meridian Ave San Jose CA 95125",
    "addr:housenumber":"1559",
    "addr:postcode":"95125",
    "addr:street":"Meridian Ave",
    "iso:country":"US",
    "sg:address":"1559 Meridian Ave",
    "sg:city":"San Jose",
    "sg:classifiers":[
        {
            "category":"Food & Beverages",
            "subcategory":"Liquor & Beverages",
            "type":"Retail Goods"
        }
    ],
    "sg:phone":"+1 408 448 9463",
    "sg:postcode":"95125",
    "sg:province":"CA",
    "sg:tags":[
        "beer",
        "spirit",
        "wine"
    ],
    "sg:website":"www.josephgeorge.com",
    "wof:name":"Joseph George",
    "wof:placetype":"venue"
},
  "geometry": {"coordinates":[-121.91300200000001,37.296001],"type":"Point"}
}