{
  "type": "Feature",
  "properties": {
    "iso:country":"US",
    "sg:address":"11426 Violeta St",
    "sg:city":"Ventura",
    "sg:classifiers":[
        {
            "category":"Education",
            "subcategory":"Library",
            "type":"Public Place"
        }
    ],
    "sg:phone":"+1 805 647 5736",
    "sg:postcode":"93004",
    "sg:province":"CA",
    "wof:name":"Saticoy Library",
    "wof:placetype":"venue"
},
  "geometry": {"coordinates":[-119.144926,34.287478],"type":"Point"}
}