{
  "type": "Feature",
  "properties": {
    "addr:full":"6522 Stanton Ave #E Buena Park CA 90621",
    "addr:housenumber":"6522",
    "addr:postcode":"90621",
    "addr:street":"Stanton Ave # E",
    "iso:country":"US",
    "sg:address":"6522 Stanton Ave #E",
    "sg:city":"Buena Park",
    "sg:classifiers":[
        {
            "category":"Restaurant",
            "type":"Food & Drink"
        }
    ],
    "sg:phone":"+1 714 523 3486",
    "sg:postcode":"90621",
    "sg:province":"CA",
    "sg:tags":[
        "korean"
    ],
    "wof:name":"Abbaee Wang Soondae",
    "wof:placetype":"venue"
},
  "geometry": {"coordinates":[-117.993799,33.865798],"type":"Point"}
}