{
  "type": "Feature",
  "properties": {
    "addr:full":"17645 State Hwy 160 Rio Vista CA 94571",
    "addr:housenumber":"17645",
    "addr:postcode":"94571",
    "addr:street":"State Hwy 160",
    "iso:country":"US",
    "sg:address":"17645 State Hwy 160",
    "sg:city":"Rio Vista",
    "sg:classifiers":[
        {
            "category":"Government",
            "subcategory":"Office",
            "type":"Public Place"
        }
    ],
    "sg:phone":"+1 916 777 6671",
    "sg:postcode":"94571",
    "sg:province":"CA",
    "sg:tags":[
        "recreation",
        "area"
    ],
    "wof:name":"Brannan Isle Recreation Area",
    "wof:placetype":"venue"
},
  "geometry": {"coordinates":[-121.733037,38.07733],"type":"Point"}
}