{
  "type": "Feature",
  "properties": {
    "addr:full":"17705 Pioneer Blvd Artesia CA 90701",
    "addr:housenumber":"17705",
    "addr:postcode":"90701",
    "addr:street":"Pioneer Blvd",
    "iso:country":"US",
    "sg:address":"17705 Pioneer Blvd",
    "sg:city":"Artesia",
    "sg:classifiers":[
        {
            "category":"Sports & Exercise",
            "subcategory":"Bowling",
            "type":"Entertainment"
        }
    ],
    "sg:phone":"+1 562 653 0900",
    "sg:postcode":"90701",
    "sg:province":"CA",
    "sg:tags":[
        "center"
    ],
    "wof:name":"Masala Bowl",
    "wof:placetype":"venue"
},
  "geometry": {"coordinates":[-118.082309,33.869447],"type":"Point"}
}