{
  "type": "Feature",
  "properties": {
    "addr:full":"147 S Western Ave Los Angeles CA 90004",
    "addr:housenumber":"147",
    "addr:postcode":"90004",
    "addr:street":"S Western Ave",
    "iso:country":"US",
    "sg:address":"147 S Western Ave",
    "sg:city":"Los Angeles",
    "sg:classifiers":[
        {
            "category":"Wholesale",
            "subcategory":"Home Furnishings",
            "type":"Manufacturing & Wholesale Goods"
        }
    ],
    "sg:phone":"+1 213 388 8874",
    "sg:postcode":"90004",
    "sg:province":"CA",
    "sg:tags":[
        "decorative",
        "fab",
        "product",
        "floor",
        "covering"
    ],
    "wof:name":"Everlux Inc",
    "wof:placetype":"venue"
},
  "geometry": {"coordinates":[-118.309202,34.072032],"type":"Point"}
}