{
  "type": "Feature",
  "properties": {
    "iso:country":"US",
    "sg:address":"318 Main St",
    "sg:city":"Watsonville",
    "sg:classifiers":[
        {
            "category":"Organizations",
            "subcategory":"Non-profit Organization",
            "type":"Services"
        }
    ],
    "sg:phone":"+1 831 722 9461",
    "sg:postcode":"95076",
    "sg:province":"CA",
    "wof:name":"Pajaro Valley Housing Corp",
    "wof:placetype":"venue"
},
  "geometry": {"coordinates":[-121.755874,36.909391],"type":"Point"}
}