{
  "type": "Feature",
  "properties": {
    "iso:country":"US",
    "sg:address":"7901 Watt Ave",
    "sg:city":"Antelope",
    "sg:classifiers":[
        {
            "category":"Utilities",
            "subcategory":"Mobile Phone",
            "type":"Services"
        }
    ],
    "sg:phone":"+1 916 331 9922",
    "sg:postcode":"95843",
    "sg:province":"CA",
    "sg:tags":[
        "telephone",
        "cellular"
    ],
    "wof:name":"Cellular Warehouse",
    "wof:placetype":"venue"
},
  "geometry": {"coordinates":[-121.391924,38.712571],"type":"Point"}
}