{
  "type": "Feature",
  "properties": {
    "iso:country":"US",
    "sg:address":"13181 Peyton Dr",
    "sg:city":"Chino Hills",
    "sg:classifiers":[
        {
            "category":"Shopping",
            "subcategory":"Pharmacy",
            "type":"Retail Goods"
        }
    ],
    "sg:phone":"+1 909 627 5099",
    "sg:postcode":"91709",
    "sg:province":"CA",
    "wof:name":"Sav-On Drugs",
    "wof:placetype":"venue"
},
  "geometry": {"coordinates":[-117.744739,34.01419],"type":"Point"}
}