{
  "type": "Feature",
  "properties": {
    "addr:full":"3165 Palisades Dr Corona CA 92880",
    "addr:housenumber":"3165",
    "addr:postcode":"92880",
    "addr:street":"Palisades Dr",
    "iso:country":"US",
    "sg:address":"3165 Palisades Dr",
    "sg:city":"Corona",
    "sg:classifiers":[
        {
            "category":"Building & Trades",
            "subcategory":"Construction",
            "type":"Services"
        }
    ],
    "sg:phone":"+1 951 271 3440",
    "sg:postcode":"92880",
    "sg:province":"CA",
    "sg:tags":[
        "contractor"
    ],
    "wof:name":"Stiff JM Construction",
    "wof:placetype":"venue"
},
  "geometry": {"coordinates":[-117.628057,33.882402],"type":"Point"}
}