{
  "type": "Feature",
  "properties": {
    "iso:country":"US",
    "sg:address":"3221 20th St",
    "sg:city":"San Francisco",
    "sg:classifiers":[
        {
            "category":"Wholesale",
            "subcategory":"Furniture",
            "type":"Manufacturing & Wholesale Goods"
        }
    ],
    "sg:phone":"+1 415 648 1880",
    "sg:postcode":"94110",
    "sg:province":"CA",
    "wof:name":"Inter Americana",
    "wof:placetype":"venue"
},
  "geometry": {"coordinates":[-122.41321600000001,37.758916],"type":"Point"}
}