{
  "type": "Feature",
  "properties": {
    "iso:country":"US",
    "sg:address":"16369 Shamhart Dr",
    "sg:city":"Granada Hills",
    "sg:classifiers":[
        {
            "category":"Building & Trades",
            "subcategory":"Electrical",
            "type":"Services"
        }
    ],
    "sg:phone":"+1 818 832 5422",
    "sg:postcode":"91344",
    "sg:province":"CA",
    "sg:tags":[
        "electric",
        "contractor"
    ],
    "wof:name":"Spark Electric Co",
    "wof:placetype":"venue"
},
  "geometry": {"coordinates":[-118.487808,34.287731],"type":"Point"}
}