{
  "type": "Feature",
  "properties": {
    "addr:full":"130 Battery Street 6th Floor San Francisco CA 94111",
    "addr:housenumber":"130;6th",
    "addr:postcode":"94111",
    "addr:street":"Battery Street;Floor",
    "iso:country":"US",
    "sg:address":"130 Battery Street 6th Floor",
    "sg:city":"San Francisco",
    "sg:classifiers":[
        {
            "category":"Professional",
            "subcategory":"Computer Services",
            "type":"Services"
        }
    ],
    "sg:phone":"+1 800 215 8423",
    "sg:postcode":"94111",
    "sg:province":"CA",
    "sg:website":"http://www.rentjuice.com/",
    "wof:name":"RentJuice",
    "wof:placetype":"venue"
},
  "geometry": {"coordinates":[-122.399838,37.79293],"type":"Point"}
}