{
  "type": "Feature",
  "properties": {
    "iso:country":"US",
    "sg:address":"5330 Derry Ave",
    "sg:city":"Agoura Hills",
    "sg:classifiers":[
        {
            "category":"Manufacturing",
            "subcategory":"Metals",
            "type":"Manufacturing & Wholesale Goods"
        }
    ],
    "sg:phone":"+1 818 889 8899",
    "sg:postcode":"91301",
    "sg:province":"CA",
    "sg:tags":[
        "building",
        "prefabricated",
        "mfg"
    ],
    "wof:name":"CA Sunrooms",
    "wof:placetype":"venue"
},
  "geometry": {"coordinates":[-118.747964,34.146849],"type":"Point"}
}