{
  "type": "Feature",
  "properties": {
    "addr:full":"967 N Main St Salinas CA 93906",
    "addr:housenumber":"967",
    "addr:postcode":"93906",
    "addr:street":"N Main St",
    "iso:country":"US",
    "sg:address":"967 N Main St",
    "sg:city":"Salinas",
    "sg:classifiers":[
        {
            "category":"Retail",
            "subcategory":"Portrait Studio",
            "type":"Services"
        }
    ],
    "sg:phone":"+1 831 757 6666",
    "sg:postcode":"93906",
    "sg:province":"CA",
    "sg:tags":[
        "photographer"
    ],
    "wof:name":"Simply Timeless Photography",
    "wof:placetype":"venue"
},
  "geometry": {"coordinates":[-121.65231300000001,36.69104],"type":"Point"}
}