{
  "type": "Feature",
  "properties": {
    "iso:country":"US",
    "sg:address":"336 Sanjon Rd",
    "sg:city":"Ventura",
    "sg:classifiers":[
        {
            "category":"Government",
            "subcategory":"Office",
            "type":"Public Place"
        }
    ],
    "sg:phone":"+1 805 652 4515",
    "sg:postcode":"93001",
    "sg:province":"CA",
    "sg:tags":[
        "village"
    ],
    "sg:website":"www.ci.ventura.ca.us",
    "wof:name":"Ventura Streets Dept",
    "wof:placetype":"venue"
},
  "geometry": {"coordinates":[-119.282224,34.275083],"type":"Point"}
}