{
  "type": "Feature",
  "properties": {
    "iso:country":"US",
    "sg:address":"1621 E 17th St Ste G",
    "sg:city":"Santa Ana",
    "sg:classifiers":[
        {
            "category":"Health Services",
            "subcategory":"Chiropractor",
            "type":"Services"
        }
    ],
    "sg:phone":"+1 714 835 1779",
    "sg:postcode":"92705",
    "sg:province":"CA",
    "wof:name":"Sabeti Chiropractic",
    "wof:placetype":"venue"
},
  "geometry": {"coordinates":[-117.817001,33.759998],"type":"Point"}
}