{
  "type": "Feature",
  "properties": {
    "iso:country":"US",
    "sg:address":"2550 Guerneville Rd",
    "sg:city":"Santa Rosa",
    "sg:classifiers":[
        {
            "category":"Banks & Credit Unions",
            "subcategory":"Bank",
            "type":"Services"
        }
    ],
    "sg:phone":"+1 707 528 2274",
    "sg:postcode":"95401",
    "sg:province":"CA",
    "sg:tags":[
        "cashing",
        "check"
    ],
    "wof:name":"ACE Cash Express",
    "wof:placetype":"venue"
},
  "geometry": {"coordinates":[-122.773521,38.452462],"type":"Point"}
}