{
  "type": "Feature",
  "properties": {
    "addr:full":"1143 Highland Ave National City CA 91950",
    "addr:housenumber":"1143",
    "addr:postcode":"91950",
    "addr:street":"Highland Ave",
    "iso:country":"US",
    "sg:address":"1143 Highland Ave",
    "sg:city":"National City",
    "sg:classifiers":[
        {
            "category":"Restaurant",
            "type":"Food & Drink"
        }
    ],
    "sg:menulink":"http://www.allmenus.com/ca/san-diego/64133-chuck-e-cheeses/menu/",
    "sg:phone":"+1 619 474 6667",
    "sg:postcode":"91950",
    "sg:province":"CA",
    "sg:tags":[
        "american",
        "pizza"
    ],
    "wof:name":"Chuck E. Cheese's",
    "wof:placetype":"venue"
},
  "geometry": {"coordinates":[-117.097584,32.67498],"type":"Point"}
}