{
  "type": "Feature",
  "properties": {
    "addr:full":"495 Gate 5 Rd Ste G Sausalito CA 94965",
    "addr:housenumber":"495;5",
    "addr:postcode":"94965",
    "addr:street":"Gate;Rd Ste G",
    "iso:country":"US",
    "sg:address":"495 Gate 5 Rd Ste G",
    "sg:city":"Sausalito",
    "sg:classifiers":[
        {
            "category":"Manufacturing",
            "subcategory":"Toys & Sporting Goods",
            "type":"Manufacturing & Wholesale Goods"
        }
    ],
    "sg:phone":"+1 415 927 7381",
    "sg:postcode":"94965",
    "sg:province":"CA",
    "sg:tags":[
        "goods-wholesale",
        "manufacturer"
    ],
    "wof:name":"Pool Covers Etc.",
    "wof:placetype":"venue"
},
  "geometry": {"coordinates":[-122.500092,37.869733],"type":"Point"}
}