{
  "type": "Feature",
  "properties": {
    "addr:full":"1216 N Douty St Hanford CA 93230",
    "addr:housenumber":"1216",
    "addr:postcode":"ca 93230",
    "addr:street":"N Douty St",
    "iso:country":"US",
    "sg:address":"1216 N Douty St",
    "sg:city":"Hanford",
    "sg:classifiers":[
        {
            "category":"Insurance",
            "subcategory":"Insurance Agent",
            "type":"Services"
        }
    ],
    "sg:phone":"+1 559 584 9460",
    "sg:postcode":"93230",
    "sg:province":"CA",
    "wof:name":"ISU Insurance Svc Unlimited",
    "wof:placetype":"venue"
},
  "geometry": {"coordinates":[-119.646106,36.337781],"type":"Point"}
}