{
  "type": "Feature",
  "properties": {
    "iso:country":"US",
    "sg:address":"500 Ioof Ave",
    "sg:city":"Gilroy",
    "sg:classifiers":[
        {
            "category":"Real Estate",
            "subcategory":"Real Estate Operator",
            "type":"Services"
        }
    ],
    "sg:phone":"+1 408 842 4457",
    "sg:postcode":"95020",
    "sg:province":"CA",
    "sg:tags":[
        "apartment"
    ],
    "wof:name":"Gilroy Apartments LTD",
    "wof:placetype":"venue"
},
  "geometry": {"coordinates":[-121.56426,37.015789],"type":"Point"}
}