{
  "type": "Feature",
  "properties": {
    "iso:country":"US",
    "sg:address":"509 Barringham Ln",
    "sg:city":"Modesto",
    "sg:classifiers":[
        {
            "category":"Professional",
            "type":"Services"
        }
    ],
    "sg:phone":"+1 209 523 6332",
    "sg:postcode":"95350",
    "sg:province":"CA",
    "wof:name":"Citizens Committee For In",
    "wof:placetype":"venue"
},
  "geometry": {"coordinates":[-120.987205,37.686621],"type":"Point"}
}