{
  "type": "Feature",
  "properties": {
    "addr:full":"1514 Spring St Paso Robles CA 93446",
    "addr:housenumber":"1514",
    "addr:postcode":"93446",
    "addr:street":"Spring St",
    "iso:country":"US",
    "sg:address":"1514 Spring St",
    "sg:city":"Paso Robles",
    "sg:classifiers":[
        {
            "category":"Food & Beverages",
            "subcategory":"Groceries & Convenience Stores",
            "type":"Retail Goods"
        }
    ],
    "sg:phone":"+1 805 226 8825",
    "sg:postcode":"93446",
    "sg:province":"CA",
    "sg:tags":[
        "grocer"
    ],
    "wof:name":"Spring Street Country Market",
    "wof:placetype":"venue"
},
  "geometry": {"coordinates":[-120.691593,35.630674],"type":"Point"}
}