{
  "type": "Feature",
  "properties": {
    "addr:full":"2060 State Rte 66 Glendora CA 91740",
    "addr:housenumber":"2060",
    "addr:postcode":"91740",
    "addr:street":"State Rte 66",
    "iso:country":"US",
    "sg:address":"2060 State Rte 66",
    "sg:city":"Glendora",
    "sg:classifiers":[
        {
            "category":"Shopping",
            "subcategory":"Computers & Home Electronics",
            "type":"Retail Goods"
        }
    ],
    "sg:phone":"+1 626 963 3919",
    "sg:postcode":"91740",
    "sg:province":"CA",
    "sg:tags":[
        "parts",
        "supply"
    ],
    "wof:name":"Jaafri Industries",
    "wof:placetype":"venue"
},
  "geometry": {"coordinates":[-117.825444,34.127819],"type":"Point"}
}