{
  "type": "Feature",
  "properties": {
    "iso:country":"US",
    "sg:address":"425 S Ocean Ave",
    "sg:city":"Cayucos",
    "sg:classifiers":[
        {
            "category":"Real Estate",
            "subcategory":"Real Estate Agent",
            "type":"Services"
        }
    ],
    "sg:phone":"+1 805 995 5090",
    "sg:postcode":"93430",
    "sg:province":"CA",
    "wof:name":"Morro Bay Realty",
    "wof:placetype":"venue"
},
  "geometry": {"coordinates":[-120.897659,35.445514],"type":"Point"}
}