{
  "type": "Feature",
  "properties": {
    "iso:country":"US",
    "sg:address":"600 Janopaul Ln",
    "sg:city":"Modesto",
    "sg:classifiers":[
        {
            "category":"Social Services",
            "type":"Services"
        }
    ],
    "sg:phone":"+1 209 577 3600",
    "sg:postcode":"95351",
    "sg:province":"CA",
    "sg:tags":[
        "organization",
        "welfare"
    ],
    "wof:name":"Salvation Army",
    "wof:placetype":"venue"
},
  "geometry": {"coordinates":[-120.987423,37.61864],"type":"Point"}
}