{
  "type": "Feature",
  "properties": {
    "iso:country":"US",
    "sg:address":"19365 McKinley Ave",
    "sg:city":"Manteca",
    "sg:classifiers":[
        {
            "category":"Retail",
            "subcategory":"Animal Services",
            "type":"Services"
        }
    ],
    "sg:phone":"+1 209 823 4942",
    "sg:postcode":"95337",
    "sg:province":"CA",
    "wof:name":"Vonduvan Dog & Cat Kennels",
    "wof:placetype":"venue"
},
  "geometry": {"coordinates":[-121.27059800000001,37.783172],"type":"Point"}
}