{
  "type": "Feature",
  "properties": {
    "addr:full":"633 California St Escalon CA 95320",
    "addr:housenumber":"633",
    "addr:postcode":"95320",
    "addr:street":"California St",
    "iso:country":"US",
    "sg:address":"633 California St",
    "sg:city":"Escalon",
    "sg:classifiers":[
        {
            "category":"Manufacturing",
            "subcategory":"Tools & Machinery",
            "type":"Manufacturing & Wholesale Goods"
        }
    ],
    "sg:phone":"+1 209 956 5690",
    "sg:postcode":"95320",
    "sg:province":"CA",
    "sg:tags":[
        "industrial",
        "mfg"
    ],
    "wof:name":"Blakesmith Tool & Machine",
    "wof:placetype":"venue"
},
  "geometry": {"coordinates":[-121.004356,37.79648],"type":"Point"}
}