{
  "type": "Feature",
  "properties": {
    "addr:full":"25350 Dustin Rd Acampo CA 95220",
    "addr:postcode":"25350;95220",
    "addr:street":"Dustin Rd",
    "iso:country":"US",
    "sg:address":"25350 Dustin Rd",
    "sg:city":"Acampo",
    "sg:classifiers":[
        {
            "category":"Retail",
            "subcategory":"Animal Services",
            "type":"Services"
        }
    ],
    "sg:phone":"+1 209 367 8982",
    "sg:postcode":"95220",
    "sg:province":"CA",
    "wof:name":"North Dustin Stables",
    "wof:placetype":"venue"
},
  "geometry": {"coordinates":[-121.22613,38.208585],"type":"Point"}
}