{
  "type": "Feature",
  "properties": {
    "iso:country":"US",
    "sg:address":"1637 E Valley Pkwy",
    "sg:city":"Escondido",
    "sg:classifiers":[
        {
            "category":"Retail",
            "subcategory":"Repair Shop",
            "type":"Services"
        }
    ],
    "sg:phone":"+1 760 724 5274",
    "sg:postcode":"92027",
    "sg:province":"CA",
    "sg:tags":[
        "equipment",
        "telephone",
        "system"
    ],
    "wof:name":"Basic Telephone",
    "wof:placetype":"venue"
},
  "geometry": {"coordinates":[-117.057618,33.134725],"type":"Point"}
}