{
  "type": "Feature",
  "properties": {
    "addr:full":"24582 Dana Dr Dana Point CA 92629",
    "addr:postcode":"24582;92629",
    "addr:street":"Dana Dr",
    "iso:country":"US",
    "sg:address":"24582 Dana Dr",
    "sg:city":"Dana Point",
    "sg:classifiers":[
        {
            "category":"Wholesale",
            "subcategory":"Computers",
            "type":"Manufacturing & Wholesale Goods"
        }
    ],
    "sg:phone":"+1 949 715 6927",
    "sg:postcode":"92629",
    "sg:province":"CA",
    "sg:tags":[
        "equipment"
    ],
    "wof:name":"Ascend Electronics LLC",
    "wof:placetype":"venue"
},
  "geometry": {"coordinates":[-117.70253200000001,33.459327],"type":"Point"}
}