{
  "type": "Feature",
  "properties": {
    "addr:full":"2526 W San Ramon Ave Fresno CA 93711",
    "addr:housenumber":"2526",
    "addr:postcode":"93711",
    "addr:street":"W San Ramon Ave",
    "iso:country":"US",
    "sg:address":"2526 W San Ramon Ave",
    "sg:city":"Fresno",
    "sg:classifiers":[
        {
            "category":"Professional",
            "subcategory":"Management & Consulting",
            "type":"Services"
        }
    ],
    "sg:phone":"+1 559 432 3677",
    "sg:postcode":"93711",
    "sg:province":"CA",
    "sg:tags":[
        "business"
    ],
    "wof:name":"Evolutionary Consulting Inc",
    "wof:placetype":"venue"
},
  "geometry": {"coordinates":[-119.839231,36.813752],"type":"Point"}
}