{
  "type": "Feature",
  "properties": {
    "addr:full":"113 W G St San Diego CA 92101",
    "addr:housenumber":"113",
    "addr:postcode":"92101",
    "addr:street":"W G St",
    "iso:country":"US",
    "sg:address":"113 W G St",
    "sg:city":"San Diego",
    "sg:classifiers":[
        {
            "category":"Shopping",
            "type":"Retail Goods"
        }
    ],
    "sg:phone":"+1 619 397 5526",
    "sg:postcode":"92101",
    "sg:province":"CA",
    "sg:tags":[
        "garden",
        "merchandise"
    ],
    "wof:name":"H2o Aquarium Products",
    "wof:placetype":"venue"
},
  "geometry": {"coordinates":[-117.164587,32.712469],"type":"Point"}
}