{
  "type": "Feature",
  "properties": {
    "iso:country":"US",
    "sg:address":"1007 E Young St",
    "sg:city":"Wilmington",
    "sg:classifiers":[
        {
            "category":"Professional",
            "type":"Services"
        }
    ],
    "sg:phone":"+1 310 834 5051",
    "sg:postcode":"90744",
    "sg:province":"CA",
    "wof:name":"Juan Rochin Guerrero",
    "wof:placetype":"venue"
},
  "geometry": {"coordinates":[-118.24959200000001,33.786548],"type":"Point"}
}