{
  "type": "Feature",
  "properties": {
    "iso:country":"US",
    "sg:address":"2525 Corporate Pl",
    "sg:city":"Monterey Park",
    "sg:classifiers":[
        {
            "category":"Government",
            "subcategory":"Court House",
            "type":"Public Place"
        }
    ],
    "sg:phone":"+1 323 526 6757",
    "sg:postcode":"91754",
    "sg:province":"CA",
    "wof:name":"Los Angeles Cnty Idc",
    "wof:placetype":"venue"
},
  "geometry": {"coordinates":[-118.164313,34.046648],"type":"Point"}
}