{
  "type": "Feature",
  "properties": {
    "addr:full":"13273 Ventura Blvd Ste 104 Studio City CA 91604",
    "addr:housenumber":"13273",
    "addr:postcode":"91604",
    "addr:street":"Ventura Blvd Ste 104",
    "iso:country":"US",
    "sg:address":"13273 Ventura Blvd Ste 104",
    "sg:city":"Studio City",
    "sg:classifiers":[
        {
            "category":"Retail",
            "subcategory":"Auto Rental",
            "type":"Services"
        }
    ],
    "sg:phone":"+1 760 767 3030",
    "sg:postcode":"91604",
    "sg:province":"CA",
    "sg:tags":[
        "car"
    ],
    "wof:name":"Bill G Auto Leasing",
    "wof:placetype":"venue"
},
  "geometry": {"coordinates":[-118.421997,34.1465],"type":"Point"}
}