{
  "type": "Feature",
  "properties": {
    "addr:full":"23710 el Toro Rd Lake Forest CA 92630",
    "addr:housenumber":"23710",
    "addr:postcode":"92630",
    "addr:street":"El Toro Rd",
    "iso:country":"US",
    "sg:address":"23710 el Toro Rd",
    "sg:city":"Lake Forest",
    "sg:classifiers":[
        {
            "category":"Restaurant",
            "type":"Food & Drink"
        }
    ],
    "sg:phone":"+1 949 768 6454",
    "sg:postcode":"92630",
    "sg:province":"CA",
    "sg:tags":[
        "parlor",
        "ice",
        "cream"
    ],
    "wof:name":"Golden Spoon",
    "wof:placetype":"venue"
},
  "geometry": {"coordinates":[-117.703041,33.618391],"type":"Point"}
}