{
  "type": "Feature",
  "properties": {
    "addr:full":"630 S Hawthorne Ave Fullerton CA 92833",
    "addr:housenumber":"630",
    "addr:postcode":"92833",
    "addr:street":"S Hawthorne Ave",
    "iso:country":"US",
    "sg:address":"630 S Hawthorne Ave",
    "sg:city":"Fullerton",
    "sg:classifiers":[
        {
            "category":"Wholesale",
            "subcategory":"Durable Goods & Equipment",
            "type":"Manufacturing & Wholesale Goods"
        }
    ],
    "sg:phone":"+1 714 773 4755",
    "sg:postcode":"92833",
    "sg:province":"CA",
    "wof:name":"Grimes Pro Cycle Supply",
    "wof:placetype":"venue"
},
  "geometry": {"coordinates":[-117.96026999999999,33.862831],"type":"Point"}
}