{
  "type": "Feature",
  "properties": {
    "iso:country":"US",
    "sg:address":"610 Alcatraz Ave",
    "sg:city":"Oakland",
    "sg:classifiers":[
        {
            "category":"Building & Trades",
            "subcategory":"Construction",
            "type":"Services"
        }
    ],
    "sg:phone":"+1 510 923 9383",
    "sg:postcode":"94609",
    "sg:province":"CA",
    "sg:tags":[
        "altering",
        "remodeling",
        "contractor"
    ],
    "wof:name":"Manou Renovations",
    "wof:placetype":"venue"
},
  "geometry": {"coordinates":[-122.262974,37.849864],"type":"Point"}
}