{
  "type": "Feature",
  "properties": {
    "iso:country":"US",
    "sg:address":"6040 Riverside Dr Ste B",
    "sg:city":"Chino",
    "sg:classifiers":[
        {
            "category":"Building & Trades",
            "subcategory":"Electrical",
            "type":"Services"
        }
    ],
    "sg:phone":"+1 909 364 9900",
    "sg:postcode":"91710",
    "sg:province":"CA",
    "sg:tags":[
        "electrician"
    ],
    "wof:name":"Divine Electric",
    "wof:placetype":"venue"
},
  "geometry": {"coordinates":[-117.674108,34.019161],"type":"Point"}
}