{
  "type": "Feature",
  "properties": {
    "iso:country":"US",
    "sg:address":"760 Newton Way",
    "sg:city":"Costa Mesa",
    "sg:classifiers":[
        {
            "category":"Wholesale",
            "subcategory":"Sporting Goods",
            "type":"Manufacturing & Wholesale Goods"
        }
    ],
    "sg:phone":"+1 949 650 5800",
    "sg:postcode":"92627",
    "sg:province":"CA",
    "sg:tags":[
        "equipment",
        "golf",
        "supply"
    ],
    "wof:name":"Drive Industries Golf",
    "wof:placetype":"venue"
},
  "geometry": {"coordinates":[-117.930924,33.637557],"type":"Point"}
}