{
  "type": "Feature",
  "properties": {
    "iso:country":"US",
    "sg:address":"1806 Roxbury Dr",
    "sg:city":"Los Angeles",
    "sg:classifiers":[
        {
            "category":"Insurance",
            "subcategory":"Insurance Agent",
            "type":"Services"
        }
    ],
    "sg:phone":"+1 310 815 8883",
    "sg:postcode":"90035",
    "sg:province":"CA",
    "wof:name":"Davis Insurance Ange",
    "wof:placetype":"venue"
},
  "geometry": {"coordinates":[-118.401285,34.047608],"type":"Point"}
}