{
  "type": "Feature",
  "properties": {
    "iso:country":"US",
    "sg:address":"2299 Post St",
    "sg:city":"San Francisco",
    "sg:classifiers":[
        {
            "category":"Health Services",
            "subcategory":"Doctor",
            "type":"Services"
        }
    ],
    "sg:phone":"+1 415 929 0660",
    "sg:postcode":"94115",
    "sg:province":"CA",
    "sg:tags":[
        "physician",
        "surgeon"
    ],
    "wof:name":"Alan J Coleman PC",
    "wof:placetype":"venue"
},
  "geometry": {"coordinates":[-122.43801999999999,37.784531],"type":"Point"}
}