{
  "type": "Feature",
  "properties": {
    "addr:full":"1300 E Pleasant Valley Rd Oxnard CA 93033",
    "addr:housenumber":"1300",
    "addr:postcode":"93033",
    "addr:street":"E Pleasant Valley Rd",
    "iso:country":"US",
    "sg:address":"1300 E Pleasant Valley Rd",
    "sg:city":"Oxnard",
    "sg:classifiers":[
        {
            "category":"Real Estate",
            "subcategory":"Real Estate Operator",
            "type":"Services"
        }
    ],
    "sg:phone":"+1 805 488 8816",
    "sg:postcode":"93033",
    "sg:province":"CA",
    "sg:tags":[
        "mobile",
        "home",
        "site"
    ],
    "wof:name":"Villa Capri Mobile Estates",
    "wof:placetype":"venue"
},
  "geometry": {"coordinates":[-119.162924,34.156129],"type":"Point"}
}