{
  "type": "Feature",
  "properties": {
    "iso:country":"US",
    "sg:address":"205 Bullard Ave",
    "sg:city":"Clovis",
    "sg:classifiers":[
        {
            "category":"Building & Trades",
            "subcategory":"Construction",
            "type":"Services"
        }
    ],
    "sg:phone":"+1 559 348 9810",
    "sg:postcode":"93612",
    "sg:province":"CA",
    "sg:tags":[
        "contractor"
    ],
    "wof:name":"BMN Building Inc",
    "wof:placetype":"venue"
},
  "geometry": {"coordinates":[-119.70546,36.823071],"type":"Point"}
}