{
  "type": "Feature",
  "properties": {
    "addr:full":"6323 S Peach Ave Fresno CA 93725",
    "addr:housenumber":"6323",
    "addr:postcode":"93725",
    "addr:street":"S Peach Ave",
    "iso:country":"US",
    "sg:address":"6323 S Peach Ave",
    "sg:city":"Fresno",
    "sg:classifiers":[
        {
            "category":"Farming",
            "subcategory":"Vineyard",
            "type":"Manufacturing & Wholesale Goods"
        }
    ],
    "sg:phone":"+1 559 834 1889",
    "sg:postcode":"93725",
    "sg:province":"CA",
    "sg:tags":[
        "grape"
    ],
    "wof:name":"Glenn S Martin",
    "wof:placetype":"venue"
},
  "geometry": {"coordinates":[-119.71799799999999,36.646257],"type":"Point"}
}