{
  "type": "Feature",
  "properties": {
    "addr:full":"540 Work St Salinas CA 93901",
    "addr:housenumber":"540",
    "addr:postcode":"93901",
    "addr:street":"Work St",
    "iso:country":"US",
    "sg:address":"540 Work St",
    "sg:city":"Salinas",
    "sg:classifiers":[
        {
            "category":"Wholesale",
            "subcategory":"Office Equipment",
            "type":"Manufacturing & Wholesale Goods"
        },
        {
            "category":"Utilities",
            "subcategory":"Telephone",
            "type":"Services"
        },
        {
            "category":"Communications",
            "type":"Services"
        },
        {
            "category":"Professional",
            "subcategory":"Computer Services",
            "type":"Services"
        }
    ],
    "sg:phone":"+1 831 759 8760",
    "sg:postcode":"93901",
    "sg:province":"CA",
    "sg:tags":[
        "repair",
        "equipment-servicing",
        "systems-repair",
        "refinish",
        "answering",
        "system",
        "equipment-repair",
        "equipment-service",
        "furniture"
    ],
    "sg:website":"http://www.startdbs.com",
    "wof:name":"Dataflow Business Systems",
    "wof:placetype":"venue"
},
  "geometry": {"coordinates":[-121.64146599999999,36.669983],"type":"Point"}
}