{
  "type": "Feature",
  "properties": {
    "addr:full":"632 Tennant Ave Morgan Hill CA 95037",
    "addr:housenumber":"632",
    "addr:postcode":"95037",
    "addr:street":"Tennant Ave",
    "iso:country":"US",
    "sg:address":"632 Tennant Ave",
    "sg:city":"Morgan Hill",
    "sg:classifiers":[
        {
            "category":"Education",
            "subcategory":"Special Training",
            "type":"Public Place"
        }
    ],
    "sg:phone":"+1 408 629 8886",
    "sg:postcode":"95037",
    "sg:province":"CA",
    "sg:tags":[
        "tutoring"
    ],
    "wof:name":"Tutoring Club",
    "wof:placetype":"venue"
},
  "geometry": {"coordinates":[-121.635667,37.115692],"type":"Point"}
}