{
  "type": "Feature",
  "properties": {
    "iso:country":"US",
    "sg:address":"28561 Rancho del Sol",
    "sg:city":"Laguna Niguel",
    "sg:classifiers":[
        {
            "category":"Manufacturing",
            "subcategory":"Lumber",
            "type":"Manufacturing & Wholesale Goods"
        }
    ],
    "sg:phone":"+1 949 831 2173",
    "sg:postcode":"92677",
    "sg:province":"CA",
    "sg:tags":[
        "product",
        "special",
        "sawmill"
    ],
    "wof:name":"For The Birds",
    "wof:placetype":"venue"
},
  "geometry": {"coordinates":[-117.693574,33.547395],"type":"Point"}
}