{
  "type": "Feature",
  "properties": {
    "iso:country":"US",
    "sg:address":"712 S Auburn St",
    "sg:city":"Grass Valley",
    "sg:classifiers":[
        {
            "category":"Retail",
            "subcategory":"Car Wash",
            "type":"Services"
        }
    ],
    "sg:phone":"+1 530 272 5823",
    "sg:postcode":"95945",
    "sg:province":"CA",
    "sg:tags":[
        "automobile",
        "detail",
        "clean"
    ],
    "wof:name":"10 Minute Oil Change & Car Wsh",
    "wof:placetype":"venue"
},
  "geometry": {"coordinates":[-121.06141599999999,39.203931],"type":"Point"}
}