{
  "type": "Feature",
  "properties": {
    "iso:country":"US",
    "sg:address":"2150 E Katella Ave",
    "sg:city":"Anaheim",
    "sg:classifiers":[
        {
            "category":"Local Transit",
            "type":"Transportation"
        }
    ],
    "sg:phone":"+1 714 765 5277",
    "sg:postcode":"92806",
    "sg:province":"CA",
    "sg:tags":[
        "public"
    ],
    "sg:website":"www.metrolinktrains.com/stations...",
    "wof:name":"Anaheim Station",
    "wof:placetype":"venue"
},
  "geometry": {"coordinates":[-117.882482,33.803577],"type":"Point"}
}