{
  "type": "Feature",
  "properties": {
    "addr:full":"73411 Hilltop Rd Desert Hot Spgs CA 92241",
    "addr:housenumber":"73411",
    "addr:postcode":"92241",
    "addr:street":"Hilltop Rd",
    "iso:country":"US",
    "sg:address":"73411 Hilltop Rd",
    "sg:city":"Desert Hot Spgs",
    "sg:classifiers":[
        {
            "category":"Building & Trades",
            "subcategory":"Construction",
            "type":"Services"
        }
    ],
    "sg:phone":"+1 760 329 7794",
    "sg:postcode":"92241",
    "sg:province":"CA",
    "sg:tags":[
        "contractor"
    ],
    "wof:name":"Andrew J Imbilli Construction",
    "wof:placetype":"venue"
},
  "geometry": {"coordinates":[-116.38489800000001,33.930964],"type":"Point"}
}