{
  "type": "Feature",
  "properties": {
    "iso:country":"US",
    "sg:address":"2800 Plaza Del AMO Unit 377",
    "sg:city":"Torrance",
    "sg:classifiers":[
        {
            "category":"Shopping",
            "subcategory":"Stationery & Office Supplies",
            "type":"Retail Goods"
        }
    ],
    "sg:phone":"+1 310 328 0988",
    "sg:postcode":"90503",
    "sg:province":"CA",
    "sg:tags":[
        "equipment"
    ],
    "wof:name":"Advanced Business International",
    "wof:placetype":"venue"
},
  "geometry": {"coordinates":[-118.33555800000001,33.826822],"type":"Point"}
}