{
  "type": "Feature",
  "properties": {
    "addr:full":"4473 Alamo St Simi Valley CA 93063",
    "addr:housenumber":"4473",
    "addr:postcode":"93063",
    "addr:street":"Alamo St",
    "iso:country":"US",
    "sg:address":"4473 Alamo St",
    "sg:city":"Simi Valley",
    "sg:classifiers":[
        {
            "category":"Shopping",
            "subcategory":"Crafts & Fabrics",
            "type":"Retail Goods"
        }
    ],
    "sg:phone":"+1 805 520 1296",
    "sg:postcode":"93063",
    "sg:province":"CA",
    "sg:tags":[
        "shop"
    ],
    "wof:name":"Beverly's Fabric",
    "wof:placetype":"venue"
},
  "geometry": {"coordinates":[-118.705736,34.28633],"type":"Point"}
}