{
  "type": "Feature",
  "properties": {
    "addr:full":"2150 San Michel Dr E Costa Mesa CA 92627",
    "addr:housenumber":"2150",
    "addr:postcode":"92627",
    "addr:street":"San Michel Dr E",
    "iso:country":"US",
    "sg:address":"2150 San Michel Dr E",
    "sg:city":"Costa Mesa",
    "sg:classifiers":[
        {
            "category":"Shopping",
            "subcategory":"Computers & Home Electronics",
            "type":"Retail Goods"
        }
    ],
    "sg:phone":"+1 949 650 0802",
    "sg:postcode":"92627",
    "sg:province":"CA",
    "sg:tags":[
        "software"
    ],
    "wof:name":"Sol Digitizing",
    "wof:placetype":"venue"
},
  "geometry": {"coordinates":[-117.923655,33.653465],"type":"Point"}
}