{
  "type": "Feature",
  "properties": {
    "iso:country":"US",
    "sg:address":"1432 State St",
    "sg:city":"Alviso",
    "sg:classifiers":[
        {
            "category":"Building & Trades",
            "subcategory":"Electrical",
            "type":"Services"
        }
    ],
    "sg:phone":"+1 408 946 4473",
    "sg:postcode":"95002",
    "sg:province":"CA",
    "sg:tags":[
        "electric",
        "contractor"
    ],
    "wof:name":"Erwin Electric",
    "wof:placetype":"venue"
},
  "geometry": {"coordinates":[-121.969336,37.430993],"type":"Point"}
}