{
  "type": "Feature",
  "properties": {
    "addr:full":"2018 Mar Azul Way Carlsbad CA 92009",
    "addr:housenumber":"2018",
    "addr:postcode":"92009",
    "addr:street":"Mar Azul Way",
    "iso:country":"US",
    "sg:address":"2018 Mar Azul Way",
    "sg:city":"Carlsbad",
    "sg:classifiers":[
        {
            "category":"Real Estate",
            "subcategory":"Real Estate Agent",
            "type":"Services"
        }
    ],
    "sg:phone":"+1 760 438 0200",
    "sg:postcode":"92009",
    "sg:province":"CA",
    "wof:name":"MCR Ventures Inc",
    "wof:placetype":"venue"
},
  "geometry": {"coordinates":[-117.264157,33.096954],"type":"Point"}
}