{
  "type": "Feature",
  "properties": {
    "addr:full":"201 Nevada St El Segundo CA 90245",
    "addr:housenumber":"201",
    "addr:postcode":"90245",
    "addr:street":"Nevada St",
    "iso:country":"US",
    "sg:address":"201 Nevada St",
    "sg:city":"El Segundo",
    "sg:classifiers":[
        {
            "category":"Wholesale",
            "subcategory":"Stationery",
            "type":"Manufacturing & Wholesale Goods"
        }
    ],
    "sg:phone":"+1 310 535 4555",
    "sg:postcode":"90245",
    "sg:province":"CA",
    "sg:tags":[
        "paper"
    ],
    "wof:name":"Frameyourartcom",
    "wof:placetype":"venue"
},
  "geometry": {"coordinates":[-118.40372499999999,33.919436],"type":"Point"}
}