{
  "type": "Feature",
  "properties": {
    "addr:full":"1280 Bison Avenue Newport Beach CA 92660",
    "addr:housenumber":"1280",
    "addr:postcode":"92660",
    "addr:street":"Bison Avenue",
    "iso:country":"US",
    "sg:address":"1280 Bison Avenue",
    "sg:city":"Newport Beach",
    "sg:classifiers":[
        {
            "category":"Shopping",
            "subcategory":"Antiques",
            "type":"Retail Goods"
        }
    ],
    "sg:phone":"+1 949 305 6132",
    "sg:postcode":"92660",
    "sg:province":"CA",
    "wof:name":"Treasures of Imperial Russia",
    "wof:placetype":"venue"
},
  "geometry": {"coordinates":[-117.862492,33.637597],"type":"Point"}
}