{
  "type": "Feature",
  "properties": {
    "iso:country":"US",
    "sg:address":"227 N Magnolia Ave",
    "sg:city":"Anaheim",
    "sg:classifiers":[
        {
            "category":"Education",
            "subcategory":"School",
            "type":"Public Place"
        }
    ],
    "sg:phone":"+1 714 220 1166",
    "sg:postcode":"92801",
    "sg:province":"CA",
    "sg:tags":[
        "high",
        "middle",
        "elementary"
    ],
    "sg:website":"www.vb.org",
    "wof:name":"Victory Baptist Church of Orange County",
    "wof:placetype":"venue"
},
  "geometry": {"coordinates":[-117.975998,33.834202],"type":"Point"}
}