{
  "type": "Feature",
  "properties": {
    "addr:full":"2116 Wilshire Blvd Santa Monica CA 90403",
    "addr:housenumber":"2116",
    "addr:postcode":"90403",
    "addr:street":"Wilshire Blvd",
    "iso:country":"US",
    "sg:address":"2116 Wilshire Blvd",
    "sg:city":"Santa Monica",
    "sg:classifiers":[
        {
            "category":"Building & Trades",
            "subcategory":"Construction",
            "type":"Services"
        }
    ],
    "sg:phone":"+1 310 828 4222",
    "sg:postcode":"90403",
    "sg:province":"CA",
    "sg:tags":[
        "contractor"
    ],
    "sg:website":"www.woodsconstruct.com",
    "wof:name":"Woods Construction",
    "wof:placetype":"venue"
},
  "geometry": {"coordinates":[-118.481499,34.03259],"type":"Point"}
}