{
  "type": "Feature",
  "properties": {
    "iso:country":"US",
    "sg:address":"23615 el Toro Rd",
    "sg:city":"Lake Forest",
    "sg:classifiers":[
        {
            "category":"Shopping",
            "subcategory":"Used Merchandise",
            "type":"Retail Goods"
        }
    ],
    "sg:phone":"+1 949 855 8045",
    "sg:postcode":"92630",
    "sg:province":"CA",
    "sg:tags":[
        "shop",
        "consignment"
    ],
    "wof:name":"Trading Post",
    "wof:placetype":"venue"
},
  "geometry": {"coordinates":[-117.700863,33.62038],"type":"Point"}
}