{
  "type": "Feature",
  "properties": {
    "iso:country":"US",
    "sg:address":"1401 Maple Ave",
    "sg:city":"Santa Rosa",
    "sg:classifiers":[
        {
            "category":"Food & Beverages",
            "subcategory":"Groceries & Convenience Stores",
            "type":"Retail Goods"
        }
    ],
    "sg:phone":"+1 707 542 8020",
    "sg:postcode":"95404",
    "sg:province":"CA",
    "wof:name":"7-Eleven",
    "wof:placetype":"venue"
},
  "geometry": {"coordinates":[-122.69663,38.434543],"type":"Point"}
}