{
  "type": "Feature",
  "properties": {
    "addr:full":"335 S Wilton Pl Los Angeles CA 90020",
    "addr:housenumber":"335",
    "addr:postcode":"90020",
    "addr:street":"S Wilton Pl",
    "iso:country":"US",
    "sg:address":"335 S Wilton Pl",
    "sg:city":"Los Angeles",
    "sg:classifiers":[
        {
            "category":"Building & Trades",
            "subcategory":"Construction",
            "type":"Services"
        }
    ],
    "sg:phone":"+1 323 933 3642",
    "sg:postcode":"90020",
    "sg:province":"CA",
    "sg:tags":[
        "resurfacing",
        "laying",
        "refinishing",
        "floor"
    ],
    "wof:name":"Axel's Carpet & Flooring",
    "wof:placetype":"venue"
},
  "geometry": {"coordinates":[-118.31414700000001,34.06777],"type":"Point"}
}