{
  "type": "Feature",
  "properties": {
    "addr:full":"5620 Birdcage St Citrus Heights CA 95610",
    "addr:housenumber":"5620",
    "addr:postcode":"95610",
    "addr:street":"Birdcage St",
    "iso:country":"US",
    "sg:address":"5620 Birdcage St",
    "sg:city":"Citrus Heights",
    "sg:classifiers":[
        {
            "category":"Insurance",
            "subcategory":"Insurance Agent",
            "type":"Services"
        }
    ],
    "sg:phone":"+1 916 962 3190",
    "sg:postcode":"95610",
    "sg:province":"CA",
    "sg:tags":[
        "administrator"
    ],
    "wof:name":"Alternative Svc Concepts",
    "wof:placetype":"venue"
},
  "geometry": {"coordinates":[-121.27370500000001,38.669982],"type":"Point"}
}