{
  "type": "Feature",
  "properties": {
    "addr:full":"7806 Rosewood Ave Los Angeles CA 90036",
    "addr:housenumber":"7806",
    "addr:postcode":"90036",
    "addr:street":"Rosewood Ave",
    "iso:country":"US",
    "sg:address":"7806 Rosewood Ave",
    "sg:city":"Los Angeles",
    "sg:classifiers":[
        {
            "category":"Professional",
            "type":"Services"
        }
    ],
    "sg:phone":"+1 323 874 4719",
    "sg:postcode":"90036",
    "sg:province":"CA",
    "wof:name":"House of Joseph Music",
    "wof:placetype":"venue"
},
  "geometry": {"coordinates":[-118.35986699999999,34.080123],"type":"Point"}
}