{
  "type": "Feature",
  "properties": {
    "addr:full":"2740 Gamble Ct Hayward CA 94542",
    "addr:housenumber":"2740",
    "addr:postcode":"94542",
    "addr:street":"Gamble Ct",
    "iso:country":"US",
    "sg:address":"2740 Gamble Ct",
    "sg:city":"Hayward",
    "sg:classifiers":[
        {
            "category":"Professional",
            "type":"Services"
        }
    ],
    "sg:phone":"+1 510 581 5511",
    "sg:postcode":"94542",
    "sg:province":"CA",
    "wof:name":"Sunny Global Inc",
    "wof:placetype":"venue"
},
  "geometry": {"coordinates":[-122.040147,37.650343],"type":"Point"}
}