{
  "type": "Feature",
  "properties": {
    "addr:full":"16430 Ventura Blvd Encino CA 91436",
    "addr:housenumber":"16430",
    "addr:postcode":"91436",
    "addr:street":"Ventura Blvd",
    "iso:country":"US",
    "sg:address":"16430 Ventura Blvd",
    "sg:city":"Encino",
    "sg:classifiers":[
        {
            "category":"Health Services",
            "subcategory":"Optometrist",
            "type":"Services"
        }
    ],
    "sg:phone":"+1 818 905 3233",
    "sg:postcode":"91436",
    "sg:province":"CA",
    "wof:name":"Fyeye Optometry Ctr",
    "wof:placetype":"venue"
},
  "geometry": {"coordinates":[-118.49180200000001,34.157399],"type":"Point"}
}