{
  "type": "Feature",
  "properties": {
    "iso:country":"US",
    "sg:address":"14361 Morton St",
    "sg:city":"Tustin",
    "sg:classifiers":[
        {
            "category":"Real Estate",
            "subcategory":"Real Estate Agent",
            "type":"Services"
        }
    ],
    "sg:phone":"+1 714 544 7981",
    "sg:postcode":"92780",
    "sg:province":"CA",
    "wof:name":"Fox C R Bob",
    "wof:placetype":"venue"
},
  "geometry": {"coordinates":[-117.808011,33.754229],"type":"Point"}
}