{
  "type": "Feature",
  "properties": {
    "iso:country":"US",
    "sg:address":"1837 N Hacienda Blvd",
    "sg:city":"City Of Industry",
    "sg:classifiers":[
        {
            "category":"Professional",
            "subcategory":"Employment Agencies",
            "type":"Services"
        }
    ],
    "sg:phone":"+1 626 917 8517",
    "sg:postcode":"91744",
    "sg:province":"CA",
    "sg:tags":[
        "help",
        "contractor"
    ],
    "wof:name":"Benchmark Staffing",
    "wof:placetype":"venue"
},
  "geometry": {"coordinates":[-117.943596,34.050888],"type":"Point"}
}