{
  "type": "Feature",
  "properties": {
    "addr:full":"4100 Semallon Dr Modesto CA 95356",
    "addr:housenumber":"4100",
    "addr:postcode":"ca 95356",
    "addr:street":"Semallon Dr",
    "iso:country":"US",
    "sg:address":"4100 Semallon Dr",
    "sg:city":"Modesto",
    "sg:classifiers":[
        {
            "category":"Insurance",
            "subcategory":"Health Insurance",
            "type":"Services"
        }
    ],
    "sg:phone":"+1 209 409 8470",
    "sg:postcode":"95356",
    "sg:province":"CA",
    "sg:tags":[
        "maintenance"
    ],
    "wof:name":"Amn Healthcare Inc",
    "wof:placetype":"venue"
},
  "geometry": {"coordinates":[-121.004141,37.698397],"type":"Point"}
}