{
  "type": "Feature",
  "properties": {
    "iso:country":"US",
    "sg:address":"351 A St",
    "sg:city":"Alameda",
    "sg:classifiers":[
        {
            "category":"Building & Trades",
            "subcategory":"Construction",
            "type":"Services"
        }
    ],
    "sg:phone":"+1 510 337 0733",
    "sg:postcode":"94525",
    "sg:province":"CA",
    "wof:name":"Wagner Construction",
    "wof:placetype":"venue"
},
  "geometry": {"coordinates":[-122.248087,38.049208],"type":"Point"}
}