{
  "type": "Feature",
  "properties": {
    "iso:country":"US",
    "sg:address":"441 N Central Ave Ste 2",
    "sg:city":"Campbell",
    "sg:classifiers":[
        {
            "category":"Insurance",
            "subcategory":"Hazard Insurance",
            "type":"Services"
        }
    ],
    "sg:phone":"+1 408 353 0303",
    "sg:postcode":"95008",
    "sg:province":"CA",
    "sg:website":"www.insuringcampbell.com/",
    "wof:name":"Kelly Katz - State Farm",
    "wof:placetype":"venue"
},
  "geometry": {"coordinates":[-121.943698,37.293528],"type":"Point"}
}