{
  "type": "Feature",
  "properties": {
    "addr:full":"2842 36th Ave San Francisco CA 94116",
    "addr:housenumber":"2842",
    "addr:postcode":"94116",
    "addr:street":"36Th Ave",
    "iso:country":"US",
    "sg:address":"2842 36th Ave",
    "sg:city":"San Francisco",
    "sg:classifiers":[
        {
            "category":"Autos & Motor Vehicles",
            "subcategory":"Automobile Sales",
            "type":"Retail Goods"
        }
    ],
    "sg:phone":"+1 415 753 6000",
    "sg:postcode":"94116",
    "sg:province":"CA",
    "sg:tags":[
        "used",
        "edible",
        "nut",
        "aircraft",
        "fruit",
        "dried"
    ],
    "wof:name":"Aerotrader Sales Inc",
    "wof:placetype":"venue"
},
  "geometry": {"coordinates":[-122.493291,37.734376],"type":"Point"}
}