{
  "type": "Feature",
  "properties": {
    "addr:full":"255 E Alvin Dr Salinas CA 93906",
    "addr:housenumber":"255",
    "addr:postcode":"93906",
    "addr:street":"E Alvin Dr",
    "iso:country":"US",
    "sg:address":"255 E Alvin Dr",
    "sg:city":"Salinas",
    "sg:classifiers":[
        {
            "category":"Organizations",
            "subcategory":"Religious Organization",
            "type":"Services"
        }
    ],
    "sg:phone":"+1 831 449 9479",
    "sg:postcode":"93906",
    "sg:province":"CA",
    "wof:name":"Corporation of President of Th",
    "wof:placetype":"venue"
},
  "geometry": {"coordinates":[-121.647885,36.707857],"type":"Point"}
}