{
  "type": "Feature",
  "properties": {
    "iso:country":"US",
    "sg:address":"40927 Big Bear Blvd",
    "sg:city":"Big Bear Lake",
    "sg:classifiers":[
        {
            "category":"Personal",
            "subcategory":"Beauty Salon",
            "type":"Services"
        }
    ],
    "sg:phone":"+1 909 866 4247",
    "sg:postcode":"92315",
    "sg:province":"CA",
    "wof:name":"Village Hairsmith",
    "wof:placetype":"venue"
},
  "geometry": {"coordinates":[-116.909246,34.243575],"type":"Point"}
}