{
  "type": "Feature",
  "properties": {
    "addr:full":"21880 Hawthorne Blvd Torrance CA 90503",
    "addr:housenumber":"21880",
    "addr:postcode":"90503",
    "addr:street":"Hawthorne Blvd",
    "iso:country":"US",
    "sg:address":"21880 Hawthorne Blvd",
    "sg:city":"Torrance",
    "sg:classifiers":[
        {
            "category":"Shopping",
            "subcategory":"Jewelry",
            "type":"Retail Goods"
        }
    ],
    "sg:phone":"+1 310 793 8777",
    "sg:postcode":"90503",
    "sg:province":"CA",
    "wof:name":"Daniel's",
    "wof:placetype":"venue"
},
  "geometry": {"coordinates":[-118.351634,33.827448],"type":"Point"}
}