{
  "type": "Feature",
  "properties": {
    "addr:full":"16100 W Bethany Rd Tracy CA 95304",
    "addr:housenumber":"16100",
    "addr:postcode":"95304",
    "addr:street":"W Bethany Rd",
    "iso:country":"US",
    "sg:address":"16100 W Bethany Rd",
    "sg:city":"Tracy",
    "sg:classifiers":[
        {
            "category":"Sports & Exercise",
            "subcategory":"Stables",
            "type":"Entertainment"
        },
        {
            "category":"Sports & Exercise",
            "subcategory":"Race Track",
            "type":"Entertainment"
        }
    ],
    "sg:phone":"+1 209 346 0581",
    "sg:postcode":"95304",
    "sg:province":"CA",
    "sg:tags":[
        "horse",
        "horse-boarding"
    ],
    "wof:name":"Dreamer Stables",
    "wof:placetype":"venue"
},
  "geometry": {"coordinates":[-121.513842,37.780364],"type":"Point"}
}