{
  "type": "Feature",
  "properties": {
    "iso:country":"US",
    "sg:address":"10120 Garden Grove Blvd",
    "sg:city":"Garden Grove",
    "sg:classifiers":[
        {
            "category":"Food & Beverages",
            "subcategory":"Bakery",
            "type":"Retail Goods"
        }
    ],
    "sg:phone":"+1 714 530 9060",
    "sg:postcode":"92844",
    "sg:province":"CA",
    "sg:tags":[
        "sandwich"
    ],
    "sg:website":"www.subway.com",
    "wof:name":"Subway",
    "wof:placetype":"venue"
},
  "geometry": {"coordinates":[-117.956217,33.773394],"type":"Point"}
}