{
  "type": "Feature",
  "properties": {
    "addr:full":"9618 W Chapman Ave Garden Grove CA 92841",
    "addr:housenumber":"9618",
    "addr:postcode":"92841",
    "addr:street":"W Chapman Ave",
    "iso:country":"US",
    "sg:address":"9618 W Chapman Ave",
    "sg:city":"Garden Grove",
    "sg:classifiers":[
        {
            "category":"Organizations",
            "subcategory":"Professional Association",
            "type":"Services"
        }
    ],
    "sg:phone":"+1 714 537 4638",
    "sg:postcode":"92841",
    "sg:province":"CA",
    "wof:name":"Mugunghwa USA",
    "wof:placetype":"venue"
},
  "geometry": {"coordinates":[-117.966668,33.788456],"type":"Point"}
}