{
  "type": "Feature",
  "properties": {
    "iso:country":"US",
    "sg:address":"9405 Gregory St",
    "sg:city":"La Mesa",
    "sg:classifiers":[
        {
            "category":"Education",
            "subcategory":"School",
            "type":"Public Place"
        }
    ],
    "sg:phone":"+1 619 668 5830",
    "sg:postcode":"91942",
    "sg:province":"CA",
    "wof:name":"Northmont Elementary School",
    "wof:placetype":"venue"
},
  "geometry": {"coordinates":[-116.992718,32.790809],"type":"Point"}
}