{
  "type": "Feature",
  "properties": {
    "iso:country":"US",
    "sg:address":"3301 Rosehedge Dr",
    "sg:city":"Fullerton",
    "sg:classifiers":[
        {
            "category":"Communications",
            "subcategory":"Film & Video Production",
            "type":"Services"
        }
    ],
    "sg:phone":"+1 714 871 0814",
    "sg:postcode":"92835",
    "sg:province":"CA",
    "sg:tags":[
        "taping"
    ],
    "wof:name":"LMS Media",
    "wof:placetype":"venue"
},
  "geometry": {"coordinates":[-117.92033,33.912369],"type":"Point"}
}