{
  "type": "Feature",
  "properties": {
    "addr:full":"360 Guerrero St San Francisco CA 94103",
    "addr:housenumber":"360",
    "addr:postcode":"94103",
    "addr:street":"Guerrero St",
    "iso:country":"US",
    "sg:address":"360 Guerrero St",
    "sg:city":"San Francisco",
    "sg:classifiers":[
        {
            "category":"Professional",
            "subcategory":"Advertising",
            "type":"Services"
        }
    ],
    "sg:phone":"+1 415 293 8464",
    "sg:postcode":"94103",
    "sg:province":"CA",
    "sg:tags":[
        "agency"
    ],
    "wof:name":"Connectionmedia",
    "wof:placetype":"venue"
},
  "geometry": {"coordinates":[-122.42430299999999,37.765769],"type":"Point"}
}