{
  "type": "Feature",
  "properties": {
    "addr:full":"10951 W Pico Boulevard Los Angeles CA 90064",
    "addr:housenumber":"10951",
    "addr:postcode":"90064",
    "addr:street":"W Pico Boulevard",
    "iso:country":"US",
    "sg:address":"10951 W Pico Boulevard",
    "sg:city":"Los Angeles",
    "sg:classifiers":[
        {
            "category":"Banks & Credit Unions",
            "subcategory":"Financial Services",
            "type":"Services"
        }
    ],
    "sg:phone":"+1 310 474 7534",
    "sg:postcode":"90064",
    "sg:province":"CA",
    "sg:tags":[
        "broker",
        "mortgage"
    ],
    "wof:name":"Sunrise Mortgage & Investment Company.",
    "wof:placetype":"venue"
},
  "geometry": {"coordinates":[-118.43114,34.038894],"type":"Point"}
}