{
  "type": "Feature",
  "properties": {
    "addr:full":"129 S Kathleen Ln Orange CA 92869",
    "addr:housenumber":"129",
    "addr:postcode":"92869",
    "addr:street":"S Kathleen Ln",
    "iso:country":"US",
    "sg:address":"129 S Kathleen Ln",
    "sg:city":"Orange",
    "sg:classifiers":[
        {
            "category":"Utilities",
            "subcategory":"Refuse",
            "type":"Services"
        }
    ],
    "sg:phone":"+1 714 538 3387",
    "sg:postcode":"92869",
    "sg:province":"CA",
    "sg:tags":[
        "asbestos",
        "abatement"
    ],
    "wof:name":"Complete Abatement",
    "wof:placetype":"venue"
},
  "geometry": {"coordinates":[-117.821006,33.78416],"type":"Point"}
}