{
  "type": "Feature",
  "properties": {
    "addr:full":"2287 S Grand Ave Santa Ana CA 92705",
    "addr:housenumber":"2287",
    "addr:postcode":"92705",
    "addr:street":"S Grand Ave",
    "iso:country":"US",
    "sg:address":"2287 S Grand Ave",
    "sg:city":"Santa Ana",
    "sg:classifiers":[
        {
            "category":"Manufacturing",
            "subcategory":"Tools & Machinery",
            "type":"Manufacturing & Wholesale Goods"
        }
    ],
    "sg:phone":"+1 714 754 1430",
    "sg:postcode":"92705",
    "sg:province":"CA",
    "sg:tags":[
        "machine",
        "mfg",
        "accessory"
    ],
    "wof:name":"CK Industries",
    "wof:placetype":"venue"
},
  "geometry": {"coordinates":[-117.850455,33.719414],"type":"Point"}
}