{
  "type": "Feature",
  "properties": {
    "addr:full":"8777 Skyway Rd Paradise CA 95969",
    "addr:housenumber":"8777",
    "addr:postcode":"95969",
    "addr:street":"Skyway Rd",
    "iso:country":"US",
    "sg:address":"8777 Skyway Rd",
    "sg:city":"Paradise",
    "sg:classifiers":[
        {
            "category":"Health Services",
            "subcategory":"Clinic",
            "type":"Services"
        }
    ],
    "sg:phone":"+1 530 872 3720",
    "sg:postcode":"95969",
    "sg:province":"CA",
    "sg:tags":[
        "home",
        "care"
    ],
    "wof:name":"North State Home Health Care",
    "wof:placetype":"venue"
},
  "geometry": {"coordinates":[-121.59794599999999,39.785145],"type":"Point"}
}