{
  "type": "Feature",
  "properties": {
    "addr:full":"3555 India St San Diego CA 92103",
    "addr:housenumber":"3555",
    "addr:postcode":"92103",
    "addr:street":"India St",
    "iso:country":"US",
    "sg:address":"3555 India St",
    "sg:city":"San Diego",
    "sg:classifiers":[
        {
            "category":"Wholesale",
            "subcategory":"Groceries",
            "type":"Manufacturing & Wholesale Goods"
        }
    ],
    "sg:phone":"+1 619 296 0245",
    "sg:postcode":"92103",
    "sg:province":"CA",
    "sg:tags":[
        "baker"
    ],
    "wof:name":"Frank's Bakery",
    "wof:placetype":"venue"
},
  "geometry": {"coordinates":[-117.178386,32.740106],"type":"Point"}
}