{
  "type": "Feature",
  "properties": {
    "addr:full":"4000 Foothills Blvd Roseville CA 95747",
    "addr:housenumber":"4000",
    "addr:postcode":"95747",
    "addr:street":"Foothills Blvd",
    "iso:country":"US",
    "sg:address":"4000 Foothills Blvd",
    "sg:city":"Roseville",
    "sg:classifiers":[
        {
            "category":"Health Services",
            "subcategory":"Doctor",
            "type":"Services"
        }
    ],
    "sg:phone":"+1 916 771 7200",
    "sg:postcode":"95747",
    "sg:province":"CA",
    "sg:tags":[
        "dentist"
    ],
    "wof:name":"A Plus Dental",
    "wof:placetype":"venue"
},
  "geometry": {"coordinates":[-121.309106,38.743815],"type":"Point"}
}