{
  "type": "Feature",
  "properties": {
    "addr:full":"3815 Atlantic Ave Long Beach CA 90807",
    "addr:housenumber":"3815",
    "addr:postcode":"90807",
    "addr:street":"Atlantic Ave",
    "iso:country":"US",
    "sg:address":"3815 Atlantic Ave",
    "sg:city":"Long Beach",
    "sg:classifiers":[
        {
            "category":"Health Services",
            "subcategory":"Health Practitioner",
            "type":"Services"
        }
    ],
    "sg:phone":"+1 562 896 3685",
    "sg:postcode":"90807",
    "sg:province":"CA",
    "sg:tags":[
        "acupuncture",
        "traditional",
        "medicine",
        "chinese"
    ],
    "sg:website":"www.essentialasianmedicine.com",
    "wof:name":"Essential Asian Medicine",
    "wof:placetype":"venue"
},
  "geometry": {"coordinates":[-118.18544199999999,33.827346],"type":"Point"}
}