{
  "type": "Feature",
  "properties": {
    "addr:full":"111 W Bastanchury Rd Fullerton CA 92835",
    "addr:housenumber":"111",
    "addr:postcode":"92835",
    "addr:street":"W Bastanchury Rd",
    "iso:country":"US",
    "sg:address":"111 W Bastanchury Rd",
    "sg:city":"Fullerton",
    "sg:classifiers":[
        {
            "category":"Insurance",
            "subcategory":"Insurance Agent",
            "type":"Services"
        }
    ],
    "sg:phone":"+1 714 525 4477",
    "sg:postcode":"92835",
    "sg:province":"CA",
    "wof:name":"Bushala Insurance",
    "wof:placetype":"venue"
},
  "geometry": {"coordinates":[-117.93052,33.89466],"type":"Point"}
}