{
  "type": "Feature",
  "properties": {
    "addr:full":"7522 Park Ave Garden Grove CA 92841",
    "addr:housenumber":"7522",
    "addr:postcode":"92841",
    "addr:street":"Park Ave",
    "iso:country":"US",
    "sg:address":"7522 Park Ave",
    "sg:city":"Garden Grove",
    "sg:classifiers":[
        {
            "category":"Wholesale",
            "subcategory":"Auto Parts",
            "type":"Manufacturing & Wholesale Goods"
        }
    ],
    "sg:phone":"+1 714 534 6882",
    "sg:postcode":"92841",
    "sg:province":"CA",
    "sg:tags":[
        "automobile",
        "supply"
    ],
    "wof:name":"Hillco Fastener Warehouse",
    "wof:placetype":"venue"
},
  "geometry": {"coordinates":[-117.999622,33.776897],"type":"Point"}
}