{
  "type": "Feature",
  "properties": {
    "iso:country":"US",
    "sg:address":"1215 Burlingame Ave",
    "sg:city":"Burlingame",
    "sg:classifiers":[
        {
            "category":"Shopping",
            "subcategory":"Clothing, Apparel, & Fashions",
            "type":"Retail Goods"
        }
    ],
    "sg:phone":"+1 650 558 1122",
    "sg:postcode":"94010",
    "sg:province":"CA",
    "sg:tags":[
        "infant",
        "wear"
    ],
    "wof:name":"Jacadi",
    "wof:placetype":"venue"
},
  "geometry": {"coordinates":[-122.346957,37.578574],"type":"Point"}
}