{
  "type": "Feature",
  "properties": {
    "addr:full":"311 Summerhill Dr Lake Elsinore CA 92532",
    "addr:housenumber":"311",
    "addr:postcode":"92532",
    "addr:street":"Summerhill Dr",
    "iso:country":"US",
    "sg:address":"311 Summerhill Dr",
    "sg:city":"Lake Elsinore",
    "sg:classifiers":[
        {
            "category":"Retail",
            "subcategory":"Auto Repair",
            "type":"Services"
        }
    ],
    "sg:phone":"+1 909 471 8445",
    "sg:postcode":"92532",
    "sg:province":"CA",
    "sg:website":"LosAngelesCA.JiffyLube.com",
    "wof:name":"Jiffy Lube",
    "wof:placetype":"venue"
},
  "geometry": {"coordinates":[-117.299211,33.664239],"type":"Point"}
}