{
  "type": "Feature",
  "properties": {
    "iso:country":"US",
    "sg:address":"619 Davenport Dr",
    "sg:city":"San Jose",
    "sg:classifiers":[
        {
            "category":"Wholesale",
            "subcategory":"Stationery",
            "type":"Manufacturing & Wholesale Goods"
        },
        {
            "category":"Wholesale",
            "subcategory":"Non-durable Goods",
            "type":"Manufacturing & Wholesale Goods"
        }
    ],
    "sg:phone":"+1 408 729 8355",
    "sg:postcode":"95127",
    "sg:province":"CA",
    "sg:tags":[
        "packaging",
        "material"
    ],
    "wof:name":"Bryce Packaging Company",
    "wof:placetype":"venue"
},
  "geometry": {"coordinates":[-121.810208,37.366843],"type":"Point"}
}