{
  "type": "Feature",
  "properties": {
    "addr:full":"913 Blossom Hill Rd San Jose CA 95123",
    "addr:housenumber":"913",
    "addr:postcode":"95123",
    "addr:street":"Blossom Hill Rd",
    "iso:country":"US",
    "sg:address":"913 Blossom Hill Rd",
    "sg:city":"San Jose",
    "sg:classifiers":[
        {
            "category":"Cinema",
            "subcategory":"Movie Theater",
            "type":"Entertainment"
        }
    ],
    "sg:phone":"+1 408 227 6660",
    "sg:postcode":"95123",
    "sg:province":"CA",
    "wof:name":"AMC Theatres Oakridge",
    "wof:placetype":"venue"
},
  "geometry": {"coordinates":[-121.86283299999999,37.250458],"type":"Point"}
}