{
  "type": "Feature",
  "properties": {
    "iso:country":"US",
    "sg:address":"552 W el Paso Ave",
    "sg:city":"Clovis",
    "sg:classifiers":[
        {
            "category":"Social Services",
            "subcategory":"Adult Care",
            "type":"Services"
        }
    ],
    "sg:phone":"+1 559 323 9583",
    "sg:postcode":"93611",
    "sg:province":"CA",
    "sg:tags":[
        "home",
        "residential"
    ],
    "wof:name":"Clovis Quality Care",
    "wof:placetype":"venue"
},
  "geometry": {"coordinates":[-119.723952,36.848768],"type":"Point"}
}