{
  "type": "Feature",
  "properties": {
    "addr:full":"12195 Hwy 116 Guerneville CA 95446",
    "addr:housenumber":"12195",
    "addr:postcode":"95446",
    "addr:street":"Hwy 116",
    "iso:country":"US",
    "sg:address":"12195 Hwy 116",
    "sg:city":"Guerneville",
    "sg:classifiers":[
        {
            "category":"Professional",
            "type":"Services"
        }
    ],
    "sg:phone":"+1 707 869 1277",
    "sg:postcode":"95446",
    "sg:province":"CA",
    "sg:tags":[
        "caterer"
    ],
    "sg:website":"www.grapevinecatering.com",
    "wof:name":"Grapevine Catering Company",
    "wof:placetype":"venue"
},
  "geometry": {"coordinates":[-122.99125600000001,38.498574],"type":"Point"}
}