{
  "type": "Feature",
  "properties": {
    "addr:full":"16107 Gale Ave City Of Industry CA 91745",
    "addr:housenumber":"16107",
    "addr:postcode":"91745",
    "addr:street":"Gale Ave",
    "iso:country":"US",
    "sg:address":"16107 Gale Ave",
    "sg:city":"City Of Industry",
    "sg:classifiers":[
        {
            "category":"Food & Beverages",
            "subcategory":"Groceries & Convenience Stores",
            "type":"Retail Goods"
        }
    ],
    "sg:phone":"+1 626 333 7310",
    "sg:postcode":"91745",
    "sg:province":"CA",
    "wof:name":"7-Eleven",
    "wof:placetype":"venue"
},
  "geometry": {"coordinates":[-117.95563799999999,34.008692],"type":"Point"}
}