{
  "type": "Feature",
  "properties": {
    "addr:full":"5221 Gilmore Ave Bakersfield CA 93308",
    "addr:housenumber":"5221",
    "addr:postcode":"93308",
    "addr:street":"Gilmore Ave",
    "iso:country":"US",
    "sg:address":"5221 Gilmore Ave",
    "sg:city":"Bakersfield",
    "sg:classifiers":[
        {
            "category":"Wholesale",
            "subcategory":"Metals & Minerals",
            "type":"Manufacturing & Wholesale Goods"
        }
    ],
    "sg:phone":"+1 661 326 7800",
    "sg:postcode":"93308",
    "sg:province":"CA",
    "sg:tags":[
        "pipe"
    ],
    "wof:name":"P & F Distributors",
    "wof:placetype":"venue"
},
  "geometry": {"coordinates":[-119.03821499999999,35.389367],"type":"Point"}
}