{
  "type": "Feature",
  "properties": {
    "addr:full":"20301 Ventura Blvd Ste 100 Woodland Hills CA 91364",
    "addr:housenumber":"20301",
    "addr:postcode":"91364",
    "addr:street":"Ventura Blvd Ste 100",
    "iso:country":"US",
    "sg:address":"20301 Ventura Blvd Ste 100",
    "sg:city":"Woodland Hills",
    "sg:classifiers":[
        {
            "category":"Professional",
            "subcategory":"Accounting & Tax Preparation",
            "type":"Services"
        }
    ],
    "sg:phone":"+1 818 710 0622",
    "sg:postcode":"91364",
    "sg:province":"CA",
    "sg:tags":[
        "accountant"
    ],
    "wof:name":"Machado Othon E CPA/Anderson Satuloff M",
    "wof:placetype":"venue"
},
  "geometry": {"coordinates":[-118.574997,34.169498],"type":"Point"}
}