{
  "type": "Feature",
  "properties": {
    "addr:full":"1115 Bridgeway Sausalito CA 94965",
    "addr:housenumber":"1115",
    "addr:postcode":"94965",
    "addr:street":"Bridgeway",
    "iso:country":"US",
    "sg:address":"1115 Bridgeway",
    "sg:city":"Sausalito",
    "sg:classifiers":[
        {
            "category":"Restaurant",
            "type":"Food & Drink"
        }
    ],
    "sg:menulink":"http://www.allmenus.com/ca/southeast-marin/50240-salsalito-taco-shop/menu/",
    "sg:phone":"+1 415 331 5595",
    "sg:postcode":"94965",
    "sg:province":"CA",
    "sg:tags":[
        "mexican"
    ],
    "wof:name":"Salsalito Taco Shop",
    "wof:placetype":"venue"
},
  "geometry": {"coordinates":[-122.48410800000001,37.858766],"type":"Point"}
}