{
  "type": "Feature",
  "properties": {
    "iso:country":"US",
    "sg:address":"3687 Memory Ln",
    "sg:city":"South Lake Tahoe",
    "sg:classifiers":[
        {
            "category":"Building & Trades",
            "subcategory":"Landscaping Services",
            "type":"Services"
        }
    ],
    "sg:phone":"+1 530 573 1049",
    "sg:postcode":"96150",
    "sg:province":"CA",
    "sg:tags":[
        "landscape",
        "contractor"
    ],
    "wof:name":"Andrews Drip Irrigation",
    "wof:placetype":"venue"
},
  "geometry": {"coordinates":[-120.019465,38.806214],"type":"Point"}
}