{
  "type": "Feature",
  "properties": {
    "addr:full":"205 S Farrell Dr Palm Springs CA 92262",
    "addr:housenumber":"205",
    "addr:postcode":"92262",
    "addr:street":"S Farrell Dr",
    "iso:country":"US",
    "sg:address":"205 S Farrell Dr",
    "sg:city":"Palm Springs",
    "sg:classifiers":[
        {
            "category":"Shopping",
            "subcategory":"Stationery & Office Supplies",
            "type":"Retail Goods"
        }
    ],
    "sg:phone":"+1 760 325 5383",
    "sg:postcode":"92262",
    "sg:province":"CA",
    "sg:tags":[
        "equipment"
    ],
    "sg:website":"www.officemax.com",
    "wof:name":"Officemax",
    "wof:placetype":"venue"
},
  "geometry": {"coordinates":[-116.53800200000001,33.841599],"type":"Point"}
}