{
  "type": "Feature",
  "properties": {
    "addr:full":"3410 Industrial Blvd West Sacramento CA 95691",
    "addr:housenumber":"3410",
    "addr:postcode":"95691",
    "addr:street":"Industrial Blvd",
    "iso:country":"US",
    "sg:address":"3410 Industrial Blvd",
    "sg:city":"West Sacramento",
    "sg:classifiers":[
        {
            "category":"Wholesale",
            "subcategory":"Electrical",
            "type":"Manufacturing & Wholesale Goods"
        }
    ],
    "sg:phone":"+1 916 372 1207",
    "sg:postcode":"95691",
    "sg:province":"CA",
    "sg:tags":[
        "wire",
        "cable"
    ],
    "wof:name":"Anixter",
    "wof:placetype":"venue"
},
  "geometry": {"coordinates":[-121.55631099999999,38.573362],"type":"Point"}
}