{
  "type": "Feature",
  "properties": {
    "iso:country":"US",
    "sg:address":"8800 N Old Stage Rd",
    "sg:city":"Weed",
    "sg:classifiers":[
        {
            "category":"Farming",
            "subcategory":"Livestock Farm",
            "type":"Manufacturing & Wholesale Goods"
        }
    ],
    "sg:phone":"+1 530 938 4200",
    "sg:postcode":"96094",
    "sg:province":"CA",
    "sg:tags":[
        "animal",
        "association",
        "general"
    ],
    "wof:name":"Hammond Ranch Fire Co",
    "wof:placetype":"venue"
},
  "geometry": {"coordinates":[-122.414189,41.396785],"type":"Point"}
}