{
  "type": "Feature",
  "properties": {
    "addr:full":"7156 10th Ave Tahoma CA 96142",
    "addr:housenumber":"7156",
    "addr:postcode":"96142",
    "addr:street":"10Th Ave",
    "iso:country":"US",
    "sg:address":"7156 10th Ave",
    "sg:city":"Tahoma",
    "sg:classifiers":[
        {
            "category":"Shopping",
            "subcategory":"Computers & Home Electronics",
            "type":"Retail Goods"
        }
    ],
    "sg:phone":"+1 530 525 5744",
    "sg:postcode":"96142",
    "sg:province":"CA",
    "sg:tags":[
        "television",
        "radio"
    ],
    "wof:name":"Associated Distributors",
    "wof:placetype":"venue"
},
  "geometry": {"coordinates":[-120.13423400000001,39.061395],"type":"Point"}
}