{
  "type": "Feature",
  "properties": {
    "addr:full":"3050 W Lincoln Ave Anaheim CA 92801",
    "addr:housenumber":"3050",
    "addr:postcode":"92801",
    "addr:street":"W Lincoln Ave",
    "iso:country":"US",
    "sg:address":"3050 W Lincoln Ave",
    "sg:city":"Anaheim",
    "sg:classifiers":[
        {
            "category":"Personal",
            "subcategory":"Nail Salon",
            "type":"Services"
        }
    ],
    "sg:phone":"+1 714 821 1927",
    "sg:postcode":"92801",
    "sg:province":"CA",
    "wof:name":"Elegant Nails",
    "wof:placetype":"venue"
},
  "geometry": {"coordinates":[-117.996002,33.831902],"type":"Point"}
}