{
  "type": "Feature",
  "properties": {
    "addr:full":"2121 Airpark Dr Redding CA 96001",
    "addr:housenumber":"2121",
    "addr:postcode":"96001",
    "addr:street":"Airpark Dr",
    "iso:country":"US",
    "sg:address":"2121 Airpark Dr",
    "sg:city":"Redding",
    "sg:classifiers":[
        {
            "category":"Health Services",
            "subcategory":"Doctor",
            "type":"Services"
        }
    ],
    "sg:phone":"+1 530 244 6001",
    "sg:postcode":"96001",
    "sg:province":"CA",
    "sg:tags":[
        "physician",
        "surgeon"
    ],
    "wof:name":"Anthony Thijssen MD",
    "wof:placetype":"venue"
},
  "geometry": {"coordinates":[-122.404833,40.57451],"type":"Point"}
}