{
  "type": "Feature",
  "properties": {
    "addr:full":"720 The Alameda Berkeley CA 94707",
    "addr:housenumber":"720",
    "addr:postcode":"94707",
    "addr:street":"The Alameda",
    "iso:country":"US",
    "sg:address":"720 The Alameda",
    "sg:city":"Berkeley",
    "sg:classifiers":[
        {
            "category":"Real Estate",
            "subcategory":"Real Estate Agent",
            "type":"Services"
        }
    ],
    "sg:phone":"+1 510 524 6711",
    "sg:postcode":"94707",
    "sg:province":"CA",
    "wof:name":"Jackson & Karr Real Estate Brokers",
    "wof:placetype":"venue"
},
  "geometry": {"coordinates":[-122.277939,37.895248],"type":"Point"}
}