{
  "type": "Feature",
  "properties": {
    "iso:country":"US",
    "sg:address":"201 S Lasky Dr",
    "sg:city":"Beverly Hills",
    "sg:classifiers":[
        {
            "category":"Health Services",
            "subcategory":"Chiropractor",
            "type":"Services"
        }
    ],
    "sg:phone":"+1 310 282 0667",
    "sg:postcode":"90212",
    "sg:province":"CA",
    "wof:name":"Gary Tearston",
    "wof:placetype":"venue"
},
  "geometry": {"coordinates":[-118.410145,34.499792],"type":"Point"}
}