{
  "type": "Feature",
  "properties": {
    "addr:full":"3769 Old Conejo Rd Newbury Park CA 91320",
    "addr:housenumber":"3769",
    "addr:postcode":"91320",
    "addr:street":"Old Conejo Rd",
    "iso:country":"US",
    "sg:address":"3769 Old Conejo Rd",
    "sg:city":"Newbury Park",
    "sg:classifiers":[
        {
            "category":"Building & Trades",
            "subcategory":"Plumbing",
            "type":"Services"
        }
    ],
    "sg:phone":"+1 805 499 9003",
    "sg:postcode":"91320",
    "sg:province":"CA",
    "sg:tags":[
        "ventilating",
        "contractor"
    ],
    "wof:name":"Temp-Tec",
    "wof:placetype":"venue"
},
  "geometry": {"coordinates":[-118.95592000000001,34.192335],"type":"Point"}
}