{
  "type": "Feature",
  "properties": {
    "addr:full":"20 Healdsburg Ave Healdsburg CA 95448",
    "addr:housenumber":"20",
    "addr:postcode":"95448",
    "addr:street":"Healdsburg Ave",
    "iso:country":"US",
    "sg:address":"20 Healdsburg Ave",
    "sg:city":"Healdsburg",
    "sg:classifiers":[
        {
            "category":"Autos & Motor Vehicles",
            "subcategory":"Boat Sales",
            "type":"Retail Goods"
        }
    ],
    "sg:phone":"+1 707 433 5599",
    "sg:postcode":"95448",
    "sg:province":"CA",
    "wof:name":"Soar Inflatables",
    "wof:placetype":"venue"
},
  "geometry": {"coordinates":[-122.863007,38.60392],"type":"Point"}
}