{
  "type": "Feature",
  "properties": {
    "iso:country":"US",
    "sg:address":"111 N Hill St",
    "sg:city":"Los Angeles",
    "sg:classifiers":[
        {
            "category":"Professional",
            "subcategory":"Secretarial Services",
            "type":"Services"
        }
    ],
    "sg:phone":"+1 213 485 1519",
    "sg:postcode":"90012",
    "sg:province":"CA",
    "sg:tags":[
        "convention",
        "court",
        "reporter"
    ],
    "wof:name":"L A County Court Reporters Inc",
    "wof:placetype":"venue"
},
  "geometry": {"coordinates":[-118.244637,34.056444],"type":"Point"}
}