{
  "type": "Feature",
  "properties": {
    "iso:country":"US",
    "sg:address":"203 Cll del Oaks",
    "sg:city":"Monterey",
    "sg:classifiers":[
        {
            "category":"Building & Trades",
            "subcategory":"Construction",
            "type":"Services"
        }
    ],
    "sg:phone":"+1 831 392 1129",
    "sg:postcode":"93940",
    "sg:province":"CA",
    "sg:tags":[
        "contractor"
    ],
    "wof:name":"Fowler Construction",
    "wof:placetype":"venue"
},
  "geometry": {"coordinates":[-121.83075100000001,36.585025],"type":"Point"}
}