{
  "type": "Feature",
  "properties": {
    "addr:full":"1350 Huntington Ave. San Bruno CA 94066",
    "addr:housenumber":"1350",
    "addr:postcode":"94066",
    "addr:street":"Huntington Ave.",
    "iso:country":"US",
    "sg:address":"1350 Huntington Ave.",
    "sg:city":"San Bruno",
    "sg:classifiers":[
        {
            "category":"Travel",
            "subcategory":"Hotels & Motels",
            "type":"Entertainment"
        },
        {
            "category":"Retail",
            "subcategory":"Event Space",
            "type":"Services"
        }
    ],
    "sg:phone":"+1 650 588 0770",
    "sg:postcode":"94066",
    "sg:province":"CA",
    "sg:tags":[
        "venue"
    ],
    "sg:website":"www.staybridge.com",
    "wof:name":"Staybridge Suites Extended Stay Hotel San Francisco Airport",
    "wof:placetype":"venue"
},
  "geometry": {"coordinates":[-122.41906299999999,37.641547],"type":"Point"}
}