{
  "type": "Feature",
  "properties": {
    "addr:full":"26550 Ynez Rd Temecula CA 92591",
    "addr:housenumber":"26550",
    "addr:postcode":"92591",
    "addr:street":"Ynez Rd",
    "iso:country":"US",
    "sg:address":"26550 Ynez Rd",
    "sg:city":"Temecula",
    "sg:phone":"+1 951 296 3668",
    "sg:postcode":"92591",
    "sg:province":"CA",
    "wof:name":"Ming's Restaurant",
    "wof:placetype":"venue"
},
  "geometry": {"coordinates":[-117.156904,33.521572],"type":"Point"}
}