{
  "type": "Feature",
  "properties": {
    "addr:full":"1400 Estelle Ln Newport Beach CA 92660",
    "addr:housenumber":"1400",
    "addr:postcode":"92660",
    "addr:street":"Estelle Ln",
    "iso:country":"US",
    "sg:address":"1400 Estelle Ln",
    "sg:city":"Newport Beach",
    "sg:classifiers":[
        {
            "category":"Airport",
            "type":"Transportation"
        }
    ],
    "sg:phone":"+1 949 645 7081",
    "sg:postcode":"92660",
    "sg:province":"CA",
    "sg:tags":[
        "aircraft",
        "maintenance"
    ],
    "wof:name":"Newport Aviation Svc",
    "wof:placetype":"venue"
},
  "geometry": {"coordinates":[-117.89918299999999,33.631057],"type":"Point"}
}