{
  "type": "Feature",
  "properties": {
    "iso:country":"US",
    "sg:address":"4519 Santa Monica Blvd",
    "sg:city":"Los Angeles",
    "sg:classifiers":[
        {
            "category":"Bars & Pubs",
            "type":"Food & Drink"
        }
    ],
    "sg:phone":"+1 323 660 4540",
    "sg:postcode":"90029",
    "sg:province":"CA",
    "sg:tags":[
        "dance",
        "club"
    ],
    "sg:website":"www.littletemple.com",
    "wof:name":"The Little Temple",
    "wof:placetype":"venue"
},
  "geometry": {"coordinates":[-118.287098,34.090994],"type":"Point"}
}