{
  "type": "Feature",
  "properties": {
    "iso:country":"US",
    "sg:address":"1316 S Allec St",
    "sg:city":"Anaheim",
    "sg:classifiers":[
        {
            "category":"Travel",
            "subcategory":"Hotels & Motels",
            "type":"Entertainment"
        }
    ],
    "sg:phone":"+1 714 956 7588",
    "sg:postcode":"92805",
    "sg:province":"CA",
    "wof:name":"Stonex Tile",
    "wof:placetype":"venue"
},
  "geometry": {"coordinates":[-117.901543,33.815807],"type":"Point"}
}