{
  "type": "Feature",
  "properties": {
    "addr:full":"11908 Firestone Blvd Norwalk CA 90650",
    "addr:housenumber":"11908",
    "addr:postcode":"90650",
    "addr:street":"Firestone Blvd",
    "iso:country":"US",
    "sg:address":"11908 Firestone Blvd",
    "sg:city":"Norwalk",
    "sg:classifiers":[
        {
            "category":"Professional",
            "subcategory":"Lawyer & Legal Services",
            "type":"Services"
        }
    ],
    "sg:phone":"+1 562 864 9978",
    "sg:postcode":"90650",
    "sg:province":"CA",
    "sg:tags":[
        "naturalization",
        "immigration"
    ],
    "wof:name":"Morillo Income Tax & Travel",
    "wof:placetype":"venue"
},
  "geometry": {"coordinates":[-118.08163399999999,33.912634],"type":"Point"}
}