{
  "type": "Feature",
  "properties": {
    "iso:country":"US",
    "sg:address":"19225 Clymer St",
    "sg:city":"Northridge",
    "sg:classifiers":[
        {
            "category":"Professional",
            "type":"Services"
        }
    ],
    "sg:phone":"+1 818 832 3972",
    "sg:postcode":"91326",
    "sg:province":"CA",
    "wof:name":"Artist and Creations",
    "wof:placetype":"venue"
},
  "geometry": {"coordinates":[-118.55363699999999,34.262741],"type":"Point"}
}