{
  "type": "Feature",
  "properties": {
    "iso:country":"US",
    "sg:address":"12917 Park St",
    "sg:city":"Santa Fe Springs",
    "sg:classifiers":[
        {
            "category":"Manufacturing",
            "subcategory":"Metals",
            "type":"Manufacturing & Wholesale Goods"
        }
    ],
    "sg:phone":"+1 562 946 7472",
    "sg:postcode":"90670",
    "sg:province":"CA",
    "sg:tags":[
        "coating"
    ],
    "wof:name":"Surface Modification Systems",
    "wof:placetype":"venue"
},
  "geometry": {"coordinates":[-118.057045,33.940519],"type":"Point"}
}