{
  "type": "Feature",
  "properties": {
    "addr:full":"380 Pitt Ave Sebastopol CA 95472",
    "addr:housenumber":"380",
    "addr:postcode":"95472",
    "addr:street":"Pitt Ave",
    "iso:country":"US",
    "sg:address":"380 Pitt Ave",
    "sg:city":"Sebastopol",
    "sg:classifiers":[
        {
            "category":"Building & Trades",
            "subcategory":"Plumbing",
            "type":"Services"
        }
    ],
    "sg:phone":"+1 707 583 2320",
    "sg:postcode":"95472",
    "sg:province":"CA",
    "sg:tags":[
        "conditioning",
        "air",
        "system",
        "contractor"
    ],
    "wof:name":"John L Ross AC",
    "wof:placetype":"venue"
},
  "geometry": {"coordinates":[-122.82749200000001,38.403977],"type":"Point"}
}