{
  "type": "Feature",
  "properties": {
    "iso:country":"US",
    "sg:address":"210 S. Juniper St. #100",
    "sg:city":"Escondido",
    "sg:classifiers":[
        {
            "category":"Real Estate",
            "subcategory":"Real Estate Services",
            "type":"Services"
        },
        {
            "category":"Building & Trades",
            "subcategory":"Construction",
            "type":"Services"
        },
        {
            "category":"Real Estate",
            "subcategory":"Real Estate Agent",
            "type":"Services"
        }
    ],
    "sg:phone":"+1 858 342 2686",
    "sg:postcode":"92025",
    "sg:province":"CA",
    "sg:tags":[
        "management",
        "cabins",
        "log",
        "broker",
        "buyer",
        "home",
        "rental"
    ],
    "sg:website":"http://www.AdvantageREpros.com",
    "wof:name":"Advantage Real Estate Professionals",
    "wof:placetype":"venue"
},
  "geometry": {"coordinates":[-117.078023,33.122027],"type":"Point"}
}