{
  "type": "Feature",
  "properties": {
    "iso:country":"US",
    "sg:address":"563 Crows Landing Rd",
    "sg:city":"Modesto",
    "sg:classifiers":[
        {
            "category":"Shopping",
            "subcategory":"Party Supplies",
            "type":"Retail Goods"
        }
    ],
    "sg:phone":"+1 209 548 0818",
    "sg:postcode":"95351",
    "sg:province":"CA",
    "wof:name":"D Todo Party Store",
    "wof:placetype":"venue"
},
  "geometry": {"coordinates":[-120.99299600000001,37.622898],"type":"Point"}
}