{
  "type": "Feature",
  "properties": {
    "addr:full":"1000 Northgate Dr San Rafael CA 94903",
    "addr:housenumber":"1000",
    "addr:postcode":"94903",
    "addr:street":"Northgate Dr",
    "iso:country":"US",
    "sg:address":"1000 Northgate Dr",
    "sg:city":"San Rafael",
    "sg:classifiers":[
        {
            "category":"Shopping",
            "subcategory":"Department Store",
            "type":"Retail Goods"
        }
    ],
    "sg:phone":"+1 415 499 5200",
    "sg:postcode":"94903",
    "sg:province":"CA",
    "wof:name":"Macy's",
    "wof:placetype":"venue"
},
  "geometry": {"coordinates":[-122.54540900000001,38.008969],"type":"Point"}
}