{
  "type": "Feature",
  "properties": {
    "iso:country":"US",
    "sg:address":"10265 Old Placerville Rd",
    "sg:city":"Sacramento",
    "sg:classifiers":[
        {
            "category":"Professional",
            "subcategory":"Advertising",
            "type":"Services"
        }
    ],
    "sg:phone":"+1 916 363 1471",
    "sg:postcode":"95827",
    "sg:province":"CA",
    "sg:tags":[
        "counselor"
    ],
    "wof:name":"T S Media",
    "wof:placetype":"venue"
},
  "geometry": {"coordinates":[-121.311511,38.564914],"type":"Point"}
}