{
  "type": "Feature",
  "properties": {
    "iso:country":"US",
    "sg:address":"2351 Clay St",
    "sg:city":"San Francisco",
    "sg:classifiers":[
        {
            "category":"Professional",
            "subcategory":"Computer Services",
            "type":"Services"
        }
    ],
    "sg:phone":"+1 415 885 8660",
    "sg:postcode":"94115",
    "sg:province":"CA",
    "sg:tags":[
        "graphics"
    ],
    "sg:website":"www.eslidesource.com",
    "wof:name":"Slidesource Computer Graphic",
    "wof:placetype":"venue"
},
  "geometry": {"coordinates":[-122.43206600000001,37.790915],"type":"Point"}
}