{
  "type": "Feature",
  "properties": {
    "iso:country":"US",
    "sg:address":"7834 Newman Ave",
    "sg:city":"Huntington Beach",
    "sg:classifiers":[
        {
            "category":"Building & Trades",
            "subcategory":"Construction",
            "type":"Services"
        }
    ],
    "sg:phone":"+1 714 841 8711",
    "sg:postcode":"92647",
    "sg:province":"CA",
    "sg:tags":[
        "contractor"
    ],
    "wof:name":"Clean Slate Window Cleaning Service",
    "wof:placetype":"venue"
},
  "geometry": {"coordinates":[-117.991649,33.704768],"type":"Point"}
}