{
  "type": "Feature",
  "properties": {
    "addr:full":"111 Rea Ave El Cajon CA 92020",
    "addr:housenumber":"111",
    "addr:postcode":"92020",
    "addr:street":"Rea Ave",
    "iso:country":"US",
    "sg:address":"111 Rea Ave",
    "sg:city":"El Cajon",
    "sg:classifiers":[
        {
            "category":"Travel",
            "subcategory":"Travel Agent",
            "type":"Entertainment"
        }
    ],
    "sg:phone":"+1 619 588 4644",
    "sg:postcode":"92020",
    "sg:province":"CA",
    "sg:tags":[
        "operator",
        "tour"
    ],
    "wof:name":"Misha Tours",
    "wof:placetype":"venue"
},
  "geometry": {"coordinates":[-116.960354,32.795614],"type":"Point"}
}