{
  "type": "Feature",
  "properties": {
    "iso:country":"US",
    "sg:address":"49 N Craig Ave Apt 4",
    "sg:city":"Pasadena",
    "sg:classifiers":[
        {
            "category":"Communications",
            "subcategory":"Film & Video Production",
            "type":"Services"
        }
    ],
    "sg:phone":"+1 818 378 9045",
    "sg:postcode":"91107",
    "sg:province":"CA",
    "sg:tags":[
        "services-commercial"
    ],
    "wof:name":"Prometheus Entertainment",
    "wof:placetype":"venue"
},
  "geometry": {"coordinates":[-118.106199,34.146895],"type":"Point"}
}