{
  "type": "Feature",
  "properties": {
    "iso:country":"US",
    "sg:address":"960 Atlantic Ave",
    "sg:city":"Alameda",
    "sg:classifiers":[
        {
            "category":"Health Services",
            "subcategory":"Medical Lab",
            "type":"Services"
        }
    ],
    "sg:phone":"+1 510 747 1740",
    "sg:postcode":"94501",
    "sg:province":"CA",
    "sg:tags":[
        "laboratories-pathological",
        "laboratory"
    ],
    "wof:name":"Berkeley Heartlab, Inc.",
    "wof:placetype":"venue"
},
  "geometry": {"coordinates":[-122.26879700000001,37.781116],"type":"Point"}
}