{
  "type": "Feature",
  "properties": {
    "iso:country":"US",
    "sg:address":"24005 Calabasas Rd",
    "sg:city":"Calabasas",
    "sg:classifiers":[
        {
            "category":"Restaurant",
            "type":"Food & Drink"
        }
    ],
    "sg:phone":"+1 818 223 8112",
    "sg:postcode":"91302",
    "sg:province":"CA",
    "sg:website":"www.redrobin.com",
    "wof:name":"Red Robin Restaurant",
    "wof:placetype":"venue"
},
  "geometry": {"coordinates":[-118.650002,34.153],"type":"Point"}
}