{
  "type": "Feature",
  "properties": {
    "addr:full":"2141 E Ave Q Palmdale CA 93550",
    "addr:housenumber":"2141",
    "addr:postcode":"ca 93550",
    "addr:street":"E Ave Q",
    "iso:country":"US",
    "sg:address":"2141 E Ave Q",
    "sg:city":"Palmdale",
    "sg:classifiers":[
        {
            "category":"Organizations",
            "subcategory":"Membership Organization",
            "type":"Services"
        }
    ],
    "sg:phone":"+1 661 266 3008",
    "sg:postcode":"93550",
    "sg:province":"CA",
    "wof:name":"Palmdale Woman's Club",
    "wof:placetype":"venue"
},
  "geometry": {"coordinates":[-118.09159200000001,34.587512],"type":"Point"}
}