{
  "type": "Feature",
  "properties": {
    "iso:country":"US",
    "sg:address":"10740 Vanowen St",
    "sg:city":"North Hollywood",
    "sg:classifiers":[
        {
            "category":"Autos & Motor Vehicles",
            "subcategory":"Fuel & Gas Station",
            "type":"Retail Goods"
        }
    ],
    "sg:phone":"+1 818 508 6282",
    "sg:postcode":"91605",
    "sg:province":"CA",
    "sg:tags":[
        "oil"
    ],
    "wof:name":"Quality Auto Repair",
    "wof:placetype":"venue"
},
  "geometry": {"coordinates":[-118.365815,34.19387],"type":"Point"}
}