{
  "type": "Feature",
  "properties": {
    "addr:full":"349 Scenic Pl Manteca CA 95337",
    "addr:housenumber":"349",
    "addr:postcode":"95337",
    "addr:street":"Scenic Pl",
    "iso:country":"US",
    "sg:address":"349 Scenic Pl",
    "sg:city":"Manteca",
    "sg:classifiers":[
        {
            "category":"Professional",
            "subcategory":"Engineering",
            "type":"Services"
        }
    ],
    "sg:phone":"+1 209 239 8090",
    "sg:postcode":"95337",
    "sg:province":"CA",
    "sg:tags":[
        "engineer"
    ],
    "wof:name":"Sandpiper Technologies",
    "wof:placetype":"venue"
},
  "geometry": {"coordinates":[-121.233007,37.803198],"type":"Point"}
}