{
  "type": "Feature",
  "properties": {
    "iso:country":"US",
    "sg:address":"1677 Superior Ave Unit H",
    "sg:city":"Costa Mesa",
    "sg:classifiers":[
        {
            "category":"Sports & Exercise",
            "subcategory":"Gym",
            "type":"Entertainment"
        }
    ],
    "sg:phone":"+1 949 502 1673",
    "sg:postcode":"92627",
    "sg:province":"CA",
    "sg:website":"www.orangecoastcrossfit.com",
    "wof:name":"Orange Coast CrossFit",
    "wof:placetype":"venue"
},
  "geometry": {"coordinates":[-117.92482,33.635405],"type":"Point"}
}