{
  "type": "Feature",
  "properties": {
    "addr:full":"725 Madison St Oakland CA 94607",
    "addr:housenumber":"725",
    "addr:postcode":"94607",
    "addr:street":"Madison St",
    "iso:country":"US",
    "sg:address":"725 Madison St",
    "sg:city":"Oakland",
    "sg:classifiers":[
        {
            "category":"Building & Trades",
            "subcategory":"Cleaning & Sanitation",
            "type":"Services"
        }
    ],
    "sg:phone":"+1 510 334 8630",
    "sg:postcode":"94607",
    "sg:province":"CA",
    "sg:tags":[
        "carpet"
    ],
    "wof:name":"Bay Area Dry Master",
    "wof:placetype":"venue"
},
  "geometry": {"coordinates":[-122.266803,37.797184],"type":"Point"}
}