{
  "type": "Feature",
  "properties": {
    "iso:country":"US",
    "sg:address":"3220 Merrill Dr",
    "sg:city":"Torrance",
    "sg:classifiers":[
        {
            "category":"Building & Trades",
            "subcategory":"Electrical",
            "type":"Services"
        }
    ],
    "sg:phone":"+1 310 515 6606",
    "sg:postcode":"90503",
    "sg:province":"CA",
    "sg:tags":[
        "electrical",
        "contractor"
    ],
    "wof:name":"Best Electric Corp",
    "wof:placetype":"venue"
},
  "geometry": {"coordinates":[-118.342328,33.830178],"type":"Point"}
}