{
  "type": "Feature",
  "properties": {
    "addr:full":"6155 Bella Oaks Ct Livermore CA 94550",
    "addr:housenumber":"6155",
    "addr:postcode":"94550",
    "addr:street":"Bella Oaks Ct",
    "iso:country":"US",
    "sg:address":"6155 Bella Oaks Ct",
    "sg:city":"Livermore",
    "sg:classifiers":[
        {
            "category":"Retail",
            "subcategory":"Laundry & Dry Cleaning",
            "type":"Services"
        }
    ],
    "sg:phone":"+1 510 768 0374",
    "sg:postcode":"94550",
    "sg:province":"CA",
    "sg:tags":[
        "cleaner",
        "rug",
        "carpet"
    ],
    "wof:name":"DK Clean",
    "wof:placetype":"venue"
},
  "geometry": {"coordinates":[-121.71550999999999,37.667906],"type":"Point"}
}