{
  "type": "Feature",
  "properties": {
    "addr:full":"186 Kings Ln Bakersfield CA 93308",
    "addr:housenumber":"186",
    "addr:postcode":"93308",
    "addr:street":"Kings Ln",
    "iso:country":"US",
    "sg:address":"186 Kings Ln",
    "sg:city":"Bakersfield",
    "sg:classifiers":[
        {
            "category":"Professional",
            "type":"Services"
        }
    ],
    "sg:phone":"+1 661 387 9788",
    "sg:postcode":"93308",
    "sg:province":"CA",
    "wof:name":"M McKinley",
    "wof:placetype":"venue"
},
  "geometry": {"coordinates":[-119.03592500000001,35.408351],"type":"Point"}
}