{
  "type": "Feature",
  "properties": {
    "addr:full":"13505 Whittier Blvd Whittier CA 90605",
    "addr:housenumber":"13505",
    "addr:postcode":"90605",
    "addr:street":"Whittier Blvd",
    "iso:country":"US",
    "sg:address":"13505 Whittier Blvd",
    "sg:city":"Whittier",
    "sg:phone":"+1 562 696 7979",
    "sg:postcode":"90605",
    "sg:province":"CA",
    "sg:website":"http://www.saloncheval.net",
    "wof:name":"Salon Cheval, L.L.C.",
    "wof:placetype":"venue"
},
  "geometry": {"coordinates":[-118.030599,33.961805],"type":"Point"}
}