{
  "type": "Feature",
  "properties": {
    "iso:country":"US",
    "sg:address":"527 N Beachwood Dr",
    "sg:city":"Burbank",
    "sg:classifiers":[
        {
            "category":"Building & Trades",
            "subcategory":"Electrical",
            "type":"Services"
        }
    ],
    "sg:phone":"+1 818 845 2133",
    "sg:postcode":"91506",
    "sg:province":"CA",
    "sg:tags":[
        "electrician"
    ],
    "wof:name":"Burbank Electric",
    "wof:placetype":"venue"
},
  "geometry": {"coordinates":[-118.324997,34.175999],"type":"Point"}
}