{
  "type": "Feature",
  "properties": {
    "addr:full":"3375 Jefferson St Napa CA 94558",
    "addr:housenumber":"3375",
    "addr:postcode":"94558",
    "addr:street":"Jefferson St",
    "iso:country":"US",
    "sg:address":"3375 Jefferson St",
    "sg:city":"Napa",
    "sg:classifiers":[
        {
            "category":"Food & Beverages",
            "subcategory":"Groceries & Convenience Stores",
            "type":"Retail Goods"
        }
    ],
    "sg:phone":"+1 707 255 0866",
    "sg:postcode":"94558",
    "sg:province":"CA",
    "sg:tags":[
        "supermarket"
    ],
    "wof:name":"Safeway",
    "wof:placetype":"venue"
},
  "geometry": {"coordinates":[-122.299593,38.321331],"type":"Point"}
}