{
  "type": "Feature",
  "properties": {
    "addr:full":"4418 Kraft Ave North Hollywood CA 91602",
    "addr:housenumber":"4418",
    "addr:postcode":"91602",
    "addr:street":"Kraft Ave",
    "iso:country":"US",
    "sg:address":"4418 Kraft Ave",
    "sg:city":"North Hollywood",
    "sg:classifiers":[
        {
            "category":"Communications",
            "subcategory":"Film & Video Production",
            "type":"Services"
        }
    ],
    "sg:phone":"+1 818 508 8275",
    "sg:postcode":"91602",
    "sg:province":"CA",
    "sg:tags":[
        "consultant",
        "audio"
    ],
    "wof:name":"Audio Video Illusions",
    "wof:placetype":"venue"
},
  "geometry": {"coordinates":[-118.380004,34.151854],"type":"Point"}
}