{
  "type": "Feature",
  "properties": {
    "addr:full":"1320 Industrial Park Ave Redlands CA 92374",
    "addr:housenumber":"1320",
    "addr:postcode":"92374",
    "addr:street":"Industrial Park Ave",
    "iso:country":"US",
    "sg:address":"1320 Industrial Park Ave",
    "sg:city":"Redlands",
    "sg:classifiers":[
        {
            "category":"Restaurant",
            "type":"Food & Drink"
        }
    ],
    "sg:menulink":"http://www.allmenus.com/ca/san-bernardino/172002-burger-king/menu/",
    "sg:phone":"+1 909 798 4636",
    "sg:postcode":"92374",
    "sg:province":"CA",
    "sg:tags":[
        "burger",
        "american"
    ],
    "wof:name":"Burger King",
    "wof:placetype":"venue"
},
  "geometry": {"coordinates":[-117.201278,34.063248],"type":"Point"}
}