{
  "type": "Feature",
  "properties": {
    "iso:country":"US",
    "sg:address":"8725 Remmet Ave",
    "sg:city":"Canoga Park",
    "sg:classifiers":[
        {
            "category":"Wholesale",
            "subcategory":"Groceries",
            "type":"Manufacturing & Wholesale Goods"
        }
    ],
    "sg:phone":"+1 818 341 3376",
    "sg:postcode":"91304",
    "sg:province":"CA",
    "sg:tags":[
        "food",
        "product",
        "health"
    ],
    "wof:name":"Sunshine Valley Foods",
    "wof:placetype":"venue"
},
  "geometry": {"coordinates":[-118.600309,34.229606],"type":"Point"}
}