{
  "type": "Feature",
  "properties": {
    "addr:full":"820 Jackson St Los Angeles CA 90012",
    "addr:housenumber":"820",
    "addr:postcode":"90012",
    "addr:street":"Jackson St",
    "iso:country":"US",
    "sg:address":"820 Jackson St",
    "sg:city":"Los Angeles",
    "sg:classifiers":[
        {
            "category":"Wholesale",
            "subcategory":"Poultry",
            "type":"Manufacturing & Wholesale Goods"
        }
    ],
    "sg:phone":"+1 213 620 1263",
    "sg:postcode":"90012",
    "sg:province":"CA",
    "wof:name":"Woodland Processing Inc",
    "wof:placetype":"venue"
},
  "geometry": {"coordinates":[-118.23076500000001,34.050686],"type":"Point"}
}