{
  "type": "Feature",
  "properties": {
    "addr:full":"12775 Saratoga Woods Cir Saratoga CA 95070",
    "addr:housenumber":"12775",
    "addr:postcode":"95070",
    "addr:street":"Saratoga Woods Cir",
    "iso:country":"US",
    "sg:address":"12775 Saratoga Woods Cir",
    "sg:city":"Saratoga",
    "sg:classifiers":[
        {
            "category":"Professional",
            "type":"Services"
        }
    ],
    "sg:phone":"+1 408 741 1434",
    "sg:postcode":"95070",
    "sg:province":"CA",
    "wof:name":"Betty Eiler",
    "wof:placetype":"venue"
},
  "geometry": {"coordinates":[-122.031465,37.283248],"type":"Point"}
}