{
  "type": "Feature",
  "properties": {
    "iso:country":"US",
    "sg:address":"1879 Magnolia Ave",
    "sg:city":"Long Beach",
    "sg:classifiers":[
        {
            "category":"Travel",
            "subcategory":"Hotels & Motels",
            "type":"Entertainment"
        }
    ],
    "sg:phone":"+1 562 599 3609",
    "sg:postcode":"90806",
    "sg:province":"CA",
    "wof:name":"Princess Inn the",
    "wof:placetype":"venue"
},
  "geometry": {"coordinates":[-118.197998,33.791],"type":"Point"}
}