{
  "type": "Feature",
  "properties": {
    "addr:full":"54385 N Circle Dr Idyllwild CA 92549",
    "addr:housenumber":"54385",
    "addr:postcode":"92549",
    "addr:street":"N Circle Dr",
    "iso:country":"US",
    "sg:address":"54385 N Circle Dr",
    "sg:city":"Idyllwild",
    "sg:classifiers":[
        {
            "category":"Professional",
            "subcategory":"Business Services",
            "type":"Services"
        }
    ],
    "sg:phone":"+1 951 659 9844",
    "sg:postcode":"92549",
    "sg:province":"CA",
    "sg:tags":[
        "interior",
        "consultant",
        "design",
        "decorator"
    ],
    "wof:name":"Turner & Turner Interior Dsgn",
    "wof:placetype":"venue"
},
  "geometry": {"coordinates":[-116.71322499999999,33.745458],"type":"Point"}
}