{
  "type": "Feature",
  "properties": {
    "iso:country":"US",
    "sg:address":"14827 Clark Ave",
    "sg:city":"Hacienda Heights",
    "sg:classifiers":[
        {
            "category":"Building & Trades",
            "subcategory":"Electrical",
            "type":"Services"
        }
    ],
    "sg:phone":"+1 626 336 7070",
    "sg:postcode":"91745",
    "sg:province":"CA",
    "sg:tags":[
        "electrical",
        "contractor"
    ],
    "wof:name":"DS Electric",
    "wof:placetype":"venue"
},
  "geometry": {"coordinates":[-117.980783,34.021321],"type":"Point"}
}