{
  "type": "Feature",
  "properties": {
    "addr:full":"Hangar 19 1125 Miller Ave Oakland CA 94601",
    "addr:housenumber":"1125",
    "addr:postcode":"94601",
    "addr:street":"Miller Ave",
    "iso:country":"US",
    "sg:address":"Hangar 19 1125 Miller Ave",
    "sg:city":"Oakland",
    "sg:classifiers":[
        {
            "category":"Shopping",
            "subcategory":"Clothing, Apparel, & Fashions",
            "type":"Retail Goods"
        }
    ],
    "sg:postcode":"94601",
    "sg:province":"CA",
    "sg:website":"www.punkstuff.com",
    "wof:name":"Punkstuff",
    "wof:placetype":"venue"
},
  "geometry": {"coordinates":[-122.23630900000001,37.780969],"type":"Point"}
}