{
  "type": "Feature",
  "properties": {
    "addr:full":"3554 W Olympic Blvd Los Angeles CA 90019",
    "addr:housenumber":"3554",
    "addr:postcode":"90019",
    "addr:street":"W Olympic Blvd",
    "iso:country":"US",
    "sg:address":"3554 W Olympic Blvd",
    "sg:city":"Los Angeles",
    "sg:classifiers":[
        {
            "category":"Retail",
            "subcategory":"Car Wash",
            "type":"Services"
        }
    ],
    "sg:phone":"+1 323 737 2100",
    "sg:postcode":"90019",
    "sg:province":"CA",
    "sg:tags":[
        "polishing",
        "washing"
    ],
    "wof:name":"Olympic Car Wash",
    "wof:placetype":"venue"
},
  "geometry": {"coordinates":[-118.317001,34.0527],"type":"Point"}
}