{
  "type": "Feature",
  "properties": {
    "addr:full":"6107 Lake Murray Blvd La Mesa CA 91942",
    "addr:housenumber":"6107",
    "addr:postcode":"91942",
    "addr:street":"Lake Murray Blvd",
    "iso:country":"US",
    "sg:address":"6107 Lake Murray Blvd",
    "sg:city":"La Mesa",
    "sg:classifiers":[
        {
            "category":"Restaurant",
            "type":"Food & Drink"
        }
    ],
    "sg:phone":"+1 619 460 8800",
    "sg:postcode":"91942",
    "sg:province":"CA",
    "sg:tags":[
        "pizza"
    ],
    "wof:name":"Little Ceasars Pizza",
    "wof:placetype":"venue"
},
  "geometry": {"coordinates":[-117.132479,32.789611],"type":"Point"}
}