{
  "type": "Feature",
  "properties": {
    "addr:full":"10417 Mooney Flat Rd Big Oak Valley CA 95977",
    "addr:housenumber":"10417",
    "addr:postcode":"95977",
    "addr:street":"Mooney Flat Rd",
    "iso:country":"US",
    "sg:address":"10417 Mooney Flat Rd",
    "sg:city":"Big Oak Valley",
    "sg:classifiers":[
        {
            "category":"Manufacturing",
            "subcategory":"Signs",
            "type":"Manufacturing & Wholesale Goods"
        }
    ],
    "sg:phone":"+1 530 432 8390",
    "sg:postcode":"95977",
    "sg:province":"CA",
    "wof:name":"Linda's Custom Signs",
    "wof:placetype":"venue"
},
  "geometry": {"coordinates":[-121.276404,39.210846],"type":"Point"}
}