{
  "type": "Feature",
  "properties": {
    "addr:full":"1039 W Mission Ave Escondido CA 92025",
    "addr:housenumber":"1039",
    "addr:postcode":"92025",
    "addr:street":"W Mission Ave",
    "iso:country":"US",
    "sg:address":"1039 W Mission Ave",
    "sg:city":"Escondido",
    "sg:classifiers":[
        {
            "category":"Manufacturing",
            "subcategory":"Pottery",
            "type":"Manufacturing & Wholesale Goods"
        }
    ],
    "sg:phone":"+1 760 745 2968",
    "sg:postcode":"92025",
    "sg:province":"CA",
    "sg:tags":[
        "product",
        "ceramic",
        "mfr",
        "miscellaneous",
        "s",
        "retail"
    ],
    "wof:name":"Conley Ceramics",
    "wof:placetype":"venue"
},
  "geometry": {"coordinates":[-117.098726,33.126131],"type":"Point"}
}