{
  "type": "Feature",
  "properties": {
    "iso:country":"US",
    "sg:address":"443 W Garvey Ave",
    "sg:city":"Monterey Park",
    "sg:classifiers":[
        {
            "category":"Wholesale",
            "subcategory":"Durable Goods & Equipment",
            "type":"Manufacturing & Wholesale Goods"
        }
    ],
    "sg:phone":"+1 626 307 7838",
    "sg:postcode":"91754",
    "sg:province":"CA",
    "wof:name":"D & V International Inc",
    "wof:placetype":"venue"
},
  "geometry": {"coordinates":[-118.128557,34.062597],"type":"Point"}
}