{
  "type": "Feature",
  "properties": {
    "iso:country":"US",
    "sg:address":"801 12th St Ste 500",
    "sg:city":"Sacramento",
    "sg:classifiers":[
        {
            "category":"Banks & Credit Unions",
            "subcategory":"Financial Services",
            "type":"Services"
        }
    ],
    "sg:phone":"+1 916 444 2615",
    "sg:postcode":"95814",
    "sg:province":"CA",
    "sg:tags":[
        "loan",
        "mortgage"
    ],
    "wof:name":"National Homebuyers Fund",
    "wof:placetype":"venue"
},
  "geometry": {"coordinates":[-121.48988300000001,38.581791],"type":"Point"}
}