{
  "type": "Feature",
  "properties": {
    "iso:country":"US",
    "sg:address":"11270 Washington Blvd",
    "sg:city":"Culver City",
    "sg:classifiers":[
        {
            "category":"Wholesale",
            "subcategory":"Durable Goods & Equipment",
            "type":"Manufacturing & Wholesale Goods"
        }
    ],
    "sg:phone":"+1 310 206 1486",
    "sg:postcode":"90230",
    "sg:province":"CA",
    "wof:name":"Pacific Sports USA",
    "wof:placetype":"venue"
},
  "geometry": {"coordinates":[-118.414232,34.004878],"type":"Point"}
}