{
  "type": "Feature",
  "properties": {
    "iso:country":"US",
    "sg:address":"4860 W 147th St",
    "sg:city":"Hawthorne",
    "sg:classifiers":[
        {
            "category":"Shopping",
            "subcategory":"Computers & Home Electronics",
            "type":"Retail Goods"
        }
    ],
    "sg:phone":"+1 888 304 9966",
    "sg:postcode":"90250",
    "sg:province":"CA",
    "sg:website":"www.kencranesbigscreentvs.com",
    "wof:name":"Ken Crane's Home Entertainment City",
    "wof:placetype":"venue"
},
  "geometry": {"coordinates":[-118.363053,33.897411],"type":"Point"}
}