{
  "type": "Feature",
  "properties": {
    "iso:country":"US",
    "sg:address":"1021 W Bastanchury Rd",
    "sg:city":"Fullerton",
    "sg:classifiers":[
        {
            "category":"Real Estate",
            "subcategory":"Real Estate Agent",
            "type":"Services"
        }
    ],
    "sg:phone":"+1 714 738 5520",
    "sg:postcode":"92833",
    "sg:province":"CA",
    "sg:tags":[
        "management"
    ],
    "wof:name":"Advanced Property Management",
    "wof:placetype":"venue"
},
  "geometry": {"coordinates":[-117.947771,33.886072],"type":"Point"}
}