{
  "type": "Feature",
  "properties": {
    "iso:country":"US",
    "sg:address":"2322 Homestead Rd",
    "sg:city":"Santa Clara",
    "sg:classifiers":[
        {
            "category":"Real Estate",
            "subcategory":"Real Estate Operator",
            "type":"Services"
        }
    ],
    "sg:phone":"+1 408 246 8249",
    "sg:postcode":"95050",
    "sg:province":"CA",
    "sg:tags":[
        "apartment"
    ],
    "wof:name":"Royal Arms Apartments",
    "wof:placetype":"venue"
},
  "geometry": {"coordinates":[-121.964799,37.342016],"type":"Point"}
}