{
  "type": "Feature",
  "properties": {
    "addr:full":"5320 Alyssum Ct Santa Rosa CA 95403",
    "addr:housenumber":"5320",
    "addr:postcode":"95403",
    "addr:street":"Alyssum Ct",
    "iso:country":"US",
    "sg:address":"5320 Alyssum Ct",
    "sg:city":"Santa Rosa",
    "sg:classifiers":[
        {
            "category":"Building & Trades",
            "subcategory":"Electrical",
            "type":"Services"
        }
    ],
    "sg:phone":"+1 707 576 0392",
    "sg:postcode":"95403",
    "sg:province":"CA",
    "sg:tags":[
        "electric",
        "contractor"
    ],
    "wof:name":"JWB Electric",
    "wof:placetype":"venue"
},
  "geometry": {"coordinates":[-122.755218,38.511571],"type":"Point"}
}