{
  "type": "Feature",
  "properties": {
    "iso:country":"US",
    "sg:address":"14140 Palm Dr",
    "sg:city":"Desert Hot Spgs",
    "sg:classifiers":[
        {
            "category":"Wholesale",
            "subcategory":"Machinery & Supplies",
            "type":"Manufacturing & Wholesale Goods"
        }
    ],
    "sg:phone":"+1 760 251 7177",
    "sg:postcode":"92240",
    "sg:province":"CA",
    "sg:tags":[
        "equipment",
        "salon",
        "establishment",
        "beauty"
    ],
    "wof:name":"Carol's Hair & Beauty Supply",
    "wof:placetype":"venue"
},
  "geometry": {"coordinates":[-116.501289,33.94518],"type":"Point"}
}