{
  "type": "Feature",
  "properties": {
    "iso:country":"US",
    "sg:address":"879 Embarcadero Dr",
    "sg:city":"El Dorado Hills",
    "sg:classifiers":[
        {
            "category":"Restaurant",
            "type":"Food & Drink"
        }
    ],
    "sg:phone":"+1 916 933 3227",
    "sg:postcode":"95762",
    "sg:province":"CA",
    "wof:name":"Michelle's American Bistro",
    "wof:placetype":"venue"
},
  "geometry": {"coordinates":[-121.084369,38.708537],"type":"Point"}
}