{
  "type": "Feature",
  "properties": {
    "addr:full":"8178 Sunset Blvd Los Angeles CA 90046",
    "addr:housenumber":"8178",
    "addr:postcode":"90046",
    "addr:street":"Sunset Blvd",
    "iso:country":"US",
    "sg:address":"8178 Sunset Blvd",
    "sg:city":"Los Angeles",
    "sg:classifiers":[
        {
            "category":"Home & Garden",
            "subcategory":"Garden Supply",
            "type":"Retail Goods"
        },
        {
            "category":"Home & Garden",
            "subcategory":"Home Furnishings",
            "type":"Retail Goods"
        },
        {
            "category":"Wholesale",
            "subcategory":"Stationery",
            "type":"Manufacturing & Wholesale Goods"
        },
        {
            "category":"Shopping",
            "subcategory":"Hobbies, Toys, & Games",
            "type":"Retail Goods"
        }
    ],
    "sg:phone":"+1 323 656 5400",
    "sg:postcode":"90046",
    "sg:province":"CA",
    "sg:tags":[
        "decor",
        "toy",
        "store",
        "card"
    ],
    "sg:website":"www.tokyojls.com",
    "wof:name":"Tokyo Japanese Lifestyle",
    "wof:placetype":"venue"
},
  "geometry": {"coordinates":[-118.367254,34.09799],"type":"Point"}
}