{
  "type": "Feature",
  "properties": {
    "addr:full":"4 Macomber Rd Danville CA 94526",
    "addr:housenumber":"4",
    "addr:postcode":"94526",
    "addr:street":"Macomber Rd",
    "iso:country":"US",
    "sg:address":"4 Macomber Rd",
    "sg:city":"Danville",
    "sg:classifiers":[
        {
            "category":"Building & Trades",
            "subcategory":"Construction",
            "type":"Services"
        }
    ],
    "sg:phone":"+1 925 820 1508",
    "sg:postcode":"94526",
    "sg:province":"CA",
    "sg:tags":[
        "wallcoverings-installation",
        "wallpaper",
        "painting",
        "contractor"
    ],
    "wof:name":"Ionic Construction & Painting",
    "wof:placetype":"venue"
},
  "geometry": {"coordinates":[-122.009506,37.81918],"type":"Point"}
}