{
  "type": "Feature",
  "properties": {
    "iso:country":"US",
    "sg:address":"6466 Gayhart St",
    "sg:city":"Los Angeles",
    "sg:classifiers":[
        {
            "category":"Manufacturing",
            "subcategory":"Motor Vehicles & Parts",
            "type":"Manufacturing & Wholesale Goods"
        }
    ],
    "sg:phone":"+1 323 724 1555",
    "sg:postcode":"90040",
    "sg:province":"CA",
    "sg:tags":[
        "equipment",
        "truck"
    ],
    "wof:name":"Dynaflex Products",
    "wof:placetype":"venue"
},
  "geometry": {"coordinates":[-118.138462,34.000884],"type":"Point"}
}