{
  "type": "Feature",
  "properties": {
    "iso:country":"US",
    "sg:address":"24155 Laguna Hills",
    "sg:city":"Laguna Hills",
    "sg:classifiers":[
        {
            "category":"Food & Beverages",
            "subcategory":"Chocolate",
            "type":"Retail Goods"
        }
    ],
    "sg:postcode":"92653",
    "sg:province":"CA",
    "sg:tags":[
        "shop",
        "chocolatiers"
    ],
    "sg:website":"www.rmcf.com",
    "wof:name":"Rocky Mountain Chocolate Factory",
    "wof:placetype":"venue"
},
  "geometry": {"coordinates":[-117.70966300000001,33.612129],"type":"Point"}
}