{
  "type": "Feature",
  "properties": {
    "iso:country":"US",
    "sg:address":"1520 D St",
    "sg:city":"Sacramento",
    "sg:classifiers":[
        {
            "category":"Travel",
            "subcategory":"Travel Agent",
            "type":"Entertainment"
        }
    ],
    "sg:phone":"+1 916 448 7496",
    "sg:postcode":"95814",
    "sg:province":"CA",
    "sg:tags":[
        "agency",
        "bureau"
    ],
    "wof:name":"American Council-Intl Studies",
    "wof:placetype":"venue"
},
  "geometry": {"coordinates":[-121.48260399999999,38.584672],"type":"Point"}
}