{
  "type": "Feature",
  "properties": {
    "addr:full":"1913 E 17th St Ste 218 Santa Ana CA 92705",
    "addr:housenumber":"1913",
    "addr:postcode":"92705",
    "addr:street":"E 17Th St Ste 218",
    "iso:country":"US",
    "sg:address":"1913 E 17th St Ste 218",
    "sg:city":"Santa Ana",
    "sg:classifiers":[
        {
            "category":"Professional",
            "subcategory":"Employment Agencies",
            "type":"Services"
        }
    ],
    "sg:phone":"+1 714 245 2701",
    "sg:postcode":"92705",
    "sg:province":"CA",
    "wof:name":"Staffing Source 2000",
    "wof:placetype":"venue"
},
  "geometry": {"coordinates":[-117.843002,33.759899],"type":"Point"}
}