{
  "type": "Feature",
  "properties": {
    "iso:country":"US",
    "sg:address":"1370 N Brea Blvd",
    "sg:city":"Fullerton",
    "sg:classifiers":[
        {
            "category":"Wholesale",
            "subcategory":"Apparel",
            "type":"Manufacturing & Wholesale Goods"
        }
    ],
    "sg:phone":"+1 310 841 0456",
    "sg:postcode":"92835",
    "sg:province":"CA",
    "sg:tags":[
        "clothing"
    ],
    "wof:name":"Kill All Dinosaurs",
    "wof:placetype":"venue"
},
  "geometry": {"coordinates":[-117.924226,33.884085],"type":"Point"}
}