{
  "type": "Feature",
  "properties": {
    "iso:country":"US",
    "sg:address":"112 del Monte Dr",
    "sg:city":"Walnut Creek",
    "sg:classifiers":[
        {
            "category":"Building & Trades",
            "subcategory":"Construction",
            "type":"Services"
        }
    ],
    "sg:phone":"+1 925 934 9385",
    "sg:postcode":"94595",
    "sg:province":"CA",
    "sg:tags":[
        "residential"
    ],
    "wof:name":"Tom Young Enterprises",
    "wof:placetype":"venue"
},
  "geometry": {"coordinates":[-122.06636399999999,37.883849],"type":"Point"}
}