{
  "type": "Feature",
  "properties": {
    "addr:full":"9525 Brookside Ave Ben Lomond CA 95005",
    "addr:housenumber":"9525",
    "addr:postcode":"95005",
    "addr:street":"Brookside Ave",
    "iso:country":"US",
    "sg:address":"9525 Brookside Ave",
    "sg:city":"Ben Lomond",
    "sg:classifiers":[
        {
            "category":"Building & Trades",
            "subcategory":"Landscaping Services",
            "type":"Services"
        }
    ],
    "sg:phone":"+1 831 336 1446",
    "sg:postcode":"95005",
    "sg:province":"CA",
    "sg:tags":[
        "tree"
    ],
    "wof:name":"Low Cost Tree Svc",
    "wof:placetype":"venue"
},
  "geometry": {"coordinates":[-122.085792,37.090407],"type":"Point"}
}