{
  "type": "Feature",
  "properties": {
    "addr:full":"7 Altura Way S San Francisco CA 94080",
    "addr:housenumber":"7",
    "addr:postcode":"94080",
    "addr:street":"Altura Way S",
    "iso:country":"US",
    "sg:address":"7 Altura Way",
    "sg:city":"S San Francisco",
    "sg:classifiers":[
        {
            "category":"Manufacturing",
            "subcategory":"Rubber & Plastics",
            "type":"Manufacturing & Wholesale Goods"
        }
    ],
    "sg:phone":"+1 650 588 7401",
    "sg:postcode":"94080",
    "sg:province":"CA",
    "sg:tags":[
        "box",
        "transparent"
    ],
    "wof:name":"Interstate Consolidated Distr",
    "wof:placetype":"venue"
},
  "geometry": {"coordinates":[-122.445725,37.65864],"type":"Point"}
}