{
  "type": "Feature",
  "properties": {
    "addr:full":"10045 W Lincoln Ave Fresno CA 93706",
    "addr:housenumber":"10045",
    "addr:postcode":"93706",
    "addr:street":"W Lincoln Ave",
    "iso:country":"US",
    "sg:address":"10045 W Lincoln Ave",
    "sg:city":"Fresno",
    "sg:classifiers":[
        {
            "category":"Freight",
            "type":"Transportation"
        }
    ],
    "sg:phone":"+1 559 266 9249",
    "sg:postcode":"93706",
    "sg:province":"CA",
    "sg:tags":[
        "warehouse"
    ],
    "wof:name":"Gerawan Farming Inc",
    "wof:placetype":"venue"
},
  "geometry": {"coordinates":[-119.97861399999999,36.647747],"type":"Point"}
}