{
  "type": "Feature",
  "properties": {
    "addr:full":"3905 State St Santa Barbara CA 93105",
    "addr:housenumber":"3905",
    "addr:postcode":"93105",
    "addr:street":"State St",
    "iso:country":"US",
    "sg:address":"3905 State St",
    "sg:city":"Santa Barbara",
    "sg:classifiers":[
        {
            "category":"Restaurant",
            "type":"Food & Drink"
        }
    ],
    "sg:phone":"+1 805 569 5550",
    "sg:postcode":"93105",
    "sg:province":"CA",
    "sg:tags":[
        "sandwich"
    ],
    "wof:name":"Sam's To Go",
    "wof:placetype":"venue"
},
  "geometry": {"coordinates":[-119.753989,34.440285],"type":"Point"}
}