{
  "type": "Feature",
  "properties": {
    "iso:country":"US",
    "sg:address":"2363 Ulric St",
    "sg:city":"San Diego",
    "sg:classifiers":[
        {
            "category":"Shopping",
            "subcategory":"Music",
            "type":"Retail Goods"
        }
    ],
    "sg:phone":"+1 858 292 7999",
    "sg:postcode":"92111",
    "sg:province":"CA",
    "sg:tags":[
        "video",
        "disc",
        "tape",
        "cassette"
    ],
    "wof:name":"Gavi Video II",
    "wof:placetype":"venue"
},
  "geometry": {"coordinates":[-117.170202,32.786525],"type":"Point"}
}