{
  "type": "Feature",
  "properties": {
    "addr:full":"838 Pine Ave Long Beach CA 90813",
    "addr:housenumber":"838",
    "addr:postcode":"90813",
    "addr:street":"Pine Ave",
    "iso:country":"US",
    "sg:address":"838 Pine Ave",
    "sg:city":"Long Beach",
    "sg:classifiers":[
        {
            "category":"Building & Trades",
            "subcategory":"Construction",
            "type":"Services"
        }
    ],
    "sg:phone":"+1 562 432 4396",
    "sg:postcode":"90813",
    "sg:province":"CA",
    "sg:tags":[
        "home",
        "builder"
    ],
    "wof:name":"Shea Homes",
    "wof:placetype":"venue"
},
  "geometry": {"coordinates":[-118.192294,33.777646],"type":"Point"}
}