{
  "type": "Feature",
  "properties": {
    "addr:full":"4015 W Clinton Ave Fresno CA 93722",
    "addr:housenumber":"4015",
    "addr:postcode":"93722",
    "addr:street":"W Clinton Ave",
    "iso:country":"US",
    "sg:address":"4015 W Clinton Ave",
    "sg:city":"Fresno",
    "sg:classifiers":[
        {
            "category":"Restaurant",
            "type":"Food & Drink"
        }
    ],
    "sg:menulink":"http://www.allmenus.com/ca/fresno/200779-long-john-silvers/menu/",
    "sg:phone":"+1 559 276 1185",
    "sg:postcode":"93722",
    "sg:province":"CA",
    "sg:tags":[
        "seafood",
        "american"
    ],
    "wof:name":"Long John Silver's",
    "wof:placetype":"venue"
},
  "geometry": {"coordinates":[-119.862782,36.771522],"type":"Point"}
}