{
  "type": "Feature",
  "properties": {
    "addr:full":"2066 Redwood Hwy Greenbrae CA 94904",
    "addr:housenumber":"2066",
    "addr:postcode":"94904",
    "addr:street":"Redwood Hwy",
    "iso:country":"US",
    "sg:address":"2066 Redwood Hwy",
    "sg:city":"Greenbrae",
    "sg:classifiers":[
        {
            "category":"Retail",
            "subcategory":"Car Wash",
            "type":"Services"
        }
    ],
    "sg:phone":"+1 415 945 1309",
    "sg:postcode":"94904",
    "sg:province":"CA",
    "sg:tags":[
        "automobile",
        "detailing"
    ],
    "wof:name":"Lucky Drive Brushless Car Wash",
    "wof:placetype":"venue"
},
  "geometry": {"coordinates":[-122.516148,37.937223],"type":"Point"}
}