{
  "type": "Feature",
  "properties": {
    "addr:full":"5875 El Cajon Blvd San Diego CA 92115",
    "addr:housenumber":"5875",
    "addr:postcode":"92115",
    "addr:street":"El Cajon Blvd",
    "iso:country":"US",
    "sg:address":"5875 El Cajon Blvd",
    "sg:city":"San Diego",
    "sg:classifiers":[
        {
            "category":"Organizations",
            "subcategory":"Religious Organization",
            "type":"Services"
        }
    ],
    "sg:phone":"+1 619 286 3251",
    "sg:postcode":"92115",
    "sg:province":"CA",
    "wof:name":"All People's Church",
    "wof:placetype":"venue"
},
  "geometry": {"coordinates":[-117.091943,32.759286],"type":"Point"}
}