{
  "type": "Feature",
  "properties": {
    "addr:full":"9838 Flower St Bellflower CA 90706",
    "addr:housenumber":"9838",
    "addr:postcode":"90706",
    "addr:street":"Flower St",
    "iso:country":"US",
    "sg:address":"9838 Flower St",
    "sg:city":"Bellflower",
    "sg:classifiers":[
        {
            "category":"Health Services",
            "subcategory":"Optometrist",
            "type":"Services"
        }
    ],
    "sg:phone":"+1 562 920 1915",
    "sg:postcode":"90706",
    "sg:province":"CA",
    "wof:name":"Bellflower Eye Care",
    "wof:placetype":"venue"
},
  "geometry": {"coordinates":[-118.12400100000001,33.882],"type":"Point"}
}