{
  "type": "Feature",
  "properties": {
    "iso:country":"US",
    "sg:address":"13925 2nd St",
    "sg:city":"Whittier",
    "sg:classifiers":[
        {
            "category":"Professional",
            "subcategory":"Business Services",
            "type":"Services"
        }
    ],
    "sg:phone":"+1 562 693 9247",
    "sg:postcode":"90605",
    "sg:province":"CA",
    "wof:name":"Sarras Interiors",
    "wof:placetype":"venue"
},
  "geometry": {"coordinates":[-118.025085,33.963112],"type":"Point"}
}