{
  "type": "Feature",
  "properties": {
    "addr:full":"2148 Via Deste Campbell CA 95008",
    "addr:housenumber":"2148",
    "addr:postcode":"95008",
    "addr:street":"Via Deste",
    "iso:country":"US",
    "sg:address":"2148 Via Deste",
    "sg:city":"Campbell",
    "sg:classifiers":[
        {
            "category":"Government",
            "subcategory":"Fire Station",
            "type":"Public Place"
        }
    ],
    "sg:phone":"+1 408 679 9169",
    "sg:postcode":"95008",
    "sg:province":"CA",
    "sg:tags":[
        "repair",
        "maintenance",
        "equipment"
    ],
    "wof:name":"Silicon Valley Printer Service",
    "wof:placetype":"venue"
},
  "geometry": {"coordinates":[-121.967934,37.28344],"type":"Point"}
}