{
  "type": "Feature",
  "properties": {
    "addr:full":"17192 Englewood Cir Huntington Beach CA 92647",
    "addr:postcode":"17192;92647",
    "addr:street":"Englewood Cir",
    "iso:country":"US",
    "sg:address":"17192 Englewood Cir",
    "sg:city":"Huntington Beach",
    "sg:classifiers":[
        {
            "category":"Shopping",
            "subcategory":"Used Merchandise",
            "type":"Retail Goods"
        }
    ],
    "sg:phone":"+1 714 848 9177",
    "sg:postcode":"92647",
    "sg:province":"CA",
    "wof:name":"Buygone Goodies",
    "wof:placetype":"venue"
},
  "geometry": {"coordinates":[-118.016139,33.713001],"type":"Point"}
}