{
  "type": "Feature",
  "properties": {
    "iso:country":"US",
    "sg:address":"7410 Edgewater St",
    "sg:city":"Chowchilla",
    "sg:classifiers":[
        {
            "category":"Real Estate",
            "subcategory":"Real Estate Agent",
            "type":"Services"
        }
    ],
    "sg:phone":"+1 559 665 5719",
    "sg:postcode":"93610",
    "sg:province":"CA",
    "wof:name":"Littrell Homes",
    "wof:placetype":"venue"
},
  "geometry": {"coordinates":[-120.234544,37.118923],"type":"Point"}
}