{
  "type": "Feature",
  "properties": {
    "addr:full":"1700 N Tustin St Orange CA 92865",
    "addr:housenumber":"1700",
    "addr:postcode":"92865",
    "addr:street":"N Tustin St",
    "iso:country":"US",
    "sg:address":"1700 N Tustin St",
    "sg:city":"Orange",
    "sg:classifiers":[
        {
            "category":"Wholesale",
            "subcategory":"Auto Parts",
            "type":"Manufacturing & Wholesale Goods"
        }
    ],
    "sg:phone":"+1 714 637 3670",
    "sg:postcode":"92865",
    "sg:province":"CA",
    "sg:tags":[
        "automotive"
    ],
    "wof:name":"J and B Auto Parts",
    "wof:placetype":"venue"
},
  "geometry": {"coordinates":[-117.835893,33.817455],"type":"Point"}
}