{
  "type": "Feature",
  "properties": {
    "iso:country":"US",
    "sg:address":"890 Fargo Ave",
    "sg:city":"San Leandro",
    "sg:classifiers":[
        {
            "category":"Social Services",
            "subcategory":"Child Care",
            "type":"Services"
        }
    ],
    "sg:phone":"+1 510 895 8736",
    "sg:postcode":"94579",
    "sg:province":"CA",
    "sg:tags":[
        "day"
    ],
    "wof:name":"Li'l Angels Day Care Center",
    "wof:placetype":"venue"
},
  "geometry": {"coordinates":[-122.144997,37.688],"type":"Point"}
}