{
  "type": "Feature",
  "properties": {
    "addr:full":"251 Post St Ste 610 San Francisco CA 94108",
    "addr:housenumber":"251",
    "addr:postcode":"94108",
    "addr:street":"Post St Ste 610",
    "iso:country":"US",
    "sg:address":"251 Post St Ste 610",
    "sg:city":"San Francisco",
    "sg:classifiers":[
        {
            "category":"Arts & Performance",
            "subcategory":"Art Gallery",
            "type":"Entertainment"
        }
    ],
    "sg:phone":"+1 415 362 1480",
    "sg:postcode":"94108",
    "sg:province":"CA",
    "sg:website":"www.bondlatin.com",
    "wof:name":"Bond Latin Gallery",
    "wof:placetype":"venue"
},
  "geometry": {"coordinates":[-122.40615099999999,37.788524],"type":"Point"}
}