{
  "type": "Feature",
  "properties": {
    "iso:country":"US",
    "sg:address":"1000 Evans Ave",
    "sg:city":"San Francisco",
    "sg:classifiers":[
        {
            "category":"Utilities",
            "subcategory":"Electric",
            "type":"Services"
        }
    ],
    "sg:phone":"+1 415 695 2257",
    "sg:postcode":"94124",
    "sg:province":"CA",
    "sg:tags":[
        "gas"
    ],
    "wof:name":"Pacific Gas and Electric Co",
    "wof:placetype":"venue"
},
  "geometry": {"coordinates":[-122.37911,37.73768],"type":"Point"}
}