{
  "type": "Feature",
  "properties": {
    "addr:full":"9262 W Whitesbridge Ave Fresno CA 93706",
    "addr:housenumber":"9262",
    "addr:postcode":"93706",
    "addr:street":"W Whitesbridge Ave",
    "iso:country":"US",
    "sg:address":"9262 W Whitesbridge Ave",
    "sg:city":"Fresno",
    "sg:classifiers":[
        {
            "category":"Restaurant",
            "type":"Food & Drink"
        }
    ],
    "sg:phone":"+1 559 268 2410",
    "sg:postcode":"93706",
    "sg:province":"CA",
    "wof:name":"Judy's Rolinda Cafe",
    "wof:placetype":"venue"
},
  "geometry": {"coordinates":[-119.956513,36.73517],"type":"Point"}
}