{
  "type": "Feature",
  "properties": {
    "addr:full":"1510 A.M. San Francisco CA 94101",
    "addr:postcode":"a.m.;94101",
    "iso:country":"US",
    "sg:address":"1510 A.M.",
    "sg:city":"San Francisco",
    "sg:classifiers":[
        {
            "category":"Communications",
            "subcategory":"Radio Station",
            "type":"Services"
        }
    ],
    "sg:postcode":"94101",
    "sg:province":"CA",
    "sg:website":"www.kpig.com",
    "wof:name":"KPIG",
    "wof:placetype":"venue"
},
  "geometry": {"coordinates":[-118.20314999999999,33.785961],"type":"Point"}
}