{
  "type": "Feature",
  "properties": {
    "addr:full":"670 W Napa St Sonoma CA 95476",
    "addr:housenumber":"670",
    "addr:postcode":"95476",
    "addr:street":"W Napa St",
    "iso:country":"US",
    "sg:address":"670 W Napa St",
    "sg:city":"Sonoma",
    "sg:classifiers":[
        {
            "category":"Education",
            "subcategory":"Vocational School",
            "type":"Public Place"
        }
    ],
    "sg:phone":"+1 707 939 9498",
    "sg:postcode":"95476",
    "sg:province":"CA",
    "sg:website":"www.tomorr.com",
    "wof:name":"Senior Insurance Training",
    "wof:placetype":"venue"
},
  "geometry": {"coordinates":[-122.470833,38.293249],"type":"Point"}
}