{
  "type": "Feature",
  "properties": {
    "addr:full":"21660 Fortini Rd San Jose CA 95120",
    "addr:postcode":"21660;95120",
    "addr:street":"Fortini Rd",
    "iso:country":"US",
    "sg:address":"21660 Fortini Rd",
    "sg:city":"San Jose",
    "sg:classifiers":[
        {
            "category":"Building & Trades",
            "subcategory":"Electrical",
            "type":"Services"
        }
    ],
    "sg:phone":"+1 408 997 2656",
    "sg:postcode":"95120",
    "sg:province":"CA",
    "sg:tags":[
        "electrician"
    ],
    "wof:name":"Rinauro Construction",
    "wof:placetype":"venue"
},
  "geometry": {"coordinates":[-121.806,37.199001],"type":"Point"}
}