{
  "type": "Feature",
  "properties": {
    "iso:country":"US",
    "sg:address":"1400 Main St",
    "sg:city":"Ferndale",
    "sg:classifiers":[
        {
            "category":"Communications",
            "subcategory":"Radio Station",
            "type":"Services"
        }
    ],
    "sg:phone":"+1 707 786 5784",
    "sg:postcode":"95536",
    "sg:province":"CA",
    "sg:tags":[
        "broadcast"
    ],
    "wof:name":"Kslg Radio",
    "wof:placetype":"venue"
},
  "geometry": {"coordinates":[-124.256509,40.588035],"type":"Point"}
}