{
  "type": "Feature",
  "properties": {
    "iso:country":"US",
    "sg:address":"7510 Clairemont Mesa Blvd",
    "sg:city":"San Diego",
    "sg:classifiers":[
        {
            "category":"Professional",
            "subcategory":"Employment Agencies",
            "type":"Services"
        }
    ],
    "sg:phone":"+1 858 836 0303",
    "sg:postcode":"92111",
    "sg:province":"CA",
    "sg:website":"www.outsourcetelecom.com",
    "wof:name":"Outsource Telecom",
    "wof:placetype":"venue"
},
  "geometry": {"coordinates":[-117.157557,32.832895],"type":"Point"}
}