{
  "type": "Feature",
  "properties": {
    "iso:country":"US",
    "sg:address":"2400 James M Wood Blvd",
    "sg:city":"Los Angeles",
    "sg:classifiers":[
        {
            "category":"Shopping",
            "subcategory":"Stationery & Office Supplies",
            "type":"Retail Goods"
        }
    ],
    "sg:phone":"+1 213 386 3570",
    "sg:postcode":"90006",
    "sg:province":"CA",
    "sg:tags":[
        "rubber",
        "stamp",
        "plastic"
    ],
    "wof:name":"Ace Stamp & Sign Co",
    "wof:placetype":"venue"
},
  "geometry": {"coordinates":[-118.283008,34.055289],"type":"Point"}
}