{
  "type": "Feature",
  "properties": {
    "addr:full":"6382 Freeport Boulevard Sacramento CA 95822",
    "addr:housenumber":"6382",
    "addr:postcode":"95822",
    "addr:street":"Freeport Boulevard",
    "iso:country":"US",
    "sg:address":"6382 Freeport Boulevard",
    "sg:city":"Sacramento",
    "sg:classifiers":[
        {
            "category":"Autos & Motor Vehicles",
            "subcategory":"Auto Supplies",
            "type":"Retail Goods"
        }
    ],
    "sg:phone":"+1 916 393 3210",
    "sg:postcode":"95822",
    "sg:province":"CA",
    "sg:tags":[
        "glass"
    ],
    "wof:name":"International Auto Tint",
    "wof:placetype":"venue"
},
  "geometry": {"coordinates":[-121.50244000000001,38.511256],"type":"Point"}
}