{
  "type": "Feature",
  "properties": {
    "iso:country":"US",
    "sg:address":"2476 Almaden Rd",
    "sg:city":"San Jose",
    "sg:classifiers":[
        {
            "category":"Building & Trades",
            "subcategory":"Cleaning & Sanitation",
            "type":"Services"
        }
    ],
    "sg:phone":"+1 408 578 5454",
    "sg:postcode":"95125",
    "sg:province":"CA",
    "sg:tags":[
        "janitor"
    ],
    "wof:name":"Clean & Shine Home Care Svc",
    "wof:placetype":"venue"
},
  "geometry": {"coordinates":[-121.88202699999999,37.287558],"type":"Point"}
}