{
  "type": "Feature",
  "properties": {
    "addr:full":"2201 W Washington St # 13 Stockton CA 95203",
    "addr:housenumber":"2201",
    "addr:postcode":"95203",
    "addr:street":"W Washington St # 13",
    "iso:country":"US",
    "sg:address":"2201 W Washington St # 13",
    "sg:city":"Stockton",
    "sg:classifiers":[
        {
            "category":"Marine",
            "type":"Transportation"
        }
    ],
    "sg:phone":"+1 209 946 0246",
    "sg:postcode":"95203",
    "sg:province":"CA",
    "sg:tags":[
        "terminals-river"
    ],
    "sg:website":"http://www.stocktonport.com",
    "wof:name":"Port Of Stockton",
    "wof:placetype":"venue"
},
  "geometry": {"coordinates":[-121.32164,37.94521],"type":"Point"}
}