{
  "type": "Feature",
  "properties": {
    "iso:country":"US",
    "sg:address":"508 Owl Ct",
    "sg:city":"Vacaville",
    "sg:classifiers":[
        {
            "category":"Wholesale",
            "subcategory":"Apparel",
            "type":"Manufacturing & Wholesale Goods"
        }
    ],
    "sg:phone":"+1 707 446 4175",
    "sg:postcode":"95687",
    "sg:province":"CA",
    "sg:tags":[
        "clothing"
    ],
    "wof:name":"Syls Dream",
    "wof:placetype":"venue"
},
  "geometry": {"coordinates":[-121.943883,38.339796],"type":"Point"}
}