{
  "type": "Feature",
  "properties": {
    "addr:full":"7533 Hamil Ct Sacramento CA 95828",
    "addr:housenumber":"7533",
    "addr:postcode":"95828",
    "addr:street":"Hamil Ct",
    "iso:country":"US",
    "sg:address":"7533 Hamil Ct",
    "sg:city":"Sacramento",
    "sg:classifiers":[
        {
            "category":"Building & Trades",
            "subcategory":"Landscaping Services",
            "type":"Services"
        }
    ],
    "sg:phone":"+1 916 689 5506",
    "sg:postcode":"95828",
    "sg:province":"CA",
    "sg:tags":[
        "landscape",
        "contractor"
    ],
    "wof:name":"RAS Landscaping & Mntnc",
    "wof:placetype":"venue"
},
  "geometry": {"coordinates":[-121.384238,38.484857],"type":"Point"}
}