{
  "type": "Feature",
  "properties": {
    "iso:country":"US",
    "sg:address":"9141 Burke St",
    "sg:city":"Pico Rivera",
    "sg:classifiers":[
        {
            "category":"Social Services",
            "subcategory":"Child Care",
            "type":"Services"
        }
    ],
    "sg:phone":"+1 562 949 3189",
    "sg:postcode":"90660",
    "sg:province":"CA",
    "sg:tags":[
        "day"
    ],
    "wof:name":"M A O F Child Care Center",
    "wof:placetype":"venue"
},
  "geometry": {"coordinates":[-118.101997,33.969101],"type":"Point"}
}