{
  "type": "Feature",
  "properties": {
    "addr:full":"600 Gravenstein Hwy N Sebastopol CA 95472",
    "addr:housenumber":"600",
    "addr:postcode":"95472",
    "addr:street":"Gravenstein Hwy N",
    "iso:country":"US",
    "sg:address":"600 Gravenstein Hwy N",
    "sg:city":"Sebastopol",
    "sg:classifiers":[
        {
            "category":"Shopping",
            "subcategory":"Music",
            "type":"Retail Goods"
        }
    ],
    "sg:phone":"+1 707 829 2200",
    "sg:postcode":"95472",
    "sg:province":"CA",
    "sg:tags":[
        "video",
        "disc",
        "tape",
        "cassette"
    ],
    "wof:name":"Video Store",
    "wof:placetype":"venue"
},
  "geometry": {"coordinates":[-122.836569,38.405411],"type":"Point"}
}