{
  "type": "Feature",
  "properties": {
    "addr:full":"11540 Washington Blvd Ste B Whittier CA 90606",
    "addr:housenumber":"11540",
    "addr:postcode":"90606",
    "addr:street":"Washington Blvd Ste B",
    "iso:country":"US",
    "sg:address":"11540 Washington Blvd Ste B",
    "sg:city":"Whittier",
    "sg:classifiers":[
        {
            "category":"Personal",
            "subcategory":"Nail Salon",
            "type":"Services"
        }
    ],
    "sg:phone":"+1 562 695 1974",
    "sg:postcode":"90606",
    "sg:province":"CA",
    "wof:name":"Kali Nails",
    "wof:placetype":"venue"
},
  "geometry": {"coordinates":[-118.06500200000001,33.970402],"type":"Point"}
}