{
  "type": "Feature",
  "properties": {
    "addr:full":"2172 Piedmont Way Pittsburg CA 94565",
    "addr:housenumber":"2172",
    "addr:postcode":"94565",
    "addr:street":"Piedmont Way",
    "iso:country":"US",
    "sg:address":"2172 Piedmont Way",
    "sg:city":"Pittsburg",
    "sg:classifiers":[
        {
            "category":"Retail",
            "subcategory":"Auto Repair",
            "type":"Services"
        }
    ],
    "sg:phone":"+1 925 439 0555",
    "sg:postcode":"94565",
    "sg:province":"CA",
    "sg:tags":[
        "repairing",
        "automobile"
    ],
    "wof:name":"Pram Ros",
    "wof:placetype":"venue"
},
  "geometry": {"coordinates":[-121.873582,38.010852],"type":"Point"}
}