{
  "type": "Feature",
  "properties": {
    "addr:full":"4000 Industrial Way Concord CA 94520",
    "addr:housenumber":"4000",
    "addr:postcode":"94520",
    "addr:street":"Industrial Way",
    "iso:country":"US",
    "sg:address":"4000 Industrial Way",
    "sg:city":"Concord",
    "sg:classifiers":[
        {
            "category":"Autos & Motor Vehicles",
            "subcategory":"Automobile Sales",
            "type":"Retail Goods"
        }
    ],
    "sg:phone":"+1 925 825 1221",
    "sg:postcode":"94520",
    "sg:province":"CA",
    "sg:tags":[
        "car",
        "dealer"
    ],
    "wof:name":"B & D Auto Sales",
    "wof:placetype":"venue"
},
  "geometry": {"coordinates":[-122.033973,38.011381],"type":"Point"}
}