{
  "type": "Feature",
  "properties": {
    "addr:full":"4909 Lakewood Blvd Lakewood CA 90712",
    "addr:housenumber":"4909",
    "addr:postcode":"90712",
    "addr:street":"Lakewood Blvd",
    "iso:country":"US",
    "sg:address":"4909 Lakewood Blvd",
    "sg:city":"Lakewood",
    "sg:classifiers":[
        {
            "category":"Professional",
            "subcategory":"Lawyer & Legal Services",
            "type":"Services"
        }
    ],
    "sg:phone":"+1 562 630 1616",
    "sg:postcode":"90712",
    "sg:province":"CA",
    "sg:tags":[
        "attorney"
    ],
    "wof:name":"Josephine A Fitzpatrick",
    "wof:placetype":"venue"
},
  "geometry": {"coordinates":[-118.142556,33.847699],"type":"Point"}
}