{
  "type": "Feature",
  "properties": {
    "iso:country":"US",
    "sg:address":"1049 S Westlake Blvd",
    "sg:city":"Thousand Oaks",
    "sg:classifiers":[
        {
            "category":"Organizations",
            "subcategory":"Religious Organization",
            "type":"Services"
        }
    ],
    "sg:phone":"+1 818 889 5431",
    "sg:postcode":"91361",
    "sg:province":"CA",
    "sg:tags":[
        "church"
    ],
    "sg:website":"www.umcwv.org",
    "wof:name":"United Methodist Church",
    "wof:placetype":"venue"
},
  "geometry": {"coordinates":[-118.828726,34.152762],"type":"Point"}
}