{
  "type": "Feature",
  "properties": {
    "addr:full":"6401 E Pacific Coast Hwy Long Beach CA 90803",
    "addr:housenumber":"6401",
    "addr:postcode":"90803",
    "addr:street":"E Pacific Coast Hwy",
    "iso:country":"US",
    "sg:address":"6401 E Pacific Coast Hwy",
    "sg:city":"Long Beach",
    "sg:classifiers":[
        {
            "category":"Autos & Motor Vehicles",
            "subcategory":"Fuel & Gas Station",
            "type":"Retail Goods"
        }
    ],
    "sg:phone":"+1 562 596 3176",
    "sg:postcode":"90803",
    "sg:province":"CA",
    "sg:tags":[
        "oil"
    ],
    "wof:name":"PCH Mobil",
    "wof:placetype":"venue"
},
  "geometry": {"coordinates":[-118.112208,33.759184],"type":"Point"}
}