{
  "type": "Feature",
  "properties": {
    "addr:full":"3300 W 8th St Los Angeles CA 90005",
    "addr:housenumber":"3300",
    "addr:postcode":"90005",
    "addr:street":"W 8Th St",
    "iso:country":"US",
    "sg:address":"3300 W 8th St",
    "sg:city":"Los Angeles",
    "sg:classifiers":[
        {
            "category":"Professional",
            "subcategory":"Business Services",
            "type":"Services"
        }
    ],
    "sg:phone":"+1 213 383 0023",
    "sg:postcode":"90005",
    "sg:province":"CA",
    "sg:tags":[
        "interior",
        "consultant",
        "design",
        "decorator"
    ],
    "wof:name":"Pride Decor House",
    "wof:placetype":"venue"
},
  "geometry": {"coordinates":[-118.300156,34.057624],"type":"Point"}
}