{
  "type": "Feature",
  "properties": {
    "iso:country":"US",
    "sg:address":"991 Montague Expy Ste 208",
    "sg:city":"Milpitas",
    "sg:classifiers":[
        {
            "category":"Real Estate",
            "subcategory":"Architect",
            "type":"Services"
        }
    ],
    "sg:phone":"+1 408 946 9300",
    "sg:postcode":"95035",
    "sg:province":"CA",
    "wof:name":"Archevon",
    "wof:placetype":"venue"
},
  "geometry": {"coordinates":[-121.8865,37.412748],"type":"Point"}
}