{
  "type": "Feature",
  "properties": {
    "addr:full":"1796 Technology Dr San Jose CA 95110",
    "addr:housenumber":"1796",
    "addr:postcode":"95110",
    "addr:street":"Technology Dr",
    "iso:country":"US",
    "sg:address":"1796 Technology Dr",
    "sg:city":"San Jose",
    "sg:classifiers":[
        {
            "category":"Wholesale",
            "subcategory":"Electrical",
            "type":"Manufacturing & Wholesale Goods"
        }
    ],
    "sg:phone":"+1 408 453 5000",
    "sg:postcode":"95110",
    "sg:province":"CA",
    "sg:tags":[
        "electronic"
    ],
    "wof:name":"Luvantix",
    "wof:placetype":"venue"
},
  "geometry": {"coordinates":[-121.91989599999999,37.369236],"type":"Point"}
}