{
  "type": "Feature",
  "properties": {
    "iso:country":"US",
    "sg:address":"1796 Technology Dr",
    "sg:city":"San Jose",
    "sg:classifiers":[
        {
            "category":"Wholesale",
            "subcategory":"Electrical",
            "type":"Manufacturing & Wholesale Goods"
        }
    ],
    "sg:phone":"+1 408 453 5000",
    "sg:postcode":"95110",
    "sg:province":"CA",
    "sg:tags":[
        "electronic"
    ],
    "wof:name":"Luvantix",
    "wof:placetype":"venue"
},
  "geometry": {"coordinates":[-121.919896,37.369236],"type":"Point"}
}