{
  "type": "Feature",
  "properties": {
    "addr:full":"629 Yosemite Ave Manteca CA 95336",
    "addr:housenumber":"629",
    "addr:postcode":"95336",
    "addr:street":"Yosemite Ave",
    "iso:country":"US",
    "sg:address":"629 Yosemite Ave",
    "sg:city":"Manteca",
    "sg:classifiers":[
        {
            "category":"Shopping",
            "subcategory":"Pharmacy",
            "type":"Retail Goods"
        }
    ],
    "sg:phone":"+1 209 823 2174",
    "sg:postcode":"95336",
    "sg:province":"CA",
    "wof:name":"Bob's Pharmacy Inc",
    "wof:placetype":"venue"
},
  "geometry": {"coordinates":[-121.20827800000001,37.797509],"type":"Point"}
}