{
  "type": "Feature",
  "properties": {
    "addr:full":"4839 E Kings Canyon Rd Fresno CA 93727",
    "addr:housenumber":"4839",
    "addr:postcode":"93727",
    "addr:street":"E Kings Canyon Rd",
    "iso:country":"US",
    "sg:address":"4839 E Kings Canyon Rd",
    "sg:city":"Fresno",
    "sg:classifiers":[
        {
            "category":"Personal",
            "subcategory":"Barber",
            "type":"Services"
        }
    ],
    "sg:phone":"+1 559 456 1342",
    "sg:postcode":"93727",
    "sg:province":"CA",
    "wof:name":"Park Barber Shop",
    "wof:placetype":"venue"
},
  "geometry": {"coordinates":[-119.735631,36.735996],"type":"Point"}
}