{
  "type": "Feature",
  "properties": {
    "addr:full":"Pier 38 Embarcadero San Francisco CA 94107",
    "addr:housenumber":"38",
    "addr:postcode":"94107",
    "addr:street":"Embarcadero",
    "iso:country":"US",
    "sg:address":"Pier 38 Embarcadero",
    "sg:city":"San Francisco",
    "sg:classifiers":[
        {
            "category":"Professional",
            "subcategory":"Advertising",
            "type":"Services"
        }
    ],
    "sg:phone":"+1 650 815 7200",
    "sg:postcode":"94107",
    "sg:province":"CA",
    "sg:website":"http://www.socialmedia.com",
    "wof:name":"Social Media Networks",
    "wof:placetype":"venue"
},
  "geometry": {"coordinates":[-122.39684099999999,37.782119],"type":"Point"}
}