{
  "type": "Feature",
  "properties": {
    "addr:full":"985 Pioneer Ave Turlock CA 95380",
    "addr:housenumber":"985",
    "addr:postcode":"95380",
    "addr:street":"Pioneer Ave",
    "iso:country":"US",
    "sg:address":"985 Pioneer Ave",
    "sg:city":"Turlock",
    "sg:classifiers":[
        {
            "category":"Wholesale",
            "subcategory":"Durable Goods & Equipment",
            "type":"Manufacturing & Wholesale Goods"
        }
    ],
    "sg:phone":"+1 209 669 0460",
    "sg:postcode":"95380",
    "sg:province":"CA",
    "wof:name":"E Quintero Supply",
    "wof:placetype":"venue"
},
  "geometry": {"coordinates":[-120.837636,37.502274],"type":"Point"}
}