{
  "type": "Feature",
  "properties": {
    "iso:country":"US",
    "sg:address":"4200 Manzanita",
    "sg:city":"Irvine",
    "sg:classifiers":[
        {
            "category":"Social Services",
            "subcategory":"Child Care",
            "type":"Services"
        },
        {
            "category":"Education",
            "subcategory":"Preschool",
            "type":"Public Place"
        },
        {
            "category":"Education",
            "subcategory":"School",
            "type":"Public Place"
        }
    ],
    "sg:phone":"+1 949 552 5628",
    "sg:postcode":"92604",
    "sg:province":"CA",
    "sg:tags":[
        "elementary",
        "day"
    ],
    "wof:name":"Rainbow Rising",
    "wof:placetype":"venue"
},
  "geometry": {"coordinates":[-117.787491,33.698298],"type":"Point"}
}