{
  "type": "Feature",
  "properties": {
    "iso:country":"US",
    "sg:address":"1227 Pacheco St",
    "sg:city":"San Francisco",
    "sg:classifiers":[
        {
            "category":"Insurance",
            "subcategory":"Insurance Agent",
            "type":"Services"
        }
    ],
    "sg:phone":"+1 415 664 3696",
    "sg:postcode":"94116",
    "sg:province":"CA",
    "wof:name":"Stephen W Roy Insurance",
    "wof:placetype":"venue"
},
  "geometry": {"coordinates":[-122.47384599999999,37.750541],"type":"Point"}
}