{
  "type": "Feature",
  "properties": {
    "addr:full":"222 N East St Anaheim CA 92805",
    "addr:housenumber":"222",
    "addr:postcode":"92805",
    "addr:street":"N East St",
    "iso:country":"US",
    "sg:address":"222 N East St",
    "sg:city":"Anaheim",
    "sg:classifiers":[
        {
            "category":"Organizations",
            "subcategory":"Religious Organization",
            "type":"Services"
        }
    ],
    "sg:phone":"+1 714 535 1169",
    "sg:postcode":"92805",
    "sg:province":"CA",
    "wof:name":"Zion Lutheran Church Missouri Synod",
    "wof:placetype":"venue"
},
  "geometry": {"coordinates":[-117.90300000000001,33.839298],"type":"Point"}
}