{
  "type": "Feature",
  "properties": {
    "iso:country":"US",
    "sg:address":"7550 W Chapman Ave",
    "sg:city":"Garden Grove",
    "sg:classifiers":[
        {
            "category":"Wholesale",
            "subcategory":"Metals & Minerals",
            "type":"Manufacturing & Wholesale Goods"
        }
    ],
    "sg:phone":"+1 714 895 7756",
    "sg:postcode":"92845",
    "sg:province":"CA",
    "sg:tags":[
        "steel",
        "warehouse"
    ],
    "sg:website":"www.piercespafford.com",
    "wof:name":"Pierce-Spafford Metals Co",
    "wof:placetype":"venue"
},
  "geometry": {"coordinates":[-118.00019899999999,33.788255],"type":"Point"}
}