{
  "type": "Feature",
  "properties": {
    "addr:full":"207 Gough St San Francisco CA 94102",
    "addr:housenumber":"207",
    "addr:postcode":"94102",
    "addr:street":"Gough St",
    "iso:country":"US",
    "sg:address":"207 Gough St",
    "sg:city":"San Francisco",
    "sg:classifiers":[
        {
            "category":"Manufacturing",
            "subcategory":"Jewelry",
            "type":"Manufacturing & Wholesale Goods"
        }
    ],
    "sg:phone":"+1 415 864 8039",
    "sg:postcode":"94102",
    "sg:province":"CA",
    "sg:tags":[
        "costume",
        "mfg"
    ],
    "wof:name":"Arlon Accessories",
    "wof:placetype":"venue"
},
  "geometry": {"coordinates":[-122.422755,37.775401],"type":"Point"}
}