{
  "type": "Feature",
  "properties": {
    "iso:country":"US",
    "sg:address":"703 N Gateway Dr",
    "sg:city":"Madera",
    "sg:classifiers":[
        {
            "category":"Restaurant",
            "type":"Food & Drink"
        }
    ],
    "sg:phone":"+1 559 673 9893",
    "sg:postcode":"93637",
    "sg:province":"CA",
    "wof:name":"Taqueria Villa Del Mar",
    "wof:placetype":"venue"
},
  "geometry": {"coordinates":[-120.066855,36.967399],"type":"Point"}
}