{
  "type": "Feature",
  "properties": {
    "addr:full":"15 Valley Ct Chico CA 95973",
    "addr:housenumber":"15",
    "addr:postcode":"95973",
    "addr:street":"Valley Ct",
    "iso:country":"US",
    "sg:address":"15 Valley Ct",
    "sg:city":"Chico",
    "sg:classifiers":[
        {
            "category":"Building & Trades",
            "subcategory":"Construction",
            "type":"Services"
        }
    ],
    "sg:phone":"+1 530 345 6369",
    "sg:postcode":"95973",
    "sg:province":"CA",
    "sg:tags":[
        "maker",
        "cabinet"
    ],
    "wof:name":"Sawyer's Cabinets",
    "wof:placetype":"venue"
},
  "geometry": {"coordinates":[-121.885099,39.782477],"type":"Point"}
}