{
  "type": "Feature",
  "properties": {
    "addr:full":"7215 Itchy Acres Rd Granite Bay CA 95746",
    "addr:housenumber":"7215",
    "addr:postcode":"95746",
    "addr:street":"Itchy Acres Rd",
    "iso:country":"US",
    "sg:address":"7215 Itchy Acres Rd",
    "sg:city":"Granite Bay",
    "sg:classifiers":[
        {
            "category":"Manufacturing",
            "subcategory":"Wood Products",
            "type":"Manufacturing & Wholesale Goods"
        }
    ],
    "sg:phone":"+1 916 791 2662",
    "sg:postcode":"95746",
    "sg:province":"CA",
    "sg:tags":[
        "shop",
        "frame",
        "art",
        "gallery"
    ],
    "wof:name":"Lakeside Galleries",
    "wof:placetype":"venue"
},
  "geometry": {"coordinates":[-121.177672,38.751049],"type":"Point"}
}