{
  "type": "Feature",
  "properties": {
    "addr:full":"1400 10th Ave San Francisco CA 94122",
    "addr:housenumber":"1400",
    "addr:postcode":"94122",
    "addr:street":"10Th Ave",
    "iso:country":"US",
    "sg:address":"1400 10th Ave",
    "sg:city":"San Francisco",
    "sg:classifiers":[
        {
            "category":"Personal",
            "type":"Services"
        }
    ],
    "sg:phone":"+1 415 722 5607",
    "sg:postcode":"94122",
    "sg:province":"CA",
    "sg:tags":[
        "chef"
    ],
    "sg:website":"www.sprigofthyme.com",
    "wof:name":"Sprig of Thyme Chef Services",
    "wof:placetype":"venue"
},
  "geometry": {"coordinates":[-122.46722699999999,37.762082],"type":"Point"}
}