{
  "type": "Feature",
  "properties": {
    "addr:full":"1838 W 144th St Gardena CA 90249",
    "addr:housenumber":"1838",
    "addr:postcode":"90249",
    "addr:street":"W 144Th St",
    "iso:country":"US",
    "sg:address":"1838 W 144th St",
    "sg:city":"Gardena",
    "sg:classifiers":[
        {
            "category":"Wholesale",
            "subcategory":"Durable Goods & Equipment",
            "type":"Manufacturing & Wholesale Goods"
        }
    ],
    "sg:phone":"+1 310 538 2141",
    "sg:postcode":"90249",
    "sg:province":"CA",
    "sg:tags":[
        "case",
        "instrument"
    ],
    "wof:name":"Roadie Products Inc",
    "wof:placetype":"venue"
},
  "geometry": {"coordinates":[-118.309253,33.900927],"type":"Point"}
}