{
  "type": "Feature",
  "properties": {
    "addr:full":"1030 Main St St Helena CA 94574",
    "addr:housenumber":"1030",
    "addr:postcode":"94574",
    "addr:street":"Main St",
    "iso:country":"US",
    "sg:address":"1030 Main St",
    "sg:city":"St Helena",
    "sg:classifiers":[
        {
            "category":"Professional",
            "subcategory":"Lawyer & Legal Services",
            "type":"Services"
        }
    ],
    "sg:phone":"+1 707 963 3800",
    "sg:postcode":"94574",
    "sg:province":"CA",
    "sg:tags":[
        "attorney"
    ],
    "sg:website":"www.herdell-yost.com",
    "wof:name":"Herdell & Yost LLP",
    "wof:placetype":"venue"
},
  "geometry": {"coordinates":[-122.46486299999999,38.501799],"type":"Point"}
}