{
  "type": "Feature",
  "properties": {
    "addr:full":"2021 Broadway St Redwood City CA 94063",
    "addr:housenumber":"2021",
    "addr:postcode":"94063",
    "addr:street":"Broadway St",
    "iso:country":"US",
    "sg:address":"2021 Broadway St",
    "sg:city":"Redwood City",
    "sg:classifiers":[
        {
            "category":"Shopping",
            "subcategory":"Bicycles & Sporting Goods",
            "type":"Retail Goods"
        }
    ],
    "sg:phone":"+1 650 368 9191",
    "sg:postcode":"94063",
    "sg:province":"CA",
    "sg:tags":[
        "tack",
        "western",
        "store",
        "wear"
    ],
    "wof:name":"B & D Tack",
    "wof:placetype":"venue"
},
  "geometry": {"coordinates":[-122.22664399999999,37.486513],"type":"Point"}
}