{
  "type": "Feature",
  "properties": {
    "addr:full":"1135 Powell St. San Francisco CA 94108",
    "addr:housenumber":"1135",
    "addr:postcode":"94108",
    "addr:street":"Powell St.",
    "iso:country":"US",
    "sg:address":"1135 Powell St.",
    "sg:city":"San Francisco",
    "sg:classifiers":[
        {
            "category":"Education",
            "subcategory":"Library",
            "type":"Public Place"
        }
    ],
    "sg:phone":"+1 415 355 2888",
    "sg:postcode":"94108",
    "sg:province":"CA",
    "sg:website":"sfpl.org/librarylocations/branch...",
    "wof:name":"San Francisco Public Library - Chinatown Branch",
    "wof:placetype":"venue"
},
  "geometry": {"coordinates":[-122.410004,37.795101],"type":"Point"}
}