{
  "type": "Feature",
  "properties": {
    "addr:full":"2 Enterprise Ofc Aliso Viejo CA 92656",
    "addr:housenumber":"2;ofc",
    "addr:postcode":"92656",
    "addr:street":"Enterprise",
    "iso:country":"US",
    "sg:address":"2 Enterprise Ofc",
    "sg:city":"Aliso Viejo",
    "sg:classifiers":[
        {
            "category":"Real Estate",
            "subcategory":"Real Estate Operator",
            "type":"Services"
        }
    ],
    "sg:phone":"+1 949 716 5600",
    "sg:postcode":"92656",
    "sg:province":"CA",
    "sg:tags":[
        "apartment"
    ],
    "wof:name":"Alize Leasing Office",
    "wof:placetype":"venue"
},
  "geometry": {"coordinates":[-117.733203,33.584834],"type":"Point"}
}