{
  "type": "Feature",
  "properties": {
    "addr:full":"1804 Viewmont Dr San Luis Obispo CA 93401",
    "addr:housenumber":"1804",
    "addr:postcode":"93401",
    "addr:street":"Viewmont Dr",
    "iso:country":"US",
    "sg:address":"1804 Viewmont Dr",
    "sg:city":"San Luis Obispo",
    "sg:classifiers":[
        {
            "category":"Wholesale",
            "subcategory":"Stationery",
            "type":"Manufacturing & Wholesale Goods"
        }
    ],
    "sg:phone":"+1 805 541 3800",
    "sg:postcode":"93401",
    "sg:province":"CA",
    "sg:tags":[
        "school",
        "supply"
    ],
    "sg:website":"www.creativeathletics.com",
    "wof:name":"Creative Athletics",
    "wof:placetype":"venue"
},
  "geometry": {"coordinates":[-120.642993,35.27476],"type":"Point"}
}