{
  "type": "Feature",
  "properties": {
    "addr:full":"2655 E Colorado Blvd Pasadena CA 91107",
    "addr:housenumber":"2655",
    "addr:postcode":"91107",
    "addr:street":"E Colorado Blvd",
    "iso:country":"US",
    "sg:address":"2655 E Colorado Blvd",
    "sg:city":"Pasadena",
    "sg:classifiers":[
        {
            "category":"Retail",
            "subcategory":"Auto Repair",
            "type":"Services"
        }
    ],
    "sg:phone":"+1 626 405 0014",
    "sg:postcode":"91107",
    "sg:province":"CA",
    "wof:name":"Silver Auto Care",
    "wof:placetype":"venue"
},
  "geometry": {"coordinates":[-118.095001,34.146198],"type":"Point"}
}