{
  "type": "Feature",
  "properties": {
    "addr:full":"4306 Auklet Way Oceanside CA 92057",
    "addr:housenumber":"4306",
    "addr:postcode":"92057",
    "addr:street":"Auklet Way",
    "iso:country":"US",
    "sg:address":"4306 Auklet Way",
    "sg:city":"Oceanside",
    "sg:classifiers":[
        {
            "category":"Building & Trades",
            "subcategory":"Construction",
            "type":"Services"
        }
    ],
    "sg:phone":"+1 760 721 6132",
    "sg:postcode":"92057",
    "sg:province":"CA",
    "sg:tags":[
        "tile",
        "dealer"
    ],
    "wof:name":"H T Tile-Rite",
    "wof:placetype":"venue"
},
  "geometry": {"coordinates":[-117.30574900000001,33.226394],"type":"Point"}
}