{
  "type": "Feature",
  "properties": {
    "addr:full":"100 Whiting St El Segundo CA 90245",
    "addr:housenumber":"100",
    "addr:postcode":"90245",
    "addr:street":"Whiting St",
    "iso:country":"US",
    "sg:address":"100 Whiting St",
    "sg:city":"El Segundo",
    "sg:classifiers":[
        {
            "category":"Park",
            "type":"Public Place"
        }
    ],
    "sg:postcode":"90245",
    "sg:province":"CA",
    "wof:name":"Candy Cane Park",
    "wof:placetype":"venue"
},
  "geometry": {"coordinates":[-118.42120199999999,33.916725],"type":"Point"}
}