{
  "type": "Feature",
  "properties": {
    "iso:country":"US",
    "sg:address":"100 Whiting St",
    "sg:city":"El Segundo",
    "sg:classifiers":[
        {
            "category":"Park",
            "type":"Public Place"
        }
    ],
    "sg:postcode":"90245",
    "sg:province":"CA",
    "wof:name":"Candy Cane Park",
    "wof:placetype":"venue"
},
  "geometry": {"coordinates":[-118.421202,33.916725],"type":"Point"}
}