{
  "type": "Feature",
  "properties": {
    "iso:country":"US",
    "sg:address":"248 Blossom Hill Road",
    "sg:city":"Los Gatos",
    "sg:classifiers":[
        {
            "category":"Professional",
            "subcategory":"Lawyer & Legal Services",
            "type":"Services"
        }
    ],
    "sg:phone":"+1 408 395 6868",
    "sg:postcode":"95032",
    "sg:province":"CA",
    "wof:name":"Eagle Alexander F Atty",
    "wof:placetype":"venue"
},
  "geometry": {"coordinates":[-121.97470199999999,37.234474],"type":"Point"}
}