{
  "type": "Feature",
  "properties": {
    "addr:full":"2428 E 56th Huntington Park CA 90255",
    "addr:housenumber":"2428",
    "addr:postcode":"90255",
    "addr:street":"E 56Th;Park",
    "iso:country":"US",
    "sg:address":"2428 E 56th",
    "sg:city":"Huntington Park",
    "sg:classifiers":[
        {
            "category":"Home & Garden",
            "subcategory":"Furniture",
            "type":"Retail Goods"
        }
    ],
    "sg:phone":"+1 323 585 0801",
    "sg:postcode":"90255",
    "sg:province":"CA",
    "sg:tags":[
        "store"
    ],
    "wof:name":"Antico",
    "wof:placetype":"venue"
},
  "geometry": {"coordinates":[-118.21460999999999,33.978285],"type":"Point"}
}