{
  "type": "Feature",
  "properties": {
    "iso:country":"US",
    "sg:address":"3430 Sacramento Dr",
    "sg:city":"San Luis Obispo",
    "sg:classifiers":[
        {
            "category":"Autos & Motor Vehicles",
            "subcategory":"Auto Supplies",
            "type":"Retail Goods"
        }
    ],
    "sg:phone":"+1 805 544 8748",
    "sg:postcode":"93401",
    "sg:province":"CA",
    "sg:tags":[
        "equipment",
        "racing",
        "car",
        "automobile"
    ],
    "sg:website":"www.maximummotorsports.com",
    "wof:name":"Maximum Motorsports",
    "wof:placetype":"venue"
},
  "geometry": {"coordinates":[-120.646188,35.258358],"type":"Point"}
}