{
  "type": "Feature",
  "properties": {
    "addr:full":"24361 el Toro Rd Laguna Woods CA 92637",
    "addr:housenumber":"24361",
    "addr:postcode":"92637",
    "addr:street":"El Toro Rd",
    "iso:country":"US",
    "sg:address":"24361 el Toro Rd",
    "sg:city":"Laguna Woods",
    "sg:classifiers":[
        {
            "category":"Banks & Credit Unions",
            "subcategory":"Investment Brokerage",
            "type":"Services"
        }
    ],
    "sg:phone":"+1 949 454 1586",
    "sg:postcode":"92637",
    "sg:province":"CA",
    "sg:tags":[
        "management"
    ],
    "wof:name":"Trinton Investment Advisor",
    "wof:placetype":"venue"
},
  "geometry": {"coordinates":[-117.72746100000001,33.609314],"type":"Point"}
}