{
  "type": "Feature",
  "properties": {
    "iso:country":"US",
    "sg:address":"4641 Artesia Boulevard",
    "sg:city":"Lawndale",
    "sg:classifiers":[
        {
            "category":"Retail",
            "subcategory":"Car Wash",
            "type":"Services"
        }
    ],
    "sg:phone":"+1 310 371 8282",
    "sg:postcode":"90260",
    "sg:province":"CA",
    "wof:name":"Executive Hand Car Wash",
    "wof:placetype":"venue"
},
  "geometry": {"coordinates":[-118.359133,33.872845],"type":"Point"}
}