{
  "type": "Feature",
  "properties": {
    "addr:full":"1105 E 3rd St Long Beach CA 90802",
    "addr:housenumber":"1105",
    "addr:postcode":"90802",
    "addr:street":"E 3Rd St",
    "iso:country":"US",
    "sg:address":"1105 E 3rd St",
    "sg:city":"Long Beach",
    "sg:classifiers":[
        {
            "category":"Shopping",
            "subcategory":"Used Merchandise",
            "type":"Retail Goods"
        }
    ],
    "sg:phone":"+1 562 983 8780",
    "sg:postcode":"90802",
    "sg:province":"CA",
    "sg:tags":[
        "antique"
    ],
    "wof:name":"Kelly's Place",
    "wof:placetype":"venue"
},
  "geometry": {"coordinates":[-118.176558,33.770224],"type":"Point"}
}