{
  "type": "Feature",
  "properties": {
    "addr:full":"13750 Van Ness Ave Gardena CA 90249",
    "addr:housenumber":"13750",
    "addr:postcode":"90249",
    "addr:street":"Van Ness Ave",
    "iso:country":"US",
    "sg:address":"13750 Van Ness Ave",
    "sg:city":"Gardena",
    "sg:classifiers":[
        {
            "category":"Wholesale",
            "subcategory":"Toys & Hobbies",
            "type":"Manufacturing & Wholesale Goods"
        }
    ],
    "sg:phone":"+1 310 217 0908",
    "sg:postcode":"90249",
    "sg:province":"CA",
    "sg:tags":[
        "wholesaler"
    ],
    "wof:name":"R D Logics Inc",
    "wof:placetype":"venue"
},
  "geometry": {"coordinates":[-118.31771500000001,33.908498],"type":"Point"}
}