{
  "type": "Feature",
  "properties": {
    "iso:country":"US",
    "sg:address":"2800 28th St",
    "sg:city":"Santa Monica",
    "sg:classifiers":[
        {
            "category":"Manufacturing",
            "subcategory":"Printing",
            "type":"Manufacturing & Wholesale Goods"
        }
    ],
    "sg:phone":"+1 310 715 6300",
    "sg:postcode":"90405",
    "sg:province":"CA",
    "sg:tags":[
        "news",
        "publication"
    ],
    "wof:name":"Mainichi International Inc",
    "wof:placetype":"venue"
},
  "geometry": {"coordinates":[-118.455556,34.018521],"type":"Point"}
}