{
  "type": "Feature",
  "properties": {
    "addr:full":"222 E 211th St Carson CA 90745",
    "addr:housenumber":"222",
    "addr:postcode":"90745",
    "addr:street":"E 211Th St",
    "iso:country":"US",
    "sg:address":"222 E 211th St",
    "sg:city":"Carson",
    "sg:classifiers":[
        {
            "category":"Restaurant",
            "type":"Food & Drink"
        }
    ],
    "sg:phone":"+1 310 549 9343",
    "sg:postcode":"90745",
    "sg:province":"CA",
    "sg:tags":[
        "caterer"
    ],
    "wof:name":"Iwalani's Hawaiian Catering",
    "wof:placetype":"venue"
},
  "geometry": {"coordinates":[-118.274992,33.837953],"type":"Point"}
}