{
  "type": "Feature",
  "properties": {
    "iso:country":"US",
    "sg:address":"18345 Ventura Blvd",
    "sg:city":"Tarzana",
    "sg:classifiers":[
        {
            "category":"Banks & Credit Unions",
            "subcategory":"Investment Brokerage",
            "type":"Services"
        }
    ],
    "sg:phone":"+1 818 609 7995",
    "sg:postcode":"91356",
    "sg:province":"CA",
    "sg:tags":[
        "management"
    ],
    "wof:name":"A & H Kassabian Investors",
    "wof:placetype":"venue"
},
  "geometry": {"coordinates":[-118.533607,34.167809],"type":"Point"}
}