{
  "type": "Feature",
  "properties": {
    "addr:full":"8175 Signal Ct Sacramento CA 95824",
    "addr:housenumber":"8175",
    "addr:postcode":"95824",
    "addr:street":"Signal Ct",
    "iso:country":"US",
    "sg:address":"8175 Signal Ct",
    "sg:city":"Sacramento",
    "sg:classifiers":[
        {
            "category":"Home & Garden",
            "subcategory":"Building Materials",
            "type":"Retail Goods"
        }
    ],
    "sg:phone":"+1 916 386 8317",
    "sg:postcode":"95824",
    "sg:province":"CA",
    "wof:name":"Oregon Pacific Bldg Products",
    "wof:placetype":"venue"
},
  "geometry": {"coordinates":[-121.408637,38.513377],"type":"Point"}
}