{
  "type": "Feature",
  "properties": {
    "addr:full":"416 Harbor Light Rd Alameda CA 94501",
    "addr:housenumber":"416",
    "addr:postcode":"94501",
    "addr:street":"Harbor Light Rd",
    "iso:country":"US",
    "sg:address":"416 Harbor Light Rd",
    "sg:city":"Alameda",
    "sg:classifiers":[
        {
            "category":"Building & Trades",
            "subcategory":"Construction",
            "type":"Services"
        }
    ],
    "sg:phone":"+1 510 769 1161",
    "sg:postcode":"94501",
    "sg:province":"CA",
    "sg:tags":[
        "resurfacing",
        "laying",
        "refinishing",
        "floor"
    ],
    "wof:name":"P K Hardwood Floor",
    "wof:placetype":"venue"
},
  "geometry": {"coordinates":[-122.265844,37.761317],"type":"Point"}
}