{
  "type": "Feature",
  "properties": {
    "addr:full":"6284 Skyway Rd Paradise CA 95969",
    "addr:housenumber":"6284",
    "addr:postcode":"95969",
    "addr:street":"Skyway Rd",
    "iso:country":"US",
    "sg:address":"6284 Skyway Rd",
    "sg:city":"Paradise",
    "sg:classifiers":[
        {
            "category":"Shopping",
            "subcategory":"Shoes",
            "type":"Retail Goods"
        }
    ],
    "sg:phone":"+1 530 877 4969",
    "sg:postcode":"95969",
    "sg:province":"CA",
    "wof:name":"City Shoes",
    "wof:placetype":"venue"
},
  "geometry": {"coordinates":[-121.625799,39.756379],"type":"Point"}
}