{
  "type": "Feature",
  "properties": {
    "addr:full":"221 Los Gatos-Saratoga Rd Los Gatos CA 95030",
    "addr:housenumber":"221",
    "addr:postcode":"95030",
    "addr:street":"Los Gatos-Saratoga Rd",
    "iso:country":"US",
    "sg:address":"221 Los Gatos-Saratoga Rd",
    "sg:city":"Los Gatos",
    "sg:classifiers":[
        {
            "category":"Real Estate",
            "subcategory":"Real Estate Agent",
            "type":"Services"
        }
    ],
    "sg:phone":"+1 408 234 7472",
    "sg:postcode":"95030",
    "sg:province":"CA",
    "sg:website":"www.TopNotchListing.com",
    "wof:name":"Leslie Alexander - Coldwell Banker",
    "wof:placetype":"venue"
},
  "geometry": {"coordinates":[-121.981703,37.229411],"type":"Point"}
}