{
  "type": "Feature",
  "properties": {
    "addr:full":"8333 Clairemont Mesa Blvd San Diego CA 92117",
    "addr:housenumber":"8333",
    "addr:postcode":"92117",
    "addr:street":"Clairemont Mesa Blvd",
    "iso:country":"US",
    "sg:address":"8333 Clairemont Mesa Blvd",
    "sg:city":"San Diego",
    "sg:classifiers":[
        {
            "category":"Professional",
            "subcategory":"Advertising",
            "type":"Services"
        }
    ],
    "sg:phone":"+1 858 292 4800",
    "sg:postcode":"92117",
    "sg:province":"CA",
    "sg:tags":[
        "mailing",
        "shipping"
    ],
    "wof:name":"Fed Ex",
    "wof:placetype":"venue"
},
  "geometry": {"coordinates":[-117.14357,32.83282],"type":"Point"}
}