{
  "type": "Feature",
  "properties": {
    "iso:country":"US",
    "sg:address":"2900 Garden Hwy",
    "sg:city":"Nicolaus",
    "sg:classifiers":[
        {
            "category":"Government",
            "subcategory":"Post Office",
            "type":"Public Place"
        }
    ],
    "sg:phone":"+1 530 656 2251",
    "sg:postcode":"95659",
    "sg:province":"CA",
    "wof:name":"Nicolaus Main Office",
    "wof:placetype":"venue"
},
  "geometry": {"coordinates":[-121.58222600000001,38.900383],"type":"Point"}
}