{
  "type": "Feature",
  "properties": {
    "addr:full":"5701 E Santa Ana Canyon Rd Ste A Anaheim CA 92807",
    "addr:housenumber":"5701",
    "addr:postcode":"92807",
    "addr:street":"E Santa Ana Canyon Rd Ste A",
    "iso:country":"US",
    "sg:address":"5701 E Santa Ana Canyon Rd Ste A",
    "sg:city":"Anaheim",
    "sg:classifiers":[
        {
            "category":"Shopping",
            "subcategory":"Bridal",
            "type":"Retail Goods"
        }
    ],
    "sg:phone":"+1 714 998 9110",
    "sg:postcode":"92807",
    "sg:province":"CA",
    "wof:name":"Mary Me Bridal and Formalwear",
    "wof:placetype":"venue"
},
  "geometry": {"coordinates":[-117.791,33.851501],"type":"Point"}
}