{
  "type": "Feature",
  "properties": {
    "addr:full":"790 Mora Dr Los Altos CA 94024",
    "addr:housenumber":"790",
    "addr:postcode":"94024",
    "addr:street":"Mora Dr",
    "iso:country":"US",
    "sg:address":"790 Mora Dr",
    "sg:city":"Los Altos",
    "sg:classifiers":[
        {
            "category":"Professional",
            "type":"Services"
        }
    ],
    "sg:phone":"+1 650 948 9142",
    "sg:postcode":"94024",
    "sg:province":"CA",
    "wof:name":"2438 San Pablo Crt Prtns Calif",
    "wof:placetype":"venue"
},
  "geometry": {"coordinates":[-122.090098,37.347664],"type":"Point"}
}