{
  "type": "Feature",
  "properties": {
    "iso:country":"US",
    "sg:address":"259 Leaf Ct",
    "sg:city":"Angels Camp",
    "sg:classifiers":[
        {
            "category":"Building & Trades",
            "subcategory":"Construction",
            "type":"Services"
        }
    ],
    "sg:phone":"+1 209 736 2236",
    "sg:postcode":"95222",
    "sg:province":"CA",
    "sg:tags":[
        "agent",
        "general",
        "real estate",
        "contractor"
    ],
    "wof:name":"Collins Development Co",
    "wof:placetype":"venue"
},
  "geometry": {"coordinates":[-120.560154,38.075962],"type":"Point"}
}