{
  "type": "Feature",
  "properties": {
    "addr:full":"1116 Colorado Blvd Los Angeles CA 90041",
    "addr:housenumber":"1116",
    "addr:postcode":"90041",
    "addr:street":"Colorado Blvd",
    "iso:country":"US",
    "sg:address":"1116 Colorado Blvd",
    "sg:city":"Los Angeles",
    "sg:classifiers":[
        {
            "category":"Shopping",
            "subcategory":"Crafts & Fabrics",
            "type":"Retail Goods"
        },
        {
            "category":"Shopping",
            "subcategory":"Discount & Variety Stores",
            "type":"Retail Goods"
        }
    ],
    "sg:phone":"+1 323 254 4100",
    "sg:postcode":"90041",
    "sg:province":"CA",
    "sg:tags":[
        "wholesale"
    ],
    "sg:website":"www.ribbonsunlimitedinc.com",
    "wof:name":"Ribbons Unlimited Inc.",
    "wof:placetype":"venue"
},
  "geometry": {"coordinates":[-118.18220100000001,34.140721],"type":"Point"}
}