{
  "type": "Feature",
  "properties": {
    "addr:full":"6525 Washington St Yountville CA 94599",
    "addr:housenumber":"6525",
    "addr:postcode":"ca 94599",
    "addr:street":"Washington St",
    "iso:country":"US",
    "sg:address":"6525 Washington St",
    "sg:city":"Yountville",
    "sg:classifiers":[
        {
            "category":"Health Services",
            "subcategory":"Doctor",
            "type":"Services"
        }
    ],
    "sg:phone":"+1 707 944 8806",
    "sg:postcode":"94599",
    "sg:province":"CA",
    "sg:tags":[
        "dentist"
    ],
    "wof:name":"Robert R Hampton DDS",
    "wof:placetype":"venue"
},
  "geometry": {"coordinates":[-122.362337,38.402386],"type":"Point"}
}