{
  "type": "Feature",
  "properties": {
    "addr:full":"30 Patera Ct Camarillo CA 93010",
    "addr:housenumber":"30",
    "addr:postcode":"93010",
    "addr:street":"Patera Ct",
    "iso:country":"US",
    "sg:address":"30 Patera Ct",
    "sg:city":"Camarillo",
    "sg:classifiers":[
        {
            "category":"Health Services",
            "subcategory":"Nursing And Care Facility",
            "type":"Services"
        }
    ],
    "sg:phone":"+1 805 383 6855",
    "sg:postcode":"93010",
    "sg:province":"CA",
    "sg:tags":[
        "skilled"
    ],
    "wof:name":"Give ME Shelter Inc",
    "wof:placetype":"venue"
},
  "geometry": {"coordinates":[-119.080196,34.242864],"type":"Point"}
}