{
  "type": "Feature",
  "properties": {
    "addr:full":"1515 W 190th St Gardena CA 90248",
    "addr:housenumber":"1515",
    "addr:postcode":"90248",
    "addr:street":"W 190Th St",
    "iso:country":"US",
    "sg:address":"1515 W 190th St",
    "sg:city":"Gardena",
    "sg:classifiers":[
        {
            "category":"Professional",
            "subcategory":"Management & Consulting",
            "type":"Services"
        }
    ],
    "sg:phone":"+1 310 532 7521",
    "sg:postcode":"90248",
    "sg:province":"CA",
    "sg:tags":[
        "consultant",
        "educational"
    ],
    "wof:name":"Pearson Professional Ctr",
    "wof:placetype":"venue"
},
  "geometry": {"coordinates":[-118.303861,33.858429],"type":"Point"}
}