{
  "type": "Feature",
  "properties": {
    "iso:country":"US",
    "sg:address":"5442 Martin Luther King Jr Blvd",
    "sg:city":"Lynwood",
    "sg:classifiers":[
        {
            "category":"Retail",
            "subcategory":"Auto Repair",
            "type":"Services"
        }
    ],
    "sg:phone":"+1 310 603 2817",
    "sg:postcode":"90262",
    "sg:province":"CA",
    "sg:tags":[
        "body",
        "repairing",
        "painting",
        "automobile"
    ],
    "wof:name":"Dobles Body Shop",
    "wof:placetype":"venue"
},
  "geometry": {"coordinates":[-118.18059100000001,33.919203],"type":"Point"}
}