{
  "type": "Feature",
  "properties": {
    "iso:country":"US",
    "sg:address":"2650 Walnut Ave",
    "sg:city":"Tustin",
    "sg:classifiers":[
        {
            "category":"Professional",
            "type":"Services"
        }
    ],
    "sg:phone":"+1 714 505 1667",
    "sg:postcode":"92780",
    "sg:province":"CA",
    "wof:name":"Bestbuychoice",
    "wof:placetype":"venue"
},
  "geometry": {"coordinates":[-117.80772399999999,33.716182],"type":"Point"}
}