{
  "type": "Feature",
  "properties": {
    "addr:full":"1834 Lynne Dr Santa Maria CA 93454",
    "addr:housenumber":"1834",
    "addr:postcode":"93454",
    "addr:street":"Lynne Dr",
    "iso:country":"US",
    "sg:address":"1834 Lynne Dr",
    "sg:city":"Santa Maria",
    "sg:classifiers":[
        {
            "category":"Wholesale",
            "subcategory":"Vending Machines",
            "type":"Manufacturing & Wholesale Goods"
        }
    ],
    "sg:phone":"+1 805 925 4257",
    "sg:postcode":"93454",
    "sg:province":"CA",
    "sg:tags":[
        "operator"
    ],
    "wof:name":"Straight Up Vending",
    "wof:placetype":"venue"
},
  "geometry": {"coordinates":[-120.42704999999999,34.972925],"type":"Point"}
}