{
  "type": "Feature",
  "properties": {
    "iso:country":"US",
    "sg:address":"2475 253rd St",
    "sg:city":"Lomita",
    "sg:classifiers":[
        {
            "category":"Manufacturing",
            "subcategory":"Rubber & Plastics",
            "type":"Manufacturing & Wholesale Goods"
        }
    ],
    "sg:phone":"+1 310 534 3049",
    "sg:postcode":"90717",
    "sg:province":"CA",
    "wof:name":"Alpine Plastics",
    "wof:placetype":"venue"
},
  "geometry": {"coordinates":[-118.328036,33.795424],"type":"Point"}
}