{
  "type": "Feature",
  "properties": {
    "addr:full":"2445 S Broadway Santa Maria CA 93454",
    "addr:housenumber":"2445",
    "addr:postcode":"93454",
    "addr:street":"S Broadway",
    "iso:country":"US",
    "sg:address":"2445 S Broadway",
    "sg:city":"Santa Maria",
    "sg:classifiers":[
        {
            "category":"Banks & Credit Unions",
            "subcategory":"Bank",
            "type":"Services"
        },
        {
            "category":"Professional",
            "subcategory":"Lawyer & Legal Services",
            "type":"Services"
        }
    ],
    "sg:phone":"+1 805 937 2768",
    "sg:postcode":"93454",
    "sg:province":"CA",
    "sg:website":"www.wachovia.com",
    "wof:name":"Wachovia",
    "wof:placetype":"venue"
},
  "geometry": {"coordinates":[-120.436218,34.915819],"type":"Point"}
}