{
  "type": "Feature",
  "properties": {
    "iso:country":"US",
    "sg:address":"344 Coogan Way",
    "sg:city":"El Cajon",
    "sg:classifiers":[
        {
            "category":"Manufacturing",
            "subcategory":"Electronics",
            "type":"Manufacturing & Wholesale Goods"
        }
    ],
    "sg:phone":"+1 619 401 1967",
    "sg:postcode":"92020",
    "sg:province":"CA",
    "sg:tags":[
        "equipment",
        "electronic",
        "supply"
    ],
    "sg:website":"www.avalonrf.com",
    "wof:name":"Pacifictech",
    "wof:placetype":"venue"
},
  "geometry": {"coordinates":[-116.96364699999999,32.809894],"type":"Point"}
}