{
  "type": "Feature",
  "properties": {
    "iso:country":"US",
    "sg:address":"5409 Florin Rd",
    "sg:city":"Sacramento",
    "sg:classifiers":[
        {
            "category":"Professional",
            "subcategory":"Lawyer & Legal Services",
            "type":"Services"
        }
    ],
    "sg:phone":"+1 916 429 4490",
    "sg:postcode":"95823",
    "sg:province":"CA",
    "sg:tags":[
        "attorney"
    ],
    "wof:name":"Sullivan Accident Law Ctr",
    "wof:placetype":"venue"
},
  "geometry": {"coordinates":[-121.438125,38.496167],"type":"Point"}
}