{
  "type": "Feature",
  "properties": {
    "iso:country":"US",
    "sg:address":"95 Wharf II",
    "sg:city":"Monterey",
    "sg:classifiers":[
        {
            "category":"Home & Garden",
            "subcategory":"Home Furnishings",
            "type":"Retail Goods"
        }
    ],
    "sg:phone":"+1 831 641 9356",
    "sg:postcode":"93940",
    "sg:province":"CA",
    "sg:tags":[
        "glassware",
        "chinaware"
    ],
    "wof:name":"Crystalix",
    "wof:placetype":"venue"
},
  "geometry": {"coordinates":[-121.892701,36.604367],"type":"Point"}
}