{
  "type": "Feature",
  "properties": {
    "iso:country":"US",
    "sg:address":"5 Riveroaks",
    "sg:city":"Irvine",
    "sg:classifiers":[
        {
            "category":"Shopping",
            "subcategory":"Pets & Pet Supplies",
            "type":"Retail Goods"
        }
    ],
    "sg:phone":"+1 714 389 1652",
    "sg:postcode":"92602",
    "sg:province":"CA",
    "sg:tags":[
        "store"
    ],
    "wof:name":"Jungleland Enterprises Inc",
    "wof:placetype":"venue"
},
  "geometry": {"coordinates":[-117.782678,33.72066],"type":"Point"}
}