{
  "type": "Feature",
  "properties": {
    "addr:full":"9011 Memory Ln Spring Valley CA 91977",
    "addr:housenumber":"9011",
    "addr:postcode":"91977",
    "addr:street":"Memory Ln",
    "iso:country":"US",
    "sg:address":"9011 Memory Ln",
    "sg:city":"Spring Valley",
    "sg:classifiers":[
        {
            "category":"Building & Trades",
            "subcategory":"Construction",
            "type":"Services"
        }
    ],
    "sg:phone":"+1 619 589 8112",
    "sg:postcode":"91977",
    "sg:province":"CA",
    "sg:tags":[
        "paving",
        "contractor"
    ],
    "wof:name":"American Asphalt & Concrete",
    "wof:placetype":"venue"
},
  "geometry": {"coordinates":[-117.002146,32.74553],"type":"Point"}
}