{
  "type": "Feature",
  "properties": {
    "addr:full":"1475 Huntington Ave South San Francisco CA 94080",
    "addr:housenumber":"1475",
    "addr:postcode":"94080",
    "addr:street":"Huntington Ave",
    "iso:country":"US",
    "sg:address":"1475 Huntington Ave",
    "sg:city":"South San Francisco",
    "sg:classifiers":[
        {
            "category":"Professional",
            "subcategory":"Accounting & Tax Preparation",
            "type":"Services"
        },
        {
            "category":"Professional",
            "subcategory":"Lawyer & Legal Services",
            "type":"Services"
        }
    ],
    "sg:phone":"+1 650 588 4333",
    "sg:postcode":"94080",
    "sg:province":"CA",
    "sg:tags":[
        "accountant"
    ],
    "wof:name":"Gordon Lee CPA",
    "wof:placetype":"venue"
},
  "geometry": {"coordinates":[-122.421997,37.644199],"type":"Point"}
}