{
  "type": "Feature",
  "properties": {
    "addr:full":"704 Garner Ave Apt 31 Salinas CA 93905",
    "addr:housenumber":"704;31",
    "addr:postcode":"93905",
    "addr:street":"Garner Ave Apt",
    "iso:country":"US",
    "sg:address":"704 Garner Ave Apt 31",
    "sg:city":"Salinas",
    "sg:classifiers":[
        {
            "category":"Shopping",
            "subcategory":"Hobbies, Toys, & Games",
            "type":"Retail Goods"
        }
    ],
    "sg:phone":"+1 831 783 1390",
    "sg:postcode":"93905",
    "sg:province":"CA",
    "sg:tags":[
        "toy",
        "store"
    ],
    "wof:name":"Ninos Del Futuro",
    "wof:placetype":"venue"
},
  "geometry": {"coordinates":[-121.61905,36.690693],"type":"Point"}
}