{
  "type": "Feature",
  "properties": {
    "iso:country":"US",
    "sg:address":"374 S Glassell St",
    "sg:city":"Orange",
    "sg:classifiers":[
        {
            "category":"Professional",
            "subcategory":"Lawyer & Legal Services",
            "type":"Services"
        }
    ],
    "sg:phone":"+1 714 289 2450",
    "sg:postcode":"92866",
    "sg:province":"CA",
    "sg:website":"www.attorneydonahue.com",
    "wof:name":"The Law Offices Of Timothy Donahue",
    "wof:placetype":"venue"
},
  "geometry": {"coordinates":[-117.853272,33.782864],"type":"Point"}
}