{
  "type": "Feature",
  "properties": {
    "addr:full":"3444 Swetzer Rd Loomis CA 95650",
    "addr:housenumber":"3444",
    "addr:postcode":"95650",
    "addr:street":"Swetzer Rd",
    "iso:country":"US",
    "sg:address":"3444 Swetzer Rd",
    "sg:city":"Loomis",
    "sg:classifiers":[
        {
            "category":"Shopping",
            "subcategory":"Bicycles & Sporting Goods",
            "type":"Retail Goods"
        }
    ],
    "sg:phone":"+1 916 652 2295",
    "sg:postcode":"95650",
    "sg:province":"CA",
    "sg:tags":[
        "gun",
        "gunsmith"
    ],
    "wof:name":"Orion Gunworks",
    "wof:placetype":"venue"
},
  "geometry": {"coordinates":[-121.19185400000001,38.827206],"type":"Point"}
}