{
  "type": "Feature",
  "properties": {
    "addr:full":"625 W Foothill Blvd Monrovia CA 91016",
    "addr:housenumber":"625",
    "addr:postcode":"91016",
    "addr:street":"W Foothill Blvd",
    "iso:country":"US",
    "sg:address":"625 W Foothill Blvd",
    "sg:city":"Monrovia",
    "sg:classifiers":[
        {
            "category":"Place Of Worship",
            "type":"Public Place"
        }
    ],
    "sg:phone":"+1 626 249 0090",
    "sg:postcode":"91016",
    "sg:province":"CA",
    "sg:tags":[
        "church"
    ],
    "wof:name":"First Evangelical Church, Arcadia",
    "wof:placetype":"venue"
},
  "geometry": {"coordinates":[-118.012377,34.151222],"type":"Point"}
}