{
  "type": "Feature",
  "properties": {
    "addr:full":"3468 Silverado Trl N Saint Helena CA 94574",
    "addr:housenumber":"3468",
    "addr:postcode":"94574",
    "addr:street":"Silverado Trl N",
    "iso:country":"US",
    "sg:address":"3468 Silverado Trl N",
    "sg:city":"Saint Helena",
    "sg:classifiers":[
        {
            "category":"Winery",
            "type":"Food & Drink"
        }
    ],
    "sg:phone":"+1 707 963 5472",
    "sg:postcode":"94574",
    "sg:province":"CA",
    "sg:website":"www.chateauboswellwinery.com",
    "wof:name":"Chateau Boswell",
    "wof:placetype":"venue"
},
  "geometry": {"coordinates":[-122.49099699999999,38.5466],"type":"Point"}
}