{
  "type": "Feature",
  "properties": {
    "addr:full":"Templeton's Salon 445 17th St #B Costa Mesa CA 92627",
    "addr:housenumber":"445",
    "addr:postcode":"92627",
    "addr:street":"17Th St # B Costa",
    "iso:country":"US",
    "sg:address":"Templeton's Salon 445 17th St #B",
    "sg:city":"Costa Mesa",
    "sg:classifiers":[
        {
            "category":"Personal",
            "subcategory":"Hair Removal",
            "type":"Services"
        },
        {
            "category":"Personal",
            "subcategory":"Skin Care",
            "type":"Services"
        }
    ],
    "sg:phone":"+1 949 436 7844",
    "sg:postcode":"92627",
    "sg:province":"CA",
    "sg:website":"www.zenofskin.com",
    "wof:name":"The Zen Of Skin",
    "wof:placetype":"venue"
},
  "geometry": {"coordinates":[-117.91110999999999,33.629074],"type":"Point"}
}