{
  "type": "Feature",
  "properties": {
    "iso:country":"US",
    "sg:address":"7313 N Pacific Ave",
    "sg:city":"Livingston",
    "sg:classifiers":[
        {
            "category":"Building & Trades",
            "subcategory":"Plumbing",
            "type":"Services"
        }
    ],
    "sg:phone":"+1 209 394 7899",
    "sg:postcode":"95334",
    "sg:province":"CA",
    "sg:tags":[
        "conditioning",
        "air",
        "system",
        "contractor"
    ],
    "wof:name":"Blaine Inc",
    "wof:placetype":"venue"
},
  "geometry": {"coordinates":[-120.741124,37.394214],"type":"Point"}
}