{
  "type": "Feature",
  "properties": {
    "addr:full":"1259 Sugarbush Dr Vista CA 92084",
    "addr:housenumber":"1259",
    "addr:postcode":"92084",
    "addr:street":"Sugarbush Dr",
    "iso:country":"US",
    "sg:address":"1259 Sugarbush Dr",
    "sg:city":"Vista",
    "sg:classifiers":[
        {
            "category":"Social Services",
            "type":"Services"
        }
    ],
    "sg:phone":"+1 760 727 6139",
    "sg:postcode":"92084",
    "sg:province":"CA",
    "sg:tags":[
        "counselor",
        "marriage",
        "family"
    ],
    "wof:name":"Mc Donald Therapy Ctr",
    "wof:placetype":"venue"
},
  "geometry": {"coordinates":[-117.18973,33.188031],"type":"Point"}
}