{
  "type": "Feature",
  "properties": {
    "addr:full":"12225 Woodside Ave Lakeside CA 92040",
    "addr:housenumber":"12225",
    "addr:postcode":"92040",
    "addr:street":"Woodside Ave",
    "iso:country":"US",
    "sg:address":"12225 Woodside Ave",
    "sg:city":"Lakeside",
    "sg:classifiers":[
        {
            "category":"Shopping",
            "subcategory":"Computers & Home Electronics",
            "type":"Retail Goods"
        }
    ],
    "sg:phone":"+1 619 447 1982",
    "sg:postcode":"92040",
    "sg:province":"CA",
    "sg:tags":[
        "equipment",
        "satellite",
        "system"
    ],
    "wof:name":"A & A Satellite By Fast TV",
    "wof:placetype":"venue"
},
  "geometry": {"coordinates":[-116.926503,32.8566],"type":"Point"}
}