{
  "type": "Feature",
  "properties": {
    "iso:country":"US",
    "sg:address":"25050 Madison Ave",
    "sg:city":"Murrieta",
    "sg:classifiers":[
        {
            "category":"Banks & Credit Unions",
            "subcategory":"Bank",
            "type":"Services"
        }
    ],
    "sg:phone":"+1 951 894 4330",
    "sg:postcode":"92562",
    "sg:province":"CA",
    "sg:tags":[
        "mortgage",
        "loan",
        "broker",
        "real estate"
    ],
    "wof:name":"All Valley Lending Inc",
    "wof:placetype":"venue"
},
  "geometry": {"coordinates":[-117.198921,33.556077],"type":"Point"}
}