{
  "type": "Feature",
  "properties": {
    "iso:country":"US",
    "sg:address":"1161 Simi Town Center Way",
    "sg:city":"Simi Valley",
    "sg:classifiers":[
        {
            "category":"Restaurant",
            "type":"Food & Drink"
        }
    ],
    "sg:menulink":"http://www.allmenus.com/ca/simi-valley/104986-carinos-italian-grill/menu/",
    "sg:phone":"+1 805 578 4558",
    "sg:postcode":"93065",
    "sg:province":"CA",
    "sg:tags":[
        "american",
        "italian"
    ],
    "wof:name":"Carino's Italian Grill",
    "wof:placetype":"venue"
},
  "geometry": {"coordinates":[-118.777612,34.284167],"type":"Point"}
}