{
  "type": "Feature",
  "properties": {
    "addr:full":"24201 Valencia Blvd Valencia CA 91355",
    "addr:housenumber":"24201",
    "addr:postcode":"91355",
    "addr:street":"Valencia Blvd",
    "iso:country":"US",
    "sg:address":"24201 Valencia Blvd",
    "sg:city":"Valencia",
    "sg:classifiers":[
        {
            "category":"Arts & Performance",
            "subcategory":"Theater",
            "type":"Entertainment"
        }
    ],
    "sg:phone":"+1 661 260 3469",
    "sg:postcode":"91355",
    "sg:province":"CA",
    "sg:tags":[
        "bureau"
    ],
    "wof:name":"Little Cutey",
    "wof:placetype":"venue"
},
  "geometry": {"coordinates":[-118.556816,34.413124],"type":"Point"}
}