{
  "type": "Feature",
  "properties": {
    "addr:full":"530 Turk Street San Francisco CA 94102",
    "addr:housenumber":"530",
    "addr:postcode":"94102",
    "addr:street":"Turk Street",
    "iso:country":"US",
    "sg:address":"530 Turk Street",
    "sg:city":"San Francisco",
    "sg:classifiers":[
        {
            "category":"Parking",
            "type":"Transportation"
        }
    ],
    "sg:phone":"+1 415 474 2237",
    "sg:postcode":"94102",
    "sg:province":"CA",
    "wof:name":"Federal Auto Parks",
    "wof:placetype":"venue"
},
  "geometry": {"coordinates":[-122.41799899999999,37.782398],"type":"Point"}
}