{
  "type": "Feature",
  "properties": {
    "addr:full":"136 Chambers St El Cajon CA 92020",
    "addr:housenumber":"136",
    "addr:postcode":"92020",
    "addr:street":"Chambers St",
    "iso:country":"US",
    "sg:address":"136 Chambers St",
    "sg:city":"El Cajon",
    "sg:classifiers":[
        {
            "category":"Retail",
            "subcategory":"Event Space",
            "type":"Services"
        }
    ],
    "sg:phone":"+1 619 447 0356",
    "sg:postcode":"92020",
    "sg:province":"CA",
    "sg:tags":[
        "venue"
    ],
    "wof:name":"Veterans Civic Memorial Halls",
    "wof:placetype":"venue"
},
  "geometry": {"coordinates":[-116.966003,32.795502],"type":"Point"}
}