{
  "type": "Feature",
  "properties": {
    "iso:country":"US",
    "sg:address":"4600 Borman Way",
    "sg:city":"Bakersfield",
    "sg:classifiers":[
        {
            "category":"Wholesale",
            "subcategory":"Metals & Minerals",
            "type":"Manufacturing & Wholesale Goods"
        }
    ],
    "sg:phone":"+1 661 835 1213",
    "sg:postcode":"93313",
    "sg:province":"CA",
    "sg:tags":[
        "pipe"
    ],
    "sg:website":"www.kellypipe.com",
    "wof:name":"Kelly Pipe Co",
    "wof:placetype":"venue"
},
  "geometry": {"coordinates":[-119.076065,35.313588],"type":"Point"}
}