{
  "type": "Feature",
  "properties": {
    "iso:country":"US",
    "sg:address":"18524 Sophia Ln",
    "sg:city":"Tarzana",
    "sg:classifiers":[
        {
            "category":"Professional",
            "subcategory":"Lawyer & Legal Services",
            "type":"Services"
        }
    ],
    "sg:phone":"+1 818 881 0691",
    "sg:postcode":"91356",
    "sg:province":"CA",
    "sg:tags":[
        "attorney"
    ],
    "wof:name":"Kellener Lucky Law Offices",
    "wof:placetype":"venue"
},
  "geometry": {"coordinates":[-118.535984,34.166921],"type":"Point"}
}