{
  "type": "Feature",
  "properties": {
    "addr:full":"121 Seminary Dr Mill Valley CA 94941",
    "addr:housenumber":"121",
    "addr:postcode":"94941",
    "addr:street":"Seminary Dr",
    "iso:country":"US",
    "sg:address":"121 Seminary Dr",
    "sg:city":"Mill Valley",
    "sg:classifiers":[
        {
            "category":"Health Services",
            "subcategory":"Health Practitioner",
            "type":"Services"
        }
    ],
    "sg:phone":"+1 415 389 9705",
    "sg:postcode":"94941",
    "sg:province":"CA",
    "sg:tags":[
        "therapist",
        "physical"
    ],
    "wof:name":"Irit Schaffer",
    "wof:placetype":"venue"
},
  "geometry": {"coordinates":[-122.510773,37.883569],"type":"Point"}
}