{
  "type": "Feature",
  "properties": {
    "addr:full":"5415 International Blvd Oakland CA 94601",
    "addr:housenumber":"5415",
    "addr:postcode":"94601",
    "addr:street":"International Blvd",
    "iso:country":"US",
    "sg:address":"5415 International Blvd",
    "sg:city":"Oakland",
    "sg:classifiers":[
        {
            "category":"Food & Beverages",
            "subcategory":"Groceries & Convenience Stores",
            "type":"Retail Goods"
        }
    ],
    "sg:phone":"+1 510 536 6802",
    "sg:postcode":"94601",
    "sg:province":"CA",
    "wof:name":"Chapala Market",
    "wof:placetype":"venue"
},
  "geometry": {"coordinates":[-122.20500199999999,37.768398],"type":"Point"}
}