{
  "type": "Feature",
  "properties": {
    "addr:full":"2736 Adams Ave San Diego CA 92116",
    "addr:housenumber":"2736",
    "addr:postcode":"92116",
    "addr:street":"Adams Ave",
    "iso:country":"US",
    "sg:address":"2736 Adams Ave",
    "sg:city":"San Diego",
    "sg:classifiers":[
        {
            "category":"Restaurant",
            "type":"Food & Drink"
        }
    ],
    "sg:menulink":"http://www.allmenus.com/ca/san-diego/6103-tinos-mexican-grill/menu/",
    "sg:phone":"+1 619 568 0917",
    "sg:postcode":"92116",
    "sg:province":"CA",
    "sg:tags":[
        "mexican"
    ],
    "wof:name":"Tino's Mexican Grill",
    "wof:placetype":"venue"
},
  "geometry": {"coordinates":[-117.13477399999999,32.762831],"type":"Point"}
}