{
  "type": "Feature",
  "properties": {
    "addr:full":"30 Los Patos Way Santa Barbara CA 93108",
    "addr:housenumber":"30",
    "addr:postcode":"93108",
    "addr:street":"Los Patos Way",
    "iso:country":"US",
    "sg:address":"30 Los Patos Way",
    "sg:city":"Santa Barbara",
    "sg:classifiers":[
        {
            "category":"Restaurant",
            "type":"Food & Drink"
        }
    ],
    "sg:phone":"+1 805 969 0448",
    "sg:postcode":"93108",
    "sg:province":"CA",
    "wof:name":"Cafe Del Sol",
    "wof:placetype":"venue"
},
  "geometry": {"coordinates":[-119.65825100000001,34.422387],"type":"Point"}
}