{
  "type": "Feature",
  "properties": {
    "addr:full":"3027 Scenic View Rd Alpine CA 91901",
    "addr:housenumber":"3027",
    "addr:postcode":"91901",
    "addr:street":"Scenic View Rd",
    "iso:country":"US",
    "sg:address":"3027 Scenic View Rd",
    "sg:city":"Alpine",
    "sg:classifiers":[
        {
            "category":"Building & Trades",
            "subcategory":"Landscaping Services",
            "type":"Services"
        }
    ],
    "sg:phone":"+1 619 659 5770",
    "sg:postcode":"91901",
    "sg:province":"CA",
    "sg:tags":[
        "tree"
    ],
    "wof:name":"Bates Tree Svc",
    "wof:placetype":"venue"
},
  "geometry": {"coordinates":[-116.748239,32.826694],"type":"Point"}
}