{
  "type": "Feature",
  "properties": {
    "iso:country":"US",
    "sg:address":"1834 Howard Rd",
    "sg:city":"Madera",
    "sg:classifiers":[
        {
            "category":"Farming",
            "subcategory":"Farm & Veterinary Services",
            "type":"Manufacturing & Wholesale Goods"
        }
    ],
    "sg:phone":"+1 559 664 8580",
    "sg:postcode":"93637",
    "sg:province":"CA",
    "sg:tags":[
        "management"
    ],
    "wof:name":"Green Valley Harvesting",
    "wof:placetype":"venue"
},
  "geometry": {"coordinates":[-120.078828,36.952756],"type":"Point"}
}