{
  "type": "Feature",
  "properties": {
    "addr:full":"1842 Glendale Blvd Los Angeles CA 90026",
    "addr:housenumber":"1842",
    "addr:postcode":"90026",
    "addr:street":"Glendale Blvd",
    "iso:country":"US",
    "sg:address":"1842 Glendale Blvd",
    "sg:city":"Los Angeles",
    "sg:classifiers":[
        {
            "category":"Shopping",
            "type":"Retail Goods"
        }
    ],
    "sg:phone":"+1 323 663 2707",
    "sg:postcode":"90026",
    "sg:province":"CA",
    "sg:tags":[
        "religious"
    ],
    "wof:name":"Grandmasters Group Of Co",
    "wof:placetype":"venue"
},
  "geometry": {"coordinates":[-118.259094,34.089823],"type":"Point"}
}