{
  "type": "Feature",
  "properties": {
    "iso:country":"US",
    "sg:address":"4050 Tampico Rd",
    "sg:city":"Atascadero",
    "sg:classifiers":[
        {
            "category":"Retail",
            "subcategory":"Repair Shop",
            "type":"Services"
        }
    ],
    "sg:phone":"+1 805 461 9087",
    "sg:postcode":"93422",
    "sg:province":"CA",
    "sg:tags":[
        "blacksmith"
    ],
    "wof:name":"Brad Felger Horseshoeing",
    "wof:placetype":"venue"
},
  "geometry": {"coordinates":[-120.644862,35.486902],"type":"Point"}
}