{
  "type": "Feature",
  "properties": {
    "iso:country":"US",
    "sg:address":"3605 W Pendleton Ave",
    "sg:city":"Santa Ana",
    "sg:classifiers":[
        {
            "category":"Professional",
            "type":"Services"
        }
    ],
    "sg:phone":"+1 714 433 2940",
    "sg:postcode":"92704",
    "sg:province":"CA",
    "wof:name":"Naturipe Berry Growers",
    "wof:placetype":"venue"
},
  "geometry": {"coordinates":[-117.917213,33.716104],"type":"Point"}
}