{
  "type": "Feature",
  "properties": {
    "iso:country":"US",
    "sg:address":"1017 J St",
    "sg:city":"Sacramento",
    "sg:classifiers":[
        {
            "category":"Government",
            "subcategory":"Office",
            "type":"Public Place"
        }
    ],
    "sg:phone":"+1 916 322 3507",
    "sg:postcode":"95814",
    "sg:province":"CA",
    "sg:tags":[
        "adm",
        "program"
    ],
    "wof:name":"Enterprise Zones",
    "wof:placetype":"venue"
},
  "geometry": {"coordinates":[-121.49226299999999,38.580084],"type":"Point"}
}