{
  "type": "Feature",
  "properties": {
    "iso:country":"US",
    "sg:address":"420 N Harrison St",
    "sg:city":"Stockton",
    "sg:classifiers":[
        {
            "category":"Building & Trades",
            "subcategory":"Construction",
            "type":"Services"
        }
    ],
    "sg:phone":"+1 209 464 1291",
    "sg:postcode":"95203",
    "sg:province":"CA",
    "sg:tags":[
        "tile",
        "dealer"
    ],
    "wof:name":"Stockton Ceramic Tile Co",
    "wof:placetype":"venue"
},
  "geometry": {"coordinates":[-121.30015,37.955987],"type":"Point"}
}