{
  "type": "Feature",
  "properties": {
    "addr:full":"28460 Ave Marquesa Cathedral City CA 92234",
    "addr:housenumber":"28460",
    "addr:postcode":"92234",
    "addr:street":"Ave Marquesa",
    "iso:country":"US",
    "sg:address":"28460 Ave Marquesa",
    "sg:city":"Cathedral City",
    "sg:classifiers":[
        {
            "category":"Building & Trades",
            "subcategory":"Construction",
            "type":"Services"
        }
    ],
    "sg:phone":"+1 760 322 2435",
    "sg:postcode":"92234",
    "sg:province":"CA",
    "sg:tags":[
        "contractor"
    ],
    "sg:website":"www.custom-interiors.net",
    "wof:name":"Custom Interiors",
    "wof:placetype":"venue"
},
  "geometry": {"coordinates":[-116.464062,33.838532],"type":"Point"}
}