{
  "type": "Feature",
  "properties": {
    "addr:full":"1647 S Main St Milpitas CA 95035",
    "addr:housenumber":"1647",
    "addr:postcode":"95035",
    "addr:street":"S Main St",
    "iso:country":"US",
    "sg:address":"1647 S Main St",
    "sg:city":"Milpitas",
    "sg:classifiers":[
        {
            "category":"Manufacturing",
            "subcategory":"Retail Goods",
            "type":"Manufacturing & Wholesale Goods"
        }
    ],
    "sg:phone":"+1 408 586 7300",
    "sg:postcode":"95035",
    "sg:province":"CA",
    "sg:tags":[
        "assembly",
        "fabricating"
    ],
    "wof:name":"ATS Svc Co",
    "wof:placetype":"venue"
},
  "geometry": {"coordinates":[-121.90299,37.406137],"type":"Point"}
}