{
  "type": "Feature",
  "properties": {
    "iso:country":"US",
    "sg:address":"1100 W. Florence Ave Ste D",
    "sg:city":"Inglewood",
    "sg:classifiers":[
        {
            "category":"Restaurant",
            "type":"Food & Drink"
        }
    ],
    "sg:phone":"+1 888 932 3882",
    "sg:postcode":"90301",
    "sg:province":"CA",
    "sg:website":"www.bettamuffins.com",
    "wof:name":"Dora Country aka Betta Muffins",
    "wof:placetype":"venue"
},
  "geometry": {"coordinates":[-118.375697,33.961022],"type":"Point"}
}