{
  "type": "Feature",
  "properties": {
    "addr:full":"43643 Skye Rd Fremont CA 94539",
    "addr:housenumber":"43643",
    "addr:postcode":"94539",
    "addr:street":"Skye Rd",
    "iso:country":"US",
    "sg:address":"43643 Skye Rd",
    "sg:city":"Fremont",
    "sg:classifiers":[
        {
            "category":"Professional",
            "subcategory":"Computer Services",
            "type":"Services"
        }
    ],
    "sg:phone":"+1 510 659 1324",
    "sg:postcode":"94539",
    "sg:province":"CA",
    "sg:tags":[
        "related"
    ],
    "wof:name":"Bill Desjardin Consulting",
    "wof:placetype":"venue"
},
  "geometry": {"coordinates":[-121.931425,37.521801],"type":"Point"}
}