{
  "type": "Feature",
  "properties": {
    "addr:full":"995 el Segundo Dr Thousand Oaks CA 91362",
    "addr:housenumber":"995",
    "addr:postcode":"91362",
    "addr:street":"El Segundo Dr",
    "iso:country":"US",
    "sg:address":"995 el Segundo Dr",
    "sg:city":"Thousand Oaks",
    "sg:classifiers":[
        {
            "category":"Wholesale",
            "subcategory":"Machinery & Supplies",
            "type":"Manufacturing & Wholesale Goods"
        }
    ],
    "sg:phone":"+1 805 230 1048",
    "sg:postcode":"91362",
    "sg:province":"CA",
    "sg:tags":[
        "tool"
    ],
    "wof:name":"Hi-Speed Corp",
    "wof:placetype":"venue"
},
  "geometry": {"coordinates":[-118.860829,34.18951],"type":"Point"}
}