{
  "type": "Feature",
  "properties": {
    "iso:country":"US",
    "sg:address":"4870 Barranca Pkwy # 330",
    "sg:city":"Irvine",
    "sg:classifiers":[
        {
            "category":"Health Services",
            "subcategory":"Doctor",
            "type":"Services"
        },
        {
            "category":"Health Services",
            "subcategory":"Clinic",
            "type":"Services"
        },
        {
            "category":"Community Center",
            "type":"Public Place"
        }
    ],
    "sg:phone":"+1 949 653 5810",
    "sg:postcode":"92604",
    "sg:province":"CA",
    "sg:tags":[
        "physician",
        "family",
        "medical",
        "practice",
        "surgeons",
        "internal",
        "osteopathic",
        "medicine",
        "surgeon"
    ],
    "wof:name":"Irvine Internal Medical Group",
    "wof:placetype":"venue"
},
  "geometry": {"coordinates":[-117.795816,33.67635],"type":"Point"}
}