{
  "type": "Feature",
  "properties": {
    "iso:country":"US",
    "sg:address":"5720 Ayala Ave",
    "sg:city":"Baldwin Park",
    "sg:classifiers":[
        {
            "category":"Professional",
            "subcategory":"Art Services",
            "type":"Services"
        },
        {
            "category":"Manufacturing",
            "subcategory":"Printing",
            "type":"Manufacturing & Wholesale Goods"
        }
    ],
    "sg:phone":"+1 626 334 5200",
    "sg:postcode":"91706",
    "sg:province":"CA",
    "sg:tags":[
        "commercial",
        "screen",
        "design"
    ],
    "wof:name":"Shaker's Shirts",
    "wof:placetype":"venue"
},
  "geometry": {"coordinates":[-117.941204,34.120375],"type":"Point"}
}