{
  "type": "Feature",
  "properties": {
    "iso:country":"US",
    "sg:address":"8335 Winnetka Ave",
    "sg:city":"Winnetka",
    "sg:classifiers":[
        {
            "category":"Social Services",
            "subcategory":"Adult Care",
            "type":"Services"
        }
    ],
    "sg:phone":"+1 818 360 2349",
    "sg:postcode":"91306",
    "sg:province":"CA",
    "sg:tags":[
        "residential",
        "facility"
    ],
    "wof:name":"Devonshire Country Homes",
    "wof:placetype":"venue"
},
  "geometry": {"coordinates":[-118.571112,34.221486],"type":"Point"}
}