{
  "type": "Feature",
  "properties": {
    "addr:full":"3200 Ocean Park Blvd Santa Monica CA 90405",
    "addr:housenumber":"3200",
    "addr:postcode":"90405",
    "addr:street":"Ocean Park Blvd",
    "iso:country":"US",
    "sg:address":"3200 Ocean Park Blvd",
    "sg:city":"Santa Monica",
    "sg:classifiers":[
        {
            "category":"Real Estate",
            "subcategory":"Real Estate Agent",
            "type":"Services"
        }
    ],
    "sg:phone":"+1 310 451 9741",
    "sg:postcode":"90405",
    "sg:province":"CA",
    "sg:tags":[
        "management"
    ],
    "sg:website":"www.equityoffice.com",
    "wof:name":"Equity Office Properties Trust",
    "wof:placetype":"venue"
},
  "geometry": {"coordinates":[-118.4509,34.021636],"type":"Point"}
}