{
  "type": "Feature",
  "properties": {
    "iso:country":"US",
    "sg:address":"1144 Palm Ave",
    "sg:city":"Imperial Beach",
    "sg:classifiers":[
        {
            "category":"Personal",
            "subcategory":"Beauty Salon",
            "type":"Services"
        }
    ],
    "sg:phone":"+1 619 423 7811",
    "sg:postcode":"91932",
    "sg:province":"CA",
    "wof:name":"Billie Jean's Hair Styling",
    "wof:placetype":"venue"
},
  "geometry": {"coordinates":[-117.110398,32.583958],"type":"Point"}
}