{
  "type": "Feature",
  "properties": {
    "iso:country":"US",
    "sg:address":"2560 Teepee Dr",
    "sg:city":"Stockton",
    "sg:classifiers":[
        {
            "category":"Wholesale",
            "subcategory":"Electrical",
            "type":"Manufacturing & Wholesale Goods"
        }
    ],
    "sg:phone":"+1 209 464 2288",
    "sg:postcode":"95205",
    "sg:province":"CA",
    "sg:tags":[
        "battery"
    ],
    "wof:name":"ELESCO",
    "wof:placetype":"venue"
},
  "geometry": {"coordinates":[-121.252326,37.985361],"type":"Point"}
}