{
  "type": "Feature",
  "properties": {
    "iso:country":"US",
    "sg:address":"31187 State Rte 44",
    "sg:city":"Shingletown",
    "sg:classifiers":[
        {
            "category":"Wholesale",
            "subcategory":"Farm Supplies",
            "type":"Manufacturing & Wholesale Goods"
        }
    ],
    "sg:phone":"+1 530 474 1151",
    "sg:postcode":"96088",
    "sg:province":"CA",
    "sg:tags":[
        "feed"
    ],
    "wof:name":"Shingletown Feed & Blacksmith",
    "wof:placetype":"venue"
},
  "geometry": {"coordinates":[-121.899055,40.49136],"type":"Point"}
}