{
  "type": "Feature",
  "properties": {
    "addr:full":"14524 Hawthorne Boulevard Lawndale CA 90260",
    "addr:housenumber":"14524",
    "addr:postcode":"ca 90260",
    "addr:street":"Hawthorne Boulevard",
    "iso:country":"US",
    "sg:address":"14524 Hawthorne Boulevard",
    "sg:city":"Lawndale",
    "sg:classifiers":[
        {
            "category":"Building & Trades",
            "subcategory":"Plumbing",
            "type":"Services"
        }
    ],
    "sg:phone":"+1 310 349 0444",
    "sg:postcode":"90260",
    "sg:province":"CA",
    "wof:name":"Brian's Plumbing Service",
    "wof:placetype":"venue"
},
  "geometry": {"coordinates":[-118.35248900000001,33.899522],"type":"Point"}
}