{
  "type": "Feature",
  "properties": {
    "addr:full":"970 Dewing Ave Lafayette CA 94549",
    "addr:housenumber":"970",
    "addr:postcode":"94549",
    "addr:street":"Dewing Ave",
    "iso:country":"US",
    "sg:address":"970 Dewing Ave",
    "sg:city":"Lafayette",
    "sg:classifiers":[
        {
            "category":"Health Services",
            "subcategory":"Doctor",
            "type":"Services"
        }
    ],
    "sg:phone":"+1 925 283 3337",
    "sg:postcode":"94549",
    "sg:province":"CA",
    "sg:tags":[
        "physician",
        "surgeon"
    ],
    "wof:name":"Bitar David E MD Inc.",
    "wof:placetype":"venue"
},
  "geometry": {"coordinates":[-122.123484,37.890212],"type":"Point"}
}