{
  "type": "Feature",
  "properties": {
    "addr:full":"4528 Brazil Street Los Angeles CA 90039",
    "addr:housenumber":"4528",
    "addr:postcode":"90039",
    "addr:street":"Brazil Street",
    "iso:country":"US",
    "sg:address":"4528 Brazil Street",
    "sg:city":"Los Angeles",
    "sg:classifiers":[
        {
            "category":"Professional",
            "subcategory":"Accounting & Tax Preparation",
            "type":"Services"
        }
    ],
    "sg:phone":"+1 818 507 9010",
    "sg:postcode":"90039",
    "sg:province":"CA",
    "sg:tags":[
        "accountant"
    ],
    "wof:name":"Ajs Asset Management",
    "wof:placetype":"venue"
},
  "geometry": {"coordinates":[-118.27287800000001,34.146925],"type":"Point"}
}