{
  "type": "Feature",
  "properties": {
    "addr:full":"404 E Branch St Arroyo Grande CA 93420",
    "addr:housenumber":"404",
    "addr:postcode":"93420",
    "addr:street":"E Branch St",
    "iso:country":"US",
    "sg:address":"404 E Branch St",
    "sg:city":"Arroyo Grande",
    "sg:classifiers":[
        {
            "category":"Social Services",
            "subcategory":"Job Training",
            "type":"Services"
        }
    ],
    "sg:phone":"+1 805 474 4594",
    "sg:postcode":"93420",
    "sg:province":"CA",
    "sg:tags":[
        "rehabilitation"
    ],
    "wof:name":"Normal Life",
    "wof:placetype":"venue"
},
  "geometry": {"coordinates":[-120.57519000000001,35.124973],"type":"Point"}
}