{
  "type": "Feature",
  "properties": {
    "addr:full":"325 E Main St Visalia CA 93291",
    "addr:housenumber":"325",
    "addr:postcode":"93291",
    "addr:street":"E Main St",
    "iso:country":"US",
    "sg:address":"325 E Main St",
    "sg:city":"Visalia",
    "sg:classifiers":[
        {
            "category":"Restaurant",
            "type":"Food & Drink"
        }
    ],
    "sg:phone":"+1 559 734 3604",
    "sg:postcode":"93291",
    "sg:province":"CA",
    "wof:name":"Visalia Tea Garden",
    "wof:placetype":"venue"
},
  "geometry": {"coordinates":[-119.28922300000001,36.330094],"type":"Point"}
}