{
  "type": "Feature",
  "properties": {
    "addr:full":"8626 S San Pedro St Los Angeles CA 90003",
    "addr:housenumber":"8626",
    "addr:postcode":"90003",
    "addr:street":"S San Pedro St",
    "iso:country":"US",
    "sg:address":"8626 S San Pedro St",
    "sg:city":"Los Angeles",
    "sg:classifiers":[
        {
            "category":"Manufacturing",
            "subcategory":"Metals",
            "type":"Manufacturing & Wholesale Goods"
        }
    ],
    "sg:phone":"+1 323 752 2266",
    "sg:postcode":"90003",
    "sg:province":"CA",
    "sg:tags":[
        "metalwork",
        "ornamental",
        "work",
        "architectural",
        "mfg"
    ],
    "wof:name":"Oziel Ornamental Irons Works",
    "wof:placetype":"venue"
},
  "geometry": {"coordinates":[-118.269418,33.959356],"type":"Point"}
}