{
  "type": "Feature",
  "properties": {
    "iso:country":"US",
    "sg:address":"178 S Victory Blvd",
    "sg:city":"Burbank",
    "sg:classifiers":[
        {
            "category":"Retail",
            "subcategory":"Auto Rental",
            "type":"Services"
        }
    ],
    "sg:phone":"+1 818 238 0110",
    "sg:postcode":"91502",
    "sg:province":"CA",
    "sg:tags":[
        "automobile",
        "leasing"
    ],
    "wof:name":"Dream Works Auto Leasing",
    "wof:placetype":"venue"
},
  "geometry": {"coordinates":[-118.316237,34.173282],"type":"Point"}
}