{
  "type": "Feature",
  "properties": {
    "iso:country":"US",
    "sg:address":"628 California Blvd",
    "sg:city":"San Luis Obispo",
    "sg:classifiers":[
        {
            "category":"Health Services",
            "subcategory":"Optometrist",
            "type":"Services"
        }
    ],
    "sg:phone":"+1 805 546 1988",
    "sg:postcode":"93401",
    "sg:province":"CA",
    "wof:name":"San Luis Optometric",
    "wof:placetype":"venue"
},
  "geometry": {"coordinates":[-120.658464,35.289459],"type":"Point"}
}