{
  "type": "Feature",
  "properties": {
    "addr:full":"5050 Folsom Blvd Sacramento CA 95819",
    "addr:housenumber":"5050",
    "addr:postcode":"95819",
    "addr:street":"Folsom Blvd",
    "iso:country":"US",
    "sg:address":"5050 Folsom Blvd",
    "sg:city":"Sacramento",
    "sg:classifiers":[
        {
            "category":"Personal",
            "subcategory":"Beauty Salon",
            "type":"Services"
        }
    ],
    "sg:phone":"+1 916 739 0702",
    "sg:postcode":"95819",
    "sg:province":"CA",
    "wof:name":"Diana Lynn",
    "wof:placetype":"venue"
},
  "geometry": {"coordinates":[-121.444416,38.560867],"type":"Point"}
}