{
  "type": "Feature",
  "properties": {
    "iso:country":"US",
    "sg:address":"1236 E Edinger Ave",
    "sg:city":"Santa Ana",
    "sg:classifiers":[
        {
            "category":"Health Services",
            "subcategory":"Hospital",
            "type":"Services"
        }
    ],
    "sg:phone":"+1 714 543 9061",
    "sg:postcode":"92707",
    "sg:province":"CA",
    "sg:tags":[
        "specialty"
    ],
    "wof:name":"Elias Garcia Vasquez",
    "wof:placetype":"venue"
},
  "geometry": {"coordinates":[-117.854417,33.726805],"type":"Point"}
}