{
  "type": "Feature",
  "properties": {
    "addr:full":"15233 Ventura Blvd Sherman Oaks CA 91403",
    "addr:housenumber":"15233",
    "addr:postcode":"91403",
    "addr:street":"Ventura Blvd",
    "iso:country":"US",
    "sg:address":"15233 Ventura Blvd",
    "sg:city":"Sherman Oaks",
    "sg:classifiers":[
        {
            "category":"Insurance",
            "subcategory":"Insurance Agent",
            "type":"Services"
        }
    ],
    "sg:phone":"+1 818 990 0280",
    "sg:postcode":"91403",
    "sg:province":"CA",
    "wof:name":"Rsi Agency",
    "wof:placetype":"venue"
},
  "geometry": {"coordinates":[-118.465603,34.153771],"type":"Point"}
}