{
  "type": "Feature",
  "properties": {
    "iso:country":"US",
    "sg:address":"380 W Martin Luther King Jr Blvd",
    "sg:city":"Los Angeles",
    "sg:classifiers":[
        {
            "category":"Wholesale",
            "subcategory":"Machinery & Supplies",
            "type":"Manufacturing & Wholesale Goods"
        }
    ],
    "sg:phone":"+1 323 233 9733",
    "sg:postcode":"90037",
    "sg:province":"CA",
    "sg:tags":[
        "equipment",
        "welding"
    ],
    "wof:name":"American Welding Alloys",
    "wof:placetype":"venue"
},
  "geometry": {"coordinates":[-118.28022799999999,34.011014],"type":"Point"}
}