{
  "type": "Feature",
  "properties": {
    "addr:full":"3410 Fruitvale Ave Bakersfield CA 93308",
    "addr:housenumber":"3410",
    "addr:postcode":"93308",
    "addr:street":"Fruitvale Ave",
    "iso:country":"US",
    "sg:address":"3410 Fruitvale Ave",
    "sg:city":"Bakersfield",
    "sg:classifiers":[
        {
            "category":"Retail",
            "subcategory":"Auto Repair",
            "type":"Services"
        }
    ],
    "sg:phone":"+1 661 588 5394",
    "sg:postcode":"93308",
    "sg:province":"CA",
    "sg:tags":[
        "repairing",
        "automobile"
    ],
    "wof:name":"Skinny's Automotive",
    "wof:placetype":"venue"
},
  "geometry": {"coordinates":[-119.07428,35.390671],"type":"Point"}
}