{
  "type": "Feature",
  "properties": {
    "addr:full":"229 Main St Brawley CA 92227",
    "addr:housenumber":"229",
    "addr:postcode":"92227",
    "addr:street":"Main St",
    "iso:country":"US",
    "sg:address":"229 Main St",
    "sg:city":"Brawley",
    "sg:classifiers":[
        {
            "category":"Wholesale",
            "subcategory":"Farm Supplies",
            "type":"Manufacturing & Wholesale Goods"
        }
    ],
    "sg:phone":"+1 760 344 9623",
    "sg:postcode":"92227",
    "sg:province":"CA",
    "sg:tags":[
        "chemical",
        "agricultural"
    ],
    "wof:name":"Jim Wavra Entomological Svc",
    "wof:placetype":"venue"
},
  "geometry": {"coordinates":[-115.53881199999999,32.978718],"type":"Point"}
}