{
  "type": "Feature",
  "properties": {
    "iso:country":"US",
    "sg:address":"5111 Telegraph Ave",
    "sg:city":"Oakland",
    "sg:classifiers":[
        {
            "category":"Building & Trades",
            "subcategory":"Cleaning & Sanitation",
            "type":"Services"
        }
    ],
    "sg:phone":"+1 510 472 0118",
    "sg:postcode":"94609",
    "sg:province":"CA",
    "sg:tags":[
        "janitor",
        "janitorial"
    ],
    "wof:name":"Complete Janatorial & Construc",
    "wof:placetype":"venue"
},
  "geometry": {"coordinates":[-122.262325,37.837334],"type":"Point"}
}