{
  "type": "Feature",
  "properties": {
    "addr:full":"24242 Hatteras St Woodland Hills CA 91367",
    "addr:housenumber":"24242",
    "addr:postcode":"91367",
    "addr:street":"Hatteras St",
    "iso:country":"US",
    "sg:address":"24242 Hatteras St",
    "sg:city":"Woodland Hills",
    "sg:classifiers":[
        {
            "category":"Wholesale",
            "subcategory":"Toys & Hobbies",
            "type":"Manufacturing & Wholesale Goods"
        }
    ],
    "sg:phone":"+1 818 702 0877",
    "sg:postcode":"91367",
    "sg:province":"CA",
    "wof:name":"B V P Inc",
    "wof:placetype":"venue"
},
  "geometry": {"coordinates":[-118.654681,34.175828],"type":"Point"}
}