{
  "type": "Feature",
  "properties": {
    "addr:full":"1231 Pacific St Bakersfield CA 93305",
    "addr:housenumber":"1231",
    "addr:postcode":"93305",
    "addr:street":"Pacific St",
    "iso:country":"US",
    "sg:address":"1231 Pacific St",
    "sg:city":"Bakersfield",
    "sg:classifiers":[
        {
            "category":"Taxi",
            "type":"Transportation"
        }
    ],
    "sg:phone":"+1 661 631 2200",
    "sg:postcode":"93305",
    "sg:province":"CA",
    "sg:tags":[
        "taxicab"
    ],
    "wof:name":"Shorty Taxi",
    "wof:placetype":"venue"
},
  "geometry": {"coordinates":[-118.981432,35.381951],"type":"Point"}
}