{
  "type": "Feature",
  "properties": {
    "iso:country":"US",
    "sg:address":"800 Scott Boulevard",
    "sg:city":"Santa Clara",
    "sg:classifiers":[
        {
            "category":"Home & Garden",
            "subcategory":"Garden Supply",
            "type":"Retail Goods"
        }
    ],
    "sg:phone":"+1 408 243 7164",
    "sg:postcode":"95050",
    "sg:province":"CA",
    "sg:tags":[
        "nursery",
        "gardening"
    ],
    "wof:name":"Citti's Cupertino Florist",
    "wof:placetype":"venue"
},
  "geometry": {"coordinates":[-121.959267,37.343775],"type":"Point"}
}