{
  "type": "Feature",
  "properties": {
    "addr:full":"12431 Lewis St Ste 202 Garden Grove CA 92840",
    "addr:housenumber":"12431",
    "addr:postcode":"92840",
    "addr:street":"Lewis St Ste 202",
    "iso:country":"US",
    "sg:address":"12431 Lewis St Ste 202",
    "sg:city":"Garden Grove",
    "sg:classifiers":[
        {
            "category":"Professional",
            "subcategory":"Lawyer & Legal Services",
            "type":"Services"
        }
    ],
    "sg:phone":"+1 714 703 8600",
    "sg:postcode":"92840",
    "sg:province":"CA",
    "wof:name":"Gomez Ronald Glenn-Law Offices Of",
    "wof:placetype":"venue"
},
  "geometry": {"coordinates":[-117.89767999999999,33.78233],"type":"Point"}
}