{
  "type": "Feature",
  "properties": {
    "addr:full":"2925 Upas St San Diego CA 92104",
    "addr:housenumber":"2925",
    "addr:postcode":"92104",
    "addr:street":"Upas St",
    "iso:country":"US",
    "sg:address":"2925 Upas St",
    "sg:city":"San Diego",
    "sg:classifiers":[
        {
            "category":"Personal",
            "subcategory":"Beauty Salon",
            "type":"Services"
        }
    ],
    "sg:phone":"+1 619 985 4238",
    "sg:postcode":"92104",
    "sg:province":"CA",
    "sg:tags":[
        "hair"
    ],
    "sg:website":"www.douglassaboe.com",
    "wof:name":"A Douglas Saboe \u00a0Hair Styling",
    "wof:placetype":"venue"
},
  "geometry": {"coordinates":[-117.13087299999999,32.741085],"type":"Point"}
}