{
  "type": "Feature",
  "properties": {
    "addr:full":"8805 Tyler St Spring Valley CA 91977",
    "addr:housenumber":"8805",
    "addr:postcode":"91977",
    "addr:street":"Tyler St",
    "iso:country":"US",
    "sg:address":"8805 Tyler St",
    "sg:city":"Spring Valley",
    "sg:classifiers":[
        {
            "category":"Recreation",
            "type":"Entertainment"
        }
    ],
    "sg:phone":"+1 619 461 0810",
    "sg:postcode":"91977",
    "sg:province":"CA",
    "sg:tags":[
        "club",
        "membership"
    ],
    "wof:name":"Lemon Grove Sprng Vly Bobby Sx",
    "wof:placetype":"venue"
},
  "geometry": {"coordinates":[-117.006524,32.731109],"type":"Point"}
}