{
  "type": "Feature",
  "properties": {
    "addr:full":"54 E Colorado Pasadena CA 91105",
    "addr:housenumber":"54",
    "addr:postcode":"91105",
    "addr:street":"E Colorado",
    "iso:country":"US",
    "sg:address":"54 E Colorado",
    "sg:city":"Pasadena",
    "sg:classifiers":[
        {
            "category":"Bars & Pubs",
            "subcategory":"Lounge",
            "type":"Food & Drink"
        },
        {
            "category":"Recreation",
            "subcategory":"Dance Hall",
            "type":"Entertainment"
        }
    ],
    "sg:phone":"+1 714 235 1501",
    "sg:postcode":"91105",
    "sg:province":"CA",
    "sg:tags":[
        "club"
    ],
    "wof:name":"Lounge54",
    "wof:placetype":"venue"
},
  "geometry": {"coordinates":[-118.149266,34.145739],"type":"Point"}
}