{
  "type": "Feature",
  "properties": {
    "iso:country":"US",
    "sg:address":"6419 Wilshire Blvd",
    "sg:city":"Los Angeles",
    "sg:classifiers":[
        {
            "category":"Manufacturing",
            "subcategory":"Printing",
            "type":"Manufacturing & Wholesale Goods"
        }
    ],
    "sg:phone":"+1 323 655 5706",
    "sg:postcode":"90048",
    "sg:province":"CA",
    "sg:tags":[
        "publisher"
    ],
    "wof:name":"Airport Marina Office Supplies",
    "wof:placetype":"venue"
},
  "geometry": {"coordinates":[-118.371145,34.06415],"type":"Point"}
}