{
  "type": "Feature",
  "properties": {
    "addr:full":"333 Hegenberger Rd Oakland CA 94621",
    "addr:housenumber":"333",
    "addr:postcode":"94621",
    "addr:street":"Hegenberger Rd",
    "iso:country":"US",
    "sg:address":"333 Hegenberger Rd",
    "sg:city":"Oakland",
    "sg:classifiers":[
        {
            "category":"Organizations",
            "subcategory":"Professional Association",
            "type":"Services"
        }
    ],
    "sg:phone":"+1 510 569 6561",
    "sg:postcode":"94621",
    "sg:province":"CA",
    "wof:name":"Ipa Assn Of America",
    "wof:placetype":"venue"
},
  "geometry": {"coordinates":[-122.19838900000001,37.733378],"type":"Point"}
}