{
  "type": "Feature",
  "properties": {
    "iso:country":"US",
    "sg:address":"431 S Western Ave",
    "sg:city":"Los Angeles",
    "sg:classifiers":[
        {
            "category":"Health Services",
            "subcategory":"Doctor",
            "type":"Services"
        }
    ],
    "sg:phone":"+1 213 383 5784",
    "sg:postcode":"90020",
    "sg:province":"CA",
    "sg:tags":[
        "dentist"
    ],
    "wof:name":"Soo Cha Kang DDS",
    "wof:placetype":"venue"
},
  "geometry": {"coordinates":[-118.309177,34.065884],"type":"Point"}
}