{
  "type": "Feature",
  "properties": {
    "iso:country":"US",
    "sg:address":"632 Castano Ave",
    "sg:city":"Pasadena",
    "sg:classifiers":[
        {
            "category":"Communications",
            "type":"Services"
        }
    ],
    "sg:phone":"+1 626 793 6823",
    "sg:postcode":"91107",
    "sg:province":"CA",
    "sg:tags":[
        "communication"
    ],
    "wof:name":"Velling & Assoc Communication",
    "wof:placetype":"venue"
},
  "geometry": {"coordinates":[-118.090467,34.155918],"type":"Point"}
}