{
  "type": "Feature",
  "properties": {
    "iso:country":"US",
    "sg:address":"418 N Glenoaks Blvd",
    "sg:city":"Burbank",
    "sg:classifiers":[
        {
            "category":"Personal",
            "subcategory":"Tanning Parlor",
            "type":"Services"
        },
        {
            "category":"Sports & Exercise",
            "subcategory":"Gym",
            "type":"Entertainment"
        },
        {
            "category":"Personal",
            "subcategory":"Day Spa",
            "type":"Services"
        }
    ],
    "sg:phone":"+1 323 651 5424",
    "sg:postcode":"91502",
    "sg:province":"CA",
    "sg:website":"www.cabotanlucas.info",
    "wof:name":"Cabo Tan Lucas Tanning Center",
    "wof:placetype":"venue"
},
  "geometry": {"coordinates":[-118.309612,34.185689],"type":"Point"}
}