{
  "type": "Feature",
  "properties": {
    "addr:full":"2725 Pheasant Run St Selma CA 93662",
    "addr:housenumber":"2725",
    "addr:postcode":"93662",
    "addr:street":"Pheasant Run St",
    "iso:country":"US",
    "sg:address":"2725 Pheasant Run St",
    "sg:city":"Selma",
    "sg:classifiers":[
        {
            "category":"Arts & Performance",
            "subcategory":"Theater",
            "type":"Entertainment"
        }
    ],
    "sg:phone":"+1 559 896 5075",
    "sg:postcode":"93662",
    "sg:province":"CA",
    "sg:tags":[
        "live",
        "music"
    ],
    "wof:name":"Green Acre Productions",
    "wof:placetype":"venue"
},
  "geometry": {"coordinates":[-119.624641,36.583815],"type":"Point"}
}