{
  "type": "Feature",
  "properties": {
    "addr:full":"118 W 21st Street Los Angeles CA 90007",
    "addr:housenumber":"118",
    "addr:postcode":"90007",
    "addr:street":"W 21St Street",
    "iso:country":"US",
    "sg:address":"118 W 21st Street",
    "sg:city":"Los Angeles",
    "sg:classifiers":[
        {
            "category":"Shopping",
            "subcategory":"Mobile Phones",
            "type":"Retail Goods"
        }
    ],
    "sg:phone":"+1 213 748 6300",
    "sg:postcode":"90007",
    "sg:province":"CA",
    "wof:name":"E Cellular Products",
    "wof:placetype":"venue"
},
  "geometry": {"coordinates":[-118.266741,34.029376],"type":"Point"}
}