{
  "type": "Feature",
  "properties": {
    "addr:full":"255 Dutton Ave Santa Rosa CA 95407",
    "addr:housenumber":"255",
    "addr:postcode":"95407",
    "addr:street":"Dutton Ave",
    "iso:country":"US",
    "sg:address":"255 Dutton Ave",
    "sg:city":"Santa Rosa",
    "sg:classifiers":[
        {
            "category":"Retail",
            "subcategory":"Auto Repair",
            "type":"Services"
        }
    ],
    "sg:phone":"+1 707 576 8013",
    "sg:postcode":"95407",
    "sg:province":"CA",
    "sg:tags":[
        "repairing",
        "automobile"
    ],
    "wof:name":"Dutton Shell",
    "wof:placetype":"venue"
},
  "geometry": {"coordinates":[-122.72589499999999,38.432081],"type":"Point"}
}