{
  "type": "Feature",
  "properties": {
    "iso:country":"US",
    "sg:address":"2051 Alameda Ave",
    "sg:city":"Ventura",
    "sg:classifiers":[
        {
            "category":"Retail",
            "subcategory":"Car Wash",
            "type":"Services"
        }
    ],
    "sg:phone":"+1 805 658 7943",
    "sg:postcode":"93003",
    "sg:province":"CA",
    "sg:tags":[
        "automobile",
        "detail",
        "clean"
    ],
    "wof:name":"Road Runner Mobile Detailers",
    "wof:placetype":"venue"
},
  "geometry": {"coordinates":[-119.208657,34.253712],"type":"Point"}
}