{
  "type": "Feature",
  "properties": {
    "addr:full":"531 Ohio Ave Richmond CA 94804",
    "addr:housenumber":"531",
    "addr:postcode":"94804",
    "addr:street":"Ohio Ave",
    "iso:country":"US",
    "sg:address":"531 Ohio Ave",
    "sg:city":"Richmond",
    "sg:classifiers":[
        {
            "category":"Manufacturing",
            "subcategory":"Glass & Minerals",
            "type":"Manufacturing & Wholesale Goods"
        }
    ],
    "sg:phone":"+1 510 236 7390",
    "sg:postcode":"94804",
    "sg:province":"CA",
    "sg:tags":[
        "product",
        "mfg"
    ],
    "wof:name":"Carters-Jamese Glass",
    "wof:placetype":"venue"
},
  "geometry": {"coordinates":[-122.364248,37.930904],"type":"Point"}
}