{
  "type": "Feature",
  "properties": {
    "iso:country":"US",
    "sg:address":"416 N Bedford Dr Suite 408",
    "sg:city":"Beverly Hills",
    "sg:classifiers":[
        {
            "category":"Health Services",
            "subcategory":"Dentist",
            "type":"Services"
        }
    ],
    "sg:phone":"+1 310 275 2721",
    "sg:postcode":"90209",
    "sg:province":"CA",
    "wof:name":"Charles Vaziri, DDS",
    "wof:placetype":"venue"
},
  "geometry": {"coordinates":[-118.405306,34.068172],"type":"Point"}
}