{
  "type": "Feature",
  "properties": {
    "iso:country":"US",
    "sg:address":"1050 E Duane Ave",
    "sg:city":"Sunnyvale",
    "sg:classifiers":[
        {
            "category":"Recreation",
            "type":"Entertainment"
        }
    ],
    "sg:phone":"+1 408 773 1330",
    "sg:postcode":"94085",
    "sg:province":"CA",
    "sg:tags":[
        "instruction",
        "golf"
    ],
    "wof:name":"Perpetual Golf",
    "wof:placetype":"venue"
},
  "geometry": {"coordinates":[-121.99708,37.3868],"type":"Point"}
}