{
  "type": "Feature",
  "properties": {
    "addr:full":"928 Franklin St Apt 335 Oakland CA 94607",
    "addr:housenumber":"928;335",
    "addr:postcode":"94607",
    "addr:street":"Franklin St Apt",
    "iso:country":"US",
    "sg:address":"928 Franklin St Apt 335",
    "sg:city":"Oakland",
    "sg:classifiers":[
        {
            "category":"Wholesale",
            "subcategory":"Non-durable Goods",
            "type":"Manufacturing & Wholesale Goods"
        }
    ],
    "sg:phone":"+1 510 839 5283",
    "sg:postcode":"94607",
    "sg:province":"CA",
    "sg:tags":[
        "merchandise-wholesale"
    ],
    "wof:name":"Jr Trading Co",
    "wof:placetype":"venue"
},
  "geometry": {"coordinates":[-122.271987,37.800585],"type":"Point"}
}