{
  "type": "Feature",
  "properties": {
    "iso:country":"US",
    "sg:address":"610 E Evelyn Ave",
    "sg:city":"Sunnyvale",
    "sg:classifiers":[
        {
            "category":"Food & Beverages",
            "subcategory":"Liquor & Beverages",
            "type":"Retail Goods"
        }
    ],
    "sg:phone":"+1 408 739 5545",
    "sg:postcode":"94086",
    "sg:province":"CA",
    "sg:tags":[
        "beer",
        "spirit",
        "wine"
    ],
    "wof:name":"Al's Liquors",
    "wof:placetype":"venue"
},
  "geometry": {"coordinates":[-122.019997,37.373001],"type":"Point"}
}