{
  "type": "Feature",
  "properties": {
    "iso:country":"US",
    "sg:address":"301 E Colorado Blvd",
    "sg:city":"Pasadena",
    "sg:classifiers":[
        {
            "category":"Insurance",
            "subcategory":"Insurance Agent",
            "type":"Services"
        }
    ],
    "sg:phone":"+1 626 795 7575",
    "sg:postcode":"91106",
    "sg:province":"CA",
    "sg:tags":[
        "agency"
    ],
    "wof:name":"Armstrng/Robitaille Insur Svcs",
    "wof:placetype":"venue"
},
  "geometry": {"coordinates":[-118.145093,34.145895],"type":"Point"}
}