{
  "type": "Feature",
  "properties": {
    "addr:full":"1400 E Main St Woodland CA 95776",
    "addr:housenumber":"1400",
    "addr:postcode":"95776",
    "addr:street":"E Main St",
    "iso:country":"US",
    "sg:address":"1400 E Main St",
    "sg:city":"Woodland",
    "sg:classifiers":[
        {
            "category":"Food & Beverages",
            "subcategory":"Groceries & Convenience Stores",
            "type":"Retail Goods"
        }
    ],
    "sg:phone":"+1 530 662 5077",
    "sg:postcode":"95776",
    "sg:province":"CA",
    "wof:name":"Quik Stop",
    "wof:placetype":"venue"
},
  "geometry": {"coordinates":[-121.752967,38.677302],"type":"Point"}
}