{
  "type": "Feature",
  "properties": {
    "addr:full":"1409 W Magnolia Blvd Burbank CA 91506",
    "addr:housenumber":"1409",
    "addr:postcode":"91506",
    "addr:street":"W Magnolia Blvd",
    "iso:country":"US",
    "sg:address":"1409 W Magnolia Blvd",
    "sg:city":"Burbank",
    "sg:classifiers":[
        {
            "category":"Health Services",
            "subcategory":"Health Practitioner",
            "type":"Services"
        }
    ],
    "sg:phone":"+1 818 841 2808",
    "sg:postcode":"91506",
    "sg:province":"CA",
    "sg:tags":[
        "occupational",
        "therapist"
    ],
    "wof:name":"Dynamic Rehabilitation Inc",
    "wof:placetype":"venue"
},
  "geometry": {"coordinates":[-118.324489,34.175462],"type":"Point"}
}