{
  "type": "Feature",
  "properties": {
    "addr:full":"278 Wildwood Ave Rio Dell CA 95562",
    "addr:housenumber":"278",
    "addr:postcode":"95562",
    "addr:street":"Wildwood Ave",
    "iso:country":"US",
    "sg:address":"278 Wildwood Ave",
    "sg:city":"Rio Dell",
    "sg:classifiers":[
        {
            "category":"Real Estate",
            "subcategory":"Real Estate Agent",
            "type":"Services"
        }
    ],
    "sg:phone":"+1 707 764 5042",
    "sg:postcode":"95562",
    "sg:province":"CA",
    "sg:tags":[
        "inspection"
    ],
    "wof:name":"Kemp Inspection Svc",
    "wof:placetype":"venue"
},
  "geometry": {"coordinates":[-124.102801,40.494185],"type":"Point"}
}