{
  "type": "Feature",
  "properties": {
    "iso:country":"US",
    "sg:address":"400 27th Ave",
    "sg:city":"San Francisco",
    "sg:classifiers":[
        {
            "category":"Food & Beverages",
            "subcategory":"Specialty",
            "type":"Retail Goods"
        }
    ],
    "sg:phone":"+1 415 221 3477",
    "sg:postcode":"94121",
    "sg:province":"CA",
    "sg:tags":[
        "health",
        "diet"
    ],
    "sg:website":"www.hri-hrbi.com",
    "wof:name":"Health Resources Intl",
    "wof:placetype":"venue"
},
  "geometry": {"coordinates":[-122.48687700000001,37.779993],"type":"Point"}
}