{
  "type": "Feature",
  "properties": {
    "addr:full":"1251 Palm Canyon Dr Borrego Springs CA 92004",
    "addr:housenumber":"1251",
    "addr:postcode":"92004",
    "addr:street":"Palm Canyon Dr",
    "iso:country":"US",
    "sg:address":"1251 Palm Canyon Dr",
    "sg:city":"Borrego Springs",
    "sg:classifiers":[
        {
            "category":"Professional",
            "type":"Services"
        }
    ],
    "sg:phone":"+1 760 767 5354",
    "sg:postcode":"92004",
    "sg:province":"CA",
    "wof:name":"Sludgebusters",
    "wof:placetype":"venue"
},
  "geometry": {"coordinates":[-116.35155399999999,33.256736],"type":"Point"}
}