{
  "type": "Feature",
  "properties": {
    "iso:country":"US",
    "sg:address":"656 Fresno St",
    "sg:city":"Parlier",
    "sg:classifiers":[
        {
            "category":"Professional",
            "subcategory":"Accounting & Tax Preparation",
            "type":"Services"
        }
    ],
    "sg:phone":"+1 559 646 3501",
    "sg:postcode":"93648",
    "sg:province":"CA",
    "sg:tags":[
        "return",
        "filing"
    ],
    "wof:name":"H & R Block Tax Svc",
    "wof:placetype":"venue"
},
  "geometry": {"coordinates":[-119.526844,36.611321],"type":"Point"}
}