{
  "type": "Feature",
  "properties": {
    "addr:full":"12341 Doherty St Riverside CA 92503",
    "addr:housenumber":"12341",
    "addr:postcode":"92503",
    "addr:street":"Doherty St",
    "iso:country":"US",
    "sg:address":"12341 Doherty St",
    "sg:city":"Riverside",
    "sg:classifiers":[
        {
            "category":"Home & Garden",
            "subcategory":"Home Furnishings",
            "type":"Retail Goods"
        }
    ],
    "sg:phone":"+1 951 734 4531",
    "sg:postcode":"92503",
    "sg:province":"CA",
    "sg:tags":[
        "curtain",
        "made",
        "drapery"
    ],
    "wof:name":"Gory's Draperies",
    "wof:placetype":"venue"
},
  "geometry": {"coordinates":[-117.50110100000001,33.892266],"type":"Point"}
}