{
  "type": "Feature",
  "properties": {
    "iso:country":"US",
    "sg:address":"2021 Mt Diablo Blvd",
    "sg:city":"Walnut Creek",
    "sg:classifiers":[
        {
            "category":"Health Services",
            "subcategory":"Doctor",
            "type":"Services"
        }
    ],
    "sg:phone":"+1 925 685 3020",
    "sg:postcode":"94596",
    "sg:province":"CA",
    "sg:tags":[
        "physician",
        "surgeon"
    ],
    "wof:name":"Neesha Pammi MD",
    "wof:placetype":"venue"
},
  "geometry": {"coordinates":[-122.067724,37.897159],"type":"Point"}
}