{
  "type": "Feature",
  "properties": {
    "iso:country":"US",
    "sg:address":"2 Hangar Way",
    "sg:city":"Watsonville",
    "sg:classifiers":[
        {
            "category":"Food & Beverages",
            "subcategory":"Bakery",
            "type":"Retail Goods"
        }
    ],
    "sg:phone":"+1 831 761 3503",
    "sg:postcode":"95076",
    "sg:province":"CA",
    "sg:tags":[
        "baker"
    ],
    "wof:name":"Wonder Hostess Bakery Thrift",
    "wof:placetype":"venue"
},
  "geometry": {"coordinates":[-121.790951,36.928332],"type":"Point"}
}