{
  "type": "Feature",
  "properties": {
    "addr:full":"522 Main St Brawley CA 92227",
    "addr:housenumber":"522",
    "addr:postcode":"92227",
    "addr:street":"Main St",
    "iso:country":"US",
    "sg:address":"522 Main St",
    "sg:city":"Brawley",
    "sg:classifiers":[
        {
            "category":"Insurance",
            "subcategory":"Insurance Agent",
            "type":"Services"
        }
    ],
    "sg:phone":"+1 760 351 1200",
    "sg:postcode":"92227",
    "sg:province":"CA",
    "wof:name":"Gene Araujo Insurance Broker",
    "wof:placetype":"venue"
},
  "geometry": {"coordinates":[-115.532381,32.97857],"type":"Point"}
}