{
  "type": "Feature",
  "properties": {
    "addr:full":"514 E Main St Visalia CA 93292",
    "addr:housenumber":"514",
    "addr:postcode":"93292",
    "addr:street":"E Main St",
    "iso:country":"US",
    "sg:address":"514 E Main St",
    "sg:city":"Visalia",
    "sg:classifiers":[
        {
            "category":"Shopping",
            "subcategory":"Used Merchandise",
            "type":"Retail Goods"
        }
    ],
    "sg:phone":"+1 559 733 3038",
    "sg:postcode":"93292",
    "sg:province":"CA",
    "sg:tags":[
        "antique"
    ],
    "wof:name":"Main St Mercantile",
    "wof:placetype":"venue"
},
  "geometry": {"coordinates":[-119.285619,36.33026],"type":"Point"}
}