{
  "type": "Feature",
  "properties": {
    "addr:full":"2145 Las Posas Rd Camarillo CA 93010",
    "addr:housenumber":"2145",
    "addr:postcode":"93010",
    "addr:street":"Las Posas Rd",
    "iso:country":"US",
    "sg:address":"2145 Las Posas Rd",
    "sg:city":"Camarillo",
    "sg:classifiers":[
        {
            "category":"Retail",
            "subcategory":"Auto Repair",
            "type":"Services"
        },
        {
            "category":"Government",
            "subcategory":"Office",
            "type":"Public Place"
        }
    ],
    "sg:phone":"+1 805 987 3177",
    "sg:postcode":"93010",
    "sg:province":"CA",
    "sg:tags":[
        "smog",
        "check"
    ],
    "wof:name":"Service One Car Care",
    "wof:placetype":"venue"
},
  "geometry": {"coordinates":[-119.041,34.236099],"type":"Point"}
}