{
  "type": "Feature",
  "properties": {
    "iso:country":"US",
    "sg:address":"735 W 17th St",
    "sg:city":"San Pedro",
    "sg:classifiers":[
        {
            "category":"Building & Trades",
            "subcategory":"Construction",
            "type":"Services"
        }
    ],
    "sg:phone":"+1 310 521 1995",
    "sg:postcode":"90731",
    "sg:province":"CA",
    "sg:tags":[
        "site",
        "clean",
        "contractor"
    ],
    "wof:name":"Johns Construction Hauling &",
    "wof:placetype":"venue"
},
  "geometry": {"coordinates":[-118.293942,33.728725],"type":"Point"}
}