{
  "type": "Feature",
  "properties": {
    "iso:country":"US",
    "sg:address":"706 56th St Ste 210",
    "sg:city":"Sacramento",
    "sg:classifiers":[
        {
            "category":"Communications",
            "subcategory":"Newspaper",
            "type":"Services"
        }
    ],
    "sg:phone":"+1 916 452 6200",
    "sg:postcode":"95819",
    "sg:province":"CA",
    "sg:tags":[
        "print",
        "medium"
    ],
    "sg:website":"www.sacmag.com",
    "wof:name":"Sacramento Magazine",
    "wof:placetype":"venue"
},
  "geometry": {"coordinates":[-121.433786,38.568293],"type":"Point"}
}