{
  "type": "Feature",
  "properties": {
    "addr:full":"2903 Granite Creek Rd Scotts Valley CA 95066",
    "addr:housenumber":"2903",
    "addr:postcode":"95066",
    "addr:street":"Granite Creek Rd",
    "iso:country":"US",
    "sg:address":"2903 Granite Creek Rd",
    "sg:city":"Scotts Valley",
    "sg:classifiers":[
        {
            "category":"Professional",
            "type":"Services"
        }
    ],
    "sg:phone":"+1 831 438 2558",
    "sg:postcode":"95066",
    "sg:province":"CA",
    "sg:tags":[
        "arts",
        "artist"
    ],
    "wof:name":"J Smith Design",
    "wof:placetype":"venue"
},
  "geometry": {"coordinates":[-121.99825300000001,37.05695],"type":"Point"}
}