{
  "type": "Feature",
  "properties": {
    "addr:full":"163 Hannalei Dr Vista CA 92083",
    "addr:housenumber":"163",
    "addr:postcode":"92083",
    "addr:street":"Hannalei Dr",
    "iso:country":"US",
    "sg:address":"163 Hannalei Dr",
    "sg:city":"Vista",
    "sg:classifiers":[
        {
            "category":"Professional",
            "type":"Services"
        }
    ],
    "sg:phone":"+1 760 433 9433",
    "sg:postcode":"92083",
    "sg:province":"CA",
    "wof:name":"Unviersal Woodwork",
    "wof:placetype":"venue"
},
  "geometry": {"coordinates":[-117.214792,33.177422],"type":"Point"}
}