{
  "type": "Feature",
  "properties": {
    "addr:full":"3546 N Humboldt Ave Kerman CA 93630",
    "addr:housenumber":"3546",
    "addr:postcode":"93630",
    "addr:street":"N Humboldt Ave",
    "iso:country":"US",
    "sg:address":"3546 N Humboldt Ave",
    "sg:city":"Kerman",
    "sg:classifiers":[
        {
            "category":"Professional",
            "subcategory":"Accounting & Tax Preparation",
            "type":"Services"
        }
    ],
    "sg:phone":"+1 559 846 8271",
    "sg:postcode":"93630",
    "sg:province":"CA",
    "sg:tags":[
        "accountant"
    ],
    "wof:name":"Bill Strope CPA",
    "wof:placetype":"venue"
},
  "geometry": {"coordinates":[-120.12358,36.79235],"type":"Point"}
}