{
  "type": "Feature",
  "properties": {
    "iso:country":"US",
    "sg:address":"39465 Paseo Padre Pkwy",
    "sg:city":"Fremont",
    "sg:classifiers":[
        {
            "category":"Professional",
            "subcategory":"Lawyer & Legal Services",
            "type":"Services"
        }
    ],
    "sg:phone":"+1 510 471 2162",
    "sg:postcode":"94538",
    "sg:province":"CA",
    "sg:tags":[
        "attorney",
        "practice"
    ],
    "wof:name":"Jo Lynn Gorelick",
    "wof:placetype":"venue"
},
  "geometry": {"coordinates":[-121.976151,37.55101],"type":"Point"}
}