{
  "type": "Feature",
  "properties": {
    "addr:full":"24501 Piute Dr Tehachapi CA 93561",
    "addr:housenumber":"24501",
    "addr:postcode":"93561",
    "addr:street":"Piute Dr",
    "iso:country":"US",
    "sg:address":"24501 Piute Dr",
    "sg:city":"Tehachapi",
    "sg:classifiers":[
        {
            "category":"Real Estate",
            "subcategory":"Real Estate Agent",
            "type":"Services"
        }
    ],
    "sg:phone":"+1 661 821 6561",
    "sg:postcode":"93561",
    "sg:province":"CA",
    "wof:name":"Straight Rate Realtors",
    "wof:placetype":"venue"
},
  "geometry": {"coordinates":[-118.65643,35.173823],"type":"Point"}
}