{
  "type": "Feature",
  "properties": {
    "addr:full":"1730 Geary Blvd San Francisco CA 94115",
    "addr:housenumber":"1730",
    "addr:postcode":"94115",
    "addr:street":"Geary Blvd",
    "iso:country":"US",
    "sg:address":"1730 Geary Blvd",
    "sg:city":"San Francisco",
    "sg:classifiers":[
        {
            "category":"Travel",
            "subcategory":"Travel Agent",
            "type":"Entertainment"
        }
    ],
    "sg:phone":"+1 415 567 1114",
    "sg:postcode":"94115",
    "sg:province":"CA",
    "sg:tags":[
        "agency",
        "bureau"
    ],
    "wof:name":"AKI Travel Svc",
    "wof:placetype":"venue"
},
  "geometry": {"coordinates":[-122.432472,37.784562],"type":"Point"}
}