{
  "type": "Feature",
  "properties": {
    "iso:country":"US",
    "sg:address":"5950 E Harney Ln",
    "sg:city":"Lodi",
    "sg:classifiers":[
        {
            "category":"Farming",
            "subcategory":"Vineyard",
            "type":"Manufacturing & Wholesale Goods"
        }
    ],
    "sg:phone":"+1 209 368 3391",
    "sg:postcode":"95240",
    "sg:province":"CA",
    "sg:tags":[
        "grape"
    ],
    "wof:name":"Joseph O Spano",
    "wof:placetype":"venue"
},
  "geometry": {"coordinates":[-121.246034,38.101241],"type":"Point"}
}