{
  "type": "Feature",
  "properties": {
    "addr:full":"6070 N 1st St Fresno CA 93710",
    "addr:housenumber":"6070",
    "addr:postcode":"93710",
    "addr:street":"N 1St St",
    "iso:country":"US",
    "sg:address":"6070 N 1st St",
    "sg:city":"Fresno",
    "sg:classifiers":[
        {
            "category":"Retail",
            "subcategory":"Self-service Laundry",
            "type":"Services"
        }
    ],
    "sg:phone":"+1 559 438 4070",
    "sg:postcode":"93710",
    "sg:province":"CA",
    "wof:name":"Launderland",
    "wof:placetype":"venue"
},
  "geometry": {"coordinates":[-119.77217,36.824528],"type":"Point"}
}