{
  "type": "Feature",
  "properties": {
    "iso:country":"US",
    "sg:address":"24380 Moulton Parkway",
    "sg:city":"Laguna Hills",
    "sg:classifiers":[
        {
            "category":"Banks & Credit Unions",
            "subcategory":"Bank",
            "type":"Services"
        }
    ],
    "sg:phone":"+1 949 588 7283",
    "sg:postcode":"92637",
    "sg:province":"CA",
    "wof:name":"Home Savings of America",
    "wof:placetype":"venue"
},
  "geometry": {"coordinates":[-117.723251,33.60784],"type":"Point"}
}