{
  "type": "Feature",
  "properties": {
    "iso:country":"US",
    "sg:address":"1321 S Railroad Ave",
    "sg:city":"San Mateo",
    "sg:classifiers":[
        {
            "category":"Retail",
            "subcategory":"Auto Repair",
            "type":"Services"
        }
    ],
    "sg:phone":"+1 650 571 0406",
    "sg:postcode":"94402",
    "sg:province":"CA",
    "wof:name":"Dino Motors",
    "wof:placetype":"venue"
},
  "geometry": {"coordinates":[-122.31199599999999,37.558201],"type":"Point"}
}