{
  "type": "Feature",
  "properties": {
    "iso:country":"US",
    "sg:address":"7252 Remmet Ave",
    "sg:city":"Canoga Park",
    "sg:classifiers":[
        {
            "category":"Professional",
            "type":"Services"
        }
    ],
    "sg:phone":"+1 818 932 8908",
    "sg:postcode":"91303",
    "sg:province":"CA",
    "sg:tags":[
        "establishment"
    ],
    "wof:name":"AMTA",
    "wof:placetype":"venue"
},
  "geometry": {"coordinates":[-118.600204,34.201879],"type":"Point"}
}