{
  "type": "Feature",
  "properties": {
    "addr:full":"545 S Manhattan Pl Los Angeles CA 90020",
    "addr:housenumber":"545",
    "addr:postcode":"90020",
    "addr:street":"S Manhattan Pl",
    "iso:country":"US",
    "sg:address":"545 S Manhattan Pl",
    "sg:city":"Los Angeles",
    "sg:classifiers":[
        {
            "category":"Professional",
            "type":"Services"
        }
    ],
    "sg:phone":"+1 213 381 2706",
    "sg:postcode":"90020",
    "sg:province":"CA",
    "wof:name":"G2k USA Inc",
    "wof:placetype":"venue"
},
  "geometry": {"coordinates":[-118.310417,34.064328],"type":"Point"}
}