{
  "type": "Feature",
  "properties": {
    "addr:full":"807 W Las Tunas Dr San Gabriel CA 91776",
    "addr:housenumber":"807",
    "addr:postcode":"91776",
    "addr:street":"W Las Tunas Dr",
    "iso:country":"US",
    "sg:address":"807 W Las Tunas Dr",
    "sg:city":"San Gabriel",
    "sg:classifiers":[
        {
            "category":"Shopping",
            "subcategory":"Music",
            "type":"Retail Goods"
        }
    ],
    "sg:phone":"+1 626 284 8680",
    "sg:postcode":"91776",
    "sg:province":"CA",
    "sg:tags":[
        "dvd's"
    ],
    "wof:name":"Firelink",
    "wof:placetype":"venue"
},
  "geometry": {"coordinates":[-118.111,34.098701],"type":"Point"}
}