{
  "type": "Feature",
  "properties": {
    "iso:country":"US",
    "sg:address":"610 Newport Center Drive Suite 210",
    "sg:city":"Newport Beach",
    "sg:classifiers":[
        {
            "category":"Professional",
            "subcategory":"Advertising",
            "type":"Services"
        }
    ],
    "sg:postcode":"92660",
    "sg:province":"CA",
    "sg:tags":[
        "marketing",
        "technology",
        "media",
        "internet",
        "software",
        "boomerang",
        "hollywood",
        "musician",
        "artist",
        "distribution",
        "network",
        "entertainment",
        "video"
    ],
    "sg:website":"http://www.eworlde.com/",
    "wof:name":"eWorld Companies",
    "wof:placetype":"venue"
},
  "geometry": {"coordinates":[-117.873126,33.61841],"type":"Point"}
}