{
  "type": "Feature",
  "properties": {
    "addr:full":"819 Ohio Ave Long Beach CA 90804",
    "addr:housenumber":"819",
    "addr:postcode":"90804",
    "addr:street":"Ohio Ave",
    "iso:country":"US",
    "sg:address":"819 Ohio Ave",
    "sg:city":"Long Beach",
    "sg:classifiers":[
        {
            "category":"Freight",
            "type":"Transportation"
        }
    ],
    "sg:phone":"+1 562 882 5590",
    "sg:postcode":"90804",
    "sg:province":"CA",
    "sg:tags":[
        "ship",
        "broker"
    ],
    "wof:name":"Vasile Tudoran Transport",
    "wof:placetype":"venue"
},
  "geometry": {"coordinates":[-118.160123,33.778804],"type":"Point"}
}