{
  "type": "Feature",
  "properties": {
    "addr:full":"3651 Duncan Rd Linden CA 95236",
    "addr:housenumber":"3651",
    "addr:postcode":"95236",
    "addr:street":"Duncan Rd",
    "iso:country":"US",
    "sg:address":"3651 Duncan Rd",
    "sg:city":"Linden",
    "sg:classifiers":[
        {
            "category":"Farming",
            "subcategory":"Orchard",
            "type":"Manufacturing & Wholesale Goods"
        }
    ],
    "sg:phone":"+1 209 887 3622",
    "sg:postcode":"95236",
    "sg:province":"CA",
    "sg:tags":[
        "grove",
        "nut",
        "fruit",
        "tree"
    ],
    "wof:name":"Guadagnolo Farms",
    "wof:placetype":"venue"
},
  "geometry": {"coordinates":[-121.09520999999999,37.997614],"type":"Point"}
}