{
  "type": "Feature",
  "properties": {
    "addr:full":"14652 Pacific Ave Baldwin Park CA 91706",
    "addr:housenumber":"14652",
    "addr:postcode":"91706",
    "addr:street":"Pacific Ave",
    "iso:country":"US",
    "sg:address":"14652 Pacific Ave",
    "sg:city":"Baldwin Park",
    "sg:classifiers":[
        {
            "category":"Health Services",
            "subcategory":"Chiropractor",
            "type":"Services"
        }
    ],
    "sg:phone":"+1 626 960 4866",
    "sg:postcode":"91706",
    "sg:province":"CA",
    "wof:name":"San Gabriel Valley Chiro",
    "wof:placetype":"venue"
},
  "geometry": {"coordinates":[-117.955986,34.08187],"type":"Point"}
}