{
  "type": "Feature",
  "properties": {
    "addr:full":"2145 E Tahquitz Canyon Way Ste 3 Palm Springs CA 92262",
    "addr:housenumber":"2145",
    "addr:postcode":"92262",
    "addr:street":"E Tahquitz Canyon Way Ste 3",
    "iso:country":"US",
    "sg:address":"2145 E Tahquitz Canyon Way Ste 3",
    "sg:city":"Palm Springs",
    "sg:classifiers":[
        {
            "category":"Health Services",
            "subcategory":"Doctor",
            "type":"Services"
        }
    ],
    "sg:phone":"+1 760 323 2517",
    "sg:postcode":"92262",
    "sg:province":"CA",
    "sg:tags":[
        "surgeon",
        "oral"
    ],
    "sg:website":"danielkellerdds.com/Home.html",
    "wof:name":"Daniel R Keller, DDS",
    "wof:placetype":"venue"
},
  "geometry": {"coordinates":[-116.522463,33.822813],"type":"Point"}
}