{
  "type": "Feature",
  "properties": {
    "iso:country":"US",
    "sg:address":"311 S Citrus Ave",
    "sg:city":"West Covina",
    "sg:classifiers":[
        {
            "category":"Education",
            "subcategory":"School",
            "type":"Public Place"
        }
    ],
    "sg:phone":"+1 626 967 7531",
    "sg:postcode":"91791",
    "sg:province":"CA",
    "wof:name":"Christ Lutheran School",
    "wof:placetype":"venue"
},
  "geometry": {"coordinates":[-117.890183,34.069143],"type":"Point"}
}