{
  "type": "Feature",
  "properties": {
    "addr:full":"311 S Citrus Ave West Covina CA 91791",
    "addr:housenumber":"311",
    "addr:postcode":"91791",
    "addr:street":"S Citrus Ave",
    "iso:country":"US",
    "sg:address":"311 S Citrus Ave",
    "sg:city":"West Covina",
    "sg:classifiers":[
        {
            "category":"Education",
            "subcategory":"School",
            "type":"Public Place"
        }
    ],
    "sg:phone":"+1 626 967 7531",
    "sg:postcode":"91791",
    "sg:province":"CA",
    "wof:name":"Christ Lutheran School",
    "wof:placetype":"venue"
},
  "geometry": {"coordinates":[-117.89018299999999,34.069143],"type":"Point"}
}