{
  "type": "Feature",
  "properties": {
    "iso:country":"US",
    "sg:address":"1547 Morton St",
    "sg:city":"Alameda",
    "sg:classifiers":[
        {
            "category":"Building & Trades",
            "subcategory":"Landscaping Services",
            "type":"Services"
        }
    ],
    "sg:phone":"+1 510 523 2552",
    "sg:postcode":"94501",
    "sg:province":"CA",
    "sg:tags":[
        "aged",
        "homes-institutional"
    ],
    "sg:website":"http://www.awayan.com",
    "wof:name":"Wildrylyn Awayan Care Homes",
    "wof:placetype":"venue"
},
  "geometry": {"coordinates":[-122.262072,37.773762],"type":"Point"}
}