{
  "type": "Feature",
  "properties": {
    "iso:country":"US",
    "sg:address":"14617 Victory Blvd",
    "sg:city":"Van Nuys",
    "sg:classifiers":[
        {
            "category":"Professional",
            "type":"Services"
        }
    ],
    "sg:phone":"+1 818 994 4544",
    "sg:postcode":"91411",
    "sg:province":"CA",
    "sg:tags":[
        "establishment"
    ],
    "wof:name":"Markwell Indusrties",
    "wof:placetype":"venue"
},
  "geometry": {"coordinates":[-118.452786,34.186733],"type":"Point"}
}