{
  "type": "Feature",
  "properties": {
    "addr:full":"1305 W Bullard Ave Fresno CA 93711",
    "addr:housenumber":"1305",
    "addr:postcode":"93711",
    "addr:street":"W Bullard Ave",
    "iso:country":"US",
    "sg:address":"1305 W Bullard Ave",
    "sg:city":"Fresno",
    "sg:classifiers":[
        {
            "category":"Professional",
            "type":"Services"
        }
    ],
    "sg:phone":"+1 559 432 6256",
    "sg:postcode":"93711",
    "sg:province":"CA",
    "sg:tags":[
        "establishment"
    ],
    "wof:name":"Aegis Bancorp",
    "wof:placetype":"venue"
},
  "geometry": {"coordinates":[-119.815496,36.822724],"type":"Point"}
}