{
  "type": "Feature",
  "properties": {
    "addr:full":"1042 Country Club Dr Ste 2D Moraga CA 94556",
    "addr:housenumber":"1042",
    "addr:postcode":"94556",
    "addr:street":"Country Club Dr Ste 2D",
    "iso:country":"US",
    "sg:address":"1042 Country Club Dr Ste 2D",
    "sg:city":"Moraga",
    "sg:classifiers":[
        {
            "category":"Insurance",
            "subcategory":"Hazard Insurance",
            "type":"Services"
        }
    ],
    "sg:phone":"+1 925 376 2244",
    "sg:postcode":"94556",
    "sg:province":"CA",
    "sg:website":"http://statefarm.mqgroup.com/url.asp?usr=053416",
    "wof:name":"State Farm Insurance Agent-Mike Rosa",
    "wof:placetype":"venue"
},
  "geometry": {"coordinates":[-122.127044,37.83225],"type":"Point"}
}