{
  "type": "Feature",
  "properties": {
    "addr:full":"111 W Saint John St Ste 400 San Jose CA 95113",
    "addr:housenumber":"111",
    "addr:postcode":"95113",
    "addr:street":"W Saint John St Ste 400",
    "iso:country":"US",
    "sg:address":"111 W Saint John St Ste 400",
    "sg:city":"San Jose",
    "sg:classifiers":[
        {
            "category":"Professional",
            "subcategory":"Lawyer & Legal Services",
            "type":"Services"
        }
    ],
    "sg:phone":"+1 408 287 9001",
    "sg:postcode":"95113",
    "sg:province":"CA",
    "wof:name":"Collins John Marshall PC",
    "wof:placetype":"venue"
},
  "geometry": {"coordinates":[-121.893997,37.3372],"type":"Point"}
}