{
  "type": "Feature",
  "properties": {
    "iso:country":"US",
    "sg:address":"1058 E 1st St",
    "sg:city":"Santa Ana",
    "sg:classifiers":[
        {
            "category":"Real Estate",
            "subcategory":"Real Estate Services",
            "type":"Services"
        }
    ],
    "sg:phone":"+1 714 953 4140",
    "sg:postcode":"92701",
    "sg:province":"CA",
    "sg:tags":[
        "management",
        "property"
    ],
    "wof:name":"Property Management",
    "wof:placetype":"venue"
},
  "geometry": {"coordinates":[-117.856003,33.745499],"type":"Point"}
}