{
  "type": "Feature",
  "properties": {
    "addr:full":"272 Spencer St Monterey CA 93940",
    "addr:housenumber":"272",
    "addr:postcode":"93940",
    "addr:street":"Spencer St",
    "iso:country":"US",
    "sg:address":"272 Spencer St",
    "sg:city":"Monterey",
    "sg:classifiers":[
        {
            "category":"Professional",
            "subcategory":"Business Services",
            "type":"Services"
        }
    ],
    "sg:phone":"+1 831 625 1199",
    "sg:postcode":"93940",
    "sg:province":"CA",
    "sg:tags":[
        "broker",
        "merchandise"
    ],
    "wof:name":"Fabel Trade",
    "wof:placetype":"venue"
},
  "geometry": {"coordinates":[-121.90236,36.608554],"type":"Point"}
}