{
  "type": "Feature",
  "properties": {
    "addr:full":"79919 Country Club Dr Bermuda Dunes CA 92203",
    "addr:housenumber":"79919",
    "addr:postcode":"92203",
    "addr:street":"Country Club Dr",
    "iso:country":"US",
    "sg:address":"79919 Country Club Dr",
    "sg:city":"Bermuda Dunes",
    "sg:classifiers":[
        {
            "category":"Home & Garden",
            "subcategory":"Home Furnishings",
            "type":"Retail Goods"
        }
    ],
    "sg:phone":"+1 760 360 2800",
    "sg:postcode":"92203",
    "sg:province":"CA",
    "sg:tags":[
        "mirror"
    ],
    "sg:website":"www.henrysglass.com",
    "wof:name":"Henry's Glass Co",
    "wof:placetype":"venue"
},
  "geometry": {"coordinates":[-116.283959,33.753466],"type":"Point"}
}