{
  "type": "Feature",
  "properties": {
    "addr:full":"18030 Brookhurst St Ste B Fountain Valley CA 92708",
    "addr:housenumber":"18030",
    "addr:postcode":"92708",
    "addr:street":"Brookhurst St Ste B",
    "iso:country":"US",
    "sg:address":"18030 Brookhurst St Ste B",
    "sg:city":"Fountain Valley",
    "sg:classifiers":[
        {
            "category":"Professional",
            "subcategory":"Lawyer & Legal Services",
            "type":"Services"
        }
    ],
    "sg:phone":"+1 714 963 3116",
    "sg:postcode":"92708",
    "sg:province":"CA",
    "sg:tags":[
        "notary"
    ],
    "wof:name":"Clines Hallmark",
    "wof:placetype":"venue"
},
  "geometry": {"coordinates":[-117.954002,33.701302],"type":"Point"}
}