{
  "type": "Feature",
  "properties": {
    "addr:full":"4443 Poinsettia St San Luis Obispo CA 93401",
    "addr:housenumber":"4443",
    "addr:postcode":"93401",
    "addr:street":"Poinsettia St",
    "iso:country":"US",
    "sg:address":"4443 Poinsettia St",
    "sg:city":"San Luis Obispo",
    "sg:classifiers":[
        {
            "category":"Shopping",
            "subcategory":"Catalog Store",
            "type":"Retail Goods"
        }
    ],
    "sg:phone":"+1 805 454 9470",
    "sg:postcode":"93401",
    "sg:province":"CA",
    "sg:tags":[
        "mail",
        "order"
    ],
    "wof:name":"Baby Banners",
    "wof:placetype":"venue"
},
  "geometry": {"coordinates":[-120.634692,35.245003],"type":"Point"}
}