{
  "type": "Feature",
  "properties": {
    "iso:country":"US",
    "sg:address":"413 Main St",
    "sg:city":"El Segundo",
    "sg:classifiers":[
        {
            "category":"Restaurant",
            "type":"Food & Drink"
        }
    ],
    "sg:phone":"+1 310 615 0979",
    "sg:postcode":"90245",
    "sg:province":"CA",
    "sg:tags":[
        "american",
        "latin"
    ],
    "sg:website":"www.playablancarestaurant.com/",
    "wof:name":"Playa Blanca Peruvian Cuisine",
    "wof:placetype":"venue"
},
  "geometry": {"coordinates":[-118.415964,33.921061],"type":"Point"}
}