{
  "type": "Feature",
  "properties": {
    "iso:country":"US",
    "sg:address":"2610 Central Ave",
    "sg:city":"Union City",
    "sg:classifiers":[
        {
            "category":"Real Estate",
            "subcategory":"Real Estate Agent",
            "type":"Services"
        }
    ],
    "sg:phone":"+1 510 429 7303",
    "sg:postcode":"94587",
    "sg:province":"CA",
    "wof:name":"First Priorty Svc",
    "wof:placetype":"venue"
},
  "geometry": {"coordinates":[-122.039816,37.591383],"type":"Point"}
}