{
  "type": "Feature",
  "properties": {
    "iso:country":"US",
    "sg:address":"2304 McHenry Ave",
    "sg:city":"Modesto",
    "sg:classifiers":[
        {
            "category":"Retail",
            "subcategory":"Animal Services",
            "type":"Services"
        }
    ],
    "sg:phone":"+1 209 571 1250",
    "sg:postcode":"95350",
    "sg:province":"CA",
    "wof:name":"Nancys Dog & Cat Grooming",
    "wof:placetype":"venue"
},
  "geometry": {"coordinates":[-120.99403,37.676667],"type":"Point"}
}