{
  "type": "Feature",
  "properties": {
    "iso:country":"US",
    "sg:address":"6802 Laurelton Ave",
    "sg:city":"Garden Grove",
    "sg:classifiers":[
        {
            "category":"Professional",
            "type":"Services"
        }
    ],
    "sg:phone":"+1 714 898 5870",
    "sg:postcode":"92845",
    "sg:province":"CA",
    "wof:name":"Patgarbone LLC",
    "wof:placetype":"venue"
},
  "geometry": {"coordinates":[-118.013026,33.785831],"type":"Point"}
}