{
  "type": "Feature",
  "properties": {
    "iso:country":"US",
    "sg:address":"333 Alabama St",
    "sg:city":"San Francisco",
    "sg:classifiers":[
        {
            "category":"Shopping",
            "subcategory":"Clothing, Apparel, & Fashions",
            "type":"Retail Goods"
        }
    ],
    "sg:phone":"+1 415 252 4300",
    "sg:postcode":"94110",
    "sg:province":"CA",
    "sg:tags":[
        "designer"
    ],
    "sg:website":"www.timbuk2.com",
    "wof:name":"Timbuk 2 Designs Inc",
    "wof:placetype":"venue"
},
  "geometry": {"coordinates":[-122.41225,37.764622],"type":"Point"}
}