{
  "type": "Feature",
  "properties": {
    "addr:full":"2306 Valleywood Dr San Bruno CA 94066",
    "addr:housenumber":"2306",
    "addr:postcode":"94066",
    "addr:street":"Valleywood Dr",
    "iso:country":"US",
    "sg:address":"2306 Valleywood Dr",
    "sg:city":"San Bruno",
    "sg:classifiers":[
        {
            "category":"Professional",
            "type":"Services"
        }
    ],
    "sg:phone":"+1 650 295 4120",
    "sg:postcode":"94066",
    "sg:province":"CA",
    "wof:name":"Events Coordinator",
    "wof:placetype":"venue"
},
  "geometry": {"coordinates":[-122.443617,37.633696],"type":"Point"}
}