{
  "type": "Feature",
  "properties": {
    "addr:full":"12306 Exposition Blvd Los Angeles CA 90064",
    "addr:housenumber":"12306",
    "addr:postcode":"90064",
    "addr:street":"Exposition Blvd",
    "iso:country":"US",
    "sg:address":"12306 Exposition Blvd",
    "sg:city":"Los Angeles",
    "sg:classifiers":[
        {
            "category":"Building & Trades",
            "subcategory":"Equipment Rental",
            "type":"Services"
        }
    ],
    "sg:phone":"+1 310 979 8173",
    "sg:postcode":"90064",
    "sg:province":"CA",
    "sg:tags":[
        "photographic"
    ],
    "wof:name":"Photographic Rental Svc Inc",
    "wof:placetype":"venue"
},
  "geometry": {"coordinates":[-118.45577900000001,34.030772],"type":"Point"}
}