{
  "type": "Feature",
  "properties": {
    "addr:full":"17640 Foothill Blvd Fontana CA 92335",
    "addr:housenumber":"17640",
    "addr:postcode":"92335",
    "addr:street":"Foothill Blvd",
    "iso:country":"US",
    "sg:address":"17640 Foothill Blvd",
    "sg:city":"Fontana",
    "sg:classifiers":[
        {
            "category":"Real Estate",
            "subcategory":"Real Estate Operator",
            "type":"Services"
        }
    ],
    "sg:phone":"+1 909 822 4244",
    "sg:postcode":"92335",
    "sg:province":"CA",
    "sg:tags":[
        "mobile",
        "home",
        "community"
    ],
    "wof:name":"Rancho LA Fon Mobile Home Park",
    "wof:placetype":"venue"
},
  "geometry": {"coordinates":[-117.421093,34.106754],"type":"Point"}
}