{
  "type": "Feature",
  "properties": {
    "iso:country":"US",
    "sg:address":"202 S Santa Cruz Ave",
    "sg:city":"Modesto",
    "sg:classifiers":[
        {
            "category":"Arts & Performance",
            "subcategory":"Arts Center",
            "type":"Entertainment"
        },
        {
            "category":"Arts & Performance",
            "subcategory":"Dance",
            "type":"Entertainment"
        }
    ],
    "sg:phone":"+1 209 524 1054",
    "sg:postcode":"95354",
    "sg:province":"CA",
    "sg:tags":[
        "performing",
        "instruction",
        "dancing"
    ],
    "wof:name":"Casa Cultural Tradiciones",
    "wof:placetype":"venue"
},
  "geometry": {"coordinates":[-120.97459600000001,37.636792],"type":"Point"}
}