{
  "type": "Feature",
  "properties": {
    "addr:full":"20034 Portero Dr Redding CA 96003",
    "addr:postcode":"20034;96003",
    "addr:street":"Portero Dr",
    "iso:country":"US",
    "sg:address":"20034 Portero Dr",
    "sg:city":"Redding",
    "sg:classifiers":[
        {
            "category":"Farming",
            "subcategory":"Nursery",
            "type":"Manufacturing & Wholesale Goods"
        }
    ],
    "sg:phone":"+1 530 275 4095",
    "sg:postcode":"96003",
    "sg:province":"CA",
    "sg:tags":[
        "ornamental"
    ],
    "wof:name":"Dutch Girl Gardens",
    "wof:placetype":"venue"
},
  "geometry": {"coordinates":[-122.31466,40.653494],"type":"Point"}
}