{
  "type": "Feature",
  "properties": {
    "iso:country":"US",
    "sg:address":"325 Mira Loma Ave",
    "sg:city":"Glendale",
    "sg:classifiers":[
        {
            "category":"Manufacturing",
            "subcategory":"Textiles",
            "type":"Manufacturing & Wholesale Goods"
        }
    ],
    "sg:phone":"+1 818 246 5440",
    "sg:postcode":"91204",
    "sg:province":"CA",
    "sg:tags":[
        "dyeing",
        "dyers-industrial",
        "fabric"
    ],
    "sg:website":"http://www.adyeingart.com",
    "wof:name":"A Dyeing Art",
    "wof:placetype":"venue"
},
  "geometry": {"coordinates":[-118.25623,34.124314],"type":"Point"}
}