{
  "type": "Feature",
  "properties": {
    "addr:full":"15198 Ave 22 Chowchilla CA 93610",
    "addr:housenumber":"15198;22",
    "addr:postcode":"93610",
    "addr:street":"Ave",
    "iso:country":"US",
    "sg:address":"15198 Ave 22",
    "sg:city":"Chowchilla",
    "sg:classifiers":[
        {
            "category":"Professional",
            "type":"Services"
        }
    ],
    "sg:phone":"+1 559 665 1798",
    "sg:postcode":"93610",
    "sg:province":"CA",
    "wof:name":"Camdor Products",
    "wof:placetype":"venue"
},
  "geometry": {"coordinates":[-120.273489,37.068933],"type":"Point"}
}