{
  "type": "Feature",
  "properties": {
    "addr:full":"155 W Bonita Ave San Dimas CA 91773",
    "addr:housenumber":"155",
    "addr:postcode":"91773",
    "addr:street":"W Bonita Ave",
    "iso:country":"US",
    "sg:address":"155 W Bonita Ave",
    "sg:city":"San Dimas",
    "sg:classifiers":[
        {
            "category":"Shopping",
            "subcategory":"Used Merchandise",
            "type":"Retail Goods"
        }
    ],
    "sg:phone":"+1 909 394 0628",
    "sg:postcode":"91773",
    "sg:province":"CA",
    "sg:tags":[
        "antique"
    ],
    "wof:name":"Heart Of The Village Antique",
    "wof:placetype":"venue"
},
  "geometry": {"coordinates":[-117.80917100000001,34.106733],"type":"Point"}
}