{
  "type": "Feature",
  "properties": {
    "addr:full":"1212 Oakland Road #14 San Jose CA 95112",
    "addr:housenumber":"1212",
    "addr:postcode":"95112",
    "addr:street":"Oakland Road # 14 San Jose",
    "iso:country":"US",
    "sg:address":"1212 Oakland Road #14",
    "sg:city":"San Jose",
    "sg:classifiers":[
        {
            "category":"Building & Trades",
            "subcategory":"Construction",
            "type":"Services"
        }
    ],
    "sg:phone":"+1 408 644 4415",
    "sg:postcode":"95112",
    "sg:province":"CA",
    "sg:tags":[
        "contractor"
    ],
    "sg:website":"www.relevantyellow.com/Telephone...",
    "wof:name":"Allied 4 Communications",
    "wof:placetype":"venue"
},
  "geometry": {"coordinates":[-121.890209,37.367326],"type":"Point"}
}