{
  "type": "Feature",
  "properties": {
    "addr:full":"211 E 11th St Merced CA 95341",
    "addr:housenumber":"211",
    "addr:postcode":"95341",
    "addr:street":"E 11Th St",
    "iso:country":"US",
    "sg:address":"211 E 11th St",
    "sg:city":"Merced",
    "sg:classifiers":[
        {
            "category":"Education",
            "subcategory":"School",
            "type":"Public Place"
        }
    ],
    "sg:phone":"+1 209 385 6619",
    "sg:postcode":"95341",
    "sg:province":"CA",
    "wof:name":"Clark Preschool",
    "wof:placetype":"venue"
},
  "geometry": {"coordinates":[-120.476438,37.291322],"type":"Point"}
}