{
  "type": "Feature",
  "properties": {
    "addr:full":"3300 Fernside Blvd Alameda CA 94501",
    "addr:housenumber":"3300",
    "addr:postcode":"94501",
    "addr:street":"Fernside Blvd",
    "iso:country":"US",
    "sg:address":"3300 Fernside Blvd",
    "sg:city":"Alameda",
    "sg:classifiers":[
        {
            "category":"Banks & Credit Unions",
            "subcategory":"Financial Services",
            "type":"Services"
        }
    ],
    "sg:phone":"+1 510 769 9637",
    "sg:postcode":"94501",
    "sg:province":"CA",
    "sg:tags":[
        "trust",
        "investment",
        "real estate"
    ],
    "wof:name":"Light Horse Capital",
    "wof:placetype":"venue"
},
  "geometry": {"coordinates":[-122.225752,37.7599],"type":"Point"}
}