{
  "type": "Feature",
  "properties": {
    "iso:country":"US",
    "sg:address":"3208 N Old Stage Rd",
    "sg:city":"Mount Shasta",
    "sg:classifiers":[
        {
            "category":"Manufacturing",
            "subcategory":"Printing",
            "type":"Manufacturing & Wholesale Goods"
        }
    ],
    "sg:phone":"+1 530 926 1440",
    "sg:postcode":"96067",
    "sg:province":"CA",
    "sg:tags":[
        "promotional"
    ],
    "wof:name":"Advanced Promotional Products",
    "wof:placetype":"venue"
},
  "geometry": {"coordinates":[-122.35316,41.342192],"type":"Point"}
}