{
  "type": "Feature",
  "properties": {
    "iso:country":"US",
    "sg:address":"1471 8th Avenue",
    "sg:city":"San Diego",
    "sg:classifiers":[
        {
            "category":"Real Estate",
            "subcategory":"Real Estate Operator",
            "type":"Services"
        }
    ],
    "sg:phone":"+1 619 239 0064",
    "sg:postcode":"92101",
    "sg:province":"CA",
    "sg:tags":[
        "apartment"
    ],
    "wof:name":"The Heritage",
    "wof:placetype":"venue"
},
  "geometry": {"coordinates":[-117.157597,32.720604],"type":"Point"}
}