{
  "type": "Feature",
  "properties": {
    "addr:full":"16200 Daily Dr Van Nuys CA 91406",
    "addr:housenumber":"16200",
    "addr:postcode":"91406",
    "addr:street":"Daily Dr",
    "iso:country":"US",
    "sg:address":"16200 Daily Dr",
    "sg:city":"Van Nuys",
    "sg:classifiers":[
        {
            "category":"Airport",
            "type":"Transportation"
        }
    ],
    "sg:phone":"+1 818 785 8894",
    "sg:postcode":"91406",
    "sg:province":"CA",
    "sg:tags":[
        "support",
        "airline"
    ],
    "wof:name":"Merle Norman Aviation Div",
    "wof:placetype":"venue"
},
  "geometry": {"coordinates":[-118.487047,34.217071],"type":"Point"}
}