{
  "type": "Feature",
  "properties": {
    "iso:country":"US",
    "sg:address":"13910 Indian Canyon Ln",
    "sg:city":"Poway",
    "sg:classifiers":[
        {
            "category":"Manufacturing",
            "subcategory":"Signs",
            "type":"Manufacturing & Wholesale Goods"
        }
    ],
    "sg:phone":"+1 858 487 2081",
    "sg:postcode":"92064",
    "sg:province":"CA",
    "wof:name":"Bill's Rustic Signs",
    "wof:placetype":"venue"
},
  "geometry": {"coordinates":[-117.030618,33.030519],"type":"Point"}
}