{
  "type": "Feature",
  "properties": {
    "addr:full":"14212 Colfax Hwy Grass Valley CA 95945",
    "addr:housenumber":"14212",
    "addr:postcode":"95945",
    "addr:street":"Colfax Hwy",
    "iso:country":"US",
    "sg:address":"14212 Colfax Hwy",
    "sg:city":"Grass Valley",
    "sg:classifiers":[
        {
            "category":"Building & Trades",
            "subcategory":"Cleaning & Sanitation",
            "type":"Services"
        }
    ],
    "sg:phone":"+1 530 273 5222",
    "sg:postcode":"95945",
    "sg:province":"CA",
    "sg:tags":[
        "window"
    ],
    "wof:name":"Professional Window Cleaning",
    "wof:placetype":"venue"
},
  "geometry": {"coordinates":[-121.00100500000001,39.191281],"type":"Point"}
}