{
  "type": "Feature",
  "properties": {
    "addr:full":"160 Washington Ave Richmond CA 94801",
    "addr:housenumber":"160",
    "addr:postcode":"94801",
    "addr:street":"Washington Ave",
    "iso:country":"US",
    "sg:address":"160 Washington Ave",
    "sg:city":"Richmond",
    "sg:classifiers":[
        {
            "category":"Food & Beverages",
            "subcategory":"Groceries & Convenience Stores",
            "type":"Retail Goods"
        }
    ],
    "sg:phone":"+1 510 233 9044",
    "sg:postcode":"94801",
    "sg:province":"CA",
    "sg:tags":[
        "liquor",
        "grocer"
    ],
    "wof:name":"Point Richmond Market",
    "wof:placetype":"venue"
},
  "geometry": {"coordinates":[-122.385468,37.926591],"type":"Point"}
}