{
  "type": "Feature",
  "properties": {
    "addr:full":"1815 Hawthorne Blvd Redondo Beach CA 90278",
    "addr:housenumber":"1815",
    "addr:postcode":"90278",
    "addr:street":"Hawthorne Blvd",
    "iso:country":"US",
    "sg:address":"1815 Hawthorne Blvd",
    "sg:city":"Redondo Beach",
    "sg:classifiers":[
        {
            "category":"Restaurant",
            "type":"Food & Drink"
        }
    ],
    "sg:menulink":"http://www.allmenus.com/ca/south-bay-cities/216114-mcdonalds/menu/",
    "sg:postcode":"90278",
    "sg:province":"CA",
    "sg:tags":[
        "burger",
        "american"
    ],
    "wof:name":"McDonald's",
    "wof:placetype":"venue"
},
  "geometry": {"coordinates":[-118.35269099999999,33.871535],"type":"Point"}
}