{
  "type": "Feature",
  "properties": {
    "iso:country":"US",
    "sg:address":"14230 Chino Hills Pkwy",
    "sg:city":"Chino Hills",
    "sg:classifiers":[
        {
            "category":"Shopping",
            "subcategory":"Florist",
            "type":"Retail Goods"
        }
    ],
    "sg:phone":"+1 909 590 7676",
    "sg:postcode":"91709",
    "sg:province":"CA",
    "wof:name":"Chino Hills Flowers",
    "wof:placetype":"venue"
},
  "geometry": {"coordinates":[-117.758589,33.995608],"type":"Point"}
}