{
  "type": "Feature",
  "properties": {
    "addr:full":"1820 Cabrillo Hwy N Half Moon Bay CA 94019",
    "addr:housenumber":"1820",
    "addr:postcode":"94019",
    "addr:street":"Cabrillo Hwy N",
    "iso:country":"US",
    "sg:address":"1820 Cabrillo Hwy N",
    "sg:city":"Half Moon Bay",
    "sg:classifiers":[
        {
            "category":"Recreation",
            "type":"Entertainment"
        }
    ],
    "sg:phone":"+1 650 888 5179",
    "sg:postcode":"94019",
    "sg:province":"CA",
    "sg:tags":[
        "stable"
    ],
    "wof:name":"Del Mar Equestrian Ctr",
    "wof:placetype":"venue"
},
  "geometry": {"coordinates":[-122.44521400000001,37.48182],"type":"Point"}
}