{
  "type": "Feature",
  "properties": {
    "iso:country":"US",
    "sg:address":"780 Inland Center Dr",
    "sg:city":"San Bernardino",
    "sg:classifiers":[
        {
            "category":"Home & Garden",
            "subcategory":"Furniture",
            "type":"Retail Goods"
        }
    ],
    "sg:phone":"+1 909 388 1266",
    "sg:postcode":"92408",
    "sg:province":"CA",
    "wof:name":"Wherehouse Furniture",
    "wof:placetype":"venue"
},
  "geometry": {"coordinates":[-117.300833,34.085533],"type":"Point"}
}