{
  "type": "Feature",
  "properties": {
    "iso:country":"US",
    "sg:address":"11930 Heritage Oak Pl",
    "sg:city":"Auburn",
    "sg:classifiers":[
        {
            "category":"Professional",
            "subcategory":"Business Services",
            "type":"Services"
        }
    ],
    "sg:phone":"+1 530 889 1588",
    "sg:postcode":"95603",
    "sg:province":"CA",
    "wof:name":"Gerco Contracting",
    "wof:placetype":"venue"
},
  "geometry": {"coordinates":[-121.098715,38.941157],"type":"Point"}
}