{
  "type": "Feature",
  "properties": {
    "iso:country":"US",
    "sg:address":"2405 Mountain View Rd",
    "sg:city":"El Monte",
    "sg:classifiers":[
        {
            "category":"Autos & Motor Vehicles",
            "subcategory":"Auto Supplies",
            "type":"Retail Goods"
        }
    ],
    "sg:phone":"+1 626 444 9015",
    "sg:postcode":"91733",
    "sg:province":"CA",
    "sg:tags":[
        "automobile",
        "parts"
    ],
    "wof:name":"Equipment Depot Inc",
    "wof:placetype":"venue"
},
  "geometry": {"coordinates":[-118.02879,34.056886],"type":"Point"}
}