{
  "type": "Feature",
  "properties": {
    "iso:country":"US",
    "sg:address":"510 Harbor Blvd",
    "sg:city":"Belmont",
    "sg:classifiers":[
        {
            "category":"Building & Trades",
            "subcategory":"Equipment Rental",
            "type":"Services"
        }
    ],
    "sg:phone":"+1 650 593 1100",
    "sg:postcode":"94002",
    "sg:province":"CA",
    "sg:tags":[
        "contractor"
    ],
    "sg:website":"www.sunbeltrentals.com",
    "wof:name":"Sunbelt Rentals Inc",
    "wof:placetype":"venue"
},
  "geometry": {"coordinates":[-122.268355,37.520391],"type":"Point"}
}