{
  "type": "Feature",
  "properties": {
    "iso:country":"US",
    "sg:address":"2627 Rosemead Blvd",
    "sg:city":"South El Monte",
    "sg:classifiers":[
        {
            "category":"Autos & Motor Vehicles",
            "subcategory":"Automobile Sales",
            "type":"Retail Goods"
        }
    ],
    "sg:phone":"+1 626 383 4859",
    "sg:postcode":"91733",
    "sg:province":"CA",
    "sg:tags":[
        "car",
        "dealer"
    ],
    "wof:name":"D & K Auto Sales",
    "wof:placetype":"venue"
},
  "geometry": {"coordinates":[-118.064355,34.059978],"type":"Point"}
}