{
  "type": "Feature",
  "properties": {
    "iso:country":"US",
    "sg:address":"16484 Victor St",
    "sg:city":"Victorville",
    "sg:classifiers":[
        {
            "category":"Insurance",
            "subcategory":"Insurance Agent",
            "type":"Services"
        },
        {
            "category":"Insurance",
            "subcategory":"Hazard Insurance",
            "type":"Services"
        },
        {
            "category":"Insurance",
            "subcategory":"Title Insurance",
            "type":"Services"
        }
    ],
    "sg:phone":"+1 760 843 1938",
    "sg:postcode":"92395",
    "sg:province":"CA",
    "sg:tags":[
        "business",
        "auto",
        "commercial",
        "homeowner",
        "property",
        "casualty"
    ],
    "sg:website":"http://www.mercuryinsurance.com",
    "wof:name":"Mercury Insurance - Massey Insurance Services",
    "wof:placetype":"venue"
},
  "geometry": {"coordinates":[-117.304428,34.521722],"type":"Point"}
}