{
  "type": "Feature",
  "properties": {
    "iso:country":"US",
    "sg:address":"2800 G St",
    "sg:city":"Merced",
    "sg:classifiers":[
        {
            "category":"Restaurant",
            "type":"Food & Drink"
        }
    ],
    "sg:menulink":"http://www.allmenus.com/ca/merced/74470-pizza-guys/menu/",
    "sg:phone":"+1 209 726 8888",
    "sg:postcode":"95340",
    "sg:province":"CA",
    "sg:tags":[
        "american",
        "pizza"
    ],
    "wof:name":"Pizza Guys",
    "wof:placetype":"venue"
},
  "geometry": {"coordinates":[-120.46963100000001,37.309432],"type":"Point"}
}