{
  "type": "Feature",
  "properties": {
    "addr:full":"2801 Loyola Ct Bakersfield CA 93306",
    "addr:housenumber":"2801",
    "addr:postcode":"93306",
    "addr:street":"Loyola Ct",
    "iso:country":"US",
    "sg:address":"2801 Loyola Ct",
    "sg:city":"Bakersfield",
    "sg:classifiers":[
        {
            "category":"Professional",
            "subcategory":"Accounting & Tax Preparation",
            "type":"Services"
        }
    ],
    "sg:phone":"+1 661 872 0850",
    "sg:postcode":"93306",
    "sg:province":"CA",
    "sg:tags":[
        "bookkeeping",
        "general"
    ],
    "wof:name":"Cns & Assoc",
    "wof:placetype":"venue"
},
  "geometry": {"coordinates":[-118.961562,35.399865],"type":"Point"}
}