{
  "type": "Feature",
  "properties": {
    "addr:full":"16571 Arrow Blvd Fontana CA 92335",
    "addr:housenumber":"16571",
    "addr:postcode":"92335",
    "addr:street":"Arrow Blvd",
    "iso:country":"US",
    "sg:address":"16571 Arrow Blvd",
    "sg:city":"Fontana",
    "sg:classifiers":[
        {
            "category":"Retail",
            "subcategory":"Auto Repair",
            "type":"Services"
        }
    ],
    "sg:phone":"+1 909 350 1114",
    "sg:postcode":"92335",
    "sg:province":"CA",
    "sg:tags":[
        "repairing",
        "automobile"
    ],
    "wof:name":"Bolger Brothers Auto Repair",
    "wof:placetype":"venue"
},
  "geometry": {"coordinates":[-117.441582,34.099267],"type":"Point"}
}