{
  "type": "Feature",
  "properties": {
    "addr:full":"536 Linden Ave Long Beach CA 90802",
    "addr:housenumber":"536",
    "addr:postcode":"90802",
    "addr:street":"Linden Ave",
    "iso:country":"US",
    "sg:address":"536 Linden Ave",
    "sg:city":"Long Beach",
    "sg:classifiers":[
        {
            "category":"Real Estate",
            "subcategory":"Real Estate Operator",
            "type":"Services"
        }
    ],
    "sg:phone":"+1 562 436 1348",
    "sg:postcode":"90802",
    "sg:province":"CA",
    "sg:tags":[
        "apartment"
    ],
    "wof:name":"Patrician Apartments",
    "wof:placetype":"venue"
},
  "geometry": {"coordinates":[-118.185997,33.773499],"type":"Point"}
}