{
  "type": "Feature",
  "properties": {
    "iso:country":"US",
    "sg:address":"1494 Boxwood Ct",
    "sg:city":"San Luis Obispo",
    "sg:classifiers":[
        {
            "category":"Wholesale",
            "subcategory":"Toys & Hobbies",
            "type":"Manufacturing & Wholesale Goods"
        }
    ],
    "sg:phone":"+1 805 541 3371",
    "sg:postcode":"93401",
    "sg:province":"CA",
    "wof:name":"Jls Distributor",
    "wof:placetype":"venue"
},
  "geometry": {"coordinates":[-120.627158,35.249807],"type":"Point"}
}