{
  "type": "Feature",
  "properties": {
    "iso:country":"US",
    "sg:address":"418 Pendleton Way",
    "sg:city":"Oakland",
    "sg:classifiers":[
        {
            "category":"Professional",
            "type":"Services"
        }
    ],
    "sg:phone":"+1 510 567 9865",
    "sg:postcode":"94621",
    "sg:province":"CA",
    "wof:name":"Buyefashion",
    "wof:placetype":"venue"
},
  "geometry": {"coordinates":[-122.200267,37.735866],"type":"Point"}
}