{
  "type": "Feature",
  "properties": {
    "iso:country":"US",
    "sg:address":"3700 W Taylor Rd",
    "sg:city":"Modesto",
    "sg:classifiers":[
        {
            "category":"Farming",
            "subcategory":"Crops",
            "type":"Manufacturing & Wholesale Goods"
        }
    ],
    "sg:phone":"+1 209 537 7341",
    "sg:postcode":"95358",
    "sg:province":"CA",
    "sg:tags":[
        "grove",
        "nut",
        "tree"
    ],
    "wof:name":"Brian Brizendine",
    "wof:placetype":"venue"
},
  "geometry": {"coordinates":[-121.06279000000001,37.536913],"type":"Point"}
}