{
  "type": "Feature",
  "properties": {
    "iso:country":"US",
    "sg:address":"1031 Summit Way",
    "sg:city":"Laguna Beach",
    "sg:classifiers":[
        {
            "category":"Manufacturing",
            "subcategory":"Toys & Sporting Goods",
            "type":"Manufacturing & Wholesale Goods"
        }
    ],
    "sg:phone":"+1 949 494 1472",
    "sg:postcode":"92651",
    "sg:province":"CA",
    "sg:tags":[
        "athletic"
    ],
    "wof:name":"Caden Shapes",
    "wof:placetype":"venue"
},
  "geometry": {"coordinates":[-117.76584800000001,33.533504],"type":"Point"}
}