{
  "type": "Feature",
  "properties": {
    "addr:full":"625 Market Street Suite 800 San Francisco CA 94105",
    "addr:housenumber":"625",
    "addr:postcode":"94105",
    "addr:street":"Market Street Suite 800",
    "iso:country":"US",
    "sg:address":"625 Market Street Suite 800",
    "sg:city":"San Francisco",
    "sg:classifiers":[
        {
            "category":"Professional",
            "subcategory":"Accounting & Tax Preparation",
            "type":"Services"
        }
    ],
    "sg:phone":"+1 415 495 2577",
    "sg:postcode":"94105",
    "sg:province":"CA",
    "sg:tags":[
        "accountant"
    ],
    "wof:name":"Rushakoff Vicki CPA",
    "wof:placetype":"venue"
},
  "geometry": {"coordinates":[-122.401937,37.788833],"type":"Point"}
}