{
  "type": "Feature",
  "properties": {
    "addr:full":"11135 Condor Ave Fountain Valley CA 92708",
    "addr:housenumber":"11135",
    "addr:postcode":"92708",
    "addr:street":"Condor Ave",
    "iso:country":"US",
    "sg:address":"11135 Condor Ave",
    "sg:city":"Fountain Valley",
    "sg:classifiers":[
        {
            "category":"Building & Trades",
            "subcategory":"Construction",
            "type":"Services"
        }
    ],
    "sg:phone":"+1 714 979 5027",
    "sg:postcode":"92708",
    "sg:province":"CA",
    "sg:tags":[
        "fabricator",
        "metal"
    ],
    "wof:name":"Coulson Metal Forming",
    "wof:placetype":"venue"
},
  "geometry": {"coordinates":[-117.933615,33.699604],"type":"Point"}
}