{
  "type": "Feature",
  "properties": {
    "addr:full":"827 Arnold Dr Martinez CA 94553",
    "addr:housenumber":"827",
    "addr:postcode":"94553",
    "addr:street":"Arnold Dr",
    "iso:country":"US",
    "sg:address":"827 Arnold Dr",
    "sg:city":"Martinez",
    "sg:classifiers":[
        {
            "category":"Wholesale",
            "subcategory":"Medical Equipment & Supplies",
            "type":"Manufacturing & Wholesale Goods"
        }
    ],
    "sg:phone":"+1 925 229 2926",
    "sg:postcode":"94553",
    "sg:province":"CA",
    "sg:tags":[
        "disabled",
        "wheelchair",
        "person"
    ],
    "sg:website":"http://www.hoveround.com/",
    "wof:name":"Hoveround Corp.",
    "wof:placetype":"venue"
},
  "geometry": {"coordinates":[-122.117379,37.996738],"type":"Point"}
}