{
  "type": "Feature",
  "properties": {
    "iso:country":"US",
    "sg:address":"455 O'Connor Dr Ste 210",
    "sg:city":"San Jose",
    "sg:classifiers":[
        {
            "category":"Health Services",
            "subcategory":"Doctor",
            "type":"Services"
        }
    ],
    "sg:phone":"+1 408 275 9442",
    "sg:postcode":"95128",
    "sg:province":"CA",
    "sg:tags":[
        "practice",
        "obstetrician",
        "family",
        "gynecologist"
    ],
    "wof:name":"Dr. Grace Yu",
    "wof:placetype":"venue"
},
  "geometry": {"coordinates":[-122.03504,37.341349],"type":"Point"}
}