{
  "type": "Feature",
  "properties": {
    "addr:full":"721 Johnson Ave San Luis Obispo CA 93401",
    "addr:housenumber":"721",
    "addr:postcode":"93401",
    "addr:street":"Johnson Ave",
    "iso:country":"US",
    "sg:address":"721 Johnson Ave",
    "sg:city":"San Luis Obispo",
    "sg:classifiers":[
        {
            "category":"Insurance",
            "subcategory":"Insurance Agent",
            "type":"Services"
        }
    ],
    "sg:phone":"+1 805 544 1922",
    "sg:postcode":"93401",
    "sg:province":"CA",
    "wof:name":"Christian Insurance Office",
    "wof:placetype":"venue"
},
  "geometry": {"coordinates":[-120.65938800000001,35.287341],"type":"Point"}
}