{
  "type": "Feature",
  "properties": {
    "addr:full":"8006 S Central Ave Los Angeles CA 90001",
    "addr:housenumber":"8006",
    "addr:postcode":"90001",
    "addr:street":"S Central Ave",
    "iso:country":"US",
    "sg:address":"8006 S Central Ave",
    "sg:city":"Los Angeles",
    "sg:classifiers":[
        {
            "category":"Food & Beverages",
            "subcategory":"Groceries & Convenience Stores",
            "type":"Retail Goods"
        }
    ],
    "sg:phone":"+1 323 581 9944",
    "sg:postcode":"90001",
    "sg:province":"CA",
    "wof:name":"7 El Fonta Food Market",
    "wof:placetype":"venue"
},
  "geometry": {"coordinates":[-118.25623400000001,33.966485],"type":"Point"}
}