{
  "type": "Feature",
  "properties": {
    "iso:country":"US",
    "sg:address":"4875 Broadway",
    "sg:city":"Sacramento",
    "sg:classifiers":[
        {
            "category":"Social Services",
            "type":"Services"
        },
        {
            "category":"Professional",
            "subcategory":"Detective & Security Services",
            "type":"Services"
        }
    ],
    "sg:phone":"+1 916 874 9471",
    "sg:postcode":"95820",
    "sg:province":"CA",
    "sg:tags":[
        "information",
        "program",
        "bureau",
        "services-information",
        "referral"
    ],
    "wof:name":"In Home Supportive Svc",
    "wof:placetype":"venue"
},
  "geometry": {"coordinates":[-121.450836,38.546732],"type":"Point"}
}