{
  "type": "Feature",
  "properties": {
    "iso:country":"US",
    "sg:address":"15901 Hawthorne Blvd Ste 460",
    "sg:city":"Lawndale",
    "sg:classifiers":[
        {
            "category":"Health Services",
            "subcategory":"Clinic",
            "type":"Services"
        }
    ],
    "sg:phone":"+1 800 268 4420",
    "sg:postcode":"90260",
    "sg:province":"CA",
    "sg:tags":[
        "cannabis"
    ],
    "sg:website":"www.marijuanamedicine.com",
    "wof:name":"Marijuana Medicine Evaluation Centers",
    "wof:placetype":"venue"
},
  "geometry": {"coordinates":[-118.353009,33.88595],"type":"Point"}
}