{
  "type": "Feature",
  "properties": {
    "iso:country":"US",
    "sg:address":"2944 Corvin Dr",
    "sg:city":"Santa Clara",
    "sg:classifiers":[
        {
            "category":"Wholesale",
            "subcategory":"Computers",
            "type":"Manufacturing & Wholesale Goods"
        }
    ],
    "sg:phone":"+1 408 736 3848",
    "sg:postcode":"95051",
    "sg:province":"CA",
    "wof:name":"Mcc Technologies Inc",
    "wof:placetype":"venue"
},
  "geometry": {"coordinates":[-121.988032,37.374181],"type":"Point"}
}