{
  "type": "Feature",
  "properties": {
    "iso:country":"US",
    "sg:address":"1114 Soquel Ave",
    "sg:city":"Santa Cruz",
    "sg:classifiers":[
        {
            "category":"Shopping",
            "subcategory":"Tobacco",
            "type":"Retail Goods"
        }
    ],
    "sg:phone":"+1 831 423 1150",
    "sg:postcode":"95062",
    "sg:province":"CA",
    "sg:tags":[
        "shop"
    ],
    "wof:name":"Ron & Bridgette's Place",
    "wof:placetype":"venue"
},
  "geometry": {"coordinates":[-122.012001,36.979099],"type":"Point"}
}