{
  "type": "Feature",
  "properties": {
    "iso:country":"US",
    "sg:address":"1392 University Ave",
    "sg:city":"Berkeley",
    "sg:classifiers":[
        {
            "category":"Social Services",
            "type":"Services"
        }
    ],
    "sg:phone":"+1 510 849 2824",
    "sg:postcode":"94702",
    "sg:province":"CA",
    "sg:tags":[
        "organization",
        "welfare"
    ],
    "wof:name":"California Autism Foundation",
    "wof:placetype":"venue"
},
  "geometry": {"coordinates":[-122.285006,37.869907],"type":"Point"}
}