{
  "type": "Feature",
  "properties": {
    "addr:full":"225 Nicasio Way Soquel CA 95073",
    "addr:housenumber":"225",
    "addr:postcode":"95073",
    "addr:street":"Nicasio Way",
    "iso:country":"US",
    "sg:address":"225 Nicasio Way",
    "sg:city":"Soquel",
    "sg:classifiers":[
        {
            "category":"Building & Trades",
            "subcategory":"Construction",
            "type":"Services"
        }
    ],
    "sg:phone":"+1 831 423 1609",
    "sg:postcode":"95073",
    "sg:province":"CA",
    "sg:tags":[
        "residential"
    ],
    "wof:name":"Architractor",
    "wof:placetype":"venue"
},
  "geometry": {"coordinates":[-121.95863799999999,37.057052],"type":"Point"}
}