{
  "type": "Feature",
  "properties": {
    "iso:country":"US",
    "sg:address":"430 Doherty Ave",
    "sg:city":"Modesto",
    "sg:classifiers":[
        {
            "category":"Manufacturing",
            "subcategory":"Metals",
            "type":"Manufacturing & Wholesale Goods"
        }
    ],
    "sg:phone":"+1 209 523 7761",
    "sg:postcode":"95354",
    "sg:province":"CA",
    "sg:tags":[
        "can"
    ],
    "wof:name":"Silgan Containers Corp",
    "wof:placetype":"venue"
},
  "geometry": {"coordinates":[-120.95106,37.635447],"type":"Point"}
}