{
  "type": "Feature",
  "properties": {
    "addr:full":"1029 University Ave San Diego CA 92103",
    "addr:housenumber":"1029",
    "addr:postcode":"92103",
    "addr:street":"University Ave",
    "iso:country":"US",
    "sg:address":"1029 University Ave",
    "sg:city":"San Diego",
    "sg:classifiers":[
        {
            "category":"Shopping",
            "subcategory":"Books",
            "type":"Retail Goods"
        }
    ],
    "sg:phone":"+1 619 297 4171",
    "sg:postcode":"92103",
    "sg:province":"CA",
    "sg:tags":[
        "bookstore"
    ],
    "sg:website":"www.obeliskshoppe.com/",
    "wof:name":"Obelisk",
    "wof:placetype":"venue"
},
  "geometry": {"coordinates":[-117.154999,32.748501],"type":"Point"}
}