{
  "type": "Feature",
  "properties": {
    "iso:country":"US",
    "sg:address":"3160 Folsom Blvd",
    "sg:city":"Sacramento",
    "sg:classifiers":[
        {
            "category":"Health Services",
            "subcategory":"Doctor",
            "type":"Services"
        }
    ],
    "sg:phone":"+1 916 733 3333",
    "sg:postcode":"95816",
    "sg:province":"CA",
    "wof:name":"Killeen Thomas E MD",
    "wof:placetype":"venue"
},
  "geometry": {"coordinates":[-121.465771,38.568594],"type":"Point"}
}