{
  "type": "Feature",
  "properties": {
    "addr:full":"249 Fox Hills Mall Culver City CA 90230",
    "addr:housenumber":"249",
    "addr:postcode":"90230",
    "addr:street":"Fox Hills Mall",
    "iso:country":"US",
    "sg:address":"249 Fox Hills Mall",
    "sg:city":"Culver City",
    "sg:classifiers":[
        {
            "category":"Sports & Exercise",
            "subcategory":"Bicycle Rental",
            "type":"Entertainment"
        }
    ],
    "sg:phone":"+1 310 398 9184",
    "sg:postcode":"90230",
    "sg:province":"CA",
    "sg:tags":[
        "wear"
    ],
    "wof:name":"Old Navy 3497",
    "wof:placetype":"venue"
},
  "geometry": {"coordinates":[-118.395009,33.984892],"type":"Point"}
}