{
  "type": "Feature",
  "properties": {
    "iso:country":"US",
    "sg:address":"2439 Bing Pl",
    "sg:city":"Union City",
    "sg:classifiers":[
        {
            "category":"Professional",
            "type":"Services"
        }
    ],
    "sg:phone":"+1 510 471 2646",
    "sg:postcode":"94587",
    "sg:province":"CA",
    "wof:name":"M8it",
    "wof:placetype":"venue"
},
  "geometry": {"coordinates":[-122.02646900000001,37.584869],"type":"Point"}
}