{
  "type": "Feature",
  "properties": {
    "addr:full":"1035 S Olive St Los Angeles CA 90015",
    "addr:housenumber":"1035",
    "addr:postcode":"90015",
    "addr:street":"S Olive St",
    "iso:country":"US",
    "sg:address":"1035 S Olive St",
    "sg:city":"Los Angeles",
    "sg:classifiers":[
        {
            "category":"Manufacturing",
            "subcategory":"Retail Goods",
            "type":"Manufacturing & Wholesale Goods"
        }
    ],
    "sg:phone":"+1 213 748 3818",
    "sg:postcode":"90015",
    "sg:province":"CA",
    "sg:tags":[
        "marking",
        "devices",
        "mfg"
    ],
    "wof:name":"A-M R C Stamp & Sign",
    "wof:placetype":"venue"
},
  "geometry": {"coordinates":[-118.260559,34.041402],"type":"Point"}
}