{
  "type": "Feature",
  "properties": {
    "addr:full":"764 N Mount Vernon Ave San Bernardino CA 92411",
    "addr:housenumber":"764",
    "addr:postcode":"92411",
    "addr:street":"N Mount Vernon Ave",
    "iso:country":"US",
    "sg:address":"764 N Mount Vernon Ave",
    "sg:city":"San Bernardino",
    "sg:classifiers":[
        {
            "category":"Personal",
            "subcategory":"Beauty Salon",
            "type":"Services"
        }
    ],
    "sg:phone":"+1 909 885 4757",
    "sg:postcode":"92411",
    "sg:province":"CA",
    "wof:name":"Pirongis Hair Cuts",
    "wof:placetype":"venue"
},
  "geometry": {"coordinates":[-117.313928,34.113663],"type":"Point"}
}