{
  "type": "Feature",
  "properties": {
    "addr:full":"7737 Highland Avenue Citrus Heights CA 95610",
    "addr:housenumber":"7737",
    "addr:postcode":"95610",
    "addr:street":"Highland Avenue",
    "iso:country":"US",
    "sg:address":"7737 Highland Avenue",
    "sg:city":"Citrus Heights",
    "sg:classifiers":[
        {
            "category":"Social Services",
            "subcategory":"Child Care",
            "type":"Services"
        },
        {
            "category":"Education",
            "subcategory":"Preschool",
            "type":"Public Place"
        },
        {
            "category":"Education",
            "subcategory":"School",
            "type":"Public Place"
        }
    ],
    "sg:phone":"+1 916 725 1780",
    "sg:postcode":"95610",
    "sg:province":"CA",
    "sg:tags":[
        "high",
        "middle",
        "day",
        "elementary"
    ],
    "wof:name":"First Apostolic Church",
    "wof:placetype":"venue"
},
  "geometry": {"coordinates":[-121.279741,38.689366],"type":"Point"}
}