{
  "type": "Feature",
  "properties": {
    "iso:country":"US",
    "sg:address":"447 Battery St",
    "sg:city":"San Francisco",
    "sg:classifiers":[
        {
            "category":"Health Services",
            "subcategory":"Health Practitioner",
            "type":"Services"
        }
    ],
    "sg:phone":"+1 415 837 5992",
    "sg:postcode":"94111",
    "sg:province":"CA",
    "sg:tags":[
        "psychologist"
    ],
    "wof:name":"Dee Haynie PHD",
    "wof:placetype":"venue"
},
  "geometry": {"coordinates":[-122.400547,37.795764],"type":"Point"}
}