{
  "type": "Feature",
  "properties": {
    "addr:full":"1380 N 10th St San Jose CA 95112",
    "addr:housenumber":"1380",
    "addr:postcode":"95112",
    "addr:street":"N 10Th St",
    "iso:country":"US",
    "sg:address":"1380 N 10th St",
    "sg:city":"San Jose",
    "sg:classifiers":[
        {
            "category":"Government",
            "subcategory":"Fire Station",
            "type":"Public Place"
        }
    ],
    "sg:phone":"+1 408 277 4365",
    "sg:postcode":"95112",
    "sg:province":"CA",
    "sg:tags":[
        "department"
    ],
    "sg:website":"www.sjfd.com",
    "wof:name":"San Jose Fire Station 5",
    "wof:placetype":"venue"
},
  "geometry": {"coordinates":[-121.89828199999999,37.363914],"type":"Point"}
}