{
  "type": "Feature",
  "properties": {
    "iso:country":"US",
    "sg:address":"1175 Flying Hill Pl",
    "sg:city":"Diamond Bar",
    "sg:classifiers":[
        {
            "category":"Professional",
            "subcategory":"Business Services",
            "type":"Services"
        }
    ],
    "sg:phone":"+1 213 445 4503",
    "sg:postcode":"91765",
    "sg:province":"CA",
    "sg:tags":[
        "notary"
    ],
    "wof:name":"Express Notaries",
    "wof:placetype":"venue"
},
  "geometry": {"coordinates":[-117.79192,34.034492],"type":"Point"}
}