{
  "type": "Feature",
  "properties": {
    "iso:country":"US",
    "sg:address":"726 S Central Ave",
    "sg:city":"Los Angeles",
    "sg:classifiers":[
        {
            "category":"Wholesale",
            "subcategory":"Fruits & Vegetables",
            "type":"Manufacturing & Wholesale Goods"
        }
    ],
    "sg:phone":"+1 213 489 1161",
    "sg:postcode":"90021",
    "sg:province":"CA",
    "sg:tags":[
        "veggie"
    ],
    "wof:name":"Pito's Produce",
    "wof:placetype":"venue"
},
  "geometry": {"coordinates":[-118.241997,34.035599],"type":"Point"}
}