{
  "type": "Feature",
  "properties": {
    "iso:country":"US",
    "sg:address":"14428 San Pablo Ave",
    "sg:city":"San Pablo",
    "sg:classifiers":[
        {
            "category":"Wholesale",
            "subcategory":"Machinery & Supplies",
            "type":"Manufacturing & Wholesale Goods"
        }
    ],
    "sg:phone":"+1 510 234 1249",
    "sg:postcode":"94806",
    "sg:province":"CA",
    "sg:tags":[
        "equipment",
        "establishment"
    ],
    "wof:name":"Living Color Beauty Supply",
    "wof:placetype":"venue"
},
  "geometry": {"coordinates":[-122.344206,37.966991],"type":"Point"}
}