{
  "type": "Feature",
  "properties": {
    "iso:country":"US",
    "sg:address":"3150 E 29th St",
    "sg:city":"Long Beach",
    "sg:classifiers":[
        {
            "category":"Organizations",
            "subcategory":"Non-profit Organization",
            "type":"Services"
        }
    ],
    "sg:phone":"+1 562 595 6341",
    "sg:postcode":"90806",
    "sg:province":"CA",
    "sg:tags":[
        "service/non-profit",
        "community"
    ],
    "wof:name":"American Red Cross",
    "wof:placetype":"venue"
},
  "geometry": {"coordinates":[-118.153999,33.807098],"type":"Point"}
}