{
  "type": "Feature",
  "properties": {
    "addr:full":"4075 Nelson Ave Atea Concord CA 94520",
    "addr:housenumber":"4075",
    "addr:postcode":"94520",
    "addr:street":"Nelson Ave",
    "iso:country":"US",
    "sg:address":"4075 Nelson Ave Atea",
    "sg:city":"Concord",
    "sg:classifiers":[
        {
            "category":"Retail",
            "subcategory":"Auto Repair",
            "type":"Services"
        }
    ],
    "sg:phone":"+1 866 363 3368",
    "sg:postcode":"94520",
    "sg:province":"CA",
    "sg:tags":[
        "body",
        "automobile",
        "painting",
        "repairing"
    ],
    "wof:name":"Dent Defense Group Inc",
    "wof:placetype":"venue"
},
  "geometry": {"coordinates":[-122.044149,38.010202],"type":"Point"}
}