{
  "type": "Feature",
  "properties": {
    "iso:country":"US",
    "sg:address":"2219 Loma Ave",
    "sg:city":"South El Monte",
    "sg:classifiers":[
        {
            "category":"Wholesale",
            "subcategory":"Auto Parts",
            "type":"Manufacturing & Wholesale Goods"
        }
    ],
    "sg:phone":"+1 626 575 3700",
    "sg:postcode":"91733",
    "sg:province":"CA",
    "sg:tags":[
        "wheel",
        "motor",
        "vehicle"
    ],
    "wof:name":"Cheetah Racing",
    "wof:placetype":"venue"
},
  "geometry": {"coordinates":[-118.06879600000001,34.052437],"type":"Point"}
}