{
  "type": "Feature",
  "properties": {
    "iso:country":"US",
    "sg:address":"3514 Curlew St",
    "sg:city":"San Diego",
    "sg:classifiers":[
        {
            "category":"Real Estate",
            "subcategory":"Real Estate Agent",
            "type":"Services"
        }
    ],
    "sg:phone":"+1 619 298 7232",
    "sg:postcode":"92103",
    "sg:province":"CA",
    "wof:name":"SBAY Properties",
    "wof:placetype":"venue"
},
  "geometry": {"coordinates":[-117.16758,32.741682],"type":"Point"}
}