{
  "type": "Feature",
  "properties": {
    "iso:country":"US",
    "sg:address":"315 S Fortuna Blvd",
    "sg:city":"Fortuna",
    "sg:classifiers":[
        {
            "category":"Real Estate",
            "subcategory":"Real Estate Operator",
            "type":"Services"
        }
    ],
    "sg:phone":"+1 707 725 1144",
    "sg:postcode":"95540",
    "sg:province":"CA",
    "sg:tags":[
        "mobile",
        "home",
        "community"
    ],
    "wof:name":"C M Rentals & Mini Storage",
    "wof:placetype":"venue"
},
  "geometry": {"coordinates":[-124.146582,40.589322],"type":"Point"}
}