{
  "type": "Feature",
  "properties": {
    "iso:country":"US",
    "sg:address":"1410 N Main St",
    "sg:city":"Walnut Creek",
    "sg:classifiers":[
        {
            "category":"Insurance",
            "subcategory":"Insurance Agent",
            "type":"Services"
        }
    ],
    "sg:phone":"+1 925 939 6600",
    "sg:postcode":"94596",
    "sg:province":"CA",
    "wof:name":"Michael Mac Donald Financial",
    "wof:placetype":"venue"
},
  "geometry": {"coordinates":[-122.060986,37.899909],"type":"Point"}
}