{
  "type": "Feature",
  "properties": {
    "addr:full":"506 W Graham Ave Lake Elsinore CA 92530",
    "addr:housenumber":"506",
    "addr:postcode":"92530",
    "addr:street":"W Graham Ave",
    "iso:country":"US",
    "sg:address":"506 W Graham Ave",
    "sg:city":"Lake Elsinore",
    "sg:classifiers":[
        {
            "category":"Banks & Credit Unions",
            "subcategory":"Atm",
            "type":"Services"
        }
    ],
    "sg:phone":"+1 877 285 2582",
    "sg:postcode":"92530",
    "sg:province":"CA",
    "sg:tags":[
        "bankruptcy"
    ],
    "sg:website":"www.bankruptcyattorneylakeelsino...",
    "wof:name":"Saunders Law Firm",
    "wof:placetype":"venue"
},
  "geometry": {"coordinates":[-117.33357599999999,33.669238],"type":"Point"}
}