{
  "type": "Feature",
  "properties": {
    "iso:country":"US",
    "sg:address":"2338 Cll del Mundo",
    "sg:city":"Santa Clara",
    "sg:classifiers":[
        {
            "category":"Professional",
            "type":"Services"
        }
    ],
    "sg:phone":"+1 408 744 1790",
    "sg:postcode":"95054",
    "sg:province":"CA",
    "wof:name":"Centra Technologies Inc",
    "wof:placetype":"venue"
},
  "geometry": {"coordinates":[-121.966972,37.409315],"type":"Point"}
}