{
  "type": "Feature",
  "properties": {
    "addr:full":"428 S Pershing Ave San Bernardino CA 92408",
    "addr:housenumber":"428",
    "addr:postcode":"92408",
    "addr:street":"S Pershing Ave",
    "iso:country":"US",
    "sg:address":"428 S Pershing Ave",
    "sg:city":"San Bernardino",
    "sg:classifiers":[
        {
            "category":"Retail",
            "subcategory":"Auto Repair",
            "type":"Services"
        }
    ],
    "sg:phone":"+1 909 381 0736",
    "sg:postcode":"92408",
    "sg:province":"CA",
    "sg:tags":[
        "wrecker"
    ],
    "wof:name":"Bedrock Towing Inc",
    "wof:placetype":"venue"
},
  "geometry": {"coordinates":[-117.28859799999999,34.095563],"type":"Point"}
}