{
  "type": "Feature",
  "properties": {
    "addr:full":"18400 Vanowen St Reseda CA 91335",
    "addr:postcode":"18400;91335",
    "addr:street":"Vanowen St",
    "iso:country":"US",
    "sg:address":"18400 Vanowen St",
    "sg:city":"Reseda",
    "sg:classifiers":[
        {
            "category":"Food & Beverages",
            "subcategory":"Liquor & Beverages",
            "type":"Retail Goods"
        }
    ],
    "sg:phone":"+1 818 345 8585",
    "sg:postcode":"91335",
    "sg:province":"CA",
    "wof:name":"L & M Liquor Jug",
    "wof:placetype":"venue"
},
  "geometry": {"coordinates":[-118.534744,34.193855],"type":"Point"}
}