{
  "type": "Feature",
  "properties": {
    "iso:country":"US",
    "sg:address":"1588 Oakdale Ct",
    "sg:city":"Fairfield",
    "sg:classifiers":[
        {
            "category":"Health Services",
            "subcategory":"Clinic",
            "type":"Services"
        }
    ],
    "sg:phone":"+1 707 863 8909",
    "sg:postcode":"94534",
    "sg:province":"CA",
    "sg:tags":[
        "specialty",
        "outpatient"
    ],
    "wof:name":"Freedom Reigns",
    "wof:placetype":"venue"
},
  "geometry": {"coordinates":[-122.132885,38.175174],"type":"Point"}
}