{
  "type": "Feature",
  "properties": {
    "iso:country":"US",
    "sg:address":"3 Civic Plz",
    "sg:city":"Newport Beach",
    "sg:classifiers":[
        {
            "category":"Real Estate",
            "subcategory":"Real Estate Agent",
            "type":"Services"
        }
    ],
    "sg:phone":"+1 949 720 3600",
    "sg:postcode":"92660",
    "sg:province":"CA",
    "wof:name":"Southwest Diversified",
    "wof:placetype":"venue"
},
  "geometry": {"coordinates":[-117.876413,33.622148],"type":"Point"}
}