{
  "type": "Feature",
  "properties": {
    "addr:full":"207 E Sierra Ave Fresno CA 93710",
    "addr:housenumber":"207",
    "addr:postcode":"93710",
    "addr:street":"E Sierra Ave",
    "iso:country":"US",
    "sg:address":"207 E Sierra Ave",
    "sg:city":"Fresno",
    "sg:classifiers":[
        {
            "category":"Recreation",
            "subcategory":"Marina",
            "type":"Entertainment"
        }
    ],
    "sg:phone":"+1 559 438 6560",
    "sg:postcode":"93710",
    "sg:province":"CA",
    "sg:tags":[
        "repairing",
        "boat"
    ],
    "wof:name":"Marine Service Ctr",
    "wof:placetype":"venue"
},
  "geometry": {"coordinates":[-119.786422,36.830088],"type":"Point"}
}