{
  "type": "Feature",
  "properties": {
    "iso:country":"US",
    "sg:address":"4750 Cll Quetzal",
    "sg:city":"Camarillo",
    "sg:classifiers":[
        {
            "category":"Communications",
            "type":"Services"
        }
    ],
    "sg:phone":"+1 805 987 2310",
    "sg:postcode":"93012",
    "sg:province":"CA",
    "sg:website":"www.mica-tech.com",
    "wof:name":"Mica-Tech",
    "wof:placetype":"venue"
},
  "geometry": {"coordinates":[-119.007361,34.196945],"type":"Point"}
}