{
  "type": "Feature",
  "properties": {
    "iso:country":"US",
    "sg:address":"753 Parkhill Rd",
    "sg:city":"Danville",
    "sg:classifiers":[
        {
            "category":"Professional",
            "subcategory":"Computer Services",
            "type":"Services"
        }
    ],
    "sg:phone":"+1 925 855 4551",
    "sg:postcode":"94526",
    "sg:province":"CA",
    "sg:tags":[
        "website",
        "design"
    ],
    "wof:name":"Dagaz Solutions",
    "wof:placetype":"venue"
},
  "geometry": {"coordinates":[-121.97192699999999,37.816269],"type":"Point"}
}