{
  "type": "Feature",
  "properties": {
    "addr:full":"2860 State St Carlsbad CA 92008",
    "addr:housenumber":"2860",
    "addr:postcode":"92008",
    "addr:street":"State St",
    "iso:country":"US",
    "sg:address":"2860 State St",
    "sg:city":"Carlsbad",
    "sg:classifiers":[
        {
            "category":"Professional",
            "type":"Services"
        },
        {
            "category":"Food & Beverages",
            "subcategory":"Specialty",
            "type":"Retail Goods"
        }
    ],
    "sg:phone":"+1 760 434 9130",
    "sg:postcode":"92008",
    "sg:province":"CA",
    "sg:tags":[
        "gourmet",
        "shop",
        "product",
        "british"
    ],
    "sg:website":"http://www.bitobritain.com",
    "wof:name":"Bit O'britain",
    "wof:placetype":"venue"
},
  "geometry": {"coordinates":[-117.349881,33.161003],"type":"Point"}
}