{
  "type": "Feature",
  "properties": {
    "addr:full":"2911 Rio Linda Blvd Sacramento CA 95815",
    "addr:housenumber":"2911",
    "addr:postcode":"95815",
    "addr:street":"Rio Linda Blvd",
    "iso:country":"US",
    "sg:address":"2911 Rio Linda Blvd",
    "sg:city":"Sacramento",
    "sg:classifiers":[
        {
            "category":"Organizations",
            "subcategory":"Religious Organization",
            "type":"Services"
        }
    ],
    "sg:phone":"+1 916 925 3696",
    "sg:postcode":"95815",
    "sg:province":"CA",
    "sg:tags":[
        "church"
    ],
    "wof:name":"Faith Tabernacle Church",
    "wof:placetype":"venue"
},
  "geometry": {"coordinates":[-121.44623300000001,38.621806],"type":"Point"}
}