{
  "type": "Feature",
  "properties": {
    "addr:full":"725 W Hammer Ln Stockton CA 95210",
    "addr:housenumber":"725",
    "addr:postcode":"95210",
    "addr:street":"W Hammer Ln",
    "iso:country":"US",
    "sg:address":"725 W Hammer Ln",
    "sg:city":"Stockton",
    "sg:classifiers":[
        {
            "category":"Restaurant",
            "type":"Food & Drink"
        }
    ],
    "sg:menulink":"http://www.allmenus.com/ca/stockton/174559-wendys/menu/",
    "sg:phone":"+1 209 472 0557",
    "sg:postcode":"95210",
    "sg:province":"CA",
    "sg:tags":[
        "burger",
        "american",
        "soup"
    ],
    "wof:name":"Wendy's",
    "wof:placetype":"venue"
},
  "geometry": {"coordinates":[-121.321662,38.021358],"type":"Point"}
}