{
  "type": "Feature",
  "properties": {
    "iso:country":"US",
    "sg:address":"740 Palm Ave",
    "sg:city":"South San Francisco",
    "sg:classifiers":[
        {
            "category":"Professional",
            "type":"Services"
        }
    ],
    "sg:phone":"+1 650 873 0166",
    "sg:postcode":"94080",
    "sg:province":"CA",
    "wof:name":"Kenneth J Weese",
    "wof:placetype":"venue"
},
  "geometry": {"coordinates":[-122.422722,37.659966],"type":"Point"}
}