{
  "type": "Feature",
  "properties": {
    "addr:full":"301 Bonifacio Pl Monterey CA 93940",
    "addr:housenumber":"301",
    "addr:postcode":"93940",
    "addr:street":"Bonifacio Pl",
    "iso:country":"US",
    "sg:address":"301 Bonifacio Pl",
    "sg:city":"Monterey",
    "sg:classifiers":[
        {
            "category":"Personal",
            "subcategory":"Beauty Salon",
            "type":"Services"
        },
        {
            "category":"Personal",
            "subcategory":"Day Spa",
            "type":"Services"
        }
    ],
    "sg:phone":"+1 831 372 4212",
    "sg:postcode":"93940",
    "sg:province":"CA",
    "wof:name":"Monterey Bay Body Works",
    "wof:placetype":"venue"
},
  "geometry": {"coordinates":[-121.89229400000001,36.598649],"type":"Point"}
}