{
  "type": "Feature",
  "properties": {
    "addr:full":"2105 W Middlefield Rd Mountain View CA 94043",
    "addr:housenumber":"2105",
    "addr:postcode":"94043",
    "addr:street":"W Middlefield Rd",
    "iso:country":"US",
    "sg:address":"2105 W Middlefield Rd",
    "sg:city":"Mountain View",
    "sg:classifiers":[
        {
            "category":"Restaurant",
            "type":"Food & Drink"
        }
    ],
    "sg:phone":"+1 650 390 9635",
    "sg:postcode":"94043",
    "sg:province":"CA",
    "wof:name":"Subway Sandwiches & Salads",
    "wof:placetype":"venue"
},
  "geometry": {"coordinates":[-122.093807,37.411551],"type":"Point"}
}