{
  "type": "Feature",
  "properties": {
    "addr:full":"4281 W 3rd St Los Angeles CA 90020",
    "addr:housenumber":"4281",
    "addr:postcode":"90020",
    "addr:street":"W 3Rd St",
    "iso:country":"US",
    "sg:address":"4281 W 3rd St",
    "sg:city":"Los Angeles",
    "sg:classifiers":[
        {
            "category":"Shopping",
            "subcategory":"Musical Instruments",
            "type":"Retail Goods"
        }
    ],
    "sg:phone":"+1 213 385 4149",
    "sg:postcode":"90020",
    "sg:province":"CA",
    "sg:tags":[
        "repair"
    ],
    "wof:name":"Nam's Music",
    "wof:placetype":"venue"
},
  "geometry": {"coordinates":[-118.306692,34.068977],"type":"Point"}
}