{
  "type": "Feature",
  "properties": {
    "iso:country":"US",
    "sg:address":"913 4th St",
    "sg:city":"Santa Rosa",
    "sg:classifiers":[
        {
            "category":"Shopping",
            "subcategory":"Bicycles & Sporting Goods",
            "type":"Retail Goods"
        }
    ],
    "sg:phone":"+1 707 527 9887",
    "sg:postcode":"95404",
    "sg:province":"CA",
    "sg:tags":[
        "tackle",
        "fishing"
    ],
    "wof:name":"Lyle's Tackle & Travel Svc",
    "wof:placetype":"venue"
},
  "geometry": {"coordinates":[-122.707272,38.443612],"type":"Point"}
}