{
  "type": "Feature",
  "properties": {
    "addr:full":"9850 Mission Gorge Rd Santee CA 92071",
    "addr:housenumber":"9850",
    "addr:postcode":"92071",
    "addr:street":"Mission Gorge Rd",
    "iso:country":"US",
    "sg:address":"9850 Mission Gorge Rd",
    "sg:city":"Santee",
    "sg:classifiers":[
        {
            "category":"Shopping",
            "subcategory":"Clothing, Apparel, & Fashions",
            "type":"Retail Goods"
        },
        {
            "category":"Shopping",
            "subcategory":"Party Supplies",
            "type":"Retail Goods"
        }
    ],
    "sg:phone":"+1 619 448 2660",
    "sg:postcode":"92071",
    "sg:province":"CA",
    "sg:tags":[
        "costume"
    ],
    "sg:website":"www.partycity.com",
    "wof:name":"Party City",
    "wof:placetype":"venue"
},
  "geometry": {"coordinates":[-116.98400100000001,32.838699],"type":"Point"}
}