{
  "type": "Feature",
  "properties": {
    "iso:country":"US",
    "sg:address":"1739 3rd St",
    "sg:city":"Lincoln",
    "sg:classifiers":[
        {
            "category":"Home & Garden",
            "subcategory":"Garden Supply",
            "type":"Retail Goods"
        }
    ],
    "sg:phone":"+1 916 223 3617",
    "sg:postcode":"95648",
    "sg:province":"CA",
    "sg:tags":[
        "sprinkler"
    ],
    "wof:name":"Andy's Sprinkler Repair",
    "wof:placetype":"venue"
},
  "geometry": {"coordinates":[-121.30877599999999,38.889069],"type":"Point"}
}