{
  "type": "Feature",
  "properties": {
    "iso:country":"US",
    "sg:address":"3045 N Sunnyside Ave",
    "sg:city":"Fresno",
    "sg:classifiers":[
        {
            "category":"Wholesale",
            "subcategory":"Construction Materials",
            "type":"Manufacturing & Wholesale Goods"
        }
    ],
    "sg:phone":"+1 559 294 8108",
    "sg:postcode":"93727",
    "sg:province":"CA",
    "wof:name":"Stone Designs",
    "wof:placetype":"venue"
},
  "geometry": {"coordinates":[-119.69176,36.778062],"type":"Point"}
}