{
  "type": "Feature",
  "properties": {
    "iso:country":"US",
    "sg:address":"1700 San Andres St",
    "sg:city":"Santa Barbara",
    "sg:classifiers":[
        {
            "category":"Food & Beverages",
            "subcategory":"Groceries & Convenience Stores",
            "type":"Retail Goods"
        }
    ],
    "sg:phone":"+1 805 687 4303",
    "sg:postcode":"93101",
    "sg:province":"CA",
    "sg:tags":[
        "market"
    ],
    "wof:name":"Fernando's Market",
    "wof:placetype":"venue"
},
  "geometry": {"coordinates":[-119.72000199999999,34.421578],"type":"Point"}
}