{
  "type": "Feature",
  "properties": {
    "addr:full":"118 S Beverly Drive Beverly Hills CA 90212",
    "addr:housenumber":"118",
    "addr:postcode":"90212",
    "addr:street":"S Beverly Drive",
    "iso:country":"US",
    "sg:address":"118 S Beverly Drive",
    "sg:city":"Beverly Hills",
    "sg:classifiers":[
        {
            "category":"Professional",
            "subcategory":"Lawyer & Legal Services",
            "type":"Services"
        }
    ],
    "sg:phone":"+1 310 275 9911",
    "sg:postcode":"90212",
    "sg:province":"CA",
    "wof:name":"Simon Mace Stephen",
    "wof:placetype":"venue"
},
  "geometry": {"coordinates":[-118.399064,34.066191],"type":"Point"}
}