{
  "type": "Feature",
  "properties": {
    "addr:full":"17294 Nagpal Ct Los Gatos CA 95030",
    "addr:postcode":"17294;95030",
    "addr:street":"Nagpal Ct",
    "iso:country":"US",
    "sg:address":"17294 Nagpal Ct",
    "sg:city":"Los Gatos",
    "sg:classifiers":[
        {
            "category":"Real Estate",
            "subcategory":"Real Estate Agent",
            "type":"Services"
        }
    ],
    "sg:phone":"+1 408 354 9161",
    "sg:postcode":"95030",
    "sg:province":"CA",
    "wof:name":"Mirassou Properties",
    "wof:placetype":"venue"
},
  "geometry": {"coordinates":[-121.97427500000001,37.24543],"type":"Point"}
}