{
  "type": "Feature",
  "properties": {
    "iso:country":"US",
    "sg:address":"732 Pamplona Ave",
    "sg:city":"Davis",
    "sg:classifiers":[
        {
            "category":"Professional",
            "subcategory":"Testing Lab",
            "type":"Services"
        }
    ],
    "sg:phone":"+1 916 652 8520",
    "sg:postcode":"95616",
    "sg:province":"CA",
    "sg:tags":[
        "electrical",
        "system",
        "power"
    ],
    "wof:name":"Electrical Reliability Svc",
    "wof:placetype":"venue"
},
  "geometry": {"coordinates":[-121.759159,38.566291],"type":"Point"}
}