{
  "type": "Feature",
  "properties": {
    "addr:full":"4251 Ashton Dr Sacramento CA 95864",
    "addr:housenumber":"4251",
    "addr:postcode":"95864",
    "addr:street":"Ashton Dr",
    "iso:country":"US",
    "sg:address":"4251 Ashton Dr",
    "sg:city":"Sacramento",
    "sg:classifiers":[
        {
            "category":"Park",
            "type":"Public Place"
        }
    ],
    "sg:postcode":"95864",
    "sg:province":"CA",
    "wof:name":"Ashton Park",
    "wof:placetype":"venue"
},
  "geometry": {"coordinates":[-121.36326099999999,38.576164],"type":"Point"}
}