{
  "type": "Feature",
  "properties": {
    "addr:full":"9224 Azalea Dr Etna CA 96027",
    "addr:housenumber":"9224",
    "addr:postcode":"96027",
    "addr:street":"Azalea Dr",
    "iso:country":"US",
    "sg:address":"9224 Azalea Dr",
    "sg:city":"Etna",
    "sg:classifiers":[
        {
            "category":"Shopping",
            "subcategory":"Hobbies, Toys, & Games",
            "type":"Retail Goods"
        }
    ],
    "sg:phone":"+1 530 467 5181",
    "sg:postcode":"96027",
    "sg:province":"CA",
    "sg:tags":[
        "basket"
    ],
    "wof:name":"Dorothy's Pine Needle Baskets",
    "wof:placetype":"venue"
},
  "geometry": {"coordinates":[-122.899818,41.35483],"type":"Point"}
}