{
  "type": "Feature",
  "properties": {
    "iso:country":"US",
    "sg:address":"14416 Victory Blvd",
    "sg:city":"Van Nuys",
    "sg:classifiers":[
        {
            "category":"Retail",
            "subcategory":"Repair Shop",
            "type":"Services"
        }
    ],
    "sg:phone":"+1 818 909 7080",
    "sg:postcode":"91401",
    "sg:province":"CA",
    "sg:tags":[
        "equipment",
        "dental",
        "refinishing"
    ],
    "wof:name":"Hayes Handpiece Co",
    "wof:placetype":"venue"
},
  "geometry": {"coordinates":[-118.44842,34.186586],"type":"Point"}
}