{
  "type": "Feature",
  "properties": {
    "iso:country":"US",
    "sg:address":"7 Sierra Gate Plz",
    "sg:city":"Roseville",
    "sg:classifiers":[
        {
            "category":"Education",
            "subcategory":"Vocational School",
            "type":"Public Place"
        }
    ],
    "sg:phone":"+1 916 638 1616",
    "sg:postcode":"95678",
    "sg:province":"CA",
    "wof:name":"Heald Institute of Technology",
    "wof:placetype":"venue"
},
  "geometry": {"coordinates":[-121.266982,38.753209],"type":"Point"}
}