{
  "type": "Feature",
  "properties": {
    "addr:full":"7295 Navajo Rd San Diego CA 92119",
    "addr:housenumber":"7295",
    "addr:postcode":"92119",
    "addr:street":"Navajo Rd",
    "iso:country":"US",
    "sg:address":"7295 Navajo Rd",
    "sg:city":"San Diego",
    "sg:classifiers":[
        {
            "category":"Personal",
            "subcategory":"Beauty Salon",
            "type":"Services"
        }
    ],
    "sg:phone":"+1 619 461 0411",
    "sg:postcode":"92119",
    "sg:province":"CA",
    "wof:name":"Shear Brilliance",
    "wof:placetype":"venue"
},
  "geometry": {"coordinates":[-117.04577999999999,32.803848],"type":"Point"}
}