{
  "type": "Feature",
  "properties": {
    "iso:country":"US",
    "sg:address":"14040 San Antonio Dr",
    "sg:city":"Norwalk",
    "sg:classifiers":[
        {
            "category":"Government",
            "subcategory":"Office",
            "type":"Public Place"
        }
    ],
    "sg:phone":"+1 562 929 5580",
    "sg:postcode":"90650",
    "sg:province":"CA",
    "sg:tags":[
        "city",
        "resource",
        "human"
    ],
    "wof:name":"Norwalk City Senior Action Ctr",
    "wof:placetype":"venue"
},
  "geometry": {"coordinates":[-118.082017,33.902585],"type":"Point"}
}