{
  "type": "Feature",
  "properties": {
    "addr:full":"5074 Santa Monica Blvd Los Angeles CA 90029",
    "addr:housenumber":"5074",
    "addr:postcode":"90029",
    "addr:street":"Santa Monica Blvd",
    "iso:country":"US",
    "sg:address":"5074 Santa Monica Blvd",
    "sg:city":"Los Angeles",
    "sg:classifiers":[
        {
            "category":"Wholesale",
            "subcategory":"Electrical",
            "type":"Manufacturing & Wholesale Goods"
        }
    ],
    "sg:phone":"+1 323 665 8000",
    "sg:postcode":"90029",
    "sg:province":"CA",
    "sg:tags":[
        "equipment",
        "electric",
        "supply"
    ],
    "wof:name":"Fox Wholesale Electric",
    "wof:placetype":"venue"
},
  "geometry": {"coordinates":[-118.300077,34.090749],"type":"Point"}
}