{
  "type": "Feature",
  "properties": {
    "addr:full":"206 5th St Galt CA 95632",
    "addr:housenumber":"206",
    "addr:postcode":"95632",
    "addr:street":"5Th St",
    "iso:country":"US",
    "sg:address":"206 5th St",
    "sg:city":"Galt",
    "sg:classifiers":[
        {
            "category":"Organizations",
            "subcategory":"Professional Association",
            "type":"Services"
        }
    ],
    "sg:phone":"+1 209 745 2529",
    "sg:postcode":"95632",
    "sg:province":"CA",
    "sg:tags":[
        "chambers",
        "commerce"
    ],
    "wof:name":"Galt District Chamber-Commerce",
    "wof:placetype":"venue"
},
  "geometry": {"coordinates":[-121.304321,38.25265],"type":"Point"}
}