{
  "type": "Feature",
  "properties": {
    "addr:full":"24711 Kim Cir Laguna Hills CA 92653",
    "addr:postcode":"24711;92653",
    "addr:street":"Kim Cir",
    "iso:country":"US",
    "sg:address":"24711 Kim Cir",
    "sg:city":"Laguna Hills",
    "sg:classifiers":[
        {
            "category":"Health Services",
            "subcategory":"Clinic",
            "type":"Services"
        }
    ],
    "sg:phone":"+1 949 461 5833",
    "sg:postcode":"92653",
    "sg:province":"CA",
    "sg:tags":[
        "organization",
        "medical",
        "surgical"
    ],
    "wof:name":"Sierra Medical Systems-Orange",
    "wof:placetype":"venue"
},
  "geometry": {"coordinates":[-117.69765099999999,33.604046],"type":"Point"}
}