{
  "type": "Feature",
  "properties": {
    "addr:full":"16225 Harbor Blvd Fountain Valley CA 92708",
    "addr:housenumber":"16225",
    "addr:postcode":"92708",
    "addr:street":"Harbor Blvd",
    "iso:country":"US",
    "sg:address":"16225 Harbor Blvd",
    "sg:city":"Fountain Valley",
    "sg:classifiers":[
        {
            "category":"Shopping",
            "subcategory":"Pharmacy",
            "type":"Retail Goods"
        }
    ],
    "sg:phone":"+1 714 839 3496",
    "sg:postcode":"92708",
    "sg:province":"CA",
    "sg:tags":[
        "drugstore"
    ],
    "wof:name":"Walgreens",
    "wof:placetype":"venue"
},
  "geometry": {"coordinates":[-117.920284,33.727684],"type":"Point"}
}