{
  "type": "Feature",
  "properties": {
    "iso:country":"US",
    "sg:address":"5019 Santa Monica Ave",
    "sg:city":"San Diego",
    "sg:classifiers":[
        {
            "category":"Sports & Exercise",
            "subcategory":"Gym",
            "type":"Entertainment"
        }
    ],
    "sg:phone":"+1 619 222 5085",
    "sg:postcode":"92107",
    "sg:province":"CA",
    "sg:tags":[
        "sp",
        "physical",
        "fitness"
    ],
    "wof:name":"Aikido-Sunset Cliffs Aikido",
    "wof:placetype":"venue"
},
  "geometry": {"coordinates":[-117.251845,32.748514],"type":"Point"}
}