{
  "type": "Feature",
  "properties": {
    "iso:country":"US",
    "sg:address":"17323 Mount Elizabeth Dr",
    "sg:city":"Sonora",
    "sg:classifiers":[
        {
            "category":"Organizations",
            "subcategory":"Professional Association",
            "type":"Services"
        }
    ],
    "sg:phone":"+1 209 586 9312",
    "sg:postcode":"95383",
    "sg:province":"CA",
    "wof:name":"Dogwood Lake Assn",
    "wof:placetype":"venue"
},
  "geometry": {"coordinates":[-120.26012900000001,38.06088],"type":"Point"}
}