{
  "type": "Feature",
  "properties": {
    "iso:country":"US",
    "sg:address":"8200 Kern Ave",
    "sg:city":"Gilroy",
    "sg:classifiers":[
        {
            "category":"Wholesale",
            "subcategory":"Groceries",
            "type":"Manufacturing & Wholesale Goods"
        }
    ],
    "sg:phone":"+1 408 847 1848",
    "sg:postcode":"95020",
    "sg:province":"CA",
    "sg:tags":[
        "food",
        "broker"
    ],
    "wof:name":"Global Produce Exchange",
    "wof:placetype":"venue"
},
  "geometry": {"coordinates":[-121.59162999999999,37.01623],"type":"Point"}
}