{
  "type": "Feature",
  "properties": {
    "iso:country":"US",
    "sg:address":"412 W 6th St",
    "sg:city":"Los Angeles",
    "sg:classifiers":[
        {
            "category":"Shopping",
            "subcategory":"Jewelry",
            "type":"Retail Goods"
        }
    ],
    "sg:phone":"+1 213 892 0512",
    "sg:postcode":"90014",
    "sg:province":"CA",
    "wof:name":"Stargate Jewelry Inc",
    "wof:placetype":"venue"
},
  "geometry": {"coordinates":[-118.253658,34.047609],"type":"Point"}
}