{
  "type": "Feature",
  "properties": {
    "iso:country":"US",
    "sg:address":"225 S Lake Ave",
    "sg:city":"Pasadena",
    "sg:classifiers":[
        {
            "category":"Freight",
            "type":"Transportation"
        }
    ],
    "sg:phone":"+1 626 432 7278",
    "sg:postcode":"91101",
    "sg:province":"CA",
    "sg:tags":[
        "arrangement"
    ],
    "wof:name":"Schaumbond Corporation",
    "wof:placetype":"venue"
},
  "geometry": {"coordinates":[-118.132388,34.141554],"type":"Point"}
}