{
  "type": "Feature",
  "properties": {
    "iso:country":"US",
    "sg:address":"830 Center St",
    "sg:city":"Taft",
    "sg:classifiers":[
        {
            "category":"Food & Beverages",
            "subcategory":"Liquor & Beverages",
            "type":"Retail Goods"
        }
    ],
    "sg:phone":"+1 661 763 3890",
    "sg:postcode":"93268",
    "sg:province":"CA",
    "wof:name":"Quiktrip Liquor & Deli",
    "wof:placetype":"venue"
},
  "geometry": {"coordinates":[-119.46458,35.142776],"type":"Point"}
}