{
  "type": "Feature",
  "properties": {
    "addr:full":"2808 E 54th Street Los Angeles CA 90058",
    "addr:housenumber":"2808",
    "addr:postcode":"90058",
    "addr:street":"E 54Th Street",
    "iso:country":"US",
    "sg:address":"2808 E 54th Street",
    "sg:city":"Los Angeles",
    "sg:classifiers":[
        {
            "category":"Food & Beverages",
            "subcategory":"Groceries & Convenience Stores",
            "type":"Retail Goods"
        }
    ],
    "sg:phone":"+1 323 588 6378",
    "sg:postcode":"90058",
    "sg:province":"CA",
    "wof:name":"Jj Market Wholesale",
    "wof:placetype":"venue"
},
  "geometry": {"coordinates":[-118.219318,33.993588],"type":"Point"}
}