{
  "type": "Feature",
  "properties": {
    "addr:full":"25746 Cervantes Ln Mission Viejo CA 92691",
    "addr:postcode":"25746;92691",
    "addr:street":"Cervantes Ln",
    "iso:country":"US",
    "sg:address":"25746 Cervantes Ln",
    "sg:city":"Mission Viejo",
    "sg:classifiers":[
        {
            "category":"Professional",
            "subcategory":"Business Services",
            "type":"Services"
        }
    ],
    "sg:phone":"+1 949 457 9514",
    "sg:postcode":"92691",
    "sg:province":"CA",
    "sg:tags":[
        "interior",
        "consultant",
        "design",
        "decorator"
    ],
    "wof:name":"August Rose",
    "wof:placetype":"venue"
},
  "geometry": {"coordinates":[-117.668193,33.590107],"type":"Point"}
}