{
  "type": "Feature",
  "properties": {
    "addr:full":"7995 California Avenue # B Fair Oaks CA 95628",
    "addr:housenumber":"7995",
    "addr:postcode":"95628",
    "addr:street":"California Avenue # B",
    "iso:country":"US",
    "sg:address":"7995 California Avenue # B",
    "sg:city":"Fair Oaks",
    "sg:classifiers":[
        {
            "category":"Shopping",
            "subcategory":"Beauty & Cosmetics",
            "type":"Retail Goods"
        }
    ],
    "sg:phone":"+1 916 966 8865",
    "sg:postcode":"95628",
    "sg:province":"CA",
    "sg:tags":[
        "supply"
    ],
    "wof:name":"Dirtie Nellies",
    "wof:placetype":"venue"
},
  "geometry": {"coordinates":[-121.26870599999999,38.642023],"type":"Point"}
}