{
  "type": "Feature",
  "properties": {
    "addr:full":"333 Gellert Blvd Daly City CA 94015",
    "addr:housenumber":"333",
    "addr:postcode":"94015",
    "addr:street":"Gellert Blvd",
    "iso:country":"US",
    "sg:address":"333 Gellert Blvd",
    "sg:city":"Daly City",
    "sg:classifiers":[
        {
            "category":"Health Services",
            "subcategory":"Doctor",
            "type":"Services"
        }
    ],
    "sg:phone":"+1 650 992 1500",
    "sg:postcode":"94015",
    "sg:province":"CA",
    "sg:tags":[
        "dentist"
    ],
    "wof:name":"Douglas K Nakamoto DDS",
    "wof:placetype":"venue"
},
  "geometry": {"coordinates":[-122.469156,37.663886],"type":"Point"}
}