{
  "type": "Feature",
  "properties": {
    "iso:country":"US",
    "sg:address":"640 Grand Ave",
    "sg:city":"Carlsbad",
    "sg:classifiers":[
        {
            "category":"Banks & Credit Unions",
            "subcategory":"Investment Brokerage",
            "type":"Services"
        }
    ],
    "sg:phone":"+1 760 603 8244",
    "sg:postcode":"92008",
    "sg:province":"CA",
    "sg:tags":[
        "consultant",
        "planning",
        "financial"
    ],
    "wof:name":"Kantowitz Engineering Corp",
    "wof:placetype":"venue"
},
  "geometry": {"coordinates":[-117.348583,33.161353],"type":"Point"}
}