{
  "type": "Feature",
  "properties": {
    "addr:full":"2527 1/2 University Ave San Diego CA 92104",
    "addr:housenumber":"2527 1 / 2",
    "addr:postcode":"92104",
    "addr:street":"University Ave",
    "iso:country":"US",
    "sg:address":"2527 1/2 University Ave",
    "sg:city":"San Diego",
    "sg:classifiers":[
        {
            "category":"Shopping",
            "type":"Retail Goods"
        }
    ],
    "sg:phone":"+1 619 296 1622",
    "sg:postcode":"92104",
    "sg:province":"CA",
    "sg:website":"thewaterlady.com",
    "wof:name":"The Water Lady Water-N-Ice Stores",
    "wof:placetype":"venue"
},
  "geometry": {"coordinates":[-117.1371,32.748221],"type":"Point"}
}