{
  "type": "Feature",
  "properties": {
    "iso:country":"US",
    "sg:address":"6235 S Walnut St",
    "sg:city":"Loomis",
    "sg:classifiers":[
        {
            "category":"Organizations",
            "subcategory":"Religious Organization",
            "type":"Services"
        }
    ],
    "sg:phone":"+1 916 652 1193",
    "sg:postcode":"95650",
    "sg:province":"CA",
    "sg:tags":[
        "church"
    ],
    "wof:name":"Church Of The Nazarene",
    "wof:placetype":"venue"
},
  "geometry": {"coordinates":[-121.193569,38.814159],"type":"Point"}
}