{
  "type": "Feature",
  "properties": {
    "iso:country":"US",
    "sg:address":"12309 Prairie Ave",
    "sg:city":"Hawthorne",
    "sg:classifiers":[
        {
            "category":"Bars & Pubs",
            "type":"Food & Drink"
        }
    ],
    "sg:phone":"+1 310 679 7760",
    "sg:postcode":"90250",
    "sg:province":"CA",
    "wof:name":"The Hop Inn",
    "wof:placetype":"venue"
},
  "geometry": {"coordinates":[-118.344002,33.920601],"type":"Point"}
}