{
  "type": "Feature",
  "properties": {
    "iso:country":"US",
    "sg:address":"15934 Hesperian Blvd",
    "sg:city":"San Lorenzo",
    "sg:classifiers":[
        {
            "category":"Building & Trades",
            "subcategory":"Landscaping Services",
            "type":"Services"
        }
    ],
    "sg:phone":"+1 510 884 0911",
    "sg:postcode":"94580",
    "sg:province":"CA",
    "sg:tags":[
        "tree"
    ],
    "wof:name":"Souto Brothers Landscape Cnstr",
    "wof:placetype":"venue"
},
  "geometry": {"coordinates":[-122.12727,37.68028],"type":"Point"}
}