{
  "type": "Feature",
  "properties": {
    "iso:country":"US",
    "sg:address":"726 44th St",
    "sg:city":"San Diego",
    "sg:classifiers":[
        {
            "category":"Organizations",
            "subcategory":"Religious Organization",
            "type":"Services"
        }
    ],
    "sg:phone":"+1 619 263 9191",
    "sg:postcode":"92102",
    "sg:province":"CA",
    "wof:name":"Wat Lao Buddaharam",
    "wof:placetype":"venue"
},
  "geometry": {"coordinates":[-117.099998,32.712898],"type":"Point"}
}