{
  "type": "Feature",
  "properties": {
    "addr:full":"6267 Variel Ave Woodland Hills CA 91367",
    "addr:housenumber":"6267",
    "addr:postcode":"91367",
    "addr:street":"Variel Ave",
    "iso:country":"US",
    "sg:address":"6267 Variel Ave",
    "sg:city":"Woodland Hills",
    "sg:classifiers":[
        {
            "category":"Shopping",
            "subcategory":"Clothing, Apparel, & Fashions",
            "type":"Retail Goods"
        }
    ],
    "sg:phone":"+1 818 992 4701",
    "sg:postcode":"91367",
    "sg:province":"CA",
    "sg:tags":[
        "hosiery"
    ],
    "wof:name":"Martha's Leg Fashions",
    "wof:placetype":"venue"
},
  "geometry": {"coordinates":[-118.59286899999999,34.187135],"type":"Point"}
}