{
  "type": "Feature",
  "properties": {
    "iso:country":"US",
    "sg:address":"2700 Eton Rd",
    "sg:city":"Cambria",
    "sg:classifiers":[
        {
            "category":"Organizations",
            "subcategory":"Religious Organization",
            "type":"Services"
        }
    ],
    "sg:phone":"+1 805 927 3239",
    "sg:postcode":"93428",
    "sg:province":"CA",
    "wof:name":"Episcopal Churches",
    "wof:placetype":"venue"
},
  "geometry": {"coordinates":[-121.074997,35.555099],"type":"Point"}
}