{
  "type": "Feature",
  "properties": {
    "iso:country":"US",
    "sg:address":"1831 V St",
    "sg:city":"Sacramento",
    "sg:classifiers":[
        {
            "category":"Professional",
            "subcategory":"Art Services",
            "type":"Services"
        }
    ],
    "sg:phone":"+1 916 447 2277",
    "sg:postcode":"95818",
    "sg:province":"CA",
    "sg:tags":[
        "graphic",
        "designer"
    ],
    "sg:website":"www.rakela.com",
    "wof:name":"Rakela Co",
    "wof:placetype":"venue"
},
  "geometry": {"coordinates":[-121.487239,38.564022],"type":"Point"}
}