{
  "type": "Feature",
  "properties": {
    "iso:country":"US",
    "sg:address":"30011 Crown Valley Pkwy",
    "sg:city":"Laguna Niguel",
    "sg:classifiers":[
        {
            "category":"Food & Beverages",
            "subcategory":"Groceries & Convenience Stores",
            "type":"Retail Goods"
        }
    ],
    "sg:phone":"+1 949 495 9480",
    "sg:postcode":"92677",
    "sg:province":"CA",
    "wof:name":"Foodmart & Soft Touch-Free Car",
    "wof:placetype":"venue"
},
  "geometry": {"coordinates":[-117.710566,33.527072],"type":"Point"}
}