{
  "type": "Feature",
  "properties": {
    "iso:country":"US",
    "sg:address":"335 N Maple Dr",
    "sg:city":"Beverly Hills",
    "sg:classifiers":[
        {
            "category":"Recreation",
            "type":"Entertainment"
        }
    ],
    "sg:phone":"+1 310 203 9522",
    "sg:postcode":"90210",
    "sg:province":"CA",
    "sg:tags":[
        "ticket"
    ],
    "wof:name":"Luxury Tickets",
    "wof:placetype":"venue"
},
  "geometry": {"coordinates":[-118.393575,34.075115],"type":"Point"}
}