{
  "type": "Feature",
  "properties": {
    "addr:full":"20232 State Rd Cerritos CA 90703",
    "addr:housenumber":"20232",
    "addr:postcode":"ca 90703",
    "addr:street":"State Rd",
    "iso:country":"US",
    "sg:address":"20232 State Rd",
    "sg:city":"Cerritos",
    "sg:classifiers":[
        {
            "category":"Professional",
            "subcategory":"Advertising",
            "type":"Services"
        }
    ],
    "sg:phone":"+1 562 402 8717",
    "sg:postcode":"90703",
    "sg:province":"CA",
    "sg:tags":[
        "counselor"
    ],
    "wof:name":"Robert Wiersema",
    "wof:placetype":"venue"
},
  "geometry": {"coordinates":[-118.09492400000001,33.847934],"type":"Point"}
}