{
  "type": "Feature",
  "properties": {
    "iso:country":"US",
    "sg:address":"1465 Austin Dr",
    "sg:city":"Dixon",
    "sg:classifiers":[
        {
            "category":"Manufacturing",
            "subcategory":"Petroleum Products",
            "type":"Manufacturing & Wholesale Goods"
        }
    ],
    "sg:phone":"+1 707 678 6884",
    "sg:postcode":"95620",
    "sg:province":"CA",
    "sg:tags":[
        "oil",
        "refiner"
    ],
    "wof:name":"Cat Tech Inc",
    "wof:placetype":"venue"
},
  "geometry": {"coordinates":[-121.831256,38.459929],"type":"Point"}
}