{
  "type": "Feature",
  "properties": {
    "addr:full":"1414 Harbour Way South Richmond CA 94804",
    "addr:housenumber":"1414",
    "addr:postcode":"94804",
    "addr:street":"Harbour Way South",
    "iso:country":"US",
    "sg:address":"1414 Harbour Way South",
    "sg:city":"Richmond",
    "sg:classifiers":[
        {
            "category":"Professional",
            "subcategory":"Research",
            "type":"Services"
        }
    ],
    "sg:phone":"+1 408 240 5500",
    "sg:postcode":"94804",
    "sg:province":"CA",
    "sg:website":"http://www.sunpowercorp.com",
    "wof:name":"SunPower Corporation",
    "wof:placetype":"venue"
},
  "geometry": {"coordinates":[-122.35928,37.910851],"type":"Point"}
}