{
  "type": "Feature",
  "properties": {
    "addr:full":"1215 K Street Sacramento CA 95814",
    "addr:housenumber":"1215",
    "addr:postcode":"95814",
    "addr:street":"K Street",
    "iso:country":"US",
    "sg:address":"1215 K Street",
    "sg:city":"Sacramento",
    "sg:classifiers":[
        {
            "category":"Professional",
            "subcategory":"Lawyer & Legal Services",
            "type":"Services"
        }
    ],
    "sg:phone":"+1 916 503 3165",
    "sg:postcode":"95814",
    "sg:province":"CA",
    "wof:name":"Ryan Paul M Atty",
    "wof:placetype":"venue"
},
  "geometry": {"coordinates":[-121.49103100000001,38.578477],"type":"Point"}
}