{
  "type": "Feature",
  "properties": {
    "addr:full":"11712 Orange Blossom Rd Oakdale CA 95361",
    "addr:housenumber":"11712",
    "addr:postcode":"95361",
    "addr:street":"Orange Blossom Rd",
    "iso:country":"US",
    "sg:address":"11712 Orange Blossom Rd",
    "sg:city":"Oakdale",
    "sg:classifiers":[
        {
            "category":"Building & Trades",
            "subcategory":"Construction",
            "type":"Services"
        }
    ],
    "sg:phone":"+1 209 845 9224",
    "sg:postcode":"95361",
    "sg:province":"CA",
    "sg:tags":[
        "excavation",
        "contractor"
    ],
    "wof:name":"Double D Excavating",
    "wof:placetype":"venue"
},
  "geometry": {"coordinates":[-120.777931,37.779159],"type":"Point"}
}