{
  "type": "Feature",
  "properties": {
    "addr:full":"1010 W La Veta Ave Orange CA 92868",
    "addr:housenumber":"1010",
    "addr:postcode":"92868",
    "addr:street":"W La Veta Ave",
    "iso:country":"US",
    "sg:address":"1010 W La Veta Ave",
    "sg:city":"Orange",
    "sg:classifiers":[
        {
            "category":"Community Center",
            "type":"Public Place"
        }
    ],
    "sg:phone":"+1 714 245 1100",
    "sg:postcode":"92868",
    "sg:province":"CA",
    "sg:tags":[
        "medical"
    ],
    "wof:name":"USC Heartburn & Swallowing Center",
    "wof:placetype":"venue"
},
  "geometry": {"coordinates":[-117.863394,33.780182],"type":"Point"}
}