{
  "type": "Feature",
  "properties": {
    "addr:full":"12342 Corby Ave Norwalk CA 90650",
    "addr:housenumber":"12342",
    "addr:postcode":"90650",
    "addr:street":"Corby Ave",
    "iso:country":"US",
    "sg:address":"12342 Corby Ave",
    "sg:city":"Norwalk",
    "sg:classifiers":[
        {
            "category":"Professional",
            "subcategory":"Business Services",
            "type":"Services"
        }
    ],
    "sg:phone":"+1 562 651 1177",
    "sg:postcode":"90650",
    "sg:province":"CA",
    "sg:tags":[
        "repossessing"
    ],
    "wof:name":"Knight Recovery",
    "wof:placetype":"venue"
},
  "geometry": {"coordinates":[-118.08247799999999,33.91897],"type":"Point"}
}