{
  "type": "Feature",
  "properties": {
    "iso:country":"US",
    "sg:address":"638 Main St",
    "sg:city":"Ferndale",
    "sg:classifiers":[
        {
            "category":"Insurance",
            "subcategory":"Insurance Agent",
            "type":"Services"
        }
    ],
    "sg:phone":"+1 707 786 4023",
    "sg:postcode":"95536",
    "sg:province":"CA",
    "wof:name":"Capital Insurance Group",
    "wof:placetype":"venue"
},
  "geometry": {"coordinates":[-124.261675,40.578331],"type":"Point"}
}