{
  "type": "Feature",
  "properties": {
    "addr:full":"1444 W Q St Wilmington CA 90744",
    "addr:housenumber":"1444",
    "addr:postcode":"90744",
    "addr:street":"W Q St",
    "iso:country":"US",
    "sg:address":"1444 W Q St",
    "sg:city":"Wilmington",
    "sg:classifiers":[
        {
            "category":"Sports & Exercise",
            "subcategory":"Sports Center",
            "type":"Entertainment"
        },
        {
            "category":"Retail",
            "subcategory":"Event Space",
            "type":"Services"
        }
    ],
    "sg:phone":"+1 310 549 8323",
    "sg:postcode":"90744",
    "sg:province":"CA",
    "sg:tags":[
        "venue",
        "amateur",
        "team"
    ],
    "sg:website":"www.bgca.org",
    "wof:name":"Boys & Girls Club of Wilmington",
    "wof:placetype":"venue"
},
  "geometry": {"coordinates":[-118.280998,33.794201],"type":"Point"}
}