{
  "type": "Feature",
  "properties": {
    "addr:full":"2933 6th St Riverside CA 92507",
    "addr:housenumber":"2933",
    "addr:postcode":"92507",
    "addr:street":"6Th St",
    "iso:country":"US",
    "sg:address":"2933 6th St",
    "sg:city":"Riverside",
    "sg:classifiers":[
        {
            "category":"Organizations",
            "subcategory":"Religious Organization",
            "type":"Services"
        }
    ],
    "sg:phone":"+1 951 787 9184",
    "sg:postcode":"92507",
    "sg:province":"CA",
    "sg:tags":[
        "church"
    ],
    "wof:name":"Ebenezer Asemblea De Dios",
    "wof:placetype":"venue"
},
  "geometry": {"coordinates":[-117.364783,33.980164],"type":"Point"}
}