{
  "type": "Feature",
  "properties": {
    "iso:country":"US",
    "sg:address":"545 Sandydale Dr",
    "sg:city":"Nipomo",
    "sg:classifiers":[
        {
            "category":"Building & Trades",
            "subcategory":"Landscaping Services",
            "type":"Services"
        }
    ],
    "sg:phone":"+1 805 929 3600",
    "sg:postcode":"93444",
    "sg:province":"CA",
    "sg:tags":[
        "contractor",
        "tree",
        "landscape",
        "removal"
    ],
    "sg:website":"http://www.RicksTreeServiceCC.com",
    "wof:name":"Rick's Tree Service",
    "wof:placetype":"venue"
},
  "geometry": {"coordinates":[-120.493596,35.045065],"type":"Point"}
}