{
  "type": "Feature",
  "properties": {
    "addr:full":"752 Northport Drive West Sacramento CA 95691",
    "addr:housenumber":"752",
    "addr:postcode":"95691",
    "addr:street":"Northport Drive",
    "iso:country":"US",
    "sg:address":"752 Northport Drive",
    "sg:city":"West Sacramento",
    "sg:classifiers":[
        {
            "category":"Shopping",
            "subcategory":"Party Supplies",
            "type":"Retail Goods"
        },
        {
            "category":"Personal",
            "type":"Services"
        }
    ],
    "sg:phone":"+1 916 373 0727",
    "sg:postcode":"95691",
    "sg:province":"CA",
    "sg:tags":[
        "planning",
        "event"
    ],
    "wof:name":"Airplay",
    "wof:placetype":"venue"
},
  "geometry": {"coordinates":[-121.561678,38.581164],"type":"Point"}
}