{
  "type": "Feature",
  "properties": {
    "iso:country":"US",
    "sg:address":"1509 Main St",
    "sg:city":"Napa",
    "sg:classifiers":[
        {
            "category":"Retail",
            "subcategory":"Auto Repair",
            "type":"Services"
        }
    ],
    "sg:phone":"+1 707 224 5566",
    "sg:postcode":"94559",
    "sg:province":"CA",
    "sg:tags":[
        "automobile",
        "smog"
    ],
    "wof:name":"Napa Smog Test Only",
    "wof:placetype":"venue"
},
  "geometry": {"coordinates":[-122.288904,38.303268],"type":"Point"}
}