{
  "type": "Feature",
  "properties": {
    "addr:full":"417 S Reese Pl Burbank CA 91506",
    "addr:housenumber":"417",
    "addr:postcode":"91506",
    "addr:street":"S Reese Pl",
    "iso:country":"US",
    "sg:address":"417 S Reese Pl",
    "sg:city":"Burbank",
    "sg:classifiers":[
        {
            "category":"Professional",
            "subcategory":"Printing & Photocopies",
            "type":"Services"
        }
    ],
    "sg:phone":"+1 818 848 6264",
    "sg:postcode":"91506",
    "sg:province":"CA",
    "sg:tags":[
        "duplicating",
        "copying"
    ],
    "wof:name":"Esp Eddie Sp Productions",
    "wof:placetype":"venue"
},
  "geometry": {"coordinates":[-118.320871,34.163045],"type":"Point"}
}