{
  "type": "Feature",
  "properties": {
    "iso:country":"US",
    "sg:address":"1477 E Washington Blvd",
    "sg:city":"Pasadena",
    "sg:classifiers":[
        {
            "category":"Retail",
            "subcategory":"Auto Repair",
            "type":"Services"
        }
    ],
    "sg:phone":"+1 626 798 4064",
    "sg:postcode":"91104",
    "sg:province":"CA",
    "sg:tags":[
        "automotive"
    ],
    "wof:name":"Hrant Auto Service",
    "wof:placetype":"venue"
},
  "geometry": {"coordinates":[-118.120003,34.169201],"type":"Point"}
}