{
  "type": "Feature",
  "properties": {
    "addr:full":"701 Long Beach Blvd Long Beach CA 90813",
    "addr:housenumber":"701",
    "addr:postcode":"90813",
    "addr:street":"Long Beach Blvd",
    "iso:country":"US",
    "sg:address":"701 Long Beach Blvd",
    "sg:city":"Long Beach",
    "sg:classifiers":[
        {
            "category":"Deli",
            "type":"Food & Drink"
        }
    ],
    "sg:phone":"+1 562 435 6238",
    "sg:postcode":"90813",
    "sg:province":"CA",
    "wof:name":"Tony's Famous French Dips",
    "wof:placetype":"venue"
},
  "geometry": {"coordinates":[-118.19000200000001,33.7756],"type":"Point"}
}