{
  "type": "Feature",
  "properties": {
    "iso:country":"US",
    "sg:address":"10202 Washington Blvd",
    "sg:city":"Culver City",
    "sg:classifiers":[
        {
            "category":"Shopping",
            "subcategory":"Computers & Home Electronics",
            "type":"Retail Goods"
        }
    ],
    "sg:phone":"+1 415 369 6265",
    "sg:postcode":"90232",
    "sg:province":"CA",
    "sg:tags":[
        "high",
        "fidelity",
        "stereophonic"
    ],
    "wof:name":"Home Theater & Automation",
    "wof:placetype":"venue"
},
  "geometry": {"coordinates":[-118.401135,34.01941],"type":"Point"}
}