{
  "type": "Feature",
  "properties": {
    "iso:country":"US",
    "sg:address":"15723 Texaco Ave",
    "sg:city":"Paramount",
    "sg:classifiers":[
        {
            "category":"Freight",
            "type":"Transportation"
        }
    ],
    "sg:phone":"+1 562 634 0366",
    "sg:postcode":"90723",
    "sg:province":"CA",
    "sg:tags":[
        "trucking"
    ],
    "wof:name":"Phoenix PDQ Inc",
    "wof:placetype":"venue"
},
  "geometry": {"coordinates":[-118.171924,33.890384],"type":"Point"}
}