{
  "type": "Feature",
  "properties": {
    "iso:country":"US",
    "sg:address":"4009 W Magnolia Blvd",
    "sg:city":"Burbank",
    "sg:classifiers":[
        {
            "category":"Personal",
            "subcategory":"Beauty Salon",
            "type":"Services"
        }
    ],
    "sg:phone":"+1 818 562 1754",
    "sg:postcode":"91505",
    "sg:province":"CA",
    "wof:name":"Moteaze Hair Design",
    "wof:placetype":"venue"
},
  "geometry": {"coordinates":[-118.350977,34.16661],"type":"Point"}
}