{
  "type": "Feature",
  "properties": {
    "iso:country":"US",
    "sg:address":"2059 Mt Diablo Blvd",
    "sg:city":"Walnut Creek",
    "sg:classifiers":[
        {
            "category":"Real Estate",
            "subcategory":"Real Estate Agent",
            "type":"Services"
        }
    ],
    "sg:phone":"+1 925 935 7050",
    "sg:postcode":"94596",
    "sg:province":"CA",
    "sg:tags":[
        "management"
    ],
    "wof:name":"Ritchie Commercial",
    "wof:placetype":"venue"
},
  "geometry": {"coordinates":[-122.07000600000001,37.8964],"type":"Point"}
}