{
  "type": "Feature",
  "properties": {
    "addr:full":"2010 Any CoffeeShop San Francisco CA 94109",
    "addr:housenumber":"2010",
    "addr:postcode":"94109",
    "addr:street":"Any Coffeeshop",
    "iso:country":"US",
    "sg:address":"2010 Any CoffeeShop",
    "sg:city":"San Francisco",
    "sg:classifiers":[
        {
            "category":"Professional",
            "subcategory":"Computer Services",
            "type":"Services"
        }
    ],
    "sg:phone":"+1 415 713 3285",
    "sg:postcode":"94109",
    "sg:province":"CA",
    "sg:tags":[
        "gamification",
        "gamify"
    ],
    "sg:website":"http://www.gamify.com",
    "wof:name":"Gamify",
    "wof:placetype":"venue"
},
  "geometry": {"coordinates":[-122.401571,37.787096],"type":"Point"}
}