{
  "type": "Feature",
  "properties": {
    "addr:full":"543 S Murphy Avenue Sunnyvale CA 94086",
    "addr:housenumber":"543",
    "addr:postcode":"94086",
    "addr:street":"S Murphy Avenue",
    "iso:country":"US",
    "sg:address":"543 S Murphy Avenue",
    "sg:city":"Sunnyvale",
    "sg:classifiers":[
        {
            "category":"Professional",
            "subcategory":"Lawyer & Legal Services",
            "type":"Services"
        }
    ],
    "sg:phone":"+1 408 739 1300",
    "sg:postcode":"94086",
    "sg:province":"CA",
    "sg:tags":[
        "notary"
    ],
    "wof:name":"Whitfield Wendell L",
    "wof:placetype":"venue"
},
  "geometry": {"coordinates":[-122.032388,37.369561],"type":"Point"}
}