{
  "type": "Feature",
  "properties": {
    "addr:full":"2646 E Ave Q Palmdale CA 93550",
    "addr:housenumber":"2646",
    "addr:postcode":"ca 93550",
    "addr:street":"E Ave Q",
    "iso:country":"US",
    "sg:address":"2646 E Ave Q",
    "sg:city":"Palmdale",
    "sg:classifiers":[
        {
            "category":"Organizations",
            "subcategory":"Religious Organization",
            "type":"Services"
        }
    ],
    "sg:phone":"+1 661 575 0248",
    "sg:postcode":"93550",
    "sg:province":"CA",
    "sg:tags":[
        "church"
    ],
    "wof:name":"Palmdale Landmark Missionary",
    "wof:placetype":"venue"
},
  "geometry": {"coordinates":[-118.081613,34.587389],"type":"Point"}
}