{
  "type": "Feature",
  "properties": {
    "addr:full":"2511 Garden Rd Monterey CA 93940",
    "addr:housenumber":"2511",
    "addr:postcode":"93940",
    "addr:street":"Garden Rd",
    "iso:country":"US",
    "sg:address":"2511 Garden Rd",
    "sg:city":"Monterey",
    "sg:classifiers":[
        {
            "category":"Manufacturing",
            "subcategory":"Metals",
            "type":"Manufacturing & Wholesale Goods"
        }
    ],
    "sg:phone":"+1 831 642 9300",
    "sg:postcode":"93940",
    "sg:province":"CA",
    "sg:tags":[
        "mfr",
        "production",
        "primary",
        "aluminum"
    ],
    "wof:name":"Century Aluminum Company",
    "wof:placetype":"venue"
},
  "geometry": {"coordinates":[-121.84900399999999,36.585368],"type":"Point"}
}