{
  "type": "Feature",
  "properties": {
    "iso:country":"US",
    "sg:address":"1948 Tice Valley Blvd",
    "sg:city":"Walnut Creek",
    "sg:classifiers":[
        {
            "category":"Shopping",
            "subcategory":"Clothing, Apparel, & Fashions",
            "type":"Retail Goods"
        }
    ],
    "sg:phone":"+1 925 937 5512",
    "sg:postcode":"94595",
    "sg:province":"CA",
    "wof:name":"Draper's & Damon's Inc",
    "wof:placetype":"venue"
},
  "geometry": {"coordinates":[-122.073556,37.877674],"type":"Point"}
}