{
  "type": "Feature",
  "properties": {
    "iso:country":"US",
    "sg:address":"7262 Bellaire Ave",
    "sg:city":"North Hollywood",
    "sg:classifiers":[
        {
            "category":"Building & Trades",
            "subcategory":"Construction",
            "type":"Services"
        }
    ],
    "sg:phone":"+1 818 759 4977",
    "sg:postcode":"91605",
    "sg:province":"CA",
    "sg:tags":[
        "resurfacing",
        "laying",
        "refinishing",
        "floor"
    ],
    "wof:name":"Armcraft Inc",
    "wof:placetype":"venue"
},
  "geometry": {"coordinates":[-118.409347,34.201808],"type":"Point"}
}