{
  "type": "Feature",
  "properties": {
    "addr:full":"1875 S Grant St Ste 800 San Mateo CA 94402",
    "addr:housenumber":"1875",
    "addr:postcode":"94402",
    "addr:street":"S Grant St Ste 800",
    "iso:country":"US",
    "sg:address":"1875 S Grant St Ste 800",
    "sg:city":"San Mateo",
    "sg:classifiers":[
        {
            "category":"Arts & Performance",
            "subcategory":"Arts Center",
            "type":"Entertainment"
        }
    ],
    "sg:phone":"+1 650 288 8600",
    "sg:postcode":"94402",
    "sg:province":"CA",
    "sg:website":"www.zvents.com",
    "wof:name":"Zvents",
    "wof:placetype":"venue"
},
  "geometry": {"coordinates":[-122.301534,37.553121],"type":"Point"}
}