{
  "type": "Feature",
  "properties": {
    "iso:country":"US",
    "sg:address":"1391 E Olive Ave",
    "sg:city":"Porterville",
    "sg:classifiers":[
        {
            "category":"Social Services",
            "subcategory":"Child Care",
            "type":"Services"
        }
    ],
    "sg:phone":"+1 559 782 1077",
    "sg:postcode":"93257",
    "sg:province":"CA",
    "sg:tags":[
        "center"
    ],
    "wof:name":"Family FOCUS",
    "wof:placetype":"venue"
},
  "geometry": {"coordinates":[-118.986207,36.065824],"type":"Point"}
}