{
  "type": "Feature",
  "properties": {
    "addr:full":"175 Sunset Ln Applegate CA 95703",
    "addr:housenumber":"175",
    "addr:postcode":"95703",
    "addr:street":"Sunset Ln Applegate",
    "iso:country":"US",
    "sg:address":"175 Sunset Ln",
    "sg:city":"Applegate",
    "sg:classifiers":[
        {
            "category":"Health Services",
            "subcategory":"Clinic",
            "type":"Services"
        }
    ],
    "sg:phone":"+1 530 305 9982",
    "sg:postcode":"95703",
    "sg:province":"CA",
    "sg:tags":[
        "information",
        "alcoholism",
        "treatment"
    ],
    "wof:name":"Renee Bueno Massage Therapy",
    "wof:placetype":"venue"
},
  "geometry": {"coordinates":[-121.011556,38.986482],"type":"Point"}
}