{
  "type": "Feature",
  "properties": {
    "addr:full":"8648 Atlantic Ave South Gate CA 90280",
    "addr:housenumber":"8648",
    "addr:postcode":"90280",
    "addr:street":"Atlantic Ave;Gate",
    "iso:country":"US",
    "sg:address":"8648 Atlantic Ave",
    "sg:city":"South Gate",
    "sg:classifiers":[
        {
            "category":"Retail",
            "subcategory":"Auto Repair",
            "type":"Services"
        }
    ],
    "sg:phone":"+1 323 563 0235",
    "sg:postcode":"90280",
    "sg:province":"CA",
    "wof:name":"Extreme Auto Body",
    "wof:placetype":"venue"
},
  "geometry": {"coordinates":[-118.18327499999999,33.953919],"type":"Point"}
}