{
  "type": "Feature",
  "properties": {
    "iso:country":"US",
    "sg:address":"16233 Arrow Hwy",
    "sg:city":"Irwindale",
    "sg:classifiers":[
        {
            "category":"Manufacturing",
            "subcategory":"Signs",
            "type":"Manufacturing & Wholesale Goods"
        }
    ],
    "sg:phone":"+1 626 969 3619",
    "sg:postcode":"91706",
    "sg:province":"CA",
    "wof:name":"Sundance Colors",
    "wof:placetype":"venue"
},
  "geometry": {"coordinates":[-117.92571700000001,34.107033],"type":"Point"}
}