{
  "type": "Feature",
  "properties": {
    "addr:full":"813 Guadalupe St Guadalupe CA 93434",
    "addr:housenumber":"813",
    "addr:postcode":"93434",
    "addr:street":"Guadalupe St",
    "iso:country":"US",
    "sg:address":"813 Guadalupe St",
    "sg:city":"Guadalupe",
    "sg:classifiers":[
        {
            "category":"Professional",
            "type":"Services"
        }
    ],
    "sg:phone":"+1 805 343 2205",
    "sg:postcode":"93434",
    "sg:province":"CA",
    "sg:tags":[
        "establishment"
    ],
    "wof:name":"Lupe's Co",
    "wof:placetype":"venue"
},
  "geometry": {"coordinates":[-120.573959,34.968181],"type":"Point"}
}