{
  "type": "Feature",
  "properties": {
    "iso:country":"US",
    "sg:address":"20 N San Pedro Rd",
    "sg:city":"San Rafael",
    "sg:classifiers":[
        {
            "category":"Social Services",
            "subcategory":"Job Training",
            "type":"Services"
        }
    ],
    "sg:phone":"+1 415 499 6003",
    "sg:postcode":"94903",
    "sg:province":"CA",
    "sg:tags":[
        "executive"
    ],
    "wof:name":"Office Employment and Training",
    "wof:placetype":"venue"
},
  "geometry": {"coordinates":[-122.534391,37.993352],"type":"Point"}
}