{
  "type": "Feature",
  "properties": {
    "addr:full":"1137 Garden St San Luis Obispo CA 93401",
    "addr:housenumber":"1137",
    "addr:postcode":"93401",
    "addr:street":"Garden St",
    "iso:country":"US",
    "sg:address":"1137 Garden St",
    "sg:city":"San Luis Obispo",
    "sg:classifiers":[
        {
            "category":"Shopping",
            "subcategory":"Gifts & Souvenirs",
            "type":"Retail Goods"
        }
    ],
    "sg:phone":"+1 805 783 2890",
    "sg:postcode":"93401",
    "sg:province":"CA",
    "wof:name":"California Blonde",
    "wof:placetype":"venue"
},
  "geometry": {"coordinates":[-120.66327699999999,35.279167],"type":"Point"}
}