{
  "type": "Feature",
  "properties": {
    "addr:full":"10250 Prospect Ave Santee CA 92071",
    "addr:housenumber":"10250",
    "addr:postcode":"92071",
    "addr:street":"Prospect Ave",
    "iso:country":"US",
    "sg:address":"10250 Prospect Ave",
    "sg:city":"Santee",
    "sg:classifiers":[
        {
            "category":"Building & Trades",
            "subcategory":"Construction",
            "type":"Services"
        }
    ],
    "sg:phone":"+1 619 596 1126",
    "sg:postcode":"92071",
    "sg:province":"CA",
    "sg:tags":[
        "general",
        "contractor"
    ],
    "wof:name":"All Christian Construction",
    "wof:placetype":"venue"
},
  "geometry": {"coordinates":[-116.973671,32.831304],"type":"Point"}
}