{
  "type": "Feature",
  "properties": {
    "iso:country":"US",
    "sg:address":"2767 E Imperial Hwy",
    "sg:city":"Brea",
    "sg:classifiers":[
        {
            "category":"Freight",
            "type":"Transportation"
        }
    ],
    "sg:phone":"+1 714 523 4301",
    "sg:postcode":"92886",
    "sg:province":"CA",
    "sg:tags":[
        "trucking"
    ],
    "sg:website":"www.gitrucking.com",
    "wof:name":"Gi Trucking Co",
    "wof:placetype":"venue"
},
  "geometry": {"coordinates":[-117.862289,33.911055],"type":"Point"}
}