{
  "type": "Feature",
  "properties": {
    "iso:country":"US",
    "sg:address":"671 W Hamilton Ave",
    "sg:city":"Campbell",
    "sg:classifiers":[
        {
            "category":"Personal",
            "subcategory":"Barber",
            "type":"Services"
        }
    ],
    "sg:phone":"+1 408 866 7816",
    "sg:postcode":"95008",
    "sg:province":"CA",
    "wof:name":"George's Riverside Barber Styling",
    "wof:placetype":"venue"
},
  "geometry": {"coordinates":[-121.96199799999999,37.294201],"type":"Point"}
}