{
  "type": "Feature",
  "properties": {
    "addr:full":"14246 Chandler Blvd Van Nuys CA 91401",
    "addr:housenumber":"14246",
    "addr:postcode":"91401",
    "addr:street":"Chandler Blvd",
    "iso:country":"US",
    "sg:address":"14246 Chandler Blvd",
    "sg:city":"Van Nuys",
    "sg:classifiers":[
        {
            "category":"Building & Trades",
            "subcategory":"Construction",
            "type":"Services"
        }
    ],
    "sg:phone":"+1 818 907 6942",
    "sg:postcode":"91401",
    "sg:province":"CA",
    "sg:tags":[
        "hanging",
        "contractor"
    ],
    "wof:name":"Aboody Herzel Painting Inc",
    "wof:placetype":"venue"
},
  "geometry": {"coordinates":[-118.443568,34.168269],"type":"Point"}
}