{
  "type": "Feature",
  "properties": {
    "iso:country":"US",
    "sg:address":"40453 Rd 40",
    "sg:city":"Dinuba",
    "sg:classifiers":[
        {
            "category":"Building & Trades",
            "subcategory":"Construction",
            "type":"Services"
        }
    ],
    "sg:phone":"+1 559 897 5498",
    "sg:postcode":"93618",
    "sg:province":"CA",
    "sg:tags":[
        "insulation",
        "heat",
        "contractor"
    ],
    "wof:name":"ISC Inc",
    "wof:placetype":"venue"
},
  "geometry": {"coordinates":[-119.48471600000001,36.522176],"type":"Point"}
}