{
  "type": "Feature",
  "properties": {
    "iso:country":"US",
    "sg:address":"173 Foote Ave",
    "sg:city":"San Francisco",
    "sg:classifiers":[
        {
            "category":"Retail",
            "subcategory":"Repair Shop",
            "type":"Services"
        }
    ],
    "sg:phone":"+1 415 452 2740",
    "sg:postcode":"94112",
    "sg:province":"CA",
    "sg:tags":[
        "lock",
        "locksmith"
    ],
    "wof:name":"Christian The Locksmith",
    "wof:placetype":"venue"
},
  "geometry": {"coordinates":[-122.44606400000001,37.713425],"type":"Point"}
}