{
  "type": "Feature",
  "properties": {
    "iso:country":"US",
    "sg:address":"450 30th Ave",
    "sg:city":"San Francisco",
    "sg:classifiers":[
        {
            "category":"Education",
            "subcategory":"School",
            "type":"Public Place"
        }
    ],
    "sg:phone":"+1 415 750 8435",
    "sg:postcode":"94121",
    "sg:province":"CA",
    "sg:tags":[
        "high",
        "middle"
    ],
    "sg:website":"sfportal.sfusd.edu/sites/presidi...",
    "wof:name":"Presidio Middle School",
    "wof:placetype":"venue"
},
  "geometry": {"coordinates":[-122.490194,37.780855],"type":"Point"}
}