{
  "type": "Feature",
  "properties": {
    "addr:full":"22701 Macfarlane Dr Woodland Hills CA 91364",
    "addr:housenumber":"22701",
    "addr:postcode":"91364",
    "addr:street":"Macfarlane Dr",
    "iso:country":"US",
    "sg:address":"22701 Macfarlane Dr",
    "sg:city":"Woodland Hills",
    "sg:classifiers":[
        {
            "category":"Professional",
            "subcategory":"Business Services",
            "type":"Services"
        }
    ],
    "sg:phone":"+1 818 225 0578",
    "sg:postcode":"91364",
    "sg:province":"CA",
    "sg:tags":[
        "drafting"
    ],
    "wof:name":"Artruins",
    "wof:placetype":"venue"
},
  "geometry": {"coordinates":[-118.623536,34.162245],"type":"Point"}
}