{
  "type": "Feature",
  "properties": {
    "iso:country":"US",
    "sg:address":"14402 Hawthorne Blvd",
    "sg:city":"Lawndale",
    "sg:classifiers":[
        {
            "category":"Real Estate",
            "subcategory":"Real Estate Agent",
            "type":"Services"
        }
    ],
    "sg:phone":"+1 310 973 7734",
    "sg:postcode":"90260",
    "sg:province":"CA",
    "wof:name":"Highlife Investments & Realtor",
    "wof:placetype":"venue"
},
  "geometry": {"coordinates":[-118.352298,33.900561],"type":"Point"}
}