{
  "type": "Feature",
  "properties": {
    "addr:full":"613 Mindy Way San Jose CA 95123",
    "addr:housenumber":"613",
    "addr:postcode":"95123",
    "addr:street":"Mindy Way",
    "iso:country":"US",
    "sg:address":"613 Mindy Way",
    "sg:city":"San Jose",
    "sg:classifiers":[
        {
            "category":"Building & Trades",
            "subcategory":"Landscaping Services",
            "type":"Services"
        }
    ],
    "sg:phone":"+1 408 497 8230",
    "sg:postcode":"95123",
    "sg:province":"CA",
    "sg:tags":[
        "gardener"
    ],
    "wof:name":"Sunstone Landscape",
    "wof:placetype":"venue"
},
  "geometry": {"coordinates":[-121.82754799999999,37.228843],"type":"Point"}
}