{
  "type": "Feature",
  "properties": {
    "iso:country":"US",
    "sg:address":"590 W Shamrock St",
    "sg:city":"Rialto",
    "sg:classifiers":[
        {
            "category":"Building & Trades",
            "subcategory":"Electrical",
            "type":"Services"
        }
    ],
    "sg:phone":"+1 562 686 8425",
    "sg:postcode":"92376",
    "sg:province":"CA",
    "sg:tags":[
        "electrician"
    ],
    "wof:name":"S&G Electic And Assc.",
    "wof:placetype":"venue"
},
  "geometry": {"coordinates":[-117.381063,34.11908],"type":"Point"}
}