{
  "type": "Feature",
  "properties": {
    "addr:full":"818 Silva Ave Santa Rosa CA 95404",
    "addr:housenumber":"818",
    "addr:postcode":"95404",
    "addr:street":"Silva Ave",
    "iso:country":"US",
    "sg:address":"818 Silva Ave",
    "sg:city":"Santa Rosa",
    "sg:classifiers":[
        {
            "category":"Manufacturing",
            "subcategory":"Building Materials",
            "type":"Manufacturing & Wholesale Goods"
        }
    ],
    "sg:phone":"+1 707 568 3002",
    "sg:postcode":"95404",
    "sg:province":"CA",
    "sg:tags":[
        "mfg"
    ],
    "wof:name":"Garvin Woodworks",
    "wof:placetype":"venue"
},
  "geometry": {"coordinates":[-122.711736,38.458564],"type":"Point"}
}