{
  "type": "Feature",
  "properties": {
    "addr:full":"555 W 5th St Los Angeles CA 90013",
    "addr:housenumber":"555",
    "addr:postcode":"90013",
    "addr:street":"W 5Th St",
    "iso:country":"US",
    "sg:address":"555 W 5th St",
    "sg:city":"Los Angeles",
    "sg:classifiers":[
        {
            "category":"Wholesale",
            "subcategory":"Furniture",
            "type":"Manufacturing & Wholesale Goods"
        }
    ],
    "sg:phone":"+1 213 622 7060",
    "sg:postcode":"90013",
    "sg:province":"CA",
    "sg:tags":[
        "equipment"
    ],
    "wof:name":"Trendway Corp",
    "wof:placetype":"venue"
},
  "geometry": {"coordinates":[-118.253998,34.0499],"type":"Point"}
}