{
  "type": "Feature",
  "properties": {
    "iso:country":"US",
    "sg:address":"4545 Dozier Ave",
    "sg:city":"Los Angeles",
    "sg:classifiers":[
        {
            "category":"Education",
            "subcategory":"School",
            "type":"Public Place"
        }
    ],
    "sg:phone":"+1 323 780 3900",
    "sg:postcode":"90022",
    "sg:province":"CA",
    "sg:tags":[
        "high",
        "middle",
        "elementary"
    ],
    "sg:website":"www.kippraices.com",
    "wof:name":"KIPP Raices",
    "wof:placetype":"venue"
},
  "geometry": {"coordinates":[-118.168243,34.162941],"type":"Point"}
}