{
  "type": "Feature",
  "properties": {
    "addr:full":"2472 Chambers Rd Ste 150 Tustin CA 92780",
    "addr:housenumber":"2472",
    "addr:postcode":"92780",
    "addr:street":"Chambers Rd Ste 150",
    "iso:country":"US",
    "sg:address":"2472 Chambers Rd Ste 150",
    "sg:city":"Tustin",
    "sg:classifiers":[
        {
            "category":"Professional",
            "subcategory":"Lawyer & Legal Services",
            "type":"Services"
        }
    ],
    "sg:phone":"+1 714 832 1600",
    "sg:postcode":"92780",
    "sg:province":"CA",
    "wof:name":"Long David M",
    "wof:placetype":"venue"
},
  "geometry": {"coordinates":[-117.80777500000001,33.717909],"type":"Point"}
}