{
  "type": "Feature",
  "properties": {
    "addr:full":"400 W Franklin St Monterey CA 93940",
    "addr:housenumber":"400",
    "addr:postcode":"93940",
    "addr:street":"W Franklin St",
    "iso:country":"US",
    "sg:address":"400 W Franklin St",
    "sg:city":"Monterey",
    "sg:classifiers":[
        {
            "category":"Place Of Worship",
            "type":"Public Place"
        },
        {
            "category":"Shopping",
            "subcategory":"Books",
            "type":"Retail Goods"
        },
        {
            "category":"Organizations",
            "subcategory":"Religious Organization",
            "type":"Services"
        }
    ],
    "sg:phone":"+1 831 372 7326",
    "sg:postcode":"93940",
    "sg:province":"CA",
    "sg:tags":[
        "science",
        "churches-religious",
        "store",
        "church"
    ],
    "sg:website":"http://www.montereycsl.org",
    "wof:name":"Monterey Center For Spriritual Living",
    "wof:placetype":"venue"
},
  "geometry": {"coordinates":[-121.8964,36.600319],"type":"Point"}
}