{
  "type": "Feature",
  "properties": {
    "iso:country":"US",
    "sg:address":"820 Oroville Ave",
    "sg:city":"Chico",
    "sg:classifiers":[
        {
            "category":"Restaurant",
            "type":"Food & Drink"
        }
    ],
    "sg:phone":"+1 530 898 8488",
    "sg:postcode":"95928",
    "sg:province":"CA",
    "wof:name":"Amigos De Acapulco",
    "wof:placetype":"venue"
},
  "geometry": {"coordinates":[-121.83628899999999,39.725546],"type":"Point"}
}