{
  "type": "Feature",
  "properties": {
    "iso:country":"US",
    "sg:address":"515 Sonora Ave",
    "sg:city":"Half Moon Bay",
    "sg:classifiers":[
        {
            "category":"Health Services",
            "subcategory":"Health Practitioner",
            "type":"Services"
        }
    ],
    "sg:phone":"+1 650 712 9750",
    "sg:postcode":"94018",
    "sg:province":"CA",
    "sg:tags":[
        "homeopath"
    ],
    "wof:name":"Cheryl Coleman",
    "wof:placetype":"venue"
},
  "geometry": {"coordinates":[-122.479903,37.507709],"type":"Point"}
}