{
  "type": "Feature",
  "properties": {
    "iso:country":"US",
    "sg:address":"40354 17th St W",
    "sg:city":"Palmdale",
    "sg:classifiers":[
        {
            "category":"Farming",
            "subcategory":"Farm",
            "type":"Manufacturing & Wholesale Goods"
        }
    ],
    "sg:phone":"+1 661 273 5858",
    "sg:postcode":"93551",
    "sg:province":"CA",
    "sg:tags":[
        "crop",
        "general"
    ],
    "wof:name":"JKL Farms",
    "wof:placetype":"venue"
},
  "geometry": {"coordinates":[-118.160951,34.61357],"type":"Point"}
}