{
  "type": "Feature",
  "properties": {
    "iso:country":"US",
    "sg:address":"2461 W Washington Blvd",
    "sg:city":"Los Angeles",
    "sg:classifiers":[
        {
            "category":"Retail",
            "subcategory":"Auto Repair",
            "type":"Services"
        }
    ],
    "sg:phone":"+1 323 731 0613",
    "sg:postcode":"90018",
    "sg:province":"CA",
    "sg:tags":[
        "repairing",
        "automobile"
    ],
    "wof:name":"Bob's Automatic Transmissions",
    "wof:placetype":"venue"
},
  "geometry": {"coordinates":[-118.317001,34.039799],"type":"Point"}
}