{
  "type": "Feature",
  "properties": {
    "iso:country":"US",
    "sg:address":"874 Gravenstein Ave",
    "sg:city":"Sebastopol",
    "sg:classifiers":[
        {
            "category":"Professional",
            "subcategory":"Art Services",
            "type":"Services"
        }
    ],
    "sg:phone":"+1 707 824 2007",
    "sg:postcode":"95472",
    "sg:province":"CA",
    "sg:tags":[
        "graphic",
        "designer"
    ],
    "wof:name":"Aha Visual",
    "wof:placetype":"venue"
},
  "geometry": {"coordinates":[-122.818467,38.393534],"type":"Point"}
}