{
  "type": "Feature",
  "properties": {
    "addr:full":"3470 Mount Diablo Blvd Lafayette CA 94549",
    "addr:housenumber":"3470",
    "addr:postcode":"94549",
    "addr:street":"Mount Diablo Blvd",
    "iso:country":"US",
    "sg:address":"3470 Mount Diablo Blvd",
    "sg:city":"Lafayette",
    "sg:classifiers":[
        {
            "category":"Insurance",
            "subcategory":"Insurance Agent",
            "type":"Services"
        }
    ],
    "sg:phone":"+1 925 283 8787",
    "sg:postcode":"94549",
    "sg:province":"CA",
    "wof:name":"Met Life",
    "wof:placetype":"venue"
},
  "geometry": {"coordinates":[-122.112369,37.892982],"type":"Point"}
}