{
  "type": "Feature",
  "properties": {
    "iso:country":"US",
    "sg:address":"902 Carmel Ave Ste 8",
    "sg:city":"Albany",
    "sg:classifiers":[
        {
            "category":"Health Services",
            "subcategory":"Clinic",
            "type":"Services"
        }
    ],
    "sg:phone":"+1 510 526 0474",
    "sg:postcode":"94706",
    "sg:province":"CA",
    "sg:tags":[
        "counseling",
        "mental"
    ],
    "wof:name":"Margaret Dodson, PhD",
    "wof:placetype":"venue"
},
  "geometry": {"coordinates":[-122.289883,37.890394],"type":"Point"}
}