{
  "type": "Feature",
  "properties": {
    "addr:full":"1959 E 4th St Long Beach CA 90802",
    "addr:housenumber":"1959",
    "addr:postcode":"90802",
    "addr:street":"E 4Th St",
    "iso:country":"US",
    "sg:address":"1959 E 4th St",
    "sg:city":"Long Beach",
    "sg:classifiers":[
        {
            "category":"Health Services",
            "subcategory":"Doctor",
            "type":"Services"
        }
    ],
    "sg:phone":"+1 562 432 9883",
    "sg:postcode":"90802",
    "sg:province":"CA",
    "sg:tags":[
        "dentist"
    ],
    "wof:name":"A Smile Dr Dentistry",
    "wof:placetype":"venue"
},
  "geometry": {"coordinates":[-118.16813,33.771782],"type":"Point"}
}