{
  "type": "Feature",
  "properties": {
    "addr:full":"2792 Norrish Rd Holtville CA 92250",
    "addr:housenumber":"2792",
    "addr:postcode":"92250",
    "addr:street":"Norrish Rd",
    "iso:country":"US",
    "sg:address":"2792 Norrish Rd",
    "sg:city":"Holtville",
    "sg:classifiers":[
        {
            "category":"Building & Trades",
            "subcategory":"Construction",
            "type":"Services"
        }
    ],
    "sg:phone":"+1 760 356 1196",
    "sg:postcode":"92250",
    "sg:province":"CA",
    "sg:tags":[
        "equipment",
        "welding",
        "repair"
    ],
    "wof:name":"Norrish Repair & Metal Works",
    "wof:placetype":"venue"
},
  "geometry": {"coordinates":[-115.289225,32.832896],"type":"Point"}
}