{
  "type": "Feature",
  "properties": {
    "iso:country":"US",
    "sg:address":"3020 Alta View Dr",
    "sg:city":"San Diego",
    "sg:classifiers":[
        {
            "category":"Shopping",
            "subcategory":"Gifts & Souvenirs",
            "type":"Retail Goods"
        }
    ],
    "sg:phone":"+1 619 475 2236",
    "sg:postcode":"92139",
    "sg:province":"CA",
    "wof:name":"Artisan Gifts",
    "wof:placetype":"venue"
},
  "geometry": {"coordinates":[-117.039721,32.67582],"type":"Point"}
}