{
  "type": "Feature",
  "properties": {
    "iso:country":"US",
    "sg:address":"2303 Chico Ave",
    "sg:city":"South El Monte",
    "sg:classifiers":[
        {
            "category":"Wholesale",
            "subcategory":"Apparel",
            "type":"Manufacturing & Wholesale Goods"
        }
    ],
    "sg:phone":"+1 626 443 4950",
    "sg:postcode":"91733",
    "sg:province":"CA",
    "sg:tags":[
        "clothing"
    ],
    "wof:name":"J I Fashion Inc",
    "wof:placetype":"venue"
},
  "geometry": {"coordinates":[-118.060064,34.051922],"type":"Point"}
}