{
  "type": "Feature",
  "properties": {
    "iso:country":"US",
    "sg:address":"408 Trevethan Ave",
    "sg:city":"Santa Cruz",
    "sg:classifiers":[
        {
            "category":"Autos & Motor Vehicles",
            "subcategory":"Motorcycle Sales",
            "type":"Retail Goods"
        }
    ],
    "sg:phone":"+1 831 460 9434",
    "sg:postcode":"95062",
    "sg:province":"CA",
    "sg:tags":[
        "scooter"
    ],
    "wof:name":"Santa Cruz Suspension & Access",
    "wof:placetype":"venue"
},
  "geometry": {"coordinates":[-121.999963,36.985751],"type":"Point"}
}