{
  "type": "Feature",
  "properties": {
    "iso:country":"US",
    "sg:address":"6636 University Ave",
    "sg:city":"San Diego",
    "sg:classifiers":[
        {
            "category":"Building & Trades",
            "subcategory":"Cleaning & Sanitation",
            "type":"Services"
        }
    ],
    "sg:phone":"+1 619 286 6679",
    "sg:postcode":"92115",
    "sg:province":"CA",
    "sg:tags":[
        "venetian",
        "blind"
    ],
    "wof:name":"A-Sparkle Blinds",
    "wof:placetype":"venue"
},
  "geometry": {"coordinates":[-117.053848,32.755392],"type":"Point"}
}