{
  "type": "Feature",
  "properties": {
    "iso:country":"US",
    "sg:address":"2452 Apple Vista Ln",
    "sg:city":"Camino",
    "sg:classifiers":[
        {
            "category":"Travel",
            "subcategory":"Hotels & Motels",
            "type":"Entertainment"
        }
    ],
    "sg:phone":"+1 530 644 0314",
    "sg:postcode":"95709",
    "sg:province":"CA",
    "sg:tags":[
        "breakfast",
        "accommodation",
        "bed"
    ],
    "wof:name":"Time Out",
    "wof:placetype":"venue"
},
  "geometry": {"coordinates":[-120.680985,38.753184],"type":"Point"}
}