{
  "type": "Feature",
  "properties": {
    "iso:country":"US",
    "sg:address":"155 17th St",
    "sg:city":"Oakland",
    "sg:classifiers":[
        {
            "category":"Personal",
            "subcategory":"Beauty Salon",
            "type":"Services"
        }
    ],
    "sg:phone":"+1 510 451 5759",
    "sg:postcode":"94612",
    "sg:province":"CA",
    "wof:name":"L'Sky Tre'Mar Spa",
    "wof:placetype":"venue"
},
  "geometry": {"coordinates":[-122.263531,37.80455],"type":"Point"}
}