{
  "type": "Feature",
  "properties": {
    "iso:country":"US",
    "sg:address":"2372 Gold River Rd.",
    "sg:city":"Rancho Cordova",
    "sg:classifiers":[
        {
            "category":"Building & Trades",
            "subcategory":"Construction",
            "type":"Services"
        }
    ],
    "sg:phone":"+1 916 631 1693",
    "sg:postcode":"95670",
    "sg:province":"CA",
    "sg:tags":[
        "contractor"
    ],
    "sg:website":"www.FiveStarRestoration.com",
    "wof:name":"Five Star Restoration & Construction, Inc.",
    "wof:placetype":"venue"
},
  "geometry": {"coordinates":[-121.260892,38.617483],"type":"Point"}
}