{
  "type": "Feature",
  "properties": {
    "iso:country":"US",
    "sg:address":"2172 Yucca Ln",
    "sg:city":"Altadena",
    "sg:classifiers":[
        {
            "category":"Building & Trades",
            "subcategory":"Electrical",
            "type":"Services"
        }
    ],
    "sg:phone":"+1 626 798 4102",
    "sg:postcode":"91001",
    "sg:province":"CA",
    "sg:tags":[
        "electric",
        "contractor"
    ],
    "wof:name":"Engineering Plant Svc",
    "wof:placetype":"venue"
},
  "geometry": {"coordinates":[-118.17001999999999,34.182752],"type":"Point"}
}