{
  "type": "Feature",
  "properties": {
    "iso:country":"US",
    "sg:address":"17865 Colima Rd",
    "sg:city":"Rowland Heights",
    "sg:classifiers":[
        {
            "category":"Restaurant",
            "type":"Food & Drink"
        }
    ],
    "sg:menulink":"http://www.allmenus.com/ca/east-san-gabriel-valley/28725-curry-house/menu/",
    "sg:phone":"+1 626 964 4355",
    "sg:postcode":"91748",
    "sg:province":"CA",
    "sg:tags":[
        "japanese",
        "asian"
    ],
    "wof:name":"Curry House",
    "wof:placetype":"venue"
},
  "geometry": {"coordinates":[-117.914979,33.990102],"type":"Point"}
}