{
  "type": "Feature",
  "properties": {
    "iso:country":"US",
    "sg:address":"555 California St",
    "sg:city":"San Francisco",
    "sg:classifiers":[
        {
            "category":"Shopping",
            "subcategory":"Computers & Home Electronics",
            "type":"Retail Goods"
        }
    ],
    "sg:phone":"+1 650 234 0583",
    "sg:postcode":"94104",
    "sg:province":"CA",
    "sg:tags":[
        "software"
    ],
    "wof:name":"Sitelet Software",
    "wof:placetype":"venue"
},
  "geometry": {"coordinates":[-122.404367,37.792571],"type":"Point"}
}