{
  "type": "Feature",
  "properties": {
    "addr:full":"3500 Cincinnati Ave Rocklin CA 95765",
    "addr:housenumber":"3500",
    "addr:postcode":"95765",
    "addr:street":"Cincinnati Ave",
    "iso:country":"US",
    "sg:address":"3500 Cincinnati Ave",
    "sg:city":"Rocklin",
    "sg:classifiers":[
        {
            "category":"Manufacturing",
            "subcategory":"Furniture",
            "type":"Manufacturing & Wholesale Goods"
        }
    ],
    "sg:phone":"+1 916 645 3301",
    "sg:postcode":"95765",
    "sg:province":"CA",
    "sg:tags":[
        "mfg",
        "wood",
        "laminated",
        "plat",
        "plastic"
    ],
    "wof:name":"Formica Corporation",
    "wof:placetype":"venue"
},
  "geometry": {"coordinates":[-121.31208700000001,38.807361],"type":"Point"}
}