{
  "type": "Feature",
  "properties": {
    "iso:country":"US",
    "sg:address":"4909 E Mckinley Ave",
    "sg:city":"Fresno",
    "sg:classifiers":[
        {
            "category":"Restaurant",
            "type":"Food & Drink"
        }
    ],
    "sg:menulink":"http://www.allmenus.com/ca/fresno/197739-kfc---kentucky-fried-chicken/menu/",
    "sg:phone":"+1 559 456 2411",
    "sg:postcode":"93727",
    "sg:province":"CA",
    "sg:tags":[
        "american",
        "chicken"
    ],
    "wof:name":"KFC - Kentucky Fried Chicken",
    "wof:placetype":"venue"
},
  "geometry": {"coordinates":[-119.73116899999999,36.765391],"type":"Point"}
}