{
  "type": "Feature",
  "properties": {
    "iso:country":"US",
    "sg:address":"16229 Devonshire St",
    "sg:city":"Granada Hills",
    "sg:classifiers":[
        {
            "category":"Retail",
            "subcategory":"Repair Shop",
            "type":"Services"
        }
    ],
    "sg:phone":"+1 818 363 7476",
    "sg:postcode":"91344",
    "sg:province":"CA",
    "sg:tags":[
        "equipment",
        "video"
    ],
    "wof:name":"House Of Video",
    "wof:placetype":"venue"
},
  "geometry": {"coordinates":[-118.488654,34.257504],"type":"Point"}
}