{
  "type": "Feature",
  "properties": {
    "addr:full":"2145 G Ave Apt 9 National City CA 91950",
    "addr:housenumber":"2145;9",
    "addr:postcode":"91950",
    "addr:street":"G Ave Apt",
    "iso:country":"US",
    "sg:address":"2145 G Ave Apt 9",
    "sg:city":"National City",
    "sg:classifiers":[
        {
            "category":"Real Estate",
            "subcategory":"Real Estate Operator",
            "type":"Services"
        }
    ],
    "sg:phone":"+1 619 474 5262",
    "sg:postcode":"91950",
    "sg:province":"CA",
    "sg:tags":[
        "apartment"
    ],
    "wof:name":"Sunshine Apartments",
    "wof:placetype":"venue"
},
  "geometry": {"coordinates":[-117.095001,32.666199],"type":"Point"}
}