{
  "type": "Feature",
  "properties": {
    "addr:full":"25018 Broadwell Ave Harbor City CA 90710",
    "addr:postcode":"25018;90710",
    "addr:street":"Broadwell Ave",
    "iso:country":"US",
    "sg:address":"25018 Broadwell Ave",
    "sg:city":"Harbor City",
    "sg:classifiers":[
        {
            "category":"Wholesale",
            "subcategory":"Office Equipment",
            "type":"Manufacturing & Wholesale Goods"
        }
    ],
    "sg:phone":"+1 310 326 1276",
    "sg:postcode":"90710",
    "sg:province":"CA",
    "sg:tags":[
        "system",
        "automation"
    ],
    "wof:name":"Trumpler Marketing Group",
    "wof:placetype":"venue"
},
  "geometry": {"coordinates":[-118.292676,33.794771],"type":"Point"}
}