{
  "type": "Feature",
  "properties": {
    "addr:full":"26643 Mission Blvd Hayward CA 94544",
    "addr:housenumber":"26643",
    "addr:postcode":"94544",
    "addr:street":"Mission Blvd",
    "iso:country":"US",
    "sg:address":"26643 Mission Blvd",
    "sg:city":"Hayward",
    "sg:classifiers":[
        {
            "category":"Food & Beverages",
            "subcategory":"Groceries & Convenience Stores",
            "type":"Retail Goods"
        }
    ],
    "sg:phone":"+1 510 885 0430",
    "sg:postcode":"94544",
    "sg:province":"CA",
    "wof:name":"Saudagar",
    "wof:placetype":"venue"
},
  "geometry": {"coordinates":[-122.064003,37.647202],"type":"Point"}
}