{
  "type": "Feature",
  "properties": {
    "addr:full":"1032 Sundance Dr Fremont CA 94539",
    "addr:housenumber":"1032",
    "addr:postcode":"94539",
    "addr:street":"Sundance Dr",
    "iso:country":"US",
    "sg:address":"1032 Sundance Dr",
    "sg:city":"Fremont",
    "sg:classifiers":[
        {
            "category":"Real Estate",
            "subcategory":"Real Estate Agent",
            "type":"Services"
        }
    ],
    "sg:phone":"+1 510 656 5427",
    "sg:postcode":"94539",
    "sg:province":"CA",
    "wof:name":"Saagar Realty",
    "wof:placetype":"venue"
},
  "geometry": {"coordinates":[-121.91,37.499048],"type":"Point"}
}