{
  "type": "Feature",
  "properties": {
    "addr:full":"5412 Eileen Dr San Jose CA 95129",
    "addr:housenumber":"5412",
    "addr:postcode":"95129",
    "addr:street":"Eileen Dr",
    "iso:country":"US",
    "sg:address":"5412 Eileen Dr",
    "sg:city":"San Jose",
    "sg:classifiers":[
        {
            "category":"Wholesale",
            "subcategory":"Apparel",
            "type":"Manufacturing & Wholesale Goods"
        }
    ],
    "sg:phone":"+1 408 366 2496",
    "sg:postcode":"95129",
    "sg:province":"CA",
    "sg:tags":[
        "clothing"
    ],
    "wof:name":"Lafleur Parfaite",
    "wof:placetype":"venue"
},
  "geometry": {"coordinates":[-121.996861,37.298491],"type":"Point"}
}