{
  "type": "Feature",
  "properties": {
    "iso:country":"US",
    "sg:address":"6501 Kelsey Canyon Rd",
    "sg:city":"Placerville",
    "sg:classifiers":[
        {
            "category":"Building & Trades",
            "subcategory":"Construction",
            "type":"Services"
        }
    ],
    "sg:phone":"+1 530 409 1774",
    "sg:postcode":"95667",
    "sg:province":"CA",
    "sg:tags":[
        "contractor"
    ],
    "sg:website":"http://www.adm-generalconstruction.com",
    "wof:name":"ADM General Construction",
    "wof:placetype":"venue"
},
  "geometry": {"coordinates":[-120.828613,38.787289],"type":"Point"}
}