{
  "type": "Feature",
  "properties": {
    "addr:full":"2300 S Lewis St Anaheim CA 92802",
    "addr:housenumber":"2300",
    "addr:postcode":"92802",
    "addr:street":"S Lewis St",
    "iso:country":"US",
    "sg:address":"2300 S Lewis St",
    "sg:city":"Anaheim",
    "sg:classifiers":[
        {
            "category":"Shopping",
            "type":"Retail Goods"
        }
    ],
    "sg:phone":"+1 714 750 0938",
    "sg:postcode":"92802",
    "sg:province":"CA",
    "sg:tags":[
        "merchandise"
    ],
    "wof:name":"Evergreen Dollar",
    "wof:placetype":"venue"
},
  "geometry": {"coordinates":[-117.89756,33.791067],"type":"Point"}
}