{
  "type": "Feature",
  "properties": {
    "addr:full":"5960 El Cajon Blvd San Diego CA 92115",
    "addr:housenumber":"5960",
    "addr:postcode":"92115",
    "addr:street":"El Cajon Blvd",
    "iso:country":"US",
    "sg:address":"5960 El Cajon Blvd",
    "sg:city":"San Diego",
    "sg:classifiers":[
        {
            "category":"Shopping",
            "subcategory":"Pawn Shop",
            "type":"Retail Goods"
        }
    ],
    "sg:phone":"+1 619 280 2075",
    "sg:postcode":"92115",
    "sg:province":"CA",
    "wof:name":"Music Rental Company & Pawn",
    "wof:placetype":"venue"
},
  "geometry": {"coordinates":[-117.06934800000001,32.76058],"type":"Point"}
}