{
  "type": "Feature",
  "properties": {
    "iso:country":"US",
    "sg:address":"7092 Maidu Dr",
    "sg:city":"Placerville",
    "sg:classifiers":[
        {
            "category":"Building & Trades",
            "subcategory":"Construction",
            "type":"Services"
        }
    ],
    "sg:phone":"+1 530 344 1373",
    "sg:postcode":"95667",
    "sg:province":"CA",
    "sg:tags":[
        "house",
        "gasoline"
    ],
    "wof:name":"Emro Artistics",
    "wof:placetype":"venue"
},
  "geometry": {"coordinates":[-120.707083,38.789822],"type":"Point"}
}