{
  "type": "Feature",
  "properties": {
    "addr:full":"1385 Shasta Ave San Jose CA 95126",
    "addr:housenumber":"1385",
    "addr:postcode":"95126",
    "addr:street":"Shasta Ave",
    "iso:country":"US",
    "sg:address":"1385 Shasta Ave",
    "sg:city":"San Jose",
    "sg:classifiers":[
        {
            "category":"Professional",
            "type":"Services"
        },
        {
            "category":"Building & Trades",
            "subcategory":"Cleaning & Sanitation",
            "type":"Services"
        }
    ],
    "sg:phone":"+1 408 799 3996",
    "sg:postcode":"95126",
    "sg:province":"CA",
    "sg:tags":[
        "carpet"
    ],
    "wof:name":"Carpet Magic",
    "wof:placetype":"venue"
},
  "geometry": {"coordinates":[-121.918588,37.329806],"type":"Point"}
}