{
  "type": "Feature",
  "properties": {
    "iso:country":"US",
    "sg:address":"587 Virginia Avenue",
    "sg:city":"Campbell",
    "sg:classifiers":[
        {
            "category":"Home & Garden",
            "subcategory":"Carpets & Floor Coverings",
            "type":"Retail Goods"
        }
    ],
    "sg:phone":"+1 408 370 3290",
    "sg:postcode":"95008",
    "sg:province":"CA",
    "sg:tags":[
        "flooring"
    ],
    "wof:name":"Tagatac Michael Hardwood Floor Man",
    "wof:placetype":"venue"
},
  "geometry": {"coordinates":[-121.964062,37.276938],"type":"Point"}
}