{
  "type": "Feature",
  "properties": {
    "iso:country":"US",
    "sg:address":"1141 el Camino Real",
    "sg:city":"Arroyo Grande",
    "sg:classifiers":[
        {
            "category":"Building & Trades",
            "subcategory":"Construction",
            "type":"Services"
        }
    ],
    "sg:phone":"+1 805 489 6863",
    "sg:postcode":"93420",
    "sg:province":"CA",
    "sg:tags":[
        "foundation"
    ],
    "wof:name":"California Foundation",
    "wof:placetype":"venue"
},
  "geometry": {"coordinates":[-120.596507,35.124854],"type":"Point"}
}