{
  "type": "Feature",
  "properties": {
    "addr:full":"4920 State Rte 132 Coulterville CA 95311",
    "addr:housenumber":"4920",
    "addr:postcode":"95311",
    "addr:street":"State Rte 132",
    "iso:country":"US",
    "sg:address":"4920 State Rte 132",
    "sg:city":"Coulterville",
    "sg:classifiers":[
        {
            "category":"Manufacturing",
            "subcategory":"Signs",
            "type":"Manufacturing & Wholesale Goods"
        }
    ],
    "sg:phone":"+1 209 878 3805",
    "sg:postcode":"95311",
    "sg:province":"CA",
    "sg:tags":[
        "specialty",
        "mfg"
    ],
    "wof:name":"Northside Signs",
    "wof:placetype":"venue"
},
  "geometry": {"coordinates":[-120.198193,37.707433],"type":"Point"}
}