{
  "type": "Feature",
  "properties": {
    "addr:full":"539 N Glenoaks Blvd Burbank CA 91502",
    "addr:housenumber":"539",
    "addr:postcode":"91502",
    "addr:street":"N Glenoaks Blvd",
    "iso:country":"US",
    "sg:address":"539 N Glenoaks Blvd",
    "sg:city":"Burbank",
    "sg:classifiers":[
        {
            "category":"Professional",
            "subcategory":"Lawyer & Legal Services",
            "type":"Services"
        }
    ],
    "sg:phone":"+1 818 840 0950",
    "sg:postcode":"91502",
    "sg:province":"CA",
    "sg:website":"www.mediate.com/BarryRoss/",
    "wof:name":"Barry Ross",
    "wof:placetype":"venue"
},
  "geometry": {"coordinates":[-118.311065,34.186391],"type":"Point"}
}