{
  "type": "Feature",
  "properties": {
    "addr:full":"5347 Cole Rd Mariposa CA 95338",
    "addr:housenumber":"5347",
    "addr:postcode":"95338",
    "addr:street":"Cole Rd",
    "iso:country":"US",
    "sg:address":"5347 Cole Rd",
    "sg:city":"Mariposa",
    "sg:classifiers":[
        {
            "category":"Building & Trades",
            "subcategory":"Construction",
            "type":"Services"
        }
    ],
    "sg:phone":"+1 209 966 6492",
    "sg:postcode":"95338",
    "sg:province":"CA",
    "sg:tags":[
        "paving",
        "road",
        "contractor"
    ],
    "wof:name":"As Contractors",
    "wof:placetype":"venue"
},
  "geometry": {"coordinates":[-119.888378,37.486537],"type":"Point"}
}