{
  "type": "Feature",
  "properties": {
    "addr:full":"510 Westaire Blvd Martinez CA 94553",
    "addr:housenumber":"510",
    "addr:postcode":"94553",
    "addr:street":"Westaire Blvd",
    "iso:country":"US",
    "sg:address":"510 Westaire Blvd",
    "sg:city":"Martinez",
    "sg:classifiers":[
        {
            "category":"Building & Trades",
            "subcategory":"Construction",
            "type":"Services"
        }
    ],
    "sg:phone":"+1 925 370 9990",
    "sg:postcode":"94553",
    "sg:province":"CA",
    "sg:tags":[
        "hanging",
        "contractor"
    ],
    "wof:name":"Molinas Paint & Wallcovering",
    "wof:placetype":"venue"
},
  "geometry": {"coordinates":[-122.108761,38.00004],"type":"Point"}
}