{
  "type": "Feature",
  "properties": {
    "iso:country":"US",
    "sg:address":"1489 White Ln",
    "sg:city":"Bakersfield",
    "sg:classifiers":[
        {
            "category":"Retail",
            "subcategory":"Laundry & Dry Cleaning",
            "type":"Services"
        }
    ],
    "sg:phone":"+1 661 834 7434",
    "sg:postcode":"93307",
    "sg:province":"CA",
    "sg:tags":[
        "cleaners"
    ],
    "wof:name":"Suzette's Cleaners",
    "wof:placetype":"venue"
},
  "geometry": {"coordinates":[-119.019171,35.317584],"type":"Point"}
}