{
  "type": "Feature",
  "properties": {
    "iso:country":"US",
    "sg:address":"3634 W Slauson Ave",
    "sg:city":"Los Angeles",
    "sg:classifiers":[
        {
            "category":"Professional",
            "subcategory":"Management & Consulting",
            "type":"Services"
        }
    ],
    "sg:phone":"+1 323 767 1067",
    "sg:postcode":"90043",
    "sg:province":"CA",
    "sg:tags":[
        "business"
    ],
    "wof:name":"UAMD Inc",
    "wof:placetype":"venue"
},
  "geometry": {"coordinates":[-118.337071,33.988903],"type":"Point"}
}