{
  "type": "Feature",
  "properties": {
    "iso:country":"US",
    "sg:address":"8332 Geary Blvd",
    "sg:city":"San Francisco",
    "sg:classifiers":[
        {
            "category":"Professional",
            "subcategory":"Lawyer & Legal Services",
            "type":"Services"
        }
    ],
    "sg:phone":"+1 415 750 9900",
    "sg:postcode":"94121",
    "sg:province":"CA",
    "wof:name":"Law Offices Of Jason Szydlik",
    "wof:placetype":"venue"
},
  "geometry": {"coordinates":[-122.50865899999999,37.779173],"type":"Point"}
}