{
  "type": "Feature",
  "properties": {
    "iso:country":"US",
    "sg:address":"17510 Pioneer Blvd",
    "sg:city":"Artesia",
    "sg:classifiers":[
        {
            "category":"Health Services",
            "subcategory":"Chiropractor",
            "type":"Services"
        }
    ],
    "sg:phone":"+1 714 220 0980",
    "sg:postcode":"90701",
    "sg:province":"CA",
    "sg:tags":[
        "chiropractic"
    ],
    "wof:name":"Choi Chiropractic Pro Corp",
    "wof:placetype":"venue"
},
  "geometry": {"coordinates":[-118.082207,33.871969],"type":"Point"}
}