{
  "type": "Feature",
  "properties": {
    "iso:country":"US",
    "sg:address":"606 W Mineral King Ave",
    "sg:city":"Visalia",
    "sg:classifiers":[
        {
            "category":"Health Services",
            "subcategory":"Health Practitioner",
            "type":"Services"
        }
    ],
    "sg:phone":"+1 559 733 4550",
    "sg:postcode":"93291",
    "sg:province":"CA",
    "sg:tags":[
        "medical",
        "therapist",
        "center",
        "physical"
    ],
    "wof:name":"Sequoia Rehab & Spt Med Clinic",
    "wof:placetype":"venue"
},
  "geometry": {"coordinates":[-119.297478,36.327362],"type":"Point"}
}