{
  "type": "Feature",
  "properties": {
    "addr:full":"10845 Lindbrook Dr Los Angeles CA 90024",
    "addr:housenumber":"10845",
    "addr:postcode":"90024",
    "addr:street":"Lindbrook Dr",
    "iso:country":"US",
    "sg:address":"10845 Lindbrook Dr",
    "sg:city":"Los Angeles",
    "sg:classifiers":[
        {
            "category":"Real Estate",
            "subcategory":"Architect",
            "type":"Services"
        }
    ],
    "sg:phone":"+1 818 990 9097",
    "sg:postcode":"90024",
    "sg:province":"CA",
    "wof:name":"Architecture Antonoff Interior",
    "wof:placetype":"venue"
},
  "geometry": {"coordinates":[-118.44300800000001,34.060151],"type":"Point"}
}