{
  "type": "Feature",
  "properties": {
    "addr:full":"26601 Ave Veronica Mission Viejo CA 92691",
    "addr:postcode":"26601;92691",
    "addr:street":"Ave Veronica",
    "iso:country":"US",
    "sg:address":"26601 Ave Veronica",
    "sg:city":"Mission Viejo",
    "sg:classifiers":[
        {
            "category":"Banks & Credit Unions",
            "subcategory":"Bank",
            "type":"Services"
        }
    ],
    "sg:phone":"+1 949 215 0200",
    "sg:postcode":"92691",
    "sg:province":"CA",
    "sg:tags":[
        "loan"
    ],
    "wof:name":"Capital West",
    "wof:placetype":"venue"
},
  "geometry": {"coordinates":[-117.66540000000001,33.61776],"type":"Point"}
}