{
  "type": "Feature",
  "properties": {
    "iso:country":"US",
    "sg:address":"5111 El Cemonte Ave",
    "sg:city":"Davis",
    "sg:classifiers":[
        {
            "category":"Wholesale",
            "subcategory":"Books, Periodicals, & Newspapers",
            "type":"Manufacturing & Wholesale Goods"
        }
    ],
    "sg:phone":"+1 530 297 7711",
    "sg:postcode":"95618",
    "sg:province":"CA",
    "sg:tags":[
        "publisher",
        "book"
    ],
    "wof:name":"Christian World Publishers",
    "wof:placetype":"venue"
},
  "geometry": {"coordinates":[-121.689002,38.54872],"type":"Point"}
}