{
  "type": "Feature",
  "properties": {
    "iso:country":"US",
    "sg:address":"11440 W Bernardo Ct",
    "sg:city":"San Diego",
    "sg:classifiers":[
        {
            "category":"Health Services",
            "subcategory":"Nursing And Care Facility",
            "type":"Services"
        }
    ],
    "sg:phone":"+1 858 674 6949",
    "sg:postcode":"92127",
    "sg:province":"CA",
    "sg:tags":[
        "skilled"
    ],
    "wof:name":"Home Hospice Care",
    "wof:placetype":"venue"
},
  "geometry": {"coordinates":[-117.083107,33.020836],"type":"Point"}
}