{
  "type": "Feature",
  "properties": {
    "addr:full":"4557 W Adams Blvd Los Angeles CA 90016",
    "addr:housenumber":"4557",
    "addr:postcode":"90016",
    "addr:street":"W Adams Blvd",
    "iso:country":"US",
    "sg:address":"4557 W Adams Blvd",
    "sg:city":"Los Angeles",
    "sg:classifiers":[
        {
            "category":"Professional",
            "subcategory":"Business Services",
            "type":"Services"
        }
    ],
    "sg:phone":"+1 323 733 4309",
    "sg:postcode":"90016",
    "sg:province":"CA",
    "sg:tags":[
        "recording",
        "studio"
    ],
    "wof:name":"LA Lae Records",
    "wof:placetype":"venue"
},
  "geometry": {"coordinates":[-118.340352,34.032635],"type":"Point"}
}