{
  "type": "Feature",
  "properties": {
    "addr:full":"130 Grace Dr Paso Robles CA 93446",
    "addr:housenumber":"130",
    "addr:postcode":"93446",
    "addr:street":"Grace Dr",
    "iso:country":"US",
    "sg:address":"130 Grace Dr",
    "sg:city":"Paso Robles",
    "sg:classifiers":[
        {
            "category":"Building & Trades",
            "subcategory":"Construction",
            "type":"Services"
        }
    ],
    "sg:phone":"+1 805 227 0289",
    "sg:postcode":"93446",
    "sg:province":"CA",
    "sg:tags":[
        "painter"
    ],
    "wof:name":"J Smith Painting",
    "wof:placetype":"venue"
},
  "geometry": {"coordinates":[-120.504656,35.660986],"type":"Point"}
}