{
  "type": "Feature",
  "properties": {
    "iso:country":"US",
    "sg:address":"6413 Tupelo Dr",
    "sg:city":"Citrus Heights",
    "sg:classifiers":[
        {
            "category":"Real Estate",
            "subcategory":"Real Estate Operator",
            "type":"Services"
        }
    ],
    "sg:phone":"+1 916 729 3652",
    "sg:postcode":"95621",
    "sg:province":"CA",
    "sg:tags":[
        "building",
        "apartment"
    ],
    "wof:name":"Antelope Woods Apartments",
    "wof:placetype":"venue"
},
  "geometry": {"coordinates":[-121.315373,38.704944],"type":"Point"}
}