{
  "type": "Feature",
  "properties": {
    "iso:country":"US",
    "sg:address":"413 Ming Ave",
    "sg:city":"Bakersfield",
    "sg:classifiers":[
        {
            "category":"Shopping",
            "subcategory":"Computers & Home Electronics",
            "type":"Retail Goods"
        }
    ],
    "sg:phone":"+1 661 837 4263",
    "sg:postcode":"93307",
    "sg:province":"CA",
    "sg:tags":[
        "game",
        "video"
    ],
    "wof:name":"Game Exchange",
    "wof:placetype":"venue"
},
  "geometry": {"coordinates":[-119.006424,35.339381],"type":"Point"}
}