{
  "type": "Feature",
  "properties": {
    "addr:full":"8338 Dauphin Dr Stockton CA 95210",
    "addr:housenumber":"8338",
    "addr:postcode":"95210",
    "addr:street":"Dauphin Dr",
    "iso:country":"US",
    "sg:address":"8338 Dauphin Dr",
    "sg:city":"Stockton",
    "sg:classifiers":[
        {
            "category":"Social Services",
            "subcategory":"Child Care",
            "type":"Services"
        }
    ],
    "sg:phone":"+1 209 957 4848",
    "sg:postcode":"95210",
    "sg:province":"CA",
    "wof:name":"Touch Of Love Childcare",
    "wof:placetype":"venue"
},
  "geometry": {"coordinates":[-121.29090100000001,38.025252],"type":"Point"}
}