{
  "type": "Feature",
  "properties": {
    "iso:country":"US",
    "sg:address":"13501 San Pablo Ave",
    "sg:city":"San Pablo",
    "sg:classifiers":[
        {
            "category":"Restaurant",
            "type":"Food & Drink"
        }
    ],
    "sg:phone":"+1 510 236 2226",
    "sg:postcode":"94806",
    "sg:province":"CA",
    "wof:name":"Cabo Taqueria",
    "wof:placetype":"venue"
},
  "geometry": {"coordinates":[-122.336371,37.956008],"type":"Point"}
}