{
  "type": "Feature",
  "properties": {
    "addr:full":"6912 S San Pedro St Los Angeles CA 90003",
    "addr:housenumber":"6912",
    "addr:postcode":"90003",
    "addr:street":"S San Pedro St",
    "iso:country":"US",
    "sg:address":"6912 S San Pedro St",
    "sg:city":"Los Angeles",
    "sg:classifiers":[
        {
            "category":"Food & Beverages",
            "subcategory":"Liquor & Beverages",
            "type":"Retail Goods"
        }
    ],
    "sg:phone":"+1 323 758 3565",
    "sg:postcode":"90003",
    "sg:province":"CA",
    "wof:name":"Marty's Liquor",
    "wof:placetype":"venue"
},
  "geometry": {"coordinates":[-118.26947199999999,33.976267],"type":"Point"}
}