{
  "type": "Feature",
  "properties": {
    "addr:full":"501 E Foothill Blvd Azusa CA 91702",
    "addr:housenumber":"501",
    "addr:postcode":"91702",
    "addr:street":"E Foothill Blvd",
    "iso:country":"US",
    "sg:address":"501 E Foothill Blvd",
    "sg:city":"Azusa",
    "sg:classifiers":[
        {
            "category":"Social Services",
            "type":"Services"
        }
    ],
    "sg:phone":"+1 626 969 2397",
    "sg:postcode":"91702",
    "sg:province":"CA",
    "sg:tags":[
        "food",
        "banks"
    ],
    "wof:name":"Azusa Community Food Bank",
    "wof:placetype":"venue"
},
  "geometry": {"coordinates":[-117.901911,34.133443],"type":"Point"}
}