{
  "type": "Feature",
  "properties": {
    "iso:country":"US",
    "sg:address":"15454 Valley Blvd",
    "sg:city":"City Of Industry",
    "sg:classifiers":[
        {
            "category":"Professional",
            "subcategory":"Art Services",
            "type":"Services"
        }
    ],
    "sg:phone":"+1 626 855 0305",
    "sg:postcode":"91746",
    "sg:province":"CA",
    "sg:tags":[
        "graphic",
        "designer"
    ],
    "wof:name":"Kevin Tuan Design Studios",
    "wof:placetype":"venue"
},
  "geometry": {"coordinates":[-117.96364800000001,34.026753],"type":"Point"}
}