{
  "type": "Feature",
  "properties": {
    "addr:full":"129 S Hacienda Blvd City Of Industry CA 91745",
    "addr:housenumber":"129",
    "addr:postcode":"91745",
    "addr:street":"S Hacienda Blvd",
    "iso:country":"US",
    "sg:address":"129 S Hacienda Blvd",
    "sg:city":"City Of Industry",
    "sg:classifiers":[
        {
            "category":"Shopping",
            "subcategory":"Bicycles & Sporting Goods",
            "type":"Retail Goods"
        }
    ],
    "sg:phone":"+1 626 336 6222",
    "sg:postcode":"91745",
    "sg:province":"CA",
    "sg:tags":[
        "gun",
        "gunsmith"
    ],
    "wof:name":"Old West Guns",
    "wof:placetype":"venue"
},
  "geometry": {"coordinates":[-117.959656,34.017622],"type":"Point"}
}