{
  "type": "Feature",
  "properties": {
    "addr:full":"6206 Topiary St Carlsbad CA 92009",
    "addr:housenumber":"6206",
    "addr:postcode":"92009",
    "addr:street":"Topiary St",
    "iso:country":"US",
    "sg:address":"6206 Topiary St",
    "sg:city":"Carlsbad",
    "sg:classifiers":[
        {
            "category":"Travel",
            "subcategory":"Hotels & Motels",
            "type":"Entertainment"
        }
    ],
    "sg:phone":"+1 760 814 1688",
    "sg:postcode":"92009",
    "sg:province":"CA",
    "sg:tags":[
        "house",
        "guest"
    ],
    "sg:website":"www.homeaway.com/vacation-rental...",
    "wof:name":"Bella Villa Siena",
    "wof:placetype":"venue"
},
  "geometry": {"coordinates":[-117.25848000000001,33.127037],"type":"Point"}
}