{
  "type": "Feature",
  "properties": {
    "iso:country":"US",
    "sg:address":"6446 Fremont St",
    "sg:city":"Riverside",
    "sg:classifiers":[
        {
            "category":"Wholesale",
            "subcategory":"Motor Vehicles",
            "type":"Manufacturing & Wholesale Goods"
        }
    ],
    "sg:phone":"+1 951 689 6000",
    "sg:postcode":"92504",
    "sg:province":"CA",
    "sg:tags":[
        "business"
    ],
    "wof:name":"California Auto Dealer Exch",
    "wof:placetype":"venue"
},
  "geometry": {"coordinates":[-117.437005,33.959025],"type":"Point"}
}