{
  "type": "Feature",
  "properties": {
    "addr:full":"756 S 5th St Montebello CA 90640",
    "addr:housenumber":"756",
    "addr:postcode":"90640",
    "addr:street":"S 5Th St",
    "iso:country":"US",
    "sg:address":"756 S 5th St",
    "sg:city":"Montebello",
    "sg:classifiers":[
        {
            "category":"Freight",
            "type":"Transportation"
        }
    ],
    "sg:phone":"+1 323 726 2497",
    "sg:postcode":"90640",
    "sg:province":"CA",
    "sg:tags":[
        "operator",
        "local",
        "trucking"
    ],
    "wof:name":"Spr Trucking Inc",
    "wof:placetype":"venue"
},
  "geometry": {"coordinates":[-118.110989,33.998288],"type":"Point"}
}