{
  "type": "Feature",
  "properties": {
    "addr:full":"457 Grass Valley Hwy Auburn CA 95603",
    "addr:housenumber":"457",
    "addr:postcode":"ca 95603",
    "addr:street":"Grass Valley Hwy",
    "iso:country":"US",
    "sg:address":"457 Grass Valley Hwy",
    "sg:city":"Auburn",
    "sg:classifiers":[
        {
            "category":"Wholesale",
            "subcategory":"Medical Equipment & Supplies",
            "type":"Manufacturing & Wholesale Goods"
        }
    ],
    "sg:phone":"+1 530 823 3937",
    "sg:postcode":"95603",
    "sg:province":"CA",
    "sg:tags":[
        "ophthalmic"
    ],
    "wof:name":"Placer Optical",
    "wof:placetype":"venue"
},
  "geometry": {"coordinates":[-121.07661,38.905359],"type":"Point"}
}