{
  "type": "Feature",
  "properties": {
    "iso:country":"US",
    "sg:address":"2 Dewberry Way",
    "sg:city":"Irvine",
    "sg:classifiers":[
        {
            "category":"Professional",
            "type":"Services"
        }
    ],
    "sg:phone":"+1 949 786 0567",
    "sg:postcode":"92612",
    "sg:province":"CA",
    "wof:name":"Precocious Digital Imaging",
    "wof:placetype":"venue"
},
  "geometry": {"coordinates":[-117.821766,33.659434],"type":"Point"}
}