{
  "type": "Feature",
  "properties": {
    "addr:full":"6311 Romaine St Los Angeles CA 90038",
    "addr:postcode":"6311;90038",
    "addr:street":"Romaine St",
    "iso:country":"US",
    "sg:address":"6311 Romaine St",
    "sg:city":"Los Angeles",
    "sg:classifiers":[
        {
            "category":"Professional",
            "type":"Services"
        }
    ],
    "sg:phone":"+1 323 463 6497",
    "sg:postcode":"90038",
    "sg:province":"CA",
    "sg:tags":[
        "establishment"
    ],
    "wof:name":"Innovative Cutting Enterprises",
    "wof:placetype":"venue"
},
  "geometry": {"coordinates":[-118.324926,34.089005],"type":"Point"}
}