{
  "type": "Feature",
  "properties": {
    "addr:full":"4949 Stevenson Blvd Fremont CA 94538",
    "addr:housenumber":"4949",
    "addr:postcode":"94538",
    "addr:street":"Stevenson Blvd",
    "iso:country":"US",
    "sg:address":"4949 Stevenson Blvd",
    "sg:city":"Fremont",
    "sg:classifiers":[
        {
            "category":"Food & Beverages",
            "subcategory":"Groceries & Convenience Stores",
            "type":"Retail Goods"
        }
    ],
    "sg:phone":"+1 510 656 5522",
    "sg:postcode":"94538",
    "sg:province":"CA",
    "sg:tags":[
        "grocer"
    ],
    "wof:name":"Albertsons",
    "wof:placetype":"venue"
},
  "geometry": {"coordinates":[-121.982258,37.529572],"type":"Point"}
}