{
  "type": "Feature",
  "properties": {
    "iso:country":"US",
    "sg:address":"17630 Rolling Hills Blvd",
    "sg:city":"Jamestown",
    "sg:classifiers":[
        {
            "category":"Restaurant",
            "type":"Food & Drink"
        }
    ],
    "sg:phone":"+1 209 984 0810",
    "sg:postcode":"95327",
    "sg:province":"CA",
    "wof:name":"Baja Sur Enterprises",
    "wof:placetype":"venue"
},
  "geometry": {"coordinates":[-120.42761299999999,37.942555],"type":"Point"}
}