{
  "type": "Feature",
  "properties": {
    "addr:full":"5607 Santa Anita Ave Temple City CA 91780",
    "addr:housenumber":"5607",
    "addr:postcode":"91780",
    "addr:street":"Santa Anita Ave",
    "iso:country":"US",
    "sg:address":"5607 Santa Anita Ave",
    "sg:city":"Temple City",
    "sg:classifiers":[
        {
            "category":"Real Estate",
            "subcategory":"Real Estate Operator",
            "type":"Services"
        }
    ],
    "sg:phone":"+1 626 444 3757",
    "sg:postcode":"91780",
    "sg:province":"CA",
    "sg:tags":[
        "apartment"
    ],
    "wof:name":"Park Plaza Apartments",
    "wof:placetype":"venue"
},
  "geometry": {"coordinates":[-118.030125,34.10466],"type":"Point"}
}