{
  "type": "Feature",
  "properties": {
    "iso:country":"US",
    "sg:address":"4752 Felspar St",
    "sg:city":"Riverside",
    "sg:classifiers":[
        {
            "category":"Organizations",
            "subcategory":"Religious Organization",
            "type":"Services"
        }
    ],
    "sg:phone":"+1 951 360 3000",
    "sg:postcode":"92509",
    "sg:province":"CA",
    "sg:tags":[
        "church"
    ],
    "wof:name":"Faith Community Church",
    "wof:placetype":"venue"
},
  "geometry": {"coordinates":[-117.48405700000001,34.000122],"type":"Point"}
}