{
  "type": "Feature",
  "properties": {
    "addr:full":"72050 Varner Rd Thousand Palms CA 92276",
    "addr:postcode":"72050;92276",
    "addr:street":"Varner Rd",
    "iso:country":"US",
    "sg:address":"72050 Varner Rd",
    "sg:city":"Thousand Palms",
    "sg:classifiers":[
        {
            "category":"Freight",
            "type":"Transportation"
        }
    ],
    "sg:phone":"+1 760 343 3464",
    "sg:postcode":"92276",
    "sg:province":"CA",
    "sg:tags":[
        "local",
        "mover",
        "storage",
        "trucking"
    ],
    "sg:website":"www.meritmovingsystems.com",
    "wof:name":"Merit Moving Systems Inc",
    "wof:placetype":"venue"
},
  "geometry": {"coordinates":[-116.401241,33.816389],"type":"Point"}
}