{
  "type": "Feature",
  "properties": {
    "addr:full":"1427 Via Corta La Verne CA 91750",
    "addr:housenumber":"1427",
    "addr:postcode":"91750",
    "addr:street":"Via Corta",
    "iso:country":"US",
    "sg:address":"1427 Via Corta",
    "sg:city":"La Verne",
    "sg:classifiers":[
        {
            "category":"Shopping",
            "subcategory":"Gifts & Souvenirs",
            "type":"Retail Goods"
        }
    ],
    "sg:phone":"+1 909 392 0202",
    "sg:postcode":"91750",
    "sg:province":"CA",
    "sg:tags":[
        "practitioner",
        "commercial",
        "health",
        "bank"
    ],
    "wof:name":"Centerline Technical",
    "wof:placetype":"venue"
},
  "geometry": {"coordinates":[-117.775762,34.125998],"type":"Point"}
}