{
  "type": "Feature",
  "properties": {
    "iso:country":"US",
    "sg:address":"999 Ocean Ave",
    "sg:city":"San Francisco",
    "sg:classifiers":[
        {
            "category":"Autos & Motor Vehicles",
            "subcategory":"Fuel & Gas Station",
            "type":"Retail Goods"
        }
    ],
    "sg:phone":"+1 415 585 8296",
    "sg:postcode":"94112",
    "sg:province":"CA",
    "sg:tags":[
        "oil"
    ],
    "wof:name":"Pacific Enterprise",
    "wof:placetype":"venue"
},
  "geometry": {"coordinates":[-122.452332,37.723079],"type":"Point"}
}