{
  "type": "Feature",
  "properties": {
    "addr:full":"1401 E Grand Ave Arroyo Grande CA 93420",
    "addr:housenumber":"1401",
    "addr:postcode":"93420",
    "addr:street":"E Grand Ave",
    "iso:country":"US",
    "sg:address":"1401 E Grand Ave",
    "sg:city":"Arroyo Grande",
    "sg:classifiers":[
        {
            "category":"Restaurant",
            "type":"Food & Drink"
        }
    ],
    "sg:menulink":"http://www.allmenus.com/ca/arroyo-grande/239774-panda-express/menu/",
    "sg:phone":"+1 805 489 8780",
    "sg:postcode":"93420",
    "sg:province":"CA",
    "sg:tags":[
        "asian",
        "chinese"
    ],
    "wof:name":"Panda Express",
    "wof:placetype":"venue"
},
  "geometry": {"coordinates":[-120.605362,35.120727],"type":"Point"}
}