{
  "type": "Feature",
  "properties": {
    "addr:full":"1073 Saratoga Ave San Jose CA 95129",
    "addr:housenumber":"1073",
    "addr:postcode":"95129",
    "addr:street":"Saratoga Ave",
    "iso:country":"US",
    "sg:address":"1073 Saratoga Ave",
    "sg:city":"San Jose",
    "sg:classifiers":[
        {
            "category":"Manufacturing",
            "subcategory":"Printing",
            "type":"Manufacturing & Wholesale Goods"
        }
    ],
    "sg:phone":"+1 408 861 0164",
    "sg:postcode":"95129",
    "sg:province":"CA",
    "sg:tags":[
        "multimedia"
    ],
    "wof:name":"Signature Digital Multimedia",
    "wof:placetype":"venue"
},
  "geometry": {"coordinates":[-121.978179,37.306537],"type":"Point"}
}