{
  "type": "Feature",
  "properties": {
    "addr:full":"1045 Hermosa Ave Pomona CA 91767",
    "addr:housenumber":"1045",
    "addr:postcode":"91767",
    "addr:street":"Hermosa Ave",
    "iso:country":"US",
    "sg:address":"1045 Hermosa Ave",
    "sg:city":"Pomona",
    "sg:classifiers":[
        {
            "category":"Home & Garden",
            "subcategory":"Furniture",
            "type":"Retail Goods"
        }
    ],
    "sg:phone":"+1 909 397 9016",
    "sg:postcode":"91767",
    "sg:province":"CA",
    "sg:tags":[
        "store"
    ],
    "wof:name":"M&G Furniture",
    "wof:placetype":"venue"
},
  "geometry": {"coordinates":[-117.730225,34.076649],"type":"Point"}
}