{
  "type": "Feature",
  "properties": {
    "iso:country":"US",
    "sg:address":"2160 E Dominguez St",
    "sg:city":"Long Beach",
    "sg:classifiers":[
        {
            "category":"Professional",
            "subcategory":"Computer Services",
            "type":"Services"
        }
    ],
    "sg:phone":"+1 949 588 1495",
    "sg:postcode":"90810",
    "sg:province":"CA",
    "sg:tags":[
        "sell",
        "develop",
        "software"
    ],
    "wof:name":"Mitrix Inc",
    "wof:placetype":"venue"
},
  "geometry": {"coordinates":[-118.235712,33.839134],"type":"Point"}
}