{
  "type": "Feature",
  "properties": {
    "iso:country":"US",
    "sg:address":"1911 Douglas Blvd",
    "sg:city":"Roseville",
    "sg:classifiers":[
        {
            "category":"Building & Trades",
            "subcategory":"Cleaning & Sanitation",
            "type":"Services"
        }
    ],
    "sg:phone":"+1 916 483 2736",
    "sg:postcode":"95661",
    "sg:province":"CA",
    "sg:tags":[
        "cleaning-industrial",
        "contractor"
    ],
    "wof:name":"All American Sweeping Co Inc",
    "wof:placetype":"venue"
},
  "geometry": {"coordinates":[-121.25730900000001,38.744241],"type":"Point"}
}