{
  "type": "Feature",
  "properties": {
    "iso:country":"US",
    "sg:address":"2055 Hoffman Ln",
    "sg:city":"Napa",
    "sg:classifiers":[
        {
            "category":"Manufacturing",
            "subcategory":"Food",
            "type":"Manufacturing & Wholesale Goods"
        }
    ],
    "sg:phone":"+1 707 945 0921",
    "sg:postcode":"94558",
    "sg:province":"CA",
    "sg:tags":[
        "winery"
    ],
    "sg:website":"www.havenswine.com",
    "wof:name":"Havens Wine Cellars",
    "wof:placetype":"venue"
},
  "geometry": {"coordinates":[-122.350718,38.384881],"type":"Point"}
}