{
  "type": "Feature",
  "properties": {
    "addr:full":"5643 Telegraph Ave Oakland CA 94609",
    "addr:housenumber":"5643",
    "addr:postcode":"94609",
    "addr:street":"Telegraph Ave",
    "iso:country":"US",
    "sg:address":"5643 Telegraph Ave",
    "sg:city":"Oakland",
    "sg:classifiers":[
        {
            "category":"Taxi",
            "type":"Transportation"
        }
    ],
    "sg:phone":"+1 510 655 5555",
    "sg:postcode":"94609",
    "sg:province":"CA",
    "sg:tags":[
        "taxicab"
    ],
    "wof:name":"Airport Cab Express Svc",
    "wof:placetype":"venue"
},
  "geometry": {"coordinates":[-122.261673,37.843032],"type":"Point"}
}