{
  "type": "Feature",
  "properties": {
    "iso:country":"US",
    "sg:address":"1801 Park Court Pl",
    "sg:city":"Santa Ana",
    "sg:classifiers":[
        {
            "category":"Professional",
            "subcategory":"Lawyer & Legal Services",
            "type":"Services"
        }
    ],
    "sg:phone":"+1 714 543 1877",
    "sg:postcode":"92701",
    "sg:province":"CA",
    "wof:name":"Law Office of Timothyjgray",
    "wof:placetype":"venue"
},
  "geometry": {"coordinates":[-117.84200300000001,33.749901],"type":"Point"}
}