{
  "type": "Feature",
  "properties": {
    "iso:country":"US",
    "sg:address":"290 De Haro St",
    "sg:city":"San Francisco",
    "sg:classifiers":[
        {
            "category":"Sports & Exercise",
            "subcategory":"Gym",
            "type":"Entertainment"
        }
    ],
    "sg:postcode":"94103",
    "sg:province":"CA",
    "sg:website":"crossfitph.com",
    "wof:name":"CrossFit Potrero Hill",
    "wof:placetype":"venue"
},
  "geometry": {"coordinates":[-122.401751,37.766249],"type":"Point"}
}