{
  "type": "Feature",
  "properties": {
    "addr:full":"42200 Moraga Rd Temecula CA 92591",
    "addr:postcode":"42200;92591",
    "addr:street":"Moraga Rd",
    "iso:country":"US",
    "sg:address":"42200 Moraga Rd",
    "sg:city":"Temecula",
    "sg:classifiers":[
        {
            "category":"Real Estate",
            "subcategory":"Real Estate Operator",
            "type":"Services"
        }
    ],
    "sg:phone":"+1 951 676 7563",
    "sg:postcode":"92591",
    "sg:province":"CA",
    "sg:tags":[
        "apartment"
    ],
    "wof:name":"Woodcreek Apartments",
    "wof:placetype":"venue"
},
  "geometry": {"coordinates":[-117.140396,33.508535],"type":"Point"}
}