{
  "type": "Feature",
  "properties": {
    "addr:full":"13566 el Camino Real Atascadero CA 93422",
    "addr:housenumber":"13566",
    "addr:postcode":"93422",
    "addr:street":"El Camino Real",
    "iso:country":"US",
    "sg:address":"13566 el Camino Real",
    "sg:city":"Atascadero",
    "sg:classifiers":[
        {
            "category":"Building & Trades",
            "subcategory":"Construction",
            "type":"Services"
        }
    ],
    "sg:phone":"+1 805 466 1316",
    "sg:postcode":"93422",
    "sg:province":"CA",
    "sg:tags":[
        "contractor"
    ],
    "wof:name":"Mark Ginder Construction",
    "wof:placetype":"venue"
},
  "geometry": {"coordinates":[-120.62290400000001,35.436597],"type":"Point"}
}