{
  "type": "Feature",
  "properties": {
    "addr:full":"331 W 7th St San Pedro CA 90731",
    "addr:housenumber":"331",
    "addr:postcode":"90731",
    "addr:street":"W 7Th St",
    "iso:country":"US",
    "sg:address":"331 W 7th St",
    "sg:city":"San Pedro",
    "sg:classifiers":[
        {
            "category":"Shopping",
            "subcategory":"Gifts & Souvenirs",
            "type":"Retail Goods"
        }
    ],
    "sg:phone":"+1 310 547 1712",
    "sg:postcode":"90731",
    "sg:province":"CA",
    "wof:name":"Antiques A Place To Dream",
    "wof:placetype":"venue"
},
  "geometry": {"coordinates":[-118.28520899999999,33.737765],"type":"Point"}
}