{
  "type": "Feature",
  "properties": {
    "iso:country":"US",
    "sg:address":"1110 S Oregon St",
    "sg:city":"Yreka",
    "sg:classifiers":[
        {
            "category":"Wholesale",
            "subcategory":"Motor Vehicles",
            "type":"Manufacturing & Wholesale Goods"
        }
    ],
    "sg:phone":"+1 530 842 4844",
    "sg:postcode":"96097",
    "sg:province":"CA",
    "sg:tags":[
        "rental"
    ],
    "wof:name":"Stan Burrell",
    "wof:placetype":"venue"
},
  "geometry": {"coordinates":[-122.64165300000001,41.722081],"type":"Point"}
}