{
  "type": "Feature",
  "properties": {
    "iso:country":"US",
    "sg:address":"1836 Fire Mountain Dr",
    "sg:city":"Oceanside",
    "sg:classifiers":[
        {
            "category":"Professional",
            "type":"Services"
        }
    ],
    "sg:phone":"+1 760 967 1591",
    "sg:postcode":"92054",
    "sg:province":"CA",
    "wof:name":"Blindmaker",
    "wof:placetype":"venue"
},
  "geometry": {"coordinates":[-117.34848100000001,33.187092],"type":"Point"}
}