{
  "type": "Feature",
  "properties": {
    "addr:full":"197 S 10th St Grover Beach CA 93433",
    "addr:housenumber":"197",
    "addr:postcode":"93433",
    "addr:street":"S 10Th St",
    "iso:country":"US",
    "sg:address":"197 S 10th St",
    "sg:city":"Grover Beach",
    "sg:classifiers":[
        {
            "category":"Insurance",
            "subcategory":"Insurance Agent",
            "type":"Services"
        }
    ],
    "sg:phone":"+1 805 489 1781",
    "sg:postcode":"93433",
    "sg:province":"CA",
    "sg:website":"www.primerica.com",
    "wof:name":"Primerica Financial Svc",
    "wof:placetype":"venue"
},
  "geometry": {"coordinates":[-120.61899099999999,35.120391],"type":"Point"}
}