{
  "type": "Feature",
  "properties": {
    "iso:country":"US",
    "sg:address":"2480 Mission St Ste 217",
    "sg:city":"San Francisco",
    "sg:classifiers":[
        {
            "category":"Health Services",
            "subcategory":"Health Practitioner",
            "type":"Services"
        }
    ],
    "sg:phone":"+1 415 282 3700",
    "sg:postcode":"94110",
    "sg:province":"CA",
    "sg:tags":[
        "therapy",
        "physical"
    ],
    "wof:name":"Marat Diner Physical Therapy",
    "wof:placetype":"venue"
},
  "geometry": {"coordinates":[-122.41909,37.757312],"type":"Point"}
}