{
  "type": "Feature",
  "properties": {
    "addr:full":"1420 Lakeshore Ave Oakland CA 94606",
    "addr:housenumber":"1420",
    "addr:postcode":"94606",
    "addr:street":"Lakeshore Ave",
    "iso:country":"US",
    "sg:address":"1420 Lakeshore Ave",
    "sg:city":"Oakland",
    "sg:classifiers":[
        {
            "category":"Real Estate",
            "subcategory":"Real Estate Operator",
            "type":"Services"
        }
    ],
    "sg:phone":"+1 510 834 5328",
    "sg:postcode":"94606",
    "sg:province":"CA",
    "sg:tags":[
        "apartment"
    ],
    "wof:name":"Lakeshore Garden Apartments",
    "wof:placetype":"venue"
},
  "geometry": {"coordinates":[-122.25700399999999,37.799801],"type":"Point"}
}