{
  "type": "Feature",
  "properties": {
    "addr:full":"2323 Oak Park Ln Santa Barbara CA 93105",
    "addr:housenumber":"2323",
    "addr:postcode":"93105",
    "addr:street":"Oak Park Ln",
    "iso:country":"US",
    "sg:address":"2323 Oak Park Ln",
    "sg:city":"Santa Barbara",
    "sg:classifiers":[
        {
            "category":"Health Services",
            "subcategory":"Doctor",
            "type":"Services"
        }
    ],
    "sg:phone":"+1 805 569 2221",
    "sg:postcode":"93105",
    "sg:province":"CA",
    "sg:tags":[
        "physician",
        "surgeon"
    ],
    "wof:name":"Ralph L Green MD",
    "wof:placetype":"venue"
},
  "geometry": {"coordinates":[-119.725291,34.429044],"type":"Point"}
}