{
  "type": "Feature",
  "properties": {
    "addr:full":"21230 Homestead Rd Cupertino CA 95014",
    "addr:housenumber":"21230",
    "addr:postcode":"95014",
    "addr:street":"Homestead Rd",
    "iso:country":"US",
    "sg:address":"21230 Homestead Rd",
    "sg:city":"Cupertino",
    "sg:classifiers":[
        {
            "category":"Wholesale",
            "subcategory":"Durable Goods & Equipment",
            "type":"Manufacturing & Wholesale Goods"
        }
    ],
    "sg:phone":"+1 408 738 5658",
    "sg:postcode":"95014",
    "sg:province":"CA",
    "sg:tags":[
        "importer"
    ],
    "wof:name":"Gil Han Trade Corp",
    "wof:placetype":"venue"
},
  "geometry": {"coordinates":[-122.04548800000001,37.337465],"type":"Point"}
}