{
  "type": "Feature",
  "properties": {
    "iso:country":"US",
    "sg:address":"937 1st St",
    "sg:city":"Encinitas",
    "sg:classifiers":[
        {
            "category":"Home & Garden",
            "subcategory":"Building Materials",
            "type":"Retail Goods"
        }
    ],
    "sg:phone":"+1 760 557 1038",
    "sg:postcode":"92024",
    "sg:province":"CA",
    "sg:tags":[
        "windows"
    ],
    "wof:name":"A Plus Windows",
    "wof:placetype":"venue"
},
  "geometry": {"coordinates":[-117.29293800000001,33.039907],"type":"Point"}
}