{
  "type": "Feature",
  "properties": {
    "iso:country":"US",
    "sg:address":"101 Boas Dr",
    "sg:city":"Santa Rosa",
    "sg:classifiers":[
        {
            "category":"Real Estate",
            "subcategory":"Real Estate Operator",
            "type":"Services"
        }
    ],
    "sg:phone":"+1 707 538 2490",
    "sg:postcode":"95409",
    "sg:province":"CA",
    "sg:tags":[
        "building",
        "apartment"
    ],
    "wof:name":"Woodcreek Village Apartments",
    "wof:placetype":"venue"
},
  "geometry": {"coordinates":[-122.657922,38.465735],"type":"Point"}
}