{
  "type": "Feature",
  "properties": {
    "iso:country":"US",
    "sg:address":"34863 Date St",
    "sg:city":"Yucaipa",
    "sg:classifiers":[
        {
            "category":"Retail",
            "subcategory":"Auto Repair",
            "type":"Services"
        }
    ],
    "sg:phone":"+1 909 790 1424",
    "sg:postcode":"92399",
    "sg:province":"CA",
    "sg:tags":[
        "body",
        "painting",
        "repairing",
        "automobile"
    ],
    "wof:name":"Casey Jodie S Auto Painting",
    "wof:placetype":"venue"
},
  "geometry": {"coordinates":[-117.044067,34.041119],"type":"Point"}
}