{
  "type": "Feature",
  "properties": {
    "addr:full":"4520 Woodley Ave Encino CA 91436",
    "addr:housenumber":"4520",
    "addr:postcode":"91436",
    "addr:street":"Woodley Ave",
    "iso:country":"US",
    "sg:address":"4520 Woodley Ave",
    "sg:city":"Encino",
    "sg:classifiers":[
        {
            "category":"Personal",
            "type":"Services"
        }
    ],
    "sg:phone":"+1 818 205 1111",
    "sg:postcode":"91436",
    "sg:province":"CA",
    "sg:tags":[
        "credit",
        "debt",
        "counseling"
    ],
    "wof:name":"Credit Team Inc",
    "wof:placetype":"venue"
},
  "geometry": {"coordinates":[-118.48353899999999,34.154439],"type":"Point"}
}