{
  "type": "Feature",
  "properties": {
    "iso:country":"US",
    "sg:address":"32905 Clinton Keith Rd Ste 108",
    "sg:city":"Wildomar",
    "sg:classifiers":[
        {
            "category":"Health Services",
            "subcategory":"Doctor",
            "type":"Services"
        },
        {
            "category":"Health Services",
            "subcategory":"Dentist",
            "type":"Services"
        }
    ],
    "sg:phone":"+1 951 678 9991",
    "sg:postcode":"92595",
    "sg:province":"CA",
    "sg:tags":[
        "dentists-oral",
        "physician",
        "maxillofacial",
        "denture",
        "dentists-prosthodontists",
        "surgeons",
        "dentists-orthodontists",
        "dentistry",
        "implant",
        "oral",
        "surgery",
        "dentists-implantology"
    ],
    "sg:website":"http://www.clintonkeithdental.com/?sc_cid=Paid-LE",
    "wof:name":"Watanabe, Bryan, Dds - Clinton Keith Dental Group",
    "wof:placetype":"venue"
},
  "geometry": {"coordinates":[-117.255691,33.582894],"type":"Point"}
}