{
  "type": "Feature",
  "properties": {
    "addr:full":"221 Richmond St El Segundo CA 90245",
    "addr:housenumber":"221",
    "addr:postcode":"90245",
    "addr:street":"Richmond St",
    "iso:country":"US",
    "sg:address":"221 Richmond St",
    "sg:city":"El Segundo",
    "sg:classifiers":[
        {
            "category":"Bars & Pubs",
            "subcategory":"Lounge",
            "type":"Food & Drink"
        },
        {
            "category":"Bars & Pubs",
            "subcategory":"Dive Bar",
            "type":"Food & Drink"
        }
    ],
    "sg:phone":"+1 310 322 5829",
    "sg:postcode":"90245",
    "sg:province":"CA",
    "wof:name":"Purple Orchid",
    "wof:placetype":"venue"
},
  "geometry": {"coordinates":[-118.417472,33.918494],"type":"Point"}
}