{
  "type": "Feature",
  "properties": {
    "addr:full":"12114 Sherman Way North Hollywood CA 91605",
    "addr:housenumber":"12114",
    "addr:postcode":"91605",
    "addr:street":"Sherman Way",
    "iso:country":"US",
    "sg:address":"12114 Sherman Way",
    "sg:city":"North Hollywood",
    "sg:classifiers":[
        {
            "category":"Wholesale",
            "subcategory":"Apparel",
            "type":"Manufacturing & Wholesale Goods"
        }
    ],
    "sg:phone":"+1 818 764 9158",
    "sg:postcode":"91605",
    "sg:province":"CA",
    "sg:tags":[
        "clothing"
    ],
    "wof:name":"CJ Costume House",
    "wof:placetype":"venue"
},
  "geometry": {"coordinates":[-118.401443,34.20112],"type":"Point"}
}