{
  "type": "Feature",
  "properties": {
    "iso:country":"US",
    "sg:address":"27555 Rimrock Rd",
    "sg:city":"Barstow",
    "sg:classifiers":[
        {
            "category":"Wholesale",
            "subcategory":"Medical Equipment & Supplies",
            "type":"Manufacturing & Wholesale Goods"
        }
    ],
    "sg:phone":"+1 760 252 2025",
    "sg:postcode":"92311",
    "sg:province":"CA",
    "sg:tags":[
        "x",
        "apparatus"
    ],
    "wof:name":"Diagnostic X Ray",
    "wof:placetype":"venue"
},
  "geometry": {"coordinates":[-117.060126,34.877447],"type":"Point"}
}