{
  "type": "Feature",
  "properties": {
    "addr:full":"38 Maple Ave Atherton CA 94027",
    "addr:housenumber":"38",
    "addr:postcode":"94027",
    "addr:street":"Maple Ave",
    "iso:country":"US",
    "sg:address":"38 Maple Ave",
    "sg:city":"Atherton",
    "sg:classifiers":[
        {
            "category":"Shopping",
            "subcategory":"Computers & Home Electronics",
            "type":"Retail Goods"
        }
    ],
    "sg:phone":"+1 925 895 8105",
    "sg:postcode":"94027",
    "sg:province":"CA",
    "sg:tags":[
        "software"
    ],
    "wof:name":"Nexidia",
    "wof:placetype":"venue"
},
  "geometry": {"coordinates":[-122.196406,37.462007],"type":"Point"}
}