{
  "type": "Feature",
  "properties": {
    "addr:full":"3837 N Clark St Fresno CA 93726",
    "addr:housenumber":"3837",
    "addr:postcode":"93726",
    "addr:street":"N Clark St",
    "iso:country":"US",
    "sg:address":"3837 N Clark St",
    "sg:city":"Fresno",
    "sg:classifiers":[
        {
            "category":"Health Services",
            "subcategory":"Clinic",
            "type":"Services"
        },
        {
            "category":"Community Center",
            "type":"Public Place"
        }
    ],
    "sg:phone":"+1 559 459 1550",
    "sg:postcode":"93726",
    "sg:province":"CA",
    "sg:tags":[
        "medical"
    ],
    "wof:name":"Adult Health Center At Sierra",
    "wof:placetype":"venue"
},
  "geometry": {"coordinates":[-119.785179,36.787481],"type":"Point"}
}