{
  "type": "Feature",
  "properties": {
    "addr:full":"8453 Florin Rd Sacramento CA 95828",
    "addr:housenumber":"8453",
    "addr:postcode":"95828",
    "addr:street":"Florin Rd",
    "iso:country":"US",
    "sg:address":"8453 Florin Rd",
    "sg:city":"Sacramento",
    "sg:classifiers":[
        {
            "category":"Real Estate",
            "subcategory":"Real Estate Agent",
            "type":"Services"
        }
    ],
    "sg:phone":"+1 916 381 4045",
    "sg:postcode":"95828",
    "sg:province":"CA",
    "wof:name":"E-Z Home Real Estate Inc",
    "wof:placetype":"venue"
},
  "geometry": {"coordinates":[-121.39270399999999,38.496155],"type":"Point"}
}