{
  "type": "Feature",
  "properties": {
    "iso:country":"US",
    "sg:address":"6114 N Figueroa St",
    "sg:city":"Los Angeles",
    "sg:classifiers":[
        {
            "category":"Organizations",
            "subcategory":"Religious Organization",
            "type":"Services"
        }
    ],
    "sg:phone":"+1 323 340 8192",
    "sg:postcode":"90042",
    "sg:province":"CA",
    "sg:tags":[
        "church"
    ],
    "wof:name":"Crossover Ministires El Camino",
    "wof:placetype":"venue"
},
  "geometry": {"coordinates":[-118.186237,34.113484],"type":"Point"}
}