{
  "type": "Feature",
  "properties": {
    "addr:full":"7738 Deer Trl Yucca Valley CA 92284",
    "addr:housenumber":"7738",
    "addr:postcode":"92284",
    "addr:street":"Deer Trl",
    "iso:country":"US",
    "sg:address":"7738 Deer Trl",
    "sg:city":"Yucca Valley",
    "sg:classifiers":[
        {
            "category":"Professional",
            "subcategory":"Engineering",
            "type":"Services"
        }
    ],
    "sg:phone":"+1 760 365 4792",
    "sg:postcode":"92284",
    "sg:province":"CA",
    "sg:tags":[
        "general",
        "contractor"
    ],
    "wof:name":"Curtis & Curtis",
    "wof:placetype":"venue"
},
  "geometry": {"coordinates":[-116.44555200000001,34.111352],"type":"Point"}
}