{
  "type": "Feature",
  "properties": {
    "iso:country":"US",
    "sg:address":"7738 Deer Trl",
    "sg:city":"Yucca Valley",
    "sg:classifiers":[
        {
            "category":"Professional",
            "subcategory":"Engineering",
            "type":"Services"
        }
    ],
    "sg:phone":"+1 760 365 4792",
    "sg:postcode":"92284",
    "sg:province":"CA",
    "sg:tags":[
        "general",
        "contractor"
    ],
    "wof:name":"Curtis & Curtis",
    "wof:placetype":"venue"
},
  "geometry": {"coordinates":[-116.445552,34.111352],"type":"Point"}
}