{
  "type": "Feature",
  "properties": {
    "addr:full":"1005 12th St Ste C Sacramento CA 95814",
    "addr:housenumber":"1005",
    "addr:postcode":"95814",
    "addr:street":"12Th St Ste C",
    "iso:country":"US",
    "sg:address":"1005 12th St Ste C",
    "sg:city":"Sacramento",
    "sg:classifiers":[
        {
            "category":"Organizations",
            "subcategory":"Political Organization",
            "type":"Services"
        }
    ],
    "sg:phone":"+1 916 443 1792",
    "sg:postcode":"95814",
    "sg:province":"CA",
    "sg:website":"http://www.commoncauseri.org",
    "wof:name":"California Common Cause",
    "wof:placetype":"venue"
},
  "geometry": {"coordinates":[-121.490803,38.579575],"type":"Point"}
}