{
  "type": "Feature",
  "properties": {
    "iso:country":"US",
    "sg:address":"1605 S Hoover St",
    "sg:city":"Los Angeles",
    "sg:classifiers":[
        {
            "category":"Retail",
            "subcategory":"Photofinishing",
            "type":"Services"
        }
    ],
    "sg:phone":"+1 213 765 0535",
    "sg:postcode":"90006",
    "sg:province":"CA",
    "sg:tags":[
        "photo",
        "finishing"
    ],
    "wof:name":"Photo Focus",
    "wof:placetype":"venue"
},
  "geometry": {"coordinates":[-118.284206,34.042866],"type":"Point"}
}