{
  "type": "Feature",
  "properties": {
    "addr:full":"3916 Cork Ln Bakersfield CA 93309",
    "addr:housenumber":"3916",
    "addr:postcode":"93309",
    "addr:street":"Cork Ln",
    "iso:country":"US",
    "sg:address":"3916 Cork Ln",
    "sg:city":"Bakersfield",
    "sg:classifiers":[
        {
            "category":"Professional",
            "subcategory":"Management & Consulting",
            "type":"Services"
        }
    ],
    "sg:phone":"+1 661 397 5560",
    "sg:postcode":"93309",
    "sg:province":"CA",
    "sg:tags":[
        "home",
        "demonstration"
    ],
    "wof:name":"Amway Distributors",
    "wof:placetype":"venue"
},
  "geometry": {"coordinates":[-119.048936,35.343665],"type":"Point"}
}