{
  "type": "Feature",
  "properties": {
    "addr:full":"5054 W Washington Blvd Los Angeles CA 90016",
    "addr:housenumber":"5054",
    "addr:postcode":"90016",
    "addr:street":"W Washington Blvd",
    "iso:country":"US",
    "sg:address":"5054 W Washington Blvd",
    "sg:city":"Los Angeles",
    "sg:classifiers":[
        {
            "category":"Retail",
            "subcategory":"Auto Repair",
            "type":"Services"
        }
    ],
    "sg:phone":"+1 323 935 5900",
    "sg:postcode":"90016",
    "sg:province":"CA",
    "wof:name":"S & H Automotive",
    "wof:placetype":"venue"
},
  "geometry": {"coordinates":[-118.349779,34.06847],"type":"Point"}
}