{
  "type": "Feature",
  "properties": {
    "iso:country":"US",
    "sg:address":"823 Maple Ave",
    "sg:city":"Los Angeles",
    "sg:classifiers":[
        {
            "category":"Wholesale",
            "subcategory":"Apparel",
            "type":"Manufacturing & Wholesale Goods"
        },
        {
            "category":"Shopping",
            "subcategory":"Clothing, Apparel, & Fashions",
            "type":"Retail Goods"
        }
    ],
    "sg:phone":"+1 213 489 7910",
    "sg:postcode":"90014",
    "sg:province":"CA",
    "sg:tags":[
        "shop",
        "bridal",
        "piece"
    ],
    "wof:name":"Massachi Behrouz",
    "wof:placetype":"venue"
},
  "geometry": {"coordinates":[-118.252475,34.039832],"type":"Point"}
}