{
  "type": "Feature",
  "properties": {
    "iso:country":"US",
    "sg:address":"715 N Mountain Ave",
    "sg:city":"Upland",
    "sg:classifiers":[
        {
            "category":"Real Estate",
            "subcategory":"Real Estate Agent",
            "type":"Services"
        }
    ],
    "sg:phone":"+1 909 373 1058",
    "sg:postcode":"91786",
    "sg:province":"CA",
    "sg:tags":[
        "inspection"
    ],
    "wof:name":"Brunsma & Associates",
    "wof:placetype":"venue"
},
  "geometry": {"coordinates":[-117.670259,34.102636],"type":"Point"}
}