{
  "type": "Feature",
  "properties": {
    "addr:full":"2151 Oakland Road Spc 532 San Jose CA 95131",
    "addr:housenumber":"2151",
    "addr:postcode":"532;95131",
    "addr:street":"Oakland Road",
    "iso:country":"US",
    "sg:address":"2151 Oakland Road Spc 532",
    "sg:city":"San Jose",
    "sg:classifiers":[
        {
            "category":"Building & Trades",
            "subcategory":"Pest Control",
            "type":"Services"
        }
    ],
    "sg:phone":"+1 408 894 0247",
    "sg:postcode":"95131",
    "sg:province":"CA",
    "wof:name":"Swat Pest Control",
    "wof:placetype":"venue"
},
  "geometry": {"coordinates":[-121.90228500000001,37.396677],"type":"Point"}
}