{
  "type": "Feature",
  "properties": {
    "addr:full":"239 E Palm Ave Burbank CA 91502",
    "addr:housenumber":"239",
    "addr:postcode":"91502",
    "addr:street":"E Palm Ave",
    "iso:country":"US",
    "sg:address":"239 E Palm Ave",
    "sg:city":"Burbank",
    "sg:classifiers":[
        {
            "category":"Building & Trades",
            "subcategory":"Construction",
            "type":"Services"
        },
        {
            "category":"Real Estate",
            "subcategory":"Architect",
            "type":"Services"
        }
    ],
    "sg:phone":"+1 818 845 3170",
    "sg:postcode":"91502",
    "sg:province":"CA",
    "sg:tags":[
        "contractor"
    ],
    "wof:name":"Gangi Architects",
    "wof:placetype":"venue"
},
  "geometry": {"coordinates":[-118.30999799999999,34.183201],"type":"Point"}
}