{
  "type": "Feature",
  "properties": {
    "iso:country":"US",
    "sg:address":"857 E Shields Ave",
    "sg:city":"Fresno",
    "sg:classifiers":[
        {
            "category":"Professional",
            "subcategory":"Accounting & Tax Preparation",
            "type":"Services"
        }
    ],
    "sg:phone":"+1 559 230 1257",
    "sg:postcode":"93704",
    "sg:province":"CA",
    "sg:tags":[
        "bookkeeping",
        "general"
    ],
    "wof:name":"Complete Business Svc",
    "wof:placetype":"venue"
},
  "geometry": {"coordinates":[-119.79967499999999,36.779544],"type":"Point"}
}