{
  "type": "Feature",
  "properties": {
    "addr:full":"4333 Woodman Ave Sherman Oaks CA 91423",
    "addr:housenumber":"4333",
    "addr:postcode":"91423",
    "addr:street":"Woodman Ave",
    "iso:country":"US",
    "sg:address":"4333 Woodman Ave",
    "sg:city":"Sherman Oaks",
    "sg:classifiers":[
        {
            "category":"Health Services",
            "subcategory":"Doctor",
            "type":"Services"
        }
    ],
    "sg:phone":"+1 818 990 7260",
    "sg:postcode":"91423",
    "sg:province":"CA",
    "sg:tags":[
        "surgeon",
        "oral"
    ],
    "wof:name":"Cohen Robert L DDS",
    "wof:placetype":"venue"
},
  "geometry": {"coordinates":[-118.431,34.149399],"type":"Point"}
}