{
  "type": "Feature",
  "properties": {
    "iso:country":"US",
    "sg:address":"1550 Circle City Dr",
    "sg:city":"Corona",
    "sg:classifiers":[
        {
            "category":"Travel",
            "subcategory":"Hotels & Motels",
            "type":"Entertainment"
        },
        {
            "category":"Retail",
            "subcategory":"Event Space",
            "type":"Services"
        }
    ],
    "sg:phone":"+1 800 345 8082",
    "sg:postcode":"92879",
    "sg:province":"CA",
    "sg:tags":[
        "facility",
        "banquet",
        "reception",
        "lodging",
        "corporate",
        "hall"
    ],
    "sg:website":"http://ad.doubleclick.net/clk;222816988;46581822;v?http://www.hiexpress.com/redirect?path=hd&brandCode=ex&hotelCode=corca&_PMID=99601036&cm_mmc=mdpr-_-yellowpages-_-ex-_-corca",
    "wof:name":"Holiday Inn Express Hotel & Suites Corona",
    "wof:placetype":"venue"
},
  "geometry": {"coordinates":[-117.54510500000001,33.868832],"type":"Point"}
}