{
  "type": "Feature",
  "properties": {
    "iso:country":"US",
    "sg:address":"22331 el Toro Rd",
    "sg:city":"Lake Forest",
    "sg:classifiers":[
        {
            "category":"Restaurant",
            "type":"Food & Drink"
        }
    ],
    "sg:phone":"+1 949 768 6983",
    "sg:postcode":"92630",
    "sg:province":"CA",
    "sg:tags":[
        "parlor",
        "ice",
        "cream"
    ],
    "wof:name":"Dairy Queen",
    "wof:placetype":"venue"
},
  "geometry": {"coordinates":[-117.627293,33.671603],"type":"Point"}
}