{
  "type": "Feature",
  "properties": {
    "iso:country":"US",
    "sg:address":"1208 Brenton Ave",
    "sg:city":"San Jose",
    "sg:classifiers":[
        {
            "category":"Communications",
            "type":"Services"
        }
    ],
    "sg:phone":"+1 408 509 6329",
    "sg:postcode":"95129",
    "sg:province":"CA",
    "sg:tags":[
        "communication"
    ],
    "wof:name":"M G Communications",
    "wof:placetype":"venue"
},
  "geometry": {"coordinates":[-121.990283,37.303187],"type":"Point"}
}