{
  "type": "Feature",
  "properties": {
    "iso:country":"US",
    "sg:address":"1908 Mission St",
    "sg:city":"San Francisco",
    "sg:classifiers":[
        {
            "category":"Organizations",
            "subcategory":"Political Organization",
            "type":"Services"
        }
    ],
    "sg:phone":"+1 415 864 1278",
    "sg:postcode":"94103",
    "sg:province":"CA",
    "wof:name":"Radical Women",
    "wof:placetype":"venue"
},
  "geometry": {"coordinates":[-122.419754,37.765178],"type":"Point"}
}