{
  "type": "Feature",
  "properties": {
    "iso:country":"US",
    "sg:address":"4611 Shetland Way",
    "sg:city":"Antioch",
    "sg:classifiers":[
        {
            "category":"Building & Trades",
            "subcategory":"Construction",
            "type":"Services"
        }
    ],
    "sg:phone":"+1 925 522 0272",
    "sg:postcode":"94531",
    "sg:province":"CA",
    "sg:tags":[
        "excavation",
        "excavating",
        "contractor"
    ],
    "wof:name":"Precision Excavation",
    "wof:placetype":"venue"
},
  "geometry": {"coordinates":[-121.753765,37.974721],"type":"Point"}
}