{
  "type": "Feature",
  "properties": {
    "iso:country":"US",
    "sg:address":"7691 Dagget St",
    "sg:city":"San Diego",
    "sg:classifiers":[
        {
            "category":"Government",
            "subcategory":"Office",
            "type":"Public Place"
        }
    ],
    "sg:phone":"+1 858 278 1099",
    "sg:postcode":"92111",
    "sg:province":"CA",
    "sg:tags":[
        "field",
        "security",
        "administration",
        "for",
        "social"
    ],
    "wof:name":"Social Security Administration",
    "wof:placetype":"venue"
},
  "geometry": {"coordinates":[-117.159947,32.823483],"type":"Point"}
}