{
  "type": "Feature",
  "properties": {
    "addr:full":"303 E Foothill Blvd Rialto CA 92376",
    "addr:housenumber":"303",
    "addr:postcode":"92376",
    "addr:street":"E Foothill Blvd",
    "iso:country":"US",
    "sg:address":"303 E Foothill Blvd",
    "sg:city":"Rialto",
    "sg:classifiers":[
        {
            "category":"Banks & Credit Unions",
            "subcategory":"Bank",
            "type":"Services"
        }
    ],
    "sg:phone":"+1 909 820 5808",
    "sg:postcode":"92376",
    "sg:province":"CA",
    "sg:tags":[
        "cashing",
        "check"
    ],
    "wof:name":"Cash 4 Checks",
    "wof:placetype":"venue"
},
  "geometry": {"coordinates":[-117.36165699999999,34.106787],"type":"Point"}
}