{
  "type": "Feature",
  "properties": {
    "addr:full":"4345 Twain Ave San Diego CA 92120",
    "addr:housenumber":"4345",
    "addr:postcode":"92120",
    "addr:street":"Twain Ave",
    "iso:country":"US",
    "sg:address":"4345 Twain Ave",
    "sg:city":"San Diego",
    "sg:classifiers":[
        {
            "category":"Building & Trades",
            "subcategory":"Plumbing",
            "type":"Services"
        }
    ],
    "sg:phone":"+1 619 640 2733",
    "sg:postcode":"92120",
    "sg:province":"CA",
    "sg:tags":[
        "sheet",
        "work",
        "metal",
        "contractor"
    ],
    "wof:name":"Atomic Motorsport Concepts",
    "wof:placetype":"venue"
},
  "geometry": {"coordinates":[-117.100264,32.784944],"type":"Point"}
}