{
  "type": "Feature",
  "properties": {
    "iso:country":"US",
    "sg:address":"1790 N Case St",
    "sg:city":"Orange",
    "sg:classifiers":[
        {
            "category":"Professional",
            "subcategory":"Art Services",
            "type":"Services"
        }
    ],
    "sg:phone":"+1 714 637 5573",
    "sg:postcode":"92865",
    "sg:province":"CA",
    "sg:tags":[
        "graphic",
        "design"
    ],
    "wof:name":"Jacks Graphics",
    "wof:placetype":"venue"
},
  "geometry": {"coordinates":[-117.859118,33.817299],"type":"Point"}
}