{
  "type": "Feature",
  "properties": {
    "iso:country":"US",
    "sg:address":"1028 W Big Bear Blvd",
    "sg:city":"Big Bear City",
    "sg:classifiers":[
        {
            "category":"Health Services",
            "subcategory":"Chiropractor",
            "type":"Services"
        }
    ],
    "sg:phone":"+1 909 585 2225",
    "sg:postcode":"92314",
    "sg:province":"CA",
    "wof:name":"East Valley Chiropractic",
    "wof:placetype":"venue"
},
  "geometry": {"coordinates":[-116.863657,34.260406],"type":"Point"}
}