{
  "type": "Feature",
  "properties": {
    "iso:country":"US",
    "sg:address":"1662 Dominican Way",
    "sg:city":"Santa Cruz",
    "sg:classifiers":[
        {
            "category":"Community Center",
            "type":"Public Place"
        }
    ],
    "sg:phone":"+1 831 458 6295",
    "sg:postcode":"95065",
    "sg:province":"CA",
    "sg:tags":[
        "medical"
    ],
    "sg:website":"www.pamf.org/Orthopedics/santacruz/",
    "wof:name":"Palo Alto Medical Foundation",
    "wof:placetype":"venue"
},
  "geometry": {"coordinates":[-121.98170399999999,36.990277],"type":"Point"}
}