{
  "type": "Feature",
  "properties": {
    "addr:full":"1333 Barrington Way Glendale CA 91206",
    "addr:housenumber":"1333",
    "addr:postcode":"91206",
    "addr:street":"Barrington Way",
    "iso:country":"US",
    "sg:address":"1333 Barrington Way",
    "sg:city":"Glendale",
    "sg:classifiers":[
        {
            "category":"Building & Trades",
            "subcategory":"Construction",
            "type":"Services"
        }
    ],
    "sg:phone":"+1 626 230 9794",
    "sg:postcode":"91206",
    "sg:province":"CA",
    "sg:tags":[
        "contractor"
    ],
    "wof:name":"Fences 4 Le$$",
    "wof:placetype":"venue"
},
  "geometry": {"coordinates":[-118.23639799999999,34.147243],"type":"Point"}
}