{
  "type": "Feature",
  "properties": {
    "iso:country":"US",
    "sg:address":"6200 Faith Home Rd",
    "sg:city":"Ceres",
    "sg:classifiers":[
        {
            "category":"Farming",
            "subcategory":"Farm",
            "type":"Manufacturing & Wholesale Goods"
        }
    ],
    "sg:phone":"+1 209 537 3432",
    "sg:postcode":"95307",
    "sg:province":"CA",
    "sg:tags":[
        "crop",
        "general"
    ],
    "wof:name":"Ron Mead",
    "wof:placetype":"venue"
},
  "geometry": {"coordinates":[-120.920321,37.546893],"type":"Point"}
}