{
  "type": "Feature",
  "properties": {
    "addr:full":"7057 E Hanbury St Long Beach CA 90808",
    "addr:housenumber":"7057",
    "addr:postcode":"90808",
    "addr:street":"E Hanbury St",
    "iso:country":"US",
    "sg:address":"7057 E Hanbury St",
    "sg:city":"Long Beach",
    "sg:classifiers":[
        {
            "category":"Wholesale",
            "subcategory":"Auto Parts",
            "type":"Manufacturing & Wholesale Goods"
        }
    ],
    "sg:phone":"+1 562 420 3557",
    "sg:postcode":"90808",
    "sg:province":"CA",
    "sg:tags":[
        "vehicle",
        "motor",
        "supply"
    ],
    "wof:name":"Bits and Pieces",
    "wof:placetype":"venue"
},
  "geometry": {"coordinates":[-118.096042,33.82866],"type":"Point"}
}