{
  "type": "Feature",
  "properties": {
    "addr:full":"1448 Esplanade Chico CA 95926",
    "addr:housenumber":"1448",
    "addr:postcode":"95926",
    "addr:street":"Esplanade Chico",
    "iso:country":"US",
    "sg:address":"1448 Esplanade",
    "sg:city":"Chico",
    "sg:classifiers":[
        {
            "category":"Professional",
            "subcategory":"Management & Consulting",
            "type":"Services"
        }
    ],
    "sg:phone":"+1 530 891 4867",
    "sg:postcode":"95926",
    "sg:province":"CA",
    "sg:tags":[
        "consultant",
        "government"
    ],
    "wof:name":"Enloe Foundation",
    "wof:placetype":"venue"
},
  "geometry": {"coordinates":[-121.84833999999999,39.741578],"type":"Point"}
}