{
  "type": "Feature",
  "properties": {
    "addr:full":"22600 Lambert St Lake Forest CA 92630",
    "addr:housenumber":"22600",
    "addr:postcode":"92630",
    "addr:street":"Lambert St",
    "iso:country":"US",
    "sg:address":"22600 Lambert St",
    "sg:city":"Lake Forest",
    "sg:classifiers":[
        {
            "category":"Wholesale",
            "subcategory":"Medical Equipment & Supplies",
            "type":"Manufacturing & Wholesale Goods"
        }
    ],
    "sg:phone":"+1 949 597 4081",
    "sg:postcode":"92630",
    "sg:province":"CA",
    "sg:tags":[
        "physician",
        "surgeon"
    ],
    "wof:name":"Lincare",
    "wof:placetype":"venue"
},
  "geometry": {"coordinates":[-117.71473,33.634319],"type":"Point"}
}