{
  "type": "Feature",
  "properties": {
    "iso:country":"US",
    "sg:address":"2060 Duane Ave",
    "sg:city":"Santa Clara",
    "sg:classifiers":[
        {
            "category":"Personal",
            "subcategory":"Day Spa",
            "type":"Services"
        }
    ],
    "sg:phone":"+1 408 844 9498",
    "sg:postcode":"95054",
    "sg:province":"CA",
    "wof:name":"Sundance Spas",
    "wof:placetype":"venue"
},
  "geometry": {"coordinates":[-121.964996,37.378799],"type":"Point"}
}