{
  "type": "Feature",
  "properties": {
    "iso:country":"US",
    "sg:address":"1785 E 1st St",
    "sg:city":"Los Angeles",
    "sg:classifiers":[
        {
            "category":"Shopping",
            "subcategory":"Hobbies, Toys, & Games",
            "type":"Retail Goods"
        }
    ],
    "sg:phone":"+1 323 264 5435",
    "sg:postcode":"90033",
    "sg:province":"CA",
    "sg:tags":[
        "doll"
    ],
    "wof:name":"Arase Doll Makings",
    "wof:placetype":"venue"
},
  "geometry": {"coordinates":[-118.220665,34.047373],"type":"Point"}
}