{
  "type": "Feature",
  "properties": {
    "iso:country":"US",
    "sg:address":"Belloccio Salon and Day Spa 1219 Camino Del Mar",
    "sg:city":"Del Mar",
    "sg:classifiers":[
        {
            "category":"Personal",
            "subcategory":"Beauty Salon",
            "type":"Services"
        }
    ],
    "sg:phone":"+1 858 603 5955",
    "sg:postcode":"92014",
    "sg:province":"CA",
    "sg:tags":[
        "makeup",
        "artist"
    ],
    "sg:website":"www.makeupbymonica.com",
    "wof:name":"Makeup By Monica",
    "wof:placetype":"venue"
},
  "geometry": {"coordinates":[-117.264,32.957118],"type":"Point"}
}