{
  "type": "Feature",
  "properties": {
    "addr:full":"9404 Twin Trails Dr San Diego CA 92129",
    "addr:housenumber":"9404",
    "addr:postcode":"92129",
    "addr:street":"Twin Trails Dr",
    "iso:country":"US",
    "sg:address":"9404 Twin Trails Dr",
    "sg:city":"San Diego",
    "sg:classifiers":[
        {
            "category":"Real Estate",
            "subcategory":"Real Estate Operator",
            "type":"Services"
        }
    ],
    "sg:phone":"+1 858 484 8220",
    "sg:postcode":"92129",
    "sg:province":"CA",
    "sg:tags":[
        "condominium"
    ],
    "wof:name":"Penasquitas Casa Blanca",
    "wof:placetype":"venue"
},
  "geometry": {"coordinates":[-117.127521,32.956441],"type":"Point"}
}