{
  "type": "Feature",
  "properties": {
    "iso:country":"US",
    "sg:address":"45135 S Grimmer Blvd",
    "sg:city":"Fremont",
    "sg:classifiers":[
        {
            "category":"Education",
            "subcategory":"School",
            "type":"Public Place"
        }
    ],
    "sg:phone":"+1 510 651 6958",
    "sg:postcode":"94539",
    "sg:province":"CA",
    "sg:tags":[
        "elementary"
    ],
    "wof:name":"Fred Weibel Elementary School",
    "wof:placetype":"venue"
},
  "geometry": {"coordinates":[-121.92636299999999,37.506746],"type":"Point"}
}