{
  "type": "Feature",
  "properties": {
    "iso:country":"US",
    "sg:address":"914 S Hoover St",
    "sg:city":"Los Angeles",
    "sg:classifiers":[
        {
            "category":"Wholesale",
            "subcategory":"Farm Supplies",
            "type":"Manufacturing & Wholesale Goods"
        },
        {
            "category":"Health Services",
            "subcategory":"Health Practitioner",
            "type":"Services"
        }
    ],
    "sg:phone":"+1 213 380 4422",
    "sg:postcode":"90006",
    "sg:province":"CA",
    "sg:tags":[
        "acupuncture",
        "food"
    ],
    "wof:name":"Yag Jun Herb Trading Co",
    "wof:placetype":"venue"
},
  "geometry": {"coordinates":[-118.28416199999999,34.055662],"type":"Point"}
}