{
  "type": "Feature",
  "properties": {
    "addr:full":"22301 S Western Ave Ste 102 Torrance CA 90501",
    "addr:housenumber":"22301",
    "addr:postcode":"90501",
    "addr:street":"S Western Ave Ste 102",
    "iso:country":"US",
    "sg:address":"22301 S Western Ave Ste 102",
    "sg:city":"Torrance",
    "sg:classifiers":[
        {
            "category":"Cinema",
            "subcategory":"Movie Theater",
            "type":"Entertainment"
        }
    ],
    "sg:phone":"+1 310 953 3380",
    "sg:postcode":"90501",
    "sg:province":"CA",
    "sg:website":"www.gridworks.net",
    "wof:name":"Gridworks",
    "wof:placetype":"venue"
},
  "geometry": {"coordinates":[-118.309524,33.823787],"type":"Point"}
}