{
  "type": "Feature",
  "properties": {
    "iso:country":"US",
    "sg:address":"3201 Steiner Street",
    "sg:city":"San Francisco",
    "sg:classifiers":[
        {
            "category":"Travel",
            "subcategory":"Hotels & Motels",
            "type":"Entertainment"
        }
    ],
    "sg:phone":"+1 415 921 5162",
    "sg:postcode":"94123",
    "sg:province":"CA",
    "sg:website":"www.greenwichinn.com/",
    "wof:name":"Greenwich Inn",
    "wof:placetype":"venue"
},
  "geometry": {"coordinates":[-122.43800400000001,37.798901],"type":"Point"}
}