{
  "type": "Feature",
  "properties": {
    "iso:country":"US",
    "sg:address":"1560 N Harmony Cir",
    "sg:city":"Anaheim",
    "sg:classifiers":[
        {
            "category":"Autos & Motor Vehicles",
            "subcategory":"Auto Supplies",
            "type":"Retail Goods"
        },
        {
            "category":"Wholesale",
            "subcategory":"Auto Parts",
            "type":"Manufacturing & Wholesale Goods"
        }
    ],
    "sg:phone":"+1 714 970 0280",
    "sg:postcode":"92807",
    "sg:province":"CA",
    "sg:tags":[
        "bearing",
        "bearings-wholesale"
    ],
    "wof:name":"KMS Bearings Inc.",
    "wof:placetype":"venue"
},
  "geometry": {"coordinates":[-117.80486000000001,33.86404],"type":"Point"}
}