{
  "type": "Feature",
  "properties": {
    "iso:country":"US",
    "sg:address":"355 Crown Point Cir",
    "sg:city":"Grass Valley",
    "sg:classifiers":[
        {
            "category":"Professional",
            "subcategory":"Engineering",
            "type":"Services"
        }
    ],
    "sg:phone":"+1 530 477 1691",
    "sg:postcode":"95945",
    "sg:province":"CA",
    "sg:tags":[
        "engineer"
    ],
    "wof:name":"Mobius Technologies",
    "wof:placetype":"venue"
},
  "geometry": {"coordinates":[-121.030058,39.220981],"type":"Point"}
}