{
  "type": "Feature",
  "properties": {
    "iso:country":"US",
    "sg:address":"2204 Summerhill Dr",
    "sg:city":"Encinitas",
    "sg:classifiers":[
        {
            "category":"Autos & Motor Vehicles",
            "subcategory":"Automobile Sales",
            "type":"Retail Goods"
        }
    ],
    "sg:phone":"+1 760 942 0601",
    "sg:postcode":"92024",
    "sg:province":"CA",
    "sg:tags":[
        "used"
    ],
    "wof:name":"Missi Motors",
    "wof:placetype":"venue"
},
  "geometry": {"coordinates":[-117.244373,33.059132],"type":"Point"}
}