{
  "type": "Feature",
  "properties": {
    "iso:country":"US",
    "sg:address":"1945 Palo Verde Ave",
    "sg:city":"Long Beach",
    "sg:classifiers":[
        {
            "category":"Real Estate",
            "subcategory":"Real Estate Agent",
            "type":"Services"
        }
    ],
    "sg:phone":"+1 562 430 6858",
    "sg:postcode":"90815",
    "sg:province":"CA",
    "sg:tags":[
        "appraiser"
    ],
    "wof:name":"Larry Skelly",
    "wof:placetype":"venue"
},
  "geometry": {"coordinates":[-118.108018,33.792158],"type":"Point"}
}