{
  "type": "Feature",
  "properties": {
    "addr:full":"5731 Braeloch St Acton CA 93510",
    "addr:housenumber":"5731",
    "addr:postcode":"93510",
    "addr:street":"Braeloch St",
    "iso:country":"US",
    "sg:address":"5731 Braeloch St",
    "sg:city":"Acton",
    "sg:classifiers":[
        {
            "category":"Building & Trades",
            "subcategory":"Construction",
            "type":"Services"
        }
    ],
    "sg:phone":"+1 818 808 2755",
    "sg:postcode":"93510",
    "sg:province":"CA",
    "sg:tags":[
        "plastering",
        "contractor"
    ],
    "wof:name":"MP Plastering",
    "wof:placetype":"venue"
},
  "geometry": {"coordinates":[-118.236581,34.519495],"type":"Point"}
}