{
  "type": "Feature",
  "properties": {
    "addr:full":"1321 N Lilac Ave Rialto CA 92376",
    "addr:housenumber":"1321",
    "addr:postcode":"92376",
    "addr:street":"N Lilac Ave",
    "iso:country":"US",
    "sg:address":"1321 N Lilac Ave",
    "sg:city":"Rialto",
    "sg:classifiers":[
        {
            "category":"Education",
            "subcategory":"School",
            "type":"Public Place"
        }
    ],
    "sg:phone":"+1 909 820 7777",
    "sg:postcode":"92376",
    "sg:province":"CA",
    "wof:name":"Rialto Unified School District",
    "wof:placetype":"venue"
},
  "geometry": {"coordinates":[-117.379176,34.123224],"type":"Point"}
}