{
  "type": "Feature",
  "properties": {
    "addr:full":"20300 S Vermont Ave Torrance CA 90502",
    "addr:housenumber":"20300",
    "addr:postcode":"90502",
    "addr:street":"S Vermont Ave",
    "iso:country":"US",
    "sg:address":"20300 S Vermont Ave",
    "sg:city":"Torrance",
    "sg:classifiers":[
        {
            "category":"Shopping",
            "subcategory":"Computers & Home Electronics",
            "type":"Retail Goods"
        }
    ],
    "sg:phone":"+1 310 225 5623",
    "sg:postcode":"90502",
    "sg:province":"CA",
    "sg:tags":[
        "software"
    ],
    "sg:website":"www.calsoftsys.com",
    "wof:name":"Calsoft Systems",
    "wof:placetype":"venue"
},
  "geometry": {"coordinates":[-118.290378,33.846433],"type":"Point"}
}