{
  "type": "Feature",
  "properties": {
    "iso:country":"US",
    "sg:address":"3262 E Thousand Oaks Blvd",
    "sg:city":"Thousand Oaks",
    "sg:classifiers":[
        {
            "category":"Real Estate",
            "subcategory":"Real Estate Agent",
            "type":"Services"
        }
    ],
    "sg:phone":"+1 805 381 1515",
    "sg:postcode":"91362",
    "sg:province":"CA",
    "wof:name":"Porterfield Commercial Real",
    "wof:placetype":"venue"
},
  "geometry": {"coordinates":[-118.835601,34.168695],"type":"Point"}
}