{
  "type": "Feature",
  "properties": {
    "addr:full":"1294 Burlingame Ave Burlingame CA 94010",
    "addr:housenumber":"1294",
    "addr:postcode":"94010",
    "addr:street":"Burlingame Ave",
    "iso:country":"US",
    "sg:address":"1294 Burlingame Ave",
    "sg:city":"Burlingame",
    "sg:classifiers":[
        {
            "category":"Shopping",
            "subcategory":"Clothing, Apparel, & Fashions",
            "type":"Retail Goods"
        },
        {
            "category":"Shopping",
            "subcategory":"Baby Store",
            "type":"Retail Goods"
        },
        {
            "category":"Shopping",
            "subcategory":"Department Store",
            "type":"Retail Goods"
        }
    ],
    "sg:phone":"+1 650 579 2823",
    "sg:postcode":"94010",
    "sg:province":"CA",
    "sg:tags":[
        "infant",
        "vintage",
        "men's",
        "period",
        "accessory",
        "children's",
        "wear",
        "apparel",
        "girls'",
        "women's",
        "clothing",
        "boys'",
        "clothing-collectible"
    ],
    "sg:website":"http://www.gap.com",
    "wof:name":"Gap",
    "wof:placetype":"venue"
},
  "geometry": {"coordinates":[-122.34705200000001,37.578558],"type":"Point"}
}