{
  "type": "Feature",
  "properties": {
    "iso:country":"US",
    "sg:address":"24115 Big Timber St",
    "sg:city":"Lake Forest",
    "sg:classifiers":[
        {
            "category":"Banks & Credit Unions",
            "subcategory":"Investment Brokerage",
            "type":"Services"
        }
    ],
    "sg:phone":"+1 949 305 1889",
    "sg:postcode":"92630",
    "sg:province":"CA",
    "sg:tags":[
        "advisory",
        "financial"
    ],
    "wof:name":"Alpha Omega Financial Svc",
    "wof:placetype":"venue"
},
  "geometry": {"coordinates":[-117.707938,33.630205],"type":"Point"}
}