{
  "type": "Feature",
  "properties": {
    "iso:country":"US",
    "sg:address":"777 Crestwood Rd",
    "sg:city":"Boulevard",
    "sg:classifiers":[
        {
            "category":"Travel",
            "subcategory":"Hotels & Motels",
            "type":"Entertainment"
        },
        {
            "category":"Casinos & Gambling",
            "type":"Entertainment"
        }
    ],
    "sg:phone":"+1 619 824 4100",
    "sg:postcode":"91905",
    "sg:province":"CA",
    "wof:name":"La Posta Casino",
    "wof:placetype":"venue"
},
  "geometry": {"coordinates":[-116.357525,32.750055],"type":"Point"}
}