{
  "type": "Feature",
  "properties": {
    "iso:country":"US",
    "sg:address":"5195 Sandy Ln",
    "sg:city":"San Jose",
    "sg:classifiers":[
        {
            "category":"Shopping",
            "type":"Retail Goods"
        }
    ],
    "sg:phone":"+1 408 371 3389",
    "sg:postcode":"95124",
    "sg:province":"CA",
    "sg:tags":[
        "merchandise"
    ],
    "wof:name":"Robert Clagett Distributing",
    "wof:placetype":"venue"
},
  "geometry": {"coordinates":[-121.926334,37.244127],"type":"Point"}
}