{
  "type": "Feature",
  "properties": {
    "addr:full":"2101 W Empire Ave Burbank CA 91504",
    "addr:housenumber":"2101",
    "addr:postcode":"91504",
    "addr:street":"W Empire Ave",
    "iso:country":"US",
    "sg:address":"2101 W Empire Ave",
    "sg:city":"Burbank",
    "sg:classifiers":[
        {
            "category":"Wholesale",
            "subcategory":"Electrical",
            "type":"Manufacturing & Wholesale Goods"
        }
    ],
    "sg:phone":"+1 818 843 4111",
    "sg:postcode":"91504",
    "sg:province":"CA",
    "sg:tags":[
        "electric",
        "supply",
        "electronic",
        "equipment",
        "supplies-wholesale",
        "manufacturer"
    ],
    "sg:website":"http://www.ced-aec.com",
    "wof:name":"All-Phase Electric Supply Co.",
    "wof:placetype":"venue"
},
  "geometry": {"coordinates":[-118.33303100000001,34.19178],"type":"Point"}
}