{
  "type": "Feature",
  "properties": {
    "addr:full":"950 Battery St San Francisco CA 94111",
    "addr:housenumber":"950",
    "addr:postcode":"94111",
    "addr:street":"Battery St",
    "iso:country":"US",
    "sg:address":"950 Battery St",
    "sg:city":"San Francisco",
    "sg:classifiers":[
        {
            "category":"Personal",
            "type":"Services"
        },
        {
            "category":"Communications",
            "type":"Services"
        }
    ],
    "sg:phone":"+1 415 434 1027",
    "sg:postcode":"94111",
    "sg:province":"CA",
    "sg:tags":[
        "mass",
        "medium",
        "local"
    ],
    "sg:website":"www.beyondpix.com",
    "wof:name":"Beyond Pix Studios",
    "wof:placetype":"venue"
},
  "geometry": {"coordinates":[-122.401381,37.800034],"type":"Point"}
}