{
  "type": "Feature",
  "properties": {
    "addr:full":"330 Reservation Rd Ste C Marina CA 93933",
    "addr:housenumber":"330",
    "addr:postcode":"93933",
    "addr:street":"Reservation Rd Ste C",
    "iso:country":"US",
    "sg:address":"330 Reservation Rd Ste C",
    "sg:city":"Marina",
    "sg:classifiers":[
        {
            "category":"Restaurant",
            "type":"Food & Drink"
        }
    ],
    "sg:phone":"+1 831 582 2509",
    "sg:postcode":"93933",
    "sg:province":"CA",
    "sg:tags":[
        "breakfast",
        "brunch"
    ],
    "sg:website":"www.ticosbreakfast-lunch.com",
    "wof:name":"Tico's Breakfast and Lunch",
    "wof:placetype":"venue"
},
  "geometry": {"coordinates":[-121.790893,36.683374],"type":"Point"}
}