{
  "type": "Feature",
  "properties": {
    "iso:country":"US",
    "sg:address":"1415 2nd St",
    "sg:city":"Napa",
    "sg:classifiers":[
        {
            "category":"Personal",
            "subcategory":"Beauty Salon",
            "type":"Services"
        }
    ],
    "sg:phone":"+1 707 224 4599",
    "sg:postcode":"94559",
    "sg:province":"CA",
    "sg:tags":[
        "manicuring"
    ],
    "wof:name":"Napa Nails",
    "wof:placetype":"venue"
},
  "geometry": {"coordinates":[-122.288686,38.296507],"type":"Point"}
}