{
  "type": "Feature",
  "properties": {
    "addr:full":"24 Blue Sky Ct Sacramento CA 95828",
    "addr:housenumber":"24",
    "addr:postcode":"95828",
    "addr:street":"Blue Sky Ct",
    "iso:country":"US",
    "sg:address":"24 Blue Sky Ct",
    "sg:city":"Sacramento",
    "sg:classifiers":[
        {
            "category":"Wholesale",
            "subcategory":"Durable Goods & Equipment",
            "type":"Manufacturing & Wholesale Goods"
        }
    ],
    "sg:phone":"+1 916 381 0204",
    "sg:postcode":"95828",
    "sg:province":"CA",
    "sg:tags":[
        "importer"
    ],
    "sg:website":"www.mccoyauction.com",
    "wof:name":"Mc Coy Auction Co",
    "wof:placetype":"venue"
},
  "geometry": {"coordinates":[-121.384765,38.51455],"type":"Point"}
}