{
  "type": "Feature",
  "properties": {
    "iso:country":"US",
    "sg:address":"133 Kearny St",
    "sg:city":"San Francisco",
    "sg:classifiers":[
        {
            "category":"Health Services",
            "subcategory":"Dentist",
            "type":"Services"
        }
    ],
    "sg:phone":"+1 415 296 9111",
    "sg:postcode":"94108",
    "sg:province":"CA",
    "wof:name":"Rivas Polly D DDS",
    "wof:placetype":"venue"
},
  "geometry": {"coordinates":[-122.403898,37.789165],"type":"Point"}
}