{
  "type": "Feature",
  "properties": {
    "addr:full":"601 Murray Circle Sausalito CA 94965",
    "addr:housenumber":"601",
    "addr:postcode":"94965",
    "addr:street":"Murray Circle",
    "iso:country":"US",
    "sg:address":"601 Murray Circle",
    "sg:city":"Sausalito",
    "sg:classifiers":[
        {
            "category":"Restaurant",
            "type":"Food & Drink"
        }
    ],
    "sg:menulink":"http://www.allmenus.com/ca/southwest-marin/269869-murray-circle---cavallo-point/menu/",
    "sg:phone":"+1 415 339 4750",
    "sg:postcode":"94965",
    "sg:province":"CA",
    "sg:tags":[
        "american",
        "californian"
    ],
    "wof:name":"Murray Circle - Cavallo Point",
    "wof:placetype":"venue"
},
  "geometry": {"coordinates":[-122.478328,37.83729],"type":"Point"}
}