{
  "type": "Feature",
  "properties": {
    "addr:full":"737 Barstow Ave Clovis CA 93612",
    "addr:housenumber":"737",
    "addr:postcode":"93612",
    "addr:street":"Barstow Ave",
    "iso:country":"US",
    "sg:address":"737 Barstow Ave",
    "sg:city":"Clovis",
    "sg:classifiers":[
        {
            "category":"Retail",
            "subcategory":"Repair Shop",
            "type":"Services"
        }
    ],
    "sg:phone":"+1 559 298 5834",
    "sg:postcode":"93612",
    "sg:province":"CA",
    "sg:tags":[
        "welding"
    ],
    "wof:name":"Metal Shoppe",
    "wof:placetype":"venue"
},
  "geometry": {"coordinates":[-119.69799500000001,36.815848],"type":"Point"}
}