{
  "type": "Feature",
  "properties": {
    "iso:country":"US",
    "sg:address":"4989 Sepulveda Blvd",
    "sg:city":"Sherman Oaks",
    "sg:classifiers":[
        {
            "category":"Recreation",
            "type":"Entertainment"
        }
    ],
    "sg:phone":"+1 818 905 1321",
    "sg:postcode":"91403",
    "sg:province":"CA",
    "sg:tags":[
        "range",
        "baseball",
        "batting"
    ],
    "wof:name":"Castle Batting Park",
    "wof:placetype":"venue"
},
  "geometry": {"coordinates":[-118.466231,34.160483],"type":"Point"}
}