{
  "type": "Feature",
  "properties": {
    "iso:country":"US",
    "sg:address":"225 Emerson St",
    "sg:city":"Palo Alto",
    "sg:classifiers":[
        {
            "category":"Professional",
            "subcategory":"Management & Consulting",
            "type":"Services"
        }
    ],
    "sg:phone":"+1 650 324 5370",
    "sg:postcode":"94301",
    "sg:province":"CA",
    "sg:tags":[
        "marketing",
        "program"
    ],
    "sg:website":"www.transend.com",
    "wof:name":"Transend",
    "wof:placetype":"venue"
},
  "geometry": {"coordinates":[-122.165571,37.446532],"type":"Point"}
}