{
  "type": "Feature",
  "properties": {
    "addr:full":"5360 Burford St San Diego CA 92111",
    "addr:housenumber":"5360",
    "addr:postcode":"92111",
    "addr:street":"Burford St",
    "iso:country":"US",
    "sg:address":"5360 Burford St",
    "sg:city":"San Diego",
    "sg:classifiers":[
        {
            "category":"Building & Trades",
            "subcategory":"Construction",
            "type":"Services"
        }
    ],
    "sg:phone":"+1 619 275 1474",
    "sg:postcode":"92111",
    "sg:province":"CA",
    "sg:tags":[
        "roofing",
        "contractor"
    ],
    "wof:name":"Admiral Roofing Co",
    "wof:placetype":"venue"
},
  "geometry": {"coordinates":[-117.18556,32.796814],"type":"Point"}
}