{
  "type": "Feature",
  "properties": {
    "addr:full":"260 Storey Rd Watsonville CA 95076",
    "addr:housenumber":"260",
    "addr:postcode":"95076",
    "addr:street":"Storey Rd",
    "iso:country":"US",
    "sg:address":"260 Storey Rd",
    "sg:city":"Watsonville",
    "sg:classifiers":[
        {
            "category":"Farming",
            "subcategory":"Farm",
            "type":"Manufacturing & Wholesale Goods"
        }
    ],
    "sg:phone":"+1 831 728 0939",
    "sg:postcode":"95076",
    "sg:province":"CA",
    "sg:tags":[
        "crop",
        "general"
    ],
    "wof:name":"Storey Road Farms",
    "wof:placetype":"venue"
},
  "geometry": {"coordinates":[-121.799773,36.971571],"type":"Point"}
}