{
  "type": "Feature",
  "properties": {
    "addr:full":"19600 Fairchild Irvine CA 92612",
    "addr:housenumber":"19600",
    "addr:postcode":"92612",
    "addr:street":"Fairchild",
    "iso:country":"US",
    "sg:address":"19600 Fairchild",
    "sg:city":"Irvine",
    "sg:classifiers":[
        {
            "category":"Building & Trades",
            "subcategory":"Construction",
            "type":"Services"
        }
    ],
    "sg:phone":"+1 949 476 2094",
    "sg:postcode":"92612",
    "sg:province":"CA",
    "sg:tags":[
        "contractor"
    ],
    "wof:name":"O'connor Construction Management",
    "wof:placetype":"venue"
},
  "geometry": {"coordinates":[-117.860001,33.654598],"type":"Point"}
}