{
  "type": "Feature",
  "properties": {
    "iso:country":"US",
    "sg:address":"4505 Eagle Rock Blvd",
    "sg:city":"Los Angeles",
    "sg:classifiers":[
        {
            "category":"Wholesale",
            "subcategory":"Hardware",
            "type":"Manufacturing & Wholesale Goods"
        }
    ],
    "sg:phone":"+1 323 256 4978",
    "sg:postcode":"90041",
    "sg:province":"CA",
    "sg:tags":[
        "fastener"
    ],
    "wof:name":"Golden Ridge Corp",
    "wof:placetype":"venue"
},
  "geometry": {"coordinates":[-118.218077,34.127482],"type":"Point"}
}