{
  "type": "Feature",
  "properties": {
    "iso:country":"US",
    "sg:address":"4025 W 226th St",
    "sg:city":"Torrance",
    "sg:classifiers":[
        {
            "category":"Health Services",
            "subcategory":"Hospital",
            "type":"Services"
        }
    ],
    "sg:phone":"+1 310 373 4556",
    "sg:postcode":"90505",
    "sg:province":"CA",
    "wof:name":"Star View Adolescent Center",
    "wof:placetype":"venue"
},
  "geometry": {"coordinates":[-118.356003,33.823399],"type":"Point"}
}