{
  "type": "Feature",
  "properties": {
    "addr:full":"6300 Auburn Folsom Rd Granite Bay CA 95746",
    "addr:housenumber":"6300",
    "addr:postcode":"95746",
    "addr:street":"Auburn Folsom Rd",
    "iso:country":"US",
    "sg:address":"6300 Auburn Folsom Rd",
    "sg:city":"Granite Bay",
    "sg:classifiers":[
        {
            "category":"Building & Trades",
            "subcategory":"Electrical",
            "type":"Services"
        }
    ],
    "sg:phone":"+1 916 660 0132",
    "sg:postcode":"95746",
    "sg:province":"CA",
    "sg:tags":[
        "electric",
        "contractor"
    ],
    "wof:name":"Sathy Electric",
    "wof:placetype":"venue"
},
  "geometry": {"coordinates":[-121.14953,38.778078],"type":"Point"}
}