{
  "type": "Feature",
  "properties": {
    "iso:country":"US",
    "sg:address":"5400 Pso Gilberto",
    "sg:city":"Yorba Linda",
    "sg:classifiers":[
        {
            "category":"Wholesale",
            "subcategory":"Machinery & Supplies",
            "type":"Manufacturing & Wholesale Goods"
        }
    ],
    "sg:phone":"+1 714 777 8201",
    "sg:postcode":"92886",
    "sg:province":"CA",
    "sg:tags":[
        "industrial"
    ],
    "wof:name":"High Technology Machines Inc",
    "wof:placetype":"venue"
},
  "geometry": {"coordinates":[-117.785393,33.883563],"type":"Point"}
}