{
  "type": "Feature",
  "properties": {
    "iso:country":"US",
    "sg:address":"434 Orange St",
    "sg:city":"Redlands",
    "sg:classifiers":[
        {
            "category":"Banks & Credit Unions",
            "subcategory":"Bank",
            "type":"Services"
        }
    ],
    "sg:phone":"+1 909 792 3225",
    "sg:postcode":"92374",
    "sg:province":"CA",
    "sg:tags":[
        "cashing",
        "check"
    ],
    "wof:name":"Check Into Cash",
    "wof:placetype":"venue"
},
  "geometry": {"coordinates":[-117.182481,34.059415],"type":"Point"}
}