{
  "type": "Feature",
  "properties": {
    "iso:country":"US",
    "sg:address":"512 2nd Ave",
    "sg:city":"Winterhaven",
    "sg:classifiers":[
        {
            "category":"Utilities",
            "subcategory":"Telephone",
            "type":"Services"
        }
    ],
    "sg:phone":"+1 760 572 3111",
    "sg:postcode":"92283",
    "sg:province":"CA",
    "sg:tags":[
        "telecommunication"
    ],
    "wof:name":"TDS Telecom",
    "wof:placetype":"venue"
},
  "geometry": {"coordinates":[-114.635321,32.739027],"type":"Point"}
}