{
  "type": "Feature",
  "properties": {
    "iso:country":"US",
    "sg:address":"1716 Cornell Dr",
    "sg:city":"Alameda",
    "sg:classifiers":[
        {
            "category":"Professional",
            "subcategory":"Accounting & Tax Preparation",
            "type":"Services"
        }
    ],
    "sg:phone":"+1 510 865 7151",
    "sg:postcode":"94501",
    "sg:province":"CA",
    "sg:tags":[
        "return",
        "filing"
    ],
    "wof:name":"Margeret Crawford",
    "wof:placetype":"venue"
},
  "geometry": {"coordinates":[-122.228606,37.762267],"type":"Point"}
}