{
  "type": "Feature",
  "properties": {
    "iso:country":"US",
    "sg:address":"1700 Lincoln St",
    "sg:city":"Bakersfield",
    "sg:classifiers":[
        {
            "category":"Personal",
            "subcategory":"Beauty Salon",
            "type":"Services"
        }
    ],
    "sg:phone":"+1 661 322 9019",
    "sg:postcode":"93305",
    "sg:province":"CA",
    "wof:name":"Bo's Hair Design",
    "wof:placetype":"venue"
},
  "geometry": {"coordinates":[-118.971875,35.383151],"type":"Point"}
}