{
  "type": "Feature",
  "properties": {
    "iso:country":"US",
    "sg:address":"349 E Garvey Ave",
    "sg:city":"Monterey Park",
    "sg:classifiers":[
        {
            "category":"Bakery",
            "type":"Food & Drink"
        }
    ],
    "sg:phone":"+1 626 288 3262",
    "sg:postcode":"91755",
    "sg:province":"CA",
    "wof:name":"Kwan Lac Bakery",
    "wof:placetype":"venue"
},
  "geometry": {"coordinates":[-118.116997,34.062698],"type":"Point"}
}