{
  "type": "Feature",
  "properties": {
    "iso:country":"US",
    "sg:address":"9000 Ming Ave",
    "sg:city":"Bakersfield",
    "sg:classifiers":[
        {
            "category":"Personal",
            "subcategory":"Beauty Salon",
            "type":"Services"
        }
    ],
    "sg:phone":"+1 661 664 8790",
    "sg:postcode":"93309",
    "sg:province":"CA",
    "sg:website":"www.supercuts.com",
    "wof:name":"Supercuts",
    "wof:placetype":"venue"
},
  "geometry": {"coordinates":[-119.10193599999999,35.339841],"type":"Point"}
}