{
  "type": "Feature",
  "properties": {
    "addr:full":"44934 Kingtree Ave Lancaster CA 93534",
    "addr:housenumber":"44934",
    "addr:postcode":"93534",
    "addr:street":"Kingtree Ave",
    "iso:country":"US",
    "sg:address":"44934 Kingtree Ave",
    "sg:city":"Lancaster",
    "sg:classifiers":[
        {
            "category":"Manufacturing",
            "subcategory":"Metals",
            "type":"Manufacturing & Wholesale Goods"
        },
        {
            "category":"Retail",
            "subcategory":"Repair Shop",
            "type":"Services"
        }
    ],
    "sg:phone":"+1 661 945 3330",
    "sg:postcode":"93534",
    "sg:province":"CA",
    "sg:tags":[
        "maintenance",
        "welding"
    ],
    "wof:name":"Kurt's Welding & Maintenance",
    "wof:placetype":"venue"
},
  "geometry": {"coordinates":[-118.150531,34.700041],"type":"Point"}
}