{
  "type": "Feature",
  "properties": {
    "iso:country":"US",
    "sg:address":"1510 11th Street, Suite 101",
    "sg:city":"Santa Monica",
    "sg:classifiers":[
        {
            "category":"Professional",
            "subcategory":"Computer Services",
            "type":"Services"
        }
    ],
    "sg:phone":"+1 310 622 4487",
    "sg:postcode":"90401",
    "sg:province":"CA",
    "sg:website":"http://www.greenscreenanimals.com",
    "wof:name":"Greenscreen Animals",
    "wof:placetype":"venue"
},
  "geometry": {"coordinates":[-118.485598,34.019225],"type":"Point"}
}