{
  "type": "Feature",
  "properties": {
    "addr:full":"23811 Aliso Creek Rd Laguna Niguel CA 92677",
    "addr:housenumber":"23811",
    "addr:postcode":"92677",
    "addr:street":"Aliso Creek Rd",
    "iso:country":"US",
    "sg:address":"23811 Aliso Creek Rd",
    "sg:city":"Laguna Niguel",
    "sg:classifiers":[
        {
            "category":"Professional",
            "subcategory":"Business Services",
            "type":"Services"
        }
    ],
    "sg:phone":"+1 949 362 4433",
    "sg:postcode":"92677",
    "sg:province":"CA",
    "sg:tags":[
        "interior",
        "consultant",
        "design",
        "decorator"
    ],
    "wof:name":"Carol Gergen Interiors",
    "wof:placetype":"venue"
},
  "geometry": {"coordinates":[-117.717882,33.55553],"type":"Point"}
}