{
  "type": "Feature",
  "properties": {
    "iso:country":"US",
    "sg:address":"5757 Wilshire Blvd",
    "sg:city":"Los Angeles",
    "sg:classifiers":[
        {
            "category":"Professional",
            "subcategory":"Lawyer & Legal Services",
            "type":"Services"
        }
    ],
    "sg:phone":"+1 323 525 3170",
    "sg:postcode":"90036",
    "sg:province":"CA",
    "sg:tags":[
        "plan"
    ],
    "sg:website":"www.grayandprouty.com",
    "wof:name":"Gray & Prouty",
    "wof:placetype":"venue"
},
  "geometry": {"coordinates":[-118.353937,34.062441],"type":"Point"}
}