{
  "type": "Feature",
  "properties": {
    "iso:country":"US",
    "sg:address":"995 Gateway Center Way",
    "sg:city":"San Diego",
    "sg:classifiers":[
        {
            "category":"Health Services",
            "subcategory":"Doctor",
            "type":"Services"
        }
    ],
    "sg:phone":"+1 619 262 1960",
    "sg:postcode":"92102",
    "sg:province":"CA",
    "sg:tags":[
        "clinic"
    ],
    "sg:website":"www.gambrohealthcare.com",
    "wof:name":"Gambro Healthcare",
    "wof:placetype":"venue"
},
  "geometry": {"coordinates":[-117.114728,32.71465],"type":"Point"}
}