{
  "type": "Feature",
  "properties": {
    "addr:full":"1 Centerpointe Dr La Palma CA 90623",
    "addr:housenumber":"1",
    "addr:postcode":"90623",
    "addr:street":"Centerpointe Dr",
    "iso:country":"US",
    "sg:address":"1 Centerpointe Dr",
    "sg:city":"La Palma",
    "sg:classifiers":[
        {
            "category":"Real Estate",
            "subcategory":"Real Estate Agent",
            "type":"Services"
        }
    ],
    "sg:phone":"+1 714 228 0700",
    "sg:postcode":"90623",
    "sg:province":"CA",
    "wof:name":"CIS Realty Inc",
    "wof:placetype":"venue"
},
  "geometry": {"coordinates":[-118.0311,33.85973],"type":"Point"}
}