{
  "type": "Feature",
  "properties": {
    "iso:country":"US",
    "sg:address":"527 Fee Ana St",
    "sg:city":"Placentia",
    "sg:classifiers":[
        {
            "category":"Manufacturing",
            "subcategory":"Printing",
            "type":"Manufacturing & Wholesale Goods"
        }
    ],
    "sg:phone":"+1 714 996 1333",
    "sg:postcode":"92870",
    "sg:province":"CA",
    "sg:tags":[
        "screen"
    ],
    "sg:website":"www.customlinescreenprint.com",
    "wof:name":"Custom Line T-Shirt Co",
    "wof:placetype":"venue"
},
  "geometry": {"coordinates":[-117.823529,33.865876],"type":"Point"}
}