{
  "type": "Feature",
  "properties": {
    "iso:country":"US",
    "sg:address":"4355 Golden Center Dr",
    "sg:city":"Placerville",
    "sg:classifiers":[
        {
            "category":"Health Services",
            "subcategory":"Doctor",
            "type":"Services"
        }
    ],
    "sg:phone":"+1 530 622 3430",
    "sg:postcode":"95667",
    "sg:province":"CA",
    "sg:tags":[
        "dentist"
    ],
    "wof:name":"Preventive Dental Care Center",
    "wof:placetype":"venue"
},
  "geometry": {"coordinates":[-120.827044,38.705954],"type":"Point"}
}