{
  "type": "Feature",
  "properties": {
    "addr:full":"812 N Miller St Santa Maria CA 93454",
    "addr:housenumber":"812",
    "addr:postcode":"93454",
    "addr:street":"N Miller St",
    "iso:country":"US",
    "sg:address":"812 N Miller St",
    "sg:city":"Santa Maria",
    "sg:classifiers":[
        {
            "category":"Shopping",
            "type":"Retail Goods"
        }
    ],
    "sg:phone":"+1 805 922 5903",
    "sg:postcode":"93454",
    "sg:province":"CA",
    "sg:tags":[
        "awning",
        "canopy"
    ],
    "wof:name":"Creative Construction",
    "wof:placetype":"venue"
},
  "geometry": {"coordinates":[-120.431166,34.962128],"type":"Point"}
}