{
  "type": "Feature",
  "properties": {
    "iso:country":"US",
    "sg:address":"25345 W Ave Stanford",
    "sg:city":"Valencia",
    "sg:classifiers":[
        {
            "category":"Wholesale",
            "subcategory":"Machinery & Supplies",
            "type":"Manufacturing & Wholesale Goods"
        }
    ],
    "sg:phone":"+1 661 257 2288",
    "sg:postcode":"91355",
    "sg:province":"CA",
    "sg:tags":[
        "tool"
    ],
    "wof:name":"UKAM Industrial Superhard",
    "wof:placetype":"venue"
},
  "geometry": {"coordinates":[-118.585542,34.431546],"type":"Point"}
}