{
  "type": "Feature",
  "properties": {
    "addr:full":"401 N Brand Blvd Glendale CA 91203",
    "addr:housenumber":"401",
    "addr:postcode":"91203",
    "addr:street":"N Brand Blvd",
    "iso:country":"US",
    "sg:address":"401 N Brand Blvd",
    "sg:city":"Glendale",
    "sg:classifiers":[
        {
            "category":"Professional",
            "subcategory":"Lawyer & Legal Services",
            "type":"Services"
        }
    ],
    "sg:phone":"+1 818 553 6668",
    "sg:postcode":"91203",
    "sg:province":"CA",
    "wof:name":"Law Offices of Braden M Cancilla",
    "wof:placetype":"venue"
},
  "geometry": {"coordinates":[-118.254997,34.152],"type":"Point"}
}