{
  "type": "Feature",
  "properties": {
    "addr:full":"818 Cherry St Santa Rosa CA 95404",
    "addr:housenumber":"818",
    "addr:postcode":"95404",
    "addr:street":"Cherry St",
    "iso:country":"US",
    "sg:address":"818 Cherry St",
    "sg:city":"Santa Rosa",
    "sg:classifiers":[
        {
            "category":"Social Services",
            "type":"Services"
        }
    ],
    "sg:phone":"+1 707 544 7959",
    "sg:postcode":"95404",
    "sg:province":"CA",
    "sg:tags":[
        "counselor",
        "marriage",
        "family"
    ],
    "wof:name":"Dinah Bachrach",
    "wof:placetype":"venue"
},
  "geometry": {"coordinates":[-122.712507,38.444466],"type":"Point"}
}