{
  "type": "Feature",
  "properties": {
    "addr:full":"803 Hyperion Ave Los Angeles CA 90029",
    "addr:housenumber":"803",
    "addr:postcode":"90029",
    "addr:street":"Hyperion Ave",
    "iso:country":"US",
    "sg:address":"803 Hyperion Ave",
    "sg:city":"Los Angeles",
    "sg:classifiers":[
        {
            "category":"Freight",
            "type":"Transportation"
        },
        {
            "category":"Manufacturing",
            "subcategory":"Tools & Machinery",
            "type":"Manufacturing & Wholesale Goods"
        }
    ],
    "sg:phone":"+1 323 666 0248",
    "sg:postcode":"90029",
    "sg:province":"CA",
    "sg:tags":[
        "mfg",
        "international",
        "computer",
        "electronic",
        "exporting"
    ],
    "wof:name":"Areex International Trading Co",
    "wof:placetype":"venue"
},
  "geometry": {"coordinates":[-118.28372,34.085761],"type":"Point"}
}