{
  "type": "Feature",
  "properties": {
    "addr:full":"2017 W Almond Ave Orange CA 92868",
    "addr:housenumber":"2017",
    "addr:postcode":"92868",
    "addr:street":"W Almond Ave",
    "iso:country":"US",
    "sg:address":"2017 W Almond Ave",
    "sg:city":"Orange",
    "sg:classifiers":[
        {
            "category":"Building & Trades",
            "subcategory":"Construction",
            "type":"Services"
        }
    ],
    "sg:phone":"+1 714 469 2155",
    "sg:postcode":"92868",
    "sg:province":"CA",
    "sg:tags":[
        "house"
    ],
    "wof:name":"CDM Construction",
    "wof:placetype":"venue"
},
  "geometry": {"coordinates":[-117.874808,33.786137],"type":"Point"}
}