{
  "type": "Feature",
  "properties": {
    "addr:full":"1081 Camino Del Rio S Ste 123 San Diego CA 92108",
    "addr:housenumber":"1081",
    "addr:postcode":"92108",
    "addr:street":"Camino Del Rio S Ste 123",
    "iso:country":"US",
    "sg:address":"1081 Camino Del Rio S Ste 123",
    "sg:city":"San Diego",
    "sg:classifiers":[
        {
            "category":"Banks & Credit Unions",
            "subcategory":"Financial Services",
            "type":"Services"
        }
    ],
    "sg:phone":"+1 619 296 5636",
    "sg:postcode":"92108",
    "sg:province":"CA",
    "sg:tags":[
        "broker",
        "mortgage"
    ],
    "wof:name":"America's Finest City Mortgage Inc",
    "wof:placetype":"venue"
},
  "geometry": {"coordinates":[-117.153848,32.764326],"type":"Point"}
}