{
  "type": "Feature",
  "properties": {
    "iso:country":"US",
    "sg:address":"642 Centre Ct",
    "sg:city":"Alameda",
    "sg:classifiers":[
        {
            "category":"Professional",
            "type":"Services"
        }
    ],
    "sg:phone":"+1 510 337 1396",
    "sg:postcode":"94502",
    "sg:province":"CA",
    "wof:name":"OnTarget",
    "wof:placetype":"venue"
},
  "geometry": {"coordinates":[-122.237363,37.745904],"type":"Point"}
}