{
  "type": "Feature",
  "properties": {
    "iso:country":"US",
    "sg:address":"319 S Azusa Ave",
    "sg:city":"Azusa",
    "sg:classifiers":[
        {
            "category":"Shopping",
            "type":"Retail Goods"
        }
    ],
    "sg:phone":"+1 626 815 0888",
    "sg:postcode":"91702",
    "sg:province":"CA",
    "sg:tags":[
        "telephone",
        "cellular"
    ],
    "wof:name":"Azusa Mobile",
    "wof:placetype":"venue"
},
  "geometry": {"coordinates":[-117.907644,34.117711],"type":"Point"}
}