{
  "type": "Feature",
  "properties": {
    "addr:full":"8393 Capwell Dr Oakland CA 94621",
    "addr:housenumber":"8393",
    "addr:postcode":"94621",
    "addr:street":"Capwell Dr",
    "iso:country":"US",
    "sg:address":"8393 Capwell Dr",
    "sg:city":"Oakland",
    "sg:classifiers":[
        {
            "category":"Professional",
            "subcategory":"Lawyer & Legal Services",
            "type":"Services"
        }
    ],
    "sg:phone":"+1 510 562 7700",
    "sg:postcode":"94621",
    "sg:province":"CA",
    "wof:name":"Joseph Jung & Associates",
    "wof:placetype":"venue"
},
  "geometry": {"coordinates":[-122.200656,37.735782],"type":"Point"}
}