{
  "type": "Feature",
  "properties": {
    "iso:country":"US",
    "sg:address":"5933 W Century Blvd",
    "sg:city":"Los Angeles",
    "sg:classifiers":[
        {
            "category":"Utilities",
            "type":"Services"
        }
    ],
    "sg:phone":"+1 310 665 0789",
    "sg:postcode":"90045",
    "sg:province":"CA",
    "sg:tags":[
        "provider",
        "internet"
    ],
    "wof:name":"Aerloconnect",
    "wof:placetype":"venue"
},
  "geometry": {"coordinates":[-118.38674,33.945715],"type":"Point"}
}