{
  "type": "Feature",
  "properties": {
    "iso:country":"US",
    "sg:address":"2173 Lomita Blvd",
    "sg:city":"Lomita",
    "sg:classifiers":[
        {
            "category":"Organizations",
            "subcategory":"Religious Organization",
            "type":"Services"
        }
    ],
    "sg:phone":"+1 310 326 4323",
    "sg:postcode":"90717",
    "sg:province":"CA",
    "sg:tags":[
        "synagogue"
    ],
    "wof:name":"Beis Rebbe Chabad",
    "wof:placetype":"venue"
},
  "geometry": {"coordinates":[-118.31999999999999,33.8022],"type":"Point"}
}