{
  "type": "Feature",
  "properties": {
    "iso:country":"US",
    "sg:address":"2845 Soquel Ave",
    "sg:city":"Santa Cruz",
    "sg:classifiers":[
        {
            "category":"Social Services",
            "type":"Services"
        }
    ],
    "sg:phone":"+1 831 479 9023",
    "sg:postcode":"95062",
    "sg:province":"CA",
    "sg:tags":[
        "housing",
        "assistance"
    ],
    "wof:name":"Santa Cruz Clean & Sober Homes",
    "wof:placetype":"venue"
},
  "geometry": {"coordinates":[-121.987721,36.985998],"type":"Point"}
}