{
  "type": "Feature",
  "properties": {
    "addr:full":"12500 Dupont Rd Sebastopol CA 95472",
    "addr:housenumber":"12500",
    "addr:postcode":"95472",
    "addr:street":"Dupont Rd",
    "iso:country":"US",
    "sg:address":"12500 Dupont Rd",
    "sg:city":"Sebastopol",
    "sg:classifiers":[
        {
            "category":"Health Services",
            "subcategory":"Clinic",
            "type":"Services"
        }
    ],
    "sg:phone":"+1 707 874 3031",
    "sg:postcode":"95472",
    "sg:province":"CA",
    "sg:tags":[
        "aids",
        "testing",
        "information"
    ],
    "sg:website":"www.ncan.org",
    "wof:name":"National Catholic AIDS Ntwk",
    "wof:placetype":"venue"
},
  "geometry": {"coordinates":[-122.914427,38.420325],"type":"Point"}
}