{
  "type": "Feature",
  "properties": {
    "addr:full":"3648 University Ave San Diego CA 92104",
    "addr:housenumber":"3648",
    "addr:postcode":"92104",
    "addr:street":"University Ave",
    "iso:country":"US",
    "sg:address":"3648 University Ave",
    "sg:city":"San Diego",
    "sg:classifiers":[
        {
            "category":"Bars & Pubs",
            "subcategory":"Sports Bar",
            "type":"Food & Drink"
        }
    ],
    "sg:phone":"+1 619 281 4124",
    "sg:postcode":"92104",
    "sg:province":"CA",
    "sg:tags":[
        "hall",
        "pool"
    ],
    "wof:name":"Mekong Billards",
    "wof:placetype":"venue"
},
  "geometry": {"coordinates":[-117.113998,32.749599],"type":"Point"}
}