{
  "type": "Feature",
  "properties": {
    "addr:full":"7388 Trade St San Diego CA 92121",
    "addr:housenumber":"7388",
    "addr:postcode":"92121",
    "addr:street":"Trade St",
    "iso:country":"US",
    "sg:address":"7388 Trade St",
    "sg:city":"San Diego",
    "sg:classifiers":[
        {
            "category":"Travel",
            "subcategory":"Hotels & Motels",
            "type":"Entertainment"
        }
    ],
    "sg:phone":"+1 858 357 4410",
    "sg:postcode":"92121",
    "sg:province":"CA",
    "wof:name":"Admiral Housing Corp",
    "wof:placetype":"venue"
},
  "geometry": {"coordinates":[-117.16338500000001,32.888807],"type":"Point"}
}