{
  "type": "Feature",
  "properties": {
    "addr:full":"315 S 12th St San Jose CA 95112",
    "addr:housenumber":"315",
    "addr:postcode":"95112",
    "addr:street":"S 12Th St",
    "iso:country":"US",
    "sg:address":"315 S 12th St",
    "sg:city":"San Jose",
    "sg:classifiers":[
        {
            "category":"Banks & Credit Unions",
            "subcategory":"Bank",
            "type":"Services"
        }
    ],
    "sg:phone":"+1 408 292 9409",
    "sg:postcode":"95112",
    "sg:province":"CA",
    "sg:tags":[
        "escrow"
    ],
    "wof:name":"DSI Technology Escrow Svc Inc",
    "wof:placetype":"venue"
},
  "geometry": {"coordinates":[-121.874627,37.33567],"type":"Point"}
}