{
  "type": "Feature",
  "properties": {
    "iso:country":"US",
    "sg:address":"4050 Wonder Stump Rd",
    "sg:city":"Crescent City",
    "sg:classifiers":[
        {
            "category":"Home & Garden",
            "subcategory":"Home Furnishings",
            "type":"Retail Goods"
        }
    ],
    "sg:phone":"+1 707 465 5562",
    "sg:postcode":"95531",
    "sg:province":"CA",
    "sg:tags":[
        "quilting"
    ],
    "wof:name":"Foxglove Quilting",
    "wof:placetype":"venue"
},
  "geometry": {"coordinates":[-124.1544,41.819503],"type":"Point"}
}