{
  "type": "Feature",
  "properties": {
    "iso:country":"US",
    "sg:address":"1129 Broadway",
    "sg:city":"San Diego",
    "sg:classifiers":[
        {
            "category":"Building & Trades",
            "subcategory":"Construction",
            "type":"Services"
        }
    ],
    "sg:phone":"+1 619 544 6828",
    "sg:postcode":"92101",
    "sg:province":"CA",
    "sg:tags":[
        "general",
        "contractor"
    ],
    "wof:name":"Hensel Phelps Construction Co",
    "wof:placetype":"venue"
},
  "geometry": {"coordinates":[-117.154073,32.715655],"type":"Point"}
}