{
  "type": "Feature",
  "properties": {
    "iso:country":"US",
    "sg:address":"1002 E el Camino Real",
    "sg:city":"Sunnyvale",
    "sg:classifiers":[
        {
            "category":"Shopping",
            "subcategory":"Florist",
            "type":"Retail Goods"
        }
    ],
    "sg:phone":"+1 408 773 1113",
    "sg:postcode":"94087",
    "sg:province":"CA",
    "wof:name":"Conroy's Flowers",
    "wof:placetype":"venue"
},
  "geometry": {"coordinates":[-122.005083,37.352025],"type":"Point"}
}