{
  "type": "Feature",
  "properties": {
    "iso:country":"US",
    "sg:address":"17800 Castleton St",
    "sg:city":"City Of Industry",
    "sg:classifiers":[
        {
            "category":"Professional",
            "type":"Services"
        }
    ],
    "sg:phone":"+1 626 964 3285",
    "sg:postcode":"91748",
    "sg:province":"CA",
    "sg:tags":[
        "establishment"
    ],
    "wof:name":"Newslink USA Inc",
    "wof:placetype":"venue"
},
  "geometry": {"coordinates":[-117.91860200000001,33.993264],"type":"Point"}
}