{
  "type": "Feature",
  "properties": {
    "iso:country":"US",
    "sg:address":"1718 N Highland Ave",
    "sg:city":"Los Angeles",
    "sg:classifiers":[
        {
            "category":"Shopping",
            "subcategory":"Used Merchandise",
            "type":"Retail Goods"
        }
    ],
    "sg:phone":"+1 323 462 5323",
    "sg:postcode":"90028",
    "sg:province":"CA",
    "sg:tags":[
        "clothing"
    ],
    "wof:name":"Fantastic Store",
    "wof:placetype":"venue"
},
  "geometry": {"coordinates":[-118.338621,34.101591],"type":"Point"}
}