{
  "type": "Feature",
  "properties": {
    "addr:full":"1016 S Victoria Ave Los Angeles CA 90019",
    "addr:housenumber":"1016",
    "addr:postcode":"90019",
    "addr:street":"S Victoria Ave",
    "iso:country":"US",
    "sg:address":"1016 S Victoria Ave",
    "sg:city":"Los Angeles",
    "sg:classifiers":[
        {
            "category":"Autos & Motor Vehicles",
            "subcategory":"Auto Supplies",
            "type":"Retail Goods"
        },
        {
            "category":"Retail",
            "subcategory":"Auto Repair",
            "type":"Services"
        }
    ],
    "sg:phone":"+1 213 744 0011",
    "sg:postcode":"90019",
    "sg:province":"CA",
    "sg:tags":[
        "tire"
    ],
    "wof:name":"Calif Tire Mart Inc",
    "wof:placetype":"venue"
},
  "geometry": {"coordinates":[-118.32399700000001,34.054798],"type":"Point"}
}