{
  "type": "Feature",
  "properties": {
    "addr:full":"5755 E Kings Canyon Rd # 122 Fresno CA 93727",
    "addr:housenumber":"5755",
    "addr:postcode":"93727",
    "addr:street":"E Kings Canyon Rd # 122",
    "iso:country":"US",
    "sg:address":"5755 E Kings Canyon Rd # 122",
    "sg:city":"Fresno",
    "sg:classifiers":[
        {
            "category":"Banks & Credit Unions",
            "subcategory":"Investment Brokerage",
            "type":"Services"
        }
    ],
    "sg:phone":"+1 559 251 4892",
    "sg:postcode":"93727",
    "sg:province":"CA",
    "sg:tags":[
        "security"
    ],
    "wof:name":"Thomas F White & Co",
    "wof:placetype":"venue"
},
  "geometry": {"coordinates":[-119.69300800000001,36.736279],"type":"Point"}
}