{
  "type": "Feature",
  "properties": {
    "addr:full":"2570 N First St San Jose CA 95131",
    "addr:housenumber":"2570",
    "addr:postcode":"95131",
    "addr:street":"N First St",
    "iso:country":"US",
    "sg:address":"2570 N First St",
    "sg:city":"San Jose",
    "sg:classifiers":[
        {
            "category":"Personal",
            "type":"Services"
        }
    ],
    "sg:phone":"+1 888 236 7576",
    "sg:postcode":"95131",
    "sg:province":"CA",
    "sg:tags":[
        "local"
    ],
    "sg:website":"www.bestmoversca.com",
    "wof:name":"Best Movers California",
    "wof:placetype":"venue"
},
  "geometry": {"coordinates":[-121.924876,37.385254],"type":"Point"}
}