{
  "type": "Feature",
  "properties": {
    "iso:country":"US",
    "sg:address":"14445 Ventura Blvd.",
    "sg:city":"Los Angeles",
    "sg:classifiers":[
        {
            "category":"Shopping",
            "subcategory":"Tobacco",
            "type":"Retail Goods"
        }
    ],
    "sg:phone":"+1 818 907 9209",
    "sg:postcode":"91423",
    "sg:province":"CA",
    "sg:tags":[
        "shop"
    ],
    "wof:name":"Sherman Oaks Cigars",
    "wof:placetype":"venue"
},
  "geometry": {"coordinates":[-118.44800499999999,34.150796],"type":"Point"}
}