{
  "type": "Feature",
  "properties": {
    "iso:country":"US",
    "sg:address":"7391 Rd 7",
    "sg:city":"Firebaugh",
    "sg:classifiers":[
        {
            "category":"Professional",
            "type":"Services"
        }
    ],
    "sg:phone":"+1 559 659 2615",
    "sg:postcode":"93622",
    "sg:province":"CA",
    "sg:tags":[
        "arts",
        "artist"
    ],
    "wof:name":"Mary Allen's Country Colors",
    "wof:placetype":"venue"
},
  "geometry": {"coordinates":[-120.417778,36.857457],"type":"Point"}
}