{
  "type": "Feature",
  "properties": {
    "addr:full":"209 Chandon Laguna Niguel CA 92677",
    "addr:housenumber":"209",
    "addr:postcode":"92677",
    "addr:street":"Chandon",
    "iso:country":"US",
    "sg:address":"209 Chandon",
    "sg:city":"Laguna Niguel",
    "sg:classifiers":[
        {
            "category":"Shopping",
            "type":"Retail Goods"
        }
    ],
    "sg:phone":"+1 949 495 2858",
    "sg:postcode":"92677",
    "sg:province":"CA",
    "sg:tags":[
        "plant",
        "flower",
        "tree",
        "artificial"
    ],
    "wof:name":"Montage Designs",
    "wof:placetype":"venue"
},
  "geometry": {"coordinates":[-117.68922999999999,33.52305],"type":"Point"}
}