{
  "type": "Feature",
  "properties": {
    "addr:full":"199 Fremont St. 21st Floor San Francisco CA 94105",
    "addr:housenumber":"199",
    "addr:postcode":"94105",
    "addr:street":"Fremont St.;Floor",
    "iso:country":"US",
    "sg:address":"199 Fremont St. 21st Floor",
    "sg:city":"San Francisco",
    "sg:classifiers":[
        {
            "category":"Professional",
            "subcategory":"Lawyer & Legal Services",
            "type":"Services"
        }
    ],
    "sg:phone":"+1 415 278 0950",
    "sg:postcode":"94105",
    "sg:province":"CA",
    "sg:website":"www.adelitollen.com",
    "wof:name":"Adeli & Tollen",
    "wof:placetype":"venue"
},
  "geometry": {"coordinates":[-122.395184,37.789268],"type":"Point"}
}