{
  "type": "Feature",
  "properties": {
    "addr:full":"1655 Brandywine Ave Chula Vista CA 91911",
    "addr:housenumber":"1655",
    "addr:postcode":"91911",
    "addr:street":"Brandywine Ave",
    "iso:country":"US",
    "sg:address":"1655 Brandywine Ave",
    "sg:city":"Chula Vista",
    "sg:classifiers":[
        {
            "category":"Restaurant",
            "type":"Food & Drink"
        }
    ],
    "sg:phone":"+1 619 482 9722",
    "sg:postcode":"91911",
    "sg:province":"CA",
    "sg:tags":[
        "pizza"
    ],
    "wof:name":"Corzy Corner Pizza",
    "wof:placetype":"venue"
},
  "geometry": {"coordinates":[-117.02887800000001,32.601828],"type":"Point"}
}