{
  "type": "Feature",
  "properties": {
    "addr:full":"13198 Greenhorn Rd Grass Valley CA 95945",
    "addr:housenumber":"13198",
    "addr:postcode":"95945",
    "addr:street":"Greenhorn Rd",
    "iso:country":"US",
    "sg:address":"13198 Greenhorn Rd",
    "sg:city":"Grass Valley",
    "sg:classifiers":[
        {
            "category":"Professional",
            "type":"Services"
        }
    ],
    "sg:phone":"+1 530 477 0944",
    "sg:postcode":"95945",
    "sg:province":"CA",
    "wof:name":"Pam Brown",
    "wof:placetype":"venue"
},
  "geometry": {"coordinates":[-121.00734799999999,39.213763],"type":"Point"}
}