{
  "type": "Feature",
  "properties": {
    "addr:full":"4195 Inland Empire Blvd Ontario CA 91764",
    "addr:housenumber":"4195",
    "addr:postcode":"91764",
    "addr:street":"Inland Empire Blvd",
    "iso:country":"US",
    "sg:address":"4195 Inland Empire Blvd",
    "sg:city":"Ontario",
    "sg:classifiers":[
        {
            "category":"Home & Garden",
            "subcategory":"Furniture",
            "type":"Retail Goods"
        }
    ],
    "sg:phone":"+1 909 477 3278",
    "sg:postcode":"91764",
    "sg:province":"CA",
    "sg:tags":[
        "store"
    ],
    "wof:name":"Easy Life Furniture",
    "wof:placetype":"venue"
},
  "geometry": {"coordinates":[-117.56194499999999,34.069904],"type":"Point"}
}