{
  "type": "Feature",
  "properties": {
    "addr:full":"3263 E Ventura Ave Fresno CA 93702",
    "addr:housenumber":"3263",
    "addr:postcode":"93702",
    "addr:street":"E Ventura Ave",
    "iso:country":"US",
    "sg:address":"3263 E Ventura Ave",
    "sg:city":"Fresno",
    "sg:classifiers":[
        {
            "category":"Shopping",
            "subcategory":"Clothing, Apparel, & Fashions",
            "type":"Retail Goods"
        }
    ],
    "sg:phone":"+1 559 233 0718",
    "sg:postcode":"93702",
    "sg:province":"CA",
    "sg:tags":[
        "western"
    ],
    "wof:name":"El Norteno",
    "wof:placetype":"venue"
},
  "geometry": {"coordinates":[-119.770172,36.735948],"type":"Point"}
}