{
  "type": "Feature",
  "properties": {
    "iso:country":"US",
    "sg:address":"8185 S Lake Cir",
    "sg:city":"Granite Bay",
    "sg:classifiers":[
        {
            "category":"Recreation",
            "subcategory":"Marina",
            "type":"Entertainment"
        }
    ],
    "sg:phone":"+1 916 791 1493",
    "sg:postcode":"95746",
    "sg:province":"CA",
    "sg:tags":[
        "operation"
    ],
    "wof:name":"Emerald Cove Resort & Marina",
    "wof:placetype":"venue"
},
  "geometry": {"coordinates":[-121.153988,38.76816],"type":"Point"}
}