{
  "type": "Feature",
  "properties": {
    "iso:country":"US",
    "sg:address":"5909 Lankershim Blvd",
    "sg:city":"North Hollywood",
    "sg:classifiers":[
        {
            "category":"Travel",
            "subcategory":"Hotels & Motels",
            "type":"Entertainment"
        }
    ],
    "sg:phone":"+1 818 763 6959",
    "sg:postcode":"91601",
    "sg:province":"CA",
    "wof:name":"Pepper Tree Motel",
    "wof:placetype":"venue"
},
  "geometry": {"coordinates":[-118.38200399999999,34.177601],"type":"Point"}
}