{
  "type": "Feature",
  "properties": {
    "addr:full":"4373 La Jolla Village Drive San Diego CA 92122",
    "addr:housenumber":"4373",
    "addr:postcode":"92122",
    "addr:street":"La Jolla Village Drive",
    "iso:country":"US",
    "sg:address":"4373 La Jolla Village Drive",
    "sg:city":"San Diego",
    "sg:classifiers":[
        {
            "category":"Shopping",
            "subcategory":"Shoes",
            "type":"Retail Goods"
        }
    ],
    "sg:phone":"+1 858 587 2864",
    "sg:postcode":"92122",
    "sg:province":"CA",
    "sg:tags":[
        "store"
    ],
    "wof:name":"Lady Foot Locker",
    "wof:placetype":"venue"
},
  "geometry": {"coordinates":[-117.212272,32.872899],"type":"Point"}
}