{
  "type": "Feature",
  "properties": {
    "iso:country":"US",
    "sg:address":"422 S Pasadena Ave",
    "sg:city":"Pasadena",
    "sg:classifiers":[
        {
            "category":"Building & Trades",
            "subcategory":"Cleaning & Sanitation",
            "type":"Services"
        }
    ],
    "sg:phone":"+1 626 398 7141",
    "sg:postcode":"91105",
    "sg:province":"CA",
    "sg:tags":[
        "awning",
        "canopy"
    ],
    "wof:name":"A-1 Superclean",
    "wof:placetype":"venue"
},
  "geometry": {"coordinates":[-118.154018,34.138635],"type":"Point"}
}