{
  "type": "Feature",
  "properties": {
    "iso:country":"US",
    "sg:address":"98 N Patterson Ave",
    "sg:city":"Santa Barbara",
    "sg:classifiers":[
        {
            "category":"Freight",
            "type":"Transportation"
        }
    ],
    "sg:phone":"+1 805 683 2150",
    "sg:postcode":"93111",
    "sg:province":"CA",
    "sg:tags":[
        "mover"
    ],
    "wof:name":"Pro Moving",
    "wof:placetype":"venue"
},
  "geometry": {"coordinates":[-119.807857,34.444644],"type":"Point"}
}