{
  "type": "Feature",
  "properties": {
    "iso:country":"US",
    "sg:address":"1101 W el Segundo Blvd",
    "sg:city":"Gardena",
    "sg:classifiers":[
        {
            "category":"Wholesale",
            "subcategory":"Auto Parts",
            "type":"Manufacturing & Wholesale Goods"
        }
    ],
    "sg:phone":"+1 323 757 9946",
    "sg:postcode":"90247",
    "sg:province":"CA",
    "wof:name":"El Segundo Auto Parts",
    "wof:placetype":"venue"
},
  "geometry": {"coordinates":[-118.294302,33.916427],"type":"Point"}
}