{
  "type": "Feature",
  "properties": {
    "iso:country":"US",
    "sg:address":"3131 Cam del Rio N",
    "sg:city":"San Diego",
    "sg:classifiers":[
        {
            "category":"Professional",
            "subcategory":"Management & Consulting",
            "type":"Services"
        }
    ],
    "sg:phone":"+1 619 516 2559",
    "sg:postcode":"92108",
    "sg:province":"CA",
    "sg:tags":[
        "counselor",
        "public",
        "relations"
    ],
    "sg:website":"www.lewispr.com",
    "wof:name":"P R Lewis Inc",
    "wof:placetype":"venue"
},
  "geometry": {"coordinates":[-117.1305,32.773899],"type":"Point"}
}