{
  "type": "Feature",
  "properties": {
    "addr:full":"261 Olive Ave Patterson CA 95363",
    "addr:housenumber":"261",
    "addr:postcode":"95363",
    "addr:street":"Olive Ave",
    "iso:country":"US",
    "sg:address":"261 Olive Ave",
    "sg:city":"Patterson",
    "sg:classifiers":[
        {
            "category":"Farming",
            "subcategory":"Orchard",
            "type":"Manufacturing & Wholesale Goods"
        }
    ],
    "sg:phone":"+1 209 892 8245",
    "sg:postcode":"95363",
    "sg:province":"CA",
    "sg:tags":[
        "fruit",
        "tree"
    ],
    "wof:name":"Arthur Filice",
    "wof:placetype":"venue"
},
  "geometry": {"coordinates":[-121.12672600000001,37.489789],"type":"Point"}
}