{
  "type": "Feature",
  "properties": {
    "addr:full":"4223 Genesee Ave San Diego CA 92117",
    "addr:housenumber":"4223",
    "addr:postcode":"92117",
    "addr:street":"Genesee Ave",
    "iso:country":"US",
    "sg:address":"4223 Genesee Ave",
    "sg:city":"San Diego",
    "sg:classifiers":[
        {
            "category":"Banks & Credit Unions",
            "subcategory":"Financial Services",
            "type":"Services"
        }
    ],
    "sg:phone":"+1 858 278 5361",
    "sg:postcode":"92117",
    "sg:province":"CA",
    "sg:tags":[
        "broker",
        "mortgage"
    ],
    "wof:name":"Household Finance Corp",
    "wof:placetype":"venue"
},
  "geometry": {"coordinates":[-117.181999,32.819901],"type":"Point"}
}