{
  "type": "Feature",
  "properties": {
    "addr:full":"5504 York Blvd Los Angeles CA 90042",
    "addr:housenumber":"5504",
    "addr:postcode":"90042",
    "addr:street":"York Blvd",
    "iso:country":"US",
    "sg:address":"5504 York Blvd",
    "sg:city":"Los Angeles",
    "sg:classifiers":[
        {
            "category":"Personal",
            "subcategory":"Beauty Salon",
            "type":"Services"
        }
    ],
    "sg:phone":"+1 323 259 5710",
    "sg:postcode":"90042",
    "sg:province":"CA",
    "wof:name":"Erika's Beauty Salon",
    "wof:placetype":"venue"
},
  "geometry": {"coordinates":[-118.19676200000001,34.119338],"type":"Point"}
}