{
  "type": "Feature",
  "properties": {
    "addr:full":"15561 Union Avenue Los Gatos CA 95032",
    "addr:housenumber":"15561",
    "addr:postcode":"95032",
    "addr:street":"Union Avenue",
    "iso:country":"US",
    "sg:address":"15561 Union Avenue",
    "sg:city":"Los Gatos",
    "sg:classifiers":[
        {
            "category":"Retail",
            "subcategory":"Laundry & Dry Cleaning",
            "type":"Services"
        }
    ],
    "sg:phone":"+1 408 371 9268",
    "sg:postcode":"95032",
    "sg:province":"CA",
    "wof:name":"Dryclean City",
    "wof:placetype":"venue"
},
  "geometry": {"coordinates":[-121.931106,37.242649],"type":"Point"}
}