{
  "type": "Feature",
  "properties": {
    "addr:full":"3665 Kearny Villa Rd San Diego CA 92123",
    "addr:housenumber":"3665",
    "addr:postcode":"92123",
    "addr:street":"Kearny Villa Rd",
    "iso:country":"US",
    "sg:address":"3665 Kearny Villa Rd",
    "sg:city":"San Diego",
    "sg:classifiers":[
        {
            "category":"Health Services",
            "subcategory":"Hospital",
            "type":"Services"
        }
    ],
    "sg:phone":"+1 858 966 5832",
    "sg:postcode":"92123",
    "sg:province":"CA",
    "wof:name":"Children's Hospital & Hlth Ctr",
    "wof:placetype":"venue"
},
  "geometry": {"coordinates":[-117.150575,32.807213],"type":"Point"}
}