{
  "type": "Feature",
  "properties": {
    "addr:full":"1350 Railroad Ave Livermore CA 94550",
    "addr:housenumber":"1350",
    "addr:postcode":"94550",
    "addr:street":"Railroad Ave",
    "iso:country":"US",
    "sg:address":"1350 Railroad Ave",
    "sg:city":"Livermore",
    "sg:classifiers":[
        {
            "category":"Health Services",
            "subcategory":"Doctor",
            "type":"Services"
        }
    ],
    "sg:phone":"+1 925 447 3057",
    "sg:postcode":"94550",
    "sg:province":"CA",
    "sg:tags":[
        "dentist"
    ],
    "sg:website":"www.livermorefamilydentist.com",
    "wof:name":"Livermore Family Dentistry",
    "wof:placetype":"venue"
},
  "geometry": {"coordinates":[-121.777012,37.681184],"type":"Point"}
}