{
  "type": "Feature",
  "properties": {
    "iso:country":"US",
    "sg:address":"5100 Woodman Ave",
    "sg:city":"Sherman Oaks",
    "sg:classifiers":[
        {
            "category":"Professional",
            "type":"Services"
        }
    ],
    "sg:phone":"+1 818 907 8064",
    "sg:postcode":"91423",
    "sg:province":"CA",
    "wof:name":"Jay-R Svc",
    "wof:placetype":"venue"
},
  "geometry": {"coordinates":[-118.431161,34.163034],"type":"Point"}
}