{
  "type": "Feature",
  "properties": {
    "iso:country":"US",
    "sg:address":"110 W A St",
    "sg:city":"San Diego",
    "sg:classifiers":[
        {
            "category":"Government",
            "subcategory":"Court House",
            "type":"Public Place"
        }
    ],
    "sg:phone":"+1 619 645 2212",
    "sg:postcode":"92101",
    "sg:province":"CA",
    "sg:tags":[
        "legal"
    ],
    "wof:name":"Califrnia Attrney Generals Off",
    "wof:placetype":"venue"
},
  "geometry": {"coordinates":[-117.164659,32.718898],"type":"Point"}
}