{
  "type": "Feature",
  "properties": {
    "addr:full":"515 Middle Rincon Rd Santa Rosa CA 95409",
    "addr:housenumber":"515",
    "addr:postcode":"95409",
    "addr:street":"Middle Rincon Rd",
    "iso:country":"US",
    "sg:address":"515 Middle Rincon Rd",
    "sg:city":"Santa Rosa",
    "sg:classifiers":[
        {
            "category":"Social Services",
            "subcategory":"Adult Care",
            "type":"Services"
        }
    ],
    "sg:phone":"+1 707 538 2140",
    "sg:postcode":"95409",
    "sg:province":"CA",
    "sg:tags":[
        "home",
        "residential"
    ],
    "wof:name":"Ward's Valley View Guest Home",
    "wof:placetype":"venue"
},
  "geometry": {"coordinates":[-122.669155,38.470568],"type":"Point"}
}