{
  "type": "Feature",
  "properties": {
    "addr:full":"3320 Palm Ave San Diego CA 92154",
    "addr:housenumber":"3320",
    "addr:postcode":"92154",
    "addr:street":"Palm Ave",
    "iso:country":"US",
    "sg:address":"3320 Palm Ave",
    "sg:city":"San Diego",
    "sg:classifiers":[
        {
            "category":"Professional",
            "subcategory":"Accounting & Tax Preparation",
            "type":"Services"
        }
    ],
    "sg:phone":"+1 619 429 1500",
    "sg:postcode":"92154",
    "sg:province":"CA",
    "sg:tags":[
        "return"
    ],
    "wof:name":"H & R Block",
    "wof:placetype":"venue"
},
  "geometry": {"coordinates":[-117.060925,32.58382],"type":"Point"}
}