{
  "type": "Feature",
  "properties": {
    "iso:country":"US",
    "sg:address":"245 S Glenwood St",
    "sg:city":"Delano",
    "sg:classifiers":[
        {
            "category":"Retail",
            "subcategory":"Repair Shop",
            "type":"Services"
        }
    ],
    "sg:phone":"+1 661 725 6839",
    "sg:postcode":"93215",
    "sg:province":"CA",
    "sg:tags":[
        "tractor"
    ],
    "wof:name":"Dale Sneed Tractor Repair",
    "wof:placetype":"venue"
},
  "geometry": {"coordinates":[-119.24393000000001,35.750613],"type":"Point"}
}