{
  "type": "Feature",
  "properties": {
    "addr:full":"1330 14th Avenue San Francisco CA 94122",
    "addr:housenumber":"1330",
    "addr:postcode":"94122",
    "addr:street":"14Th Avenue",
    "iso:country":"US",
    "sg:address":"1330 14th Avenue",
    "sg:city":"San Francisco",
    "sg:classifiers":[
        {
            "category":"Education",
            "subcategory":"School",
            "type":"Public Place"
        }
    ],
    "sg:phone":"+1 415 665 3929",
    "sg:postcode":"94122",
    "sg:province":"CA",
    "sg:tags":[
        "high",
        "middle",
        "elementary"
    ],
    "wof:name":"St Anne's Chinese School",
    "wof:placetype":"venue"
},
  "geometry": {"coordinates":[-122.47199999999999,37.7631],"type":"Point"}
}