{
  "type": "Feature",
  "properties": {
    "iso:country":"US",
    "sg:address":"87 Encina Ave",
    "sg:city":"Palo Alto",
    "sg:classifiers":[
        {
            "category":"Health Services",
            "subcategory":"Doctor",
            "type":"Services"
        }
    ],
    "sg:phone":"+1 650 853 2975",
    "sg:postcode":"94301",
    "sg:province":"CA",
    "sg:tags":[
        "physician",
        "surgeon"
    ],
    "wof:name":"Palo Alto Medical Foundation",
    "wof:placetype":"venue"
},
  "geometry": {"coordinates":[-122.159539,37.439505],"type":"Point"}
}