{
  "type": "Feature",
  "properties": {
    "iso:country":"US",
    "sg:address":"22185 McBride Rd",
    "sg:city":"Escalon",
    "sg:classifiers":[
        {
            "category":"Retail",
            "subcategory":"Animal Services",
            "type":"Services"
        }
    ],
    "sg:phone":"+1 209 838 8201",
    "sg:postcode":"95320",
    "sg:province":"CA",
    "wof:name":"Huffman Ranch",
    "wof:placetype":"venue"
},
  "geometry": {"coordinates":[-120.930509,37.756613],"type":"Point"}
}