{
  "type": "Feature",
  "properties": {
    "addr:full":"7901 Stoneridge Dr Pleasanton CA 94588",
    "addr:housenumber":"7901",
    "addr:postcode":"94588",
    "addr:street":"Stoneridge Dr",
    "iso:country":"US",
    "sg:address":"7901 Stoneridge Dr",
    "sg:city":"Pleasanton",
    "sg:classifiers":[
        {
            "category":"Utilities",
            "subcategory":"Cable",
            "type":"Services"
        }
    ],
    "sg:phone":"+1 925 463 1919",
    "sg:postcode":"94588",
    "sg:province":"CA",
    "sg:tags":[
        "television"
    ],
    "wof:name":"Pacific Sun Cable Partner",
    "wof:placetype":"venue"
},
  "geometry": {"coordinates":[-121.930286,37.6888],"type":"Point"}
}