{
  "type": "Feature",
  "properties": {
    "iso:country":"US",
    "sg:address":"1708 Ocean Park Blvd",
    "sg:city":"Santa Monica",
    "sg:classifiers":[
        {
            "category":"Personal",
            "subcategory":"Shoe Repair & Shine",
            "type":"Services"
        }
    ],
    "sg:phone":"+1 310 452 1113",
    "sg:postcode":"90405",
    "sg:province":"CA",
    "sg:tags":[
        "repairing",
        "boot"
    ],
    "wof:name":"Maya Shoe Repair",
    "wof:placetype":"venue"
},
  "geometry": {"coordinates":[-118.465664,34.013051],"type":"Point"}
}