{
  "type": "Feature",
  "properties": {
    "iso:country":"US",
    "sg:address":"2603 Denver St",
    "sg:city":"San Diego",
    "sg:classifiers":[
        {
            "category":"Personal",
            "subcategory":"Beauty Salon",
            "type":"Services"
        }
    ],
    "sg:phone":"+1 619 276 7300",
    "sg:postcode":"92110",
    "sg:province":"CA",
    "sg:tags":[
        "hair"
    ],
    "wof:name":"Essence Salon",
    "wof:placetype":"venue"
},
  "geometry": {"coordinates":[-117.20331400000001,32.789578],"type":"Point"}
}