{
  "type": "Feature",
  "properties": {
    "iso:country":"US",
    "sg:address":"161 E 40th St",
    "sg:city":"San Bernardino",
    "sg:classifiers":[
        {
            "category":"Banks & Credit Unions",
            "subcategory":"Bank",
            "type":"Services"
        }
    ],
    "sg:phone":"+1 909 881 8872",
    "sg:postcode":"92404",
    "sg:province":"CA",
    "wof:name":"Arrowhead Credit Union",
    "wof:placetype":"venue"
},
  "geometry": {"coordinates":[-117.283592,34.164758],"type":"Point"}
}