{
  "type": "Feature",
  "properties": {
    "iso:country":"US",
    "sg:address":"6460 Ivarene Ave",
    "sg:city":"Los Angeles",
    "sg:classifiers":[
        {
            "category":"Professional",
            "type":"Services"
        }
    ],
    "sg:phone":"+1 323 465 7289",
    "sg:postcode":"90068",
    "sg:province":"CA",
    "wof:name":"Kniaz Estes Inc",
    "wof:placetype":"venue"
},
  "geometry": {"coordinates":[-118.327743,34.11153],"type":"Point"}
}