{
  "type": "Feature",
  "properties": {
    "iso:country":"US",
    "sg:address":"16133 Ventura Blvd",
    "sg:city":"Encino",
    "sg:classifiers":[
        {
            "category":"Professional",
            "type":"Services"
        }
    ],
    "sg:phone":"+1 818 995 9159",
    "sg:postcode":"91436",
    "sg:province":"CA",
    "sg:tags":[
        "establishment"
    ],
    "wof:name":"Speed Freaks",
    "wof:placetype":"venue"
},
  "geometry": {"coordinates":[-118.487387,34.156944],"type":"Point"}
}