{
  "type": "Feature",
  "properties": {
    "addr:full":"20346 Valley Blvd Tehachapi CA 93561",
    "addr:housenumber":"20346",
    "addr:postcode":"93561",
    "addr:street":"Valley Blvd",
    "iso:country":"US",
    "sg:address":"20346 Valley Blvd",
    "sg:city":"Tehachapi",
    "sg:classifiers":[
        {
            "category":"Shopping",
            "subcategory":"Computers & Home Electronics",
            "type":"Retail Goods"
        }
    ],
    "sg:phone":"+1 661 822 4512",
    "sg:postcode":"93561",
    "sg:province":"CA",
    "sg:tags":[
        "equipment",
        "electronic",
        "supply"
    ],
    "wof:name":"Radio Shack",
    "wof:placetype":"venue"
},
  "geometry": {"coordinates":[-118.49208,35.124359],"type":"Point"}
}