{
  "type": "Feature",
  "properties": {
    "addr:full":"29292 Kestrel Ln Laguna Niguel CA 92677",
    "addr:housenumber":"29292",
    "addr:postcode":"92677",
    "addr:street":"Kestrel Ln",
    "iso:country":"US",
    "sg:address":"29292 Kestrel Ln",
    "sg:city":"Laguna Niguel",
    "sg:classifiers":[
        {
            "category":"Education",
            "subcategory":"Library",
            "type":"Public Place"
        }
    ],
    "sg:phone":"+1 952 446 1418",
    "sg:postcode":"92677",
    "sg:province":"CA",
    "sg:tags":[
        "executive"
    ],
    "wof:name":"Saint Bonifacius Library",
    "wof:placetype":"venue"
},
  "geometry": {"coordinates":[-117.709664,33.538155],"type":"Point"}
}