{
  "type": "Feature",
  "properties": {
    "iso:country":"US",
    "sg:address":"14255 San Pablo Ave",
    "sg:city":"San Pablo",
    "sg:classifiers":[
        {
            "category":"Personal",
            "subcategory":"Beauty Salon",
            "type":"Services"
        }
    ],
    "sg:phone":"+1 510 237 9813",
    "sg:postcode":"94806",
    "sg:province":"CA",
    "wof:name":"Coco's Beauty Salon",
    "wof:placetype":"venue"
},
  "geometry": {"coordinates":[-122.345248,37.964411],"type":"Point"}
}