{
  "type": "Feature",
  "properties": {
    "addr:full":"6750 Folsom Blvd #228 Sacramento CA 95819",
    "addr:housenumber":"6750",
    "addr:postcode":"95819",
    "addr:street":"Folsom Blvd # 228",
    "iso:country":"US",
    "sg:address":"6750 Folsom Blvd #228",
    "sg:city":"Sacramento",
    "sg:classifiers":[
        {
            "category":"Retail",
            "subcategory":"Driving School",
            "type":"Services"
        }
    ],
    "sg:phone":"+1 916 690 6888",
    "sg:postcode":"95819",
    "sg:province":"CA",
    "sg:tags":[
        "instruction"
    ],
    "sg:website":"http://www.camellok.com",
    "wof:name":"Camellok Driving School",
    "wof:placetype":"venue"
},
  "geometry": {"coordinates":[-121.42497899999999,38.55339],"type":"Point"}
}