{
  "type": "Feature",
  "properties": {
    "addr:full":"2025 Ainsley Rd San Diego CA 92123",
    "addr:housenumber":"2025",
    "addr:postcode":"92123",
    "addr:street":"Ainsley Rd",
    "iso:country":"US",
    "sg:address":"2025 Ainsley Rd",
    "sg:city":"San Diego",
    "sg:classifiers":[
        {
            "category":"Professional",
            "subcategory":"Business Services",
            "type":"Services"
        }
    ],
    "sg:phone":"+1 858 565 0464",
    "sg:postcode":"92123",
    "sg:province":"CA",
    "sg:tags":[
        "appraiser"
    ],
    "wof:name":"Conrique Efrain & Assoc",
    "wof:placetype":"venue"
},
  "geometry": {"coordinates":[-117.150509,32.780284],"type":"Point"}
}