{
  "type": "Feature",
  "properties": {
    "addr:full":"100 Coddingtown Ctr Santa Rosa CA 95401",
    "addr:housenumber":"100",
    "addr:postcode":"95401",
    "addr:street":"Coddingtown Ctr",
    "iso:country":"US",
    "sg:address":"100 Coddingtown Ctr",
    "sg:city":"Santa Rosa",
    "sg:classifiers":[
        {
            "category":"Restaurant",
            "type":"Food & Drink"
        }
    ],
    "sg:menulink":"http://www.allmenus.com/ca/santa-rosa/149354-subway/menu/",
    "sg:phone":"+1 707 546 9493",
    "sg:postcode":"95401",
    "sg:province":"CA",
    "sg:tags":[
        "american",
        "sandwich"
    ],
    "wof:name":"Subway",
    "wof:placetype":"venue"
},
  "geometry": {"coordinates":[-122.728759,38.459504],"type":"Point"}
}