{
  "type": "Feature",
  "properties": {
    "addr:full":"1968 N Gateway Blvd Fresno CA 93727",
    "addr:housenumber":"1968",
    "addr:postcode":"93727",
    "addr:street":"N Gateway Blvd",
    "iso:country":"US",
    "sg:address":"1968 N Gateway Blvd",
    "sg:city":"Fresno",
    "sg:classifiers":[
        {
            "category":"Professional",
            "subcategory":"Advertising",
            "type":"Services"
        }
    ],
    "sg:phone":"+1 559 456 3333",
    "sg:postcode":"93727",
    "sg:province":"CA",
    "sg:tags":[
        "guide"
    ],
    "wof:name":"Latino Yellow Pages",
    "wof:placetype":"venue"
},
  "geometry": {"coordinates":[-119.72669399999999,36.767735],"type":"Point"}
}