{
  "type": "Feature",
  "properties": {
    "addr:full":"372 Luddy Ln San Andreas CA 95249",
    "addr:housenumber":"372",
    "addr:postcode":"95249",
    "addr:street":"Luddy Ln",
    "iso:country":"US",
    "sg:address":"372 Luddy Ln",
    "sg:city":"San Andreas",
    "sg:classifiers":[
        {
            "category":"Health Services",
            "subcategory":"Doctor",
            "type":"Services"
        }
    ],
    "sg:phone":"+1 209 754 3864",
    "sg:postcode":"95249",
    "sg:province":"CA",
    "sg:tags":[
        "dentist"
    ],
    "wof:name":"Bruce Dunwell DDS",
    "wof:placetype":"venue"
},
  "geometry": {"coordinates":[-120.687409,38.19794],"type":"Point"}
}