{
  "type": "Feature",
  "properties": {
    "iso:country":"US",
    "sg:address":"523 S Maple St",
    "sg:city":"Corona",
    "sg:classifiers":[
        {
            "category":"Real Estate",
            "subcategory":"Real Estate Agent",
            "type":"Services"
        }
    ],
    "sg:phone":"+1 951 736 1373",
    "sg:postcode":"92880",
    "sg:province":"CA",
    "wof:name":"Stardust Real Estate",
    "wof:placetype":"venue"
},
  "geometry": {"coordinates":[-117.60359099999999,33.880871],"type":"Point"}
}