{
  "type": "Feature",
  "properties": {
    "iso:country":"US",
    "sg:address":"1505 W Walnut Pkwy",
    "sg:city":"Compton",
    "sg:classifiers":[
        {
            "category":"Freight",
            "type":"Transportation"
        }
    ],
    "sg:phone":"+1 310 631 1810",
    "sg:postcode":"90220",
    "sg:province":"CA",
    "sg:website":"www.atlant.com",
    "wof:name":"Atlant USA Inc",
    "wof:placetype":"venue"
},
  "geometry": {"coordinates":[-118.24688500000001,33.877261],"type":"Point"}
}