{
  "type": "Feature",
  "properties": {
    "addr:full":"369 S Mountain Ave Upland CA 91786",
    "addr:housenumber":"369",
    "addr:postcode":"91786",
    "addr:street":"S Mountain Ave",
    "iso:country":"US",
    "sg:address":"369 S Mountain Ave",
    "sg:city":"Upland",
    "sg:classifiers":[
        {
            "category":"Food & Beverages",
            "subcategory":"Bakery",
            "type":"Retail Goods"
        }
    ],
    "sg:phone":"+1 909 982 3988",
    "sg:postcode":"91786",
    "sg:province":"CA",
    "sg:tags":[
        "doughnut"
    ],
    "wof:name":"Dara Donuts Ice Cream",
    "wof:placetype":"venue"
},
  "geometry": {"coordinates":[-117.670214,34.091867],"type":"Point"}
}