{
  "type": "Feature",
  "properties": {
    "iso:country":"US",
    "sg:address":"390 N Palm Canyon Dr",
    "sg:city":"Palm Springs",
    "sg:classifiers":[
        {
            "category":"Home & Garden",
            "subcategory":"Home Furnishings",
            "type":"Retail Goods"
        },
        {
            "category":"Food & Beverages",
            "subcategory":"Liquor & Beverages",
            "type":"Retail Goods"
        }
    ],
    "sg:phone":"+1 760 325 9930",
    "sg:postcode":"92262",
    "sg:province":"CA",
    "sg:tags":[
        "decor",
        "wine",
        "beer",
        "spirit"
    ],
    "sg:website":"www.wildforthevine.com",
    "wof:name":"Wild for the Vine",
    "wof:placetype":"venue"
},
  "geometry": {"coordinates":[-116.54684399999999,33.828365],"type":"Point"}
}