{
  "type": "Feature",
  "properties": {
    "iso:country":"US",
    "sg:address":"196 E 3rd St",
    "sg:city":"Pomona",
    "sg:classifiers":[
        {
            "category":"Utilities",
            "subcategory":"Natural Gas",
            "type":"Services"
        }
    ],
    "sg:phone":"+1 800 535 3339",
    "sg:postcode":"91766",
    "sg:province":"CA",
    "wof:name":"Southern California Gas Co",
    "wof:placetype":"venue"
},
  "geometry": {"coordinates":[-117.749905,34.056857],"type":"Point"}
}