{
  "type": "Feature",
  "properties": {
    "iso:country":"US",
    "sg:address":"1039 H St",
    "sg:city":"Eureka",
    "sg:classifiers":[
        {
            "category":"Organizations",
            "subcategory":"Religious Organization",
            "type":"Services"
        }
    ],
    "sg:phone":"+1 707 442 1122",
    "sg:postcode":"95501",
    "sg:province":"CA",
    "sg:tags":[
        "church"
    ],
    "wof:name":"Christian Science Church",
    "wof:placetype":"venue"
},
  "geometry": {"coordinates":[-124.162669,40.797835],"type":"Point"}
}