{
  "type": "Feature",
  "properties": {
    "addr:full":"615 Templeton Ct Sunnyvale CA 94087",
    "addr:housenumber":"615",
    "addr:postcode":"94087",
    "addr:street":"Templeton Ct",
    "iso:country":"US",
    "sg:address":"615 Templeton Ct",
    "sg:city":"Sunnyvale",
    "sg:classifiers":[
        {
            "category":"Professional",
            "subcategory":"Computer Services",
            "type":"Services"
        }
    ],
    "sg:phone":"+1 408 737 7092",
    "sg:postcode":"94087",
    "sg:province":"CA",
    "sg:tags":[
        "cd-rom"
    ],
    "sg:website":"http://www.inliteresearch.com",
    "wof:name":"Inlite Research Inc",
    "wof:placetype":"venue"
},
  "geometry": {"coordinates":[-122.037277,37.357559],"type":"Point"}
}