{
  "type": "Feature",
  "properties": {
    "addr:full":"556 N State College Blvd Fullerton CA 92831",
    "addr:housenumber":"556",
    "addr:postcode":"92831",
    "addr:street":"N State College Blvd",
    "iso:country":"US",
    "sg:address":"556 N State College Blvd",
    "sg:city":"Fullerton",
    "sg:classifiers":[
        {
            "category":"Manufacturing",
            "subcategory":"Aerospace",
            "type":"Manufacturing & Wholesale Goods"
        }
    ],
    "sg:phone":"+1 714 526 1919",
    "sg:postcode":"92831",
    "sg:province":"CA",
    "sg:tags":[
        "aircraft",
        "mfg"
    ],
    "wof:name":"Horizon Instruments Inc",
    "wof:placetype":"venue"
},
  "geometry": {"coordinates":[-117.889526,33.875436],"type":"Point"}
}