{
  "type": "Feature",
  "properties": {
    "iso:country":"US",
    "sg:address":"32247 Dunlap Blvd",
    "sg:city":"Yucaipa",
    "sg:classifiers":[
        {
            "category":"Retail",
            "subcategory":"Auto Repair",
            "type":"Services"
        }
    ],
    "sg:phone":"+1 909 795 6699",
    "sg:postcode":"92399",
    "sg:province":"CA",
    "sg:tags":[
        "body",
        "shop"
    ],
    "wof:name":"Ben Clymer's the Bodyshop",
    "wof:placetype":"venue"
},
  "geometry": {"coordinates":[-117.100998,34.0215],"type":"Point"}
}