{
  "type": "Feature",
  "properties": {
    "iso:country":"US",
    "sg:address":"1850 E Bayshore Rd",
    "sg:city":"Palo Alto",
    "sg:classifiers":[
        {
            "category":"Professional",
            "type":"Services"
        }
    ],
    "sg:phone":"+1 650 838 9015",
    "sg:postcode":"94303",
    "sg:province":"CA",
    "wof:name":"Tevita Takapautolo",
    "wof:placetype":"venue"
},
  "geometry": {"coordinates":[-122.133125,37.456358],"type":"Point"}
}