{
  "type": "Feature",
  "properties": {
    "iso:country":"US",
    "sg:address":"405 W Rosamond Blvd",
    "sg:city":"Edwards Afb",
    "sg:classifiers":[
        {
            "category":"Museum",
            "type":"Entertainment"
        }
    ],
    "sg:phone":"+1 661 258 1658",
    "sg:postcode":"93560",
    "sg:province":"CA",
    "wof:name":"Flight Test Historical Fndtn",
    "wof:placetype":"venue"
},
  "geometry": {"coordinates":[-118.149851,34.864577],"type":"Point"}
}