{
  "type": "Feature",
  "properties": {
    "iso:country":"US",
    "sg:address":"The Salvation Army Thrift Store 6120 Lankershim Blvd",
    "sg:city":"Los Angeles",
    "sg:classifiers":[
        {
            "category":"Shopping",
            "subcategory":"Thrift Store",
            "type":"Retail Goods"
        }
    ],
    "sg:phone":"+1 818 985 8105",
    "sg:postcode":"91606",
    "sg:province":"CA",
    "wof:name":"Sally's Boutique",
    "wof:placetype":"venue"
},
  "geometry": {"coordinates":[-118.38469600000001,34.181572],"type":"Point"}
}