{
  "type": "Feature",
  "properties": {
    "iso:country":"US",
    "sg:address":"71650 Sahara Rd",
    "sg:city":"Rancho Mirage",
    "sg:classifiers":[
        {
            "category":"Health Services",
            "subcategory":"Health Practitioner",
            "type":"Services"
        }
    ],
    "sg:phone":"+1 760 568 1799",
    "sg:postcode":"92270",
    "sg:province":"CA",
    "sg:tags":[
        "psychotherapist"
    ],
    "wof:name":"Desert Springs Mental Health",
    "wof:placetype":"venue"
},
  "geometry": {"coordinates":[-116.41421,33.740929],"type":"Point"}
}