{
  "type": "Feature",
  "properties": {
    "addr:full":"5790 Lindero Canyon Rd Westlake Village CA 91362",
    "addr:housenumber":"5790",
    "addr:postcode":"91362",
    "addr:street":"Lindero Canyon Rd",
    "iso:country":"US",
    "sg:address":"5790 Lindero Canyon Rd",
    "sg:city":"Westlake Village",
    "sg:classifiers":[
        {
            "category":"Restaurant",
            "type":"Food & Drink"
        }
    ],
    "sg:phone":"+1 818 707 9064",
    "sg:postcode":"91362",
    "sg:province":"CA",
    "wof:name":"Genki Sushi",
    "wof:placetype":"venue"
},
  "geometry": {"coordinates":[-118.796637,34.153968],"type":"Point"}
}