{
  "type": "Feature",
  "properties": {
    "iso:country":"US",
    "sg:address":"San Francisco Bay",
    "sg:city":"San Francisco",
    "sg:classifiers":[
        {
            "category":"Recreation",
            "subcategory":"Boat Charter",
            "type":"Entertainment"
        }
    ],
    "sg:postcode":"94199",
    "sg:province":"CA",
    "sg:tags":[
        "boating"
    ],
    "sg:website":"www.isharescup.com",
    "wof:name":"iShares Extreme 40 Catamaran",
    "wof:placetype":"venue"
},
  "geometry": {"coordinates":[-122.409362,37.808582],"type":"Point"}
}