{
  "type": "Feature",
  "properties": {
    "addr:full":"15 Williamsburg Ln #C Chico CA 95926",
    "addr:housenumber":"15",
    "addr:postcode":"95926",
    "addr:street":"Williamsburg Ln # C",
    "iso:country":"US",
    "sg:address":"15 Williamsburg Ln #C",
    "sg:city":"Chico",
    "sg:classifiers":[
        {
            "category":"Shopping",
            "subcategory":"Beauty & Cosmetics",
            "type":"Retail Goods"
        },
        {
            "category":"Personal",
            "subcategory":"Day Spa",
            "type":"Services"
        },
        {
            "category":"Personal",
            "subcategory":"Nail Salon",
            "type":"Services"
        },
        {
            "category":"Personal",
            "subcategory":"Skin Care",
            "type":"Services"
        },
        {
            "category":"Personal",
            "subcategory":"Beauty Salon",
            "type":"Services"
        },
        {
            "category":"Personal",
            "subcategory":"Massage",
            "type":"Services"
        }
    ],
    "sg:phone":"+1 530 342 0434",
    "sg:postcode":"95926",
    "sg:province":"CA",
    "sg:tags":[
        "permanent",
        "therapist",
        "make-up"
    ],
    "sg:website":"http://www.chicodayspa.com",
    "wof:name":"Bella Day Spa Salon & Boutique",
    "wof:placetype":"venue"
},
  "geometry": {"coordinates":[-121.85476199999999,39.752887],"type":"Point"}
}