{
  "type": "Feature",
  "properties": {
    "iso:country":"US",
    "sg:address":"5597 Stockton Boulevard",
    "sg:city":"Sacramento",
    "sg:classifiers":[
        {
            "category":"Autos & Motor Vehicles",
            "subcategory":"Fuel & Gas Station",
            "type":"Retail Goods"
        }
    ],
    "sg:phone":"+1 916 452 8319",
    "sg:postcode":"95820",
    "sg:province":"CA",
    "wof:name":"Valero Fruitridge",
    "wof:placetype":"venue"
},
  "geometry": {"coordinates":[-121.44252400000001,38.525162],"type":"Point"}
}