{
  "type": "Feature",
  "properties": {
    "iso:country":"US",
    "sg:address":"1944 E Gladwick St",
    "sg:city":"Bell",
    "sg:classifiers":[
        {
            "category":"Manufacturing",
            "subcategory":"Furniture",
            "type":"Manufacturing & Wholesale Goods"
        }
    ],
    "sg:phone":"+1 310 763 7663",
    "sg:postcode":"90220",
    "sg:province":"CA",
    "sg:tags":[
        "upholstered",
        "household",
        "mfg"
    ],
    "wof:name":"J E Furniture Manufacturer",
    "wof:placetype":"venue"
},
  "geometry": {"coordinates":[-118.232277,33.853262],"type":"Point"}
}