{
  "type": "Feature",
  "properties": {
    "addr:full":"123 Phillips Ln Redwood City CA 94062",
    "addr:housenumber":"123",
    "addr:postcode":"94062",
    "addr:street":"Phillips Ln",
    "iso:country":"US",
    "sg:address":"123 Phillips Ln",
    "sg:city":"Redwood City",
    "sg:classifiers":[
        {
            "category":"Travel",
            "subcategory":"Travel Agent",
            "type":"Entertainment"
        }
    ],
    "sg:phone":"+1 650 851 3875",
    "sg:postcode":"94062",
    "sg:province":"CA",
    "sg:tags":[
        "operator",
        "tour"
    ],
    "wof:name":"Tailored Travel & Tours",
    "wof:placetype":"venue"
},
  "geometry": {"coordinates":[-122.250496,37.401714],"type":"Point"}
}