{
  "type": "Feature",
  "properties": {
    "addr:full":"14105 Prairie Ave Hawthorne CA 90250",
    "addr:housenumber":"14105",
    "addr:postcode":"90250",
    "addr:street":"Prairie Ave",
    "iso:country":"US",
    "sg:address":"14105 Prairie Ave",
    "sg:city":"Hawthorne",
    "sg:classifiers":[
        {
            "category":"Home & Garden",
            "subcategory":"Furniture",
            "type":"Retail Goods"
        }
    ],
    "sg:phone":"+1 310 644 7743",
    "sg:postcode":"90250",
    "sg:province":"CA",
    "sg:tags":[
        "store"
    ],
    "wof:name":"Furniture City",
    "wof:placetype":"venue"
},
  "geometry": {"coordinates":[-118.34391100000001,33.903794],"type":"Point"}
}