{
  "type": "Feature",
  "properties": {
    "iso:country":"US",
    "sg:address":"10413 Park Ave",
    "sg:city":"Santee",
    "sg:classifiers":[
        {
            "category":"Wholesale",
            "subcategory":"Auto Parts",
            "type":"Manufacturing & Wholesale Goods"
        }
    ],
    "sg:phone":"+1 619 448 5210",
    "sg:postcode":"92071",
    "sg:province":"CA",
    "sg:tags":[
        "automotive",
        "toy",
        "supply"
    ],
    "wof:name":"Pacific International",
    "wof:placetype":"venue"
},
  "geometry": {"coordinates":[-116.970682,32.83949],"type":"Point"}
}