{
  "type": "Feature",
  "properties": {
    "addr:full":"8001 Irvine Center Dr Irvine CA 92618",
    "addr:housenumber":"8001",
    "addr:postcode":"92618",
    "addr:street":"Irvine Center Dr",
    "iso:country":"US",
    "sg:address":"8001 Irvine Center Dr",
    "sg:city":"Irvine",
    "sg:classifiers":[
        {
            "category":"Real Estate",
            "subcategory":"Real Estate Agent",
            "type":"Services"
        }
    ],
    "sg:phone":"+1 949 754 3101",
    "sg:postcode":"92618",
    "sg:province":"CA",
    "wof:name":"Vp Executive Services",
    "wof:placetype":"venue"
},
  "geometry": {"coordinates":[-117.753137,33.661938],"type":"Point"}
}