{
  "type": "Feature",
  "properties": {
    "addr:full":"23751 Eichler St Hayward CA 94545",
    "addr:housenumber":"23751",
    "addr:postcode":"94545",
    "addr:street":"Eichler St",
    "iso:country":"US",
    "sg:address":"23751 Eichler St",
    "sg:city":"Hayward",
    "sg:classifiers":[
        {
            "category":"Freight",
            "type":"Transportation"
        }
    ],
    "sg:phone":"+1 510 780 9333",
    "sg:postcode":"94545",
    "sg:province":"CA",
    "sg:tags":[
        "delivery"
    ],
    "wof:name":"3 P Delivery",
    "wof:placetype":"venue"
},
  "geometry": {"coordinates":[-122.126884,37.641438],"type":"Point"}
}