{
  "type": "Feature",
  "properties": {
    "addr:full":"822 S Main St Santa Ana CA 92701",
    "addr:housenumber":"822",
    "addr:postcode":"92701",
    "addr:street":"S Main St",
    "iso:country":"US",
    "sg:address":"822 S Main St",
    "sg:city":"Santa Ana",
    "sg:classifiers":[
        {
            "category":"Airline",
            "type":"Transportation"
        }
    ],
    "sg:phone":"+1 323 589 2038",
    "sg:postcode":"92701",
    "sg:province":"CA",
    "sg:tags":[
        "cargo",
        "air"
    ],
    "wof:name":"Multi Cargo",
    "wof:placetype":"venue"
},
  "geometry": {"coordinates":[-117.867791,33.73736],"type":"Point"}
}