{
  "type": "Feature",
  "properties": {
    "addr:full":"2095 Foothill Blvd La Verne CA 91750",
    "addr:housenumber":"2095",
    "addr:postcode":"91750",
    "addr:street":"Foothill Blvd",
    "iso:country":"US",
    "sg:address":"2095 Foothill Blvd",
    "sg:city":"La Verne",
    "sg:classifiers":[
        {
            "category":"Restaurant",
            "type":"Food & Drink"
        }
    ],
    "sg:phone":"+1 909 596 4002",
    "sg:postcode":"91750",
    "sg:province":"CA",
    "wof:name":"Bagelry",
    "wof:placetype":"venue"
},
  "geometry": {"coordinates":[-117.76548099999999,34.113501],"type":"Point"}
}