{
  "type": "Feature",
  "properties": {
    "iso:country":"US",
    "sg:address":"27051 McBean Pkwy",
    "sg:city":"Santa Clarita",
    "sg:classifiers":[
        {
            "category":"Home & Garden",
            "subcategory":"Carpets & Floor Coverings",
            "type":"Retail Goods"
        }
    ],
    "sg:phone":"+1 661 247 0133",
    "sg:postcode":"91355",
    "sg:province":"CA",
    "sg:tags":[
        "installation"
    ],
    "wof:name":"Santa Clarita Carpet Cleaning",
    "wof:placetype":"venue"
},
  "geometry": {"coordinates":[-118.563923,34.421608],"type":"Point"}
}