{
  "type": "Feature",
  "properties": {
    "addr:full":"1395 W Arrow Hwy San Dimas CA 91773",
    "addr:housenumber":"1395",
    "addr:postcode":"91773",
    "addr:street":"W Arrow Hwy",
    "iso:country":"US",
    "sg:address":"1395 W Arrow Hwy",
    "sg:city":"San Dimas",
    "sg:classifiers":[
        {
            "category":"Personal",
            "subcategory":"Beauty Salon",
            "type":"Services"
        }
    ],
    "sg:phone":"+1 909 599 6388",
    "sg:postcode":"91773",
    "sg:province":"CA",
    "sg:tags":[
        "manicuring"
    ],
    "wof:name":"San Dimas Nails",
    "wof:placetype":"venue"
},
  "geometry": {"coordinates":[-117.83744299999999,34.106684],"type":"Point"}
}