{
  "type": "Feature",
  "properties": {
    "addr:full":"2323 4th St Berkeley CA 94710",
    "addr:housenumber":"2323",
    "addr:postcode":"94710",
    "addr:street":"4Th St",
    "iso:country":"US",
    "sg:address":"2323 4th St",
    "sg:city":"Berkeley",
    "sg:classifiers":[
        {
            "category":"Winery",
            "type":"Food & Drink"
        }
    ],
    "sg:phone":"+1 510 981 8098",
    "sg:postcode":"94710",
    "sg:province":"CA",
    "wof:name":"A Donkey & Goat Winery",
    "wof:placetype":"venue"
},
  "geometry": {"coordinates":[-122.29813900000001,37.862721],"type":"Point"}
}