{
  "type": "Feature",
  "properties": {
    "addr:full":"1754 Westwood Blvd. Los Angeles CA 90024",
    "addr:housenumber":"1754",
    "addr:postcode":"90024",
    "addr:street":"Westwood Blvd.",
    "iso:country":"US",
    "sg:address":"1754 Westwood Blvd.",
    "sg:city":"Los Angeles",
    "sg:classifiers":[
        {
            "category":"Personal",
            "subcategory":"Beauty Salon",
            "type":"Services"
        }
    ],
    "sg:phone":"+1 310 614 5797",
    "sg:postcode":"90024",
    "sg:province":"CA",
    "sg:tags":[
        "hair"
    ],
    "sg:website":"www.elanhair.net",
    "wof:name":"Elan Hair Salon",
    "wof:placetype":"venue"
},
  "geometry": {"coordinates":[-118.437757,34.050726],"type":"Point"}
}