{
  "type": "Feature",
  "properties": {
    "iso:country":"US",
    "sg:address":"1301 Westwood Blvd",
    "sg:city":"Los Angeles",
    "sg:classifiers":[
        {
            "category":"Restaurant",
            "type":"Food & Drink"
        }
    ],
    "sg:menulink":"http://www.allmenus.com/ca/los-angeles/64716-papa-johns-pizza/menu/",
    "sg:phone":"+1 310 478 2999",
    "sg:postcode":"90024",
    "sg:province":"CA",
    "sg:tags":[
        "american",
        "pizza"
    ],
    "wof:name":"Papa John's Pizza",
    "wof:placetype":"venue"
},
  "geometry": {"coordinates":[-118.443005,34.056752],"type":"Point"}
}