{
  "type": "Feature",
  "properties": {
    "iso:country":"US",
    "sg:address":"8022 River Pl",
    "sg:city":"Carmel",
    "sg:classifiers":[
        {
            "category":"Recreation",
            "type":"Entertainment"
        }
    ],
    "sg:phone":"+1 831 624 2526",
    "sg:postcode":"93923",
    "sg:province":"CA",
    "sg:tags":[
        "instruction",
        "golf"
    ],
    "wof:name":"Ben J Doyle Golf",
    "wof:placetype":"venue"
},
  "geometry": {"coordinates":[-121.860327,36.532121],"type":"Point"}
}