{
  "type": "Feature",
  "properties": {
    "iso:country":"US",
    "sg:address":"200 S Brand Blvd",
    "sg:city":"Glendale",
    "sg:classifiers":[
        {
            "category":"Wholesale",
            "subcategory":"Home Furnishings",
            "type":"Manufacturing & Wholesale Goods"
        }
    ],
    "sg:phone":"+1 818 247 3005",
    "sg:postcode":"91204",
    "sg:province":"CA",
    "sg:tags":[
        "lamp",
        "shade"
    ],
    "sg:website":"http://LampsPlus.com",
    "wof:name":"Lamps Plus Glendale",
    "wof:placetype":"venue"
},
  "geometry": {"coordinates":[-118.25495100000001,34.144421],"type":"Point"}
}