{
  "type": "Feature",
  "properties": {
    "addr:full":"507 3rd St San Jn Bautista CA 95045",
    "addr:housenumber":"507",
    "addr:postcode":"95045",
    "addr:street":"3Rd St",
    "iso:country":"US",
    "sg:address":"507 3rd St",
    "sg:city":"San Jn Bautista",
    "sg:classifiers":[
        {
            "category":"Shopping",
            "subcategory":"Used Merchandise",
            "type":"Retail Goods"
        }
    ],
    "sg:phone":"+1 831 623 8882",
    "sg:postcode":"95045",
    "sg:province":"CA",
    "sg:tags":[
        "antique"
    ],
    "wof:name":"Mr B's Z-Place II",
    "wof:placetype":"venue"
},
  "geometry": {"coordinates":[-121.53911600000001,36.845984],"type":"Point"}
}