{
  "type": "Feature",
  "properties": {
    "iso:country":"US",
    "sg:address":"507 3rd St",
    "sg:city":"San Jn Bautista",
    "sg:classifiers":[
        {
            "category":"Shopping",
            "subcategory":"Used Merchandise",
            "type":"Retail Goods"
        }
    ],
    "sg:phone":"+1 831 623 8882",
    "sg:postcode":"95045",
    "sg:province":"CA",
    "sg:tags":[
        "antique"
    ],
    "wof:name":"Mr B's Z-Place II",
    "wof:placetype":"venue"
},
  "geometry": {"coordinates":[-121.539116,36.845984],"type":"Point"}
}