{
  "type": "Feature",
  "properties": {
    "iso:country":"US",
    "sg:address":"1130 30th St",
    "sg:city":"San Diego",
    "sg:classifiers":[
        {
            "category":"Retail",
            "subcategory":"Auto Repair",
            "type":"Services"
        }
    ],
    "sg:phone":"+1 619 423 3315",
    "sg:postcode":"92154",
    "sg:province":"CA",
    "sg:tags":[
        "automobile",
        "smog"
    ],
    "wof:name":"E & M Smog",
    "wof:placetype":"venue"
},
  "geometry": {"coordinates":[-117.069024,32.575439],"type":"Point"}
}