{
  "type": "Feature",
  "properties": {
    "iso:country":"US",
    "sg:address":"27000 Crown Valley Pkwy Ste 306B",
    "sg:city":"Mission Viejo",
    "sg:classifiers":[
        {
            "category":"Shopping",
            "subcategory":"Clothing, Apparel, & Fashions",
            "type":"Retail Goods"
        }
    ],
    "sg:phone":"+1 949 347 0167",
    "sg:postcode":"92691",
    "sg:province":"CA",
    "sg:tags":[
        "accessory",
        "clothing",
        "women's"
    ],
    "wof:name":"Destination Maternity",
    "wof:placetype":"venue"
},
  "geometry": {"coordinates":[-117.669493,33.561573],"type":"Point"}
}