{
  "type": "Feature",
  "properties": {
    "iso:country":"US",
    "sg:address":"1100 Hartnell Ave",
    "sg:city":"Redding",
    "sg:classifiers":[
        {
            "category":"Food & Beverages",
            "subcategory":"Specialty",
            "type":"Retail Goods"
        }
    ],
    "sg:phone":"+1 530 221 8081",
    "sg:postcode":"96002",
    "sg:province":"CA",
    "sg:tags":[
        "bars",
        "espresso"
    ],
    "wof:name":"Judy Espresso",
    "wof:placetype":"venue"
},
  "geometry": {"coordinates":[-122.35302900000001,40.563841],"type":"Point"}
}