{
  "type": "Feature",
  "properties": {
    "addr:full":"1516 6th Ave San Francisco CA 94122",
    "addr:housenumber":"1516",
    "addr:postcode":"94122",
    "addr:street":"6Th Ave",
    "iso:country":"US",
    "sg:address":"1516 6th Ave",
    "sg:city":"San Francisco",
    "sg:classifiers":[
        {
            "category":"Professional",
            "type":"Services"
        }
    ],
    "sg:phone":"+1 415 778 2838",
    "sg:postcode":"94122",
    "sg:province":"CA",
    "wof:name":"Harderware",
    "wof:placetype":"venue"
},
  "geometry": {"coordinates":[-122.46272399999999,37.759857],"type":"Point"}
}