{
  "type": "Feature",
  "properties": {
    "iso:country":"US",
    "sg:address":"71874 Sahara Rd",
    "sg:city":"Rancho Mirage",
    "sg:classifiers":[
        {
            "category":"Health Services",
            "subcategory":"Doctor",
            "type":"Services"
        }
    ],
    "sg:phone":"+1 760 568 2211",
    "sg:postcode":"92270",
    "sg:province":"CA",
    "sg:tags":[
        "surgeon",
        "cosmetic"
    ],
    "wof:name":"Ordon Andrew P MD Facs",
    "wof:placetype":"venue"
},
  "geometry": {"coordinates":[-116.410004,33.735401],"type":"Point"}
}