{
  "type": "Feature",
  "properties": {
    "addr:full":"1888 Solano Ave Berkeley CA 94707",
    "addr:housenumber":"1888",
    "addr:postcode":"94707",
    "addr:street":"Solano Ave",
    "iso:country":"US",
    "sg:address":"1888 Solano Ave",
    "sg:city":"Berkeley",
    "sg:classifiers":[
        {
            "category":"Restaurant",
            "type":"Food & Drink"
        }
    ],
    "sg:menulink":"http://www.allmenus.com/ca/berkeley/57553-ajanta/menu/",
    "sg:phone":"+1 510 526 4373",
    "sg:postcode":"94707",
    "sg:province":"CA",
    "sg:tags":[
        "indian",
        "asian"
    ],
    "wof:name":"Ajanta",
    "wof:placetype":"venue"
},
  "geometry": {"coordinates":[-122.277378,37.891305],"type":"Point"}
}