{
  "type": "Feature",
  "properties": {
    "iso:country":"US",
    "sg:address":"436 N Bedford Dr Ste 306",
    "sg:city":"Beverly Hills",
    "sg:classifiers":[
        {
            "category":"Health Services",
            "subcategory":"Doctor",
            "type":"Services"
        }
    ],
    "sg:phone":"+1 310 274 4401",
    "sg:postcode":"90210",
    "sg:province":"CA",
    "sg:tags":[
        "dermatologist"
    ],
    "wof:name":"Rapaport Marvin MD A Professional Corp",
    "wof:placetype":"venue"
},
  "geometry": {"coordinates":[-118.405998,34.0686],"type":"Point"}
}