{
  "type": "Feature",
  "properties": {
    "addr:full":"6943 Chisholm Ave Van Nuys CA 91406",
    "addr:housenumber":"6943",
    "addr:postcode":"91406",
    "addr:street":"Chisholm Ave",
    "iso:country":"US",
    "sg:address":"6943 Chisholm Ave",
    "sg:city":"Van Nuys",
    "sg:classifiers":[
        {
            "category":"Wholesale",
            "subcategory":"Medical Equipment & Supplies",
            "type":"Manufacturing & Wholesale Goods"
        }
    ],
    "sg:phone":"+1 949 636 1244",
    "sg:postcode":"91406",
    "sg:province":"CA",
    "wof:name":"Intotel Mechanical Equipment",
    "wof:placetype":"venue"
},
  "geometry": {"coordinates":[-118.471726,34.194939],"type":"Point"}
}