{
  "type": "Feature",
  "properties": {
    "addr:full":"1742 S Clementine St Anaheim CA 92802",
    "addr:housenumber":"1742",
    "addr:postcode":"92802",
    "addr:street":"S Clementine St",
    "iso:country":"US",
    "sg:address":"1742 S Clementine St",
    "sg:city":"Anaheim",
    "sg:classifiers":[
        {
            "category":"Travel",
            "subcategory":"Hotels & Motels",
            "type":"Entertainment"
        },
        {
            "category":"Real Estate",
            "subcategory":"Real Estate Operator",
            "type":"Services"
        }
    ],
    "sg:phone":"+1 714 502 9988",
    "sg:postcode":"92802",
    "sg:province":"CA",
    "sg:tags":[
        "apartment"
    ],
    "wof:name":"Extended Stay America",
    "wof:placetype":"venue"
},
  "geometry": {"coordinates":[-117.910004,33.8046],"type":"Point"}
}