{
  "type": "Feature",
  "properties": {
    "iso:country":"US",
    "sg:address":"2652 Chinook Way",
    "sg:city":"Camp Connell",
    "sg:classifiers":[
        {
            "category":"Building & Trades",
            "subcategory":"Electrical",
            "type":"Services"
        }
    ],
    "sg:phone":"+1 209 795 1859",
    "sg:postcode":"95223",
    "sg:province":"CA",
    "sg:tags":[
        "electric",
        "contractor"
    ],
    "wof:name":"Electric Express",
    "wof:placetype":"venue"
},
  "geometry": {"coordinates":[-120.277074,38.293897],"type":"Point"}
}