{
  "type": "Feature",
  "properties": {
    "iso:country":"US",
    "sg:address":"4411 Mercury St Ste 106",
    "sg:city":"San Diego",
    "sg:classifiers":[
        {
            "category":"Shopping",
            "subcategory":"Jewelry",
            "type":"Retail Goods"
        }
    ],
    "sg:phone":"+1 858 565 1112",
    "sg:postcode":"92111",
    "sg:province":"CA",
    "sg:website":"www.diamondgallerysd.com",
    "wof:name":"Diamond Gallery SD",
    "wof:placetype":"venue"
},
  "geometry": {"coordinates":[-117.14828799999999,32.820561],"type":"Point"}
}