{
  "type": "Feature",
  "properties": {
    "addr:full":"3031 Tisch Way San Jose CA 95128",
    "addr:postcode":"3031;95128",
    "addr:street":"Tisch Way",
    "iso:country":"US",
    "sg:address":"3031 Tisch Way",
    "sg:city":"San Jose",
    "sg:classifiers":[
        {
            "category":"Real Estate",
            "subcategory":"Real Estate Agent",
            "type":"Services"
        }
    ],
    "sg:phone":"+1 408 377 6700",
    "sg:postcode":"95128",
    "sg:province":"CA",
    "sg:tags":[
        "exchanger"
    ],
    "sg:website":"www.xchangesolutions.net",
    "wof:name":"Xchange Solutions",
    "wof:placetype":"venue"
},
  "geometry": {"coordinates":[-121.949229,37.317164],"type":"Point"}
}