{
  "type": "Feature",
  "properties": {
    "addr:full":"929 Koster St Eureka CA 95501",
    "addr:housenumber":"929",
    "addr:postcode":"95501",
    "addr:street":"Koster St",
    "iso:country":"US",
    "sg:address":"929 Koster St",
    "sg:city":"Eureka",
    "sg:classifiers":[
        {
            "category":"Government",
            "subcategory":"Office",
            "type":"Public Place"
        }
    ],
    "sg:phone":"+1 707 445 6103",
    "sg:postcode":"95501",
    "sg:province":"CA",
    "sg:tags":[
        "county",
        "resource"
    ],
    "wof:name":"Humbold County Social Svc Dept",
    "wof:placetype":"venue"
},
  "geometry": {"coordinates":[-124.179059,40.798],"type":"Point"}
}