{
  "type": "Feature",
  "properties": {
    "addr:full":"12709 Poway Rd Poway CA 92064",
    "addr:housenumber":"12709",
    "addr:postcode":"ca 92064",
    "addr:street":"Poway Rd",
    "iso:country":"US",
    "sg:address":"12709 Poway Rd",
    "sg:city":"Poway",
    "sg:classifiers":[
        {
            "category":"Real Estate",
            "subcategory":"Real Estate Agent",
            "type":"Services"
        }
    ],
    "sg:phone":"+1 858 748 0098",
    "sg:postcode":"92064",
    "sg:province":"CA",
    "wof:name":"Pomerado Real Estate Services",
    "wof:placetype":"venue"
},
  "geometry": {"coordinates":[-117.057582,32.953581],"type":"Point"}
}