{
  "type": "Feature",
  "properties": {
    "addr:full":"6611 Coyle Ave Carmichael CA 95608",
    "addr:housenumber":"6611",
    "addr:postcode":"95608",
    "addr:street":"Coyle Ave",
    "iso:country":"US",
    "sg:address":"6611 Coyle Ave",
    "sg:city":"Carmichael",
    "sg:classifiers":[
        {
            "category":"Health Services",
            "subcategory":"Clinic",
            "type":"Services"
        }
    ],
    "sg:phone":"+1 916 961 6800",
    "sg:postcode":"95608",
    "sg:province":"CA",
    "sg:website":"www.ncctc.com",
    "wof:name":"Northern California Cmprssn",
    "wof:placetype":"venue"
},
  "geometry": {"coordinates":[-121.308802,38.668088],"type":"Point"}
}