{
  "type": "Feature",
  "properties": {
    "addr:full":"18556 Ventura Blvd Tarzana CA 91356",
    "addr:housenumber":"18556",
    "addr:postcode":"91356",
    "addr:street":"Ventura Blvd",
    "iso:country":"US",
    "sg:address":"18556 Ventura Blvd",
    "sg:city":"Tarzana",
    "sg:classifiers":[
        {
            "category":"Retail",
            "subcategory":"Auto Repair",
            "type":"Services"
        }
    ],
    "sg:phone":"+1 818 342 0777",
    "sg:postcode":"91356",
    "sg:province":"CA",
    "sg:tags":[
        "brake"
    ],
    "sg:website":"www.brakemasters.com",
    "wof:name":"Brake Masters",
    "wof:placetype":"venue"
},
  "geometry": {"coordinates":[-118.538511,34.169692],"type":"Point"}
}