{
  "type": "Feature",
  "properties": {
    "iso:country":"US",
    "sg:address":"17415 Catalpa St Ste 7",
    "sg:city":"Hesperia",
    "sg:classifiers":[
        {
            "category":"Professional",
            "subcategory":"Lawyer & Legal Services",
            "type":"Services"
        }
    ],
    "sg:phone":"+1 760 244 0002",
    "sg:postcode":"92345",
    "sg:province":"CA",
    "sg:tags":[
        "paralegal"
    ],
    "wof:name":"American",
    "wof:placetype":"venue"
},
  "geometry": {"coordinates":[-117.283446,34.45984],"type":"Point"}
}