{
  "type": "Feature",
  "properties": {
    "addr:full":"1136 Mountain Quail Cir San Jose CA 95120",
    "addr:housenumber":"1136",
    "addr:postcode":"95120",
    "addr:street":"Mountain Quail Cir",
    "iso:country":"US",
    "sg:address":"1136 Mountain Quail Cir",
    "sg:city":"San Jose",
    "sg:classifiers":[
        {
            "category":"Professional",
            "type":"Services"
        }
    ],
    "sg:phone":"+1 408 997 1412",
    "sg:postcode":"95120",
    "sg:province":"CA",
    "wof:name":"Rj Hancock Inc",
    "wof:placetype":"venue"
},
  "geometry": {"coordinates":[-121.849186,37.203584],"type":"Point"}
}