{
  "type": "Feature",
  "properties": {
    "addr:full":"Old Navy 801 Market Street San Francisco CA 94103",
    "addr:housenumber":"801",
    "addr:postcode":"94103",
    "addr:street":"Market Street",
    "iso:country":"US",
    "sg:address":"Old Navy 801 Market Street",
    "sg:city":"San Francisco",
    "sg:classifiers":[
        {
            "category":"Restaurant",
            "type":"Food & Drink"
        }
    ],
    "sg:phone":"+1 415 344 0375",
    "sg:postcode":"94103",
    "sg:province":"CA",
    "wof:name":"Torpedo Joe's",
    "wof:placetype":"venue"
},
  "geometry": {"coordinates":[-122.30272600000001,37.789435],"type":"Point"}
}