{
  "type": "Feature",
  "properties": {
    "iso:country":"US",
    "sg:address":"4326 Crenshaw Blvd",
    "sg:city":"Los Angeles",
    "sg:classifiers":[
        {
            "category":"Restaurant",
            "type":"Food & Drink"
        }
    ],
    "sg:menulink":"http://www.allmenus.com/ca/los-angeles/241891-earles-grill/menu/",
    "sg:phone":"+1 323 299 2867",
    "sg:postcode":"90008",
    "sg:province":"CA",
    "sg:tags":[
        "american"
    ],
    "wof:name":"Earle's Grill",
    "wof:placetype":"venue"
},
  "geometry": {"coordinates":[-118.33303100000001,34.004524],"type":"Point"}
}