{
  "type": "Feature",
  "properties": {
    "iso:country":"US",
    "sg:address":"330 41st St",
    "sg:city":"Oakland",
    "sg:classifiers":[
        {
            "category":"Health Services",
            "subcategory":"Health Practitioner",
            "type":"Services"
        }
    ],
    "sg:phone":"+1 510 653 6490",
    "sg:postcode":"94609",
    "sg:province":"CA",
    "sg:tags":[
        "acupuncture"
    ],
    "wof:name":"Mary Stewart",
    "wof:placetype":"venue"
},
  "geometry": {"coordinates":[-122.257379,37.828838],"type":"Point"}
}