{
  "type": "Feature",
  "properties": {
    "addr:full":"1600 Rodgers Rd Hanford CA 93230",
    "addr:housenumber":"1600",
    "addr:postcode":"ca 93230",
    "addr:street":"Rodgers Rd",
    "iso:country":"US",
    "sg:address":"1600 Rodgers Rd",
    "sg:city":"Hanford",
    "sg:classifiers":[
        {
            "category":"Farming",
            "subcategory":"Farm & Veterinary Services",
            "type":"Manufacturing & Wholesale Goods"
        }
    ],
    "sg:phone":"+1 559 584 2244",
    "sg:postcode":"93230",
    "sg:province":"CA",
    "sg:tags":[
        "breeder",
        "vet",
        "livestock"
    ],
    "wof:name":"Tri County Breeding Service",
    "wof:placetype":"venue"
},
  "geometry": {"coordinates":[-119.659598,36.34261],"type":"Point"}
}