{
  "type": "Feature",
  "properties": {
    "iso:country":"US",
    "sg:address":"980 N Fair Oaks Ave",
    "sg:city":"Pasadena",
    "sg:classifiers":[
        {
            "category":"Organizations",
            "subcategory":"Religious Organization",
            "type":"Services"
        }
    ],
    "sg:phone":"+1 626 791 3459",
    "sg:postcode":"91103",
    "sg:province":"CA",
    "sg:tags":[
        "church"
    ],
    "wof:name":"Bartimaeus Ministries",
    "wof:placetype":"venue"
},
  "geometry": {"coordinates":[-118.150536,34.161514],"type":"Point"}
}