{
  "type": "Feature",
  "properties": {
    "addr:full":"9934 Artesia Blvd Bellflower CA 90706",
    "addr:housenumber":"9934",
    "addr:postcode":"90706",
    "addr:street":"Artesia Blvd",
    "iso:country":"US",
    "sg:address":"9934 Artesia Blvd",
    "sg:city":"Bellflower",
    "sg:classifiers":[
        {
            "category":"Autos & Motor Vehicles",
            "subcategory":"Automobile Sales",
            "type":"Retail Goods"
        }
    ],
    "sg:phone":"+1 562 867 5068",
    "sg:postcode":"90706",
    "sg:province":"CA",
    "sg:tags":[
        "automotive"
    ],
    "wof:name":"Straight Pipes & Fabrication",
    "wof:placetype":"venue"
},
  "geometry": {"coordinates":[-118.121889,33.874691],"type":"Point"}
}