{
  "type": "Feature",
  "properties": {
    "iso:country":"US",
    "sg:address":"12707 Rives Ave Ste F",
    "sg:city":"Downey",
    "sg:classifiers":[
        {
            "category":"Shopping",
            "subcategory":"Clothing, Apparel, & Fashions",
            "type":"Retail Goods"
        }
    ],
    "sg:phone":"+1 562 803 7959",
    "sg:postcode":"90242",
    "sg:province":"CA",
    "sg:tags":[
        "children's",
        "clothing"
    ],
    "wof:name":"Kinds Of California",
    "wof:placetype":"venue"
},
  "geometry": {"coordinates":[-118.157966,33.92445],"type":"Point"}
}