{
  "type": "Feature",
  "properties": {
    "iso:country":"US",
    "sg:address":"2005 Rockefeller Dr",
    "sg:city":"Ceres",
    "sg:classifiers":[
        {
            "category":"Wholesale",
            "subcategory":"Hardware",
            "type":"Manufacturing & Wholesale Goods"
        }
    ],
    "sg:phone":"+1 209 531 0446",
    "sg:postcode":"95307",
    "sg:province":"CA",
    "sg:tags":[
        "bar",
        "made",
        "fixture"
    ],
    "wof:name":"Jiggs Distributing",
    "wof:placetype":"venue"
},
  "geometry": {"coordinates":[-120.970459,37.599364],"type":"Point"}
}