{
  "type": "Feature",
  "properties": {
    "iso:country":"US",
    "sg:address":"5800 Freeport Blvd",
    "sg:city":"Sacramento",
    "sg:classifiers":[
        {
            "category":"Shopping",
            "subcategory":"Bicycles & Sporting Goods",
            "type":"Retail Goods"
        }
    ],
    "sg:phone":"+1 916 399 9798",
    "sg:postcode":"95822",
    "sg:province":"CA",
    "sg:tags":[
        "apparel",
        "bowling",
        "accessory"
    ],
    "wof:name":"Wayne Webb's Hall Of Fame Pro",
    "wof:placetype":"venue"
},
  "geometry": {"coordinates":[-121.499458,38.517813],"type":"Point"}
}