{
  "type": "Feature",
  "properties": {
    "iso:country":"US",
    "sg:address":"3596 Cajon Blvd",
    "sg:city":"San Bernardino",
    "sg:classifiers":[
        {
            "category":"Retail",
            "subcategory":"Auto Repair",
            "type":"Services"
        }
    ],
    "sg:phone":"+1 909 880 9019",
    "sg:postcode":"92407",
    "sg:province":"CA",
    "sg:tags":[
        "wrecker"
    ],
    "wof:name":"Hot Rod Towing",
    "wof:placetype":"venue"
},
  "geometry": {"coordinates":[-117.335648,34.157427],"type":"Point"}
}