{
  "type": "Feature",
  "properties": {
    "addr:full":"5882 Karen Ave Cypress CA 90630",
    "addr:housenumber":"5882",
    "addr:postcode":"90630",
    "addr:street":"Karen Ave",
    "iso:country":"US",
    "sg:address":"5882 Karen Ave",
    "sg:city":"Cypress",
    "sg:classifiers":[
        {
            "category":"Wholesale",
            "subcategory":"Chemicals & Plastics",
            "type":"Manufacturing & Wholesale Goods"
        }
    ],
    "sg:phone":"+1 714 995 4985",
    "sg:postcode":"90630",
    "sg:province":"CA",
    "wof:name":"Kplastic Bag Supply",
    "wof:placetype":"venue"
},
  "geometry": {"coordinates":[-118.029661,33.826534],"type":"Point"}
}