{
  "type": "Feature",
  "properties": {
    "addr:full":"4430 Commerce St Riverside CA 92507",
    "addr:housenumber":"4430",
    "addr:postcode":"92507",
    "addr:street":"Commerce St",
    "iso:country":"US",
    "sg:address":"4430 Commerce St",
    "sg:city":"Riverside",
    "sg:classifiers":[
        {
            "category":"Manufacturing",
            "subcategory":"Chemicals & Compounds",
            "type":"Manufacturing & Wholesale Goods"
        }
    ],
    "sg:phone":"+1 951 222 3300",
    "sg:postcode":"92507",
    "sg:province":"CA",
    "sg:tags":[
        "performance",
        "industrial",
        "mfg"
    ],
    "wof:name":"FMC Corporation",
    "wof:placetype":"venue"
},
  "geometry": {"coordinates":[-117.37184499999999,33.972024],"type":"Point"}
}