{
  "type": "Feature",
  "properties": {
    "addr:full":"599 N Lake Blvd Tahoe City CA 96145",
    "addr:housenumber":"599",
    "addr:postcode":"96145",
    "addr:street":"N Lake Blvd",
    "iso:country":"US",
    "sg:address":"599 N Lake Blvd",
    "sg:city":"Tahoe City",
    "sg:classifiers":[
        {
            "category":"Restaurant",
            "type":"Food & Drink"
        },
        {
            "category":"Arts & Performance",
            "subcategory":"Music",
            "type":"Entertainment"
        }
    ],
    "sg:phone":"+1 530 583 3355",
    "sg:postcode":"96145",
    "sg:province":"CA",
    "sg:tags":[
        "venue"
    ],
    "wof:name":"Fat Cat Cafe",
    "wof:placetype":"venue"
},
  "geometry": {"coordinates":[-120.14009900000001,39.172129],"type":"Point"}
}