{
  "type": "Feature",
  "properties": {
    "iso:country":"US",
    "sg:address":"7320 Firestone Boulevard Suite 107",
    "sg:city":"Downey",
    "sg:classifiers":[
        {
            "category":"Insurance",
            "subcategory":"Health Insurance",
            "type":"Services"
        }
    ],
    "sg:phone":"+1 562 806 5516",
    "sg:postcode":"90241",
    "sg:province":"CA",
    "sg:tags":[
        "market"
    ],
    "wof:name":"Max Muscle",
    "wof:placetype":"venue"
},
  "geometry": {"coordinates":[-118.151394,33.947111],"type":"Point"}
}