{
  "type": "Feature",
  "properties": {
    "addr:full":"701 Madera Drive San Mateo CA 94403",
    "addr:housenumber":"701",
    "addr:postcode":"94403",
    "addr:street":"Madera Drive",
    "iso:country":"US",
    "sg:address":"701 Madera Drive",
    "sg:city":"San Mateo",
    "sg:classifiers":[
        {
            "category":"Sports & Exercise",
            "subcategory":"Golf",
            "type":"Entertainment"
        }
    ],
    "sg:phone":"+1 650 638 2200",
    "sg:postcode":"94403",
    "sg:province":"CA",
    "wof:name":"Peninsula Golf & Country Club",
    "wof:placetype":"venue"
},
  "geometry": {"coordinates":[-122.320633,37.542127],"type":"Point"}
}