{
  "type": "Feature",
  "properties": {
    "addr:full":"13472 5th St Chino CA 91710",
    "addr:housenumber":"13472",
    "addr:postcode":"91710",
    "addr:street":"5Th St",
    "iso:country":"US",
    "sg:address":"13472 5th St",
    "sg:city":"Chino",
    "sg:classifiers":[
        {
            "category":"Wholesale",
            "subcategory":"Machinery & Supplies",
            "type":"Manufacturing & Wholesale Goods"
        }
    ],
    "sg:phone":"+1 909 591 4921",
    "sg:postcode":"91710",
    "sg:province":"CA",
    "sg:website":"www.chencomachinery.com",
    "wof:name":"Chenco Machinery Co",
    "wof:placetype":"venue"
},
  "geometry": {"coordinates":[-117.693102,34.010696],"type":"Point"}
}