{
  "type": "Feature",
  "properties": {
    "addr:full":"560 Higuera St San Luis Obispo CA 93401",
    "addr:housenumber":"560",
    "addr:postcode":"93401",
    "addr:street":"Higuera St",
    "iso:country":"US",
    "sg:address":"560 Higuera St",
    "sg:city":"San Luis Obispo",
    "sg:classifiers":[
        {
            "category":"Real Estate",
            "subcategory":"Real Estate Agent",
            "type":"Services"
        }
    ],
    "sg:phone":"+1 805 544 1144",
    "sg:postcode":"93401",
    "sg:province":"CA",
    "wof:name":"Source Commercial Group",
    "wof:placetype":"venue"
},
  "geometry": {"coordinates":[-120.66723500000001,35.277114],"type":"Point"}
}