{
  "type": "Feature",
  "properties": {
    "iso:country":"US",
    "sg:address":"1808 A St",
    "sg:city":"Antioch",
    "sg:classifiers":[
        {
            "category":"Shopping",
            "subcategory":"Musical Instruments",
            "type":"Retail Goods"
        }
    ],
    "sg:phone":"+1 925 778 6206",
    "sg:postcode":"94509",
    "sg:province":"CA",
    "wof:name":"Music & More",
    "wof:placetype":"venue"
},
  "geometry": {"coordinates":[-121.806078,38.004664],"type":"Point"}
}