{
  "type": "Feature",
  "properties": {
    "iso:country":"US",
    "sg:address":"587 E Chartres St",
    "sg:city":"Anaheim",
    "sg:classifiers":[
        {
            "category":"Professional",
            "type":"Services"
        }
    ],
    "sg:phone":"+1 714 991 4677",
    "sg:postcode":"92805",
    "sg:province":"CA",
    "wof:name":"Christys Creations",
    "wof:placetype":"venue"
},
  "geometry": {"coordinates":[-117.907543,33.838744],"type":"Point"}
}