{
  "type": "Feature",
  "properties": {
    "iso:country":"US",
    "sg:address":"1106 Corker St",
    "sg:city":"Placerville",
    "sg:classifiers":[
        {
            "category":"Health Services",
            "subcategory":"Doctor",
            "type":"Services"
        }
    ],
    "sg:phone":"+1 530 295 3588",
    "sg:postcode":"95667",
    "sg:province":"CA",
    "sg:tags":[
        "physician",
        "surgeon"
    ],
    "wof:name":"Patrick Knoste MD",
    "wof:placetype":"venue"
},
  "geometry": {"coordinates":[-120.790347,38.725716],"type":"Point"}
}