{
  "type": "Feature",
  "properties": {
    "addr:full":"329 LeCouvreur Ave Wilmington CA 90744",
    "addr:housenumber":"329",
    "addr:postcode":"90744",
    "addr:street":"Lecouvreur Ave",
    "iso:country":"US",
    "sg:address":"329 LeCouvreur Ave",
    "sg:city":"Wilmington",
    "sg:classifiers":[
        {
            "category":"Building & Trades",
            "subcategory":"Construction",
            "type":"Services"
        }
    ],
    "sg:phone":"+1 310 847 7717",
    "sg:postcode":"90744",
    "sg:province":"CA",
    "sg:tags":[
        "contractor"
    ],
    "wof:name":"Amore Design Inc",
    "wof:placetype":"venue"
},
  "geometry": {"coordinates":[-118.255796,33.773947],"type":"Point"}
}