{
  "type": "Feature",
  "properties": {
    "addr:full":"105 E 7th St Los Angeles CA 90014",
    "addr:housenumber":"105",
    "addr:postcode":"90014",
    "addr:street":"E 7Th St",
    "iso:country":"US",
    "sg:address":"105 E 7th St",
    "sg:city":"Los Angeles",
    "sg:classifiers":[
        {
            "category":"Food & Beverages",
            "subcategory":"Liquor & Beverages",
            "type":"Retail Goods"
        }
    ],
    "sg:phone":"+1 213 624 3404",
    "sg:postcode":"90014",
    "sg:province":"CA",
    "sg:tags":[
        "beer",
        "spirit",
        "wine"
    ],
    "wof:name":"Main Market",
    "wof:placetype":"venue"
},
  "geometry": {"coordinates":[-118.25099899999999,34.0439],"type":"Point"}
}