{
  "type": "Feature",
  "properties": {
    "iso:country":"US",
    "sg:address":"8549 el Modena Ave",
    "sg:city":"Elverta",
    "sg:classifiers":[
        {
            "category":"Autos & Motor Vehicles",
            "subcategory":"Automobile Sales",
            "type":"Retail Goods"
        }
    ],
    "sg:phone":"+1 916 215 3206",
    "sg:postcode":"95626",
    "sg:province":"CA",
    "sg:tags":[
        "performance",
        "race",
        "dealer"
    ],
    "wof:name":"R & K Racing",
    "wof:placetype":"venue"
},
  "geometry": {"coordinates":[-121.45748,38.725863],"type":"Point"}
}