{
  "type": "Feature",
  "properties": {
    "addr:full":"1400 Coleman Ave Santa Clara CA 95050",
    "addr:housenumber":"1400",
    "addr:postcode":"95050",
    "addr:street":"Coleman Ave",
    "iso:country":"US",
    "sg:address":"1400 Coleman Ave",
    "sg:city":"Santa Clara",
    "sg:classifiers":[
        {
            "category":"Banks & Credit Unions",
            "subcategory":"Investment Brokerage",
            "type":"Services"
        }
    ],
    "sg:phone":"+1 408 988 1004",
    "sg:postcode":"95050",
    "sg:province":"CA",
    "sg:tags":[
        "management"
    ],
    "wof:name":"Martin Capital Benefits",
    "wof:placetype":"venue"
},
  "geometry": {"coordinates":[-121.94004,37.35837],"type":"Point"}
}