{
  "type": "Feature",
  "properties": {
    "iso:country":"US",
    "sg:address":"6616 Laguna Blvd",
    "sg:city":"Elk Grove",
    "sg:classifiers":[
        {
            "category":"Restaurant",
            "type":"Food & Drink"
        }
    ],
    "sg:phone":"+1 916 683 5464",
    "sg:postcode":"95758",
    "sg:province":"CA",
    "sg:tags":[
        "eating"
    ],
    "wof:name":"Caffe Latte Co",
    "wof:placetype":"venue"
},
  "geometry": {"coordinates":[-121.418813,38.423335],"type":"Point"}
}