{
  "type": "Feature",
  "properties": {
    "addr:full":"820 S Rockefeller Ave Ontario CA 91761",
    "addr:housenumber":"820",
    "addr:postcode":"91761",
    "addr:street":"S Rockefeller Ave",
    "iso:country":"US",
    "sg:address":"820 S Rockefeller Ave",
    "sg:city":"Ontario",
    "sg:phone":"+1 909 390 9600",
    "sg:postcode":"91761",
    "sg:province":"CA",
    "sg:tags":[
        "agricultural",
        "product"
    ],
    "wof:name":"Valplastic USA",
    "wof:placetype":"venue"
},
  "geometry": {"coordinates":[-117.554671,34.058145],"type":"Point"}
}