{
  "type": "Feature",
  "properties": {
    "iso:country":"US",
    "sg:address":"1036 Goodview Way",
    "sg:city":"Redding",
    "sg:classifiers":[
        {
            "category":"Building & Trades",
            "subcategory":"Construction",
            "type":"Services"
        }
    ],
    "sg:phone":"+1 530 244 6518",
    "sg:postcode":"96003",
    "sg:province":"CA",
    "sg:tags":[
        "wallcoverings-installation",
        "wallpaper",
        "painting",
        "contractor"
    ],
    "wof:name":"Modern Painting",
    "wof:placetype":"venue"
},
  "geometry": {"coordinates":[-122.399738,40.622004],"type":"Point"}
}