{
  "type": "Feature",
  "properties": {
    "iso:country":"US",
    "sg:address":"2275 W 25th St",
    "sg:city":"San Pedro",
    "sg:classifiers":[
        {
            "category":"Banks & Credit Unions",
            "subcategory":"Investment Brokerage",
            "type":"Services"
        }
    ],
    "sg:phone":"+1 310 547 2628",
    "sg:postcode":"90732",
    "sg:province":"CA",
    "wof:name":"Mike Investment",
    "wof:placetype":"venue"
},
  "geometry": {"coordinates":[-118.329635,33.727492],"type":"Point"}
}