{
  "type": "Feature",
  "properties": {
    "addr:full":"10737 Laurel St Rancho Cucamonga CA 91730",
    "addr:housenumber":"10737",
    "addr:postcode":"91730",
    "addr:street":"Laurel St",
    "iso:country":"US",
    "sg:address":"10737 Laurel St",
    "sg:city":"Rancho Cucamonga",
    "sg:classifiers":[
        {
            "category":"Professional",
            "subcategory":"Lawyer & Legal Services",
            "type":"Services"
        }
    ],
    "sg:phone":"+1 909 476 0552",
    "sg:postcode":"91730",
    "sg:province":"CA",
    "sg:tags":[
        "attorney"
    ],
    "sg:website":"www.bradfordbarthel.com",
    "wof:name":"Bradford & Barthel",
    "wof:placetype":"venue"
},
  "geometry": {"coordinates":[-117.570204,34.105126],"type":"Point"}
}