{
  "type": "Feature",
  "properties": {
    "addr:full":"611 E Ocean Ave Lompoc CA 93436",
    "addr:housenumber":"611",
    "addr:postcode":"93436",
    "addr:street":"E Ocean Ave",
    "iso:country":"US",
    "sg:address":"611 E Ocean Ave",
    "sg:city":"Lompoc",
    "sg:classifiers":[
        {
            "category":"Insurance",
            "subcategory":"Insurance Agent",
            "type":"Services"
        }
    ],
    "sg:phone":"+1 805 735 2442",
    "sg:postcode":"93436",
    "sg:province":"CA",
    "wof:name":"Allstate",
    "wof:placetype":"venue"
},
  "geometry": {"coordinates":[-120.45039,34.639015],"type":"Point"}
}