{
  "type": "Feature",
  "properties": {
    "addr:full":"202 Madison St Oakland CA 94607",
    "addr:housenumber":"202",
    "addr:postcode":"94607",
    "addr:street":"Madison St",
    "iso:country":"US",
    "sg:address":"202 Madison St",
    "sg:city":"Oakland",
    "sg:classifiers":[
        {
            "category":"Wholesale",
            "subcategory":"Fruits & Vegetables",
            "type":"Manufacturing & Wholesale Goods"
        }
    ],
    "sg:phone":"+1 510 452 3539",
    "sg:postcode":"94607",
    "sg:province":"CA",
    "sg:tags":[
        "grocery"
    ],
    "wof:name":"Leogrande Bros Produce",
    "wof:placetype":"venue"
},
  "geometry": {"coordinates":[-122.268997,37.793301],"type":"Point"}
}