{
  "type": "Feature",
  "properties": {
    "iso:country":"US",
    "sg:address":"37048 Niles Blvd",
    "sg:city":"Fremont",
    "sg:classifiers":[
        {
            "category":"Wholesale",
            "subcategory":"Durable Goods & Equipment",
            "type":"Manufacturing & Wholesale Goods"
        }
    ],
    "sg:phone":"+1 510 745 8800",
    "sg:postcode":"94536",
    "sg:province":"CA",
    "sg:tags":[
        "importer"
    ],
    "wof:name":"Guans Mushroom Co",
    "wof:placetype":"venue"
},
  "geometry": {"coordinates":[-121.983417,37.578034],"type":"Point"}
}