{
  "type": "Feature",
  "properties": {
    "addr:full":"111 Deerwood Rd San Ramon CA 94583",
    "addr:housenumber":"111",
    "addr:postcode":"ca 94583",
    "addr:street":"Deerwood Rd",
    "iso:country":"US",
    "sg:address":"111 Deerwood Rd",
    "sg:city":"San Ramon",
    "sg:classifiers":[
        {
            "category":"Banks & Credit Unions",
            "subcategory":"Financial Services",
            "type":"Services"
        }
    ],
    "sg:phone":"+1 925 314 1218",
    "sg:postcode":"94583",
    "sg:province":"CA",
    "sg:tags":[
        "broker",
        "mortgage"
    ],
    "wof:name":"Priority Financial-Eric Robles",
    "wof:placetype":"venue"
},
  "geometry": {"coordinates":[-121.989321,37.774189],"type":"Point"}
}