{
  "type": "Feature",
  "properties": {
    "addr:full":"7001 Village Pkwy Dublin CA 94568",
    "addr:housenumber":"7001",
    "addr:postcode":"94568",
    "addr:street":"Village Pkwy",
    "iso:country":"US",
    "sg:address":"7001 Village Pkwy",
    "sg:city":"Dublin",
    "sg:classifiers":[
        {
            "category":"Banks & Credit Unions",
            "subcategory":"Bank",
            "type":"Services"
        }
    ],
    "sg:phone":"+1 925 829 6550",
    "sg:postcode":"94568",
    "sg:province":"CA",
    "sg:tags":[
        "loan"
    ],
    "sg:website":"www.mortgagemarket.net",
    "wof:name":"Mortgage Market Inc",
    "wof:placetype":"venue"
},
  "geometry": {"coordinates":[-121.925505,37.708146],"type":"Point"}
}