{
  "type": "Feature",
  "properties": {
    "iso:country":"US",
    "sg:address":"5600 Pso del Norte",
    "sg:city":"Carlsbad",
    "sg:classifiers":[
        {
            "category":"Shopping",
            "subcategory":"Clothing, Apparel, & Fashions",
            "type":"Retail Goods"
        }
    ],
    "sg:phone":"+1 760 804 0667",
    "sg:postcode":"92008",
    "sg:province":"CA",
    "sg:tags":[
        "sportswear"
    ],
    "wof:name":"Adidas Retail Outlet",
    "wof:placetype":"venue"
},
  "geometry": {"coordinates":[-117.162406,33.331505],"type":"Point"}
}