{
  "type": "Feature",
  "properties": {
    "addr:full":"42031 Main St Ste F Temecula CA 92590",
    "addr:housenumber":"42031",
    "addr:postcode":"92590",
    "addr:street":"Main St Ste F",
    "iso:country":"US",
    "sg:address":"42031 Main St Ste F",
    "sg:city":"Temecula",
    "sg:classifiers":[
        {
            "category":"Personal",
            "subcategory":"Beauty Salon",
            "type":"Services"
        }
    ],
    "sg:phone":"+1 951 676 6904",
    "sg:postcode":"92590",
    "sg:province":"CA",
    "sg:tags":[
        "hair",
        "stylist"
    ],
    "wof:name":"Main Street Salon",
    "wof:placetype":"venue"
},
  "geometry": {"coordinates":[-117.14891799999999,33.493256],"type":"Point"}
}