{
  "type": "Feature",
  "properties": {
    "iso:country":"US",
    "sg:address":"363 Terraine Ave",
    "sg:city":"Long Beach",
    "sg:classifiers":[
        {
            "category":"Manufacturing",
            "subcategory":"Toys & Sporting Goods",
            "type":"Manufacturing & Wholesale Goods"
        }
    ],
    "sg:phone":"+1 562 597 5366",
    "sg:postcode":"90814",
    "sg:province":"CA",
    "sg:tags":[
        "fabric",
        "sculpture",
        "design",
        "retail",
        "soft",
        "decorator"
    ],
    "wof:name":"Colonial Craft",
    "wof:placetype":"venue"
},
  "geometry": {"coordinates":[-118.127498,33.770542],"type":"Point"}
}