{
  "type": "Feature",
  "properties": {
    "iso:country":"US",
    "sg:address":"25789 Dollar St",
    "sg:city":"Hayward",
    "sg:classifiers":[
        {
            "category":"Autos & Motor Vehicles",
            "subcategory":"Automobile Sales",
            "type":"Retail Goods"
        }
    ],
    "sg:phone":"+1 510 751 1700",
    "sg:postcode":"94544",
    "sg:province":"CA",
    "sg:tags":[
        "car",
        "dealer"
    ],
    "wof:name":"Hayward Ford Fleet",
    "wof:placetype":"venue"
},
  "geometry": {"coordinates":[-122.06870600000001,37.651383],"type":"Point"}
}