{
  "type": "Feature",
  "properties": {
    "addr:full":"286 Loch Lomond Rd Rancho Mirage CA 92270",
    "addr:housenumber":"286",
    "addr:postcode":"92270",
    "addr:street":"Loch Lomond Rd",
    "iso:country":"US",
    "sg:address":"286 Loch Lomond Rd",
    "sg:city":"Rancho Mirage",
    "sg:classifiers":[
        {
            "category":"Professional",
            "type":"Services"
        }
    ],
    "sg:phone":"+1 760 898 5157",
    "sg:postcode":"92270",
    "sg:province":"CA",
    "sg:website":"www.4uido.net",
    "wof:name":"4 U I Do Weddings",
    "wof:placetype":"venue"
},
  "geometry": {"coordinates":[-116.43616900000001,33.8083],"type":"Point"}
}