{
  "type": "Feature",
  "properties": {
    "addr:full":"6910 Bristol Dr Berkeley CA 94705",
    "addr:housenumber":"6910",
    "addr:postcode":"94705",
    "addr:street":"Bristol Dr",
    "iso:country":"US",
    "sg:address":"6910 Bristol Dr",
    "sg:city":"Berkeley",
    "sg:classifiers":[
        {
            "category":"Shopping",
            "subcategory":"Photographic Equipment",
            "type":"Retail Goods"
        }
    ],
    "sg:phone":"+1 510 527 5905",
    "sg:postcode":"94705",
    "sg:province":"CA",
    "sg:tags":[
        "supply"
    ],
    "wof:name":"Pilecki's Antique Camera",
    "wof:placetype":"venue"
},
  "geometry": {"coordinates":[-122.22342500000001,37.859611],"type":"Point"}
}