{
  "type": "Feature",
  "properties": {
    "addr:full":"15132 Bolsa Chica St Huntington Beach CA 92649",
    "addr:housenumber":"15132",
    "addr:postcode":"92649",
    "addr:street":"Bolsa Chica St",
    "iso:country":"US",
    "sg:address":"15132 Bolsa Chica St",
    "sg:city":"Huntington Beach",
    "sg:classifiers":[
        {
            "category":"Farming",
            "subcategory":"Nursery",
            "type":"Manufacturing & Wholesale Goods"
        }
    ],
    "sg:phone":"+1 714 897 5624",
    "sg:postcode":"92649",
    "sg:province":"CA",
    "sg:tags":[
        "ornamental"
    ],
    "wof:name":"Rcn",
    "wof:placetype":"venue"
},
  "geometry": {"coordinates":[-118.041821,33.743944],"type":"Point"}
}