{
  "type": "Feature",
  "properties": {
    "iso:country":"US",
    "sg:address":"17332 Irvine Blvd Ste 290",
    "sg:city":"Tustin",
    "sg:classifiers":[
        {
            "category":"Organizations",
            "subcategory":"Professional Association",
            "type":"Services"
        }
    ],
    "sg:phone":"+1 714 505 3394",
    "sg:postcode":"92780",
    "sg:province":"CA",
    "wof:name":"Nationwide Research Network",
    "wof:placetype":"venue"
},
  "geometry": {"coordinates":[-117.82993999999999,33.748154],"type":"Point"}
}