{
  "type": "Feature",
  "properties": {
    "addr:full":"6440 Sepulveda Blvd Van Nuys CA 91411",
    "addr:housenumber":"6440",
    "addr:postcode":"91411",
    "addr:street":"Sepulveda Blvd",
    "iso:country":"US",
    "sg:address":"6440 Sepulveda Blvd",
    "sg:city":"Van Nuys",
    "sg:classifiers":[
        {
            "category":"Shopping",
            "subcategory":"Stationery & Office Supplies",
            "type":"Retail Goods"
        }
    ],
    "sg:phone":"+1 818 780 9916",
    "sg:postcode":"91411",
    "sg:province":"CA",
    "sg:website":"www.officedepot.com",
    "wof:name":"Office Depot",
    "wof:placetype":"venue"
},
  "geometry": {"coordinates":[-118.466106,34.18773],"type":"Point"}
}