{
  "type": "Feature",
  "properties": {
    "addr:full":"7803 Madison Ave Citrus Heights CA 95610",
    "addr:housenumber":"7803",
    "addr:postcode":"95610",
    "addr:street":"Madison Ave",
    "iso:country":"US",
    "sg:address":"7803 Madison Ave",
    "sg:city":"Citrus Heights",
    "sg:classifiers":[
        {
            "category":"Banks & Credit Unions",
            "subcategory":"Investment Brokerage",
            "type":"Services"
        }
    ],
    "sg:phone":"+1 916 536 1447",
    "sg:postcode":"95610",
    "sg:province":"CA",
    "sg:tags":[
        "consultant",
        "planning",
        "financial"
    ],
    "wof:name":"Scott & Assoc",
    "wof:placetype":"venue"
},
  "geometry": {"coordinates":[-121.27553899999999,38.663932],"type":"Point"}
}