{
  "type": "Feature",
  "properties": {
    "addr:full":"289 Redwood Cir Petaluma CA 94954",
    "addr:housenumber":"289",
    "addr:postcode":"94954",
    "addr:street":"Redwood Cir",
    "iso:country":"US",
    "sg:address":"289 Redwood Cir",
    "sg:city":"Petaluma",
    "sg:classifiers":[
        {
            "category":"Building & Trades",
            "subcategory":"Electrical",
            "type":"Services"
        }
    ],
    "sg:phone":"+1 707 766 6071",
    "sg:postcode":"94954",
    "sg:province":"CA",
    "sg:tags":[
        "electrician"
    ],
    "wof:name":"California Custom Electrical Contractors",
    "wof:placetype":"venue"
},
  "geometry": {"coordinates":[-122.617915,38.260094],"type":"Point"}
}