{
  "type": "Feature",
  "properties": {
    "iso:country":"US",
    "sg:address":"3849 Macarthur Blvd",
    "sg:city":"Oakland",
    "sg:classifiers":[
        {
            "category":"Social Services",
            "subcategory":"Child Care",
            "type":"Services"
        }
    ],
    "sg:phone":"+1 510 530 7316",
    "sg:postcode":"94619",
    "sg:province":"CA",
    "wof:name":"Cornerstone After School",
    "wof:placetype":"venue"
},
  "geometry": {"coordinates":[-122.198557,37.791308],"type":"Point"}
}