{
  "type": "Feature",
  "properties": {
    "addr:full":"1936 Freedom Blvd A Freedom CA 95019",
    "addr:housenumber":"1936",
    "addr:postcode":"95019",
    "addr:street":"Freedom Blvd A",
    "iso:country":"US",
    "sg:address":"1936 Freedom Blvd A",
    "sg:city":"Freedom",
    "sg:classifiers":[
        {
            "category":"Social Services",
            "subcategory":"Child Care",
            "type":"Services"
        }
    ],
    "sg:phone":"+1 831 724 3749",
    "sg:postcode":"95019",
    "sg:province":"CA",
    "sg:tags":[
        "nursery",
        "day"
    ],
    "wof:name":"Vista Verda Child Development Center",
    "wof:placetype":"venue"
},
  "geometry": {"coordinates":[-121.775075,36.936456],"type":"Point"}
}