{
  "type": "Feature",
  "properties": {
    "addr:full":"4408 Corliss St Los Angeles CA 90041",
    "addr:housenumber":"4408",
    "addr:postcode":"90041",
    "addr:street":"Corliss St",
    "iso:country":"US",
    "sg:address":"4408 Corliss St",
    "sg:city":"Los Angeles",
    "sg:classifiers":[
        {
            "category":"Professional",
            "subcategory":"Art Services",
            "type":"Services"
        }
    ],
    "sg:phone":"+1 702 527 4337",
    "sg:postcode":"90041",
    "sg:province":"CA",
    "sg:tags":[
        "photographer"
    ],
    "sg:website":"www.litratistas.com",
    "wof:name":"Litratistas Freelance Photography",
    "wof:placetype":"venue"
},
  "geometry": {"coordinates":[-118.21888300000001,34.128584],"type":"Point"}
}