{
  "type": "Feature",
  "properties": {
    "iso:country":"US",
    "sg:address":"3028 Handel Way",
    "sg:city":"Sacramento",
    "sg:classifiers":[
        {
            "category":"Manufacturing",
            "subcategory":"Jewelry",
            "type":"Manufacturing & Wholesale Goods"
        }
    ],
    "sg:phone":"+1 916 369 9689",
    "sg:postcode":"95826",
    "sg:province":"CA",
    "sg:tags":[
        "costume",
        "mfg"
    ],
    "wof:name":"OH My Stars Designs",
    "wof:placetype":"venue"
},
  "geometry": {"coordinates":[-121.36036300000001,38.558229],"type":"Point"}
}