{
  "type": "Feature",
  "properties": {
    "iso:country":"US",
    "sg:address":"4101 Chevy Chase Dr",
    "sg:city":"Los Angeles",
    "sg:classifiers":[
        {
            "category":"Food & Beverages",
            "subcategory":"Groceries & Convenience Stores",
            "type":"Retail Goods"
        }
    ],
    "sg:phone":"+1 818 247 4426",
    "sg:postcode":"90039",
    "sg:province":"CA",
    "wof:name":"Boone's Market",
    "wof:placetype":"venue"
},
  "geometry": {"coordinates":[-118.268997,34.133499],"type":"Point"}
}