{
  "type": "Feature",
  "properties": {
    "addr:full":"3564 Van Buren Blvd Riverside CA 92503",
    "addr:housenumber":"3564",
    "addr:postcode":"92503",
    "addr:street":"Van Buren Blvd",
    "iso:country":"US",
    "sg:address":"3564 Van Buren Blvd",
    "sg:city":"Riverside",
    "sg:classifiers":[
        {
            "category":"Health Services",
            "subcategory":"Doctor",
            "type":"Services"
        }
    ],
    "sg:phone":"+1 866 688 3898",
    "sg:postcode":"92503",
    "sg:province":"CA",
    "sg:tags":[
        "dentist",
        "dentists-orthodontists"
    ],
    "wof:name":"Dentistry 4 Kids",
    "wof:placetype":"venue"
},
  "geometry": {"coordinates":[-117.443336,33.916431],"type":"Point"}
}