{
  "type": "Feature",
  "properties": {
    "iso:country":"US",
    "sg:address":"102 E Arrow Hwy",
    "sg:city":"San Dimas",
    "sg:classifiers":[
        {
            "category":"Autos & Motor Vehicles",
            "subcategory":"Fuel & Gas Station",
            "type":"Retail Goods"
        }
    ],
    "sg:phone":"+1 909 599 8288",
    "sg:postcode":"91773",
    "sg:province":"CA",
    "sg:tags":[
        "oil"
    ],
    "wof:name":"San Dimas Svc Station",
    "wof:placetype":"venue"
},
  "geometry": {"coordinates":[-117.802781,34.102884],"type":"Point"}
}