{
  "type": "Feature",
  "properties": {
    "addr:full":"258 Daffodil Dr Fairfield CA 94533",
    "addr:housenumber":"258",
    "addr:postcode":"94533",
    "addr:street":"Daffodil Dr",
    "iso:country":"US",
    "sg:address":"258 Daffodil Dr",
    "sg:city":"Fairfield",
    "sg:classifiers":[
        {
            "category":"Professional",
            "subcategory":"Lawyer & Legal Services",
            "type":"Services"
        }
    ],
    "sg:phone":"+1 707 427 1874",
    "sg:postcode":"94533",
    "sg:province":"CA",
    "sg:tags":[
        "attorney"
    ],
    "wof:name":"Certified Appellate Law",
    "wof:placetype":"venue"
},
  "geometry": {"coordinates":[-122.037515,38.282073],"type":"Point"}
}