{
  "type": "Feature",
  "properties": {
    "iso:country":"US",
    "sg:address":"2407 N Sepulveda Blvd",
    "sg:city":"Manhattan Beach",
    "sg:classifiers":[
        {
            "category":"Health Services",
            "subcategory":"Chiropractor",
            "type":"Services"
        }
    ],
    "sg:phone":"+1 310 796 6955",
    "sg:postcode":"90266",
    "sg:province":"CA",
    "wof:name":"Aim Treatment Ctr",
    "wof:placetype":"venue"
},
  "geometry": {"coordinates":[-118.396069,33.894572],"type":"Point"}
}