{
  "type": "Feature",
  "properties": {
    "addr:full":"40970 California Oaks Rd Murrieta CA 92562",
    "addr:housenumber":"40970",
    "addr:postcode":"92562",
    "addr:street":"California Oaks Rd",
    "iso:country":"US",
    "sg:address":"40970 California Oaks Rd",
    "sg:city":"Murrieta",
    "sg:classifiers":[
        {
            "category":"Deli",
            "type":"Food & Drink"
        },
        {
            "category":"Restaurant",
            "type":"Food & Drink"
        }
    ],
    "sg:menulink":"http://www.allmenus.com/ca/murrieta/52294-submarina/menu/",
    "sg:phone":"+1 951 304 9970",
    "sg:postcode":"92562",
    "sg:province":"CA",
    "sg:tags":[
        "deli",
        "wrap",
        "american",
        "sandwich"
    ],
    "wof:name":"Submarina",
    "wof:placetype":"venue"
},
  "geometry": {"coordinates":[-117.20587500000001,33.567431],"type":"Point"}
}