{
  "type": "Feature",
  "properties": {
    "iso:country":"US",
    "sg:address":"9320 Chesapeake Dr # 104",
    "sg:city":"San Diego",
    "sg:classifiers":[
        {
            "category":"Personal",
            "type":"Services"
        },
        {
            "category":"Utilities",
            "type":"Services"
        },
        {
            "category":"Professional",
            "subcategory":"Computer Services",
            "type":"Services"
        }
    ],
    "sg:phone":"+1 858 633 1126",
    "sg:postcode":"92123",
    "sg:province":"CA",
    "sg:tags":[
        "home",
        "repair",
        "provider",
        "internet"
    ],
    "sg:website":"www.c3networx.com",
    "wof:name":"C3 Networx",
    "wof:placetype":"venue"
},
  "geometry": {"coordinates":[-117.127971,32.838028],"type":"Point"}
}