{
  "type": "Feature",
  "properties": {
    "addr:full":"226 Airport Pkwy Ste 150 San Jose CA 95110",
    "addr:housenumber":"226",
    "addr:postcode":"95110",
    "addr:street":"Airport Pkwy Ste 150",
    "iso:country":"US",
    "sg:address":"226 Airport Pkwy Ste 150",
    "sg:city":"San Jose",
    "sg:classifiers":[
        {
            "category":"Building & Trades",
            "subcategory":"Construction",
            "type":"Services"
        }
    ],
    "sg:phone":"+1 408 454 2750",
    "sg:postcode":"95110",
    "sg:province":"CA",
    "sg:tags":[
        "contractor"
    ],
    "wof:name":"Hensel Phelps",
    "wof:placetype":"venue"
},
  "geometry": {"coordinates":[-121.92242400000001,37.369168],"type":"Point"}
}