{
  "type": "Feature",
  "properties": {
    "iso:country":"US",
    "sg:address":"4831 Lago Dr",
    "sg:city":"Huntington Beach",
    "sg:classifiers":[
        {
            "category":"Manufacturing",
            "subcategory":"Tools & Machinery",
            "type":"Manufacturing & Wholesale Goods"
        }
    ],
    "sg:phone":"+1 714 846 7364",
    "sg:postcode":"92649",
    "sg:province":"CA",
    "sg:tags":[
        "electrical",
        "mfg"
    ],
    "wof:name":"University Test Prep",
    "wof:placetype":"venue"
},
  "geometry": {"coordinates":[-118.044253,33.721178],"type":"Point"}
}