{
  "type": "Feature",
  "properties": {
    "iso:country":"US",
    "sg:address":"4614 W Rishell Ct",
    "sg:city":"Concord",
    "sg:classifiers":[
        {
            "category":"Building & Trades",
            "subcategory":"Landscaping Services",
            "type":"Services"
        }
    ],
    "sg:phone":"+1 925 798 1486",
    "sg:postcode":"94521",
    "sg:province":"CA",
    "wof:name":"Matsuno Shigeru Gardening",
    "wof:placetype":"venue"
},
  "geometry": {"coordinates":[-121.983864,37.96352],"type":"Point"}
}