{
  "type": "Feature",
  "properties": {
    "iso:country":"US",
    "sg:address":"999 Skyway Road Suite 200",
    "sg:city":"San Carlos",
    "sg:classifiers":[
        {
            "category":"Professional",
            "subcategory":"Computer Services",
            "type":"Services"
        }
    ],
    "sg:phone":"+1 650 655 2300",
    "sg:postcode":"94070",
    "sg:province":"CA",
    "sg:tags":[
        "xml",
        "content-management",
        "xquery",
        "enterprise-search",
        "xml-content-platform"
    ],
    "sg:website":"http://www.marklogic.com/",
    "wof:name":"MarkLogic",
    "wof:placetype":"venue"
},
  "geometry": {"coordinates":[-122.44973,37.657313],"type":"Point"}
}