{
  "type": "Feature",
  "properties": {
    "addr:full":"6109 S Western Ave Los Angeles CA 90047",
    "addr:housenumber":"6109",
    "addr:postcode":"90047",
    "addr:street":"S Western Ave",
    "iso:country":"US",
    "sg:address":"6109 S Western Ave",
    "sg:city":"Los Angeles",
    "sg:classifiers":[
        {
            "category":"Personal",
            "type":"Services"
        }
    ],
    "sg:phone":"+1 323 750 1672",
    "sg:postcode":"90047",
    "sg:province":"CA",
    "sg:tags":[
        "bankruptcy"
    ],
    "wof:name":"Bankruptcy Clinic",
    "wof:placetype":"venue"
},
  "geometry": {"coordinates":[-118.309022,33.984029],"type":"Point"}
}