{
  "type": "Feature",
  "properties": {
    "iso:country":"US",
    "sg:address":"5345 Fawn Crossing Way",
    "sg:city":"Antelope",
    "sg:classifiers":[
        {
            "category":"Building & Trades",
            "subcategory":"Construction",
            "type":"Services"
        }
    ],
    "sg:phone":"+1 916 725 7135",
    "sg:postcode":"95843",
    "sg:province":"CA",
    "sg:tags":[
        "general",
        "contractor"
    ],
    "wof:name":"Briggs Brothers Construction",
    "wof:placetype":"venue"
},
  "geometry": {"coordinates":[-121.343941,38.714073],"type":"Point"}
}