{
  "type": "Feature",
  "properties": {
    "addr:full":"110 Sutter St Ste 700 San Francisco CA 94104",
    "addr:housenumber":"110",
    "addr:postcode":"94104",
    "addr:street":"Sutter St Ste 700",
    "iso:country":"US",
    "sg:address":"110 Sutter St Ste 700",
    "sg:city":"San Francisco",
    "sg:classifiers":[
        {
            "category":"Professional",
            "type":"Services"
        },
        {
            "category":"Communications",
            "type":"Services"
        }
    ],
    "sg:phone":"+1 415 694 6700",
    "sg:postcode":"94104",
    "sg:province":"CA",
    "sg:tags":[
        "medium",
        "mass"
    ],
    "sg:website":"www.racepointgroup.com",
    "wof:name":"Racepoint Group",
    "wof:placetype":"venue"
},
  "geometry": {"coordinates":[-122.402627,37.790029],"type":"Point"}
}