{
  "type": "Feature",
  "properties": {
    "iso:country":"US",
    "sg:address":"381 Tehama Street",
    "sg:city":"San Francisco",
    "sg:classifiers":[
        {
            "category":"Real Estate",
            "subcategory":"Architect",
            "type":"Services"
        }
    ],
    "sg:phone":"+1 415 995 9870",
    "sg:postcode":"94103",
    "sg:province":"CA",
    "wof:name":"Robin Chiang & Company",
    "wof:placetype":"venue"
},
  "geometry": {"coordinates":[-122.403999,37.7813],"type":"Point"}
}