{
  "type": "Feature",
  "properties": {
    "iso:country":"US",
    "sg:address":"720 San Julian Street",
    "sg:city":"Los Angeles",
    "sg:classifiers":[
        {
            "category":"Shopping",
            "subcategory":"Florist",
            "type":"Retail Goods"
        }
    ],
    "sg:phone":"+1 213 683 1217",
    "sg:postcode":"90014",
    "sg:province":"CA",
    "wof:name":"A & C Flowers",
    "wof:placetype":"venue"
},
  "geometry": {"coordinates":[-118.247891,34.040855],"type":"Point"}
}