{
  "type": "Feature",
  "properties": {
    "addr:full":"9500 S de Wolf Ave Selma CA 93662",
    "addr:housenumber":"9500",
    "addr:postcode":"93662",
    "addr:street":"S De Wolf Ave",
    "iso:country":"US",
    "sg:address":"9500 S de Wolf Ave",
    "sg:city":"Selma",
    "sg:classifiers":[
        {
            "category":"Manufacturing",
            "subcategory":"Food",
            "type":"Manufacturing & Wholesale Goods"
        }
    ],
    "sg:phone":"+1 559 834 6677",
    "sg:postcode":"93662",
    "sg:province":"CA",
    "sg:tags":[
        "fruits-dried",
        "product",
        "manufacturer"
    ],
    "sg:website":"http://www.lionraisins.com",
    "wof:name":"Lion Packing Co",
    "wof:placetype":"venue"
},
  "geometry": {"coordinates":[-119.646529,36.596995],"type":"Point"}
}