{
  "type": "Feature",
  "properties": {
    "iso:country":"US",
    "sg:address":"765 E Easy St",
    "sg:city":"Simi Valley",
    "sg:classifiers":[
        {
            "category":"Retail",
            "subcategory":"Auto Repair",
            "type":"Services"
        }
    ],
    "sg:phone":"+1 805 581 2822",
    "sg:postcode":"93065",
    "sg:province":"CA",
    "sg:tags":[
        "repairing",
        "automobile"
    ],
    "wof:name":"Peterson Repair",
    "wof:placetype":"venue"
},
  "geometry": {"coordinates":[-118.782265,34.273728],"type":"Point"}
}