{
  "type": "Feature",
  "properties": {
    "iso:country":"US",
    "sg:address":"22110 Roscoe Blvd Ste 300",
    "sg:city":"Canoga Park",
    "sg:classifiers":[
        {
            "category":"Health Services",
            "subcategory":"Doctor",
            "type":"Services"
        },
        {
            "category":"Personal",
            "subcategory":"Hair Removal",
            "type":"Services"
        },
        {
            "category":"Personal",
            "subcategory":"Day Spa",
            "type":"Services"
        }
    ],
    "sg:phone":"+1 818 999 9096",
    "sg:postcode":"91304",
    "sg:province":"CA",
    "wof:name":"Max Ghannadi Md Inc",
    "wof:placetype":"venue"
},
  "geometry": {"coordinates":[-118.608071,34.219492],"type":"Point"}
}