{
  "type": "Feature",
  "properties": {
    "iso:country":"US",
    "sg:address":"40709 Gualala Pl",
    "sg:city":"Fremont",
    "sg:classifiers":[
        {
            "category":"Manufacturing",
            "subcategory":"Tools & Machinery",
            "type":"Manufacturing & Wholesale Goods"
        }
    ],
    "sg:phone":"+1 510 623 1223",
    "sg:postcode":"94539",
    "sg:province":"CA",
    "sg:tags":[
        "fasteners-industrial"
    ],
    "wof:name":"Mission Fasteners Inc",
    "wof:placetype":"venue"
},
  "geometry": {"coordinates":[-121.950981,37.547615],"type":"Point"}
}