{
  "type": "Feature",
  "properties": {
    "addr:full":"2840 N Verdugo Rd Glendale CA 91208",
    "addr:housenumber":"2840",
    "addr:postcode":"91208",
    "addr:street":"N Verdugo Rd",
    "iso:country":"US",
    "sg:address":"2840 N Verdugo Rd",
    "sg:city":"Glendale",
    "sg:classifiers":[
        {
            "category":"Personal",
            "subcategory":"Beauty Salon",
            "type":"Services"
        }
    ],
    "sg:phone":"+1 818 419 3074",
    "sg:postcode":"91208",
    "sg:province":"CA",
    "wof:name":"Great Escape",
    "wof:placetype":"venue"
},
  "geometry": {"coordinates":[-118.225831,34.188122],"type":"Point"}
}