{
  "type": "Feature",
  "properties": {
    "addr:full":"2617 Maestro Way Modesto CA 95355",
    "addr:housenumber":"2617",
    "addr:postcode":"ca 95355",
    "addr:street":"Maestro Way",
    "iso:country":"US",
    "sg:address":"2617 Maestro Way",
    "sg:city":"Modesto",
    "sg:classifiers":[
        {
            "category":"Professional",
            "subcategory":"Management & Consulting",
            "type":"Services"
        }
    ],
    "sg:phone":"+1 209 551 6791",
    "sg:postcode":"95355",
    "sg:province":"CA",
    "sg:tags":[
        "party",
        "planning"
    ],
    "wof:name":"Events Unlimited",
    "wof:placetype":"venue"
},
  "geometry": {"coordinates":[-120.949029,37.68768],"type":"Point"}
}