{
  "type": "Feature",
  "properties": {
    "addr:full":"150 N Santa Anita Ave Arcadia CA 91006",
    "addr:housenumber":"150",
    "addr:postcode":"91006",
    "addr:street":"N Santa Anita Ave",
    "iso:country":"US",
    "sg:address":"150 N Santa Anita Ave",
    "sg:city":"Arcadia",
    "sg:classifiers":[
        {
            "category":"Wholesale",
            "subcategory":"Computers",
            "type":"Manufacturing & Wholesale Goods"
        }
    ],
    "sg:phone":"+1 626 821 1818",
    "sg:postcode":"91006",
    "sg:province":"CA",
    "sg:tags":[
        "equipment",
        "banking",
        "coding",
        "bar"
    ],
    "wof:name":"Gicom Enterprises Inc",
    "wof:placetype":"venue"
},
  "geometry": {"coordinates":[-118.03139,34.141801],"type":"Point"}
}