{
  "type": "Feature",
  "properties": {
    "addr:full":"16201 Halsey St Granada Hills CA 91344",
    "addr:housenumber":"16201",
    "addr:postcode":"91344",
    "addr:street":"Halsey St",
    "iso:country":"US",
    "sg:address":"16201 Halsey St",
    "sg:city":"Granada Hills",
    "sg:classifiers":[
        {
            "category":"Building & Trades",
            "subcategory":"Construction",
            "type":"Services"
        }
    ],
    "sg:phone":"+1 818 363 1986",
    "sg:postcode":"91344",
    "sg:province":"CA",
    "sg:tags":[
        "contractor"
    ],
    "wof:name":"Eli Tile",
    "wof:placetype":"venue"
},
  "geometry": {"coordinates":[-118.485747,34.279841],"type":"Point"}
}