{
  "type": "Feature",
  "properties": {
    "addr:full":"710 S Victory Blvd Burbank CA 91502",
    "addr:housenumber":"710",
    "addr:postcode":"91502",
    "addr:street":"S Victory Blvd",
    "iso:country":"US",
    "sg:address":"710 S Victory Blvd",
    "sg:city":"Burbank",
    "sg:classifiers":[
        {
            "category":"Social Services",
            "type":"Services"
        }
    ],
    "sg:phone":"+1 818 563 2300",
    "sg:postcode":"91502",
    "sg:province":"CA",
    "sg:tags":[
        "crisis",
        "intervention"
    ],
    "wof:name":"Olivecrest Treatment Ctr",
    "wof:placetype":"venue"
},
  "geometry": {"coordinates":[-118.31045,34.168723],"type":"Point"}
}