{
  "type": "Feature",
  "properties": {
    "addr:full":"131 Venture St San Marcos CA 92078",
    "addr:housenumber":"131",
    "addr:postcode":"92078",
    "addr:street":"Venture St",
    "iso:country":"US",
    "sg:address":"131 Venture St",
    "sg:city":"San Marcos",
    "sg:classifiers":[
        {
            "category":"Manufacturing",
            "subcategory":"Tools & Machinery",
            "type":"Manufacturing & Wholesale Goods"
        }
    ],
    "sg:phone":"+1 760 591 4595",
    "sg:postcode":"92078",
    "sg:province":"CA",
    "sg:tags":[
        "shop",
        "specializing",
        "for",
        "machine",
        "p",
        "computer",
        "electronics"
    ],
    "wof:name":"Mercury Tool & Die Corp",
    "wof:placetype":"venue"
},
  "geometry": {"coordinates":[-117.15361,33.138176],"type":"Point"}
}