{
  "type": "Feature",
  "properties": {
    "addr:full":"9 Vivian St San Rafael CA 94901",
    "addr:housenumber":"9",
    "addr:postcode":"94901",
    "addr:street":"Vivian St",
    "iso:country":"US",
    "sg:address":"9 Vivian St",
    "sg:city":"San Rafael",
    "sg:classifiers":[
        {
            "category":"Building & Trades",
            "subcategory":"Construction",
            "type":"Services"
        }
    ],
    "sg:phone":"+1 415 455 8915",
    "sg:postcode":"94901",
    "sg:province":"CA",
    "sg:tags":[
        "contractor"
    ],
    "wof:name":"Jl Cleaning",
    "wof:placetype":"venue"
},
  "geometry": {"coordinates":[-122.50772499999999,37.964294],"type":"Point"}
}