{
  "type": "Feature",
  "properties": {
    "iso:country":"US",
    "sg:address":"511 Dawson Dr Ste A",
    "sg:city":"Camarillo",
    "sg:classifiers":[
        {
            "category":"Building & Trades",
            "subcategory":"Construction",
            "type":"Services"
        }
    ],
    "sg:phone":"+1 805 388 8233",
    "sg:postcode":"93012",
    "sg:province":"CA",
    "sg:tags":[
        "interior",
        "design"
    ],
    "wof:name":"Star Class Interiors Inc",
    "wof:placetype":"venue"
},
  "geometry": {"coordinates":[-119.03600299999999,34.207298],"type":"Point"}
}