{
  "type": "Feature",
  "properties": {
    "iso:country":"US",
    "sg:address":"554 E 1st St",
    "sg:city":"Tustin",
    "sg:classifiers":[
        {
            "category":"Personal",
            "subcategory":"Beauty Salon",
            "type":"Services"
        }
    ],
    "sg:phone":"+1 714 731 3810",
    "sg:postcode":"92780",
    "sg:province":"CA",
    "sg:tags":[
        "hair"
    ],
    "sg:website":"www.fantasticsams.com",
    "wof:name":"Fantastic Sams",
    "wof:placetype":"venue"
},
  "geometry": {"coordinates":[-117.81790599999999,33.745676],"type":"Point"}
}