{
  "type": "Feature",
  "properties": {
    "addr:full":"12881 Knott St Garden Grove CA 92841",
    "addr:housenumber":"12881",
    "addr:postcode":"92841",
    "addr:street":"Knott St",
    "iso:country":"US",
    "sg:address":"12881 Knott St",
    "sg:city":"Garden Grove",
    "sg:classifiers":[
        {
            "category":"Banks & Credit Unions",
            "subcategory":"Financial Services",
            "type":"Services"
        }
    ],
    "sg:phone":"+1 714 893 4965",
    "sg:postcode":"92841",
    "sg:province":"CA",
    "sg:tags":[
        "broker",
        "mortgage"
    ],
    "wof:name":"Mortgage Services",
    "wof:placetype":"venue"
},
  "geometry": {"coordinates":[-118.008003,33.774899],"type":"Point"}
}