{
  "type": "Feature",
  "properties": {
    "iso:country":"US",
    "sg:address":"429 Main St",
    "sg:city":"West Point",
    "sg:classifiers":[
        {
            "category":"Shopping",
            "subcategory":"Hobbies, Toys, & Games",
            "type":"Retail Goods"
        }
    ],
    "sg:phone":"+1 209 293 3440",
    "sg:postcode":"95255",
    "sg:province":"CA",
    "sg:tags":[
        "model",
        "supply"
    ],
    "wof:name":"West Point Hobby Shop",
    "wof:placetype":"venue"
},
  "geometry": {"coordinates":[-120.527143,38.403206],"type":"Point"}
}