{
  "type": "Feature",
  "properties": {
    "addr:full":"102 Joliet Ct El Cajon CA 92019",
    "addr:housenumber":"102",
    "addr:postcode":"92019",
    "addr:street":"Joliet Ct",
    "iso:country":"US",
    "sg:address":"102 Joliet Ct",
    "sg:city":"El Cajon",
    "sg:classifiers":[
        {
            "category":"Building & Trades",
            "subcategory":"Construction",
            "type":"Services"
        }
    ],
    "sg:phone":"+1 619 447 5543",
    "sg:postcode":"92019",
    "sg:province":"CA",
    "sg:tags":[
        "masonry",
        "contractor"
    ],
    "wof:name":"Ace Masonry Co",
    "wof:placetype":"venue"
},
  "geometry": {"coordinates":[-116.931873,32.794507],"type":"Point"}
}