{
  "type": "Feature",
  "properties": {
    "addr:full":"220 10th St San Francisco CA 94103",
    "addr:housenumber":"220",
    "addr:postcode":"94103",
    "addr:street":"10Th St",
    "iso:country":"US",
    "sg:address":"220 10th St",
    "sg:city":"San Francisco",
    "sg:classifiers":[
        {
            "category":"Social Services",
            "type":"Services"
        }
    ],
    "sg:phone":"+1 415 575 4920",
    "sg:postcode":"94103",
    "sg:province":"CA",
    "sg:tags":[
        "organization",
        "welfare"
    ],
    "wof:name":"St Joseph's Village",
    "wof:placetype":"venue"
},
  "geometry": {"coordinates":[-122.414068,37.773761],"type":"Point"}
}