{
  "type": "Feature",
  "properties": {
    "addr:full":"538 W Simpson Ave Fresno CA 93705",
    "addr:housenumber":"538",
    "addr:postcode":"93705",
    "addr:street":"W Simpson Ave",
    "iso:country":"US",
    "sg:address":"538 W Simpson Ave",
    "sg:city":"Fresno",
    "sg:classifiers":[
        {
            "category":"Building & Trades",
            "subcategory":"Construction",
            "type":"Services"
        }
    ],
    "sg:phone":"+1 559 227 0309",
    "sg:postcode":"93705",
    "sg:province":"CA",
    "sg:tags":[
        "fence",
        "contractor"
    ],
    "wof:name":"Zumkeller Fencing",
    "wof:placetype":"venue"
},
  "geometry": {"coordinates":[-119.81944799999999,36.778501],"type":"Point"}
}