{
  "type": "Feature",
  "properties": {
    "iso:country":"US",
    "sg:address":"1848 W Washington Blvd",
    "sg:city":"Los Angeles",
    "sg:classifiers":[
        {
            "category":"Building & Trades",
            "subcategory":"Construction",
            "type":"Services"
        }
    ],
    "sg:phone":"+1 323 734 6416",
    "sg:postcode":"90007",
    "sg:province":"CA",
    "sg:tags":[
        "carpenter"
    ],
    "wof:name":"Felix Castejon Wood Care",
    "wof:placetype":"venue"
},
  "geometry": {"coordinates":[-118.299911,34.039896],"type":"Point"}
}