{
  "type": "Feature",
  "properties": {
    "addr:full":"1224 I St Modesto CA 95354",
    "addr:housenumber":"1224",
    "addr:postcode":"ca 95354",
    "addr:street":"I St",
    "iso:country":"US",
    "sg:address":"1224 I St",
    "sg:city":"Modesto",
    "sg:classifiers":[
        {
            "category":"Education",
            "subcategory":"Special Training",
            "type":"Public Place"
        }
    ],
    "sg:phone":"+1 209 522 0656",
    "sg:postcode":"95354",
    "sg:province":"CA",
    "sg:tags":[
        "reading",
        "instruction",
        "improvement"
    ],
    "sg:website":"www.readnow.org",
    "wof:name":"Stanislaus Literacy Ctr",
    "wof:placetype":"venue"
},
  "geometry": {"coordinates":[-120.996414,37.641468],"type":"Point"}
}