{
  "type": "Feature",
  "properties": {
    "addr:full":"4141 E Belmont Ave Fresno CA 93702",
    "addr:housenumber":"4141",
    "addr:postcode":"93702",
    "addr:street":"E Belmont Ave",
    "iso:country":"US",
    "sg:address":"4141 E Belmont Ave",
    "sg:city":"Fresno",
    "sg:classifiers":[
        {
            "category":"Building & Trades",
            "subcategory":"Equipment Rental",
            "type":"Services"
        }
    ],
    "sg:phone":"+1 559 233 5261",
    "sg:postcode":"93702",
    "sg:province":"CA",
    "sg:tags":[
        "contractor"
    ],
    "sg:website":"www.ur.com",
    "wof:name":"United Rentals",
    "wof:placetype":"venue"
},
  "geometry": {"coordinates":[-119.755183,36.750563],"type":"Point"}
}