{
  "type": "Feature",
  "properties": {
    "addr:full":"3464 Descanso Ave San Marcos CA 92078",
    "addr:housenumber":"3464",
    "addr:postcode":"92078",
    "addr:street":"Descanso Ave",
    "iso:country":"US",
    "sg:address":"3464 Descanso Ave",
    "sg:city":"San Marcos",
    "sg:classifiers":[
        {
            "category":"Building & Trades",
            "subcategory":"Landscaping Services",
            "type":"Services"
        }
    ],
    "sg:phone":"+1 760 580 4500",
    "sg:postcode":"92078",
    "sg:province":"CA",
    "sg:tags":[
        "landscape"
    ],
    "wof:name":"Ramiros Landscape",
    "wof:placetype":"venue"
},
  "geometry": {"coordinates":[-117.202365,33.15034],"type":"Point"}
}