{
  "type": "Feature",
  "properties": {
    "iso:country":"US",
    "sg:address":"3079 Riviera Rd",
    "sg:city":"Gridley",
    "sg:classifiers":[
        {
            "category":"Retail",
            "subcategory":"Veterinary Services",
            "type":"Services"
        }
    ],
    "sg:phone":"+1 530 846 2713",
    "sg:postcode":"95948",
    "sg:province":"CA",
    "wof:name":"Lee Brenda T Dvm",
    "wof:placetype":"venue"
},
  "geometry": {"coordinates":[-121.671245,39.30159],"type":"Point"}
}