{
  "type": "Feature",
  "properties": {
    "addr:full":"27223 Craig Ave Menifee CA 92584",
    "addr:housenumber":"27223",
    "addr:postcode":"92584",
    "addr:street":"Craig Ave",
    "iso:country":"US",
    "sg:address":"27223 Craig Ave",
    "sg:city":"Menifee",
    "sg:classifiers":[
        {
            "category":"Retail",
            "subcategory":"Repair Shop",
            "type":"Services"
        },
        {
            "category":"Professional",
            "subcategory":"Business Services",
            "type":"Services"
        }
    ],
    "sg:phone":"+1 951 679 4343",
    "sg:postcode":"92584",
    "sg:province":"CA",
    "sg:tags":[
        "interior",
        "design",
        "remodeling",
        "upholsterer",
        "contractor"
    ],
    "wof:name":"Lowry's Interiors",
    "wof:placetype":"venue"
},
  "geometry": {"coordinates":[-117.185014,33.663236],"type":"Point"}
}