{
  "type": "Feature",
  "properties": {
    "iso:country":"US",
    "sg:address":"350 N Main St",
    "sg:city":"Fort Bragg",
    "sg:classifiers":[
        {
            "category":"Shopping",
            "subcategory":"Hobbies, Toys, & Games",
            "type":"Retail Goods"
        }
    ],
    "sg:phone":"+1 707 961 5443",
    "sg:postcode":"95437",
    "sg:province":"CA",
    "wof:name":"Spunky Skunk",
    "wof:placetype":"venue"
},
  "geometry": {"coordinates":[-123.805819,39.444836],"type":"Point"}
}