{
  "type": "Feature",
  "properties": {
    "addr:full":"3030 Corvin Dr Santa Clara CA 95051",
    "addr:housenumber":"3030",
    "addr:postcode":"95051",
    "addr:street":"Corvin Dr",
    "iso:country":"US",
    "sg:address":"3030 Corvin Dr",
    "sg:city":"Santa Clara",
    "sg:classifiers":[
        {
            "category":"Utilities",
            "type":"Services"
        }
    ],
    "sg:phone":"+1 408 245 8675",
    "sg:postcode":"95051",
    "sg:province":"CA",
    "sg:tags":[
        "provider",
        "internet"
    ],
    "wof:name":"Terremark Worldwide",
    "wof:placetype":"venue"
},
  "geometry": {"coordinates":[-121.987999,37.376202],"type":"Point"}
}