{
  "type": "Feature",
  "properties": {
    "addr:full":"2041 Market St Oakland CA 94607",
    "addr:housenumber":"2041",
    "addr:postcode":"94607",
    "addr:street":"Market St",
    "iso:country":"US",
    "sg:address":"2041 Market St",
    "sg:city":"Oakland",
    "sg:classifiers":[
        {
            "category":"Real Estate",
            "subcategory":"Real Estate Agent",
            "type":"Services"
        }
    ],
    "sg:phone":"+1 510 238 9532",
    "sg:postcode":"94607",
    "sg:province":"CA",
    "sg:tags":[
        "management"
    ],
    "wof:name":"Duncan's Management",
    "wof:placetype":"venue"
},
  "geometry": {"coordinates":[-122.279495,37.812638],"type":"Point"}
}