{
  "type": "Feature",
  "properties": {
    "addr:full":"10607 Meadow Glen Way E Escondido CA 92026",
    "addr:housenumber":"10607",
    "addr:postcode":"92026",
    "addr:street":"Meadow Glen Way E",
    "iso:country":"US",
    "sg:address":"10607 Meadow Glen Way E",
    "sg:city":"Escondido",
    "sg:classifiers":[
        {
            "category":"Retail",
            "subcategory":"Laundry & Dry Cleaning",
            "type":"Services"
        }
    ],
    "sg:phone":"+1 760 751 8532",
    "sg:postcode":"92026",
    "sg:province":"CA",
    "sg:tags":[
        "cleaners",
        "rug",
        "carpet"
    ],
    "wof:name":"Adams Chem Dry One",
    "wof:placetype":"venue"
},
  "geometry": {"coordinates":[-117.105189,33.21731],"type":"Point"}
}