{
  "type": "Feature",
  "properties": {
    "addr:full":"6795 Flanders Dr San Diego CA 92126",
    "addr:housenumber":"6795",
    "addr:postcode":"92126",
    "addr:street":"Flanders Dr",
    "iso:country":"US",
    "sg:address":"6795 Flanders Dr",
    "sg:city":"San Diego",
    "sg:classifiers":[
        {
            "category":"Manufacturing",
            "subcategory":"Electronics",
            "type":"Manufacturing & Wholesale Goods"
        }
    ],
    "sg:phone":"+1 858 642 2400",
    "sg:postcode":"92126",
    "sg:province":"CA",
    "sg:tags":[
        "equipment",
        "engineering",
        "mfg",
        "communication"
    ],
    "wof:name":"Sensormatic Electronics Corp",
    "wof:placetype":"venue"
},
  "geometry": {"coordinates":[-117.177156,32.9065],"type":"Point"}
}