{
  "type": "Feature",
  "properties": {
    "iso:country":"US",
    "sg:address":"921 11th St Ste 904",
    "sg:city":"Sacramento",
    "sg:classifiers":[
        {
            "category":"Professional",
            "subcategory":"Business Services",
            "type":"Services"
        },
        {
            "category":"Shopping",
            "type":"Retail Goods"
        },
        {
            "category":"Organizations",
            "subcategory":"Non-profit Organization",
            "type":"Services"
        }
    ],
    "sg:phone":"+1 916 441 6855",
    "sg:postcode":"95814",
    "sg:province":"CA",
    "sg:tags":[
        "coach",
        "supply",
        "consultant",
        "fund",
        "games",
        "merchandise",
        "raising"
    ],
    "wof:name":"McKinley Pillows Fund Raising & Events",
    "wof:placetype":"venue"
},
  "geometry": {"coordinates":[-121.491733,38.580831],"type":"Point"}
}