{
  "type": "Feature",
  "properties": {
    "iso:country":"US",
    "sg:address":"15520 Ventura Blvd",
    "sg:city":"Encino",
    "sg:classifiers":[
        {
            "category":"Organizations",
            "subcategory":"Religious Organization",
            "type":"Services"
        }
    ],
    "sg:phone":"+1 818 986 8234",
    "sg:postcode":"91436",
    "sg:province":"CA",
    "sg:tags":[
        "church"
    ],
    "sg:website":"www.stcyril.net",
    "wof:name":"St Cyril Of Jerusalem Church",
    "wof:placetype":"venue"
},
  "geometry": {"coordinates":[-118.474105,34.154988],"type":"Point"}
}