{
  "type": "Feature",
  "properties": {
    "addr:full":"4801 Tiffany Way Fair Oaks CA 95628",
    "addr:housenumber":"4801",
    "addr:postcode":"95628",
    "addr:street":"Tiffany Way",
    "iso:country":"US",
    "sg:address":"4801 Tiffany Way",
    "sg:city":"Fair Oaks",
    "sg:classifiers":[
        {
            "category":"Wholesale",
            "subcategory":"Groceries",
            "type":"Manufacturing & Wholesale Goods"
        }
    ],
    "sg:phone":"+1 916 201 9147",
    "sg:postcode":"95628",
    "sg:province":"CA",
    "sg:tags":[
        "food",
        "product"
    ],
    "wof:name":"All Real",
    "wof:placetype":"venue"
},
  "geometry": {"coordinates":[-121.259958,38.655203],"type":"Point"}
}