{
  "type": "Feature",
  "properties": {
    "iso:country":"US",
    "sg:address":"3210 California Ave",
    "sg:city":"Carmichael",
    "sg:classifiers":[
        {
            "category":"Place Of Worship",
            "subcategory":"Church",
            "type":"Public Place"
        },
        {
            "category":"Place Of Worship",
            "type":"Public Place"
        }
    ],
    "sg:phone":"+1 916 481 2911",
    "sg:postcode":"95608",
    "sg:province":"CA",
    "sg:tags":[
        "churches-baptist-general",
        "churches-baptist-independent",
        "churches-baptist"
    ],
    "sg:website":"http://www.carmichaelbaptist.com",
    "wof:name":"Carmichael Baptist Church",
    "wof:placetype":"venue"
},
  "geometry": {"coordinates":[-121.32145,38.622522],"type":"Point"}
}