{
  "type": "Feature",
  "properties": {
    "addr:full":"4222 Green Valley Rd Rescue CA 95672",
    "addr:housenumber":"4222",
    "addr:postcode":"95672",
    "addr:street":"Green Valley Rd",
    "iso:country":"US",
    "sg:address":"4222 Green Valley Rd",
    "sg:city":"Rescue",
    "sg:classifiers":[
        {
            "category":"Restaurant",
            "type":"Food & Drink"
        }
    ],
    "sg:phone":"+1 530 677 7785",
    "sg:postcode":"95672",
    "sg:province":"CA",
    "wof:name":"Rescue Roadhouse",
    "wof:placetype":"venue"
},
  "geometry": {"coordinates":[-120.951695,38.711511],"type":"Point"}
}