{
  "type": "Feature",
  "properties": {
    "iso:country":"US",
    "sg:address":"1116 Fair Weather Cir",
    "sg:city":"Concord",
    "sg:classifiers":[
        {
            "category":"Professional",
            "subcategory":"Management & Consulting",
            "type":"Services"
        }
    ],
    "sg:phone":"+1 925 671 0404",
    "sg:postcode":"94518",
    "sg:province":"CA",
    "sg:tags":[
        "consultant",
        "business"
    ],
    "wof:name":"Management Advantage Inc",
    "wof:placetype":"venue"
},
  "geometry": {"coordinates":[-122.000118,37.946857],"type":"Point"}
}