{
  "type": "Feature",
  "properties": {
    "iso:country":"US",
    "sg:address":"5814 N Figueroa St",
    "sg:city":"Los Angeles",
    "sg:classifiers":[
        {
            "category":"Shopping",
            "subcategory":"Music",
            "type":"Retail Goods"
        }
    ],
    "sg:phone":"+1 323 257 8135",
    "sg:postcode":"90042",
    "sg:province":"CA",
    "sg:tags":[
        "dvd's"
    ],
    "wof:name":"CD's Y Acessorios Ashley",
    "wof:placetype":"venue"
},
  "geometry": {"coordinates":[-118.191422,34.110114],"type":"Point"}
}