{
  "type": "Feature",
  "properties": {
    "addr:full":"200 Couch St Vallejo CA 94590",
    "addr:housenumber":"200",
    "addr:postcode":"94590",
    "addr:street":"Couch St",
    "iso:country":"US",
    "sg:address":"200 Couch St",
    "sg:city":"Vallejo",
    "sg:phone":"+1 800 777 0133",
    "sg:postcode":"94590",
    "sg:province":"CA",
    "sg:website":"http://www.dmv.ca.gov",
    "wof:name":"California Department of Motor Vehicles - DMV",
    "wof:placetype":"venue"
},
  "geometry": {"coordinates":[-122.252762,38.11692],"type":"Point"}
}