{
  "type": "Feature",
  "properties": {
    "addr:full":"186 Lake Dr San Bruno CA 94066",
    "addr:housenumber":"186",
    "addr:postcode":"94066",
    "addr:street":"Lake Dr",
    "iso:country":"US",
    "sg:address":"186 Lake Dr",
    "sg:city":"San Bruno",
    "sg:classifiers":[
        {
            "category":"Building & Trades",
            "subcategory":"Construction",
            "type":"Services"
        }
    ],
    "sg:phone":"+1 650 873 4332",
    "sg:postcode":"94066",
    "sg:province":"CA",
    "sg:tags":[
        "contractor"
    ],
    "sg:website":"www.blahblahwoofwoof.com",
    "wof:name":"Blah Blah WOOF WOOF",
    "wof:placetype":"venue"
},
  "geometry": {"coordinates":[-122.45128800000001,37.619422],"type":"Point"}
}