{
  "type": "Feature",
  "properties": {
    "addr:full":"814 W Arrow Hwy San Dimas CA 91773",
    "addr:housenumber":"814",
    "addr:postcode":"91773",
    "addr:street":"W Arrow Hwy",
    "iso:country":"US",
    "sg:address":"814 W Arrow Hwy",
    "sg:city":"San Dimas",
    "sg:classifiers":[
        {
            "category":"Food & Beverages",
            "subcategory":"Fruits & Vegetables",
            "type":"Retail Goods"
        }
    ],
    "sg:phone":"+1 909 592 1984",
    "sg:postcode":"91773",
    "sg:province":"CA",
    "sg:tags":[
        "juice"
    ],
    "wof:name":"Feelin Juicy",
    "wof:placetype":"venue"
},
  "geometry": {"coordinates":[-117.823093,34.106547],"type":"Point"}
}