{
  "type": "Feature",
  "properties": {
    "iso:country":"US",
    "sg:address":"704 N Glassell St",
    "sg:city":"Orange",
    "sg:classifiers":[
        {
            "category":"Social Services",
            "type":"Services"
        }
    ],
    "sg:phone":"+1 760 947 4220",
    "sg:postcode":"92867",
    "sg:province":"CA",
    "wof:name":"Lutheran Social Services",
    "wof:placetype":"venue"
},
  "geometry": {"coordinates":[-117.85314700000001,33.798447],"type":"Point"}
}