{
  "type": "Feature",
  "properties": {
    "addr:full":"1331 7th St Berkeley CA 94710",
    "addr:housenumber":"1331",
    "addr:postcode":"94710",
    "addr:street":"7Th St",
    "iso:country":"US",
    "sg:address":"1331 7th St",
    "sg:city":"Berkeley",
    "sg:classifiers":[
        {
            "category":"Manufacturing",
            "subcategory":"Apparel",
            "type":"Manufacturing & Wholesale Goods"
        }
    ],
    "sg:phone":"+1 510 525 3360",
    "sg:postcode":"94710",
    "sg:province":"CA",
    "sg:tags":[
        "work",
        "clothing-wholesale",
        "manufacturer"
    ],
    "wof:name":"Glasshouse",
    "wof:placetype":"venue"
},
  "geometry": {"coordinates":[-122.3001,37.879053],"type":"Point"}
}