{
  "type": "Feature",
  "properties": {
    "iso:country":"US",
    "sg:address":"1450 McCoy Ln",
    "sg:city":"Santa Maria",
    "sg:classifiers":[
        {
            "category":"Wholesale",
            "subcategory":"Machinery & Supplies",
            "type":"Manufacturing & Wholesale Goods"
        }
    ],
    "sg:phone":"+1 805 925 9516",
    "sg:postcode":"93455",
    "sg:province":"CA",
    "sg:tags":[
        "bearing",
        "industrial"
    ],
    "wof:name":"Kaman Industrial Tech Corp",
    "wof:placetype":"venue"
},
  "geometry": {"coordinates":[-120.461871,34.915883],"type":"Point"}
}