{
  "type": "Feature",
  "properties": {
    "addr:full":"119 S Orange St Glendale CA 91204",
    "addr:housenumber":"119",
    "addr:postcode":"91204",
    "addr:street":"S Orange St",
    "iso:country":"US",
    "sg:address":"119 S Orange St",
    "sg:city":"Glendale",
    "sg:classifiers":[
        {
            "category":"Personal",
            "subcategory":"Massage",
            "type":"Services"
        }
    ],
    "sg:phone":"+1 818 242 4039",
    "sg:postcode":"91204",
    "sg:province":"CA",
    "wof:name":"California Blondes Plus",
    "wof:placetype":"venue"
},
  "geometry": {"coordinates":[-118.256377,34.146241],"type":"Point"}
}