{
  "type": "Feature",
  "properties": {
    "iso:country":"US",
    "sg:address":"1093 45th St",
    "sg:city":"Emeryville",
    "sg:classifiers":[
        {
            "category":"Building & Trades",
            "subcategory":"Construction",
            "type":"Services"
        }
    ],
    "sg:phone":"+1 510 595 7261",
    "sg:postcode":"94608",
    "sg:province":"CA",
    "sg:tags":[
        "contractor"
    ],
    "wof:name":"Ascential Roofing Co",
    "wof:placetype":"venue"
},
  "geometry": {"coordinates":[-122.279921,37.834743],"type":"Point"}
}