{
  "type": "Feature",
  "properties": {
    "addr:full":"790 Clovis Ave Clovis CA 93612",
    "addr:housenumber":"790",
    "addr:postcode":"93612",
    "addr:street":"Clovis Ave",
    "iso:country":"US",
    "sg:address":"790 Clovis Ave",
    "sg:city":"Clovis",
    "sg:classifiers":[
        {
            "category":"Autos & Motor Vehicles",
            "subcategory":"Auto Supplies",
            "type":"Retail Goods"
        },
        {
            "category":"Retail",
            "subcategory":"Auto Repair",
            "type":"Services"
        }
    ],
    "sg:phone":"+1 559 323 0157",
    "sg:postcode":"93612",
    "sg:province":"CA",
    "sg:tags":[
        "lube",
        "oil",
        "tire"
    ],
    "sg:website":"http://www.firestonecompleteautocare.com/?s_kwcid=IYP_NTL",
    "wof:name":"Firestone Complete Auto Care Store",
    "wof:placetype":"venue"
},
  "geometry": {"coordinates":[-119.70069100000001,36.82082],"type":"Point"}
}