{
  "type": "Feature",
  "properties": {
    "addr:full":"9006 Barbaresco Cir Stockton CA 95212",
    "addr:housenumber":"9006",
    "addr:postcode":"95212",
    "addr:street":"Barbaresco Cir",
    "iso:country":"US",
    "sg:address":"9006 Barbaresco Cir",
    "sg:city":"Stockton",
    "sg:classifiers":[
        {
            "category":"Building & Trades",
            "subcategory":"Construction",
            "type":"Services"
        }
    ],
    "sg:phone":"+1 209 954 9662",
    "sg:postcode":"95212",
    "sg:province":"CA",
    "sg:tags":[
        "home",
        "builder"
    ],
    "wof:name":"California Homes",
    "wof:placetype":"venue"
},
  "geometry": {"coordinates":[-121.265246,38.032504],"type":"Point"}
}