{
  "type": "Feature",
  "properties": {
    "addr:full":"902 W Hobsonway Blythe CA 92225",
    "addr:housenumber":"902",
    "addr:postcode":"92225",
    "addr:street":"W Hobsonway",
    "iso:country":"US",
    "sg:address":"902 W Hobsonway",
    "sg:city":"Blythe",
    "sg:classifiers":[
        {
            "category":"Restaurant",
            "type":"Food & Drink"
        }
    ],
    "sg:phone":"+1 760 921 2174",
    "sg:postcode":"92225",
    "sg:province":"CA",
    "wof:name":"El Ranchito Restaurant",
    "wof:placetype":"venue"
},
  "geometry": {"coordinates":[-114.6066,33.610115],"type":"Point"}
}