{
  "type": "Feature",
  "properties": {
    "iso:country":"US",
    "sg:address":"410 W Central Ave Ste 207",
    "sg:city":"Brea",
    "sg:phone":"+1 714 529 5674",
    "sg:postcode":"92821",
    "sg:province":"CA",
    "wof:name":"Cerni Mary",
    "wof:placetype":"venue"
},
  "geometry": {"coordinates":[-117.902798,33.931979],"type":"Point"}
}