{
  "type": "Feature",
  "properties": {
    "iso:country":"US",
    "sg:address":"1601 Placentia Avenue",
    "sg:city":"Costa Mesa",
    "sg:classifiers":[
        {
            "category":"Retail",
            "subcategory":"Auto Repair",
            "type":"Services"
        }
    ],
    "sg:phone":"+1 949 646 4238",
    "sg:postcode":"92627",
    "sg:province":"CA",
    "sg:website":"www.bandfautoair.com",
    "wof:name":"B & F Auto Air Conditioning",
    "wof:placetype":"venue"
},
  "geometry": {"coordinates":[-117.932011,33.632867],"type":"Point"}
}