{
  "type": "Feature",
  "properties": {
    "iso:country":"US",
    "sg:address":"167 Commercial St",
    "sg:city":"Sunnyvale",
    "sg:classifiers":[
        {
            "category":"Building & Trades",
            "subcategory":"Construction",
            "type":"Services"
        },
        {
            "category":"Building & Trades",
            "subcategory":"Electrical",
            "type":"Services"
        }
    ],
    "sg:phone":"+1 888 657 6527",
    "sg:postcode":"94086",
    "sg:province":"CA",
    "sg:tags":[
        "installation",
        "electrician",
        "solar"
    ],
    "sg:website":"www.recsolar.com",
    "wof:name":"REC Solar",
    "wof:placetype":"venue"
},
  "geometry": {"coordinates":[-122.00859,37.375509],"type":"Point"}
}