{
  "type": "Feature",
  "properties": {
    "addr:full":"2150 Shattuck Ave Ste 920 Berkeley CA 94704",
    "addr:housenumber":"2150",
    "addr:postcode":"94704",
    "addr:street":"Shattuck Ave Ste 920",
    "iso:country":"US",
    "sg:address":"2150 Shattuck Ave Ste 920",
    "sg:city":"Berkeley",
    "sg:classifiers":[
        {
            "category":"Professional",
            "subcategory":"Research",
            "type":"Services"
        }
    ],
    "sg:phone":"+1 510 665 1890",
    "sg:postcode":"94704",
    "sg:province":"CA",
    "sg:tags":[
        "educational"
    ],
    "wof:name":"Japan Society For Promotion Of Science",
    "wof:placetype":"venue"
},
  "geometry": {"coordinates":[-122.267899,37.870319],"type":"Point"}
}