{
  "type": "Feature",
  "properties": {
    "addr:full":"8827 W Olympic Blvd Beverly Hills CA 90211",
    "addr:housenumber":"8827",
    "addr:postcode":"90211",
    "addr:street":"W Olympic Blvd",
    "iso:country":"US",
    "sg:address":"8827 W Olympic Blvd",
    "sg:city":"Beverly Hills",
    "sg:classifiers":[
        {
            "category":"Manufacturing",
            "subcategory":"Printing",
            "type":"Manufacturing & Wholesale Goods"
        }
    ],
    "sg:phone":"+1 310 855 0007",
    "sg:postcode":"90211",
    "sg:province":"CA",
    "sg:tags":[
        "printer"
    ],
    "sg:website":"www.designprintingla.com",
    "wof:name":"Design Printing",
    "wof:placetype":"venue"
},
  "geometry": {"coordinates":[-118.38408699999999,34.059374],"type":"Point"}
}