{
  "type": "Feature",
  "properties": {
    "addr:full":"546 Stevens Ave Solana Beach CA 92075",
    "addr:housenumber":"546",
    "addr:postcode":"92075",
    "addr:street":"Stevens Ave",
    "iso:country":"US",
    "sg:address":"546 Stevens Ave",
    "sg:city":"Solana Beach",
    "sg:classifiers":[
        {
            "category":"Shopping",
            "type":"Retail Goods"
        }
    ],
    "sg:phone":"+1 858 793 1696",
    "sg:postcode":"92075",
    "sg:province":"CA",
    "sg:tags":[
        "stamp",
        "wholesale",
        "collector",
        "for"
    ],
    "wof:name":"Dana Okey Enterprises",
    "wof:placetype":"venue"
},
  "geometry": {"coordinates":[-117.261287,32.991185],"type":"Point"}
}