{
  "type": "Feature",
  "properties": {
    "addr:full":"7007 Friars Rd Ste 811 San Diego CA 92108",
    "addr:housenumber":"7007",
    "addr:postcode":"92108",
    "addr:street":"Friars Rd Ste 811",
    "iso:country":"US",
    "sg:address":"7007 Friars Rd Ste 811",
    "sg:city":"San Diego",
    "sg:classifiers":[
        {
            "category":"Wholesale",
            "subcategory":"Stationery",
            "type":"Manufacturing & Wholesale Goods"
        }
    ],
    "sg:phone":"+1 619 542 1192",
    "sg:postcode":"92108",
    "sg:province":"CA",
    "sg:tags":[
        "card"
    ],
    "wof:name":"Papyrus",
    "wof:placetype":"venue"
},
  "geometry": {"coordinates":[-117.13400300000001,32.778801],"type":"Point"}
}