{
  "type": "Feature",
  "properties": {
    "addr:full":"37444 Sycamore St Newark CA 94560",
    "addr:housenumber":"37444",
    "addr:postcode":"94560",
    "addr:street":"Sycamore St",
    "iso:country":"US",
    "sg:address":"37444 Sycamore St",
    "sg:city":"Newark",
    "sg:classifiers":[
        {
            "category":"Manufacturing",
            "subcategory":"Building Materials",
            "type":"Manufacturing & Wholesale Goods"
        }
    ],
    "sg:phone":"+1 510 791 6100",
    "sg:postcode":"94560",
    "sg:province":"CA",
    "wof:name":"B & D Custom Milling",
    "wof:placetype":"venue"
},
  "geometry": {"coordinates":[-122.032251,37.527057],"type":"Point"}
}