{
  "type": "Feature",
  "properties": {
    "iso:country":"US",
    "sg:address":"165 Phillip Rd",
    "sg:city":"Redwood City",
    "sg:classifiers":[
        {
            "category":"Farming",
            "subcategory":"Livestock Farm",
            "type":"Manufacturing & Wholesale Goods"
        }
    ],
    "sg:phone":"+1 650 851 2665",
    "sg:postcode":"94062",
    "sg:province":"CA",
    "sg:tags":[
        "animal",
        "general"
    ],
    "wof:name":"Broken River Ranch LP",
    "wof:placetype":"venue"
},
  "geometry": {"coordinates":[-122.251462,37.403062],"type":"Point"}
}