{
  "type": "Feature",
  "properties": {
    "addr:full":"355 Main St Vacaville CA 95688",
    "addr:housenumber":"355",
    "addr:postcode":"95688",
    "addr:street":"Main St",
    "iso:country":"US",
    "sg:address":"355 Main St",
    "sg:city":"Vacaville",
    "sg:classifiers":[
        {
            "category":"Real Estate",
            "subcategory":"Real Estate Agent",
            "type":"Services"
        }
    ],
    "sg:phone":"+1 707 446 0600",
    "sg:postcode":"95688",
    "sg:province":"CA",
    "sg:tags":[
        "insurance"
    ],
    "sg:website":"http://www.kappels.com",
    "wof:name":"Kappel & Kappel Inc.",
    "wof:placetype":"venue"
},
  "geometry": {"coordinates":[-121.989225,38.356635],"type":"Point"}
}