{
  "type": "Feature",
  "properties": {
    "iso:country":"US",
    "sg:address":"767 Jamacha Rd",
    "sg:city":"El Cajon",
    "sg:classifiers":[
        {
            "category":"Health Services",
            "subcategory":"Doctor",
            "type":"Services"
        }
    ],
    "sg:phone":"+1 619 579 9901",
    "sg:postcode":"92019",
    "sg:province":"CA",
    "sg:tags":[
        "dentist"
    ],
    "wof:name":"Christopher Kleber DDS",
    "wof:placetype":"venue"
},
  "geometry": {"coordinates":[-116.927844,32.78691],"type":"Point"}
}