{
  "type": "Feature",
  "properties": {
    "iso:country":"US",
    "sg:address":"995 Widgeon Ln",
    "sg:city":"Chula Vista",
    "sg:classifiers":[
        {
            "category":"Professional",
            "type":"Services"
        }
    ],
    "sg:phone":"+1 619 422 2108",
    "sg:postcode":"91911",
    "sg:province":"CA",
    "wof:name":"X Dimension Inc",
    "wof:placetype":"venue"
},
  "geometry": {"coordinates":[-117.075466,32.616273],"type":"Point"}
}