{
  "type": "Feature",
  "properties": {
    "addr:full":"3121 W March Ln Stockton CA 95219",
    "addr:housenumber":"3121",
    "addr:postcode":"95219",
    "addr:street":"W March Ln",
    "iso:country":"US",
    "sg:address":"3121 W March Ln",
    "sg:city":"Stockton",
    "sg:classifiers":[
        {
            "category":"Restaurant",
            "type":"Food & Drink"
        }
    ],
    "sg:phone":"+1 209 476 4600",
    "sg:postcode":"95219",
    "sg:province":"CA",
    "wof:name":"Jack In The Box",
    "wof:placetype":"venue"
},
  "geometry": {"coordinates":[-121.35189699999999,37.984092],"type":"Point"}
}