{
  "type": "Feature",
  "properties": {
    "iso:country":"US",
    "sg:address":"2121 Saint Francis Dr",
    "sg:city":"Palo Alto",
    "sg:classifiers":[
        {
            "category":"Food & Beverages",
            "subcategory":"Liquor & Beverages",
            "type":"Retail Goods"
        }
    ],
    "sg:phone":"+1 650 856 0242",
    "sg:postcode":"94303",
    "sg:province":"CA",
    "sg:tags":[
        "wine"
    ],
    "wof:name":"Century Liquors",
    "wof:placetype":"venue"
},
  "geometry": {"coordinates":[-122.126535,37.447195],"type":"Point"}
}