{
  "type": "Feature",
  "properties": {
    "iso:country":"US",
    "sg:address":"8765 Washington Blvd",
    "sg:city":"Culver City",
    "sg:classifiers":[
        {
            "category":"Professional",
            "subcategory":"Art Services",
            "type":"Services"
        }
    ],
    "sg:phone":"+1 323 937 2300",
    "sg:postcode":"90232",
    "sg:province":"CA",
    "sg:tags":[
        "photographer"
    ],
    "wof:name":"Trevor Pearson Photography",
    "wof:placetype":"venue"
},
  "geometry": {"coordinates":[-118.386537,34.028264],"type":"Point"}
}