{
  "type": "Feature",
  "properties": {
    "addr:full":"437 W Shields Ave Fresno CA 93705",
    "addr:housenumber":"437",
    "addr:postcode":"93705",
    "addr:street":"W Shields Ave",
    "iso:country":"US",
    "sg:address":"437 W Shields Ave",
    "sg:city":"Fresno",
    "sg:classifiers":[
        {
            "category":"Restaurant",
            "type":"Food & Drink"
        }
    ],
    "sg:phone":"+1 559 224 9008",
    "sg:postcode":"93705",
    "sg:province":"CA",
    "sg:tags":[
        "asian",
        "chinese",
        "pan"
    ],
    "wof:name":"Yu Bing Liang",
    "wof:placetype":"venue"
},
  "geometry": {"coordinates":[-119.816816,36.779327],"type":"Point"}
}