{
  "type": "Feature",
  "properties": {
    "iso:country":"US",
    "sg:address":"4380 W Shaw Ave",
    "sg:city":"Fresno",
    "sg:classifiers":[
        {
            "category":"Food & Beverages",
            "subcategory":"Liquor & Beverages",
            "type":"Retail Goods"
        }
    ],
    "sg:phone":"+1 559 275 0106",
    "sg:postcode":"93722",
    "sg:province":"CA",
    "wof:name":"Shaw Liquor Deli",
    "wof:placetype":"venue"
},
  "geometry": {"coordinates":[-119.870524,36.808325],"type":"Point"}
}