{
  "type": "Feature",
  "properties": {
    "iso:country":"US",
    "sg:address":"44091 Nobel Dr",
    "sg:city":"Fremont",
    "sg:classifiers":[
        {
            "category":"Wholesale",
            "subcategory":"Office Equipment",
            "type":"Manufacturing & Wholesale Goods"
        }
    ],
    "sg:phone":"+1 510 897 4150",
    "sg:postcode":"94538",
    "sg:province":"CA",
    "sg:tags":[
        "furniture"
    ],
    "wof:name":"Global The Total Office",
    "wof:placetype":"venue"
},
  "geometry": {"coordinates":[-121.97970100000001,37.4974],"type":"Point"}
}