{
  "type": "Feature",
  "properties": {
    "iso:country":"US",
    "sg:address":"5605 el Cajon Blvd",
    "sg:city":"San Diego",
    "sg:classifiers":[
        {
            "category":"Health Services",
            "subcategory":"Hospital",
            "type":"Services"
        }
    ],
    "sg:phone":"+1 619 229 8201",
    "sg:postcode":"92115",
    "sg:province":"CA",
    "sg:tags":[
        "specialty"
    ],
    "wof:name":"Options For Recovery Central",
    "wof:placetype":"venue"
},
  "geometry": {"coordinates":[-117.073728,32.758544],"type":"Point"}
}