{
  "type": "Feature",
  "properties": {
    "addr:full":"111 Healdsburg Ave Healdsburg CA 95448",
    "addr:housenumber":"111",
    "addr:postcode":"95448",
    "addr:street":"Healdsburg Ave",
    "iso:country":"US",
    "sg:address":"111 Healdsburg Ave",
    "sg:city":"Healdsburg",
    "sg:classifiers":[
        {
            "category":"Restaurant",
            "type":"Food & Drink"
        }
    ],
    "sg:menulink":"http://www.allmenus.com/ca/healdsburg/197881-kfc---kentucky-fried-chicken/menu/",
    "sg:phone":"+1 707 433 0726",
    "sg:postcode":"95448",
    "sg:province":"CA",
    "sg:tags":[
        "american",
        "chicken"
    ],
    "wof:name":"KFC - Kentucky Fried Chicken",
    "wof:placetype":"venue"
},
  "geometry": {"coordinates":[-122.868521,38.605035],"type":"Point"}
}