{
  "type": "Feature",
  "properties": {
    "addr:full":"343 Monterey Rd Pacifica CA 94044",
    "addr:housenumber":"343",
    "addr:postcode":"94044",
    "addr:street":"Monterey Rd",
    "iso:country":"US",
    "sg:address":"343 Monterey Rd",
    "sg:city":"Pacifica",
    "sg:classifiers":[
        {
            "category":"Local Transit",
            "type":"Transportation"
        }
    ],
    "sg:phone":"+1 650 359 8128",
    "sg:postcode":"94044",
    "sg:province":"CA",
    "sg:tags":[
        "limousine"
    ],
    "wof:name":"Red Roses Limousine Svc",
    "wof:placetype":"venue"
},
  "geometry": {"coordinates":[-122.48652199999999,37.651541],"type":"Point"}
}