{
  "type": "Feature",
  "properties": {
    "addr:full":"3344 State St Santa Barbara CA 93105",
    "addr:housenumber":"3344",
    "addr:postcode":"93105",
    "addr:street":"State St",
    "iso:country":"US",
    "sg:address":"3344 State St",
    "sg:city":"Santa Barbara",
    "sg:classifiers":[
        {
            "category":"Travel",
            "subcategory":"Hotels & Motels",
            "type":"Entertainment"
        }
    ],
    "sg:phone":"+1 805 687 6611",
    "sg:postcode":"93105",
    "sg:province":"CA",
    "sg:tags":[
        "breakfast",
        "accommodation",
        "bed"
    ],
    "sg:website":"www.sanroque.com",
    "wof:name":"San Roque Motel",
    "wof:placetype":"venue"
},
  "geometry": {"coordinates":[-119.73562200000001,34.440467],"type":"Point"}
}