{
  "type": "Feature",
  "properties": {
    "iso:country":"US",
    "sg:address":"5026 Fruitridge Rd",
    "sg:city":"Sacramento",
    "sg:classifiers":[
        {
            "category":"Health Services",
            "subcategory":"Doctor",
            "type":"Services"
        }
    ],
    "sg:phone":"+1 916 391 9497",
    "sg:postcode":"95820",
    "sg:province":"CA",
    "sg:tags":[
        "physician",
        "surgeon"
    ],
    "wof:name":"Anh Huynh Nguyen MD",
    "wof:placetype":"venue"
},
  "geometry": {"coordinates":[-121.446958,38.52486],"type":"Point"}
}