{
  "type": "Feature",
  "properties": {
    "addr:full":"32900 Riverside Dr Lake Elsinore CA 92530",
    "addr:housenumber":"32900",
    "addr:postcode":"92530",
    "addr:street":"Riverside Dr",
    "iso:country":"US",
    "sg:address":"32900 Riverside Dr",
    "sg:city":"Lake Elsinore",
    "sg:classifiers":[
        {
            "category":"Real Estate",
            "subcategory":"Real Estate Operator",
            "type":"Services"
        }
    ],
    "sg:phone":"+1 951 678 3302",
    "sg:postcode":"92530",
    "sg:province":"CA",
    "sg:tags":[
        "mobile",
        "home",
        "community"
    ],
    "wof:name":"Butterfield Village Mobile Hm",
    "wof:placetype":"venue"
},
  "geometry": {"coordinates":[-117.382105,33.667203],"type":"Point"}
}