{
  "type": "Feature",
  "properties": {
    "addr:full":"15229 Moorpark St Sherman Oaks CA 91403",
    "addr:housenumber":"15229",
    "addr:postcode":"91403",
    "addr:street":"Moorpark St",
    "iso:country":"US",
    "sg:address":"15229 Moorpark St",
    "sg:city":"Sherman Oaks",
    "sg:classifiers":[
        {
            "category":"Education",
            "subcategory":"Special Training",
            "type":"Public Place"
        }
    ],
    "sg:phone":"+1 818 419 2376",
    "sg:postcode":"91403",
    "sg:province":"CA",
    "sg:tags":[
        "tutoring"
    ],
    "wof:name":"Academic Achievement Team",
    "wof:placetype":"venue"
},
  "geometry": {"coordinates":[-118.46417700000001,34.154513],"type":"Point"}
}