{
  "type": "Feature",
  "properties": {
    "iso:country":"US",
    "sg:address":"5524 Cahuenga Blvd",
    "sg:city":"North Hollywood",
    "sg:classifiers":[
        {
            "category":"Shopping",
            "subcategory":"Florist",
            "type":"Retail Goods"
        }
    ],
    "sg:phone":"+1 818 763 4818",
    "sg:postcode":"91601",
    "sg:province":"CA",
    "wof:name":"Studio Stems",
    "wof:placetype":"venue"
},
  "geometry": {"coordinates":[-118.361479,34.171626],"type":"Point"}
}