{
  "type": "Feature",
  "properties": {
    "iso:country":"US",
    "sg:address":"21730 S Vermont Ave Ste 131",
    "sg:city":"Torrance",
    "sg:classifiers":[
        {
            "category":"Health Services",
            "subcategory":"Doctor",
            "type":"Services"
        },
        {
            "category":"Health Services",
            "subcategory":"Hospital",
            "type":"Services"
        }
    ],
    "sg:phone":"+1 310 606 3877",
    "sg:postcode":"90502",
    "sg:province":"CA",
    "sg:tags":[
        "urgent",
        "care"
    ],
    "sg:website":"www.accesahealth.com",
    "wof:name":"Accesa Health",
    "wof:placetype":"venue"
},
  "geometry": {"coordinates":[-118.289654,33.830491],"type":"Point"}
}