{
  "type": "Feature",
  "properties": {
    "iso:country":"US",
    "sg:address":"311 Washington Blvd",
    "sg:city":"Marina Del Rey",
    "sg:classifiers":[
        {
            "category":"Restaurant",
            "type":"Food & Drink"
        }
    ],
    "sg:phone":"+1 310 821 2252",
    "sg:postcode":"90292",
    "sg:province":"CA",
    "sg:tags":[
        "mexican"
    ],
    "sg:website":"www.bajacantinavenice.com",
    "wof:name":"Baja Cantina",
    "wof:placetype":"venue"
},
  "geometry": {"coordinates":[-118.464721,33.980258],"type":"Point"}
}