{
  "type": "Feature",
  "properties": {
    "iso:country":"US",
    "sg:address":"852 Richmond Ave",
    "sg:city":"Oxnard",
    "sg:classifiers":[
        {
            "category":"Manufacturing",
            "subcategory":"Wood Products",
            "type":"Manufacturing & Wholesale Goods"
        }
    ],
    "sg:phone":"+1 805 385 0095",
    "sg:postcode":"93030",
    "sg:province":"CA",
    "sg:tags":[
        "mfg"
    ],
    "wof:name":"Alco Pallets",
    "wof:placetype":"venue"
},
  "geometry": {"coordinates":[-119.168788,34.19053],"type":"Point"}
}