{
  "type": "Feature",
  "properties": {
    "iso:country":"US",
    "sg:address":"14095 Bronte Dr",
    "sg:city":"Whittier",
    "sg:classifiers":[
        {
            "category":"Shopping",
            "subcategory":"Gifts & Souvenirs",
            "type":"Retail Goods"
        }
    ],
    "sg:phone":"+1 562 696 5082",
    "sg:postcode":"90602",
    "sg:province":"CA",
    "wof:name":"Lydia Law",
    "wof:placetype":"venue"
},
  "geometry": {"coordinates":[-118.018233,33.971285],"type":"Point"}
}