{
  "type": "Feature",
  "properties": {
    "addr:full":"133 N Valencia Blvd Woodlake CA 93286",
    "addr:housenumber":"133",
    "addr:postcode":"93286",
    "addr:street":"N Valencia Blvd",
    "iso:country":"US",
    "sg:address":"133 N Valencia Blvd",
    "sg:city":"Woodlake",
    "sg:classifiers":[
        {
            "category":"Food & Beverages",
            "subcategory":"Groceries & Convenience Stores",
            "type":"Retail Goods"
        }
    ],
    "sg:phone":"+1 559 564 8206",
    "sg:postcode":"93286",
    "sg:province":"CA",
    "sg:tags":[
        "grocer"
    ],
    "wof:name":"Lara's Market",
    "wof:placetype":"venue"
},
  "geometry": {"coordinates":[-119.09901499999999,36.41419],"type":"Point"}
}