{
  "type": "Feature",
  "properties": {
    "iso:country":"US",
    "sg:address":"74063 Hwy 111",
    "sg:city":"Palm Desert",
    "sg:classifiers":[
        {
            "category":"Restaurant",
            "type":"Food & Drink"
        }
    ],
    "sg:phone":"+1 760 568 1315",
    "sg:postcode":"92260",
    "sg:province":"CA",
    "sg:website":"www.jovannas.net",
    "wof:name":"Jovanna's Bistro Grill",
    "wof:placetype":"venue"
},
  "geometry": {"coordinates":[-116.371928,33.721229],"type":"Point"}
}