{
  "type": "Feature",
  "properties": {
    "addr:full":"350 Crenshaw Blvd Torrance CA 90503",
    "addr:housenumber":"350",
    "addr:postcode":"90503",
    "addr:street":"Crenshaw Blvd",
    "iso:country":"US",
    "sg:address":"350 Crenshaw Blvd",
    "sg:city":"Torrance",
    "sg:classifiers":[
        {
            "category":"Freight",
            "type":"Transportation"
        }
    ],
    "sg:phone":"+1 310 212 5569",
    "sg:postcode":"90503",
    "sg:province":"CA",
    "sg:tags":[
        "arrangement"
    ],
    "wof:name":"D C S Line  Inc",
    "wof:placetype":"venue"
},
  "geometry": {"coordinates":[-118.328669,33.846459],"type":"Point"}
}