{
  "type": "Feature",
  "properties": {
    "addr:full":"1275 3rd Ave San Francisco CA 94122",
    "addr:housenumber":"1275",
    "addr:postcode":"94122",
    "addr:street":"3Rd Ave",
    "iso:country":"US",
    "sg:address":"1275 3rd Ave",
    "sg:city":"San Francisco",
    "sg:classifiers":[
        {
            "category":"Health Services",
            "subcategory":"Health Practitioner",
            "type":"Services"
        }
    ],
    "sg:phone":"+1 415 681 2266",
    "sg:postcode":"94122",
    "sg:province":"CA",
    "sg:tags":[
        "therapist",
        "physical"
    ],
    "wof:name":"Margaret P Schubert",
    "wof:placetype":"venue"
},
  "geometry": {"coordinates":[-122.45998899999999,37.764784],"type":"Point"}
}