{
  "type": "Feature",
  "properties": {
    "addr:full":"424 Jones St San Francisco CA 94102",
    "addr:housenumber":"424",
    "addr:postcode":"94102",
    "addr:street":"Jones St",
    "iso:country":"US",
    "sg:address":"424 Jones St",
    "sg:city":"San Francisco",
    "sg:classifiers":[
        {
            "category":"Professional",
            "type":"Services"
        }
    ],
    "sg:phone":"+1 415 567 6457",
    "sg:postcode":"94102",
    "sg:province":"CA",
    "wof:name":"Bayeyes",
    "wof:placetype":"venue"
},
  "geometry": {"coordinates":[-122.412762,37.785099],"type":"Point"}
}