{
  "type": "Feature",
  "properties": {
    "addr:full":"147 Clement St San Francisco CA 94118",
    "addr:housenumber":"147",
    "addr:postcode":"94118",
    "addr:street":"Clement St",
    "iso:country":"US",
    "sg:address":"147 Clement St",
    "sg:city":"San Francisco",
    "sg:classifiers":[
        {
            "category":"Arts & Performance",
            "subcategory":"Art Gallery",
            "type":"Entertainment"
        },
        {
            "category":"Home & Garden",
            "subcategory":"Home Furnishings",
            "type":"Retail Goods"
        }
    ],
    "sg:phone":"+1 415 752 2140",
    "sg:postcode":"94118",
    "sg:province":"CA",
    "sg:tags":[
        "decor"
    ],
    "sg:website":"www.kumquatart.com",
    "wof:name":"Kumquat Art & Home",
    "wof:placetype":"venue"
},
  "geometry": {"coordinates":[-122.46096799999999,37.783128],"type":"Point"}
}