{
  "type": "Feature",
  "properties": {
    "iso:country":"US",
    "sg:address":"1666 Garnet Ave Ste 222",
    "sg:city":"San Diego",
    "sg:classifiers":[
        {
            "category":"Communications",
            "subcategory":"Newspaper",
            "type":"Services"
        }
    ],
    "sg:phone":"+1 888 828 4323",
    "sg:postcode":"92109",
    "sg:province":"CA",
    "sg:tags":[
        "advertising"
    ],
    "wof:name":"Avid Advertising",
    "wof:placetype":"venue"
},
  "geometry": {"coordinates":[-117.239498,32.800107],"type":"Point"}
}