{
  "type": "Feature",
  "properties": {
    "iso:country":"US",
    "sg:address":"1670 Alhambra Ln",
    "sg:city":"Oakland",
    "sg:classifiers":[
        {
            "category":"Building & Trades",
            "subcategory":"Landscaping Services",
            "type":"Services"
        }
    ],
    "sg:phone":"+1 510 482 3236",
    "sg:postcode":"94611",
    "sg:province":"CA",
    "wof:name":"Roots N Shoots Landscaping",
    "wof:placetype":"venue"
},
  "geometry": {"coordinates":[-122.21088,37.836375],"type":"Point"}
}