{
  "type": "Feature",
  "properties": {
    "addr:full":"21341 Falkirk Ln Lake Forest CA 92630",
    "addr:housenumber":"21341",
    "addr:postcode":"92630",
    "addr:street":"Falkirk Ln",
    "iso:country":"US",
    "sg:address":"21341 Falkirk Ln",
    "sg:city":"Lake Forest",
    "sg:classifiers":[
        {
            "category":"Building & Trades",
            "subcategory":"Construction",
            "type":"Services"
        }
    ],
    "sg:phone":"+1 949 855 4226",
    "sg:postcode":"92630",
    "sg:province":"CA",
    "sg:tags":[
        "fish",
        "pool"
    ],
    "wof:name":"Water In The Garden",
    "wof:placetype":"venue"
},
  "geometry": {"coordinates":[-117.67648699999999,33.651628],"type":"Point"}
}