{
  "type": "Feature",
  "properties": {
    "addr:full":"3490 Sellers Ave Brentwood CA 94513",
    "addr:housenumber":"3490",
    "addr:postcode":"ca 94513",
    "addr:street":"Sellers Ave",
    "iso:country":"US",
    "sg:address":"3490 Sellers Ave",
    "sg:city":"Brentwood",
    "sg:classifiers":[
        {
            "category":"Retail",
            "subcategory":"Repair Shop",
            "type":"Services"
        }
    ],
    "sg:phone":"+1 925 634 1888",
    "sg:postcode":"94513",
    "sg:province":"CA",
    "sg:tags":[
        "refinishing",
        "furniture"
    ],
    "wof:name":"Frank's Refinishing & Repairs",
    "wof:placetype":"venue"
},
  "geometry": {"coordinates":[-121.67771500000001,37.948135],"type":"Point"}
}