{
  "type": "Feature",
  "properties": {
    "iso:country":"US",
    "sg:address":"3700 Market St",
    "sg:city":"Ventura",
    "sg:classifiers":[
        {
            "category":"Freight",
            "type":"Transportation"
        }
    ],
    "sg:phone":"+1 805 644 6993",
    "sg:postcode":"93003",
    "sg:province":"CA",
    "sg:tags":[
        "commercial",
        "storage",
        "general"
    ],
    "wof:name":"Foot Locker Mini Storage",
    "wof:placetype":"venue"
},
  "geometry": {"coordinates":[-119.245369,34.261122],"type":"Point"}
}