{
  "type": "Feature",
  "properties": {
    "addr:full":"3858 W Carson St Ste 121 Torrance CA 90503",
    "addr:housenumber":"3858",
    "addr:postcode":"90503",
    "addr:street":"W Carson St Ste 121",
    "iso:country":"US",
    "sg:address":"3858 W Carson St Ste 121",
    "sg:city":"Torrance",
    "sg:classifiers":[
        {
            "category":"Food & Beverages",
            "subcategory":"Meat & Fish",
            "type":"Retail Goods"
        }
    ],
    "sg:phone":"+1 310 944 9870",
    "sg:postcode":"90503",
    "sg:province":"CA",
    "sg:tags":[
        "seafood",
        "market"
    ],
    "wof:name":"Kamerycah Inc",
    "wof:placetype":"venue"
},
  "geometry": {"coordinates":[-118.355768,33.831176],"type":"Point"}
}