{
  "type": "Feature",
  "properties": {
    "addr:full":"4585 Vanderbilt Dr San Jose CA 95130",
    "addr:housenumber":"4585",
    "addr:postcode":"95130",
    "addr:street":"Vanderbilt Dr",
    "iso:country":"US",
    "sg:address":"4585 Vanderbilt Dr",
    "sg:city":"San Jose",
    "sg:classifiers":[
        {
            "category":"Manufacturing",
            "subcategory":"Tools & Machinery",
            "type":"Manufacturing & Wholesale Goods"
        }
    ],
    "sg:phone":"+1 408 364 2010",
    "sg:postcode":"95130",
    "sg:province":"CA",
    "sg:tags":[
        "industrial",
        "mfg"
    ],
    "wof:name":"Acme Deburring",
    "wof:placetype":"venue"
},
  "geometry": {"coordinates":[-121.98142199999999,37.279082],"type":"Point"}
}