{
  "type": "Feature",
  "properties": {
    "iso:country":"US",
    "sg:address":"210 Fell Street Ste 17",
    "sg:city":"San Francisco",
    "sg:classifiers":[
        {
            "category":"Professional",
            "type":"Services"
        }
    ],
    "sg:phone":"+1 415 543 9977",
    "sg:postcode":"94102",
    "sg:province":"CA",
    "sg:website":"www.aalegalservice.com",
    "wof:name":"A & A Legal Service, Inc",
    "wof:placetype":"venue"
},
  "geometry": {"coordinates":[-122.422068,37.776304],"type":"Point"}
}