{
  "type": "Feature",
  "properties": {
    "addr:full":"23803 Wilmington Ave Carson CA 90745",
    "addr:housenumber":"23803",
    "addr:postcode":"90745",
    "addr:street":"Wilmington Ave",
    "iso:country":"US",
    "sg:address":"23803 Wilmington Ave",
    "sg:city":"Carson",
    "sg:classifiers":[
        {
            "category":"Retail",
            "subcategory":"Auto Repair",
            "type":"Services"
        }
    ],
    "sg:phone":"+1 310 549 7070",
    "sg:postcode":"90745",
    "sg:province":"CA",
    "sg:tags":[
        "automobile",
        "co",
        "drive",
        "transporter"
    ],
    "wof:name":"Pasha Group",
    "wof:placetype":"venue"
},
  "geometry": {"coordinates":[-118.25420800000001,33.809839],"type":"Point"}
}