{
  "type": "Feature",
  "properties": {
    "addr:full":"3631 Hayden Ave Culver City CA 90232",
    "addr:housenumber":"3631",
    "addr:postcode":"90232",
    "addr:street":"Hayden Ave",
    "iso:country":"US",
    "sg:address":"3631 Hayden Ave",
    "sg:city":"Culver City",
    "sg:classifiers":[
        {
            "category":"Education",
            "subcategory":"Dance Studio",
            "type":"Public Place"
        }
    ],
    "sg:phone":"+1 310 280 9145",
    "sg:postcode":"90232",
    "sg:province":"CA",
    "sg:tags":[
        "instruction",
        "dancing"
    ],
    "wof:name":"Debbie Allen Dance Academy",
    "wof:placetype":"venue"
},
  "geometry": {"coordinates":[-118.381631,34.024076],"type":"Point"}
}