{
  "type": "Feature",
  "properties": {
    "addr:full":"325 Corey Way # 115 South San Francisco CA 94080",
    "addr:housenumber":"325",
    "addr:postcode":"94080",
    "addr:street":"Corey Way # 115",
    "iso:country":"US",
    "sg:address":"325 Corey Way # 115",
    "sg:city":"South San Francisco",
    "sg:classifiers":[
        {
            "category":"Freight",
            "type":"Transportation"
        }
    ],
    "sg:phone":"+1 650 583 8555",
    "sg:postcode":"94080",
    "sg:province":"CA",
    "sg:tags":[
        "shipping"
    ],
    "sg:website":"www.cratersandfreighters.com",
    "wof:name":"Craters & Freighters",
    "wof:placetype":"venue"
},
  "geometry": {"coordinates":[-122.402266,37.645543],"type":"Point"}
}