{
  "type": "Feature",
  "properties": {
    "addr:full":"416 S Van Ness Ave Los Angeles CA 90020",
    "addr:housenumber":"416",
    "addr:postcode":"90020",
    "addr:street":"S Van Ness Ave",
    "iso:country":"US",
    "sg:address":"416 S Van Ness Ave",
    "sg:city":"Los Angeles",
    "sg:classifiers":[
        {
            "category":"Wholesale",
            "subcategory":"Electrical",
            "type":"Manufacturing & Wholesale Goods"
        }
    ],
    "sg:phone":"+1 213 388 4181",
    "sg:postcode":"90020",
    "sg:province":"CA",
    "sg:tags":[
        "sporting"
    ],
    "wof:name":"A H & M Trading Co",
    "wof:placetype":"venue"
},
  "geometry": {"coordinates":[-118.315062,34.065622],"type":"Point"}
}