{
  "type": "Feature",
  "properties": {
    "iso:country":"US",
    "sg:address":"1225 N Pacific Ave",
    "sg:city":"Glendale",
    "sg:classifiers":[
        {
            "category":"Real Estate",
            "subcategory":"Real Estate Agent",
            "type":"Services"
        }
    ],
    "sg:phone":"+1 818 244 5800",
    "sg:postcode":"91202",
    "sg:province":"CA",
    "wof:name":"Arden Realty Inc",
    "wof:placetype":"venue"
},
  "geometry": {"coordinates":[-118.26519999999999,34.163989],"type":"Point"}
}