{
  "type": "Feature",
  "properties": {
    "iso:country":"US",
    "sg:address":"1600 Shattuck Ave Ste 122",
    "sg:city":"Berkeley",
    "sg:classifiers":[
        {
            "category":"Education",
            "subcategory":"Special Training",
            "type":"Public Place"
        },
        {
            "category":"Education",
            "subcategory":"School",
            "type":"Public Place"
        }
    ],
    "sg:phone":"+1 510 869 2797",
    "sg:postcode":"94709",
    "sg:province":"CA",
    "sg:tags":[
        "adult"
    ],
    "sg:website":"www.birthways.org",
    "wof:name":"Birth Ways",
    "wof:placetype":"venue"
},
  "geometry": {"coordinates":[-122.269164,37.878394],"type":"Point"}
}