{
  "type": "Feature",
  "properties": {
    "iso:country":"US",
    "sg:address":"9117 E Stockton Blvd",
    "sg:city":"Elk Grove",
    "sg:classifiers":[
        {
            "category":"Government",
            "subcategory":"Office",
            "type":"Public Place"
        }
    ],
    "sg:phone":"+1 916 685 5705",
    "sg:postcode":"95624",
    "sg:province":"CA",
    "wof:name":"Sacramento Cnty Community Svc",
    "wof:placetype":"venue"
},
  "geometry": {"coordinates":[-121.398175,38.430643],"type":"Point"}
}