{
  "type": "Feature",
  "properties": {
    "addr:full":"4660 La Jolla Village Dr San Diego CA 92122",
    "addr:housenumber":"4660",
    "addr:postcode":"92122",
    "addr:street":"La Jolla Village Dr",
    "iso:country":"US",
    "sg:address":"4660 La Jolla Village Dr",
    "sg:city":"San Diego",
    "sg:classifiers":[
        {
            "category":"Professional",
            "subcategory":"Lawyer & Legal Services",
            "type":"Services"
        }
    ],
    "sg:phone":"+1 858 450 1544",
    "sg:postcode":"92122",
    "sg:province":"CA",
    "wof:name":"Haack Richard Atty",
    "wof:placetype":"venue"
},
  "geometry": {"coordinates":[-117.20700100000001,32.874199],"type":"Point"}
}