{
  "type": "Feature",
  "properties": {
    "addr:full":"7772 Hansom Dr Oakland CA 94605",
    "addr:housenumber":"7772",
    "addr:postcode":"94605",
    "addr:street":"Hansom Dr",
    "iso:country":"US",
    "sg:address":"7772 Hansom Dr",
    "sg:city":"Oakland",
    "sg:classifiers":[
        {
            "category":"Manufacturing",
            "subcategory":"Printing",
            "type":"Manufacturing & Wholesale Goods"
        }
    ],
    "sg:phone":"+1 510 568 2742",
    "sg:postcode":"94605",
    "sg:province":"CA",
    "sg:tags":[
        "publisher",
        "software"
    ],
    "wof:name":"Document Assembly Solutions",
    "wof:placetype":"venue"
},
  "geometry": {"coordinates":[-122.140046,37.776938],"type":"Point"}
}