{
  "type": "Feature",
  "properties": {
    "addr:full":"548 N Azusa Ave Azusa CA 91702",
    "addr:housenumber":"548",
    "addr:postcode":"91702",
    "addr:street":"N Azusa Ave",
    "iso:country":"US",
    "sg:address":"548 N Azusa Ave",
    "sg:city":"Azusa",
    "sg:classifiers":[
        {
            "category":"Shopping",
            "subcategory":"Gifts & Souvenirs",
            "type":"Retail Goods"
        }
    ],
    "sg:phone":"+1 626 969 2362",
    "sg:postcode":"91702",
    "sg:province":"CA",
    "sg:tags":[
        "party",
        "supply"
    ],
    "wof:name":"Mi Fiesta TU Fiesta",
    "wof:placetype":"venue"
},
  "geometry": {"coordinates":[-117.907478,34.130766],"type":"Point"}
}