{
  "type": "Feature",
  "properties": {
    "iso:country":"US",
    "sg:address":"1500 Lytton Springs Rd",
    "sg:city":"Healdsburg",
    "sg:classifiers":[
        {
            "category":"Airport",
            "type":"Transportation"
        }
    ],
    "sg:phone":"+1 707 433 8540",
    "sg:postcode":"95448",
    "sg:province":"CA",
    "sg:tags":[
        "aircraft",
        "maintenance"
    ],
    "wof:name":"Healdsburg Aviation Inc",
    "wof:placetype":"venue"
},
  "geometry": {"coordinates":[-122.902969,38.656999],"type":"Point"}
}