{
  "type": "Feature",
  "properties": {
    "iso:country":"US",
    "sg:address":"3405 Motor Avenue",
    "sg:city":"Los Angeles",
    "sg:classifiers":[
        {
            "category":"Retail",
            "subcategory":"Auto Repair",
            "type":"Services"
        }
    ],
    "sg:phone":"+1 310 838 3333",
    "sg:postcode":"90034",
    "sg:province":"CA",
    "wof:name":"Capt V's Automotive Service",
    "wof:placetype":"venue"
},
  "geometry": {"coordinates":[-118.40929,34.027607],"type":"Point"}
}