{
  "type": "Feature",
  "properties": {
    "addr:full":"2020 Eye St Bakersfield CA 93301",
    "addr:housenumber":"2020",
    "addr:postcode":"93301",
    "addr:street":"Eye St",
    "iso:country":"US",
    "sg:address":"2020 Eye St",
    "sg:city":"Bakersfield",
    "sg:classifiers":[
        {
            "category":"Professional",
            "subcategory":"Engineering",
            "type":"Services"
        }
    ],
    "sg:phone":"+1 661 392 1124",
    "sg:postcode":"93301",
    "sg:province":"CA",
    "sg:tags":[
        "engineer"
    ],
    "wof:name":"Joseph Eribarne Svc",
    "wof:placetype":"venue"
},
  "geometry": {"coordinates":[-119.01994000000001,35.377333],"type":"Point"}
}