{
  "type": "Feature",
  "properties": {
    "iso:country":"US",
    "sg:address":"40826 Mino Way",
    "sg:city":"Fremont",
    "sg:classifiers":[
        {
            "category":"Professional",
            "type":"Services"
        }
    ],
    "sg:phone":"+1 510 656 2168",
    "sg:postcode":"94539",
    "sg:province":"CA",
    "wof:name":"Brain Power USA Inc",
    "wof:placetype":"venue"
},
  "geometry": {"coordinates":[-121.951435,37.543918],"type":"Point"}
}