{
  "type": "Feature",
  "properties": {
    "iso:country":"US",
    "sg:address":"3029 E Main St",
    "sg:city":"Ventura",
    "sg:classifiers":[
        {
            "category":"Restaurant",
            "type":"Food & Drink"
        }
    ],
    "sg:menulink":"http://www.allmenus.com/ca/ventura/269788-the-sidecar-restaurant/menu/",
    "sg:phone":"+1 805 653 7433",
    "sg:postcode":"93003",
    "sg:province":"CA",
    "sg:tags":[
        "american",
        "californian"
    ],
    "wof:name":"The Sidecar Restaurant",
    "wof:placetype":"venue"
},
  "geometry": {"coordinates":[-119.254952,34.270717],"type":"Point"}
}