{
  "type": "Feature",
  "properties": {
    "iso:country":"US",
    "sg:address":"1842 N Keystone St",
    "sg:city":"Burbank",
    "sg:classifiers":[
        {
            "category":"Professional",
            "type":"Services"
        }
    ],
    "sg:phone":"+1 818 842 1325",
    "sg:postcode":"91504",
    "sg:province":"CA",
    "sg:tags":[
        "establishment"
    ],
    "wof:name":"Carter Plating Co",
    "wof:placetype":"venue"
},
  "geometry": {"coordinates":[-118.33396399999999,34.192893],"type":"Point"}
}