{
  "type": "Feature",
  "properties": {
    "iso:country":"US",
    "sg:address":"2429 S Stockton St",
    "sg:city":"Lodi",
    "sg:classifiers":[
        {
            "category":"Retail",
            "subcategory":"Repair Shop",
            "type":"Services"
        }
    ],
    "sg:phone":"+1 209 367 4557",
    "sg:postcode":"95240",
    "sg:province":"CA",
    "sg:tags":[
        "welding"
    ],
    "wof:name":"Hoochie Tower Vince Products",
    "wof:placetype":"venue"
},
  "geometry": {"coordinates":[-121.269701,38.104025],"type":"Point"}
}