{
  "type": "Feature",
  "properties": {
    "addr:full":"6780 Amador Plaza Rd Dublin CA 94568",
    "addr:housenumber":"6780",
    "addr:postcode":"94568",
    "addr:street":"Amador Plaza Rd",
    "iso:country":"US",
    "sg:address":"6780 Amador Plaza Rd",
    "sg:city":"Dublin",
    "sg:classifiers":[
        {
            "category":"Home & Garden",
            "subcategory":"Furniture",
            "type":"Retail Goods"
        }
    ],
    "sg:phone":"+1 925 828 6288",
    "sg:postcode":"94568",
    "sg:province":"CA",
    "sg:tags":[
        "mattress"
    ],
    "wof:name":"Mattress Discounters",
    "wof:placetype":"venue"
},
  "geometry": {"coordinates":[-121.927358,37.704492],"type":"Point"}
}