{
  "type": "Feature",
  "properties": {
    "addr:full":"915 Wilshire Blvd Los Angeles CA 90017",
    "addr:housenumber":"915",
    "addr:postcode":"90017",
    "addr:street":"Wilshire Blvd",
    "iso:country":"US",
    "sg:address":"915 Wilshire Blvd",
    "sg:city":"Los Angeles",
    "sg:classifiers":[
        {
            "category":"Professional",
            "subcategory":"Employment Agencies",
            "type":"Services"
        }
    ],
    "sg:phone":"+1 213 614 7404",
    "sg:postcode":"90017",
    "sg:province":"CA",
    "wof:name":"Trimble Tricia",
    "wof:placetype":"venue"
},
  "geometry": {"coordinates":[-118.26026899999999,34.050815],"type":"Point"}
}