{
  "type": "Feature",
  "properties": {
    "addr:full":"7055 McComber St Sacramento CA 95828",
    "addr:housenumber":"7055",
    "addr:postcode":"95828",
    "addr:street":"Mccomber St",
    "iso:country":"US",
    "sg:address":"7055 McComber St",
    "sg:city":"Sacramento",
    "sg:classifiers":[
        {
            "category":"Building & Trades",
            "subcategory":"Construction",
            "type":"Services"
        }
    ],
    "sg:phone":"+1 916 386 1268",
    "sg:postcode":"95828",
    "sg:province":"CA",
    "sg:tags":[
        "contractor"
    ],
    "wof:name":"Ronald W Parsons Construction",
    "wof:placetype":"venue"
},
  "geometry": {"coordinates":[-121.395939,38.500014],"type":"Point"}
}