{
  "type": "Feature",
  "properties": {
    "addr:full":"9100 Mccoy Ave Sacramento CA 95829",
    "addr:housenumber":"9100",
    "addr:postcode":"95829",
    "addr:street":"Mccoy Ave",
    "iso:country":"US",
    "sg:address":"9100 Mccoy Ave",
    "sg:city":"Sacramento",
    "sg:classifiers":[
        {
            "category":"Professional",
            "subcategory":"Engineering",
            "type":"Services"
        }
    ],
    "sg:phone":"+1 916 423 3577",
    "sg:postcode":"95829",
    "sg:province":"CA",
    "sg:tags":[
        "aircraft",
        "maintenance"
    ],
    "wof:name":"Capitol Machinery Repr & Maint",
    "wof:placetype":"venue"
},
  "geometry": {"coordinates":[-121.365657,38.4871],"type":"Point"}
}