{
  "type": "Feature",
  "properties": {
    "addr:full":"1504 S Main St Ste 373 Los Gatos CA 95030",
    "addr:housenumber":"1504",
    "addr:postcode":"95030",
    "addr:street":"S Main St Ste 373",
    "iso:country":"US",
    "sg:address":"1504 S Main St Ste 373",
    "sg:city":"Los Gatos",
    "sg:classifiers":[
        {
            "category":"Autos & Motor Vehicles",
            "subcategory":"Auto Supplies",
            "type":"Retail Goods"
        }
    ],
    "sg:phone":"+1 408 597 6628",
    "sg:postcode":"95030",
    "sg:province":"CA",
    "sg:tags":[
        "part"
    ],
    "wof:name":"Batteries On the Go",
    "wof:placetype":"venue"
},
  "geometry": {"coordinates":[-121.981577,37.221247],"type":"Point"}
}