{
  "type": "Feature",
  "properties": {
    "addr:full":"440 Tecate Rd Tecate CA 91980",
    "addr:housenumber":"440",
    "addr:postcode":"91980",
    "addr:street":"Tecate Rd",
    "iso:country":"US",
    "sg:address":"440 Tecate Rd",
    "sg:city":"Tecate",
    "sg:classifiers":[
        {
            "category":"Shopping",
            "type":"Retail Goods"
        }
    ],
    "sg:phone":"+1 619 478 5710",
    "sg:postcode":"91980",
    "sg:province":"CA",
    "sg:tags":[
        "art",
        "gallery",
        "dealer"
    ],
    "wof:name":"Construction Art Galleria",
    "wof:placetype":"venue"
},
  "geometry": {"coordinates":[-116.62802499999999,32.578033],"type":"Point"}
}