{
  "type": "Feature",
  "properties": {
    "addr:full":"3400 Incline Dr Bakersfield CA 93306",
    "addr:postcode":"3400;93306",
    "addr:street":"Incline Dr",
    "iso:country":"US",
    "sg:address":"3400 Incline Dr",
    "sg:city":"Bakersfield",
    "sg:classifiers":[
        {
            "category":"Professional",
            "subcategory":"Advertising",
            "type":"Services"
        }
    ],
    "sg:phone":"+1 661 832 4245",
    "sg:postcode":"93306",
    "sg:province":"CA",
    "wof:name":"Real Estate Book-Bakersfield",
    "wof:placetype":"venue"
},
  "geometry": {"coordinates":[-118.93026,35.394121],"type":"Point"}
}