{
  "type": "Feature",
  "properties": {
    "addr:full":"506 S San Pedro St Los Angeles CA 90013",
    "addr:housenumber":"506",
    "addr:postcode":"90013",
    "addr:street":"S San Pedro St",
    "iso:country":"US",
    "sg:address":"506 S San Pedro St",
    "sg:city":"Los Angeles",
    "sg:classifiers":[
        {
            "category":"Education",
            "subcategory":"Special Training",
            "type":"Public Place"
        }
    ],
    "sg:phone":"+1 213 896 9200",
    "sg:postcode":"90013",
    "sg:province":"CA",
    "sg:tags":[
        "tutoring"
    ],
    "sg:website":"www.schoolonwheels.com",
    "wof:name":"School On Wheels Inc",
    "wof:placetype":"venue"
},
  "geometry": {"coordinates":[-118.24400300000001,34.044102],"type":"Point"}
}