{
  "type": "Feature",
  "properties": {
    "addr:full":"2385 A St Santa Maria CA 93455",
    "addr:housenumber":"2385",
    "addr:postcode":"93455",
    "addr:street":"A St",
    "iso:country":"US",
    "sg:address":"2385 A St",
    "sg:city":"Santa Maria",
    "sg:classifiers":[
        {
            "category":"Professional",
            "type":"Services"
        }
    ],
    "sg:phone":"+1 805 739 0809",
    "sg:postcode":"93455",
    "sg:province":"CA",
    "sg:tags":[
        "caterer"
    ],
    "wof:name":"Testa Catering",
    "wof:placetype":"venue"
},
  "geometry": {"coordinates":[-120.46568000000001,34.918084],"type":"Point"}
}