{
  "type": "Feature",
  "properties": {
    "addr:full":"1607 S Crescent Heights Blvd Los Angeles CA 90035",
    "addr:housenumber":"1607",
    "addr:postcode":"90035",
    "addr:street":"S Crescent Heights Blvd",
    "iso:country":"US",
    "sg:address":"1607 S Crescent Heights Blvd",
    "sg:city":"Los Angeles",
    "sg:classifiers":[
        {
            "category":"Banks & Credit Unions",
            "subcategory":"Financial Services",
            "type":"Services"
        }
    ],
    "sg:phone":"+1 323 634 0578",
    "sg:postcode":"90035",
    "sg:province":"CA",
    "sg:tags":[
        "company",
        "holding"
    ],
    "wof:name":"Inner Quest Group",
    "wof:placetype":"venue"
},
  "geometry": {"coordinates":[-118.37350600000001,34.047823],"type":"Point"}
}