{
  "type": "Feature",
  "properties": {
    "addr:full":"12932 Hesperia Rd Ste-B Victorville CA 92395",
    "addr:housenumber":"12932",
    "addr:postcode":"92395",
    "addr:street":"Hesperia Rd",
    "iso:country":"US",
    "sg:address":"12932 Hesperia Rd Ste-B",
    "sg:city":"Victorville",
    "sg:classifiers":[
        {
            "category":"Manufacturing",
            "subcategory":"Glass & Minerals",
            "type":"Manufacturing & Wholesale Goods"
        },
        {
            "category":"Retail",
            "subcategory":"Auto Repair",
            "type":"Services"
        }
    ],
    "sg:phone":"+1 760 951 2575",
    "sg:postcode":"92395",
    "sg:province":"CA",
    "sg:tags":[
        "plate",
        "window",
        "windshield",
        "glass-auto"
    ],
    "wof:name":"SAFELITE AUTO GLASS",
    "wof:placetype":"venue"
},
  "geometry": {"coordinates":[-117.290108,34.485924],"type":"Point"}
}