{
  "type": "Feature",
  "properties": {
    "addr:full":"1557 Albany Ct Milpitas CA 95035",
    "addr:housenumber":"1557",
    "addr:postcode":"95035",
    "addr:street":"Albany Ct",
    "iso:country":"US",
    "sg:address":"1557 Albany Ct",
    "sg:city":"Milpitas",
    "sg:classifiers":[
        {
            "category":"Building & Trades",
            "subcategory":"Landscaping Services",
            "type":"Services"
        }
    ],
    "sg:phone":"+1 408 235 0333",
    "sg:postcode":"95035",
    "sg:province":"CA",
    "wof:name":"Lo S Gardening & Service",
    "wof:placetype":"venue"
},
  "geometry": {"coordinates":[-121.87856499999999,37.435245],"type":"Point"}
}