{
  "type": "Feature",
  "properties": {
    "addr:full":"The Parlour 345 S. Coast Hwy 101 Encinitas CA 92024",
    "addr:housenumber":"345",
    "addr:postcode":"92024",
    "addr:street":"S. Coast Hwy 101",
    "iso:country":"US",
    "sg:address":"The Parlour 345 S. Coast Hwy 101",
    "sg:city":"Encinitas",
    "sg:classifiers":[
        {
            "category":"Personal",
            "subcategory":"Beauty Salon",
            "type":"Services"
        }
    ],
    "sg:phone":"+1 760 586 1879",
    "sg:postcode":"92024",
    "sg:province":"CA",
    "sg:tags":[
        "hair"
    ],
    "wof:name":"Hair by Robin Fisher",
    "wof:placetype":"venue"
},
  "geometry": {"coordinates":[-117.293464,33.04774],"type":"Point"}
}