{
  "type": "Feature",
  "properties": {
    "iso:country":"US",
    "sg:address":"11807 Walnut Ave",
    "sg:city":"Oakdale",
    "sg:classifiers":[
        {
            "category":"Building & Trades",
            "subcategory":"Landscaping Services",
            "type":"Services"
        }
    ],
    "sg:phone":"+1 209 847 6586",
    "sg:postcode":"95361",
    "sg:province":"CA",
    "sg:tags":[
        "lawn",
        "maintenance"
    ],
    "wof:name":"Modesto Lawn And Garden",
    "wof:placetype":"venue"
},
  "geometry": {"coordinates":[-120.896058,37.809565],"type":"Point"}
}