{
  "type": "Feature",
  "properties": {
    "iso:country":"US",
    "sg:address":"41 Lovell Ave",
    "sg:city":"Mill Valley",
    "sg:classifiers":[
        {
            "category":"Shopping",
            "subcategory":"Jewelry",
            "type":"Retail Goods"
        }
    ],
    "sg:phone":"+1 650 941 7233",
    "sg:postcode":"94941",
    "sg:province":"CA",
    "sg:tags":[
        "platinum",
        "silver",
        "gold"
    ],
    "wof:name":"Studio Creaius",
    "wof:placetype":"venue"
},
  "geometry": {"coordinates":[-122.549211,37.906687],"type":"Point"}
}