{
  "type": "Feature",
  "properties": {
    "addr:full":"2129 Harrison St San Francisco CA 94110",
    "addr:housenumber":"2129",
    "addr:postcode":"94110",
    "addr:street":"Harrison St",
    "iso:country":"US",
    "sg:address":"2129 Harrison St",
    "sg:city":"San Francisco",
    "sg:classifiers":[
        {
            "category":"Autos & Motor Vehicles",
            "subcategory":"Automobile Sales",
            "type":"Retail Goods"
        }
    ],
    "sg:phone":"+1 415 819 3914",
    "sg:postcode":"94110",
    "sg:province":"CA",
    "sg:tags":[
        "automotive"
    ],
    "sg:website":"www.dirtydavecustoms.com",
    "wof:name":"Dirty Dave Customs",
    "wof:placetype":"venue"
},
  "geometry": {"coordinates":[-122.412885,37.762935],"type":"Point"}
}