{
  "type": "Feature",
  "properties": {
    "addr:full":"1115 K St Modesto CA 95354",
    "addr:housenumber":"1115",
    "addr:postcode":"ca 95354",
    "addr:street":"K St",
    "iso:country":"US",
    "sg:address":"1115 K St",
    "sg:city":"Modesto",
    "sg:classifiers":[
        {
            "category":"Retail",
            "subcategory":"Auto Repair",
            "type":"Services"
        }
    ],
    "sg:phone":"+1 209 522 8049",
    "sg:postcode":"95354",
    "sg:province":"CA",
    "sg:tags":[
        "truck"
    ],
    "wof:name":"J & H Mobile Truck Repair",
    "wof:placetype":"venue"
},
  "geometry": {"coordinates":[-120.999712,37.642862],"type":"Point"}
}