{
  "type": "Feature",
  "properties": {
    "iso:country":"US",
    "sg:address":"1910 Park Blvd",
    "sg:city":"Oakland",
    "sg:classifiers":[
        {
            "category":"Restaurant",
            "type":"Food & Drink"
        }
    ],
    "sg:phone":"+1 510 834 8915",
    "sg:postcode":"94606",
    "sg:province":"CA",
    "sg:tags":[
        "mexican"
    ],
    "wof:name":"Casa Vallarta Restaurant",
    "wof:placetype":"venue"
},
  "geometry": {"coordinates":[-122.25,37.799702],"type":"Point"}
}