{
  "type": "Feature",
  "properties": {
    "addr:full":"1313 Arbutus Ave Chico CA 95926",
    "addr:housenumber":"1313",
    "addr:postcode":"95926",
    "addr:street":"Arbutus Ave",
    "iso:country":"US",
    "sg:address":"1313 Arbutus Ave",
    "sg:city":"Chico",
    "sg:classifiers":[
        {
            "category":"Retail",
            "subcategory":"Portrait Studio",
            "type":"Services"
        }
    ],
    "sg:phone":"+1 530 343 8888",
    "sg:postcode":"95926",
    "sg:province":"CA",
    "sg:tags":[
        "photographer"
    ],
    "wof:name":"Lasting Imagery",
    "wof:placetype":"venue"
},
  "geometry": {"coordinates":[-121.838663,39.745132],"type":"Point"}
}