{
  "type": "Feature",
  "properties": {
    "addr:full":"692 del Monte Center Monterey CA 93940",
    "addr:housenumber":"692",
    "addr:postcode":"93940",
    "addr:street":"Del Monte Center",
    "iso:country":"US",
    "sg:address":"692 del Monte Center",
    "sg:city":"Monterey",
    "sg:classifiers":[
        {
            "category":"Shopping",
            "type":"Retail Goods"
        }
    ],
    "sg:phone":"+1 831 655 9771",
    "sg:postcode":"93940",
    "sg:province":"CA",
    "sg:tags":[
        "candle"
    ],
    "wof:name":"Illuminata",
    "wof:placetype":"venue"
},
  "geometry": {"coordinates":[-121.893371,36.584931],"type":"Point"}
}