{
  "type": "Feature",
  "properties": {
    "addr:full":"25388 Jaclyn Ave Moreno Valley CA 92557",
    "addr:housenumber":"25388",
    "addr:postcode":"92557",
    "addr:street":"Jaclyn Ave",
    "iso:country":"US",
    "sg:address":"25388 Jaclyn Ave",
    "sg:city":"Moreno Valley",
    "sg:classifiers":[
        {
            "category":"Insurance",
            "subcategory":"Insurance Agent",
            "type":"Services"
        }
    ],
    "sg:phone":"+1 951 242 6935",
    "sg:postcode":"92557",
    "sg:province":"CA",
    "wof:name":"Luther Harrison Jr Insurance",
    "wof:placetype":"venue"
},
  "geometry": {"coordinates":[-117.21996799999999,33.957232],"type":"Point"}
}