{
  "type": "Feature",
  "properties": {
    "iso:country":"US",
    "sg:address":"3333 Sunrise Blvd",
    "sg:city":"Rancho Cordova",
    "sg:classifiers":[
        {
            "category":"Wholesale",
            "subcategory":"Durable Goods & Equipment",
            "type":"Manufacturing & Wholesale Goods"
        }
    ],
    "sg:phone":"+1 916 858 0985",
    "sg:postcode":"95742",
    "sg:province":"CA",
    "sg:tags":[
        "representative",
        "manufacturer"
    ],
    "wof:name":"Heimburg Sales Group",
    "wof:placetype":"venue"
},
  "geometry": {"coordinates":[-121.264224,38.581908],"type":"Point"}
}