{
  "type": "Feature",
  "properties": {
    "addr:full":"39403 Fremont Blvd Fremont CA 94538",
    "addr:housenumber":"39403",
    "addr:postcode":"94538",
    "addr:street":"Fremont Blvd",
    "iso:country":"US",
    "sg:address":"39403 Fremont Blvd",
    "sg:city":"Fremont",
    "sg:classifiers":[
        {
            "category":"Restaurant",
            "type":"Food & Drink"
        }
    ],
    "sg:menulink":"http://www.allmenus.com/ca/fremont/111103-classic-diner/menu/",
    "sg:phone":"+1 510 651 7241",
    "sg:postcode":"94538",
    "sg:province":"CA",
    "sg:tags":[
        "american",
        "diner"
    ],
    "wof:name":"Classic Diner",
    "wof:placetype":"venue"
},
  "geometry": {"coordinates":[-121.983863,37.546192],"type":"Point"}
}