{
  "type": "Feature",
  "properties": {
    "addr:full":"1617 Brookes Ave. San Diego CA 92106",
    "addr:housenumber":"1617",
    "addr:postcode":"92106",
    "addr:street":"Brookes Ave.",
    "iso:country":"US",
    "sg:address":"1617 Brookes Ave.",
    "sg:city":"San Diego",
    "sg:classifiers":[
        {
            "category":"Personal",
            "type":"Services"
        },
        {
            "category":"Home & Garden",
            "subcategory":"Building Materials",
            "type":"Retail Goods"
        }
    ],
    "sg:phone":"+1 858 229 8156",
    "sg:postcode":"92106",
    "sg:province":"CA",
    "sg:tags":[
        "fixture",
        "equipment",
        "planning",
        "lighting",
        "party",
        "event"
    ],
    "wof:name":"Christmas Light Crew",
    "wof:placetype":"venue"
},
  "geometry": {"coordinates":[-117.148692,32.743],"type":"Point"}
}