{
  "type": "Feature",
  "properties": {
    "iso:country":"US",
    "sg:address":"11747 Vose St",
    "sg:city":"North Hollywood",
    "sg:classifiers":[
        {
            "category":"Manufacturing",
            "subcategory":"Metals",
            "type":"Manufacturing & Wholesale Goods"
        }
    ],
    "sg:phone":"+1 818 764 2345",
    "sg:postcode":"91605",
    "sg:province":"CA",
    "sg:tags":[
        "fabricator",
        "sheet"
    ],
    "wof:name":"Chal Industries",
    "wof:placetype":"venue"
},
  "geometry": {"coordinates":[-118.391308,34.198515],"type":"Point"}
}