{
  "type": "Feature",
  "properties": {
    "iso:country":"US",
    "sg:address":"122 E Belle Ave",
    "sg:city":"Bakersfield",
    "sg:classifiers":[
        {
            "category":"Building & Trades",
            "subcategory":"Landscaping Services",
            "type":"Services"
        }
    ],
    "sg:phone":"+1 661 393 7884",
    "sg:postcode":"93308",
    "sg:province":"CA",
    "sg:tags":[
        "tree"
    ],
    "wof:name":"Ben's Tree Service",
    "wof:placetype":"venue"
},
  "geometry": {"coordinates":[-119.020473,35.41048],"type":"Point"}
}