{
  "type": "Feature",
  "properties": {
    "iso:country":"US",
    "sg:address":"137 Anita Rd Apt D",
    "sg:city":"Burlingame",
    "sg:classifiers":[
        {
            "category":"Retail",
            "subcategory":"Auto Repair",
            "type":"Services"
        }
    ],
    "sg:phone":"+1 650 347 7084",
    "sg:postcode":"94010",
    "sg:province":"CA",
    "sg:tags":[
        "body",
        "painting",
        "repairing",
        "automobile"
    ],
    "wof:name":"Tech Blend",
    "wof:placetype":"venue"
},
  "geometry": {"coordinates":[-122.340339,37.579533],"type":"Point"}
}