{
  "type": "Feature",
  "properties": {
    "iso:country":"US",
    "sg:address":"439 1st St",
    "sg:city":"Benicia",
    "sg:classifiers":[
        {
            "category":"Home & Garden",
            "subcategory":"Furniture",
            "type":"Retail Goods"
        }
    ],
    "sg:phone":"+1 707 747 0200",
    "sg:postcode":"94510",
    "sg:province":"CA",
    "wof:name":"Ironhorse For Kids",
    "wof:placetype":"venue"
},
  "geometry": {"coordinates":[-122.16029399999999,38.047488],"type":"Point"}
}