{
  "type": "Feature",
  "properties": {
    "addr:full":"1525 McHenry Ave Modesto CA 95350",
    "addr:housenumber":"1525",
    "addr:postcode":"ca 95350",
    "addr:street":"Mchenry Ave",
    "iso:country":"US",
    "sg:address":"1525 McHenry Ave",
    "sg:city":"Modesto",
    "sg:classifiers":[
        {
            "category":"Travel",
            "subcategory":"Hotels & Motels",
            "type":"Entertainment"
        }
    ],
    "sg:phone":"+1 209 521 6340",
    "sg:postcode":"95350",
    "sg:province":"CA",
    "sg:website":"www.heritageinn.us",
    "wof:name":"Vagabond Inn",
    "wof:placetype":"venue"
},
  "geometry": {"coordinates":[-120.99400300000001,37.666698],"type":"Point"}
}