{
  "type": "Feature",
  "properties": {
    "iso:country":"US",
    "sg:address":"150 Almaden Blvd",
    "sg:city":"San Jose",
    "sg:classifiers":[
        {
            "category":"Real Estate",
            "subcategory":"Real Estate Services",
            "type":"Services"
        }
    ],
    "sg:phone":"+1 408 280 5181",
    "sg:postcode":"95113",
    "sg:province":"CA",
    "sg:tags":[
        "management",
        "property"
    ],
    "wof:name":"Park Center Plaza Investors LP",
    "wof:placetype":"venue"
},
  "geometry": {"coordinates":[-121.892923,37.331783],"type":"Point"}
}