{
  "type": "Feature",
  "properties": {
    "iso:country":"US",
    "sg:address":"1255 E Main St",
    "sg:city":"Santa Paula",
    "sg:classifiers":[
        {
            "category":"Building & Trades",
            "subcategory":"Plumbing",
            "type":"Services"
        }
    ],
    "sg:phone":"+1 805 525 5516",
    "sg:postcode":"93060",
    "sg:province":"CA",
    "sg:tags":[
        "ventilating",
        "contractor"
    ],
    "wof:name":"F M Pearce Co",
    "wof:placetype":"venue"
},
  "geometry": {"coordinates":[-119.054979,34.355664],"type":"Point"}
}