{
  "type": "Feature",
  "properties": {
    "addr:full":"3240 Fawn Dr San Jose CA 95124",
    "addr:housenumber":"3240",
    "addr:postcode":"95124",
    "addr:street":"Fawn Dr",
    "iso:country":"US",
    "sg:address":"3240 Fawn Dr",
    "sg:city":"San Jose",
    "sg:classifiers":[
        {
            "category":"Building & Trades",
            "subcategory":"Electrical",
            "type":"Services"
        }
    ],
    "sg:phone":"+1 408 371 1638",
    "sg:postcode":"95124",
    "sg:province":"CA",
    "sg:tags":[
        "electrical",
        "contractor"
    ],
    "wof:name":"Mld Electric",
    "wof:placetype":"venue"
},
  "geometry": {"coordinates":[-121.924301,37.264523],"type":"Point"}
}