{
  "type": "Feature",
  "properties": {
    "iso:country":"US",
    "sg:address":"1582 Parkway Loop",
    "sg:city":"Tustin",
    "sg:classifiers":[
        {
            "category":"Wholesale",
            "subcategory":"Durable Goods & Equipment",
            "type":"Manufacturing & Wholesale Goods"
        }
    ],
    "sg:phone":"+1 714 259 8988",
    "sg:postcode":"92780",
    "sg:province":"CA",
    "sg:tags":[
        "importer"
    ],
    "wof:name":"Alton Industries Inc",
    "wof:placetype":"venue"
},
  "geometry": {"coordinates":[-117.82887,33.720025],"type":"Point"}
}