{
  "type": "Feature",
  "properties": {
    "iso:country":"US",
    "sg:address":"201 Mission Street Fl 8",
    "sg:city":"San Francisco",
    "sg:classifiers":[
        {
            "category":"Utilities",
            "type":"Services"
        }
    ],
    "sg:phone":"+1 415 829 1900",
    "sg:postcode":"94105",
    "sg:province":"CA",
    "sg:tags":[
        "provider",
        "internet"
    ],
    "wof:name":"I Traffic",
    "wof:placetype":"venue"
},
  "geometry": {"coordinates":[-122.394902,37.791854],"type":"Point"}
}