{
  "type": "Feature",
  "properties": {
    "iso:country":"US",
    "sg:address":"8930 Cohasset Rd",
    "sg:city":"Chico",
    "sg:classifiers":[
        {
            "category":"Food & Beverages",
            "subcategory":"Groceries & Convenience Stores",
            "type":"Retail Goods"
        }
    ],
    "sg:phone":"+1 530 343 0974",
    "sg:postcode":"95973",
    "sg:province":"CA",
    "sg:tags":[
        "grocer"
    ],
    "wof:name":"Cohasset Country Store",
    "wof:placetype":"venue"
},
  "geometry": {"coordinates":[-121.749278,39.892889],"type":"Point"}
}