{
  "type": "Feature",
  "properties": {
    "iso:country":"US",
    "sg:address":"3089 Clairemont Drive Suite D",
    "sg:city":"San Diego",
    "sg:classifiers":[
        {
            "category":"Food & Beverages",
            "subcategory":"Bakery",
            "type":"Retail Goods"
        }
    ],
    "sg:phone":"+1 619 276 6948",
    "sg:postcode":"92117",
    "sg:province":"CA",
    "sg:tags":[
        "sandwich"
    ],
    "sg:website":"www.subway.com",
    "wof:name":"Subway",
    "wof:placetype":"venue"
},
  "geometry": {"coordinates":[-117.192564,32.794775],"type":"Point"}
}