{
  "type": "Feature",
  "properties": {
    "addr:full":"173 Lassen Cir Vacaville CA 95687",
    "addr:housenumber":"173",
    "addr:postcode":"95687",
    "addr:street":"Lassen Cir",
    "iso:country":"US",
    "sg:address":"173 Lassen Cir",
    "sg:city":"Vacaville",
    "sg:classifiers":[
        {
            "category":"Real Estate",
            "subcategory":"Real Estate Services",
            "type":"Services"
        },
        {
            "category":"Real Estate",
            "subcategory":"Real Estate Agent",
            "type":"Services"
        }
    ],
    "sg:phone":"+1 707 449 6939",
    "sg:postcode":"95687",
    "sg:province":"CA",
    "sg:tags":[
        "buyer",
        "management",
        "broker"
    ],
    "wof:name":"Eunice Cranmer Realty",
    "wof:placetype":"venue"
},
  "geometry": {"coordinates":[-121.947839,38.369093],"type":"Point"}
}