{
  "type": "Feature",
  "properties": {
    "iso:country":"US",
    "sg:address":"2070 Business Center Drive",
    "sg:city":"Irvine",
    "sg:classifiers":[
        {
            "category":"Professional",
            "subcategory":"Computer Services",
            "type":"Services"
        }
    ],
    "sg:phone":"+1 949 477 1080",
    "sg:postcode":"92612",
    "sg:province":"CA",
    "sg:tags":[
        "repair"
    ],
    "sg:website":"www.solutions-1st.com",
    "wof:name":"Solutions 1st",
    "wof:placetype":"venue"
},
  "geometry": {"coordinates":[-117.857429,33.678181],"type":"Point"}
}