{
  "type": "Feature",
  "properties": {
    "addr:full":"2299 19th Avenue San Francisco CA 94116",
    "addr:housenumber":"2299",
    "addr:postcode":"94116",
    "addr:street":"19Th Avenue",
    "iso:country":"US",
    "sg:address":"2299 19th Avenue",
    "sg:city":"San Francisco",
    "sg:classifiers":[
        {
            "category":"Health Services",
            "subcategory":"Dentist",
            "type":"Services"
        }
    ],
    "sg:phone":"+1 415 665 0272",
    "sg:postcode":"94116",
    "sg:province":"CA",
    "sg:website":"www.mysfdentist.net",
    "wof:name":"Michael W. Hing, DDS",
    "wof:placetype":"venue"
},
  "geometry": {"coordinates":[-122.47614400000001,37.745114],"type":"Point"}
}