{
  "type": "Feature",
  "properties": {
    "addr:full":"1919 Fulton Ave Sacramento CA 95825",
    "addr:housenumber":"1919",
    "addr:postcode":"95825",
    "addr:street":"Fulton Ave",
    "iso:country":"US",
    "sg:address":"1919 Fulton Ave",
    "sg:city":"Sacramento",
    "sg:classifiers":[
        {
            "category":"Shopping",
            "subcategory":"Mobile Phones",
            "type":"Retail Goods"
        }
    ],
    "sg:phone":"+1 916 979 1467",
    "sg:postcode":"95825",
    "sg:province":"CA",
    "wof:name":"RadioShack",
    "wof:placetype":"venue"
},
  "geometry": {"coordinates":[-121.401715,38.600187],"type":"Point"}
}