{
  "type": "Feature",
  "properties": {
    "addr:full":"4735 18th St San Francisco CA 94114",
    "addr:housenumber":"4735",
    "addr:postcode":"94114",
    "addr:street":"18Th St",
    "iso:country":"US",
    "sg:address":"4735 18th St",
    "sg:city":"San Francisco",
    "sg:classifiers":[
        {
            "category":"Building & Trades",
            "subcategory":"Electrical",
            "type":"Services"
        },
        {
            "category":"Professional",
            "subcategory":"Business Services",
            "type":"Services"
        }
    ],
    "sg:phone":"+1 415 865 9736",
    "sg:postcode":"94114",
    "sg:province":"CA",
    "sg:tags":[
        "teleconferencing",
        "electrical",
        "contractor"
    ],
    "wof:name":"Premiere Conferencing",
    "wof:placetype":"venue"
},
  "geometry": {"coordinates":[-122.444215,37.759776],"type":"Point"}
}