{
  "type": "Feature",
  "properties": {
    "addr:full":"2120 Carlmont Dr Belmont CA 94002",
    "addr:postcode":"2120;94002",
    "addr:street":"Carlmont Dr",
    "iso:country":"US",
    "sg:address":"2120 Carlmont Dr",
    "sg:city":"Belmont",
    "sg:classifiers":[
        {
            "category":"Personal",
            "subcategory":"Beauty Salon",
            "type":"Services"
        }
    ],
    "sg:phone":"+1 650 508 9344",
    "sg:postcode":"94002",
    "sg:province":"CA",
    "wof:name":"Skin Care By KERI",
    "wof:placetype":"venue"
},
  "geometry": {"coordinates":[-122.294208,37.50984],"type":"Point"}
}