{
  "type": "Feature",
  "properties": {
    "addr:full":"704 18th St Santa Monica CA 90402",
    "addr:housenumber":"704",
    "addr:postcode":"90402",
    "addr:street":"18Th St",
    "iso:country":"US",
    "sg:address":"704 18th St",
    "sg:city":"Santa Monica",
    "sg:classifiers":[
        {
            "category":"Government",
            "subcategory":"Court House",
            "type":"Public Place"
        }
    ],
    "sg:phone":"+1 310 229 1060",
    "sg:postcode":"90402",
    "sg:province":"CA",
    "sg:tags":[
        "legal"
    ],
    "wof:name":"Sohaili Hushmand",
    "wof:placetype":"venue"
},
  "geometry": {"coordinates":[-118.491556,34.035204],"type":"Point"}
}