{
  "type": "Feature",
  "properties": {
    "addr:full":"216 W Cabrillo Blvd Santa Barbara CA 93101",
    "addr:housenumber":"216",
    "addr:postcode":"93101",
    "addr:street":"W Cabrillo Blvd",
    "iso:country":"US",
    "sg:address":"216 W Cabrillo Blvd",
    "sg:city":"Santa Barbara",
    "sg:classifiers":[
        {
            "category":"Restaurant",
            "type":"Food & Drink"
        }
    ],
    "sg:phone":"+1 805 965 3269",
    "sg:postcode":"93101",
    "sg:province":"CA",
    "wof:name":"Sambo's Restaurants",
    "wof:placetype":"venue"
},
  "geometry": {"coordinates":[-119.692463,34.409529],"type":"Point"}
}