{
  "type": "Feature",
  "properties": {
    "addr:full":"4921 Robert J Mathews Pkwy El Dorado Hills CA 95762",
    "addr:housenumber":"4921",
    "addr:postcode":"95762",
    "addr:street":"Robert J Mathews Pkwy",
    "iso:country":"US",
    "sg:address":"4921 Robert J Mathews Pkwy",
    "sg:city":"El Dorado Hills",
    "sg:classifiers":[
        {
            "category":"Professional",
            "subcategory":"Management & Consulting",
            "type":"Services"
        }
    ],
    "sg:phone":"+1 916 933 0688",
    "sg:postcode":"95762",
    "sg:province":"CA",
    "sg:tags":[
        "consultant",
        "business"
    ],
    "sg:website":"www.gulf-pacific.com",
    "wof:name":"Gulf Pacific Inc",
    "wof:placetype":"venue"
},
  "geometry": {"coordinates":[-121.05758899999999,38.621649],"type":"Point"}
}