{
  "type": "Feature",
  "properties": {
    "addr:full":"1402 Lerma Rd El Monte CA 91733",
    "addr:housenumber":"1402",
    "addr:postcode":"91733",
    "addr:street":"Lerma Rd",
    "iso:country":"US",
    "sg:address":"1402 Lerma Rd",
    "sg:city":"El Monte",
    "sg:classifiers":[
        {
            "category":"Recreation",
            "type":"Entertainment"
        }
    ],
    "sg:phone":"+1 626 448 3641",
    "sg:postcode":"91733",
    "sg:province":"CA",
    "sg:tags":[
        "parks"
    ],
    "wof:name":"Dean Shively Park",
    "wof:placetype":"venue"
},
  "geometry": {"coordinates":[-118.047484,34.04539],"type":"Point"}
}