{
  "type": "Feature",
  "properties": {
    "addr:full":"415 7th St Petaluma CA 94952",
    "addr:housenumber":"415",
    "addr:postcode":"94952",
    "addr:street":"7Th St",
    "iso:country":"US",
    "sg:address":"415 7th St",
    "sg:city":"Petaluma",
    "sg:classifiers":[
        {
            "category":"Real Estate",
            "subcategory":"Real Estate Operator",
            "type":"Services"
        }
    ],
    "sg:phone":"+1 707 763 4645",
    "sg:postcode":"94952",
    "sg:province":"CA",
    "sg:tags":[
        "apartment"
    ],
    "wof:name":"Caliente Apartments",
    "wof:placetype":"venue"
},
  "geometry": {"coordinates":[-122.636404,38.227373],"type":"Point"}
}