{
  "type": "Feature",
  "properties": {
    "addr:full":"1620 N Pannes Ave Compton CA 90221",
    "addr:housenumber":"1620",
    "addr:postcode":"90221",
    "addr:street":"N Pannes Ave",
    "iso:country":"US",
    "sg:address":"1620 N Pannes Ave",
    "sg:city":"Compton",
    "sg:classifiers":[
        {
            "category":"Education",
            "subcategory":"School",
            "type":"Public Place"
        }
    ],
    "sg:phone":"+1 310 898 6180",
    "sg:postcode":"90221",
    "sg:province":"CA",
    "sg:tags":[
        "elementary"
    ],
    "sg:website":"http://www.compton.k12.ca.us",
    "wof:name":"Foster Elementary School",
    "wof:placetype":"venue"
},
  "geometry": {"coordinates":[-118.203003,33.905899],"type":"Point"}
}