{
  "type": "Feature",
  "properties": {
    "addr:full":"20781 Golden Rain Rd Riverside CA 92508",
    "addr:housenumber":"20781",
    "addr:postcode":"92508",
    "addr:street":"Golden Rain Rd",
    "iso:country":"US",
    "sg:address":"20781 Golden Rain Rd",
    "sg:city":"Riverside",
    "sg:classifiers":[
        {
            "category":"Building & Trades",
            "subcategory":"Construction",
            "type":"Services"
        }
    ],
    "sg:phone":"+1 951 687 3028",
    "sg:postcode":"92508",
    "sg:province":"CA",
    "sg:tags":[
        "repairing",
        "remodeling",
        "contractor"
    ],
    "wof:name":"Sherwood West Carpentry",
    "wof:placetype":"venue"
},
  "geometry": {"coordinates":[-117.297194,33.888016],"type":"Point"}
}