{
  "type": "Feature",
  "properties": {
    "addr:full":"1632 E. Cesar Chavez Ave Los Angeles CA 90033",
    "addr:housenumber":"1632",
    "addr:postcode":"90033",
    "addr:street":"E. Cesar Chavez Ave",
    "iso:country":"US",
    "sg:address":"1632 E. Cesar Chavez Ave",
    "sg:city":"Los Angeles",
    "sg:classifiers":[
        {
            "category":"Community Center",
            "type":"Public Place"
        }
    ],
    "sg:phone":"+1 888 840 8688",
    "sg:postcode":"90033",
    "sg:province":"CA",
    "sg:tags":[
        "medical"
    ],
    "sg:website":"www.nonprofitSTDtesting.org",
    "wof:name":"Los Angeles HIV/STD Testing",
    "wof:placetype":"venue"
},
  "geometry": {"coordinates":[-118.217902,34.051326],"type":"Point"}
}