{
  "type": "Feature",
  "properties": {
    "addr:full":"1815 Knoll Dr Ventura CA 93003",
    "addr:housenumber":"1815",
    "addr:postcode":"93003",
    "addr:street":"Knoll Dr",
    "iso:country":"US",
    "sg:address":"1815 Knoll Dr",
    "sg:city":"Ventura",
    "sg:classifiers":[
        {
            "category":"Insurance",
            "subcategory":"Hazard Insurance",
            "type":"Services"
        },
        {
            "category":"Insurance",
            "subcategory":"Insurance Agent",
            "type":"Services"
        },
        {
            "category":"Insurance",
            "subcategory":"Life Insurance",
            "type":"Services"
        },
        {
            "category":"Insurance",
            "subcategory":"Title Insurance",
            "type":"Services"
        }
    ],
    "sg:phone":"+1 805 642 4800",
    "sg:postcode":"93003",
    "sg:province":"CA",
    "sg:tags":[
        "auto",
        "commercial",
        "business",
        "homeowner"
    ],
    "sg:website":"http://www.farmersagent.com/causter/",
    "wof:name":"Chris Auster - Farmers Insurance",
    "wof:placetype":"venue"
},
  "geometry": {"coordinates":[-119.220125,34.256057],"type":"Point"}
}