{
  "type": "Feature",
  "properties": {
    "addr:full":"1512 la Loma Ave Bldg Cott Berkeley CA 94708",
    "addr:housenumber":"1512",
    "addr:postcode":"94708",
    "addr:street":"La Loma Ave Bldg",
    "iso:country":"US",
    "sg:address":"1512 la Loma Ave Bldg Cott",
    "sg:city":"Berkeley",
    "sg:classifiers":[
        {
            "category":"Professional",
            "subcategory":"Management & Consulting",
            "type":"Services"
        },
        {
            "category":"Professional",
            "subcategory":"Business Services",
            "type":"Services"
        }
    ],
    "sg:phone":"+1 510 540 7875",
    "sg:postcode":"94708",
    "sg:province":"CA",
    "sg:tags":[
        "consultant",
        "organizing",
        "services-household"
    ],
    "sg:website":"http://www.sequenceadvisors.com",
    "wof:name":"Sequence Advisors",
    "wof:placetype":"venue"
},
  "geometry": {"coordinates":[-122.25833900000001,37.881138],"type":"Point"}
}