{
  "type": "Feature",
  "properties": {
    "addr:full":"309 E Mountain View St Barstow CA 92311",
    "addr:housenumber":"309",
    "addr:postcode":"92311",
    "addr:street":"E Mountain View St",
    "iso:country":"US",
    "sg:address":"309 E Mountain View St",
    "sg:city":"Barstow",
    "sg:classifiers":[
        {
            "category":"Social Services",
            "type":"Services"
        }
    ],
    "sg:phone":"+1 760 256 0376",
    "sg:postcode":"92311",
    "sg:province":"CA",
    "sg:tags":[
        "counseling"
    ],
    "wof:name":"Oasis Counseling Ctr",
    "wof:placetype":"venue"
},
  "geometry": {"coordinates":[-117.02297799999999,34.893546],"type":"Point"}
}