{
  "type": "Feature",
  "properties": {
    "iso:country":"US",
    "sg:address":"12130 Sherman Way",
    "sg:city":"North Hollywood",
    "sg:classifiers":[
        {
            "category":"Wholesale",
            "subcategory":"Electrical",
            "type":"Manufacturing & Wholesale Goods"
        }
    ],
    "sg:phone":"+1 818 764 7420",
    "sg:postcode":"91605",
    "sg:province":"CA",
    "sg:tags":[
        "durable",
        "electronic"
    ],
    "sg:website":"www.vtplus.com",
    "wof:name":"Videotape Plus",
    "wof:placetype":"venue"
},
  "geometry": {"coordinates":[-118.401129,34.20112],"type":"Point"}
}