{
  "type": "Feature",
  "properties": {
    "addr:full":"809 Green Valley Rd Watsonville CA 95076",
    "addr:housenumber":"809",
    "addr:postcode":"95076",
    "addr:street":"Green Valley Rd",
    "iso:country":"US",
    "sg:address":"809 Green Valley Rd",
    "sg:city":"Watsonville",
    "sg:classifiers":[
        {
            "category":"Building & Trades",
            "subcategory":"Plumbing",
            "type":"Services"
        }
    ],
    "sg:phone":"+1 831 728 2324",
    "sg:postcode":"95076",
    "sg:province":"CA",
    "sg:tags":[
        "plumbing",
        "contractor"
    ],
    "wof:name":"Cabrillo Plumbing",
    "wof:placetype":"venue"
},
  "geometry": {"coordinates":[-121.76505899999999,36.965776],"type":"Point"}
}