{
  "type": "Feature",
  "properties": {
    "addr:full":"295 N Rampart St Orange CA 92868",
    "addr:housenumber":"295",
    "addr:postcode":"92868",
    "addr:street":"N Rampart St",
    "iso:country":"US",
    "sg:address":"295 N Rampart St",
    "sg:city":"Orange",
    "sg:classifiers":[
        {
            "category":"Education",
            "subcategory":"Special Training",
            "type":"Public Place"
        }
    ],
    "sg:phone":"+1 714 634 4767",
    "sg:postcode":"92868",
    "sg:province":"CA",
    "wof:name":"Dale Carnegie MGT Seminar",
    "wof:placetype":"venue"
},
  "geometry": {"coordinates":[-117.88220699999999,33.791802],"type":"Point"}
}