{
  "type": "Feature",
  "properties": {
    "iso:country":"US",
    "sg:address":"11151 Long Beach Blvd",
    "sg:city":"Lynwood",
    "sg:classifiers":[
        {
            "category":"Education",
            "subcategory":"Kindergarten",
            "type":"Public Place"
        }
    ],
    "sg:phone":"+1 310 886 0352",
    "sg:postcode":"90262",
    "sg:province":"CA",
    "sg:tags":[
        "school",
        "driving"
    ],
    "wof:name":"Redflex Traffic Systems",
    "wof:placetype":"venue"
},
  "geometry": {"coordinates":[-118.21187500000001,33.930726],"type":"Point"}
}