{
  "type": "Feature",
  "properties": {
    "iso:country":"US",
    "sg:address":"860 Geary Street Suite 101-A",
    "sg:city":"San Francisco",
    "sg:classifiers":[
        {
            "category":"Autos & Motor Vehicles",
            "subcategory":"Automobile Sales",
            "type":"Retail Goods"
        }
    ],
    "sg:phone":"+1 415 929 5254",
    "sg:postcode":"94109",
    "sg:province":"CA",
    "sg:tags":[
        "limo"
    ],
    "sg:website":"www.whitegloveslimousine.com",
    "wof:name":"White Gloves Limousine Service",
    "wof:placetype":"venue"
},
  "geometry": {"coordinates":[-122.417479,37.786468],"type":"Point"}
}