{
  "type": "Feature",
  "properties": {
    "addr:full":"444 S Flower St Los Angeles CA 90071",
    "addr:housenumber":"444",
    "addr:postcode":"90071",
    "addr:street":"S Flower St",
    "iso:country":"US",
    "sg:address":"444 S Flower St",
    "sg:city":"Los Angeles",
    "sg:classifiers":[
        {
            "category":"Professional",
            "subcategory":"Management & Consulting",
            "type":"Services"
        }
    ],
    "sg:phone":"+1 213 622 4424",
    "sg:postcode":"90071",
    "sg:province":"CA",
    "wof:name":"Alcoa Wireless Services Inc",
    "wof:placetype":"venue"
},
  "geometry": {"coordinates":[-118.255578,34.052093],"type":"Point"}
}