{
  "type": "Feature",
  "properties": {
    "addr:full":"1423 J St Sacramento CA 95814",
    "addr:housenumber":"1423",
    "addr:postcode":"95814",
    "addr:street":"J St",
    "iso:country":"US",
    "sg:address":"1423 J St",
    "sg:city":"Sacramento",
    "sg:classifiers":[
        {
            "category":"Building & Trades",
            "subcategory":"Construction",
            "type":"Services"
        }
    ],
    "sg:phone":"+1 916 331 1100",
    "sg:postcode":"95814",
    "sg:province":"CA",
    "sg:tags":[
        "masonry",
        "contractor"
    ],
    "wof:name":"Frazier Masonry Corp",
    "wof:placetype":"venue"
},
  "geometry": {"coordinates":[-121.486755,38.578619],"type":"Point"}
}