{
  "type": "Feature",
  "properties": {
    "iso:country":"US",
    "sg:address":"3151 Airway Ave",
    "sg:city":"Costa Mesa",
    "sg:classifiers":[
        {
            "category":"Education",
            "subcategory":"Special Training",
            "type":"Public Place"
        }
    ],
    "sg:phone":"+1 714 751 5708",
    "sg:postcode":"92626",
    "sg:province":"CA",
    "sg:tags":[
        "center"
    ],
    "wof:name":"Enhancement Courses",
    "wof:placetype":"venue"
},
  "geometry": {"coordinates":[-117.8706,33.68015],"type":"Point"}
}