{
  "type": "Feature",
  "properties": {
    "iso:country":"US",
    "sg:address":"24801 Sunnymead Blvd",
    "sg:city":"Moreno Valley",
    "sg:classifiers":[
        {
            "category":"Bars & Pubs",
            "type":"Food & Drink"
        }
    ],
    "sg:phone":"+1 951 485 0203",
    "sg:postcode":"92553",
    "sg:province":"CA",
    "sg:tags":[
        "lounge",
        "cocktail"
    ],
    "wof:name":"Bahama Mama's",
    "wof:placetype":"venue"
},
  "geometry": {"coordinates":[-117.228291,33.939027],"type":"Point"}
}