{
  "type": "Feature",
  "properties": {
    "iso:country":"US",
    "sg:address":"7617 Auburn Blvd",
    "sg:city":"Citrus Heights",
    "sg:classifiers":[
        {
            "category":"Retail",
            "subcategory":"Auto Repair",
            "type":"Services"
        }
    ],
    "sg:phone":"+1 916 725 2021",
    "sg:postcode":"95610",
    "sg:province":"CA",
    "sg:tags":[
        "muffler",
        "exhaust",
        "system"
    ],
    "wof:name":"Gwin's Muffler Svc",
    "wof:placetype":"venue"
},
  "geometry": {"coordinates":[-121.290392,38.703951],"type":"Point"}
}