{
  "type": "Feature",
  "properties": {
    "iso:country":"US",
    "sg:address":"2220 Chester Ave",
    "sg:city":"Bakersfield",
    "sg:classifiers":[
        {
            "category":"Restaurant",
            "type":"Food & Drink"
        }
    ],
    "sg:menulink":"http://www.allmenus.com/ca/bakersfield/178763-jack-in-the-box/menu/",
    "sg:phone":"+1 661 324 9330",
    "sg:postcode":"93301",
    "sg:province":"CA",
    "sg:tags":[
        "burger",
        "american"
    ],
    "wof:name":"Jack in the Box",
    "wof:placetype":"venue"
},
  "geometry": {"coordinates":[-119.01836900000001,35.379689],"type":"Point"}
}