{
  "type": "Feature",
  "properties": {
    "addr:full":"6141 Franklin Ave Los Angeles CA 90028",
    "addr:housenumber":"6141",
    "addr:postcode":"90028",
    "addr:street":"Franklin Ave",
    "iso:country":"US",
    "sg:address":"6141 Franklin Ave",
    "sg:city":"Los Angeles",
    "sg:classifiers":[
        {
            "category":"Travel",
            "subcategory":"Hotels & Motels",
            "type":"Entertainment"
        }
    ],
    "sg:phone":"+1 323 464 5181",
    "sg:postcode":"90028",
    "sg:province":"CA",
    "sg:website":"book.bestwestern.com/bestwestern...",
    "wof:name":"Best Western Hollywood Hills",
    "wof:placetype":"venue"
},
  "geometry": {"coordinates":[-118.322998,34.105099],"type":"Point"}
}