{
  "type": "Feature",
  "properties": {
    "addr:full":"230 W Laurel St San Diego CA 92101",
    "addr:housenumber":"230",
    "addr:postcode":"92101",
    "addr:street":"W Laurel St",
    "iso:country":"US",
    "sg:address":"230 W Laurel St",
    "sg:city":"San Diego",
    "sg:classifiers":[
        {
            "category":"Real Estate",
            "subcategory":"Real Estate Operator",
            "type":"Services"
        }
    ],
    "sg:phone":"+1 619 232 0475",
    "sg:postcode":"92101",
    "sg:province":"CA",
    "sg:tags":[
        "condominium"
    ],
    "wof:name":"Brittany Tower Condominiums",
    "wof:placetype":"venue"
},
  "geometry": {"coordinates":[-117.165491,32.731431],"type":"Point"}
}