{
  "type": "Feature",
  "properties": {
    "iso:country":"US",
    "sg:address":"333 W Broadway",
    "sg:city":"Long Beach",
    "sg:classifiers":[
        {
            "category":"Utilities",
            "subcategory":"Telephone",
            "type":"Services"
        }
    ],
    "sg:phone":"+1 714 350 3115",
    "sg:postcode":"90802",
    "sg:province":"CA",
    "sg:tags":[
        "communications"
    ],
    "wof:name":"Mis Dept Inc",
    "wof:placetype":"venue"
},
  "geometry": {"coordinates":[-118.196297,33.769368],"type":"Point"}
}