{
  "type": "Feature",
  "properties": {
    "addr:full":"2065 E Belmont Ave Fresno CA 93701",
    "addr:housenumber":"2065",
    "addr:postcode":"93701",
    "addr:street":"E Belmont Ave",
    "iso:country":"US",
    "sg:address":"2065 E Belmont Ave",
    "sg:city":"Fresno",
    "sg:classifiers":[
        {
            "category":"Retail",
            "subcategory":"Auto Repair",
            "type":"Services"
        }
    ],
    "sg:phone":"+1 559 270 2355",
    "sg:postcode":"93701",
    "sg:province":"CA",
    "sg:tags":[
        "wrecker"
    ],
    "wof:name":"Two Thumbs Up Towing",
    "wof:placetype":"venue"
},
  "geometry": {"coordinates":[-119.785601,36.750449],"type":"Point"}
}