{
  "type": "Feature",
  "properties": {
    "addr:full":"20800 Madrona Ave Torrance CA 90503",
    "addr:housenumber":"20800",
    "addr:postcode":"90503",
    "addr:street":"Madrona Ave",
    "iso:country":"US",
    "sg:address":"20800 Madrona Ave",
    "sg:city":"Torrance",
    "sg:classifiers":[
        {
            "category":"Restaurant",
            "type":"Food & Drink"
        }
    ],
    "sg:phone":"+1 310 533 8602",
    "sg:postcode":"90503",
    "sg:province":"CA",
    "sg:tags":[
        "caterer"
    ],
    "wof:name":"Creative Cuisine Concepts",
    "wof:placetype":"venue"
},
  "geometry": {"coordinates":[-118.344646,33.840344],"type":"Point"}
}