{
  "type": "Feature",
  "properties": {
    "addr:full":"30313 Canwood St Agoura Hills CA 91301",
    "addr:housenumber":"30313",
    "addr:postcode":"91301",
    "addr:street":"Canwood St",
    "iso:country":"US",
    "sg:address":"30313 Canwood St",
    "sg:city":"Agoura Hills",
    "sg:classifiers":[
        {
            "category":"Health Services",
            "subcategory":"Optometrist",
            "type":"Services"
        }
    ],
    "sg:phone":"+1 818 991 3937",
    "sg:postcode":"91301",
    "sg:province":"CA",
    "wof:name":"James J Giraldi OD",
    "wof:placetype":"venue"
},
  "geometry": {"coordinates":[-118.781306,34.148054],"type":"Point"}
}