{
  "type": "Feature",
  "properties": {
    "addr:full":"832 N Juniper St Escondido CA 92025",
    "addr:housenumber":"832",
    "addr:postcode":"92025",
    "addr:street":"N Juniper St",
    "iso:country":"US",
    "sg:address":"832 N Juniper St",
    "sg:city":"Escondido",
    "sg:classifiers":[
        {
            "category":"Real Estate",
            "subcategory":"Real Estate Operator",
            "type":"Services"
        }
    ],
    "sg:phone":"+1 760 747 3549",
    "sg:postcode":"92025",
    "sg:province":"CA",
    "sg:tags":[
        "apartment"
    ],
    "wof:name":"Mission Terrace Apartments Inc",
    "wof:placetype":"venue"
},
  "geometry": {"coordinates":[-117.083549,33.131528],"type":"Point"}
}