{
  "type": "Feature",
  "properties": {
    "addr:full":"44 Montgomery St Ste 1670 San Francisco CA 94104",
    "addr:housenumber":"44",
    "addr:postcode":"94104",
    "addr:street":"Montgomery St Ste 1670",
    "iso:country":"US",
    "sg:address":"44 Montgomery St Ste 1670",
    "sg:city":"San Francisco",
    "sg:classifiers":[
        {
            "category":"Professional",
            "subcategory":"Lawyer & Legal Services",
            "type":"Services"
        }
    ],
    "sg:phone":"+1 415 984 9915",
    "sg:postcode":"94104",
    "sg:province":"CA",
    "wof:name":"Huster Law Group",
    "wof:placetype":"venue"
},
  "geometry": {"coordinates":[-122.40190800000001,37.789554],"type":"Point"}
}