{
  "type": "Feature",
  "properties": {
    "addr:full":"1924 Stine Rd Bakersfield CA 93309",
    "addr:housenumber":"1924",
    "addr:postcode":"93309",
    "addr:street":"Stine Rd",
    "iso:country":"US",
    "sg:address":"1924 Stine Rd",
    "sg:city":"Bakersfield",
    "sg:classifiers":[
        {
            "category":"Real Estate",
            "subcategory":"Real Estate Agent",
            "type":"Services"
        }
    ],
    "sg:phone":"+1 661 397 8441",
    "sg:postcode":"93309",
    "sg:province":"CA",
    "wof:name":"Townhouse West",
    "wof:placetype":"venue"
},
  "geometry": {"coordinates":[-119.05238199999999,35.336819],"type":"Point"}
}