{
  "type": "Feature",
  "properties": {
    "iso:country":"US",
    "sg:address":"865 Market Street",
    "sg:city":"San Francisco",
    "sg:classifiers":[
        {
            "category":"Shopping",
            "subcategory":"Beauty & Cosmetics",
            "type":"Retail Goods"
        }
    ],
    "sg:phone":"+1 415 537 9440",
    "sg:postcode":"94103",
    "sg:province":"CA",
    "sg:tags":[
        "supply"
    ],
    "wof:name":"Origins",
    "wof:placetype":"venue"
},
  "geometry": {"coordinates":[-122.40799699999999,37.784199],"type":"Point"}
}