{
  "type": "Feature",
  "properties": {
    "iso:country":"US",
    "sg:address":"399 Elmhurst St",
    "sg:city":"Hayward",
    "sg:classifiers":[
        {
            "category":"Government",
            "subcategory":"Office",
            "type":"Public Place"
        }
    ],
    "sg:phone":"+1 510 670 5480",
    "sg:postcode":"94544",
    "sg:province":"CA",
    "wof:name":"Alameda County Roads Dept",
    "wof:placetype":"venue"
},
  "geometry": {"coordinates":[-122.09286899999999,37.656434],"type":"Point"}
}