{
  "type": "Feature",
  "properties": {
    "iso:country":"US",
    "sg:address":"1042 Brea Mall",
    "sg:city":"Brea",
    "sg:phone":"+1 714 671 7965",
    "sg:postcode":"92821",
    "sg:province":"CA",
    "sg:website":"http://www.cathyjeanshoes.com",
    "wof:name":"Cathy Jean",
    "wof:placetype":"venue"
},
  "geometry": {"coordinates":[-117.886047,33.913402],"type":"Point"}
}