{
  "type": "Feature",
  "properties": {
    "addr:full":"445 Eden St Lodi CA 95240",
    "addr:housenumber":"445",
    "addr:postcode":"95240",
    "addr:street":"Eden St",
    "iso:country":"US",
    "sg:address":"445 Eden St",
    "sg:city":"Lodi",
    "sg:classifiers":[
        {
            "category":"Organizations",
            "subcategory":"Religious Organization",
            "type":"Services"
        }
    ],
    "sg:phone":"+1 209 367 8565",
    "sg:postcode":"95240",
    "sg:province":"CA",
    "sg:tags":[
        "church"
    ],
    "wof:name":"Templo Gethsemani Cladic",
    "wof:placetype":"venue"
},
  "geometry": {"coordinates":[-121.26331500000001,38.127939],"type":"Point"}
}