{
  "type": "Feature",
  "properties": {
    "iso:country":"US",
    "sg:address":"1351 Brookview Dr",
    "sg:city":"Concord",
    "sg:classifiers":[
        {
            "category":"Taxi",
            "type":"Transportation"
        }
    ],
    "sg:phone":"+1 925 686 3519",
    "sg:postcode":"94520",
    "sg:province":"CA",
    "sg:tags":[
        "independent",
        "cab"
    ],
    "wof:name":"Diamond Cab",
    "wof:placetype":"venue"
},
  "geometry": {"coordinates":[-122.05110500000001,37.956256],"type":"Point"}
}