{
  "type": "Feature",
  "properties": {
    "iso:country":"US",
    "sg:address":"29680 Skyline Dr",
    "sg:city":"Tehachapi",
    "sg:classifiers":[
        {
            "category":"Professional",
            "type":"Services"
        }
    ],
    "sg:phone":"+1 661 821 3206",
    "sg:postcode":"93561",
    "sg:province":"CA",
    "wof:name":"Ronald M Hayton",
    "wof:placetype":"venue"
},
  "geometry": {"coordinates":[-118.661365,35.142483],"type":"Point"}
}