{
  "type": "Feature",
  "properties": {
    "addr:full":"111 Neal St Pleasanton CA 94566",
    "addr:housenumber":"111",
    "addr:postcode":"94566",
    "addr:street":"Neal St",
    "iso:country":"US",
    "sg:address":"111 Neal St",
    "sg:city":"Pleasanton",
    "sg:classifiers":[
        {
            "category":"Home & Garden",
            "subcategory":"Household Appliances",
            "type":"Retail Goods"
        }
    ],
    "sg:phone":"+1 925 846 6150",
    "sg:postcode":"94566",
    "sg:province":"CA",
    "wof:name":"Appliance Master",
    "wof:placetype":"venue"
},
  "geometry": {"coordinates":[-121.873007,37.659151],"type":"Point"}
}