{
  "type": "Feature",
  "properties": {
    "iso:country":"US",
    "sg:address":"18316 Sierra Hwy",
    "sg:city":"Canyon Country",
    "sg:classifiers":[
        {
            "category":"Shopping",
            "subcategory":"Computers & Home Electronics",
            "type":"Retail Goods"
        }
    ],
    "sg:phone":"+1 661 252 6942",
    "sg:postcode":"91351",
    "sg:province":"CA",
    "sg:tags":[
        "television",
        "radio"
    ],
    "wof:name":"Exclusive VCR Repair Co",
    "wof:placetype":"venue"
},
  "geometry": {"coordinates":[-118.45419099999999,34.419291],"type":"Point"}
}