{
  "type": "Feature",
  "properties": {
    "iso:country":"US",
    "sg:address":"1125 Detroit Ave",
    "sg:city":"Concord",
    "sg:classifiers":[
        {
            "category":"Autos & Motor Vehicles",
            "subcategory":"Automobile Sales",
            "type":"Retail Goods"
        }
    ],
    "sg:phone":"+1 925 691 8265",
    "sg:postcode":"94520",
    "sg:province":"CA",
    "sg:tags":[
        "car",
        "dealer"
    ],
    "wof:name":"Concord Auto & Rv",
    "wof:placetype":"venue"
},
  "geometry": {"coordinates":[-122.034143,37.960469],"type":"Point"}
}