{
  "type": "Feature",
  "properties": {
    "addr:full":"7715 W 80th St Playa Del Rey CA 90293",
    "addr:housenumber":"7715",
    "addr:postcode":"90293",
    "addr:street":"W 80Th St",
    "iso:country":"US",
    "sg:address":"7715 W 80th St",
    "sg:city":"Playa Del Rey",
    "sg:classifiers":[
        {
            "category":"Professional",
            "type":"Services"
        }
    ],
    "sg:phone":"+1 310 301 9128",
    "sg:postcode":"90293",
    "sg:province":"CA",
    "wof:name":"Treasured Endeavours",
    "wof:placetype":"venue"
},
  "geometry": {"coordinates":[-118.432588,33.963392],"type":"Point"}
}