{
  "type": "Feature",
  "properties": {
    "addr:full":"18714 Bryant St Northridge CA 91324",
    "addr:housenumber":"18714",
    "addr:postcode":"91324",
    "addr:street":"Bryant St",
    "iso:country":"US",
    "sg:address":"18714 Bryant St",
    "sg:city":"Northridge",
    "sg:classifiers":[
        {
            "category":"Home & Garden",
            "subcategory":"Furniture",
            "type":"Retail Goods"
        }
    ],
    "sg:phone":"+1 818 349 9707",
    "sg:postcode":"91324",
    "sg:province":"CA",
    "sg:tags":[
        "carpentry",
        "contractor"
    ],
    "wof:name":"Woodworks",
    "wof:placetype":"venue"
},
  "geometry": {"coordinates":[-118.54348299999999,34.227251],"type":"Point"}
}