{
  "type": "Feature",
  "properties": {
    "iso:country":"US",
    "sg:address":"2609 N San Fernando Blvd",
    "sg:city":"Burbank",
    "sg:classifiers":[
        {
            "category":"Manufacturing",
            "subcategory":"Tools & Machinery",
            "type":"Manufacturing & Wholesale Goods"
        }
    ],
    "sg:phone":"+1 818 848 6277",
    "sg:postcode":"91504",
    "sg:province":"CA",
    "sg:tags":[
        "industrial",
        "mfg"
    ],
    "wof:name":"Circle Weld Manufacturing",
    "wof:placetype":"venue"
},
  "geometry": {"coordinates":[-118.339912,34.19917],"type":"Point"}
}