{
  "type": "Feature",
  "properties": {
    "addr:full":"22 Mar Monte Ave Watsonville CA 95076",
    "addr:housenumber":"22",
    "addr:postcode":"95076",
    "addr:street":"Mar Monte Ave",
    "iso:country":"US",
    "sg:address":"22 Mar Monte Ave",
    "sg:city":"Watsonville",
    "sg:classifiers":[
        {
            "category":"Food & Beverages",
            "subcategory":"Bakery",
            "type":"Retail Goods"
        }
    ],
    "sg:phone":"+1 831 662 3300",
    "sg:postcode":"95076",
    "sg:province":"CA",
    "wof:name":"Chiffonos Gourmet Desserts",
    "wof:placetype":"venue"
},
  "geometry": {"coordinates":[-121.852092,36.946031],"type":"Point"}
}