{
  "type": "Feature",
  "properties": {
    "addr:full":"192 Fox Hills Mall Culver City CA 90230",
    "addr:housenumber":"192",
    "addr:postcode":"90230",
    "addr:street":"Fox Hills Mall",
    "iso:country":"US",
    "sg:address":"192 Fox Hills Mall",
    "sg:city":"Culver City",
    "sg:classifiers":[
        {
            "category":"Shopping",
            "subcategory":"Optician",
            "type":"Retail Goods"
        }
    ],
    "sg:phone":"+1 310 390 1902",
    "sg:postcode":"90230",
    "sg:province":"CA",
    "sg:tags":[
        "eyewear"
    ],
    "wof:name":"Lenscrafters",
    "wof:placetype":"venue"
},
  "geometry": {"coordinates":[-118.394497,33.984516],"type":"Point"}
}