{
  "type": "Feature",
  "properties": {
    "addr:full":"225 N Harbor Blvd Fullerton CA 92832",
    "addr:housenumber":"225",
    "addr:postcode":"92832",
    "addr:street":"N Harbor Blvd",
    "iso:country":"US",
    "sg:address":"225 N Harbor Blvd",
    "sg:city":"Fullerton",
    "sg:classifiers":[
        {
            "category":"Restaurant",
            "type":"Food & Drink"
        }
    ],
    "sg:phone":"+1 714 871 9418",
    "sg:postcode":"92832",
    "sg:province":"CA",
    "sg:tags":[
        "japanese"
    ],
    "sg:website":"www.mitsueshabu.com",
    "wof:name":"Mitsu E Shabu Shabu",
    "wof:placetype":"venue"
},
  "geometry": {"coordinates":[-117.92440000000001,33.871719],"type":"Point"}
}