{
  "type": "Feature",
  "properties": {
    "iso:country":"US",
    "sg:address":"445 Aldo Ave",
    "sg:city":"Santa Clara",
    "sg:classifiers":[
        {
            "category":"Wholesale",
            "subcategory":"Durable Goods & Equipment",
            "type":"Manufacturing & Wholesale Goods"
        }
    ],
    "sg:phone":"+1 408 749 1688",
    "sg:postcode":"95054",
    "sg:province":"CA",
    "sg:tags":[
        "exporter"
    ],
    "wof:name":"KFI Technology Corp",
    "wof:placetype":"venue"
},
  "geometry": {"coordinates":[-121.93932700000001,37.387685],"type":"Point"}
}