{
  "type": "Feature",
  "properties": {
    "addr:full":"3138 Bilbo Dr San Jose CA 95121",
    "addr:housenumber":"3138",
    "addr:postcode":"95121",
    "addr:street":"Bilbo Dr",
    "iso:country":"US",
    "sg:address":"3138 Bilbo Dr",
    "sg:city":"San Jose",
    "sg:classifiers":[
        {
            "category":"Professional",
            "subcategory":"Business Services",
            "type":"Services"
        }
    ],
    "sg:phone":"+1 408 629 4501",
    "sg:postcode":"95121",
    "sg:province":"CA",
    "sg:tags":[
        "transcribing",
        "disc"
    ],
    "wof:name":"Accu Med Transcription",
    "wof:placetype":"venue"
},
  "geometry": {"coordinates":[-121.819958,37.302727],"type":"Point"}
}