{
  "type": "Feature",
  "properties": {
    "addr:full":"937 Spring St Placerville CA 95667",
    "addr:housenumber":"937",
    "addr:postcode":"95667",
    "addr:street":"Spring St",
    "iso:country":"US",
    "sg:address":"937 Spring St",
    "sg:city":"Placerville",
    "sg:classifiers":[
        {
            "category":"Government",
            "subcategory":"Office",
            "type":"Public Place"
        }
    ],
    "sg:phone":"+1 530 621 6176",
    "sg:postcode":"95667",
    "sg:province":"CA",
    "sg:tags":[
        "county",
        "resource"
    ],
    "wof:name":"El Dorado County WIC Program",
    "wof:placetype":"venue"
},
  "geometry": {"coordinates":[-120.80262500000001,38.732165],"type":"Point"}
}