{
  "type": "Feature",
  "properties": {
    "addr:full":"729 Ashbourne Dr Sunnyvale CA 94087",
    "addr:housenumber":"729",
    "addr:postcode":"94087",
    "addr:street":"Ashbourne Dr",
    "iso:country":"US",
    "sg:address":"729 Ashbourne Dr",
    "sg:city":"Sunnyvale",
    "sg:classifiers":[
        {
            "category":"Professional",
            "subcategory":"Accounting & Tax Preparation",
            "type":"Services"
        }
    ],
    "sg:phone":"+1 408 720 8092",
    "sg:postcode":"94087",
    "sg:province":"CA",
    "sg:tags":[
        "bookkeeping",
        "general"
    ],
    "wof:name":"E B Accounting & Tax Svc",
    "wof:placetype":"venue"
},
  "geometry": {"coordinates":[-122.02111600000001,37.351344],"type":"Point"}
}