{
  "type": "Feature",
  "properties": {
    "addr:full":"2190 Ridgewood Dr Eureka CA 95503",
    "addr:housenumber":"2190",
    "addr:postcode":"95503",
    "addr:street":"Ridgewood Dr",
    "iso:country":"US",
    "sg:address":"2190 Ridgewood Dr",
    "sg:city":"Eureka",
    "sg:classifiers":[
        {
            "category":"Professional",
            "subcategory":"Computer Services",
            "type":"Services"
        }
    ],
    "sg:phone":"+1 707 476 8896",
    "sg:postcode":"95503",
    "sg:province":"CA",
    "sg:tags":[
        "repair"
    ],
    "wof:name":"Dynamic Data Solutions",
    "wof:placetype":"venue"
},
  "geometry": {"coordinates":[-124.144752,40.733342],"type":"Point"}
}