{
  "type": "Feature",
  "properties": {
    "addr:full":"3040 S Robertson Blvd Los Angeles CA 90230",
    "addr:housenumber":"3040",
    "addr:postcode":"90230",
    "addr:street":"S Robertson Blvd",
    "iso:country":"US",
    "sg:address":"3040 S Robertson Blvd",
    "sg:city":"Los Angeles",
    "sg:classifiers":[
        {
            "category":"Retail",
            "subcategory":"Auto Repair",
            "type":"Services"
        }
    ],
    "sg:phone":"+1 310 836 2448",
    "sg:postcode":"90230",
    "sg:province":"CA",
    "sg:tags":[
        "body",
        "shop",
        "painting",
        "automobile"
    ],
    "sg:website":"www.lemansbody.com/",
    "wof:name":"Le Mans Auto Body",
    "wof:placetype":"venue"
},
  "geometry": {"coordinates":[-118.390332,34.031952],"type":"Point"}
}