{
  "type": "Feature",
  "properties": {
    "addr:full":"8055 Lankershim Blvd Ste 16 North Hollywood CA 91605",
    "addr:postcode":"8055;91605",
    "addr:street":"Lankershim Blvd Ste 16",
    "iso:country":"US",
    "sg:address":"8055 Lankershim Blvd Ste 16",
    "sg:city":"North Hollywood",
    "sg:classifiers":[
        {
            "category":"Professional",
            "subcategory":"Computer Services",
            "type":"Services"
        }
    ],
    "sg:phone":"+1 818 767 1391",
    "sg:postcode":"91605",
    "sg:province":"CA",
    "sg:tags":[
        "stereo",
        "installation"
    ],
    "wof:name":"Alarming Sounds",
    "wof:placetype":"venue"
},
  "geometry": {"coordinates":[-118.38800000000001,34.217098],"type":"Point"}
}