{
  "type": "Feature",
  "properties": {
    "iso:country":"US",
    "sg:address":"3359 E Foothill Blvd",
    "sg:city":"Pasadena",
    "sg:classifiers":[
        {
            "category":"Shopping",
            "subcategory":"Bicycles & Sporting Goods",
            "type":"Retail Goods"
        }
    ],
    "sg:phone":"+1 626 351 1843",
    "sg:postcode":"91107",
    "sg:province":"CA",
    "sg:website":"www.chickssportinggoods.com",
    "wof:name":"Dick's Sporting Goods",
    "wof:placetype":"venue"
},
  "geometry": {"coordinates":[-118.08200100000001,34.1502],"type":"Point"}
}