{
  "type": "Feature",
  "properties": {
    "iso:country":"US",
    "sg:address":"6401 Mount Ada Rd",
    "sg:city":"San Diego",
    "sg:classifiers":[
        {
            "category":"Real Estate",
            "subcategory":"Real Estate Operator",
            "type":"Services"
        }
    ],
    "sg:phone":"+1 858 268 1133",
    "sg:postcode":"92111",
    "sg:province":"CA",
    "sg:tags":[
        "apartment"
    ],
    "wof:name":"Parkwood Apartments",
    "wof:placetype":"venue"
},
  "geometry": {"coordinates":[-117.174616,32.819274],"type":"Point"}
}