{
  "type": "Feature",
  "properties": {
    "iso:country":"US",
    "sg:address":"220 Montgomery St",
    "sg:city":"San Francisco",
    "sg:classifiers":[
        {
            "category":"Professional",
            "subcategory":"Employment Agencies",
            "type":"Services"
        }
    ],
    "sg:phone":"+1 415 989 6252",
    "sg:postcode":"94104",
    "sg:province":"CA",
    "sg:tags":[
        "opportunity"
    ],
    "wof:name":"Interplace",
    "wof:placetype":"venue"
},
  "geometry": {"coordinates":[-122.402466,37.791721],"type":"Point"}
}