{
  "type": "Feature",
  "properties": {
    "addr:full":"2462 Shattuck Ave Berkeley CA 94704",
    "addr:housenumber":"2462",
    "addr:postcode":"94704",
    "addr:street":"Shattuck Ave",
    "iso:country":"US",
    "sg:address":"2462 Shattuck Ave",
    "sg:city":"Berkeley",
    "sg:classifiers":[
        {
            "category":"Retail",
            "subcategory":"Self-service Laundry",
            "type":"Services"
        }
    ],
    "sg:phone":"+1 510 841 1787",
    "sg:postcode":"94704",
    "sg:province":"CA",
    "sg:tags":[
        "dry",
        "dryer",
        "cleaning",
        "operated",
        "washer",
        "coin"
    ],
    "wof:name":"Central Launderette",
    "wof:placetype":"venue"
},
  "geometry": {"coordinates":[-122.267528,37.86463],"type":"Point"}
}