{
  "type": "Feature",
  "properties": {
    "iso:country":"US",
    "sg:address":"11059 Lamby Ln",
    "sg:city":"Grass Valley",
    "sg:classifiers":[
        {
            "category":"Building & Trades",
            "subcategory":"Construction",
            "type":"Services"
        }
    ],
    "sg:phone":"+1 530 272 6239",
    "sg:postcode":"95945",
    "sg:province":"CA",
    "sg:tags":[
        "tile",
        "dealer"
    ],
    "wof:name":"Brico Tile",
    "wof:placetype":"venue"
},
  "geometry": {"coordinates":[-121.07943,39.219967],"type":"Point"}
}