{
  "type": "Feature",
  "properties": {
    "iso:country":"US",
    "sg:address":"12191 Ventura Blvd",
    "sg:city":"Studio City",
    "sg:classifiers":[
        {
            "category":"Banks & Credit Unions",
            "subcategory":"Bank",
            "type":"Services"
        }
    ],
    "sg:phone":"+1 818 766 6142",
    "sg:postcode":"91604",
    "sg:province":"CA",
    "wof:name":"Citibank West F S B",
    "wof:placetype":"venue"
},
  "geometry": {"coordinates":[-118.398003,34.1432],"type":"Point"}
}