{
  "type": "Feature",
  "properties": {
    "iso:country":"US",
    "sg:address":"1502 W el Camino Ave",
    "sg:city":"Sacramento",
    "sg:classifiers":[
        {
            "category":"Insurance",
            "subcategory":"Insurance Agent",
            "type":"Services"
        }
    ],
    "sg:phone":"+1 916 286 7766",
    "sg:postcode":"95833",
    "sg:province":"CA",
    "wof:name":"Baja Insurance Svc",
    "wof:placetype":"venue"
},
  "geometry": {"coordinates":[-121.49454,38.61284],"type":"Point"}
}