{
  "type": "Feature",
  "properties": {
    "iso:country":"US",
    "sg:address":"12265 Scripps Poway Pkwy",
    "sg:city":"Poway",
    "sg:classifiers":[
        {
            "category":"Sports & Exercise",
            "subcategory":"Gym",
            "type":"Entertainment"
        }
    ],
    "sg:phone":"+1 858 578 2225",
    "sg:postcode":"92064",
    "sg:province":"CA",
    "sg:tags":[
        "club",
        "health",
        "studio",
        "gymnasium"
    ],
    "wof:name":"Healthy Exercise",
    "wof:placetype":"venue"
},
  "geometry": {"coordinates":[-117.052953,32.938774],"type":"Point"}
}