{
  "type": "Feature",
  "properties": {
    "addr:full":"3720 Easton Dr Bakersfield CA 93309",
    "addr:housenumber":"3720",
    "addr:postcode":"93309",
    "addr:street":"Easton Dr",
    "iso:country":"US",
    "sg:address":"3720 Easton Dr",
    "sg:city":"Bakersfield",
    "sg:classifiers":[
        {
            "category":"Retail",
            "subcategory":"Photofinishing",
            "type":"Services"
        }
    ],
    "sg:phone":"+1 661 835 1298",
    "sg:postcode":"93309",
    "sg:province":"CA",
    "sg:tags":[
        "photo",
        "finishing"
    ],
    "wof:name":"Timeless Photo",
    "wof:placetype":"venue"
},
  "geometry": {"coordinates":[-119.044634,35.368222],"type":"Point"}
}