{
  "type": "Feature",
  "properties": {
    "addr:full":"2430 Sand Creek Rd Brentwood CA 94513",
    "addr:housenumber":"2430",
    "addr:postcode":"ca 94513",
    "addr:street":"Sand Creek Rd",
    "iso:country":"US",
    "sg:address":"2430 Sand Creek Rd",
    "sg:city":"Brentwood",
    "sg:classifiers":[
        {
            "category":"Shopping",
            "subcategory":"Clothing, Apparel, & Fashions",
            "type":"Retail Goods"
        },
        {
            "category":"Shopping",
            "subcategory":"Used Merchandise",
            "type":"Retail Goods"
        },
        {
            "category":"Home & Garden",
            "subcategory":"Home Furnishings",
            "type":"Retail Goods"
        },
        {
            "category":"Home & Garden",
            "subcategory":"Furniture",
            "type":"Retail Goods"
        }
    ],
    "sg:phone":"+1 925 513 1194",
    "sg:postcode":"94513",
    "sg:province":"CA",
    "sg:tags":[
        "shop",
        "house",
        "resale",
        "consignment",
        "store"
    ],
    "sg:website":"http://www.visions-home.com",
    "wof:name":"Visions Home Staging & Consignment",
    "wof:placetype":"venue"
},
  "geometry": {"coordinates":[-121.736653,37.943501],"type":"Point"}
}