{
  "type": "Feature",
  "properties": {
    "iso:country":"US",
    "sg:address":"67 Magnolia Ave",
    "sg:city":"Petaluma",
    "sg:classifiers":[
        {
            "category":"Home & Garden",
            "subcategory":"Building Materials",
            "type":"Retail Goods"
        },
        {
            "category":"Professional",
            "subcategory":"Printing & Photocopies",
            "type":"Services"
        },
        {
            "category":"Building & Trades",
            "subcategory":"Locksmith",
            "type":"Services"
        }
    ],
    "sg:phone":"+1 707 763 0265",
    "sg:postcode":"94952",
    "sg:province":"CA",
    "sg:tags":[
        "repair",
        "door",
        "garage",
        "opener",
        "door-overhead",
        "type"
    ],
    "wof:name":"Don's Garage Door",
    "wof:placetype":"venue"
},
  "geometry": {"coordinates":[-122.646658,38.244888],"type":"Point"}
}