{
  "type": "Feature",
  "properties": {
    "iso:country":"US",
    "sg:address":"1160 Industrial Rd",
    "sg:city":"San Carlos",
    "sg:classifiers":[
        {
            "category":"Building & Trades",
            "subcategory":"Electrical",
            "type":"Services"
        }
    ],
    "sg:phone":"+1 650 594 1054",
    "sg:postcode":"94070",
    "sg:province":"CA",
    "sg:tags":[
        "electrical",
        "electric",
        "contractor"
    ],
    "wof:name":"Lynch Electric",
    "wof:placetype":"venue"
},
  "geometry": {"coordinates":[-122.24691900000001,37.502129],"type":"Point"}
}