{
  "type": "Feature",
  "properties": {
    "iso:country":"US",
    "sg:address":"41765 12th St W",
    "sg:city":"Palmdale",
    "sg:classifiers":[
        {
            "category":"Shopping",
            "subcategory":"Bicycles & Sporting Goods",
            "type":"Retail Goods"
        }
    ],
    "sg:phone":"+1 661 945 5755",
    "sg:postcode":"93551",
    "sg:province":"CA",
    "sg:tags":[
        "tackle",
        "fishing"
    ],
    "wof:name":"Desert Offshore",
    "wof:placetype":"venue"
},
  "geometry": {"coordinates":[-118.151419,34.642324],"type":"Point"}
}