{
  "type": "Feature",
  "properties": {
    "iso:country":"US",
    "sg:address":"1007 W Foothill Blvd",
    "sg:city":"Azusa",
    "sg:classifiers":[
        {
            "category":"Shopping",
            "subcategory":"Bicycles & Sporting Goods",
            "type":"Retail Goods"
        },
        {
            "category":"Professional",
            "subcategory":"Printing & Photocopies",
            "type":"Services"
        }
    ],
    "sg:phone":"+1 626 334 6918",
    "sg:postcode":"91702",
    "sg:province":"CA",
    "sg:tags":[
        "medal",
        "plaque",
        "trophies"
    ],
    "wof:name":"J & J's Sports & Trophies",
    "wof:placetype":"venue"
},
  "geometry": {"coordinates":[-117.920838,34.133681],"type":"Point"}
}