{
  "type": "Feature",
  "properties": {
    "addr:full":"173 E 3rd Ave Chico CA 95926",
    "addr:housenumber":"173",
    "addr:postcode":"95926",
    "addr:street":"E 3Rd Ave",
    "iso:country":"US",
    "sg:address":"173 E 3rd Ave",
    "sg:city":"Chico",
    "sg:classifiers":[
        {
            "category":"Shopping",
            "type":"Retail Goods"
        }
    ],
    "sg:phone":"+1 530 345 7500",
    "sg:postcode":"95926",
    "sg:province":"CA",
    "sg:tags":[
        "art",
        "gallery",
        "dealer"
    ],
    "wof:name":"Dovetail Design",
    "wof:placetype":"venue"
},
  "geometry": {"coordinates":[-121.846334,39.740091],"type":"Point"}
}