{
  "type": "Feature",
  "properties": {
    "iso:country":"US",
    "sg:address":"15758 Bellflower Blvd",
    "sg:city":"Bellflower",
    "sg:classifiers":[
        {
            "category":"Coffee & Tea",
            "type":"Food & Drink"
        }
    ],
    "sg:phone":"+1 562 920 3505",
    "sg:postcode":"90706",
    "sg:province":"CA",
    "wof:name":"Roberto's Restaurant",
    "wof:placetype":"venue"
},
  "geometry": {"coordinates":[-118.125,33.890598],"type":"Point"}
}