{
  "type": "Feature",
  "properties": {
    "addr:full":"695 W Homestead Rd Sunnyvale CA 94087",
    "addr:housenumber":"695",
    "addr:postcode":"94087",
    "addr:street":"W Homestead Rd",
    "iso:country":"US",
    "sg:address":"695 W Homestead Rd",
    "sg:city":"Sunnyvale",
    "sg:classifiers":[
        {
            "category":"Retail",
            "subcategory":"Auto Repair",
            "type":"Services"
        },
        {
            "category":"Government",
            "subcategory":"Office",
            "type":"Public Place"
        }
    ],
    "sg:phone":"+1 408 730 1118",
    "sg:postcode":"94087",
    "sg:province":"CA",
    "sg:tags":[
        "smog",
        "oil",
        "check",
        "change"
    ],
    "sg:website":"www.speedeeoil.com",
    "wof:name":"Speedee Oil Change & Tune-Up",
    "wof:placetype":"venue"
},
  "geometry": {"coordinates":[-122.04098999999999,37.33791],"type":"Point"}
}