{
  "type": "Feature",
  "properties": {
    "iso:country":"US",
    "sg:address":"5244 E Tulare Ave",
    "sg:city":"Fresno",
    "sg:classifiers":[
        {
            "category":"Real Estate",
            "subcategory":"Real Estate Operator",
            "type":"Services"
        }
    ],
    "sg:phone":"+1 559 252 1293",
    "sg:postcode":"93727",
    "sg:province":"CA",
    "sg:tags":[
        "apartment"
    ],
    "wof:name":"Cottonwood Apartments",
    "wof:placetype":"venue"
},
  "geometry": {"coordinates":[-119.718229,36.743119],"type":"Point"}
}