{
  "type": "Feature",
  "properties": {
    "iso:country":"US",
    "sg:address":"1775 S de Lay Ave",
    "sg:city":"Chino Hills",
    "sg:phone":"+1 909 606 5720",
    "sg:postcode":"91723",
    "sg:province":"CA",
    "sg:tags":[
        "equipment",
        "commercial"
    ],
    "wof:name":"Elliott Equipment Rental Inc",
    "wof:placetype":"venue"
},
  "geometry": {"coordinates":[-117.874583,34.078189],"type":"Point"}
}