{
  "type": "Feature",
  "properties": {
    "addr:full":"7030 Keighley Ct San Diego CA 92120",
    "addr:housenumber":"7030",
    "addr:postcode":"92120",
    "addr:street":"Keighley Ct",
    "iso:country":"US",
    "sg:address":"7030 Keighley Ct",
    "sg:city":"San Diego",
    "sg:classifiers":[
        {
            "category":"Professional",
            "subcategory":"Management & Consulting",
            "type":"Services"
        }
    ],
    "sg:phone":"+1 619 287 6133",
    "sg:postcode":"92120",
    "sg:province":"CA",
    "sg:tags":[
        "party",
        "planning"
    ],
    "wof:name":"Celebrations Event Planning",
    "wof:placetype":"venue"
},
  "geometry": {"coordinates":[-117.08110600000001,32.799215],"type":"Point"}
}