{
  "type": "Feature",
  "properties": {
    "iso:country":"US",
    "sg:address":"1430 Bonnie Cove Ave",
    "sg:city":"Glendora",
    "sg:classifiers":[
        {
            "category":"Building & Trades",
            "subcategory":"Construction",
            "type":"Services"
        }
    ],
    "sg:phone":"+1 626 914 3999",
    "sg:postcode":"91740",
    "sg:province":"CA",
    "sg:tags":[
        "acoustical",
        "contractor"
    ],
    "wof:name":"J G Acoustics Inc",
    "wof:placetype":"venue"
},
  "geometry": {"coordinates":[-117.855002,34.112642],"type":"Point"}
}