{
  "type": "Feature",
  "properties": {
    "iso:country":"US",
    "sg:address":"2560 Midge Ave",
    "sg:city":"Merced",
    "sg:classifiers":[
        {
            "category":"Real Estate",
            "subcategory":"Real Estate Services",
            "type":"Services"
        },
        {
            "category":"Real Estate",
            "subcategory":"Real Estate Operator",
            "type":"Services"
        }
    ],
    "sg:phone":"+1 209 726 6150",
    "sg:postcode":"95340",
    "sg:province":"CA",
    "sg:tags":[
        "vacancy",
        "apartment",
        "rental",
        "listing"
    ],
    "wof:name":"Las Palmas Apartments",
    "wof:placetype":"venue"
},
  "geometry": {"coordinates":[-120.459576,37.303516],"type":"Point"}
}