{
  "type": "Feature",
  "properties": {
    "iso:country":"US",
    "sg:address":"3401 W 5th St",
    "sg:city":"Oxnard",
    "sg:classifiers":[
        {
            "category":"Building & Trades",
            "subcategory":"Plumbing",
            "type":"Services"
        }
    ],
    "sg:phone":"+1 805 985 8885",
    "sg:postcode":"93030",
    "sg:province":"CA",
    "sg:tags":[
        "plumber"
    ],
    "wof:name":"Donlon Plumbing",
    "wof:placetype":"venue"
},
  "geometry": {"coordinates":[-119.215468,34.197611],"type":"Point"}
}