{
  "type": "Feature",
  "properties": {
    "iso:country":"US",
    "sg:address":"1251 Cll Sarmentoso",
    "sg:city":"San Clemente",
    "sg:classifiers":[
        {
            "category":"Education",
            "subcategory":"School",
            "type":"Public Place"
        }
    ],
    "sg:phone":"+1 949 498 6617",
    "sg:postcode":"92673",
    "sg:province":"CA",
    "wof:name":"Truman Benedict Elem School",
    "wof:placetype":"venue"
},
  "geometry": {"coordinates":[-117.622726,33.469771],"type":"Point"}
}