{
  "type": "Feature",
  "properties": {
    "iso:country":"US",
    "sg:address":"2500 D St",
    "sg:city":"Sacramento",
    "sg:classifiers":[
        {
            "category":"Personal",
            "type":"Services"
        },
        {
            "category":"Professional",
            "subcategory":"Art Services",
            "type":"Services"
        }
    ],
    "sg:phone":"+1 916 443 5866",
    "sg:postcode":"95816",
    "sg:province":"CA",
    "sg:tags":[
        "photography",
        "videography",
        "wedding"
    ],
    "wof:name":"Willie Cornelius Photographer",
    "wof:placetype":"venue"
},
  "geometry": {"coordinates":[-121.470383,38.581501],"type":"Point"}
}