{
  "type": "Feature",
  "properties": {
    "iso:country":"US",
    "sg:address":"22664 Ventura Blvd",
    "sg:city":"Woodland Hills",
    "sg:classifiers":[
        {
            "category":"Restaurant",
            "type":"Food & Drink"
        }
    ],
    "sg:menulink":"http://www.allmenus.com/ca/san-fernando-valley/178774-jack-in-the-box/menu/",
    "sg:phone":"+1 818 224 3460",
    "sg:postcode":"91364",
    "sg:province":"CA",
    "sg:tags":[
        "burger",
        "american"
    ],
    "wof:name":"Jack in the Box",
    "wof:placetype":"venue"
},
  "geometry": {"coordinates":[-118.620305,34.166579],"type":"Point"}
}