{
  "type": "Feature",
  "properties": {
    "addr:full":"3493 Sonora Rd Palm Springs CA 92264",
    "addr:housenumber":"3493",
    "addr:postcode":"92264",
    "addr:street":"Sonora Rd",
    "iso:country":"US",
    "sg:address":"3493 Sonora Rd",
    "sg:city":"Palm Springs",
    "sg:classifiers":[
        {
            "category":"Home & Garden",
            "subcategory":"Furniture",
            "type":"Retail Goods"
        }
    ],
    "sg:phone":"+1 760 321 8167",
    "sg:postcode":"92264",
    "sg:province":"CA",
    "wof:name":"Carlos & Carmella's Furniture",
    "wof:placetype":"venue"
},
  "geometry": {"coordinates":[-116.507958,33.804942],"type":"Point"}
}