{
  "type": "Feature",
  "properties": {
    "iso:country":"US",
    "sg:address":"100 W San Marcos Blvd",
    "sg:city":"San Marcos",
    "sg:classifiers":[
        {
            "category":"Professional",
            "subcategory":"Employment Agencies",
            "type":"Services"
        }
    ],
    "sg:phone":"+1 760 752 4940",
    "sg:postcode":"92069",
    "sg:province":"CA",
    "sg:tags":[
        "opportunity"
    ],
    "sg:website":"www.aerotek.com",
    "wof:name":"Aerotek",
    "wof:placetype":"venue"
},
  "geometry": {"coordinates":[-117.165206,33.140864],"type":"Point"}
}