{
  "type": "Feature",
  "properties": {
    "iso:country":"US",
    "sg:address":"3201 S Main St",
    "sg:city":"Santa Ana",
    "sg:classifiers":[
        {
            "category":"Retail",
            "subcategory":"Auto Repair",
            "type":"Services"
        }
    ],
    "sg:phone":"+1 714 432 0144",
    "sg:postcode":"92707",
    "sg:province":"CA",
    "wof:name":"Avila Auto Care",
    "wof:placetype":"venue"
},
  "geometry": {"coordinates":[-117.86799600000001,33.7047],"type":"Point"}
}