{
  "type": "Feature",
  "properties": {
    "iso:country":"US",
    "sg:address":"15330 S Hacienda Blvd",
    "sg:city":"Hacienda Heights",
    "sg:classifiers":[
        {
            "category":"Building & Trades",
            "subcategory":"Pest Control",
            "type":"Services"
        }
    ],
    "sg:phone":"+1 626 934 9937",
    "sg:postcode":"91745",
    "sg:province":"CA",
    "wof:name":"Hacienda Pest Control/Ad Smart",
    "wof:placetype":"venue"
},
  "geometry": {"coordinates":[-117.971025,33.986613],"type":"Point"}
}