{
  "type": "Feature",
  "properties": {
    "addr:full":"13025 Montecito Rd Red Bluff CA 96080",
    "addr:housenumber":"13025",
    "addr:postcode":"96080",
    "addr:street":"Montecito Rd",
    "iso:country":"US",
    "sg:address":"13025 Montecito Rd",
    "sg:city":"Red Bluff",
    "sg:classifiers":[
        {
            "category":"Real Estate",
            "subcategory":"Real Estate Agent",
            "type":"Services"
        }
    ],
    "sg:phone":"+1 530 529 1105",
    "sg:postcode":"96080",
    "sg:province":"CA",
    "wof:name":"Heart Realty",
    "wof:placetype":"venue"
},
  "geometry": {"coordinates":[-122.32766100000001,40.17256],"type":"Point"}
}