{
  "type": "Feature",
  "properties": {
    "addr:full":"800 Bancroft Way Ste 105 Berkeley CA 94710",
    "addr:housenumber":"800",
    "addr:postcode":"94710",
    "addr:street":"Bancroft Way Ste 105",
    "iso:country":"US",
    "sg:address":"800 Bancroft Way Ste 105",
    "sg:city":"Berkeley",
    "sg:classifiers":[
        {
            "category":"Food & Beverages",
            "subcategory":"Specialty",
            "type":"Retail Goods"
        }
    ],
    "sg:phone":"+1 510 540 5185",
    "sg:postcode":"94710",
    "sg:province":"CA",
    "sg:website":"www.culturedpickleshop.com",
    "wof:name":"Cultured",
    "wof:placetype":"venue"
},
  "geometry": {"coordinates":[-122.297122,37.863284],"type":"Point"}
}