{
  "type": "Feature",
  "properties": {
    "addr:full":"1187 Coast Village Rd Santa Barbara CA 93108",
    "addr:housenumber":"1187",
    "addr:postcode":"93108",
    "addr:street":"Coast Village Rd",
    "iso:country":"US",
    "sg:address":"1187 Coast Village Rd",
    "sg:city":"Santa Barbara",
    "sg:classifiers":[
        {
            "category":"Professional",
            "subcategory":"Business Services",
            "type":"Services"
        }
    ],
    "sg:phone":"+1 805 884 0019",
    "sg:postcode":"93108",
    "sg:province":"CA",
    "sg:tags":[
        "interior",
        "consultant",
        "design",
        "decorator"
    ],
    "wof:name":"Korpinen & Erickson Design",
    "wof:placetype":"venue"
},
  "geometry": {"coordinates":[-119.64746,34.421356],"type":"Point"}
}