{
  "type": "Feature",
  "properties": {
    "addr:full":"3833 Ming Ave Bakersfield CA 93309",
    "addr:housenumber":"3833",
    "addr:postcode":"93309",
    "addr:street":"Ming Ave",
    "iso:country":"US",
    "sg:address":"3833 Ming Ave",
    "sg:city":"Bakersfield",
    "sg:classifiers":[
        {
            "category":"Health Services",
            "subcategory":"Doctor",
            "type":"Services"
        },
        {
            "category":"Health Services",
            "subcategory":"Dentist",
            "type":"Services"
        }
    ],
    "sg:phone":"+1 661 831 5437",
    "sg:postcode":"93309",
    "sg:province":"CA",
    "sg:tags":[
        "dentists-oral",
        "physician",
        "maxillofacial",
        "denture",
        "dental",
        "surgeons",
        "dentists-prosthodontists",
        "clinic",
        "dentistry",
        "implant",
        "oral",
        "surgery",
        "dentists-implantology"
    ],
    "wof:name":"Comfort Dental Kids",
    "wof:placetype":"venue"
},
  "geometry": {"coordinates":[-119.046463,35.339454],"type":"Point"}
}