{
  "type": "Feature",
  "properties": {
    "addr:full":"1080 S de Anza Blvd San Jose CA 95129",
    "addr:housenumber":"1080",
    "addr:postcode":"95129",
    "addr:street":"S De Anza Blvd",
    "iso:country":"US",
    "sg:address":"1080 S de Anza Blvd",
    "sg:city":"San Jose",
    "sg:classifiers":[
        {
            "category":"Travel",
            "subcategory":"Travel Agent",
            "type":"Entertainment"
        }
    ],
    "sg:phone":"+1 408 257 8181",
    "sg:postcode":"95129",
    "sg:province":"CA",
    "sg:tags":[
        "agency"
    ],
    "wof:name":"Hillcrest Travel Services",
    "wof:placetype":"venue"
},
  "geometry": {"coordinates":[-122.03218099999999,37.307309],"type":"Point"}
}