{
  "type": "Feature",
  "properties": {
    "iso:country":"US",
    "sg:address":"1845 Rollins Rd",
    "sg:city":"Burlingame",
    "sg:classifiers":[
        {
            "category":"Airline",
            "type":"Transportation"
        }
    ],
    "sg:phone":"+1 650 692 2841",
    "sg:postcode":"94010",
    "sg:province":"CA",
    "wof:name":"San Francisco Service Base",
    "wof:placetype":"venue"
},
  "geometry": {"coordinates":[-122.38075499999999,37.598338],"type":"Point"}
}