{
  "type": "Feature",
  "properties": {
    "addr:full":"29489 Via Las Colinas Temecula CA 92592",
    "addr:housenumber":"29489",
    "addr:postcode":"92592",
    "addr:street":"Via Las Colinas",
    "iso:country":"US",
    "sg:address":"29489 Via Las Colinas",
    "sg:city":"Temecula",
    "sg:classifiers":[
        {
            "category":"Real Estate",
            "subcategory":"Real Estate Operator",
            "type":"Services"
        }
    ],
    "sg:phone":"+1 951 676 1187",
    "sg:postcode":"92592",
    "sg:province":"CA",
    "sg:tags":[
        "apartment"
    ],
    "wof:name":"Summer Breeze Apartments",
    "wof:placetype":"venue"
},
  "geometry": {"coordinates":[-117.140413,33.506101],"type":"Point"}
}