{
  "type": "Feature",
  "properties": {
    "addr:full":"11400 W Olympic Blvd Los Angeles CA 90064",
    "addr:housenumber":"11400",
    "addr:postcode":"90064",
    "addr:street":"W Olympic Blvd",
    "iso:country":"US",
    "sg:address":"11400 W Olympic Blvd",
    "sg:city":"Los Angeles",
    "sg:classifiers":[
        {
            "category":"Professional",
            "subcategory":"Employment Agencies",
            "type":"Services"
        }
    ],
    "sg:phone":"+1 310 231 0191",
    "sg:postcode":"90064",
    "sg:province":"CA",
    "sg:tags":[
        "opportunity"
    ],
    "wof:name":"Careers In Transition",
    "wof:placetype":"venue"
},
  "geometry": {"coordinates":[-118.444074,34.036502],"type":"Point"}
}