{
  "type": "Feature",
  "properties": {
    "addr:full":"9216 Marysville Rd Oregon House CA 95962",
    "addr:housenumber":"9216",
    "addr:postcode":"95962",
    "addr:street":"Marysville Rd",
    "iso:country":"US",
    "sg:address":"9216 Marysville Rd",
    "sg:city":"Oregon House",
    "sg:classifiers":[
        {
            "category":"Insurance",
            "subcategory":"Insurance Agent",
            "type":"Services"
        }
    ],
    "sg:phone":"+1 530 692 1007",
    "sg:postcode":"95962",
    "sg:province":"CA",
    "wof:name":"Malloy Insurance Svc",
    "wof:placetype":"venue"
},
  "geometry": {"coordinates":[-121.249076,39.36507],"type":"Point"}
}