{
  "type": "Feature",
  "properties": {
    "iso:country":"US",
    "sg:address":"1140 Sutter Street",
    "sg:city":"San Francisco",
    "sg:classifiers":[
        {
            "category":"Real Estate",
            "subcategory":"Real Estate Operator",
            "type":"Services"
        }
    ],
    "sg:phone":"+1 415 673 0500",
    "sg:postcode":"94109",
    "sg:province":"CA",
    "sg:tags":[
        "apartment"
    ],
    "wof:name":"Sutter House",
    "wof:placetype":"venue"
},
  "geometry": {"coordinates":[-122.418999,37.787899],"type":"Point"}
}