{
  "type": "Feature",
  "properties": {
    "addr:full":"3831 Cogswell Rd El Monte CA 91732",
    "addr:housenumber":"3831",
    "addr:postcode":"91732",
    "addr:street":"Cogswell Rd",
    "iso:country":"US",
    "sg:address":"3831 Cogswell Rd",
    "sg:city":"El Monte",
    "sg:classifiers":[
        {
            "category":"Professional",
            "type":"Services"
        }
    ],
    "sg:phone":"+1 626 575 4979",
    "sg:postcode":"91732",
    "sg:province":"CA",
    "wof:name":"Organization O California",
    "wof:placetype":"venue"
},
  "geometry": {"coordinates":[-118.014178,34.072387],"type":"Point"}
}