{
  "type": "Feature",
  "properties": {
    "addr:full":"660 4th Street #117 San Francisco CA",
    "addr:housenumber":"660",
    "addr:street":"4Th Street # 117",
    "iso:country":"US",
    "sg:address":"660 4th Street #117",
    "sg:city":"San Francisco",
    "sg:classifiers":[
        {
            "category":"Professional",
            "subcategory":"Computer Services",
            "type":"Services"
        }
    ],
    "sg:province":"CA",
    "sg:tags":[
        "media-company",
        "mobile-performance-marketing",
        "lead-generation",
        "customer-acquisition",
        "advertisers",
        "publishers"
    ],
    "sg:website":"http://www.moolah-media.com/",
    "wof:name":"Moolah Media",
    "wof:placetype":"venue"
},
  "geometry": {"coordinates":[-122.46172300000001,37.776613],"type":"Point"}
}