{
  "type": "Feature",
  "properties": {
    "iso:country":"US",
    "sg:address":"401 Victor Way",
    "sg:city":"Salinas",
    "sg:classifiers":[
        {
            "category":"Manufacturing",
            "subcategory":"Food",
            "type":"Manufacturing & Wholesale Goods"
        }
    ],
    "sg:phone":"+1 831 422 8028",
    "sg:postcode":"93907",
    "sg:province":"CA",
    "sg:tags":[
        "preparation",
        "farm",
        "covered",
        "crop",
        "mfg"
    ],
    "wof:name":"Jack and Beanstalk",
    "wof:placetype":"venue"
},
  "geometry": {"coordinates":[-121.66769,36.684256],"type":"Point"}
}