{
  "type": "Feature",
  "properties": {
    "addr:full":"959 Grace Ave Emeryville CA 94608",
    "addr:housenumber":"959",
    "addr:postcode":"94608",
    "addr:street":"Grace Ave",
    "iso:country":"US",
    "sg:address":"959 Grace Ave",
    "sg:city":"Emeryville",
    "sg:classifiers":[
        {
            "category":"Wholesale",
            "subcategory":"Non-durable Goods",
            "type":"Manufacturing & Wholesale Goods"
        },
        {
            "category":"Wholesale",
            "subcategory":"Durable Goods & Equipment",
            "type":"Manufacturing & Wholesale Goods"
        }
    ],
    "sg:phone":"+1 510 428 2783",
    "sg:postcode":"94608",
    "sg:province":"CA",
    "sg:tags":[
        "importer"
    ],
    "wof:name":"May Hing Import Export",
    "wof:placetype":"venue"
},
  "geometry": {"coordinates":[-122.277168,37.842699],"type":"Point"}
}