{
  "type": "Feature",
  "properties": {
    "addr:full":"3100 Imperial Hwy Lynwood CA 90262",
    "addr:housenumber":"3100",
    "addr:postcode":"90262",
    "addr:street":"Imperial Hwy",
    "iso:country":"US",
    "sg:address":"3100 Imperial Hwy",
    "sg:city":"Lynwood",
    "sg:classifiers":[
        {
            "category":"Shopping",
            "type":"Retail Goods"
        }
    ],
    "sg:phone":"+1 310 638 9275",
    "sg:postcode":"90262",
    "sg:province":"CA",
    "sg:tags":[
        "picture",
        "frame"
    ],
    "wof:name":"Pictures & Frames",
    "wof:placetype":"venue"
},
  "geometry": {"coordinates":[-118.21160399999999,33.930513],"type":"Point"}
}