{
  "type": "Feature",
  "properties": {
    "addr:full":"2985 Woodside Rd Woodside CA 94062",
    "addr:housenumber":"2985",
    "addr:postcode":"94062",
    "addr:street":"Woodside Rd",
    "iso:country":"US",
    "sg:address":"2985 Woodside Rd",
    "sg:city":"Woodside",
    "sg:classifiers":[
        {
            "category":"Building & Trades",
            "subcategory":"Construction",
            "type":"Services"
        }
    ],
    "sg:phone":"+1 650 851 5035",
    "sg:postcode":"94062",
    "sg:province":"CA",
    "sg:tags":[
        "utility",
        "contractor"
    ],
    "wof:name":"RGT Utilities Of Ca Inc",
    "wof:placetype":"venue"
},
  "geometry": {"coordinates":[-122.25203500000001,37.429055],"type":"Point"}
}