{
  "type": "Feature",
  "properties": {
    "iso:country":"US",
    "sg:address":"515 13th St",
    "sg:city":"Modesto",
    "sg:classifiers":[
        {
            "category":"Banks & Credit Unions",
            "subcategory":"Atm",
            "type":"Services"
        }
    ],
    "sg:phone":"+1 209 588 1500",
    "sg:postcode":"95354",
    "sg:province":"CA",
    "sg:tags":[
        "bankruptcy"
    ],
    "sg:website":"bankruptcycenterhelp.com",
    "wof:name":"The Bankruptcy Center",
    "wof:placetype":"venue"
},
  "geometry": {"coordinates":[-120.99248799999999,37.638058],"type":"Point"}
}