{
  "type": "Feature",
  "properties": {
    "iso:country":"US",
    "sg:address":"101 McCollum Ln",
    "sg:city":"Coalinga",
    "sg:classifiers":[
        {
            "category":"Freight",
            "type":"Transportation"
        }
    ],
    "sg:phone":"+1 559 301 3942",
    "sg:postcode":"93210",
    "sg:province":"CA",
    "sg:tags":[
        "operator",
        "local",
        "trucking"
    ],
    "wof:name":"R W Burnett Transportation",
    "wof:placetype":"venue"
},
  "geometry": {"coordinates":[-120.366118,36.130016],"type":"Point"}
}