{
  "type": "Feature",
  "properties": {
    "addr:full":"1522 S Shenandoah St Los Angeles CA 90035",
    "addr:housenumber":"1522",
    "addr:postcode":"90035",
    "addr:street":"S Shenandoah St",
    "iso:country":"US",
    "sg:address":"1522 S Shenandoah St",
    "sg:city":"Los Angeles",
    "sg:classifiers":[
        {
            "category":"Building & Trades",
            "subcategory":"Construction",
            "type":"Services"
        }
    ],
    "sg:phone":"+1 310 248 3933",
    "sg:postcode":"90035",
    "sg:province":"CA",
    "sg:tags":[
        "contractor"
    ],
    "wof:name":"AAR Construction",
    "wof:placetype":"venue"
},
  "geometry": {"coordinates":[-118.38205000000001,34.050545],"type":"Point"}
}