{
  "type": "Feature",
  "properties": {
    "addr:full":"926 S San Pedro St Los Angeles CA 90015",
    "addr:housenumber":"926",
    "addr:postcode":"90015",
    "addr:street":"S San Pedro St",
    "iso:country":"US",
    "sg:address":"926 S San Pedro St",
    "sg:city":"Los Angeles",
    "sg:classifiers":[
        {
            "category":"Wholesale",
            "subcategory":"Durable Goods & Equipment",
            "type":"Manufacturing & Wholesale Goods"
        }
    ],
    "sg:phone":"+1 213 627 1185",
    "sg:postcode":"90015",
    "sg:province":"CA",
    "sg:tags":[
        "importer"
    ],
    "wof:name":"Connections Import",
    "wof:placetype":"venue"
},
  "geometry": {"coordinates":[-118.25055399999999,34.037068],"type":"Point"}
}