{
  "type": "Feature",
  "properties": {
    "addr:full":"4839 Lone Tree Way Antioch CA 94531",
    "addr:housenumber":"4839",
    "addr:postcode":"ca 94531",
    "addr:street":"Lone Tree Way",
    "iso:country":"US",
    "sg:address":"4839 Lone Tree Way",
    "sg:city":"Antioch",
    "sg:classifiers":[
        {
            "category":"Banks & Credit Unions",
            "subcategory":"Bank",
            "type":"Services"
        }
    ],
    "sg:phone":"+1 925 776 1520",
    "sg:postcode":"94531",
    "sg:province":"CA",
    "sg:tags":[
        "loan",
        "real estate"
    ],
    "wof:name":"Countrywide Home Loans",
    "wof:placetype":"venue"
},
  "geometry": {"coordinates":[-121.76763200000001,37.962823],"type":"Point"}
}