{
  "type": "Feature",
  "properties": {
    "addr:full":"3860 Blackhawk Rd Danville CA 94506",
    "addr:housenumber":"3860",
    "addr:postcode":"94506",
    "addr:street":"Blackhawk Rd",
    "iso:country":"US",
    "sg:address":"3860 Blackhawk Rd",
    "sg:city":"Danville",
    "sg:classifiers":[
        {
            "category":"Communications",
            "type":"Services"
        }
    ],
    "sg:phone":"+1 925 736 6272",
    "sg:postcode":"94506",
    "sg:province":"CA",
    "sg:tags":[
        "communication"
    ],
    "wof:name":"Syncordia Outsourcing Services",
    "wof:placetype":"venue"
},
  "geometry": {"coordinates":[-121.921402,37.800519],"type":"Point"}
}