{
  "type": "Feature",
  "properties": {
    "addr:full":"2124 W Rosecrans Ave Gardena CA 90249",
    "addr:housenumber":"2124",
    "addr:postcode":"90249",
    "addr:street":"W Rosecrans Ave",
    "iso:country":"US",
    "sg:address":"2124 W Rosecrans Ave",
    "sg:city":"Gardena",
    "sg:classifiers":[
        {
            "category":"Manufacturing",
            "subcategory":"Rubber & Plastics",
            "type":"Manufacturing & Wholesale Goods"
        }
    ],
    "sg:phone":"+1 310 515 5111",
    "sg:postcode":"90249",
    "sg:province":"CA",
    "wof:name":"Superior Plastic Fabrication",
    "wof:placetype":"venue"
},
  "geometry": {"coordinates":[-118.316304,33.901858],"type":"Point"}
}