{
  "type": "Feature",
  "properties": {
    "addr:full":"325 Columbus Ave San Francisco CA 94133",
    "addr:housenumber":"325",
    "addr:postcode":"94133",
    "addr:street":"Columbus Ave",
    "iso:country":"US",
    "sg:address":"325 Columbus Ave",
    "sg:city":"San Francisco",
    "sg:classifiers":[
        {
            "category":"Restaurant",
            "type":"Food & Drink"
        }
    ],
    "sg:menulink":"http://www.allmenus.com/ca/san-francisco/22242-the-stinking-rose/menu/",
    "sg:phone":"+1 415 781 7673",
    "sg:postcode":"94133",
    "sg:province":"CA",
    "sg:tags":[
        "american",
        "californian"
    ],
    "wof:name":"The Stinking Rose",
    "wof:placetype":"venue"
},
  "geometry": {"coordinates":[-122.40765,37.79846],"type":"Point"}
}