{
  "type": "Feature",
  "properties": {
    "iso:country":"US",
    "sg:address":"107 E Citrus Ave",
    "sg:city":"Redlands",
    "sg:classifiers":[
        {
            "category":"Restaurant",
            "type":"Food & Drink"
        }
    ],
    "sg:phone":"+1 909 792 5400",
    "sg:postcode":"92373",
    "sg:province":"CA",
    "wof:name":"Eating Room",
    "wof:placetype":"venue"
},
  "geometry": {"coordinates":[-117.181383,34.05555],"type":"Point"}
}