{
  "type": "Feature",
  "properties": {
    "iso:country":"US",
    "sg:address":"955 S Western Ave",
    "sg:city":"Los Angeles",
    "sg:classifiers":[
        {
            "category":"Insurance",
            "subcategory":"Insurance Agent",
            "type":"Services"
        }
    ],
    "sg:phone":"+1 323 735 0109",
    "sg:postcode":"90006",
    "sg:province":"CA",
    "wof:name":"Farmers Insurance Group",
    "wof:placetype":"venue"
},
  "geometry": {"coordinates":[-118.30913200000001,34.05399],"type":"Point"}
}