{
  "type": "Feature",
  "properties": {
    "addr:full":"833 Alpine St Los Angeles CA 90012",
    "addr:housenumber":"833",
    "addr:postcode":"90012",
    "addr:street":"Alpine St",
    "iso:country":"US",
    "sg:address":"833 Alpine St",
    "sg:city":"Los Angeles",
    "sg:classifiers":[
        {
            "category":"Health Services",
            "subcategory":"Health Practitioner",
            "type":"Services"
        }
    ],
    "sg:phone":"+1 213 680 0746",
    "sg:postcode":"90012",
    "sg:province":"CA",
    "sg:tags":[
        "acupuncture"
    ],
    "wof:name":"Jian Min Acupuncture Clinic",
    "wof:placetype":"venue"
},
  "geometry": {"coordinates":[-118.245003,34.063999],"type":"Point"}
}