{
  "type": "Feature",
  "properties": {
    "addr:full":"1250 Newell Ave Walnut Creek CA 94595",
    "addr:housenumber":"1250",
    "addr:postcode":"94595",
    "addr:street":"Newell Ave",
    "iso:country":"US",
    "sg:address":"1250 Newell Ave",
    "sg:city":"Walnut Creek",
    "sg:classifiers":[
        {
            "category":"Manufacturing",
            "subcategory":"Printing",
            "type":"Manufacturing & Wholesale Goods"
        }
    ],
    "sg:phone":"+1 925 947 1282",
    "sg:postcode":"94595",
    "sg:province":"CA",
    "sg:tags":[
        "publisher"
    ],
    "wof:name":"Alluvium Books",
    "wof:placetype":"venue"
},
  "geometry": {"coordinates":[-122.054545,37.893731],"type":"Point"}
}