{
  "type": "Feature",
  "properties": {
    "iso:country":"US",
    "sg:address":"1550 San Leandro Blvd",
    "sg:city":"San Leandro",
    "sg:classifiers":[
        {
            "category":"Professional",
            "subcategory":"Business Services",
            "type":"Services"
        }
    ],
    "sg:phone":"+1 510 351 3937",
    "sg:postcode":"94577",
    "sg:province":"CA",
    "sg:tags":[
        "translator",
        "interpreter"
    ],
    "wof:name":"DCARA Bookstore",
    "wof:placetype":"venue"
},
  "geometry": {"coordinates":[-122.15924200000001,37.72074],"type":"Point"}
}