{
  "type": "Feature",
  "properties": {
    "addr:full":"5720 Nicolle St Ventura CA 93003",
    "addr:housenumber":"5720",
    "addr:postcode":"93003",
    "addr:street":"Nicolle St",
    "iso:country":"US",
    "sg:address":"5720 Nicolle St",
    "sg:city":"Ventura",
    "sg:classifiers":[
        {
            "category":"Professional",
            "subcategory":"Computer Services",
            "type":"Services"
        }
    ],
    "sg:phone":"+1 805 644 2969",
    "sg:postcode":"93003",
    "sg:province":"CA",
    "sg:tags":[
        "electronics"
    ],
    "sg:website":"www.rigel.org",
    "wof:name":"Rigel Corp",
    "wof:placetype":"venue"
},
  "geometry": {"coordinates":[-119.209895,34.247439],"type":"Point"}
}