{
  "type": "Feature",
  "properties": {
    "iso:country":"US",
    "sg:address":"629 J St",
    "sg:city":"Sacramento",
    "sg:classifiers":[
        {
            "category":"Wholesale",
            "subcategory":"Groceries",
            "type":"Manufacturing & Wholesale Goods"
        }
    ],
    "sg:phone":"+1 916 557 8060",
    "sg:postcode":"95814",
    "sg:province":"CA",
    "sg:tags":[
        "pet",
        "food"
    ],
    "wof:name":"Pinnacle Management Co LLC",
    "wof:placetype":"venue"
},
  "geometry": {"coordinates":[-121.497664,38.581529],"type":"Point"}
}