{
  "type": "Feature",
  "properties": {
    "addr:full":"2005 Main St Oakley CA 94561",
    "addr:housenumber":"2005",
    "addr:postcode":"94561",
    "addr:street":"Main St",
    "iso:country":"US",
    "sg:address":"2005 Main St",
    "sg:city":"Oakley",
    "sg:classifiers":[
        {
            "category":"Real Estate",
            "subcategory":"Real Estate Agent",
            "type":"Services"
        }
    ],
    "sg:phone":"+1 925 625 4663",
    "sg:postcode":"94561",
    "sg:province":"CA",
    "sg:website":"www.teamglieden.com",
    "wof:name":"Assist 2 Sell Of Pittsburg",
    "wof:placetype":"venue"
},
  "geometry": {"coordinates":[-121.73568400000001,38.005109],"type":"Point"}
}