{
  "type": "Feature",
  "properties": {
    "iso:country":"US",
    "sg:address":"3388 Rossi St",
    "sg:city":"Lafayette",
    "sg:classifiers":[
        {
            "category":"Wholesale",
            "subcategory":"Furniture",
            "type":"Manufacturing & Wholesale Goods"
        }
    ],
    "sg:phone":"+1 925 299 1023",
    "sg:postcode":"94549",
    "sg:province":"CA",
    "sg:tags":[
        "furniture-wholesale",
        "manufacturer"
    ],
    "wof:name":"Furniture Logic",
    "wof:placetype":"venue"
},
  "geometry": {"coordinates":[-122.107319,37.918182],"type":"Point"}
}