{
  "type": "Feature",
  "properties": {
    "addr:full":"2079 Lockwood Dr San Jose CA 95132",
    "addr:housenumber":"2079",
    "addr:postcode":"95132",
    "addr:street":"Lockwood Dr",
    "iso:country":"US",
    "sg:address":"2079 Lockwood Dr",
    "sg:city":"San Jose",
    "sg:classifiers":[
        {
            "category":"Building & Trades",
            "subcategory":"Electrical",
            "type":"Services"
        }
    ],
    "sg:phone":"+1 408 219 1100",
    "sg:postcode":"95132",
    "sg:province":"CA",
    "sg:tags":[
        "electric",
        "contractor"
    ],
    "wof:name":"Han Kook Electric",
    "wof:placetype":"venue"
},
  "geometry": {"coordinates":[-121.860122,37.414921],"type":"Point"}
}