{
  "type": "Feature",
  "properties": {
    "iso:country":"US",
    "sg:address":"716 Yarmouth Rd",
    "sg:city":"Palos Vrds Ests",
    "sg:classifiers":[
        {
            "category":"Health Services",
            "subcategory":"Health Practitioner",
            "type":"Services"
        }
    ],
    "sg:phone":"+1 310 544 1978",
    "sg:postcode":"90274",
    "sg:province":"CA",
    "sg:tags":[
        "psychologist"
    ],
    "wof:name":"Scott Watson PHD",
    "wof:placetype":"venue"
},
  "geometry": {"coordinates":[-118.41886,33.775711],"type":"Point"}
}