{
  "type": "Feature",
  "properties": {
    "addr:full":"625 Holly Park Cir San Francisco CA 94110",
    "addr:housenumber":"625",
    "addr:postcode":"94110",
    "addr:street":"Holly Park Cir",
    "iso:country":"US",
    "sg:address":"625 Holly Park Cir",
    "sg:city":"San Francisco",
    "sg:classifiers":[
        {
            "category":"Education",
            "subcategory":"School",
            "type":"Public Place"
        }
    ],
    "sg:phone":"+1 415 695 5685",
    "sg:postcode":"94110",
    "sg:province":"CA",
    "sg:tags":[
        "elementary"
    ],
    "wof:name":"Junipero Serra Elementary School",
    "wof:placetype":"venue"
},
  "geometry": {"coordinates":[-122.420998,37.736599],"type":"Point"}
}