{
  "type": "Feature",
  "properties": {
    "addr:full":"3521 Truman Ave Bakersfield CA 93309",
    "addr:housenumber":"3521",
    "addr:postcode":"93309",
    "addr:street":"Truman Ave",
    "iso:country":"US",
    "sg:address":"3521 Truman Ave",
    "sg:city":"Bakersfield",
    "sg:classifiers":[
        {
            "category":"Professional",
            "subcategory":"Management & Consulting",
            "type":"Services"
        }
    ],
    "sg:phone":"+1 661 836 2606",
    "sg:postcode":"93309",
    "sg:province":"CA",
    "sg:tags":[
        "consultant",
        "training"
    ],
    "wof:name":"Visual Fire Technologies",
    "wof:placetype":"venue"
},
  "geometry": {"coordinates":[-119.04316799999999,35.327364],"type":"Point"}
}