{
  "type": "Feature",
  "properties": {
    "addr:full":"61 Divisadero St San Francisco CA 94117",
    "addr:housenumber":"61",
    "addr:postcode":"94117",
    "addr:street":"Divisadero St",
    "iso:country":"US",
    "sg:address":"61 Divisadero St",
    "sg:city":"San Francisco",
    "sg:classifiers":[
        {
            "category":"Retail",
            "subcategory":"Repair Shop",
            "type":"Services"
        }
    ],
    "sg:phone":"+1 415 864 2521",
    "sg:postcode":"94117",
    "sg:province":"CA",
    "sg:tags":[
        "lock",
        "locksmith"
    ],
    "wof:name":"A Aardvark Locksmiths",
    "wof:placetype":"venue"
},
  "geometry": {"coordinates":[-122.43662999999999,37.76794],"type":"Point"}
}