{
  "type": "Feature",
  "properties": {
    "iso:country":"US",
    "sg:address":"138 N Brand Blvd",
    "sg:city":"Glendale",
    "sg:classifiers":[
        {
            "category":"Restaurant",
            "type":"Food & Drink"
        },
        {
            "category":"Food & Beverages",
            "subcategory":"Fruits & Vegetables",
            "type":"Retail Goods"
        }
    ],
    "sg:menulink":"http://www.allmenus.com/ca/san-fernando-valley/135504-jamba-juice/menu/",
    "sg:phone":"+1 818 550 0922",
    "sg:postcode":"91203",
    "sg:province":"CA",
    "sg:tags":[
        "smoothy",
        "juice",
        "american"
    ],
    "wof:name":"Jamba Juice",
    "wof:placetype":"venue"
},
  "geometry": {"coordinates":[-118.25493,34.147715],"type":"Point"}
}