{
  "type": "Feature",
  "properties": {
    "iso:country":"US",
    "sg:address":"19018 Nestor Ave",
    "sg:city":"Carson",
    "sg:classifiers":[
        {
            "category":"Personal",
            "subcategory":"Beauty Salon",
            "type":"Services"
        }
    ],
    "sg:phone":"+1 310 537 3243",
    "sg:postcode":"90746",
    "sg:province":"CA",
    "wof:name":"Kathy's Beauty Nook",
    "wof:placetype":"venue"
},
  "geometry": {"coordinates":[-118.244513,33.85671],"type":"Point"}
}