{
  "type": "Feature",
  "properties": {
    "addr:full":"1220 S Victory Blvd Burbank CA 91502",
    "addr:housenumber":"1220",
    "addr:postcode":"91502",
    "addr:street":"S Victory Blvd",
    "iso:country":"US",
    "sg:address":"1220 S Victory Blvd",
    "sg:city":"Burbank",
    "sg:classifiers":[
        {
            "category":"Retail",
            "subcategory":"Auto Rental",
            "type":"Services"
        }
    ],
    "sg:phone":"+1 818 846 8290",
    "sg:postcode":"91502",
    "sg:province":"CA",
    "sg:tags":[
        "renting",
        "truck",
        "leasing"
    ],
    "wof:name":"U-Haul Co",
    "wof:placetype":"venue"
},
  "geometry": {"coordinates":[-118.304998,34.164741],"type":"Point"}
}