{
  "type": "Feature",
  "properties": {
    "addr:full":"35 W Colton Ave Redlands CA 92374",
    "addr:housenumber":"35",
    "addr:postcode":"92374",
    "addr:street":"W Colton Ave",
    "iso:country":"US",
    "sg:address":"35 W Colton Ave",
    "sg:city":"Redlands",
    "sg:classifiers":[
        {
            "category":"Utilities",
            "subcategory":"Telephone",
            "type":"Services"
        }
    ],
    "sg:phone":"+1 909 792 2611",
    "sg:postcode":"92374",
    "sg:province":"CA",
    "sg:tags":[
        "communications"
    ],
    "wof:name":"Mag7 Inc",
    "wof:placetype":"venue"
},
  "geometry": {"coordinates":[-117.18313499999999,34.062768],"type":"Point"}
}