{
  "type": "Feature",
  "properties": {
    "addr:full":"7920 Arjons Dr San Diego CA 92126",
    "addr:housenumber":"7920",
    "addr:postcode":"92126",
    "addr:street":"Arjons Dr",
    "iso:country":"US",
    "sg:address":"7920 Arjons Dr",
    "sg:city":"San Diego",
    "sg:classifiers":[
        {
            "category":"Wholesale",
            "subcategory":"Sporting Goods",
            "type":"Manufacturing & Wholesale Goods"
        }
    ],
    "sg:phone":"+1 858 547 3720",
    "sg:postcode":"92126",
    "sg:province":"CA",
    "sg:website":"www.eforce.com",
    "wof:name":"E Force Inc",
    "wof:placetype":"venue"
},
  "geometry": {"coordinates":[-117.15119,32.893928],"type":"Point"}
}