{
  "type": "Feature",
  "properties": {
    "addr:full":"1604 Via Palermo Montebello CA 90640",
    "addr:housenumber":"1604",
    "addr:postcode":"90640",
    "addr:street":"Via Palermo",
    "iso:country":"US",
    "sg:address":"1604 Via Palermo",
    "sg:city":"Montebello",
    "sg:classifiers":[
        {
            "category":"Shopping",
            "subcategory":"Used Merchandise",
            "type":"Retail Goods"
        }
    ],
    "sg:phone":"+1 323 887 2310",
    "sg:postcode":"90640",
    "sg:province":"CA",
    "sg:tags":[
        "record",
        "rare"
    ],
    "wof:name":"Jorge Borrego",
    "wof:placetype":"venue"
},
  "geometry": {"coordinates":[-118.114968,34.032652],"type":"Point"}
}