{
  "type": "Feature",
  "properties": {
    "iso:country":"US",
    "sg:address":"26724 Oak Ave",
    "sg:city":"Canyon Country",
    "sg:classifiers":[
        {
            "category":"Wholesale",
            "subcategory":"Office Equipment",
            "type":"Manufacturing & Wholesale Goods"
        }
    ],
    "sg:phone":"+1 818 341 0496",
    "sg:postcode":"91351",
    "sg:province":"CA",
    "sg:tags":[
        "machine",
        "duplicating",
        "copying"
    ],
    "wof:name":"American Fax & Copier",
    "wof:placetype":"venue"
},
  "geometry": {"coordinates":[-118.500406,34.422876],"type":"Point"}
}