{
  "type": "Feature",
  "properties": {
    "iso:country":"US",
    "sg:address":"1233 Grass Valley Hwy",
    "sg:city":"Auburn",
    "sg:classifiers":[
        {
            "category":"Personal",
            "subcategory":"Beauty Salon",
            "type":"Services"
        }
    ],
    "sg:phone":"+1 530 888 0488",
    "sg:postcode":"95603",
    "sg:province":"CA",
    "wof:name":"Pizazz",
    "wof:placetype":"venue"
},
  "geometry": {"coordinates":[-121.083358,38.922806],"type":"Point"}
}