{
  "type": "Feature",
  "properties": {
    "addr:full":"999 W Town and Country Rd Orange CA 92868",
    "addr:housenumber":"999",
    "addr:postcode":"92868",
    "addr:street":"W Town And Country Rd",
    "iso:country":"US",
    "sg:address":"999 W Town and Country Rd",
    "sg:city":"Orange",
    "sg:classifiers":[
        {
            "category":"Real Estate",
            "subcategory":"Architect",
            "type":"Services"
        }
    ],
    "sg:phone":"+1 714 567 2400",
    "sg:postcode":"92868",
    "sg:province":"CA",
    "sg:tags":[
        "project",
        "engineering",
        "architectural"
    ],
    "wof:name":"N Dmjmh Inc",
    "wof:placetype":"venue"
},
  "geometry": {"coordinates":[-117.86711,33.776678],"type":"Point"}
}