{
  "type": "Feature",
  "properties": {
    "iso:country":"US",
    "sg:address":"11629 Iberia Pl",
    "sg:city":"San Diego",
    "sg:classifiers":[
        {
            "category":"Retail",
            "subcategory":"Auto Rental",
            "type":"Services"
        }
    ],
    "sg:phone":"+1 858 485 8525",
    "sg:postcode":"92128",
    "sg:province":"CA",
    "sg:tags":[
        "renting",
        "automobile"
    ],
    "wof:name":"Enterprise Rent-A-Car",
    "wof:placetype":"venue"
},
  "geometry": {"coordinates":[-117.077187,33.01526],"type":"Point"}
}