{
  "type": "Feature",
  "properties": {
    "addr:full":"374 Santa Rosa St San Luis Obispo CA 93405",
    "addr:housenumber":"374",
    "addr:postcode":"93405",
    "addr:street":"Santa Rosa St",
    "iso:country":"US",
    "sg:address":"374 Santa Rosa St",
    "sg:city":"San Luis Obispo",
    "sg:classifiers":[
        {
            "category":"Restaurant",
            "type":"Food & Drink"
        }
    ],
    "sg:phone":"+1 805 545 7736",
    "sg:postcode":"93405",
    "sg:province":"CA",
    "sg:tags":[
        "out"
    ],
    "wof:name":"Taco De Mexico",
    "wof:placetype":"venue"
},
  "geometry": {"coordinates":[-120.66446500000001,35.287737],"type":"Point"}
}