{
  "type": "Feature",
  "properties": {
    "addr:full":"4618 E Belmont Ave Fresno CA 93702",
    "addr:housenumber":"4618",
    "addr:postcode":"93702",
    "addr:street":"E Belmont Ave",
    "iso:country":"US",
    "sg:address":"4618 E Belmont Ave",
    "sg:city":"Fresno",
    "sg:classifiers":[
        {
            "category":"Bars & Pubs",
            "type":"Food & Drink"
        }
    ],
    "sg:phone":"+1 559 251 5898",
    "sg:postcode":"93702",
    "sg:province":"CA",
    "sg:tags":[
        "lounge",
        "cocktail"
    ],
    "wof:name":"Red Lantern",
    "wof:placetype":"venue"
},
  "geometry": {"coordinates":[-119.743916,36.750384],"type":"Point"}
}