{
  "type": "Feature",
  "properties": {
    "iso:country":"US",
    "sg:address":"241 N Mill St",
    "sg:city":"Santa Paula",
    "sg:classifiers":[
        {
            "category":"Organizations",
            "subcategory":"Religious Organization",
            "type":"Services"
        }
    ],
    "sg:phone":"+1 805 525 2814",
    "sg:postcode":"93060",
    "sg:province":"CA",
    "sg:tags":[
        "church"
    ],
    "sg:website":"www.hvcf.org",
    "wof:name":"Heritage Valley Christian",
    "wof:placetype":"venue"
},
  "geometry": {"coordinates":[-119.062026,34.355783],"type":"Point"}
}