{
  "type": "Feature",
  "properties": {
    "addr:full":"12702 Via Cortina Del Mar CA 92014",
    "addr:housenumber":"12702",
    "addr:postcode":"92014",
    "addr:street":"Via Cortina",
    "iso:country":"US",
    "sg:address":"12702 Via Cortina",
    "sg:city":"Del Mar",
    "sg:classifiers":[
        {
            "category":"Professional",
            "subcategory":"Management & Consulting",
            "type":"Services"
        }
    ],
    "sg:phone":"+1 858 259 3979",
    "sg:postcode":"92014",
    "sg:province":"CA",
    "sg:tags":[
        "health",
        "care"
    ],
    "sg:website":"www.mckahan.com",
    "wof:name":"Mc Kahan Planning Group",
    "wof:placetype":"venue"
},
  "geometry": {"coordinates":[-117.25269900000001,32.934348],"type":"Point"}
}