{
  "type": "Feature",
  "properties": {
    "iso:country":"US",
    "sg:address":"905 S Kellogg Ave",
    "sg:city":"Goleta",
    "sg:classifiers":[
        {
            "category":"Building & Trades",
            "subcategory":"Construction",
            "type":"Services"
        }
    ],
    "sg:phone":"+1 805 967 0062",
    "sg:postcode":"93117",
    "sg:province":"CA",
    "sg:tags":[
        "contractor"
    ],
    "wof:name":"Mobile Sandblasting",
    "wof:placetype":"venue"
},
  "geometry": {"coordinates":[-119.82513299999999,34.427268],"type":"Point"}
}