{
  "type": "Feature",
  "properties": {
    "iso:country":"US",
    "sg:address":"9611 52nd St",
    "sg:city":"Riverside",
    "sg:classifiers":[
        {
            "category":"Manufacturing",
            "subcategory":"Printing",
            "type":"Manufacturing & Wholesale Goods"
        }
    ],
    "sg:phone":"+1 951 685 1163",
    "sg:postcode":"92509",
    "sg:province":"CA",
    "sg:tags":[
        "commercial"
    ],
    "wof:name":"C&K Screen Printing",
    "wof:placetype":"venue"
},
  "geometry": {"coordinates":[-117.49199,33.992808],"type":"Point"}
}