{
  "type": "Feature",
  "properties": {
    "iso:country":"US",
    "sg:address":"38 Corporate Park",
    "sg:city":"Irvine",
    "sg:classifiers":[
        {
            "category":"Professional",
            "subcategory":"Lawyer & Legal Services",
            "type":"Services"
        }
    ],
    "sg:phone":"+1 949 250 8868",
    "sg:postcode":"92606",
    "sg:province":"CA",
    "wof:name":"Kazemi & Associates Law Offices of",
    "wof:placetype":"venue"
},
  "geometry": {"coordinates":[-117.82789699999999,33.688946],"type":"Point"}
}