{
  "type": "Feature",
  "properties": {
    "iso:country":"US",
    "sg:address":"5450 Orange Ave",
    "sg:city":"Cypress",
    "sg:classifiers":[
        {
            "category":"Banks & Credit Unions",
            "subcategory":"Financial Services",
            "type":"Services"
        }
    ],
    "sg:phone":"+1 714 220 0743",
    "sg:postcode":"90630",
    "sg:province":"CA",
    "sg:tags":[
        "loan"
    ],
    "wof:name":"Gary Prince",
    "wof:placetype":"venue"
},
  "geometry": {"coordinates":[-118.037625,33.824344],"type":"Point"}
}