{
  "type": "Feature",
  "properties": {
    "addr:full":"2665 W Pico Blvd Los Angeles CA 90006",
    "addr:housenumber":"2665",
    "addr:postcode":"90006",
    "addr:street":"W Pico Blvd",
    "iso:country":"US",
    "sg:address":"2665 W Pico Blvd",
    "sg:city":"Los Angeles",
    "sg:classifiers":[
        {
            "category":"Shopping",
            "subcategory":"Used Merchandise",
            "type":"Retail Goods"
        }
    ],
    "sg:phone":"+1 323 737 3500",
    "sg:postcode":"90006",
    "sg:province":"CA",
    "sg:tags":[
        "record",
        "rare"
    ],
    "wof:name":"Festival Records",
    "wof:placetype":"venue"
},
  "geometry": {"coordinates":[-118.29640499999999,34.047317],"type":"Point"}
}