{
  "type": "Feature",
  "properties": {
    "addr:full":"7116 Aztec Way Bakersfield CA 93308",
    "addr:housenumber":"7116",
    "addr:postcode":"93308",
    "addr:street":"Aztec Way",
    "iso:country":"US",
    "sg:address":"7116 Aztec Way",
    "sg:city":"Bakersfield",
    "sg:classifiers":[
        {
            "category":"Building & Trades",
            "subcategory":"Construction",
            "type":"Services"
        }
    ],
    "sg:phone":"+1 661 589 7795",
    "sg:postcode":"93308",
    "sg:province":"CA",
    "sg:tags":[
        "excavating",
        "contractor"
    ],
    "wof:name":"Accurate Trenching Inc",
    "wof:placetype":"venue"
},
  "geometry": {"coordinates":[-119.080262,35.404762],"type":"Point"}
}