{
  "type": "Feature",
  "properties": {
    "addr:full":"13455 Ventura Blvd Sherman Oaks CA 91423",
    "addr:housenumber":"13455",
    "addr:postcode":"91423",
    "addr:street":"Ventura Blvd",
    "iso:country":"US",
    "sg:address":"13455 Ventura Blvd",
    "sg:city":"Sherman Oaks",
    "sg:classifiers":[
        {
            "category":"Banks & Credit Unions",
            "subcategory":"Bank",
            "type":"Services"
        }
    ],
    "sg:phone":"+1 818 788 6900",
    "sg:postcode":"91423",
    "sg:province":"CA",
    "sg:tags":[
        "loan",
        "real estate"
    ],
    "wof:name":"Benefit Lending",
    "wof:placetype":"venue"
},
  "geometry": {"coordinates":[-118.426777,34.147351],"type":"Point"}
}