{
  "type": "Feature",
  "properties": {
    "addr:full":"846 W Duarte Rd Arcadia CA 91007",
    "addr:housenumber":"846",
    "addr:postcode":"91007",
    "addr:street":"W Duarte Rd",
    "iso:country":"US",
    "sg:address":"846 W Duarte Rd",
    "sg:city":"Arcadia",
    "sg:classifiers":[
        {
            "category":"Coffee & Tea",
            "type":"Food & Drink"
        }
    ],
    "sg:phone":"+1 626 821 0250",
    "sg:postcode":"91007",
    "sg:province":"CA",
    "sg:website":"www.tenren.com",
    "wof:name":"Ten Ren's Tea Time",
    "wof:placetype":"venue"
},
  "geometry": {"coordinates":[-118.06080900000001,34.12522],"type":"Point"}
}