{
  "type": "Feature",
  "properties": {
    "addr:full":"791 School Rd Mckinleyville CA 95519",
    "addr:housenumber":"791",
    "addr:postcode":"95519",
    "addr:street":"School Rd",
    "iso:country":"US",
    "sg:address":"791 School Rd",
    "sg:city":"Mckinleyville",
    "sg:classifiers":[
        {
            "category":"Food & Beverages",
            "subcategory":"Groceries & Convenience Stores",
            "type":"Retail Goods"
        }
    ],
    "sg:phone":"+1 707 839 3866",
    "sg:postcode":"95519",
    "sg:province":"CA",
    "sg:tags":[
        "grocer"
    ],
    "wof:name":"Rogers Markets Inc",
    "wof:placetype":"venue"
},
  "geometry": {"coordinates":[-124.120543,40.933997],"type":"Point"}
}