{
  "type": "Feature",
  "properties": {
    "addr:full":"159 W Harris Avenue South San Francisco CA 94080",
    "addr:housenumber":"159",
    "addr:postcode":"94080",
    "addr:street":"W Harris Avenue",
    "iso:country":"US",
    "sg:address":"159 W Harris Avenue",
    "sg:city":"South San Francisco",
    "sg:classifiers":[
        {
            "category":"Home & Garden",
            "subcategory":"Household Appliances",
            "type":"Retail Goods"
        }
    ],
    "sg:phone":"+1 650 588 9100",
    "sg:postcode":"94080",
    "sg:province":"CA",
    "wof:name":"Select Appliance",
    "wof:placetype":"venue"
},
  "geometry": {"coordinates":[-122.401995,37.650633],"type":"Point"}
}