{
  "type": "Feature",
  "properties": {
    "addr:full":"207 Trickling Brook Ct Simi Valley CA 93065",
    "addr:housenumber":"207",
    "addr:postcode":"93065",
    "addr:street":"Trickling Brook Ct",
    "iso:country":"US",
    "sg:address":"207 Trickling Brook Ct",
    "sg:city":"Simi Valley",
    "sg:classifiers":[
        {
            "category":"Shopping",
            "subcategory":"Catalog Store",
            "type":"Retail Goods"
        }
    ],
    "sg:phone":"+1 661 222 4608",
    "sg:postcode":"93065",
    "sg:province":"CA",
    "sg:tags":[
        "mail",
        "order"
    ],
    "wof:name":"Willow Grove",
    "wof:placetype":"venue"
},
  "geometry": {"coordinates":[-118.758797,34.243042],"type":"Point"}
}