{
  "type": "Feature",
  "properties": {
    "iso:country":"US",
    "sg:address":"130 S John Muir Rd",
    "sg:city":"Lake Arrowhead",
    "sg:classifiers":[
        {
            "category":"Banks & Credit Unions",
            "subcategory":"Investment Brokerage",
            "type":"Services"
        }
    ],
    "sg:phone":"+1 909 337 7426",
    "sg:postcode":"92352",
    "sg:province":"CA",
    "wof:name":"UDI Investment Co",
    "wof:placetype":"venue"
},
  "geometry": {"coordinates":[-117.177733,34.251304],"type":"Point"}
}