{
  "type": "Feature",
  "properties": {
    "addr:full":"40778 Fremont Blvd Fremont CA 94538",
    "addr:housenumber":"40778",
    "addr:postcode":"94538",
    "addr:street":"Fremont Blvd",
    "iso:country":"US",
    "sg:address":"40778 Fremont Blvd",
    "sg:city":"Fremont",
    "sg:classifiers":[
        {
            "category":"Home & Garden",
            "subcategory":"Building Materials",
            "type":"Retail Goods"
        }
    ],
    "sg:phone":"+1 510 623 9034",
    "sg:postcode":"94538",
    "sg:province":"CA",
    "sg:tags":[
        "paint"
    ],
    "wof:name":"Kelley-Moore Paint Co",
    "wof:placetype":"venue"
},
  "geometry": {"coordinates":[-121.96270199999999,37.53493],"type":"Point"}
}