{
  "type": "Feature",
  "properties": {
    "iso:country":"US",
    "sg:address":"Clay Avenue and Dundee Drive",
    "sg:city":"South San Francisco",
    "sg:classifiers":[
        {
            "category":"Recreation",
            "subcategory":"Playground",
            "type":"Entertainment"
        }
    ],
    "sg:phone":"+1 650 829 3800",
    "sg:postcode":"94080",
    "sg:province":"CA",
    "sg:website":"www.ssf.net/news/displaynews.asp...",
    "wof:name":"Clay Park",
    "wof:placetype":"venue"
},
  "geometry": {"coordinates":[-122.462462,37.661607],"type":"Point"}
}