{
  "type": "Feature",
  "properties": {
    "addr:full":"1119 Angelo Dr Beverly Hills CA 90210",
    "addr:housenumber":"1119",
    "addr:postcode":"90210",
    "addr:street":"Angelo Dr",
    "iso:country":"US",
    "sg:address":"1119 Angelo Dr",
    "sg:city":"Beverly Hills",
    "sg:classifiers":[
        {
            "category":"Professional",
            "type":"Services"
        }
    ],
    "sg:phone":"+1 310 205 5557",
    "sg:postcode":"90210",
    "sg:province":"CA",
    "wof:name":"Bernard L Markowitz",
    "wof:placetype":"venue"
},
  "geometry": {"coordinates":[-118.437759,34.097941],"type":"Point"}
}