{
  "type": "Feature",
  "properties": {
    "iso:country":"US",
    "sg:address":"2390 E. Pacifica Place",
    "sg:city":"Compton",
    "sg:classifiers":[
        {
            "category":"Food & Beverages",
            "subcategory":"Bakery",
            "type":"Retail Goods"
        }
    ],
    "sg:phone":"+1 310 763 5198",
    "sg:postcode":"90220",
    "sg:province":"CA",
    "sg:tags":[
        "sandwich"
    ],
    "wof:name":"Sub Connection",
    "wof:placetype":"venue"
},
  "geometry": {"coordinates":[-118.223167,33.848903],"type":"Point"}
}