{
  "type": "Feature",
  "properties": {
    "addr:full":"2567 N 1st St San Jose CA 95131",
    "addr:housenumber":"2567",
    "addr:postcode":"95131",
    "addr:street":"N 1St St",
    "iso:country":"US",
    "sg:address":"2567 N 1st St",
    "sg:city":"San Jose",
    "sg:classifiers":[
        {
            "category":"Juice Bar",
            "subcategory":"None",
            "type":"Food & Drink"
        }
    ],
    "sg:phone":"+1 408 943 0250",
    "sg:postcode":"95131",
    "sg:province":"CA",
    "sg:tags":[
        "smoothy"
    ],
    "wof:name":"Jamba Juice",
    "wof:placetype":"venue"
},
  "geometry": {"coordinates":[-121.927002,37.384602],"type":"Point"}
}