{
  "type": "Feature",
  "properties": {
    "addr:full":"657 Highland Dr Palm Springs CA 92264",
    "addr:housenumber":"657",
    "addr:postcode":"92264",
    "addr:street":"Highland Dr",
    "iso:country":"US",
    "sg:address":"657 Highland Dr",
    "sg:city":"Palm Springs",
    "sg:classifiers":[
        {
            "category":"Health Services",
            "subcategory":"Clinic",
            "type":"Services"
        }
    ],
    "sg:phone":"+1 760 416 6330",
    "sg:postcode":"92264",
    "sg:province":"CA",
    "sg:tags":[
        "home",
        "care"
    ],
    "wof:name":"Palm Spgs Eldercr Hm",
    "wof:placetype":"venue"
},
  "geometry": {"coordinates":[-116.50896400000001,33.813313],"type":"Point"}
}