{
  "type": "Feature",
  "properties": {
    "addr:full":"1055 W 7th St Los Angeles CA 90017",
    "addr:housenumber":"1055",
    "addr:postcode":"90017",
    "addr:street":"W 7Th St",
    "iso:country":"US",
    "sg:address":"1055 W 7th St",
    "sg:city":"Los Angeles",
    "sg:classifiers":[
        {
            "category":"Professional",
            "subcategory":"Lawyer & Legal Services",
            "type":"Services"
        }
    ],
    "sg:phone":"+1 213 489 3222",
    "sg:postcode":"90017",
    "sg:province":"CA",
    "wof:name":"Rasberry Sean P",
    "wof:placetype":"venue"
},
  "geometry": {"coordinates":[-118.264,34.0508],"type":"Point"}
}