{
  "type": "Feature",
  "properties": {
    "iso:country":"US",
    "sg:address":"106 Church St",
    "sg:city":"Roseville",
    "sg:classifiers":[
        {
            "category":"Utilities",
            "subcategory":"Refuse",
            "type":"Services"
        }
    ],
    "sg:phone":"+1 916 786 0572",
    "sg:postcode":"95678",
    "sg:province":"CA",
    "sg:tags":[
        "garbage",
        "collection"
    ],
    "wof:name":"C & L Disposal Co Inc",
    "wof:placetype":"venue"
},
  "geometry": {"coordinates":[-121.286393,38.750987],"type":"Point"}
}