{
  "type": "Feature",
  "properties": {
    "iso:country":"US",
    "sg:address":"732 Codington Way",
    "sg:city":"Modesto",
    "sg:classifiers":[
        {
            "category":"Professional",
            "subcategory":"Art Services",
            "type":"Services"
        },
        {
            "category":"Building & Trades",
            "subcategory":"Construction",
            "type":"Services"
        }
    ],
    "sg:phone":"+1 209 544 9096",
    "sg:postcode":"95357",
    "sg:province":"CA",
    "sg:tags":[
        "interior",
        "designer",
        "design",
        "decorator"
    ],
    "wof:name":"Ambiance Designs",
    "wof:placetype":"venue"
},
  "geometry": {"coordinates":[-120.92156,37.64814],"type":"Point"}
}