{
  "type": "Feature",
  "properties": {
    "addr:full":"4594 Normandie Pl La Mesa CA 91941",
    "addr:housenumber":"4594",
    "addr:postcode":"91941",
    "addr:street":"Normandie Pl",
    "iso:country":"US",
    "sg:address":"4594 Normandie Pl",
    "sg:city":"La Mesa",
    "sg:classifiers":[
        {
            "category":"Banks & Credit Unions",
            "subcategory":"Financial Services",
            "type":"Services"
        }
    ],
    "sg:phone":"+1 619 460 4598",
    "sg:postcode":"91941",
    "sg:province":"CA",
    "sg:tags":[
        "trust",
        "management"
    ],
    "wof:name":"Brandt Family Trust",
    "wof:placetype":"venue"
},
  "geometry": {"coordinates":[-117.04411899999999,32.759421],"type":"Point"}
}