{
  "type": "Feature",
  "properties": {
    "addr:full":"3051 Wabash Ave Los Angeles CA 90063",
    "addr:housenumber":"3051",
    "addr:postcode":"90063",
    "addr:street":"Wabash Ave",
    "iso:country":"US",
    "sg:address":"3051 Wabash Ave",
    "sg:city":"Los Angeles",
    "sg:classifiers":[
        {
            "category":"Retail",
            "subcategory":"Laundry & Dry Cleaning",
            "type":"Services"
        }
    ],
    "sg:phone":"+1 323 780 8492",
    "sg:postcode":"90063",
    "sg:province":"CA",
    "wof:name":"Wash & Dry Coin Laundry",
    "wof:placetype":"venue"
},
  "geometry": {"coordinates":[-118.195831,34.049694],"type":"Point"}
}