{
  "type": "Feature",
  "properties": {
    "iso:country":"US",
    "sg:address":"12617 Cleardale Cir",
    "sg:city":"Stanton",
    "sg:classifiers":[
        {
            "category":"Building & Trades",
            "subcategory":"Construction",
            "type":"Services"
        }
    ],
    "sg:phone":"+1 714 891 8820",
    "sg:postcode":"90680",
    "sg:province":"CA",
    "sg:tags":[
        "contractor"
    ],
    "wof:name":"GWS Precast & Stone Instltn",
    "wof:placetype":"venue"
},
  "geometry": {"coordinates":[-117.995462,33.77871],"type":"Point"}
}