{
  "type": "Feature",
  "properties": {
    "addr:full":"8542 Kermes Ave Fair Oaks CA 95628",
    "addr:postcode":"8542;95628",
    "addr:street":"Kermes Ave",
    "iso:country":"US",
    "sg:address":"8542 Kermes Ave",
    "sg:city":"Fair Oaks",
    "sg:classifiers":[
        {
            "category":"Building & Trades",
            "subcategory":"Plumbing",
            "type":"Services"
        }
    ],
    "sg:phone":"+1 916 879 0918",
    "sg:postcode":"95628",
    "sg:province":"CA",
    "sg:tags":[
        "mechanical",
        "contractor"
    ],
    "wof:name":"D L Mechanical",
    "wof:placetype":"venue"
},
  "geometry": {"coordinates":[-121.24206700000001,38.662876],"type":"Point"}
}