{
  "type": "Feature",
  "properties": {
    "iso:country":"US",
    "sg:address":"11497 Davis St",
    "sg:city":"Moreno Valley",
    "sg:classifiers":[
        {
            "category":"Professional",
            "subcategory":"Business Services",
            "type":"Services"
        }
    ],
    "sg:phone":"+1 909 821 3690",
    "sg:postcode":"92557",
    "sg:province":"CA",
    "wof:name":"Anthony James Interiors",
    "wof:placetype":"venue"
},
  "geometry": {"coordinates":[-117.239653,33.956628],"type":"Point"}
}