{
  "type": "Feature",
  "properties": {
    "addr:full":"11332 Beach Blvd Stanton CA 90680",
    "addr:housenumber":"11332",
    "addr:postcode":"ca 90680",
    "addr:street":"Beach Blvd",
    "iso:country":"US",
    "sg:address":"11332 Beach Blvd",
    "sg:city":"Stanton",
    "sg:classifiers":[
        {
            "category":"Banks & Credit Unions",
            "subcategory":"Bank",
            "type":"Services"
        },
        {
            "category":"Shopping",
            "subcategory":"Used Merchandise",
            "type":"Retail Goods"
        }
    ],
    "sg:phone":"+1 714 897 1458",
    "sg:postcode":"90680",
    "sg:province":"CA",
    "sg:tags":[
        "resale",
        "shop",
        "second",
        "hand"
    ],
    "wof:name":"United Cerebral Palsy Association",
    "wof:placetype":"venue"
},
  "geometry": {"coordinates":[-117.99296699999999,33.798253],"type":"Point"}
}