{
  "type": "Feature",
  "properties": {
    "addr:full":"3122 16th St San Francisco CA 94103",
    "addr:housenumber":"3122",
    "addr:postcode":"94103",
    "addr:street":"16Th St",
    "iso:country":"US",
    "sg:address":"3122 16th St",
    "sg:city":"San Francisco",
    "sg:classifiers":[
        {
            "category":"Bars & Pubs",
            "subcategory":"Hookah Bar",
            "type":"Food & Drink"
        },
        {
            "category":"Restaurant",
            "type":"Food & Drink"
        }
    ],
    "sg:phone":"+1 415 553 8966",
    "sg:postcode":"94103",
    "sg:province":"CA",
    "sg:tags":[
        "middle",
        "moroccan",
        "eastern"
    ],
    "sg:website":"www.moraclounge.com",
    "wof:name":"Morac Restaurant & Lounge",
    "wof:placetype":"venue"
},
  "geometry": {"coordinates":[-122.422614,37.765124],"type":"Point"}
}