{
  "type": "Feature",
  "properties": {
    "iso:country":"US",
    "sg:address":"2754 Georgetown St",
    "sg:city":"Palo Alto",
    "sg:classifiers":[
        {
            "category":"Restaurant",
            "type":"Food & Drink"
        }
    ],
    "sg:phone":"+1 650 328 1652",
    "sg:postcode":"94303",
    "sg:province":"CA",
    "sg:tags":[
        "caterer"
    ],
    "wof:name":"ABC Catering",
    "wof:placetype":"venue"
},
  "geometry": {"coordinates":[-122.137734,37.478989],"type":"Point"}
}