{
  "type": "Feature",
  "properties": {
    "iso:country":"US",
    "sg:address":"85 Brookwood Ave",
    "sg:city":"Santa Rosa",
    "sg:classifiers":[
        {
            "category":"Professional",
            "subcategory":"Lawyer & Legal Services",
            "type":"Services"
        }
    ],
    "sg:phone":"+1 707 566 7501",
    "sg:postcode":"95404",
    "sg:province":"CA",
    "sg:tags":[
        "attorney"
    ],
    "wof:name":"Lana Karhu Law Offices",
    "wof:placetype":"venue"
},
  "geometry": {"coordinates":[-122.706646,38.44273],"type":"Point"}
}