{
  "type": "Feature",
  "properties": {
    "addr:full":"645 5th St Ferndale CA 95536",
    "addr:housenumber":"645",
    "addr:postcode":"95536",
    "addr:street":"5Th St",
    "iso:country":"US",
    "sg:address":"645 5th St",
    "sg:city":"Ferndale",
    "sg:classifiers":[
        {
            "category":"Building & Trades",
            "subcategory":"Construction",
            "type":"Services"
        }
    ],
    "sg:phone":"+1 707 786 4174",
    "sg:postcode":"95536",
    "sg:province":"CA",
    "sg:tags":[
        "general",
        "contractor"
    ],
    "wof:name":"James P Stretch Construction",
    "wof:placetype":"venue"
},
  "geometry": {"coordinates":[-124.265891,40.578849],"type":"Point"}
}