{
  "type": "Feature",
  "properties": {
    "iso:country":"US",
    "sg:address":"103 State Rte 66",
    "sg:city":"Glendora",
    "sg:classifiers":[
        {
            "category":"Wholesale",
            "subcategory":"Machinery & Supplies",
            "type":"Manufacturing & Wholesale Goods"
        }
    ],
    "sg:phone":"+1 626 852 8684",
    "sg:postcode":"91740",
    "sg:province":"CA",
    "sg:tags":[
        "salon",
        "beauty"
    ],
    "wof:name":"Aroma Beauty Supply",
    "wof:placetype":"venue"
},
  "geometry": {"coordinates":[-117.866174,34.128745],"type":"Point"}
}