{
  "type": "Feature",
  "properties": {
    "iso:country":"US",
    "sg:address":"2020 W Swain Rd",
    "sg:city":"Stockton",
    "sg:classifiers":[
        {
            "category":"Education",
            "subcategory":"School",
            "type":"Public Place"
        }
    ],
    "sg:phone":"+1 209 953 8740",
    "sg:postcode":"95207",
    "sg:province":"CA",
    "sg:website":"http://www.lusd.net/schools/jm/index.html",
    "wof:name":"John McCandles Center",
    "wof:placetype":"venue"
},
  "geometry": {"coordinates":[-121.33465200000001,38.000465],"type":"Point"}
}