{
  "type": "Feature",
  "properties": {
    "addr:full":"1659 Hollenbeck Ave Sunnyvale CA 94087",
    "addr:housenumber":"1659",
    "addr:postcode":"94087",
    "addr:street":"Hollenbeck Ave",
    "iso:country":"US",
    "sg:address":"1659 Hollenbeck Ave",
    "sg:city":"Sunnyvale",
    "sg:classifiers":[
        {
            "category":"Shopping",
            "subcategory":"Jewelry",
            "type":"Retail Goods"
        },
        {
            "category":"Shopping",
            "subcategory":"Thrift Store",
            "type":"Retail Goods"
        },
        {
            "category":"Organizations",
            "subcategory":"Non-profit Organization",
            "type":"Services"
        },
        {
            "category":"Shopping",
            "subcategory":"Used Merchandise",
            "type":"Retail Goods"
        }
    ],
    "sg:phone":"+1 408 737 7707",
    "sg:postcode":"94087",
    "sg:province":"CA",
    "sg:tags":[
        "vintage",
        "consignment",
        "community",
        "service/non-profit"
    ],
    "sg:website":"discoveryshop-sunnyvale.org/",
    "wof:name":"American Cancer Society Discovery Shop",
    "wof:placetype":"venue"
},
  "geometry": {"coordinates":[-122.04151,37.33914],"type":"Point"}
}