{
  "type": "Feature",
  "properties": {
    "iso:country":"US",
    "sg:address":"1129 Hartnell Ave",
    "sg:city":"Redding",
    "sg:phone":"+1 530 222 9453",
    "sg:postcode":"96002",
    "sg:province":"CA",
    "wof:name":"Wild Hair A",
    "wof:placetype":"venue"
},
  "geometry": {"coordinates":[-122.35059,40.563794],"type":"Point"}
}