{
  "type": "Feature",
  "properties": {
    "addr:full":"3617 Martin Luther King Jr Blvd Lynwood CA 90262",
    "addr:housenumber":"3617",
    "addr:postcode":"90262",
    "addr:street":"Martin Luther King Jr Blvd",
    "iso:country":"US",
    "sg:address":"3617 Martin Luther King Jr Blvd",
    "sg:city":"Lynwood",
    "sg:classifiers":[
        {
            "category":"Health Services",
            "subcategory":"Doctor",
            "type":"Services"
        }
    ],
    "sg:phone":"+1 310 638 5119",
    "sg:postcode":"90262",
    "sg:province":"CA",
    "sg:tags":[
        "orthopedist"
    ],
    "wof:name":"PETERSON THOS K MD INC",
    "wof:placetype":"venue"
},
  "geometry": {"coordinates":[-118.202645,33.931252],"type":"Point"}
}