{
  "type": "Feature",
  "properties": {
    "iso:country":"US",
    "sg:address":"8923 S San Pedro St",
    "sg:city":"Los Angeles",
    "sg:classifiers":[
        {
            "category":"Restaurant",
            "type":"Food & Drink"
        }
    ],
    "sg:phone":"+1 323 752 3389",
    "sg:postcode":"90003",
    "sg:province":"CA",
    "sg:tags":[
        "eating"
    ],
    "wof:name":"Rips Ribs and Things",
    "wof:placetype":"venue"
},
  "geometry": {"coordinates":[-118.269589,33.954882],"type":"Point"}
}