{
  "type": "Feature",
  "properties": {
    "iso:country":"US",
    "sg:address":"1700 Greenleaf Canyon Rd",
    "sg:city":"Topanga",
    "sg:classifiers":[
        {
            "category":"Manufacturing",
            "subcategory":"Pottery",
            "type":"Manufacturing & Wholesale Goods"
        }
    ],
    "sg:phone":"+1 310 455 1169",
    "sg:postcode":"90290",
    "sg:province":"CA",
    "sg:tags":[
        "product",
        "mfg"
    ],
    "wof:name":"Sullivan Ceramics",
    "wof:placetype":"venue"
},
  "geometry": {"coordinates":[-118.606854,34.108295],"type":"Point"}
}