{
  "type": "Feature",
  "properties": {
    "addr:full":"1 Frank Ogawa Plz Oakland CA 94612",
    "addr:housenumber":"1",
    "addr:postcode":"94612",
    "addr:street":"Frank Ogawa Plz",
    "iso:country":"US",
    "sg:address":"1 Frank Ogawa Plz",
    "sg:city":"Oakland",
    "sg:classifiers":[
        {
            "category":"Government",
            "subcategory":"City Hall",
            "type":"Public Place"
        },
        {
            "category":"Restaurant",
            "type":"Food & Drink"
        }
    ],
    "sg:phone":"+1 510 444 2489",
    "sg:postcode":"94612",
    "sg:province":"CA",
    "sg:tags":[
        "flavor",
        "local"
    ],
    "sg:website":"www.oaklandnet.com",
    "wof:name":"City of Oakland",
    "wof:placetype":"venue"
},
  "geometry": {"coordinates":[-122.272533,37.805315],"type":"Point"}
}