{
  "type": "Feature",
  "properties": {
    "addr:full":"2946 Dyer Ave Sebastopol CA 95472",
    "addr:housenumber":"2946",
    "addr:postcode":"95472",
    "addr:street":"Dyer Ave",
    "iso:country":"US",
    "sg:address":"2946 Dyer Ave",
    "sg:city":"Sebastopol",
    "sg:classifiers":[
        {
            "category":"Communications",
            "subcategory":"Film & Video Production",
            "type":"Services"
        }
    ],
    "sg:phone":"+1 707 824 8475",
    "sg:postcode":"95472",
    "sg:province":"CA",
    "sg:tags":[
        "tv",
        "radio",
        "services-commercial",
        "companies-film"
    ],
    "wof:name":"True To Life Films",
    "wof:placetype":"venue"
},
  "geometry": {"coordinates":[-122.87808099999999,38.433687],"type":"Point"}
}