{
  "type": "Feature",
  "properties": {
    "addr:full":"14311 Bear Valley Rd Suite 101 Victorville CA 92392",
    "addr:housenumber":"14311",
    "addr:postcode":"92392",
    "addr:street":"Bear Valley Rd Suite 101",
    "iso:country":"US",
    "sg:address":"14311 Bear Valley Rd Suite 101",
    "sg:city":"Victorville",
    "sg:classifiers":[
        {
            "category":"Education",
            "subcategory":"College",
            "type":"Public Place"
        }
    ],
    "sg:phone":"+1 877 397 5442",
    "sg:postcode":"92392",
    "sg:province":"CA",
    "sg:tags":[
        "school",
        "beauty"
    ],
    "sg:website":"http://national.citysearch.com/profile/external/604379242/victorville_ca/marinello_schools_of_beauty.html?publisher=yellowpages&reference_id=1&placement=ypwebsitemip",
    "wof:name":"Marinello Schools of Beauty",
    "wof:placetype":"venue"
},
  "geometry": {"coordinates":[-117.349682,34.470409],"type":"Point"}
}