{
  "type": "Feature",
  "properties": {
    "addr:full":"611 Folsom St San Francisco CA 94107",
    "addr:housenumber":"611",
    "addr:postcode":"94107",
    "addr:street":"Folsom St",
    "iso:country":"US",
    "sg:address":"611 Folsom St",
    "sg:city":"San Francisco",
    "sg:classifiers":[
        {
            "category":"Professional",
            "type":"Services"
        }
    ],
    "sg:phone":"+1 415 883 4472",
    "sg:postcode":"94107",
    "sg:province":"CA",
    "wof:name":"Product Edge",
    "wof:placetype":"venue"
},
  "geometry": {"coordinates":[-122.39755100000001,37.784822],"type":"Point"}
}