{
  "type": "Feature",
  "properties": {
    "addr:full":"732 Flint Ave Wilmington CA 90744",
    "addr:housenumber":"732",
    "addr:postcode":"90744",
    "addr:street":"Flint Ave",
    "iso:country":"US",
    "sg:address":"732 Flint Ave",
    "sg:city":"Wilmington",
    "sg:classifiers":[
        {
            "category":"Retail",
            "subcategory":"Auto Repair",
            "type":"Services"
        }
    ],
    "sg:phone":"+1 310 513 9856",
    "sg:postcode":"90744",
    "sg:province":"CA",
    "sg:tags":[
        "body",
        "shop"
    ],
    "wof:name":"Motor Sport Auto Body & Dismantling",
    "wof:placetype":"venue"
},
  "geometry": {"coordinates":[-118.24900100000001,33.779202],"type":"Point"}
}