{
  "type": "Feature",
  "properties": {
    "addr:full":"33975 Pourroy Rd Winchester CA 92596",
    "addr:postcode":"33975;92596",
    "addr:street":"Pourroy Rd",
    "iso:country":"US",
    "sg:address":"33975 Pourroy Rd",
    "sg:city":"Winchester",
    "sg:classifiers":[
        {
            "category":"Shopping",
            "type":"Retail Goods"
        }
    ],
    "sg:phone":"+1 951 926 3772",
    "sg:postcode":"92596",
    "sg:province":"CA",
    "sg:tags":[
        "equipment",
        "telephone",
        "supply"
    ],
    "wof:name":"Telephones Today",
    "wof:placetype":"venue"
},
  "geometry": {"coordinates":[-117.101322,33.627552],"type":"Point"}
}