{
  "type": "Feature",
  "properties": {
    "iso:country":"US",
    "sg:address":"482 W San Ysidro Blvd Ste 2108",
    "sg:city":"San Diego",
    "sg:classifiers":[
        {
            "category":"Professional",
            "type":"Services"
        }
    ],
    "sg:phone":"+1 619 793 5577",
    "sg:postcode":"92101",
    "sg:province":"CA",
    "sg:tags":[
        "planning",
        "event"
    ],
    "sg:website":"flushrentals.com/whysd.htm",
    "wof:name":"Flush Rentals",
    "wof:placetype":"venue"
},
  "geometry": {"coordinates":[-117.16198199999999,32.716779],"type":"Point"}
}