{
  "type": "Feature",
  "properties": {
    "addr:full":"820 S Robertson Culver City CA 90230",
    "addr:housenumber":"820",
    "addr:postcode":"90230",
    "addr:street":"S Robertson",
    "iso:country":"US",
    "sg:address":"820 S Robertson",
    "sg:city":"Culver City",
    "sg:classifiers":[
        {
            "category":"Building & Trades",
            "subcategory":"Locksmith",
            "type":"Services"
        }
    ],
    "sg:phone":"+1 310 837 2963",
    "sg:postcode":"90230",
    "sg:province":"CA",
    "sg:tags":[
        "key"
    ],
    "wof:name":"Smitty's Locksmith",
    "wof:placetype":"venue"
},
  "geometry": {"coordinates":[-118.397003,33.996899],"type":"Point"}
}