{
  "type": "Feature",
  "properties": {
    "iso:country":"US",
    "sg:address":"3525 W Carson St",
    "sg:city":"Torrance",
    "sg:classifiers":[
        {
            "category":"Shopping",
            "subcategory":"Optician",
            "type":"Retail Goods"
        }
    ],
    "sg:phone":"+1 310 214 8106",
    "sg:postcode":"90503",
    "sg:province":"CA",
    "sg:tags":[
        "eyewear"
    ],
    "wof:name":"Via Monet",
    "wof:placetype":"venue"
},
  "geometry": {"coordinates":[-118.347877,33.831357],"type":"Point"}
}