{
  "type": "Feature",
  "properties": {
    "iso:country":"US",
    "sg:address":"3356 E Olympic Boulevard",
    "sg:city":"Los Angeles",
    "sg:classifiers":[
        {
            "category":"Health Services",
            "subcategory":"Dentist",
            "type":"Services"
        }
    ],
    "sg:phone":"+1 323 269 5221",
    "sg:postcode":"90023",
    "sg:province":"CA",
    "wof:name":"Ganapolsky Ida Dss",
    "wof:placetype":"venue"
},
  "geometry": {"coordinates":[-118.20611,34.01865],"type":"Point"}
}