{
  "type": "Feature",
  "properties": {
    "addr:full":"1242 Wellesley Ave Los Angeles CA 90025",
    "addr:housenumber":"1242",
    "addr:postcode":"90025",
    "addr:street":"Wellesley Ave",
    "iso:country":"US",
    "sg:address":"1242 Wellesley Ave",
    "sg:city":"Los Angeles",
    "sg:classifiers":[
        {
            "category":"Building & Trades",
            "subcategory":"Construction",
            "type":"Services"
        }
    ],
    "sg:phone":"+1 310 820 3265",
    "sg:postcode":"90025",
    "sg:province":"CA",
    "sg:tags":[
        "general",
        "contractor"
    ],
    "wof:name":"Cedars Construction Grp Inc",
    "wof:placetype":"venue"
},
  "geometry": {"coordinates":[-118.468137,34.04207],"type":"Point"}
}