{
  "type": "Feature",
  "properties": {
    "iso:country":"US",
    "sg:address":"545 Cleveland Ave",
    "sg:city":"Sebastopol",
    "sg:classifiers":[
        {
            "category":"Professional",
            "subcategory":"Art Services",
            "type":"Services"
        }
    ],
    "sg:phone":"+1 707 829 3246",
    "sg:postcode":"95472",
    "sg:province":"CA",
    "sg:tags":[
        "graphic",
        "designer"
    ],
    "wof:name":"Communication Graphics",
    "wof:placetype":"venue"
},
  "geometry": {"coordinates":[-122.829018,38.406633],"type":"Point"}
}