{
  "type": "Feature",
  "properties": {
    "iso:country":"US",
    "sg:address":"2838 el Roya Ave",
    "sg:city":"Modesto",
    "sg:classifiers":[
        {
            "category":"Building & Trades",
            "subcategory":"Construction",
            "type":"Services"
        }
    ],
    "sg:phone":"+1 209 576 1166",
    "sg:postcode":"95354",
    "sg:province":"CA",
    "sg:tags":[
        "roofing",
        "contractor"
    ],
    "wof:name":"Cal-West Roofing Co",
    "wof:placetype":"venue"
},
  "geometry": {"coordinates":[-120.942846,37.633115],"type":"Point"}
}