{
  "type": "Feature",
  "properties": {
    "iso:country":"US",
    "sg:address":"4512 W Pico Blvd",
    "sg:city":"Los Angeles",
    "sg:classifiers":[
        {
            "category":"Food & Beverages",
            "subcategory":"Specialty",
            "type":"Retail Goods"
        }
    ],
    "sg:phone":"+1 323 937 3450",
    "sg:postcode":"90019",
    "sg:province":"CA",
    "wof:name":"Wright Helen A",
    "wof:placetype":"venue"
},
  "geometry": {"coordinates":[-118.33331699999999,34.048441],"type":"Point"}
}