{
  "type": "Feature",
  "properties": {
    "addr:full":"3810 E Palm Ave Anaheim CA 92869",
    "addr:housenumber":"3810",
    "addr:postcode":"92869",
    "addr:street":"E Palm Ave",
    "iso:country":"US",
    "sg:address":"3810 E Palm Ave",
    "sg:city":"Anaheim",
    "sg:classifiers":[
        {
            "category":"Insurance",
            "subcategory":"Insurance Agent",
            "type":"Services"
        }
    ],
    "sg:phone":"+1 714 630 1455",
    "sg:postcode":"92869",
    "sg:province":"CA",
    "wof:name":"Davis & Madden Insurance Inc",
    "wof:placetype":"venue"
},
  "geometry": {"coordinates":[-117.81281799999999,33.792145],"type":"Point"}
}