{
  "type": "Feature",
  "properties": {
    "addr:full":"11201 Aviation Blvd Los Angeles CA 90045",
    "addr:housenumber":"11201",
    "addr:postcode":"90045",
    "addr:street":"Aviation Blvd",
    "iso:country":"US",
    "sg:address":"11201 Aviation Blvd",
    "sg:city":"Los Angeles",
    "sg:classifiers":[
        {
            "category":"Professional",
            "subcategory":"Detective & Security Services",
            "type":"Services"
        }
    ],
    "sg:phone":"+1 310 338 0227",
    "sg:postcode":"90045",
    "sg:province":"CA",
    "sg:tags":[
        "guard",
        "patrol"
    ],
    "wof:name":"Aero Protection Specialist",
    "wof:placetype":"venue"
},
  "geometry": {"coordinates":[-118.378495,33.93093],"type":"Point"}
}