{
  "type": "Feature",
  "properties": {
    "iso:country":"US",
    "sg:address":"4535 College Ave",
    "sg:city":"San Diego",
    "sg:classifiers":[
        {
            "category":"Health Services",
            "subcategory":"Doctor",
            "type":"Services"
        }
    ],
    "sg:phone":"+1 619 286 1353",
    "sg:postcode":"92115",
    "sg:province":"CA",
    "sg:tags":[
        "physician",
        "surgeon"
    ],
    "wof:name":"R Seenu Reddy MD",
    "wof:placetype":"venue"
},
  "geometry": {"coordinates":[-117.066253,32.759201],"type":"Point"}
}