{
  "type": "Feature",
  "properties": {
    "iso:country":"US",
    "sg:address":"1323 16th Ave",
    "sg:city":"San Francisco",
    "sg:classifiers":[
        {
            "category":"Professional",
            "type":"Services"
        }
    ],
    "sg:phone":"+1 415 664 4459",
    "sg:postcode":"94122",
    "sg:province":"CA",
    "wof:name":"Paperworks",
    "wof:placetype":"venue"
},
  "geometry": {"coordinates":[-122.473881,37.762255],"type":"Point"}
}