{
  "type": "Feature",
  "properties": {
    "addr:full":"505 S Main St Orange CA 92868",
    "addr:housenumber":"505",
    "addr:postcode":"92868",
    "addr:street":"S Main St",
    "iso:country":"US",
    "sg:address":"505 S Main St",
    "sg:city":"Orange",
    "sg:classifiers":[
        {
            "category":"Insurance",
            "subcategory":"Title Insurance",
            "type":"Services"
        }
    ],
    "sg:phone":"+1 714 550 6500",
    "sg:postcode":"92868",
    "sg:province":"CA",
    "sg:tags":[
        "company",
        "real estate"
    ],
    "wof:name":"North American Title Company",
    "wof:placetype":"venue"
},
  "geometry": {"coordinates":[-117.867217,33.778691],"type":"Point"}
}