{
  "type": "Feature",
  "properties": {
    "iso:country":"US",
    "sg:address":"95 W Matheson St",
    "sg:city":"Healdsburg",
    "sg:classifiers":[
        {
            "category":"Manufacturing",
            "subcategory":"Metals",
            "type":"Manufacturing & Wholesale Goods"
        }
    ],
    "sg:phone":"+1 707 433 3963",
    "sg:postcode":"95448",
    "sg:province":"CA",
    "sg:tags":[
        "anodizing"
    ],
    "wof:name":"Peralco",
    "wof:placetype":"venue"
},
  "geometry": {"coordinates":[-122.874357,38.609484],"type":"Point"}
}