{
  "type": "Feature",
  "properties": {
    "addr:full":"1209 W Cll de Oro Calexico CA 92231",
    "addr:housenumber":"1209",
    "addr:postcode":"92231",
    "addr:street":"W Cll De Oro",
    "iso:country":"US",
    "sg:address":"1209 W Cll de Oro",
    "sg:city":"Calexico",
    "sg:classifiers":[
        {
            "category":"Shopping",
            "subcategory":"Gifts & Souvenirs",
            "type":"Retail Goods"
        }
    ],
    "sg:phone":"+1 760 357 2145",
    "sg:postcode":"92231",
    "sg:province":"CA",
    "sg:tags":[
        "party",
        "supply"
    ],
    "wof:name":"Rental Shop",
    "wof:placetype":"venue"
},
  "geometry": {"coordinates":[-115.490354,32.681983],"type":"Point"}
}