{
  "type": "Feature",
  "properties": {
    "addr:full":"430 W 17th St Santa Ana CA 92706",
    "addr:housenumber":"430",
    "addr:postcode":"92706",
    "addr:street":"W 17Th St",
    "iso:country":"US",
    "sg:address":"430 W 17th St",
    "sg:city":"Santa Ana",
    "sg:classifiers":[
        {
            "category":"Autos & Motor Vehicles",
            "subcategory":"Auto Supplies",
            "type":"Retail Goods"
        }
    ],
    "sg:phone":"+1 714 547 7003",
    "sg:postcode":"92706",
    "sg:province":"CA",
    "sg:tags":[
        "automobile",
        "parts"
    ],
    "wof:name":"Autozone",
    "wof:placetype":"venue"
},
  "geometry": {"coordinates":[-117.871247,33.759967],"type":"Point"}
}