{
  "type": "Feature",
  "properties": {
    "iso:country":"US",
    "sg:address":"14532 Friar St",
    "sg:city":"Van Nuys",
    "sg:classifiers":[
        {
            "category":"Food & Beverages",
            "subcategory":"Specialty",
            "type":"Retail Goods"
        }
    ],
    "sg:phone":"+1 661 265 7101",
    "sg:postcode":"91411",
    "sg:province":"CA",
    "sg:tags":[
        "water",
        "bulk",
        "company"
    ],
    "wof:name":"Royal Prestiege Agua Pura",
    "wof:placetype":"venue"
},
  "geometry": {"coordinates":[-118.450307,34.185595],"type":"Point"}
}