{
  "type": "Feature",
  "properties": {
    "addr:full":"6508 Ira Ave Bell Gardens CA 90201",
    "addr:housenumber":"6508",
    "addr:postcode":"90201",
    "addr:street":"Ira Ave",
    "iso:country":"US",
    "sg:address":"6508 Ira Ave",
    "sg:city":"Bell Gardens",
    "sg:classifiers":[
        {
            "category":"Retail",
            "subcategory":"Auto Repair",
            "type":"Services"
        }
    ],
    "sg:phone":"+1 323 771 3205",
    "sg:postcode":"90201",
    "sg:province":"CA",
    "sg:tags":[
        "body",
        "automobile",
        "painting"
    ],
    "wof:name":"Charles J Davila",
    "wof:placetype":"venue"
},
  "geometry": {"coordinates":[-118.154287,33.96963],"type":"Point"}
}