{
  "type": "Feature",
  "properties": {
    "addr:full":"2907 Minna Ave Oakland CA 94619",
    "addr:housenumber":"2907",
    "addr:postcode":"94619",
    "addr:street":"Minna Ave",
    "iso:country":"US",
    "sg:address":"2907 Minna Ave",
    "sg:city":"Oakland",
    "sg:classifiers":[
        {
            "category":"Professional",
            "subcategory":"Management & Consulting",
            "type":"Services"
        }
    ],
    "sg:phone":"+1 510 536 1962",
    "sg:postcode":"94619",
    "sg:province":"CA",
    "sg:tags":[
        "consultant",
        "business"
    ],
    "wof:name":"Intuitive Leadership Services",
    "wof:placetype":"venue"
},
  "geometry": {"coordinates":[-122.20285,37.786269],"type":"Point"}
}