{
  "type": "Feature",
  "properties": {
    "addr:full":"11671 Brookshire Ave Garden Grove CA 92840",
    "addr:housenumber":"11671",
    "addr:postcode":"92840",
    "addr:street":"Brookshire Ave",
    "iso:country":"US",
    "sg:address":"11671 Brookshire Ave",
    "sg:city":"Garden Grove",
    "sg:classifiers":[
        {
            "category":"Building & Trades",
            "subcategory":"Electrical",
            "type":"Services"
        }
    ],
    "sg:phone":"+1 714 530 6800",
    "sg:postcode":"92840",
    "sg:province":"CA",
    "sg:tags":[
        "contractor",
        "electrical",
        "mfg"
    ],
    "wof:name":"C & G Electrical Control Svc",
    "wof:placetype":"venue"
},
  "geometry": {"coordinates":[-117.927155,33.786461],"type":"Point"}
}