{
  "type": "Feature",
  "properties": {
    "addr:full":"4686 Frontier Way Stockton CA 95215",
    "addr:housenumber":"4686",
    "addr:postcode":"95215",
    "addr:street":"Frontier Way",
    "iso:country":"US",
    "sg:address":"4686 Frontier Way",
    "sg:city":"Stockton",
    "sg:classifiers":[
        {
            "category":"Manufacturing",
            "subcategory":"Furniture",
            "type":"Manufacturing & Wholesale Goods"
        }
    ],
    "sg:phone":"+1 209 944 8080",
    "sg:postcode":"95215",
    "sg:province":"CA",
    "wof:name":"England/Corsair Inc",
    "wof:placetype":"venue"
},
  "geometry": {"coordinates":[-121.21293799999999,37.908466],"type":"Point"}
}