{
  "type": "Feature",
  "properties": {
    "iso:country":"US",
    "sg:address":"4686 Frontier Way",
    "sg:city":"Stockton",
    "sg:classifiers":[
        {
            "category":"Manufacturing",
            "subcategory":"Furniture",
            "type":"Manufacturing & Wholesale Goods"
        }
    ],
    "sg:phone":"+1 209 944 8080",
    "sg:postcode":"95215",
    "sg:province":"CA",
    "wof:name":"England/Corsair Inc",
    "wof:placetype":"venue"
},
  "geometry": {"coordinates":[-121.212938,37.908466],"type":"Point"}
}