{
  "type": "Feature",
  "properties": {
    "addr:full":"23670 Wiley Canyon Rd Valencia CA 91355",
    "addr:housenumber":"23670",
    "addr:postcode":"91355",
    "addr:street":"Wiley Canyon Rd",
    "iso:country":"US",
    "sg:address":"23670 Wiley Canyon Rd",
    "sg:city":"Valencia",
    "sg:classifiers":[
        {
            "category":"Organizations",
            "subcategory":"Religious Organization",
            "type":"Services"
        }
    ],
    "sg:phone":"+1 661 259 2400",
    "sg:postcode":"91355",
    "sg:province":"CA",
    "sg:tags":[
        "place",
        "worship",
        "church"
    ],
    "sg:website":"http://www.hiswaycommunity.org",
    "wof:name":"HisWay Community Church",
    "wof:placetype":"venue"
},
  "geometry": {"coordinates":[-118.549004,34.387993],"type":"Point"}
}