{
  "type": "Feature",
  "properties": {
    "iso:country":"US",
    "sg:address":"2180 Bryant Street",
    "sg:city":"San Francisco",
    "sg:classifiers":[
        {
            "category":"Professional",
            "subcategory":"Computer Services",
            "type":"Services"
        }
    ],
    "sg:phone":"+1 415 282 2187",
    "sg:postcode":"94110",
    "sg:province":"CA",
    "sg:tags":[
        "repair"
    ],
    "wof:name":"Infomatum",
    "wof:placetype":"venue"
},
  "geometry": {"coordinates":[-122.409843,37.759427],"type":"Point"}
}