{
  "type": "Feature",
  "properties": {
    "addr:full":"2665 Ocean Ave San Francisco CA 94132",
    "addr:housenumber":"2665",
    "addr:postcode":"94132",
    "addr:street":"Ocean Ave",
    "iso:country":"US",
    "sg:address":"2665 Ocean Ave",
    "sg:city":"San Francisco",
    "sg:classifiers":[
        {
            "category":"Health Services",
            "subcategory":"Doctor",
            "type":"Services"
        }
    ],
    "sg:phone":"+1 415 585 4200",
    "sg:postcode":"94132",
    "sg:province":"CA",
    "sg:tags":[
        "dentist"
    ],
    "wof:name":"Robyn L Moyer DDS",
    "wof:placetype":"venue"
},
  "geometry": {"coordinates":[-122.474705,37.732227],"type":"Point"}
}