{
  "type": "Feature",
  "properties": {
    "iso:country":"US",
    "sg:address":"12 Sharon St",
    "sg:city":"San Francisco",
    "sg:classifiers":[
        {
            "category":"Professional",
            "type":"Services"
        }
    ],
    "sg:phone":"+1 415 626 5873",
    "sg:postcode":"94114",
    "sg:province":"CA",
    "wof:name":"Big Basket",
    "wof:placetype":"venue"
},
  "geometry": {"coordinates":[-122.42985899999999,37.764604],"type":"Point"}
}