{
  "type": "Feature",
  "properties": {
    "addr:full":"3651 Business Dr Sacramento CA 95820",
    "addr:housenumber":"3651",
    "addr:postcode":"95820",
    "addr:street":"Business Dr",
    "iso:country":"US",
    "sg:address":"3651 Business Dr",
    "sg:city":"Sacramento",
    "sg:classifiers":[
        {
            "category":"Professional",
            "subcategory":"Computer Services",
            "type":"Services"
        }
    ],
    "sg:phone":"+1 916 736 3715",
    "sg:postcode":"95820",
    "sg:province":"CA",
    "sg:tags":[
        "processing",
        "datum"
    ],
    "wof:name":"Quasar Computer Svc",
    "wof:placetype":"venue"
},
  "geometry": {"coordinates":[-121.419555,38.539608],"type":"Point"}
}