{
  "type": "Feature",
  "properties": {
    "iso:country":"US",
    "sg:address":"550 Hamilton Ave",
    "sg:city":"Palo Alto",
    "sg:classifiers":[
        {
            "category":"Health Services",
            "subcategory":"Health Practitioner",
            "type":"Services"
        }
    ],
    "sg:phone":"+1 650 322 1975",
    "sg:postcode":"94301",
    "sg:province":"CA",
    "sg:tags":[
        "psychologist"
    ],
    "wof:name":"Elizabeth Biggart PHD",
    "wof:placetype":"venue"
},
  "geometry": {"coordinates":[-122.156948,37.448373],"type":"Point"}
}