{
  "type": "Feature",
  "properties": {
    "iso:country":"US",
    "sg:address":"613 Eastwood Dr",
    "sg:city":"Oxnard",
    "sg:classifiers":[
        {
            "category":"Wholesale",
            "subcategory":"Durable Goods & Equipment",
            "type":"Manufacturing & Wholesale Goods"
        }
    ],
    "sg:phone":"+1 805 988 3626",
    "sg:postcode":"93030",
    "sg:province":"CA",
    "sg:tags":[
        "representative",
        "manufacturer"
    ],
    "wof:name":"Talon Enterprises",
    "wof:placetype":"venue"
},
  "geometry": {"coordinates":[-119.182142,34.212439],"type":"Point"}
}