{
  "type": "Feature",
  "properties": {
    "iso:country":"US",
    "sg:address":"2065 N Broadway",
    "sg:city":"Walnut Creek",
    "sg:classifiers":[
        {
            "category":"Travel",
            "subcategory":"Travel Agent",
            "type":"Entertainment"
        }
    ],
    "sg:phone":"+1 925 927 6618",
    "sg:postcode":"94596",
    "sg:province":"CA",
    "sg:tags":[
        "operator",
        "tour",
        "agency",
        "bureau"
    ],
    "sg:website":"www.holdytours.com",
    "wof:name":"Holdy Tours LLC",
    "wof:placetype":"venue"
},
  "geometry": {"coordinates":[-122.061625,37.906997],"type":"Point"}
}