{
  "type": "Feature",
  "properties": {
    "iso:country":"US",
    "sg:address":"11 E Kappas Marina",
    "sg:city":"Sausalito",
    "sg:classifiers":[
        {
            "category":"Manufacturing",
            "subcategory":"Tools & Machinery",
            "type":"Manufacturing & Wholesale Goods"
        }
    ],
    "sg:phone":"+1 415 332 1365",
    "sg:postcode":"94965",
    "sg:province":"CA",
    "sg:tags":[
        "equipment",
        "mfg"
    ],
    "wof:name":"Telerobotic Corporation",
    "wof:placetype":"venue"
},
  "geometry": {"coordinates":[-122.505289,37.873232],"type":"Point"}
}