{
  "type": "Feature",
  "properties": {
    "iso:country":"US",
    "sg:address":"560 Valdry Court Unit B7",
    "sg:city":"Brentwood",
    "sg:classifiers":[
        {
            "category":"Retail",
            "subcategory":"Auto Repair",
            "type":"Services"
        }
    ],
    "sg:phone":"+1 925 513 4095",
    "sg:postcode":"90049",
    "sg:province":"CA",
    "sg:website":"www.vintagetransmissionandgear.com/",
    "wof:name":"Vintage Transmission And Gear",
    "wof:placetype":"venue"
},
  "geometry": {"coordinates":[-121.68712499999999,37.921828],"type":"Point"}
}