{
  "type": "Feature",
  "properties": {
    "addr:full":"9280 Hwy 128 Healdsburg CA 95448",
    "addr:housenumber":"9280",
    "addr:postcode":"95448",
    "addr:street":"Hwy 128",
    "iso:country":"US",
    "sg:address":"9280 Hwy 128",
    "sg:city":"Healdsburg",
    "sg:classifiers":[
        {
            "category":"Manufacturing",
            "subcategory":"Food",
            "type":"Manufacturing & Wholesale Goods"
        }
    ],
    "sg:phone":"+1 707 431 4310",
    "sg:postcode":"95448",
    "sg:province":"CA",
    "sg:tags":[
        "winery"
    ],
    "sg:website":"www.hannawinery.com",
    "wof:name":"Hanna Winery",
    "wof:placetype":"venue"
},
  "geometry": {"coordinates":[-122.79047799999999,38.65411],"type":"Point"}
}