{
  "type": "Feature",
  "properties": {
    "iso:country":"US",
    "sg:address":"538 Steffan St",
    "sg:city":"Vallejo",
    "sg:classifiers":[
        {
            "category":"Professional",
            "type":"Services"
        }
    ],
    "sg:phone":"+1 707 552 6844",
    "sg:postcode":"94591",
    "sg:province":"CA",
    "wof:name":"Fluffys Creations",
    "wof:placetype":"venue"
},
  "geometry": {"coordinates":[-122.22849,38.097097],"type":"Point"}
}