{
  "type": "Feature",
  "properties": {
    "iso:country":"US",
    "sg:address":"1141 S Gaffey St",
    "sg:city":"San Pedro",
    "sg:classifiers":[
        {
            "category":"Restaurant",
            "type":"Food & Drink"
        }
    ],
    "sg:phone":"+1 310 548 1295",
    "sg:postcode":"90731",
    "sg:province":"CA",
    "wof:name":"Tommy's Burgers",
    "wof:placetype":"venue"
},
  "geometry": {"coordinates":[-118.29242,33.734993],"type":"Point"}
}