{
  "type": "Feature",
  "properties": {
    "iso:country":"US",
    "sg:address":"721 S Glendale Ave",
    "sg:city":"Glendale",
    "sg:classifiers":[
        {
            "category":"Organizations",
            "subcategory":"Membership Organization",
            "type":"Services"
        }
    ],
    "sg:phone":"+1 818 243 3444",
    "sg:postcode":"91205",
    "sg:province":"CA",
    "wof:name":"Armenian National Committee",
    "wof:placetype":"venue"
},
  "geometry": {"coordinates":[-118.251102,34.138684],"type":"Point"}
}