{
  "type": "Feature",
  "properties": {
    "addr:full":"655 University Ave Sacramento CA 95825",
    "addr:housenumber":"655",
    "addr:postcode":"95825",
    "addr:street":"University Ave",
    "iso:country":"US",
    "sg:address":"655 University Ave",
    "sg:city":"Sacramento",
    "sg:classifiers":[
        {
            "category":"Health Services",
            "subcategory":"Clinic",
            "type":"Services"
        }
    ],
    "sg:phone":"+1 916 925 9040",
    "sg:postcode":"95825",
    "sg:province":"CA",
    "wof:name":"Improving Access Counseling",
    "wof:placetype":"venue"
},
  "geometry": {"coordinates":[-121.419462,38.566619],"type":"Point"}
}