{
  "type": "Feature",
  "properties": {
    "iso:country":"US",
    "sg:address":"464 W 4th St",
    "sg:city":"San Bernardino",
    "sg:classifiers":[
        {
            "category":"Government",
            "subcategory":"Office",
            "type":"Public Place"
        }
    ],
    "sg:phone":"+1 909 383 4561",
    "sg:postcode":"92401",
    "sg:province":"CA",
    "sg:tags":[
        "state",
        "program"
    ],
    "sg:website":"www.dot.ca.gov",
    "wof:name":"Transportation Dept",
    "wof:placetype":"venue"
},
  "geometry": {"coordinates":[-117.29362,34.106516],"type":"Point"}
}