{
  "type": "Feature",
  "properties": {
    "addr:full":"2122 Union St San Francisco CA 94123",
    "addr:housenumber":"2122",
    "addr:postcode":"94123",
    "addr:street":"Union St",
    "iso:country":"US",
    "sg:address":"2122 Union St",
    "sg:city":"San Francisco",
    "sg:classifiers":[
        {
            "category":"Shopping",
            "subcategory":"Clothing, Apparel, & Fashions",
            "type":"Retail Goods"
        }
    ],
    "sg:phone":"+1 415 351 2122",
    "sg:postcode":"94123",
    "sg:province":"CA",
    "wof:name":"Brown Eyed Girl",
    "wof:placetype":"venue"
},
  "geometry": {"coordinates":[-122.43521,37.79721],"type":"Point"}
}