{
  "type": "Feature",
  "properties": {
    "iso:country":"US",
    "sg:address":"5044 Huntington Dr S",
    "sg:city":"Los Angeles",
    "sg:classifiers":[
        {
            "category":"Shopping",
            "subcategory":"Gifts & Souvenirs",
            "type":"Retail Goods"
        }
    ],
    "sg:phone":"+1 323 223 3957",
    "sg:postcode":"90032",
    "sg:province":"CA",
    "wof:name":"Margaritas Gift Shop",
    "wof:placetype":"venue"
},
  "geometry": {"coordinates":[-118.173084,34.088047],"type":"Point"}
}