{
  "type": "Feature",
  "properties": {
    "addr:full":"504 S Gateway Dr Madera CA 93637",
    "addr:housenumber":"504",
    "addr:postcode":"93637",
    "addr:street":"S Gateway Dr",
    "iso:country":"US",
    "sg:address":"504 S Gateway Dr",
    "sg:city":"Madera",
    "sg:classifiers":[
        {
            "category":"Autos & Motor Vehicles",
            "subcategory":"Automobile Sales",
            "type":"Retail Goods"
        }
    ],
    "sg:phone":"+1 559 674 7220",
    "sg:postcode":"93637",
    "sg:province":"CA",
    "sg:tags":[
        "car",
        "dealer"
    ],
    "wof:name":"Elite Auto Sales",
    "wof:placetype":"venue"
},
  "geometry": {"coordinates":[-120.056377,36.957113],"type":"Point"}
}