{
  "type": "Feature",
  "properties": {
    "addr:full":"5320 Carpinteria Ave Carpinteria CA 93013",
    "addr:housenumber":"5320",
    "addr:postcode":"93013",
    "addr:street":"Carpinteria Ave",
    "iso:country":"US",
    "sg:address":"5320 Carpinteria Ave",
    "sg:city":"Carpinteria",
    "sg:classifiers":[
        {
            "category":"Professional",
            "subcategory":"Management & Consulting",
            "type":"Services"
        }
    ],
    "sg:phone":"+1 805 745 5998",
    "sg:postcode":"93013",
    "sg:province":"CA",
    "sg:tags":[
        "consultant",
        "telecommunication"
    ],
    "wof:name":"Universal Communication",
    "wof:placetype":"venue"
},
  "geometry": {"coordinates":[-119.514393,34.395834],"type":"Point"}
}