{
  "type": "Feature",
  "properties": {
    "addr:full":"4300 Stine Rd Bakersfield CA 93313",
    "addr:housenumber":"4300",
    "addr:postcode":"93313",
    "addr:street":"Stine Rd",
    "iso:country":"US",
    "sg:address":"4300 Stine Rd",
    "sg:city":"Bakersfield",
    "sg:classifiers":[
        {
            "category":"Wholesale",
            "subcategory":"Durable Goods & Equipment",
            "type":"Manufacturing & Wholesale Goods"
        }
    ],
    "sg:phone":"+1 661 835 9000",
    "sg:postcode":"93313",
    "sg:province":"CA",
    "sg:tags":[
        "laboratory",
        "supply"
    ],
    "sg:website":"www.modernlab.com",
    "wof:name":"Modern Laboratory Svc & Supls",
    "wof:placetype":"venue"
},
  "geometry": {"coordinates":[-119.056597,35.315781],"type":"Point"}
}