{
  "type": "Feature",
  "properties": {
    "iso:country":"US",
    "sg:address":"7230 Cutler Ave",
    "sg:city":"Orland",
    "sg:classifiers":[
        {
            "category":"Manufacturing",
            "subcategory":"Metals",
            "type":"Manufacturing & Wholesale Goods"
        }
    ],
    "sg:phone":"+1 530 865 5721",
    "sg:postcode":"95963",
    "sg:province":"CA",
    "sg:tags":[
        "pottery",
        "product",
        "cutlery",
        "mfg"
    ],
    "wof:name":"Schulps Pottery & Knives",
    "wof:placetype":"venue"
},
  "geometry": {"coordinates":[-122.10961399999999,39.789785],"type":"Point"}
}