{
  "type": "Feature",
  "properties": {
    "addr:full":"74075 el Paseo Palm Desert CA 92260",
    "addr:housenumber":"74075",
    "addr:postcode":"ca 92260",
    "addr:street":"El Paseo",
    "iso:country":"US",
    "sg:address":"74075 el Paseo",
    "sg:city":"Palm Desert",
    "sg:classifiers":[
        {
            "category":"Professional",
            "subcategory":"Lawyer & Legal Services",
            "type":"Services"
        }
    ],
    "sg:phone":"+1 760 341 8366",
    "sg:postcode":"92260",
    "sg:province":"CA",
    "sg:tags":[
        "attorney"
    ],
    "wof:name":"Healey & Healey",
    "wof:placetype":"venue"
},
  "geometry": {"coordinates":[-116.373075,33.719725],"type":"Point"}
}