{
  "type": "Feature",
  "properties": {
    "iso:country":"US",
    "sg:address":"530 Aldo Avenue",
    "sg:city":"Santa Clara",
    "sg:classifiers":[
        {
            "category":"Building & Trades",
            "subcategory":"Construction",
            "type":"Services"
        }
    ],
    "sg:phone":"+1 408 562 9956",
    "sg:postcode":"95054",
    "sg:province":"CA",
    "sg:tags":[
        "contractor"
    ],
    "sg:website":"www.hsrinc.net",
    "wof:name":"Hsr Environmental Services",
    "wof:placetype":"venue"
},
  "geometry": {"coordinates":[-121.945088,37.385521],"type":"Point"}
}