{
  "type": "Feature",
  "properties": {
    "addr:full":"25348 Crenshaw Blvd Torrance CA 90505",
    "addr:housenumber":"25348",
    "addr:postcode":"90505",
    "addr:street":"Crenshaw Blvd",
    "iso:country":"US",
    "sg:address":"25348 Crenshaw Blvd",
    "sg:city":"Torrance",
    "sg:classifiers":[
        {
            "category":"Coffee & Tea",
            "type":"Food & Drink"
        }
    ],
    "sg:menulink":"http://www.allmenus.com/ca/torrance/118527-starbucks-coffee/menu/",
    "sg:phone":"+1 310 534 4835",
    "sg:postcode":"90505",
    "sg:province":"CA",
    "sg:tags":[
        "american"
    ],
    "wof:name":"Starbucks Coffee",
    "wof:placetype":"venue"
},
  "geometry": {"coordinates":[-118.33056000000001,33.793799],"type":"Point"}
}