{
  "type": "Feature",
  "properties": {
    "addr:full":"2500 West Olympic Blvd Los Angeles CA 90006",
    "addr:housenumber":"2500",
    "addr:postcode":"90006",
    "addr:street":"West Olympic Blvd",
    "iso:country":"US",
    "sg:address":"2500 West Olympic Blvd",
    "sg:city":"Los Angeles",
    "sg:classifiers":[
        {
            "category":"Personal",
            "type":"Services"
        },
        {
            "category":"Retail",
            "subcategory":"Auto Repair",
            "type":"Services"
        }
    ],
    "sg:phone":"+1 213 249 9900",
    "sg:postcode":"90006",
    "sg:province":"CA",
    "sg:tags":[
        "body",
        "shop",
        "towing"
    ],
    "sg:website":"www.facebook.com/pages/Los-Angel...",
    "wof:name":"Grand Prix Auto Body Shop",
    "wof:placetype":"venue"
},
  "geometry": {"coordinates":[-118.284238,34.052386],"type":"Point"}
}