{
  "type": "Feature",
  "properties": {
    "addr:full":"245 S Quince St Escondido CA 92025",
    "addr:housenumber":"245",
    "addr:postcode":"92025",
    "addr:street":"S Quince St",
    "iso:country":"US",
    "sg:address":"245 S Quince St",
    "sg:city":"Escondido",
    "sg:classifiers":[
        {
            "category":"Food & Beverages",
            "subcategory":"Specialty",
            "type":"Retail Goods"
        }
    ],
    "sg:phone":"+1 858 487 3366",
    "sg:postcode":"92025",
    "sg:province":"CA",
    "sg:tags":[
        "water",
        "bulk",
        "company"
    ],
    "sg:website":"www.boncor.com",
    "wof:name":"Boncor Water Systems",
    "wof:placetype":"venue"
},
  "geometry": {"coordinates":[-117.087615,33.117277],"type":"Point"}
}