{
  "type": "Feature",
  "properties": {
    "addr:full":"1461 E Cooley Dr Colton CA 92324",
    "addr:housenumber":"1461",
    "addr:postcode":"92324",
    "addr:street":"E Cooley Dr",
    "iso:country":"US",
    "sg:address":"1461 E Cooley Dr",
    "sg:city":"Colton",
    "sg:classifiers":[
        {
            "category":"Professional",
            "subcategory":"Research",
            "type":"Services"
        }
    ],
    "sg:phone":"+1 909 554 5000",
    "sg:postcode":"92324",
    "sg:province":"CA",
    "sg:tags":[
        "environmental",
        "ecological"
    ],
    "wof:name":"Earth Tech",
    "wof:placetype":"venue"
},
  "geometry": {"coordinates":[-117.301151,34.060147],"type":"Point"}
}