{
  "type": "Feature",
  "properties": {
    "addr:full":"7704 Compton Ave Los Angeles CA 90001",
    "addr:housenumber":"7704",
    "addr:postcode":"90001",
    "addr:street":"Compton Ave",
    "iso:country":"US",
    "sg:address":"7704 Compton Ave",
    "sg:city":"Los Angeles",
    "sg:classifiers":[
        {
            "category":"Personal",
            "subcategory":"Beauty Salon",
            "type":"Services"
        }
    ],
    "sg:phone":"+1 323 587 1488",
    "sg:postcode":"90001",
    "sg:province":"CA",
    "sg:tags":[
        "lawyer"
    ],
    "wof:name":"Evelyn's Beauty Salon",
    "wof:placetype":"venue"
},
  "geometry": {"coordinates":[-118.248001,33.969898],"type":"Point"}
}