{
  "type": "Feature",
  "properties": {
    "addr:full":"12604 Mountain Mesa Rd Mountain Mesa CA 93240",
    "addr:housenumber":"12604",
    "addr:postcode":"93240",
    "addr:street":"Mountain Mesa Rd",
    "iso:country":"US",
    "sg:address":"12604 Mountain Mesa Rd",
    "sg:city":"Mountain Mesa",
    "sg:classifiers":[
        {
            "category":"Government",
            "subcategory":"Post Office",
            "type":"Public Place"
        }
    ],
    "sg:phone":"+1 760 379 8464",
    "sg:postcode":"93240",
    "sg:province":"CA",
    "wof:name":"US Post Office",
    "wof:placetype":"venue"
},
  "geometry": {"coordinates":[-118.402321,35.637897],"type":"Point"}
}