{
  "type": "Feature",
  "properties": {
    "addr:full":"7610 Woodley Ave Van Nuys CA 91406",
    "addr:housenumber":"7610",
    "addr:postcode":"91406",
    "addr:street":"Woodley Ave",
    "iso:country":"US",
    "sg:address":"7610 Woodley Ave",
    "sg:city":"Van Nuys",
    "sg:classifiers":[
        {
            "category":"Travel",
            "subcategory":"Travel Agent",
            "type":"Entertainment"
        }
    ],
    "sg:phone":"+1 818 994 5019",
    "sg:postcode":"91406",
    "sg:province":"CA",
    "sg:tags":[
        "ticket",
        "airline"
    ],
    "wof:name":"Northwest Airlines",
    "wof:placetype":"venue"
},
  "geometry": {"coordinates":[-118.48366799999999,34.208435],"type":"Point"}
}