{
  "type": "Feature",
  "properties": {
    "iso:country":"US",
    "sg:address":"235 Montgomery Street Suite 1125",
    "sg:city":"San Francisco",
    "sg:classifiers":[
        {
            "category":"Professional",
            "subcategory":"Employment Agencies",
            "type":"Services"
        }
    ],
    "sg:phone":"+1 415 392 4600",
    "sg:postcode":"94104",
    "sg:province":"CA",
    "sg:website":"www.enhire.com",
    "wof:name":"Elite Network",
    "wof:placetype":"venue"
},
  "geometry": {"coordinates":[-122.40285900000001,37.791391],"type":"Point"}
}