{
  "type": "Feature",
  "properties": {
    "addr:full":"3943 Irvine Blvd Irvine CA 92602",
    "addr:housenumber":"3943",
    "addr:postcode":"92602",
    "addr:street":"Irvine Blvd",
    "iso:country":"US",
    "sg:address":"3943 Irvine Blvd",
    "sg:city":"Irvine",
    "sg:classifiers":[
        {
            "category":"Manufacturing",
            "subcategory":"Furniture",
            "type":"Manufacturing & Wholesale Goods"
        }
    ],
    "sg:phone":"+1 949 252 1016",
    "sg:postcode":"92602",
    "sg:province":"CA",
    "sg:tags":[
        "drapery",
        "mfg"
    ],
    "wof:name":"Vertical Web Design",
    "wof:placetype":"venue"
},
  "geometry": {"coordinates":[-117.773034,33.722949],"type":"Point"}
}