{
  "type": "Feature",
  "properties": {
    "iso:country":"US",
    "sg:address":"416 Union Ave",
    "sg:city":"Fairfield",
    "sg:classifiers":[
        {
            "category":"Retail",
            "subcategory":"Repair Shop",
            "type":"Services"
        }
    ],
    "sg:phone":"+1 707 421 2025",
    "sg:postcode":"94533",
    "sg:province":"CA",
    "sg:tags":[
        "scooter",
        "motorcycle",
        "motor"
    ],
    "wof:name":"Other Place",
    "wof:placetype":"venue"
},
  "geometry": {"coordinates":[-122.040483,38.246264],"type":"Point"}
}