{
  "type": "Feature",
  "properties": {
    "iso:country":"US",
    "sg:address":"2264 Pacific Ave",
    "sg:city":"Long Beach",
    "sg:classifiers":[
        {
            "category":"Restaurant",
            "type":"Food & Drink"
        }
    ],
    "sg:phone":"+1 562 426 8888",
    "sg:postcode":"90806",
    "sg:province":"CA",
    "sg:tags":[
        "thai"
    ],
    "sg:website":"www.thaiboomlongbeach.com",
    "wof:name":"Thai Boom",
    "wof:placetype":"venue"
},
  "geometry": {"coordinates":[-118.193609,33.798381],"type":"Point"}
}