{
  "type": "Feature",
  "properties": {
    "iso:country":"US",
    "sg:address":"3311 Mission St #257",
    "sg:city":"San Francisco",
    "sg:classifiers":[
        {
            "category":"Building & Trades",
            "subcategory":"Cleaning & Sanitation",
            "type":"Services"
        }
    ],
    "sg:phone":"+1 415 574 9270",
    "sg:postcode":"94110",
    "sg:province":"CA",
    "sg:tags":[
        "home"
    ],
    "wof:name":"Gloria's House Cleaning",
    "wof:placetype":"venue"
},
  "geometry": {"coordinates":[-122.420637,37.743847],"type":"Point"}
}