{
  "type": "Feature",
  "properties": {
    "iso:country":"US",
    "sg:address":"7155 Broadway",
    "sg:city":"Lemon Grove",
    "sg:classifiers":[
        {
            "category":"Food & Beverages",
            "subcategory":"Groceries & Convenience Stores",
            "type":"Retail Goods"
        }
    ],
    "sg:phone":"+1 619 644 8540",
    "sg:postcode":"91945",
    "sg:province":"CA",
    "sg:tags":[
        "grocer"
    ],
    "wof:name":"Farmers Market",
    "wof:placetype":"venue"
},
  "geometry": {"coordinates":[-117.045371,32.742432],"type":"Point"}
}