{
  "type": "Feature",
  "properties": {
    "iso:country":"US",
    "sg:address":"2874 Golden Gate Ave",
    "sg:city":"San Francisco",
    "sg:classifiers":[
        {
            "category":"Building & Trades",
            "subcategory":"Construction",
            "type":"Services"
        }
    ],
    "sg:phone":"+1 415 716 1876",
    "sg:postcode":"94118",
    "sg:province":"CA",
    "sg:tags":[
        "house"
    ],
    "wof:name":"Devenish Construction",
    "wof:placetype":"venue"
},
  "geometry": {"coordinates":[-122.45741700000001,37.776437],"type":"Point"}
}