{
  "type": "Feature",
  "properties": {
    "addr:full":"30 N Raymond Ave Pasadena CA 91103",
    "addr:housenumber":"30",
    "addr:postcode":"91103",
    "addr:street":"N Raymond Ave",
    "iso:country":"US",
    "sg:address":"30 N Raymond Ave",
    "sg:city":"Pasadena",
    "sg:classifiers":[
        {
            "category":"Professional",
            "subcategory":"Lawyer & Legal Services",
            "type":"Services"
        }
    ],
    "sg:phone":"+1 626 304 7062",
    "sg:postcode":"91103",
    "sg:province":"CA",
    "sg:tags":[
        "attorney"
    ],
    "wof:name":"Vincent P Landeros",
    "wof:placetype":"venue"
},
  "geometry": {"coordinates":[-118.148822,34.146264],"type":"Point"}
}