{
  "type": "Feature",
  "properties": {
    "iso:country":"US",
    "sg:address":"1561 W Pacheco Blvd",
    "sg:city":"Los Banos",
    "sg:classifiers":[
        {
            "category":"Banks & Credit Unions",
            "subcategory":"Bank",
            "type":"Services"
        }
    ],
    "sg:phone":"+1 209 827 3700",
    "sg:postcode":"93635",
    "sg:province":"CA",
    "sg:tags":[
        "cashing",
        "check"
    ],
    "wof:name":"Check 'n Go",
    "wof:placetype":"venue"
},
  "geometry": {"coordinates":[-120.87038800000001,37.056693],"type":"Point"}
}