{
  "type": "Feature",
  "properties": {
    "addr:full":"2260 el Cajon Blvd San Diego CA 92104",
    "addr:housenumber":"2260",
    "addr:postcode":"92104",
    "addr:street":"El Cajon Blvd",
    "iso:country":"US",
    "sg:address":"2260 el Cajon Blvd",
    "sg:city":"San Diego",
    "sg:classifiers":[
        {
            "category":"Communications",
            "type":"Services"
        }
    ],
    "sg:phone":"+1 619 295 3853",
    "sg:postcode":"92104",
    "sg:province":"CA",
    "sg:tags":[
        "communication"
    ],
    "wof:name":"Mlm World News & Reports",
    "wof:placetype":"venue"
},
  "geometry": {"coordinates":[-117.140737,32.755342],"type":"Point"}
}