{
  "type": "Feature",
  "properties": {
    "addr:full":"2404 X St Sacramento CA 95818",
    "addr:housenumber":"2404",
    "addr:postcode":"95818",
    "addr:street":"X St",
    "iso:country":"US",
    "sg:address":"2404 X St",
    "sg:city":"Sacramento",
    "sg:classifiers":[
        {
            "category":"Arts & Performance",
            "subcategory":"Art Gallery",
            "type":"Entertainment"
        }
    ],
    "sg:phone":"+1 916 455 2105",
    "sg:postcode":"95818",
    "sg:province":"CA",
    "wof:name":"Sacramento Art & Frame",
    "wof:placetype":"venue"
},
  "geometry": {"coordinates":[-121.481003,38.5597],"type":"Point"}
}