{
  "type": "Feature",
  "properties": {
    "addr:full":"2 Henry Adams Street San Francisco CA 94103",
    "addr:housenumber":"2",
    "addr:postcode":"94103",
    "addr:street":"Henry Adams Street",
    "iso:country":"US",
    "sg:address":"2 Henry Adams Street",
    "sg:city":"San Francisco",
    "sg:classifiers":[
        {
            "category":"Building & Trades",
            "subcategory":"Construction",
            "type":"Services"
        }
    ],
    "sg:phone":"+1 415 626 5504",
    "sg:postcode":"94103",
    "sg:province":"CA",
    "sg:tags":[
        "interior",
        "design"
    ],
    "wof:name":"McKinney Tres Design",
    "wof:placetype":"venue"
},
  "geometry": {"coordinates":[-122.403978,37.769773],"type":"Point"}
}