{
  "type": "Feature",
  "properties": {
    "addr:full":"2701 Tuberose Ct Pleasanton CA 94588",
    "addr:housenumber":"2701",
    "addr:postcode":"94588",
    "addr:street":"Tuberose Ct",
    "iso:country":"US",
    "sg:address":"2701 Tuberose Ct",
    "sg:city":"Pleasanton",
    "sg:classifiers":[
        {
            "category":"Professional",
            "type":"Services"
        }
    ],
    "sg:phone":"+1 925 461 4396",
    "sg:postcode":"94588",
    "sg:province":"CA",
    "wof:name":"Jiawei Guo",
    "wof:placetype":"venue"
},
  "geometry": {"coordinates":[-121.85821799999999,37.692593],"type":"Point"}
}