{
  "type": "Feature",
  "properties": {
    "iso:country":"US",
    "sg:address":"1239 E Hammer Ln",
    "sg:city":"Stockton",
    "sg:classifiers":[
        {
            "category":"Food & Beverages",
            "subcategory":"Specialty",
            "type":"Retail Goods"
        }
    ],
    "sg:phone":"+1 209 477 4898",
    "sg:postcode":"95210",
    "sg:province":"CA",
    "sg:tags":[
        "water",
        "bulk",
        "company"
    ],
    "wof:name":"Hammer Lane Pure Water",
    "wof:placetype":"venue"
},
  "geometry": {"coordinates":[-121.297042,38.020994],"type":"Point"}
}