{
  "type": "Feature",
  "properties": {
    "iso:country":"US",
    "sg:address":"7310 Miramar Rd",
    "sg:city":"San Diego",
    "sg:classifiers":[
        {
            "category":"Home & Garden",
            "subcategory":"Furniture",
            "type":"Retail Goods"
        }
    ],
    "sg:phone":"+1 858 566 4030",
    "sg:postcode":"92126",
    "sg:province":"CA",
    "wof:name":"Unique Wood Designs By Marcos",
    "wof:placetype":"venue"
},
  "geometry": {"coordinates":[-117.149254,32.886107],"type":"Point"}
}