{
  "type": "Feature",
  "properties": {
    "iso:country":"US",
    "sg:address":"Bancroft Way & Telegraph Ave 1 Sproul Hall",
    "sg:city":"Berkeley",
    "sg:classifiers":[
        {
            "category":"Government",
            "subcategory":"City Hall",
            "type":"Public Place"
        }
    ],
    "sg:phone":"+1 510 642 6760",
    "sg:postcode":"94704",
    "sg:province":"CA",
    "sg:website":"police.berkeley.edu",
    "wof:name":"UC Berkeley Police Department",
    "wof:placetype":"venue"
},
  "geometry": {"coordinates":[-122.259209,37.868713],"type":"Point"}
}