{
  "type": "Feature",
  "properties": {
    "addr:full":"19057 Colima Rd Rowland Heights CA 91748",
    "addr:postcode":"19057;91748",
    "addr:street":"Colima Rd",
    "iso:country":"US",
    "sg:address":"19057 Colima Rd",
    "sg:city":"Rowland Heights",
    "sg:classifiers":[
        {
            "category":"Real Estate",
            "subcategory":"Real Estate Agent",
            "type":"Services"
        }
    ],
    "sg:phone":"+1 626 854 2888",
    "sg:postcode":"91748",
    "sg:province":"CA",
    "wof:name":"Walton Realty",
    "wof:placetype":"venue"
},
  "geometry": {"coordinates":[-117.88901,33.987561],"type":"Point"}
}