{
  "type": "Feature",
  "properties": {
    "addr:full":"292 Merced Ave Merced CA 95351",
    "addr:housenumber":"292",
    "addr:postcode":"95351",
    "addr:street":"Merced Ave",
    "iso:country":"US",
    "sg:address":"292 Merced Ave",
    "sg:city":"Merced",
    "sg:classifiers":[
        {
            "category":"Shopping",
            "type":"Retail Goods"
        }
    ],
    "sg:phone":"+1 209 383 9292",
    "sg:postcode":"95351",
    "sg:province":"CA",
    "sg:tags":[
        "telephone",
        "cellular"
    ],
    "wof:name":"Radio Shack",
    "wof:placetype":"venue"
},
  "geometry": {"coordinates":[-120.998886,37.629252],"type":"Point"}
}