{
  "type": "Feature",
  "properties": {
    "iso:country":"US",
    "sg:address":"5600 Fresca Dr",
    "sg:city":"La Palma",
    "sg:classifiers":[
        {
            "category":"Wholesale",
            "subcategory":"Electrical",
            "type":"Manufacturing & Wholesale Goods"
        }
    ],
    "sg:phone":"+1 714 562 1934",
    "sg:postcode":"90623",
    "sg:province":"CA",
    "sg:tags":[
        "wiring",
        "electric",
        "supply"
    ],
    "wof:name":"Walters Wholesale Electric Co",
    "wof:placetype":"venue"
},
  "geometry": {"coordinates":[-118.03646000000001,33.861558],"type":"Point"}
}