{
  "type": "Feature",
  "properties": {
    "addr:full":"10323 Santa Monica Boulevard Los Angeles CA 90025",
    "addr:housenumber":"10323",
    "addr:postcode":"90025",
    "addr:street":"Santa Monica Boulevard",
    "iso:country":"US",
    "sg:address":"10323 Santa Monica Boulevard",
    "sg:city":"Los Angeles",
    "sg:classifiers":[
        {
            "category":"Professional",
            "subcategory":"Lawyer & Legal Services",
            "type":"Services"
        }
    ],
    "sg:phone":"+1 310 553 6611",
    "sg:postcode":"90025",
    "sg:province":"CA",
    "wof:name":"Owens & Gach-Ray",
    "wof:placetype":"venue"
},
  "geometry": {"coordinates":[-118.4216,34.05105],"type":"Point"}
}