{
  "type": "Feature",
  "properties": {
    "iso:country":"US",
    "sg:address":"4350 Lockwood Way",
    "sg:city":"Sacramento",
    "sg:classifiers":[
        {
            "category":"Professional",
            "subcategory":"Management & Consulting",
            "type":"Services"
        }
    ],
    "sg:phone":"+1 916 688 0630",
    "sg:postcode":"95821",
    "sg:province":"CA",
    "sg:tags":[
        "consultant"
    ],
    "wof:name":"C & J Consulting",
    "wof:placetype":"venue"
},
  "geometry": {"coordinates":[-121.363363,38.627629],"type":"Point"}
}