{
  "type": "Feature",
  "properties": {
    "addr:full":"4825 Fair Oaks Blvd Carmichael CA 95608",
    "addr:housenumber":"4825",
    "addr:postcode":"95608",
    "addr:street":"Fair Oaks Blvd",
    "iso:country":"US",
    "sg:address":"4825 Fair Oaks Blvd",
    "sg:city":"Carmichael",
    "sg:classifiers":[
        {
            "category":"Building & Trades",
            "subcategory":"Construction",
            "type":"Services"
        }
    ],
    "sg:phone":"+1 916 487 7702",
    "sg:postcode":"95608",
    "sg:province":"CA",
    "sg:tags":[
        "contractor"
    ],
    "wof:name":"Sam J Chilelli",
    "wof:placetype":"venue"
},
  "geometry": {"coordinates":[-121.351027,38.589752],"type":"Point"}
}