{
  "type": "Feature",
  "properties": {
    "addr:full":"1681 Coolidge St San Diego CA 92111",
    "addr:housenumber":"1681",
    "addr:postcode":"92111",
    "addr:street":"Coolidge St",
    "iso:country":"US",
    "sg:address":"1681 Coolidge St",
    "sg:city":"San Diego",
    "sg:classifiers":[
        {
            "category":"Home & Garden",
            "subcategory":"Carpets & Floor Coverings",
            "type":"Retail Goods"
        }
    ],
    "sg:phone":"+1 858 761 1816",
    "sg:postcode":"92111",
    "sg:province":"CA",
    "wof:name":"Zaks Floor Coverings Inc",
    "wof:placetype":"venue"
},
  "geometry": {"coordinates":[-117.17080799999999,32.774616],"type":"Point"}
}