{
  "type": "Feature",
  "properties": {
    "addr:full":"10773 Los Alamitos Blvd Los Alamitos CA 90720",
    "addr:housenumber":"10773",
    "addr:postcode":"90720",
    "addr:street":"Los Alamitos Blvd",
    "iso:country":"US",
    "sg:address":"10773 Los Alamitos Blvd",
    "sg:city":"Los Alamitos",
    "sg:classifiers":[
        {
            "category":"Real Estate",
            "subcategory":"Real Estate Services",
            "type":"Services"
        },
        {
            "category":"Banks & Credit Unions",
            "subcategory":"Financial Services",
            "type":"Services"
        }
    ],
    "sg:phone":"+1 562 799 6556",
    "sg:postcode":"90720",
    "sg:province":"CA",
    "sg:tags":[
        "management",
        "property",
        "broker",
        "mortgage"
    ],
    "wof:name":"RAD Properties",
    "wof:placetype":"venue"
},
  "geometry": {"coordinates":[-118.20163599999999,33.806092],"type":"Point"}
}