{
  "type": "Feature",
  "properties": {
    "addr:full":"423 N Main St Pomona CA 91768",
    "addr:housenumber":"423",
    "addr:postcode":"91768",
    "addr:street":"N Main St",
    "iso:country":"US",
    "sg:address":"423 N Main St",
    "sg:city":"Pomona",
    "sg:classifiers":[
        {
            "category":"Organizations",
            "subcategory":"Religious Organization",
            "type":"Services"
        }
    ],
    "sg:phone":"+1 909 622 3611",
    "sg:postcode":"91768",
    "sg:province":"CA",
    "sg:tags":[
        "church"
    ],
    "wof:name":"Templo De LA Fe",
    "wof:placetype":"venue"
},
  "geometry": {"coordinates":[-117.752548,34.062113],"type":"Point"}
}