{
  "type": "Feature",
  "properties": {
    "iso:country":"US",
    "sg:address":"27501 Ynez Rd",
    "sg:city":"Temecula",
    "sg:classifiers":[
        {
            "category":"Coffee & Tea",
            "type":"Food & Drink"
        }
    ],
    "sg:menulink":"http://www.allmenus.com/ca/murrieta/118532-starbucks-coffee/menu/",
    "sg:phone":"+1 951 699 2966",
    "sg:postcode":"92591",
    "sg:province":"CA",
    "sg:tags":[
        "american"
    ],
    "wof:name":"Starbucks Coffee",
    "wof:placetype":"venue"
},
  "geometry": {"coordinates":[-117.149944,33.505069],"type":"Point"}
}