{
  "type": "Feature",
  "properties": {
    "iso:country":"US",
    "sg:address":"2555 Morena Blvd",
    "sg:city":"San Diego",
    "sg:classifiers":[
        {
            "category":"Real Estate",
            "subcategory":"Architect",
            "type":"Services"
        }
    ],
    "sg:phone":"+1 619 275 5323",
    "sg:postcode":"92110",
    "sg:province":"CA",
    "sg:tags":[
        "designer",
        "architectural"
    ],
    "wof:name":"LA Grange Assoc",
    "wof:placetype":"venue"
},
  "geometry": {"coordinates":[-117.205875,32.788926],"type":"Point"}
}