{
  "type": "Feature",
  "properties": {
    "iso:country":"US",
    "sg:address":"24642 Jeronimo Road",
    "sg:city":"Lake Forest",
    "sg:classifiers":[
        {
            "category":"Education",
            "subcategory":"School",
            "type":"Public Place"
        }
    ],
    "sg:phone":"+1 949 586 3221",
    "sg:postcode":"92630",
    "sg:province":"CA",
    "sg:tags":[
        "high",
        "middle",
        "elementary"
    ],
    "wof:name":"Serrano Intermediate School",
    "wof:placetype":"venue"
},
  "geometry": {"coordinates":[-117.697254,33.633152],"type":"Point"}
}