{
  "type": "Feature",
  "properties": {
    "addr:full":"601 University Ave Ste 288 Sacramento CA 95825",
    "addr:housenumber":"601",
    "addr:postcode":"95825",
    "addr:street":"University Ave Ste 288",
    "iso:country":"US",
    "sg:address":"601 University Ave Ste 288",
    "sg:city":"Sacramento",
    "sg:classifiers":[
        {
            "category":"Professional",
            "subcategory":"Lawyer & Legal Services",
            "type":"Services"
        }
    ],
    "sg:phone":"+1 916 925 7177",
    "sg:postcode":"95825",
    "sg:province":"CA",
    "sg:tags":[
        "attorney",
        "practice",
        "plan"
    ],
    "sg:website":"http://www.cohenattorneys.com",
    "wof:name":"Cohen, Frederick S Law Offices Of",
    "wof:placetype":"venue"
},
  "geometry": {"coordinates":[-121.419134,38.567671],"type":"Point"}
}