{
  "type": "Feature",
  "properties": {
    "addr:full":"580 E Keats Ave Fresno CA 93710",
    "addr:housenumber":"580",
    "addr:postcode":"93710",
    "addr:street":"E Keats Ave",
    "iso:country":"US",
    "sg:address":"580 E Keats Ave",
    "sg:city":"Fresno",
    "sg:classifiers":[
        {
            "category":"Building & Trades",
            "subcategory":"Pest Control",
            "type":"Services"
        }
    ],
    "sg:phone":"+1 559 297 9181",
    "sg:postcode":"93710",
    "sg:province":"CA",
    "wof:name":"Back Off Bugs",
    "wof:placetype":"venue"
},
  "geometry": {"coordinates":[-119.778633,36.81042],"type":"Point"}
}