{
  "type": "Feature",
  "properties": {
    "addr:full":"610 N Redondo Dr Oceanside CA 92057",
    "addr:housenumber":"610",
    "addr:postcode":"92057",
    "addr:street":"N Redondo Dr",
    "iso:country":"US",
    "sg:address":"610 N Redondo Dr",
    "sg:city":"Oceanside",
    "sg:classifiers":[
        {
            "category":"Government",
            "subcategory":"Office",
            "type":"Public Place"
        }
    ],
    "sg:phone":"+1 760 757 4050",
    "sg:postcode":"92057",
    "sg:province":"CA",
    "sg:tags":[
        "legislative",
        "body"
    ],
    "wof:name":"Byron For Congress",
    "wof:placetype":"venue"
},
  "geometry": {"coordinates":[-117.301084,33.254992],"type":"Point"}
}