{
  "type": "Feature",
  "properties": {
    "iso:country":"US",
    "sg:address":"515 Cabrillo Park Dr",
    "sg:city":"Santa Ana",
    "sg:classifiers":[
        {
            "category":"Banks & Credit Unions",
            "subcategory":"Bank",
            "type":"Services"
        }
    ],
    "sg:phone":"+1 714 210 0719",
    "sg:postcode":"92701",
    "sg:province":"CA",
    "sg:tags":[
        "loan",
        "real estate"
    ],
    "wof:name":"Security Mortgage",
    "wof:placetype":"venue"
},
  "geometry": {"coordinates":[-117.840451,33.748798],"type":"Point"}
}