{
  "type": "Feature",
  "properties": {
    "iso:country":"US",
    "sg:address":"2455 Masonic Drive",
    "sg:city":"San Jose",
    "sg:classifiers":[
        {
            "category":"Retail",
            "subcategory":"Event Space",
            "type":"Services"
        }
    ],
    "sg:phone":"+1 408 978 7483",
    "sg:postcode":"95125",
    "sg:province":"CA",
    "sg:tags":[
        "venue"
    ],
    "wof:name":"San Jose Scottish Rite Center",
    "wof:placetype":"venue"
},
  "geometry": {"coordinates":[-121.87308400000001,37.290857],"type":"Point"}
}