{
  "type": "Feature",
  "properties": {
    "addr:full":"5801 N Figueroa St Los Angeles CA 90042",
    "addr:housenumber":"5801",
    "addr:postcode":"90042",
    "addr:street":"N Figueroa St",
    "iso:country":"US",
    "sg:address":"5801 N Figueroa St",
    "sg:city":"Los Angeles",
    "sg:classifiers":[
        {
            "category":"Restaurant",
            "type":"Food & Drink"
        }
    ],
    "sg:phone":"+1 323 257 7399",
    "sg:postcode":"90042",
    "sg:province":"CA",
    "sg:tags":[
        "fast"
    ],
    "wof:name":"Tam's Junior Burger No 2",
    "wof:placetype":"venue"
},
  "geometry": {"coordinates":[-118.191377,34.110299],"type":"Point"}
}