{
  "type": "Feature",
  "properties": {
    "iso:country":"US",
    "sg:address":"3048 Sunny Meadow Ln",
    "sg:city":"San Jose",
    "sg:classifiers":[
        {
            "category":"Real Estate",
            "subcategory":"Architect",
            "type":"Services"
        }
    ],
    "sg:phone":"+1 408 270 3327",
    "sg:postcode":"95135",
    "sg:province":"CA",
    "sg:tags":[
        "architectural"
    ],
    "wof:name":"Fish Richard L AIA Architect",
    "wof:placetype":"venue"
},
  "geometry": {"coordinates":[-121.760945,37.296848],"type":"Point"}
}