{
  "type": "Feature",
  "properties": {
    "addr:full":"1242 E Colorado Blvd Pasadena CA 91106",
    "addr:housenumber":"1242",
    "addr:postcode":"91106",
    "addr:street":"E Colorado Blvd",
    "iso:country":"US",
    "sg:address":"1242 E Colorado Blvd",
    "sg:city":"Pasadena",
    "sg:classifiers":[
        {
            "category":"Banks & Credit Unions",
            "subcategory":"Bank",
            "type":"Services"
        }
    ],
    "sg:phone":"+1 626 795 2920",
    "sg:postcode":"91106",
    "sg:province":"CA",
    "sg:tags":[
        "loan",
        "real estate"
    ],
    "wof:name":"Pasadena Home Loans Inc",
    "wof:placetype":"venue"
},
  "geometry": {"coordinates":[-118.125114,34.146023],"type":"Point"}
}