{
  "type": "Feature",
  "properties": {
    "iso:country":"US",
    "sg:address":"330 Lang Rd",
    "sg:city":"Burlingame",
    "sg:classifiers":[
        {
            "category":"Retail",
            "subcategory":"Repair Shop",
            "type":"Services"
        }
    ],
    "sg:phone":"+1 650 375 8480",
    "sg:postcode":"94010",
    "sg:province":"CA",
    "sg:tags":[
        "related"
    ],
    "wof:name":"Espresso Equipment Engineering",
    "wof:placetype":"venue"
},
  "geometry": {"coordinates":[-122.336541,37.587231],"type":"Point"}
}