{
  "type": "Feature",
  "properties": {
    "iso:country":"US",
    "sg:address":"4126 Sepulveda Blvd",
    "sg:city":"Torrance",
    "sg:classifiers":[
        {
            "category":"Personal",
            "subcategory":"Beauty Salon",
            "type":"Services"
        }
    ],
    "sg:phone":"+1 310 375 8279",
    "sg:postcode":"90505",
    "sg:province":"CA",
    "sg:tags":[
        "hair"
    ],
    "wof:name":"Cute Haircuts for Kids",
    "wof:placetype":"venue"
},
  "geometry": {"coordinates":[-118.357,33.825682],"type":"Point"}
}