{
  "type": "Feature",
  "properties": {
    "iso:country":"US",
    "sg:address":"1437 W Chapman Ave",
    "sg:city":"Orange",
    "sg:classifiers":[
        {
            "category":"Retail",
            "subcategory":"Laundry & Dry Cleaning",
            "type":"Services"
        }
    ],
    "sg:phone":"+1 714 978 7489",
    "sg:postcode":"92868",
    "sg:province":"CA",
    "wof:name":"Orange Cleaners",
    "wof:placetype":"venue"
},
  "geometry": {"coordinates":[-117.86799600000001,33.7878],"type":"Point"}
}