{
  "type": "Feature",
  "properties": {
    "addr:full":"14808 Olympic Dr Clearlake CA 95422",
    "addr:housenumber":"14808",
    "addr:postcode":"95422",
    "addr:street":"Olympic Dr",
    "iso:country":"US",
    "sg:address":"14808 Olympic Dr",
    "sg:city":"Clearlake",
    "sg:phone":"+1 707 994 7400",
    "sg:postcode":"95422",
    "sg:province":"CA",
    "wof:name":"Dollar Smart Inc",
    "wof:placetype":"venue"
},
  "geometry": {"coordinates":[-122.634855,38.96183],"type":"Point"}
}