{
  "type": "Feature",
  "properties": {
    "iso:country":"US",
    "sg:address":"1205 John Reed Ct",
    "sg:city":"City Of Industry",
    "sg:classifiers":[
        {
            "category":"Wholesale",
            "subcategory":"Construction Materials",
            "type":"Manufacturing & Wholesale Goods"
        }
    ],
    "sg:phone":"+1 626 912 8377",
    "sg:postcode":"91745",
    "sg:province":"CA",
    "sg:tags":[
        "fence"
    ],
    "wof:name":"K P Distribution Inc",
    "wof:placetype":"venue"
},
  "geometry": {"coordinates":[-117.940332,34.001562],"type":"Point"}
}