{
  "type": "Feature",
  "properties": {
    "iso:country":"US",
    "sg:address":"6355 Pacific Boulevard",
    "sg:city":"Huntington Park",
    "sg:classifiers":[
        {
            "category":"Shopping",
            "subcategory":"Hobbies, Toys, & Games",
            "type":"Retail Goods"
        }
    ],
    "sg:phone":"+1 323 581 0376",
    "sg:postcode":"90255",
    "sg:province":"CA",
    "sg:tags":[
        "toy",
        "store"
    ],
    "wof:name":"Compita Gift & Toy",
    "wof:placetype":"venue"
},
  "geometry": {"coordinates":[-118.225098,33.982198],"type":"Point"}
}