{
  "type": "Feature",
  "properties": {
    "addr:full":"2332 Harrison Ave Eureka CA 95501",
    "addr:housenumber":"2332",
    "addr:postcode":"95501",
    "addr:street":"Harrison Ave",
    "iso:country":"US",
    "sg:address":"2332 Harrison Ave",
    "sg:city":"Eureka",
    "sg:classifiers":[
        {
            "category":"Health Services",
            "subcategory":"Doctor",
            "type":"Services"
        }
    ],
    "sg:phone":"+1 707 443 7381",
    "sg:postcode":"95501",
    "sg:province":"CA",
    "sg:tags":[
        "dentist"
    ],
    "wof:name":"I Leonard Agnew DDS",
    "wof:placetype":"venue"
},
  "geometry": {"coordinates":[-124.139685,40.786563],"type":"Point"}
}