{
  "type": "Feature",
  "properties": {
    "addr:full":"6892 Doolittle Ave Riverside CA 92503",
    "addr:housenumber":"6892",
    "addr:postcode":"92503",
    "addr:street":"Doolittle Ave",
    "iso:country":"US",
    "sg:address":"6892 Doolittle Ave",
    "sg:city":"Riverside",
    "sg:classifiers":[
        {
            "category":"Retail",
            "subcategory":"Auto Repair",
            "type":"Services"
        }
    ],
    "sg:phone":"+1 951 354 2231",
    "sg:postcode":"92503",
    "sg:province":"CA",
    "sg:tags":[
        "repairing",
        "automobile",
        "general"
    ],
    "sg:website":"www.cadspecialties.com",
    "wof:name":"Cad Specialties",
    "wof:placetype":"venue"
},
  "geometry": {"coordinates":[-117.45963,33.954534],"type":"Point"}
}