{
  "type": "Feature",
  "properties": {
    "iso:country":"US",
    "sg:address":"241 W Dawson Ave",
    "sg:city":"Glendora",
    "sg:classifiers":[
        {
            "category":"Community Center",
            "subcategory":"Youth",
            "type":"Public Place"
        },
        {
            "category":"Government",
            "subcategory":"Office",
            "type":"Public Place"
        }
    ],
    "sg:phone":"+1 626 914 2357",
    "sg:postcode":"91740",
    "sg:province":"CA",
    "wof:name":"Glendora Crowther Teen Ctr",
    "wof:placetype":"venue"
},
  "geometry": {"coordinates":[-117.866775,34.11756],"type":"Point"}
}