{
  "type": "Feature",
  "properties": {
    "addr:full":"1540 Petaluma Hill Rd Santa Rosa CA 95404",
    "addr:housenumber":"1540",
    "addr:postcode":"95404",
    "addr:street":"Petaluma Hill Rd",
    "iso:country":"US",
    "sg:address":"1540 Petaluma Hill Rd",
    "sg:city":"Santa Rosa",
    "sg:classifiers":[
        {
            "category":"Retail",
            "subcategory":"Auto Repair",
            "type":"Services"
        }
    ],
    "sg:phone":"+1 707 527 0805",
    "sg:postcode":"95404",
    "sg:province":"CA",
    "sg:tags":[
        "repairing",
        "automobile"
    ],
    "wof:name":"Race Automotive",
    "wof:placetype":"venue"
},
  "geometry": {"coordinates":[-122.707734,38.42334],"type":"Point"}
}