{
  "type": "Feature",
  "properties": {
    "iso:country":"US",
    "sg:address":"1012 Main St",
    "sg:city":"Fortuna",
    "sg:classifiers":[
        {
            "category":"Shopping",
            "subcategory":"Hobbies, Toys, & Games",
            "type":"Retail Goods"
        }
    ],
    "sg:phone":"+1 707 725 1817",
    "sg:postcode":"95540",
    "sg:province":"CA",
    "sg:tags":[
        "supply"
    ],
    "wof:name":"Crasty's Total Gamer",
    "wof:placetype":"venue"
},
  "geometry": {"coordinates":[-124.15651800000001,40.598083],"type":"Point"}
}