{
  "type": "Feature",
  "properties": {
    "iso:country":"US",
    "sg:address":"9849 Fair Oaks Blvd",
    "sg:city":"Fair Oaks",
    "sg:classifiers":[
        {
            "category":"Organizations",
            "subcategory":"Religious Organization",
            "type":"Services"
        }
    ],
    "sg:phone":"+1 916 965 6206",
    "sg:postcode":"95628",
    "sg:province":"CA",
    "sg:tags":[
        "church"
    ],
    "wof:name":"Korean Central Presbyterian",
    "wof:placetype":"venue"
},
  "geometry": {"coordinates":[-121.276421,38.639366],"type":"Point"}
}