{
  "type": "Feature",
  "properties": {
    "addr:full":"6600 Madison Ave #4B Carmichael CA 95608",
    "addr:housenumber":"6600;4b",
    "addr:postcode":"95608",
    "addr:street":"Madison Ave #",
    "iso:country":"US",
    "sg:address":"6600 Madison Ave #4B",
    "sg:city":"Carmichael",
    "sg:classifiers":[
        {
            "category":"Health Services",
            "subcategory":"Dentist",
            "type":"Services"
        }
    ],
    "sg:phone":"+1 916 961 8454",
    "sg:postcode":"95608",
    "sg:province":"CA",
    "sg:website":"www.carmichaelfamilydentist.com",
    "wof:name":"Brian S Orcutt, DDS",
    "wof:placetype":"venue"
},
  "geometry": {"coordinates":[-121.310225,38.662979],"type":"Point"}
}