{
  "type": "Feature",
  "properties": {
    "iso:country":"US",
    "sg:address":"1922 E Front St",
    "sg:city":"Selma",
    "sg:classifiers":[
        {
            "category":"Shopping",
            "subcategory":"Computers & Home Electronics",
            "type":"Retail Goods"
        }
    ],
    "sg:phone":"+1 559 891 7831",
    "sg:postcode":"93662",
    "sg:province":"CA",
    "sg:tags":[
        "television",
        "radio"
    ],
    "wof:name":"Machado's TV Ctr",
    "wof:placetype":"venue"
},
  "geometry": {"coordinates":[-119.612443,36.567871],"type":"Point"}
}