{
  "type": "Feature",
  "properties": {
    "iso:country":"US",
    "sg:address":"3203 Fitzgerald Rd",
    "sg:city":"Rancho Cordova",
    "sg:classifiers":[
        {
            "category":"Personal",
            "type":"Services"
        }
    ],
    "sg:phone":"+1 916 631 1365",
    "sg:postcode":"95742",
    "sg:province":"CA",
    "sg:tags":[
        "local"
    ],
    "sg:website":"www.cookengineeringinc.com",
    "wof:name":"Cook Engineering",
    "wof:placetype":"venue"
},
  "geometry": {"coordinates":[-121.25846300000001,38.586795],"type":"Point"}
}