{
  "type": "Feature",
  "properties": {
    "iso:country":"US",
    "sg:address":"1953 Parkmont Dr",
    "sg:city":"Alamo",
    "sg:classifiers":[
        {
            "category":"Professional",
            "subcategory":"Advertising",
            "type":"Services"
        }
    ],
    "sg:phone":"+1 925 855 8566",
    "sg:postcode":"94507",
    "sg:province":"CA",
    "sg:tags":[
        "counselor"
    ],
    "sg:website":"www.hdesign.com",
    "wof:name":"Hirsch Design",
    "wof:placetype":"venue"
},
  "geometry": {"coordinates":[-121.967353,37.846493],"type":"Point"}
}