{
  "type": "Feature",
  "properties": {
    "addr:full":"152 N 3rd Street Suite 501 San Jose CA 95112",
    "addr:housenumber":"152",
    "addr:postcode":"95112",
    "addr:street":"N 3Rd Street Suite 501",
    "iso:country":"US",
    "sg:address":"152 N 3rd Street Suite 501",
    "sg:city":"San Jose",
    "sg:classifiers":[
        {
            "category":"Professional",
            "subcategory":"Lawyer & Legal Services",
            "type":"Services"
        }
    ],
    "sg:phone":"+1 408 289 1417",
    "sg:postcode":"95112",
    "sg:province":"CA",
    "sg:tags":[
        "personal",
        "injury"
    ],
    "wof:name":"Saucedo & Corsiglia",
    "wof:placetype":"venue"
},
  "geometry": {"coordinates":[-121.89004,37.339367],"type":"Point"}
}