{
  "type": "Feature",
  "properties": {
    "addr:full":"1608 Sandcroft St Lake Sherwood CA 91361",
    "addr:housenumber":"1608",
    "addr:postcode":"91361",
    "addr:street":"Sandcroft St",
    "iso:country":"US",
    "sg:address":"1608 Sandcroft St",
    "sg:city":"Lake Sherwood",
    "sg:classifiers":[
        {
            "category":"Manufacturing",
            "subcategory":"Paper Products",
            "type":"Manufacturing & Wholesale Goods"
        }
    ],
    "sg:phone":"+1 805 495 8887",
    "sg:postcode":"91361",
    "sg:province":"CA",
    "sg:tags":[
        "stationery",
        "prod",
        "mfg"
    ],
    "wof:name":"Write Impressions",
    "wof:placetype":"venue"
},
  "geometry": {"coordinates":[-118.870141,34.146034],"type":"Point"}
}