{
  "type": "Feature",
  "properties": {
    "addr:full":"762 N 9th St San Jose CA 95112",
    "addr:housenumber":"762",
    "addr:postcode":"95112",
    "addr:street":"N 9Th St",
    "iso:country":"US",
    "sg:address":"762 N 9th St",
    "sg:city":"San Jose",
    "sg:classifiers":[
        {
            "category":"Manufacturing",
            "subcategory":"Tools & Machinery",
            "type":"Manufacturing & Wholesale Goods"
        }
    ],
    "sg:phone":"+1 408 295 9377",
    "sg:postcode":"95112",
    "sg:province":"CA",
    "sg:tags":[
        "machine",
        "shop"
    ],
    "wof:name":"Specialty Shop",
    "wof:placetype":"venue"
},
  "geometry": {"coordinates":[-121.89360499999999,37.355394],"type":"Point"}
}