{
  "type": "Feature",
  "properties": {
    "addr:full":"109 W Whittier Blvd Montebello CA 90640",
    "addr:housenumber":"109",
    "addr:postcode":"90640",
    "addr:street":"W Whittier Blvd",
    "iso:country":"US",
    "sg:address":"109 W Whittier Blvd",
    "sg:city":"Montebello",
    "sg:classifiers":[
        {
            "category":"Shopping",
            "subcategory":"Clothing, Apparel, & Fashions",
            "type":"Retail Goods"
        },
        {
            "category":"Shopping",
            "subcategory":"Party Supplies",
            "type":"Retail Goods"
        },
        {
            "category":"Shopping",
            "subcategory":"Gifts & Souvenirs",
            "type":"Retail Goods"
        },
        {
            "category":"Building & Trades",
            "subcategory":"Equipment Rental",
            "type":"Services"
        }
    ],
    "sg:phone":"+1 323 722 3524",
    "sg:postcode":"90640",
    "sg:province":"CA",
    "sg:tags":[
        "shop",
        "decoration",
        "yard",
        "favors",
        "delivery",
        "balloons-retail",
        "costume",
        "store"
    ],
    "wof:name":"Derian's Party Warehouse",
    "wof:placetype":"venue"
},
  "geometry": {"coordinates":[-118.100998,34.008499],"type":"Point"}
}