{
  "type": "Feature",
  "properties": {
    "addr:full":"68 W Henderson Ave Porterville CA 93257",
    "addr:housenumber":"68",
    "addr:postcode":"93257",
    "addr:street":"W Henderson Ave",
    "iso:country":"US",
    "sg:address":"68 W Henderson Ave",
    "sg:city":"Porterville",
    "sg:classifiers":[
        {
            "category":"Retail",
            "subcategory":"Auto Repair",
            "type":"Services"
        }
    ],
    "sg:phone":"+1 559 781 7779",
    "sg:postcode":"93257",
    "sg:province":"CA",
    "sg:tags":[
        "transmission"
    ],
    "wof:name":"Wilson's Transmission",
    "wof:placetype":"venue"
},
  "geometry": {"coordinates":[-119.019001,36.080227],"type":"Point"}
}