{
  "type": "Feature",
  "properties": {
    "iso:country":"US",
    "sg:address":"13724 Gavina Ave",
    "sg:city":"Sylmar",
    "sg:classifiers":[
        {
            "category":"Manufacturing",
            "subcategory":"Glass & Minerals",
            "type":"Manufacturing & Wholesale Goods"
        }
    ],
    "sg:phone":"+1 818 899 1697",
    "sg:postcode":"91342",
    "sg:province":"CA",
    "sg:tags":[
        "product",
        "marble"
    ],
    "wof:name":"L A Marble",
    "wof:placetype":"venue"
},
  "geometry": {"coordinates":[-118.40799,34.322816],"type":"Point"}
}