{
  "type": "Feature",
  "properties": {
    "addr:full":"6114 32nd St North Highlands CA 95660",
    "addr:housenumber":"6114",
    "addr:postcode":"95660",
    "addr:street":"32Nd St",
    "iso:country":"US",
    "sg:address":"6114 32nd St",
    "sg:city":"North Highlands",
    "sg:classifiers":[
        {
            "category":"Wholesale",
            "subcategory":"Auto Parts",
            "type":"Manufacturing & Wholesale Goods"
        }
    ],
    "sg:phone":"+1 916 348 7943",
    "sg:postcode":"95660",
    "sg:province":"CA",
    "sg:tags":[
        "material",
        "used"
    ],
    "wof:name":"A B C Foreign Dismantlers",
    "wof:placetype":"venue"
},
  "geometry": {"coordinates":[-121.392088,38.677274],"type":"Point"}
}