{
  "type": "Feature",
  "properties": {
    "addr:full":"2580 Sea Scape Glen Escondido CA 92026",
    "addr:housenumber":"2580",
    "addr:postcode":"92026",
    "addr:street":"Sea Scape Glen",
    "iso:country":"US",
    "sg:address":"2580 Sea Scape Glen",
    "sg:city":"Escondido",
    "sg:classifiers":[
        {
            "category":"Recreation",
            "type":"Entertainment"
        }
    ],
    "sg:phone":"+1 760 510 0188",
    "sg:postcode":"92026",
    "sg:province":"CA",
    "sg:tags":[
        "gambling",
        "casio",
        "via",
        "proposed",
        "internet"
    ],
    "wof:name":"Virtual Gaming Enterprises",
    "wof:placetype":"venue"
},
  "geometry": {"coordinates":[-117.13937199999999,33.166901],"type":"Point"}
}