{
  "type": "Feature",
  "properties": {
    "addr:full":"3726 W 102nd St Inglewood CA 90303",
    "addr:housenumber":"3726",
    "addr:postcode":"90303",
    "addr:street":"W 102Nd St",
    "iso:country":"US",
    "sg:address":"3726 W 102nd St",
    "sg:city":"Inglewood",
    "sg:classifiers":[
        {
            "category":"Freight",
            "type":"Transportation"
        }
    ],
    "sg:phone":"+1 310 671 5937",
    "sg:postcode":"90303",
    "sg:province":"CA",
    "sg:tags":[
        "operator",
        "local",
        "trucking"
    ],
    "wof:name":"Baja Trucking",
    "wof:placetype":"venue"
},
  "geometry": {"coordinates":[-118.336788,33.943564],"type":"Point"}
}