{
  "type": "Feature",
  "properties": {
    "iso:country":"US",
    "sg:address":"2900 S Sunol Dr",
    "sg:city":"Los Angeles",
    "sg:classifiers":[
        {
            "category":"Manufacturing",
            "subcategory":"Metals",
            "type":"Manufacturing & Wholesale Goods"
        }
    ],
    "sg:phone":"+1 323 264 0111",
    "sg:postcode":"90023",
    "sg:province":"CA",
    "sg:tags":[
        "treating",
        "heat"
    ],
    "sg:website":"www.bodycote-na.com",
    "wof:name":"Bodycote Inc",
    "wof:placetype":"venue"
},
  "geometry": {"coordinates":[-118.183987,34.000693],"type":"Point"}
}