{
  "type": "Feature",
  "properties": {
    "addr:full":"3338 Innerwick Ln San Jose CA 95121",
    "addr:housenumber":"3338",
    "addr:postcode":"95121",
    "addr:street":"Innerwick Ln",
    "iso:country":"US",
    "sg:address":"3338 Innerwick Ln",
    "sg:city":"San Jose",
    "sg:classifiers":[
        {
            "category":"Professional",
            "subcategory":"Management & Consulting",
            "type":"Services"
        }
    ],
    "sg:phone":"+1 408 238 2415",
    "sg:postcode":"95121",
    "sg:province":"CA",
    "sg:tags":[
        "consultant",
        "business"
    ],
    "wof:name":"Appsupport",
    "wof:placetype":"venue"
},
  "geometry": {"coordinates":[-121.80329999999999,37.30804],"type":"Point"}
}