{
  "type": "Feature",
  "properties": {
    "addr:full":"354 Orange Ave Seaside CA 93955",
    "addr:housenumber":"354",
    "addr:postcode":"93955",
    "addr:street":"Orange Ave",
    "iso:country":"US",
    "sg:address":"354 Orange Ave",
    "sg:city":"Seaside",
    "sg:classifiers":[
        {
            "category":"Restaurant",
            "type":"Food & Drink"
        }
    ],
    "sg:phone":"+1 831 393 9479",
    "sg:postcode":"93955",
    "sg:province":"CA",
    "sg:tags":[
        "caterer"
    ],
    "wof:name":"Eddison & Melrose",
    "wof:placetype":"venue"
},
  "geometry": {"coordinates":[-121.85415399999999,36.610596],"type":"Point"}
}