{
  "type": "Feature",
  "properties": {
    "iso:country":"US",
    "sg:address":"919 Stanford Ave",
    "sg:city":"Emeryville",
    "sg:classifiers":[
        {
            "category":"Manufacturing",
            "subcategory":"Printing",
            "type":"Manufacturing & Wholesale Goods"
        }
    ],
    "sg:phone":"+1 510 549 0176",
    "sg:postcode":"94608",
    "sg:province":"CA",
    "sg:tags":[
        "graphic",
        "designer",
        "commercial",
        "publishing",
        "printer"
    ],
    "wof:name":"New Earth Press",
    "wof:placetype":"venue"
},
  "geometry": {"coordinates":[-122.27641300000001,37.843609],"type":"Point"}
}