{
  "type": "Feature",
  "properties": {
    "addr:full":"220 N Loma Ave Long Beach CA 90803",
    "addr:housenumber":"220",
    "addr:postcode":"90803",
    "addr:street":"N Loma Ave",
    "iso:country":"US",
    "sg:address":"220 N Loma Ave",
    "sg:city":"Long Beach",
    "sg:classifiers":[
        {
            "category":"Food & Beverages",
            "subcategory":"Liquor & Beverages",
            "type":"Retail Goods"
        }
    ],
    "sg:phone":"+1 562 439 3390",
    "sg:postcode":"90803",
    "sg:province":"CA",
    "wof:name":"Loma Liquor",
    "wof:placetype":"venue"
},
  "geometry": {"coordinates":[-118.150159,33.763444],"type":"Point"}
}