{
  "type": "Feature",
  "properties": {
    "addr:full":"110 S Fairfax Ave Los Angeles CA 90036",
    "addr:housenumber":"110",
    "addr:postcode":"90036",
    "addr:street":"S Fairfax Ave",
    "iso:country":"US",
    "sg:address":"110 S Fairfax Ave",
    "sg:city":"Los Angeles",
    "sg:classifiers":[
        {
            "category":"Personal",
            "subcategory":"Beauty Salon",
            "type":"Services"
        },
        {
            "category":"Personal",
            "subcategory":"Hair Removal",
            "type":"Services"
        },
        {
            "category":"Personal",
            "subcategory":"Day Spa",
            "type":"Services"
        },
        {
            "category":"Personal",
            "subcategory":"Barber",
            "type":"Services"
        },
        {
            "category":"Shopping",
            "subcategory":"Beauty & Cosmetics",
            "type":"Retail Goods"
        }
    ],
    "sg:phone":"+1 323 933 0212",
    "sg:postcode":"90036",
    "sg:province":"CA",
    "sg:tags":[
        "supply"
    ],
    "wof:name":"Elements-Spa & Salon",
    "wof:placetype":"venue"
},
  "geometry": {"coordinates":[-118.36141499999999,34.074192],"type":"Point"}
}