{
  "type": "Feature",
  "properties": {
    "addr:full":"1764 Emory St San Jose CA 95126",
    "addr:housenumber":"1764",
    "addr:postcode":"95126",
    "addr:street":"Emory St",
    "iso:country":"US",
    "sg:address":"1764 Emory St",
    "sg:city":"San Jose",
    "sg:classifiers":[
        {
            "category":"Professional",
            "subcategory":"Research",
            "type":"Services"
        }
    ],
    "sg:phone":"+1 408 293 7447",
    "sg:postcode":"95126",
    "sg:province":"CA",
    "wof:name":"LDM Assoc",
    "wof:placetype":"venue"
},
  "geometry": {"coordinates":[-121.932458,37.329985],"type":"Point"}
}