{
  "type": "Feature",
  "properties": {
    "iso:country":"US",
    "sg:address":"608 Terminal Way",
    "sg:city":"Costa Mesa",
    "sg:classifiers":[
        {
            "category":"Autos & Motor Vehicles",
            "subcategory":"Automobile Sales",
            "type":"Retail Goods"
        }
    ],
    "sg:phone":"+1 949 223 1000",
    "sg:postcode":"92627",
    "sg:province":"CA",
    "sg:tags":[
        "used"
    ],
    "wof:name":"J Williams Cars Inc",
    "wof:placetype":"venue"
},
  "geometry": {"coordinates":[-117.925546,33.637506],"type":"Point"}
}