{
  "type": "Feature",
  "properties": {
    "iso:country":"US",
    "sg:address":"4164 Pico Rd",
    "sg:city":"Vista",
    "sg:classifiers":[
        {
            "category":"Farming",
            "subcategory":"Crops",
            "type":"Manufacturing & Wholesale Goods"
        }
    ],
    "sg:phone":"+1 760 758 4468",
    "sg:postcode":"92084",
    "sg:province":"CA",
    "sg:tags":[
        "farm"
    ],
    "wof:name":"Wild Acres Ranch",
    "wof:placetype":"venue"
},
  "geometry": {"coordinates":[-117.170755,33.261545],"type":"Point"}
}