{
  "type": "Feature",
  "properties": {
    "addr:full":"4545 La Jolla Village Drive San Diego CA 92122",
    "addr:housenumber":"4545",
    "addr:postcode":"92122",
    "addr:street":"La Jolla Village Drive",
    "iso:country":"US",
    "sg:address":"4545 La Jolla Village Drive",
    "sg:city":"San Diego",
    "sg:classifiers":[
        {
            "category":"Social Services",
            "subcategory":"Child Care",
            "type":"Services"
        },
        {
            "category":"Education",
            "subcategory":"Preschool",
            "type":"Public Place"
        },
        {
            "category":"Education",
            "subcategory":"School",
            "type":"Public Place"
        }
    ],
    "sg:phone":"+1 858 452 9732",
    "sg:postcode":"92122",
    "sg:province":"CA",
    "sg:tags":[
        "elementary",
        "day"
    ],
    "wof:name":"Childtime Learning Centers",
    "wof:placetype":"venue"
},
  "geometry": {"coordinates":[-117.20866100000001,32.873787],"type":"Point"}
}