{
  "type": "Feature",
  "properties": {
    "iso:country":"US",
    "sg:address":"4110 Manzanita Ave",
    "sg:city":"Carmichael",
    "sg:classifiers":[
        {
            "category":"Restaurant",
            "type":"Food & Drink"
        }
    ],
    "sg:phone":"+1 916 486 2579",
    "sg:postcode":"95608",
    "sg:province":"CA",
    "sg:tags":[
        "chinese",
        "vietnamese"
    ],
    "wof:name":"TM Noodle",
    "wof:placetype":"venue"
},
  "geometry": {"coordinates":[-121.32786,38.639004],"type":"Point"}
}