{
  "type": "Feature",
  "properties": {
    "iso:country":"US",
    "sg:address":"1300 S F St",
    "sg:city":"Porterville",
    "sg:classifiers":[
        {
            "category":"Professional",
            "type":"Services"
        }
    ],
    "sg:phone":"+1 559 791 1668",
    "sg:postcode":"93257",
    "sg:province":"CA",
    "sg:tags":[
        "establishment"
    ],
    "wof:name":"Belly-Busters",
    "wof:placetype":"venue"
},
  "geometry": {"coordinates":[-119.024624,36.041488],"type":"Point"}
}