{
  "type": "Feature",
  "properties": {
    "addr:full":"6265 Greenwich Dr San Diego CA 92122",
    "addr:housenumber":"6265",
    "addr:postcode":"92122",
    "addr:street":"Greenwich Dr",
    "iso:country":"US",
    "sg:address":"6265 Greenwich Dr",
    "sg:city":"San Diego",
    "sg:classifiers":[
        {
            "category":"Banks & Credit Unions",
            "subcategory":"Investment Brokerage",
            "type":"Services"
        }
    ],
    "sg:phone":"+1 858 455 5068",
    "sg:postcode":"92122",
    "sg:province":"CA",
    "sg:tags":[
        "consultant",
        "planning",
        "financial"
    ],
    "wof:name":"Ian Kutnar",
    "wof:placetype":"venue"
},
  "geometry": {"coordinates":[-117.184528,32.854195],"type":"Point"}
}