{
  "type": "Feature",
  "properties": {
    "addr:full":"36500 Bottle Brush Ct Newark CA 94560",
    "addr:postcode":"36500;94560",
    "addr:street":"Bottle Brush Ct",
    "iso:country":"US",
    "sg:address":"36500 Bottle Brush Ct",
    "sg:city":"Newark",
    "sg:classifiers":[
        {
            "category":"Freight",
            "type":"Transportation"
        }
    ],
    "sg:phone":"+1 510 792 3965",
    "sg:postcode":"94560",
    "sg:province":"CA",
    "sg:tags":[
        "local",
        "storage",
        "trucking"
    ],
    "wof:name":"E A Transport",
    "wof:placetype":"venue"
},
  "geometry": {"coordinates":[-122.043813,37.533311],"type":"Point"}
}