{
  "type": "Feature",
  "properties": {
    "addr:full":"809 E Chestnut Ave Lompoc CA 93436",
    "addr:housenumber":"809",
    "addr:postcode":"93436",
    "addr:street":"E Chestnut Ave",
    "iso:country":"US",
    "sg:address":"809 E Chestnut Ave",
    "sg:city":"Lompoc",
    "sg:classifiers":[
        {
            "category":"Autos & Motor Vehicles",
            "subcategory":"Auto Supplies",
            "type":"Retail Goods"
        },
        {
            "category":"Retail",
            "subcategory":"Auto Repair",
            "type":"Services"
        }
    ],
    "sg:phone":"+1 805 735 8655",
    "sg:postcode":"93436",
    "sg:province":"CA",
    "sg:tags":[
        "body",
        "automobile",
        "truck",
        "painting",
        "repairing"
    ],
    "wof:name":"Onestop Body Shop",
    "wof:placetype":"venue"
},
  "geometry": {"coordinates":[-120.448795,34.64215],"type":"Point"}
}