{
  "type": "Feature",
  "properties": {
    "addr:full":"1670 Mitchell Rd Ceres CA 95307",
    "addr:housenumber":"1670",
    "addr:postcode":"95307",
    "addr:street":"Mitchell Rd",
    "iso:country":"US",
    "sg:address":"1670 Mitchell Rd",
    "sg:city":"Ceres",
    "sg:phone":"+1 209 541 0253",
    "sg:postcode":"95307",
    "sg:province":"CA",
    "sg:website":"http://clickserve.dartsearch.net/link/click?lid=43000000308049899",
    "wof:name":"T-Mobile",
    "wof:placetype":"venue"
},
  "geometry": {"coordinates":[-120.938744,37.606721],"type":"Point"}
}