{
  "type": "Feature",
  "properties": {
    "addr:full":"1901 N Fairview St Santa Ana CA 92706",
    "addr:housenumber":"1901",
    "addr:postcode":"92706",
    "addr:street":"N Fairview St",
    "iso:country":"US",
    "sg:address":"1901 N Fairview St",
    "sg:city":"Santa Ana",
    "sg:classifiers":[
        {
            "category":"Health Services",
            "subcategory":"Doctor",
            "type":"Services"
        }
    ],
    "sg:phone":"+1 714 554 1653",
    "sg:postcode":"92706",
    "sg:province":"CA",
    "sg:tags":[
        "medical",
        "hospital",
        "general"
    ],
    "wof:name":"Santa Ana Hospital Medical Ctr",
    "wof:placetype":"venue"
},
  "geometry": {"coordinates":[-117.90288700000001,33.762888],"type":"Point"}
}