{
  "type": "Feature",
  "properties": {
    "iso:country":"US",
    "sg:address":"1053 W March Ln",
    "sg:city":"Stockton",
    "sg:classifiers":[
        {
            "category":"Shopping",
            "subcategory":"Bicycles & Sporting Goods",
            "type":"Retail Goods"
        }
    ],
    "sg:phone":"+1 209 957 3095",
    "sg:postcode":"95207",
    "sg:province":"CA",
    "wof:name":"Big 5 Sporting Goods",
    "wof:placetype":"venue"
},
  "geometry": {"coordinates":[-121.320105,37.98966],"type":"Point"}
}