{
  "type": "Feature",
  "properties": {
    "addr:full":"13202 Harbor Blvd Garden Grove CA 92843",
    "addr:housenumber":"13202",
    "addr:postcode":"92843",
    "addr:street":"Harbor Blvd",
    "iso:country":"US",
    "sg:address":"13202 Harbor Blvd",
    "sg:city":"Garden Grove",
    "sg:classifiers":[
        {
            "category":"Shopping",
            "subcategory":"Clothing, Apparel, & Fashions",
            "type":"Retail Goods"
        }
    ],
    "sg:phone":"+1 714 534 6424",
    "sg:postcode":"92843",
    "sg:province":"CA",
    "sg:tags":[
        "accessory",
        "clothing",
        "women's"
    ],
    "wof:name":"Glamoda",
    "wof:placetype":"venue"
},
  "geometry": {"coordinates":[-117.920143,33.771705],"type":"Point"}
}