{
  "type": "Feature",
  "properties": {
    "iso:country":"US",
    "sg:address":"1030 N Union St",
    "sg:city":"Stockton",
    "sg:classifiers":[
        {
            "category":"Building & Trades",
            "subcategory":"Construction",
            "type":"Services"
        }
    ],
    "sg:phone":"+1 209 948 0178",
    "sg:postcode":"95205",
    "sg:province":"CA",
    "sg:tags":[
        "contractor"
    ],
    "wof:name":"Montanez Builders",
    "wof:placetype":"venue"
},
  "geometry": {"coordinates":[-121.27969400000001,37.965854],"type":"Point"}
}