{
  "type": "Feature",
  "properties": {
    "addr:full":"554 W Ave I Lancaster CA 93534",
    "addr:housenumber":"554",
    "addr:postcode":"93534",
    "addr:street":"W Ave I",
    "iso:country":"US",
    "sg:address":"554 W Ave I",
    "sg:city":"Lancaster",
    "sg:classifiers":[
        {
            "category":"Shopping",
            "subcategory":"Tobacco",
            "type":"Retail Goods"
        }
    ],
    "sg:phone":"+1 661 942 4440",
    "sg:postcode":"93534",
    "sg:province":"CA",
    "sg:tags":[
        "shop",
        "smoke",
        "supply"
    ],
    "wof:name":"Max's Pipe Shop",
    "wof:placetype":"venue"
},
  "geometry": {"coordinates":[-118.139601,34.703856],"type":"Point"}
}