{
  "type": "Feature",
  "properties": {
    "addr:full":"1750 el Camino Real Grover Beach CA 93433",
    "addr:housenumber":"1750",
    "addr:postcode":"93433",
    "addr:street":"El Camino Real",
    "iso:country":"US",
    "sg:address":"1750 el Camino Real",
    "sg:city":"Grover Beach",
    "sg:classifiers":[
        {
            "category":"Food & Beverages",
            "subcategory":"Liquor & Beverages",
            "type":"Retail Goods"
        }
    ],
    "sg:phone":"+1 805 473 8466",
    "sg:postcode":"93433",
    "sg:province":"CA",
    "sg:tags":[
        "wine"
    ],
    "wof:name":"Great Gatsby's",
    "wof:placetype":"venue"
},
  "geometry": {"coordinates":[-120.60766099999999,35.129906],"type":"Point"}
}