{
  "type": "Feature",
  "properties": {
    "iso:country":"US",
    "sg:address":"135 South Prospect",
    "sg:city":"Tustin",
    "sg:classifiers":[
        {
            "category":"Autos & Motor Vehicles",
            "subcategory":"Auto Supplies",
            "type":"Retail Goods"
        },
        {
            "category":"Retail",
            "subcategory":"Auto Repair",
            "type":"Services"
        }
    ],
    "sg:phone":"+1 877 872 0144",
    "sg:postcode":"92780",
    "sg:province":"CA",
    "sg:tags":[
        "tire"
    ],
    "sg:website":"www.mountainviewtire.com/tustin",
    "wof:name":"Mountain View Tire and Service",
    "wof:placetype":"venue"
},
  "geometry": {"coordinates":[-117.822439,33.745196],"type":"Point"}
}