{
  "type": "Feature",
  "properties": {
    "addr:full":"2320 E South St Anaheim CA 92806",
    "addr:housenumber":"2320 e",
    "addr:postcode":"92806",
    "addr:street":"South St",
    "iso:country":"US",
    "sg:address":"2320 E South St",
    "sg:city":"Anaheim",
    "sg:classifiers":[
        {
            "category":"Autos & Motor Vehicles",
            "subcategory":"Motorcycle Sales",
            "type":"Retail Goods"
        }
    ],
    "sg:phone":"+1 714 549 9086",
    "sg:postcode":"92806",
    "sg:province":"CA",
    "wof:name":"Beach Yamaha",
    "wof:placetype":"venue"
},
  "geometry": {"coordinates":[-117.885002,33.8325],"type":"Point"}
}