{
  "type": "Feature",
  "properties": {
    "iso:country":"US",
    "sg:address":"3D Church",
    "sg:city":"Guerneville",
    "sg:classifiers":[
        {
            "category":"Health Services",
            "subcategory":"Dentist",
            "type":"Services"
        }
    ],
    "sg:phone":"+1 707 869 2933",
    "sg:postcode":"95446",
    "sg:province":"CA",
    "wof:name":"Russian River Dental Office",
    "wof:placetype":"venue"
},
  "geometry": {"coordinates":[-122.991997,38.504902],"type":"Point"}
}