{
  "type": "Feature",
  "properties": {
    "iso:country":"US",
    "sg:address":"510 W Main St",
    "sg:city":"Ripon",
    "sg:classifiers":[
        {
            "category":"Organizations",
            "subcategory":"Religious Organization",
            "type":"Services"
        }
    ],
    "sg:phone":"+1 209 599 4233",
    "sg:postcode":"95366",
    "sg:province":"CA",
    "sg:tags":[
        "church"
    ],
    "wof:name":"Heartland Community Church",
    "wof:placetype":"venue"
},
  "geometry": {"coordinates":[-121.129543,37.739331],"type":"Point"}
}