{
  "type": "Feature",
  "properties": {
    "addr:full":"6833 Indiana Ave Riverside CA 92506",
    "addr:housenumber":"6833",
    "addr:postcode":"92506",
    "addr:street":"Indiana Ave",
    "iso:country":"US",
    "sg:address":"6833 Indiana Ave",
    "sg:city":"Riverside",
    "sg:classifiers":[
        {
            "category":"Professional",
            "subcategory":"Detective & Security Services",
            "type":"Services"
        }
    ],
    "sg:phone":"+1 951 687 6293",
    "sg:postcode":"92506",
    "sg:province":"CA",
    "sg:tags":[
        "system"
    ],
    "wof:name":"Advance Detection Technologies",
    "wof:placetype":"venue"
},
  "geometry": {"coordinates":[-117.39285700000001,33.942481],"type":"Point"}
}