{
  "type": "Feature",
  "properties": {
    "iso:country":"US",
    "sg:address":"1809 McHenry Ave Ste A",
    "sg:city":"Modesto",
    "sg:classifiers":[
        {
            "category":"Shopping",
            "subcategory":"Mobile Phones",
            "type":"Retail Goods"
        }
    ],
    "sg:phone":"+1 209 341 1800",
    "sg:postcode":"95350",
    "sg:province":"CA",
    "sg:website":"www.parrotcellular.com",
    "wof:name":"Parrot Cellular",
    "wof:placetype":"venue"
},
  "geometry": {"coordinates":[-120.994799,37.671113],"type":"Point"}
}