{
  "type": "Feature",
  "properties": {
    "iso:country":"US",
    "sg:address":"255 Valdez Ave",
    "sg:city":"San Francisco",
    "sg:classifiers":[
        {
            "category":"Building & Trades",
            "subcategory":"Construction",
            "type":"Services"
        }
    ],
    "sg:phone":"+1 415 469 7261",
    "sg:postcode":"94127",
    "sg:province":"CA",
    "sg:tags":[
        "painter"
    ],
    "sg:website":"www.colortouchpainting.com",
    "wof:name":"Color Touch Painting And Decorating",
    "wof:placetype":"venue"
},
  "geometry": {"coordinates":[-122.456147,37.732048],"type":"Point"}
}