{
  "type": "Feature",
  "properties": {
    "addr:full":"507 W Whittier Blvd Montebello CA 90640",
    "addr:housenumber":"507",
    "addr:postcode":"90640",
    "addr:street":"W Whittier Blvd",
    "iso:country":"US",
    "sg:address":"507 W Whittier Blvd",
    "sg:city":"Montebello",
    "sg:classifiers":[
        {
            "category":"Shopping",
            "subcategory":"Clothing, Apparel, & Fashions",
            "type":"Retail Goods"
        },
        {
            "category":"Shopping",
            "subcategory":"Party Supplies",
            "type":"Retail Goods"
        },
        {
            "category":"Shopping",
            "subcategory":"Bridal",
            "type":"Retail Goods"
        }
    ],
    "sg:phone":"+1 323 888 0306",
    "sg:postcode":"90640",
    "sg:province":"CA",
    "sg:tags":[
        "shop",
        "tuxedo",
        "sale",
        "wear",
        "wedding",
        "rental",
        "formal"
    ],
    "wof:name":"Crown Tuxedos",
    "wof:placetype":"venue"
},
  "geometry": {"coordinates":[-118.105039,34.009394],"type":"Point"}
}