{
  "type": "Feature",
  "properties": {
    "iso:country":"US",
    "sg:address":"141 Locust St",
    "sg:city":"Redding",
    "sg:classifiers":[
        {
            "category":"Shopping",
            "type":"Retail Goods"
        }
    ],
    "sg:phone":"+1 530 246 2227",
    "sg:postcode":"96001",
    "sg:province":"CA",
    "sg:tags":[
        "telephone",
        "cellular"
    ],
    "sg:website":"www.bentronics.com",
    "wof:name":"Bentronics",
    "wof:placetype":"venue"
},
  "geometry": {"coordinates":[-122.374143,40.574186],"type":"Point"}
}