{
  "type": "Feature",
  "properties": {
    "addr:full":"2002 Old Ranch Rd Los Angeles CA 90049",
    "addr:housenumber":"2002",
    "addr:postcode":"90049",
    "addr:street":"Old Ranch Rd",
    "iso:country":"US",
    "sg:address":"2002 Old Ranch Rd",
    "sg:city":"Los Angeles",
    "sg:classifiers":[
        {
            "category":"Retail",
            "subcategory":"Animal Services",
            "type":"Services"
        }
    ],
    "sg:phone":"+1 310 454 0383",
    "sg:postcode":"90049",
    "sg:province":"CA",
    "wof:name":"R & R Stables",
    "wof:placetype":"venue"
},
  "geometry": {"coordinates":[-118.502849,34.067434],"type":"Point"}
}