{
  "type": "Feature",
  "properties": {
    "addr:full":"12444 Moorpark St Studio City CA 91604",
    "addr:housenumber":"12444",
    "addr:postcode":"91604",
    "addr:street":"Moorpark St",
    "iso:country":"US",
    "sg:address":"12444 Moorpark St",
    "sg:city":"Studio City",
    "sg:classifiers":[
        {
            "category":"Personal",
            "subcategory":"Beauty Salon",
            "type":"Services"
        }
    ],
    "sg:phone":"+1 818 505 0842",
    "sg:postcode":"91604",
    "sg:province":"CA",
    "sg:tags":[
        "manicuring"
    ],
    "wof:name":"Julie Mach",
    "wof:placetype":"venue"
},
  "geometry": {"coordinates":[-118.40506499999999,34.150287],"type":"Point"}
}