{
  "type": "Feature",
  "properties": {
    "addr:full":"1145 E Clark Ave Orcutt CA 93455",
    "addr:housenumber":"1145",
    "addr:postcode":"93455",
    "addr:street":"E Clark Ave",
    "iso:country":"US",
    "sg:address":"1145 E Clark Ave",
    "sg:city":"Orcutt",
    "sg:classifiers":[
        {
            "category":"Health Services",
            "subcategory":"Podiatrist",
            "type":"Services"
        }
    ],
    "sg:phone":"+1 805 934 0570",
    "sg:postcode":"93455",
    "sg:province":"CA",
    "wof:name":"Foot & Ankle Ctr Of Ctr Cst",
    "wof:placetype":"venue"
},
  "geometry": {"coordinates":[-120.416265,34.865163],"type":"Point"}
}