{
  "type": "Feature",
  "properties": {
    "iso:country":"US",
    "sg:address":"212 Shaw Road",
    "sg:city":"South San Francisco",
    "sg:classifiers":[
        {
            "category":"Freight",
            "type":"Transportation"
        }
    ],
    "sg:phone":"+1 650 866 4703",
    "sg:postcode":"94080",
    "sg:province":"CA",
    "sg:tags":[
        "shipping"
    ],
    "wof:name":"SFO Express",
    "wof:placetype":"venue"
},
  "geometry": {"coordinates":[-122.41004,37.640232],"type":"Point"}
}