{
  "type": "Feature",
  "properties": {
    "iso:country":"US",
    "sg:address":"668 S Vermont Ave",
    "sg:city":"Los Angeles",
    "sg:classifiers":[
        {
            "category":"Food & Beverages",
            "subcategory":"Groceries & Convenience Stores",
            "type":"Retail Goods"
        }
    ],
    "sg:phone":"+1 213 383 2583",
    "sg:postcode":"90005",
    "sg:province":"CA",
    "wof:name":"Islamic Food Mart",
    "wof:placetype":"venue"
},
  "geometry": {"coordinates":[-118.29155799999999,34.059872],"type":"Point"}
}