{
  "type": "Feature",
  "properties": {
    "iso:country":"US",
    "sg:address":"13757 Ventura Blvd",
    "sg:city":"Sherman Oaks",
    "sg:classifiers":[
        {
            "category":"Shopping",
            "subcategory":"Clothing, Apparel, & Fashions",
            "type":"Retail Goods"
        },
        {
            "category":"Personal",
            "type":"Services"
        }
    ],
    "sg:phone":"+1 818 981 5738",
    "sg:postcode":"91423",
    "sg:province":"CA",
    "sg:tags":[
        "men's",
        "clothing",
        "alteration",
        "sewing"
    ],
    "sg:website":"www.michaelsahi.com",
    "wof:name":"Michael's Custom Clothes",
    "wof:placetype":"venue"
},
  "geometry": {"coordinates":[-118.432999,34.148201],"type":"Point"}
}