{
  "type": "Feature",
  "properties": {
    "addr:full":"4371 Glencoe Ave Marina Del Rey CA 90292",
    "addr:housenumber":"4371",
    "addr:postcode":"90292",
    "addr:street":"Glencoe Ave",
    "iso:country":"US",
    "sg:address":"4371 Glencoe Ave",
    "sg:city":"Marina Del Rey",
    "sg:classifiers":[
        {
            "category":"Restaurant",
            "type":"Food & Drink"
        }
    ],
    "sg:phone":"+1 310 823 7333",
    "sg:postcode":"90292",
    "sg:province":"CA",
    "sg:tags":[
        "pizza"
    ],
    "sg:website":"www.pizzarito.com",
    "wof:name":"Pizzarito",
    "wof:placetype":"venue"
},
  "geometry": {"coordinates":[-118.43910200000001,33.984969],"type":"Point"}
}