{
  "type": "Feature",
  "properties": {
    "addr:full":"464 E Walnut St Pasadena CA 91101",
    "addr:housenumber":"464",
    "addr:postcode":"91101",
    "addr:street":"E Walnut St",
    "iso:country":"US",
    "sg:address":"464 E Walnut St",
    "sg:city":"Pasadena",
    "sg:classifiers":[
        {
            "category":"Shopping",
            "type":"Retail Goods"
        }
    ],
    "sg:phone":"+1 626 795 9276",
    "sg:postcode":"91101",
    "sg:province":"CA",
    "sg:tags":[
        "art",
        "gallery"
    ],
    "sg:website":"www.pasadenaartalliance.org",
    "wof:name":"Pasadena Art Alliance",
    "wof:placetype":"venue"
},
  "geometry": {"coordinates":[-118.14099899999999,34.149399],"type":"Point"}
}