{
  "type": "Feature",
  "properties": {
    "iso:country":"US",
    "sg:address":"Pier 27",
    "sg:city":"San Francisco",
    "sg:classifiers":[
        {
            "category":"Park",
            "type":"Public Place"
        }
    ],
    "sg:phone":"+1 415 640 0021",
    "sg:postcode":"94111",
    "sg:province":"CA",
    "sg:website":"www.sanfranciscosoccer.org",
    "wof:name":"Telegraph Field",
    "wof:placetype":"venue"
},
  "geometry": {"coordinates":[-122.402394,37.805173],"type":"Point"}
}