{
  "type": "Feature",
  "properties": {
    "addr:full":"4060 Rocklin Rd Rocklin CA 95677",
    "addr:housenumber":"4060",
    "addr:postcode":"95677",
    "addr:street":"Rocklin Rd",
    "iso:country":"US",
    "sg:address":"4060 Rocklin Rd",
    "sg:city":"Rocklin",
    "sg:classifiers":[
        {
            "category":"Government",
            "subcategory":"Fire Station",
            "type":"Public Place"
        }
    ],
    "sg:phone":"+1 916 632 4150",
    "sg:postcode":"95677",
    "sg:province":"CA",
    "sg:tags":[
        "protection"
    ],
    "wof:name":"City Rocklin Fire Department",
    "wof:placetype":"venue"
},
  "geometry": {"coordinates":[-121.235849,38.790587],"type":"Point"}
}