{
  "type": "Feature",
  "properties": {
    "addr:full":"10545 Burbank Blvd North Hollywood CA 91601",
    "addr:housenumber":"10545",
    "addr:postcode":"91601",
    "addr:street":"Burbank Blvd",
    "iso:country":"US",
    "sg:address":"10545 Burbank Blvd",
    "sg:city":"North Hollywood",
    "sg:classifiers":[
        {
            "category":"Education",
            "subcategory":"Kindergarten",
            "type":"Public Place"
        }
    ],
    "sg:phone":"+1 818 755 2845",
    "sg:postcode":"91601",
    "sg:province":"CA",
    "sg:tags":[
        "school",
        "driving"
    ],
    "wof:name":"Galaxy Traffic School",
    "wof:placetype":"venue"
},
  "geometry": {"coordinates":[-118.36068400000001,34.172297],"type":"Point"}
}