{
  "type": "Feature",
  "properties": {
    "iso:country":"US",
    "sg:address":"11660 S St",
    "sg:city":"Artesia",
    "sg:classifiers":[
        {
            "category":"Personal",
            "subcategory":"Nail Salon",
            "type":"Services"
        }
    ],
    "sg:phone":"+1 562 865 0289",
    "sg:postcode":"90701",
    "sg:province":"CA",
    "wof:name":"Swan Nails",
    "wof:placetype":"venue"
},
  "geometry": {"coordinates":[-117.89547,33.713443],"type":"Point"}
}