{
  "type": "Feature",
  "properties": {
    "addr:full":"4754 E 6th St Los Angeles CA 90022",
    "addr:housenumber":"4754",
    "addr:postcode":"90022",
    "addr:street":"E 6Th St",
    "iso:country":"US",
    "sg:address":"4754 E 6th St",
    "sg:city":"Los Angeles",
    "sg:classifiers":[
        {
            "category":"Food & Beverages",
            "subcategory":"Groceries & Convenience Stores",
            "type":"Retail Goods"
        }
    ],
    "sg:phone":"+1 323 263 5316",
    "sg:postcode":"90022",
    "sg:province":"CA",
    "sg:tags":[
        "grocer"
    ],
    "sg:website":"www.tomsmarket.com",
    "wof:name":"Tom's Market",
    "wof:placetype":"venue"
},
  "geometry": {"coordinates":[-118.16300200000001,34.026402],"type":"Point"}
}