{
  "type": "Feature",
  "properties": {
    "iso:country":"US",
    "sg:address":"921 11th St",
    "sg:city":"Sacramento",
    "sg:classifiers":[
        {
            "category":"Organizations",
            "subcategory":"Professional Association",
            "type":"Services"
        }
    ],
    "sg:phone":"+1 916 444 9950",
    "sg:postcode":"95814",
    "sg:province":"CA",
    "wof:name":"Howard Jarvis Taxpayers Assn",
    "wof:placetype":"venue"
},
  "geometry": {"coordinates":[-121.491732,38.580703],"type":"Point"}
}