{
  "type": "Feature",
  "properties": {
    "addr:full":"3732 Vis de Ora Los Alamitos CA 90720",
    "addr:housenumber":"3732",
    "addr:postcode":"90720",
    "addr:street":"Vis De Ora",
    "iso:country":"US",
    "sg:address":"3732 Vis de Ora",
    "sg:city":"Los Alamitos",
    "sg:classifiers":[
        {
            "category":"Manufacturing",
            "subcategory":"Tools & Machinery",
            "type":"Manufacturing & Wholesale Goods"
        }
    ],
    "sg:phone":"+1 562 598 7149",
    "sg:postcode":"90720",
    "sg:province":"CA",
    "sg:tags":[
        "engine",
        "equipment",
        "electrical",
        "mfg"
    ],
    "wof:name":"Lindow Enterprises",
    "wof:placetype":"venue"
},
  "geometry": {"coordinates":[-118.068738,33.793552],"type":"Point"}
}