{
  "type": "Feature",
  "properties": {
    "addr:full":"600 S Vincent Ave Azusa CA 91702",
    "addr:housenumber":"600",
    "addr:postcode":"91702",
    "addr:street":"S Vincent Ave",
    "iso:country":"US",
    "sg:address":"600 S Vincent Ave",
    "sg:city":"Azusa",
    "sg:classifiers":[
        {
            "category":"Building & Trades",
            "subcategory":"Construction",
            "type":"Services"
        }
    ],
    "sg:phone":"+1 877 364 6495",
    "sg:postcode":"91702",
    "sg:province":"CA",
    "sg:tags":[
        "insulation",
        "home",
        "heat",
        "improvement",
        "contractor"
    ],
    "sg:website":"http://losangeles.citysearch.com/profile/external/603815702/azusa_ca/oj_insulation.html?publisher=yellowpages&reference_id=1&placement=ypwebsitemip",
    "wof:name":"OJ Insulation",
    "wof:placetype":"venue"
},
  "geometry": {"coordinates":[-117.925293,34.111671],"type":"Point"}
}