{
  "type": "Feature",
  "properties": {
    "iso:country":"US",
    "sg:address":"329 Hartz Ave",
    "sg:city":"Danville",
    "sg:classifiers":[
        {
            "category":"Personal",
            "subcategory":"Beauty Salon",
            "type":"Services"
        }
    ],
    "sg:phone":"+1 925 855 7089",
    "sg:postcode":"94526",
    "sg:province":"CA",
    "wof:name":"Hair By Ami Kraft",
    "wof:placetype":"venue"
},
  "geometry": {"coordinates":[-122.000652,37.82226],"type":"Point"}
}