{
  "type": "Feature",
  "properties": {
    "addr:full":"810 Napa Ave Rodeo CA 94572",
    "addr:housenumber":"810",
    "addr:postcode":"94572",
    "addr:street":"Napa Ave",
    "iso:country":"US",
    "sg:address":"810 Napa Ave",
    "sg:city":"Rodeo",
    "sg:classifiers":[
        {
            "category":"Professional",
            "subcategory":"Secretarial Services",
            "type":"Services"
        }
    ],
    "sg:phone":"+1 510 799 0643",
    "sg:postcode":"94572",
    "sg:province":"CA",
    "sg:tags":[
        "reporting",
        "court"
    ],
    "wof:name":"Judy's Secretarial Svc",
    "wof:placetype":"venue"
},
  "geometry": {"coordinates":[-122.26363499999999,38.030092],"type":"Point"}
}