{
  "type": "Feature",
  "properties": {
    "iso:country":"US",
    "sg:address":"1750 E Bullard Ave",
    "sg:city":"Fresno",
    "sg:classifiers":[
        {
            "category":"Banks & Credit Unions",
            "subcategory":"Bank",
            "type":"Services"
        }
    ],
    "sg:phone":"+1 559 431 8420",
    "sg:postcode":"93710",
    "sg:province":"CA",
    "sg:tags":[
        "loan"
    ],
    "wof:name":"Bright Financial",
    "wof:placetype":"venue"
},
  "geometry": {"coordinates":[-119.755831,36.823186],"type":"Point"}
}