{
  "type": "Feature",
  "properties": {
    "iso:country":"US",
    "sg:address":"101 1st St",
    "sg:city":"Los Altos",
    "sg:classifiers":[
        {
            "category":"Professional",
            "subcategory":"Management & Consulting",
            "type":"Services"
        }
    ],
    "sg:phone":"+1 650 941 9773",
    "sg:postcode":"94022",
    "sg:province":"CA",
    "sg:tags":[
        "consultant",
        "business"
    ],
    "wof:name":"Bill Closs & Assoc",
    "wof:placetype":"venue"
},
  "geometry": {"coordinates":[-122.11867,37.37903],"type":"Point"}
}