{
  "type": "Feature",
  "properties": {
    "iso:country":"US",
    "sg:address":"44301 Fremont Blvd",
    "sg:city":"Fremont",
    "sg:classifiers":[
        {
            "category":"Retail",
            "subcategory":"Storage",
            "type":"Services"
        }
    ],
    "sg:phone":"+1 510 656 7066",
    "sg:postcode":"94538",
    "sg:province":"CA",
    "sg:tags":[
        "self",
        "recreational",
        "commercial",
        "campers-storage",
        "vehicle",
        "household"
    ],
    "sg:website":"http://www.calselfstoragefremont.com",
    "wof:name":"Cal Self Storage",
    "wof:placetype":"venue"
},
  "geometry": {"coordinates":[-121.94954199999999,37.507622],"type":"Point"}
}