{
  "type": "Feature",
  "properties": {
    "addr:full":"12 Novilla Laguna Niguel CA 92677",
    "addr:housenumber":"12",
    "addr:postcode":"92677",
    "addr:street":"Novilla",
    "iso:country":"US",
    "sg:address":"12 Novilla",
    "sg:city":"Laguna Niguel",
    "sg:classifiers":[
        {
            "category":"Retail",
            "subcategory":"Portrait Studio",
            "type":"Services"
        }
    ],
    "sg:phone":"+1 949 388 3383",
    "sg:postcode":"92677",
    "sg:province":"CA",
    "sg:tags":[
        "photographer"
    ],
    "wof:name":"Memories Made Perfect",
    "wof:placetype":"venue"
},
  "geometry": {"coordinates":[-117.69763399999999,33.522304],"type":"Point"}
}