{
  "type": "Feature",
  "properties": {
    "addr:full":"4630 Soquel Dr Ste 3 Soquel CA 95073",
    "addr:housenumber":"4630",
    "addr:postcode":"95073",
    "addr:street":"Soquel Dr Ste 3",
    "iso:country":"US",
    "sg:address":"4630 Soquel Dr Ste 3",
    "sg:city":"Soquel",
    "sg:classifiers":[
        {
            "category":"Professional",
            "subcategory":"Lawyer & Legal Services",
            "type":"Services"
        }
    ],
    "sg:phone":"+1 831 462 8212",
    "sg:postcode":"95073",
    "sg:province":"CA",
    "wof:name":"Kerrigan Nancy J Atty",
    "wof:placetype":"venue"
},
  "geometry": {"coordinates":[-121.958,36.9879],"type":"Point"}
}