{
  "type": "Feature",
  "properties": {
    "addr:full":"1172 S Main St Salinas CA 93901",
    "addr:housenumber":"1172",
    "addr:postcode":"93901",
    "addr:street":"S Main St",
    "iso:country":"US",
    "sg:address":"1172 S Main St",
    "sg:city":"Salinas",
    "sg:classifiers":[
        {
            "category":"Professional",
            "subcategory":"Computer Services",
            "type":"Services"
        }
    ],
    "sg:phone":"+1 831 455 1052",
    "sg:postcode":"93901",
    "sg:province":"CA",
    "sg:tags":[
        "website",
        "design"
    ],
    "sg:website":"www.paciserv.com",
    "wof:name":"Pacific Internet Svc",
    "wof:placetype":"venue"
},
  "geometry": {"coordinates":[-121.65942,36.658277],"type":"Point"}
}