{
  "type": "Feature",
  "properties": {
    "iso:country":"US",
    "sg:address":"21 Santa Rosa St",
    "sg:city":"San Luis Obispo",
    "sg:classifiers":[
        {
            "category":"Professional",
            "subcategory":"Lawyer & Legal Services",
            "type":"Services"
        }
    ],
    "sg:phone":"+1 805 925 9255",
    "sg:postcode":"93405",
    "sg:province":"CA",
    "sg:tags":[
        "attorney"
    ],
    "sg:website":"www.mckiernanlaw.com",
    "wof:name":"James Mc Kiernan Lawyers",
    "wof:placetype":"venue"
},
  "geometry": {"coordinates":[-120.667776,35.29333],"type":"Point"}
}