{
  "type": "Feature",
  "properties": {
    "iso:country":"US",
    "sg:address":"1211 W College Ave",
    "sg:city":"Santa Rosa",
    "sg:classifiers":[
        {
            "category":"Food & Beverages",
            "subcategory":"Groceries & Convenience Stores",
            "type":"Retail Goods"
        }
    ],
    "sg:phone":"+1 707 546 6877",
    "sg:postcode":"95401",
    "sg:province":"CA",
    "sg:tags":[
        "independent",
        "grocer",
        "supermarket"
    ],
    "sg:website":"www.gandgmarket.com",
    "wof:name":"G & G Super Market",
    "wof:placetype":"venue"
},
  "geometry": {"coordinates":[-122.74254500000001,38.445378],"type":"Point"}
}