{
  "type": "Feature",
  "properties": {
    "addr:full":"5151 Amalfi Drive Irvine CA 92603",
    "addr:housenumber":"5151",
    "addr:postcode":"92603",
    "addr:street":"Amalfi Drive",
    "iso:country":"US",
    "sg:address":"5151 Amalfi Drive",
    "sg:city":"Irvine",
    "sg:classifiers":[
        {
            "category":"Social Services",
            "subcategory":"Child Care",
            "type":"Services"
        }
    ],
    "sg:phone":"+1 949 854 5060",
    "sg:postcode":"92603",
    "sg:province":"CA",
    "sg:tags":[
        "day"
    ],
    "wof:name":"Child Development Centers",
    "wof:placetype":"venue"
},
  "geometry": {"coordinates":[-117.81869399999999,33.646798],"type":"Point"}
}