{
  "type": "Feature",
  "properties": {
    "iso:country":"US",
    "sg:address":"104 Santa Clara St",
    "sg:city":"Watsonville",
    "sg:classifiers":[
        {
            "category":"Retail",
            "subcategory":"Auto Repair",
            "type":"Services"
        }
    ],
    "sg:phone":"+1 831 234 7224",
    "sg:postcode":"95076",
    "sg:province":"CA",
    "sg:tags":[
        "automobile",
        "lubrication"
    ],
    "wof:name":"Traveling Oil Doctor",
    "wof:placetype":"venue"
},
  "geometry": {"coordinates":[-121.76666,36.92237],"type":"Point"}
}