{
  "type": "Feature",
  "properties": {
    "addr:full":"1201 Morena Blvd San Diego CA 92110",
    "addr:housenumber":"1201",
    "addr:postcode":"92110",
    "addr:street":"Morena Blvd",
    "iso:country":"US",
    "sg:address":"1201 Morena Blvd",
    "sg:city":"San Diego",
    "sg:classifiers":[
        {
            "category":"Personal",
            "subcategory":"Barber",
            "type":"Services"
        }
    ],
    "sg:phone":"+1 619 276 1888",
    "sg:postcode":"92110",
    "sg:province":"CA",
    "wof:name":"P & L Barber Shop",
    "wof:placetype":"venue"
},
  "geometry": {"coordinates":[-117.20182,32.770888],"type":"Point"}
}