{
  "type": "Feature",
  "properties": {
    "iso:country":"US",
    "sg:address":"15 Red Rock Way",
    "sg:city":"San Francisco",
    "sg:classifiers":[
        {
            "category":"Building & Trades",
            "subcategory":"Landscaping Services",
            "type":"Services"
        }
    ],
    "sg:phone":"+1 415 877 1549",
    "sg:postcode":"94131",
    "sg:province":"CA",
    "sg:tags":[
        "gardener"
    ],
    "sg:website":"www.sanfranciscolandscaping.org",
    "wof:name":"Atlas Landscapes",
    "wof:placetype":"venue"
},
  "geometry": {"coordinates":[-122.44146000000001,37.746425],"type":"Point"}
}