{
  "type": "Feature",
  "properties": {
    "iso:country":"US",
    "sg:address":"2001 S Garey Ave",
    "sg:city":"Pomona",
    "sg:classifiers":[
        {
            "category":"Autos & Motor Vehicles",
            "subcategory":"Motorcycle Sales",
            "type":"Retail Goods"
        }
    ],
    "sg:phone":"+1 909 364 9600",
    "sg:postcode":"91766",
    "sg:province":"CA",
    "sg:tags":[
        "scooter"
    ],
    "wof:name":"5 Star Scooters",
    "wof:placetype":"venue"
},
  "geometry": {"coordinates":[-117.749381,34.035236],"type":"Point"}
}