{
  "type": "Feature",
  "properties": {
    "addr:full":"1441 Grant St San Francisco CA 94133",
    "addr:housenumber":"1441",
    "addr:postcode":"94133",
    "addr:street":"Grant St",
    "iso:country":"US",
    "sg:address":"1441 Grant St",
    "sg:city":"San Francisco",
    "sg:classifiers":[
        {
            "category":"Sports & Exercise",
            "subcategory":"Gym",
            "type":"Entertainment"
        }
    ],
    "sg:phone":"+1 415 225 2405",
    "sg:postcode":"94133",
    "sg:province":"CA",
    "sg:tags":[
        "trainer"
    ],
    "sg:website":"www.strengthofaspiral.com",
    "wof:name":"Strength of a Spiral",
    "wof:placetype":"venue"
},
  "geometry": {"coordinates":[-122.407588,37.800197],"type":"Point"}
}