{
  "type": "Feature",
  "properties": {
    "addr:full":"5513 W 142nd St Hawthorne CA 90250",
    "addr:housenumber":"5513",
    "addr:postcode":"90250",
    "addr:street":"W 142Nd St",
    "iso:country":"US",
    "sg:address":"5513 W 142nd St",
    "sg:city":"Hawthorne",
    "sg:classifiers":[
        {
            "category":"Organizations",
            "subcategory":"Non-profit Organization",
            "type":"Services"
        }
    ],
    "sg:phone":"+1 310 643 5687",
    "sg:postcode":"90250",
    "sg:province":"CA",
    "wof:name":"Hawthorne Presidents Council",
    "wof:placetype":"venue"
},
  "geometry": {"coordinates":[-118.37600399999999,33.903159],"type":"Point"}
}