{
  "type": "Feature",
  "properties": {
    "addr:full":"4108 Verdugo Road Los Angeles CA 90065",
    "addr:housenumber":"4108",
    "addr:postcode":"90065",
    "addr:street":"Verdugo Road",
    "iso:country":"US",
    "sg:address":"4108 Verdugo Road",
    "sg:city":"Los Angeles",
    "sg:classifiers":[
        {
            "category":"Cinema",
            "subcategory":"Movie Rental",
            "type":"Entertainment"
        }
    ],
    "sg:phone":"+1 323 257 7225",
    "sg:postcode":"90065",
    "sg:province":"CA",
    "sg:tags":[
        "game",
        "video"
    ],
    "wof:name":"Hbc",
    "wof:placetype":"venue"
},
  "geometry": {"coordinates":[-118.231667,34.125397],"type":"Point"}
}