{
  "type": "Feature",
  "properties": {
    "iso:country":"US",
    "sg:address":"575 San Pablo Ave",
    "sg:city":"Rodeo",
    "sg:classifiers":[
        {
            "category":"Education",
            "subcategory":"Special Training",
            "type":"Public Place"
        }
    ],
    "sg:phone":"+1 510 799 0234",
    "sg:postcode":"94572",
    "sg:province":"CA",
    "sg:tags":[
        "tutoring"
    ],
    "sg:website":"www.gemstonevision.org",
    "wof:name":"Gemstone Educational Mgmt",
    "wof:placetype":"venue"
},
  "geometry": {"coordinates":[-122.266559,38.039359],"type":"Point"}
}