{
  "type": "Feature",
  "properties": {
    "addr:full":"220 S Alta St Gonzales CA 93926",
    "addr:housenumber":"220",
    "addr:postcode":"93926",
    "addr:street":"S Alta St",
    "iso:country":"US",
    "sg:address":"220 S Alta St",
    "sg:city":"Gonzales",
    "sg:classifiers":[
        {
            "category":"Food & Beverages",
            "subcategory":"Groceries & Convenience Stores",
            "type":"Retail Goods"
        }
    ],
    "sg:phone":"+1 831 675 3369",
    "sg:postcode":"93926",
    "sg:province":"CA",
    "sg:tags":[
        "grocer"
    ],
    "wof:name":"Hp Mini Mart",
    "wof:placetype":"venue"
},
  "geometry": {"coordinates":[-121.44119600000001,36.503359],"type":"Point"}
}