{
  "type": "Feature",
  "properties": {
    "addr:full":"1874 E. Washington Blvd Pasadena CA 91104",
    "addr:housenumber":"1874",
    "addr:postcode":"91104",
    "addr:street":"E. Washington Blvd",
    "iso:country":"US",
    "sg:address":"1874 E. Washington Blvd",
    "sg:city":"Pasadena",
    "sg:classifiers":[
        {
            "category":"Education",
            "subcategory":"Kindergarten",
            "type":"Public Place"
        }
    ],
    "sg:phone":"+1 626 797 4888",
    "sg:postcode":"91104",
    "sg:province":"CA",
    "sg:tags":[
        "school",
        "driving"
    ],
    "wof:name":"Fast Lane Traffic School",
    "wof:placetype":"venue"
},
  "geometry": {"coordinates":[-118.111814,34.168895],"type":"Point"}
}