{
  "type": "Feature",
  "properties": {
    "addr:full":"390 N Forbes St Lakeport CA 95453",
    "addr:housenumber":"390",
    "addr:postcode":"95453",
    "addr:street":"N Forbes St",
    "iso:country":"US",
    "sg:address":"390 N Forbes St",
    "sg:city":"Lakeport",
    "sg:classifiers":[
        {
            "category":"Professional",
            "subcategory":"Lawyer & Legal Services",
            "type":"Services"
        }
    ],
    "sg:phone":"+1 707 262 0544",
    "sg:postcode":"95453",
    "sg:province":"CA",
    "sg:tags":[
        "attorney",
        "law",
        "family",
        "duo",
        "divorce",
        "child",
        "criminal",
        "dwi",
        "custody"
    ],
    "sg:website":"http://www.lakeportattorneys.com",
    "wof:name":"Alvord & Conard",
    "wof:placetype":"venue"
},
  "geometry": {"coordinates":[-122.91610799999999,39.044579],"type":"Point"}
}