{
  "type": "Feature",
  "properties": {
    "iso:country":"US",
    "sg:address":"1895 Jefferson Street, Ste 201",
    "sg:city":"San Francisco",
    "sg:classifiers":[
        {
            "category":"Professional",
            "type":"Services"
        }
    ],
    "sg:phone":"+1 415 999 1506",
    "sg:postcode":"94123",
    "sg:province":"CA",
    "sg:website":"www.gpdesignlab.com",
    "wof:name":"Gi Paoletti Design Lab",
    "wof:placetype":"venue"
},
  "geometry": {"coordinates":[-122.44372,37.804692],"type":"Point"}
}