{
  "type": "Feature",
  "properties": {
    "iso:country":"US",
    "sg:address":"4355 Bonillo Dr",
    "sg:city":"San Diego",
    "sg:classifiers":[
        {
            "category":"Professional",
            "subcategory":"Art Services",
            "type":"Services"
        }
    ],
    "sg:phone":"+1 619 286 9504",
    "sg:postcode":"92115",
    "sg:province":"CA",
    "sg:tags":[
        "graphic",
        "designer"
    ],
    "wof:name":"Jla Advertising Design",
    "wof:placetype":"venue"
},
  "geometry": {"coordinates":[-117.060228,32.757267],"type":"Point"}
}