{
  "type": "Feature",
  "properties": {
    "addr:full":"8530 Holloway Dr Los Angeles CA 90069",
    "addr:housenumber":"8530",
    "addr:postcode":"90069",
    "addr:street":"Holloway Dr",
    "iso:country":"US",
    "sg:address":"8530 Holloway Dr",
    "sg:city":"Los Angeles",
    "sg:classifiers":[
        {
            "category":"Manufacturing",
            "subcategory":"Printing",
            "type":"Manufacturing & Wholesale Goods"
        }
    ],
    "sg:phone":"+1 310 652 8902",
    "sg:postcode":"90069",
    "sg:province":"CA",
    "sg:tags":[
        "publisher",
        "music"
    ],
    "wof:name":"Happy Medium Music",
    "wof:placetype":"venue"
},
  "geometry": {"coordinates":[-118.376409,34.090561],"type":"Point"}
}