{
  "type": "Feature",
  "properties": {
    "iso:country":"US",
    "sg:address":"1204 E Thousand Oaks Blvd",
    "sg:city":"Thousand Oaks",
    "sg:classifiers":[
        {
            "category":"Personal",
            "type":"Services"
        }
    ],
    "sg:phone":"+1 805 494 4114",
    "sg:postcode":"91362",
    "sg:province":"CA",
    "sg:tags":[
        "dating"
    ],
    "wof:name":"Debra Winkler Personals",
    "wof:placetype":"venue"
},
  "geometry": {"coordinates":[-118.859231,34.178843],"type":"Point"}
}