{
  "type": "Feature",
  "properties": {
    "iso:country":"US",
    "sg:address":"366 Cambridge Ave, Suite 209",
    "sg:city":"Palo Alto",
    "sg:classifiers":[
        {
            "category":"Professional",
            "subcategory":"Computer Services",
            "type":"Services"
        }
    ],
    "sg:phone":"+31 341 375 555",
    "sg:postcode":"94306",
    "sg:province":"CA",
    "sg:tags":[
        "bpm",
        "bpms",
        "bam",
        "saas",
        "paas",
        "mashed-up-applications",
        "mashapps",
        "google-enterprise-partener",
        "cloud-orchestration",
        "soa",
        "integration"
    ],
    "sg:website":"http://www.cordys.com/",
    "wof:name":"Cordys",
    "wof:placetype":"venue"
},
  "geometry": {"coordinates":[-122.1468,37.42552],"type":"Point"}
}