{
  "type": "Feature",
  "properties": {
    "iso:country":"US",
    "sg:address":"1325 Sunnyvale Saratoga Rd",
    "sg:city":"Sunnyvale",
    "sg:classifiers":[
        {
            "category":"Personal",
            "type":"Services"
        }
    ],
    "sg:phone":"+1 408 733 0880",
    "sg:postcode":"94087",
    "sg:province":"CA",
    "sg:tags":[
        "local"
    ],
    "wof:name":"Bahara's Farmers Outlet",
    "wof:placetype":"venue"
},
  "geometry": {"coordinates":[-122.03245,37.350701],"type":"Point"}
}