{
  "type": "Feature",
  "properties": {
    "iso:country":"US",
    "sg:address":"583 25th Ave",
    "sg:city":"San Francisco",
    "sg:classifiers":[
        {
            "category":"Home & Garden",
            "subcategory":"Building Materials",
            "type":"Retail Goods"
        },
        {
            "category":"Building & Trades",
            "subcategory":"Electrical",
            "type":"Services"
        }
    ],
    "sg:phone":"+1 866 702 0026",
    "sg:postcode":"94121",
    "sg:province":"CA",
    "sg:tags":[
        "equipment",
        "lighting",
        "fixture",
        "electrician"
    ],
    "sg:website":"www.sanfranciscocaelectrician.com",
    "wof:name":"Retter Electric",
    "wof:placetype":"venue"
},
  "geometry": {"coordinates":[-122.484917,37.778503],"type":"Point"}
}