{
  "type": "Feature",
  "properties": {
    "iso:country":"US",
    "sg:address":"150 Catherine Ln",
    "sg:city":"Grass Valley",
    "sg:classifiers":[
        {
            "category":"Health Services",
            "subcategory":"Podiatrist",
            "type":"Services"
        }
    ],
    "sg:phone":"+1 530 272 1050",
    "sg:postcode":"95945",
    "sg:province":"CA",
    "wof:name":"Advance Podiatry",
    "wof:placetype":"venue"
},
  "geometry": {"coordinates":[-121.048809,39.228944],"type":"Point"}
}