{
  "type": "Feature",
  "properties": {
    "addr:full":"150 Airpark Blvd Chico CA 95973",
    "addr:postcode":"95973",
    "addr:street":"Airpark Blvd",
    "iso:country":"US",
    "sg:address":"150 Airpark Blvd",
    "sg:city":"Chico",
    "sg:classifiers":[
        {
            "category":"Retail",
            "subcategory":"Auto Rental",
            "type":"Services"
        }
    ],
    "sg:phone":"+1 530 332 9663",
    "sg:postcode":"95973",
    "sg:province":"CA",
    "sg:tags":[
        "renting",
        "automobile"
    ],
    "wof:name":"Hertz Rent A Car",
    "wof:placetype":"venue"
},
  "geometry": {"coordinates":[-121.85390200000001,39.798951],"type":"Point"}
}