{
  "type": "Feature",
  "properties": {
    "acgov:api":"690.0",
    "acgov:type":"ES",
    "addr:full":"17115 Meekland Ave Hayward CA",
    "wof:categories":[
        "education_and_religion:education=school"
    ],
    "wof:name":"Colonial Acres Elementary",
    "wof:placetype":"venue"
},
  "geometry": {"coordinates":[-122.1162558479604,37.68342118242888],"type":"Point"}
}