{
  "type": "Feature",
  "properties": {
    "iso:country":"US",
    "sg:address":"48800 Warm Springs Blvd",
    "sg:city":"Fremont",
    "sg:classifiers":[
        {
            "category":"Retail",
            "subcategory":"Funeral Services",
            "type":"Services"
        }
    ],
    "sg:phone":"+1 510 656 5565",
    "sg:postcode":"94539",
    "sg:province":"CA",
    "sg:tags":[
        "cemetery"
    ],
    "wof:name":"Abbey Chapel of Lima Family Milpitas Fremont Mrtry",
    "wof:placetype":"venue"
},
  "geometry": {"coordinates":[-121.915001,37.4645],"type":"Point"}
}