{
  "type": "Feature",
  "properties": {
    "addr:full":"3994 Morrell St San Diego CA 92109",
    "addr:housenumber":"3994",
    "addr:postcode":"92109",
    "addr:street":"Morrell St",
    "iso:country":"US",
    "sg:address":"3994 Morrell St",
    "sg:city":"San Diego",
    "sg:classifiers":[
        {
            "category":"Building & Trades",
            "subcategory":"Construction",
            "type":"Services"
        }
    ],
    "sg:phone":"+1 858 361 5909",
    "sg:postcode":"92109",
    "sg:province":"CA",
    "sg:tags":[
        "painter"
    ],
    "wof:name":"Rodriguez Paint & Wallpaper",
    "wof:placetype":"venue"
},
  "geometry": {"coordinates":[-117.23112999999999,32.793497],"type":"Point"}
}