{
  "type": "Feature",
  "properties": {
    "iso:country":"US",
    "sg:address":"166 E Sierra Ave Ste A",
    "sg:city":"Fresno",
    "sg:classifiers":[
        {
            "category":"Autos & Motor Vehicles",
            "subcategory":"Auto Supplies",
            "type":"Retail Goods"
        }
    ],
    "sg:phone":"+1 559 261 2450",
    "sg:postcode":"93710",
    "sg:province":"CA",
    "sg:tags":[
        "washing",
        "car",
        "equipment",
        "part",
        "automobile",
        "polishing"
    ],
    "wof:name":"Car Beauty Products",
    "wof:placetype":"venue"
},
  "geometry": {"coordinates":[-119.78654,36.830132],"type":"Point"}
}