{
  "type": "Feature",
  "properties": {
    "addr:full":"19636 8th St E Sonoma CA 95476",
    "addr:housenumber":"19636",
    "addr:postcode":"95476",
    "addr:street":"8Th St E",
    "iso:country":"US",
    "sg:address":"19636 8th St E",
    "sg:city":"Sonoma",
    "sg:classifiers":[
        {
            "category":"Retail",
            "subcategory":"Laundry & Dry Cleaning",
            "type":"Services"
        }
    ],
    "sg:phone":"+1 707 938 8398",
    "sg:postcode":"95476",
    "sg:province":"CA",
    "sg:tags":[
        "curtain",
        "drapery",
        "cleaners"
    ],
    "wof:name":"Wayne's On Site Drapery Cleani",
    "wof:placetype":"venue"
},
  "geometry": {"coordinates":[-122.436345,38.28615],"type":"Point"}
}