{
  "type": "Feature",
  "properties": {
    "iso:country":"US",
    "sg:address":"2501 Rubidoux Blvd Ste B",
    "sg:city":"Riverside",
    "sg:classifiers":[
        {
            "category":"Professional",
            "subcategory":"Business Services",
            "type":"Services"
        }
    ],
    "sg:phone":"+1 951 786 4155",
    "sg:postcode":"92509",
    "sg:province":"CA",
    "sg:tags":[
        "repossessing"
    ],
    "wof:name":"All Cal Adjusters",
    "wof:placetype":"venue"
},
  "geometry": {"coordinates":[-117.391786,34.014142],"type":"Point"}
}