{
  "type": "Feature",
  "properties": {
    "addr:full":"1117 Kern St Taft CA 93268",
    "addr:housenumber":"1117",
    "addr:postcode":"93268",
    "addr:street":"Kern St",
    "iso:country":"US",
    "sg:address":"1117 Kern St",
    "sg:city":"Taft",
    "sg:phone":"+1 661 763 1177",
    "sg:postcode":"93268",
    "sg:province":"CA",
    "sg:website":"http://www.kfc.com",
    "wof:name":"Kfc",
    "wof:placetype":"venue"
},
  "geometry": {"coordinates":[-119.468053,35.145889],"type":"Point"}
}