{
  "type": "Feature",
  "properties": {
    "addr:full":"1446 N Mount Vernon Ave San Bernardino CA 92411",
    "addr:housenumber":"1446",
    "addr:postcode":"92411",
    "addr:street":"N Mount Vernon Ave",
    "iso:country":"US",
    "sg:address":"1446 N Mount Vernon Ave",
    "sg:city":"San Bernardino",
    "sg:classifiers":[
        {
            "category":"Professional",
            "subcategory":"Management & Consulting",
            "type":"Services"
        }
    ],
    "sg:phone":"+1 909 888 2930",
    "sg:postcode":"92411",
    "sg:province":"CA",
    "sg:tags":[
        "consultant",
        "energy",
        "conservation"
    ],
    "wof:name":"Lampost Resource Group",
    "wof:placetype":"venue"
},
  "geometry": {"coordinates":[-117.31384300000001,34.125033],"type":"Point"}
}