{
  "type": "Feature",
  "properties": {
    "iso:country":"US",
    "sg:address":"3000 Cleveland Ave",
    "sg:city":"Santa Rosa",
    "sg:classifiers":[
        {
            "category":"Real Estate",
            "subcategory":"Real Estate Agent",
            "type":"Services"
        }
    ],
    "sg:phone":"+1 707 571 8957",
    "sg:postcode":"95403",
    "sg:province":"CA",
    "wof:name":"Harding Appraisal Co Inc",
    "wof:placetype":"venue"
},
  "geometry": {"coordinates":[-122.728554,38.467622],"type":"Point"}
}