{
  "type": "Feature",
  "properties": {
    "addr:full":"4961 Mountain View Rd Hughson CA 95326",
    "addr:housenumber":"4961",
    "addr:postcode":"95326",
    "addr:street":"Mountain View Rd",
    "iso:country":"US",
    "sg:address":"4961 Mountain View Rd",
    "sg:city":"Hughson",
    "sg:classifiers":[
        {
            "category":"Building & Trades",
            "subcategory":"Construction",
            "type":"Services"
        }
    ],
    "sg:phone":"+1 209 883 0386",
    "sg:postcode":"95326",
    "sg:province":"CA",
    "sg:tags":[
        "contractor"
    ],
    "wof:name":"Anson Construction",
    "wof:placetype":"venue"
},
  "geometry": {"coordinates":[-120.878998,37.567402],"type":"Point"}
}