{
  "type": "Feature",
  "properties": {
    "iso:country":"US",
    "sg:address":"14030 Lanning Dr",
    "sg:city":"Whittier",
    "sg:classifiers":[
        {
            "category":"Building & Trades",
            "subcategory":"Construction",
            "type":"Services"
        }
    ],
    "sg:phone":"+1 562 789 1937",
    "sg:postcode":"90605",
    "sg:province":"CA",
    "sg:tags":[
        "house"
    ],
    "wof:name":"Integrity Construction",
    "wof:placetype":"venue"
},
  "geometry": {"coordinates":[-118.028898,33.950007],"type":"Point"}
}