{
  "type": "Feature",
  "properties": {
    "iso:country":"US",
    "sg:address":"714 Santa Cruz Ave",
    "sg:city":"Menlo Park",
    "sg:classifiers":[
        {
            "category":"Shopping",
            "subcategory":"Hobbies, Toys, & Games",
            "type":"Retail Goods"
        }
    ],
    "sg:phone":"+1 650 328 7975",
    "sg:postcode":"94025",
    "sg:province":"CA",
    "sg:website":"www.cheekymonkeytoys.com",
    "wof:name":"Cheeky Monkey Toys",
    "wof:placetype":"venue"
},
  "geometry": {"coordinates":[-122.184175,37.452163],"type":"Point"}
}