{
  "type": "Feature",
  "properties": {
    "iso:country":"US",
    "sg:address":"443 1st St",
    "sg:city":"Woodland",
    "sg:classifiers":[
        {
            "category":"Retail",
            "subcategory":"Auto Repair",
            "type":"Services"
        }
    ],
    "sg:phone":"+1 530 666 9131",
    "sg:postcode":"95695",
    "sg:province":"CA",
    "sg:tags":[
        "automobile",
        "top",
        "upholstery"
    ],
    "wof:name":"Jack's Upholstery",
    "wof:placetype":"venue"
},
  "geometry": {"coordinates":[-121.773096,38.676932],"type":"Point"}
}