{
  "type": "Feature",
  "properties": {
    "iso:country":"US",
    "sg:address":"810 Los Vallecitos Blvd",
    "sg:city":"San Marcos",
    "sg:classifiers":[
        {
            "category":"Manufacturing",
            "subcategory":"Signs",
            "type":"Manufacturing & Wholesale Goods"
        }
    ],
    "sg:phone":"+1 760 489 6830",
    "sg:postcode":"92069",
    "sg:province":"CA",
    "wof:name":"Premier Signs LLC",
    "wof:placetype":"venue"
},
  "geometry": {"coordinates":[-117.18250500000001,33.140265],"type":"Point"}
}