{
  "type": "Feature",
  "properties": {
    "addr:full":"6241 E Catlett Rd Lincoln CA 95648",
    "addr:housenumber":"6241",
    "addr:postcode":"95648",
    "addr:street":"E Catlett Rd",
    "iso:country":"US",
    "sg:address":"6241 E Catlett Rd",
    "sg:city":"Lincoln",
    "sg:classifiers":[
        {
            "category":"Farming",
            "subcategory":"Dairy Farm",
            "type":"Manufacturing & Wholesale Goods"
        }
    ],
    "sg:phone":"+1 916 655 3439",
    "sg:postcode":"95648",
    "sg:province":"CA",
    "wof:name":"Frank Machado",
    "wof:placetype":"venue"
},
  "geometry": {"coordinates":[-121.45239599999999,38.846014],"type":"Point"}
}