{
  "type": "Feature",
  "properties": {
    "addr:full":"3455 El Camino Real Santa Clara CA 95051",
    "addr:housenumber":"3455",
    "addr:postcode":"95051",
    "addr:street":"El Camino Real",
    "iso:country":"US",
    "sg:address":"3455 El Camino Real",
    "sg:city":"Santa Clara",
    "sg:classifiers":[
        {
            "category":"Retail",
            "subcategory":"Car Wash",
            "type":"Services"
        },
        {
            "category":"Retail",
            "subcategory":"Auto Repair",
            "type":"Services"
        }
    ],
    "sg:phone":"+1 408 244 8233",
    "sg:postcode":"95051",
    "sg:province":"CA",
    "sg:tags":[
        "detailing"
    ],
    "sg:website":"www.touchlesscarwash.biz",
    "wof:name":"Tan's Touchless Car Wash",
    "wof:placetype":"venue"
},
  "geometry": {"coordinates":[-121.991518,37.352314],"type":"Point"}
}