{
  "type": "Feature",
  "properties": {
    "addr:full":"134 E Valley Blvd Alhambra CA 91801",
    "addr:housenumber":"134",
    "addr:postcode":"91801",
    "addr:street":"E Valley Blvd",
    "iso:country":"US",
    "sg:address":"134 E Valley Blvd",
    "sg:city":"Alhambra",
    "sg:classifiers":[
        {
            "category":"Shopping",
            "subcategory":"Clothing, Apparel, & Fashions",
            "type":"Retail Goods"
        }
    ],
    "sg:phone":"+1 626 281 0080",
    "sg:postcode":"91801",
    "sg:province":"CA",
    "sg:tags":[
        "accessory"
    ],
    "sg:website":"www.mariasfashiononline.com",
    "wof:name":"Maria's Fashion",
    "wof:placetype":"venue"
},
  "geometry": {"coordinates":[-118.121002,34.078602],"type":"Point"}
}