{
  "type": "Feature",
  "properties": {
    "iso:country":"US",
    "sg:address":"1080 W San Marcos Blvd",
    "sg:city":"San Marcos",
    "sg:classifiers":[
        {
            "category":"Restaurant",
            "type":"Food & Drink"
        }
    ],
    "sg:phone":"+1 760 471 7646",
    "sg:postcode":"92078",
    "sg:province":"CA",
    "wof:name":"Market Street Cafe & Bakery",
    "wof:placetype":"venue"
},
  "geometry": {"coordinates":[-117.190629,33.134183],"type":"Point"}
}