{
  "type": "Feature",
  "properties": {
    "addr:full":"11140 Plainview Ave Tujunga CA 91042",
    "addr:housenumber":"11140",
    "addr:postcode":"91042",
    "addr:street":"Plainview Ave",
    "iso:country":"US",
    "sg:address":"11140 Plainview Ave",
    "sg:city":"Tujunga",
    "sg:classifiers":[
        {
            "category":"Organizations",
            "subcategory":"Professional Association",
            "type":"Services"
        }
    ],
    "sg:phone":"+1 818 353 1807",
    "sg:postcode":"91042",
    "sg:province":"CA",
    "sg:tags":[
        "sale"
    ],
    "wof:name":"Mikes Glass",
    "wof:placetype":"venue"
},
  "geometry": {"coordinates":[-118.30162,34.271496],"type":"Point"}
}