{
  "type": "Feature",
  "properties": {
    "addr:full":"2361 Heidi Pl Santa Rosa CA 95403",
    "addr:housenumber":"2361",
    "addr:postcode":"95403",
    "addr:street":"Heidi Pl",
    "iso:country":"US",
    "sg:address":"2361 Heidi Pl",
    "sg:city":"Santa Rosa",
    "sg:classifiers":[
        {
            "category":"Retail",
            "subcategory":"Auto Repair",
            "type":"Services"
        }
    ],
    "sg:phone":"+1 707 526 9211",
    "sg:postcode":"95403",
    "sg:province":"CA",
    "sg:tags":[
        "repairing",
        "automobile"
    ],
    "wof:name":"Wine Country On Site",
    "wof:placetype":"venue"
},
  "geometry": {"coordinates":[-122.738077,38.460992],"type":"Point"}
}