{
  "type": "Feature",
  "properties": {
    "addr:full":"182 Keller St Petaluma CA 94952",
    "addr:housenumber":"182",
    "addr:postcode":"94952",
    "addr:street":"Keller St",
    "iso:country":"US",
    "sg:address":"182 Keller St",
    "sg:city":"Petaluma",
    "sg:classifiers":[
        {
            "category":"Building & Trades",
            "subcategory":"Construction",
            "type":"Services"
        }
    ],
    "sg:phone":"+1 707 769 1170",
    "sg:postcode":"94952",
    "sg:province":"CA",
    "sg:tags":[
        "roofing",
        "contractor"
    ],
    "wof:name":"Calif Roof Savers Inc",
    "wof:placetype":"venue"
},
  "geometry": {"coordinates":[-122.642762,38.234904],"type":"Point"}
}