{
  "type": "Feature",
  "properties": {
    "addr:full":"10016 Rosedale Hwy Bakersfield CA 93312",
    "addr:housenumber":"10016",
    "addr:postcode":"93312",
    "addr:street":"Rosedale Hwy",
    "iso:country":"US",
    "sg:address":"10016 Rosedale Hwy",
    "sg:city":"Bakersfield",
    "sg:classifiers":[
        {
            "category":"Wholesale",
            "subcategory":"Durable Goods & Equipment",
            "type":"Manufacturing & Wholesale Goods"
        }
    ],
    "sg:phone":"+1 661 589 9091",
    "sg:postcode":"93312",
    "sg:province":"CA",
    "sg:tags":[
        "fire",
        "extinguisher"
    ],
    "wof:name":"Independent Fire & Safety Co",
    "wof:placetype":"venue"
},
  "geometry": {"coordinates":[-119.11353699999999,35.383551],"type":"Point"}
}