{
  "type": "Feature",
  "properties": {
    "addr:full":"22410 Indals Pl Calabasas CA 91302",
    "addr:postcode":"22410;91302",
    "addr:street":"Indals Pl",
    "iso:country":"US",
    "sg:address":"22410 Indals Pl",
    "sg:city":"Calabasas",
    "sg:classifiers":[
        {
            "category":"Arts & Performance",
            "subcategory":"Theater",
            "type":"Entertainment"
        }
    ],
    "sg:phone":"+1 818 752 0900",
    "sg:postcode":"91302",
    "sg:province":"CA",
    "sg:tags":[
        "equipment",
        "theatrical",
        "supply"
    ],
    "wof:name":"Hollywood International",
    "wof:placetype":"venue"
},
  "geometry": {"coordinates":[-118.61549100000001,34.135285],"type":"Point"}
}