{
  "type": "Feature",
  "properties": {
    "addr:full":"207 N Glendale Ave Glendale CA 91206",
    "addr:housenumber":"207",
    "addr:postcode":"91206",
    "addr:street":"N Glendale Ave",
    "iso:country":"US",
    "sg:address":"207 N Glendale Ave",
    "sg:city":"Glendale",
    "sg:classifiers":[
        {
            "category":"Shopping",
            "subcategory":"Jewelry",
            "type":"Retail Goods"
        }
    ],
    "sg:phone":"+1 818 545 3819",
    "sg:postcode":"91206",
    "sg:province":"CA",
    "wof:name":"Family Jewels",
    "wof:placetype":"venue"
},
  "geometry": {"coordinates":[-118.24700199999999,34.1483],"type":"Point"}
}