{
  "type": "Feature",
  "properties": {
    "addr:full":"5537 38th Ave Sacramento CA 95824",
    "addr:housenumber":"5537",
    "addr:postcode":"95824",
    "addr:street":"38Th Ave",
    "iso:country":"US",
    "sg:address":"5537 38th Ave",
    "sg:city":"Sacramento",
    "sg:phone":"+1 916 947 8513",
    "sg:postcode":"95824",
    "sg:province":"CA",
    "wof:name":"Move 4 Less",
    "wof:placetype":"venue"
},
  "geometry": {"coordinates":[-121.43831900000001,38.519993],"type":"Point"}
}