{
  "type": "Feature",
  "properties": {
    "addr:full":"7030 Ave Encinas Carlsbad CA 92011",
    "addr:housenumber":"7030",
    "addr:postcode":"92011",
    "addr:street":"Ave Encinas",
    "iso:country":"US",
    "sg:address":"7030 Ave Encinas",
    "sg:city":"Carlsbad",
    "sg:classifiers":[
        {
            "category":"Real Estate",
            "subcategory":"Real Estate Agent",
            "type":"Services"
        }
    ],
    "sg:phone":"+1 760 431 3338",
    "sg:postcode":"92011",
    "sg:province":"CA",
    "wof:name":"Lund Team",
    "wof:placetype":"venue"
},
  "geometry": {"coordinates":[-117.31293700000001,33.101693],"type":"Point"}
}