{
  "type": "Feature",
  "properties": {
    "addr:full":"3342 S La Cienega Blvd Los Angeles CA 90016",
    "addr:housenumber":"3342",
    "addr:postcode":"90016",
    "addr:street":"S La Cienega Blvd",
    "iso:country":"US",
    "sg:address":"3342 S La Cienega Blvd",
    "sg:city":"Los Angeles",
    "sg:classifiers":[
        {
            "category":"Fast Food",
            "type":"Food & Drink"
        }
    ],
    "sg:phone":"+1 310 210 3666",
    "sg:postcode":"90016",
    "sg:province":"CA",
    "sg:website":"www.arbys.com",
    "wof:name":"Arby's",
    "wof:placetype":"venue"
},
  "geometry": {"coordinates":[-118.371977,34.026903],"type":"Point"}
}