{
  "type": "Feature",
  "properties": {
    "iso:country":"US",
    "sg:address":"2239 E Via Burton",
    "sg:city":"Anaheim",
    "sg:classifiers":[
        {
            "category":"Building & Trades",
            "subcategory":"Construction",
            "type":"Services"
        }
    ],
    "sg:phone":"+1 714 713 6466",
    "sg:postcode":"92806",
    "sg:province":"CA",
    "sg:tags":[
        "fence",
        "contractor"
    ],
    "wof:name":"Evergreen Iron Works",
    "wof:placetype":"venue"
},
  "geometry": {"coordinates":[-117.885722,33.856054],"type":"Point"}
}