{
  "type": "Feature",
  "properties": {
    "addr:full":"13204 Estrella Avenue Gardena CA 90248",
    "addr:housenumber":"13204",
    "addr:postcode":"90248",
    "addr:street":"Estrella Avenue",
    "iso:country":"US",
    "sg:address":"13204 Estrella Avenue",
    "sg:city":"Gardena",
    "sg:classifiers":[
        {
            "category":"Home & Garden",
            "subcategory":"Carpets & Floor Coverings",
            "type":"Retail Goods"
        }
    ],
    "sg:phone":"+1 310 329 8898",
    "sg:postcode":"90248",
    "sg:province":"CA",
    "sg:tags":[
        "carpeting"
    ],
    "sg:website":"www.abstractcarpet.com",
    "wof:name":"Abstract Carpet Design",
    "wof:placetype":"venue"
},
  "geometry": {"coordinates":[-118.28534399999999,33.913288],"type":"Point"}
}