{
  "type": "Feature",
  "properties": {
    "iso:country":"US",
    "sg:address":"100 Victoria Ave",
    "sg:city":"Oxnard",
    "sg:classifiers":[
        {
            "category":"Food & Beverages",
            "subcategory":"Fruits & Vegetables",
            "type":"Retail Goods"
        }
    ],
    "sg:phone":"+1 805 382 0799",
    "sg:postcode":"93030",
    "sg:province":"CA",
    "sg:tags":[
        "produce"
    ],
    "wof:name":"Lil Red Barn",
    "wof:placetype":"venue"
},
  "geometry": {"coordinates":[-119.22093,34.208514],"type":"Point"}
}