{
  "type": "Feature",
  "properties": {
    "addr:full":"12 Camino Encinas Ste 3 Orinda CA 94563",
    "addr:housenumber":"12",
    "addr:postcode":"94563",
    "addr:street":"Camino Encinas Ste 3",
    "iso:country":"US",
    "sg:address":"12 Camino Encinas Ste 3",
    "sg:city":"Orinda",
    "sg:classifiers":[
        {
            "category":"Health Services",
            "subcategory":"Doctor",
            "type":"Services"
        }
    ],
    "sg:phone":"+1 925 254 2360",
    "sg:postcode":"94563",
    "sg:province":"CA",
    "sg:tags":[
        "surgeon",
        "oral"
    ],
    "wof:name":"Todd B. Pearson, DDS",
    "wof:placetype":"venue"
},
  "geometry": {"coordinates":[-122.18044500000001,37.876571],"type":"Point"}
}