{
  "type": "Feature",
  "properties": {
    "iso:country":"US",
    "sg:address":"1080 Broadway",
    "sg:city":"Millbrae",
    "sg:classifiers":[
        {
            "category":"Insurance",
            "subcategory":"Insurance Agent",
            "type":"Services"
        },
        {
            "category":"Insurance",
            "subcategory":"Hazard Insurance",
            "type":"Services"
        },
        {
            "category":"Insurance",
            "subcategory":"Title Insurance",
            "type":"Services"
        },
        {
            "category":"Insurance",
            "subcategory":"Life Insurance",
            "type":"Services"
        }
    ],
    "sg:phone":"+1 650 552 0055",
    "sg:postcode":"94030",
    "sg:province":"CA",
    "sg:tags":[
        "auto",
        "commercial",
        "business",
        "homeowner"
    ],
    "sg:website":"http://www.farmersagent.com/scheung/",
    "wof:name":"Stephen Cheung - Farmers Insurance",
    "wof:placetype":"venue"
},
  "geometry": {"coordinates":[-122.397941,37.605687],"type":"Point"}
}