{
  "type": "Feature",
  "properties": {
    "addr:full":"4695 Via Palma La Mesa CA 91941",
    "addr:housenumber":"4695",
    "addr:postcode":"91941",
    "addr:street":"Via Palma",
    "iso:country":"US",
    "sg:address":"4695 Via Palma",
    "sg:city":"La Mesa",
    "sg:classifiers":[
        {
            "category":"Utilities",
            "subcategory":"Telephone",
            "type":"Services"
        }
    ],
    "sg:phone":"+1 619 667 6990",
    "sg:postcode":"91941",
    "sg:province":"CA",
    "sg:tags":[
        "local"
    ],
    "wof:name":"Mpower Communications Corp",
    "wof:placetype":"venue"
},
  "geometry": {"coordinates":[-116.953129,32.745824],"type":"Point"}
}