{
  "type": "Feature",
  "properties": {
    "addr:full":"3759 W Shaw Ave Fresno CA 93711",
    "addr:housenumber":"3759",
    "addr:postcode":"93711",
    "addr:street":"W Shaw Ave",
    "iso:country":"US",
    "sg:address":"3759 W Shaw Ave",
    "sg:city":"Fresno",
    "sg:classifiers":[
        {
            "category":"Utilities",
            "subcategory":"Mobile Phone",
            "type":"Services"
        },
        {
            "category":"Shopping",
            "subcategory":"Mobile Phones",
            "type":"Retail Goods"
        }
    ],
    "sg:phone":"+1 559 277 0922",
    "sg:postcode":"93711",
    "sg:province":"CA",
    "sg:tags":[
        "equipment",
        "telephone",
        "cellular",
        "supply"
    ],
    "wof:name":"Cricket Wireless",
    "wof:placetype":"venue"
},
  "geometry": {"coordinates":[-119.859859,36.808177],"type":"Point"}
}