{
  "type": "Feature",
  "properties": {
    "iso:country":"US",
    "sg:address":"882 El Camino Avenue",
    "sg:city":"Sacramento",
    "sg:classifiers":[
        {
            "category":"Restaurant",
            "type":"Food & Drink"
        }
    ],
    "sg:phone":"+1 916 929 3068",
    "sg:postcode":"95815",
    "sg:province":"CA",
    "sg:website":"www.ambrosiafinefood.com",
    "wof:name":"Ambrosia Fine Food",
    "wof:placetype":"venue"
},
  "geometry": {"coordinates":[-121.446568,38.611034],"type":"Point"}
}