{
  "type": "Feature",
  "properties": {
    "iso:country":"US",
    "sg:address":"1111 N Garfield Ave",
    "sg:city":"Alhambra",
    "sg:classifiers":[
        {
            "category":"Food & Beverages",
            "subcategory":"Groceries & Convenience Stores",
            "type":"Retail Goods"
        }
    ],
    "sg:phone":"+1 626 576 7755",
    "sg:postcode":"91801",
    "sg:province":"CA",
    "wof:name":"7-Eleven",
    "wof:placetype":"venue"
},
  "geometry": {"coordinates":[-118.133954,34.104597],"type":"Point"}
}