{
  "type": "Feature",
  "properties": {
    "addr:full":"627 Otis Dr Ripon CA 95366",
    "addr:housenumber":"627",
    "addr:postcode":"ca 95366",
    "addr:street":"Otis Dr",
    "iso:country":"US",
    "sg:address":"627 Otis Dr",
    "sg:city":"Ripon",
    "sg:classifiers":[
        {
            "category":"Building & Trades",
            "subcategory":"Construction",
            "type":"Services"
        }
    ],
    "sg:phone":"+1 209 599 3866",
    "sg:postcode":"95366",
    "sg:province":"CA",
    "sg:tags":[
        "home",
        "builder"
    ],
    "wof:name":"Brookline By Morrison Homes",
    "wof:placetype":"venue"
},
  "geometry": {"coordinates":[-121.13135800000001,37.747938],"type":"Point"}
}