{
  "type": "Feature",
  "properties": {
    "iso:country":"US",
    "sg:address":"1643 Micheltorena St",
    "sg:city":"Los Angeles",
    "sg:classifiers":[
        {
            "category":"Building & Trades",
            "subcategory":"Construction",
            "type":"Services"
        }
    ],
    "sg:phone":"+1 562 708 0627",
    "sg:postcode":"90026",
    "sg:province":"CA",
    "sg:tags":[
        "painter"
    ],
    "wof:name":"Sam Painting",
    "wof:placetype":"venue"
},
  "geometry": {"coordinates":[-118.273975,34.091066],"type":"Point"}
}