{
  "type": "Feature",
  "properties": {
    "iso:country":"US",
    "sg:address":"1550 N Clark St",
    "sg:city":"Fresno",
    "sg:classifiers":[
        {
            "category":"Building & Trades",
            "subcategory":"Construction",
            "type":"Services"
        }
    ],
    "sg:phone":"+1 559 497 5224",
    "sg:postcode":"93703",
    "sg:province":"CA",
    "sg:tags":[
        "contractor"
    ],
    "wof:name":"New Image",
    "wof:placetype":"venue"
},
  "geometry": {"coordinates":[-119.785965,36.764052],"type":"Point"}
}