{
  "type": "Feature",
  "properties": {
    "addr:full":"15300 Mc Kendree Ave Pacific Plsds CA 90272",
    "addr:housenumber":"15300",
    "addr:postcode":"90272",
    "addr:street":"Mc Kendree Ave",
    "iso:country":"US",
    "sg:address":"15300 Mc Kendree Ave",
    "sg:city":"Pacific Plsds",
    "sg:classifiers":[
        {
            "category":"Communications",
            "subcategory":"Film & Video Production",
            "type":"Services"
        }
    ],
    "sg:phone":"+1 310 454 1742",
    "sg:postcode":"90272",
    "sg:province":"CA",
    "sg:tags":[
        "motion",
        "picture",
        "studio",
        "producer"
    ],
    "wof:name":"D & K Productions",
    "wof:placetype":"venue"
},
  "geometry": {"coordinates":[-118.52588299999999,34.052657],"type":"Point"}
}