{
  "type": "Feature",
  "properties": {
    "addr:full":"2343 E Richmond Ave Fresno CA 93720",
    "addr:housenumber":"2343",
    "addr:postcode":"93720",
    "addr:street":"E Richmond Ave",
    "iso:country":"US",
    "sg:address":"2343 E Richmond Ave",
    "sg:city":"Fresno",
    "sg:classifiers":[
        {
            "category":"Wholesale",
            "subcategory":"Medical Equipment & Supplies",
            "type":"Manufacturing & Wholesale Goods"
        }
    ],
    "sg:phone":"+1 559 323 7733",
    "sg:postcode":"93720",
    "sg:province":"CA",
    "sg:tags":[
        "physician",
        "surgeon"
    ],
    "wof:name":"West Coast Medical Sales",
    "wof:placetype":"venue"
},
  "geometry": {"coordinates":[-119.74066999999999,36.857493],"type":"Point"}
}