{
  "type": "Feature",
  "properties": {
    "addr:full":"6431 Riverside Blvd Sacramento CA 95831",
    "addr:housenumber":"6431",
    "addr:postcode":"95831",
    "addr:street":"Riverside Blvd",
    "iso:country":"US",
    "sg:address":"6431 Riverside Blvd",
    "sg:city":"Sacramento",
    "sg:classifiers":[
        {
            "category":"Taxi",
            "type":"Transportation"
        }
    ],
    "sg:phone":"+1 916 288 8498",
    "sg:postcode":"95831",
    "sg:province":"CA",
    "wof:name":"Taxi Services",
    "wof:placetype":"venue"
},
  "geometry": {"coordinates":[-121.54251600000001,38.509929],"type":"Point"}
}