{
  "type": "Feature",
  "properties": {
    "iso:country":"US",
    "sg:address":"33 Serramonte Blvd",
    "sg:city":"Daly City",
    "sg:classifiers":[
        {
            "category":"Manufacturing",
            "subcategory":"Printing",
            "type":"Manufacturing & Wholesale Goods"
        }
    ],
    "sg:phone":"+1 650 756 5006",
    "sg:postcode":"94015",
    "sg:province":"CA",
    "sg:tags":[
        "poster"
    ],
    "sg:website":"www.printsplus.com",
    "wof:name":"Prints Plus",
    "wof:placetype":"venue"
},
  "geometry": {"coordinates":[-122.466886,37.669422],"type":"Point"}
}