{
  "type": "Feature",
  "properties": {
    "iso:country":"US",
    "sg:address":"69100 Converse Rd",
    "sg:city":"Cathedral City",
    "sg:classifiers":[
        {
            "category":"Autos & Motor Vehicles",
            "subcategory":"Automobile Sales",
            "type":"Retail Goods"
        },
        {
            "category":"Retail",
            "subcategory":"Auto Repair",
            "type":"Services"
        }
    ],
    "sg:phone":"+1 760 346 2345",
    "sg:postcode":"92234",
    "sg:province":"CA",
    "sg:tags":[
        "car"
    ],
    "wof:name":"Simon Motors Chevrolet Cadillac",
    "wof:placetype":"venue"
},
  "geometry": {"coordinates":[-116.456001,33.790501],"type":"Point"}
}