{
  "type": "Feature",
  "properties": {
    "iso:country":"US",
    "sg:address":"6161 Santa Monica Blvd",
    "sg:city":"Los Angeles",
    "sg:classifiers":[
        {
            "category":"Arts & Performance",
            "subcategory":"Theater",
            "type":"Entertainment"
        }
    ],
    "sg:phone":"+1 323 874 6070",
    "sg:postcode":"90038",
    "sg:province":"CA",
    "sg:tags":[
        "bureau"
    ],
    "wof:name":"Zig Zag Communications",
    "wof:placetype":"venue"
},
  "geometry": {"coordinates":[-118.324133,34.090819],"type":"Point"}
}