{
  "type": "Feature",
  "properties": {
    "iso:country":"US",
    "sg:address":"256 Covington St",
    "sg:city":"Oakland",
    "sg:classifiers":[
        {
            "category":"Food & Beverages",
            "subcategory":"Liquor & Beverages",
            "type":"Retail Goods"
        },
        {
            "category":"Wholesale",
            "subcategory":"Wine & Distilled Alcoholic Beverages",
            "type":"Manufacturing & Wholesale Goods"
        }
    ],
    "sg:phone":"+1 510 430 3083",
    "sg:postcode":"94605",
    "sg:province":"CA",
    "sg:tags":[
        "broker"
    ],
    "wof:name":"Paul S Hunt Wine Selections",
    "wof:placetype":"venue"
},
  "geometry": {"coordinates":[-122.13597300000001,37.735271],"type":"Point"}
}