{
  "type": "Feature",
  "properties": {
    "addr:full":"1031 Ocean Ave San Francisco CA 94112",
    "addr:housenumber":"1031",
    "addr:postcode":"94112",
    "addr:street":"Ocean Ave",
    "iso:country":"US",
    "sg:address":"1031 Ocean Ave",
    "sg:city":"San Francisco",
    "sg:classifiers":[
        {
            "category":"Cafe",
            "type":"Food & Drink"
        },
        {
            "category":"Restaurant",
            "type":"Food & Drink"
        }
    ],
    "sg:menulink":"http://www.allmenus.com/ca/san-francisco/81829-ocean-cafe-restaurant/menu/",
    "sg:phone":"+1 415 333 8668",
    "sg:postcode":"94112",
    "sg:province":"CA",
    "sg:tags":[
        "asian",
        "chinese"
    ],
    "wof:name":"Ocean Cafe Restaurant",
    "wof:placetype":"venue"
},
  "geometry": {"coordinates":[-122.453689,37.72338],"type":"Point"}
}