{
  "type": "Feature",
  "properties": {
    "iso:country":"US",
    "sg:address":"643 S Olive St",
    "sg:city":"Los Angeles",
    "sg:classifiers":[
        {
            "category":"Manufacturing",
            "subcategory":"Jewelry",
            "type":"Manufacturing & Wholesale Goods"
        }
    ],
    "sg:phone":"+1 213 623 5889",
    "sg:postcode":"90014",
    "sg:province":"CA",
    "sg:tags":[
        "precious",
        "metal",
        "mfg"
    ],
    "wof:name":"Jewel Designs By A P Inc",
    "wof:placetype":"venue"
},
  "geometry": {"coordinates":[-118.255104,34.047262],"type":"Point"}
}