{
  "type": "Feature",
  "properties": {
    "iso:country":"US",
    "sg:address":"239 E Acacia St",
    "sg:city":"Salinas",
    "sg:classifiers":[
        {
            "category":"Banks & Credit Unions",
            "subcategory":"Investment Brokerage",
            "type":"Services"
        }
    ],
    "sg:phone":"+1 831 424 7781",
    "sg:postcode":"93901",
    "sg:province":"CA",
    "sg:tags":[
        "security"
    ],
    "wof:name":"Gillson Brokerage Co Inc",
    "wof:placetype":"venue"
},
  "geometry": {"coordinates":[-121.650593,36.662856],"type":"Point"}
}