{
  "type": "Feature",
  "properties": {
    "iso:country":"US",
    "sg:address":"6777 Hollywood Blvd",
    "sg:city":"Los Angeles",
    "sg:classifiers":[
        {
            "category":"Professional",
            "type":"Services"
        }
    ],
    "sg:phone":"+1 323 463 1575",
    "sg:postcode":"90028",
    "sg:province":"CA",
    "wof:name":"Stars Stars Stars",
    "wof:placetype":"venue"
},
  "geometry": {"coordinates":[-118.338123,34.101624],"type":"Point"}
}