{
  "type": "Feature",
  "properties": {
    "addr:full":"Warner Center Trillium 6320 Canoga Ave, Ste 1500 Woodland Hills CA 91367",
    "addr:housenumber":"6320",
    "addr:postcode":"91367",
    "addr:street":"Canoga Ave Ste 1500",
    "iso:country":"US",
    "sg:address":"Warner Center Trillium 6320 Canoga Ave, Ste 1500",
    "sg:city":"Woodland Hills",
    "sg:classifiers":[
        {
            "category":"Professional",
            "subcategory":"Accounting & Tax Preparation",
            "type":"Services"
        },
        {
            "category":"Banks & Credit Unions",
            "subcategory":"Investment Brokerage",
            "type":"Services"
        }
    ],
    "sg:phone":"+1 818 582 5945",
    "sg:postcode":"91367",
    "sg:province":"CA",
    "sg:tags":[
        "investing",
        "accountant"
    ],
    "sg:website":"www.ahcpa.info",
    "wof:name":"Ara Haddadian, CPA",
    "wof:placetype":"venue"
},
  "geometry": {"coordinates":[-118.596226,34.185596],"type":"Point"}
}