{
  "type": "Feature",
  "properties": {
    "iso:country":"US",
    "sg:address":"1385 Norma Dr",
    "sg:city":"Napa",
    "sg:classifiers":[
        {
            "category":"Retail",
            "subcategory":"Laundry & Dry Cleaning",
            "type":"Services"
        }
    ],
    "sg:phone":"+1 707 255 4298",
    "sg:postcode":"94558",
    "sg:province":"CA",
    "sg:tags":[
        "cleaners",
        "rug",
        "carpet"
    ],
    "wof:name":"Dave's Dry Extraction Carpet",
    "wof:placetype":"venue"
},
  "geometry": {"coordinates":[-122.313814,38.312766],"type":"Point"}
}