{
  "type": "Feature",
  "properties": {
    "addr:full":"236 W Mountain St Pasadena CA 91103",
    "addr:housenumber":"236",
    "addr:postcode":"91103",
    "addr:street":"W Mountain St",
    "iso:country":"US",
    "sg:address":"236 W Mountain St",
    "sg:city":"Pasadena",
    "sg:classifiers":[
        {
            "category":"Personal",
            "subcategory":"Beauty Salon",
            "type":"Services"
        }
    ],
    "sg:phone":"+1 626 356 2172",
    "sg:postcode":"91103",
    "sg:province":"CA",
    "wof:name":"Fantastic Hair Design Barber",
    "wof:placetype":"venue"
},
  "geometry": {"coordinates":[-118.156893,34.162054],"type":"Point"}
}