{
  "type": "Feature",
  "properties": {
    "iso:country":"US",
    "sg:address":"314 N Palm Canyon Dr",
    "sg:city":"Palm Springs",
    "sg:classifiers":[
        {
            "category":"Banks & Credit Unions",
            "subcategory":"Financial Services",
            "type":"Services"
        }
    ],
    "sg:phone":"+1 760 969 5820",
    "sg:postcode":"92262",
    "sg:province":"CA",
    "sg:tags":[
        "broker",
        "mortgage"
    ],
    "wof:name":"Gray Home Loans",
    "wof:placetype":"venue"
},
  "geometry": {"coordinates":[-116.54665799999999,33.826972],"type":"Point"}
}