{
  "type": "Feature",
  "properties": {
    "iso:country":"US",
    "sg:address":"3400 E Anaheim St",
    "sg:city":"Long Beach",
    "sg:classifiers":[
        {
            "category":"Autos & Motor Vehicles",
            "subcategory":"Fuel & Gas Station",
            "type":"Retail Goods"
        }
    ],
    "sg:phone":"+1 562 597 0813",
    "sg:postcode":"90804",
    "sg:province":"CA",
    "sg:tags":[
        "oil"
    ],
    "wof:name":"Batshon Service Ctr",
    "wof:placetype":"venue"
},
  "geometry": {"coordinates":[-118.151322,33.782596],"type":"Point"}
}