{
  "type": "Feature",
  "properties": {
    "addr:full":"10196 Shangri-la Ave Hesperia CA 92345",
    "addr:postcode":"10196;92345",
    "addr:street":"Shangri-La Ave",
    "iso:country":"US",
    "sg:address":"10196 Shangri-la Ave",
    "sg:city":"Hesperia",
    "sg:classifiers":[
        {
            "category":"Freight",
            "type":"Transportation"
        }
    ],
    "sg:phone":"+1 760 949 5288",
    "sg:postcode":"92345",
    "sg:province":"CA",
    "wof:name":"AFP Transport",
    "wof:placetype":"venue"
},
  "geometry": {"coordinates":[-117.348156,34.435951],"type":"Point"}
}