{
  "type": "Feature",
  "properties": {
    "iso:country":"US",
    "sg:address":"8251 Heil Avenue",
    "sg:city":"Westminster",
    "sg:classifiers":[
        {
            "category":"Social Services",
            "subcategory":"Child Care",
            "type":"Services"
        }
    ],
    "sg:phone":"+1 714 841 7017",
    "sg:postcode":"92683",
    "sg:province":"CA",
    "sg:tags":[
        "day"
    ],
    "wof:name":"Westmont School Day Care",
    "wof:placetype":"venue"
},
  "geometry": {"coordinates":[-117.984435,33.723123],"type":"Point"}
}