{
  "type": "Feature",
  "properties": {
    "iso:country":"US",
    "sg:address":"14801 Comet St",
    "sg:city":"Irvine",
    "sg:classifiers":[
        {
            "category":"Shopping",
            "subcategory":"Clothing, Apparel, & Fashions",
            "type":"Retail Goods"
        }
    ],
    "sg:phone":"+1 949 502 7620",
    "sg:postcode":"92604",
    "sg:province":"CA",
    "sg:tags":[
        "children's",
        "clothing"
    ],
    "sg:website":"www.HauteForTots.com",
    "wof:name":"Haute For Tots Company",
    "wof:placetype":"venue"
},
  "geometry": {"coordinates":[-117.778138,33.692516],"type":"Point"}
}