{
  "type": "Feature",
  "properties": {
    "addr:full":"31735 Riverside Dr Ste K Lake Elsinore CA 92530",
    "addr:housenumber":"31735",
    "addr:postcode":"92530",
    "addr:street":"Riverside Dr Ste K",
    "iso:country":"US",
    "sg:address":"31735 Riverside Dr Ste K",
    "sg:city":"Lake Elsinore",
    "sg:classifiers":[
        {
            "category":"Arts & Performance",
            "subcategory":"Arts Center",
            "type":"Entertainment"
        }
    ],
    "sg:phone":"+1 951 674 4546",
    "sg:postcode":"92530",
    "sg:province":"CA",
    "sg:tags":[
        "performing"
    ],
    "sg:website":"www.composdance.com",
    "wof:name":"COMPOS DANCE STUDIO",
    "wof:placetype":"venue"
},
  "geometry": {"coordinates":[-117.372756,33.677897],"type":"Point"}
}