{
  "type": "Feature",
  "properties": {
    "iso:country":"US",
    "sg:address":"500 E 9th St",
    "sg:city":"Claremont",
    "sg:classifiers":[
        {
            "category":"Government",
            "subcategory":"Office",
            "type":"Public Place"
        }
    ],
    "sg:phone":"+1 909 624 7965",
    "sg:postcode":"91711",
    "sg:province":"CA",
    "sg:tags":[
        "federal",
        "security"
    ],
    "wof:name":"US Army Dept",
    "wof:placetype":"venue"
},
  "geometry": {"coordinates":[-117.704435,34.102588],"type":"Point"}
}