{
  "type": "Feature",
  "properties": {
    "addr:full":"300 E 5th St Perris CA 92570",
    "addr:housenumber":"300",
    "addr:postcode":"92570",
    "addr:street":"E 5Th St",
    "iso:country":"US",
    "sg:address":"300 E 5th St",
    "sg:city":"Perris",
    "sg:classifiers":[
        {
            "category":"Place Of Worship",
            "subcategory":"Church",
            "type":"Public Place"
        },
        {
            "category":"Place Of Worship",
            "type":"Public Place"
        }
    ],
    "sg:phone":"+1 951 657 2798",
    "sg:postcode":"92570",
    "sg:province":"CA",
    "sg:tags":[
        "churches-seventh-day",
        "adventist",
        "christian",
        "churches-advent"
    ],
    "sg:website":"http://www.lmadventist.org",
    "wof:name":"Seventh Day Adventist Church",
    "wof:placetype":"venue"
},
  "geometry": {"coordinates":[-117.222448,33.781326],"type":"Point"}
}