{
  "type": "Feature",
  "properties": {
    "iso:country":"US",
    "sg:address":"340 E Jefferson Blvd",
    "sg:city":"Los Angeles",
    "sg:classifiers":[
        {
            "category":"Wholesale",
            "subcategory":"Apparel",
            "type":"Manufacturing & Wholesale Goods"
        }
    ],
    "sg:phone":"+1 323 232 4500",
    "sg:postcode":"90011",
    "sg:province":"CA",
    "sg:tags":[
        "clothing"
    ],
    "wof:name":"Sns Apparel Inc",
    "wof:placetype":"venue"
},
  "geometry": {"coordinates":[-118.267645,34.016336],"type":"Point"}
}