{
  "type": "Feature",
  "properties": {
    "addr:full":"2421 Foothill Blvd La Crescenta CA 91214",
    "addr:housenumber":"2421",
    "addr:postcode":"91214",
    "addr:street":"Foothill Blvd",
    "iso:country":"US",
    "sg:address":"2421 Foothill Blvd",
    "sg:city":"La Crescenta",
    "sg:classifiers":[
        {
            "category":"Personal",
            "type":"Services"
        }
    ],
    "sg:phone":"+1 818 957 8273",
    "sg:postcode":"91214",
    "sg:province":"CA",
    "sg:tags":[
        "sewing",
        "alteration"
    ],
    "wof:name":"Perfection",
    "wof:placetype":"venue"
},
  "geometry": {"coordinates":[-118.233002,34.219601],"type":"Point"}
}