{
  "type": "Feature",
  "properties": {
    "iso:country":"US",
    "sg:address":"21 Caribe Isle",
    "sg:city":"Novato",
    "sg:classifiers":[
        {
            "category":"Professional",
            "subcategory":"Management & Consulting",
            "type":"Services"
        }
    ],
    "sg:phone":"+1 415 382 9420",
    "sg:postcode":"94949",
    "sg:province":"CA",
    "sg:tags":[
        "consultant"
    ],
    "wof:name":"Creative Management & Engineering Solutions",
    "wof:placetype":"venue"
},
  "geometry": {"coordinates":[-122.520816,38.078245],"type":"Point"}
}