{
  "type": "Feature",
  "properties": {
    "iso:country":"US",
    "sg:address":"10951 W. Pico Blvd. Suite 321",
    "sg:city":"Los Angeles",
    "sg:classifiers":[
        {
            "category":"Health Services",
            "subcategory":"Clinic",
            "type":"Services"
        },
        {
            "category":"Sports & Exercise",
            "subcategory":"Playing Field",
            "type":"Entertainment"
        }
    ],
    "sg:phone":"+1 310 909 8758",
    "sg:postcode":"90064",
    "sg:province":"CA",
    "sg:tags":[
        "medical",
        "instruction",
        "fitness"
    ],
    "sg:website":"lightandlongevity.com",
    "wof:name":"Healing Light and Longevity with Regina Bernstein",
    "wof:placetype":"venue"
},
  "geometry": {"coordinates":[-118.431138,34.039162],"type":"Point"}
}