{
  "type": "Feature",
  "properties": {
    "addr:full":"500 N. Garfield Ave Ste 104 Monterey Park CA 91754",
    "addr:housenumber":"500",
    "addr:postcode":"91754",
    "addr:street":"N. Garfield Ave Ste 104",
    "iso:country":"US",
    "sg:address":"500 N. Garfield Ave Ste 104",
    "sg:city":"Monterey Park",
    "sg:classifiers":[
        {
            "category":"Health Services",
            "subcategory":"Doctor",
            "type":"Services"
        }
    ],
    "sg:phone":"+1 626 280 3781",
    "sg:postcode":"91754",
    "sg:province":"CA",
    "sg:tags":[
        "obstetrician",
        "gynecologist"
    ],
    "wof:name":"Dr. Ben Ha",
    "wof:placetype":"venue"
},
  "geometry": {"coordinates":[-118.122874,34.068402],"type":"Point"}
}