{
  "type": "Feature",
  "properties": {
    "addr:full":"900 Belle Ter Bakersfield CA 93304",
    "addr:housenumber":"900",
    "addr:postcode":"93304",
    "addr:street":"Belle Ter",
    "iso:country":"US",
    "sg:address":"900 Belle Ter",
    "sg:city":"Bakersfield",
    "sg:classifiers":[
        {
            "category":"Education",
            "subcategory":"School",
            "type":"Public Place"
        }
    ],
    "sg:phone":"+1 661 631 5940",
    "sg:postcode":"93304",
    "sg:province":"CA",
    "wof:name":"Bakersfield City Schl Dist Schools ; Jr High Mid Sch",
    "wof:placetype":"venue"
},
  "geometry": {"coordinates":[-119.011848,35.346691],"type":"Point"}
}