{
  "type": "Feature",
  "properties": {
    "addr:full":"2601 E 19th St Signal Hill CA 90755",
    "addr:housenumber":"2601",
    "addr:postcode":"90755",
    "addr:street":"E 19Th St",
    "iso:country":"US",
    "sg:address":"2601 E 19th St",
    "sg:city":"Signal Hill",
    "sg:classifiers":[
        {
            "category":"Real Estate",
            "subcategory":"Real Estate Agent",
            "type":"Services"
        }
    ],
    "sg:phone":"+1 562 494 0127",
    "sg:postcode":"90755",
    "sg:province":"CA",
    "wof:name":"Pacific Garden View Property",
    "wof:placetype":"venue"
},
  "geometry": {"coordinates":[-118.159986,33.791669],"type":"Point"}
}