{
  "type": "Feature",
  "properties": {
    "iso:country":"US",
    "sg:address":"15290 Sycamore Dr",
    "sg:city":"Morgan Hill",
    "sg:classifiers":[
        {
            "category":"Building & Trades",
            "subcategory":"Construction",
            "type":"Services"
        }
    ],
    "sg:phone":"+1 408 779 5173",
    "sg:postcode":"95037",
    "sg:province":"CA",
    "sg:tags":[
        "concrete",
        "contractor"
    ],
    "wof:name":"Sycamore Concrete Construction",
    "wof:placetype":"venue"
},
  "geometry": {"coordinates":[-121.652069,37.094499],"type":"Point"}
}