{
  "type": "Feature",
  "properties": {
    "iso:country":"US",
    "sg:address":"1773 Quiet View Ln",
    "sg:city":"Alpine",
    "sg:classifiers":[
        {
            "category":"Wholesale",
            "subcategory":"Durable Goods & Equipment",
            "type":"Manufacturing & Wholesale Goods"
        }
    ],
    "sg:phone":"+1 619 445 9699",
    "sg:postcode":"91901",
    "sg:province":"CA",
    "wof:name":"Zacks Place of Wholesale",
    "wof:placetype":"venue"
},
  "geometry": {"coordinates":[-116.792164,32.829766],"type":"Point"}
}