{
  "type": "Feature",
  "properties": {
    "addr:full":"1505 E 17th St Ste 109 Santa Ana CA 92705",
    "addr:housenumber":"1505",
    "addr:postcode":"92705",
    "addr:street":"E 17Th St Ste 109",
    "iso:country":"US",
    "sg:address":"1505 E 17th St Ste 109",
    "sg:city":"Santa Ana",
    "sg:classifiers":[
        {
            "category":"Health Services",
            "subcategory":"Doctor",
            "type":"Services"
        }
    ],
    "sg:phone":"+1 714 569 0441",
    "sg:postcode":"92705",
    "sg:province":"CA",
    "wof:name":"Metro-Care Non-Emergency Medical",
    "wof:placetype":"venue"
},
  "geometry": {"coordinates":[-117.84699999999999,33.759998],"type":"Point"}
}