{
  "type": "Feature",
  "properties": {
    "iso:country":"US",
    "sg:address":"1 W California Blvd",
    "sg:city":"Pasadena",
    "sg:classifiers":[
        {
            "category":"Banks & Credit Unions",
            "subcategory":"Bank",
            "type":"Services"
        }
    ],
    "sg:phone":"+1 626 471 3300",
    "sg:postcode":"91105",
    "sg:province":"CA",
    "wof:name":"First City Credit Union",
    "wof:placetype":"venue"
},
  "geometry": {"coordinates":[-118.15100099999999,34.136151],"type":"Point"}
}