{
  "type": "Feature",
  "properties": {
    "iso:country":"US",
    "sg:address":"270 Lafayette Cir",
    "sg:city":"Lafayette",
    "sg:classifiers":[
        {
            "category":"Banks & Credit Unions",
            "subcategory":"Financial Services",
            "type":"Services"
        }
    ],
    "sg:phone":"+1 925 283 8910",
    "sg:postcode":"94549",
    "sg:province":"CA",
    "sg:tags":[
        "trust",
        "investment",
        "real estate"
    ],
    "sg:website":"www.bedfordproperty.com",
    "wof:name":"Bedford Property Investors Inc",
    "wof:placetype":"venue"
},
  "geometry": {"coordinates":[-122.121404,37.890152],"type":"Point"}
}