{
  "type": "Feature",
  "properties": {
    "addr:full":"891 Golden State Blvd Selma CA 93662",
    "addr:housenumber":"891",
    "addr:postcode":"93662",
    "addr:street":"Golden State Blvd",
    "iso:country":"US",
    "sg:address":"891 Golden State Blvd",
    "sg:city":"Selma",
    "sg:classifiers":[
        {
            "category":"Building & Trades",
            "subcategory":"Construction",
            "type":"Services"
        }
    ],
    "sg:phone":"+1 559 896 4879",
    "sg:postcode":"93662",
    "sg:province":"CA",
    "sg:tags":[
        "water",
        "well",
        "drilling"
    ],
    "wof:name":"Seth Abajian Well Drilling",
    "wof:placetype":"venue"
},
  "geometry": {"coordinates":[-119.599313,36.554752],"type":"Point"}
}