{
  "type": "Feature",
  "properties": {
    "iso:country":"US",
    "sg:address":"5959 East St",
    "sg:city":"Anderson",
    "sg:classifiers":[
        {
            "category":"Building & Trades",
            "subcategory":"Equipment Rental",
            "type":"Services"
        }
    ],
    "sg:phone":"+1 530 365 2525",
    "sg:postcode":"96007",
    "sg:province":"CA",
    "sg:tags":[
        "crane"
    ],
    "sg:website":"www.duracrane.com",
    "wof:name":"Dura Crane Inc",
    "wof:placetype":"venue"
},
  "geometry": {"coordinates":[-122.31111,40.461333],"type":"Point"}
}