{
  "type": "Feature",
  "properties": {
    "iso:country":"US",
    "sg:address":"1036 Commerce St",
    "sg:city":"San Marcos",
    "sg:classifiers":[
        {
            "category":"Social Services",
            "type":"Services"
        }
    ],
    "sg:phone":"+1 760 510 9623",
    "sg:postcode":"92078",
    "sg:province":"CA",
    "sg:tags":[
        "organization",
        "welfare"
    ],
    "wof:name":"A Better Way",
    "wof:placetype":"venue"
},
  "geometry": {"coordinates":[-117.187647,33.137575],"type":"Point"}
}