{
  "type": "Feature",
  "properties": {
    "addr:full":"1590 Wilson Ln Windsor CA 95492",
    "addr:housenumber":"1590",
    "addr:postcode":"95492",
    "addr:street":"Wilson Ln",
    "iso:country":"US",
    "sg:address":"1590 Wilson Ln",
    "sg:city":"Windsor",
    "sg:classifiers":[
        {
            "category":"Sports & Exercise",
            "subcategory":"Golf",
            "type":"Entertainment"
        }
    ],
    "sg:phone":"+1 707 838 0848",
    "sg:postcode":"95492",
    "sg:province":"CA",
    "sg:tags":[
        "course"
    ],
    "wof:name":"Windsor Golf Club",
    "wof:placetype":"venue"
},
  "geometry": {"coordinates":[-122.815608,38.532682],"type":"Point"}
}