{
  "type": "Feature",
  "properties": {
    "addr:full":"40045 95th St W Leona Valley CA 93551",
    "addr:housenumber":"40045",
    "addr:postcode":"93551",
    "addr:street":"95Th St W Leona Valley",
    "iso:country":"US",
    "sg:address":"40045 95th St W",
    "sg:city":"Leona Valley",
    "sg:classifiers":[
        {
            "category":"Retail",
            "subcategory":"Laundry & Dry Cleaning",
            "type":"Services"
        }
    ],
    "sg:phone":"+1 661 270 1526",
    "sg:postcode":"93551",
    "sg:province":"CA",
    "sg:tags":[
        "cleaners",
        "rug",
        "carpet"
    ],
    "wof:name":"Horizon Carpet Care",
    "wof:placetype":"venue"
},
  "geometry": {"coordinates":[-118.29767099999999,34.6138],"type":"Point"}
}