{
  "type": "Feature",
  "properties": {
    "addr:full":"3133 N San Fernando Rd Los Angeles CA 90065",
    "addr:housenumber":"3133",
    "addr:postcode":"90065",
    "addr:street":"N San Fernando Rd",
    "iso:country":"US",
    "sg:address":"3133 N San Fernando Rd",
    "sg:city":"Los Angeles",
    "sg:classifiers":[
        {
            "category":"Shopping",
            "subcategory":"Gifts & Souvenirs",
            "type":"Retail Goods"
        }
    ],
    "sg:phone":"+1 323 344 0477",
    "sg:postcode":"90065",
    "sg:province":"CA",
    "sg:tags":[
        "shop"
    ],
    "wof:name":"Porcelana Gift Shop",
    "wof:placetype":"venue"
},
  "geometry": {"coordinates":[-118.25028,34.119436],"type":"Point"}
}