{
  "type": "Feature",
  "properties": {
    "iso:country":"US",
    "sg:address":"1065 W Sunset Blvd",
    "sg:city":"Los Angeles",
    "sg:classifiers":[
        {
            "category":"Shopping",
            "subcategory":"Florist",
            "type":"Retail Goods"
        }
    ],
    "sg:phone":"+1 213 481 8216",
    "sg:postcode":"90012",
    "sg:province":"CA",
    "wof:name":"Cathay Florist",
    "wof:placetype":"venue"
},
  "geometry": {"coordinates":[-118.248603,34.064648],"type":"Point"}
}