{
  "type": "Feature",
  "properties": {
    "iso:country":"US",
    "sg:address":"1915 W 1st St",
    "sg:city":"Santa Ana",
    "sg:classifiers":[
        {
            "category":"Shopping",
            "subcategory":"Clothing, Apparel, & Fashions",
            "type":"Retail Goods"
        }
    ],
    "sg:phone":"+1 714 953 9080",
    "sg:postcode":"92703",
    "sg:province":"CA",
    "wof:name":"Diseno Enoe",
    "wof:placetype":"venue"
},
  "geometry": {"coordinates":[-117.895872,33.745429],"type":"Point"}
}