{
  "type": "Feature",
  "properties": {
    "addr:full":"12039 Hertz Ave Moorpark CA 93021",
    "addr:postcode":"12039;ca 93021",
    "addr:street":"Hertz Ave",
    "iso:country":"US",
    "sg:address":"12039 Hertz Ave",
    "sg:city":"Moorpark",
    "sg:classifiers":[
        {
            "category":"Organizations",
            "subcategory":"Religious Organization",
            "type":"Services"
        }
    ],
    "sg:phone":"+1 805 529 5577",
    "sg:postcode":"93021",
    "sg:province":"CA",
    "sg:tags":[
        "church"
    ],
    "sg:website":"www.gbcmpk.org",
    "wof:name":"Grace Bible Church",
    "wof:placetype":"venue"
},
  "geometry": {"coordinates":[-118.894398,34.281721],"type":"Point"}
}