{
  "type": "Feature",
  "properties": {
    "iso:country":"US",
    "sg:address":"1400 Needles Hwy",
    "sg:city":"Needles",
    "sg:classifiers":[
        {
            "category":"Social Services",
            "type":"Services"
        }
    ],
    "sg:phone":"+1 760 326 3047",
    "sg:postcode":"92363",
    "sg:province":"CA",
    "sg:tags":[
        "crisis",
        "intervention"
    ],
    "wof:name":"Fort Mojave Indian Tribe",
    "wof:placetype":"venue"
},
  "geometry": {"coordinates":[-114.6152,34.848459],"type":"Point"}
}