{
  "type": "Feature",
  "properties": {
    "addr:full":"1582 E 21st St Los Angeles CA 90011",
    "addr:housenumber":"1582",
    "addr:postcode":"90011",
    "addr:street":"E 21St St",
    "iso:country":"US",
    "sg:address":"1582 E 21st St",
    "sg:city":"Los Angeles",
    "sg:classifiers":[
        {
            "category":"Freight",
            "type":"Transportation"
        }
    ],
    "sg:phone":"+1 213 746 4408",
    "sg:postcode":"90011",
    "sg:province":"CA",
    "sg:tags":[
        "distance",
        "long"
    ],
    "wof:name":"Transportes Miron",
    "wof:placetype":"venue"
},
  "geometry": {"coordinates":[-118.24664799999999,34.019382],"type":"Point"}
}