{
  "type": "Feature",
  "properties": {
    "iso:country":"US",
    "sg:address":"6700 Fallbrook Ave",
    "sg:city":"West Hills",
    "sg:classifiers":[
        {
            "category":"Health Services",
            "subcategory":"Clinic",
            "type":"Services"
        }
    ],
    "sg:phone":"+1 818 999 6164",
    "sg:postcode":"91307",
    "sg:province":"CA",
    "sg:tags":[
        "counseling",
        "mental"
    ],
    "wof:name":"Absey Patricia MA Mfcc",
    "wof:placetype":"venue"
},
  "geometry": {"coordinates":[-118.623001,34.1922],"type":"Point"}
}