{
  "type": "Feature",
  "properties": {
    "iso:country":"US",
    "sg:address":"6387 Riverbank Cir",
    "sg:city":"Stockton",
    "sg:classifiers":[
        {
            "category":"Recreation",
            "subcategory":"Amusement Park",
            "type":"Entertainment"
        },
        {
            "category":"Recreation",
            "subcategory":"Picnic Area",
            "type":"Entertainment"
        }
    ],
    "sg:phone":"+1 209 948 1997",
    "sg:postcode":"95219",
    "sg:province":"CA",
    "sg:tags":[
        "equipment",
        "ride",
        "place",
        "arcade"
    ],
    "wof:name":"Catch All Baseball",
    "wof:placetype":"venue"
},
  "geometry": {"coordinates":[-121.363345,37.991095],"type":"Point"}
}