{
  "type": "Feature",
  "properties": {
    "addr:full":"5425 Impala Dr Paso Robles CA 93446",
    "addr:housenumber":"5425",
    "addr:postcode":"93446",
    "addr:street":"Impala Dr",
    "iso:country":"US",
    "sg:address":"5425 Impala Dr",
    "sg:city":"Paso Robles",
    "sg:classifiers":[
        {
            "category":"Retail",
            "subcategory":"Laundry & Dry Cleaning",
            "type":"Services"
        }
    ],
    "sg:phone":"+1 805 237 1159",
    "sg:postcode":"93446",
    "sg:province":"CA",
    "sg:tags":[
        "cleaners",
        "rug",
        "carpet"
    ],
    "wof:name":"Rapid Response Carpet Care",
    "wof:placetype":"venue"
},
  "geometry": {"coordinates":[-120.53147199999999,35.629093],"type":"Point"}
}