{
  "type": "Feature",
  "properties": {
    "iso:country":"US",
    "sg:address":"16206 Devonshire St",
    "sg:city":"Granada Hills",
    "sg:classifiers":[
        {
            "category":"Wholesale",
            "subcategory":"Medical Equipment & Supplies",
            "type":"Manufacturing & Wholesale Goods"
        }
    ],
    "sg:phone":"+1 818 893 2333",
    "sg:postcode":"91344",
    "sg:province":"CA",
    "wof:name":"Coach Med Care Equipment Inc",
    "wof:placetype":"venue"
},
  "geometry": {"coordinates":[-118.48905,34.257357],"type":"Point"}
}