{
  "type": "Feature",
  "properties": {
    "addr:full":"3804 Drakeshire Dr Modesto CA 95356",
    "addr:housenumber":"3804",
    "addr:postcode":"ca 95356",
    "addr:street":"Drakeshire Dr",
    "iso:country":"US",
    "sg:address":"3804 Drakeshire Dr",
    "sg:city":"Modesto",
    "sg:classifiers":[
        {
            "category":"Manufacturing",
            "subcategory":"Electronics",
            "type":"Manufacturing & Wholesale Goods"
        }
    ],
    "sg:phone":"+1 209 614 5381",
    "sg:postcode":"95356",
    "sg:province":"CA",
    "sg:tags":[
        "equipment",
        "mfg",
        "home"
    ],
    "wof:name":"Wet Box Marine LLC",
    "wof:placetype":"venue"
},
  "geometry": {"coordinates":[-120.98107,37.693999],"type":"Point"}
}