{
  "type": "Feature",
  "properties": {
    "addr:full":"3845 Stockdale Hwy Bakersfield CA 93309",
    "addr:housenumber":"3845",
    "addr:postcode":"93309",
    "addr:street":"Stockdale Hwy",
    "iso:country":"US",
    "sg:address":"3845 Stockdale Hwy",
    "sg:city":"Bakersfield",
    "sg:classifiers":[
        {
            "category":"Professional",
            "subcategory":"Management & Consulting",
            "type":"Services"
        }
    ],
    "sg:phone":"+1 661 396 8426",
    "sg:postcode":"93309",
    "sg:province":"CA",
    "sg:tags":[
        "consultant"
    ],
    "wof:name":"EDS Consultant Group",
    "wof:placetype":"venue"
},
  "geometry": {"coordinates":[-119.04682200000001,35.354099],"type":"Point"}
}