{
  "type": "Feature",
  "properties": {
    "iso:country":"US",
    "sg:address":"2370 Watson Court, Suite 100",
    "sg:city":"Palo Alto",
    "sg:classifiers":[
        {
            "category":"Professional",
            "subcategory":"Computer Services",
            "type":"Services"
        }
    ],
    "sg:phone":"+1 650 618 6100",
    "sg:postcode":"94303",
    "sg:province":"CA",
    "sg:tags":[
        "sop",
        "spreadsheet-collaboration",
        "database",
        "spreadsheet-change-management"
    ],
    "sg:website":"http://www.boardwalktech.com",
    "wof:name":"Boardwalktech",
    "wof:placetype":"venue"
},
  "geometry": {"coordinates":[-122.119876,37.448296],"type":"Point"}
}