{
  "type": "Feature",
  "properties": {
    "addr:full":"705 Lincoln Blvd Venice CA 90291",
    "addr:housenumber":"705",
    "addr:postcode":"90291",
    "addr:street":"Lincoln Blvd",
    "iso:country":"US",
    "sg:address":"705 Lincoln Blvd",
    "sg:city":"Venice",
    "sg:classifiers":[
        {
            "category":"Restaurant",
            "type":"Food & Drink"
        }
    ],
    "sg:phone":"+1 310 450 4030",
    "sg:postcode":"90291",
    "sg:province":"CA",
    "sg:tags":[
        "eating"
    ],
    "wof:name":"Pizza Man",
    "wof:placetype":"venue"
},
  "geometry": {"coordinates":[-118.464094,33.999446],"type":"Point"}
}