{
  "type": "Feature",
  "properties": {
    "iso:country":"US",
    "sg:address":"4690 Eagle Rock Blvd",
    "sg:city":"Los Angeles",
    "sg:classifiers":[
        {
            "category":"Arts & Performance",
            "subcategory":"Art Gallery",
            "type":"Entertainment"
        }
    ],
    "sg:phone":"+1 818 203 6027",
    "sg:postcode":"90041",
    "sg:province":"CA",
    "sg:website":"thelandofoddgallery.com/",
    "wof:name":"The Land Of Odd Gallery",
    "wof:placetype":"venue"
},
  "geometry": {"coordinates":[-118.216415,34.129879],"type":"Point"}
}