{
  "type": "Feature",
  "properties": {
    "addr:full":"8500 Eastside Rd Healdsburg CA 95448",
    "addr:housenumber":"8500",
    "addr:postcode":"95448",
    "addr:street":"Eastside Rd",
    "iso:country":"US",
    "sg:address":"8500 Eastside Rd",
    "sg:city":"Healdsburg",
    "sg:classifiers":[
        {
            "category":"Farming",
            "subcategory":"Vineyard",
            "type":"Manufacturing & Wholesale Goods"
        }
    ],
    "sg:phone":"+1 707 838 6608",
    "sg:postcode":"95448",
    "sg:province":"CA",
    "sg:tags":[
        "grape"
    ],
    "wof:name":"Calplans Partners",
    "wof:placetype":"venue"
},
  "geometry": {"coordinates":[-122.847797,38.524357],"type":"Point"}
}