{
  "type": "Feature",
  "properties": {
    "addr:full":"4388 W Shaw Ave Fresno CA 93722",
    "addr:housenumber":"4388",
    "addr:postcode":"93722",
    "addr:street":"W Shaw Ave",
    "iso:country":"US",
    "sg:address":"4388 W Shaw Ave",
    "sg:city":"Fresno",
    "sg:classifiers":[
        {
            "category":"Restaurant",
            "type":"Food & Drink"
        }
    ],
    "sg:phone":"+1 559 276 2244",
    "sg:postcode":"93722",
    "sg:province":"CA",
    "wof:name":"Chubby's Diner",
    "wof:placetype":"venue"
},
  "geometry": {"coordinates":[-119.870261,36.808327],"type":"Point"}
}