{
  "type": "Feature",
  "properties": {
    "addr:full":"7847 Florence Ave Downey CA 90240",
    "addr:housenumber":"7847",
    "addr:postcode":"90240",
    "addr:street":"Florence Ave",
    "iso:country":"US",
    "sg:address":"7847 Florence Ave",
    "sg:city":"Downey",
    "sg:classifiers":[
        {
            "category":"Banks & Credit Unions",
            "subcategory":"Bank",
            "type":"Services"
        }
    ],
    "sg:phone":"+1 562 776 5714",
    "sg:postcode":"90240",
    "sg:province":"CA",
    "sg:tags":[
        "loan",
        "real estate"
    ],
    "wof:name":"Barrington Capital",
    "wof:placetype":"venue"
},
  "geometry": {"coordinates":[-118.131865,33.954606],"type":"Point"}
}