{
  "type": "Feature",
  "properties": {
    "addr:full":"10385 Rue Mont Grenoble San Diego CA 92131",
    "addr:housenumber":"10385",
    "addr:postcode":"92131",
    "addr:street":"Rue Mont Grenoble",
    "iso:country":"US",
    "sg:address":"10385 Rue Mont Grenoble",
    "sg:city":"San Diego",
    "sg:classifiers":[
        {
            "category":"Wholesale",
            "subcategory":"Furniture",
            "type":"Manufacturing & Wholesale Goods"
        }
    ],
    "sg:phone":"+1 858 566 4103",
    "sg:postcode":"92131",
    "sg:province":"CA",
    "wof:name":"Ronald G McGrath",
    "wof:placetype":"venue"
},
  "geometry": {"coordinates":[-117.073504,32.906658],"type":"Point"}
}