{
  "type": "Feature",
  "properties": {
    "addr:full":"685 E Grand Ave Porterville CA 93257",
    "addr:housenumber":"685",
    "addr:postcode":"93257",
    "addr:street":"E Grand Ave",
    "iso:country":"US",
    "sg:address":"685 E Grand Ave",
    "sg:city":"Porterville",
    "sg:classifiers":[
        {
            "category":"Wholesale",
            "subcategory":"Vending Machines",
            "type":"Manufacturing & Wholesale Goods"
        }
    ],
    "sg:phone":"+1 559 784 4788",
    "sg:postcode":"93257",
    "sg:province":"CA",
    "sg:tags":[
        "operator"
    ],
    "wof:name":"All American Vending",
    "wof:placetype":"venue"
},
  "geometry": {"coordinates":[-119.002476,36.076481],"type":"Point"}
}