{
  "type": "Feature",
  "properties": {
    "addr:full":"7592 Park Ave Garden Grove CA 92841",
    "addr:housenumber":"7592",
    "addr:postcode":"92841",
    "addr:street":"Park Ave",
    "iso:country":"US",
    "sg:address":"7592 Park Ave",
    "sg:city":"Garden Grove",
    "sg:classifiers":[
        {
            "category":"Manufacturing",
            "subcategory":"Signs",
            "type":"Manufacturing & Wholesale Goods"
        }
    ],
    "sg:phone":"+1 714 898 4270",
    "sg:postcode":"92841",
    "sg:province":"CA",
    "sg:tags":[
        "advertising",
        "specialty"
    ],
    "wof:name":"ISID Inc",
    "wof:placetype":"venue"
},
  "geometry": {"coordinates":[-118.000266,33.776817],"type":"Point"}
}