{
  "type": "Feature",
  "properties": {
    "iso:country":"US",
    "sg:address":"1420 River Park Dr Ste 100",
    "sg:city":"Sacramento",
    "sg:classifiers":[
        {
            "category":"Professional",
            "subcategory":"Lawyer & Legal Services",
            "type":"Services"
        }
    ],
    "sg:phone":"+1 916 646 3841",
    "sg:postcode":"95815",
    "sg:province":"CA",
    "sg:website":"www.norcaldui.com",
    "wof:name":"Phillips Paul Nathan Attorney At Law",
    "wof:placetype":"venue"
},
  "geometry": {"coordinates":[-121.43913999999999,38.597287],"type":"Point"}
}