{
  "type": "Feature",
  "properties": {
    "iso:country":"US",
    "sg:address":"870 Market St",
    "sg:city":"San Francisco",
    "sg:classifiers":[
        {
            "category":"Organizations",
            "subcategory":"Professional Association",
            "type":"Services"
        }
    ],
    "sg:phone":"+1 415 362 2500",
    "sg:postcode":"94102",
    "sg:province":"CA",
    "sg:website":"www.marketstreet.citysearch.com",
    "wof:name":"Market Street Development Inc",
    "wof:placetype":"venue"
},
  "geometry": {"coordinates":[-122.406645,37.785415],"type":"Point"}
}