{
  "type": "Feature",
  "properties": {
    "addr:full":"1801 Urban Retreat Ln Cool CA 95614",
    "addr:housenumber":"1801",
    "addr:postcode":"95614",
    "addr:street":"Urban Retreat Ln",
    "iso:country":"US",
    "sg:address":"1801 Urban Retreat Ln",
    "sg:city":"Cool",
    "sg:classifiers":[
        {
            "category":"Manufacturing",
            "subcategory":"Retail Goods",
            "type":"Manufacturing & Wholesale Goods"
        }
    ],
    "sg:phone":"+1 530 889 9307",
    "sg:postcode":"95614",
    "sg:province":"CA",
    "sg:tags":[
        "product",
        "mfg"
    ],
    "wof:name":"Stobie Mfg",
    "wof:placetype":"venue"
},
  "geometry": {"coordinates":[-120.985156,38.88191],"type":"Point"}
}