{
  "type": "Feature",
  "properties": {
    "addr:full":"19242 Nashville St Northridge CA 91326",
    "addr:housenumber":"19242",
    "addr:postcode":"91326",
    "addr:street":"Nashville St",
    "iso:country":"US",
    "sg:address":"19242 Nashville St",
    "sg:city":"Northridge",
    "sg:classifiers":[
        {
            "category":"Wholesale",
            "subcategory":"Medical Equipment & Supplies",
            "type":"Manufacturing & Wholesale Goods"
        }
    ],
    "sg:phone":"+1 818 576 4700",
    "sg:postcode":"91326",
    "sg:province":"CA",
    "wof:name":"Mini Med Inc",
    "wof:placetype":"venue"
},
  "geometry": {"coordinates":[-118.552699,34.269186],"type":"Point"}
}