{
  "type": "Feature",
  "properties": {
    "addr:full":"1246 East St Redding CA 96001",
    "addr:housenumber":"1246",
    "addr:postcode":"96001",
    "addr:street":"East St",
    "iso:country":"US",
    "sg:address":"1246 East St",
    "sg:city":"Redding",
    "sg:classifiers":[
        {
            "category":"Social Services",
            "type":"Services"
        }
    ],
    "sg:phone":"+1 530 242 9234",
    "sg:postcode":"96001",
    "sg:province":"CA",
    "sg:tags":[
        "counselor",
        "marriage",
        "family"
    ],
    "wof:name":"Linda Lafferty",
    "wof:placetype":"venue"
},
  "geometry": {"coordinates":[-122.38915799999999,40.587005],"type":"Point"}
}