{
  "type": "Feature",
  "properties": {
    "addr:full":"14640 Halldale Ave Gardena CA 90247",
    "addr:housenumber":"14640",
    "addr:postcode":"90247",
    "addr:street":"Halldale Ave",
    "iso:country":"US",
    "sg:address":"14640 Halldale Ave",
    "sg:city":"Gardena",
    "sg:classifiers":[
        {
            "category":"Professional",
            "type":"Services"
        }
    ],
    "sg:phone":"+1 310 515 9891",
    "sg:postcode":"90247",
    "sg:province":"CA",
    "wof:name":"Kirks",
    "wof:placetype":"venue"
},
  "geometry": {"coordinates":[-118.302503,33.898662],"type":"Point"}
}