{
  "type": "Feature",
  "properties": {
    "addr:full":"3650 Clairemont Dr San Diego CA 92117",
    "addr:housenumber":"3650",
    "addr:postcode":"92117",
    "addr:street":"Clairemont Dr",
    "iso:country":"US",
    "sg:address":"3650 Clairemont Dr",
    "sg:city":"San Diego",
    "sg:classifiers":[
        {
            "category":"Health Services",
            "subcategory":"Medical Lab",
            "type":"Services"
        }
    ],
    "sg:phone":"+1 858 270 1218",
    "sg:postcode":"92117",
    "sg:province":"CA",
    "sg:tags":[
        "laboratory"
    ],
    "wof:name":"Andino Orthodontic Lab",
    "wof:placetype":"venue"
},
  "geometry": {"coordinates":[-117.20099399999999,32.805902],"type":"Point"}
}