{
  "type": "Feature",
  "properties": {
    "addr:full":"770 W Imperial Ave El Segundo CA 90245",
    "addr:housenumber":"770",
    "addr:postcode":"90245",
    "addr:street":"W Imperial Ave",
    "iso:country":"US",
    "sg:address":"770 W Imperial Ave",
    "sg:city":"El Segundo",
    "sg:classifiers":[
        {
            "category":"Real Estate",
            "subcategory":"Real Estate Agent",
            "type":"Services"
        }
    ],
    "sg:phone":"+1 310 322 8992",
    "sg:postcode":"90245",
    "sg:province":"CA",
    "wof:name":"C R Pollard & Company",
    "wof:placetype":"venue"
},
  "geometry": {"coordinates":[-118.426423,33.93075],"type":"Point"}
}