{
  "type": "Feature",
  "properties": {
    "iso:country":"US",
    "sg:address":"25030 W Ave Stanford",
    "sg:city":"Santa Clarita",
    "sg:classifiers":[
        {
            "category":"Professional",
            "subcategory":"Business Services",
            "type":"Services"
        }
    ],
    "sg:phone":"+1 661 775 9273",
    "sg:postcode":"91355",
    "sg:province":"CA",
    "wof:name":"Rastiff Business Ventures",
    "wof:placetype":"venue"
},
  "geometry": {"coordinates":[-118.576239,34.435824],"type":"Point"}
}