{
  "type": "Feature",
  "properties": {
    "iso:country":"US",
    "sg:address":"3735 Columbus St",
    "sg:city":"Bakersfield",
    "sg:classifiers":[
        {
            "category":"Personal",
            "subcategory":"Barber",
            "type":"Services"
        }
    ],
    "sg:phone":"+1 661 871 4452",
    "sg:postcode":"93306",
    "sg:province":"CA",
    "wof:name":"His Barber Shop",
    "wof:placetype":"venue"
},
  "geometry": {"coordinates":[-118.952046,35.399188],"type":"Point"}
}