{
  "type": "Feature",
  "properties": {
    "iso:country":"US",
    "sg:address":"515 Michigan Blvd",
    "sg:city":"West Sacramento",
    "sg:classifiers":[
        {
            "category":"Education",
            "subcategory":"Dance Studio",
            "type":"Public Place"
        }
    ],
    "sg:phone":"+1 916 371 5061",
    "sg:postcode":"95691",
    "sg:province":"CA",
    "sg:tags":[
        "instruction",
        "dancing"
    ],
    "wof:name":"Dance Factory",
    "wof:placetype":"venue"
},
  "geometry": {"coordinates":[-121.527744,38.583733],"type":"Point"}
}