{
  "type": "Feature",
  "properties": {
    "addr:full":"981 Fremont St Santa Clara CA 95050",
    "addr:housenumber":"981",
    "addr:postcode":"95050",
    "addr:street":"Fremont St",
    "iso:country":"US",
    "sg:address":"981 Fremont St",
    "sg:city":"Santa Clara",
    "sg:classifiers":[
        {
            "category":"Professional",
            "subcategory":"Lawyer & Legal Services",
            "type":"Services"
        }
    ],
    "sg:phone":"+1 408 984 8555",
    "sg:postcode":"95050",
    "sg:province":"CA",
    "sg:website":"www.kimandjohnsoncriminallaw.com/",
    "wof:name":"Kim & Johnson Law Offices",
    "wof:placetype":"venue"
},
  "geometry": {"coordinates":[-121.94499999999999,37.3517],"type":"Point"}
}