{
  "type": "Feature",
  "properties": {
    "addr:full":"2727 W Olympic Blvd Los Angeles CA 90006",
    "addr:housenumber":"2727",
    "addr:postcode":"90006",
    "addr:street":"W Olympic Blvd",
    "iso:country":"US",
    "sg:address":"2727 W Olympic Blvd",
    "sg:city":"Los Angeles",
    "sg:classifiers":[
        {
            "category":"Wholesale",
            "subcategory":"Medical Equipment & Supplies",
            "type":"Manufacturing & Wholesale Goods"
        }
    ],
    "sg:phone":"+1 213 385 4560",
    "sg:postcode":"90006",
    "sg:province":"CA",
    "wof:name":"Creation Medical",
    "wof:placetype":"venue"
},
  "geometry": {"coordinates":[-118.29361900000001,34.05273],"type":"Point"}
}