{
  "type": "Feature",
  "properties": {
    "iso:country":"US",
    "sg:address":"22200 Main St Ste F",
    "sg:city":"Carson",
    "sg:classifiers":[
        {
            "category":"Bakery",
            "type":"Food & Drink"
        }
    ],
    "sg:phone":"+1 310 835 2193",
    "sg:postcode":"90745",
    "sg:province":"CA",
    "wof:name":"Casa Filipina Restaurant & Bake Shop Inc",
    "wof:placetype":"venue"
},
  "geometry": {"coordinates":[-118.27600099999999,33.825401],"type":"Point"}
}