{
  "type": "Feature",
  "properties": {
    "addr:full":"150 N Mill Creek Rd Quincy CA 95971",
    "addr:housenumber":"150",
    "addr:postcode":"95971",
    "addr:street":"N Mill Creek Rd",
    "iso:country":"US",
    "sg:address":"150 N Mill Creek Rd",
    "sg:city":"Quincy",
    "sg:classifiers":[
        {
            "category":"Wholesale",
            "subcategory":"Auto Parts",
            "type":"Manufacturing & Wholesale Goods"
        }
    ],
    "sg:phone":"+1 530 283 3432",
    "sg:postcode":"95971",
    "sg:province":"CA",
    "sg:tags":[
        "automobile"
    ],
    "wof:name":"Quincy Dismantlers",
    "wof:placetype":"venue"
},
  "geometry": {"coordinates":[-120.904903,39.938473],"type":"Point"}
}