{
  "type": "Feature",
  "properties": {
    "addr:full":"5148 W Washington Blvd Los Angeles CA 90016",
    "addr:housenumber":"5148",
    "addr:postcode":"90016",
    "addr:street":"W Washington Blvd",
    "iso:country":"US",
    "sg:address":"5148 W Washington Blvd",
    "sg:city":"Los Angeles",
    "sg:classifiers":[
        {
            "category":"Wholesale",
            "subcategory":"Plants",
            "type":"Manufacturing & Wholesale Goods"
        }
    ],
    "sg:phone":"+1 310 792 7706",
    "sg:postcode":"90016",
    "sg:province":"CA",
    "sg:tags":[
        "supply"
    ],
    "wof:name":"Craft House",
    "wof:placetype":"venue"
},
  "geometry": {"coordinates":[-118.352176,34.041033],"type":"Point"}
}