{
  "type": "Feature",
  "properties": {
    "iso:country":"US",
    "sg:address":"1371 Lincoln Ave",
    "sg:city":"Calistoga",
    "sg:classifiers":[
        {
            "category":"Winery",
            "type":"Food & Drink"
        }
    ],
    "sg:phone":"+1 707 942 7422",
    "sg:postcode":"94515",
    "sg:province":"CA",
    "sg:website":"www.calistogacellars.com/",
    "wof:name":"Calistoga Cellars",
    "wof:placetype":"venue"
},
  "geometry": {"coordinates":[-122.578998,38.57848],"type":"Point"}
}