{
  "type": "Feature",
  "properties": {
    "addr:full":"2524 E 54th St Huntington Park CA 90255",
    "addr:housenumber":"2524",
    "addr:postcode":"90255",
    "addr:street":"E 54Th St;Park",
    "iso:country":"US",
    "sg:address":"2524 E 54th St",
    "sg:city":"Huntington Park",
    "sg:classifiers":[
        {
            "category":"Manufacturing",
            "subcategory":"Tools & Machinery",
            "type":"Manufacturing & Wholesale Goods"
        }
    ],
    "sg:phone":"+1 323 582 3877",
    "sg:postcode":"90255",
    "sg:province":"CA",
    "sg:tags":[
        "die",
        "maker"
    ],
    "wof:name":"Real Color Dye House",
    "wof:placetype":"venue"
},
  "geometry": {"coordinates":[-118.22643100000001,33.993778],"type":"Point"}
}