{
  "type": "Feature",
  "properties": {
    "addr:full":"1121 Striker Ave Ste 130 Sacramento CA 95834",
    "addr:housenumber":"1121",
    "addr:postcode":"95834",
    "addr:street":"Striker Ave Ste 130",
    "iso:country":"US",
    "sg:address":"1121 Striker Ave Ste 130",
    "sg:city":"Sacramento",
    "sg:classifiers":[
        {
            "category":"Wholesale",
            "subcategory":"Machinery & Supplies",
            "type":"Manufacturing & Wholesale Goods"
        }
    ],
    "sg:phone":"+1 916 928 6101",
    "sg:postcode":"95834",
    "sg:province":"CA",
    "sg:tags":[
        "generator"
    ],
    "wof:name":"Aee Solar, Inc.",
    "wof:placetype":"venue"
},
  "geometry": {"coordinates":[-121.485922,38.651043],"type":"Point"}
}