{
  "type": "Feature",
  "properties": {
    "addr:full":"3813 Macdonald Ave Richmond CA 94805",
    "addr:housenumber":"3813",
    "addr:postcode":"94805",
    "addr:street":"Macdonald Ave",
    "iso:country":"US",
    "sg:address":"3813 Macdonald Ave",
    "sg:city":"Richmond",
    "sg:classifiers":[
        {
            "category":"Shopping",
            "subcategory":"Books",
            "type":"Retail Goods"
        }
    ],
    "sg:phone":"+1 510 236 3055",
    "sg:postcode":"94805",
    "sg:province":"CA",
    "sg:tags":[
        "bible",
        "store"
    ],
    "wof:name":"Nell's Bible Book Store",
    "wof:placetype":"venue"
},
  "geometry": {"coordinates":[-122.33321100000001,37.933694],"type":"Point"}
}