{
  "type": "Feature",
  "properties": {
    "addr:full":"10055 Slater Ave Fountain Valley CA 92708",
    "addr:housenumber":"10055",
    "addr:postcode":"92708",
    "addr:street":"Slater Ave",
    "iso:country":"US",
    "sg:address":"10055 Slater Ave",
    "sg:city":"Fountain Valley",
    "sg:classifiers":[
        {
            "category":"Banks & Credit Unions",
            "subcategory":"Financial Services",
            "type":"Services"
        }
    ],
    "sg:phone":"+1 714 698 4288",
    "sg:postcode":"92708",
    "sg:province":"CA",
    "sg:tags":[
        "broker",
        "mortgage"
    ],
    "wof:name":"Boardwalk Financial Group",
    "wof:placetype":"venue"
},
  "geometry": {"coordinates":[-117.95371,33.709217],"type":"Point"}
}