{
  "type": "Feature",
  "properties": {
    "addr:full":"404 S Figueroa St Los Angeles CA 90071",
    "addr:housenumber":"404",
    "addr:postcode":"90071",
    "addr:street":"S Figueroa St",
    "iso:country":"US",
    "sg:address":"404 S Figueroa St",
    "sg:city":"Los Angeles",
    "sg:classifiers":[
        {
            "category":"Personal",
            "subcategory":"Beauty Salon",
            "type":"Services"
        }
    ],
    "sg:phone":"+1 213 324 8851",
    "sg:postcode":"90071",
    "sg:province":"CA",
    "wof:name":"Hair Care By Marina",
    "wof:placetype":"venue"
},
  "geometry": {"coordinates":[-118.257158,34.052265],"type":"Point"}
}