{
  "type": "Feature",
  "properties": {
    "addr:full":"846 W Palmdale Blvd Palmdale CA 93551",
    "addr:housenumber":"846",
    "addr:postcode":"ca 93551",
    "addr:street":"W Palmdale Blvd",
    "iso:country":"US",
    "sg:address":"846 W Palmdale Blvd",
    "sg:city":"Palmdale",
    "sg:classifiers":[
        {
            "category":"Insurance",
            "subcategory":"Insurance Agent",
            "type":"Services"
        }
    ],
    "sg:phone":"+1 661 538 1100",
    "sg:postcode":"93551",
    "sg:province":"CA",
    "wof:name":"American Wizzard North Ins Svc",
    "wof:placetype":"venue"
},
  "geometry": {"coordinates":[-118.14646999999999,34.58694],"type":"Point"}
}