{
  "type": "Feature",
  "properties": {
    "addr:full":"7688 Indiana Ave Riverside CA 92504",
    "addr:housenumber":"7688",
    "addr:postcode":"92504",
    "addr:street":"Indiana Ave",
    "iso:country":"US",
    "sg:address":"7688 Indiana Ave",
    "sg:city":"Riverside",
    "sg:classifiers":[
        {
            "category":"Autos & Motor Vehicles",
            "subcategory":"Motorcycle Sales",
            "type":"Retail Goods"
        }
    ],
    "sg:phone":"+1 951 785 0100",
    "sg:postcode":"92504",
    "sg:province":"CA",
    "sg:tags":[
        "scooter"
    ],
    "sg:website":"www.skipfordyce.com",
    "wof:name":"Skip Fordyce Motorcycle Ctr",
    "wof:placetype":"venue"
},
  "geometry": {"coordinates":[-117.407385,33.933405],"type":"Point"}
}