{
  "type": "Feature",
  "properties": {
    "iso:country":"US",
    "sg:address":"2226 Sacramento St",
    "sg:city":"Berkeley",
    "sg:classifiers":[
        {
            "category":"Professional",
            "subcategory":"Management & Consulting",
            "type":"Services"
        }
    ],
    "sg:phone":"+1 301 646 3231",
    "sg:postcode":"94702",
    "sg:province":"CA",
    "sg:tags":[
        "consultant",
        "educational"
    ],
    "wof:name":"The Shadow Puppet Workshop",
    "wof:placetype":"venue"
},
  "geometry": {"coordinates":[-122.281713,37.86694],"type":"Point"}
}