{
  "type": "Feature",
  "properties": {
    "addr:full":"1347 N Blue Gum St Anaheim CA 92806",
    "addr:housenumber":"1347",
    "addr:postcode":"92806",
    "addr:street":"N Blue Gum St",
    "iso:country":"US",
    "sg:address":"1347 N Blue Gum St",
    "sg:city":"Anaheim",
    "sg:classifiers":[
        {
            "category":"Personal",
            "type":"Services"
        }
    ],
    "sg:phone":"+1 714 666 0424",
    "sg:postcode":"92806",
    "sg:province":"CA",
    "sg:tags":[
        "home"
    ],
    "sg:website":"furnituresolutions.us/",
    "wof:name":"Furniture Solutions",
    "wof:placetype":"venue"
},
  "geometry": {"coordinates":[-117.873728,33.855289],"type":"Point"}
}