{
  "type": "Feature",
  "properties": {
    "addr:full":"1001 San Fernando Rd San Fernando CA 91340",
    "addr:housenumber":"1001",
    "addr:postcode":"91340",
    "addr:street":"San Fernando Rd",
    "iso:country":"US",
    "sg:address":"1001 San Fernando Rd",
    "sg:city":"San Fernando",
    "sg:classifiers":[
        {
            "category":"Shopping",
            "subcategory":"Clothing, Apparel, & Fashions",
            "type":"Retail Goods"
        }
    ],
    "sg:phone":"+1 818 365 6077",
    "sg:postcode":"91340",
    "sg:province":"CA",
    "sg:tags":[
        "shop",
        "bridal"
    ],
    "wof:name":"Wedding Planner Specialist",
    "wof:placetype":"venue"
},
  "geometry": {"coordinates":[-118.440918,34.282282],"type":"Point"}
}