{
  "type": "Feature",
  "properties": {
    "iso:country":"US",
    "sg:address":"763 E Anaheim St",
    "sg:city":"Long Beach",
    "sg:classifiers":[
        {
            "category":"Shopping",
            "type":"Retail Goods"
        }
    ],
    "sg:phone":"+1 562 591 3838",
    "sg:postcode":"90813",
    "sg:province":"CA",
    "sg:tags":[
        "telephone",
        "cellular"
    ],
    "wof:name":"D C Video & Wireless",
    "wof:placetype":"venue"
},
  "geometry": {"coordinates":[-118.182963,33.782676],"type":"Point"}
}