{
  "type": "Feature",
  "properties": {
    "iso:country":"US",
    "sg:address":"1016 10th St",
    "sg:city":"Sacramento",
    "sg:classifiers":[
        {
            "category":"Banks & Credit Unions",
            "subcategory":"Bank",
            "type":"Services"
        }
    ],
    "sg:phone":"+1 916 447 8333",
    "sg:postcode":"95814",
    "sg:province":"CA",
    "sg:tags":[
        "cashing",
        "check"
    ],
    "wof:name":"Money Mart",
    "wof:placetype":"venue"
},
  "geometry": {"coordinates":[-121.493713,38.579965],"type":"Point"}
}