{
  "type": "Feature",
  "properties": {
    "addr:full":"9031 Alcott St Los Angeles CA 90035",
    "addr:housenumber":"9031",
    "addr:postcode":"90035",
    "addr:street":"Alcott St",
    "iso:country":"US",
    "sg:address":"9031 Alcott St",
    "sg:city":"Los Angeles",
    "sg:classifiers":[
        {
            "category":"Real Estate",
            "subcategory":"Real Estate Operator",
            "type":"Services"
        }
    ],
    "sg:phone":"+1 310 385 0092",
    "sg:postcode":"90035",
    "sg:province":"CA",
    "sg:tags":[
        "apartment"
    ],
    "wof:name":"Alcott Apartments",
    "wof:placetype":"venue"
},
  "geometry": {"coordinates":[-118.389428,34.054264],"type":"Point"}
}