{
  "type": "Feature",
  "properties": {
    "addr:full":"4241 Florin Rd Sacramento CA 95823",
    "addr:housenumber":"4241",
    "addr:postcode":"95823",
    "addr:street":"Florin Rd",
    "iso:country":"US",
    "sg:address":"4241 Florin Rd",
    "sg:city":"Sacramento",
    "sg:classifiers":[
        {
            "category":"Home & Garden",
            "subcategory":"Furniture",
            "type":"Retail Goods"
        }
    ],
    "sg:phone":"+1 916 392 8863",
    "sg:postcode":"95823",
    "sg:province":"CA",
    "wof:name":"Discovery Furniture",
    "wof:placetype":"venue"
},
  "geometry": {"coordinates":[-121.45840800000001,38.496092],"type":"Point"}
}