{
  "type": "Feature",
  "properties": {
    "iso:country":"US",
    "sg:address":"22065 Sherman Wy",
    "sg:city":"Canoga Park",
    "sg:classifiers":[
        {
            "category":"Retail",
            "subcategory":"Portrait Studio",
            "type":"Services"
        }
    ],
    "sg:phone":"+1 818 346 5506",
    "sg:postcode":"91303",
    "sg:province":"CA",
    "sg:tags":[
        "photography",
        "store"
    ],
    "sg:website":"www.CanogaCamera.com",
    "wof:name":"Canoga Camera",
    "wof:placetype":"venue"
},
  "geometry": {"coordinates":[-118.607957,34.201044],"type":"Point"}
}