{
  "type": "Feature",
  "properties": {
    "addr:full":"115 W. 4th Street Ste. C1 Long Beach CA 90802",
    "addr:housenumber":"115",
    "addr:postcode":"90802",
    "addr:street":"W. 4Th Street Ste. C1",
    "iso:country":"US",
    "sg:address":"115 W. 4th Street Ste. C1",
    "sg:city":"Long Beach",
    "sg:classifiers":[
        {
            "category":"Professional",
            "type":"Services"
        }
    ],
    "sg:phone":"+1 562 624 5888",
    "sg:postcode":"90802",
    "sg:province":"CA",
    "sg:website":"530medialab.com",
    "wof:name":"530Medialab",
    "wof:placetype":"venue"
},
  "geometry": {"coordinates":[-118.192886,33.771713],"type":"Point"}
}