{
  "type": "Feature",
  "properties": {
    "iso:country":"US",
    "sg:address":"145 Russell Ave",
    "sg:city":"Susanville",
    "sg:classifiers":[
        {
            "category":"Restaurant",
            "type":"Food & Drink"
        }
    ],
    "sg:phone":"+1 530 257 7827",
    "sg:postcode":"96130",
    "sg:province":"CA",
    "wof:name":"Sub City",
    "wof:placetype":"venue"
},
  "geometry": {"coordinates":[-120.636566,40.412023],"type":"Point"}
}