{
  "type": "Feature",
  "properties": {
    "addr:full":"7695 N Palm Ave Fresno CA 93711",
    "addr:housenumber":"7695",
    "addr:postcode":"93711",
    "addr:street":"N Palm Ave",
    "iso:country":"US",
    "sg:address":"7695 N Palm Ave",
    "sg:city":"Fresno",
    "sg:classifiers":[
        {
            "category":"Retail",
            "subcategory":"Storage",
            "type":"Services"
        },
        {
            "category":"Manufacturing",
            "subcategory":"Paper Products",
            "type":"Manufacturing & Wholesale Goods"
        }
    ],
    "sg:phone":"+1 559 435 2622",
    "sg:postcode":"93711",
    "sg:province":"CA",
    "sg:tags":[
        "fiber",
        "self",
        "recreational",
        "commercial",
        "boxes-corrugated",
        "campers-storage",
        "vehicle",
        "household",
        "boat"
    ],
    "sg:website":"http://derrels-com.netsolads.com/location.asp?location_id=46&_nsag=36021",
    "wof:name":"Derrel's Mini Storage",
    "wof:placetype":"venue"
},
  "geometry": {"coordinates":[-119.805689,36.850375],"type":"Point"}
}