{
  "type": "Feature",
  "properties": {
    "iso:country":"US",
    "sg:address":"9100 Wilshire Blvd",
    "sg:city":"Beverly Hills",
    "sg:classifiers":[
        {
            "category":"Professional",
            "subcategory":"Lawyer & Legal Services",
            "type":"Services"
        }
    ],
    "sg:phone":"+1 310 274 1830",
    "sg:postcode":"90212",
    "sg:province":"CA",
    "wof:name":"Enright Judy Attorney At Law",
    "wof:placetype":"venue"
},
  "geometry": {"coordinates":[-118.389999,34.067101],"type":"Point"}
}