{
  "type": "Feature",
  "properties": {
    "iso:country":"US",
    "sg:address":"11911 San Vicente Blvd",
    "sg:city":"Los Angeles",
    "sg:classifiers":[
        {
            "category":"Professional",
            "subcategory":"Art Services",
            "type":"Services"
        }
    ],
    "sg:phone":"+1 310 440 3355",
    "sg:postcode":"90049",
    "sg:province":"CA",
    "sg:tags":[
        "graphic",
        "designer"
    ],
    "sg:website":"www.emamultimedia.com",
    "wof:name":"EMA Multimedia Inc",
    "wof:placetype":"venue"
},
  "geometry": {"coordinates":[-118.47266,34.052172],"type":"Point"}
}