{
  "type": "Feature",
  "properties": {
    "iso:country":"US",
    "sg:address":"3250 Wilshire Blvd",
    "sg:city":"Los Angeles",
    "sg:classifiers":[
        {
            "category":"Professional",
            "subcategory":"Lawyer & Legal Services",
            "type":"Services"
        }
    ],
    "sg:phone":"+1 213 307 9604",
    "sg:postcode":"90010",
    "sg:province":"CA",
    "sg:tags":[
        "personal",
        "injury"
    ],
    "wof:name":"Ekine Donny Adonis Attorney At Law",
    "wof:placetype":"venue"
},
  "geometry": {"coordinates":[-118.292999,34.061798],"type":"Point"}
}