{
  "type": "Feature",
  "properties": {
    "addr:full":"11154 Hwy 76 Pala CA 92059",
    "addr:housenumber":"11154",
    "addr:postcode":"92059",
    "addr:street":"Hwy 76",
    "iso:country":"US",
    "sg:address":"11154 Hwy 76",
    "sg:city":"Pala",
    "sg:classifiers":[
        {
            "category":"Personal",
            "subcategory":"Beauty Salon",
            "type":"Services"
        }
    ],
    "sg:phone":"+1 760 510 2189",
    "sg:postcode":"92059",
    "sg:province":"CA",
    "sg:tags":[
        "spa",
        "day"
    ],
    "wof:name":"Pala Casino Resort & Spa",
    "wof:placetype":"venue"
},
  "geometry": {"coordinates":[-117.09128699999999,33.36473],"type":"Point"}
}