{
  "type": "Feature",
  "properties": {
    "addr:full":"1660 Willow St San Jose CA 95125",
    "addr:housenumber":"1660",
    "addr:postcode":"95125",
    "addr:street":"Willow St",
    "iso:country":"US",
    "sg:address":"1660 Willow St",
    "sg:city":"San Jose",
    "sg:classifiers":[
        {
            "category":"Health Services",
            "subcategory":"Dentist",
            "type":"Services"
        }
    ],
    "sg:phone":"+1 408 269 1060",
    "sg:postcode":"95125",
    "sg:province":"CA",
    "sg:tags":[
        "periodontist"
    ],
    "wof:name":"Mark C Fagan, DDS",
    "wof:placetype":"venue"
},
  "geometry": {"coordinates":[-121.915524,37.303437],"type":"Point"}
}