{
  "type": "Feature",
  "properties": {
    "addr:full":"5469 Dehesa Rd El Cajon CA 92019",
    "addr:housenumber":"5469",
    "addr:postcode":"92019",
    "addr:street":"Dehesa Rd",
    "iso:country":"US",
    "sg:address":"5469 Dehesa Rd",
    "sg:city":"El Cajon",
    "sg:classifiers":[
        {
            "category":"Government",
            "subcategory":"Office",
            "type":"Public Place"
        }
    ],
    "sg:phone":"+1 619 445 6002",
    "sg:postcode":"92019",
    "sg:province":"CA",
    "sg:tags":[
        "american",
        "native",
        "tribal",
        "nation"
    ],
    "wof:name":"Sycuan Gift Shop",
    "wof:placetype":"venue"
},
  "geometry": {"coordinates":[-116.831709,32.791476],"type":"Point"}
}