{
  "type": "Feature",
  "properties": {
    "addr:full":"887 71st Ave Oakland CA 94621",
    "addr:housenumber":"887",
    "addr:postcode":"94621",
    "addr:street":"71St Ave",
    "iso:country":"US",
    "sg:address":"887 71st Ave",
    "sg:city":"Oakland",
    "sg:classifiers":[
        {
            "category":"Building & Trades",
            "subcategory":"Construction",
            "type":"Services"
        }
    ],
    "sg:phone":"+1 415 285 1091",
    "sg:postcode":"94621",
    "sg:province":"CA",
    "sg:tags":[
        "industrial",
        "painting",
        "contractors-commercial",
        "contractor"
    ],
    "wof:name":"Phoenix Paint Co",
    "wof:placetype":"venue"
},
  "geometry": {"coordinates":[-122.19596799999999,37.755281],"type":"Point"}
}