{
  "type": "Feature",
  "properties": {
    "iso:country":"US",
    "sg:address":"2120 E Parkside Ave",
    "sg:city":"Orange",
    "sg:classifiers":[
        {
            "category":"Building & Trades",
            "subcategory":"Construction",
            "type":"Services"
        }
    ],
    "sg:phone":"+1 714 532 3280",
    "sg:postcode":"92867",
    "sg:province":"CA",
    "sg:tags":[
        "tile",
        "dealer"
    ],
    "wof:name":"Jon Pavano Hot Mop Shower",
    "wof:placetype":"venue"
},
  "geometry": {"coordinates":[-117.830555,33.814262],"type":"Point"}
}