{
  "type": "Feature",
  "properties": {
    "iso:country":"US",
    "sg:address":"4651 Silva St",
    "sg:city":"Lakewood",
    "sg:classifiers":[
        {
            "category":"Shopping",
            "subcategory":"Optician",
            "type":"Retail Goods"
        }
    ],
    "sg:phone":"+1 562 634 2442",
    "sg:postcode":"90712",
    "sg:province":"CA",
    "sg:tags":[
        "eyewear"
    ],
    "sg:website":"www.lenscrafters.com",
    "wof:name":"Lenscrafters",
    "wof:placetype":"venue"
},
  "geometry": {"coordinates":[-118.138624,33.847996],"type":"Point"}
}