{
  "type": "Feature",
  "properties": {
    "addr:full":"9222 Kiefer Blvd Sacramento CA 95826",
    "addr:housenumber":"9222",
    "addr:postcode":"95826",
    "addr:street":"Kiefer Blvd",
    "iso:country":"US",
    "sg:address":"9222 Kiefer Blvd",
    "sg:city":"Sacramento",
    "sg:classifiers":[
        {
            "category":"Personal",
            "type":"Services"
        }
    ],
    "sg:phone":"+1 916 731 3953",
    "sg:postcode":"95826",
    "sg:province":"CA",
    "sg:tags":[
        "therapist",
        "massage"
    ],
    "wof:name":"Caring Hands Caring Heart Body",
    "wof:placetype":"venue"
},
  "geometry": {"coordinates":[-121.35802200000001,38.547288],"type":"Point"}
}