{
  "type": "Feature",
  "properties": {
    "iso:country":"US",
    "sg:address":"7069 Danyeur Rd",
    "sg:city":"Redding",
    "sg:classifiers":[
        {
            "category":"Building & Trades",
            "subcategory":"Plumbing",
            "type":"Services"
        }
    ],
    "sg:phone":"+1 530 244 6900",
    "sg:postcode":"96001",
    "sg:province":"CA",
    "sg:tags":[
        "sheet",
        "metal",
        "heating",
        "air",
        "conditioning",
        "contractor"
    ],
    "wof:name":"Thermo Dynamics",
    "wof:placetype":"venue"
},
  "geometry": {"coordinates":[-122.37797399999999,40.515159],"type":"Point"}
}