{
  "type": "Feature",
  "properties": {
    "addr:full":"1482 E Valley Rd Santa Barbara CA 93108",
    "addr:housenumber":"1482",
    "addr:postcode":"93108",
    "addr:street":"E Valley Rd",
    "iso:country":"US",
    "sg:address":"1482 E Valley Rd",
    "sg:city":"Santa Barbara",
    "sg:classifiers":[
        {
            "category":"Shopping",
            "subcategory":"Gifts & Souvenirs",
            "type":"Retail Goods"
        }
    ],
    "sg:phone":"+1 805 969 9914",
    "sg:postcode":"93108",
    "sg:province":"CA",
    "sg:tags":[
        "shop"
    ],
    "wof:name":"Luminaria",
    "wof:placetype":"venue"
},
  "geometry": {"coordinates":[-119.633506,34.437032],"type":"Point"}
}