{
  "type": "Feature",
  "properties": {
    "iso:country":"US",
    "sg:address":"490 N Foothill Rd",
    "sg:city":"Los Angeles",
    "sg:classifiers":[
        {
            "category":"Professional",
            "subcategory":"Lawyer & Legal Services",
            "type":"Services"
        }
    ],
    "sg:phone":"+1 310 271 7678",
    "sg:postcode":"90001",
    "sg:province":"CA",
    "wof:name":"Drucker Barry",
    "wof:placetype":"venue"
},
  "geometry": {"coordinates":[-118.396086,34.076294],"type":"Point"}
}