{
  "type": "Feature",
  "properties": {
    "addr:full":"1895 Dobbin Dr San Jose CA 95133",
    "addr:housenumber":"1895",
    "addr:postcode":"95133",
    "addr:street":"Dobbin Dr",
    "iso:country":"US",
    "sg:address":"1895 Dobbin Dr",
    "sg:city":"San Jose",
    "sg:classifiers":[
        {
            "category":"Real Estate",
            "subcategory":"Architect",
            "type":"Services"
        }
    ],
    "sg:phone":"+1 408 259 1155",
    "sg:postcode":"95133",
    "sg:province":"CA",
    "wof:name":"Miro Design Group",
    "wof:placetype":"venue"
},
  "geometry": {"coordinates":[-121.865055,37.366111],"type":"Point"}
}