{
  "type": "Feature",
  "properties": {
    "addr:full":"2078 Hayes St San Francisco CA 94117",
    "addr:housenumber":"2078",
    "addr:postcode":"94117",
    "addr:street":"Hayes St",
    "iso:country":"US",
    "sg:address":"2078 Hayes St",
    "sg:city":"San Francisco",
    "sg:classifiers":[
        {
            "category":"Restaurant",
            "type":"Food & Drink"
        }
    ],
    "sg:menulink":"http://www.allmenus.com/ca/san-francisco/275867-abacus/menu/",
    "sg:phone":"+1 415 387 2828",
    "sg:postcode":"94117",
    "sg:province":"CA",
    "sg:tags":[
        "american",
        "asian",
        "chinese",
        "californian"
    ],
    "wof:name":"Abacus",
    "wof:placetype":"venue"
},
  "geometry": {"coordinates":[-122.45055499999999,37.773514],"type":"Point"}
}