{
  "type": "Feature",
  "properties": {
    "addr:full":"6350 Pso Santa Maria Pleasanton CA 94566",
    "addr:housenumber":"6350",
    "addr:postcode":"94566",
    "addr:street":"Pso Santa Maria",
    "iso:country":"US",
    "sg:address":"6350 Pso Santa Maria",
    "sg:city":"Pleasanton",
    "sg:classifiers":[
        {
            "category":"Wholesale",
            "subcategory":"Machinery & Supplies",
            "type":"Manufacturing & Wholesale Goods"
        }
    ],
    "sg:phone":"+1 925 426 0894",
    "sg:postcode":"94566",
    "sg:province":"CA",
    "sg:tags":[
        "equipment",
        "industrial"
    ],
    "wof:name":"Bay Pac Equipment",
    "wof:placetype":"venue"
},
  "geometry": {"coordinates":[-121.90536,37.670014],"type":"Point"}
}