{
  "type": "Feature",
  "properties": {
    "iso:country":"US",
    "sg:address":"23969 Mission Blvd",
    "sg:city":"Hayward",
    "sg:classifiers":[
        {
            "category":"Restaurant",
            "type":"Food & Drink"
        }
    ],
    "sg:menulink":"http://www.allmenus.com/ca/hayward/174408-wendys/menu/",
    "sg:phone":"+1 510 538 6320",
    "sg:postcode":"94544",
    "sg:province":"CA",
    "sg:tags":[
        "burger",
        "american",
        "soup"
    ],
    "wof:name":"Wendy's",
    "wof:placetype":"venue"
},
  "geometry": {"coordinates":[-122.080581,37.667827],"type":"Point"}
}