{
  "type": "Feature",
  "properties": {
    "addr:full":"130 Belmont Ct Redlands CA 92373",
    "addr:housenumber":"130",
    "addr:postcode":"92373",
    "addr:street":"Belmont Ct",
    "iso:country":"US",
    "sg:address":"130 Belmont Ct",
    "sg:city":"Redlands",
    "sg:classifiers":[
        {
            "category":"Wholesale",
            "subcategory":"Machinery & Supplies",
            "type":"Manufacturing & Wholesale Goods"
        }
    ],
    "sg:phone":"+1 909 792 8766",
    "sg:postcode":"92373",
    "sg:province":"CA",
    "sg:tags":[
        "equipment",
        "aircraft",
        "transportation",
        "avionics"
    ],
    "wof:name":"Brian Thomas & Associates Inc",
    "wof:placetype":"venue"
},
  "geometry": {"coordinates":[-117.15977100000001,34.034708],"type":"Point"}
}