{
  "type": "Feature",
  "properties": {
    "addr:full":"8541 Amelia St Oakland CA 94621",
    "addr:housenumber":"8541",
    "addr:postcode":"94621",
    "addr:street":"Amelia St",
    "iso:country":"US",
    "sg:address":"8541 Amelia St",
    "sg:city":"Oakland",
    "sg:classifiers":[
        {
            "category":"Wholesale",
            "subcategory":"Chemicals & Plastics",
            "type":"Manufacturing & Wholesale Goods"
        },
        {
            "category":"Manufacturing",
            "subcategory":"Paper Products",
            "type":"Manufacturing & Wholesale Goods"
        }
    ],
    "sg:phone":"+1 510 568 8639",
    "sg:postcode":"94621",
    "sg:province":"CA",
    "sg:tags":[
        "bag",
        "bags-paper"
    ],
    "wof:name":"U.S. Plastic Mfg., Inc.",
    "wof:placetype":"venue"
},
  "geometry": {"coordinates":[-122.186145,37.748349],"type":"Point"}
}