{
  "type": "Feature",
  "properties": {
    "iso:country":"US",
    "sg:address":"2440 16th St",
    "sg:city":"San Francisco",
    "sg:classifiers":[
        {
            "category":"Professional",
            "subcategory":"Art Services",
            "type":"Services"
        }
    ],
    "sg:phone":"+1 415 377 6999",
    "sg:postcode":"94103",
    "sg:province":"CA",
    "sg:tags":[
        "photographer"
    ],
    "sg:website":"www.refleximaging.com",
    "wof:name":"Reflex Imaging",
    "wof:placetype":"venue"
},
  "geometry": {"coordinates":[-122.410867,37.765612],"type":"Point"}
}