{
  "type": "Feature",
  "properties": {
    "iso:country":"US",
    "sg:address":"340 Avenida Nogales",
    "sg:city":"San Jose",
    "sg:classifiers":[
        {
            "category":"Building & Trades",
            "subcategory":"Landscaping Services",
            "type":"Services"
        }
    ],
    "sg:phone":"+1 408 225 2952",
    "sg:postcode":"95123",
    "sg:province":"CA",
    "sg:tags":[
        "tree"
    ],
    "wof:name":"California Tree Service",
    "wof:placetype":"venue"
},
  "geometry": {"coordinates":[-121.833853,37.256791],"type":"Point"}
}