{
  "type": "Feature",
  "properties": {
    "addr:full":"3194 De La Cruz Boulevard Santa Clara CA 95054",
    "addr:housenumber":"3194",
    "addr:postcode":"95054",
    "addr:street":"De La Cruz Boulevard",
    "iso:country":"US",
    "sg:address":"3194 De La Cruz Boulevard",
    "sg:city":"Santa Clara",
    "sg:classifiers":[
        {
            "category":"Shopping",
            "subcategory":"Florist",
            "type":"Retail Goods"
        }
    ],
    "sg:phone":"+1 408 748 8791",
    "sg:postcode":"95054",
    "sg:province":"CA",
    "wof:name":"Angela's Flowers & Gifts",
    "wof:placetype":"venue"
},
  "geometry": {"coordinates":[-121.94131400000001,37.382049],"type":"Point"}
}