{
  "type": "Feature",
  "properties": {
    "addr:full":"33404 Western Ave Union City CA 94587",
    "addr:housenumber":"33404",
    "addr:postcode":"94587",
    "addr:street":"Western Ave",
    "iso:country":"US",
    "sg:address":"33404 Western Ave",
    "sg:city":"Union City",
    "sg:classifiers":[
        {
            "category":"Professional",
            "type":"Services"
        }
    ],
    "sg:phone":"+1 510 324 2414",
    "sg:postcode":"94587",
    "sg:province":"CA",
    "sg:tags":[
        "establishment"
    ],
    "wof:name":"Atlas Impex Inc",
    "wof:placetype":"venue"
},
  "geometry": {"coordinates":[-122.035072,37.591201],"type":"Point"}
}