{
  "type": "Feature",
  "properties": {
    "addr:full":"750 The City Dr S Orange CA 92868",
    "addr:housenumber":"750",
    "addr:postcode":"92868",
    "addr:street":"The City Dr S",
    "iso:country":"US",
    "sg:address":"750 The City Dr S",
    "sg:city":"Orange",
    "sg:classifiers":[
        {
            "category":"Professional",
            "subcategory":"Employment Agencies",
            "type":"Services"
        }
    ],
    "sg:phone":"+1 714 558 6829",
    "sg:postcode":"92868",
    "sg:province":"CA",
    "wof:name":"Culver Careers",
    "wof:placetype":"venue"
},
  "geometry": {"coordinates":[-117.889999,33.776901],"type":"Point"}
}