{
  "type": "Feature",
  "properties": {
    "addr:full":"11380 Luddington St Sun Valley CA 91352",
    "addr:housenumber":"11380",
    "addr:postcode":"91352",
    "addr:street":"Luddington St",
    "iso:country":"US",
    "sg:address":"11380 Luddington St",
    "sg:city":"Sun Valley",
    "sg:classifiers":[
        {
            "category":"Retail",
            "subcategory":"Repair Shop",
            "type":"Services"
        }
    ],
    "sg:phone":"+1 818 771 0964",
    "sg:postcode":"91352",
    "sg:province":"CA",
    "sg:tags":[
        "welding"
    ],
    "wof:name":"Kuton Welding Inc",
    "wof:placetype":"venue"
},
  "geometry": {"coordinates":[-118.379119,34.224848],"type":"Point"}
}