{
  "type": "Feature",
  "properties": {
    "addr:full":"231 W Vernon Ave Los Angeles CA 90037",
    "addr:housenumber":"231",
    "addr:postcode":"90037",
    "addr:street":"W Vernon Ave",
    "iso:country":"US",
    "sg:address":"231 W Vernon Ave",
    "sg:city":"Los Angeles",
    "sg:classifiers":[
        {
            "category":"Health Services",
            "subcategory":"Doctor",
            "type":"Services"
        }
    ],
    "sg:phone":"+1 323 233 8436",
    "sg:postcode":"90037",
    "sg:province":"CA",
    "sg:tags":[
        "clinic"
    ],
    "wof:name":"St Martins Medical Group Inc",
    "wof:placetype":"venue"
},
  "geometry": {"coordinates":[-118.275969,34.003891],"type":"Point"}
}