{
  "type": "Feature",
  "properties": {
    "addr:full":"795 Zion St Nevada City CA 95959",
    "addr:housenumber":"795",
    "addr:postcode":"95959",
    "addr:street":"Zion St",
    "iso:country":"US",
    "sg:address":"795 Zion St",
    "sg:city":"Nevada City",
    "sg:classifiers":[
        {
            "category":"Retail",
            "subcategory":"Auto Repair",
            "type":"Services"
        }
    ],
    "sg:phone":"+1 530 265 2001",
    "sg:postcode":"95959",
    "sg:province":"CA",
    "sg:tags":[
        "repairing",
        "automobile"
    ],
    "wof:name":"Muffler & Brake Barn",
    "wof:placetype":"venue"
},
  "geometry": {"coordinates":[-121.026295,39.252587],"type":"Point"}
}