{
  "type": "Feature",
  "properties": {
    "addr:full":"1876 Rosecrans Street San Diego CA 92106",
    "addr:housenumber":"1876",
    "addr:postcode":"92106",
    "addr:street":"Rosecrans Street",
    "iso:country":"US",
    "sg:address":"1876 Rosecrans Street",
    "sg:city":"San Diego",
    "sg:classifiers":[
        {
            "category":"Personal",
            "subcategory":"Beauty Salon",
            "type":"Services"
        },
        {
            "category":"Personal",
            "subcategory":"Nail Salon",
            "type":"Services"
        }
    ],
    "sg:phone":"+1 619 221 1925",
    "sg:postcode":"92106",
    "sg:province":"CA",
    "sg:tags":[
        "eyelash"
    ],
    "wof:name":"Nails by Lesa",
    "wof:placetype":"venue"
},
  "geometry": {"coordinates":[-117.223759,32.7308],"type":"Point"}
}