{
  "type": "Feature",
  "properties": {
    "iso:country":"US",
    "sg:address":"171 N 8th St",
    "sg:city":"San Jose",
    "sg:classifiers":[
        {
            "category":"Wholesale",
            "subcategory":"Motor Vehicles",
            "type":"Manufacturing & Wholesale Goods"
        }
    ],
    "sg:phone":"+1 408 287 9722",
    "sg:postcode":"95112",
    "sg:province":"CA",
    "wof:name":"George Rodney Blackstone",
    "wof:placetype":"venue"
},
  "geometry": {"coordinates":[-121.884736,37.341558],"type":"Point"}
}