{
  "type": "Feature",
  "properties": {
    "addr:full":"18718 Soledad Canyon Rd Santa Clarita CA 91351",
    "addr:housenumber":"18718",
    "addr:postcode":"91351",
    "addr:street":"Soledad Canyon Rd",
    "iso:country":"US",
    "sg:address":"18718 Soledad Canyon Rd",
    "sg:city":"Santa Clarita",
    "sg:classifiers":[
        {
            "category":"Shopping",
            "subcategory":"Music",
            "type":"Retail Goods"
        }
    ],
    "sg:phone":"+1 661 229 2345",
    "sg:postcode":"91351",
    "sg:province":"CA",
    "sg:tags":[
        "compact",
        "record",
        "musical",
        "instrument",
        "disc",
        "tape",
        "teacher"
    ],
    "sg:website":"www.nickrailmusic.com",
    "wof:name":"Nick Rail Music",
    "wof:placetype":"venue"
},
  "geometry": {"coordinates":[-118.460559,34.415887],"type":"Point"}
}