{
  "type": "Feature",
  "properties": {
    "iso:country":"US",
    "sg:address":"365 12th St",
    "sg:city":"Oakland",
    "sg:classifiers":[
        {
            "category":"Shopping",
            "subcategory":"Clothing, Apparel, & Fashions",
            "type":"Retail Goods"
        }
    ],
    "sg:phone":"+1 510 251 8298",
    "sg:postcode":"94607",
    "sg:province":"CA",
    "wof:name":"Sum Sum Trading",
    "wof:placetype":"venue"
},
  "geometry": {"coordinates":[-122.270585,37.802266],"type":"Point"}
}