{
  "type": "Feature",
  "properties": {
    "addr:full":"13 S Quarantina St Santa Barbara CA 93103",
    "addr:housenumber":"13",
    "addr:postcode":"93103",
    "addr:street":"S Quarantina St",
    "iso:country":"US",
    "sg:address":"13 S Quarantina St",
    "sg:city":"Santa Barbara",
    "sg:classifiers":[
        {
            "category":"Wholesale",
            "subcategory":"Groceries",
            "type":"Manufacturing & Wholesale Goods"
        }
    ],
    "sg:phone":"+1 805 965 2232",
    "sg:postcode":"93103",
    "sg:province":"CA",
    "sg:tags":[
        "food",
        "product",
        "health"
    ],
    "wof:name":"Performance Nutritionals",
    "wof:placetype":"venue"
},
  "geometry": {"coordinates":[-119.680587,34.419187],"type":"Point"}
}