{
  "type": "Feature",
  "properties": {
    "addr:full":"8300 Brentwood Blvd Brentwood CA 94513",
    "addr:housenumber":"8300",
    "addr:postcode":"ca 94513",
    "addr:street":"Brentwood Blvd",
    "iso:country":"US",
    "sg:address":"8300 Brentwood Blvd",
    "sg:city":"Brentwood",
    "sg:classifiers":[
        {
            "category":"Restaurant",
            "type":"Food & Drink"
        }
    ],
    "sg:phone":"+1 925 240 8555",
    "sg:postcode":"94513",
    "sg:province":"CA",
    "sg:tags":[
        "pizza"
    ],
    "sg:website":"www.dominos.com",
    "wof:name":"Domino's Pizza",
    "wof:placetype":"venue"
},
  "geometry": {"coordinates":[-121.697998,37.934101],"type":"Point"}
}