{
  "type": "Feature",
  "properties": {
    "iso:country":"US",
    "sg:address":"303 Pasadena Ave",
    "sg:city":"South Pasadena",
    "sg:classifiers":[
        {
            "category":"Deli",
            "type":"Food & Drink"
        }
    ],
    "sg:phone":"+1 626 799 8397",
    "sg:postcode":"91030",
    "sg:province":"CA",
    "wof:name":"Pappa Don's Delicatessen",
    "wof:placetype":"venue"
},
  "geometry": {"coordinates":[-118.169998,34.112099],"type":"Point"}
}