{
  "type": "Feature",
  "properties": {
    "addr:full":"303 Pasadena Ave South Pasadena CA 91030",
    "addr:housenumber":"303",
    "addr:postcode":"91030",
    "addr:street":"Pasadena Ave",
    "iso:country":"US",
    "sg:address":"303 Pasadena Ave",
    "sg:city":"South Pasadena",
    "sg:classifiers":[
        {
            "category":"Deli",
            "type":"Food & Drink"
        }
    ],
    "sg:phone":"+1 626 799 8397",
    "sg:postcode":"91030",
    "sg:province":"CA",
    "wof:name":"Pappa Don's Delicatessen",
    "wof:placetype":"venue"
},
  "geometry": {"coordinates":[-118.16999800000001,34.112099],"type":"Point"}
}