{
  "type": "Feature",
  "properties": {
    "addr:full":"11552 Knott St Garden Grove CA 92841",
    "addr:housenumber":"11552",
    "addr:postcode":"92841",
    "addr:street":"Knott St",
    "iso:country":"US",
    "sg:address":"11552 Knott St",
    "sg:city":"Garden Grove",
    "sg:classifiers":[
        {
            "category":"Wholesale",
            "subcategory":"Electrical",
            "type":"Manufacturing & Wholesale Goods"
        }
    ],
    "sg:phone":"+1 714 373 1171",
    "sg:postcode":"92841",
    "sg:province":"CA",
    "sg:tags":[
        "equipment",
        "electronic",
        "supply"
    ],
    "wof:name":"Mil Aero Electronics Inc",
    "wof:placetype":"venue"
},
  "geometry": {"coordinates":[-118.010994,33.79475],"type":"Point"}
}