{
  "type": "Feature",
  "properties": {
    "iso:country":"US",
    "sg:address":"72840 Hwy 111",
    "sg:city":"Palm Desert",
    "sg:classifiers":[
        {
            "category":"Professional",
            "type":"Services"
        },
        {
            "category":"Professional",
            "subcategory":"Management & Consulting",
            "type":"Services"
        }
    ],
    "sg:phone":"+1 760 773 2888",
    "sg:postcode":"92260",
    "sg:province":"CA",
    "sg:tags":[
        "party",
        "planning",
        "establishment"
    ],
    "wof:name":"A Bear Is Born",
    "wof:placetype":"venue"
},
  "geometry": {"coordinates":[-116.39235100000001,33.721574],"type":"Point"}
}