{
  "type": "Feature",
  "properties": {
    "iso:country":"US",
    "sg:address":"7979 E 11th St",
    "sg:city":"Tracy",
    "sg:classifiers":[
        {
            "category":"Retail",
            "subcategory":"Auto Repair",
            "type":"Services"
        }
    ],
    "sg:phone":"+1 209 836 0300",
    "sg:postcode":"95304",
    "sg:province":"CA",
    "sg:tags":[
        "repairing",
        "automobile",
        "radiator"
    ],
    "wof:name":"S & J's Radiator & Auto Care",
    "wof:placetype":"venue"
},
  "geometry": {"coordinates":[-121.400533,37.739917],"type":"Point"}
}