{
  "type": "Feature",
  "properties": {
    "iso:country":"US",
    "sg:address":"16016 Alhambra Ln",
    "sg:city":"Redding",
    "sg:classifiers":[
        {
            "category":"Professional",
            "type":"Services"
        }
    ],
    "sg:phone":"+1 530 229 7793",
    "sg:postcode":"96001",
    "sg:province":"CA",
    "wof:name":"Chicoine & Lewallen Entps",
    "wof:placetype":"venue"
},
  "geometry": {"coordinates":[-122.46430599999999,40.540578],"type":"Point"}
}