{
  "type": "Feature",
  "properties": {
    "addr:full":"27701 Murrieta Rd Sun City CA 92586",
    "addr:housenumber":"27701",
    "addr:postcode":"92586",
    "addr:street":"Murrieta Rd",
    "iso:country":"US",
    "sg:address":"27701 Murrieta Rd",
    "sg:city":"Sun City",
    "sg:classifiers":[
        {
            "category":"Retail",
            "subcategory":"Laundry & Dry Cleaning",
            "type":"Services"
        }
    ],
    "sg:phone":"+1 951 679 6552",
    "sg:postcode":"92586",
    "sg:province":"CA",
    "sg:tags":[
        "cleaners",
        "rug",
        "carpet"
    ],
    "wof:name":"Pilebrite Carpet Cleaning",
    "wof:placetype":"venue"
},
  "geometry": {"coordinates":[-117.206217,33.72071],"type":"Point"}
}