{
  "type": "Feature",
  "properties": {
    "addr:full":"4800 McCloud Dr Sacramento CA 95842",
    "addr:housenumber":"4800",
    "addr:postcode":"95842",
    "addr:street":"Mccloud Dr",
    "iso:country":"US",
    "sg:address":"4800 McCloud Dr",
    "sg:city":"Sacramento",
    "sg:classifiers":[
        {
            "category":"Professional",
            "subcategory":"Accounting & Tax Preparation",
            "type":"Services"
        }
    ],
    "sg:phone":"+1 916 331 2380",
    "sg:postcode":"95842",
    "sg:province":"CA",
    "sg:tags":[
        "consultant"
    ],
    "wof:name":"Sparks Tax Svc",
    "wof:placetype":"venue"
},
  "geometry": {"coordinates":[-121.351834,38.681674],"type":"Point"}
}