{
  "type": "Feature",
  "properties": {
    "iso:country":"US",
    "sg:address":"San Carlos & Ocean SE Corner",
    "sg:city":"Carmel",
    "sg:classifiers":[
        {
            "category":"Home & Garden",
            "subcategory":"Home Furnishings",
            "type":"Retail Goods"
        }
    ],
    "sg:phone":"+1 831 624 6247",
    "sg:postcode":"93923",
    "sg:province":"CA",
    "sg:tags":[
        "decor"
    ],
    "wof:name":"Haven Home Furnishings",
    "wof:placetype":"venue"
},
  "geometry": {"coordinates":[-121.921784,36.55515],"type":"Point"}
}