{
  "type": "Feature",
  "properties": {
    "addr:full":"3700 N Twin Oaks Valley Rd San Marcos CA 92069",
    "addr:housenumber":"3700",
    "addr:postcode":"92069",
    "addr:street":"N Twin Oaks Valley Rd",
    "iso:country":"US",
    "sg:address":"3700 N Twin Oaks Valley Rd",
    "sg:city":"San Marcos",
    "sg:classifiers":[
        {
            "category":"Wholesale",
            "subcategory":"Groceries",
            "type":"Manufacturing & Wholesale Goods"
        }
    ],
    "sg:phone":"+1 760 591 4151",
    "sg:postcode":"92069",
    "sg:province":"CA",
    "sg:tags":[
        "food",
        "product",
        "health"
    ],
    "wof:name":"Bell Rock Growers Inc",
    "wof:placetype":"venue"
},
  "geometry": {"coordinates":[-117.171391,33.215012],"type":"Point"}
}