{
  "type": "Feature",
  "properties": {
    "iso:country":"US",
    "sg:address":"1001 Eastshore Hwy",
    "sg:city":"Albany",
    "sg:classifiers":[
        {
            "category":"Shopping",
            "subcategory":"Pets & Pet Supplies",
            "type":"Retail Goods"
        }
    ],
    "sg:phone":"+1 510 524 1518",
    "sg:postcode":"94710",
    "sg:province":"CA",
    "sg:tags":[
        "store"
    ],
    "sg:website":"www.petsmart.com",
    "wof:name":"PetSmart",
    "wof:placetype":"venue"
},
  "geometry": {"coordinates":[-122.307503,37.886323],"type":"Point"}
}