{
  "type": "Feature",
  "properties": {
    "addr:full":"456 S Serrano Ave Los Angeles CA 90020",
    "addr:housenumber":"456",
    "addr:postcode":"90020",
    "addr:street":"S Serrano Ave",
    "iso:country":"US",
    "sg:address":"456 S Serrano Ave",
    "sg:city":"Los Angeles",
    "sg:classifiers":[
        {
            "category":"Health Services",
            "subcategory":"Health Practitioner",
            "type":"Services"
        }
    ],
    "sg:phone":"+1 213 388 2946",
    "sg:postcode":"90020",
    "sg:province":"CA",
    "sg:tags":[
        "acupuncture"
    ],
    "wof:name":"Yuenam Acupuncture",
    "wof:placetype":"venue"
},
  "geometry": {"coordinates":[-118.306532,34.066389],"type":"Point"}
}