{
  "type": "Feature",
  "properties": {
    "addr:full":"1456 Main St Newman CA 95360",
    "addr:housenumber":"1456",
    "addr:postcode":"95360",
    "addr:street":"Main St",
    "iso:country":"US",
    "sg:address":"1456 Main St",
    "sg:city":"Newman",
    "sg:classifiers":[
        {
            "category":"Personal",
            "subcategory":"Beauty Salon",
            "type":"Services"
        }
    ],
    "sg:phone":"+1 209 862 1476",
    "sg:postcode":"95360",
    "sg:province":"CA",
    "sg:tags":[
        "manicuring"
    ],
    "wof:name":"T's Nail Care",
    "wof:placetype":"venue"
},
  "geometry": {"coordinates":[-121.022059,37.314118],"type":"Point"}
}