{
  "type": "Feature",
  "properties": {
    "addr:full":"3432 Dwight Rd Elk Grove CA 95758",
    "addr:housenumber":"3432",
    "addr:postcode":"95758",
    "addr:street":"Dwight Rd",
    "iso:country":"US",
    "sg:address":"3432 Dwight Rd",
    "sg:city":"Elk Grove",
    "sg:classifiers":[
        {
            "category":"Professional",
            "subcategory":"Engineering",
            "type":"Services"
        }
    ],
    "sg:phone":"+1 916 391 8042",
    "sg:postcode":"95758",
    "sg:province":"CA",
    "sg:tags":[
        "engineer"
    ],
    "wof:name":"F & M Engineering Contractors",
    "wof:placetype":"venue"
},
  "geometry": {"coordinates":[-121.45826700000001,38.434128],"type":"Point"}
}