{
  "type": "Feature",
  "properties": {
    "iso:country":"US",
    "sg:address":"12 Chandra Ln",
    "sg:city":"Rancho Mirage",
    "sg:classifiers":[
        {
            "category":"Communications",
            "type":"Services"
        }
    ],
    "sg:phone":"+1 760 512 0049",
    "sg:postcode":"92270",
    "sg:province":"CA",
    "sg:tags":[
        "web",
        "design"
    ],
    "sg:website":"www.OperationWeb.com",
    "wof:name":"Operation Web",
    "wof:placetype":"venue"
},
  "geometry": {"coordinates":[-116.442043,33.776567],"type":"Point"}
}