{
  "type": "Feature",
  "properties": {
    "addr:full":"926 Railroad Ave Santa Paula CA 93060",
    "addr:housenumber":"926",
    "addr:postcode":"93060",
    "addr:street":"Railroad Ave",
    "iso:country":"US",
    "sg:address":"926 Railroad Ave",
    "sg:city":"Santa Paula",
    "sg:classifiers":[
        {
            "category":"Shopping",
            "subcategory":"Used Merchandise",
            "type":"Retail Goods"
        }
    ],
    "sg:phone":"+1 805 933 3789",
    "sg:postcode":"93060",
    "sg:province":"CA",
    "wof:name":"Railroad Nursery",
    "wof:placetype":"venue"
},
  "geometry": {"coordinates":[-119.063035,34.35572],"type":"Point"}
}