{
  "type": "Feature",
  "properties": {
    "addr:full":"600 Apple Blossom Dr Murphys CA 95247",
    "addr:housenumber":"600",
    "addr:postcode":"95247",
    "addr:street":"Apple Blossom Dr",
    "iso:country":"US",
    "sg:address":"600 Apple Blossom Dr",
    "sg:city":"Murphys",
    "sg:classifiers":[
        {
            "category":"Personal",
            "type":"Services"
        }
    ],
    "sg:phone":"+1 209 728 2268",
    "sg:postcode":"95247",
    "sg:province":"CA",
    "sg:tags":[
        "miscellaneous"
    ],
    "wof:name":"Personal Solutions",
    "wof:placetype":"venue"
},
  "geometry": {"coordinates":[-120.456256,38.149327],"type":"Point"}
}