{
  "type": "Feature",
  "properties": {
    "addr:full":"10850 MacArthur Blvd Ste 300 Oakland CA 94605",
    "addr:housenumber":"10850",
    "addr:postcode":"94605",
    "addr:street":"Macarthur Blvd Ste 300",
    "iso:country":"US",
    "sg:address":"10850 MacArthur Blvd Ste 300",
    "sg:city":"Oakland",
    "sg:classifiers":[
        {
            "category":"Health Services",
            "subcategory":"Doctor",
            "type":"Services"
        },
        {
            "category":"Health Services",
            "subcategory":"Clinic",
            "type":"Services"
        }
    ],
    "sg:phone":"+1 510 569 9334",
    "sg:postcode":"94605",
    "sg:province":"CA",
    "sg:tags":[
        "counseling",
        "mental",
        "psychiatrist"
    ],
    "wof:name":"Schuman-Liles Clinic",
    "wof:placetype":"venue"
},
  "geometry": {"coordinates":[-122.15010100000001,37.741527],"type":"Point"}
}