{
  "type": "Feature",
  "properties": {
    "iso:country":"US",
    "sg:address":"18897 Ave 96",
    "sg:city":"Terra Bella",
    "sg:classifiers":[
        {
            "category":"Farming",
            "subcategory":"Farm & Veterinary Services",
            "type":"Manufacturing & Wholesale Goods"
        }
    ],
    "sg:phone":"+1 559 784 0142",
    "sg:postcode":"93270",
    "sg:province":"CA",
    "sg:tags":[
        "gin",
        "cotton"
    ],
    "wof:name":"Tri-City Growers Inc",
    "wof:placetype":"venue"
},
  "geometry": {"coordinates":[-119.145062,35.96426],"type":"Point"}
}