{
  "type": "Feature",
  "properties": {
    "iso:country":"US",
    "sg:address":"13619 Inglewood Ave",
    "sg:city":"Hawthorne",
    "sg:classifiers":[
        {
            "category":"Restaurant",
            "type":"Food & Drink"
        }
    ],
    "sg:phone":"+1 310 644 6395",
    "sg:postcode":"90250",
    "sg:province":"CA",
    "sg:tags":[
        "middle",
        "indian",
        "halal",
        "eastern"
    ],
    "wof:name":"Al Watan Halal Restaurant",
    "wof:placetype":"venue"
},
  "geometry": {"coordinates":[-118.361,33.9086],"type":"Point"}
}