{
  "type": "Feature",
  "properties": {
    "addr:full":"560 San Antonio Rd Palo Alto CA 94306",
    "addr:housenumber":"560",
    "addr:postcode":"94306",
    "addr:street":"San Antonio Rd",
    "iso:country":"US",
    "sg:address":"560 San Antonio Rd",
    "sg:city":"Palo Alto",
    "sg:classifiers":[
        {
            "category":"Shopping",
            "subcategory":"Computers & Home Electronics",
            "type":"Retail Goods"
        }
    ],
    "sg:phone":"+1 650 493 4122",
    "sg:postcode":"94306",
    "sg:province":"CA",
    "sg:tags":[
        "software"
    ],
    "wof:name":"Operations Control Systems",
    "wof:placetype":"venue"
},
  "geometry": {"coordinates":[-122.103623,37.41513],"type":"Point"}
}