{
  "type": "Feature",
  "properties": {
    "addr:full":"6617 Dume Dr Malibu CA 90265",
    "addr:housenumber":"6617",
    "addr:postcode":"90265",
    "addr:street":"Dume Dr",
    "iso:country":"US",
    "sg:address":"6617 Dume Dr",
    "sg:city":"Malibu",
    "sg:classifiers":[
        {
            "category":"Building & Trades",
            "subcategory":"Electrical",
            "type":"Services"
        }
    ],
    "sg:phone":"+1 310 457 1497",
    "sg:postcode":"90265",
    "sg:province":"CA",
    "sg:tags":[
        "electric",
        "contractor"
    ],
    "wof:name":"Daniels Electric",
    "wof:placetype":"venue"
},
  "geometry": {"coordinates":[-118.807675,34.018638],"type":"Point"}
}