{
  "type": "Feature",
  "properties": {
    "iso:country":"US",
    "sg:address":"31400 Avenida Ximino",
    "sg:city":"Cathedral City",
    "sg:classifiers":[
        {
            "category":"Building & Trades",
            "subcategory":"Plumbing",
            "type":"Services"
        }
    ],
    "sg:phone":"+1 760 770 9088",
    "sg:postcode":"92234",
    "sg:province":"CA",
    "wof:name":"L K Plumbing Inc",
    "wof:placetype":"venue"
},
  "geometry": {"coordinates":[-116.465034,33.820266],"type":"Point"}
}