{
  "type": "Feature",
  "properties": {
    "iso:country":"US",
    "sg:address":"4450 E Belmont Ave",
    "sg:city":"Fresno",
    "sg:classifiers":[
        {
            "category":"Retail",
            "subcategory":"Auto Repair",
            "type":"Services"
        }
    ],
    "sg:phone":"+1 559 252 3726",
    "sg:postcode":"93702",
    "sg:province":"CA",
    "sg:tags":[
        "muffler",
        "exhaust",
        "system"
    ],
    "wof:name":"A Better Auto & Muffler Svc",
    "wof:placetype":"venue"
},
  "geometry": {"coordinates":[-119.75093099999999,36.750386],"type":"Point"}
}