{
  "type": "Feature",
  "properties": {
    "iso:country":"US",
    "sg:address":"15651 Pasadena Ave Apt G",
    "sg:city":"Tustin",
    "sg:classifiers":[
        {
            "category":"Shopping",
            "type":"Retail Goods"
        }
    ],
    "sg:phone":"+1 714 315 2030",
    "sg:postcode":"92780",
    "sg:province":"CA",
    "sg:tags":[
        "merchandise"
    ],
    "wof:name":"Discount Electric",
    "wof:placetype":"venue"
},
  "geometry": {"coordinates":[-117.83181399999999,33.736268],"type":"Point"}
}