{
  "type": "Feature",
  "properties": {
    "iso:country":"US",
    "sg:address":"4100 Pin Oak Park Blvd",
    "sg:city":"Bakersfield",
    "sg:classifiers":[
        {
            "category":"Organizations",
            "subcategory":"Religious Organization",
            "type":"Services"
        }
    ],
    "sg:phone":"+1 661 664 1604",
    "sg:postcode":"93311",
    "sg:province":"CA",
    "sg:tags":[
        "church"
    ],
    "wof:name":"Church Of Jesus Christ Of Lds",
    "wof:placetype":"venue"
},
  "geometry": {"coordinates":[-119.09879100000001,35.316666],"type":"Point"}
}