{
  "type": "Feature",
  "properties": {
    "addr:full":"1986 S Victoria Ave Ventura CA 93003",
    "addr:housenumber":"1986",
    "addr:postcode":"93003",
    "addr:street":"S Victoria Ave",
    "iso:country":"US",
    "sg:address":"1986 S Victoria Ave",
    "sg:city":"Ventura",
    "sg:classifiers":[
        {
            "category":"Professional",
            "subcategory":"Lawyer & Legal Services",
            "type":"Services"
        }
    ],
    "sg:phone":"+1 805 658 0655",
    "sg:postcode":"93003",
    "sg:province":"CA",
    "sg:tags":[
        "attorney"
    ],
    "wof:name":"Stenzel & Koehn",
    "wof:placetype":"venue"
},
  "geometry": {"coordinates":[-119.21049499999999,34.256674],"type":"Point"}
}