{
  "type": "Feature",
  "properties": {
    "iso:country":"US",
    "sg:address":"920 S 1st St",
    "sg:city":"King City",
    "sg:classifiers":[
        {
            "category":"Autos & Motor Vehicles",
            "subcategory":"Fuel & Gas Station",
            "type":"Retail Goods"
        }
    ],
    "sg:phone":"+1 831 385 5786",
    "sg:postcode":"93930",
    "sg:province":"CA",
    "sg:tags":[
        "oil"
    ],
    "wof:name":"Trevino's Shell",
    "wof:placetype":"venue"
},
  "geometry": {"coordinates":[-121.113237,36.202769],"type":"Point"}
}