{
  "type": "Feature",
  "properties": {
    "iso:country":"US",
    "sg:address":"100 W Tehachapi Blvd",
    "sg:city":"Tehachapi",
    "sg:classifiers":[
        {
            "category":"Shopping",
            "subcategory":"Gifts & Souvenirs",
            "type":"Retail Goods"
        }
    ],
    "sg:phone":"+1 661 822 6062",
    "sg:postcode":"93561",
    "sg:province":"CA",
    "sg:tags":[
        "shop"
    ],
    "sg:website":"www.galleryngifts.com",
    "wof:name":"Gallery N Gifts",
    "wof:placetype":"venue"
},
  "geometry": {"coordinates":[-118.449083,35.132321],"type":"Point"}
}