{
  "type": "Feature",
  "properties": {
    "iso:country":"US",
    "sg:address":"1721 Garnet Ave",
    "sg:city":"San Diego",
    "sg:classifiers":[
        {
            "category":"Communications",
            "type":"Services"
        }
    ],
    "sg:phone":"+1 858 453 4321",
    "sg:postcode":"92109",
    "sg:province":"CA",
    "sg:tags":[
        "communication"
    ],
    "wof:name":"Enfusion Communications",
    "wof:placetype":"venue"
},
  "geometry": {"coordinates":[-117.237517,32.800446],"type":"Point"}
}