{
  "type": "Feature",
  "properties": {
    "addr:full":"845 Sousa Ln Napa CA 94559",
    "addr:housenumber":"845",
    "addr:postcode":"94559",
    "addr:street":"Sousa Ln",
    "iso:country":"US",
    "sg:address":"845 Sousa Ln",
    "sg:city":"Napa",
    "sg:classifiers":[
        {
            "category":"Building & Trades",
            "subcategory":"Electrical",
            "type":"Services"
        }
    ],
    "sg:phone":"+1 707 252 0450",
    "sg:postcode":"94559",
    "sg:province":"CA",
    "sg:tags":[
        "electric",
        "contractor"
    ],
    "wof:name":"Silverado Electric",
    "wof:placetype":"venue"
},
  "geometry": {"coordinates":[-122.27701,38.292489],"type":"Point"}
}