{
  "type": "Feature",
  "properties": {
    "iso:country":"US",
    "sg:address":"5355 Monterey Frontage Rd",
    "sg:city":"Gilroy",
    "sg:classifiers":[
        {
            "category":"Wholesale",
            "subcategory":"Farm Supplies",
            "type":"Manufacturing & Wholesale Goods"
        }
    ],
    "sg:phone":"+1 408 847 4242",
    "sg:postcode":"95020",
    "sg:province":"CA",
    "sg:tags":[
        "bulb",
        "seed"
    ],
    "wof:name":"Syngenta Seeds Inc",
    "wof:placetype":"venue"
},
  "geometry": {"coordinates":[-121.555728,36.976304],"type":"Point"}
}