{
  "type": "Feature",
  "properties": {
    "addr:full":"10990 California Avenue Lynwood CA 90262",
    "addr:housenumber":"10990",
    "addr:postcode":"90262",
    "addr:street":"California Avenue",
    "iso:country":"US",
    "sg:address":"10990 California Avenue",
    "sg:city":"Lynwood",
    "sg:classifiers":[
        {
            "category":"Organizations",
            "subcategory":"Religious Organization",
            "type":"Services"
        }
    ],
    "sg:phone":"+1 310 635 7184",
    "sg:postcode":"90262",
    "sg:province":"CA",
    "wof:name":"St Emydius Catholic School",
    "wof:placetype":"venue"
},
  "geometry": {"coordinates":[-118.20862700000001,33.933118],"type":"Point"}
}