{
  "type": "Feature",
  "properties": {
    "iso:country":"US",
    "sg:address":"334 Via Vera Cruz",
    "sg:city":"San Marcos",
    "sg:classifiers":[
        {
            "category":"Government",
            "subcategory":"Office",
            "type":"Public Place"
        }
    ],
    "sg:phone":"+1 760 510 5850",
    "sg:postcode":"92078",
    "sg:province":"CA",
    "sg:tags":[
        "equalization",
        "board"
    ],
    "wof:name":"San Marcos Office",
    "wof:placetype":"venue"
},
  "geometry": {"coordinates":[-117.188523,33.136085],"type":"Point"}
}