{
  "type": "Feature",
  "properties": {
    "addr:full":"34081 Date Palm Dr Cathedral City CA 92234",
    "addr:housenumber":"34081",
    "addr:postcode":"92234",
    "addr:street":"Date Palm Dr",
    "iso:country":"US",
    "sg:address":"34081 Date Palm Dr",
    "sg:city":"Cathedral City",
    "sg:classifiers":[
        {
            "category":"Autos & Motor Vehicles",
            "subcategory":"Auto Supplies",
            "type":"Retail Goods"
        }
    ],
    "sg:phone":"+1 760 770 4646",
    "sg:postcode":"92234",
    "sg:province":"CA",
    "sg:tags":[
        "tire"
    ],
    "sg:website":"www.goodyear.com",
    "wof:name":"Goodyear Auto Svc Ctr",
    "wof:placetype":"venue"
},
  "geometry": {"coordinates":[-116.458135,33.798413],"type":"Point"}
}