{
  "type": "Feature",
  "properties": {
    "iso:country":"US",
    "sg:address":"14400 Bear Valley Rd",
    "sg:city":"Victorville",
    "sg:classifiers":[
        {
            "category":"Food & Beverages",
            "subcategory":"Bakery",
            "type":"Retail Goods"
        }
    ],
    "sg:phone":"+1 760 241 3701",
    "sg:postcode":"92392",
    "sg:province":"CA",
    "sg:tags":[
        "pretzel"
    ],
    "wof:name":"Pretzelmaker",
    "wof:placetype":"venue"
},
  "geometry": {"coordinates":[-117.356047,34.470374],"type":"Point"}
}