{
  "type": "Feature",
  "properties": {
    "addr:full":"107 Keppel Way Cotati CA 94931",
    "addr:housenumber":"107",
    "addr:postcode":"94931",
    "addr:street":"Keppel Way",
    "iso:country":"US",
    "sg:address":"107 Keppel Way",
    "sg:city":"Cotati",
    "sg:classifiers":[
        {
            "category":"Manufacturing",
            "subcategory":"Printing",
            "type":"Manufacturing & Wholesale Goods"
        }
    ],
    "sg:phone":"+1 707 792 0322",
    "sg:postcode":"94931",
    "sg:province":"CA",
    "sg:tags":[
        "screen"
    ],
    "wof:name":"AFEX Graphics",
    "wof:placetype":"venue"
},
  "geometry": {"coordinates":[-122.694078,38.320432],"type":"Point"}
}