{
  "type": "Feature",
  "properties": {
    "addr:full":"2180 Harbor Blvd Costa Mesa CA 92627",
    "addr:housenumber":"2180",
    "addr:postcode":"92627",
    "addr:street":"Harbor Blvd Costa",
    "iso:country":"US",
    "sg:address":"2180 Harbor Blvd",
    "sg:city":"Costa Mesa",
    "sg:classifiers":[
        {
            "category":"Shopping",
            "subcategory":"Jewelry",
            "type":"Retail Goods"
        }
    ],
    "sg:phone":"+1 949 645 4481",
    "sg:postcode":"92627",
    "sg:province":"CA",
    "wof:name":"Nayarit Joyeria",
    "wof:placetype":"venue"
},
  "geometry": {"coordinates":[-117.918837,33.65351],"type":"Point"}
}