{
  "type": "Feature",
  "properties": {
    "addr:full":"5025 State Rte 140 Mariposa CA 95338",
    "addr:housenumber":"5025",
    "addr:postcode":"95338",
    "addr:street":"State Rte 140",
    "iso:country":"US",
    "sg:address":"5025 State Rte 140",
    "sg:city":"Mariposa",
    "sg:classifiers":[
        {
            "category":"Professional",
            "subcategory":"Art Services",
            "type":"Services"
        }
    ],
    "sg:phone":"+1 209 966 3122",
    "sg:postcode":"95338",
    "sg:province":"CA",
    "sg:tags":[
        "artist"
    ],
    "wof:name":"Shockley Designs Un-LTD",
    "wof:placetype":"venue"
},
  "geometry": {"coordinates":[-119.965419,37.48496],"type":"Point"}
}