{
  "type": "Feature",
  "properties": {
    "iso:country":"US",
    "sg:address":"289 Rose Lane",
    "sg:city":"Costa Mesa",
    "sg:classifiers":[
        {
            "category":"Communications",
            "type":"Services"
        }
    ],
    "sg:phone":"+1 949 554 0660",
    "sg:postcode":"92627",
    "sg:province":"CA",
    "sg:tags":[
        "web",
        "design"
    ],
    "wof:name":"Nolines4U",
    "wof:placetype":"venue"
},
  "geometry": {"coordinates":[-117.902914,33.646177],"type":"Point"}
}