{
  "type": "Feature",
  "properties": {
    "iso:country":"US",
    "sg:address":"1424 Crest Dr",
    "sg:city":"Encinitas",
    "sg:classifiers":[
        {
            "category":"Recreation",
            "type":"Entertainment"
        }
    ],
    "sg:phone":"+1 760 942 9378",
    "sg:postcode":"92024",
    "sg:province":"CA",
    "sg:tags":[
        "club",
        "membership"
    ],
    "wof:name":"Cardiff Soccer League Inc",
    "wof:placetype":"venue"
},
  "geometry": {"coordinates":[-117.263475,33.031641],"type":"Point"}
}