{
  "type": "Feature",
  "properties": {
    "iso:country":"US",
    "sg:address":"1268 W Scott Ave",
    "sg:city":"Fresno",
    "sg:classifiers":[
        {
            "category":"Shopping",
            "type":"Retail Goods"
        }
    ],
    "sg:phone":"+1 559 228 8102",
    "sg:postcode":"93711",
    "sg:province":"CA",
    "sg:tags":[
        "wedding",
        "supply"
    ],
    "wof:name":"A Perfect Wedding",
    "wof:placetype":"venue"
},
  "geometry": {"coordinates":[-119.81073,36.811161],"type":"Point"}
}