{
  "type": "Feature",
  "properties": {
    "addr:full":"3139 N Hartman St Orange CA 92865",
    "addr:housenumber":"3139",
    "addr:postcode":"92865",
    "addr:street":"N Hartman St",
    "iso:country":"US",
    "sg:address":"3139 N Hartman St",
    "sg:city":"Orange",
    "sg:classifiers":[
        {
            "category":"Autos & Motor Vehicles",
            "subcategory":"Automobile Sales",
            "type":"Retail Goods"
        }
    ],
    "sg:phone":"+1 714 720 8095",
    "sg:postcode":"92865",
    "sg:province":"CA",
    "sg:tags":[
        "new",
        "used",
        "car"
    ],
    "wof:name":"S T Motors",
    "wof:placetype":"venue"
},
  "geometry": {"coordinates":[-117.848268,33.842019],"type":"Point"}
}