{
  "type": "Feature",
  "properties": {
    "iso:country":"US",
    "sg:address":"4112 Del Rey Ave",
    "sg:city":"Marina del Rey",
    "sg:classifiers":[
        {
            "category":"Professional",
            "subcategory":"Business Services",
            "type":"Services"
        }
    ],
    "sg:phone":"+1 877 251 1494",
    "sg:postcode":"90292",
    "sg:province":"CA",
    "sg:tags":[
        "food",
        "delivery"
    ],
    "wof:name":"California Fresh & Fit",
    "wof:placetype":"venue"
},
  "geometry": {"coordinates":[-118.44417,33.988509],"type":"Point"}
}