{
  "type": "Feature",
  "properties": {
    "iso:country":"US",
    "sg:address":"1440 S State College Blvd Ste 5M",
    "sg:city":"Anaheim",
    "sg:classifiers":[
        {
            "category":"Shopping",
            "subcategory":"Stationery & Office Supplies",
            "type":"Retail Goods"
        }
    ],
    "sg:phone":"+1 714 772 7160",
    "sg:postcode":"92806",
    "sg:province":"CA",
    "sg:tags":[
        "equipment"
    ],
    "wof:name":"Business Machines Unlimited",
    "wof:placetype":"venue"
},
  "geometry": {"coordinates":[-117.88811,33.811611],"type":"Point"}
}