{
  "type": "Feature",
  "properties": {
    "iso:country":"US",
    "sg:address":"5001 Wilshire Boulevard Suite 111",
    "sg:city":"Los Angeles",
    "sg:classifiers":[
        {
            "category":"Retail",
            "subcategory":"Portrait Studio",
            "type":"Services"
        }
    ],
    "sg:phone":"+1 323 937 1414",
    "sg:postcode":"90036",
    "sg:province":"CA",
    "sg:tags":[
        "photography",
        "store"
    ],
    "wof:name":"Digital Color House",
    "wof:placetype":"venue"
},
  "geometry": {"coordinates":[-118.33851,34.062127],"type":"Point"}
}