{
  "type": "Feature",
  "properties": {
    "addr:full":"12769 Via Nieve San Diego CA 92130",
    "addr:housenumber":"12769",
    "addr:postcode":"92130",
    "addr:street":"Via Nieve",
    "iso:country":"US",
    "sg:address":"12769 Via Nieve",
    "sg:city":"San Diego",
    "sg:classifiers":[
        {
            "category":"Shopping",
            "subcategory":"Gifts & Souvenirs",
            "type":"Retail Goods"
        }
    ],
    "sg:phone":"+1 619 847 3298",
    "sg:postcode":"92130",
    "sg:province":"CA",
    "wof:name":"Cedros Treasures",
    "wof:placetype":"venue"
},
  "geometry": {"coordinates":[-117.22778,32.949488],"type":"Point"}
}