{
  "type": "Feature",
  "properties": {
    "addr:full":"8245 Ronson Rd San Diego CA 92111",
    "addr:housenumber":"8245",
    "addr:postcode":"92111",
    "addr:street":"Ronson Rd",
    "iso:country":"US",
    "sg:address":"8245 Ronson Rd",
    "sg:city":"San Diego",
    "sg:classifiers":[
        {
            "category":"Manufacturing",
            "subcategory":"Tools & Machinery",
            "type":"Manufacturing & Wholesale Goods"
        }
    ],
    "sg:phone":"+1 858 565 4556",
    "sg:postcode":"92111",
    "sg:province":"CA",
    "sg:tags":[
        "machine",
        "shop"
    ],
    "wof:name":"Inno Tech Machining",
    "wof:placetype":"venue"
},
  "geometry": {"coordinates":[-117.14363899999999,32.828598],"type":"Point"}
}