{
  "type": "Feature",
  "properties": {
    "iso:country":"US",
    "sg:address":"42454 4th St E",
    "sg:city":"Lancaster",
    "sg:classifiers":[
        {
            "category":"Professional",
            "type":"Services"
        }
    ],
    "sg:phone":"+1 661 949 0343",
    "sg:postcode":"93535",
    "sg:province":"CA",
    "sg:tags":[
        "establishment"
    ],
    "wof:name":"Central Division Detectives",
    "wof:placetype":"venue"
},
  "geometry": {"coordinates":[-118.12324099999999,34.654056],"type":"Point"}
}