{
  "type": "Feature",
  "properties": {
    "iso:country":"US",
    "sg:address":"692 E Ann Dr",
    "sg:city":"Reedley",
    "sg:classifiers":[
        {
            "category":"Building & Trades",
            "subcategory":"Construction",
            "type":"Services"
        }
    ],
    "sg:phone":"+1 559 638 6661",
    "sg:postcode":"93654",
    "sg:province":"CA",
    "sg:tags":[
        "clearing",
        "land",
        "leveling"
    ],
    "wof:name":"Y-K Laser Leveling Inc",
    "wof:placetype":"venue"
},
  "geometry": {"coordinates":[-119.442356,36.609313],"type":"Point"}
}