{
  "type": "Feature",
  "properties": {
    "addr:full":"2200 Glenridge Rd Escondido CA 92027",
    "addr:housenumber":"2200",
    "addr:postcode":"92027",
    "addr:street":"Glenridge Rd",
    "iso:country":"US",
    "sg:address":"2200 Glenridge Rd",
    "sg:city":"Escondido",
    "sg:classifiers":[
        {
            "category":"Education",
            "subcategory":"School",
            "type":"Public Place"
        }
    ],
    "sg:phone":"+1 760 291 5000",
    "sg:postcode":"92027",
    "sg:province":"CA",
    "sg:website":"http://www.escusd.k12.ca.us",
    "wof:name":"Orange Glen High School Njrotc",
    "wof:placetype":"venue"
},
  "geometry": {"coordinates":[-117.040249,33.128382],"type":"Point"}
}