{
  "type": "Feature",
  "properties": {
    "iso:country":"US",
    "sg:address":"105 Bronson St",
    "sg:city":"Santa Cruz",
    "sg:classifiers":[
        {
            "category":"Retail",
            "subcategory":"Auto Repair",
            "type":"Services"
        }
    ],
    "sg:phone":"+1 831 459 8258",
    "sg:postcode":"95062",
    "sg:province":"CA",
    "sg:tags":[
        "body",
        "automobile",
        "painting"
    ],
    "wof:name":"LA Vars Auto",
    "wof:placetype":"venue"
},
  "geometry": {"coordinates":[-122.006835,36.968772],"type":"Point"}
}