{
  "type": "Feature",
  "properties": {
    "iso:country":"US",
    "sg:address":"607 S Hill St",
    "sg:city":"Los Angeles",
    "sg:classifiers":[
        {
            "category":"Professional",
            "type":"Services"
        }
    ],
    "sg:phone":"+1 213 689 0989",
    "sg:postcode":"90014",
    "sg:province":"CA",
    "sg:tags":[
        "establishment"
    ],
    "wof:name":"Pheonix Gems Inc",
    "wof:placetype":"venue"
},
  "geometry": {"coordinates":[-118.254439,34.046043],"type":"Point"}
}