{
  "type": "Feature",
  "properties": {
    "iso:country":"US",
    "sg:address":"120 W Bellevue Dr",
    "sg:city":"Pasadena",
    "sg:classifiers":[
        {
            "category":"Professional",
            "type":"Services"
        },
        {
            "category":"Real Estate",
            "subcategory":"Real Estate Agent",
            "type":"Services"
        }
    ],
    "sg:phone":"+1 626 577 5007",
    "sg:postcode":"91105",
    "sg:province":"CA",
    "wof:name":"Realty Investore Advisors",
    "wof:placetype":"venue"
},
  "geometry": {"coordinates":[-118.15340399999999,34.138245],"type":"Point"}
}