{
  "type": "Feature",
  "properties": {
    "addr:full":"4412 Piedmont Ave Oakland CA 94611",
    "addr:housenumber":"4412",
    "addr:postcode":"94611",
    "addr:street":"Piedmont Ave",
    "iso:country":"US",
    "sg:address":"4412 Piedmont Ave",
    "sg:city":"Oakland",
    "sg:classifiers":[
        {
            "category":"Shopping",
            "subcategory":"Clothing, Apparel, & Fashions",
            "type":"Retail Goods"
        }
    ],
    "sg:phone":"+1 510 652 6936",
    "sg:postcode":"94611",
    "sg:province":"CA",
    "sg:tags":[
        "alteration"
    ],
    "wof:name":"Bonnie Carpenter-Fine Clothing",
    "wof:placetype":"venue"
},
  "geometry": {"coordinates":[-122.24547200000001,37.831633],"type":"Point"}
}