{
  "type": "Feature",
  "properties": {
    "iso:country":"US",
    "sg:address":"1950 E 4th St",
    "sg:city":"Long Beach",
    "sg:classifiers":[
        {
            "category":"Home & Garden",
            "subcategory":"Furniture",
            "type":"Retail Goods"
        }
    ],
    "sg:phone":"+1 562 590 9794",
    "sg:postcode":"90802",
    "sg:province":"CA",
    "wof:name":"Sleep Express",
    "wof:placetype":"venue"
},
  "geometry": {"coordinates":[-118.168063,33.771632],"type":"Point"}
}