{
  "type": "Feature",
  "properties": {
    "addr:full":"5892 Magnolia Ave Riverside CA 92506",
    "addr:housenumber":"5892",
    "addr:postcode":"92506",
    "addr:street":"Magnolia Ave",
    "iso:country":"US",
    "sg:address":"5892 Magnolia Ave",
    "sg:city":"Riverside",
    "sg:classifiers":[
        {
            "category":"Banks & Credit Unions",
            "subcategory":"Bank",
            "type":"Services"
        }
    ],
    "sg:phone":"+1 951 686 9639",
    "sg:postcode":"92506",
    "sg:province":"CA",
    "sg:tags":[
        "loan",
        "real estate"
    ],
    "wof:name":"Standard Mortgage Financial",
    "wof:placetype":"venue"
},
  "geometry": {"coordinates":[-117.390711,33.96243],"type":"Point"}
}