{
  "type": "Feature",
  "properties": {
    "iso:country":"US",
    "sg:address":"1000 Broadway",
    "sg:city":"Oakland",
    "sg:classifiers":[
        {
            "category":"Professional",
            "type":"Services"
        }
    ],
    "sg:phone":"+1 510 457 4300",
    "sg:postcode":"94607",
    "sg:province":"CA",
    "sg:tags":[
        "establishment"
    ],
    "sg:website":"www.montclare.com",
    "wof:name":"Montclare Technology",
    "wof:placetype":"venue"
},
  "geometry": {"coordinates":[-122.272535,37.802292],"type":"Point"}
}