{
  "type": "Feature",
  "properties": {
    "iso:country":"US",
    "sg:address":"303 Columbus Ave",
    "sg:city":"San Francisco",
    "sg:classifiers":[
        {
            "category":"Restaurant",
            "type":"Food & Drink"
        }
    ],
    "sg:menulink":"http://www.allmenus.com/ca/san-francisco/48548-giordanos/menu/",
    "sg:phone":"+1 415 397 2767",
    "sg:postcode":"94133",
    "sg:province":"CA",
    "sg:tags":[
        "american",
        "italian",
        "pizza"
    ],
    "wof:name":"Giordano's",
    "wof:placetype":"venue"
},
  "geometry": {"coordinates":[-122.40783,37.798588],"type":"Point"}
}