{
  "type": "Feature",
  "properties": {
    "iso:country":"US",
    "sg:address":"4672 E Shields Ave",
    "sg:city":"Fresno",
    "sg:classifiers":[
        {
            "category":"Real Estate",
            "subcategory":"Real Estate Operator",
            "type":"Services"
        }
    ],
    "sg:phone":"+1 559 452 0690",
    "sg:postcode":"93726",
    "sg:province":"CA",
    "sg:tags":[
        "apartment"
    ],
    "wof:name":"Gateway Apartments",
    "wof:placetype":"venue"
},
  "geometry": {"coordinates":[-119.742001,36.779489],"type":"Point"}
}