{
  "type": "Feature",
  "properties": {
    "addr:full":"7772 Santa Monica Blvd West Hollywood CA 90046",
    "addr:housenumber":"7772",
    "addr:postcode":"90046",
    "addr:street":"Santa Monica Blvd",
    "iso:country":"US",
    "sg:address":"7772 Santa Monica Blvd",
    "sg:city":"West Hollywood",
    "sg:classifiers":[
        {
            "category":"Arts & Performance",
            "subcategory":"Art Gallery",
            "type":"Entertainment"
        }
    ],
    "sg:phone":"+1 323 654 6223",
    "sg:postcode":"90046",
    "sg:province":"CA",
    "sg:website":"www.weidmangallery.com",
    "wof:name":"Weidman Gallery & Framing",
    "wof:placetype":"venue"
},
  "geometry": {"coordinates":[-118.35901699999999,34.090534],"type":"Point"}
}