{
  "type": "Feature",
  "properties": {
    "addr:full":"10090 Arlington Ave Riverside CA 92503",
    "addr:housenumber":"10090",
    "addr:postcode":"92503",
    "addr:street":"Arlington Ave",
    "iso:country":"US",
    "sg:address":"10090 Arlington Ave",
    "sg:city":"Riverside",
    "sg:classifiers":[
        {
            "category":"Retail",
            "subcategory":"Auto Repair",
            "type":"Services"
        }
    ],
    "sg:phone":"+1 951 359 0498",
    "sg:postcode":"92503",
    "sg:province":"CA",
    "sg:tags":[
        "muffler",
        "exhaust",
        "system"
    ],
    "wof:name":"Discount Mufflers",
    "wof:placetype":"venue"
},
  "geometry": {"coordinates":[-117.474948,33.94648],"type":"Point"}
}