{
  "type": "Feature",
  "properties": {
    "iso:country":"US",
    "sg:address":"1275 Central Blvd",
    "sg:city":"Brentwood",
    "sg:classifiers":[
        {
            "category":"Real Estate",
            "subcategory":"Real Estate Services",
            "type":"Services"
        },
        {
            "category":"Real Estate",
            "subcategory":"Real Estate Operator",
            "type":"Services"
        }
    ],
    "sg:phone":"+1 925 513 1110",
    "sg:postcode":"94513",
    "sg:province":"CA",
    "sg:tags":[
        "vacancy",
        "apartment",
        "rental",
        "listing"
    ],
    "wof:name":"Town Centre Commons",
    "wof:placetype":"venue"
},
  "geometry": {"coordinates":[-121.697998,37.939499],"type":"Point"}
}