{
  "type": "Feature",
  "properties": {
    "addr:full":"2036 N Raymond Ave Pasadena CA 91103",
    "addr:housenumber":"2036",
    "addr:postcode":"91103",
    "addr:street":"N Raymond Ave",
    "iso:country":"US",
    "sg:address":"2036 N Raymond Ave",
    "sg:city":"Pasadena",
    "sg:classifiers":[
        {
            "category":"Retail",
            "subcategory":"Repair Shop",
            "type":"Services"
        }
    ],
    "sg:phone":"+1 323 478 9894",
    "sg:postcode":"91103",
    "sg:province":"CA",
    "sg:tags":[
        "refrigerator",
        "freezer"
    ],
    "wof:name":"Pinto Refrigeration & Appl Svc",
    "wof:placetype":"venue"
},
  "geometry": {"coordinates":[-118.149175,34.177918],"type":"Point"}
}