{
  "type": "Feature",
  "properties": {
    "addr:full":"6411 W Imperial Hwy Los Angeles CA 90045",
    "addr:housenumber":"6411",
    "addr:postcode":"90045",
    "addr:street":"W Imperial Hwy",
    "iso:country":"US",
    "sg:address":"6411 W Imperial Hwy",
    "sg:city":"Los Angeles",
    "sg:classifiers":[
        {
            "category":"Retail",
            "subcategory":"Auto Repair",
            "type":"Services"
        }
    ],
    "sg:phone":"+1 310 215 5713",
    "sg:postcode":"90045",
    "sg:province":"CA",
    "sg:website":"www.mercuryservice.com",
    "wof:name":"Mercury Service",
    "wof:placetype":"venue"
},
  "geometry": {"coordinates":[-118.39946,33.932054],"type":"Point"}
}