{
  "type": "Feature",
  "properties": {
    "addr:full":"2050 University Ave Berkeley CA 94704",
    "addr:housenumber":"2050",
    "addr:postcode":"94704",
    "addr:street":"University Ave",
    "iso:country":"US",
    "sg:address":"2050 University Ave",
    "sg:city":"Berkeley",
    "sg:classifiers":[
        {
            "category":"Bars & Pubs",
            "type":"Food & Drink"
        },
        {
            "category":"Bars & Pubs",
            "subcategory":"Lounge",
            "type":"Food & Drink"
        },
        {
            "category":"Restaurant",
            "type":"Food & Drink"
        },
        {
            "category":"Bars & Pubs",
            "subcategory":"Sports Bar",
            "type":"Food & Drink"
        }
    ],
    "sg:phone":"+1 510 705 1450",
    "sg:postcode":"94704",
    "sg:province":"CA",
    "sg:tags":[
        "gastropubs"
    ],
    "sg:website":"www.berkeleymeridian.com",
    "wof:name":"Meridian International Sports Cafe",
    "wof:placetype":"venue"
},
  "geometry": {"coordinates":[-122.26958500000001,37.871927],"type":"Point"}
}