{
  "type": "Feature",
  "properties": {
    "iso:country":"US",
    "sg:address":"4948 Trent Dr",
    "sg:city":"San Jose",
    "sg:classifiers":[
        {
            "category":"Retail",
            "subcategory":"Car Wash",
            "type":"Services"
        }
    ],
    "sg:phone":"+1 408 559 1827",
    "sg:postcode":"95124",
    "sg:province":"CA",
    "sg:tags":[
        "automobile",
        "detail",
        "clean"
    ],
    "wof:name":"Showroom Finish Auto Detailing",
    "wof:placetype":"venue"
},
  "geometry": {"coordinates":[-121.92397699999999,37.249495],"type":"Point"}
}