{
  "type": "Feature",
  "properties": {
    "iso:country":"US",
    "sg:address":"12289 S Mac Donough Ave",
    "sg:city":"Reedley",
    "sg:classifiers":[
        {
            "category":"Farming",
            "subcategory":"Orchard",
            "type":"Manufacturing & Wholesale Goods"
        }
    ],
    "sg:phone":"+1 559 897 7824",
    "sg:postcode":"93654",
    "sg:province":"CA",
    "sg:tags":[
        "citrus",
        "grove",
        "fruit"
    ],
    "wof:name":"Bill Richardson",
    "wof:placetype":"venue"
},
  "geometry": {"coordinates":[-119.493668,36.581938],"type":"Point"}
}