{
  "type": "Feature",
  "properties": {
    "iso:country":"US",
    "sg:address":"7248 S Land Park Dr",
    "sg:city":"Sacramento",
    "sg:classifiers":[
        {
            "category":"Health Services",
            "subcategory":"Chiropractor",
            "type":"Services"
        }
    ],
    "sg:phone":"+1 916 393 9011",
    "sg:postcode":"95831",
    "sg:province":"CA",
    "wof:name":"Brian Shepherd Chiropractic",
    "wof:placetype":"venue"
},
  "geometry": {"coordinates":[-121.51145,38.494202],"type":"Point"}
}