{
  "type": "Feature",
  "properties": {
    "addr:full":"728 Danielle St Escalon CA 95320",
    "addr:housenumber":"728",
    "addr:postcode":"95320",
    "addr:street":"Danielle St",
    "iso:country":"US",
    "sg:address":"728 Danielle St",
    "sg:city":"Escalon",
    "sg:classifiers":[
        {
            "category":"Wholesale",
            "subcategory":"Non-durable Goods",
            "type":"Manufacturing & Wholesale Goods"
        }
    ],
    "sg:phone":"+1 209 838 3155",
    "sg:postcode":"95320",
    "sg:province":"CA",
    "wof:name":"Coleyjo Distributing",
    "wof:placetype":"venue"
},
  "geometry": {"coordinates":[-120.995334,37.805789],"type":"Point"}
}