{
  "type": "Feature",
  "properties": {
    "iso:country":"US",
    "sg:address":"1010 State St",
    "sg:city":"Santa Barbara",
    "sg:classifiers":[
        {
            "category":"Banks & Credit Unions",
            "subcategory":"Bank",
            "type":"Services"
        }
    ],
    "sg:phone":"+1 805 963 7511",
    "sg:postcode":"93101",
    "sg:province":"CA",
    "sg:website":"www.montecito.com",
    "wof:name":"Montecito Bankcorp",
    "wof:placetype":"venue"
},
  "geometry": {"coordinates":[-119.703007,34.42238],"type":"Point"}
}