{
  "type": "Feature",
  "properties": {
    "addr:full":"8700 Reseda Blvd Northridge CA 91324",
    "addr:housenumber":"8700",
    "addr:postcode":"91324",
    "addr:street":"Reseda Blvd",
    "iso:country":"US",
    "sg:address":"8700 Reseda Blvd",
    "sg:city":"Northridge",
    "sg:classifiers":[
        {
            "category":"Professional",
            "type":"Services"
        }
    ],
    "sg:phone":"+1 818 709 8455",
    "sg:postcode":"91324",
    "sg:province":"CA",
    "wof:name":"Coast To Coast Financial Servi",
    "wof:placetype":"venue"
},
  "geometry": {"coordinates":[-118.53608199999999,34.2294],"type":"Point"}
}