{
  "type": "Feature",
  "properties": {
    "iso:country":"US",
    "sg:address":"134 Rose Ln",
    "sg:city":"Saint Helena",
    "sg:classifiers":[
        {
            "category":"Restaurant",
            "type":"Food & Drink"
        }
    ],
    "sg:phone":"+1 707 963 5330",
    "sg:postcode":"94574",
    "sg:province":"CA",
    "wof:name":"Roux",
    "wof:placetype":"venue"
},
  "geometry": {"coordinates":[-122.476997,38.5378],"type":"Point"}
}