{
  "type": "Feature",
  "properties": {
    "addr:full":"13914 Bora Bora Way Marina Del Rey CA 90292",
    "addr:housenumber":"13914",
    "addr:postcode":"90292",
    "addr:street":"Bora Bora Way",
    "iso:country":"US",
    "sg:address":"13914 Bora Bora Way",
    "sg:city":"Marina Del Rey",
    "sg:classifiers":[
        {
            "category":"Shopping",
            "subcategory":"Computers & Home Electronics",
            "type":"Retail Goods"
        }
    ],
    "sg:phone":"+1 310 578 1020",
    "sg:postcode":"90292",
    "sg:province":"CA",
    "wof:name":"Tech Northwest Inc",
    "wof:placetype":"venue"
},
  "geometry": {"coordinates":[-118.45386000000001,33.971143],"type":"Point"}
}