{
  "type": "Feature",
  "properties": {
    "iso:country":"US",
    "sg:address":"4282 Rafael St",
    "sg:city":"Irvine",
    "sg:classifiers":[
        {
            "category":"Shopping",
            "subcategory":"Gifts & Souvenirs",
            "type":"Retail Goods"
        }
    ],
    "sg:phone":"+1 949 559 9406",
    "sg:postcode":"92604",
    "sg:province":"CA",
    "wof:name":"Enchanted Memories",
    "wof:placetype":"venue"
},
  "geometry": {"coordinates":[-117.786903,33.698958],"type":"Point"}
}