{
  "type": "Feature",
  "properties": {
    "addr:full":"320 W Washington St San Diego CA 92103",
    "addr:housenumber":"320",
    "addr:postcode":"92103",
    "addr:street":"W Washington St",
    "iso:country":"US",
    "sg:address":"320 W Washington St",
    "sg:city":"San Diego",
    "sg:classifiers":[
        {
            "category":"Personal",
            "subcategory":"Beauty Salon",
            "type":"Services"
        },
        {
            "category":"Personal",
            "subcategory":"Skin Care",
            "type":"Services"
        }
    ],
    "sg:phone":"+1 619 295 4166",
    "sg:postcode":"92103",
    "sg:province":"CA",
    "sg:tags":[
        "hair"
    ],
    "sg:website":"genesisthesalonandspa.com",
    "wof:name":"Genesis The Salon",
    "wof:placetype":"venue"
},
  "geometry": {"coordinates":[-117.16661499999999,32.750123],"type":"Point"}
}