{
  "type": "Feature",
  "properties": {
    "addr:full":"9601 Broad Stripes Way Elk Grove CA 95624",
    "addr:housenumber":"9601",
    "addr:postcode":"95624",
    "addr:street":"Broad Stripes Way",
    "iso:country":"US",
    "sg:address":"9601 Broad Stripes Way",
    "sg:city":"Elk Grove",
    "sg:classifiers":[
        {
            "category":"Building & Trades",
            "subcategory":"Construction",
            "type":"Services"
        }
    ],
    "sg:phone":"+1 916 685 7800",
    "sg:postcode":"95624",
    "sg:province":"CA",
    "sg:tags":[
        "general",
        "contractor"
    ],
    "wof:name":"Zenco Construction",
    "wof:placetype":"venue"
},
  "geometry": {"coordinates":[-121.33729200000001,38.420961],"type":"Point"}
}