{
  "type": "Feature",
  "properties": {
    "addr:full":"636 Larchmont Dr Daly City CA 94015",
    "addr:housenumber":"636",
    "addr:postcode":"94015",
    "addr:street":"Larchmont Dr",
    "iso:country":"US",
    "sg:address":"636 Larchmont Dr",
    "sg:city":"Daly City",
    "sg:classifiers":[
        {
            "category":"Professional",
            "subcategory":"Engineering",
            "type":"Services"
        }
    ],
    "sg:phone":"+1 650 758 2686",
    "sg:postcode":"94015",
    "sg:province":"CA",
    "sg:tags":[
        "general",
        "contractor"
    ],
    "wof:name":"MHN Structech Consulting",
    "wof:placetype":"venue"
},
  "geometry": {"coordinates":[-122.483643,37.688822],"type":"Point"}
}