{
  "type": "Feature",
  "properties": {
    "iso:country":"US",
    "sg:address":"1235 Buena Vista St",
    "sg:city":"Duarte",
    "sg:classifiers":[
        {
            "category":"Health Services",
            "subcategory":"Optometrist",
            "type":"Services"
        }
    ],
    "sg:phone":"+1 626 359 8145",
    "sg:postcode":"91010",
    "sg:province":"CA",
    "wof:name":"Duarte Optometry",
    "wof:placetype":"venue"
},
  "geometry": {"coordinates":[-117.977547,34.138892],"type":"Point"}
}