{
  "type": "Feature",
  "properties": {
    "iso:country":"US",
    "sg:address":"1926 W Orangewood Ave",
    "sg:city":"Orange",
    "sg:classifiers":[
        {
            "category":"Home & Garden",
            "subcategory":"Home Furnishings",
            "type":"Retail Goods"
        }
    ],
    "sg:phone":"+1 714 773 1777",
    "sg:postcode":"92868",
    "sg:province":"CA",
    "wof:name":"Decor & More",
    "wof:placetype":"venue"
},
  "geometry": {"coordinates":[-117.872863,33.795651],"type":"Point"}
}