{
  "type": "Feature",
  "properties": {
    "addr:full":"201 S 3rd St Grover Beach CA 93433",
    "addr:housenumber":"201",
    "addr:postcode":"93433",
    "addr:street":"S 3Rd St",
    "iso:country":"US",
    "sg:address":"201 S 3rd St",
    "sg:city":"Grover Beach",
    "sg:classifiers":[
        {
            "category":"Building & Trades",
            "subcategory":"Construction",
            "type":"Services"
        }
    ],
    "sg:phone":"+1 805 489 8231",
    "sg:postcode":"93433",
    "sg:province":"CA",
    "sg:tags":[
        "roofing",
        "contractor"
    ],
    "wof:name":"C & S Roofing",
    "wof:placetype":"venue"
},
  "geometry": {"coordinates":[-120.627706,35.120768],"type":"Point"}
}