{
  "type": "Feature",
  "properties": {
    "iso:country":"US",
    "sg:address":"437 N Euclid Ave",
    "sg:city":"Ontario",
    "sg:classifiers":[
        {
            "category":"Health Services",
            "subcategory":"Doctor",
            "type":"Services"
        }
    ],
    "sg:phone":"+1 909 988 2555",
    "sg:postcode":"91762",
    "sg:province":"CA",
    "sg:tags":[
        "clinic"
    ],
    "wof:name":"Medical Center Of Santa Rita",
    "wof:placetype":"venue"
},
  "geometry": {"coordinates":[-117.651089,34.067783],"type":"Point"}
}