{
  "type": "Feature",
  "properties": {
    "iso:country":"US",
    "sg:address":"24964 Valley Way",
    "sg:city":"Carmel",
    "sg:classifiers":[
        {
            "category":"Professional",
            "subcategory":"Business Services",
            "type":"Services"
        }
    ],
    "sg:phone":"+1 831 622 9382",
    "sg:postcode":"93923",
    "sg:province":"CA",
    "sg:tags":[
        "interior",
        "consultant",
        "design",
        "decorator"
    ],
    "sg:website":"www.alexdes.com",
    "wof:name":"Alexander Design Assoc",
    "wof:placetype":"venue"
},
  "geometry": {"coordinates":[-121.912278,36.560585],"type":"Point"}
}