{
  "type": "Feature",
  "properties": {
    "addr:full":"345 Oak Avenue San Bruno, Ca 94066",
    "wof:categories":[
        "education_and_religion:education=school"
    ],
    "wof:name":"Saint Robert Elementary School",
    "wof:placetype":"venue"
},
  "geometry": {"coordinates":[-122.41562838269307,37.61722720917601],"type":"Point"}
}