{
  "type": "Feature",
  "properties": {
    "addr:full":"3880 S El Camino Real San Mateo CA 94403",
    "addr:housenumber":"3880",
    "addr:postcode":"94403",
    "addr:street":"S El Camino Real",
    "iso:country":"US",
    "sg:address":"3880 S El Camino Real",
    "sg:city":"San Mateo",
    "sg:classifiers":[
        {
            "category":"Restaurant",
            "type":"Food & Drink"
        }
    ],
    "sg:phone":"+1 650 341 1446",
    "sg:postcode":"94403",
    "sg:province":"CA",
    "wof:name":"Subway Sandwiches",
    "wof:placetype":"venue"
},
  "geometry": {"coordinates":[-122.29298900000001,37.532962],"type":"Point"}
}