{
  "type": "Feature",
  "properties": {
    "iso:country":"US",
    "sg:address":"48501 Warm Springs Blvd",
    "sg:city":"Fremont",
    "sg:classifiers":[
        {
            "category":"Wholesale",
            "subcategory":"Durable Goods & Equipment",
            "type":"Manufacturing & Wholesale Goods"
        }
    ],
    "sg:phone":"+1 510 659 9245",
    "sg:postcode":"94539",
    "sg:province":"CA",
    "sg:tags":[
        "representative",
        "manufacturer"
    ],
    "wof:name":"CKD",
    "wof:placetype":"venue"
},
  "geometry": {"coordinates":[-121.917478,37.468823],"type":"Point"}
}