{
  "type": "Feature",
  "properties": {
    "iso:country":"US",
    "sg:address":"44436 15th St E",
    "sg:city":"Lancaster",
    "sg:classifiers":[
        {
            "category":"Travel",
            "subcategory":"Travel Agent",
            "type":"Entertainment"
        }
    ],
    "sg:phone":"+1 661 940 8136",
    "sg:postcode":"93535",
    "sg:province":"CA",
    "sg:tags":[
        "agency"
    ],
    "wof:name":"Gary Travel Agency",
    "wof:placetype":"venue"
},
  "geometry": {"coordinates":[-118.103601,34.690854],"type":"Point"}
}