{
  "type": "Feature",
  "properties": {
    "iso:country":"US",
    "sg:address":"725 S Eliseo Dr Apt 5",
    "sg:city":"Greenbrae",
    "sg:classifiers":[
        {
            "category":"Professional",
            "type":"Services"
        }
    ],
    "sg:phone":"+1 415 464 0774",
    "sg:postcode":"94904",
    "sg:province":"CA",
    "sg:tags":[
        "publication",
        "editorial"
    ],
    "wof:name":"Benedict & Nancy Freedman",
    "wof:placetype":"venue"
},
  "geometry": {"coordinates":[-122.53099400000001,37.944555],"type":"Point"}
}