{
  "type": "Feature",
  "properties": {
    "addr:full":"3614 Arden Dr Ste D1 El Monte CA 91731",
    "addr:housenumber":"3614",
    "addr:postcode":"91731",
    "addr:street":"Arden Dr Ste D1",
    "iso:country":"US",
    "sg:address":"3614 Arden Dr Ste D1",
    "sg:city":"El Monte",
    "sg:classifiers":[
        {
            "category":"Retail",
            "subcategory":"Repair Shop",
            "type":"Services"
        },
        {
            "category":"Professional",
            "subcategory":"Business Services",
            "type":"Services"
        }
    ],
    "sg:phone":"+1 626 444 7410",
    "sg:postcode":"91731",
    "sg:province":"CA",
    "sg:tags":[
        "delivery",
        "reupholstery",
        "courier",
        "furniture"
    ],
    "wof:name":"Merlo's Co",
    "wof:placetype":"venue"
},
  "geometry": {"coordinates":[-118.047997,34.073399],"type":"Point"}
}