{
  "type": "Feature",
  "properties": {
    "iso:country":"US",
    "sg:address":"145 S Humboldt St",
    "sg:city":"Willits",
    "sg:classifiers":[
        {
            "category":"Organizations",
            "subcategory":"Non-profit Organization",
            "type":"Services"
        }
    ],
    "sg:phone":"+1 707 459 9431",
    "sg:postcode":"95490",
    "sg:province":"CA",
    "sg:tags":[
        "information",
        "alcoholism",
        "treatment"
    ],
    "wof:name":"Lucky Deuce",
    "wof:placetype":"venue"
},
  "geometry": {"coordinates":[-123.35321500000001,39.411003],"type":"Point"}
}