{
  "type": "Feature",
  "properties": {
    "iso:country":"US",
    "sg:address":"4728 E 2nd St",
    "sg:city":"Benicia",
    "sg:classifiers":[
        {
            "category":"Organizations",
            "subcategory":"Religious Organization",
            "type":"Services"
        }
    ],
    "sg:phone":"+1 707 747 5522",
    "sg:postcode":"94510",
    "sg:province":"CA",
    "sg:tags":[
        "church"
    ],
    "sg:website":"www.eastgatechurch.com",
    "wof:name":"Eastgate Christian Church",
    "wof:placetype":"venue"
},
  "geometry": {"coordinates":[-122.12688900000001,38.080905],"type":"Point"}
}