{
  "type": "Feature",
  "properties": {
    "addr:full":"1555 Mendocino Dr Chula Vista CA 91911",
    "addr:housenumber":"1555",
    "addr:postcode":"91911",
    "addr:street":"Mendocino Dr",
    "iso:country":"US",
    "sg:address":"1555 Mendocino Dr",
    "sg:city":"Chula Vista",
    "sg:classifiers":[
        {
            "category":"Building & Trades",
            "subcategory":"Construction",
            "type":"Services"
        }
    ],
    "sg:phone":"+1 619 397 5956",
    "sg:postcode":"91911",
    "sg:province":"CA",
    "sg:tags":[
        "coping",
        "plastering",
        "tiling",
        "pool",
        "swimming"
    ],
    "wof:name":"Sharko Pool Svc & Maintenance",
    "wof:placetype":"venue"
},
  "geometry": {"coordinates":[-117.02981699999999,32.601209],"type":"Point"}
}