{
  "type": "Feature",
  "properties": {
    "addr:full":"750 Oriental Ave Redlands CA 92374",
    "addr:housenumber":"750",
    "addr:postcode":"92374",
    "addr:street":"Oriental Ave",
    "iso:country":"US",
    "sg:address":"750 Oriental Ave",
    "sg:city":"Redlands",
    "sg:classifiers":[
        {
            "category":"Professional",
            "type":"Services"
        }
    ],
    "sg:phone":"+1 909 798 2699",
    "sg:postcode":"92374",
    "sg:province":"CA",
    "sg:tags":[
        "establishment"
    ],
    "wof:name":"Novus Internatl",
    "wof:placetype":"venue"
},
  "geometry": {"coordinates":[-117.186846,34.058586],"type":"Point"}
}