{
  "type": "Feature",
  "properties": {
    "iso:country":"US",
    "sg:address":"21038 Adamson Dr",
    "sg:city":"Grass Valley",
    "sg:classifiers":[
        {
            "category":"Travel",
            "subcategory":"Travel Agent",
            "type":"Entertainment"
        }
    ],
    "sg:phone":"+1 530 268 1756",
    "sg:postcode":"95949",
    "sg:province":"CA",
    "sg:tags":[
        "agency"
    ],
    "wof:name":"Dream Maker Travel",
    "wof:placetype":"venue"
},
  "geometry": {"coordinates":[-121.03348200000001,39.070246],"type":"Point"}
}