{
  "type": "Feature",
  "properties": {
    "iso:country":"US",
    "sg:address":"9315 Narrows Dr",
    "sg:city":"Pico Rivera",
    "sg:classifiers":[
        {
            "category":"Shopping",
            "subcategory":"Clothing, Apparel, & Fashions",
            "type":"Retail Goods"
        }
    ],
    "sg:phone":"+1 562 692 1810",
    "sg:postcode":"90660",
    "sg:province":"CA",
    "sg:tags":[
        "item",
        "boutique"
    ],
    "wof:name":"Juliejeans Boutique",
    "wof:placetype":"venue"
},
  "geometry": {"coordinates":[-118.062889,34.019247],"type":"Point"}
}