{
  "type": "Feature",
  "properties": {
    "iso:country":"US",
    "sg:address":"1445 S Lemon St",
    "sg:city":"Fullerton",
    "sg:classifiers":[
        {
            "category":"Restaurant",
            "type":"Food & Drink"
        }
    ],
    "sg:phone":"+1 714 447 1200",
    "sg:postcode":"92832",
    "sg:province":"CA",
    "sg:tags":[
        "steakhouse",
        "brazilian"
    ],
    "sg:website":"www.amazonbbq.com",
    "wof:name":"Amazon Churrascaria",
    "wof:placetype":"venue"
},
  "geometry": {"coordinates":[-117.91999800000001,33.855099],"type":"Point"}
}