{
  "type": "Feature",
  "properties": {
    "addr:full":"27 Woodward Ct Crockett CA 94525",
    "addr:housenumber":"27",
    "addr:postcode":"94525",
    "addr:street":"Woodward Ct",
    "iso:country":"US",
    "sg:address":"27 Woodward Ct",
    "sg:city":"Crockett",
    "sg:classifiers":[
        {
            "category":"Shopping",
            "subcategory":"Clothing, Apparel, & Fashions",
            "type":"Retail Goods"
        }
    ],
    "sg:phone":"+1 510 787 2151",
    "sg:postcode":"94525",
    "sg:province":"CA",
    "wof:name":"First Collection",
    "wof:placetype":"venue"
},
  "geometry": {"coordinates":[-122.21668,38.050954],"type":"Point"}
}