{
  "type": "Feature",
  "properties": {
    "addr:full":"3824 N Montpelier Rd Denair CA 95316",
    "addr:housenumber":"3824",
    "addr:postcode":"95316",
    "addr:street":"N Montpelier Rd",
    "iso:country":"US",
    "sg:address":"3824 N Montpelier Rd",
    "sg:city":"Denair",
    "sg:classifiers":[
        {
            "category":"Wholesale",
            "subcategory":"Groceries",
            "type":"Manufacturing & Wholesale Goods"
        }
    ],
    "sg:phone":"+1 209 874 5488",
    "sg:postcode":"95316",
    "sg:province":"CA",
    "sg:tags":[
        "grocer"
    ],
    "wof:name":"Cordova & Cordova",
    "wof:placetype":"venue"
},
  "geometry": {"coordinates":[-120.685715,37.523423],"type":"Point"}
}