{
  "type": "Feature",
  "properties": {
    "iso:country":"US",
    "sg:address":"6536 Pacific Blvd",
    "sg:city":"Huntington Park",
    "sg:classifiers":[
        {
            "category":"Shopping",
            "subcategory":"Clothing, Apparel, & Fashions",
            "type":"Retail Goods"
        }
    ],
    "sg:phone":"+1 323 582 5843",
    "sg:postcode":"90255",
    "sg:province":"CA",
    "sg:tags":[
        "maternity",
        "wear"
    ],
    "wof:name":"Shine On",
    "wof:placetype":"venue"
},
  "geometry": {"coordinates":[-118.224998,33.979599],"type":"Point"}
}