{
  "type": "Feature",
  "properties": {
    "addr:full":"2125 Knoll Dr Ventura CA 93003",
    "addr:housenumber":"2125",
    "addr:postcode":"93003",
    "addr:street":"Knoll Dr",
    "iso:country":"US",
    "sg:address":"2125 Knoll Dr",
    "sg:city":"Ventura",
    "sg:classifiers":[
        {
            "category":"Restaurant",
            "type":"Food & Drink"
        },
        {
            "category":"Insurance",
            "subcategory":"Insurance Agent",
            "type":"Services"
        }
    ],
    "sg:phone":"+1 805 650 2100",
    "sg:postcode":"93003",
    "sg:province":"CA",
    "sg:tags":[
        "management",
        "broker"
    ],
    "wof:name":"Alliance United Insurance Svcs",
    "wof:placetype":"venue"
},
  "geometry": {"coordinates":[-119.218479,34.25175],"type":"Point"}
}