{
  "type": "Feature",
  "properties": {
    "iso:country":"US",
    "sg:address":"113 Avenue F",
    "sg:city":"Barstow",
    "sg:classifiers":[
        {
            "category":"Place Of Worship",
            "subcategory":"Church",
            "type":"Public Place"
        },
        {
            "category":"Place Of Worship",
            "type":"Public Place"
        }
    ],
    "sg:phone":"+1 760 256 1802",
    "sg:postcode":"92311",
    "sg:province":"CA",
    "sg:tags":[
        "churches-interdenominational",
        "churches-various",
        "denomination"
    ],
    "wof:name":"Mojave Desert Christian Church",
    "wof:placetype":"venue"
},
  "geometry": {"coordinates":[-117.041037,34.895578],"type":"Point"}
}