{
  "type": "Feature",
  "properties": {
    "iso:country":"US",
    "sg:address":"8468 Venus Dr",
    "sg:city":"Buena Park",
    "sg:classifiers":[
        {
            "category":"Professional",
            "subcategory":"Art Services",
            "type":"Services"
        }
    ],
    "sg:phone":"+1 714 527 9065",
    "sg:postcode":"90620",
    "sg:province":"CA",
    "sg:tags":[
        "graphic",
        "designer"
    ],
    "wof:name":"Brad Jansen Design",
    "wof:placetype":"venue"
},
  "geometry": {"coordinates":[-117.986399,33.842671],"type":"Point"}
}