{
  "type": "Feature",
  "properties": {
    "iso:country":"US",
    "sg:address":"229 34th St",
    "sg:city":"Bakersfield",
    "sg:classifiers":[
        {
            "category":"Home & Garden",
            "subcategory":"Furniture",
            "type":"Retail Goods"
        }
    ],
    "sg:phone":"+1 661 327 8811",
    "sg:postcode":"93301",
    "sg:province":"CA",
    "sg:tags":[
        "top",
        "counter"
    ],
    "wof:name":"Welch's Counter Tops",
    "wof:placetype":"venue"
},
  "geometry": {"coordinates":[-119.008005,35.390406],"type":"Point"}
}