{
  "type": "Feature",
  "properties": {
    "addr:full":"21028 Barrett Smith Rd Dulzura CA 91917",
    "addr:housenumber":"21028",
    "addr:postcode":"91917",
    "addr:street":"Barrett Smith Rd",
    "iso:country":"US",
    "sg:address":"21028 Barrett Smith Rd",
    "sg:city":"Dulzura",
    "sg:classifiers":[
        {
            "category":"Building & Trades",
            "subcategory":"Landscaping Services",
            "type":"Services"
        }
    ],
    "sg:phone":"+1 619 468 3197",
    "sg:postcode":"91917",
    "sg:province":"CA",
    "sg:tags":[
        "tree"
    ],
    "wof:name":"Bob Magoffin & Sons Tree Svc",
    "wof:placetype":"venue"
},
  "geometry": {"coordinates":[-116.69829300000001,32.610435],"type":"Point"}
}