{
  "type": "Feature",
  "properties": {
    "iso:country":"US",
    "sg:address":"121 E 5th St",
    "sg:city":"Los Angeles",
    "sg:classifiers":[
        {
            "category":"Travel",
            "subcategory":"Hotels & Motels",
            "type":"Entertainment"
        }
    ],
    "sg:phone":"+1 213 972 9187",
    "sg:postcode":"90013",
    "sg:province":"CA",
    "wof:name":"King Edward Hotel",
    "wof:placetype":"venue"
},
  "geometry": {"coordinates":[-118.248001,34.046398],"type":"Point"}
}