{
  "type": "Feature",
  "properties": {
    "addr:full":"10560 Wilshire Blvd Los Angeles CA 90024",
    "addr:postcode":"10560;90024",
    "addr:street":"Wilshire Blvd",
    "iso:country":"US",
    "sg:address":"10560 Wilshire Blvd",
    "sg:city":"Los Angeles",
    "sg:classifiers":[
        {
            "category":"Professional",
            "subcategory":"Management & Consulting",
            "type":"Services"
        }
    ],
    "sg:phone":"+1 310 470 4503",
    "sg:postcode":"90024",
    "sg:province":"CA",
    "sg:tags":[
        "construction"
    ],
    "wof:name":"Zinger Construction Mgmt Co",
    "wof:placetype":"venue"
},
  "geometry": {"coordinates":[-118.43370299999999,34.061532],"type":"Point"}
}