{
  "type": "Feature",
  "properties": {
    "iso:country":"US",
    "sg:address":"4444 Hansen Ave",
    "sg:city":"Fremont",
    "sg:classifiers":[
        {
            "category":"Freight",
            "type":"Transportation"
        }
    ],
    "sg:phone":"+1 510 797 5086",
    "sg:postcode":"94536",
    "sg:province":"CA",
    "sg:tags":[
        "operator",
        "local",
        "trucking"
    ],
    "wof:name":"Bring Trucking",
    "wof:placetype":"venue"
},
  "geometry": {"coordinates":[-122.012858,37.553831],"type":"Point"}
}