{
  "type": "Feature",
  "properties": {
    "addr:full":"1319 Magazine St Vallejo CA 94591",
    "addr:housenumber":"1319",
    "addr:postcode":"94591",
    "addr:street":"Magazine St",
    "iso:country":"US",
    "sg:address":"1319 Magazine St",
    "sg:city":"Vallejo",
    "sg:classifiers":[
        {
            "category":"Building & Trades",
            "subcategory":"Landscaping Services",
            "type":"Services"
        }
    ],
    "sg:phone":"+1 707 290 6573",
    "sg:postcode":"94591",
    "sg:province":"CA",
    "sg:tags":[
        "lawn",
        "maintenance",
        "grounds"
    ],
    "wof:name":"Rodriguez Lawn & Landscaping",
    "wof:placetype":"venue"
},
  "geometry": {"coordinates":[-122.22721199999999,38.084777],"type":"Point"}
}