{
  "type": "Feature",
  "properties": {
    "addr:full":"13191 Franklin Ave Mountain View CA 94040",
    "addr:housenumber":"13191",
    "addr:postcode":"94040",
    "addr:street":"Franklin Ave",
    "iso:country":"US",
    "sg:address":"13191 Franklin Ave",
    "sg:city":"Mountain View",
    "sg:classifiers":[
        {
            "category":"Manufacturing",
            "subcategory":"Metals",
            "type":"Manufacturing & Wholesale Goods"
        }
    ],
    "sg:phone":"+1 650 964 8252",
    "sg:postcode":"94040",
    "sg:province":"CA",
    "sg:tags":[
        "fabricated",
        "mfg"
    ],
    "wof:name":"Kbs",
    "wof:placetype":"venue"
},
  "geometry": {"coordinates":[-122.068405,37.36957],"type":"Point"}
}