{
  "type": "Feature",
  "properties": {
    "addr:full":"759 Linden Ave Long Beach CA 90813",
    "addr:housenumber":"759",
    "addr:postcode":"90813",
    "addr:street":"Linden Ave",
    "iso:country":"US",
    "sg:address":"759 Linden Ave",
    "sg:city":"Long Beach",
    "sg:classifiers":[
        {
            "category":"Organizations",
            "subcategory":"Religious Organization",
            "type":"Services"
        }
    ],
    "sg:phone":"+1 562 437 4002",
    "sg:postcode":"90813",
    "sg:province":"CA",
    "sg:tags":[
        "church"
    ],
    "wof:name":"Trinity Lutheran Church",
    "wof:placetype":"venue"
},
  "geometry": {"coordinates":[-118.18642800000001,33.776248],"type":"Point"}
}