{
  "type": "Feature",
  "properties": {
    "addr:full":"521 E 11th St Los Angeles CA 90015",
    "addr:housenumber":"521",
    "addr:postcode":"90015",
    "addr:street":"E 11Th St",
    "iso:country":"US",
    "sg:address":"521 E 11th St",
    "sg:city":"Los Angeles",
    "sg:classifiers":[
        {
            "category":"Wholesale",
            "subcategory":"Apparel",
            "type":"Manufacturing & Wholesale Goods"
        }
    ],
    "sg:phone":"+1 213 742 0046",
    "sg:postcode":"90015",
    "sg:province":"CA",
    "wof:name":"Yaffa Collection",
    "wof:placetype":"venue"
},
  "geometry": {"coordinates":[-118.253264,34.036048],"type":"Point"}
}