{
  "type": "Feature",
  "properties": {
    "iso:country":"US",
    "sg:address":"61 Via Floreado",
    "sg:city":"Orinda",
    "sg:classifiers":[
        {
            "category":"Wholesale",
            "subcategory":"Computers",
            "type":"Manufacturing & Wholesale Goods"
        }
    ],
    "sg:phone":"+1 925 254 2960",
    "sg:postcode":"94563",
    "sg:province":"CA",
    "sg:tags":[
        "computer-wholesale",
        "manufacturer"
    ],
    "wof:name":"Beal Systems Inc",
    "wof:placetype":"venue"
},
  "geometry": {"coordinates":[-122.176239,37.895433],"type":"Point"}
}