{
  "type": "Feature",
  "properties": {
    "iso:country":"US",
    "sg:address":"7415 Eigleberry St",
    "sg:city":"Gilroy",
    "sg:classifiers":[
        {
            "category":"Organizations",
            "subcategory":"Non-profit Organization",
            "type":"Services"
        }
    ],
    "sg:phone":"+1 408 847 1805",
    "sg:postcode":"95020",
    "sg:province":"CA",
    "sg:tags":[
        "human"
    ],
    "wof:name":"Silicone Independent Living",
    "wof:placetype":"venue"
},
  "geometry": {"coordinates":[-121.57061,37.007788],"type":"Point"}
}