{
  "type": "Feature",
  "properties": {
    "addr:full":"336 Fuego Ave Pomona CA 91767",
    "addr:housenumber":"336",
    "addr:postcode":"91767",
    "addr:street":"Fuego Ave",
    "iso:country":"US",
    "sg:address":"336 Fuego Ave",
    "sg:city":"Pomona",
    "sg:classifiers":[
        {
            "category":"Building & Trades",
            "subcategory":"Construction",
            "type":"Services"
        }
    ],
    "sg:phone":"+1 909 623 1290",
    "sg:postcode":"91767",
    "sg:province":"CA",
    "sg:tags":[
        "painter"
    ],
    "wof:name":"Navajo Custom Painting",
    "wof:placetype":"venue"
},
  "geometry": {"coordinates":[-117.752886,34.107081],"type":"Point"}
}