{
  "type": "Feature",
  "properties": {
    "iso:country":"US",
    "sg:address":"521 E 11th St",
    "sg:city":"Los Angeles",
    "sg:classifiers":[
        {
            "category":"Shopping",
            "subcategory":"Clothing, Apparel, & Fashions",
            "type":"Retail Goods"
        }
    ],
    "sg:phone":"+1 213 744 1772",
    "sg:postcode":"90015",
    "sg:province":"CA",
    "sg:tags":[
        "clothing",
        "women's"
    ],
    "wof:name":"Diva Collection",
    "wof:placetype":"venue"
},
  "geometry": {"coordinates":[-118.253998,34.0364],"type":"Point"}
}