{
  "type": "Feature",
  "properties": {
    "iso:country":"US",
    "sg:address":"251 S Lincoln Ave",
    "sg:city":"Corona",
    "sg:classifiers":[
        {
            "category":"Cinema",
            "subcategory":"Movie Rental",
            "type":"Entertainment"
        }
    ],
    "sg:phone":"+1 951 371 7495",
    "sg:postcode":"92882",
    "sg:province":"CA",
    "sg:tags":[
        "leasing",
        "video",
        "disc",
        "tape"
    ],
    "wof:name":"Hollywood Video",
    "wof:placetype":"venue"
},
  "geometry": {"coordinates":[-117.58262499999999,33.880778],"type":"Point"}
}