{
  "type": "Feature",
  "properties": {
    "addr:full":"558 San Ramon Valley Blvd Danville CA 94583",
    "addr:housenumber":"558",
    "addr:postcode":"94583",
    "addr:street":"San Ramon Valley Blvd",
    "iso:country":"US",
    "sg:address":"558 San Ramon Valley Blvd",
    "sg:city":"Danville",
    "sg:classifiers":[
        {
            "category":"Restaurant",
            "type":"Food & Drink"
        }
    ],
    "sg:phone":"+1 925 820 3823",
    "sg:postcode":"94583",
    "sg:province":"CA",
    "wof:name":"Sushi Tokyoya",
    "wof:placetype":"venue"
},
  "geometry": {"coordinates":[-121.99650099999999,37.81707],"type":"Point"}
}