{
  "type": "Feature",
  "properties": {
    "iso:country":"US",
    "sg:address":"364 41st St.",
    "sg:city":"Oakland",
    "sg:classifiers":[
        {
            "category":"Real Estate",
            "subcategory":"Real Estate Services",
            "type":"Services"
        }
    ],
    "sg:phone":"+1 510 547 8916",
    "sg:postcode":"94609",
    "sg:province":"CA",
    "sg:website":"www.jras.com/",
    "wof:name":"J and R Associates",
    "wof:placetype":"venue"
},
  "geometry": {"coordinates":[-122.25802,37.829192],"type":"Point"}
}