{
  "type": "Feature",
  "properties": {
    "iso:country":"US",
    "sg:address":"4131 Norse Way",
    "sg:city":"Long Beach",
    "sg:classifiers":[
        {
            "category":"Food & Beverages",
            "subcategory":"Candy",
            "type":"Retail Goods"
        },
        {
            "category":"Bakery",
            "type":"Food & Drink"
        }
    ],
    "sg:phone":"+1 562 377 6385",
    "sg:postcode":"90808",
    "sg:province":"CA",
    "sg:tags":[
        "dessert"
    ],
    "sg:website":"www.missprisscupcakes.com",
    "wof:name":"Miss Priss Cupcakes & Such",
    "wof:placetype":"venue"
},
  "geometry": {"coordinates":[-118.141507,33.832833],"type":"Point"}
}