{
  "type": "Feature",
  "properties": {
    "iso:country":"US",
    "sg:address":"1026 N Highland Ave",
    "sg:city":"Los Angeles",
    "sg:classifiers":[
        {
            "category":"Wholesale",
            "subcategory":"Photographic Equipment",
            "type":"Manufacturing & Wholesale Goods"
        }
    ],
    "sg:phone":"+1 323 466 8211",
    "sg:postcode":"90038",
    "sg:province":"CA",
    "sg:tags":[
        "motion",
        "picture",
        "supply"
    ],
    "sg:website":"www.birnsandsawyer.com",
    "wof:name":"Birns & Sawyer Inc",
    "wof:placetype":"venue"
},
  "geometry": {"coordinates":[-118.33852,34.090231],"type":"Point"}
}