{
  "type": "Feature",
  "properties": {
    "addr:full":"937 Howe Ave Sacramento CA 95825",
    "addr:housenumber":"937",
    "addr:postcode":"95825",
    "addr:street":"Howe Ave",
    "iso:country":"US",
    "sg:address":"937 Howe Ave",
    "sg:city":"Sacramento",
    "sg:classifiers":[
        {
            "category":"Shopping",
            "subcategory":"Mobile Phones",
            "type":"Retail Goods"
        }
    ],
    "sg:phone":"+1 916 567 3900",
    "sg:postcode":"95825",
    "sg:province":"CA",
    "wof:name":"Sprint",
    "wof:placetype":"venue"
},
  "geometry": {"coordinates":[-121.416,38.582401],"type":"Point"}
}