{
  "type": "Feature",
  "properties": {
    "addr:full":"3404 Ave Simi Simi Valley CA 93063",
    "addr:housenumber":"3404",
    "addr:postcode":"93063",
    "addr:street":"Ave Simi",
    "iso:country":"US",
    "sg:address":"3404 Ave Simi",
    "sg:city":"Simi Valley",
    "sg:classifiers":[
        {
            "category":"Retail",
            "subcategory":"Laundry & Dry Cleaning",
            "type":"Services"
        }
    ],
    "sg:phone":"+1 805 577 8084",
    "sg:postcode":"93063",
    "sg:province":"CA",
    "sg:tags":[
        "cleaners",
        "rug",
        "carpet"
    ],
    "wof:name":"Enviro Carpet & Floor Care",
    "wof:placetype":"venue"
},
  "geometry": {"coordinates":[-118.729006,34.289796],"type":"Point"}
}