{
  "type": "Feature",
  "properties": {
    "addr:full":"231 Old Bernal Ave Pleasanton CA 94566",
    "addr:housenumber":"231",
    "addr:postcode":"94566",
    "addr:street":"Old Bernal Ave",
    "iso:country":"US",
    "sg:address":"231 Old Bernal Ave",
    "sg:city":"Pleasanton",
    "sg:classifiers":[
        {
            "category":"Professional",
            "subcategory":"Research",
            "type":"Services"
        }
    ],
    "sg:phone":"+1 925 462 6803",
    "sg:postcode":"94566",
    "sg:province":"CA",
    "wof:name":"Javelin Strategy & Research",
    "wof:placetype":"venue"
},
  "geometry": {"coordinates":[-121.87888599999999,37.658625],"type":"Point"}
}