{
  "type": "Feature",
  "properties": {
    "iso:country":"US",
    "sg:address":"5731 Delbrook Ln",
    "sg:city":"Carmichael",
    "sg:classifiers":[
        {
            "category":"Professional",
            "subcategory":"Art Services",
            "type":"Services"
        }
    ],
    "sg:phone":"+1 916 487 7567",
    "sg:postcode":"95608",
    "sg:province":"CA",
    "sg:tags":[
        "designer",
        "display",
        "producer"
    ],
    "wof:name":"Green Line Design",
    "wof:placetype":"venue"
},
  "geometry": {"coordinates":[-121.33101600000001,38.652096],"type":"Point"}
}