{
  "type": "Feature",
  "properties": {
    "iso:country":"US",
    "sg:address":"3320 Auburn Blvd",
    "sg:city":"Sacramento",
    "sg:classifiers":[
        {
            "category":"Professional",
            "subcategory":"Management & Consulting",
            "type":"Services"
        }
    ],
    "sg:phone":"+1 916 679 0447",
    "sg:postcode":"95821",
    "sg:province":"CA",
    "sg:tags":[
        "consultant",
        "financing"
    ],
    "wof:name":"C Fg. Financial",
    "wof:placetype":"venue"
},
  "geometry": {"coordinates":[-121.386965,38.635603],"type":"Point"}
}