{
  "type": "Feature",
  "properties": {
    "iso:country":"US",
    "sg:address":"1271 S Livermore Ave",
    "sg:city":"Livermore",
    "sg:classifiers":[
        {
            "category":"Travel",
            "subcategory":"Travel Agent",
            "type":"Entertainment"
        }
    ],
    "sg:phone":"+1 925 455 5441",
    "sg:postcode":"94550",
    "sg:province":"CA",
    "sg:tags":[
        "agency"
    ],
    "wof:name":"Cruise & Tour Vacations",
    "wof:placetype":"venue"
},
  "geometry": {"coordinates":[-121.753987,37.672652],"type":"Point"}
}