{
  "type": "Feature",
  "properties": {
    "iso:country":"US",
    "sg:address":"1230 W Spring St",
    "sg:city":"Riverside",
    "sg:classifiers":[
        {
            "category":"Wholesale",
            "subcategory":"Computers",
            "type":"Manufacturing & Wholesale Goods"
        }
    ],
    "sg:phone":"+1 951 686 5005",
    "sg:postcode":"92507",
    "sg:province":"CA",
    "sg:tags":[
        "equipment"
    ],
    "sg:website":"http://www.iscatech.com",
    "wof:name":"Isca Technologies, Inc.",
    "wof:placetype":"venue"
},
  "geometry": {"coordinates":[-117.338683,34.012028],"type":"Point"}
}