{
  "type": "Feature",
  "properties": {
    "addr:full":"555 S Promenade Ave Corona CA 92879",
    "addr:housenumber":"555",
    "addr:postcode":"92879",
    "addr:street":"S Promenade Ave",
    "iso:country":"US",
    "sg:address":"555 S Promenade Ave",
    "sg:city":"Corona",
    "sg:classifiers":[
        {
            "category":"Wholesale",
            "subcategory":"Office Equipment",
            "type":"Manufacturing & Wholesale Goods"
        },
        {
            "category":"Manufacturing",
            "subcategory":"Tools & Machinery",
            "type":"Manufacturing & Wholesale Goods"
        }
    ],
    "sg:phone":"+1 951 738 9431",
    "sg:postcode":"92879",
    "sg:province":"CA",
    "sg:tags":[
        "packaging",
        "machinery-wholesale",
        "manufacturer"
    ],
    "wof:name":"Deco-Pac",
    "wof:placetype":"venue"
},
  "geometry": {"coordinates":[-117.532229,33.875259],"type":"Point"}
}