{
  "type": "Feature",
  "properties": {
    "addr:full":"711 Oak St Bakersfield CA 93304",
    "addr:housenumber":"711",
    "addr:postcode":"93304",
    "addr:street":"Oak St",
    "iso:country":"US",
    "sg:address":"711 Oak St",
    "sg:city":"Bakersfield",
    "sg:classifiers":[
        {
            "category":"Autos & Motor Vehicles",
            "subcategory":"Automobile Sales",
            "type":"Retail Goods"
        }
    ],
    "sg:phone":"+1 661 864 1175",
    "sg:postcode":"93304",
    "sg:province":"CA",
    "sg:tags":[
        "dealers-used",
        "used",
        "cars-wholesale",
        "car"
    ],
    "wof:name":"Auto Planet Superstore",
    "wof:placetype":"venue"
},
  "geometry": {"coordinates":[-119.038821,35.364171],"type":"Point"}
}