{
  "type": "Feature",
  "properties": {
    "addr:full":"12153 Izetta Ave Downey CA 90242",
    "addr:housenumber":"12153",
    "addr:postcode":"90242",
    "addr:street":"Izetta Ave",
    "iso:country":"US",
    "sg:address":"12153 Izetta Ave",
    "sg:city":"Downey",
    "sg:classifiers":[
        {
            "category":"Building & Trades",
            "subcategory":"Construction",
            "type":"Services"
        }
    ],
    "sg:phone":"+1 562 923 7391",
    "sg:postcode":"90242",
    "sg:province":"CA",
    "sg:tags":[
        "contractor"
    ],
    "wof:name":"Deming Air Conditioning & Refrigeration Repair",
    "wof:placetype":"venue"
},
  "geometry": {"coordinates":[-118.12226099999999,33.923389],"type":"Point"}
}