{
  "type": "Feature",
  "properties": {
    "addr:full":"2905 San Pablo Dam Rd El Sobrante CA 94803",
    "addr:housenumber":"2905",
    "addr:postcode":"94803",
    "addr:street":"San Pablo Dam Rd",
    "iso:country":"US",
    "sg:address":"2905 San Pablo Dam Rd",
    "sg:city":"El Sobrante",
    "sg:classifiers":[
        {
            "category":"Retail",
            "subcategory":"Auto Rental",
            "type":"Services"
        }
    ],
    "sg:phone":"+1 510 223 4611",
    "sg:postcode":"94803",
    "sg:province":"CA",
    "sg:tags":[
        "renting",
        "automobile"
    ],
    "wof:name":"Montgomery Rentals",
    "wof:placetype":"venue"
},
  "geometry": {"coordinates":[-122.32939399999999,37.958601],"type":"Point"}
}