{
  "type": "Feature",
  "properties": {
    "iso:country":"US",
    "sg:address":"13923 S Archibald Ave",
    "sg:city":"Ontario",
    "sg:classifiers":[
        {
            "category":"Farming",
            "subcategory":"Farm",
            "type":"Manufacturing & Wholesale Goods"
        }
    ],
    "sg:phone":"+1 909 947 2253",
    "sg:postcode":"91761",
    "sg:province":"CA",
    "sg:tags":[
        "crop",
        "general"
    ],
    "wof:name":"SA Chul Farms",
    "wof:placetype":"venue"
},
  "geometry": {"coordinates":[-117.593141,34.003835],"type":"Point"}
}