{
  "type": "Feature",
  "properties": {
    "addr:full":"3055 India St San Diego CA 92103",
    "addr:housenumber":"3055",
    "addr:postcode":"92103",
    "addr:street":"India St",
    "iso:country":"US",
    "sg:address":"3055 India St",
    "sg:city":"San Diego",
    "sg:classifiers":[
        {
            "category":"Professional",
            "subcategory":"Lawyer & Legal Services",
            "type":"Services"
        }
    ],
    "sg:phone":"+1 619 297 7330",
    "sg:postcode":"92103",
    "sg:province":"CA",
    "wof:name":"Trucchi Theresa Atty At Law",
    "wof:placetype":"venue"
},
  "geometry": {"coordinates":[-117.175003,32.7355],"type":"Point"}
}