{
  "type": "Feature",
  "properties": {
    "iso:country":"US",
    "sg:address":"687 S Cam Real",
    "sg:city":"Palm Springs",
    "sg:classifiers":[
        {
            "category":"Real Estate",
            "subcategory":"Real Estate Operator",
            "type":"Services"
        }
    ],
    "sg:phone":"+1 760 323 7678",
    "sg:postcode":"92264",
    "sg:province":"CA",
    "sg:tags":[
        "building",
        "apartment"
    ],
    "wof:name":"Benjamin Liverman II",
    "wof:placetype":"venue"
},
  "geometry": {"coordinates":[-116.538683,33.813849],"type":"Point"}
}