{
  "type": "Feature",
  "properties": {
    "iso:country":"US",
    "sg:address":"410 Hegenberger Loop",
    "sg:city":"Oakland",
    "sg:classifiers":[
        {
            "category":"Retail",
            "subcategory":"Veterinary Services",
            "type":"Services"
        },
        {
            "category":"Retail",
            "subcategory":"Animal Services",
            "type":"Services"
        }
    ],
    "sg:phone":"+1 510 639 7387",
    "sg:postcode":"94621",
    "sg:province":"CA",
    "sg:tags":[
        "pet",
        "veterinarian"
    ],
    "sg:website":"www.eastbayspca.org/",
    "wof:name":"East Bay SPCA -- Oakland Spay & Neuter Surgery Center",
    "wof:placetype":"venue"
},
  "geometry": {"coordinates":[-122.196607,37.736963],"type":"Point"}
}