{
  "type": "Feature",
  "properties": {
    "iso:country":"US",
    "sg:address":"11275 Sunrise Gold Cir Ste U",
    "sg:city":"Rncho Cordova",
    "sg:classifiers":[
        {
            "category":"Professional",
            "subcategory":"Computer Services",
            "type":"Services"
        }
    ],
    "sg:phone":"+1 916 638 0531",
    "sg:postcode":"95742",
    "sg:province":"CA",
    "sg:tags":[
        "repair"
    ],
    "wof:name":"Computers 4 Less",
    "wof:placetype":"venue"
},
  "geometry": {"coordinates":[-121.264999,38.599701],"type":"Point"}
}