{
  "type": "Feature",
  "properties": {
    "addr:full":"8 Yosemite Ave Oakland CA 94611",
    "addr:housenumber":"8",
    "addr:postcode":"94611",
    "addr:street":"Yosemite Ave",
    "iso:country":"US",
    "sg:address":"8 Yosemite Ave",
    "sg:city":"Oakland",
    "sg:classifiers":[
        {
            "category":"Building & Trades",
            "subcategory":"Cleaning & Sanitation",
            "type":"Services"
        }
    ],
    "sg:phone":"+1 510 658 1210",
    "sg:postcode":"94611",
    "sg:province":"CA",
    "sg:tags":[
        "house"
    ],
    "wof:name":"Alain Cleaning Svc",
    "wof:placetype":"venue"
},
  "geometry": {"coordinates":[-122.254836,37.823313],"type":"Point"}
}