{
  "type": "Feature",
  "properties": {
    "addr:full":"7325 Medical Center Dr Canoga Park CA 91307",
    "addr:housenumber":"7325",
    "addr:postcode":"91307",
    "addr:street":"Medical Center Dr",
    "iso:country":"US",
    "sg:address":"7325 Medical Center Dr",
    "sg:city":"Canoga Park",
    "sg:classifiers":[
        {
            "category":"Freight",
            "type":"Transportation"
        }
    ],
    "sg:phone":"+1 818 884 5450",
    "sg:postcode":"91307",
    "sg:province":"CA",
    "wof:name":"Diamex US",
    "wof:placetype":"venue"
},
  "geometry": {"coordinates":[-118.631826,34.203637],"type":"Point"}
}