{
  "type": "Feature",
  "properties": {
    "addr:full":"1063 Diablo Ave Chico CA 95973",
    "addr:housenumber":"1063",
    "addr:postcode":"95973",
    "addr:street":"Diablo Ave",
    "iso:country":"US",
    "sg:address":"1063 Diablo Ave",
    "sg:city":"Chico",
    "sg:classifiers":[
        {
            "category":"Health Services",
            "subcategory":"Health Practitioner",
            "type":"Services"
        }
    ],
    "sg:phone":"+1 530 343 8202",
    "sg:postcode":"95973",
    "sg:province":"CA",
    "sg:tags":[
        "hypnotist"
    ],
    "wof:name":"Kaleidoscopes",
    "wof:placetype":"venue"
},
  "geometry": {"coordinates":[-121.83881100000001,39.771497],"type":"Point"}
}