{
  "type": "Feature",
  "properties": {
    "addr:full":"2305 Banbury Loop Martinez CA 94553",
    "addr:housenumber":"2305",
    "addr:postcode":"94553",
    "addr:street":"Banbury Loop",
    "iso:country":"US",
    "sg:address":"2305 Banbury Loop",
    "sg:city":"Martinez",
    "sg:classifiers":[
        {
            "category":"Wholesale",
            "subcategory":"Furniture",
            "type":"Manufacturing & Wholesale Goods"
        }
    ],
    "sg:phone":"+1 925 228 6683",
    "sg:postcode":"94553",
    "sg:province":"CA",
    "wof:name":"Del Prato Interiors & Assoc",
    "wof:placetype":"venue"
},
  "geometry": {"coordinates":[-122.08630700000001,37.999869],"type":"Point"}
}