{
  "type": "Feature",
  "properties": {
    "iso:country":"US",
    "sg:address":"521 D St",
    "sg:city":"Upland",
    "sg:classifiers":[
        {
            "category":"Building & Trades",
            "subcategory":"Landscaping Services",
            "type":"Services"
        }
    ],
    "sg:phone":"+1 909 763 1966",
    "sg:postcode":"91786",
    "sg:province":"CA",
    "sg:tags":[
        "tree"
    ],
    "wof:name":"Navidad Tree Service",
    "wof:placetype":"venue"
},
  "geometry": {"coordinates":[-117.646119,34.09851],"type":"Point"}
}