{
  "type": "Feature",
  "properties": {
    "iso:country":"US",
    "sg:address":"730 E Easy St",
    "sg:city":"Simi Valley",
    "sg:classifiers":[
        {
            "category":"Shopping",
            "type":"Retail Goods"
        }
    ],
    "sg:phone":"+1 805 522 6646",
    "sg:postcode":"93065",
    "sg:province":"CA",
    "sg:tags":[
        "telescope"
    ],
    "wof:name":"Scope City",
    "wof:placetype":"venue"
},
  "geometry": {"coordinates":[-118.78165,34.273578],"type":"Point"}
}