{
  "type": "Feature",
  "properties": {
    "iso:country":"US",
    "sg:address":"2490 W Shaw Ave",
    "sg:city":"Fresno",
    "sg:classifiers":[
        {
            "category":"Wholesale",
            "subcategory":"Construction Materials",
            "type":"Manufacturing & Wholesale Goods"
        }
    ],
    "sg:phone":"+1 559 439 5076",
    "sg:postcode":"93711",
    "sg:province":"CA",
    "sg:tags":[
        "elevator"
    ],
    "wof:name":"Mwk 2 Inc.",
    "wof:placetype":"venue"
},
  "geometry": {"coordinates":[-119.837864,36.808383],"type":"Point"}
}