{
  "type": "Feature",
  "properties": {
    "addr:full":"2353 Foothill Blvd La Verne CA 91750",
    "addr:housenumber":"2353",
    "addr:postcode":"91750",
    "addr:street":"Foothill Blvd",
    "iso:country":"US",
    "sg:address":"2353 Foothill Blvd",
    "sg:city":"La Verne",
    "sg:classifiers":[
        {
            "category":"Retail",
            "subcategory":"Laundry & Dry Cleaning",
            "type":"Services"
        }
    ],
    "sg:phone":"+1 909 593 3600",
    "sg:postcode":"91750",
    "sg:province":"CA",
    "sg:tags":[
        "cleaners"
    ],
    "wof:name":"Rainbow Cleaners",
    "wof:placetype":"venue"
},
  "geometry": {"coordinates":[-117.760885,34.112008],"type":"Point"}
}