{
  "type": "Feature",
  "properties": {
    "addr:full":"4761 Cass St San Diego CA 92109",
    "addr:housenumber":"4761",
    "addr:postcode":"92109",
    "addr:street":"Cass St",
    "iso:country":"US",
    "sg:address":"4761 Cass St",
    "sg:city":"San Diego",
    "sg:classifiers":[
        {
            "category":"Social Services",
            "type":"Services"
        }
    ],
    "sg:phone":"+1 858 483 8208",
    "sg:postcode":"92109",
    "sg:province":"CA",
    "sg:tags":[
        "youth",
        "organization",
        "center"
    ],
    "wof:name":"24 Hour Youth Hotline",
    "wof:placetype":"venue"
},
  "geometry": {"coordinates":[-117.252999,32.801378],"type":"Point"}
}