{
  "type": "Feature",
  "properties": {
    "iso:country":"US",
    "sg:address":"1166 Esplanade",
    "sg:city":"Chico",
    "sg:classifiers":[
        {
            "category":"Personal",
            "subcategory":"Beauty Salon",
            "type":"Services"
        }
    ],
    "sg:phone":"+1 530 899 8773",
    "sg:postcode":"95926",
    "sg:province":"CA",
    "wof:name":"Body Resort",
    "wof:placetype":"venue"
},
  "geometry": {"coordinates":[-121.845902,39.738196],"type":"Point"}
}