{
  "type": "Feature",
  "properties": {
    "addr:full":"2737 Elks Way Napa CA 94558",
    "addr:housenumber":"2737",
    "addr:postcode":"94558",
    "addr:street":"Elks Way",
    "iso:country":"US",
    "sg:address":"2737 Elks Way",
    "sg:city":"Napa",
    "sg:classifiers":[
        {
            "category":"Shopping",
            "subcategory":"Catalog Store",
            "type":"Retail Goods"
        }
    ],
    "sg:phone":"+1 707 888 5023",
    "sg:postcode":"94558",
    "sg:province":"CA",
    "sg:tags":[
        "house",
        "mail"
    ],
    "wof:name":"Creative Peddler",
    "wof:placetype":"venue"
},
  "geometry": {"coordinates":[-122.2834,38.319466],"type":"Point"}
}