{
  "type": "Feature",
  "properties": {
    "addr:full":"24 Corporate Plaza Dr Ste 100 Newport Beach CA 92660",
    "addr:housenumber":"24",
    "addr:postcode":"92660",
    "addr:street":"Plaza Dr Ste 100",
    "iso:country":"US",
    "sg:address":"24 Corporate Plaza Dr Ste 100",
    "sg:city":"Newport Beach",
    "sg:classifiers":[
        {
            "category":"Professional",
            "subcategory":"Lawyer & Legal Services",
            "type":"Services"
        }
    ],
    "sg:phone":"+1 949 640 7208",
    "sg:postcode":"92660",
    "sg:province":"CA",
    "sg:website":"www.lawsonmarketing.com",
    "wof:name":"Lawson Marketing Group The",
    "wof:placetype":"venue"
},
  "geometry": {"coordinates":[-117.874667,33.607864],"type":"Point"}
}