{
  "type": "Feature",
  "properties": {
    "addr:full":"762 Stewart Ct Alameda CA 94501",
    "addr:housenumber":"762",
    "addr:postcode":"94501",
    "addr:street":"Stewart Ct",
    "iso:country":"US",
    "sg:address":"762 Stewart Ct",
    "sg:city":"Alameda",
    "sg:classifiers":[
        {
            "category":"Building & Trades",
            "subcategory":"Construction",
            "type":"Services"
        }
    ],
    "sg:phone":"+1 510 865 3350",
    "sg:postcode":"94501",
    "sg:province":"CA",
    "sg:tags":[
        "repairing",
        "remodeling",
        "contractor"
    ],
    "sg:website":"www.thomasmeansinc.com",
    "wof:name":"Thomas Means Design & Constr",
    "wof:placetype":"venue"
},
  "geometry": {"coordinates":[-122.273133,37.778877],"type":"Point"}
}