{
  "type": "Feature",
  "properties": {
    "iso:country":"US",
    "sg:address":"11645 Riverside Dr",
    "sg:city":"Lakeside",
    "sg:classifiers":[
        {
            "category":"Utilities",
            "subcategory":"Water",
            "type":"Services"
        }
    ],
    "sg:phone":"+1 619 328 0498",
    "sg:postcode":"92040",
    "sg:province":"CA",
    "sg:tags":[
        "consultant"
    ],
    "wof:name":"Maki Manufacturing Inc",
    "wof:placetype":"venue"
},
  "geometry": {"coordinates":[-116.942009,32.862667],"type":"Point"}
}