{
  "type": "Feature",
  "properties": {
    "iso:country":"US",
    "sg:address":"8550 Chetle Ave",
    "sg:city":"Whittier",
    "sg:classifiers":[
        {
            "category":"Manufacturing",
            "subcategory":"Wood Products",
            "type":"Manufacturing & Wholesale Goods"
        }
    ],
    "sg:phone":"+1 562 968 2000",
    "sg:postcode":"90606",
    "sg:province":"CA",
    "sg:tags":[
        "picture",
        "frame"
    ],
    "sg:website":"www.nielsen-bainbridge.com",
    "wof:name":"Nielsen & Bainbridge",
    "wof:placetype":"venue"
},
  "geometry": {"coordinates":[-118.05499,33.963677],"type":"Point"}
}