{
  "type": "Feature",
  "properties": {
    "addr:full":"2307 W Empire Ave Burbank CA 91504",
    "addr:housenumber":"2307",
    "addr:postcode":"91504",
    "addr:street":"W Empire Ave",
    "iso:country":"US",
    "sg:address":"2307 W Empire Ave",
    "sg:city":"Burbank",
    "sg:classifiers":[
        {
            "category":"Health Services",
            "subcategory":"Doctor",
            "type":"Services"
        }
    ],
    "sg:phone":"+1 818 841 3420",
    "sg:postcode":"91504",
    "sg:province":"CA",
    "wof:name":"Nazo Samir MD",
    "wof:placetype":"venue"
},
  "geometry": {"coordinates":[-118.335999,34.1917],"type":"Point"}
}