{
  "type": "Feature",
  "properties": {
    "iso:country":"US",
    "sg:address":"10951 Barnett Valley Rd",
    "sg:city":"Sebastopol",
    "sg:classifiers":[
        {
            "category":"Farming",
            "subcategory":"Farm",
            "type":"Manufacturing & Wholesale Goods"
        },
        {
            "category":"Farming",
            "subcategory":"Farm & Veterinary Services",
            "type":"Manufacturing & Wholesale Goods"
        }
    ],
    "sg:phone":"+1 707 823 6528",
    "sg:postcode":"95472",
    "sg:province":"CA",
    "sg:tags":[
        "management",
        "eating"
    ],
    "wof:name":"Orchards Farms",
    "wof:placetype":"venue"
},
  "geometry": {"coordinates":[-122.890399,38.365962],"type":"Point"}
}