{
  "type": "Feature",
  "properties": {
    "addr:full":"212 S State College Blvd Anaheim CA 92806",
    "addr:housenumber":"212",
    "addr:postcode":"92806",
    "addr:street":"S;Blvd",
    "iso:country":"US",
    "sg:address":"212 S State College Blvd",
    "sg:city":"Anaheim",
    "sg:classifiers":[
        {
            "category":"Ice Cream",
            "type":"Food & Drink"
        }
    ],
    "sg:phone":"+1 714 772 3063",
    "sg:postcode":"92806",
    "sg:province":"CA",
    "sg:tags":[
        "frozen",
        "yogurt"
    ],
    "sg:website":"www.baskinrobbins.com",
    "wof:name":"Baskin Robbins",
    "wof:placetype":"venue"
},
  "geometry": {"coordinates":[-117.889,33.839901],"type":"Point"}
}