{
  "type": "Feature",
  "properties": {
    "iso:country":"US",
    "sg:address":"5801 Durham Ferry Rd",
    "sg:city":"Tracy",
    "sg:classifiers":[
        {
            "category":"Building & Trades",
            "subcategory":"Cleaning & Sanitation",
            "type":"Services"
        }
    ],
    "sg:phone":"+1 209 836 3282",
    "sg:postcode":"95304",
    "sg:province":"CA",
    "sg:tags":[
        "janitor"
    ],
    "wof:name":"A-Z Gary's Janitorial Svc",
    "wof:placetype":"venue"
},
  "geometry": {"coordinates":[-121.379214,37.66724],"type":"Point"}
}