{
  "type": "Feature",
  "properties": {
    "iso:country":"US",
    "sg:address":"191 W Shaw Ave",
    "sg:city":"Fresno",
    "sg:classifiers":[
        {
            "category":"Banks & Credit Unions",
            "subcategory":"Bank",
            "type":"Services"
        }
    ],
    "sg:phone":"+1 559 228 8244",
    "sg:postcode":"93704",
    "sg:province":"CA",
    "sg:tags":[
        "loan",
        "real estate"
    ],
    "sg:website":"www.bankers1stmortgage.com",
    "wof:name":"Bankers First Mortgage",
    "wof:placetype":"venue"
},
  "geometry": {"coordinates":[-119.793763,36.808421],"type":"Point"}
}