{
  "type": "Feature",
  "properties": {
    "iso:country":"US",
    "sg:address":"895 Coats St",
    "sg:city":"Bishop",
    "sg:classifiers":[
        {
            "category":"Insurance",
            "subcategory":"Hazard Insurance",
            "type":"Services"
        }
    ],
    "sg:phone":"+1 760 873 4921",
    "sg:postcode":"93514",
    "sg:province":"CA",
    "sg:tags":[
        "bond"
    ],
    "wof:name":"Buckaroo Bail Bonds",
    "wof:placetype":"venue"
},
  "geometry": {"coordinates":[-118.399897,37.369547],"type":"Point"}
}