{
  "type": "Feature",
  "properties": {
    "addr:full":"6152 Mission Gorge Rd San Diego CA 92120",
    "addr:housenumber":"6152",
    "addr:postcode":"92120",
    "addr:street":"Mission Gorge Rd",
    "iso:country":"US",
    "sg:address":"6152 Mission Gorge Rd",
    "sg:city":"San Diego",
    "sg:classifiers":[
        {
            "category":"Shopping",
            "subcategory":"Hobbies, Toys, & Games",
            "type":"Retail Goods"
        }
    ],
    "sg:phone":"+1 619 516 3899",
    "sg:postcode":"92120",
    "sg:province":"CA",
    "sg:tags":[
        "equipment",
        "ceramic",
        "supply"
    ],
    "wof:name":"KITA Ceramics & Glassware",
    "wof:placetype":"venue"
},
  "geometry": {"coordinates":[-117.09781599999999,32.786266],"type":"Point"}
}