{
  "type": "Feature",
  "properties": {
    "iso:country":"US",
    "sg:address":"1221 Artesia Blvd",
    "sg:city":"Manhattan Beach",
    "sg:classifiers":[
        {
            "category":"Food & Beverages",
            "subcategory":"Groceries & Convenience Stores",
            "type":"Retail Goods"
        }
    ],
    "sg:phone":"+1 310 318 6205",
    "sg:postcode":"90266",
    "sg:province":"CA",
    "wof:name":"7-Eleven",
    "wof:placetype":"venue"
},
  "geometry": {"coordinates":[-118.3919,33.872894],"type":"Point"}
}