{
  "type": "Feature",
  "properties": {
    "iso:country":"US",
    "sg:address":"301 S Soderquist Rd",
    "sg:city":"Turlock",
    "sg:classifiers":[
        {
            "category":"Organizations",
            "subcategory":"Religious Organization",
            "type":"Services"
        }
    ],
    "sg:phone":"+1 209 669 8300",
    "sg:postcode":"95380",
    "sg:province":"CA",
    "sg:tags":[
        "church"
    ],
    "wof:name":"Calvary Chapel Of Turlock",
    "wof:placetype":"venue"
},
  "geometry": {"coordinates":[-120.862641,37.490476],"type":"Point"}
}