{
  "type": "Feature",
  "properties": {
    "addr:full":"4515 Ocean View Blvd La Canada Fltrdg CA 91011",
    "addr:housenumber":"4515",
    "addr:postcode":"91011",
    "addr:street":"Ocean View Blvd La Canada",
    "iso:country":"US",
    "sg:address":"4515 Ocean View Blvd",
    "sg:city":"La Canada Fltrdg",
    "sg:classifiers":[
        {
            "category":"Professional",
            "subcategory":"Management & Consulting",
            "type":"Services"
        }
    ],
    "sg:phone":"+1 818 542 6880",
    "sg:postcode":"91011",
    "sg:province":"CA",
    "sg:tags":[
        "counselor",
        "public",
        "relations"
    ],
    "sg:website":"www.ssanalyst.com",
    "wof:name":"Michael Baybak & Co Inc",
    "wof:placetype":"venue"
},
  "geometry": {"coordinates":[-118.227867,34.219331],"type":"Point"}
}