{
  "type": "Feature",
  "properties": {
    "addr:full":"1800 S Robertson Blvd Los Angeles CA 90035",
    "addr:housenumber":"1800",
    "addr:postcode":"90035",
    "addr:street":"S Robertson Blvd",
    "iso:country":"US",
    "sg:address":"1800 S Robertson Blvd",
    "sg:city":"Los Angeles",
    "sg:classifiers":[
        {
            "category":"Building & Trades",
            "subcategory":"Construction",
            "type":"Services"
        }
    ],
    "sg:phone":"+1 310 287 2420",
    "sg:postcode":"90035",
    "sg:province":"CA",
    "sg:tags":[
        "tile",
        "dealer"
    ],
    "wof:name":"Tile With Style",
    "wof:placetype":"venue"
},
  "geometry": {"coordinates":[-118.38633400000001,34.045812],"type":"Point"}
}