{
  "type": "Feature",
  "properties": {
    "iso:country":"US",
    "sg:address":"29280 Central Ave",
    "sg:city":"Lake Elsinore",
    "sg:classifiers":[
        {
            "category":"Retail",
            "subcategory":"Laundry & Dry Cleaning",
            "type":"Services"
        }
    ],
    "sg:phone":"+1 951 471 3770",
    "sg:postcode":"92532",
    "sg:province":"CA",
    "wof:name":"Central Cleaners",
    "wof:placetype":"venue"
},
  "geometry": {"coordinates":[-117.333,33.6959],"type":"Point"}
}