{
  "type": "Feature",
  "properties": {
    "addr:full":"946 5th Ave San Diego CA 92101",
    "addr:housenumber":"946",
    "addr:postcode":"92101",
    "addr:street":"5Th Ave",
    "iso:country":"US",
    "sg:address":"946 5th Ave",
    "sg:city":"San Diego",
    "sg:classifiers":[
        {
            "category":"Shopping",
            "subcategory":"Clothing, Apparel, & Fashions",
            "type":"Retail Goods"
        }
    ],
    "sg:phone":"+1 619 235 8999",
    "sg:postcode":"92101",
    "sg:province":"CA",
    "wof:name":"Boutique Voss",
    "wof:placetype":"venue"
},
  "geometry": {"coordinates":[-117.16023,32.715207],"type":"Point"}
}