{
  "type": "Feature",
  "properties": {
    "addr:full":"12500 State Hwy 20 Clearlake Oaks CA 95423",
    "addr:housenumber":"12500",
    "addr:postcode":"95423",
    "addr:street":"State Hwy 20 Clearlake",
    "iso:country":"US",
    "sg:address":"12500 State Hwy 20",
    "sg:city":"Clearlake Oaks",
    "sg:classifiers":[
        {
            "category":"Professional",
            "subcategory":"Accounting & Tax Preparation",
            "type":"Services"
        }
    ],
    "sg:phone":"+1 707 998 9296",
    "sg:postcode":"95423",
    "sg:province":"CA",
    "sg:tags":[
        "accountant"
    ],
    "wof:name":"Kapalahike Account Svc",
    "wof:placetype":"venue"
},
  "geometry": {"coordinates":[-122.676294,39.01982],"type":"Point"}
}