{
  "type": "Feature",
  "properties": {
    "addr:full":"697 N Euclid St Anaheim CA 92801",
    "addr:housenumber":"697",
    "addr:postcode":"92801",
    "addr:street":"N Euclid St",
    "iso:country":"US",
    "sg:address":"697 N Euclid St",
    "sg:city":"Anaheim",
    "sg:classifiers":[
        {
            "category":"Health Services",
            "subcategory":"Health Practitioner",
            "type":"Services"
        }
    ],
    "sg:phone":"+1 714 535 7508",
    "sg:postcode":"92801",
    "sg:province":"CA",
    "sg:tags":[
        "audiologists"
    ],
    "wof:name":"Anaheim Hearing Ctr",
    "wof:placetype":"venue"
},
  "geometry": {"coordinates":[-117.94166199999999,33.839814],"type":"Point"}
}