{
  "type": "Feature",
  "properties": {
    "iso:country":"US",
    "sg:address":"1321 E Thousand Oaks Blvd",
    "sg:city":"Thousand Oaks",
    "sg:classifiers":[
        {
            "category":"Shopping",
            "subcategory":"Crafts & Fabrics",
            "type":"Retail Goods"
        }
    ],
    "sg:phone":"+1 805 379 0722",
    "sg:postcode":"91362",
    "sg:province":"CA",
    "sg:tags":[
        "sewing",
        "yarn"
    ],
    "wof:name":"Eva's Needlework",
    "wof:placetype":"venue"
},
  "geometry": {"coordinates":[-118.855362,34.178132],"type":"Point"}
}