{
  "type": "Feature",
  "properties": {
    "addr:full":"15835 San Antonio Ave Chino CA 91708",
    "addr:housenumber":"15835",
    "addr:postcode":"91708",
    "addr:street":"San Antonio Ave",
    "iso:country":"US",
    "sg:address":"15835 San Antonio Ave",
    "sg:city":"Chino",
    "sg:classifiers":[
        {
            "category":"Freight",
            "type":"Transportation"
        },
        {
            "category":"Transit Center",
            "subcategory":"Freight",
            "type":"Transportation"
        },
        {
            "category":"Retail",
            "subcategory":"Storage",
            "type":"Services"
        }
    ],
    "sg:phone":"+1 909 393 7575",
    "sg:postcode":"91708",
    "sg:province":"CA",
    "sg:tags":[
        "self",
        "forwarding",
        "local",
        "trucking"
    ],
    "wof:name":"Gilbert West",
    "wof:placetype":"venue"
},
  "geometry": {"coordinates":[-117.658355,33.963556],"type":"Point"}
}