{
  "type": "Feature",
  "properties": {
    "iso:country":"US",
    "sg:address":"50 E San Fernando St",
    "sg:city":"San Jose",
    "sg:classifiers":[
        {
            "category":"Banks & Credit Unions",
            "subcategory":"Investment Brokerage",
            "type":"Services"
        }
    ],
    "sg:phone":"+1 408 283 3000",
    "sg:postcode":"95113",
    "sg:province":"CA",
    "sg:tags":[
        "advisory",
        "security",
        "planning",
        "financial",
        "consultant"
    ],
    "wof:name":"Merrill Lynch",
    "wof:placetype":"venue"
},
  "geometry": {"coordinates":[-121.887087,37.335319],"type":"Point"}
}