{
  "type": "Feature",
  "properties": {
    "iso:country":"US",
    "sg:address":"780 N San Vicente Blvd",
    "sg:city":"West Hollywood",
    "sg:classifiers":[
        {
            "category":"Government",
            "subcategory":"City Hall",
            "type":"Public Place"
        }
    ],
    "sg:phone":"+1 310 855 8850",
    "sg:postcode":"90069",
    "sg:province":"CA",
    "sg:website":"www.wehosheriff.com",
    "wof:name":"West Hollywood Sheriff's Station",
    "wof:placetype":"venue"
},
  "geometry": {"coordinates":[-118.383972,34.084731],"type":"Point"}
}