{
  "type": "Feature",
  "properties": {
    "addr:full":"1262 W 34th St Long Beach CA 90810",
    "addr:housenumber":"1262",
    "addr:postcode":"90810",
    "addr:street":"W 34Th St",
    "iso:country":"US",
    "sg:address":"1262 W 34th St",
    "sg:city":"Long Beach",
    "sg:classifiers":[
        {
            "category":"Professional",
            "type":"Services"
        }
    ],
    "sg:phone":"+1 562 427 7116",
    "sg:postcode":"90810",
    "sg:province":"CA",
    "wof:name":"Figures",
    "wof:placetype":"venue"
},
  "geometry": {"coordinates":[-118.208624,33.818829],"type":"Point"}
}