{
  "type": "Feature",
  "properties": {
    "addr:full":"504 E Groverdale St Covina CA 91722",
    "addr:housenumber":"504",
    "addr:postcode":"91722",
    "addr:street":"E Groverdale St",
    "iso:country":"US",
    "sg:address":"504 E Groverdale St",
    "sg:city":"Covina",
    "sg:classifiers":[
        {
            "category":"Health Services",
            "subcategory":"Clinic",
            "type":"Services"
        }
    ],
    "sg:phone":"+1 626 332 3964",
    "sg:postcode":"91722",
    "sg:province":"CA",
    "sg:tags":[
        "home",
        "care"
    ],
    "wof:name":"Heritage Home Health Serv",
    "wof:placetype":"venue"
},
  "geometry": {"coordinates":[-117.879777,34.101991],"type":"Point"}
}