{
  "type": "Feature",
  "properties": {
    "iso:country":"US",
    "sg:address":"313 N Birch St",
    "sg:city":"Santa Ana",
    "sg:classifiers":[
        {
            "category":"Professional",
            "subcategory":"Lawyer & Legal Services",
            "type":"Services"
        }
    ],
    "sg:phone":"+1 714 835 5585",
    "sg:postcode":"92701",
    "sg:province":"CA",
    "wof:name":"Leone Fernando Law Offices of",
    "wof:placetype":"venue"
},
  "geometry": {"coordinates":[-117.870459,33.747551],"type":"Point"}
}