{
  "type": "Feature",
  "properties": {
    "addr:full":"5445 Chicago Ave Riverside CA 92507",
    "addr:housenumber":"5445",
    "addr:postcode":"92507",
    "addr:street":"Chicago Ave",
    "iso:country":"US",
    "sg:address":"5445 Chicago Ave",
    "sg:city":"Riverside",
    "sg:classifiers":[
        {
            "category":"Shopping",
            "subcategory":"Bicycles & Sporting Goods",
            "type":"Retail Goods"
        }
    ],
    "sg:phone":"+1 909 731 8008",
    "sg:postcode":"92507",
    "sg:province":"CA",
    "sg:tags":[
        "product",
        "outdoor",
        "fishing"
    ],
    "wof:name":"S C W Fishing & Outdoor Pdts",
    "wof:placetype":"venue"
},
  "geometry": {"coordinates":[-117.346368,33.952622],"type":"Point"}
}