{
  "type": "Feature",
  "properties": {
    "addr:full":"1250 E Shaw Ave Fresno CA 93710",
    "addr:housenumber":"1250",
    "addr:postcode":"93710",
    "addr:street":"E Shaw Ave",
    "iso:country":"US",
    "sg:address":"1250 E Shaw Ave",
    "sg:city":"Fresno",
    "sg:classifiers":[
        {
            "category":"Real Estate",
            "subcategory":"Real Estate Agent",
            "type":"Services"
        }
    ],
    "sg:phone":"+1 559 226 4646",
    "sg:postcode":"93710",
    "sg:province":"CA",
    "wof:name":"Bergman Realty",
    "wof:placetype":"venue"
},
  "geometry": {"coordinates":[-119.765494,36.808578],"type":"Point"}
}