{
  "type": "Feature",
  "properties": {
    "addr:full":"50 Debussy Ln Ventura CA 93003",
    "addr:housenumber":"50",
    "addr:postcode":"93003",
    "addr:street":"Debussy Ln",
    "iso:country":"US",
    "sg:address":"50 Debussy Ln",
    "sg:city":"Ventura",
    "sg:classifiers":[
        {
            "category":"Banks & Credit Unions",
            "subcategory":"Investment Brokerage",
            "type":"Services"
        },
        {
            "category":"Banks & Credit Unions",
            "subcategory":"Financial Services",
            "type":"Services"
        }
    ],
    "sg:phone":"+1 805 639 0011",
    "sg:postcode":"93003",
    "sg:province":"CA",
    "sg:tags":[
        "advisory",
        "planner"
    ],
    "wof:name":"Money Smart Financial",
    "wof:placetype":"venue"
},
  "geometry": {"coordinates":[-119.221813,34.265056],"type":"Point"}
}