{
  "type": "Feature",
  "properties": {
    "addr:full":"118 Paseo de San Antonio San Jose CA 95112",
    "addr:housenumber":"118",
    "addr:postcode":"95112",
    "addr:street":"Paseo De San Antonio",
    "iso:country":"US",
    "sg:address":"118 Paseo de San Antonio",
    "sg:city":"San Jose",
    "sg:classifiers":[
        {
            "category":"Coffee & Tea",
            "type":"Food & Drink"
        }
    ],
    "sg:phone":"+1 408 971 4212",
    "sg:postcode":"95112",
    "sg:province":"CA",
    "sg:website":"www.philzcoffee.com",
    "wof:name":"Philz Coffee",
    "wof:placetype":"venue"
},
  "geometry": {"coordinates":[-121.884843,37.333644],"type":"Point"}
}