{
  "type": "Feature",
  "properties": {
    "iso:country":"US",
    "sg:address":"105 Hop Ranch Rd",
    "sg:city":"Santa Rosa",
    "sg:classifiers":[
        {
            "category":"Home & Garden",
            "subcategory":"Home Furnishings",
            "type":"Retail Goods"
        }
    ],
    "sg:phone":"+1 707 545 4269",
    "sg:postcode":"95403",
    "sg:province":"CA",
    "sg:tags":[
        "curtain",
        "made",
        "drapery"
    ],
    "wof:name":"Interior Design Studio The",
    "wof:placetype":"venue"
},
  "geometry": {"coordinates":[-122.76429899999999,38.507609],"type":"Point"}
}