{
  "type": "Feature",
  "properties": {
    "addr:full":"5800 San Fernando Rd Glendale CA 91202",
    "addr:housenumber":"5800",
    "addr:postcode":"91202",
    "addr:street":"San Fernando Rd",
    "iso:country":"US",
    "sg:address":"5800 San Fernando Rd",
    "sg:city":"Glendale",
    "sg:classifiers":[
        {
            "category":"Retail",
            "subcategory":"Auto Repair",
            "type":"Services"
        }
    ],
    "sg:phone":"+1 818 409 9973",
    "sg:postcode":"91202",
    "sg:province":"CA",
    "wof:name":"Fred's Auto",
    "wof:placetype":"venue"
},
  "geometry": {"coordinates":[-118.277,34.156898],"type":"Point"}
}