{
  "type": "Feature",
  "properties": {
    "iso:country":"US",
    "sg:address":"8281 Santa Monica Blvd",
    "sg:city":"West Hollywood",
    "sg:classifiers":[
        {
            "category":"Restaurant",
            "type":"Food & Drink"
        }
    ],
    "sg:phone":"+1 323 654 7952",
    "sg:postcode":"90046",
    "sg:province":"CA",
    "sg:tags":[
        "thai"
    ],
    "wof:name":"Sammy's Thai Bbq",
    "wof:placetype":"venue"
},
  "geometry": {"coordinates":[-118.370003,34.090599],"type":"Point"}
}