{
  "type": "Feature",
  "properties": {
    "iso:country":"US",
    "sg:address":"20450 Lake Chabot Rd",
    "sg:city":"Castro Valley",
    "sg:classifiers":[
        {
            "category":"Health Services",
            "subcategory":"Clinic",
            "type":"Services"
        }
    ],
    "sg:phone":"+1 650 548 1528",
    "sg:postcode":"94546",
    "sg:province":"CA",
    "sg:tags":[
        "home",
        "care"
    ],
    "wof:name":"Eden Hospital Home Care",
    "wof:placetype":"venue"
},
  "geometry": {"coordinates":[-122.08776,37.700112],"type":"Point"}
}