{
  "type": "Feature",
  "properties": {
    "iso:country":"US",
    "sg:address":"8424 Lincoln Blvd",
    "sg:city":"Los Angeles",
    "sg:classifiers":[
        {
            "category":"Personal",
            "subcategory":"Beauty Salon",
            "type":"Services"
        }
    ],
    "sg:phone":"+1 310 670 4720",
    "sg:postcode":"90045",
    "sg:province":"CA",
    "wof:name":"Cherry Blossom Beauty Salon",
    "wof:placetype":"venue"
},
  "geometry": {"coordinates":[-118.420007,33.96092],"type":"Point"}
}