{
  "type": "Feature",
  "properties": {
    "iso:country":"US",
    "sg:address":"5780 Chesapeake Ct",
    "sg:city":"San Diego",
    "sg:classifiers":[
        {
            "category":"Building & Trades",
            "subcategory":"Construction",
            "type":"Services"
        }
    ],
    "sg:phone":"+1 858 569 0676",
    "sg:postcode":"92123",
    "sg:province":"CA",
    "sg:tags":[
        "contractor"
    ],
    "wof:name":"Getchell Construction",
    "wof:placetype":"venue"
},
  "geometry": {"coordinates":[-117.129261,32.838127],"type":"Point"}
}