{
  "type": "Feature",
  "properties": {
    "addr:full":"434 W Cedar St San Diego CA 92101",
    "addr:housenumber":"434",
    "addr:postcode":"92101",
    "addr:street":"W Cedar St",
    "iso:country":"US",
    "sg:address":"434 W Cedar St",
    "sg:city":"San Diego",
    "sg:classifiers":[
        {
            "category":"Real Estate",
            "subcategory":"Architect",
            "type":"Services"
        }
    ],
    "sg:phone":"+1 619 232 0888",
    "sg:postcode":"92101",
    "sg:province":"CA",
    "sg:website":"www.robquigley.com",
    "wof:name":"Rob Wellington Quigley F A I A",
    "wof:placetype":"venue"
},
  "geometry": {"coordinates":[-117.167,32.722],"type":"Point"}
}