{
  "type": "Feature",
  "properties": {
    "iso:country":"US",
    "sg:address":"6201 Descanso Ln",
    "sg:city":"Paradise",
    "sg:classifiers":[
        {
            "category":"Insurance",
            "subcategory":"Insurance Agent",
            "type":"Services"
        }
    ],
    "sg:phone":"+1 530 877 3272",
    "sg:postcode":"95969",
    "sg:province":"CA",
    "wof:name":"Howard Hurst Financial",
    "wof:placetype":"venue"
},
  "geometry": {"coordinates":[-121.60446399999999,39.771647],"type":"Point"}
}