{
  "type": "Feature",
  "properties": {
    "iso:country":"US",
    "sg:address":"5475 Wadean Pl",
    "sg:city":"Oakland",
    "sg:classifiers":[
        {
            "category":"Wholesale",
            "subcategory":"Non-durable Goods",
            "type":"Manufacturing & Wholesale Goods"
        }
    ],
    "sg:phone":"+1 510 261 5161",
    "sg:postcode":"94601",
    "sg:province":"CA",
    "sg:tags":[
        "import",
        "export",
        "merchandise",
        "general"
    ],
    "wof:name":"Logans Import & Export",
    "wof:placetype":"venue"
},
  "geometry": {"coordinates":[-122.202715,37.769884],"type":"Point"}
}