{
  "type": "Feature",
  "properties": {
    "iso:country":"US",
    "sg:address":"5737 Terminal Ave",
    "sg:city":"Riverbank",
    "sg:classifiers":[
        {
            "category":"Freight",
            "type":"Transportation"
        }
    ],
    "sg:phone":"+1 209 869 4994",
    "sg:postcode":"95367",
    "sg:province":"CA",
    "sg:tags":[
        "general"
    ],
    "wof:name":"Affordable Storage",
    "wof:placetype":"venue"
},
  "geometry": {"coordinates":[-120.931131,37.722798],"type":"Point"}
}