{
  "type": "Feature",
  "properties": {
    "addr:full":"1020 Whispering Pines Ln Grass Valley CA 95945",
    "addr:housenumber":"1020",
    "addr:postcode":"95945",
    "addr:street":"Whispering Pines Ln",
    "iso:country":"US",
    "sg:address":"1020 Whispering Pines Ln",
    "sg:city":"Grass Valley",
    "sg:classifiers":[
        {
            "category":"Home & Garden",
            "subcategory":"Building Materials",
            "type":"Retail Goods"
        }
    ],
    "sg:phone":"+1 530 478 9011",
    "sg:postcode":"95945",
    "sg:province":"CA",
    "sg:tags":[
        "windows"
    ],
    "wof:name":"California Craftsman",
    "wof:placetype":"venue"
},
  "geometry": {"coordinates":[-121.033445,39.222285],"type":"Point"}
}