{
  "type": "Feature",
  "properties": {
    "iso:country":"US",
    "sg:address":"4872 Casitas Pass Rd",
    "sg:city":"Ventura",
    "sg:classifiers":[
        {
            "category":"Government",
            "subcategory":"Office",
            "type":"Public Place"
        }
    ],
    "sg:phone":"+1 805 649 8028",
    "sg:postcode":"93001",
    "sg:province":"CA",
    "sg:tags":[
        "state",
        "program",
        "health"
    ],
    "sg:website":"www.juicing.com",
    "wof:name":"Perfect Health",
    "wof:placetype":"venue"
},
  "geometry": {"coordinates":[-119.403284,34.38201],"type":"Point"}
}