{
  "type": "Feature",
  "properties": {
    "iso:country":"US",
    "sg:address":"2819 182nd St",
    "sg:city":"Redondo Beach",
    "sg:classifiers":[
        {
            "category":"Communications",
            "type":"Services"
        }
    ],
    "sg:phone":"+1 310 542 1703",
    "sg:postcode":"90278",
    "sg:province":"CA",
    "sg:tags":[
        "communication"
    ],
    "wof:name":"Secc Corp",
    "wof:placetype":"venue"
},
  "geometry": {"coordinates":[-118.358884,33.865618],"type":"Point"}
}