{
  "type": "Feature",
  "properties": {
    "addr:full":"995 Gateway Center Way San Diego CA 92102",
    "addr:housenumber":"995",
    "addr:postcode":"92102",
    "addr:street":"Gateway Center Way",
    "iso:country":"US",
    "sg:address":"995 Gateway Center Way",
    "sg:city":"San Diego",
    "sg:classifiers":[
        {
            "category":"Government",
            "subcategory":"Office",
            "type":"Public Place"
        }
    ],
    "sg:phone":"+1 619 266 6060",
    "sg:postcode":"92102",
    "sg:province":"CA",
    "sg:tags":[
        "program",
        "administrative"
    ],
    "wof:name":"Health & Human Services",
    "wof:placetype":"venue"
},
  "geometry": {"coordinates":[-117.114728,32.71465],"type":"Point"}
}