{
  "type": "Feature",
  "properties": {
    "iso:country":"US",
    "sg:address":"361 Sutton Pl",
    "sg:city":"Santa Rosa",
    "sg:classifiers":[
        {
            "category":"Freight",
            "type":"Transportation"
        }
    ],
    "sg:phone":"+1 707 586 7890",
    "sg:postcode":"95407",
    "sg:province":"CA",
    "sg:tags":[
        "forwarder",
        "broker"
    ],
    "wof:name":"Dts Transportation Services",
    "wof:placetype":"venue"
},
  "geometry": {"coordinates":[-122.72614299999999,38.390964],"type":"Point"}
}