{
  "type": "Feature",
  "properties": {
    "addr:full":"527 Soledad St Soledad CA 93960",
    "addr:housenumber":"527",
    "addr:postcode":"93960",
    "addr:street":"Soledad St",
    "iso:country":"US",
    "sg:address":"527 Soledad St",
    "sg:city":"Soledad",
    "sg:classifiers":[
        {
            "category":"Retail",
            "subcategory":"Laundry & Dry Cleaning",
            "type":"Services"
        }
    ],
    "sg:phone":"+1 831 678 0537",
    "sg:postcode":"93960",
    "sg:province":"CA",
    "sg:tags":[
        "cleaners",
        "rug",
        "carpet"
    ],
    "wof:name":"Evercleen Carpets",
    "wof:placetype":"venue"
},
  "geometry": {"coordinates":[-121.32371500000001,36.432193],"type":"Point"}
}