{
  "type": "Feature",
  "properties": {
    "addr:full":"1747 Westwood Blvd Los Angeles CA 90024",
    "addr:housenumber":"1747",
    "addr:postcode":"90024",
    "addr:street":"Westwood Blvd",
    "iso:country":"US",
    "sg:address":"1747 Westwood Blvd",
    "sg:city":"Los Angeles",
    "sg:classifiers":[
        {
            "category":"Shopping",
            "type":"Retail Goods"
        }
    ],
    "sg:phone":"+1 310 444 8998",
    "sg:postcode":"90024",
    "sg:province":"CA",
    "sg:tags":[
        "cosmetic",
        "perfume"
    ],
    "wof:name":"Miba",
    "wof:placetype":"venue"
},
  "geometry": {"coordinates":[-118.437752,34.05074],"type":"Point"}
}