{
  "type": "Feature",
  "properties": {
    "addr:full":"2520 California St Mountain View CA 94040",
    "addr:housenumber":"2520",
    "addr:postcode":"94040",
    "addr:street":"California St",
    "iso:country":"US",
    "sg:address":"2520 California St",
    "sg:city":"Mountain View",
    "sg:classifiers":[
        {
            "category":"Food & Beverages",
            "subcategory":"Bakery",
            "type":"Retail Goods"
        }
    ],
    "sg:phone":"+1 650 949 1775",
    "sg:postcode":"94040",
    "sg:province":"CA",
    "sg:tags":[
        "baker"
    ],
    "wof:name":"Panaderia Marlen",
    "wof:placetype":"venue"
},
  "geometry": {"coordinates":[-122.10663099999999,37.403767],"type":"Point"}
}