{
  "type": "Feature",
  "properties": {
    "addr:full":"2872 W Devoy Dr Anaheim CA 92804",
    "addr:housenumber":"2872",
    "addr:postcode":"92804",
    "addr:street":"W Devoy Dr",
    "iso:country":"US",
    "sg:address":"2872 W Devoy Dr",
    "sg:city":"Anaheim",
    "sg:classifiers":[
        {
            "category":"Shopping",
            "subcategory":"Clothing, Apparel, & Fashions",
            "type":"Retail Goods"
        }
    ],
    "sg:phone":"+1 714 484 7506",
    "sg:postcode":"92804",
    "sg:province":"CA",
    "wof:name":"Happy Life Clothing",
    "wof:placetype":"venue"
},
  "geometry": {"coordinates":[-117.98921,33.819941],"type":"Point"}
}