{
  "type": "Feature",
  "properties": {
    "addr:full":"115 Mason Circle Suite E Concord CA 94520",
    "addr:housenumber":"115",
    "addr:postcode":"94520",
    "addr:street":"Mason Circle Suite E",
    "iso:country":"US",
    "sg:address":"115 Mason Circle Suite E",
    "sg:city":"Concord",
    "sg:classifiers":[
        {
            "category":"Manufacturing",
            "subcategory":"Electronics",
            "type":"Manufacturing & Wholesale Goods"
        }
    ],
    "sg:phone":"+1 888 572 7372",
    "sg:postcode":"94520",
    "sg:province":"CA",
    "sg:tags":[
        "apple",
        "mac",
        "macintosh",
        "macbook",
        "macbook-pro",
        "powerbook",
        "ibook",
        "iphone",
        "ipod",
        "ipod-touch",
        "mac-repair",
        "iphone-repair",
        "ipod-repair"
    ],
    "sg:website":"http://techrestore.com",
    "wof:name":"TechRestore, Inc.",
    "wof:placetype":"venue"
},
  "geometry": {"coordinates":[-122.04134999999999,38.011709],"type":"Point"}
}