{
  "type": "Feature",
  "properties": {
    "iso:country":"US",
    "sg:address":"1 Grant Ave",
    "sg:city":"San Francisco",
    "sg:classifiers":[
        {
            "category":"Shopping",
            "subcategory":"Books",
            "type":"Retail Goods"
        }
    ],
    "sg:phone":"+1 415 677 9418",
    "sg:postcode":"94108",
    "sg:province":"CA",
    "wof:name":"Old St Marys Gift & Book Shop",
    "wof:placetype":"venue"
},
  "geometry": {"coordinates":[-122.404972,37.787417],"type":"Point"}
}