{
  "type": "Feature",
  "properties": {
    "addr:full":"8032 Doodlebug Ln Shingletown CA 96088",
    "addr:housenumber":"8032",
    "addr:postcode":"96088",
    "addr:street":"Doodlebug Ln",
    "iso:country":"US",
    "sg:address":"8032 Doodlebug Ln",
    "sg:city":"Shingletown",
    "sg:classifiers":[
        {
            "category":"Farming",
            "subcategory":"Farm",
            "type":"Manufacturing & Wholesale Goods"
        }
    ],
    "sg:phone":"+1 530 474 4161",
    "sg:postcode":"96088",
    "sg:province":"CA",
    "sg:tags":[
        "crop",
        "general"
    ],
    "wof:name":"Doodlebug Farm",
    "wof:placetype":"venue"
},
  "geometry": {"coordinates":[-121.938292,40.521137],"type":"Point"}
}