{
  "type": "Feature",
  "properties": {
    "addr:full":"22 N Main St San Andreas CA 95249",
    "addr:housenumber":"22",
    "addr:postcode":"95249",
    "addr:street":"N Main St",
    "iso:country":"US",
    "sg:address":"22 N Main St",
    "sg:city":"San Andreas",
    "sg:classifiers":[
        {
            "category":"Museum",
            "type":"Entertainment"
        }
    ],
    "sg:phone":"+1 209 754 1774",
    "sg:postcode":"95249",
    "sg:province":"CA",
    "sg:tags":[
        "organization",
        "arts",
        "information"
    ],
    "sg:website":"www.calaverasarts.org",
    "wof:name":"Calaveras County Arts Council",
    "wof:placetype":"venue"
},
  "geometry": {"coordinates":[-120.68070400000001,38.197015],"type":"Point"}
}