{
  "type": "Feature",
  "properties": {
    "iso:country":"US",
    "sg:address":"1325 Leavenworth St",
    "sg:city":"San Francisco",
    "sg:classifiers":[
        {
            "category":"Government",
            "subcategory":"City Hall",
            "type":"Public Place"
        }
    ],
    "sg:postcode":"94107",
    "sg:province":"CA",
    "sg:website":"www.sfgov.org/site/sffd_index.asp",
    "wof:name":"San Francisco Fire Department - Station 41",
    "wof:placetype":"venue"
},
  "geometry": {"coordinates":[-122.416495,37.793377],"type":"Point"}
}