{
  "type": "Feature",
  "properties": {
    "addr:full":"9735 Silva Rd El Cajon CA 92021",
    "addr:housenumber":"9735",
    "addr:postcode":"92021",
    "addr:street":"Silva Rd",
    "iso:country":"US",
    "sg:address":"9735 Silva Rd",
    "sg:city":"El Cajon",
    "sg:classifiers":[
        {
            "category":"Wholesale",
            "subcategory":"Non-durable Goods",
            "type":"Manufacturing & Wholesale Goods"
        }
    ],
    "sg:phone":"+1 619 390 5819",
    "sg:postcode":"92021",
    "sg:province":"CA",
    "wof:name":"Feather Ranch Residential Care",
    "wof:placetype":"venue"
},
  "geometry": {"coordinates":[-116.825532,32.858584],"type":"Point"}
}