{
  "type": "Feature",
  "properties": {
    "iso:country":"US",
    "sg:address":"120 Miramontes Rd",
    "sg:city":"Redwood City",
    "sg:classifiers":[
        {
            "category":"Professional",
            "type":"Services"
        }
    ],
    "sg:phone":"+1 650 851 8127",
    "sg:postcode":"94062",
    "sg:province":"CA",
    "wof:name":"Rapley Rapley Inc",
    "wof:placetype":"venue"
},
  "geometry": {"coordinates":[-122.262243,37.427719],"type":"Point"}
}