{
  "type": "Feature",
  "properties": {
    "iso:country":"US",
    "sg:address":"1045 S East St",
    "sg:city":"Anaheim",
    "sg:classifiers":[
        {
            "category":"Communications",
            "subcategory":"Radio Station",
            "type":"Services"
        }
    ],
    "sg:phone":"+1 714 502 9494",
    "sg:postcode":"92805",
    "sg:province":"CA",
    "sg:tags":[
        "broadcast"
    ],
    "wof:name":"Kik-FM",
    "wof:placetype":"venue"
},
  "geometry": {"coordinates":[-117.898181,33.824377],"type":"Point"}
}