{
  "type": "Feature",
  "properties": {
    "addr:full":"1625 W Olympic Blvd Los Angeles CA 90015",
    "addr:housenumber":"1625",
    "addr:postcode":"90015",
    "addr:street":"W Olympic Blvd",
    "iso:country":"US",
    "sg:address":"1625 W Olympic Blvd",
    "sg:city":"Los Angeles",
    "sg:classifiers":[
        {
            "category":"Government",
            "subcategory":"Office",
            "type":"Public Place"
        }
    ],
    "sg:phone":"+1 213 365 9251",
    "sg:postcode":"90015",
    "sg:province":"CA",
    "sg:tags":[
        "federal",
        "affairs"
    ],
    "wof:name":"Consulate General Of Guatemala",
    "wof:placetype":"venue"
},
  "geometry": {"coordinates":[-118.27451499999999,34.049402],"type":"Point"}
}