{
  "type": "Feature",
  "properties": {
    "iso:country":"US",
    "sg:address":"5620 Wilbur Ave",
    "sg:city":"Tarzana",
    "sg:classifiers":[
        {
            "category":"Health Services",
            "subcategory":"Doctor",
            "type":"Services"
        }
    ],
    "sg:phone":"+1 818 708 7116",
    "sg:postcode":"91356",
    "sg:province":"CA",
    "sg:tags":[
        "physician",
        "surgeon"
    ],
    "wof:name":"Breast Beautification Ctr",
    "wof:placetype":"venue"
},
  "geometry": {"coordinates":[-118.544653,34.172511],"type":"Point"}
}