{
  "type": "Feature",
  "properties": {
    "addr:full":"16406 Cll Daggett Santa Clarita CA 91390",
    "addr:postcode":"16406;91390",
    "iso:country":"US",
    "sg:address":"16406 Cll Daggett",
    "sg:city":"Santa Clarita",
    "sg:classifiers":[
        {
            "category":"Retail",
            "subcategory":"Portrait Studio",
            "type":"Services"
        }
    ],
    "sg:phone":"+1 661 270 0208",
    "sg:postcode":"91390",
    "sg:province":"CA",
    "sg:tags":[
        "photo"
    ],
    "wof:name":"Greens4u Studio Productio",
    "wof:placetype":"venue"
},
  "geometry": {"coordinates":[-118.419524,34.61658],"type":"Point"}
}