{
  "type": "Feature",
  "properties": {
    "iso:country":"US",
    "sg:address":"17 Bluxome Street",
    "sg:city":"San Francisco",
    "sg:classifiers":[
        {
            "category":"Real Estate",
            "subcategory":"Real Estate Services",
            "type":"Services"
        }
    ],
    "sg:phone":"+1 415 546 3100",
    "sg:postcode":"94107",
    "sg:province":"CA",
    "sg:website":"www.loftsunlimited.com",
    "wof:name":"Lofts Unlimited",
    "wof:placetype":"venue"
},
  "geometry": {"coordinates":[-122.394997,37.783901],"type":"Point"}
}