{
  "type": "Feature",
  "properties": {
    "addr:full":"210 Main St Salinas CA 93901",
    "addr:housenumber":"210",
    "addr:postcode":"93901",
    "addr:street":"Main St",
    "iso:country":"US",
    "sg:address":"210 Main St",
    "sg:city":"Salinas",
    "sg:classifiers":[
        {
            "category":"Professional",
            "subcategory":"Computer Services",
            "type":"Services"
        }
    ],
    "sg:phone":"+1 831 422 1760",
    "sg:postcode":"93901",
    "sg:province":"CA",
    "sg:tags":[
        "internet"
    ],
    "wof:name":"Rollick's Specialty Coffee",
    "wof:placetype":"venue"
},
  "geometry": {"coordinates":[-121.65506499999999,36.674471],"type":"Point"}
}