{
  "type": "Feature",
  "properties": {
    "addr:full":"6050 Geary Blvd San Francisco CA 94121",
    "addr:housenumber":"6050",
    "addr:postcode":"94121",
    "addr:street":"Geary Blvd",
    "iso:country":"US",
    "sg:address":"6050 Geary Blvd",
    "sg:city":"San Francisco",
    "sg:classifiers":[
        {
            "category":"Coffee & Tea",
            "type":"Food & Drink"
        }
    ],
    "sg:phone":"+1 415 592 8918",
    "sg:postcode":"94121",
    "sg:province":"CA",
    "sg:website":"www.lol-sf.com/",
    "wof:name":"LOL Cafe",
    "wof:placetype":"venue"
},
  "geometry": {"coordinates":[-122.484646,37.780225],"type":"Point"}
}