{
  "type": "Feature",
  "properties": {
    "addr:full":"2020 Sutter Pl Davis CA 95616",
    "addr:housenumber":"2020",
    "addr:postcode":"95616",
    "addr:street":"Sutter Pl",
    "iso:country":"US",
    "sg:address":"2020 Sutter Pl",
    "sg:city":"Davis",
    "sg:classifiers":[
        {
            "category":"Health Services",
            "subcategory":"Doctor",
            "type":"Services"
        }
    ],
    "sg:phone":"+1 530 750 5800",
    "sg:postcode":"95616",
    "sg:province":"CA",
    "sg:tags":[
        "physician",
        "surgeon"
    ],
    "wof:name":"Arfan Din DO",
    "wof:placetype":"venue"
},
  "geometry": {"coordinates":[-121.772493,38.562582],"type":"Point"}
}