{
  "type": "Feature",
  "properties": {
    "addr:full":"1150 N Red Gum St Anaheim CA 92806",
    "addr:housenumber":"1150",
    "addr:postcode":"92806",
    "addr:street":"N Red Gum St",
    "iso:country":"US",
    "sg:address":"1150 N Red Gum St",
    "sg:city":"Anaheim",
    "sg:classifiers":[
        {
            "category":"Wholesale",
            "subcategory":"Machinery & Supplies",
            "type":"Manufacturing & Wholesale Goods"
        }
    ],
    "sg:phone":"+1 714 666 8893",
    "sg:postcode":"92806",
    "sg:province":"CA",
    "sg:tags":[
        "equipment",
        "establishment"
    ],
    "wof:name":"Noseg Disposables Inc",
    "wof:placetype":"venue"
},
  "geometry": {"coordinates":[-117.864355,33.851796],"type":"Point"}
}