{
  "type": "Feature",
  "properties": {
    "addr:full":"3136 W Parkview Cir Anaheim CA 92804",
    "addr:housenumber":"3136",
    "addr:postcode":"92804",
    "addr:street":"W Parkview Cir",
    "iso:country":"US",
    "sg:address":"3136 W Parkview Cir",
    "sg:city":"Anaheim",
    "sg:classifiers":[
        {
            "category":"Education",
            "subcategory":"Special Training",
            "type":"Public Place"
        }
    ],
    "sg:phone":"+1 714 828 5488",
    "sg:postcode":"92804",
    "sg:province":"CA",
    "wof:name":"Toastmasters International",
    "wof:placetype":"venue"
},
  "geometry": {"coordinates":[-117.99969,33.823373],"type":"Point"}
}