{
  "type": "Feature",
  "properties": {
    "iso:country":"US",
    "sg:address":"11355 Folsom Blvd",
    "sg:city":"Rancho Cordova",
    "sg:classifiers":[
        {
            "category":"Freight",
            "type":"Transportation"
        }
    ],
    "sg:phone":"+1 916 631 0324",
    "sg:postcode":"95742",
    "sg:province":"CA",
    "wof:name":"Ace Structures & Trnsprtn",
    "wof:placetype":"venue"
},
  "geometry": {"coordinates":[-121.256485,38.612031],"type":"Point"}
}