{
  "type": "Feature",
  "properties": {
    "addr:full":"601 W Arrow Hwy San Dimas CA 91773",
    "addr:housenumber":"601",
    "addr:postcode":"91773",
    "addr:street":"W Arrow Hwy",
    "iso:country":"US",
    "sg:address":"601 W Arrow Hwy",
    "sg:city":"San Dimas",
    "sg:classifiers":[
        {
            "category":"Home & Garden",
            "subcategory":"Furniture",
            "type":"Retail Goods"
        }
    ],
    "sg:phone":"+1 909 599 9501",
    "sg:postcode":"91773",
    "sg:province":"CA",
    "wof:name":"Furniture Depot",
    "wof:placetype":"venue"
},
  "geometry": {"coordinates":[-117.81933100000001,34.105977],"type":"Point"}
}