{
  "type": "Feature",
  "properties": {
    "iso:country":"US",
    "sg:address":"601 W Arrow Hwy",
    "sg:city":"San Dimas",
    "sg:classifiers":[
        {
            "category":"Home & Garden",
            "subcategory":"Furniture",
            "type":"Retail Goods"
        }
    ],
    "sg:phone":"+1 909 599 9501",
    "sg:postcode":"91773",
    "sg:province":"CA",
    "wof:name":"Furniture Depot",
    "wof:placetype":"venue"
},
  "geometry": {"coordinates":[-117.819331,34.105977],"type":"Point"}
}