{
  "type": "Feature",
  "properties": {
    "iso:country":"US",
    "sg:address":"25464 Franklin Ave",
    "sg:city":"Hayward",
    "sg:classifiers":[
        {
            "category":"Building & Trades",
            "subcategory":"Construction",
            "type":"Services"
        }
    ],
    "sg:phone":"+1 510 675 6287",
    "sg:postcode":"94544",
    "sg:province":"CA",
    "sg:tags":[
        "handyman"
    ],
    "wof:name":"Lawns N Such",
    "wof:placetype":"venue"
},
  "geometry": {"coordinates":[-122.07559500000001,37.650072],"type":"Point"}
}