{
  "type": "Feature",
  "properties": {
    "iso:country":"US",
    "sg:address":"12545 E Huntsman Ave",
    "sg:city":"Selma",
    "sg:classifiers":[
        {
            "category":"Farming",
            "subcategory":"Vineyard",
            "type":"Manufacturing & Wholesale Goods"
        }
    ],
    "sg:phone":"+1 559 896 3588",
    "sg:postcode":"93662",
    "sg:province":"CA",
    "sg:tags":[
        "grape"
    ],
    "wof:name":"Louis E Olson",
    "wof:placetype":"venue"
},
  "geometry": {"coordinates":[-119.562508,36.583225],"type":"Point"}
}