{
  "type": "Feature",
  "properties": {
    "addr:full":"11741 Sterling Ave Riverside CA 92503",
    "addr:housenumber":"11741",
    "addr:postcode":"92503",
    "addr:street":"Sterling Ave",
    "iso:country":"US",
    "sg:address":"11741 Sterling Ave",
    "sg:city":"Riverside",
    "sg:classifiers":[
        {
            "category":"Manufacturing",
            "subcategory":"Lumber",
            "type":"Manufacturing & Wholesale Goods"
        }
    ],
    "sg:phone":"+1 951 509 3766",
    "sg:postcode":"92503",
    "sg:province":"CA",
    "sg:tags":[
        "hardwood",
        "mills",
        "dimension",
        "flooring"
    ],
    "wof:name":"Woods Of The Past Inc",
    "wof:placetype":"venue"
},
  "geometry": {"coordinates":[-117.486411,33.89513],"type":"Point"}
}