{
  "type": "Feature",
  "properties": {
    "addr:full":"11027 Long Beach Blvd Lynwood CA 90262",
    "addr:housenumber":"11027",
    "addr:postcode":"90262",
    "addr:street":"Long Beach Blvd",
    "iso:country":"US",
    "sg:address":"11027 Long Beach Blvd",
    "sg:city":"Lynwood",
    "sg:classifiers":[
        {
            "category":"Food & Beverages",
            "subcategory":"Specialty",
            "type":"Retail Goods"
        }
    ],
    "sg:phone":"+1 310 639 9717",
    "sg:postcode":"90262",
    "sg:province":"CA",
    "sg:tags":[
        "herb"
    ],
    "wof:name":"Los Olivos Tienda Naturista",
    "wof:placetype":"venue"
},
  "geometry": {"coordinates":[-118.211969,33.932077],"type":"Point"}
}