{
  "type": "Feature",
  "properties": {
    "addr:full":"155 E Artesia St Pomona CA 91767",
    "addr:housenumber":"155",
    "addr:postcode":"91767",
    "addr:street":"E Artesia St",
    "iso:country":"US",
    "sg:address":"155 E Artesia St",
    "sg:city":"Pomona",
    "sg:classifiers":[
        {
            "category":"Health Services",
            "subcategory":"Hospital",
            "type":"Services"
        }
    ],
    "sg:phone":"+1 909 865 9899",
    "sg:postcode":"91767",
    "sg:province":"CA",
    "wof:name":"Regional Kidney Stone Ctr",
    "wof:placetype":"venue"
},
  "geometry": {"coordinates":[-117.750961,34.075886],"type":"Point"}
}