{
  "type": "Feature",
  "properties": {
    "addr:full":"15006 Arrow Hwy Baldwin Park CA 91706",
    "addr:housenumber":"15006",
    "addr:postcode":"91706",
    "addr:street":"Arrow Hwy",
    "iso:country":"US",
    "sg:address":"15006 Arrow Hwy",
    "sg:city":"Baldwin Park",
    "sg:classifiers":[
        {
            "category":"Building & Trades",
            "subcategory":"Cleaning & Sanitation",
            "type":"Services"
        }
    ],
    "sg:phone":"+1 626 851 1111",
    "sg:postcode":"91706",
    "sg:province":"CA",
    "sg:tags":[
        "filter"
    ],
    "wof:name":"Interstate Filter Svc",
    "wof:placetype":"venue"
},
  "geometry": {"coordinates":[-117.95092699999999,34.106915],"type":"Point"}
}