{
  "type": "Feature",
  "properties": {
    "addr:full":"735 W Duarte Rd Arcadia CA 91007",
    "addr:housenumber":"735",
    "addr:postcode":"91007",
    "addr:street":"W Duarte Rd",
    "iso:country":"US",
    "sg:address":"735 W Duarte Rd",
    "sg:city":"Arcadia",
    "sg:classifiers":[
        {
            "category":"Wholesale",
            "subcategory":"Durable Goods & Equipment",
            "type":"Manufacturing & Wholesale Goods"
        }
    ],
    "sg:phone":"+1 626 446 2328",
    "sg:postcode":"91007",
    "sg:province":"CA",
    "sg:tags":[
        "importer"
    ],
    "sg:website":"www.americankanox.com",
    "wof:name":"American Kanox Corp",
    "wof:placetype":"venue"
},
  "geometry": {"coordinates":[-118.055567,34.126072],"type":"Point"}
}