{
  "type": "Feature",
  "properties": {
    "addr:full":"2116 Yale St Santa Ana CA 92704",
    "addr:housenumber":"2116",
    "addr:postcode":"92704",
    "addr:street":"Yale St",
    "iso:country":"US",
    "sg:address":"2116 Yale St",
    "sg:city":"Santa Ana",
    "sg:classifiers":[
        {
            "category":"Professional",
            "subcategory":"Art Services",
            "type":"Services"
        },
        {
            "category":"Professional",
            "subcategory":"Printing & Photocopies",
            "type":"Services"
        }
    ],
    "sg:phone":"+1 714 437 1056",
    "sg:postcode":"92704",
    "sg:province":"CA",
    "sg:tags":[
        "graphic",
        "design"
    ],
    "sg:website":"www.imatrixinc.com",
    "wof:name":"Imatrix, Inc.",
    "wof:placetype":"venue"
},
  "geometry": {"coordinates":[-117.916162,33.718508],"type":"Point"}
}