{
  "type": "Feature",
  "properties": {
    "addr:full":"2126 W Beverly Blvd Montebello CA 90640",
    "addr:housenumber":"2126",
    "addr:postcode":"90640",
    "addr:street":"W Beverly Blvd",
    "iso:country":"US",
    "sg:address":"2126 W Beverly Blvd",
    "sg:city":"Montebello",
    "sg:classifiers":[
        {
            "category":"Health Services",
            "subcategory":"Health Practitioner",
            "type":"Services"
        }
    ],
    "sg:phone":"+1 323 888 9469",
    "sg:postcode":"90640",
    "sg:province":"CA",
    "sg:tags":[
        "acupuncture"
    ],
    "wof:name":"J J Acupunture",
    "wof:placetype":"venue"
},
  "geometry": {"coordinates":[-118.12173300000001,34.071135],"type":"Point"}
}