{
  "type": "Feature",
  "properties": {
    "iso:country":"US",
    "sg:address":"19220 San Jose Ave",
    "sg:city":"City Of Industry",
    "sg:classifiers":[
        {
            "category":"Manufacturing",
            "subcategory":"Metals",
            "type":"Manufacturing & Wholesale Goods"
        }
    ],
    "sg:phone":"+1 626 965 0668",
    "sg:postcode":"91748",
    "sg:province":"CA",
    "sg:tags":[
        "tool"
    ],
    "sg:website":"www.cditorque.com",
    "wof:name":"Consolidated Devices Inc",
    "wof:placetype":"venue"
},
  "geometry": {"coordinates":[-117.88251099999999,33.998949],"type":"Point"}
}