{
  "type": "Feature",
  "properties": {
    "addr:full":"400 Grand Ave S San Francisco CA 94080",
    "addr:housenumber":"400",
    "addr:postcode":"94080",
    "addr:street":"Grand Ave S",
    "iso:country":"US",
    "sg:address":"400 Grand Ave",
    "sg:city":"S San Francisco",
    "sg:classifiers":[
        {
            "category":"Government",
            "subcategory":"Office",
            "type":"Public Place"
        }
    ],
    "sg:phone":"+1 650 877 8500",
    "sg:postcode":"94080",
    "sg:province":"CA",
    "sg:tags":[
        "city"
    ],
    "wof:name":"City Mayor",
    "wof:placetype":"venue"
},
  "geometry": {"coordinates":[-122.41433499999999,37.656104],"type":"Point"}
}