{
  "type": "Feature",
  "properties": {
    "iso:country":"US",
    "sg:address":"1001 B Avenue",
    "sg:city":"Coronado",
    "sg:classifiers":[
        {
            "category":"Professional",
            "subcategory":"Lawyer & Legal Services",
            "type":"Services"
        }
    ],
    "sg:phone":"+1 619 435 0100",
    "sg:postcode":"92118",
    "sg:province":"CA",
    "wof:name":"Sandke M Tami",
    "wof:placetype":"venue"
},
  "geometry": {"coordinates":[-117.17754100000001,32.684918],"type":"Point"}
}