{
  "type": "Feature",
  "properties": {
    "addr:full":"4804 Brompton Ct Carmichael CA 95608",
    "addr:housenumber":"4804",
    "addr:postcode":"95608",
    "addr:street":"Brompton Ct",
    "iso:country":"US",
    "sg:address":"4804 Brompton Ct",
    "sg:city":"Carmichael",
    "sg:classifiers":[
        {
            "category":"Wholesale",
            "subcategory":"Construction Materials",
            "type":"Manufacturing & Wholesale Goods"
        }
    ],
    "sg:phone":"+1 916 484 7273",
    "sg:postcode":"95608",
    "sg:province":"CA",
    "sg:tags":[
        "control",
        "manufacturer",
        "system",
        "controls",
        "regulators-wholesale"
    ],
    "wof:name":"Innovative Energy Ideas",
    "wof:placetype":"venue"
},
  "geometry": {"coordinates":[-121.347452,38.582191],"type":"Point"}
}