{
  "type": "Feature",
  "properties": {
    "iso:country":"US",
    "sg:address":"201 Mission St Ste 2020",
    "sg:city":"San Francsico",
    "sg:classifiers":[
        {
            "category":"Professional",
            "type":"Services"
        }
    ],
    "sg:phone":"+1 415 962 4600",
    "sg:postcode":"94105",
    "sg:province":"CA",
    "sg:website":"www.magenic.com",
    "wof:name":"Magenic Technologies",
    "wof:placetype":"venue"
},
  "geometry": {"coordinates":[-122.39542299999999,37.791174],"type":"Point"}
}