{
  "type": "Feature",
  "properties": {
    "iso:country":"US",
    "sg:address":"1338 Myrtle Ave",
    "sg:city":"Eureka",
    "sg:classifiers":[
        {
            "category":"Restaurant",
            "type":"Food & Drink"
        }
    ],
    "sg:phone":"+1 707 445 9238",
    "sg:postcode":"95501",
    "sg:province":"CA",
    "wof:name":"Tea Garden Cafe",
    "wof:placetype":"venue"
},
  "geometry": {"coordinates":[-124.144254,40.797843],"type":"Point"}
}