{
  "type": "Feature",
  "properties": {
    "iso:country":"US",
    "sg:address":"1475 W Park Ave",
    "sg:city":"Redlands",
    "sg:classifiers":[
        {
            "category":"Professional",
            "subcategory":"Business Services",
            "type":"Services"
        }
    ],
    "sg:phone":"+1 909 793 9920",
    "sg:postcode":"92373",
    "sg:province":"CA",
    "sg:tags":[
        "information",
        "referral"
    ],
    "wof:name":"Infosend Inc",
    "wof:placetype":"venue"
},
  "geometry": {"coordinates":[-117.206017,34.059312],"type":"Point"}
}