{
  "type": "Feature",
  "properties": {
    "iso:country":"US",
    "sg:address":"2436 Professional Pkwy",
    "sg:city":"Santa Maria",
    "sg:classifiers":[
        {
            "category":"Government",
            "subcategory":"Office",
            "type":"Public Place"
        }
    ],
    "sg:phone":"+1 805 934 8162",
    "sg:postcode":"93455",
    "sg:province":"CA",
    "sg:tags":[
        "program",
        "administrative"
    ],
    "wof:name":"Social Security Administration",
    "wof:placetype":"venue"
},
  "geometry": {"coordinates":[-120.43831900000001,34.914988],"type":"Point"}
}