{
  "type": "Feature",
  "properties": {
    "addr:full":"1501 Park St Alameda CA 94521",
    "addr:housenumber":"1501",
    "addr:postcode":"94521",
    "addr:street":"Park St",
    "iso:country":"US",
    "sg:address":"1501 Park St",
    "sg:city":"Alameda",
    "sg:classifiers":[
        {
            "category":"Shopping",
            "subcategory":"Clothing, Apparel, & Fashions",
            "type":"Retail Goods"
        },
        {
            "category":"Shopping",
            "subcategory":"Shoes",
            "type":"Retail Goods"
        }
    ],
    "sg:phone":"+1 510 523 7463",
    "sg:postcode":"94521",
    "sg:province":"CA",
    "sg:tags":[
        "men's",
        "clothing",
        "store",
        "accessory"
    ],
    "wof:name":"Doumitt Shoes",
    "wof:placetype":"venue"
},
  "geometry": {"coordinates":[-122.24185,37.765365],"type":"Point"}
}