{
  "type": "Feature",
  "properties": {
    "iso:country":"US",
    "sg:address":"505 Montgomery St 11th Floor",
    "sg:city":"San Francisco",
    "sg:classifiers":[
        {
            "category":"Professional",
            "subcategory":"Computer Services",
            "type":"Services"
        }
    ],
    "sg:phone":"+1 415 946 7400",
    "sg:postcode":"94111",
    "sg:province":"CA",
    "sg:tags":[
        "repair"
    ],
    "sg:website":"www.uistechnologypartners.com",
    "wof:name":"UIS Technology Partners",
    "wof:placetype":"venue"
},
  "geometry": {"coordinates":[-122.403552,37.794024],"type":"Point"}
}