{
  "type": "Feature",
  "properties": {
    "iso:country":"US",
    "sg:address":"1135 E Alluvial Ave",
    "sg:city":"Fresno",
    "sg:classifiers":[
        {
            "category":"Social Services",
            "subcategory":"Child Care",
            "type":"Services"
        }
    ],
    "sg:phone":"+1 559 439 5326",
    "sg:postcode":"93720",
    "sg:province":"CA",
    "wof:name":"Children's Center",
    "wof:placetype":"venue"
},
  "geometry": {"coordinates":[-119.76315,36.84464],"type":"Point"}
}