{
  "type": "Feature",
  "properties": {
    "addr:full":"809 Merced St Maricopa CA 93252",
    "addr:housenumber":"809",
    "addr:postcode":"93252",
    "addr:street":"Merced St",
    "iso:country":"US",
    "sg:address":"809 Merced St",
    "sg:city":"Maricopa",
    "sg:classifiers":[
        {
            "category":"Shopping",
            "subcategory":"Bicycles & Sporting Goods",
            "type":"Retail Goods"
        }
    ],
    "sg:phone":"+1 661 769 8538",
    "sg:postcode":"93252",
    "sg:province":"CA",
    "wof:name":"L A Ammo",
    "wof:placetype":"venue"
},
  "geometry": {"coordinates":[-119.40072499999999,35.056871],"type":"Point"}
}