{
  "type": "Feature",
  "properties": {
    "addr:full":"10970 Sherman Way Burbank CA 91505",
    "addr:housenumber":"10970",
    "addr:postcode":"91505",
    "addr:street":"Sherman Way",
    "iso:country":"US",
    "sg:address":"10970 Sherman Way",
    "sg:city":"Burbank",
    "sg:classifiers":[
        {
            "category":"Shopping",
            "subcategory":"Pharmacy",
            "type":"Retail Goods"
        }
    ],
    "sg:phone":"+1 818 847 8600",
    "sg:postcode":"91505",
    "sg:province":"CA",
    "sg:tags":[
        "drugstore"
    ],
    "wof:name":"Kd Pharmacy Inc.",
    "wof:placetype":"venue"
},
  "geometry": {"coordinates":[-118.369663,34.201054],"type":"Point"}
}