{
  "type": "Feature",
  "properties": {
    "addr:full":"1601 Marine World Pkwy Vallejo CA 94589",
    "addr:housenumber":"1601",
    "addr:postcode":"94589",
    "addr:street":"Marine World Pkwy",
    "iso:country":"US",
    "sg:address":"1601 Marine World Pkwy",
    "sg:city":"Vallejo",
    "sg:classifiers":[
        {
            "category":"Food & Beverages",
            "subcategory":"Groceries & Convenience Stores",
            "type":"Retail Goods"
        },
        {
            "category":"Food & Beverages",
            "subcategory":"Specialty",
            "type":"Retail Goods"
        }
    ],
    "sg:phone":"+1 707 554 3835",
    "sg:postcode":"94589",
    "sg:province":"CA",
    "sg:tags":[
        "oriental"
    ],
    "wof:name":"Alegria's Oriental Store",
    "wof:placetype":"venue"
},
  "geometry": {"coordinates":[-122.25106700000001,38.14189],"type":"Point"}
}