{
  "type": "Feature",
  "properties": {
    "addr:full":"2257 S Willow Ave Bloomington CA 92316",
    "addr:housenumber":"2257",
    "addr:postcode":"92316",
    "addr:street":"S Willow Ave",
    "iso:country":"US",
    "sg:address":"2257 S Willow Ave",
    "sg:city":"Bloomington",
    "sg:classifiers":[
        {
            "category":"Manufacturing",
            "subcategory":"Metals",
            "type":"Manufacturing & Wholesale Goods"
        }
    ],
    "sg:phone":"+1 909 820 7565",
    "sg:postcode":"92316",
    "sg:province":"CA",
    "sg:tags":[
        "steel"
    ],
    "wof:name":"Visco Steel Co Inc",
    "wof:placetype":"venue"
},
  "geometry": {"coordinates":[-117.374556,34.058788],"type":"Point"}
}