{
  "type": "Feature",
  "properties": {
    "addr:full":"200 Tamal Vista Blvd Corte Madera CA 94925",
    "addr:housenumber":"200",
    "addr:postcode":"94925",
    "addr:street":"Tamal Vista Blvd",
    "iso:country":"US",
    "sg:address":"200 Tamal Vista Blvd",
    "sg:city":"Corte Madera",
    "sg:classifiers":[
        {
            "category":"Professional",
            "type":"Services"
        }
    ],
    "sg:phone":"+1 415 945 9380",
    "sg:postcode":"94925",
    "sg:province":"CA",
    "wof:name":"Total Living Network",
    "wof:placetype":"venue"
},
  "geometry": {"coordinates":[-122.518682,37.938324],"type":"Point"}
}