{
  "type": "Feature",
  "properties": {
    "addr:full":"10400 Rosecrans Ave Bellflower CA 90706",
    "addr:housenumber":"10400",
    "addr:postcode":"90706",
    "addr:street":"Rosecrans Ave",
    "iso:country":"US",
    "sg:address":"10400 Rosecrans Ave",
    "sg:city":"Bellflower",
    "sg:classifiers":[
        {
            "category":"Restaurant",
            "type":"Food & Drink"
        }
    ],
    "sg:phone":"+1 562 925 5392",
    "sg:postcode":"90706",
    "sg:province":"CA",
    "sg:tags":[
        "pizza"
    ],
    "wof:name":"Kmart Little Caesars Pizza Station",
    "wof:placetype":"venue"
},
  "geometry": {"coordinates":[-118.111,33.901901],"type":"Point"}
}