{
  "type": "Feature",
  "properties": {
    "iso:country":"US",
    "sg:address":"21312 Bulkhead Cir",
    "sg:city":"Huntington Beach",
    "sg:classifiers":[
        {
            "category":"Retail",
            "subcategory":"Event Space",
            "type":"Services"
        }
    ],
    "sg:phone":"+1 714 378 0061",
    "sg:postcode":"92646",
    "sg:province":"CA",
    "sg:tags":[
        "venue"
    ],
    "wof:name":"FHE",
    "wof:placetype":"venue"
},
  "geometry": {"coordinates":[-117.962622,33.652771],"type":"Point"}
}