{
  "type": "Feature",
  "properties": {
    "iso:country":"US",
    "sg:address":"23520 Telo Ave",
    "sg:city":"Torrance",
    "sg:classifiers":[
        {
            "category":"Professional",
            "subcategory":"Business Services",
            "type":"Services"
        }
    ],
    "sg:phone":"+1 310 325 6800",
    "sg:postcode":"90505",
    "sg:province":"CA",
    "sg:tags":[
        "embroidery"
    ],
    "wof:name":"DNA Studios",
    "wof:placetype":"venue"
},
  "geometry": {"coordinates":[-118.337736,33.813095],"type":"Point"}
}