{
  "type": "Feature",
  "properties": {
    "iso:country":"US",
    "sg:address":"1428 El Camino Real",
    "sg:city":"Belmont",
    "sg:classifiers":[
        {
            "category":"Bars & Pubs",
            "subcategory":"Sports Bar",
            "type":"Food & Drink"
        }
    ],
    "sg:phone":"+1 650 593 7201",
    "sg:postcode":"94002",
    "sg:province":"CA",
    "wof:name":"The Lariat Tavern",
    "wof:placetype":"venue"
},
  "geometry": {"coordinates":[-122.272255,37.516901],"type":"Point"}
}