{
  "type": "Feature",
  "properties": {
    "iso:country":"US",
    "sg:address":"4441 Park Blvd",
    "sg:city":"San Diego",
    "sg:classifiers":[
        {
            "category":"Real Estate",
            "subcategory":"Architect",
            "type":"Services"
        }
    ],
    "sg:phone":"+1 619 682 4083",
    "sg:postcode":"92116",
    "sg:province":"CA",
    "wof:name":"Public",
    "wof:placetype":"venue"
},
  "geometry": {"coordinates":[-117.146004,32.758099],"type":"Point"}
}