{
  "type": "Feature",
  "properties": {
    "iso:country":"US",
    "sg:address":"1180 Roundhouse Ave",
    "sg:city":"San Luis Obispo",
    "sg:classifiers":[
        {
            "category":"Wholesale",
            "subcategory":"Electrical",
            "type":"Manufacturing & Wholesale Goods"
        }
    ],
    "sg:phone":"+1 805 543 1082",
    "sg:postcode":"93401",
    "sg:province":"CA",
    "sg:tags":[
        "parts",
        "appliance"
    ],
    "wof:name":"A-Ped Appliance Parts",
    "wof:placetype":"venue"
},
  "geometry": {"coordinates":[-120.655887,35.270561],"type":"Point"}
}