{
  "type": "Feature",
  "properties": {
    "addr:full":"20602 Robertson Blvd Chowchilla CA 93610",
    "addr:housenumber":"20602",
    "addr:postcode":"93610",
    "addr:street":"Robertson Blvd",
    "iso:country":"US",
    "sg:address":"20602 Robertson Blvd",
    "sg:city":"Chowchilla",
    "sg:phone":"+1 559 665 3882",
    "sg:postcode":"93610",
    "sg:province":"CA",
    "sg:tags":[
        "beef",
        "farm",
        "corn",
        "crop",
        "field",
        "cattle",
        "cotton"
    ],
    "wof:name":"Johnny Romeri",
    "wof:placetype":"venue"
},
  "geometry": {"coordinates":[-120.32231299999999,37.054438],"type":"Point"}
}