{
  "type": "Feature",
  "properties": {
    "iso:country":"US",
    "sg:address":"907 Newport Center Dr",
    "sg:city":"Newport Beach",
    "sg:classifiers":[
        {
            "category":"Professional",
            "type":"Services"
        }
    ],
    "sg:phone":"+1 949 729 1035",
    "sg:postcode":"92660",
    "sg:province":"CA",
    "sg:tags":[
        "establishment"
    ],
    "wof:name":"JIJ Design",
    "wof:placetype":"venue"
},
  "geometry": {"coordinates":[-117.878075,33.614405],"type":"Point"}
}