{
  "type": "Feature",
  "properties": {
    "iso:country":"US",
    "sg:address":"5455 Wilshire Blvd",
    "sg:city":"Los Angeles",
    "sg:classifiers":[
        {
            "category":"Professional",
            "subcategory":"Lawyer & Legal Services",
            "type":"Services"
        }
    ],
    "sg:phone":"+1 323 937 7455",
    "sg:postcode":"90036",
    "sg:province":"CA",
    "wof:name":"Meade Michael J Attorney At Law",
    "wof:placetype":"venue"
},
  "geometry": {"coordinates":[-118.347,34.062302],"type":"Point"}
}