{
  "type": "Feature",
  "properties": {
    "iso:country":"US",
    "sg:address":"230 E Betteravia Rd",
    "sg:city":"Santa Maria",
    "sg:classifiers":[
        {
            "category":"Restaurant",
            "type":"Food & Drink"
        }
    ],
    "sg:phone":"+1 805 739 2821",
    "sg:postcode":"93454",
    "sg:province":"CA",
    "wof:name":"Senor Salsa",
    "wof:placetype":"venue"
},
  "geometry": {"coordinates":[-120.434089,34.920948],"type":"Point"}
}