{
  "type": "Feature",
  "properties": {
    "iso:country":"US",
    "sg:address":"8320 Lincoln Blvd Ste 102",
    "sg:city":"Los Angeles",
    "sg:classifiers":[
        {
            "category":"Personal",
            "subcategory":"Nail Salon",
            "type":"Services"
        }
    ],
    "sg:phone":"+1 310 645 5480",
    "sg:postcode":"90045",
    "sg:province":"CA",
    "wof:name":"Beautiful Nails",
    "wof:placetype":"venue"
},
  "geometry": {"coordinates":[-118.420908,33.962222],"type":"Point"}
}