{
  "type": "Feature",
  "properties": {
    "addr:full":"3418 Marber Ave Long Beach CA 90808",
    "addr:housenumber":"3418",
    "addr:postcode":"90808",
    "addr:street":"Marber Ave",
    "iso:country":"US",
    "sg:address":"3418 Marber Ave",
    "sg:city":"Long Beach",
    "sg:classifiers":[
        {
            "category":"Social Services",
            "type":"Services"
        }
    ],
    "sg:phone":"+1 562 494 7284",
    "sg:postcode":"90808",
    "sg:province":"CA",
    "sg:tags":[
        "counseling"
    ],
    "wof:name":"Universal Counseling Group",
    "wof:placetype":"venue"
},
  "geometry": {"coordinates":[-118.124076,33.8219],"type":"Point"}
}