{
  "type": "Feature",
  "properties": {
    "iso:country":"US",
    "sg:address":"555 W Shaw Ave",
    "sg:city":"Fresno",
    "sg:classifiers":[
        {
            "category":"Professional",
            "subcategory":"Accounting & Tax Preparation",
            "type":"Services"
        }
    ],
    "sg:phone":"+1 559 230 0575",
    "sg:postcode":"93704",
    "sg:province":"CA",
    "sg:tags":[
        "accountant"
    ],
    "sg:website":"www.thadscottcpa.com",
    "wof:name":"Thad Scott & Co",
    "wof:placetype":"venue"
},
  "geometry": {"coordinates":[-119.800667,36.808355],"type":"Point"}
}