{
  "type": "Feature",
  "properties": {
    "addr:full":"1045 14th St San Diego CA 92101",
    "addr:housenumber":"1045",
    "addr:postcode":"92101",
    "addr:street":"14Th St",
    "iso:country":"US",
    "sg:address":"1045 14th St",
    "sg:city":"San Diego",
    "sg:classifiers":[
        {
            "category":"Wholesale",
            "subcategory":"Durable Goods & Equipment",
            "type":"Manufacturing & Wholesale Goods"
        }
    ],
    "sg:phone":"+1 619 239 9933",
    "sg:postcode":"92101",
    "sg:province":"CA",
    "wof:name":"House of Antiques",
    "wof:placetype":"venue"
},
  "geometry": {"coordinates":[-117.15189100000001,32.715937],"type":"Point"}
}