{
  "type": "Feature",
  "properties": {
    "addr:full":"5692 Bridgecross Dr Sacramento CA 95835",
    "addr:housenumber":"5692",
    "addr:postcode":"95835",
    "addr:street":"Bridgecross Dr",
    "iso:country":"US",
    "sg:address":"5692 Bridgecross Dr",
    "sg:city":"Sacramento",
    "sg:classifiers":[
        {
            "category":"Building & Trades",
            "subcategory":"Construction",
            "type":"Services"
        }
    ],
    "sg:phone":"+1 916 928 0880",
    "sg:postcode":"95835",
    "sg:province":"CA",
    "sg:tags":[
        "tile",
        "dealer"
    ],
    "wof:name":"Modern Tile Design",
    "wof:placetype":"venue"
},
  "geometry": {"coordinates":[-121.495741,38.677893],"type":"Point"}
}