{
  "type": "Feature",
  "properties": {
    "addr:full":"3245 Cherry Ave Long Beach CA 90807",
    "addr:housenumber":"3245",
    "addr:postcode":"90807",
    "addr:street":"Cherry Ave",
    "iso:country":"US",
    "sg:address":"3245 Cherry Ave",
    "sg:city":"Long Beach",
    "sg:classifiers":[
        {
            "category":"Wholesale",
            "subcategory":"Metals & Minerals",
            "type":"Manufacturing & Wholesale Goods"
        }
    ],
    "sg:phone":"+1 562 595 6621",
    "sg:postcode":"90807",
    "sg:province":"CA",
    "sg:tags":[
        "alloy"
    ],
    "sg:website":"www.doncasters.com",
    "wof:name":"Certified Alloy Products Inc",
    "wof:placetype":"venue"
},
  "geometry": {"coordinates":[-118.167704,33.817073],"type":"Point"}
}