{
  "type": "Feature",
  "properties": {
    "iso:country":"US",
    "sg:address":"3605 Via Capilla",
    "sg:city":"Bakersfield",
    "sg:classifiers":[
        {
            "category":"Real Estate",
            "subcategory":"Real Estate Agent",
            "type":"Services"
        }
    ],
    "sg:phone":"+1 661 664 7766",
    "sg:postcode":"93311",
    "sg:province":"CA",
    "wof:name":"R & R Assoc",
    "wof:placetype":"venue"
},
  "geometry": {"coordinates":[-119.122143,35.322283],"type":"Point"}
}