{
  "type": "Feature",
  "properties": {
    "iso:country":"US",
    "sg:address":"2288 E Main St",
    "sg:city":"Quincy",
    "sg:classifiers":[
        {
            "category":"Shopping",
            "subcategory":"Clothing, Apparel, & Fashions",
            "type":"Retail Goods"
        }
    ],
    "sg:phone":"+1 530 283 9363",
    "sg:postcode":"95971",
    "sg:province":"CA",
    "wof:name":"Funky Fingers & Twinkle Toes",
    "wof:placetype":"venue"
},
  "geometry": {"coordinates":[-120.895477,39.933741],"type":"Point"}
}