{
  "type": "Feature",
  "properties": {
    "iso:country":"US",
    "sg:address":"39155 Calle Anita",
    "sg:city":"Temecula",
    "sg:classifiers":[
        {
            "category":"Manufacturing",
            "subcategory":"Tools & Machinery",
            "type":"Manufacturing & Wholesale Goods"
        }
    ],
    "sg:phone":"+1 951 506 2436",
    "sg:postcode":"92592",
    "sg:province":"CA",
    "sg:tags":[
        "fasteners-industrial"
    ],
    "wof:name":"Outsource Ltd.",
    "wof:placetype":"venue"
},
  "geometry": {"coordinates":[-117.02364900000001,33.548577],"type":"Point"}
}