{
  "type": "Feature",
  "properties": {
    "addr:full":"156 S Main St Bishop CA 93514",
    "addr:housenumber":"156",
    "addr:postcode":"93514",
    "addr:street":"S Main St",
    "iso:country":"US",
    "sg:address":"156 S Main St",
    "sg:city":"Bishop",
    "sg:classifiers":[
        {
            "category":"Shopping",
            "subcategory":"Bicycles & Sporting Goods",
            "type":"Retail Goods"
        }
    ],
    "sg:phone":"+1 760 872 8361",
    "sg:postcode":"93514",
    "sg:province":"CA",
    "wof:name":"Culver's Sporting Goods",
    "wof:placetype":"venue"
},
  "geometry": {"coordinates":[-118.395203,37.36091],"type":"Point"}
}