{
  "type": "Feature",
  "properties": {
    "iso:country":"US",
    "sg:address":"50 Terminal Ave",
    "sg:city":"Menlo Park",
    "sg:classifiers":[
        {
            "category":"Education",
            "subcategory":"School",
            "type":"Public Place"
        }
    ],
    "sg:phone":"+1 650 327 5052",
    "sg:postcode":"94025",
    "sg:province":"CA",
    "wof:name":"Beechwood School",
    "wof:placetype":"venue"
},
  "geometry": {"coordinates":[-122.16797,37.478433],"type":"Point"}
}