{
  "type": "Feature",
  "properties": {
    "iso:country":"US",
    "sg:address":"5025 Columbia Way",
    "sg:city":"Lancaster",
    "sg:classifiers":[
        {
            "category":"Place Of Worship",
            "subcategory":"Church",
            "type":"Public Place"
        },
        {
            "category":"Place Of Worship",
            "type":"Public Place"
        }
    ],
    "sg:phone":"+1 661 943 2774",
    "sg:postcode":"93536",
    "sg:province":"CA",
    "sg:tags":[
        "churches-methodist"
    ],
    "sg:website":"http://www.cosumc.net",
    "wof:name":"Christ Our Savior Untd Mthdst",
    "wof:placetype":"venue"
},
  "geometry": {"coordinates":[-118.219646,34.645634],"type":"Point"}
}