{
  "type": "Feature",
  "properties": {
    "addr:full":"4646 Convoy St Ste 103 San Diego CA 92111",
    "addr:housenumber":"4646",
    "addr:postcode":"92111",
    "addr:street":"Convoy St Ste 103",
    "iso:country":"US",
    "sg:address":"4646 Convoy St Ste 103",
    "sg:city":"San Diego",
    "sg:classifiers":[
        {
            "category":"Fast Food",
            "type":"Food & Drink"
        }
    ],
    "sg:phone":"+1 858 571 6038",
    "sg:postcode":"92111",
    "sg:province":"CA",
    "sg:tags":[
        "burger"
    ],
    "wof:name":"The B Spot",
    "wof:placetype":"venue"
},
  "geometry": {"coordinates":[-117.15569600000001,32.824921],"type":"Point"}
}