{
  "type": "Feature",
  "properties": {
    "addr:full":"4809 Sparks Ave San Diego CA 92110",
    "addr:housenumber":"4809",
    "addr:postcode":"92110",
    "addr:street":"Sparks Ave",
    "iso:country":"US",
    "sg:address":"4809 Sparks Ave",
    "sg:city":"San Diego",
    "sg:classifiers":[
        {
            "category":"Insurance",
            "subcategory":"Insurance Agent",
            "type":"Services"
        }
    ],
    "sg:phone":"+1 858 272 0062",
    "sg:postcode":"92110",
    "sg:province":"CA",
    "wof:name":"Allan Wiser Insurance Svc Inc",
    "wof:placetype":"venue"
},
  "geometry": {"coordinates":[-117.197383,32.778487],"type":"Point"}
}