{
  "type": "Feature",
  "properties": {
    "addr:full":"11157 W Larch Rd Tracy CA 95304",
    "addr:housenumber":"11157",
    "addr:postcode":"95304",
    "addr:street":"W Larch Rd",
    "iso:country":"US",
    "sg:address":"11157 W Larch Rd",
    "sg:city":"Tracy",
    "sg:classifiers":[
        {
            "category":"Social Services",
            "type":"Services"
        }
    ],
    "sg:phone":"+1 209 835 1617",
    "sg:postcode":"95304",
    "sg:province":"CA",
    "sg:tags":[
        "executive"
    ],
    "wof:name":"Senior Serv Agency Nutritn",
    "wof:placetype":"venue"
},
  "geometry": {"coordinates":[-121.45332999999999,37.765009],"type":"Point"}
}