{
  "type": "Feature",
  "properties": {
    "iso:country":"US",
    "sg:address":"535 San Benito St",
    "sg:city":"Hollister",
    "sg:classifiers":[
        {
            "category":"Shopping",
            "subcategory":"Jewelry",
            "type":"Retail Goods"
        }
    ],
    "sg:phone":"+1 831 637 3481",
    "sg:postcode":"95023",
    "sg:province":"CA",
    "sg:tags":[
        "jeweler"
    ],
    "wof:name":"Maddux Jewelry",
    "wof:placetype":"venue"
},
  "geometry": {"coordinates":[-121.401994,36.851014],"type":"Point"}
}