{
  "type": "Feature",
  "properties": {
    "addr:full":"134 US Hwy 101 Crescent City CA 95531",
    "addr:housenumber":"134",
    "addr:postcode":"95531",
    "addr:street":"Us Hwy 101 Crescent",
    "iso:country":"US",
    "sg:address":"134 US Hwy 101",
    "sg:city":"Crescent City",
    "sg:classifiers":[
        {
            "category":"Manufacturing",
            "subcategory":"Signs",
            "type":"Manufacturing & Wholesale Goods"
        }
    ],
    "sg:phone":"+1 707 464 1355",
    "sg:postcode":"95531",
    "sg:province":"CA",
    "wof:name":"Redwood Coast Signs",
    "wof:placetype":"venue"
},
  "geometry": {"coordinates":[-124.198099,41.759251],"type":"Point"}
}