{
  "type": "Feature",
  "properties": {
    "iso:country":"US",
    "sg:address":"9051 Soquel Drive",
    "sg:city":"Aptos",
    "sg:classifiers":[
        {
            "category":"Professional",
            "type":"Services"
        },
        {
            "category":"Restaurant",
            "type":"Food & Drink"
        }
    ],
    "sg:phone":"+1 831 688 5566",
    "sg:postcode":"95003",
    "sg:province":"CA",
    "sg:tags":[
        "seafood",
        "french",
        "caterer"
    ],
    "sg:website":"www.mamaisonrestaurant.com",
    "wof:name":"Ma Maison Restaurant",
    "wof:placetype":"venue"
},
  "geometry": {"coordinates":[-121.890939,36.975652],"type":"Point"}
}