{
  "type": "Feature",
  "properties": {
    "addr:full":"1445 Sepulveda Blvd Torrance CA 90501",
    "addr:housenumber":"1445",
    "addr:postcode":"90501",
    "addr:street":"Sepulveda Blvd",
    "iso:country":"US",
    "sg:address":"1445 Sepulveda Blvd",
    "sg:city":"Torrance",
    "sg:classifiers":[
        {
            "category":"Manufacturing",
            "subcategory":"Signs",
            "type":"Manufacturing & Wholesale Goods"
        }
    ],
    "sg:phone":"+1 310 530 9450",
    "sg:postcode":"90501",
    "sg:province":"CA",
    "sg:tags":[
        "specialty",
        "mfg"
    ],
    "wof:name":"Signs For Faith",
    "wof:placetype":"venue"
},
  "geometry": {"coordinates":[-118.303625,33.815108],"type":"Point"}
}