{
  "type": "Feature",
  "properties": {
    "addr:full":"19517 Saticoy St Reseda CA 91335",
    "addr:postcode":"19517;91335",
    "addr:street":"Saticoy St",
    "iso:country":"US",
    "sg:address":"19517 Saticoy St",
    "sg:city":"Reseda",
    "sg:classifiers":[
        {
            "category":"Building & Trades",
            "subcategory":"Landscaping Services",
            "type":"Services"
        }
    ],
    "sg:phone":"+1 818 727 1064",
    "sg:postcode":"91335",
    "sg:province":"CA",
    "wof:name":"Raul Esparza Gardening",
    "wof:placetype":"venue"
},
  "geometry": {"coordinates":[-118.558397,34.208432],"type":"Point"}
}