{
  "type": "Feature",
  "properties": {
    "iso:country":"US",
    "sg:address":"16332 E San Bernardino Rd",
    "sg:city":"Covina",
    "sg:classifiers":[
        {
            "category":"Building & Trades",
            "subcategory":"Construction",
            "type":"Services"
        }
    ],
    "sg:phone":"+1 626 337 7116",
    "sg:postcode":"91722",
    "sg:province":"CA",
    "sg:tags":[
        "repairing",
        "remodeling",
        "contractor"
    ],
    "wof:name":"Al Wittig Builders Inc",
    "wof:placetype":"venue"
},
  "geometry": {"coordinates":[-117.927424,34.089551],"type":"Point"}
}