{
  "type": "Feature",
  "properties": {
    "addr:full":"1772 Orchid Avenue Los Angeles CA 90028",
    "addr:housenumber":"1772",
    "addr:postcode":"90028",
    "addr:street":"Orchid Avenue",
    "iso:country":"US",
    "sg:address":"1772 Orchid Avenue",
    "sg:city":"Los Angeles",
    "sg:classifiers":[
        {
            "category":"Travel",
            "subcategory":"Hotels & Motels",
            "type":"Entertainment"
        },
        {
            "category":"Real Estate",
            "subcategory":"Real Estate Operator",
            "type":"Services"
        }
    ],
    "sg:phone":"+1 323 465 7680",
    "sg:postcode":"90028",
    "sg:province":"CA",
    "sg:tags":[
        "apartment"
    ],
    "wof:name":"Orchid Properties",
    "wof:placetype":"venue"
},
  "geometry": {"coordinates":[-118.340174,34.103836],"type":"Point"}
}