{
  "type": "Feature",
  "properties": {
    "addr:full":"70755 Sunny Ln Rancho Mirage CA 92270",
    "addr:housenumber":"70755",
    "addr:postcode":"92270",
    "addr:street":"Sunny Ln",
    "iso:country":"US",
    "sg:address":"70755 Sunny Ln",
    "sg:city":"Rancho Mirage",
    "sg:classifiers":[
        {
            "category":"Professional",
            "type":"Services"
        }
    ],
    "sg:phone":"+1 760 202 1181",
    "sg:postcode":"92270",
    "sg:province":"CA",
    "wof:name":"Mary Beth Lacy Inc",
    "wof:placetype":"venue"
},
  "geometry": {"coordinates":[-116.427108,33.781517],"type":"Point"}
}