{
  "type": "Feature",
  "properties": {
    "iso:country":"US",
    "sg:address":"3140 W Ave K",
    "sg:city":"Lancaster",
    "sg:classifiers":[
        {
            "category":"Organizations",
            "subcategory":"Religious Organization",
            "type":"Services"
        }
    ],
    "sg:phone":"+1 661 943 0023",
    "sg:postcode":"93536",
    "sg:province":"CA",
    "wof:name":"Corporation of President of Th",
    "wof:placetype":"venue"
},
  "geometry": {"coordinates":[-118.18598,34.674778],"type":"Point"}
}