{
  "type": "Feature",
  "properties": {
    "addr:full":"960 E Grevillea Ct Ontario CA 91761",
    "addr:housenumber":"960",
    "addr:postcode":"91761",
    "addr:street":"E Grevillea Ct",
    "iso:country":"US",
    "sg:address":"960 E Grevillea Ct",
    "sg:city":"Ontario",
    "sg:classifiers":[
        {
            "category":"Wholesale",
            "subcategory":"Machinery & Supplies",
            "type":"Manufacturing & Wholesale Goods"
        }
    ],
    "sg:phone":"+1 909 947 7735",
    "sg:postcode":"91761",
    "sg:province":"CA",
    "sg:tags":[
        "industrial",
        "representative",
        "for",
        "manufacturer"
    ],
    "sg:website":"www.pneu-con.com",
    "wof:name":"Priority Systems Inc",
    "wof:placetype":"venue"
},
  "geometry": {"coordinates":[-117.636798,34.039756],"type":"Point"}
}