{
  "type": "Feature",
  "properties": {
    "iso:country":"US",
    "sg:address":"43080 Calle Camellia",
    "sg:city":"Temecula",
    "sg:classifiers":[
        {
            "category":"Bars & Pubs",
            "type":"Food & Drink"
        }
    ],
    "sg:phone":"+1 951 506 4474",
    "sg:postcode":"92592",
    "sg:province":"CA",
    "sg:tags":[
        "tavern"
    ],
    "wof:name":"Temecula Wine & Beer Garden",
    "wof:placetype":"venue"
},
  "geometry": {"coordinates":[-117.12039799999999,33.495893],"type":"Point"}
}