{
  "type": "Feature",
  "properties": {
    "addr:full":"445 S Figueroa St Los Angeles CA 90071",
    "addr:housenumber":"445",
    "addr:postcode":"90071",
    "addr:street":"S Figueroa St",
    "iso:country":"US",
    "sg:address":"445 S Figueroa St",
    "sg:city":"Los Angeles",
    "sg:classifiers":[
        {
            "category":"Professional",
            "subcategory":"Computer Services",
            "type":"Services"
        }
    ],
    "sg:phone":"+1 213 489 6886",
    "sg:postcode":"90071",
    "sg:province":"CA",
    "sg:tags":[
        "hardware",
        "provider",
        "internet",
        "software"
    ],
    "wof:name":"Isoftel Inc",
    "wof:placetype":"venue"
},
  "geometry": {"coordinates":[-118.256773,34.052881],"type":"Point"}
}