{
  "type": "Feature",
  "properties": {
    "addr:full":"1280 Bell Ave Sacramento CA 95838",
    "addr:housenumber":"1280",
    "addr:postcode":"95838",
    "addr:street":"Bell Ave",
    "iso:country":"US",
    "sg:address":"1280 Bell Ave",
    "sg:city":"Sacramento",
    "sg:classifiers":[
        {
            "category":"Manufacturing",
            "subcategory":"Buildings",
            "type":"Manufacturing & Wholesale Goods"
        },
        {
            "category":"Building & Trades",
            "subcategory":"Construction",
            "type":"Services"
        }
    ],
    "sg:phone":"+1 916 207 7191",
    "sg:postcode":"95838",
    "sg:province":"CA",
    "sg:tags":[
        "altering",
        "remodeling",
        "builder",
        "contractor",
        "home",
        "mason",
        "demolition"
    ],
    "wof:name":"Naulu Construction",
    "wof:placetype":"venue"
},
  "geometry": {"coordinates":[-121.43651199999999,38.647434],"type":"Point"}
}