{
  "type": "Feature",
  "properties": {
    "iso:country":"US",
    "sg:address":"5131 Naples Pl",
    "sg:city":"San Diego",
    "sg:classifiers":[
        {
            "category":"Professional",
            "subcategory":"Business Services",
            "type":"Services"
        }
    ],
    "sg:phone":"+1 619 275 4477",
    "sg:postcode":"92110",
    "sg:province":"CA",
    "sg:tags":[
        "made",
        "shoes"
    ],
    "wof:name":"Ebuys 77",
    "wof:placetype":"venue"
},
  "geometry": {"coordinates":[-117.199949,32.768082],"type":"Point"}
}