{
  "type": "Feature",
  "properties": {
    "iso:country":"US",
    "sg:address":"749 College Ct",
    "sg:city":"Los Altos",
    "sg:classifiers":[
        {
            "category":"Professional",
            "subcategory":"Management & Consulting",
            "type":"Services"
        }
    ],
    "sg:phone":"+1 650 948 5750",
    "sg:postcode":"94022",
    "sg:province":"CA",
    "sg:tags":[
        "operator",
        "dwelling",
        "f"
    ],
    "wof:name":"Plum Enterprises",
    "wof:placetype":"venue"
},
  "geometry": {"coordinates":[-122.111159,37.369286],"type":"Point"}
}