{
  "type": "Feature",
  "properties": {
    "iso:country":"US",
    "sg:address":"1175 11th St",
    "sg:city":"Lakeport",
    "sg:classifiers":[
        {
            "category":"Personal",
            "subcategory":"Beauty Salon",
            "type":"Services"
        }
    ],
    "sg:phone":"+1 707 263 4050",
    "sg:postcode":"95453",
    "sg:province":"CA",
    "wof:name":"Ceridono's Hair Co",
    "wof:placetype":"venue"
},
  "geometry": {"coordinates":[-122.928997,39.049271],"type":"Point"}
}