{
  "type": "Feature",
  "properties": {
    "addr:full":"207 G St Antioch CA 94509",
    "addr:housenumber":"207",
    "addr:postcode":"ca 94509",
    "addr:street":"G St",
    "iso:country":"US",
    "sg:address":"207 G St",
    "sg:city":"Antioch",
    "sg:classifiers":[
        {
            "category":"Banks & Credit Unions",
            "subcategory":"Investment Brokerage",
            "type":"Services"
        }
    ],
    "sg:phone":"+1 925 757 1470",
    "sg:postcode":"94509",
    "sg:province":"CA",
    "sg:tags":[
        "consultant",
        "planning",
        "financial"
    ],
    "wof:name":"Earline La Buy",
    "wof:placetype":"venue"
},
  "geometry": {"coordinates":[-121.813698,38.016226],"type":"Point"}
}