{
  "type": "Feature",
  "properties": {
    "addr:full":"4350 Redondo Beach Blvd Torrance CA 90504",
    "addr:housenumber":"4350",
    "addr:postcode":"90504",
    "addr:street":"Redondo Beach Blvd",
    "iso:country":"US",
    "sg:address":"4350 Redondo Beach Blvd",
    "sg:city":"Torrance",
    "sg:classifiers":[
        {
            "category":"Health Services",
            "subcategory":"Doctor",
            "type":"Services"
        }
    ],
    "sg:phone":"+1 310 370 2966",
    "sg:postcode":"90504",
    "sg:province":"CA",
    "sg:tags":[
        "dentist"
    ],
    "wof:name":"Northpoint Dental Ctr",
    "wof:placetype":"venue"
},
  "geometry": {"coordinates":[-118.348815,33.87571],"type":"Point"}
}