{
  "type": "Feature",
  "properties": {
    "addr:full":"1600 Poplar Ave Wasco CA 93280",
    "addr:housenumber":"1600",
    "addr:postcode":"ca 93280",
    "addr:street":"Poplar Ave",
    "iso:country":"US",
    "sg:address":"1600 Poplar Ave",
    "sg:city":"Wasco",
    "sg:classifiers":[
        {
            "category":"Real Estate",
            "subcategory":"Real Estate Operator",
            "type":"Services"
        }
    ],
    "sg:phone":"+1 661 758 8410",
    "sg:postcode":"93280",
    "sg:province":"CA",
    "sg:tags":[
        "apartment"
    ],
    "wof:name":"Sunrise Villa",
    "wof:placetype":"venue"
},
  "geometry": {"coordinates":[-119.344887,35.583961],"type":"Point"}
}