{
  "type": "Feature",
  "properties": {
    "addr:full":"1566 Scott St San Jose CA 95126",
    "addr:housenumber":"1566",
    "addr:postcode":"95126",
    "addr:street":"Scott St",
    "iso:country":"US",
    "sg:address":"1566 Scott St",
    "sg:city":"San Jose",
    "sg:classifiers":[
        {
            "category":"Shopping",
            "subcategory":"Clothing, Apparel, & Fashions",
            "type":"Retail Goods"
        }
    ],
    "sg:phone":"+1 408 371 3978",
    "sg:postcode":"95126",
    "sg:province":"CA",
    "sg:tags":[
        "shop",
        "bridal"
    ],
    "wof:name":"Starry Corners",
    "wof:placetype":"venue"
},
  "geometry": {"coordinates":[-121.919377,37.319578],"type":"Point"}
}