{
  "type": "Feature",
  "properties": {
    "addr:full":"12 Main St Hyampom CA 96044",
    "addr:housenumber":"12",
    "addr:postcode":"96044",
    "addr:street":"Main St",
    "iso:country":"US",
    "sg:address":"12 Main St",
    "sg:city":"Hyampom",
    "sg:classifiers":[
        {
            "category":"Government",
            "subcategory":"Fire Station",
            "type":"Public Place"
        }
    ],
    "sg:phone":"+1 530 628 5755",
    "sg:postcode":"96044",
    "sg:province":"CA",
    "sg:tags":[
        "department"
    ],
    "wof:name":"Hyampom Volunteer Fire Dept",
    "wof:placetype":"venue"
},
  "geometry": {"coordinates":[-122.566609,41.904678],"type":"Point"}
}