{
  "type": "Feature",
  "properties": {
    "addr:full":"3033 Arden Way Sacramento CA 95825",
    "addr:housenumber":"3033",
    "addr:postcode":"95825",
    "addr:street":"Arden Way",
    "iso:country":"US",
    "sg:address":"3033 Arden Way",
    "sg:city":"Sacramento",
    "sg:classifiers":[
        {
            "category":"Restaurant",
            "type":"Food & Drink"
        }
    ],
    "sg:phone":"+1 916 485 6616",
    "sg:postcode":"95825",
    "sg:province":"CA",
    "wof:name":"Jimboy's Tacos",
    "wof:placetype":"venue"
},
  "geometry": {"coordinates":[-121.392511,38.595993],"type":"Point"}
}