{
  "type": "Feature",
  "properties": {
    "iso:country":"US",
    "sg:address":"1700 Main St",
    "sg:city":"Susanville",
    "sg:classifiers":[
        {
            "category":"Restaurant",
            "type":"Food & Drink"
        }
    ],
    "sg:phone":"+1 530 257 7220",
    "sg:postcode":"96130",
    "sg:province":"CA",
    "sg:tags":[
        "mexican"
    ],
    "wof:name":"Esther Faustino",
    "wof:placetype":"venue"
},
  "geometry": {"coordinates":[-120.64894099999999,40.415482],"type":"Point"}
}