{
  "type": "Feature",
  "properties": {
    "addr:full":"48 Village Pkwy Santa Monica CA 90405",
    "addr:housenumber":"48",
    "addr:postcode":"90405",
    "addr:street":"Village Pkwy",
    "iso:country":"US",
    "sg:address":"48 Village Pkwy",
    "sg:city":"Santa Monica",
    "sg:classifiers":[
        {
            "category":"Professional",
            "subcategory":"Lawyer & Legal Services",
            "type":"Services"
        }
    ],
    "sg:phone":"+1 310 450 4337",
    "sg:postcode":"90405",
    "sg:province":"CA",
    "sg:tags":[
        "attorney"
    ],
    "wof:name":"Louis Gotenstein",
    "wof:placetype":"venue"
},
  "geometry": {"coordinates":[-118.457151,34.019135],"type":"Point"}
}