{
  "type": "Feature",
  "properties": {
    "addr:full":"1125 E Broadway Glendale CA 91205",
    "addr:housenumber":"1125",
    "addr:postcode":"91205",
    "addr:street":"E Broadway",
    "iso:country":"US",
    "sg:address":"1125 E Broadway",
    "sg:city":"Glendale",
    "sg:classifiers":[
        {
            "category":"Professional",
            "subcategory":"Management & Consulting",
            "type":"Services"
        }
    ],
    "sg:phone":"+1 818 547 3191",
    "sg:postcode":"91205",
    "sg:province":"CA",
    "sg:tags":[
        "consultant",
        "business"
    ],
    "wof:name":"Nancy Novak & Assoc",
    "wof:placetype":"venue"
},
  "geometry": {"coordinates":[-118.24161700000001,34.146328],"type":"Point"}
}