{
  "type": "Feature",
  "properties": {
    "iso:country":"US",
    "sg:address":"11689 Lowhills Rd",
    "sg:city":"Nevada City",
    "sg:classifiers":[
        {
            "category":"Professional",
            "type":"Services"
        }
    ],
    "sg:phone":"+1 530 265 3180",
    "sg:postcode":"95959",
    "sg:province":"CA",
    "wof:name":"Global Family",
    "wof:placetype":"venue"
},
  "geometry": {"coordinates":[-121.088701,39.252096],"type":"Point"}
}