{
  "type": "Feature",
  "properties": {
    "addr:full":"3338 N Texas St Fairfield CA 94533",
    "addr:housenumber":"3338",
    "addr:postcode":"94533",
    "addr:street":"N Texas St",
    "iso:country":"US",
    "sg:address":"3338 N Texas St",
    "sg:city":"Fairfield",
    "sg:classifiers":[
        {
            "category":"Real Estate",
            "subcategory":"Real Estate Agent",
            "type":"Services"
        }
    ],
    "sg:phone":"+1 707 427 6050",
    "sg:postcode":"94533",
    "sg:province":"CA",
    "wof:name":"Era Home Traditions",
    "wof:placetype":"venue"
},
  "geometry": {"coordinates":[-122.033873,38.288205],"type":"Point"}
}