{
  "type": "Feature",
  "properties": {
    "addr:full":"1234 Wilshire Blvd Los Angeles CA 90017",
    "addr:housenumber":"1234",
    "addr:postcode":"90017",
    "addr:street":"Wilshire Blvd",
    "iso:country":"US",
    "sg:address":"1234 Wilshire Blvd",
    "sg:city":"Los Angeles",
    "sg:classifiers":[
        {
            "category":"Restaurant",
            "type":"Food & Drink"
        }
    ],
    "sg:phone":"+1 213 250 2345",
    "sg:postcode":"90017",
    "sg:province":"CA",
    "sg:website":"www.subway.com",
    "wof:name":"Subway",
    "wof:placetype":"venue"
},
  "geometry": {"coordinates":[-118.26596600000001,34.053489],"type":"Point"}
}