{
  "type": "Feature",
  "properties": {
    "iso:country":"US",
    "sg:address":"9500 Gilman Dr.",
    "sg:city":"La Jolla",
    "sg:classifiers":[
        {
            "category":"Education",
            "subcategory":"University",
            "type":"Public Place"
        }
    ],
    "sg:phone":"+1 858 534 2660",
    "sg:postcode":"92037",
    "sg:province":"CA",
    "sg:tags":[
        "college"
    ],
    "sg:website":"irps.ucsd.edu/",
    "wof:name":"Graduate School Of International Relations and Pacific Studies",
    "wof:placetype":"venue"
},
  "geometry": {"coordinates":[-117.23961,32.875294],"type":"Point"}
}