{
  "type": "Feature",
  "properties": {
    "iso:country":"US",
    "sg:address":"3700 McHenry Ave",
    "sg:city":"Modesto",
    "sg:classifiers":[
        {
            "category":"Restaurant",
            "type":"Food & Drink"
        }
    ],
    "sg:phone":"+1 209 523 1439",
    "sg:postcode":"95356",
    "sg:province":"CA",
    "sg:tags":[
        "pizza"
    ],
    "wof:name":"LA Pizza Cafe",
    "wof:placetype":"venue"
},
  "geometry": {"coordinates":[-120.994272,37.692161],"type":"Point"}
}