{
  "type": "Feature",
  "properties": {
    "addr:full":"1254 S Glendale Ave Glendale CA 91205",
    "addr:housenumber":"1254",
    "addr:postcode":"91205",
    "addr:street":"S Glendale Ave",
    "iso:country":"US",
    "sg:address":"1254 S Glendale Ave",
    "sg:city":"Glendale",
    "sg:classifiers":[
        {
            "category":"Professional",
            "subcategory":"Detective & Security Services",
            "type":"Services"
        }
    ],
    "sg:phone":"+1 877 774 2245",
    "sg:postcode":"91205",
    "sg:province":"CA",
    "sg:tags":[
        "bail",
        "bond"
    ],
    "wof:name":"Sevan Bail Bond Agency",
    "wof:placetype":"venue"
},
  "geometry": {"coordinates":[-118.252357,34.131177],"type":"Point"}
}