{
  "type": "Feature",
  "properties": {
    "iso:country":"US",
    "sg:address":"3519 McDonald Ave",
    "sg:city":"Modesto",
    "sg:classifiers":[
        {
            "category":"Bus Charters",
            "type":"Transportation"
        }
    ],
    "sg:phone":"+1 209 521 8250",
    "sg:postcode":"95358",
    "sg:province":"CA",
    "sg:tags":[
        "operator",
        "travel",
        "local"
    ],
    "wof:name":"Storer Travel Service",
    "wof:placetype":"venue"
},
  "geometry": {"coordinates":[-121.049691,37.663852],"type":"Point"}
}