{
  "type": "Feature",
  "properties": {
    "addr:full":"7128 11th Ave Los Angeles CA 90043",
    "addr:housenumber":"7128",
    "addr:postcode":"90043",
    "addr:street":"11Th Ave",
    "iso:country":"US",
    "sg:address":"7128 11th Ave",
    "sg:city":"Los Angeles",
    "sg:classifiers":[
        {
            "category":"Home & Garden",
            "subcategory":"Home Furnishings",
            "type":"Retail Goods"
        }
    ],
    "sg:phone":"+1 323 753 3943",
    "sg:postcode":"90043",
    "sg:province":"CA",
    "sg:tags":[
        "cutlery"
    ],
    "wof:name":"Obi Training Institute",
    "wof:placetype":"venue"
},
  "geometry": {"coordinates":[-118.329399,33.975676],"type":"Point"}
}