{
  "type": "Feature",
  "properties": {
    "iso:country":"US",
    "sg:address":"4515 Rosita Ave",
    "sg:city":"Atascadero",
    "sg:classifiers":[
        {
            "category":"Freight",
            "type":"Transportation"
        }
    ],
    "sg:phone":"+1 805 464 0616",
    "sg:postcode":"93422",
    "sg:province":"CA",
    "sg:tags":[
        "operator",
        "trucking"
    ],
    "wof:name":"Gorapid Auto Transport Inc",
    "wof:placetype":"venue"
},
  "geometry": {"coordinates":[-120.677576,35.501213],"type":"Point"}
}