{
  "type": "Feature",
  "properties": {
    "addr:full":"2797 Union St San Francisco CA 94123",
    "addr:housenumber":"2797",
    "addr:postcode":"94123",
    "addr:street":"Union St",
    "iso:country":"US",
    "sg:address":"2797 Union St",
    "sg:city":"San Francisco",
    "sg:classifiers":[
        {
            "category":"Personal",
            "subcategory":"Massage",
            "type":"Services"
        },
        {
            "category":"Health Services",
            "subcategory":"Clinic",
            "type":"Services"
        }
    ],
    "sg:phone":"+1 415 820 1485",
    "sg:postcode":"94123",
    "sg:province":"CA",
    "sg:tags":[
        "medical"
    ],
    "wof:name":"David Brown Massage",
    "wof:placetype":"venue"
},
  "geometry": {"coordinates":[-122.445251,37.79576],"type":"Point"}
}