{
  "type": "Feature",
  "properties": {
    "addr:full":"4515 Ocean View Blvd La Canada Flintridge CA 91011",
    "addr:housenumber":"4515",
    "addr:postcode":"91011",
    "addr:street":"Ocean View Blvd",
    "iso:country":"US",
    "sg:address":"4515 Ocean View Blvd",
    "sg:city":"La Canada Flintridge",
    "sg:classifiers":[
        {
            "category":"Insurance",
            "subcategory":"Hazard Insurance",
            "type":"Services"
        }
    ],
    "sg:phone":"+1 818 957 9300",
    "sg:postcode":"91011",
    "sg:province":"CA",
    "wof:name":"Kristie Daily Insurance Agents & Brokers",
    "wof:placetype":"venue"
},
  "geometry": {"coordinates":[-118.227985,34.217596],"type":"Point"}
}