{
  "type": "Feature",
  "properties": {
    "iso:country":"US",
    "sg:address":"1810 Berkeley Way",
    "sg:city":"Berkeley",
    "sg:classifiers":[
        {
            "category":"Taxi",
            "type":"Transportation"
        }
    ],
    "sg:phone":"+1 510 528 1111",
    "sg:postcode":"94703",
    "sg:province":"CA",
    "sg:tags":[
        "taxicab"
    ],
    "wof:name":"A Yellow Cab Berkeley",
    "wof:placetype":"venue"
},
  "geometry": {"coordinates":[-122.273342,37.872354],"type":"Point"}
}