{
  "type": "Feature",
  "properties": {
    "addr:full":"3911 Alemany Blvd San Francisco CA 94132",
    "addr:housenumber":"3911",
    "addr:postcode":"94132",
    "addr:street":"Alemany Blvd",
    "iso:country":"US",
    "sg:address":"3911 Alemany Blvd",
    "sg:city":"San Francisco",
    "sg:classifiers":[
        {
            "category":"Restaurant",
            "type":"Food & Drink"
        }
    ],
    "sg:menulink":"http://www.allmenus.com/ca/san-francisco/56960-subway/menu/",
    "sg:phone":"+1 650 757 6100",
    "sg:postcode":"94132",
    "sg:province":"CA",
    "sg:tags":[
        "american",
        "sandwich"
    ],
    "wof:name":"Subway",
    "wof:placetype":"venue"
},
  "geometry": {"coordinates":[-122.46826,37.710991],"type":"Point"}
}