{
  "type": "Feature",
  "properties": {
    "addr:full":"8650 Genesee Ave Ste 230 San Diego CA 92122",
    "addr:housenumber":"8650",
    "addr:postcode":"92122",
    "addr:street":"Genesee Ave Ste 230",
    "iso:country":"US",
    "sg:address":"8650 Genesee Ave Ste 230",
    "sg:city":"San Diego",
    "sg:classifiers":[
        {
            "category":"Communications",
            "subcategory":"Newspaper",
            "type":"Services"
        },
        {
            "category":"Shopping",
            "subcategory":"Books",
            "type":"Retail Goods"
        }
    ],
    "sg:phone":"+1 858 457 7561",
    "sg:postcode":"92122",
    "sg:province":"CA",
    "sg:tags":[
        "magazine",
        "bookstore"
    ],
    "wof:name":"Bookstar",
    "wof:placetype":"venue"
},
  "geometry": {"coordinates":[-117.21399700000001,32.870701],"type":"Point"}
}