{
  "type": "Feature",
  "properties": {
    "addr:full":"12349 Spry St Norwalk CA 90650",
    "addr:postcode":"12349;90650",
    "addr:street":"St",
    "iso:country":"US",
    "sg:address":"12349 Spry St",
    "sg:city":"Norwalk",
    "sg:classifiers":[
        {
            "category":"Professional",
            "type":"Services"
        }
    ],
    "sg:phone":"+1 562 868 5032",
    "sg:postcode":"90650",
    "sg:province":"CA",
    "wof:name":"Ellis Fine Arts Ltd",
    "wof:placetype":"venue"
},
  "geometry": {"coordinates":[-118.071011,33.919906],"type":"Point"}
}