{
  "type": "Feature",
  "properties": {
    "iso:country":"US",
    "sg:address":"9477 el Camino Real",
    "sg:city":"Atascadero",
    "sg:classifiers":[
        {
            "category":"Shopping",
            "subcategory":"Hobbies, Toys, & Games",
            "type":"Retail Goods"
        },
        {
            "category":"Wholesale",
            "subcategory":"Jewelry",
            "type":"Manufacturing & Wholesale Goods"
        }
    ],
    "sg:phone":"+1 805 466 4797",
    "sg:postcode":"93422",
    "sg:province":"CA",
    "sg:tags":[
        "beads"
    ],
    "wof:name":"A Place To Bead",
    "wof:placetype":"venue"
},
  "geometry": {"coordinates":[-120.649785,35.467085],"type":"Point"}
}