{
  "type": "Feature",
  "properties": {
    "iso:country":"US",
    "sg:address":"21 Tamal Vista Blvd",
    "sg:city":"Corte Madera",
    "sg:classifiers":[
        {
            "category":"Health Services",
            "subcategory":"Chiropractor",
            "type":"Services"
        }
    ],
    "sg:phone":"+1 415 927 4995",
    "sg:postcode":"94925",
    "sg:province":"CA",
    "wof:name":"Richard Allen DC",
    "wof:placetype":"venue"
},
  "geometry": {"coordinates":[-122.518386,37.929724],"type":"Point"}
}