{
  "type": "Feature",
  "properties": {
    "addr:full":"510 E Manchester Ave Los Angeles CA 90003",
    "addr:housenumber":"510",
    "addr:postcode":"90003",
    "addr:street":"E Manchester Ave",
    "iso:country":"US",
    "sg:address":"510 E Manchester Ave",
    "sg:city":"Los Angeles",
    "sg:classifiers":[
        {
            "category":"Retail",
            "subcategory":"Auto Repair",
            "type":"Services"
        }
    ],
    "sg:phone":"+1 323 752 5745",
    "sg:postcode":"90003",
    "sg:province":"CA",
    "wof:name":"R & F Auto Service",
    "wof:placetype":"venue"
},
  "geometry": {"coordinates":[-118.26599899999999,33.959999],"type":"Point"}
}