{
  "type": "Feature",
  "properties": {
    "addr:full":"4865 E 1st Street Los Angeles CA 90022",
    "addr:housenumber":"4865",
    "addr:postcode":"90022",
    "addr:street":"E 1St Street",
    "iso:country":"US",
    "sg:address":"4865 E 1st Street",
    "sg:city":"Los Angeles",
    "sg:classifiers":[
        {
            "category":"Education",
            "subcategory":"School",
            "type":"Public Place"
        }
    ],
    "sg:phone":"+1 323 263 3869",
    "sg:postcode":"90022",
    "sg:province":"CA",
    "sg:tags":[
        "high",
        "middle",
        "elementary"
    ],
    "sg:website":"www.lausd.k12.ca.us",
    "wof:name":"Hamasaki Morris K Elementary School",
    "wof:placetype":"venue"
},
  "geometry": {"coordinates":[-118.159341,34.037135],"type":"Point"}
}