{
  "type": "Feature",
  "properties": {
    "iso:country":"US",
    "sg:address":"Studio Plaza 10939 Ventura Blvd",
    "sg:city":"Studio City",
    "sg:classifiers":[
        {
            "category":"Personal",
            "subcategory":"Nail Salon",
            "type":"Services"
        }
    ],
    "sg:phone":"+1 818 506 4868",
    "sg:postcode":"91604",
    "sg:province":"CA",
    "sg:website":"www.nailgarden.com",
    "wof:name":"Nail Garden",
    "wof:placetype":"venue"
},
  "geometry": {"coordinates":[-118.369376,34.140141],"type":"Point"}
}