{
  "type": "Feature",
  "properties": {
    "iso:country":"US",
    "sg:address":"3455 E 1st St",
    "sg:city":"Los Angeles",
    "sg:classifiers":[
        {
            "category":"Professional",
            "type":"Services"
        }
    ],
    "sg:phone":"+1 323 768 3295",
    "sg:postcode":"90063",
    "sg:province":"CA",
    "sg:tags":[
        "establishment"
    ],
    "wof:name":"El Mercado",
    "wof:placetype":"venue"
},
  "geometry": {"coordinates":[-118.19341799999999,34.036551],"type":"Point"}
}