{
  "type": "Feature",
  "properties": {
    "iso:country":"US",
    "sg:address":"3101 S Grand Avenue",
    "sg:city":"Los Angeles",
    "sg:classifiers":[
        {
            "category":"Organizations",
            "subcategory":"Non-profit Organization",
            "type":"Services"
        }
    ],
    "sg:phone":"+1 213 743 6193",
    "sg:postcode":"90007",
    "sg:province":"CA",
    "sg:tags":[
        "service/non-profit",
        "community"
    ],
    "wof:name":"Coalition For Responsible Community Development",
    "wof:placetype":"venue"
},
  "geometry": {"coordinates":[-118.274793,34.02228],"type":"Point"}
}