{
  "type": "Feature",
  "properties": {
    "addr:full":"18546 Sherman Way Reseda CA 91335",
    "addr:housenumber":"18546",
    "addr:postcode":"91335",
    "addr:street":"Sherman Way",
    "iso:country":"US",
    "sg:address":"18546 Sherman Way",
    "sg:city":"Reseda",
    "sg:classifiers":[
        {
            "category":"Retail",
            "subcategory":"Repair Shop",
            "type":"Services"
        }
    ],
    "sg:phone":"+1 818 705 7892",
    "sg:postcode":"91335",
    "sg:province":"CA",
    "sg:tags":[
        "equipment",
        "electronic",
        "supply"
    ],
    "wof:name":"Electro Computer Svc",
    "wof:placetype":"venue"
},
  "geometry": {"coordinates":[-118.53837300000001,34.200986],"type":"Point"}
}