{
  "type": "Feature",
  "properties": {
    "addr:full":"423 Green Ridge Dr Daly City CA 94014",
    "addr:housenumber":"423",
    "addr:postcode":"94014",
    "addr:street":"Green Ridge Dr",
    "iso:country":"US",
    "sg:address":"423 Green Ridge Dr",
    "sg:city":"Daly City",
    "sg:classifiers":[
        {
            "category":"Real Estate",
            "subcategory":"Real Estate Agent",
            "type":"Services"
        }
    ],
    "sg:phone":"+1 650 756 5120",
    "sg:postcode":"94014",
    "sg:province":"CA",
    "wof:name":"Lone Wolf Investments",
    "wof:placetype":"venue"
},
  "geometry": {"coordinates":[-122.453593,37.699608],"type":"Point"}
}