{
  "type": "Feature",
  "properties": {
    "iso:country":"US",
    "sg:address":"115 W Canon Perdido St",
    "sg:city":"Santa Barbara",
    "sg:classifiers":[
        {
            "category":"Freight",
            "type":"Transportation"
        }
    ],
    "sg:phone":"+1 805 966 9488",
    "sg:postcode":"93101",
    "sg:province":"CA",
    "sg:tags":[
        "commercial",
        "storage",
        "general"
    ],
    "wof:name":"City Storage",
    "wof:placetype":"venue"
},
  "geometry": {"coordinates":[-119.70266100000001,34.418491],"type":"Point"}
}