{
  "type": "Feature",
  "properties": {
    "addr:full":"333 Preston Ave Ione CA 95640",
    "addr:housenumber":"333",
    "addr:postcode":"ca 95640",
    "addr:street":"Preston Ave",
    "iso:country":"US",
    "sg:address":"333 Preston Ave",
    "sg:city":"Ione",
    "sg:classifiers":[
        {
            "category":"Personal",
            "subcategory":"Beauty Salon",
            "type":"Services"
        }
    ],
    "sg:phone":"+1 209 274 4280",
    "sg:postcode":"95640",
    "sg:province":"CA",
    "sg:tags":[
        "nail",
        "manicuring"
    ],
    "wof:name":"Ione Nails",
    "wof:placetype":"venue"
},
  "geometry": {"coordinates":[-120.93534200000001,38.353572],"type":"Point"}
}