{
  "type": "Feature",
  "properties": {
    "iso:country":"US",
    "sg:address":"510 Barber Ln",
    "sg:city":"Milpitas",
    "sg:classifiers":[
        {
            "category":"Shopping",
            "subcategory":"Jewelry",
            "type":"Retail Goods"
        }
    ],
    "sg:phone":"+1 408 321 8377",
    "sg:postcode":"95035",
    "sg:province":"CA",
    "sg:tags":[
        "jeweler"
    ],
    "wof:name":"House Of Ruyi",
    "wof:placetype":"venue"
},
  "geometry": {"coordinates":[-121.91768999999999,37.421195],"type":"Point"}
}