{
  "type": "Feature",
  "properties": {
    "addr:full":"3839 Brockton Ave Riverside CA 92501",
    "addr:housenumber":"3839",
    "addr:postcode":"92501",
    "addr:street":"Brockton Ave",
    "iso:country":"US",
    "sg:address":"3839 Brockton Ave",
    "sg:city":"Riverside",
    "sg:classifiers":[
        {
            "category":"Arts & Performance",
            "subcategory":"Theater",
            "type":"Entertainment"
        }
    ],
    "sg:phone":"+1 951 683 6440",
    "sg:postcode":"92501",
    "sg:province":"CA",
    "sg:tags":[
        "band",
        "orchestra"
    ],
    "wof:name":"Riverside Concert Band",
    "wof:placetype":"venue"
},
  "geometry": {"coordinates":[-117.379689,33.983542],"type":"Point"}
}