{
  "type": "Feature",
  "properties": {
    "addr:full":"1250 N San Fernando Rd Los Angeles CA 90065",
    "addr:housenumber":"1250",
    "addr:postcode":"90065",
    "addr:street":"N San Fernando Rd",
    "iso:country":"US",
    "sg:address":"1250 N San Fernando Rd",
    "sg:city":"Los Angeles",
    "sg:classifiers":[
        {
            "category":"Manufacturing",
            "subcategory":"Apparel",
            "type":"Manufacturing & Wholesale Goods"
        }
    ],
    "sg:phone":"+1 323 225 0481",
    "sg:postcode":"90065",
    "sg:province":"CA",
    "sg:tags":[
        "sewing",
        "contractor"
    ],
    "wof:name":"N & R Sewing",
    "wof:placetype":"venue"
},
  "geometry": {"coordinates":[-118.233324,34.097724],"type":"Point"}
}