{
  "type": "Feature",
  "properties": {
    "addr:full":"5950 La Place Ct Ste 160 Carlsbad CA 92008",
    "addr:housenumber":"5950",
    "addr:postcode":"92008",
    "addr:street":"La Place Ct Ste 160",
    "iso:country":"US",
    "sg:address":"5950 La Place Ct Ste 160",
    "sg:city":"Carlsbad",
    "sg:classifiers":[
        {
            "category":"Banks & Credit Unions",
            "subcategory":"Bank",
            "type":"Services"
        }
    ],
    "sg:phone":"+1 858 578 6424",
    "sg:postcode":"92008",
    "sg:province":"CA",
    "wof:name":"First Regional Bank",
    "wof:placetype":"venue"
},
  "geometry": {"coordinates":[-117.272003,33.132702],"type":"Point"}
}