{
  "type": "Feature",
  "properties": {
    "iso:country":"US",
    "sg:address":"4941 Orange Ave",
    "sg:city":"Cypress",
    "sg:classifiers":[
        {
            "category":"Retail",
            "subcategory":"Laundry & Dry Cleaning",
            "type":"Services"
        }
    ],
    "sg:phone":"+1 714 527 5281",
    "sg:postcode":"90630",
    "sg:province":"CA",
    "wof:name":"Green World Cleaners",
    "wof:placetype":"venue"
},
  "geometry": {"coordinates":[-118.046997,33.824402],"type":"Point"}
}