{
  "type": "Feature",
  "properties": {
    "addr:full":"1830 Ave del Mundo Coronado CA 92118",
    "addr:postcode":"92118",
    "addr:street":"1830 Ave Del Mundo",
    "iso:country":"US",
    "sg:address":"1830 Ave del Mundo",
    "sg:city":"Coronado",
    "sg:classifiers":[
        {
            "category":"Professional",
            "subcategory":"Business Services",
            "type":"Services"
        }
    ],
    "sg:phone":"+1 619 435 3931",
    "sg:postcode":"92118",
    "sg:province":"CA",
    "sg:tags":[
        "translator",
        "interpreter"
    ],
    "wof:name":"Franslations",
    "wof:placetype":"venue"
},
  "geometry": {"coordinates":[-117.172929,32.675866],"type":"Point"}
}