{
  "type": "Feature",
  "properties": {
    "addr:full":"630 W Duarte Rd Arcadia CA 91007",
    "addr:housenumber":"630",
    "addr:postcode":"91007",
    "addr:street":"W Duarte Rd",
    "iso:country":"US",
    "sg:address":"630 W Duarte Rd",
    "sg:city":"Arcadia",
    "sg:classifiers":[
        {
            "category":"Professional",
            "subcategory":"Accounting & Tax Preparation",
            "type":"Services"
        }
    ],
    "sg:phone":"+1 626 447 1151",
    "sg:postcode":"91007",
    "sg:province":"CA",
    "sg:tags":[
        "return",
        "filing"
    ],
    "wof:name":"Dellinger-Wilde Tax Svc",
    "wof:placetype":"venue"
},
  "geometry": {"coordinates":[-118.053939,34.126164],"type":"Point"}
}