{
  "type": "Feature",
  "properties": {
    "iso:country":"US",
    "sg:address":"9217 Airport Blvd",
    "sg:city":"Los Angeles",
    "sg:classifiers":[
        {
            "category":"Retail",
            "subcategory":"Auto Rental",
            "type":"Services"
        }
    ],
    "sg:phone":"+1 310 646 5600",
    "sg:postcode":"90045",
    "sg:province":"CA",
    "sg:tags":[
        "renting",
        "car",
        "automobile"
    ],
    "wof:name":"Avis Rent A Car",
    "wof:placetype":"venue"
},
  "geometry": {"coordinates":[-118.386002,33.952],"type":"Point"}
}