{
  "type": "Feature",
  "properties": {
    "addr:full":"20072 SW Birch St Ste 130 Newport Beach CA 92660",
    "addr:housenumber":"20072",
    "addr:postcode":"92660",
    "addr:street":"Sw Birch St Ste 130",
    "iso:country":"US",
    "sg:address":"20072 SW Birch St Ste 130",
    "sg:city":"Newport Beach",
    "sg:classifiers":[
        {
            "category":"Health Services",
            "subcategory":"Clinic",
            "type":"Services"
        }
    ],
    "sg:phone":"+1 702 514 0328",
    "sg:postcode":"92660",
    "sg:province":"CA",
    "sg:tags":[
        "loss",
        "weight"
    ],
    "sg:website":"www.shapewithin.com",
    "wof:name":"Shape Within",
    "wof:placetype":"venue"
},
  "geometry": {"coordinates":[-117.874156,33.659545],"type":"Point"}
}