{
  "type": "Feature",
  "properties": {
    "addr:full":"2730 17th Street San Francisco CA 94110",
    "addr:housenumber":"2730",
    "addr:postcode":"94110",
    "addr:street":"17Th Street",
    "iso:country":"US",
    "sg:address":"2730 17th Street",
    "sg:city":"San Francisco",
    "sg:classifiers":[
        {
            "category":"Building & Trades",
            "subcategory":"Electrical",
            "type":"Services"
        }
    ],
    "sg:phone":"+1 415 626 4422",
    "sg:postcode":"94110",
    "sg:province":"CA",
    "sg:tags":[
        "electrician"
    ],
    "wof:name":"Gardini Electric Company",
    "wof:placetype":"venue"
},
  "geometry": {"coordinates":[-122.41100299999999,37.7644],"type":"Point"}
}