{
  "type": "Feature",
  "properties": {
    "addr:full":"3055 W 7th St Los Angeles CA 90005",
    "addr:housenumber":"3055",
    "addr:postcode":"90005",
    "addr:street":"W 7Th St",
    "iso:country":"US",
    "sg:address":"3055 W 7th St",
    "sg:city":"Los Angeles",
    "sg:classifiers":[
        {
            "category":"Restaurant",
            "type":"Food & Drink"
        }
    ],
    "sg:phone":"+1 213 738 7008",
    "sg:postcode":"90005",
    "sg:province":"CA",
    "sg:tags":[
        "korean",
        "chinese"
    ],
    "wof:name":"Dong Roo",
    "wof:placetype":"venue"
},
  "geometry": {"coordinates":[-118.290706,34.060125],"type":"Point"}
}