{
  "type": "Feature",
  "properties": {
    "addr:full":"20290 Tuolumne Rd N Tuolumne CA 95379",
    "addr:postcode":"20290;95379",
    "addr:street":"Tuolumne Rd N",
    "iso:country":"US",
    "sg:address":"20290 Tuolumne Rd N",
    "sg:city":"Tuolumne",
    "sg:classifiers":[
        {
            "category":"Building & Trades",
            "subcategory":"Plumbing",
            "type":"Services"
        }
    ],
    "sg:phone":"+1 209 928 3477",
    "sg:postcode":"95379",
    "sg:province":"CA",
    "wof:name":"Dan & John Dunlap Plumbing Inc",
    "wof:placetype":"venue"
},
  "geometry": {"coordinates":[-120.246002,37.986401],"type":"Point"}
}