{
  "type": "Feature",
  "properties": {
    "addr:full":"807 N Bunker Hill Ave Los Angeles CA 90012",
    "addr:housenumber":"807",
    "addr:postcode":"90012",
    "addr:street":"N Bunker Hill Ave",
    "iso:country":"US",
    "sg:address":"807 N Bunker Hill Ave",
    "sg:city":"Los Angeles",
    "sg:classifiers":[
        {
            "category":"Insurance",
            "subcategory":"Insurance Agent",
            "type":"Services"
        }
    ],
    "sg:phone":"+1 213 626 2014",
    "sg:postcode":"90012",
    "sg:province":"CA",
    "sg:tags":[
        "processing"
    ],
    "wof:name":"Pro-Claim Inc",
    "wof:placetype":"venue"
},
  "geometry": {"coordinates":[-118.24235899999999,34.06445],"type":"Point"}
}