{
  "type": "Feature",
  "properties": {
    "addr:full":"442 Hyde St San Francisco CA 94109",
    "addr:housenumber":"442",
    "addr:postcode":"94109",
    "addr:street":"Hyde St",
    "iso:country":"US",
    "sg:address":"442 Hyde St",
    "sg:city":"San Francisco",
    "sg:classifiers":[
        {
            "category":"Restaurant",
            "type":"Food & Drink"
        }
    ],
    "sg:phone":"+1 415 567 0398",
    "sg:postcode":"94109",
    "sg:province":"CA",
    "sg:tags":[
        "shop",
        "coffee"
    ],
    "wof:name":"KMT Cafe",
    "wof:placetype":"venue"
},
  "geometry": {"coordinates":[-122.416122,37.78499],"type":"Point"}
}