{
  "type": "Feature",
  "properties": {
    "addr:full":"1863 S Norfolk St San Mateo CA 94403",
    "addr:housenumber":"1863",
    "addr:postcode":"94403",
    "addr:street":"S Norfolk St",
    "iso:country":"US",
    "sg:address":"1863 S Norfolk St",
    "sg:city":"San Mateo",
    "sg:classifiers":[
        {
            "category":"Professional",
            "subcategory":"Business Services",
            "type":"Services"
        }
    ],
    "sg:phone":"+1 650 345 9605",
    "sg:postcode":"94403",
    "sg:province":"CA",
    "sg:tags":[
        "equipment",
        "liquidator"
    ],
    "sg:website":"www.abettersource.com",
    "wof:name":"Better Source Liquidators",
    "wof:placetype":"venue"
},
  "geometry": {"coordinates":[-122.29301100000001,37.555409],"type":"Point"}
}