{
  "type": "Feature",
  "properties": {
    "addr:full":"1001 Sylmar Ave Ofc Clovis CA 93612",
    "addr:housenumber":"1001",
    "addr:postcode":"93612",
    "addr:street":"Sylmar Ave",
    "iso:country":"US",
    "sg:address":"1001 Sylmar Ave Ofc",
    "sg:city":"Clovis",
    "sg:classifiers":[
        {
            "category":"Building & Trades",
            "subcategory":"Construction",
            "type":"Services"
        }
    ],
    "sg:phone":"+1 559 299 9261",
    "sg:postcode":"93612",
    "sg:province":"CA",
    "sg:tags":[
        "manufactured",
        "housing-communities"
    ],
    "wof:name":"Woods Mobile Country Club",
    "wof:placetype":"venue"
},
  "geometry": {"coordinates":[-119.721107,36.81786],"type":"Point"}
}