{
  "type": "Feature",
  "properties": {
    "iso:country":"US",
    "sg:address":"18401 Von Karman Avenue Suite 350",
    "sg:city":"Irvine",
    "sg:classifiers":[
        {
            "category":"Building & Trades",
            "subcategory":"Construction",
            "type":"Services"
        }
    ],
    "sg:phone":"+1 949 253 7100",
    "sg:postcode":"92612",
    "sg:province":"CA",
    "sg:tags":[
        "contractor"
    ],
    "wof:name":"Vintage Communities",
    "wof:placetype":"venue"
},
  "geometry": {"coordinates":[-117.829486,33.662148],"type":"Point"}
}