{
  "type": "Feature",
  "properties": {
    "addr:full":"197 Country Club Gate Center Pacific Grove CA 93950",
    "addr:housenumber":"197",
    "addr:postcode":"93950",
    "addr:street":"Country Club Gate",
    "iso:country":"US",
    "sg:address":"197 Country Club Gate Center",
    "sg:city":"Pacific Grove",
    "sg:classifiers":[
        {
            "category":"Restaurant",
            "type":"Food & Drink"
        }
    ],
    "sg:phone":"+1 831 647 8654",
    "sg:postcode":"93950",
    "sg:province":"CA",
    "wof:name":"Michael's Grill & Taqueria",
    "wof:placetype":"venue"
},
  "geometry": {"coordinates":[-121.92291,36.609281],"type":"Point"}
}