{
  "type": "Feature",
  "properties": {
    "iso:country":"US",
    "sg:address":"903 Hunter St",
    "sg:city":"Ramona",
    "sg:classifiers":[
        {
            "category":"Manufacturing",
            "subcategory":"Printing",
            "type":"Manufacturing & Wholesale Goods"
        }
    ],
    "sg:phone":"+1 760 788 1669",
    "sg:postcode":"92065",
    "sg:province":"CA",
    "sg:tags":[
        "newspaper"
    ],
    "wof:name":"Herald Brooks P",
    "wof:placetype":"venue"
},
  "geometry": {"coordinates":[-116.886046,33.023663],"type":"Point"}
}