{
  "type": "Feature",
  "properties": {
    "iso:country":"US",
    "sg:address":"940 W San Marcos Blvd",
    "sg:city":"San Marcos",
    "sg:classifiers":[
        {
            "category":"Personal",
            "subcategory":"Beauty Salon",
            "type":"Services"
        }
    ],
    "sg:phone":"+1 760 752 3142",
    "sg:postcode":"92078",
    "sg:province":"CA",
    "wof:name":"Salon Bellezza",
    "wof:placetype":"venue"
},
  "geometry": {"coordinates":[-117.183984,33.135923],"type":"Point"}
}