{
  "type": "Feature",
  "properties": {
    "addr:full":"4 S 2nd St San Jose CA 95113",
    "addr:housenumber":"4",
    "addr:postcode":"95113",
    "addr:street":"S 2Nd St",
    "iso:country":"US",
    "sg:address":"4 S 2nd St",
    "sg:city":"San Jose",
    "sg:classifiers":[
        {
            "category":"Government",
            "subcategory":"Court House",
            "type":"Public Place"
        }
    ],
    "sg:phone":"+1 408 299 7200",
    "sg:postcode":"95113",
    "sg:province":"CA",
    "sg:tags":[
        "legal"
    ],
    "wof:name":"Public Dfender Alternate- Main",
    "wof:placetype":"venue"
},
  "geometry": {"coordinates":[-121.889126,37.336276],"type":"Point"}
}