{
  "type": "Feature",
  "properties": {
    "iso:country":"US",
    "sg:address":"1001 W Ranch Rd",
    "sg:city":"Pescadero",
    "sg:classifiers":[
        {
            "category":"Wholesale",
            "subcategory":"Plants",
            "type":"Manufacturing & Wholesale Goods"
        }
    ],
    "sg:phone":"+1 650 879 0264",
    "sg:postcode":"94060",
    "sg:province":"CA",
    "sg:tags":[
        "nursery",
        "tree"
    ],
    "wof:name":"Fogline Nursery",
    "wof:placetype":"venue"
},
  "geometry": {"coordinates":[-122.33551799999999,37.240269],"type":"Point"}
}