{
  "type": "Feature",
  "properties": {
    "iso:country":"US",
    "sg:address":"1950 S Bascom Ave",
    "sg:city":"Campbell",
    "sg:classifiers":[
        {
            "category":"Fast Food",
            "type":"Food & Drink"
        },
        {
            "category":"Restaurant",
            "type":"Food & Drink"
        }
    ],
    "sg:phone":"+1 408 371 5611",
    "sg:postcode":"95009",
    "sg:province":"CA",
    "sg:tags":[
        "mexican"
    ],
    "wof:name":"Taco Bravo",
    "wof:placetype":"venue"
},
  "geometry": {"coordinates":[-121.93156999999999,37.288069],"type":"Point"}
}