{
  "type": "Feature",
  "properties": {
    "iso:country":"US",
    "sg:address":"3400 Patterson Rd",
    "sg:city":"Riverbank",
    "sg:classifiers":[
        {
            "category":"Manufacturing",
            "subcategory":"Wood Products",
            "type":"Manufacturing & Wholesale Goods"
        }
    ],
    "sg:phone":"+1 209 869 4561",
    "sg:postcode":"95367",
    "sg:province":"CA",
    "sg:tags":[
        "lumber"
    ],
    "wof:name":"Thunderbolt Wood Treating Co",
    "wof:placetype":"venue"
},
  "geometry": {"coordinates":[-120.931328,37.732693],"type":"Point"}
}