{
  "type": "Feature",
  "properties": {
    "iso:country":"US",
    "sg:address":"1801 Fort Jones Rd",
    "sg:city":"Yreka",
    "sg:classifiers":[
        {
            "category":"Restaurant",
            "type":"Food & Drink"
        }
    ],
    "sg:phone":"+1 530 842 5768",
    "sg:postcode":"96097",
    "sg:province":"CA",
    "wof:name":"Dos Amigos Steak House",
    "wof:placetype":"venue"
},
  "geometry": {"coordinates":[-122.644977,41.703807],"type":"Point"}
}