{
  "type": "Feature",
  "properties": {
    "iso:country":"US",
    "sg:address":"1753 Doncaster Ct",
    "sg:city":"Fairfield",
    "sg:classifiers":[
        {
            "category":"Home & Garden",
            "subcategory":"Building Materials",
            "type":"Retail Goods"
        }
    ],
    "sg:phone":"+1 707 428 9806",
    "sg:postcode":"94533",
    "sg:province":"CA",
    "sg:tags":[
        "glass",
        "leaded"
    ],
    "wof:name":"Shards Of Light",
    "wof:placetype":"venue"
},
  "geometry": {"coordinates":[-122.016334,38.296877],"type":"Point"}
}