{
  "type": "Feature",
  "properties": {
    "addr:full":"118 Oak Park Dr Los Gatos CA 95032",
    "addr:housenumber":"118",
    "addr:postcode":"95032",
    "addr:street":"Oak Park Dr",
    "iso:country":"US",
    "sg:address":"118 Oak Park Dr",
    "sg:city":"Los Gatos",
    "sg:classifiers":[
        {
            "category":"Recreation",
            "subcategory":"Playground",
            "type":"Entertainment"
        }
    ],
    "sg:phone":"+1 408 399 5770",
    "sg:postcode":"95032",
    "sg:province":"CA",
    "sg:website":"www.town.los-gatos.ca.us/index.a...",
    "wof:name":"Oak Hill Playlot",
    "wof:placetype":"venue"
},
  "geometry": {"coordinates":[-121.958727,37.246437],"type":"Point"}
}