{
  "type": "Feature",
  "properties": {
    "addr:full":"631 Reed St Santa Clara CA 95050",
    "addr:housenumber":"631",
    "addr:postcode":"95050",
    "addr:street":"Reed St",
    "iso:country":"US",
    "sg:address":"631 Reed St",
    "sg:city":"Santa Clara",
    "sg:classifiers":[
        {
            "category":"Building & Trades",
            "subcategory":"Construction",
            "type":"Services"
        }
    ],
    "sg:phone":"+1 408 970 8823",
    "sg:postcode":"95050",
    "sg:province":"CA",
    "sg:tags":[
        "maker",
        "cabinet"
    ],
    "wof:name":"Oak Designs Custom Cabinetry",
    "wof:placetype":"venue"
},
  "geometry": {"coordinates":[-121.94466,37.35942],"type":"Point"}
}