{
  "type": "Feature",
  "properties": {
    "iso:country":"US",
    "sg:address":"2048 Orange Tree Ln",
    "sg:city":"Redlands",
    "sg:classifiers":[
        {
            "category":"Health Services",
            "subcategory":"Doctor",
            "type":"Services"
        }
    ],
    "sg:phone":"+1 909 798 1614",
    "sg:postcode":"92374",
    "sg:province":"CA",
    "sg:tags":[
        "physician",
        "surgeon"
    ],
    "wof:name":"Forever Slim Weight Control",
    "wof:placetype":"venue"
},
  "geometry": {"coordinates":[-117.225751,34.068112],"type":"Point"}
}