{
  "type": "Feature",
  "properties": {
    "iso:country":"US",
    "sg:address":"236 States St",
    "sg:city":"San Francisco",
    "sg:classifiers":[
        {
            "category":"Professional",
            "subcategory":"Management & Consulting",
            "type":"Services"
        }
    ],
    "sg:phone":"+1 415 552 5598",
    "sg:postcode":"94114",
    "sg:province":"CA",
    "sg:tags":[
        "marketing",
        "program"
    ],
    "sg:website":"www.marcus.com",
    "wof:name":"Ari Marcus & Co",
    "wof:placetype":"venue"
},
  "geometry": {"coordinates":[-122.441399,37.764593],"type":"Point"}
}