{
  "type": "Feature",
  "properties": {
    "addr:full":"1174 Castro St Ste 275 Mountain View CA 94040",
    "addr:housenumber":"1174",
    "addr:postcode":"94040",
    "addr:street":"Castro St Ste 275",
    "iso:country":"US",
    "sg:address":"1174 Castro St Ste 275",
    "sg:city":"Mountain View",
    "sg:classifiers":[
        {
            "category":"Community Center",
            "type":"Public Place"
        }
    ],
    "sg:phone":"+1 650 988 8011",
    "sg:postcode":"94040",
    "sg:province":"CA",
    "sg:tags":[
        "medical"
    ],
    "sg:website":"buchholzmedgroup.com",
    "wof:name":"Buchholz Medical Group",
    "wof:placetype":"venue"
},
  "geometry": {"coordinates":[-122.086286,37.381578],"type":"Point"}
}