{
  "type": "Feature",
  "properties": {
    "addr:full":"999 Pennsylvania Avenue San Francisco CA 94107",
    "addr:housenumber":"999",
    "addr:postcode":"94107",
    "addr:street":"Pennsylvania Avenue",
    "iso:country":"US",
    "sg:address":"999 Pennsylvania Avenue",
    "sg:city":"San Francisco",
    "sg:classifiers":[
        {
            "category":"Taxi",
            "type":"Transportation"
        }
    ],
    "sg:phone":"+1 415 285 3800",
    "sg:postcode":"94107",
    "sg:province":"CA",
    "wof:name":"Black & White Checker Cabs",
    "wof:placetype":"venue"
},
  "geometry": {"coordinates":[-122.392776,37.754039],"type":"Point"}
}