{
  "type": "Feature",
  "properties": {
    "iso:country":"US",
    "sg:address":"1109 W Union Ave",
    "sg:city":"Modesto",
    "sg:classifiers":[
        {
            "category":"Professional",
            "subcategory":"Detective & Security Services",
            "type":"Services"
        }
    ],
    "sg:phone":"+1 209 409 4479",
    "sg:postcode":"95356",
    "sg:province":"CA",
    "sg:tags":[
        "car",
        "armored"
    ],
    "wof:name":"Armoured Guardian",
    "wof:placetype":"venue"
},
  "geometry": {"coordinates":[-121.008899,37.692929],"type":"Point"}
}