{
  "type": "Feature",
  "properties": {
    "addr:full":"11130 Magnolia Ave Riverside CA 92505",
    "addr:housenumber":"11130",
    "addr:postcode":"92505",
    "addr:street":"Magnolia Ave",
    "iso:country":"US",
    "sg:address":"11130 Magnolia Ave",
    "sg:city":"Riverside",
    "sg:classifiers":[
        {
            "category":"Personal",
            "subcategory":"Beauty Salon",
            "type":"Services"
        }
    ],
    "sg:phone":"+1 951 359 5461",
    "sg:postcode":"92505",
    "sg:province":"CA",
    "wof:name":"Creative Image Hair & Nail Sln",
    "wof:placetype":"venue"
},
  "geometry": {"coordinates":[-117.476921,33.903015],"type":"Point"}
}