{
  "type": "Feature",
  "properties": {
    "iso:country":"US",
    "sg:address":"925 W 223rd St",
    "sg:city":"Torrance",
    "sg:classifiers":[
        {
            "category":"Organizations",
            "subcategory":"Religious Organization",
            "type":"Services"
        }
    ],
    "sg:phone":"+1 310 328 1664",
    "sg:postcode":"90502",
    "sg:province":"CA",
    "sg:tags":[
        "churches-baptist",
        "church"
    ],
    "wof:name":"Iglesia Bautista Horeb",
    "wof:placetype":"venue"
},
  "geometry": {"coordinates":[-118.291025,33.824445],"type":"Point"}
}