{
  "type": "Feature",
  "properties": {
    "addr:full":"122 Clear Creek Ct Martinez CA 94553",
    "addr:housenumber":"122",
    "addr:postcode":"94553",
    "addr:street":"Clear Creek Ct",
    "iso:country":"US",
    "sg:address":"122 Clear Creek Ct",
    "sg:city":"Martinez",
    "sg:classifiers":[
        {
            "category":"Building & Trades",
            "subcategory":"Construction",
            "type":"Services"
        }
    ],
    "sg:phone":"+1 925 938 2233",
    "sg:postcode":"94553",
    "sg:province":"CA",
    "sg:tags":[
        "designer"
    ],
    "wof:name":"Laura's Design",
    "wof:placetype":"venue"
},
  "geometry": {"coordinates":[-122.095265,37.957204],"type":"Point"}
}