{
  "type": "Feature",
  "properties": {
    "addr:full":"2017 Girard St Delano CA 93215",
    "addr:housenumber":"2017",
    "addr:postcode":"93215",
    "addr:street":"Girard St",
    "iso:country":"US",
    "sg:address":"2017 Girard St",
    "sg:city":"Delano",
    "sg:classifiers":[
        {
            "category":"Retail",
            "subcategory":"Repair Shop",
            "type":"Services"
        }
    ],
    "sg:phone":"+1 661 725 2265",
    "sg:postcode":"93215",
    "sg:province":"CA",
    "sg:tags":[
        "upholsterer"
    ],
    "wof:name":"Dorsey's Upholstering",
    "wof:placetype":"venue"
},
  "geometry": {"coordinates":[-119.249871,35.78437],"type":"Point"}
}