{
  "type": "Feature",
  "properties": {
    "addr:full":"482 W San Ysidro Blvd San Ysidro CA 92173",
    "addr:housenumber":"482",
    "addr:postcode":"92173",
    "addr:street":"W San Ysidro Blvd",
    "iso:country":"US",
    "sg:address":"482 W San Ysidro Blvd",
    "sg:city":"San Ysidro",
    "sg:classifiers":[
        {
            "category":"Cinema",
            "subcategory":"Movie Rental",
            "type":"Entertainment"
        }
    ],
    "sg:phone":"+1 619 662 5930",
    "sg:postcode":"92173",
    "sg:province":"CA",
    "sg:tags":[
        "leasing",
        "video",
        "disc",
        "tape"
    ],
    "wof:name":"Fotografia Y Video",
    "wof:placetype":"venue"
},
  "geometry": {"coordinates":[-117.05206800000001,32.555515],"type":"Point"}
}