{
  "type": "Feature",
  "properties": {
    "iso:country":"US",
    "sg:address":"26734 Jordan Rd",
    "sg:city":"Helendale",
    "sg:classifiers":[
        {
            "category":"Manufacturing",
            "subcategory":"Printing",
            "type":"Manufacturing & Wholesale Goods"
        }
    ],
    "sg:phone":"+1 760 952 3834",
    "sg:postcode":"92342",
    "sg:province":"CA",
    "sg:tags":[
        "printer"
    ],
    "wof:name":"Sol Printing & Graphics Inc",
    "wof:placetype":"venue"
},
  "geometry": {"coordinates":[-117.328007,34.736107],"type":"Point"}
}