{
  "type": "Feature",
  "properties": {
    "iso:country":"US",
    "sg:address":"2976 Alvarado St",
    "sg:city":"San Leandro",
    "sg:classifiers":[
        {
            "category":"Freight",
            "type":"Transportation"
        }
    ],
    "sg:phone":"+1 510 483 9424",
    "sg:postcode":"94577",
    "sg:province":"CA",
    "sg:tags":[
        "warehouse",
        "self",
        "storage",
        "general"
    ],
    "wof:name":"S & S Warehousing Inc",
    "wof:placetype":"venue"
},
  "geometry": {"coordinates":[-122.154295,37.708892],"type":"Point"}
}