{
  "type": "Feature",
  "properties": {
    "iso:country":"US",
    "sg:address":"700 Mountain View Ave A",
    "sg:city":"Oxnard",
    "sg:classifiers":[
        {
            "category":"Retail",
            "subcategory":"Auto Repair",
            "type":"Services"
        }
    ],
    "sg:phone":"+1 805 486 4349",
    "sg:postcode":"93030",
    "sg:province":"CA",
    "sg:tags":[
        "body",
        "repairing",
        "painting",
        "automobile"
    ],
    "wof:name":"New Era Body Shop",
    "wof:placetype":"venue"
},
  "geometry": {"coordinates":[-119.170286,34.193794],"type":"Point"}
}