{
  "type": "Feature",
  "properties": {
    "iso:country":"US",
    "sg:address":"617 S Lower Sacramento Rd",
    "sg:city":"Lodi",
    "sg:classifiers":[
        {
            "category":"Real Estate",
            "subcategory":"Architect",
            "type":"Services"
        }
    ],
    "sg:phone":"+1 209 369 9547",
    "sg:postcode":"95242",
    "sg:province":"CA",
    "sg:tags":[
        "architectural",
        "landscape"
    ],
    "wof:name":"K D A",
    "wof:placetype":"venue"
},
  "geometry": {"coordinates":[-121.306721,38.126503],"type":"Point"}
}