{
  "type": "Feature",
  "properties": {
    "addr:full":"200 Sloat Blvd San Francisco CA 94132",
    "addr:housenumber":"200",
    "addr:postcode":"94132",
    "addr:street":"Sloat Blvd",
    "iso:country":"US",
    "sg:address":"200 Sloat Blvd",
    "sg:city":"San Francisco",
    "sg:classifiers":[
        {
            "category":"Education",
            "subcategory":"School",
            "type":"Public Place"
        }
    ],
    "sg:phone":"+1 415 665 6330",
    "sg:postcode":"94132",
    "sg:province":"CA",
    "sg:tags":[
        "high",
        "middle",
        "elementary"
    ],
    "sg:website":"www.wplsf.com",
    "wof:name":"West Portal Lutheran School",
    "wof:placetype":"venue"
},
  "geometry": {"coordinates":[-122.474405,37.73478],"type":"Point"}
}