{
  "type": "Feature",
  "properties": {
    "addr:full":"1300 N Tustin St Orange CA 92867",
    "addr:housenumber":"1300",
    "addr:postcode":"92867",
    "addr:street":"N Tustin St",
    "iso:country":"US",
    "sg:address":"1300 N Tustin St",
    "sg:city":"Orange",
    "sg:classifiers":[
        {
            "category":"Shopping",
            "subcategory":"Florist",
            "type":"Retail Goods"
        }
    ],
    "sg:phone":"+1 714 538 0770",
    "sg:postcode":"92867",
    "sg:province":"CA",
    "sg:website":"www.capriflowersorange.com/",
    "wof:name":"Capri Flowers",
    "wof:placetype":"venue"
},
  "geometry": {"coordinates":[-117.836152,33.809483],"type":"Point"}
}