{
  "type": "Feature",
  "properties": {
    "addr:full":"17011 Beach Blvd Ste Garden Grove CA 92840",
    "addr:housenumber":"17011",
    "addr:postcode":"92840",
    "addr:street":"Beach Blvd Ste",
    "iso:country":"US",
    "sg:address":"17011 Beach Blvd Ste",
    "sg:city":"Garden Grove",
    "sg:classifiers":[
        {
            "category":"Banks & Credit Unions",
            "subcategory":"Bank",
            "type":"Services"
        }
    ],
    "sg:phone":"+1 714 848 6368",
    "sg:postcode":"92840",
    "sg:province":"CA",
    "wof:name":"Ferraro Jr Carl J Insurance Agency Inc",
    "wof:placetype":"venue"
},
  "geometry": {"coordinates":[-117.931,33.784698],"type":"Point"}
}