{
  "type": "Feature",
  "properties": {
    "iso:country":"US",
    "sg:address":"1015 Airport Rd",
    "sg:city":"Rio Vista",
    "sg:classifiers":[
        {
            "category":"Freight",
            "type":"Transportation"
        }
    ],
    "sg:phone":"+1 707 374 5800",
    "sg:postcode":"94571",
    "sg:province":"CA",
    "sg:tags":[
        "hauling",
        "trucking"
    ],
    "wof:name":"Allan Farmer Trucking",
    "wof:placetype":"venue"
},
  "geometry": {"coordinates":[-121.687176,38.173518],"type":"Point"}
}