{
  "type": "Feature",
  "properties": {
    "iso:country":"US",
    "sg:address":"5000 Birch St",
    "sg:city":"Newport Beach",
    "sg:classifiers":[
        {
            "category":"Professional",
            "type":"Services"
        }
    ],
    "sg:phone":"+1 949 475 6807",
    "sg:postcode":"92660",
    "sg:province":"CA",
    "sg:tags":[
        "establishment"
    ],
    "wof:name":"Document Solutions",
    "wof:placetype":"venue"
},
  "geometry": {"coordinates":[-117.858181,33.665774],"type":"Point"}
}