{
  "type": "Feature",
  "properties": {
    "addr:full":"8438 S Vermont Ave Los Angeles CA 90044",
    "addr:housenumber":"8438",
    "addr:postcode":"90044",
    "addr:street":"S Vermont Ave",
    "iso:country":"US",
    "sg:address":"8438 S Vermont Ave",
    "sg:city":"Los Angeles",
    "sg:classifiers":[
        {
            "category":"Personal",
            "subcategory":"Beauty Salon",
            "type":"Services"
        }
    ],
    "sg:phone":"+1 323 541 9301",
    "sg:postcode":"90044",
    "sg:province":"CA",
    "wof:name":"C Q Nails & Spa Chairs",
    "wof:placetype":"venue"
},
  "geometry": {"coordinates":[-118.291489,33.961373],"type":"Point"}
}