{
  "type": "Feature",
  "properties": {
    "iso:country":"US",
    "sg:address":"5525 Imperial Hwy",
    "sg:city":"South Gate",
    "sg:classifiers":[
        {
            "category":"Education",
            "subcategory":"Library",
            "type":"Public Place"
        }
    ],
    "sg:phone":"+1 562 861 0316",
    "sg:postcode":"90280",
    "sg:province":"CA",
    "wof:name":"Los Angeles County Law Library Beverly Hills Br",
    "wof:placetype":"venue"
},
  "geometry": {"coordinates":[-118.172997,33.9305],"type":"Point"}
}