{
  "type": "Feature",
  "properties": {
    "addr:full":"6135 Blue Mountain Rd Wilseyville CA 95257",
    "addr:housenumber":"6135",
    "addr:postcode":"95257",
    "addr:street":"Blue Mountain Rd",
    "iso:country":"US",
    "sg:address":"6135 Blue Mountain Rd",
    "sg:city":"Wilseyville",
    "sg:classifiers":[
        {
            "category":"Recreation",
            "type":"Entertainment"
        }
    ],
    "sg:phone":"+1 209 293 4980",
    "sg:postcode":"95257",
    "sg:province":"CA",
    "sg:tags":[
        "camps-recreational"
    ],
    "wof:name":"Lodestar Camp",
    "wof:placetype":"venue"
},
  "geometry": {"coordinates":[-120.462879,38.373678],"type":"Point"}
}