{
  "type": "Feature",
  "properties": {
    "iso:country":"US",
    "sg:address":"2750 Main St",
    "sg:city":"Susanville",
    "sg:classifiers":[
        {
            "category":"Autos & Motor Vehicles",
            "subcategory":"Fuel & Gas Station",
            "type":"Retail Goods"
        }
    ],
    "sg:phone":"+1 530 257 4076",
    "sg:postcode":"96130",
    "sg:province":"CA",
    "sg:tags":[
        "oil"
    ],
    "wof:name":"Shell",
    "wof:placetype":"venue"
},
  "geometry": {"coordinates":[-120.638212,40.412056],"type":"Point"}
}