{
  "type": "Feature",
  "properties": {
    "addr:full":"11616 Garvey Ave El Monte CA 91732",
    "addr:housenumber":"11616",
    "addr:postcode":"91732",
    "addr:street":"Garvey Ave",
    "iso:country":"US",
    "sg:address":"11616 Garvey Ave",
    "sg:city":"El Monte",
    "sg:classifiers":[
        {
            "category":"Insurance",
            "subcategory":"Insurance Agent",
            "type":"Services"
        }
    ],
    "sg:phone":"+1 626 582 4785",
    "sg:postcode":"91732",
    "sg:province":"CA",
    "wof:name":"Revival Insurance Services",
    "wof:placetype":"venue"
},
  "geometry": {"coordinates":[-118.02628900000001,34.062755],"type":"Point"}
}