{
  "type": "Feature",
  "properties": {
    "addr:full":"800 W Broadway St Ste A Needles CA 92363",
    "addr:housenumber":"800",
    "addr:postcode":"92363",
    "addr:street":"W Broadway St Ste A",
    "iso:country":"US",
    "sg:address":"800 W Broadway St Ste A",
    "sg:city":"Needles",
    "sg:classifiers":[
        {
            "category":"Shopping",
            "subcategory":"Department Store",
            "type":"Retail Goods"
        }
    ],
    "sg:phone":"+1 760 326 8875",
    "sg:postcode":"92363",
    "sg:province":"CA",
    "wof:name":"99 Cent Pavilion",
    "wof:placetype":"venue"
},
  "geometry": {"coordinates":[-114.604851,34.838718],"type":"Point"}
}