{
  "type": "Feature",
  "properties": {
    "addr:full":"12445 Moorpark St Ste B Studio City CA 91604",
    "addr:housenumber":"12445",
    "addr:postcode":"91604",
    "addr:street":"Moorpark St Ste B",
    "iso:country":"US",
    "sg:address":"12445 Moorpark St Ste B",
    "sg:city":"Studio City",
    "sg:classifiers":[
        {
            "category":"Arts & Performance",
            "subcategory":"Arts Center",
            "type":"Entertainment"
        },
        {
            "category":"Education",
            "subcategory":"Special Training",
            "type":"Public Place"
        }
    ],
    "sg:phone":"+1 818 509 1064",
    "sg:postcode":"91604",
    "sg:province":"CA",
    "sg:tags":[
        "school",
        "performing",
        "specialty"
    ],
    "wof:name":"Richard Brander Acting Studio",
    "wof:placetype":"venue"
},
  "geometry": {"coordinates":[-118.404608,34.150614],"type":"Point"}
}