{
  "type": "Feature",
  "properties": {
    "addr:full":"4001 Las Positas Rd Livermore CA 94551",
    "addr:housenumber":"4001",
    "addr:postcode":"94551",
    "addr:street":"Las Positas Rd",
    "iso:country":"US",
    "sg:address":"4001 Las Positas Rd",
    "sg:city":"Livermore",
    "sg:classifiers":[
        {
            "category":"Professional",
            "subcategory":"Accounting & Tax Preparation",
            "type":"Services"
        }
    ],
    "sg:phone":"+1 925 449 0595",
    "sg:postcode":"94551",
    "sg:province":"CA",
    "sg:tags":[
        "accountant"
    ],
    "wof:name":"Madeleine Heal CPA",
    "wof:placetype":"venue"
},
  "geometry": {"coordinates":[-121.756748,37.701831],"type":"Point"}
}