{
  "type": "Feature",
  "properties": {
    "iso:country":"US",
    "sg:address":"25673 Nickel Pl",
    "sg:city":"Hayward",
    "sg:classifiers":[
        {
            "category":"Home & Garden",
            "subcategory":"Furniture",
            "type":"Retail Goods"
        }
    ],
    "sg:phone":"+1 510 887 6000",
    "sg:postcode":"94545",
    "sg:province":"CA",
    "sg:tags":[
        "top",
        "counter",
        "contractor"
    ],
    "sg:website":"www.solid-surface.com",
    "wof:name":"Surface Technology Corp",
    "wof:placetype":"venue"
},
  "geometry": {"coordinates":[-122.12400100000001,37.632301],"type":"Point"}
}