{
  "type": "Feature",
  "properties": {
    "addr:full":"421 El Camino Real San Bruno CA 94066",
    "addr:housenumber":"421",
    "addr:postcode":"94066",
    "addr:street":"El Camino Real",
    "iso:country":"US",
    "sg:address":"421 El Camino Real",
    "sg:city":"San Bruno",
    "sg:classifiers":[
        {
            "category":"Travel",
            "subcategory":"Hotels & Motels",
            "type":"Entertainment"
        }
    ],
    "sg:phone":"+1 650 624 0999",
    "sg:postcode":"94066",
    "sg:province":"CA",
    "sg:website":"www.sanbrunosuper8.com",
    "wof:name":"Super 8 Motel",
    "wof:placetype":"venue"
},
  "geometry": {"coordinates":[-122.412322,37.621754],"type":"Point"}
}