{
  "type": "Feature",
  "properties": {
    "addr:full":"2900 Myers St Oroville CA 95966",
    "addr:housenumber":"2900",
    "addr:postcode":"95966",
    "addr:street":"Myers St",
    "iso:country":"US",
    "sg:address":"2900 Myers St",
    "sg:city":"Oroville",
    "sg:classifiers":[
        {
            "category":"Home & Garden",
            "subcategory":"Building Materials",
            "type":"Retail Goods"
        }
    ],
    "sg:phone":"+1 530 533 3696",
    "sg:postcode":"95966",
    "sg:province":"CA",
    "sg:tags":[
        "glass",
        "window",
        "plate"
    ],
    "wof:name":"Jackson's Glass",
    "wof:placetype":"venue"
},
  "geometry": {"coordinates":[-121.54916,39.502165],"type":"Point"}
}