{
  "type": "Feature",
  "properties": {
    "addr:full":"1740 E Avenue J Lancaster CA 93535",
    "addr:housenumber":"1740",
    "addr:postcode":"93535",
    "addr:street":"E Avenue J",
    "iso:country":"US",
    "sg:address":"1740 E Avenue J",
    "sg:city":"Lancaster",
    "sg:classifiers":[
        {
            "category":"Restaurant",
            "type":"Food & Drink"
        }
    ],
    "sg:menulink":"http://www.allmenus.com/ca/north-antelope-valley/214175-taco-bell/menu/",
    "sg:phone":"+1 661 940 1994",
    "sg:postcode":"93535",
    "sg:province":"CA",
    "sg:tags":[
        "mexican"
    ],
    "wof:name":"Taco Bell",
    "wof:placetype":"venue"
},
  "geometry": {"coordinates":[-118.098282,34.689464],"type":"Point"}
}