{
  "type": "Feature",
  "properties": {
    "iso:country":"US",
    "sg:address":"1173 S De Anza Blvd",
    "sg:city":"San Jose",
    "sg:classifiers":[
        {
            "category":"Health Services",
            "subcategory":"Doctor",
            "type":"Services"
        },
        {
            "category":"Health Services",
            "subcategory":"Health Practitioner",
            "type":"Services"
        }
    ],
    "sg:phone":"+1 408 252 8017",
    "sg:postcode":"95129",
    "sg:province":"CA",
    "sg:tags":[
        "acupuncture"
    ],
    "wof:name":"Dr William Wang Lac PHD",
    "wof:placetype":"venue"
},
  "geometry": {"coordinates":[-122.031998,37.303398],"type":"Point"}
}