{
  "type": "Feature",
  "properties": {
    "addr:full":"1518 Vanessa Cir Encinitas CA 92024",
    "addr:housenumber":"1518",
    "addr:postcode":"92024",
    "addr:street":"Vanessa Cir",
    "iso:country":"US",
    "sg:address":"1518 Vanessa Cir",
    "sg:city":"Encinitas",
    "sg:classifiers":[
        {
            "category":"Professional",
            "subcategory":"Business Services",
            "type":"Services"
        }
    ],
    "sg:phone":"+1 760 942 8911",
    "sg:postcode":"92024",
    "sg:province":"CA",
    "sg:tags":[
        "appraiser"
    ],
    "wof:name":"Southwest Appraisers",
    "wof:placetype":"venue"
},
  "geometry": {"coordinates":[-117.257977,33.056365],"type":"Point"}
}