{
  "type": "Feature",
  "properties": {
    "iso:country":"US",
    "sg:address":"681 S Tustin St #113",
    "sg:city":"Orange",
    "sg:classifiers":[
        {
            "category":"Insurance",
            "subcategory":"Insurance Agent",
            "type":"Services"
        },
        {
            "category":"Insurance",
            "subcategory":"Title Insurance",
            "type":"Services"
        },
        {
            "category":"Insurance",
            "subcategory":"Hazard Insurance",
            "type":"Services"
        },
        {
            "category":"Banks & Credit Unions",
            "subcategory":"Financial Services",
            "type":"Services"
        },
        {
            "category":"Insurance",
            "subcategory":"Life Insurance",
            "type":"Services"
        }
    ],
    "sg:phone":"+1 714 769 7007",
    "sg:postcode":"92866",
    "sg:province":"CA",
    "sg:tags":[
        "retirement",
        "business",
        "annuity",
        "commercial",
        "homeowner",
        "plan",
        "auto",
        "analyst",
        "consultant"
    ],
    "sg:website":"http://www.farmersagent.com/mbuttacavoli/",
    "wof:name":"Michael Buttacavoli - Farmers Insurance",
    "wof:placetype":"venue"
},
  "geometry": {"coordinates":[-117.835747,33.777672],"type":"Point"}
}