{
  "type": "Feature",
  "properties": {
    "addr:full":"263 South LaCienega Blvd Beverly Hills CA 90211",
    "addr:housenumber":"263",
    "addr:postcode":"90211",
    "addr:street":"South Lacienega Blvd",
    "iso:country":"US",
    "sg:address":"263 South LaCienega Blvd",
    "sg:city":"Beverly Hills",
    "sg:classifiers":[
        {
            "category":"Shopping",
            "subcategory":"Jewelry",
            "type":"Retail Goods"
        },
        {
            "category":"Shopping",
            "subcategory":"Pawn Shop",
            "type":"Retail Goods"
        }
    ],
    "sg:phone":"+1 310 657 9999",
    "sg:postcode":"90211",
    "sg:province":"CA",
    "wof:name":"Gem and Loan of Beverly Hills",
    "wof:placetype":"venue"
},
  "geometry": {"coordinates":[-118.376385,34.069817],"type":"Point"}
}