{
  "type": "Feature",
  "properties": {
    "iso:country":"US",
    "sg:address":"8134 Stevenson Ave",
    "sg:city":"Sacramento",
    "sg:classifiers":[
        {
            "category":"Professional",
            "subcategory":"Management & Consulting",
            "type":"Services"
        }
    ],
    "sg:phone":"+1 916 796 6006",
    "sg:postcode":"95828",
    "sg:province":"CA",
    "sg:tags":[
        "consultant"
    ],
    "wof:name":"Ben The Consultant & Assoc",
    "wof:placetype":"venue"
},
  "geometry": {"coordinates":[-121.404639,38.46527],"type":"Point"}
}