{
  "type": "Feature",
  "properties": {
    "iso:country":"US",
    "sg:address":"200 S Main St",
    "sg:city":"Corona",
    "sg:classifiers":[
        {
            "category":"Banks & Credit Unions",
            "subcategory":"Bank",
            "type":"Services"
        }
    ],
    "sg:phone":"+1 951 278 1092",
    "sg:postcode":"92882",
    "sg:province":"CA",
    "wof:name":"Vineyard Bank",
    "wof:placetype":"venue"
},
  "geometry": {"coordinates":[-117.565763,33.879511],"type":"Point"}
}