{
  "type": "Feature",
  "properties": {
    "iso:country":"US",
    "sg:address":"630 Broadway St",
    "sg:city":"Vallejo",
    "sg:classifiers":[
        {
            "category":"Restaurant",
            "type":"Food & Drink"
        }
    ],
    "sg:phone":"+1 707 554 9681",
    "sg:postcode":"94590",
    "sg:province":"CA",
    "wof:name":"LA Cabanita Lunch Truck",
    "wof:placetype":"venue"
},
  "geometry": {"coordinates":[-122.24848299999999,38.113551],"type":"Point"}
}