{
  "type": "Feature",
  "properties": {
    "addr:full":"1556 Hartnell Ave Redding CA 96002",
    "addr:housenumber":"1556",
    "addr:postcode":"96002",
    "addr:street":"Hartnell Ave",
    "iso:country":"US",
    "sg:address":"1556 Hartnell Ave",
    "sg:city":"Redding",
    "sg:classifiers":[
        {
            "category":"Utilities",
            "subcategory":"Telephone",
            "type":"Services"
        }
    ],
    "sg:phone":"+1 530 222 4000",
    "sg:postcode":"96002",
    "sg:province":"CA",
    "sg:tags":[
        "telecommunication"
    ],
    "wof:name":"Communication Impact",
    "wof:placetype":"venue"
},
  "geometry": {"coordinates":[-122.34217200000001,40.563839],"type":"Point"}
}