{
  "type": "Feature",
  "properties": {
    "iso:country":"US",
    "sg:address":"5917 Oak Ave",
    "sg:city":"Temple City",
    "sg:classifiers":[
        {
            "category":"Building & Trades",
            "subcategory":"Plumbing",
            "type":"Services"
        }
    ],
    "sg:phone":"+1 626 287 8043",
    "sg:postcode":"91780",
    "sg:province":"CA",
    "sg:tags":[
        "conditioning",
        "air",
        "system",
        "contractor"
    ],
    "wof:name":"Rite Way Svc",
    "wof:placetype":"venue"
},
  "geometry": {"coordinates":[-118.065551,34.107566],"type":"Point"}
}