{
  "type": "Feature",
  "properties": {
    "iso:country":"US",
    "sg:address":"716 S Euclid Ave",
    "sg:city":"Ontario",
    "sg:classifiers":[
        {
            "category":"Shopping",
            "subcategory":"Computers & Home Electronics",
            "type":"Retail Goods"
        }
    ],
    "sg:phone":"+1 909 984 8585",
    "sg:postcode":"91762",
    "sg:province":"CA",
    "sg:tags":[
        "high",
        "fidelity",
        "stereophonic"
    ],
    "wof:name":"O B Audio",
    "wof:placetype":"venue"
},
  "geometry": {"coordinates":[-117.651023,34.05593],"type":"Point"}
}