{
  "type": "Feature",
  "properties": {
    "iso:country":"US",
    "sg:address":"50 Maxwell Ct",
    "sg:city":"Santa Rosa",
    "sg:classifiers":[
        {
            "category":"Retail",
            "subcategory":"Auto Repair",
            "type":"Services"
        }
    ],
    "sg:phone":"+1 707 546 6661",
    "sg:postcode":"95401",
    "sg:province":"CA",
    "sg:tags":[
        "spring"
    ],
    "wof:name":"Alignment Shop",
    "wof:placetype":"venue"
},
  "geometry": {"coordinates":[-122.72752699999999,38.443117],"type":"Point"}
}