{
  "type": "Feature",
  "properties": {
    "addr:full":"1487 Main St Watsonville CA 95076",
    "addr:housenumber":"1487",
    "addr:postcode":"95076",
    "addr:street":"Main St",
    "iso:country":"US",
    "sg:address":"1487 Main St",
    "sg:city":"Watsonville",
    "sg:classifiers":[
        {
            "category":"Ice Cream",
            "type":"Food & Drink"
        }
    ],
    "sg:menulink":"http://www.allmenus.com/ca/watsonville/184525-cold-stone-creamery/menu/",
    "sg:phone":"+1 831 722 4406",
    "sg:postcode":"95076",
    "sg:province":"CA",
    "sg:tags":[
        "smoothy",
        "juice",
        "american"
    ],
    "wof:name":"Cold Stone Creamery",
    "wof:placetype":"venue"
},
  "geometry": {"coordinates":[-121.77681699999999,36.91741],"type":"Point"}
}