{
  "type": "Feature",
  "properties": {
    "addr:full":"4891 Mascagni St Ventura CA 93003",
    "addr:postcode":"4891;93003",
    "addr:street":"Mascagni St",
    "iso:country":"US",
    "sg:address":"4891 Mascagni St",
    "sg:city":"Ventura",
    "sg:classifiers":[
        {
            "category":"Building & Trades",
            "subcategory":"Construction",
            "type":"Services"
        }
    ],
    "sg:phone":"+1 805 647 4721",
    "sg:postcode":"93003",
    "sg:province":"CA",
    "sg:tags":[
        "painter"
    ],
    "wof:name":"A Mc Kay's Painting",
    "wof:placetype":"venue"
},
  "geometry": {"coordinates":[-119.227479,34.267206],"type":"Point"}
}