{
  "type": "Feature",
  "properties": {
    "addr:full":"149 W Yokuts Ave Stockton CA 95207",
    "addr:housenumber":"149",
    "addr:postcode":"95207",
    "addr:street":"W Yokuts Ave",
    "iso:country":"US",
    "sg:address":"149 W Yokuts Ave",
    "sg:city":"Stockton",
    "sg:classifiers":[
        {
            "category":"Banks & Credit Unions",
            "subcategory":"Bank",
            "type":"Services"
        }
    ],
    "sg:phone":"+1 209 957 1934",
    "sg:postcode":"95207",
    "sg:province":"CA",
    "sg:tags":[
        "loan",
        "real estate"
    ],
    "sg:website":"www.calstatemortgage.com",
    "wof:name":"Cal State Mortgage Co Inc",
    "wof:placetype":"venue"
},
  "geometry": {"coordinates":[-121.308021,37.998404],"type":"Point"}
}