{
  "type": "Feature",
  "properties": {
    "addr:full":"1132 Sereno Dr Vallejo CA 94589",
    "addr:housenumber":"1132",
    "addr:postcode":"94589",
    "addr:street":"Sereno Dr",
    "iso:country":"US",
    "sg:address":"1132 Sereno Dr",
    "sg:city":"Vallejo",
    "sg:classifiers":[
        {
            "category":"Personal",
            "subcategory":"Beauty Salon",
            "type":"Services"
        }
    ],
    "sg:phone":"+1 707 648 1216",
    "sg:postcode":"94589",
    "sg:province":"CA",
    "sg:tags":[
        "nail",
        "manicuring"
    ],
    "wof:name":"Lacy's Nails",
    "wof:placetype":"venue"
},
  "geometry": {"coordinates":[-122.24292800000001,38.128761],"type":"Point"}
}