{
  "type": "Feature",
  "properties": {
    "addr:full":"1505 W Ave L Lancaster CA 93534",
    "addr:housenumber":"1505",
    "addr:postcode":"93534",
    "addr:street":"W Ave L",
    "iso:country":"US",
    "sg:address":"1505 W Ave L",
    "sg:city":"Lancaster",
    "sg:classifiers":[
        {
            "category":"Retail",
            "subcategory":"Laundry & Dry Cleaning",
            "type":"Services"
        }
    ],
    "sg:phone":"+1 661 533 0861",
    "sg:postcode":"93534",
    "sg:province":"CA",
    "sg:tags":[
        "cleaners",
        "rug",
        "carpet"
    ],
    "wof:name":"Elite Carpet Care",
    "wof:placetype":"venue"
},
  "geometry": {"coordinates":[-118.156701,34.660311],"type":"Point"}
}