{
  "type": "Feature",
  "properties": {
    "iso:country":"US",
    "sg:address":"369 Pso de Playa",
    "sg:city":"Ventura",
    "sg:classifiers":[
        {
            "category":"Real Estate",
            "subcategory":"Real Estate Operator",
            "type":"Services"
        }
    ],
    "sg:phone":"+1 805 643 8555",
    "sg:postcode":"93001",
    "sg:province":"CA",
    "sg:tags":[
        "apartment"
    ],
    "wof:name":"Beachfronter Apartments",
    "wof:placetype":"venue"
},
  "geometry": {"coordinates":[-119.295673,34.276453],"type":"Point"}
}