{
  "type": "Feature",
  "properties": {
    "iso:country":"US",
    "sg:address":"4375 Prado Rd",
    "sg:city":"Corona",
    "sg:classifiers":[
        {
            "category":"Personal",
            "type":"Services"
        },
        {
            "category":"Recreation",
            "subcategory":"Playground",
            "type":"Entertainment"
        }
    ],
    "sg:phone":"+1 951 739 9555",
    "sg:postcode":"92880",
    "sg:province":"CA",
    "sg:tags":[
        "party",
        "planning",
        "event"
    ],
    "wof:name":"Arctic Fun Zone",
    "wof:placetype":"venue"
},
  "geometry": {"coordinates":[-117.652613,33.879797],"type":"Point"}
}