{
  "type": "Feature",
  "properties": {
    "iso:country":"US",
    "sg:address":"6600 Schirra Ct",
    "sg:city":"Bakersfield",
    "sg:classifiers":[
        {
            "category":"Retail",
            "subcategory":"Auto Repair",
            "type":"Services"
        }
    ],
    "sg:phone":"+1 661 836 3080",
    "sg:postcode":"93313",
    "sg:province":"CA",
    "sg:tags":[
        "automobile",
        "smog"
    ],
    "wof:name":"Accurate Smog Test Only Ctr",
    "wof:placetype":"venue"
},
  "geometry": {"coordinates":[-119.081628,35.31661],"type":"Point"}
}