{
  "type": "Feature",
  "properties": {
    "iso:country":"US",
    "sg:address":"260 S Maple Ave",
    "sg:city":"South San Francisco",
    "sg:classifiers":[
        {
            "category":"Food & Beverages",
            "subcategory":"Specialty",
            "type":"Retail Goods"
        }
    ],
    "sg:phone":"+1 650 873 5400",
    "sg:postcode":"94080",
    "sg:province":"CA",
    "sg:website":"www.renaissancespecialtyfoods.com",
    "wof:name":"Renaissance Specialty Foods",
    "wof:placetype":"venue"
},
  "geometry": {"coordinates":[-122.416377,37.644489],"type":"Point"}
}