{
  "type": "Feature",
  "properties": {
    "addr:full":"2929 Hidden Valley Rd Templeton CA 93465",
    "addr:housenumber":"2929",
    "addr:postcode":"93465",
    "addr:street":"Hidden Valley Rd",
    "iso:country":"US",
    "sg:address":"2929 Hidden Valley Rd",
    "sg:city":"Templeton",
    "sg:classifiers":[
        {
            "category":"Farming",
            "subcategory":"Livestock Farm",
            "type":"Manufacturing & Wholesale Goods"
        }
    ],
    "sg:phone":"+1 805 434 5033",
    "sg:postcode":"93465",
    "sg:province":"CA",
    "sg:tags":[
        "equine"
    ],
    "wof:name":"Brenna Vito Performance Horses",
    "wof:placetype":"venue"
},
  "geometry": {"coordinates":[-120.76467700000001,35.54323],"type":"Point"}
}