{
  "type": "Feature",
  "properties": {
    "addr:full":"7847 Clairemont Mesa Blvd San Diego CA 92117",
    "addr:housenumber":"7847",
    "addr:postcode":"92117",
    "addr:street":"Clairemont Mesa Blvd",
    "iso:country":"US",
    "sg:address":"7847 Clairemont Mesa Blvd",
    "sg:city":"San Diego",
    "sg:classifiers":[
        {
            "category":"Building & Trades",
            "subcategory":"Construction",
            "type":"Services"
        }
    ],
    "sg:phone":"+1 858 751 0168",
    "sg:postcode":"92117",
    "sg:province":"CA",
    "sg:tags":[
        "resurfacing",
        "laying",
        "refinishing",
        "floor"
    ],
    "wof:name":"Mesa Flooring",
    "wof:placetype":"venue"
},
  "geometry": {"coordinates":[-117.149445,32.832685],"type":"Point"}
}