{
  "type": "Feature",
  "properties": {
    "addr:full":"39022 Presidio Way Fremont CA 94538",
    "addr:postcode":"39022;94538",
    "addr:street":"Presidio Way",
    "iso:country":"US",
    "sg:address":"39022 Presidio Way",
    "sg:city":"Fremont",
    "sg:classifiers":[
        {
            "category":"Health Services",
            "subcategory":"Nursing And Care Facility",
            "type":"Services"
        }
    ],
    "sg:phone":"+1 510 792 3743",
    "sg:postcode":"94538",
    "sg:province":"CA",
    "sg:tags":[
        "skilled"
    ],
    "wof:name":"Driftwood Convalescent Hosp",
    "wof:placetype":"venue"
},
  "geometry": {"coordinates":[-121.990994,37.544246],"type":"Point"}
}