{
  "type": "Feature",
  "properties": {
    "addr:full":"1280 Boulevard Way Walnut Creek CA 94595",
    "addr:housenumber":"1280",
    "addr:postcode":"94595",
    "addr:street":"Boulevard Way",
    "iso:country":"US",
    "sg:address":"1280 Boulevard Way",
    "sg:city":"Walnut Creek",
    "sg:classifiers":[
        {
            "category":"Building & Trades",
            "subcategory":"Cleaning & Sanitation",
            "type":"Services"
        }
    ],
    "sg:phone":"+1 925 937 0277",
    "sg:postcode":"94595",
    "sg:province":"CA",
    "sg:tags":[
        "house"
    ],
    "wof:name":"Green Clean",
    "wof:placetype":"venue"
},
  "geometry": {"coordinates":[-122.076454,37.893701],"type":"Point"}
}