{
  "type": "Feature",
  "properties": {
    "iso:country":"US",
    "sg:address":"640 Cam de la Reina",
    "sg:city":"San Diego",
    "sg:classifiers":[
        {
            "category":"Health Services",
            "subcategory":"Health Practitioner",
            "type":"Services"
        }
    ],
    "sg:phone":"+1 619 297 6830",
    "sg:postcode":"92108",
    "sg:province":"CA",
    "sg:tags":[
        "therapist",
        "physical"
    ],
    "wof:name":"Visiting Therapist Assn",
    "wof:placetype":"venue"
},
  "geometry": {"coordinates":[-117.159616,32.76659],"type":"Point"}
}