{
  "type": "Feature",
  "properties": {
    "addr:full":"1958 Vallejo St San Francisco CA 94123",
    "addr:housenumber":"1958",
    "addr:postcode":"94123",
    "addr:street":"Vallejo St",
    "iso:country":"US",
    "sg:address":"1958 Vallejo St",
    "sg:city":"San Francisco",
    "sg:classifiers":[
        {
            "category":"Personal",
            "type":"Services"
        }
    ],
    "sg:phone":"+1 415 563 6387",
    "sg:postcode":"94123",
    "sg:province":"CA",
    "sg:tags":[
        "consultant",
        "image"
    ],
    "wof:name":"Strategic Imaging",
    "wof:placetype":"venue"
},
  "geometry": {"coordinates":[-122.42942600000001,37.796052],"type":"Point"}
}