{
  "type": "Feature",
  "properties": {
    "addr:full":"3901 Las Posas Rd Camarillo CA 93010",
    "addr:housenumber":"3901",
    "addr:postcode":"93010",
    "addr:street":"Las Posas Rd",
    "iso:country":"US",
    "sg:address":"3901 Las Posas Rd",
    "sg:city":"Camarillo",
    "sg:classifiers":[
        {
            "category":"Social Services",
            "type":"Services"
        }
    ],
    "sg:phone":"+1 805 384 9399",
    "sg:postcode":"93010",
    "sg:province":"CA",
    "sg:tags":[
        "counselor",
        "marriage",
        "family"
    ],
    "wof:name":"Bonnie Quinton",
    "wof:placetype":"venue"
},
  "geometry": {"coordinates":[-119.01513300000001,34.242305],"type":"Point"}
}