{
  "type": "Feature",
  "properties": {
    "addr:full":"2121 Rosecrans Ave. Suite 4310 El Segundo CA 90245",
    "addr:housenumber":"2121",
    "addr:postcode":"90245",
    "addr:street":"Rosecrans Ave. Suite 4310",
    "iso:country":"US",
    "sg:address":"2121 Rosecrans Ave. Suite 4310",
    "sg:city":"El Segundo",
    "sg:classifiers":[
        {
            "category":"Professional",
            "subcategory":"Computer Services",
            "type":"Services"
        }
    ],
    "sg:phone":"+1 866 424 8864",
    "sg:postcode":"90245",
    "sg:province":"CA",
    "sg:tags":[
        "video",
        "media-platform"
    ],
    "sg:website":"http://www.mydamnchannel.com",
    "wof:name":"My Damn Channel",
    "wof:placetype":"venue"
},
  "geometry": {"coordinates":[-118.387151,33.90195],"type":"Point"}
}