{
  "type": "Feature",
  "properties": {
    "addr:full":"18148 Sherman Way Reseda CA 91335",
    "addr:housenumber":"18148",
    "addr:postcode":"91335",
    "addr:street":"Sherman Way",
    "iso:country":"US",
    "sg:address":"18148 Sherman Way",
    "sg:city":"Reseda",
    "sg:classifiers":[
        {
            "category":"Manufacturing",
            "subcategory":"Printing",
            "type":"Manufacturing & Wholesale Goods"
        }
    ],
    "sg:phone":"+1 818 881 4600",
    "sg:postcode":"91335",
    "sg:province":"CA",
    "sg:tags":[
        "lithographic",
        "commercial"
    ],
    "wof:name":"Printing Man Inst Prntng Ctr I",
    "wof:placetype":"venue"
},
  "geometry": {"coordinates":[-118.53080799999999,34.200932],"type":"Point"}
}