{
  "type": "Feature",
  "properties": {
    "iso:country":"US",
    "sg:address":"25021 Express Dr",
    "sg:city":"Laguna Hills",
    "sg:classifiers":[
        {
            "category":"Building & Trades",
            "subcategory":"Construction",
            "type":"Services"
        }
    ],
    "sg:phone":"+1 949 933 0178",
    "sg:postcode":"92653",
    "sg:province":"CA",
    "sg:tags":[
        "home",
        "improvement"
    ],
    "wof:name":"Williams Co",
    "wof:placetype":"venue"
},
  "geometry": {"coordinates":[-117.683891,33.599992],"type":"Point"}
}