{
  "type": "Feature",
  "properties": {
    "addr:full":"10717 Sherman Pl Sun Valley CA 91352",
    "addr:housenumber":"10717",
    "addr:postcode":"91352",
    "addr:street":"Sherman Pl",
    "iso:country":"US",
    "sg:address":"10717 Sherman Pl",
    "sg:city":"Sun Valley",
    "sg:classifiers":[
        {
            "category":"Professional",
            "type":"Services"
        }
    ],
    "sg:phone":"+1 818 765 6824",
    "sg:postcode":"91352",
    "sg:province":"CA",
    "wof:name":"Pokerhantas",
    "wof:placetype":"venue"
},
  "geometry": {"coordinates":[-118.36418,34.202119],"type":"Point"}
}