{
  "type": "Feature",
  "properties": {
    "addr:full":"1305 Mckenzie Avenue Los Altos CA 94024",
    "addr:housenumber":"1305",
    "addr:postcode":"94024",
    "addr:street":"Mckenzie Avenue",
    "iso:country":"US",
    "sg:address":"1305 Mckenzie Avenue",
    "sg:city":"Los Altos",
    "sg:classifiers":[
        {
            "category":"Park",
            "type":"Public Place"
        }
    ],
    "sg:postcode":"94024",
    "sg:province":"CA",
    "wof:name":"Heritage Oaks Park",
    "wof:placetype":"venue"
},
  "geometry": {"coordinates":[-122.085999,37.359501],"type":"Point"}
}