{
  "type": "Feature",
  "properties": {
    "iso:country":"US",
    "sg:address":"3041 Michelson Dr",
    "sg:city":"Irvine",
    "sg:classifiers":[
        {
            "category":"Restaurant",
            "type":"Food & Drink"
        }
    ],
    "sg:phone":"+1 949 752 0288",
    "sg:postcode":"92612",
    "sg:province":"CA",
    "wof:name":"Aji Grill",
    "wof:placetype":"venue"
},
  "geometry": {"coordinates":[-117.844239,33.670875],"type":"Point"}
}