{
  "type": "Feature",
  "properties": {
    "iso:country":"US",
    "sg:address":"4242 Francis Ave",
    "sg:city":"Chino",
    "sg:classifiers":[
        {
            "category":"Autos & Motor Vehicles",
            "subcategory":"Automobile Sales",
            "type":"Retail Goods"
        }
    ],
    "sg:phone":"+1 909 548 4595",
    "sg:postcode":"91710",
    "sg:province":"CA",
    "sg:tags":[
        "car",
        "dealer"
    ],
    "wof:name":"Julio Villacis",
    "wof:placetype":"venue"
},
  "geometry": {"coordinates":[-117.714052,34.040766],"type":"Point"}
}