{
  "type": "Feature",
  "properties": {
    "iso:country":"US",
    "sg:address":"220 Newport Center Drive #11",
    "sg:city":"Newport Beach",
    "sg:classifiers":[
        {
            "category":"Health Services",
            "subcategory":"Clinic",
            "type":"Services"
        }
    ],
    "sg:phone":"+1 949 222 4200",
    "sg:postcode":"92660",
    "sg:province":"CA",
    "sg:tags":[
        "counseling",
        "mental"
    ],
    "sg:website":"www.lisaquinncounseling.com/#cid...",
    "wof:name":"Lisa M. Quinn, Newport Beach Therapist",
    "wof:placetype":"venue"
},
  "geometry": {"coordinates":[-117.873919,33.61174],"type":"Point"}
}