{
  "type": "Feature",
  "properties": {
    "addr:full":"151 W Base Line Rd Rialto CA 92376",
    "addr:housenumber":"151",
    "addr:postcode":"92376",
    "addr:street":"W Base Line Rd",
    "iso:country":"US",
    "sg:address":"151 W Base Line Rd",
    "sg:city":"Rialto",
    "sg:classifiers":[
        {
            "category":"Utilities",
            "subcategory":"Mobile Phone",
            "type":"Services"
        }
    ],
    "sg:phone":"+1 909 875 2610",
    "sg:postcode":"92376",
    "sg:province":"CA",
    "sg:tags":[
        "communication",
        "radiotelephone"
    ],
    "wof:name":"AT&T Wireless",
    "wof:placetype":"venue"
},
  "geometry": {"coordinates":[-117.373735,34.121445],"type":"Point"}
}