{
  "type": "Feature",
  "properties": {
    "addr:full":"3428 W Pico Boulevard Los Angeles CA 90019",
    "addr:housenumber":"3428",
    "addr:postcode":"90019",
    "addr:street":"W Pico Boulevard",
    "iso:country":"US",
    "sg:address":"3428 W Pico Boulevard",
    "sg:city":"Los Angeles",
    "sg:classifiers":[
        {
            "category":"Food & Beverages",
            "subcategory":"Liquor & Beverages",
            "type":"Retail Goods"
        }
    ],
    "sg:phone":"+1 323 734 3080",
    "sg:postcode":"90019",
    "sg:province":"CA",
    "sg:tags":[
        "beer",
        "spirit",
        "wine"
    ],
    "wof:name":"E-Dong USA",
    "wof:placetype":"venue"
},
  "geometry": {"coordinates":[-118.31838500000001,34.047279],"type":"Point"}
}