{
  "type": "Feature",
  "properties": {
    "iso:country":"US",
    "sg:address":"1510 Linda Sue Ln",
    "sg:city":"Encinitas",
    "sg:classifiers":[
        {
            "category":"Professional",
            "type":"Services"
        }
    ],
    "sg:phone":"+1 760 634 8166",
    "sg:postcode":"92024",
    "sg:province":"CA",
    "wof:name":"Xpand Inc",
    "wof:placetype":"venue"
},
  "geometry": {"coordinates":[-117.25680699999999,33.052459],"type":"Point"}
}