{
  "type": "Feature",
  "properties": {
    "addr:full":"376 Race St San Jose CA 95126",
    "addr:housenumber":"376",
    "addr:postcode":"95126",
    "addr:street":"Race St",
    "iso:country":"US",
    "sg:address":"376 Race St",
    "sg:city":"San Jose",
    "sg:classifiers":[
        {
            "category":"Manufacturing",
            "subcategory":"Tools & Machinery",
            "type":"Manufacturing & Wholesale Goods"
        }
    ],
    "sg:phone":"+1 408 271 2450",
    "sg:postcode":"95126",
    "sg:province":"CA",
    "sg:tags":[
        "equipment",
        "lighting"
    ],
    "wof:name":"Lumatronix Co",
    "wof:placetype":"venue"
},
  "geometry": {"coordinates":[-121.911267,37.322914],"type":"Point"}
}