{
  "type": "Feature",
  "properties": {
    "addr:full":"1316 Lyndon St South Pasadena CA 91030",
    "addr:housenumber":"1316",
    "addr:postcode":"91030",
    "addr:street":"Lyndon St",
    "iso:country":"US",
    "sg:address":"1316 Lyndon St",
    "sg:city":"South Pasadena",
    "sg:classifiers":[
        {
            "category":"Organizations",
            "subcategory":"Religious Organization",
            "type":"Services"
        }
    ],
    "sg:phone":"+1 626 403 2820",
    "sg:postcode":"91030",
    "sg:province":"CA",
    "sg:tags":[
        "church"
    ],
    "wof:name":"Iglesia Restauracion",
    "wof:placetype":"venue"
},
  "geometry": {"coordinates":[-118.155047,34.111006],"type":"Point"}
}