{
  "type": "Feature",
  "properties": {
    "addr:full":"201 California Street Lbby San Francisco CA 94111",
    "addr:housenumber":"201",
    "addr:postcode":"94111",
    "addr:street":"California Street",
    "iso:country":"US",
    "sg:address":"201 California Street Lbby",
    "sg:city":"San Francisco",
    "sg:classifiers":[
        {
            "category":"Professional",
            "subcategory":"Lawyer & Legal Services",
            "type":"Services"
        }
    ],
    "sg:phone":"+1 415 433 1900",
    "sg:postcode":"94111",
    "sg:province":"CA",
    "wof:name":"Simon Beau C",
    "wof:placetype":"venue"
},
  "geometry": {"coordinates":[-122.399002,37.7934],"type":"Point"}
}