{
  "type": "Feature",
  "properties": {
    "iso:country":"US",
    "sg:address":"12340 South St",
    "sg:city":"Cerritos",
    "sg:classifiers":[
        {
            "category":"Landmark",
            "subcategory":"Historic",
            "type":"Public Place"
        },
        {
            "category":"Park",
            "type":"Public Place"
        },
        {
            "category":"Recreation",
            "subcategory":"Playground",
            "type":"Entertainment"
        }
    ],
    "sg:phone":"+1 562 916 8550",
    "sg:postcode":"90703",
    "sg:province":"CA",
    "sg:tags":[
        "building",
        "historical"
    ],
    "sg:website":"www.ci.cerritos.ca.us/cityserv/s...",
    "wof:name":"Cerritos Senior Center at Pat Nixon Park",
    "wof:placetype":"venue"
},
  "geometry": {"coordinates":[-118.068348,33.857712],"type":"Point"}
}