{
  "type": "Feature",
  "properties": {
    "iso:country":"US",
    "sg:address":"3710 Flight Ave",
    "sg:city":"Redding",
    "sg:classifiers":[
        {
            "category":"Professional",
            "type":"Services"
        }
    ],
    "sg:phone":"+1 530 722 9045",
    "sg:postcode":"96002",
    "sg:province":"CA",
    "wof:name":"Meonis",
    "wof:placetype":"venue"
},
  "geometry": {"coordinates":[-122.300885,40.509482],"type":"Point"}
}