{
  "type": "Feature",
  "properties": {
    "iso:country":"US",
    "sg:address":"26311 Las Alturas Ave",
    "sg:city":"Laguna Hills",
    "sg:classifiers":[
        {
            "category":"Banks & Credit Unions",
            "subcategory":"Investment Brokerage",
            "type":"Services"
        }
    ],
    "sg:phone":"+1 949 360 8600",
    "sg:postcode":"92653",
    "sg:province":"CA",
    "sg:tags":[
        "advisory",
        "financial"
    ],
    "wof:name":"World Wide Financial",
    "wof:placetype":"venue"
},
  "geometry": {"coordinates":[-117.69926,33.580699],"type":"Point"}
}