{
  "type": "Feature",
  "properties": {
    "iso:country":"US",
    "sg:address":"16014 Main St",
    "sg:city":"La Puente",
    "sg:classifiers":[
        {
            "category":"Personal",
            "subcategory":"Barber",
            "type":"Services"
        }
    ],
    "sg:phone":"+1 626 968 4478",
    "sg:postcode":"91744",
    "sg:province":"CA",
    "wof:name":"Candy Barber Shop",
    "wof:placetype":"venue"
},
  "geometry": {"coordinates":[-117.94817,34.02003],"type":"Point"}
}