{
  "type": "Feature",
  "properties": {
    "addr:full":"665 N Tustin St Orange CA 92867",
    "addr:housenumber":"665",
    "addr:postcode":"92867",
    "addr:street":"N Tustin St",
    "iso:country":"US",
    "sg:address":"665 N Tustin St",
    "sg:city":"Orange",
    "sg:classifiers":[
        {
            "category":"Home & Garden",
            "subcategory":"Furniture",
            "type":"Retail Goods"
        }
    ],
    "sg:phone":"+1 714 997 7684",
    "sg:postcode":"92867",
    "sg:province":"CA",
    "wof:name":"Home By Design",
    "wof:placetype":"venue"
},
  "geometry": {"coordinates":[-117.83557399999999,33.797893],"type":"Point"}
}