{
  "type": "Feature",
  "properties": {
    "iso:country":"US",
    "sg:address":"1830 Riverside Dr",
    "sg:city":"Glendale",
    "sg:classifiers":[
        {
            "category":"Professional",
            "subcategory":"Business Services",
            "type":"Services"
        }
    ],
    "sg:phone":"+1 818 953 8528",
    "sg:postcode":"91201",
    "sg:province":"CA",
    "wof:name":"Equine Ramey Group",
    "wof:placetype":"venue"
},
  "geometry": {"coordinates":[-118.305887,34.161202],"type":"Point"}
}