{
  "type": "Feature",
  "properties": {
    "iso:country":"US",
    "sg:address":"4709 Patricia Dr",
    "sg:city":"Eureka",
    "sg:classifiers":[
        {
            "category":"Real Estate",
            "subcategory":"Real Estate Agent",
            "type":"Services"
        }
    ],
    "sg:phone":"+1 707 445 3811",
    "sg:postcode":"95503",
    "sg:province":"CA",
    "sg:tags":[
        "appraiser"
    ],
    "wof:name":"Mike Retzloff Appraisal Svc",
    "wof:placetype":"venue"
},
  "geometry": {"coordinates":[-124.165418,40.757916],"type":"Point"}
}