{
  "type": "Feature",
  "properties": {
    "iso:country":"US",
    "sg:address":"2020 Hillhurst Ave",
    "sg:city":"Los Angeles",
    "sg:classifiers":[
        {
            "category":"Real Estate",
            "subcategory":"Real Estate Agent",
            "type":"Services"
        }
    ],
    "sg:phone":"+1 323 662 3144",
    "sg:postcode":"90027",
    "sg:province":"CA",
    "sg:tags":[
        "manager",
        "property",
        "investor",
        "broker"
    ],
    "wof:name":"Southwest Appraisal Services",
    "wof:placetype":"venue"
},
  "geometry": {"coordinates":[-118.287347,34.10799],"type":"Point"}
}