{
  "type": "Feature",
  "properties": {
    "addr:full":"20911 Earl St Torrance CA 90503",
    "addr:housenumber":"20911",
    "addr:postcode":"90503",
    "addr:street":"Earl St",
    "iso:country":"US",
    "sg:address":"20911 Earl St",
    "sg:city":"Torrance",
    "sg:classifiers":[
        {
            "category":"Health Services",
            "subcategory":"Doctor",
            "type":"Services"
        }
    ],
    "sg:phone":"+1 310 542 6333",
    "sg:postcode":"90503",
    "sg:province":"CA",
    "sg:tags":[
        "physician",
        "surgeon"
    ],
    "wof:name":"South Bay Endocrine Assoc",
    "wof:placetype":"venue"
},
  "geometry": {"coordinates":[-118.358092,33.84053],"type":"Point"}
}