{
  "type": "Feature",
  "properties": {
    "iso:country":"US",
    "sg:address":"16922 Main St",
    "sg:city":"Hesperia",
    "sg:classifiers":[
        {
            "category":"Restaurant",
            "type":"Food & Drink"
        }
    ],
    "sg:menulink":"http://www.allmenus.com/ca/barstow-victorville/150530-subway/menu/",
    "sg:phone":"+1 760 949 5545",
    "sg:postcode":"92345",
    "sg:province":"CA",
    "sg:tags":[
        "american",
        "sandwich"
    ],
    "wof:name":"Subway",
    "wof:placetype":"venue"
},
  "geometry": {"coordinates":[-117.294139,34.420593],"type":"Point"}
}