{
  "type": "Feature",
  "properties": {
    "addr:full":"826 N Winchester Blvd Santa Clara CA 95050",
    "addr:housenumber":"826",
    "addr:postcode":"95050",
    "addr:street":"N Winchester Blvd",
    "iso:country":"US",
    "sg:address":"826 N Winchester Blvd",
    "sg:city":"Santa Clara",
    "sg:classifiers":[
        {
            "category":"Health Services",
            "subcategory":"Chiropractor",
            "type":"Services"
        }
    ],
    "sg:phone":"+1 408 615 0222",
    "sg:postcode":"95050",
    "sg:province":"CA",
    "wof:name":"Chiropractic Edge",
    "wof:placetype":"venue"
},
  "geometry": {"coordinates":[-121.95134,37.345965],"type":"Point"}
}