{
  "type": "Feature",
  "properties": {
    "iso:country":"US",
    "sg:address":"7500 W Sunset Blvd",
    "sg:city":"Los Angeles",
    "sg:classifiers":[
        {
            "category":"Personal",
            "subcategory":"Beauty Salon",
            "type":"Services"
        }
    ],
    "sg:phone":"+1 323 851 2164",
    "sg:postcode":"90046",
    "sg:province":"CA",
    "sg:tags":[
        "nail",
        "manicuring"
    ],
    "wof:name":"Annie's Nails",
    "wof:placetype":"venue"
},
  "geometry": {"coordinates":[-118.35356,34.097674],"type":"Point"}
}