{
  "type": "Feature",
  "properties": {
    "iso:country":"US",
    "sg:address":"41236 Torrey Pine Ct",
    "sg:city":"Hemet",
    "sg:classifiers":[
        {
            "category":"Building & Trades",
            "subcategory":"Electrical",
            "type":"Services"
        }
    ],
    "sg:phone":"+1 951 929 7688",
    "sg:postcode":"92544",
    "sg:province":"CA",
    "sg:tags":[
        "electrical",
        "electric",
        "contractor"
    ],
    "wof:name":"G & R Electric Company",
    "wof:placetype":"venue"
},
  "geometry": {"coordinates":[-116.941761,33.741241],"type":"Point"}
}