{
  "type": "Feature",
  "properties": {
    "iso:country":"US",
    "sg:address":"8885 Balboa Ave",
    "sg:city":"San Diego",
    "sg:classifiers":[
        {
            "category":"Restaurant",
            "type":"Food & Drink"
        }
    ],
    "sg:phone":"+1 858 560 6771",
    "sg:postcode":"92123",
    "sg:province":"CA",
    "sg:tags":[
        "traditional",
        "american",
        "brunch",
        "breakfast"
    ],
    "sg:website":"www.94thaerosquadron.signonsandi...",
    "wof:name":"94th Aero Squadron",
    "wof:placetype":"venue"
},
  "geometry": {"coordinates":[-117.13696,32.82008],"type":"Point"}
}