{
  "type": "Feature",
  "properties": {
    "addr:full":"2200 W 3rd Street Suite 300 Los Angeles CA 90057",
    "addr:housenumber":"2200",
    "addr:postcode":"90057",
    "addr:street":"W 3Rd Street Suite 300",
    "iso:country":"US",
    "sg:address":"2200 W 3rd Street Suite 300",
    "sg:city":"Los Angeles",
    "sg:classifiers":[
        {
            "category":"Health Services",
            "subcategory":"Doctor",
            "type":"Services"
        }
    ],
    "sg:phone":"+1 213 639 2200",
    "sg:postcode":"90057",
    "sg:province":"CA",
    "sg:tags":[
        "cardiologist"
    ],
    "wof:name":"Yokoyama Taro MD",
    "wof:placetype":"venue"
},
  "geometry": {"coordinates":[-118.27384600000001,34.063234],"type":"Point"}
}