{
  "type": "Feature",
  "properties": {
    "addr:full":"4820 Spencer St Torrance CA 90503",
    "addr:housenumber":"4820",
    "addr:postcode":"90503",
    "addr:street":"Spencer St",
    "iso:country":"US",
    "sg:address":"4820 Spencer St",
    "sg:city":"Torrance",
    "sg:classifiers":[
        {
            "category":"Education",
            "subcategory":"School",
            "type":"Public Place"
        }
    ],
    "sg:phone":"+1 310 533 4542",
    "sg:postcode":"90503",
    "sg:province":"CA",
    "sg:tags":[
        "high",
        "middle",
        "elementary"
    ],
    "wof:name":"Torrance Unified School District",
    "wof:placetype":"venue"
},
  "geometry": {"coordinates":[-118.36499499999999,33.844832],"type":"Point"}
}