{
  "type": "Feature",
  "properties": {
    "iso:country":"US",
    "sg:address":"3661 N Parkway Dr",
    "sg:city":"Fresno",
    "sg:classifiers":[
        {
            "category":"Retail",
            "subcategory":"Auto Rental",
            "type":"Services"
        }
    ],
    "sg:phone":"+1 559 276 0176",
    "sg:postcode":"93722",
    "sg:province":"CA",
    "sg:tags":[
        "renting",
        "truck",
        "leasing"
    ],
    "wof:name":"U-Haul Co",
    "wof:placetype":"venue"
},
  "geometry": {"coordinates":[-119.866975,36.793603],"type":"Point"}
}