{
  "type": "Feature",
  "properties": {
    "addr:full":"1178 San Carlos Ave San Carlos CA 94070",
    "addr:housenumber":"1178",
    "addr:postcode":"94070",
    "addr:street":"San Carlos Ave",
    "iso:country":"US",
    "sg:address":"1178 San Carlos Ave",
    "sg:city":"San Carlos",
    "sg:classifiers":[
        {
            "category":"Personal",
            "subcategory":"Beauty Salon",
            "type":"Services"
        }
    ],
    "sg:phone":"+1 650 593 4088",
    "sg:postcode":"94070",
    "sg:province":"CA",
    "wof:name":"Robyn Hekking",
    "wof:placetype":"venue"
},
  "geometry": {"coordinates":[-122.260631,37.507159],"type":"Point"}
}