{
  "type": "Feature",
  "properties": {
    "addr:full":"24301 Southland Dr Ste 613 Hayward CA 94545",
    "addr:housenumber":"24301",
    "addr:postcode":"94545",
    "addr:street":"Southland Dr Ste 613",
    "iso:country":"US",
    "sg:address":"24301 Southland Dr Ste 613",
    "sg:city":"Hayward",
    "sg:classifiers":[
        {
            "category":"Professional",
            "subcategory":"Lawyer & Legal Services",
            "type":"Services"
        }
    ],
    "sg:phone":"+1 510 784 1200",
    "sg:postcode":"94545",
    "sg:province":"CA",
    "sg:tags":[
        "personal",
        "injury"
    ],
    "wof:name":"Law Offices of Ross M Meltzer",
    "wof:placetype":"venue"
},
  "geometry": {"coordinates":[-122.10558899999999,37.652975],"type":"Point"}
}