{
  "type": "Feature",
  "properties": {
    "addr:full":"10733 Breezy Meadow Dr Moreno Valley CA 92557",
    "addr:housenumber":"10733",
    "addr:postcode":"92557",
    "addr:street":"Breezy Meadow Dr",
    "iso:country":"US",
    "sg:address":"10733 Breezy Meadow Dr",
    "sg:city":"Moreno Valley",
    "sg:classifiers":[
        {
            "category":"Building & Trades",
            "subcategory":"Construction",
            "type":"Services"
        }
    ],
    "sg:phone":"+1 951 247 5955",
    "sg:postcode":"92557",
    "sg:province":"CA",
    "sg:tags":[
        "hanging",
        "contractor"
    ],
    "wof:name":"CAM Painting",
    "wof:placetype":"venue"
},
  "geometry": {"coordinates":[-117.25696499999999,33.966445],"type":"Point"}
}