{
  "type": "Feature",
  "properties": {
    "addr:full":"14837 Pomerado Rd Poway CA 92064",
    "addr:housenumber":"14837",
    "addr:postcode":"ca 92064",
    "addr:street":"Pomerado Rd",
    "iso:country":"US",
    "sg:address":"14837 Pomerado Rd",
    "sg:city":"Poway",
    "sg:classifiers":[
        {
            "category":"Banks & Credit Unions",
            "subcategory":"Bank",
            "type":"Services"
        }
    ],
    "sg:phone":"+1 858 748 7070",
    "sg:postcode":"92064",
    "sg:province":"CA",
    "wof:name":"Bank Of America",
    "wof:placetype":"venue"
},
  "geometry": {"coordinates":[-117.062029,32.98292],"type":"Point"}
}