{
  "type": "Feature",
  "properties": {
    "addr:full":"802 E Cll Laureles Santa Barbara CA 93105",
    "addr:housenumber":"802",
    "addr:postcode":"93105",
    "addr:street":"E Cll Laureles",
    "iso:country":"US",
    "sg:address":"802 E Cll Laureles",
    "sg:city":"Santa Barbara",
    "sg:classifiers":[
        {
            "category":"Professional",
            "subcategory":"Computer Services",
            "type":"Services"
        }
    ],
    "sg:phone":"+1 805 682 1830",
    "sg:postcode":"93105",
    "sg:province":"CA",
    "sg:tags":[
        "internet"
    ],
    "wof:name":"Arachnifile Web Svc",
    "wof:placetype":"venue"
},
  "geometry": {"coordinates":[-119.72438200000001,34.450747],"type":"Point"}
}