{
  "type": "Feature",
  "properties": {
    "iso:country":"US",
    "sg:address":"74924 Country Club Dr",
    "sg:city":"Palm Desert",
    "sg:classifiers":[
        {
            "category":"Professional",
            "subcategory":"Business Services",
            "type":"Services"
        }
    ],
    "sg:phone":"+1 760 776 1922",
    "sg:postcode":"92260",
    "sg:province":"CA",
    "sg:tags":[
        "packaging"
    ],
    "sg:website":"www.postnetpd.com",
    "wof:name":"Postnet",
    "wof:placetype":"venue"
},
  "geometry": {"coordinates":[-116.378472,33.758042],"type":"Point"}
}