{
  "type": "Feature",
  "properties": {
    "addr:full":"909 S Santa Anita Ave Arcadia CA 91006",
    "addr:housenumber":"909",
    "addr:postcode":"91006",
    "addr:street":"S Santa Anita Ave",
    "iso:country":"US",
    "sg:address":"909 S Santa Anita Ave",
    "sg:city":"Arcadia",
    "sg:classifiers":[
        {
            "category":"Professional",
            "subcategory":"Management & Consulting",
            "type":"Services"
        }
    ],
    "sg:phone":"+1 626 447 5411",
    "sg:postcode":"91006",
    "sg:province":"CA",
    "sg:tags":[
        "report",
        "construction"
    ],
    "wof:name":"Golden Sierra",
    "wof:placetype":"venue"
},
  "geometry": {"coordinates":[-118.031261,34.130834],"type":"Point"}
}