{
  "type": "Feature",
  "properties": {
    "iso:country":"US",
    "sg:address":"7624 Jemez Trl",
    "sg:city":"Yucca Valley",
    "sg:classifiers":[
        {
            "category":"Building & Trades",
            "subcategory":"Plumbing",
            "type":"Services"
        }
    ],
    "sg:phone":"+1 760 365 6241",
    "sg:postcode":"92284",
    "sg:province":"CA",
    "sg:tags":[
        "plumbing",
        "contractor"
    ],
    "wof:name":"Flash Plumbing",
    "wof:placetype":"venue"
},
  "geometry": {"coordinates":[-116.455698,34.114014],"type":"Point"}
}