{
  "type": "Feature",
  "properties": {
    "addr:full":"3011 Teagarden St San Leandro CA 94577",
    "addr:postcode":"3011;94577",
    "addr:street":"Teagarden St",
    "iso:country":"US",
    "sg:address":"3011 Teagarden St",
    "sg:city":"San Leandro",
    "sg:classifiers":[
        {
            "category":"Wholesale",
            "subcategory":"Hardware",
            "type":"Manufacturing & Wholesale Goods"
        }
    ],
    "sg:phone":"+1 510 352 1514",
    "sg:postcode":"94577",
    "sg:province":"CA",
    "sg:tags":[
        "distributor",
        "connector",
        "fluid"
    ],
    "wof:name":"Hose & Fittings Etc",
    "wof:placetype":"venue"
},
  "geometry": {"coordinates":[-122.15780700000001,37.705827],"type":"Point"}
}