{
  "type": "Feature",
  "properties": {
    "addr:full":"458 San Marin Dr Novato CA 94945",
    "addr:housenumber":"458",
    "addr:postcode":"94945",
    "addr:street":"San Marin Dr",
    "iso:country":"US",
    "sg:address":"458 San Marin Dr",
    "sg:city":"Novato",
    "sg:classifiers":[
        {
            "category":"Professional",
            "subcategory":"Management & Consulting",
            "type":"Services"
        },
        {
            "category":"Professional",
            "subcategory":"Employment Agencies",
            "type":"Services"
        }
    ],
    "sg:phone":"+1 415 892 1497",
    "sg:postcode":"94945",
    "sg:province":"CA",
    "sg:tags":[
        "consultant",
        "resource",
        "human"
    ],
    "sg:website":"http://www.employeerelationsmanagement.net",
    "wof:name":"Levy, Lawrence C Employee Relations Management Consultant",
    "wof:placetype":"venue"
},
  "geometry": {"coordinates":[-122.58717300000001,38.124008],"type":"Point"}
}