{
  "type": "Feature",
  "properties": {
    "addr:full":"1400 Fairlane Rd Ste C Yreka CA 96097",
    "addr:housenumber":"1400",
    "addr:postcode":"96097",
    "addr:street":"Fairlane Rd Ste C",
    "iso:country":"US",
    "sg:address":"1400 Fairlane Rd Ste C",
    "sg:city":"Yreka",
    "sg:classifiers":[
        {
            "category":"Building & Trades",
            "subcategory":"Construction",
            "type":"Services"
        },
        {
            "category":"Military Area",
            "subcategory":"Armory",
            "type":"Public Place"
        }
    ],
    "sg:phone":"+1 530 842 6979",
    "sg:postcode":"96097",
    "sg:province":"CA",
    "sg:tags":[
        "repair",
        "fence-sales",
        "fence",
        "contractor"
    ],
    "wof:name":"Dancer Fencing, Inc.",
    "wof:placetype":"venue"
},
  "geometry": {"coordinates":[-122.640083,41.713692],"type":"Point"}
}