{
  "type": "Feature",
  "properties": {
    "addr:full":"2025 Lincoln St Berkeley CA 94709",
    "addr:housenumber":"2025",
    "addr:postcode":"94709",
    "addr:street":"Lincoln St",
    "iso:country":"US",
    "sg:address":"2025 Lincoln St",
    "sg:city":"Berkeley",
    "sg:classifiers":[
        {
            "category":"Health Services",
            "subcategory":"Clinic",
            "type":"Services"
        }
    ],
    "sg:phone":"+1 510 594 4300",
    "sg:postcode":"94709",
    "sg:province":"CA",
    "sg:tags":[
        "counseling",
        "mental"
    ],
    "sg:website":"www.holisticgardner.com",
    "wof:name":"Laura Gardner, MFTi",
    "wof:placetype":"venue"
},
  "geometry": {"coordinates":[-122.270179,37.877599],"type":"Point"}
}