{
  "type": "Feature",
  "properties": {
    "addr:full":"11134 Rancho Carmel Dr San Diego CA 92128",
    "addr:housenumber":"11134",
    "addr:postcode":"92128",
    "addr:street":"Rancho Carmel Dr",
    "iso:country":"US",
    "sg:address":"11134 Rancho Carmel Dr",
    "sg:city":"San Diego",
    "sg:classifiers":[
        {
            "category":"Coffee & Tea",
            "type":"Food & Drink"
        },
        {
            "category":"Bagels",
            "type":"Food & Drink"
        }
    ],
    "sg:menulink":"http://www.allmenus.com/ca/san-diego/37764-brueggers/menu/",
    "sg:phone":"+1 858 618 1177",
    "sg:postcode":"92128",
    "sg:province":"CA",
    "sg:tags":[
        "wrap",
        "soup",
        "american",
        "sandwich",
        "salad"
    ],
    "wof:name":"Bruegger's",
    "wof:placetype":"venue"
},
  "geometry": {"coordinates":[-117.08227100000001,32.979787],"type":"Point"}
}