{
  "type": "Feature",
  "properties": {
    "iso:country":"US",
    "sg:address":"24921 Whitman St Apt 103",
    "sg:city":"Hayward",
    "sg:classifiers":[
        {
            "category":"Health Services",
            "subcategory":"Doctor",
            "type":"Services"
        }
    ],
    "sg:phone":"+1 510 962 3306",
    "sg:postcode":"94544",
    "sg:province":"CA",
    "sg:tags":[
        "physician",
        "surgeon"
    ],
    "wof:name":"Alta Bates",
    "wof:placetype":"venue"
},
  "geometry": {"coordinates":[-122.076983,37.658936],"type":"Point"}
}