{
  "type": "Feature",
  "properties": {
    "iso:country":"US",
    "sg:address":"400 Main St",
    "sg:city":"Fortuna",
    "sg:classifiers":[
        {
            "category":"Manufacturing",
            "subcategory":"Lumber",
            "type":"Manufacturing & Wholesale Goods"
        }
    ],
    "sg:phone":"+1 707 725 6507",
    "sg:postcode":"95540",
    "sg:province":"CA",
    "sg:tags":[
        "logging"
    ],
    "wof:name":"Scott Dunn Logging",
    "wof:placetype":"venue"
},
  "geometry": {"coordinates":[-124.16437500000001,40.59914],"type":"Point"}
}