{
  "type": "Feature",
  "properties": {
    "iso:country":"US",
    "sg:address":"6540 Young Oak Ct",
    "sg:city":"Orangevale",
    "sg:classifiers":[
        {
            "category":"Wholesale",
            "subcategory":"Non-durable Goods",
            "type":"Manufacturing & Wholesale Goods"
        }
    ],
    "sg:phone":"+1 916 987 3223",
    "sg:postcode":"95662",
    "sg:province":"CA",
    "sg:tags":[
        "advertising",
        "specialty"
    ],
    "wof:name":"Paul Edwards Group",
    "wof:placetype":"venue"
},
  "geometry": {"coordinates":[-121.24118900000001,38.685152],"type":"Point"}
}