{
  "type": "Feature",
  "properties": {
    "addr:full":"431 Nelo St Santa Clara CA 95054",
    "addr:housenumber":"431",
    "addr:postcode":"95054",
    "addr:street":"Nelo St",
    "iso:country":"US",
    "sg:address":"431 Nelo St",
    "sg:city":"Santa Clara",
    "sg:classifiers":[
        {
            "category":"Professional",
            "type":"Services"
        }
    ],
    "sg:phone":"+1 408 970 9800",
    "sg:postcode":"95054",
    "sg:province":"CA",
    "wof:name":"Karya Brothers Networks Inc",
    "wof:placetype":"venue"
},
  "geometry": {"coordinates":[-121.942588,37.387486],"type":"Point"}
}