{
  "type": "Feature",
  "properties": {
    "addr:full":"5337 Via del Valle Torrance CA 90505",
    "addr:housenumber":"5337",
    "addr:postcode":"90505",
    "addr:street":"Via Del Valle",
    "iso:country":"US",
    "sg:address":"5337 Via del Valle",
    "sg:city":"Torrance",
    "sg:classifiers":[
        {
            "category":"Professional",
            "type":"Services"
        }
    ],
    "sg:phone":"+1 310 375 1741",
    "sg:postcode":"90505",
    "sg:province":"CA",
    "sg:website":"www.fictiondb.com",
    "wof:name":"FICTIONDB.COM",
    "wof:placetype":"venue"
},
  "geometry": {"coordinates":[-118.373107,33.805395],"type":"Point"}
}