{
  "type": "Feature",
  "properties": {
    "addr:full":"2959 E Thousand Oaks Blvd Thousand Oaks CA 91362",
    "addr:housenumber":"2959",
    "addr:postcode":"91362",
    "addr:street":"E Thousand Oaks Blvd",
    "iso:country":"US",
    "sg:address":"2959 E Thousand Oaks Blvd",
    "sg:city":"Thousand Oaks",
    "sg:classifiers":[
        {
            "category":"Shopping",
            "subcategory":"Jewelry",
            "type":"Retail Goods"
        }
    ],
    "sg:phone":"+1 805 374 1300",
    "sg:postcode":"91362",
    "sg:province":"CA",
    "sg:tags":[
        "jeweler"
    ],
    "wof:name":"Du Bois & Co Antique",
    "wof:placetype":"venue"
},
  "geometry": {"coordinates":[-118.837868,34.170633],"type":"Point"}
}