{
  "type": "Feature",
  "properties": {
    "iso:country":"US",
    "sg:address":"2275 Westwood Blvd",
    "sg:city":"Los Angeles",
    "sg:classifiers":[
        {
            "category":"Education",
            "subcategory":"Special Training",
            "type":"Public Place"
        }
    ],
    "sg:phone":"+1 310 475 2222",
    "sg:postcode":"90064",
    "sg:province":"CA",
    "sg:tags":[
        "tutoring"
    ],
    "sg:website":"www.Mathnasium.com",
    "wof:name":"Mathnasium",
    "wof:placetype":"venue"
},
  "geometry": {"coordinates":[-118.43104099999999,34.042569],"type":"Point"}
}