{
  "type": "Feature",
  "properties": {
    "addr:full":"4795 Opal Cliff Dr Santa Cruz CA 95062",
    "addr:housenumber":"4795",
    "addr:postcode":"95062",
    "addr:street":"Opal Cliff Dr",
    "iso:country":"US",
    "sg:address":"4795 Opal Cliff Dr",
    "sg:city":"Santa Cruz",
    "sg:classifiers":[
        {
            "category":"Social Services",
            "subcategory":"Job Training",
            "type":"Services"
        }
    ],
    "sg:phone":"+1 831 464 8694",
    "sg:postcode":"95062",
    "sg:province":"CA",
    "sg:tags":[
        "rehabilitation"
    ],
    "wof:name":"Opal Cliff Rehab Ctr",
    "wof:placetype":"venue"
},
  "geometry": {"coordinates":[-121.961518,36.964997],"type":"Point"}
}