{
  "type": "Feature",
  "properties": {
    "addr:full":"28202 Cabot Rd Laguna Niguel CA 92677",
    "addr:housenumber":"28202",
    "addr:postcode":"92677",
    "addr:street":"Cabot Rd",
    "iso:country":"US",
    "sg:address":"28202 Cabot Rd",
    "sg:city":"Laguna Niguel",
    "sg:classifiers":[
        {
            "category":"Professional",
            "subcategory":"Lawyer & Legal Services",
            "type":"Services"
        }
    ],
    "sg:phone":"+1 949 498 3203",
    "sg:postcode":"92677",
    "sg:province":"CA",
    "sg:tags":[
        "attorney"
    ],
    "wof:name":"Schadrack & Chapman",
    "wof:placetype":"venue"
},
  "geometry": {"coordinates":[-117.679001,33.551899],"type":"Point"}
}