{
  "type": "Feature",
  "properties": {
    "addr:full":"2830 Thornbury Ct Vallejo CA 94591",
    "addr:housenumber":"2830",
    "addr:postcode":"94591",
    "addr:street":"Thornbury Ct",
    "iso:country":"US",
    "sg:address":"2830 Thornbury Ct",
    "sg:city":"Vallejo",
    "sg:classifiers":[
        {
            "category":"Real Estate",
            "subcategory":"Real Estate Services",
            "type":"Services"
        },
        {
            "category":"Real Estate",
            "subcategory":"Real Estate Agent",
            "type":"Services"
        }
    ],
    "sg:phone":"+1 707 864 3766",
    "sg:postcode":"94591",
    "sg:province":"CA",
    "sg:tags":[
        "management"
    ],
    "wof:name":"Solano Equity Investments",
    "wof:placetype":"venue"
},
  "geometry": {"coordinates":[-122.187532,38.161943],"type":"Point"}
}