{
  "type": "Feature",
  "properties": {
    "addr:full":"3639 Las Posas Rd Ste 119 Camarillo CA 93010",
    "addr:housenumber":"3639",
    "addr:postcode":"93010",
    "addr:street":"Las Posas Rd Ste 119",
    "iso:country":"US",
    "sg:address":"3639 Las Posas Rd Ste 119",
    "sg:city":"Camarillo",
    "sg:classifiers":[
        {
            "category":"Personal",
            "subcategory":"Beauty Salon",
            "type":"Services"
        }
    ],
    "sg:phone":"+1 805 987 3920",
    "sg:postcode":"93010",
    "sg:province":"CA",
    "wof:name":"Auntie Sue",
    "wof:placetype":"venue"
},
  "geometry": {"coordinates":[-119.02164999999999,34.240772],"type":"Point"}
}