{
  "type": "Feature",
  "properties": {
    "iso:country":"US",
    "sg:address":"1810 Hillsdale Rd",
    "sg:city":"El Cajon",
    "sg:classifiers":[
        {
            "category":"Building & Trades",
            "subcategory":"Electrical",
            "type":"Services"
        }
    ],
    "sg:phone":"+1 619 447 4178",
    "sg:postcode":"92019",
    "sg:province":"CA",
    "sg:tags":[
        "installation"
    ],
    "wof:name":"Branch Hardware",
    "wof:placetype":"venue"
},
  "geometry": {"coordinates":[-116.916605,32.762241],"type":"Point"}
}