{
  "type": "Feature",
  "properties": {
    "addr:full":"1572 Cool Ridge Hts Escondido CA 92027",
    "addr:housenumber":"1572",
    "addr:postcode":"92027",
    "addr:street":"Cool Ridge Hts",
    "iso:country":"US",
    "sg:address":"1572 Cool Ridge Hts",
    "sg:city":"Escondido",
    "sg:classifiers":[
        {
            "category":"Building & Trades",
            "subcategory":"Landscaping Services",
            "type":"Services"
        }
    ],
    "sg:phone":"+1 760 737 9801",
    "sg:postcode":"92027",
    "sg:province":"CA",
    "sg:tags":[
        "landscape"
    ],
    "wof:name":"Hoey Bruce D Landscape",
    "wof:placetype":"venue"
},
  "geometry": {"coordinates":[-117.03478699999999,33.1032],"type":"Point"}
}