{
  "type": "Feature",
  "properties": {
    "iso:country":"US",
    "sg:address":"968 W Foothill Blvd",
    "sg:city":"Azusa",
    "sg:classifiers":[
        {
            "category":"Manufacturing",
            "subcategory":"Furniture",
            "type":"Manufacturing & Wholesale Goods"
        }
    ],
    "sg:phone":"+1 626 815 0168",
    "sg:postcode":"91702",
    "sg:province":"CA",
    "sg:website":"www.seatingresource.com",
    "wof:name":"Seating Resource",
    "wof:placetype":"venue"
},
  "geometry": {"coordinates":[-117.925891,34.133486],"type":"Point"}
}