{
  "type": "Feature",
  "properties": {
    "iso:country":"US",
    "sg:address":"102 W G St",
    "sg:city":"Ontario",
    "sg:classifiers":[
        {
            "category":"Insurance",
            "subcategory":"Insurance Agent",
            "type":"Services"
        }
    ],
    "sg:phone":"+1 909 391 2284",
    "sg:postcode":"91762",
    "sg:province":"CA",
    "wof:name":"Deza Insurance",
    "wof:placetype":"venue"
},
  "geometry": {"coordinates":[-117.65239099999999,34.070721],"type":"Point"}
}