{
  "type": "Feature",
  "properties": {
    "iso:country":"US",
    "sg:address":"2011 Vis Cajon",
    "sg:city":"Newport Beach",
    "sg:classifiers":[
        {
            "category":"Professional",
            "type":"Services"
        }
    ],
    "sg:phone":"+1 949 759 9227",
    "sg:postcode":"92660",
    "sg:province":"CA",
    "wof:name":"Merrilyn Avila Gauld",
    "wof:placetype":"venue"
},
  "geometry": {"coordinates":[-117.882526,33.63667],"type":"Point"}
}