{
  "type": "Feature",
  "properties": {
    "addr:full":"111 W Saint John St San Jose CA 95113",
    "addr:housenumber":"111",
    "addr:postcode":"95113",
    "addr:street":"W Saint John St",
    "iso:country":"US",
    "sg:address":"111 W Saint John St",
    "sg:city":"San Jose",
    "sg:classifiers":[
        {
            "category":"Real Estate",
            "subcategory":"Architect",
            "type":"Services"
        }
    ],
    "sg:phone":"+1 408 947 9500",
    "sg:postcode":"95113",
    "sg:province":"CA",
    "wof:name":"Julio Espinoza Architect",
    "wof:placetype":"venue"
},
  "geometry": {"coordinates":[-121.89395500000001,37.337239],"type":"Point"}
}