{
  "type": "Feature",
  "properties": {
    "iso:country":"US",
    "sg:address":"3420 Buck Owens Blvd",
    "sg:city":"Bakersfield",
    "sg:classifiers":[
        {
            "category":"Wholesale",
            "subcategory":"Apparel",
            "type":"Manufacturing & Wholesale Goods"
        }
    ],
    "sg:phone":"+1 661 864 1009",
    "sg:postcode":"93308",
    "sg:province":"CA",
    "sg:tags":[
        "hat"
    ],
    "wof:name":"Western Hard Hat Inc",
    "wof:placetype":"venue"
},
  "geometry": {"coordinates":[-119.0431,35.390613],"type":"Point"}
}