{
  "type": "Feature",
  "properties": {
    "iso:country":"US",
    "sg:address":"7th Ave & San Carlos St",
    "sg:city":"Carmel",
    "sg:classifiers":[
        {
            "category":"Food & Beverages",
            "subcategory":"Liquor & Beverages",
            "type":"Retail Goods"
        },
        {
            "category":"Food & Beverages",
            "subcategory":"Cheese",
            "type":"Retail Goods"
        },
        {
            "category":"Food & Beverages",
            "subcategory":"Groceries & Convenience Stores",
            "type":"Retail Goods"
        }
    ],
    "sg:phone":"+1 831 624 5939",
    "sg:postcode":"93923",
    "sg:province":"CA",
    "sg:tags":[
        "shop",
        "beer",
        "spirit",
        "wine"
    ],
    "sg:website":"www.nielsenmarket.com",
    "wof:name":"Nielsen Bros Market & Deli",
    "wof:placetype":"venue"
},
  "geometry": {"coordinates":[-121.921791,36.553782],"type":"Point"}
}