{
  "type": "Feature",
  "properties": {
    "addr:full":"805 Stockton St San Francisco CA 94108",
    "addr:housenumber":"805",
    "addr:postcode":"94108",
    "addr:street":"Stockton St",
    "iso:country":"US",
    "sg:address":"805 Stockton St",
    "sg:city":"San Francisco",
    "sg:classifiers":[
        {
            "category":"Food & Beverages",
            "subcategory":"Specialty",
            "type":"Retail Goods"
        }
    ],
    "sg:phone":"+1 415 982 3886",
    "sg:postcode":"94108",
    "sg:province":"CA",
    "sg:tags":[
        "herb"
    ],
    "wof:name":"Ellision Enterprise Co USA",
    "wof:placetype":"venue"
},
  "geometry": {"coordinates":[-122.407971,37.794012],"type":"Point"}
}