{
  "type": "Feature",
  "properties": {
    "addr:full":"3090 Dwight Ave Camarillo CA 93010",
    "addr:housenumber":"3090",
    "addr:postcode":"93010",
    "addr:street":"Dwight Ave",
    "iso:country":"US",
    "sg:address":"3090 Dwight Ave",
    "sg:city":"Camarillo",
    "sg:classifiers":[
        {
            "category":"Local Transit",
            "type":"Transportation"
        }
    ],
    "sg:phone":"+1 805 987 1034",
    "sg:postcode":"93010",
    "sg:province":"CA",
    "wof:name":"Curtis & Down Studio Svc",
    "wof:placetype":"venue"
},
  "geometry": {"coordinates":[-119.02866,34.231602],"type":"Point"}
}