{
  "type": "Feature",
  "properties": {
    "iso:country":"US",
    "sg:address":"37552 Winchester Rd",
    "sg:city":"Murrieta",
    "sg:classifiers":[
        {
            "category":"Autos & Motor Vehicles",
            "subcategory":"Automobile Sales",
            "type":"Retail Goods"
        }
    ],
    "sg:phone":"+1 951 677 5115",
    "sg:postcode":"92563",
    "sg:province":"CA",
    "sg:tags":[
        "aircraft"
    ],
    "wof:name":"Aviation Sales California",
    "wof:placetype":"venue"
},
  "geometry": {"coordinates":[-117.13247,33.582878],"type":"Point"}
}