{
  "type": "Feature",
  "properties": {
    "addr:full":"1752 W Adams Blvd Los Angeles CA 90018",
    "addr:housenumber":"1752",
    "addr:postcode":"90018",
    "addr:street":"W Adams Blvd",
    "iso:country":"US",
    "sg:address":"1752 W Adams Blvd",
    "sg:city":"Los Angeles",
    "sg:classifiers":[
        {
            "category":"Education",
            "subcategory":"Special Training",
            "type":"Public Place"
        }
    ],
    "sg:phone":"+1 323 730 5878",
    "sg:postcode":"90018",
    "sg:province":"CA",
    "sg:tags":[
        "instruction",
        "music"
    ],
    "wof:name":"Centro De Capacitacion Musical",
    "wof:placetype":"venue"
},
  "geometry": {"coordinates":[-118.302142,34.032646],"type":"Point"}
}