{
  "type": "Feature",
  "properties": {
    "addr:full":"19 Monte Vis Newbury Park CA 91320",
    "addr:housenumber":"19",
    "addr:postcode":"91320",
    "addr:street":"Monte Vis",
    "iso:country":"US",
    "sg:address":"19 Monte Vis",
    "sg:city":"Newbury Park",
    "sg:classifiers":[
        {
            "category":"Professional",
            "subcategory":"Business Services",
            "type":"Services"
        }
    ],
    "sg:phone":"+1 805 493 1920",
    "sg:postcode":"91320",
    "sg:province":"CA",
    "wof:name":"B & L Black",
    "wof:placetype":"venue"
},
  "geometry": {"coordinates":[-118.958364,34.193601],"type":"Point"}
}