{
  "type": "Feature",
  "properties": {
    "addr:full":"14891 Royal Way Truckee CA 96161",
    "addr:housenumber":"14891",
    "addr:postcode":"96161",
    "addr:street":"Royal Way",
    "iso:country":"US",
    "sg:address":"14891 Royal Way",
    "sg:city":"Truckee",
    "sg:classifiers":[
        {
            "category":"Building & Trades",
            "subcategory":"Construction",
            "type":"Services"
        }
    ],
    "sg:phone":"+1 530 587 3310",
    "sg:postcode":"96161",
    "sg:province":"CA",
    "sg:tags":[
        "excavating",
        "contractor"
    ],
    "wof:name":"Aspen Developers Corp",
    "wof:placetype":"venue"
},
  "geometry": {"coordinates":[-120.110906,39.349695],"type":"Point"}
}