{
  "type": "Feature",
  "properties": {
    "addr:full":"101 Henry Adams St San Francisco CA 94103",
    "addr:housenumber":"101",
    "addr:postcode":"94103",
    "addr:street":"Henry Adams St",
    "iso:country":"US",
    "sg:address":"101 Henry Adams St",
    "sg:city":"San Francisco",
    "sg:classifiers":[
        {
            "category":"Home & Garden",
            "subcategory":"Furniture",
            "type":"Retail Goods"
        }
    ],
    "sg:phone":"+1 415 934 1454",
    "sg:postcode":"94103",
    "sg:province":"CA",
    "sg:tags":[
        "equipment",
        "kitchen",
        "cabinet"
    ],
    "wof:name":"Kitchen Matrix",
    "wof:placetype":"venue"
},
  "geometry": {"coordinates":[-122.403779,37.767527],"type":"Point"}
}