{
  "type": "Feature",
  "properties": {
    "iso:country":"US",
    "sg:address":"3054 Story Rd",
    "sg:city":"San Jose",
    "sg:classifiers":[
        {
            "category":"Retail",
            "subcategory":"Repair Shop",
            "type":"Services"
        }
    ],
    "sg:phone":"+1 408 259 8653",
    "sg:postcode":"95127",
    "sg:province":"CA",
    "sg:tags":[
        "jewelry"
    ],
    "wof:name":"Joyeria Torres",
    "wof:placetype":"venue"
},
  "geometry": {"coordinates":[-121.819457,37.355808],"type":"Point"}
}