{
  "type": "Feature",
  "properties": {
    "addr:full":"453 S Spring St Studio 839 Los Angeles CA 90013",
    "addr:housenumber":"453;839",
    "addr:postcode":"90013",
    "addr:street":"S Spring St",
    "iso:country":"US",
    "sg:address":"453 S Spring St Studio 839",
    "sg:city":"Los Angeles",
    "sg:classifiers":[
        {
            "category":"Home & Garden",
            "subcategory":"Home Furnishings",
            "type":"Retail Goods"
        },
        {
            "category":"Home & Garden",
            "subcategory":"Furniture",
            "type":"Retail Goods"
        }
    ],
    "sg:phone":"+1 213 624 7309",
    "sg:postcode":"90013",
    "sg:province":"CA",
    "sg:tags":[
        "decor",
        "store"
    ],
    "sg:website":"www.amenityhome.com",
    "wof:name":"Amenity",
    "wof:placetype":"venue"
},
  "geometry": {"coordinates":[-118.249748,34.047787],"type":"Point"}
}