{
  "type": "Feature",
  "properties": {
    "addr:full":"20755 Prairie St Chatsworth CA 91311",
    "addr:housenumber":"20755",
    "addr:postcode":"91311",
    "addr:street":"Prairie St",
    "iso:country":"US",
    "sg:address":"20755 Prairie St",
    "sg:city":"Chatsworth",
    "sg:classifiers":[
        {
            "category":"Manufacturing",
            "subcategory":"Printing",
            "type":"Manufacturing & Wholesale Goods"
        }
    ],
    "sg:phone":"+1 818 882 8926",
    "sg:postcode":"91311",
    "sg:province":"CA",
    "sg:tags":[
        "printer"
    ],
    "wof:name":"ABC Print Shirts & Embroidery",
    "wof:placetype":"venue"
},
  "geometry": {"coordinates":[-118.585358,34.240983],"type":"Point"}
}