{
  "type": "Feature",
  "properties": {
    "iso:country":"US",
    "sg:address":"299 N Smith Ave",
    "sg:city":"Corona",
    "sg:classifiers":[
        {
            "category":"Manufacturing",
            "subcategory":"Buildings",
            "type":"Manufacturing & Wholesale Goods"
        }
    ],
    "sg:phone":"+1 951 734 6610",
    "sg:postcode":"92880",
    "sg:province":"CA",
    "sg:tags":[
        "prefab"
    ],
    "wof:name":"Silvercrest Western Homes Corp",
    "wof:placetype":"venue"
},
  "geometry": {"coordinates":[-117.592683,33.889393],"type":"Point"}
}