{
  "type": "Feature",
  "properties": {
    "iso:country":"US",
    "sg:address":"9260 Sierra College Blvd",
    "sg:city":"Roseville",
    "sg:classifiers":[
        {
            "category":"Retail",
            "subcategory":"Veterinary Services",
            "type":"Services"
        }
    ],
    "sg:phone":"+1 916 774 6630",
    "sg:postcode":"95661",
    "sg:province":"CA",
    "sg:tags":[
        "veterinarian"
    ],
    "wof:name":"Johnson Ranch Veterinary",
    "wof:placetype":"venue"
},
  "geometry": {"coordinates":[-121.226054,38.731624],"type":"Point"}
}