{
  "type": "Feature",
  "properties": {
    "iso:country":"US",
    "sg:address":"1520 W Olympic Blvd",
    "sg:city":"Montebello",
    "sg:classifiers":[
        {
            "category":"Retail",
            "subcategory":"Auto Repair",
            "type":"Services"
        }
    ],
    "sg:phone":"+1 323 888 9522",
    "sg:postcode":"90640",
    "sg:province":"CA",
    "sg:tags":[
        "body",
        "automobile",
        "painting"
    ],
    "wof:name":"I & R Auto Body & Paint",
    "wof:placetype":"venue"
},
  "geometry": {"coordinates":[-118.11899,34.009264],"type":"Point"}
}