{
  "type": "Feature",
  "properties": {
    "addr:full":"1150 N Harbor Blvd # 124 Anaheim CA 92801",
    "addr:housenumber":"1150",
    "addr:postcode":"92801",
    "addr:street":"N Harbor Blvd # 124",
    "iso:country":"US",
    "sg:address":"1150 N Harbor Blvd # 124",
    "sg:city":"Anaheim",
    "sg:classifiers":[
        {
            "category":"Personal",
            "subcategory":"Nail Salon",
            "type":"Services"
        }
    ],
    "sg:phone":"+1 714 563 2627",
    "sg:postcode":"92801",
    "sg:province":"CA",
    "wof:name":"Blue Orchid Nail Salon",
    "wof:placetype":"venue"
},
  "geometry": {"coordinates":[-117.923462,33.850365],"type":"Point"}
}