{
  "type": "Feature",
  "properties": {
    "iso:country":"US",
    "sg:address":"27440 Cypress St",
    "sg:city":"Highland",
    "sg:classifiers":[
        {
            "category":"Building & Trades",
            "subcategory":"Construction",
            "type":"Services"
        }
    ],
    "sg:phone":"+1 909 887 1433",
    "sg:postcode":"92346",
    "sg:province":"CA",
    "sg:tags":[
        "fence",
        "contractor"
    ],
    "wof:name":"Empire Fence",
    "wof:placetype":"venue"
},
  "geometry": {"coordinates":[-117.2051,34.113392],"type":"Point"}
}