{
  "type": "Feature",
  "properties": {
    "addr:full":"1424 Continental St San Diego CA 92154",
    "addr:housenumber":"1424",
    "addr:postcode":"92154",
    "addr:street":"Continental St",
    "iso:country":"US",
    "sg:address":"1424 Continental St",
    "sg:city":"San Diego",
    "sg:classifiers":[
        {
            "category":"Education",
            "subcategory":"Special Training",
            "type":"Public Place"
        }
    ],
    "sg:phone":"+1 619 661 1121",
    "sg:postcode":"92154",
    "sg:province":"CA",
    "sg:tags":[
        "product",
        "petroleum",
        "air"
    ],
    "wof:name":"Bearden Fuel",
    "wof:placetype":"venue"
},
  "geometry": {"coordinates":[-116.984539,32.568262],"type":"Point"}
}