{
  "type": "Feature",
  "properties": {
    "addr:full":"1199 Stanyan St San Francisco CA 94117",
    "addr:housenumber":"1199",
    "addr:postcode":"94117",
    "addr:street":"Stanyan St",
    "iso:country":"US",
    "sg:address":"1199 Stanyan St",
    "sg:city":"San Francisco",
    "sg:classifiers":[
        {
            "category":"Building & Trades",
            "subcategory":"Landscaping Services",
            "type":"Services"
        }
    ],
    "sg:phone":"+1 415 753 1366",
    "sg:postcode":"94117",
    "sg:province":"CA",
    "sg:tags":[
        "tree"
    ],
    "wof:name":"R S Scudder Tree & Landscape",
    "wof:placetype":"venue"
},
  "geometry": {"coordinates":[-122.45222200000001,37.762475],"type":"Point"}
}