{
  "type": "Feature",
  "properties": {
    "addr:full":"2022 Solano St Corning CA 96021",
    "addr:housenumber":"2022",
    "addr:postcode":"96021",
    "addr:street":"Solano St",
    "iso:country":"US",
    "sg:address":"2022 Solano St",
    "sg:city":"Corning",
    "sg:classifiers":[
        {
            "category":"Real Estate",
            "subcategory":"Real Estate Agent",
            "type":"Services"
        }
    ],
    "sg:phone":"+1 530 824 4264",
    "sg:postcode":"96021",
    "sg:province":"CA",
    "wof:name":"American Homes & Land Realty",
    "wof:placetype":"venue"
},
  "geometry": {"coordinates":[-122.196943,39.928124],"type":"Point"}
}