{
  "type": "Feature",
  "properties": {
    "iso:country":"US",
    "sg:address":"2755 Jefferson St",
    "sg:city":"Carlsbad",
    "sg:classifiers":[
        {
            "category":"Banks & Credit Unions",
            "subcategory":"Bank",
            "type":"Services"
        }
    ],
    "sg:phone":"+1 760 720 1785",
    "sg:postcode":"92008",
    "sg:province":"CA",
    "sg:tags":[
        "personal",
        "consulting",
        "management",
        "institution"
    ],
    "wof:name":"Stewart Financial Svc",
    "wof:placetype":"venue"
},
  "geometry": {"coordinates":[-117.347218,33.163295],"type":"Point"}
}