{
  "type": "Feature",
  "properties": {
    "addr:full":"1617 Westcliff Dr Ste #205 Newport Beach CA 92660",
    "addr:housenumber":"1617",
    "addr:postcode":"92660",
    "addr:street":"Westcliff Dr Ste # 205",
    "iso:country":"US",
    "sg:address":"1617 Westcliff Dr Ste #205",
    "sg:city":"Newport Beach",
    "sg:classifiers":[
        {
            "category":"Health Services",
            "subcategory":"Hospital",
            "type":"Services"
        },
        {
            "category":"Health Services",
            "subcategory":"Chiropractor",
            "type":"Services"
        }
    ],
    "sg:phone":"+1 888 311 7246",
    "sg:postcode":"92660",
    "sg:province":"CA",
    "sg:tags":[
        "urgent",
        "care"
    ],
    "wof:name":"Paindoc Back Pain Treatment",
    "wof:placetype":"venue"
},
  "geometry": {"coordinates":[-117.90565700000001,33.625652],"type":"Point"}
}