{
  "type": "Feature",
  "properties": {
    "iso:country":"US",
    "sg:address":"139 N Maple St",
    "sg:city":"Corona",
    "sg:classifiers":[
        {
            "category":"Professional",
            "subcategory":"Management & Consulting",
            "type":"Services"
        }
    ],
    "sg:phone":"+1 951 734 3507",
    "sg:postcode":"92880",
    "sg:province":"CA",
    "sg:tags":[
        "consultant",
        "construction"
    ],
    "wof:name":"General Consolidated Cnstrctrs",
    "wof:placetype":"venue"
},
  "geometry": {"coordinates":[-117.60311900000001,33.883833],"type":"Point"}
}