{
  "type": "Feature",
  "properties": {
    "iso:country":"US",
    "sg:address":"14410 Sylvan St",
    "sg:city":"Van Nuys",
    "sg:classifiers":[
        {
            "category":"Government",
            "subcategory":"Office",
            "type":"Public Place"
        }
    ],
    "sg:phone":"+1 818 756 9874",
    "sg:postcode":"91401",
    "sg:province":"CA",
    "sg:tags":[
        "program",
        "administrative"
    ],
    "wof:name":"Neighborhood Empowerment Dept",
    "wof:placetype":"venue"
},
  "geometry": {"coordinates":[-118.44852899999999,34.184579],"type":"Point"}
}