{
  "type": "Feature",
  "properties": {
    "addr:full":"8025 Corkoaks Way Citrus Heights CA 95621",
    "addr:housenumber":"8025",
    "addr:postcode":"95621",
    "addr:street":"Corkoaks Way",
    "iso:country":"US",
    "sg:address":"8025 Corkoaks Way",
    "sg:city":"Citrus Heights",
    "sg:classifiers":[
        {
            "category":"Freight",
            "type":"Transportation"
        },
        {
            "category":"Utilities",
            "subcategory":"Refuse",
            "type":"Services"
        }
    ],
    "sg:phone":"+1 916 743 4302",
    "sg:postcode":"95621",
    "sg:province":"CA",
    "sg:tags":[
        "hauling",
        "system",
        "trucking"
    ],
    "wof:name":"A G Hauling & Cleaning & Rcycl",
    "wof:placetype":"venue"
},
  "geometry": {"coordinates":[-121.300723,38.712612],"type":"Point"}
}