{
  "type": "Feature",
  "properties": {
    "iso:country":"US",
    "sg:address":"7011 Atlantic Avenue",
    "sg:city":"Bell",
    "sg:classifiers":[
        {
            "category":"Shopping",
            "subcategory":"Beauty & Cosmetics",
            "type":"Retail Goods"
        }
    ],
    "sg:phone":"+1 323 773 7660",
    "sg:postcode":"90201",
    "sg:province":"CA",
    "sg:tags":[
        "supply"
    ],
    "wof:name":"Marco Beauty Supplies & Salon",
    "wof:placetype":"venue"
},
  "geometry": {"coordinates":[-118.18780700000001,33.972053],"type":"Point"}
}