{
  "type": "Feature",
  "properties": {
    "addr:full":"4021 Scott Valley Rd Etna CA 96027",
    "addr:housenumber":"4021",
    "addr:postcode":"96027",
    "addr:street":"Scott Valley Rd",
    "iso:country":"US",
    "sg:address":"4021 Scott Valley Rd",
    "sg:city":"Etna",
    "sg:classifiers":[
        {
            "category":"Manufacturing",
            "subcategory":"Lumber",
            "type":"Manufacturing & Wholesale Goods"
        }
    ],
    "sg:phone":"+1 530 467 3781",
    "sg:postcode":"96027",
    "sg:province":"CA",
    "sg:tags":[
        "forestry"
    ],
    "wof:name":"Jennifer Moore",
    "wof:placetype":"venue"
},
  "geometry": {"coordinates":[-122.90053,41.522949],"type":"Point"}
}