{
  "type": "Feature",
  "properties": {
    "iso:country":"US",
    "sg:address":"737 N Citrus Ave",
    "sg:city":"Los Angeles",
    "sg:classifiers":[
        {
            "category":"Personal",
            "type":"Services"
        }
    ],
    "sg:phone":"+1 323 932 9528",
    "sg:postcode":"90038",
    "sg:province":"CA",
    "sg:tags":[
        "consultant",
        "image"
    ],
    "wof:name":"Surface Management LLC",
    "wof:placetype":"venue"
},
  "geometry": {"coordinates":[-118.339738,34.084605],"type":"Point"}
}