{
  "type": "Feature",
  "properties": {
    "iso:country":"US",
    "sg:address":"2647 Senter Road Ste 111",
    "sg:city":"San Jose",
    "sg:classifiers":[
        {
            "category":"Shopping",
            "subcategory":"Mobile Phones",
            "type":"Retail Goods"
        }
    ],
    "sg:phone":"+1 408 292 6886",
    "sg:postcode":"95111",
    "sg:province":"CA",
    "wof:name":"Di Dong Mobile",
    "wof:placetype":"venue"
},
  "geometry": {"coordinates":[-121.84298200000001,37.303001],"type":"Point"}
}