{
  "type": "Feature",
  "properties": {
    "addr:full":"8023 Montelena Ct Sacramento CA 95829",
    "addr:housenumber":"8023",
    "addr:postcode":"95829",
    "addr:street":"Montelena Ct",
    "iso:country":"US",
    "sg:address":"8023 Montelena Ct",
    "sg:city":"Sacramento",
    "sg:classifiers":[
        {
            "category":"Professional",
            "subcategory":"Business Services",
            "type":"Services"
        }
    ],
    "sg:phone":"+1 916 410 7553",
    "sg:postcode":"95829",
    "sg:province":"CA",
    "sg:tags":[
        "notary"
    ],
    "wof:name":"Maria's Notary Svc",
    "wof:placetype":"venue"
},
  "geometry": {"coordinates":[-121.36089200000001,38.466401],"type":"Point"}
}