{
  "type": "Feature",
  "properties": {
    "iso:country":"US",
    "sg:address":"2659 Doray Cir",
    "sg:city":"Monrovia",
    "sg:classifiers":[
        {
            "category":"Banks & Credit Unions",
            "subcategory":"Financial Services",
            "type":"Services"
        }
    ],
    "sg:phone":"+1 626 475 4046",
    "sg:postcode":"91016",
    "sg:province":"CA",
    "sg:tags":[
        "investor"
    ],
    "wof:name":"No Limit Investments Inc",
    "wof:placetype":"venue"
},
  "geometry": {"coordinates":[-118.005314,34.117209],"type":"Point"}
}