{
  "type": "Feature",
  "properties": {
    "iso:country":"US",
    "sg:address":"1645 Telegraph Ave",
    "sg:city":"Oakland",
    "sg:classifiers":[
        {
            "category":"Communications",
            "subcategory":"Film & Video Production",
            "type":"Services"
        }
    ],
    "sg:phone":"+1 510 444 1330",
    "sg:postcode":"94612",
    "sg:province":"CA",
    "sg:tags":[
        "taping"
    ],
    "wof:name":"Peter Brown & Assoc",
    "wof:placetype":"venue"
},
  "geometry": {"coordinates":[-122.270483,37.806498],"type":"Point"}
}