{
  "type": "Feature",
  "properties": {
    "addr:full":"211 S Beverly Drive Beverly Hills CA 90212",
    "addr:housenumber":"211",
    "addr:postcode":"90212",
    "addr:street":"S Beverly Drive",
    "iso:country":"US",
    "sg:address":"211 S Beverly Drive",
    "sg:city":"Beverly Hills",
    "sg:classifiers":[
        {
            "category":"Professional",
            "subcategory":"Lawyer & Legal Services",
            "type":"Services"
        }
    ],
    "sg:phone":"+1 310 550 8700",
    "sg:postcode":"90212",
    "sg:province":"CA",
    "wof:name":"Lapidus & Lapidus",
    "wof:placetype":"venue"
},
  "geometry": {"coordinates":[-118.39910500000001,34.06472],"type":"Point"}
}