{
  "type": "Feature",
  "properties": {
    "addr:full":"1501 N Harbor Blvd Fullerton CA 92835",
    "addr:housenumber":"1501",
    "addr:postcode":"92835",
    "addr:street":"N Harbor Blvd",
    "iso:country":"US",
    "sg:address":"1501 N Harbor Blvd",
    "sg:city":"Fullerton",
    "sg:classifiers":[
        {
            "category":"Professional",
            "subcategory":"Accounting & Tax Preparation",
            "type":"Services"
        }
    ],
    "sg:phone":"+1 714 870 0285",
    "sg:postcode":"92835",
    "sg:province":"CA",
    "sg:tags":[
        "accountant"
    ],
    "sg:website":"www.hensleecpa.com",
    "wof:name":"Stanley C Henslee CPA",
    "wof:placetype":"venue"
},
  "geometry": {"coordinates":[-117.926473,33.886351],"type":"Point"}
}