{
  "type": "Feature",
  "properties": {
    "addr:full":"2407 21st Ave San Francisco CA 94116",
    "addr:housenumber":"2407",
    "addr:postcode":"94116",
    "addr:street":"21St Ave",
    "iso:country":"US",
    "sg:address":"2407 21st Ave",
    "sg:city":"San Francisco",
    "sg:classifiers":[
        {
            "category":"Building & Trades",
            "subcategory":"Plumbing",
            "type":"Services"
        }
    ],
    "sg:phone":"+1 415 681 9323",
    "sg:postcode":"94116",
    "sg:province":"CA",
    "wof:name":"CW Lee Plumbing",
    "wof:placetype":"venue"
},
  "geometry": {"coordinates":[-122.478144,37.74269],"type":"Point"}
}