{
  "type": "Feature",
  "properties": {
    "addr:full":"1200 Santee St #400 Los Angeles CA 90015",
    "addr:housenumber":"1200",
    "addr:postcode":"90015",
    "addr:street":"Santee St # 400",
    "iso:country":"US",
    "sg:address":"1200 Santee St #400",
    "sg:city":"Los Angeles",
    "sg:classifiers":[
        {
            "category":"Animal Shelter",
            "type":"Public Place"
        },
        {
            "category":"Shopping",
            "subcategory":"Bridal",
            "type":"Retail Goods"
        }
    ],
    "sg:phone":"+1 213 747 0600",
    "sg:postcode":"90015",
    "sg:province":"CA",
    "sg:tags":[
        "adult"
    ],
    "wof:name":"Donna di Capri Lingerie",
    "wof:placetype":"venue"
},
  "geometry": {"coordinates":[-118.257338,34.036269],"type":"Point"}
}