{
  "type": "Feature",
  "properties": {
    "addr:full":"2470 Fleetwood Dr San Bruno CA 94066",
    "addr:housenumber":"2470",
    "addr:postcode":"94066",
    "addr:street":"Fleetwood Dr",
    "iso:country":"US",
    "sg:address":"2470 Fleetwood Dr",
    "sg:city":"San Bruno",
    "sg:classifiers":[
        {
            "category":"Professional",
            "subcategory":"Art Services",
            "type":"Services"
        }
    ],
    "sg:phone":"+1 650 583 6057",
    "sg:postcode":"94066",
    "sg:province":"CA",
    "sg:tags":[
        "photographer"
    ],
    "sg:website":"www.joanm.com",
    "wof:name":"John M Studios",
    "wof:placetype":"venue"
},
  "geometry": {"coordinates":[-122.44183200000001,37.629523],"type":"Point"}
}