{
  "type": "Feature",
  "properties": {
    "iso:country":"US",
    "sg:address":"1275 Boulevard Way",
    "sg:city":"Walnut Creek",
    "sg:classifiers":[
        {
            "category":"Building & Trades",
            "subcategory":"Plumbing",
            "type":"Services"
        }
    ],
    "sg:phone":"+1 925 946 9101",
    "sg:postcode":"94595",
    "sg:province":"CA",
    "sg:tags":[
        "sheet",
        "work",
        "metal",
        "contractor"
    ],
    "sg:website":"www.amsofusa.com",
    "wof:name":"American Mechanical Svc",
    "wof:placetype":"venue"
},
  "geometry": {"coordinates":[-122.07653999999999,37.893827],"type":"Point"}
}