{
  "type": "Feature",
  "properties": {
    "iso:country":"US",
    "sg:address":"295 W Cromwell Ave",
    "sg:city":"Fresno",
    "sg:classifiers":[
        {
            "category":"Wholesale",
            "subcategory":"Medical Equipment & Supplies",
            "type":"Manufacturing & Wholesale Goods"
        }
    ],
    "sg:phone":"+1 559 432 1920",
    "sg:postcode":"93711",
    "sg:province":"CA",
    "sg:tags":[
        "physician",
        "surgeon"
    ],
    "sg:website":"www.switzermedical.com",
    "wof:name":"Switzer Medical",
    "wof:placetype":"venue"
},
  "geometry": {"coordinates":[-119.842911,36.847001],"type":"Point"}
}