{
  "type": "Feature",
  "properties": {
    "addr:full":"504 Lake Park Ave Oakland CA 94610",
    "addr:housenumber":"504",
    "addr:postcode":"94610",
    "addr:street":"Lake Park Ave",
    "iso:country":"US",
    "sg:address":"504 Lake Park Ave",
    "sg:city":"Oakland",
    "sg:classifiers":[
        {
            "category":"Bars & Pubs",
            "type":"Food & Drink"
        }
    ],
    "sg:phone":"+1 510 832 2644",
    "sg:postcode":"94610",
    "sg:province":"CA",
    "sg:tags":[
        "lounge",
        "cocktail"
    ],
    "wof:name":"Serenader",
    "wof:placetype":"venue"
},
  "geometry": {"coordinates":[-122.24704199999999,37.810569],"type":"Point"}
}