{
  "type": "Feature",
  "properties": {
    "addr:full":"17027 State Hwy 175 Middletown CA 95461",
    "addr:housenumber":"17027",
    "addr:postcode":"95461",
    "addr:street":"State Hwy 175",
    "iso:country":"US",
    "sg:address":"17027 State Hwy 175",
    "sg:city":"Middletown",
    "sg:classifiers":[
        {
            "category":"Restaurant",
            "type":"Food & Drink"
        }
    ],
    "sg:phone":"+1 707 928 5781",
    "sg:postcode":"95461",
    "sg:province":"CA",
    "wof:name":"Bruceski's",
    "wof:placetype":"venue"
},
  "geometry": {"coordinates":[-122.711894,38.814118],"type":"Point"}
}