{
  "type": "Feature",
  "properties": {
    "addr:full":"2463 W 208th St Torrance CA 90501",
    "addr:housenumber":"2463",
    "addr:postcode":"90501",
    "addr:street":"W 208Th St",
    "iso:country":"US",
    "sg:address":"2463 W 208th St",
    "sg:city":"Torrance",
    "sg:classifiers":[
        {
            "category":"Professional",
            "subcategory":"Computer Services",
            "type":"Services"
        }
    ],
    "sg:phone":"+1 310 533 0477",
    "sg:postcode":"90501",
    "sg:province":"CA",
    "sg:tags":[
        "information",
        "technology"
    ],
    "wof:name":"Vaau",
    "wof:placetype":"venue"
},
  "geometry": {"coordinates":[-118.327913,33.843814],"type":"Point"}
}