{
  "type": "Feature",
  "properties": {
    "addr:full":"1430 Cutting Blvd Richmond CA 94804",
    "addr:housenumber":"1430",
    "addr:postcode":"94804",
    "addr:street":"Cutting Blvd",
    "iso:country":"US",
    "sg:address":"1430 Cutting Blvd",
    "sg:city":"Richmond",
    "sg:classifiers":[
        {
            "category":"Professional",
            "subcategory":"Business Services",
            "type":"Services"
        }
    ],
    "sg:phone":"+1 510 233 0402",
    "sg:postcode":"94804",
    "sg:province":"CA",
    "sg:tags":[
        "cloth",
        "cutting"
    ],
    "wof:name":"Cutting Discount",
    "wof:placetype":"venue"
},
  "geometry": {"coordinates":[-122.355182,37.925127],"type":"Point"}
}