{
  "type": "Feature",
  "properties": {
    "iso:country":"US",
    "sg:address":"2427 Douglas St",
    "sg:city":"Union City",
    "sg:classifiers":[
        {
            "category":"Real Estate",
            "subcategory":"Real Estate Agent",
            "type":"Services"
        }
    ],
    "sg:phone":"+1 510 471 3458",
    "sg:postcode":"94587",
    "sg:province":"CA",
    "sg:tags":[
        "broker"
    ],
    "wof:name":"Mitchell Peter Real Estate Brk",
    "wof:placetype":"venue"
},
  "geometry": {"coordinates":[-122.054654,37.59864],"type":"Point"}
}