{
  "type": "Feature",
  "properties": {
    "addr:full":"1028 N Lake Ave Pasadena CA 91104",
    "addr:housenumber":"1028",
    "addr:postcode":"91104",
    "addr:street":"N Lake Ave",
    "iso:country":"US",
    "sg:address":"1028 N Lake Ave",
    "sg:city":"Pasadena",
    "sg:classifiers":[
        {
            "category":"Health Services",
            "subcategory":"Health Practitioner",
            "type":"Services"
        }
    ],
    "sg:phone":"+1 626 319 8725",
    "sg:postcode":"91104",
    "sg:province":"CA",
    "sg:tags":[
        "acupuncture"
    ],
    "sg:website":"www.hamptonshealth.com",
    "wof:name":"Hamptons Health",
    "wof:placetype":"venue"
},
  "geometry": {"coordinates":[-118.132474,34.163448],"type":"Point"}
}