{
  "type": "Feature",
  "properties": {
    "addr:full":"201 Seminary Dr Mill Valley CA 94941",
    "addr:housenumber":"201",
    "addr:postcode":"94941",
    "addr:street":"Seminary Dr",
    "iso:country":"US",
    "sg:address":"201 Seminary Dr",
    "sg:city":"Mill Valley",
    "sg:classifiers":[
        {
            "category":"Education",
            "subcategory":"College",
            "type":"Public Place"
        }
    ],
    "sg:phone":"+1 415 380 1320",
    "sg:postcode":"94941",
    "sg:province":"CA",
    "sg:tags":[
        "seminary"
    ],
    "wof:name":"Golden Gate Baptist Theologica",
    "wof:placetype":"venue"
},
  "geometry": {"coordinates":[-122.513676,37.890877],"type":"Point"}
}