{
  "type": "Feature",
  "properties": {
    "iso:country":"US",
    "sg:address":"2576 Hartnell Ave",
    "sg:city":"Redding",
    "sg:classifiers":[
        {
            "category":"Health Services",
            "subcategory":"Medical Lab",
            "type":"Services"
        }
    ],
    "sg:phone":"+1 530 223 9729",
    "sg:postcode":"96002",
    "sg:province":"CA",
    "sg:tags":[
        "x",
        "laboratory"
    ],
    "wof:name":"North West X Ray Inc",
    "wof:placetype":"venue"
},
  "geometry": {"coordinates":[-122.325076,40.563828],"type":"Point"}
}