{
  "type": "Feature",
  "properties": {
    "addr:full":"901 N Coast Hwy Oceanside CA 92054",
    "addr:housenumber":"901",
    "addr:postcode":"92054",
    "addr:street":"N Coast Hwy",
    "iso:country":"US",
    "sg:address":"901 N Coast Hwy",
    "sg:city":"Oceanside",
    "sg:classifiers":[
        {
            "category":"Travel",
            "subcategory":"Hotels & Motels",
            "type":"Entertainment"
        }
    ],
    "sg:phone":"+1 760 722 1781",
    "sg:postcode":"92054",
    "sg:province":"CA",
    "wof:name":"Pacific Inn of Oceanside",
    "wof:placetype":"venue"
},
  "geometry": {"coordinates":[-117.38400300000001,33.201599],"type":"Point"}
}