{
  "type": "Feature",
  "properties": {
    "iso:country":"US",
    "sg:address":"22854 Calvert St",
    "sg:city":"Woodland Hills",
    "sg:classifiers":[
        {
            "category":"Building & Trades",
            "subcategory":"Plumbing",
            "type":"Services"
        }
    ],
    "sg:phone":"+1 818 363 4021",
    "sg:postcode":"91367",
    "sg:province":"CA",
    "sg:tags":[
        "plumbing",
        "contractor"
    ],
    "wof:name":"Cwb Shrewsbury Plumbing Inc",
    "wof:placetype":"venue"
},
  "geometry": {"coordinates":[-118.630479,34.180915],"type":"Point"}
}