{
  "type": "Feature",
  "properties": {
    "addr:full":"3050 Citrus Cir Ste 201 Walnut Creek CA 94598",
    "addr:housenumber":"3050",
    "addr:postcode":"94598",
    "addr:street":"Citrus Cir Ste 201",
    "iso:country":"US",
    "sg:address":"3050 Citrus Cir Ste 201",
    "sg:city":"Walnut Creek",
    "sg:classifiers":[
        {
            "category":"Banks & Credit Unions",
            "subcategory":"Financial Services",
            "type":"Services"
        }
    ],
    "sg:phone":"+1 925 934 3050",
    "sg:postcode":"94598",
    "sg:province":"CA",
    "sg:tags":[
        "broker",
        "mortgage"
    ],
    "wof:name":"Infinity Capital Lending",
    "wof:placetype":"venue"
},
  "geometry": {"coordinates":[-122.369922,37.928867],"type":"Point"}
}