{
  "type": "Feature",
  "properties": {
    "addr:full":"198 Webster St Monterey CA 93940",
    "addr:housenumber":"198",
    "addr:postcode":"93940",
    "addr:street":"Webster St",
    "iso:country":"US",
    "sg:address":"198 Webster St",
    "sg:city":"Monterey",
    "sg:classifiers":[
        {
            "category":"Retail",
            "subcategory":"Auto Repair",
            "type":"Services"
        }
    ],
    "sg:phone":"+1 831 649 1344",
    "sg:postcode":"93940",
    "sg:province":"CA",
    "sg:tags":[
        "brake"
    ],
    "wof:name":"Monterey Mercedes Svc Inc",
    "wof:placetype":"venue"
},
  "geometry": {"coordinates":[-121.894423,36.595982],"type":"Point"}
}