{
  "type": "Feature",
  "properties": {
    "iso:country":"US",
    "sg:address":"127 Jewell St",
    "sg:city":"Santa Cruz",
    "sg:classifiers":[
        {
            "category":"Health Services",
            "subcategory":"Health Practitioner",
            "type":"Services"
        }
    ],
    "sg:phone":"+1 831 426 1778",
    "sg:postcode":"95060",
    "sg:province":"CA",
    "sg:tags":[
        "psychologist"
    ],
    "wof:name":"A Angst-Net For Therapy",
    "wof:placetype":"venue"
},
  "geometry": {"coordinates":[-122.024818,36.987503],"type":"Point"}
}