{
  "type": "Feature",
  "properties": {
    "addr:full":"16264 Church St Morgan Hill CA 95037",
    "addr:housenumber":"16264",
    "addr:postcode":"95037",
    "addr:street":"Church St",
    "iso:country":"US",
    "sg:address":"16264 Church St",
    "sg:city":"Morgan Hill",
    "sg:classifiers":[
        {
            "category":"Social Services",
            "type":"Services"
        }
    ],
    "sg:phone":"+1 408 779 2113",
    "sg:postcode":"95037",
    "sg:province":"CA",
    "sg:tags":[
        "counseling"
    ],
    "wof:name":"Community Solutions",
    "wof:placetype":"venue"
},
  "geometry": {"coordinates":[-121.64594099999999,37.121629],"type":"Point"}
}