{
  "type": "Feature",
  "properties": {
    "iso:country":"US",
    "sg:address":"11980 San Vicente Blvd",
    "sg:city":"Los Angeles",
    "sg:classifiers":[
        {
            "category":"Real Estate",
            "subcategory":"Real Estate Agent",
            "type":"Services"
        }
    ],
    "sg:phone":"+1 310 820 5768",
    "sg:postcode":"90049",
    "sg:province":"CA",
    "sg:tags":[
        "management"
    ],
    "wof:name":"Brentwood Plaza",
    "wof:placetype":"venue"
},
  "geometry": {"coordinates":[-118.47092600000001,34.052415],"type":"Point"}
}