{
  "type": "Feature",
  "properties": {
    "addr:full":"2815 Los Flores Blvd Lynwood CA 90262",
    "addr:housenumber":"2815",
    "addr:postcode":"90262",
    "addr:street":"Los Flores Blvd",
    "iso:country":"US",
    "sg:address":"2815 Los Flores Blvd",
    "sg:city":"Lynwood",
    "sg:classifiers":[
        {
            "category":"Home & Garden",
            "subcategory":"Home Furnishings",
            "type":"Retail Goods"
        }
    ],
    "sg:phone":"+1 310 603 9344",
    "sg:postcode":"90262",
    "sg:province":"CA",
    "sg:tags":[
        "lighting",
        "fixture"
    ],
    "wof:name":"Pacific Lighting & Standards",
    "wof:placetype":"venue"
},
  "geometry": {"coordinates":[-118.220732,33.932734],"type":"Point"}
}