{
  "type": "Feature",
  "properties": {
    "addr:full":"9188 E Shaw Ave Clovis CA 93619",
    "addr:housenumber":"9188",
    "addr:postcode":"93619",
    "addr:street":"E Shaw Ave",
    "iso:country":"US",
    "sg:address":"9188 E Shaw Ave",
    "sg:city":"Clovis",
    "sg:classifiers":[
        {
            "category":"Manufacturing",
            "subcategory":"Tools & Machinery",
            "type":"Manufacturing & Wholesale Goods"
        },
        {
            "category":"Home & Garden",
            "subcategory":"Hardware",
            "type":"Retail Goods"
        }
    ],
    "sg:phone":"+1 559 299 6745",
    "sg:postcode":"93619",
    "sg:province":"CA",
    "sg:tags":[
        "pumps-wholesale",
        "filtration",
        "purification",
        "water",
        "equipment",
        "manufacturer"
    ],
    "wof:name":"The Montgomery Company",
    "wof:placetype":"venue"
},
  "geometry": {"coordinates":[-119.62347,36.816549],"type":"Point"}
}