{
  "type": "Feature",
  "properties": {
    "addr:full":"3753 Mission Ave Oceanside CA 92057",
    "addr:housenumber":"3753",
    "addr:postcode":"92057",
    "addr:street":"Mission Ave",
    "iso:country":"US",
    "sg:address":"3753 Mission Ave",
    "sg:city":"Oceanside",
    "sg:classifiers":[
        {
            "category":"Personal",
            "subcategory":"Beauty Salon",
            "type":"Services"
        }
    ],
    "sg:phone":"+1 760 439 3331",
    "sg:postcode":"92057",
    "sg:province":"CA",
    "wof:name":"Attitudez",
    "wof:placetype":"venue"
},
  "geometry": {"coordinates":[-117.331462,33.225349],"type":"Point"}
}