{
  "type": "Feature",
  "properties": {
    "addr:full":"125 S 6th St Brawley CA 92227",
    "addr:housenumber":"125",
    "addr:postcode":"92227",
    "addr:street":"S 6Th St",
    "iso:country":"US",
    "sg:address":"125 S 6th St",
    "sg:city":"Brawley",
    "sg:classifiers":[
        {
            "category":"Shopping",
            "subcategory":"Jewelry",
            "type":"Retail Goods"
        }
    ],
    "sg:phone":"+1 760 351 1747",
    "sg:postcode":"92227",
    "sg:province":"CA",
    "sg:tags":[
        "jeweler"
    ],
    "wof:name":"Taller De Joyeria Cecy",
    "wof:placetype":"venue"
},
  "geometry": {"coordinates":[-115.532107,32.978368],"type":"Point"}
}