{
  "type": "Feature",
  "properties": {
    "iso:country":"US",
    "sg:address":"8901 Melrose Avenue",
    "sg:city":"West Hollywood",
    "sg:classifiers":[
        {
            "category":"Retail",
            "subcategory":"Laundry & Dry Cleaning",
            "type":"Services"
        }
    ],
    "sg:phone":"+1 310 274 9073",
    "sg:postcode":"90069",
    "sg:province":"CA",
    "wof:name":"Leonard's",
    "wof:placetype":"venue"
},
  "geometry": {"coordinates":[-118.386841,34.080688],"type":"Point"}
}