{
  "type": "Feature",
  "properties": {
    "addr:full":"1251 E Dyer Rd Ste 120 Santa Ana CA 92705",
    "addr:housenumber":"1251",
    "addr:postcode":"92705",
    "addr:street":"E Dyer Rd Ste 120",
    "iso:country":"US",
    "sg:address":"1251 E Dyer Rd Ste 120",
    "sg:city":"Santa Ana",
    "sg:classifiers":[
        {
            "category":"Professional",
            "subcategory":"Lawyer & Legal Services",
            "type":"Services"
        }
    ],
    "sg:phone":"+1 714 544 5193",
    "sg:postcode":"92705",
    "sg:province":"CA",
    "wof:name":"Rimel & Nichols LLP",
    "wof:placetype":"venue"
},
  "geometry": {"coordinates":[-117.855639,33.708807],"type":"Point"}
}