{
  "type": "Feature",
  "properties": {
    "addr:full":"47 Oakvale Ave Berkeley CA 94705",
    "addr:housenumber":"47",
    "addr:postcode":"94705",
    "addr:street":"Oakvale Ave",
    "iso:country":"US",
    "sg:address":"47 Oakvale Ave",
    "sg:city":"Berkeley",
    "sg:classifiers":[
        {
            "category":"Building & Trades",
            "subcategory":"Construction",
            "type":"Services"
        }
    ],
    "sg:phone":"+1 510 841 1951",
    "sg:postcode":"94705",
    "sg:province":"CA",
    "sg:tags":[
        "wallcoverings-installation",
        "wallpaper"
    ],
    "wof:name":"Hanging Stick",
    "wof:placetype":"venue"
},
  "geometry": {"coordinates":[-122.246651,37.855276],"type":"Point"}
}