{
  "type": "Feature",
  "properties": {
    "iso:country":"US",
    "sg:address":"47341 Bayside Pkwy",
    "sg:city":"Fremont",
    "sg:classifiers":[
        {
            "category":"Wholesale",
            "subcategory":"Computers",
            "type":"Manufacturing & Wholesale Goods"
        }
    ],
    "sg:phone":"+1 510 249 1144",
    "sg:postcode":"94538",
    "sg:province":"CA",
    "wof:name":"Oryx Instruments Corp",
    "wof:placetype":"venue"
},
  "geometry": {"coordinates":[-121.935997,37.475101],"type":"Point"}
}