{
  "type": "Feature",
  "properties": {
    "iso:country":"US",
    "sg:address":"2750 Oregon Ct",
    "sg:city":"Torrance",
    "sg:classifiers":[
        {
            "category":"Professional",
            "type":"Services"
        }
    ],
    "sg:phone":"+1 310 328 1722",
    "sg:postcode":"90503",
    "sg:province":"CA",
    "sg:tags":[
        "establishment"
    ],
    "wof:name":"Kagura Shuzo USA Inc",
    "wof:placetype":"venue"
},
  "geometry": {"coordinates":[-118.33984599999999,33.846334],"type":"Point"}
}