{
  "type": "Feature",
  "properties": {
    "iso:country":"US",
    "sg:address":"549 El Camino Real",
    "sg:city":"Greenfield",
    "sg:classifiers":[
        {
            "category":"Place Of Worship",
            "subcategory":"Church",
            "type":"Public Place"
        },
        {
            "category":"Place Of Worship",
            "type":"Public Place"
        },
        {
            "category":"Organizations",
            "subcategory":"Religious Organization",
            "type":"Services"
        }
    ],
    "sg:phone":"+1 831 674 2132",
    "sg:postcode":"93927",
    "sg:province":"CA",
    "sg:tags":[
        "god",
        "god-independent",
        "churches-assemblies"
    ],
    "wof:name":"First Assembly Of God Of Greenfield Inc",
    "wof:placetype":"venue"
},
  "geometry": {"coordinates":[-121.249908,36.328511],"type":"Point"}
}