{
  "type": "Feature",
  "properties": {
    "iso:country":"US",
    "sg:address":"590 Market St",
    "sg:city":"San Francisco",
    "sg:classifiers":[
        {
            "category":"Banks & Credit Unions",
            "subcategory":"Investment Brokerage",
            "type":"Services"
        }
    ],
    "sg:phone":"+1 415 391 1575",
    "sg:postcode":"94104",
    "sg:province":"CA",
    "wof:name":"Citicorp",
    "wof:placetype":"venue"
},
  "geometry": {"coordinates":[-122.40145,37.789328],"type":"Point"}
}