{
  "type": "Feature",
  "properties": {
    "addr:full":"1514 Anacapa St Santa Barbara CA 93101",
    "addr:housenumber":"1514",
    "addr:postcode":"93101",
    "addr:street":"Anacapa St",
    "iso:country":"US",
    "sg:address":"1514 Anacapa St",
    "sg:city":"Santa Barbara",
    "sg:classifiers":[
        {
            "category":"Professional",
            "subcategory":"Lawyer & Legal Services",
            "type":"Services"
        }
    ],
    "sg:phone":"+1 805 569 2223",
    "sg:postcode":"93101",
    "sg:province":"CA",
    "sg:tags":[
        "attorney"
    ],
    "wof:name":"Martin Cohn & Assoc",
    "wof:placetype":"venue"
},
  "geometry": {"coordinates":[-119.707264,34.427345],"type":"Point"}
}