{
  "type": "Feature",
  "properties": {
    "addr:full":"4325 Etiwanda Ave Mira Loma CA 91752",
    "addr:housenumber":"4325",
    "addr:postcode":"91752",
    "addr:street":"Etiwanda Ave",
    "iso:country":"US",
    "sg:address":"4325 Etiwanda Ave",
    "sg:city":"Mira Loma",
    "sg:classifiers":[
        {
            "category":"Wholesale",
            "subcategory":"Hardware",
            "type":"Manufacturing & Wholesale Goods"
        }
    ],
    "sg:phone":"+1 951 685 2086",
    "sg:postcode":"91752",
    "sg:province":"CA",
    "sg:tags":[
        "air",
        "parts",
        "conditioning",
        "supply"
    ],
    "sg:website":"www.msihvac.com",
    "wof:name":"Material Supply",
    "wof:placetype":"venue"
},
  "geometry": {"coordinates":[-117.524517,34.010159],"type":"Point"}
}