{
  "type": "Feature",
  "properties": {
    "addr:full":"2270 Fair Oaks Boulevard Sacramento CA 95825",
    "addr:housenumber":"2270",
    "addr:postcode":"95825",
    "addr:street":"Fair Oaks Boulevard",
    "iso:country":"US",
    "sg:address":"2270 Fair Oaks Boulevard",
    "sg:city":"Sacramento",
    "sg:classifiers":[
        {
            "category":"Retail",
            "subcategory":"Auto Repair",
            "type":"Services"
        },
        {
            "category":"Government",
            "subcategory":"Office",
            "type":"Public Place"
        }
    ],
    "sg:phone":"+1 916 922 6653",
    "sg:postcode":"95825",
    "sg:province":"CA",
    "sg:tags":[
        "smog",
        "check"
    ],
    "wof:name":"Shell Service Stations",
    "wof:placetype":"venue"
},
  "geometry": {"coordinates":[-121.411546,38.574156],"type":"Point"}
}