{
  "type": "Feature",
  "properties": {
    "iso:country":"US",
    "sg:address":"1101 Luneta Plz",
    "sg:city":"Santa Barbara",
    "sg:classifiers":[
        {
            "category":"Wholesale",
            "subcategory":"Furniture",
            "type":"Manufacturing & Wholesale Goods"
        }
    ],
    "sg:phone":"+1 607 262 4648",
    "sg:postcode":"93109",
    "sg:province":"CA",
    "wof:name":"Jadora LLC",
    "wof:placetype":"venue"
},
  "geometry": {"coordinates":[-119.703487,34.399975],"type":"Point"}
}