{
  "type": "Feature",
  "properties": {
    "addr:full":"790 E Colorado Blvd Pasadena CA 91101",
    "addr:housenumber":"790",
    "addr:postcode":"91101",
    "addr:street":"E Colorado Blvd",
    "iso:country":"US",
    "sg:address":"790 E Colorado Blvd",
    "sg:city":"Pasadena",
    "sg:classifiers":[
        {
            "category":"Professional",
            "subcategory":"Lawyer & Legal Services",
            "type":"Services"
        }
    ],
    "sg:phone":"+1 626 683 8750",
    "sg:postcode":"91101",
    "sg:province":"CA",
    "sg:website":"www.younglawoffices.com",
    "wof:name":"Law Offices of Young & Young",
    "wof:placetype":"venue"
},
  "geometry": {"coordinates":[-118.13400300000001,34.145901],"type":"Point"}
}