{
  "type": "Feature",
  "properties": {
    "addr:full":"1169 Wellington St Oakland CA 94602",
    "addr:housenumber":"1169",
    "addr:postcode":"94602",
    "addr:street":"Wellington St",
    "iso:country":"US",
    "sg:address":"1169 Wellington St",
    "sg:city":"Oakland",
    "sg:classifiers":[
        {
            "category":"Retail",
            "subcategory":"Portrait Studio",
            "type":"Services"
        }
    ],
    "sg:phone":"+1 510 530 5168",
    "sg:postcode":"94602",
    "sg:province":"CA",
    "sg:tags":[
        "photographer"
    ],
    "wof:name":"Cherry Kim Photography",
    "wof:placetype":"venue"
},
  "geometry": {"coordinates":[-122.223851,37.80925],"type":"Point"}
}