{
  "type": "Feature",
  "properties": {
    "iso:country":"US",
    "sg:address":"8413 Pioneer Blvd",
    "sg:city":"Whittier",
    "sg:classifiers":[
        {
            "category":"Personal",
            "subcategory":"Barber",
            "type":"Services"
        }
    ],
    "sg:phone":"+1 562 692 5889",
    "sg:postcode":"90606",
    "sg:province":"CA",
    "wof:name":"Day & Night Barber Shop",
    "wof:placetype":"venue"
},
  "geometry": {"coordinates":[-118.08200100000001,33.9678],"type":"Point"}
}