{
  "type": "Feature",
  "properties": {
    "addr:full":"2 Belshaw St Antioch CA 94509",
    "addr:housenumber":"2",
    "addr:postcode":"ca 94509",
    "addr:street":"Belshaw St",
    "iso:country":"US",
    "sg:address":"2 Belshaw St",
    "sg:city":"Antioch",
    "sg:classifiers":[
        {
            "category":"Professional",
            "subcategory":"Business Services",
            "type":"Services"
        }
    ],
    "sg:phone":"+1 925 753 5645",
    "sg:postcode":"94509",
    "sg:province":"CA",
    "wof:name":"National Assoc Hispanic REA",
    "wof:placetype":"venue"
},
  "geometry": {"coordinates":[-121.80512400000001,38.001958],"type":"Point"}
}