{
  "type": "Feature",
  "properties": {
    "addr:full":"10000 Stockdale Hwy Bakersfield CA 93311",
    "addr:housenumber":"10000",
    "addr:postcode":"93311",
    "addr:street":"Stockdale Hwy",
    "iso:country":"US",
    "sg:address":"10000 Stockdale Hwy",
    "sg:city":"Bakersfield",
    "sg:classifiers":[
        {
            "category":"Real Estate",
            "subcategory":"Real Estate Agent",
            "type":"Services"
        }
    ],
    "sg:phone":"+1 661 631 3800",
    "sg:postcode":"93311",
    "sg:province":"CA",
    "sg:website":"www.tingey.com",
    "wof:name":"Colliers Tingey Intl",
    "wof:placetype":"venue"
},
  "geometry": {"coordinates":[-119.11482599999999,35.353279],"type":"Point"}
}