{
  "type": "Feature",
  "properties": {
    "iso:country":"US",
    "sg:address":"1706 Meadow Ave",
    "sg:city":"Stockton",
    "sg:classifiers":[
        {
            "category":"Building & Trades",
            "subcategory":"Construction",
            "type":"Services"
        }
    ],
    "sg:phone":"+1 209 951 6293",
    "sg:postcode":"95207",
    "sg:province":"CA",
    "sg:tags":[
        "fence",
        "contractor"
    ],
    "wof:name":"Fence Dr",
    "wof:placetype":"venue"
},
  "geometry": {"coordinates":[-121.334424,38.015946],"type":"Point"}
}