{
  "type": "Feature",
  "properties": {
    "iso:country":"US",
    "sg:address":"101 Rowland Way",
    "sg:city":"Novato",
    "sg:classifiers":[
        {
            "category":"Building & Trades",
            "subcategory":"Construction",
            "type":"Services"
        }
    ],
    "sg:phone":"+1 415 897 8794",
    "sg:postcode":"94945",
    "sg:province":"CA",
    "sg:tags":[
        "contractor"
    ],
    "wof:name":"Harris & Assoc",
    "wof:placetype":"venue"
},
  "geometry": {"coordinates":[-122.559365,38.097733],"type":"Point"}
}