{
  "type": "Feature",
  "properties": {
    "addr:full":"7392 Count Cir Huntington Beach CA 92647",
    "addr:housenumber":"7392",
    "addr:postcode":"92647",
    "addr:street":"Count Cir",
    "iso:country":"US",
    "sg:address":"7392 Count Cir",
    "sg:city":"Huntington Beach",
    "sg:classifiers":[
        {
            "category":"Autos & Motor Vehicles",
            "subcategory":"Recreational Vehicle Sales",
            "type":"Retail Goods"
        }
    ],
    "sg:phone":"+1 714 596 4461",
    "sg:postcode":"92647",
    "sg:province":"CA",
    "sg:tags":[
        "canopy",
        "shell",
        "truck",
        "cap"
    ],
    "sg:website":"www.dynatrac.com",
    "wof:name":"Dynatrac Products Co",
    "wof:placetype":"venue"
},
  "geometry": {"coordinates":[-117.998953,33.720141],"type":"Point"}
}