{
  "type": "Feature",
  "properties": {
    "addr:full":"7200 Saltgrass Way Elk Grove CA 95758",
    "addr:postcode":"7200;95758",
    "addr:street":"Saltgrass Way",
    "iso:country":"US",
    "sg:address":"7200 Saltgrass Way",
    "sg:city":"Elk Grove",
    "sg:classifiers":[
        {
            "category":"Professional",
            "subcategory":"Advertising",
            "type":"Services"
        }
    ],
    "sg:phone":"+1 916 684 0171",
    "sg:postcode":"95758",
    "sg:province":"CA",
    "sg:tags":[
        "agency",
        "specialty",
        "mfg"
    ],
    "wof:name":"Zot Promotions",
    "wof:placetype":"venue"
},
  "geometry": {"coordinates":[-121.42089199999999,38.414713],"type":"Point"}
}