{
  "type": "Feature",
  "properties": {
    "iso:country":"US",
    "sg:address":"1707 E Thompson Blvd",
    "sg:city":"Ventura",
    "sg:classifiers":[
        {
            "category":"Building & Trades",
            "subcategory":"Plumbing",
            "type":"Services"
        }
    ],
    "sg:phone":"+1 805 648 6933",
    "sg:postcode":"93001",
    "sg:province":"CA",
    "sg:tags":[
        "plumbing",
        "contractor"
    ],
    "wof:name":"Noyes Plumbing & Heating",
    "wof:placetype":"venue"
},
  "geometry": {"coordinates":[-119.276093,34.275634],"type":"Point"}
}