{
  "type": "Feature",
  "properties": {
    "iso:country":"US",
    "sg:address":"2617 W Woodland Dr",
    "sg:city":"Anaheim",
    "sg:classifiers":[
        {
            "category":"Wholesale",
            "subcategory":"Construction Materials",
            "type":"Manufacturing & Wholesale Goods"
        },
        {
            "category":"Home & Garden",
            "subcategory":"Building Materials",
            "type":"Retail Goods"
        },
        {
            "category":"Utilities",
            "subcategory":"Natural Gas",
            "type":"Services"
        }
    ],
    "sg:phone":"+1 714 821 5400",
    "sg:postcode":"92801",
    "sg:province":"CA",
    "sg:tags":[
        "equipment",
        "marble-natural",
        "stone",
        "masonry",
        "supply"
    ],
    "sg:website":"http://www.natural-stoneresources.com",
    "wof:name":"Natural Stone Resources",
    "wof:placetype":"venue"
},
  "geometry": {"coordinates":[-117.976985,33.84918],"type":"Point"}
}