{
  "type": "Feature",
  "properties": {
    "iso:country":"US",
    "sg:address":"7880 Walerga Rd",
    "sg:city":"Antelope",
    "sg:classifiers":[
        {
            "category":"Retail",
            "subcategory":"Auto Repair",
            "type":"Services"
        }
    ],
    "sg:phone":"+1 916 729 1339",
    "sg:postcode":"95843",
    "sg:province":"CA",
    "sg:tags":[
        "brake"
    ],
    "wof:name":"Les Schwab Tire Ctr",
    "wof:placetype":"venue"
},
  "geometry": {"coordinates":[-121.36438,38.712884],"type":"Point"}
}