{
  "type": "Feature",
  "properties": {
    "addr:full":"990 Arroyo Dr South Pasadena CA 91030",
    "addr:housenumber":"990",
    "addr:postcode":"91030",
    "addr:street":"Arroyo Dr",
    "iso:country":"US",
    "sg:address":"990 Arroyo Dr",
    "sg:city":"South Pasadena",
    "sg:classifiers":[
        {
            "category":"Personal",
            "subcategory":"Beauty Salon",
            "type":"Services"
        }
    ],
    "sg:phone":"+1 626 403 8918",
    "sg:postcode":"91030",
    "sg:province":"CA",
    "wof:name":"Chenice Beverly Hills",
    "wof:placetype":"venue"
},
  "geometry": {"coordinates":[-118.169139,34.114075],"type":"Point"}
}