{
  "type": "Feature",
  "properties": {
    "iso:country":"US",
    "sg:address":"1336 Main St",
    "sg:city":"Ramona",
    "sg:classifiers":[
        {
            "category":"Personal",
            "subcategory":"Beauty Salon",
            "type":"Services"
        }
    ],
    "sg:phone":"+1 760 789 3750",
    "sg:postcode":"92065",
    "sg:province":"CA",
    "sg:tags":[
        "hair",
        "stylist"
    ],
    "wof:name":"Mane Event",
    "wof:placetype":"venue"
},
  "geometry": {"coordinates":[-116.873932,33.039071],"type":"Point"}
}