{
  "type": "Feature",
  "properties": {
    "addr:full":"933 5th Avenue San Diego CA 92101",
    "addr:housenumber":"933",
    "addr:postcode":"92101",
    "addr:street":"5Th Avenue",
    "iso:country":"US",
    "sg:address":"933 5th Avenue",
    "sg:city":"San Diego",
    "sg:classifiers":[
        {
            "category":"Shopping",
            "subcategory":"Jewelry",
            "type":"Retail Goods"
        },
        {
            "category":"Shopping",
            "subcategory":"Pawn Shop",
            "type":"Retail Goods"
        }
    ],
    "sg:phone":"+1 619 234 5450",
    "sg:postcode":"92101",
    "sg:province":"CA",
    "wof:name":"San Diego Jewelry & Loan",
    "wof:placetype":"venue"
},
  "geometry": {"coordinates":[-117.160282,32.715092],"type":"Point"}
}