{
  "type": "Feature",
  "properties": {
    "addr:full":"528 Green St San Francisco CA 94133",
    "addr:housenumber":"528",
    "addr:postcode":"94133",
    "addr:street":"Green St",
    "iso:country":"US",
    "sg:address":"528 Green St",
    "sg:city":"San Francisco",
    "sg:classifiers":[
        {
            "category":"Manufacturing",
            "subcategory":"Printing",
            "type":"Manufacturing & Wholesale Goods"
        }
    ],
    "sg:phone":"+1 415 391 0730",
    "sg:postcode":"94133",
    "sg:province":"CA",
    "sg:tags":[
        "lithographic",
        "commercial"
    ],
    "wof:name":"Printing Place",
    "wof:placetype":"venue"
},
  "geometry": {"coordinates":[-122.407698,37.799664],"type":"Point"}
}