{
  "type": "Feature",
  "properties": {
    "addr:full":"250 N Golden Circle Dr Ste 110 Santa Ana CA 92705",
    "addr:housenumber":"250",
    "addr:postcode":"92705",
    "addr:street":"N Golden Circle Dr Ste 110",
    "iso:country":"US",
    "sg:address":"250 N Golden Circle Dr Ste 110",
    "sg:city":"Santa Ana",
    "sg:classifiers":[
        {
            "category":"Professional",
            "subcategory":"Lawyer & Legal Services",
            "type":"Services"
        }
    ],
    "sg:phone":"+1 714 836 6711",
    "sg:postcode":"92705",
    "sg:province":"CA",
    "wof:name":"Law Offices of Krishna Gulaya",
    "wof:placetype":"venue"
},
  "geometry": {"coordinates":[-117.817001,33.759998],"type":"Point"}
}