{
  "type": "Feature",
  "properties": {
    "iso:country":"US",
    "sg:address":"1812 N Chester Ave",
    "sg:city":"Bakersfield",
    "sg:classifiers":[
        {
            "category":"Shopping",
            "subcategory":"Stationery & Office Supplies",
            "type":"Retail Goods"
        }
    ],
    "sg:phone":"+1 661 399 4333",
    "sg:postcode":"93308",
    "sg:province":"CA",
    "wof:name":"Ken's Office Supply",
    "wof:placetype":"venue"
},
  "geometry": {"coordinates":[-119.02113,35.423088],"type":"Point"}
}