{
  "type": "Feature",
  "properties": {
    "addr:full":"1049 el Monte Ave Mountain View CA 94040",
    "addr:housenumber":"1049",
    "addr:postcode":"94040",
    "addr:street":"El Monte Ave",
    "iso:country":"US",
    "sg:address":"1049 el Monte Ave",
    "sg:city":"Mountain View",
    "sg:classifiers":[
        {
            "category":"Sports & Exercise",
            "subcategory":"Gym",
            "type":"Entertainment"
        }
    ],
    "sg:phone":"+1 650 938 7223",
    "sg:postcode":"94040",
    "sg:province":"CA",
    "sg:tags":[
        "club",
        "health",
        "studio",
        "gymnasium"
    ],
    "wof:name":"Pace Yourself Fitness Studio",
    "wof:placetype":"venue"
},
  "geometry": {"coordinates":[-122.09579100000001,37.390367],"type":"Point"}
}