{
  "type": "Feature",
  "properties": {
    "iso:country":"US",
    "sg:address":"3020 Fredricksburg Way",
    "sg:city":"Modesto",
    "sg:classifiers":[
        {
            "category":"Farming",
            "subcategory":"Farm & Veterinary Services",
            "type":"Manufacturing & Wholesale Goods"
        }
    ],
    "sg:phone":"+1 209 529 6785",
    "sg:postcode":"95355",
    "sg:province":"CA",
    "sg:tags":[
        "livestock"
    ],
    "wof:name":"San Jnquin Dar Herd Imprv Assn",
    "wof:placetype":"venue"
},
  "geometry": {"coordinates":[-120.935501,37.659504],"type":"Point"}
}