{
  "type": "Feature",
  "properties": {
    "addr:full":"41 Snapdragon Irvine CA 92604",
    "addr:housenumber":"41",
    "addr:postcode":"92604",
    "addr:street":"Snapdragon",
    "iso:country":"US",
    "sg:address":"41 Snapdragon",
    "sg:city":"Irvine",
    "sg:classifiers":[
        {
            "category":"Professional",
            "type":"Services"
        }
    ],
    "sg:phone":"+1 949 559 0409",
    "sg:postcode":"92604",
    "sg:province":"CA",
    "wof:name":"Point of Art",
    "wof:placetype":"venue"
},
  "geometry": {"coordinates":[-117.785619,33.691913],"type":"Point"}
}