{
  "type": "Feature",
  "properties": {
    "addr:full":"3203 Overland Ave Los Angeles CA 90034",
    "addr:housenumber":"3203",
    "addr:postcode":"90034",
    "addr:street":"Overland Ave",
    "iso:country":"US",
    "sg:address":"3203 Overland Ave",
    "sg:city":"Los Angeles",
    "sg:classifiers":[
        {
            "category":"Manufacturing",
            "subcategory":"Jewelry",
            "type":"Manufacturing & Wholesale Goods"
        }
    ],
    "sg:phone":"+1 310 838 1019",
    "sg:postcode":"90034",
    "sg:province":"CA",
    "sg:tags":[
        "precious",
        "metal",
        "mfg"
    ],
    "wof:name":"Rasnick Designs",
    "wof:placetype":"venue"
},
  "geometry": {"coordinates":[-118.413342,34.026859],"type":"Point"}
}