{
  "type": "Feature",
  "properties": {
    "iso:country":"US",
    "sg:address":"3110 Rio Grande Dr",
    "sg:city":"Antioch",
    "sg:classifiers":[
        {
            "category":"Home & Garden",
            "subcategory":"Building Materials",
            "type":"Retail Goods"
        }
    ],
    "sg:phone":"+1 925 363 9612",
    "sg:postcode":"94509",
    "sg:province":"CA",
    "sg:tags":[
        "garage",
        "opener",
        "door"
    ],
    "sg:website":"http://www.deltadiablodoors.com",
    "wof:name":"Delta Diablo Door",
    "wof:placetype":"venue"
},
  "geometry": {"coordinates":[-121.82914100000001,37.9894],"type":"Point"}
}