{
  "type": "Feature",
  "properties": {
    "addr:full":"3141 Cahuenga Blvd W Los Angeles CA 90068",
    "addr:housenumber":"3141",
    "addr:postcode":"90068",
    "addr:street":"Cahuenga Blvd W",
    "iso:country":"US",
    "sg:address":"3141 Cahuenga Blvd W",
    "sg:city":"Los Angeles",
    "sg:classifiers":[
        {
            "category":"Arts & Performance",
            "subcategory":"Arts Center",
            "type":"Entertainment"
        }
    ],
    "sg:phone":"+1 323 851 7409",
    "sg:postcode":"90068",
    "sg:province":"CA",
    "sg:tags":[
        "performing"
    ],
    "wof:name":"916 Music Productions",
    "wof:placetype":"venue"
},
  "geometry": {"coordinates":[-118.346356,34.127418],"type":"Point"}
}