{
  "type": "Feature",
  "properties": {
    "addr:full":"560 Moraga Rd Moraga CA 94556",
    "addr:housenumber":"560",
    "addr:postcode":"94556",
    "addr:street":"Moraga Rd",
    "iso:country":"US",
    "sg:address":"560 Moraga Rd",
    "sg:city":"Moraga",
    "sg:classifiers":[
        {
            "category":"Restaurant",
            "type":"Food & Drink"
        }
    ],
    "sg:phone":"+1 925 376 3431",
    "sg:postcode":"94556",
    "sg:province":"CA",
    "sg:tags":[
        "parlor",
        "ice",
        "cream"
    ],
    "wof:name":"Loards Ice Cream Of Moraga",
    "wof:placetype":"venue"
},
  "geometry": {"coordinates":[-122.124799,37.855484],"type":"Point"}
}