{
  "type": "Feature",
  "properties": {
    "addr:full":"1437 Columbus Ave Livermore CA 94550",
    "addr:housenumber":"1437",
    "addr:postcode":"94550",
    "addr:street":"Columbus Ave",
    "iso:country":"US",
    "sg:address":"1437 Columbus Ave",
    "sg:city":"Livermore",
    "sg:classifiers":[
        {
            "category":"Retail",
            "subcategory":"Repair Shop",
            "type":"Services"
        }
    ],
    "sg:phone":"+1 925 487 8418",
    "sg:postcode":"94550",
    "sg:province":"CA",
    "sg:tags":[
        "watch",
        "clock"
    ],
    "wof:name":"Quartzfix.Com",
    "wof:placetype":"venue"
},
  "geometry": {"coordinates":[-121.77628900000001,37.668011],"type":"Point"}
}