{
  "type": "Feature",
  "properties": {
    "addr:full":"8797 Humboldt Rd Forest Ranch CA 95942",
    "addr:housenumber":"8797",
    "addr:postcode":"95942",
    "addr:street":"Humboldt Rd",
    "iso:country":"US",
    "sg:address":"8797 Humboldt Rd",
    "sg:city":"Forest Ranch",
    "sg:classifiers":[
        {
            "category":"Autos & Motor Vehicles",
            "subcategory":"Automobile Sales",
            "type":"Retail Goods"
        }
    ],
    "sg:phone":"+1 530 873 6052",
    "sg:postcode":"95942",
    "sg:province":"CA",
    "sg:tags":[
        "snowmobile"
    ],
    "wof:name":"Butte Meadows Hillsiders",
    "wof:placetype":"venue"
},
  "geometry": {"coordinates":[-121.46738000000001,40.112793],"type":"Point"}
}