{
  "type": "Feature",
  "properties": {
    "addr:full":"2610 Mission St San Francisco CA 94110",
    "addr:housenumber":"2610",
    "addr:postcode":"94110",
    "addr:street":"Mission St",
    "iso:country":"US",
    "sg:address":"2610 Mission St",
    "sg:city":"San Francisco",
    "sg:classifiers":[
        {
            "category":"Home & Garden",
            "subcategory":"Home Furnishings",
            "type":"Retail Goods"
        }
    ],
    "sg:phone":"+1 415 643 4830",
    "sg:postcode":"94110",
    "sg:province":"CA",
    "sg:tags":[
        "linen"
    ],
    "sg:website":"www.annaslinens.com",
    "wof:name":"Anna's Linens",
    "wof:placetype":"venue"
},
  "geometry": {"coordinates":[-122.41868100000001,37.753995],"type":"Point"}
}