{
  "type": "Feature",
  "properties": {
    "iso:country":"US",
    "sg:address":"23721 Moulton Pkwy",
    "sg:city":"Laguna Hills",
    "sg:classifiers":[
        {
            "category":"Social Services",
            "type":"Services"
        }
    ],
    "sg:phone":"+1 949 380 0155",
    "sg:postcode":"92653",
    "sg:province":"CA",
    "wof:name":"Florence Sylvester Memorial Sr",
    "wof:placetype":"venue"
},
  "geometry": {"coordinates":[-117.73122499999999,33.617759],"type":"Point"}
}