{
  "type": "Feature",
  "properties": {
    "addr:full":"1315 Esplanade Chico CA 95926",
    "addr:housenumber":"1315",
    "addr:postcode":"95926",
    "addr:street":"Esplanade Chico",
    "iso:country":"US",
    "sg:address":"1315 Esplanade",
    "sg:city":"Chico",
    "sg:classifiers":[
        {
            "category":"Health Services",
            "subcategory":"Doctor",
            "type":"Services"
        }
    ],
    "sg:phone":"+1 530 332 9288",
    "sg:postcode":"95926",
    "sg:province":"CA",
    "sg:tags":[
        "physician",
        "surgeon"
    ],
    "wof:name":"Esplanade Women's Care",
    "wof:placetype":"venue"
},
  "geometry": {"coordinates":[-121.847917,39.740812],"type":"Point"}
}