{
  "type": "Feature",
  "properties": {
    "addr:full":"370 San Bruno Ave W Ste F San Bruno CA 94066",
    "addr:housenumber":"370",
    "addr:postcode":"94066",
    "addr:street":"San Bruno Ave W Ste F",
    "iso:country":"US",
    "sg:address":"370 San Bruno Ave W Ste F",
    "sg:city":"San Bruno",
    "sg:classifiers":[
        {
            "category":"Insurance",
            "subcategory":"Health Insurance",
            "type":"Services"
        }
    ],
    "sg:phone":"+1 650 588 8335",
    "sg:postcode":"94066",
    "sg:province":"CA",
    "sg:tags":[
        "market"
    ],
    "sg:website":"www.merryclinic.com",
    "wof:name":"Merry Clinic",
    "wof:placetype":"venue"
},
  "geometry": {"coordinates":[-122.414305,37.63005],"type":"Point"}
}