{
  "type": "Feature",
  "properties": {
    "iso:country":"US",
    "sg:address":"9358 W Whitesbridge Ave",
    "sg:city":"Fresno",
    "sg:classifiers":[
        {
            "category":"Manufacturing",
            "subcategory":"Metals",
            "type":"Manufacturing & Wholesale Goods"
        }
    ],
    "sg:phone":"+1 559 268 0684",
    "sg:postcode":"93706",
    "sg:province":"CA",
    "sg:tags":[
        "metalwork",
        "architectural",
        "mfg"
    ],
    "wof:name":"Rods Wrought Ironworks",
    "wof:placetype":"venue"
},
  "geometry": {"coordinates":[-119.958035,36.735157],"type":"Point"}
}