{
  "type": "Feature",
  "properties": {
    "addr:full":"9024 S Vermont Ave Los Angeles CA 90044",
    "addr:housenumber":"9024",
    "addr:postcode":"90044",
    "addr:street":"S Vermont Ave",
    "iso:country":"US",
    "sg:address":"9024 S Vermont Ave",
    "sg:city":"Los Angeles",
    "sg:classifiers":[
        {
            "category":"Government",
            "subcategory":"Office",
            "type":"Public Place"
        }
    ],
    "sg:phone":"+1 323 777 3454",
    "sg:postcode":"90044",
    "sg:province":"CA",
    "sg:tags":[
        "housing",
        "program"
    ],
    "wof:name":"La Urbn Lge Hd Strt",
    "wof:placetype":"venue"
},
  "geometry": {"coordinates":[-118.29153100000001,33.954784],"type":"Point"}
}