{
  "type": "Feature",
  "properties": {
    "addr:full":"1629 Hollenbeck Avenue Sunnyvale CA 94087",
    "addr:housenumber":"1629",
    "addr:postcode":"94087",
    "addr:street":"Hollenbeck Avenue",
    "iso:country":"US",
    "sg:address":"1629 Hollenbeck Avenue",
    "sg:city":"Sunnyvale",
    "sg:classifiers":[
        {
            "category":"Personal",
            "subcategory":"Nail Salon",
            "type":"Services"
        }
    ],
    "sg:phone":"+1 408 730 1116",
    "sg:postcode":"94087",
    "sg:province":"CA",
    "wof:name":"Nail Time",
    "wof:placetype":"venue"
},
  "geometry": {"coordinates":[-122.041313,37.340123],"type":"Point"}
}