{
  "type": "Feature",
  "properties": {
    "addr:full":"31033 Huntwood Ave Hayward CA 94544",
    "addr:postcode":"31033;94544",
    "addr:street":"Huntwood Ave",
    "iso:country":"US",
    "sg:address":"31033 Huntwood Ave",
    "sg:city":"Hayward",
    "sg:classifiers":[
        {
            "category":"Wholesale",
            "subcategory":"Electrical",
            "type":"Manufacturing & Wholesale Goods"
        }
    ],
    "sg:phone":"+1 510 477 5000",
    "sg:postcode":"94544",
    "sg:province":"CA",
    "sg:tags":[
        "assembler",
        "electronic",
        "parts"
    ],
    "sg:website":"www.ableco.com",
    "wof:name":"Able Electronics",
    "wof:placetype":"venue"
},
  "geometry": {"coordinates":[-122.054925,37.610283],"type":"Point"}
}