{
  "type": "Feature",
  "properties": {
    "iso:country":"US",
    "sg:address":"1325 Las Villas Way",
    "sg:city":"Escondido",
    "sg:classifiers":[
        {
            "category":"Health Services",
            "subcategory":"Nursing And Care Facility",
            "type":"Services"
        }
    ],
    "sg:phone":"+1 760 741 1047",
    "sg:postcode":"92026",
    "sg:province":"CA",
    "sg:tags":[
        "skilled",
        "intermediate"
    ],
    "wof:name":"Healthcare Group",
    "wof:placetype":"venue"
},
  "geometry": {"coordinates":[-117.094327,33.140237],"type":"Point"}
}