{
  "type": "Feature",
  "properties": {
    "addr:full":"2241 Lundy Ave San Jose CA 95131",
    "addr:housenumber":"2241",
    "addr:postcode":"95131",
    "addr:street":"Lundy Ave",
    "iso:country":"US",
    "sg:address":"2241 Lundy Ave",
    "sg:city":"San Jose",
    "sg:classifiers":[
        {
            "category":"Manufacturing",
            "subcategory":"Electronics",
            "type":"Manufacturing & Wholesale Goods"
        }
    ],
    "sg:phone":"+1 408 428 0123",
    "sg:postcode":"95131",
    "sg:province":"CA",
    "sg:tags":[
        "equipment",
        "electronic",
        "supply"
    ],
    "wof:name":"Peripheral Imaging Corp",
    "wof:placetype":"venue"
},
  "geometry": {"coordinates":[-121.89112,37.398178],"type":"Point"}
}