{
  "type": "Feature",
  "properties": {
    "addr:full":"1495 Lorraine Way Santa Rosa CA 95404",
    "addr:housenumber":"1495",
    "addr:postcode":"95404",
    "addr:street":"Lorraine Way",
    "iso:country":"US",
    "sg:address":"1495 Lorraine Way",
    "sg:city":"Santa Rosa",
    "sg:classifiers":[
        {
            "category":"Shopping",
            "subcategory":"Computers & Home Electronics",
            "type":"Retail Goods"
        }
    ],
    "sg:phone":"+1 707 573 3715",
    "sg:postcode":"95404",
    "sg:province":"CA",
    "wof:name":"Communication Integrators",
    "wof:placetype":"venue"
},
  "geometry": {"coordinates":[-122.72374000000001,38.516434],"type":"Point"}
}