{
  "type": "Feature",
  "properties": {
    "iso:country":"US",
    "sg:address":"37190 County Road 24",
    "sg:city":"Woodland",
    "sg:classifiers":[
        {
            "category":"Food & Beverages",
            "subcategory":"Farmers Market",
            "type":"Retail Goods"
        }
    ],
    "sg:phone":"+1 530 662 3012",
    "sg:postcode":"95695",
    "sg:province":"CA",
    "sg:tags":[
        "vegetable",
        "fruit",
        "shipper",
        "grower"
    ],
    "wof:name":"Don Beeman Farms",
    "wof:placetype":"venue"
},
  "geometry": {"coordinates":[-121.81659399999999,38.66324],"type":"Point"}
}