{
  "type": "Feature",
  "properties": {
    "addr:full":"3544 W Olympic Blvd Los Angeles CA 90019",
    "addr:housenumber":"3544",
    "addr:postcode":"90019",
    "addr:street":"W Olympic Blvd",
    "iso:country":"US",
    "sg:address":"3544 W Olympic Blvd",
    "sg:city":"Los Angeles",
    "sg:classifiers":[
        {
            "category":"Shopping",
            "subcategory":"Pharmacy",
            "type":"Retail Goods"
        }
    ],
    "sg:phone":"+1 323 733 5594",
    "sg:postcode":"90019",
    "sg:province":"CA",
    "sg:tags":[
        "drugstore"
    ],
    "wof:name":"Shyn's Pharmacy",
    "wof:placetype":"venue"
},
  "geometry": {"coordinates":[-118.316002,34.052502],"type":"Point"}
}