{
  "type": "Feature",
  "properties": {
    "iso:country":"US",
    "sg:address":"14410 S Saint Andrews Pl",
    "sg:city":"Gardena",
    "sg:classifiers":[
        {
            "category":"Autos & Motor Vehicles",
            "subcategory":"Automobile Sales",
            "type":"Retail Goods"
        }
    ],
    "sg:phone":"+1 310 527 7155",
    "sg:postcode":"90249",
    "sg:province":"CA",
    "sg:tags":[
        "classic"
    ],
    "wof:name":"J D Rod's",
    "wof:placetype":"venue"
},
  "geometry": {"coordinates":[-118.31132100000001,33.900207],"type":"Point"}
}