{
  "type": "Feature",
  "properties": {
    "iso:country":"US",
    "sg:address":"122 Grant St",
    "sg:city":"Calexico",
    "sg:classifiers":[
        {
            "category":"Professional",
            "subcategory":"Lawyer & Legal Services",
            "type":"Services"
        }
    ],
    "sg:phone":"+1 760 357 0599",
    "sg:postcode":"92231",
    "sg:province":"CA",
    "sg:tags":[
        "attorney"
    ],
    "wof:name":"Larry Dawson",
    "wof:placetype":"venue"
},
  "geometry": {"coordinates":[-115.500198,32.673945],"type":"Point"}
}