{
  "type": "Feature",
  "properties": {
    "iso:country":"US",
    "sg:address":"1592 Union St",
    "sg:city":"San Francisco",
    "sg:classifiers":[
        {
            "category":"Professional",
            "type":"Services"
        }
    ],
    "sg:phone":"+1 415 221 0345",
    "sg:postcode":"94123",
    "sg:province":"CA",
    "wof:name":"Neil Monnens",
    "wof:placetype":"venue"
},
  "geometry": {"coordinates":[-122.424418,37.798613],"type":"Point"}
}