{
  "type": "Feature",
  "properties": {
    "addr:full":"2801 Waterman Blvd Fairfield CA 94534",
    "addr:housenumber":"2801",
    "addr:postcode":"94534",
    "addr:street":"Waterman Blvd",
    "iso:country":"US",
    "sg:address":"2801 Waterman Blvd",
    "sg:city":"Fairfield",
    "sg:classifiers":[
        {
            "category":"Health Services",
            "subcategory":"Dentist",
            "type":"Services"
        }
    ],
    "sg:phone":"+1 707 429 0451",
    "sg:postcode":"94534",
    "sg:province":"CA",
    "wof:name":"Marc L Bowen Dds",
    "wof:placetype":"venue"
},
  "geometry": {"coordinates":[-122.061817,38.269485],"type":"Point"}
}