{
  "type": "Feature",
  "properties": {
    "addr:full":"1822 E 41st Place Los Angeles CA 90058",
    "addr:housenumber":"1822",
    "addr:postcode":"90058",
    "addr:street":"E 41St Place",
    "iso:country":"US",
    "sg:address":"1822 E 41st Place",
    "sg:city":"Los Angeles",
    "sg:classifiers":[
        {
            "category":"Shopping",
            "subcategory":"Clothing, Apparel, & Fashions",
            "type":"Retail Goods"
        }
    ],
    "sg:phone":"+1 323 234 0036",
    "sg:postcode":"90058",
    "sg:province":"CA",
    "sg:tags":[
        "clothing",
        "women's"
    ],
    "wof:name":"Symphony",
    "wof:placetype":"venue"
},
  "geometry": {"coordinates":[-118.240455,34.006913],"type":"Point"}
}