{
  "type": "Feature",
  "properties": {
    "addr:full":"3808 W Ave J Lancaster CA 93536",
    "addr:housenumber":"3808",
    "addr:postcode":"93536",
    "addr:street":"W Ave J",
    "iso:country":"US",
    "sg:address":"3808 W Ave J",
    "sg:city":"Lancaster",
    "sg:classifiers":[
        {
            "category":"Health Services",
            "subcategory":"Doctor",
            "type":"Services"
        }
    ],
    "sg:phone":"+1 661 273 5253",
    "sg:postcode":"93536",
    "sg:province":"CA",
    "sg:tags":[
        "dentist"
    ],
    "wof:name":"Paul Newman DDS",
    "wof:placetype":"venue"
},
  "geometry": {"coordinates":[-118.198686,34.689239],"type":"Point"}
}