{
  "type": "Feature",
  "properties": {
    "iso:country":"US",
    "sg:address":"15428 Civic Dr Ste. 300",
    "sg:city":"Victorville",
    "sg:classifiers":[
        {
            "category":"Professional",
            "subcategory":"Business Services",
            "type":"Services"
        },
        {
            "category":"Real Estate",
            "subcategory":"Architect",
            "type":"Services"
        }
    ],
    "sg:phone":"+1 760 245 9673",
    "sg:postcode":"92392",
    "sg:province":"CA",
    "sg:tags":[
        "building",
        "development",
        "product",
        "designer",
        "designers-industrial",
        "marketing",
        "commercial",
        "drafting",
        "design",
        "residential"
    ],
    "wof:name":"PA Design Associates, Inc.",
    "wof:placetype":"venue"
},
  "geometry": {"coordinates":[-117.32684500000001,34.509936],"type":"Point"}
}