{
  "type": "Feature",
  "properties": {
    "addr:full":"724 W Onstott Rd Yuba City CA 95991",
    "addr:housenumber":"724",
    "addr:postcode":"95991",
    "addr:street":"W Onstott Rd",
    "iso:country":"US",
    "sg:address":"724 W Onstott Rd",
    "sg:city":"Yuba City",
    "sg:classifiers":[
        {
            "category":"Restaurant",
            "type":"Food & Drink"
        }
    ],
    "sg:phone":"+1 530 674 8251",
    "sg:postcode":"95991",
    "sg:province":"CA",
    "wof:name":"Perko's Cafe",
    "wof:placetype":"venue"
},
  "geometry": {"coordinates":[-121.634975,39.136],"type":"Point"}
}