{
  "type": "Feature",
  "properties": {
    "addr:full":"1105 W Park Ave Redlands CA 92373",
    "addr:housenumber":"1105",
    "addr:postcode":"92373",
    "addr:street":"W Park Ave",
    "iso:country":"US",
    "sg:address":"1105 W Park Ave",
    "sg:city":"Redlands",
    "sg:classifiers":[
        {
            "category":"Real Estate",
            "subcategory":"Real Estate Agent",
            "type":"Services"
        }
    ],
    "sg:phone":"+1 909 798 3972",
    "sg:postcode":"92373",
    "sg:province":"CA",
    "sg:tags":[
        "management"
    ],
    "wof:name":"A-Tnt Property Management",
    "wof:placetype":"venue"
},
  "geometry": {"coordinates":[-117.198043,34.059161],"type":"Point"}
}