{
  "type": "Feature",
  "properties": {
    "addr:full":"PO Box 3427 Santa Clara CA 95055",
    "addr:housenumber":"po",
    "addr:postcode":"95055",
    "addr:street":"Box 3427",
    "iso:country":"US",
    "sg:address":"PO Box 3427",
    "sg:city":"Santa Clara",
    "sg:classifiers":[
        {
            "category":"Building & Trades",
            "subcategory":"Construction",
            "type":"Services"
        }
    ],
    "sg:phone":"+1 408 554 9315",
    "sg:postcode":"95055",
    "sg:province":"CA",
    "sg:tags":[
        "contractor"
    ],
    "wof:name":"Safeco Builders",
    "wof:placetype":"venue"
},
  "geometry": {"coordinates":[-121.97787599999999,37.344978],"type":"Point"}
}