{
  "type": "Feature",
  "properties": {
    "iso:country":"US",
    "sg:address":"2377 Northgate Blvd",
    "sg:city":"Sacramento",
    "sg:classifiers":[
        {
            "category":"Restaurant",
            "type":"Food & Drink"
        }
    ],
    "sg:phone":"+1 916 920 8640",
    "sg:postcode":"95833",
    "sg:province":"CA",
    "wof:name":"Five-Twenty Four Restaurant",
    "wof:placetype":"venue"
},
  "geometry": {"coordinates":[-121.475998,38.6101],"type":"Point"}
}