{
  "type": "Feature",
  "properties": {
    "addr:full":"730 S Hope St Los Angeles CA 90017",
    "addr:housenumber":"730",
    "addr:postcode":"90017",
    "addr:street":"S Hope St",
    "iso:country":"US",
    "sg:address":"730 S Hope St",
    "sg:city":"Los Angeles",
    "sg:classifiers":[
        {
            "category":"Organizations",
            "subcategory":"Religious Organization",
            "type":"Services"
        }
    ],
    "sg:phone":"+1 213 623 2185",
    "sg:postcode":"90017",
    "sg:province":"CA",
    "sg:tags":[
        "church"
    ],
    "wof:name":"3rd Christian Science Church",
    "wof:placetype":"venue"
},
  "geometry": {"coordinates":[-118.25862600000001,34.046953],"type":"Point"}
}