{
  "type": "Feature",
  "properties": {
    "addr:full":"25380 Marguerite Pkwy Ste D Mission Viejo CA 92692",
    "addr:housenumber":"25380",
    "addr:postcode":"92692",
    "addr:street":"Marguerite Pkwy Ste D",
    "iso:country":"US",
    "sg:address":"25380 Marguerite Pkwy Ste D",
    "sg:city":"Mission Viejo",
    "sg:classifiers":[
        {
            "category":"Restaurant",
            "type":"Food & Drink"
        }
    ],
    "sg:phone":"+1 949 855 6866",
    "sg:postcode":"92692",
    "sg:province":"CA",
    "sg:tags":[
        "italian"
    ],
    "wof:name":"Capriccio Italiano Restaurant",
    "wof:placetype":"venue"
},
  "geometry": {"coordinates":[-117.659176,33.59427],"type":"Point"}
}