{
  "type": "Feature",
  "properties": {
    "iso:country":"US",
    "sg:address":"8312 Garfield Ave",
    "sg:city":"Bell Gardens",
    "sg:classifiers":[
        {
            "category":"Government",
            "subcategory":"Office",
            "type":"Public Place"
        }
    ],
    "sg:phone":"+1 562 776 0311",
    "sg:postcode":"90201",
    "sg:province":"CA",
    "sg:tags":[
        "smog",
        "check"
    ],
    "wof:name":"A & R Test Only",
    "wof:placetype":"venue"
},
  "geometry": {"coordinates":[-118.160928,33.95544],"type":"Point"}
}