{
  "type": "Feature",
  "properties": {
    "addr:full":"910 W Wood St Willows CA 95988",
    "addr:housenumber":"910",
    "addr:postcode":"95988",
    "addr:street":"W Wood St",
    "iso:country":"US",
    "sg:address":"910 W Wood St",
    "sg:city":"Willows",
    "sg:classifiers":[
        {
            "category":"Professional",
            "subcategory":"Accounting & Tax Preparation",
            "type":"Services"
        }
    ],
    "sg:phone":"+1 530 934 8841",
    "sg:postcode":"95988",
    "sg:province":"CA",
    "sg:tags":[
        "accountant"
    ],
    "wof:name":"Roy R Seiler CPA",
    "wof:placetype":"venue"
},
  "geometry": {"coordinates":[-122.205637,39.524159],"type":"Point"}
}