{
  "type": "Feature",
  "properties": {
    "addr:full":"3063 N California St Burbank CA 91504",
    "addr:housenumber":"3063",
    "addr:postcode":"91504",
    "addr:street":"N California St",
    "iso:country":"US",
    "sg:address":"3063 N California St",
    "sg:city":"Burbank",
    "sg:classifiers":[
        {
            "category":"Manufacturing",
            "subcategory":"Metals",
            "type":"Manufacturing & Wholesale Goods"
        }
    ],
    "sg:phone":"+1 323 849 3151",
    "sg:postcode":"91504",
    "sg:province":"CA",
    "sg:tags":[
        "plating"
    ],
    "wof:name":"Magna Plating",
    "wof:placetype":"venue"
},
  "geometry": {"coordinates":[-118.345585,34.203839],"type":"Point"}
}