{
  "type": "Feature",
  "properties": {
    "addr:full":"11889 Valley View St Garden Grove CA 92845",
    "addr:housenumber":"11889",
    "addr:postcode":"92845",
    "addr:street":"Valley View St",
    "iso:country":"US",
    "sg:address":"11889 Valley View St",
    "sg:city":"Garden Grove",
    "sg:classifiers":[
        {
            "category":"Shopping",
            "type":"Retail Goods"
        }
    ],
    "sg:phone":"+1 714 895 4299",
    "sg:postcode":"92845",
    "sg:province":"CA",
    "wof:name":"Aloha 99",
    "wof:placetype":"venue"
},
  "geometry": {"coordinates":[-118.02860099999999,33.790025],"type":"Point"}
}