{
  "type": "Feature",
  "properties": {
    "iso:country":"US",
    "sg:address":"2201 Broadway",
    "sg:city":"Oakland",
    "sg:classifiers":[
        {
            "category":"Health Services",
            "subcategory":"Chiropractor",
            "type":"Services"
        }
    ],
    "sg:phone":"+1 510 832 2121",
    "sg:postcode":"94612",
    "sg:province":"CA",
    "sg:website":"www.tedsdc.com",
    "wof:name":"An Ted S DC",
    "wof:placetype":"venue"
},
  "geometry": {"coordinates":[-122.267583,37.811436],"type":"Point"}
}