{
  "type": "Feature",
  "properties": {
    "addr:full":"1604 Seacreek Way San Jose CA 95121",
    "addr:housenumber":"1604",
    "addr:postcode":"95121",
    "addr:street":"Seacreek Way",
    "iso:country":"US",
    "sg:address":"1604 Seacreek Way",
    "sg:city":"San Jose",
    "sg:classifiers":[
        {
            "category":"Wholesale",
            "subcategory":"Vending Machines",
            "type":"Manufacturing & Wholesale Goods"
        }
    ],
    "sg:phone":"+1 408 531 8516",
    "sg:postcode":"95121",
    "sg:province":"CA",
    "sg:tags":[
        "operator"
    ],
    "wof:name":"My Little Break Vending",
    "wof:placetype":"venue"
},
  "geometry": {"coordinates":[-121.812592,37.304343],"type":"Point"}
}