{
  "type": "Feature",
  "properties": {
    "addr:full":"5770 Ruffin Rd San Diego CA 92123",
    "addr:housenumber":"5770",
    "addr:postcode":"92123",
    "addr:street":"Ruffin Rd",
    "iso:country":"US",
    "sg:address":"5770 Ruffin Rd",
    "sg:city":"San Diego",
    "sg:classifiers":[
        {
            "category":"Communications",
            "subcategory":"Television Station",
            "type":"Services"
        }
    ],
    "sg:phone":"+1 858 576 1919",
    "sg:postcode":"92123",
    "sg:province":"CA",
    "sg:website":"www.mytv13.com",
    "wof:name":"MyTV 13",
    "wof:placetype":"venue"
},
  "geometry": {"coordinates":[-117.12783,32.838748],"type":"Point"}
}