{
  "type": "Feature",
  "properties": {
    "addr:full":"346 Ridgemont Ct Newbury Park CA 91320",
    "addr:housenumber":"346",
    "addr:postcode":"91320",
    "addr:street":"Ridgemont Ct",
    "iso:country":"US",
    "sg:address":"346 Ridgemont Ct",
    "sg:city":"Newbury Park",
    "sg:classifiers":[
        {
            "category":"Building & Trades",
            "subcategory":"Landscaping Services",
            "type":"Services"
        }
    ],
    "sg:phone":"+1 805 498 6551",
    "sg:postcode":"91320",
    "sg:province":"CA",
    "sg:tags":[
        "landscape"
    ],
    "wof:name":"Newbury Landscape Co",
    "wof:placetype":"venue"
},
  "geometry": {"coordinates":[-118.960594,34.172472],"type":"Point"}
}