{
  "type": "Feature",
  "properties": {
    "addr:full":"444 Cam del Rio S San Diego CA 92108",
    "addr:housenumber":"444",
    "addr:postcode":"92108",
    "addr:street":"Cam Del Rio S",
    "iso:country":"US",
    "sg:address":"444 Cam del Rio S",
    "sg:city":"San Diego",
    "sg:classifiers":[
        {
            "category":"Health Services",
            "subcategory":"Chiropractor",
            "type":"Services"
        }
    ],
    "sg:phone":"+1 619 688 2090",
    "sg:postcode":"92108",
    "sg:province":"CA",
    "wof:name":"Alan M Blum DC",
    "wof:placetype":"venue"
},
  "geometry": {"coordinates":[-117.154735,32.764251],"type":"Point"}
}