{
  "type": "Feature",
  "properties": {
    "addr:full":"4919 Lexington Ave Los Angeles CA 90029",
    "addr:housenumber":"4919",
    "addr:postcode":"90029",
    "addr:street":"Lexington Ave",
    "iso:country":"US",
    "sg:address":"4919 Lexington Ave",
    "sg:city":"Los Angeles",
    "sg:classifiers":[
        {
            "category":"Professional",
            "type":"Services"
        }
    ],
    "sg:phone":"+1 818 439 2428",
    "sg:postcode":"90029",
    "sg:province":"CA",
    "wof:name":"Cyberbros",
    "wof:placetype":"venue"
},
  "geometry": {"coordinates":[-118.297183,34.093486],"type":"Point"}
}