{
  "type": "Feature",
  "properties": {
    "addr:full":"5757 Lake Murray Blvd La Mesa CA 91942",
    "addr:housenumber":"5757",
    "addr:postcode":"91942",
    "addr:street":"Lake Murray Blvd",
    "iso:country":"US",
    "sg:address":"5757 Lake Murray Blvd",
    "sg:city":"La Mesa",
    "sg:classifiers":[
        {
            "category":"Wholesale",
            "subcategory":"Non-durable Goods",
            "type":"Manufacturing & Wholesale Goods"
        }
    ],
    "sg:phone":"+1 619 460 7531",
    "sg:postcode":"91942",
    "sg:province":"CA",
    "sg:tags":[
        "commercial",
        "design"
    ],
    "wof:name":"Fourever Beatles",
    "wof:placetype":"venue"
},
  "geometry": {"coordinates":[-117.027659,32.783549],"type":"Point"}
}