{
  "type": "Feature",
  "properties": {
    "addr:full":"2105 S Blosser Rd Santa Maria CA 93458",
    "addr:housenumber":"2105",
    "addr:postcode":"93458",
    "addr:street":"S Blosser Rd",
    "iso:country":"US",
    "sg:address":"2105 S Blosser Rd",
    "sg:city":"Santa Maria",
    "sg:classifiers":[
        {
            "category":"Manufacturing",
            "subcategory":"Electronics",
            "type":"Manufacturing & Wholesale Goods"
        }
    ],
    "sg:phone":"+1 805 928 4343",
    "sg:postcode":"93458",
    "sg:province":"CA",
    "sg:tags":[
        "voice",
        "command",
        "switching",
        "mfg"
    ],
    "sg:website":"www.quintron.com",
    "wof:name":"Quintron Systems Inc",
    "wof:placetype":"venue"
},
  "geometry": {"coordinates":[-120.453942,34.921837],"type":"Point"}
}