{
  "type": "Feature",
  "properties": {
    "addr:full":"8700 Beverly Blvd Los Angeles CA 90048",
    "addr:housenumber":"8700",
    "addr:postcode":"90048",
    "addr:street":"Beverly Blvd",
    "iso:country":"US",
    "sg:address":"8700 Beverly Blvd",
    "sg:city":"Los Angeles",
    "sg:classifiers":[
        {
            "category":"Health Services",
            "subcategory":"Hospital",
            "type":"Services"
        }
    ],
    "sg:phone":"+1 310 423 3277",
    "sg:postcode":"90048",
    "sg:province":"CA",
    "sg:website":"www.cedars-sinai.edu",
    "wof:name":"Cedars Sinai Medical Center",
    "wof:placetype":"venue"
},
  "geometry": {"coordinates":[-118.380116,34.07655],"type":"Point"}
}