{
  "type": "Feature",
  "properties": {
    "addr:city":"Los Angeles",
    "addr:full":"8700 Beverly Blvd Room 2416 Los Angeles, Ca 90048",
    "addr:house_number":"8700",
    "addr:housenumber":"8700",
    "addr:phone":"+1 310-423-3277",
    "addr:postcode":"90048",
    "addr:road":"Beverly Blvd",
    "addr:state":"CA",
    "addr:street":"Beverly Blvd",
    "addr:unit":"Room 2416",
    "iso:country":"US",
    "sg:address":"8700 Beverly Blvd",
    "sg:city":"Los Angeles",
    "sg:classifiers":[
        {
            "category":"Health Services",
            "subcategory":"Hospital",
            "type":"Services"
        }
    ],
    "sg:phone":"+1 310 423 3277",
    "sg:postcode":"90048",
    "sg:province":"CA",
    "sg:website":"www.cedars-sinai.edu",
    "wof:airports":[
        102527521,
        102527917,
        102531511,
        102532771,
        102533795
    ],
    "wof:name":"Art Collection At Cedars-Sinai",
    "wof:placetype":"venue"
},
  "geometry": {"coordinates":[-118.38,34.07654],"type":"Point"}
}