{
  "type": "Feature",
  "properties": {
    "addr:full":"438 E 1st St Los Angeles CA 90189",
    "addr:housenumber":"438",
    "addr:postcode":"90189",
    "addr:street":"E 1St St",
    "iso:country":"US",
    "sg:address":"438 E 1st St",
    "sg:city":"Los Angeles",
    "sg:classifiers":[
        {
            "category":"Arts & Performance",
            "subcategory":"Music",
            "type":"Entertainment"
        }
    ],
    "sg:postcode":"90189",
    "sg:province":"CA",
    "sg:tags":[
        "venue"
    ],
    "wof:name":"Brave Dog",
    "wof:placetype":"venue"
},
  "geometry": {"coordinates":[-118.238715,34.049116],"type":"Point"}
}