{
  "type": "Feature",
  "properties": {
    "iso:country":"US",
    "sg:address":"1912 Lincoln Blvd",
    "sg:city":"Santa Monica",
    "sg:classifiers":[
        {
            "category":"Food & Beverages",
            "subcategory":"Bakery",
            "type":"Retail Goods"
        }
    ],
    "sg:phone":"+1 310 396 2220",
    "sg:postcode":"90405",
    "sg:province":"CA",
    "wof:name":"Donut King",
    "wof:placetype":"venue"
},
  "geometry": {"coordinates":[-118.482288,34.011668],"type":"Point"}
}