{
  "type": "Feature",
  "properties": {
    "addr:full":"5150 E Hunter Ave Anaheim CA 92807",
    "addr:housenumber":"5150 e",
    "addr:postcode":"92807",
    "addr:street":"Hunter Ave",
    "iso:country":"US",
    "sg:address":"5150 E Hunter Ave",
    "sg:city":"Anaheim",
    "sg:classifiers":[
        {
            "category":"Real Estate",
            "subcategory":"Surveying",
            "type":"Services"
        }
    ],
    "sg:phone":"+1 714 777 8877",
    "sg:postcode":"92807",
    "sg:province":"CA",
    "sg:tags":[
        "surveyor"
    ],
    "wof:name":"Johnson-Frank & Assoc",
    "wof:placetype":"venue"
},
  "geometry": {"coordinates":[-117.80482600000001,33.862814],"type":"Point"}
}