{
  "type": "Feature",
  "properties": {
    "iso:country":"US",
    "sg:address":"2647 International Blvd",
    "sg:city":"Oakland",
    "sg:classifiers":[
        {
            "category":"Health Services",
            "subcategory":"Nursing And Care Facility",
            "type":"Services"
        },
        {
            "category":"Health Services",
            "subcategory":"Health Practitioner",
            "type":"Services"
        }
    ],
    "sg:phone":"+1 510 261 6096",
    "sg:postcode":"94601",
    "sg:province":"CA",
    "sg:tags":[
        "home",
        "eldercare-home"
    ],
    "wof:name":"Bay Area Black Health Consortium Family Life Resource Center",
    "wof:placetype":"venue"
},
  "geometry": {"coordinates":[-122.232066,37.7811],"type":"Point"}
}