{
  "type": "Feature",
  "properties": {
    "addr:full":"1760 Termino Ave Ste 116 Long Beach CA 90804",
    "addr:housenumber":"1760",
    "addr:postcode":"90804",
    "addr:street":"Termino Ave Ste 116",
    "iso:country":"US",
    "sg:address":"1760 Termino Ave Ste 116",
    "sg:city":"Long Beach",
    "sg:classifiers":[
        {
            "category":"Health Services",
            "subcategory":"Doctor",
            "type":"Services"
        }
    ],
    "sg:phone":"+1 562 597 8885",
    "sg:postcode":"90804",
    "sg:province":"CA",
    "wof:name":"Jayatilaka George M MD Inc",
    "wof:placetype":"venue"
},
  "geometry": {"coordinates":[-118.146004,33.7892],"type":"Point"}
}