{
  "type": "Feature",
  "properties": {
    "iso:country":"US",
    "sg:address":"1650 Wilshire Blvd",
    "sg:city":"Los Angeles",
    "sg:classifiers":[
        {
            "category":"Professional",
            "subcategory":"Accounting & Tax Preparation",
            "type":"Services"
        }
    ],
    "sg:phone":"+1 213 484 1180",
    "sg:postcode":"90017",
    "sg:province":"CA",
    "sg:tags":[
        "return",
        "filing"
    ],
    "wof:name":"Robert Scianca Agency",
    "wof:placetype":"venue"
},
  "geometry": {"coordinates":[-118.27058700000001,34.055373],"type":"Point"}
}