{
  "type": "Feature",
  "properties": {
    "addr:full":"1666 N Avalon Blvd Wilmington CA 90744",
    "addr:housenumber":"1666",
    "addr:postcode":"90744",
    "addr:street":"N Avalon Blvd",
    "iso:country":"US",
    "sg:address":"1666 N Avalon Blvd",
    "sg:city":"Wilmington",
    "sg:classifiers":[
        {
            "category":"Real Estate",
            "subcategory":"Real Estate Operator",
            "type":"Services"
        }
    ],
    "sg:phone":"+1 310 518 5044",
    "sg:postcode":"90744",
    "sg:province":"CA",
    "sg:tags":[
        "apartment"
    ],
    "wof:name":"B & C Properties",
    "wof:placetype":"venue"
},
  "geometry": {"coordinates":[-118.263592,33.796948],"type":"Point"}
}