{
  "type": "Feature",
  "properties": {
    "iso:country":"US",
    "sg:address":"3401 Ramona Dr",
    "sg:city":"Riverside",
    "sg:classifiers":[
        {
            "category":"Real Estate",
            "subcategory":"Real Estate Operator",
            "type":"Services"
        }
    ],
    "sg:phone":"+1 951 683 2471",
    "sg:postcode":"92506",
    "sg:province":"CA",
    "sg:tags":[
        "apartment"
    ],
    "wof:name":"Ramona Oaks Apartments",
    "wof:placetype":"venue"
},
  "geometry": {"coordinates":[-117.38169000000001,33.965683],"type":"Point"}
}