{
  "type": "Feature",
  "properties": {
    "iso:country":"US",
    "sg:address":"130 E 17th St",
    "sg:city":"Costa Mesa",
    "sg:classifiers":[
        {
            "category":"Wholesale",
            "subcategory":"Durable Goods & Equipment",
            "type":"Manufacturing & Wholesale Goods"
        }
    ],
    "sg:phone":"+1 949 650 5947",
    "sg:postcode":"92627",
    "sg:province":"CA",
    "wof:name":"Sarah Whitcomb Antiques",
    "wof:placetype":"venue"
},
  "geometry": {"coordinates":[-117.920776,33.636996],"type":"Point"}
}