{
  "type": "Feature",
  "properties": {
    "iso:country":"US",
    "sg:address":"490 G St",
    "sg:city":"Lincoln",
    "sg:classifiers":[
        {
            "category":"Restaurant",
            "type":"Food & Drink"
        }
    ],
    "sg:phone":"+1 916 645 9766",
    "sg:postcode":"95648",
    "sg:province":"CA",
    "wof:name":"Awful Annie's",
    "wof:placetype":"venue"
},
  "geometry": {"coordinates":[-121.29283700000001,38.891711],"type":"Point"}
}