{
  "type": "Feature",
  "properties": {
    "addr:full":"1184 Forest Ave Pacific Grove CA 93950",
    "addr:housenumber":"1184",
    "addr:postcode":"93950",
    "addr:street":"Forest Ave",
    "iso:country":"US",
    "sg:address":"1184 Forest Ave",
    "sg:city":"Pacific Grove",
    "sg:classifiers":[
        {
            "category":"Restaurant",
            "type":"Food & Drink"
        }
    ],
    "sg:phone":"+1 831 658 0134",
    "sg:postcode":"93950",
    "sg:province":"CA",
    "wof:name":"Thaiwaiian Bistro",
    "wof:placetype":"venue"
},
  "geometry": {"coordinates":[-121.920624,36.60496],"type":"Point"}
}