{
  "type": "Feature",
  "properties": {
    "addr:full":"6204 Washington St Napa CA 94558",
    "addr:housenumber":"6204",
    "addr:postcode":"94558",
    "addr:street":"Washington St",
    "iso:country":"US",
    "sg:address":"6204 Washington St",
    "sg:city":"Napa",
    "sg:classifiers":[
        {
            "category":"Manufacturing",
            "subcategory":"Food",
            "type":"Manufacturing & Wholesale Goods"
        }
    ],
    "sg:phone":"+1 707 944 0675",
    "sg:postcode":"94558",
    "sg:province":"CA",
    "sg:tags":[
        "winery"
    ],
    "wof:name":"Noah Vineyards",
    "wof:placetype":"venue"
},
  "geometry": {"coordinates":[-122.34988199999999,38.387116],"type":"Point"}
}