{
  "type": "Feature",
  "properties": {
    "addr:full":"10694 Olson Drive Rancho Cordova CA 95670",
    "addr:housenumber":"10694",
    "addr:postcode":"95670",
    "addr:street":"Olson Drive",
    "iso:country":"US",
    "sg:address":"10694 Olson Drive",
    "sg:city":"Rancho Cordova",
    "sg:classifiers":[
        {
            "category":"Travel",
            "subcategory":"Hotels & Motels",
            "type":"Entertainment"
        }
    ],
    "sg:phone":"+1 916 635 8784",
    "sg:postcode":"95670",
    "sg:province":"CA",
    "wof:name":"Motel 6",
    "wof:placetype":"venue"
},
  "geometry": {"coordinates":[-121.29061799999999,38.593401],"type":"Point"}
}