{
  "type": "Feature",
  "properties": {
    "addr:full":"1331 33rd St Ste B Bakersfield CA 93301",
    "addr:housenumber":"1331",
    "addr:postcode":"93301",
    "addr:street":"33Rd St Ste B",
    "iso:country":"US",
    "sg:address":"1331 33rd St Ste B",
    "sg:city":"Bakersfield",
    "sg:classifiers":[
        {
            "category":"Retail",
            "subcategory":"Auto Repair",
            "type":"Services"
        }
    ],
    "sg:phone":"+1 661 324 1603",
    "sg:postcode":"93301",
    "sg:province":"CA",
    "sg:tags":[
        "body",
        "automobile",
        "painting",
        "repairing"
    ],
    "wof:name":"Jim Reagle",
    "wof:placetype":"venue"
},
  "geometry": {"coordinates":[-119.016786,35.389564],"type":"Point"}
}