{
  "type": "Feature",
  "properties": {
    "iso:country":"US",
    "sg:address":"637 S Clarence St",
    "sg:city":"Los Angeles",
    "sg:classifiers":[
        {
            "category":"Shopping",
            "subcategory":"Crafts & Fabrics",
            "type":"Retail Goods"
        }
    ],
    "sg:phone":"+1 323 268 2015",
    "sg:postcode":"90023",
    "sg:province":"CA",
    "sg:tags":[
        "sewing"
    ],
    "wof:name":"Fabric Studio Inc",
    "wof:placetype":"venue"
},
  "geometry": {"coordinates":[-118.222537,34.037948],"type":"Point"}
}