{
  "type": "Feature",
  "properties": {
    "addr:full":"1025 E Katella Ave Ste C Anaheim CA 92805",
    "addr:housenumber":"1025",
    "addr:postcode":"92805",
    "addr:street":"E Katella Ave Ste C",
    "iso:country":"US",
    "sg:address":"1025 E Katella Ave Ste C",
    "sg:city":"Anaheim",
    "sg:classifiers":[
        {
            "category":"Autos & Motor Vehicles",
            "subcategory":"Motorcycle Sales",
            "type":"Retail Goods"
        },
        {
            "category":"Retail",
            "subcategory":"Auto Repair",
            "type":"Services"
        }
    ],
    "sg:phone":"+1 714 634 8000",
    "sg:postcode":"92805",
    "sg:province":"CA",
    "sg:website":"www.axxismotorsports.com",
    "wof:name":"AXXIS Motorsports",
    "wof:placetype":"venue"
},
  "geometry": {"coordinates":[-117.895287,33.803403],"type":"Point"}
}