{
  "type": "Feature",
  "properties": {
    "iso:country":"US",
    "sg:address":"4100 Newport Place Dr",
    "sg:city":"Newport Beach",
    "sg:classifiers":[
        {
            "category":"Professional",
            "subcategory":"Lawyer & Legal Services",
            "type":"Services"
        }
    ],
    "sg:phone":"+1 714 953 5033",
    "sg:postcode":"92660",
    "sg:province":"CA",
    "sg:tags":[
        "divorce",
        "law",
        "family"
    ],
    "wof:name":"Orange County Family Law Center",
    "wof:placetype":"venue"
},
  "geometry": {"coordinates":[-117.86599699999999,33.662102],"type":"Point"}
}