{
  "type": "Feature",
  "properties": {
    "iso:country":"US",
    "sg:address":"1215 Colusa Ave",
    "sg:city":"Yuba City",
    "sg:classifiers":[
        {
            "category":"Shopping",
            "subcategory":"Clothing, Apparel, & Fashions",
            "type":"Retail Goods"
        }
    ],
    "sg:phone":"+1 530 673 5612",
    "sg:postcode":"95991",
    "sg:province":"CA",
    "sg:tags":[
        "sportswear"
    ],
    "wof:name":"Pacific Sunwear",
    "wof:placetype":"venue"
},
  "geometry": {"coordinates":[-121.63288900000001,39.141808],"type":"Point"}
}