{
  "type": "Feature",
  "properties": {
    "iso:country":"US",
    "sg:address":"715 N Arrowhead Ave",
    "sg:city":"San Bernardino",
    "sg:classifiers":[
        {
            "category":"Health Services",
            "subcategory":"Clinic",
            "type":"Services"
        }
    ],
    "sg:phone":"+1 909 383 0030",
    "sg:postcode":"92401",
    "sg:province":"CA",
    "sg:tags":[
        "specialty",
        "outpatient"
    ],
    "wof:name":"Pacific Rehabilitation",
    "wof:placetype":"venue"
},
  "geometry": {"coordinates":[-117.289604,34.113678],"type":"Point"}
}