{
  "type": "Feature",
  "properties": {
    "addr:full":"742 Celis St San Fernando CA 91340",
    "addr:housenumber":"742",
    "addr:postcode":"91340",
    "addr:street":"Celis St",
    "iso:country":"US",
    "sg:address":"742 Celis St",
    "sg:city":"San Fernando",
    "sg:classifiers":[
        {
            "category":"Retail",
            "subcategory":"Auto Rental",
            "type":"Services"
        }
    ],
    "sg:phone":"+1 818 898 4044",
    "sg:postcode":"91340",
    "sg:province":"CA",
    "sg:tags":[
        "renting",
        "automobile"
    ],
    "wof:name":"Horizon Rent A Car",
    "wof:placetype":"venue"
},
  "geometry": {"coordinates":[-118.43953399999999,34.279651],"type":"Point"}
}