{
  "type": "Feature",
  "properties": {
    "iso:country":"US",
    "sg:address":"8740 Ramona St",
    "sg:city":"Bellflower",
    "sg:classifiers":[
        {
            "category":"Social Services",
            "subcategory":"Child Care",
            "type":"Services"
        }
    ],
    "sg:phone":"+1 562 634 7527",
    "sg:postcode":"90706",
    "sg:province":"CA",
    "sg:tags":[
        "elementary",
        "school"
    ],
    "wof:name":"Creative Day Preschool",
    "wof:placetype":"venue"
},
  "geometry": {"coordinates":[-118.146004,33.872799],"type":"Point"}
}