{
  "type": "Feature",
  "properties": {
    "addr:full":"8555 Elder Creek Rd Sacramento CA 95828",
    "addr:housenumber":"8555",
    "addr:postcode":"95828",
    "addr:street":"Elder Creek Rd",
    "iso:country":"US",
    "sg:address":"8555 Elder Creek Rd",
    "sg:city":"Sacramento",
    "sg:classifiers":[
        {
            "category":"Recreation",
            "subcategory":"Sailing Club",
            "type":"Entertainment"
        }
    ],
    "sg:phone":"+1 916 383 5353",
    "sg:postcode":"95828",
    "sg:province":"CA",
    "sg:tags":[
        "caster",
        "glide"
    ],
    "wof:name":"Industrial Caster & Wheel Co.",
    "wof:placetype":"venue"
},
  "geometry": {"coordinates":[-121.389144,38.510624],"type":"Point"}
}