{
  "type": "Feature",
  "properties": {
    "addr:full":"5960 Van Nuys Blvd Van Nuys CA 91401",
    "addr:housenumber":"5960",
    "addr:postcode":"91401",
    "addr:street":"Van Nuys Blvd",
    "iso:country":"US",
    "sg:address":"5960 Van Nuys Blvd",
    "sg:city":"Van Nuys",
    "sg:classifiers":[
        {
            "category":"Home & Garden",
            "subcategory":"Building Materials",
            "type":"Retail Goods"
        }
    ],
    "sg:phone":"+1 818 304 0444",
    "sg:postcode":"91401",
    "sg:province":"CA",
    "sg:tags":[
        "paint"
    ],
    "wof:name":"Catalina Paint Stores",
    "wof:placetype":"venue"
},
  "geometry": {"coordinates":[-118.448635,34.179015],"type":"Point"}
}