{
  "type": "Feature",
  "properties": {
    "addr:full":"117 Broadway Santa Monica CA 90401",
    "addr:housenumber":"117",
    "addr:postcode":"90401",
    "addr:street":"Broadway",
    "iso:country":"US",
    "sg:address":"117 Broadway",
    "sg:city":"Santa Monica",
    "sg:classifiers":[
        {
            "category":"Shopping",
            "subcategory":"Gifts & Souvenirs",
            "type":"Retail Goods"
        }
    ],
    "sg:phone":"+1 310 395 4933",
    "sg:postcode":"90401",
    "sg:province":"CA",
    "sg:tags":[
        "novelty"
    ],
    "wof:name":"Novelty Training Inc",
    "wof:placetype":"venue"
},
  "geometry": {"coordinates":[-118.49562299999999,34.013475],"type":"Point"}
}