{
  "type": "Feature",
  "properties": {
    "iso:country":"US",
    "sg:address":"601 Van Ness Avenue  Suite E3-970",
    "sg:city":"San Francisco",
    "sg:classifiers":[
        {
            "category":"Professional",
            "subcategory":"Computer Services",
            "type":"Services"
        }
    ],
    "sg:phone":"+1 415 398 5674",
    "sg:postcode":"94102",
    "sg:province":"CA",
    "sg:website":"http://www.guba.com",
    "wof:name":"Guba",
    "wof:placetype":"venue"
},
  "geometry": {"coordinates":[-122.42062300000001,37.781493],"type":"Point"}
}