{
  "type": "Feature",
  "properties": {
    "addr:full":"5188 State Rte 49 Mariposa CA 95338",
    "addr:housenumber":"5188",
    "addr:postcode":"95338",
    "addr:street":"State Rte 49",
    "iso:country":"US",
    "sg:address":"5188 State Rte 49",
    "sg:city":"Mariposa",
    "sg:classifiers":[
        {
            "category":"Food & Beverages",
            "subcategory":"Liquor & Beverages",
            "type":"Retail Goods"
        }
    ],
    "sg:phone":"+1 209 966 5125",
    "sg:postcode":"95338",
    "sg:province":"CA",
    "wof:name":"Lucky Logger Liquors",
    "wof:placetype":"venue"
},
  "geometry": {"coordinates":[-119.945579,37.461358],"type":"Point"}
}