{
  "type": "Feature",
  "properties": {
    "addr:full":"4207 Park Blvd San Diego CA 92103",
    "addr:housenumber":"4207",
    "addr:postcode":"92103",
    "addr:street":"Park Blvd",
    "iso:country":"US",
    "sg:address":"4207 Park Blvd",
    "sg:city":"San Diego",
    "sg:classifiers":[
        {
            "category":"Restaurant",
            "type":"Food & Drink"
        }
    ],
    "sg:phone":"+1 619 299 3404",
    "sg:postcode":"92103",
    "sg:province":"CA",
    "wof:name":"Indulgence Bakery",
    "wof:placetype":"venue"
},
  "geometry": {"coordinates":[-117.14629499999999,32.755169],"type":"Point"}
}