{
  "type": "Feature",
  "properties": {
    "addr:full":"6336 Patterson Pass Rd Livermore CA 94550",
    "addr:housenumber":"6336",
    "addr:postcode":"94550",
    "addr:street":"Patterson Pass Rd",
    "iso:country":"US",
    "sg:address":"6336 Patterson Pass Rd",
    "sg:city":"Livermore",
    "sg:classifiers":[
        {
            "category":"Building & Trades",
            "subcategory":"Construction",
            "type":"Services"
        }
    ],
    "sg:phone":"+1 925 455 1680",
    "sg:postcode":"94550",
    "sg:province":"CA",
    "sg:tags":[
        "maker",
        "cabinet"
    ],
    "wof:name":"Doe's Cabinets",
    "wof:placetype":"venue"
},
  "geometry": {"coordinates":[-121.7133,37.695864],"type":"Point"}
}