{
  "type": "Feature",
  "properties": {
    "addr:full":"1067 Burgoyne St Mountain View CA 94043",
    "addr:housenumber":"1067",
    "addr:postcode":"94043",
    "addr:street":"Burgoyne St",
    "iso:country":"US",
    "sg:address":"1067 Burgoyne St",
    "sg:city":"Mountain View",
    "sg:classifiers":[
        {
            "category":"Professional",
            "subcategory":"Management & Consulting",
            "type":"Services"
        }
    ],
    "sg:phone":"+1 650 964 6098",
    "sg:postcode":"94043",
    "sg:province":"CA",
    "sg:tags":[
        "retail",
        "direct",
        "sales"
    ],
    "wof:name":"Harvest Moon Landscape",
    "wof:placetype":"venue"
},
  "geometry": {"coordinates":[-122.08555699999999,37.407009],"type":"Point"}
}