{
  "type": "Feature",
  "properties": {
    "iso:country":"US",
    "sg:address":"3655 Artesia Blvd",
    "sg:city":"Torrance",
    "sg:classifiers":[
        {
            "category":"Real Estate",
            "subcategory":"Real Estate Operator",
            "type":"Services"
        }
    ],
    "sg:phone":"+1 310 327 3681",
    "sg:postcode":"90504",
    "sg:province":"CA",
    "sg:tags":[
        "apartment"
    ],
    "wof:name":"II Pompeii Apts",
    "wof:placetype":"venue"
},
  "geometry": {"coordinates":[-118.33699799999999,33.872898],"type":"Point"}
}