{
  "type": "Feature",
  "properties": {
    "iso:country":"US",
    "sg:address":"6231 N Blackstone Ave",
    "sg:city":"Fresno",
    "sg:classifiers":[
        {
            "category":"Retail",
            "subcategory":"Auto Repair",
            "type":"Services"
        }
    ],
    "sg:phone":"+1 559 440 1000",
    "sg:postcode":"93710",
    "sg:province":"CA",
    "sg:tags":[
        "repairing",
        "automobile"
    ],
    "wof:name":"Super Lube",
    "wof:placetype":"venue"
},
  "geometry": {"coordinates":[-119.790386,36.826892],"type":"Point"}
}