{
  "type": "Feature",
  "properties": {
    "iso:country":"US",
    "sg:address":"18815 Sherman Way",
    "sg:city":"Reseda",
    "sg:classifiers":[
        {
            "category":"Retail",
            "subcategory":"Auto Repair",
            "type":"Services"
        }
    ],
    "sg:phone":"+1 818 881 7650",
    "sg:postcode":"91335",
    "sg:province":"CA",
    "sg:tags":[
        "repairing",
        "automobile"
    ],
    "wof:name":"Burns Automotive",
    "wof:placetype":"venue"
},
  "geometry": {"coordinates":[-118.54311199999999,34.201131],"type":"Point"}
}