{
  "type": "Feature",
  "properties": {
    "addr:full":"844 Richland Rd Yuba City CA 95991",
    "addr:housenumber":"844",
    "addr:postcode":"95991",
    "addr:street":"Richland Rd",
    "iso:country":"US",
    "sg:address":"844 Richland Rd",
    "sg:city":"Yuba City",
    "sg:classifiers":[
        {
            "category":"Real Estate",
            "subcategory":"Real Estate Agent",
            "type":"Services"
        }
    ],
    "sg:phone":"+1 530 673 5167",
    "sg:postcode":"95991",
    "sg:province":"CA",
    "sg:tags":[
        "appraiser"
    ],
    "wof:name":"Peter F Brennan & Sons",
    "wof:placetype":"venue"
},
  "geometry": {"coordinates":[-121.623946,39.118035],"type":"Point"}
}