{
  "type": "Feature",
  "properties": {
    "iso:country":"US",
    "sg:address":"3530 Sandpiper Pl",
    "sg:city":"Oceanside",
    "sg:classifiers":[
        {
            "category":"Building & Trades",
            "subcategory":"Cleaning & Sanitation",
            "type":"Services"
        }
    ],
    "sg:phone":"+1 760 726 6360",
    "sg:postcode":"92056",
    "sg:province":"CA",
    "sg:tags":[
        "carpet"
    ],
    "wof:name":"Hector's Carpet Cleaning",
    "wof:placetype":"venue"
},
  "geometry": {"coordinates":[-117.285004,33.180302],"type":"Point"}
}