{
  "type": "Feature",
  "properties": {
    "iso:country":"US",
    "sg:address":"110 Spring Hill Dr",
    "sg:city":"Grass Valley",
    "sg:classifiers":[
        {
            "category":"Recreation",
            "type":"Entertainment"
        }
    ],
    "sg:phone":"+1 530 273 3680",
    "sg:postcode":"95945",
    "sg:province":"CA",
    "sg:tags":[
        "instruction",
        "gymnastic"
    ],
    "wof:name":"Stellar Gymnastic Academy",
    "wof:placetype":"venue"
},
  "geometry": {"coordinates":[-121.043027,39.225508],"type":"Point"}
}