{
  "type": "Feature",
  "properties": {
    "addr:full":"328 E 1st St Los Angeles CA 90012",
    "addr:housenumber":"328",
    "addr:postcode":"90012",
    "addr:street":"E 1St St",
    "iso:country":"US",
    "sg:address":"328 E 1st St",
    "sg:city":"Los Angeles",
    "sg:classifiers":[
        {
            "category":"Building & Trades",
            "subcategory":"Cleaning & Sanitation",
            "type":"Services"
        },
        {
            "category":"Home & Garden",
            "subcategory":"Carpets & Floor Coverings",
            "type":"Retail Goods"
        }
    ],
    "sg:phone":"+1 818 301 3470",
    "sg:postcode":"90012",
    "sg:province":"CA",
    "sg:tags":[
        "carpeting"
    ],
    "wof:name":"When Clean Meets Green Carpet Cleaning",
    "wof:placetype":"venue"
},
  "geometry": {"coordinates":[-118.240143,34.049688],"type":"Point"}
}