{
  "type": "Feature",
  "properties": {
    "iso:country":"US",
    "sg:address":"901 Campus Dr",
    "sg:city":"Daly City",
    "sg:classifiers":[
        {
            "category":"Real Estate",
            "subcategory":"Real Estate Agent",
            "type":"Services"
        }
    ],
    "sg:phone":"+1 650 991 4506",
    "sg:postcode":"94015",
    "sg:province":"CA",
    "sg:tags":[
        "management"
    ],
    "wof:name":"Rogers S Martins",
    "wof:placetype":"venue"
},
  "geometry": {"coordinates":[-122.477107,37.666985],"type":"Point"}
}