{
  "type": "Feature",
  "properties": {
    "iso:country":"US",
    "sg:address":"19259 Harleigh Dr",
    "sg:city":"Saratoga",
    "sg:classifiers":[
        {
            "category":"Shopping",
            "type":"Retail Goods"
        }
    ],
    "sg:phone":"+1 408 867 2677",
    "sg:postcode":"95070",
    "sg:province":"CA",
    "sg:tags":[
        "merchandise"
    ],
    "wof:name":"Hull Enterprises",
    "wof:placetype":"venue"
},
  "geometry": {"coordinates":[-122.009719,37.26949],"type":"Point"}
}