{
  "type": "Feature",
  "properties": {
    "iso:country":"US",
    "sg:address":"2011 Artesia Boulevard",
    "sg:city":"Redondo Beach",
    "sg:classifiers":[
        {
            "category":"Organizations",
            "subcategory":"Religious Organization",
            "type":"Services"
        }
    ],
    "sg:phone":"+1 310 374 9157",
    "sg:postcode":"90278",
    "sg:province":"CA",
    "wof:name":"Madam Laura",
    "wof:placetype":"venue"
},
  "geometry": {"coordinates":[-118.37606599999999,33.873016],"type":"Point"}
}