{
  "type": "Feature",
  "properties": {
    "addr:full":"20855 Ventura Blvd Woodland Hills CA 91364",
    "addr:housenumber":"20855",
    "addr:postcode":"91364",
    "addr:street":"Ventura Blvd",
    "iso:country":"US",
    "sg:address":"20855 Ventura Blvd",
    "sg:city":"Woodland Hills",
    "sg:classifiers":[
        {
            "category":"Education",
            "subcategory":"Vocational School",
            "type":"Public Place"
        }
    ],
    "sg:phone":"+1 818 598 8007",
    "sg:postcode":"91364",
    "sg:province":"CA",
    "sg:tags":[
        "training",
        "computer"
    ],
    "wof:name":"Oxford Institute Of Technology",
    "wof:placetype":"venue"
},
  "geometry": {"coordinates":[-118.586929,34.166409],"type":"Point"}
}