{
  "type": "Feature",
  "properties": {
    "addr:full":"240 N Beverly Drive Beverly Hills CA 90210",
    "addr:housenumber":"240",
    "addr:postcode":"90210",
    "addr:street":"N Beverly Drive",
    "iso:country":"US",
    "sg:address":"240 N Beverly Drive",
    "sg:city":"Beverly Hills",
    "sg:classifiers":[
        {
            "category":"Building & Trades",
            "subcategory":"Locksmith",
            "type":"Services"
        }
    ],
    "sg:phone":"+1 310 499 0773",
    "sg:postcode":"90210",
    "sg:province":"CA",
    "sg:tags":[
        "key"
    ],
    "wof:name":"7 24 Emergency Locks & Locksmith",
    "wof:placetype":"venue"
},
  "geometry": {"coordinates":[-118.399911,34.06808],"type":"Point"}
}