{
  "type": "Feature",
  "properties": {
    "addr:full":"755 S Cochran Ave Los Angeles CA 90036",
    "addr:housenumber":"755",
    "addr:postcode":"90036",
    "addr:street":"S Cochran Ave",
    "iso:country":"US",
    "sg:address":"755 S Cochran Ave",
    "sg:city":"Los Angeles",
    "sg:classifiers":[
        {
            "category":"Education",
            "subcategory":"School",
            "type":"Public Place"
        }
    ],
    "sg:phone":"+1 323 938 9976",
    "sg:postcode":"90036",
    "sg:province":"CA",
    "sg:tags":[
        "high",
        "middle",
        "elementary"
    ],
    "wof:name":"Cathedral Chapel School",
    "wof:placetype":"venue"
},
  "geometry": {"coordinates":[-118.348,34.060799],"type":"Point"}
}