{
  "type": "Feature",
  "properties": {
    "addr:full":"9605 Airway Rd San Diego CA 92154",
    "addr:housenumber":"9605",
    "addr:postcode":"92154",
    "addr:street":"Airway Rd",
    "iso:country":"US",
    "sg:address":"9605 Airway Rd",
    "sg:city":"San Diego",
    "sg:classifiers":[
        {
            "category":"Home & Garden",
            "subcategory":"Building Materials",
            "type":"Retail Goods"
        }
    ],
    "sg:phone":"+1 619 710 1626",
    "sg:postcode":"92154",
    "sg:province":"CA",
    "sg:tags":[
        "hardwood"
    ],
    "wof:name":"Hardwoods Inc",
    "wof:placetype":"venue"
},
  "geometry": {"coordinates":[-116.940787,32.560249],"type":"Point"}
}