{
  "type": "Feature",
  "properties": {
    "addr:full":"12517 Crenshaw Blvd Hawthorne CA 90250",
    "addr:housenumber":"12517",
    "addr:postcode":"90250",
    "addr:street":"Crenshaw Blvd",
    "iso:country":"US",
    "sg:address":"12517 Crenshaw Blvd",
    "sg:city":"Hawthorne",
    "sg:classifiers":[
        {
            "category":"Building & Trades",
            "subcategory":"Construction",
            "type":"Services"
        }
    ],
    "sg:phone":"+1 310 355 1995",
    "sg:postcode":"90250",
    "sg:province":"CA",
    "sg:tags":[
        "general",
        "contractor"
    ],
    "wof:name":"Bestek Engineering Inc",
    "wof:placetype":"venue"
},
  "geometry": {"coordinates":[-118.326565,33.919615],"type":"Point"}
}