{
  "type": "Feature",
  "properties": {
    "addr:full":"1125 Southampton Rd Benicia CA 94510",
    "addr:housenumber":"1125",
    "addr:postcode":"94510",
    "addr:street":"Southampton Rd",
    "iso:country":"US",
    "sg:address":"1125 Southampton Rd",
    "sg:city":"Benicia",
    "sg:classifiers":[
        {
            "category":"Place Of Worship",
            "subcategory":"Church",
            "type":"Public Place"
        },
        {
            "category":"Place Of Worship",
            "type":"Public Place"
        }
    ],
    "sg:phone":"+1 707 745 8483",
    "sg:postcode":"94510",
    "sg:province":"CA",
    "sg:tags":[
        "jesus",
        "churches-church",
        "christ",
        "saint",
        "latter-day"
    ],
    "sg:website":"http://www.lds.org",
    "wof:name":"The Corp Of Church Of Christ Latter-Day St",
    "wof:placetype":"venue"
},
  "geometry": {"coordinates":[-122.174316,38.069592],"type":"Point"}
}