{
  "type": "Feature",
  "properties": {
    "iso:country":"US",
    "sg:address":"347 E Campbell Ave",
    "sg:city":"Campbell",
    "sg:classifiers":[
        {
            "category":"Professional",
            "subcategory":"Lawyer & Legal Services",
            "type":"Services"
        }
    ],
    "sg:phone":"+1 408 364 2173",
    "sg:postcode":"95008",
    "sg:province":"CA",
    "sg:tags":[
        "attorney"
    ],
    "wof:name":"Scott Sagaria",
    "wof:placetype":"venue"
},
  "geometry": {"coordinates":[-121.944575,37.287112],"type":"Point"}
}