{
  "type": "Feature",
  "properties": {
    "iso:country":"US",
    "sg:address":"5935 Whittier Blvd",
    "sg:city":"Los Angeles",
    "sg:classifiers":[
        {
            "category":"Food & Beverages",
            "subcategory":"Groceries & Convenience Stores",
            "type":"Retail Goods"
        }
    ],
    "sg:phone":"+1 323 721 7572",
    "sg:postcode":"90022",
    "sg:province":"CA",
    "wof:name":"Papas Ranch Market",
    "wof:placetype":"venue"
},
  "geometry": {"coordinates":[-118.142158,34.017288],"type":"Point"}
}