{
  "type": "Feature",
  "properties": {
    "addr:full":"4111 Pso de Las Tortugas Torrance CA 90505",
    "addr:housenumber":"4111",
    "addr:postcode":"90505",
    "addr:street":"Pso De Las Tortugas",
    "iso:country":"US",
    "sg:address":"4111 Pso de Las Tortugas",
    "sg:city":"Torrance",
    "sg:classifiers":[
        {
            "category":"Banks & Credit Unions",
            "subcategory":"Financial Services",
            "type":"Services"
        }
    ],
    "sg:phone":"+1 310 378 5511",
    "sg:postcode":"90505",
    "sg:province":"CA",
    "sg:tags":[
        "trust",
        "management"
    ],
    "wof:name":"Fitzpatrick Family Trust",
    "wof:placetype":"venue"
},
  "geometry": {"coordinates":[-118.360877,33.803801],"type":"Point"}
}