{
  "type": "Feature",
  "properties": {
    "iso:country":"US",
    "sg:address":"505 E 1st St",
    "sg:city":"Tustin",
    "sg:classifiers":[
        {
            "category":"Shopping",
            "subcategory":"Computers & Home Electronics",
            "type":"Retail Goods"
        }
    ],
    "sg:phone":"+1 714 838 2234",
    "sg:postcode":"92780",
    "sg:province":"CA",
    "sg:website":"www.dishnetwork.com",
    "wof:name":"A Direct Dish Satellite TV",
    "wof:placetype":"venue"
},
  "geometry": {"coordinates":[-117.818353,33.745917],"type":"Point"}
}