{
  "type": "Feature",
  "properties": {
    "addr:full":"6660 Indiana Ave Riverside CA 92506",
    "addr:housenumber":"6660",
    "addr:postcode":"92506",
    "addr:street":"Indiana Ave",
    "iso:country":"US",
    "sg:address":"6660 Indiana Ave",
    "sg:city":"Riverside",
    "sg:classifiers":[
        {
            "category":"Home & Garden",
            "subcategory":"Carpets & Floor Coverings",
            "type":"Retail Goods"
        }
    ],
    "sg:phone":"+1 951 369 3007",
    "sg:postcode":"92506",
    "sg:province":"CA",
    "sg:tags":[
        "dealer",
        "rug"
    ],
    "wof:name":"Carpet Connection",
    "wof:placetype":"venue"
},
  "geometry": {"coordinates":[-117.388744,33.945187],"type":"Point"}
}