{
  "type": "Feature",
  "properties": {
    "iso:country":"US",
    "sg:address":"8330 18th Ave",
    "sg:city":"Lemoore",
    "sg:phone":"+1 559 924 2423",
    "sg:postcode":"93245",
    "sg:province":"CA",
    "sg:tags":[
        "farm",
        "dairy",
        "general"
    ],
    "wof:name":"Aa and Nelson Rodrigues Inc",
    "wof:placetype":"venue"
},
  "geometry": {"coordinates":[-119.780877,36.348973],"type":"Point"}
}