{
  "type": "Feature",
  "properties": {
    "addr:full":"40067 Gibraltar Dr Murrieta CA 92562",
    "addr:housenumber":"40067",
    "addr:postcode":"92562",
    "addr:street":"Gibraltar Dr",
    "iso:country":"US",
    "sg:address":"40067 Gibraltar Dr",
    "sg:city":"Murrieta",
    "sg:classifiers":[
        {
            "category":"Wholesale",
            "subcategory":"Chemicals & Plastics",
            "type":"Manufacturing & Wholesale Goods"
        }
    ],
    "sg:phone":"+1 951 304 2037",
    "sg:postcode":"92562",
    "sg:province":"CA",
    "wof:name":"P C I of America",
    "wof:placetype":"venue"
},
  "geometry": {"coordinates":[-117.187032,33.56854],"type":"Point"}
}