{
  "type": "Feature",
  "properties": {
    "addr:full":"530 N Sepulveda Blvd El Segundo CA 90245",
    "addr:housenumber":"530",
    "addr:postcode":"90245",
    "addr:street":"N Sepulveda Blvd",
    "iso:country":"US",
    "sg:address":"530 N Sepulveda Blvd",
    "sg:city":"El Segundo",
    "sg:classifiers":[
        {
            "category":"Restaurant",
            "type":"Food & Drink"
        }
    ],
    "sg:phone":"+1 310 647 5684",
    "sg:postcode":"90245",
    "sg:province":"CA",
    "sg:tags":[
        "shop",
        "tea",
        "coffee"
    ],
    "sg:website":"www.starbucks.com",
    "wof:name":"Starbucks",
    "wof:placetype":"venue"
},
  "geometry": {"coordinates":[-118.395853,33.923038],"type":"Point"}
}