{
  "type": "Feature",
  "properties": {
    "addr:full":"320 13th St Oakland CA 94612",
    "addr:housenumber":"320",
    "addr:postcode":"94612",
    "addr:street":"13Th St",
    "iso:country":"US",
    "sg:address":"320 13th St",
    "sg:city":"Oakland",
    "sg:classifiers":[
        {
            "category":"Food & Beverages",
            "subcategory":"Specialty",
            "type":"Retail Goods"
        }
    ],
    "sg:phone":"+1 510 272 9788",
    "sg:postcode":"94612",
    "sg:province":"CA",
    "sg:tags":[
        "health",
        "diet"
    ],
    "wof:name":"Sinla Health Food Store",
    "wof:placetype":"venue"
},
  "geometry": {"coordinates":[-122.26877399999999,37.802578],"type":"Point"}
}