{
  "type": "Feature",
  "properties": {
    "iso:country":"US",
    "sg:address":"101 W Central Ave",
    "sg:city":"Brea",
    "sg:classifiers":[
        {
            "category":"Personal",
            "type":"Services"
        }
    ],
    "sg:phone":"+1 714 990 0402",
    "sg:postcode":"92821",
    "sg:province":"CA",
    "sg:tags":[
        "mail",
        "receiving"
    ],
    "wof:name":"E-Z Mail Etc",
    "wof:placetype":"venue"
},
  "geometry": {"coordinates":[-117.89512000000001,33.93208],"type":"Point"}
}