{
  "type": "Feature",
  "properties": {
    "addr:full":"8306 Hwy 79 Descanso CA 91916",
    "addr:housenumber":"8306",
    "addr:postcode":"91916",
    "addr:street":"Hwy 79",
    "iso:country":"US",
    "sg:address":"8306 Hwy 79",
    "sg:city":"Descanso",
    "sg:classifiers":[
        {
            "category":"Shopping",
            "subcategory":"Gifts & Souvenirs",
            "type":"Retail Goods"
        }
    ],
    "sg:phone":"+1 619 445 3560",
    "sg:postcode":"91916",
    "sg:province":"CA",
    "sg:tags":[
        "shop"
    ],
    "wof:name":"Kim's Country Cottage",
    "wof:placetype":"venue"
},
  "geometry": {"coordinates":[-116.61282,32.84131],"type":"Point"}
}