{
  "type": "Feature",
  "properties": {
    "addr:full":"11018 Glencreek Cir San Diego CA 92131",
    "addr:housenumber":"11018",
    "addr:postcode":"92131",
    "addr:street":"Glencreek Cir",
    "iso:country":"US",
    "sg:address":"11018 Glencreek Cir",
    "sg:city":"San Diego",
    "sg:classifiers":[
        {
            "category":"Manufacturing",
            "subcategory":"Tools & Machinery",
            "type":"Manufacturing & Wholesale Goods"
        }
    ],
    "sg:phone":"+1 858 695 2763",
    "sg:postcode":"92131",
    "sg:province":"CA",
    "sg:tags":[
        "management",
        "investment",
        "asset"
    ],
    "wof:name":"Tribe Oglala Corporation",
    "wof:placetype":"venue"
},
  "geometry": {"coordinates":[-117.07986699999999,32.916947],"type":"Point"}
}