{
  "type": "Feature",
  "properties": {
    "addr:full":"1299 University Ave Riverside CA 92507",
    "addr:housenumber":"1299",
    "addr:postcode":"92507",
    "addr:street":"University Ave",
    "iso:country":"US",
    "sg:address":"1299 University Ave",
    "sg:city":"Riverside",
    "sg:classifiers":[
        {
            "category":"Restaurant",
            "type":"Food & Drink"
        }
    ],
    "sg:phone":"+1 951 369 7425",
    "sg:postcode":"92507",
    "sg:province":"CA",
    "sg:tags":[
        "parlor",
        "ice",
        "cream"
    ],
    "wof:name":"Baskin-Robbins",
    "wof:placetype":"venue"
},
  "geometry": {"coordinates":[-117.335897,33.975688],"type":"Point"}
}