{
  "type": "Feature",
  "properties": {
    "addr:full":"3801 N Madsen Ave Sanger CA 93657",
    "addr:housenumber":"3801",
    "addr:postcode":"ca 93657",
    "addr:street":"N Madsen Ave",
    "iso:country":"US",
    "sg:address":"3801 N Madsen Ave",
    "sg:city":"Sanger",
    "sg:classifiers":[
        {
            "category":"Insurance",
            "subcategory":"Insurance Agent",
            "type":"Services"
        }
    ],
    "sg:phone":"+1 559 875 2710",
    "sg:postcode":"93657",
    "sg:province":"CA",
    "wof:name":"Joneson & Associates",
    "wof:placetype":"venue"
},
  "geometry": {"coordinates":[-119.537948,36.789815],"type":"Point"}
}