{
  "type": "Feature",
  "properties": {
    "addr:full":"19810 Hirsch Ct Anderson CA 96007",
    "addr:postcode":"19810;96007",
    "addr:street":"Hirsch Ct",
    "iso:country":"US",
    "sg:address":"19810 Hirsch Ct",
    "sg:city":"Anderson",
    "sg:classifiers":[
        {
            "category":"Building & Trades",
            "subcategory":"Electrical",
            "type":"Services"
        }
    ],
    "sg:phone":"+1 530 378 1432",
    "sg:postcode":"96007",
    "sg:province":"CA",
    "sg:tags":[
        "electrical",
        "contractor"
    ],
    "wof:name":"Price John L Electrical Contr",
    "wof:placetype":"venue"
},
  "geometry": {"coordinates":[-122.32004999999999,40.465025],"type":"Point"}
}