{
  "type": "Feature",
  "properties": {
    "iso:country":"US",
    "sg:address":"2276 Foothill Blvd",
    "sg:city":"La Verne",
    "sg:classifiers":[
        {
            "category":"Personal",
            "subcategory":"Beauty Salon",
            "type":"Services"
        }
    ],
    "sg:phone":"+1 909 593 6899",
    "sg:postcode":"91750",
    "sg:province":"CA",
    "sg:tags":[
        "treatment",
        "skin"
    ],
    "wof:name":"Eden Wellness For Life",
    "wof:placetype":"venue"
},
  "geometry": {"coordinates":[-117.762672,34.112446],"type":"Point"}
}