{
  "type": "Feature",
  "properties": {
    "iso:country":"US",
    "sg:address":"2415 W Lincoln Ave Ste H",
    "sg:city":"Anaheim",
    "sg:classifiers":[
        {
            "category":"Restaurant",
            "type":"Food & Drink"
        }
    ],
    "sg:phone":"+1 714 761 4585",
    "sg:postcode":"92801",
    "sg:province":"CA",
    "sg:tags":[
        "thai"
    ],
    "wof:name":"Essential Thai Cuisine",
    "wof:placetype":"venue"
},
  "geometry": {"coordinates":[-117.968602,33.832822],"type":"Point"}
}