{
  "type": "Feature",
  "properties": {
    "addr:full":"2069 W Florence Ave Los Angeles CA 90047",
    "addr:housenumber":"2069",
    "addr:postcode":"90047",
    "addr:street":"W Florence Ave",
    "iso:country":"US",
    "sg:address":"2069 W Florence Ave",
    "sg:city":"Los Angeles",
    "sg:classifiers":[
        {
            "category":"Building & Trades",
            "subcategory":"Cleaning & Sanitation",
            "type":"Services"
        }
    ],
    "sg:phone":"+1 323 751 3324",
    "sg:postcode":"90047",
    "sg:province":"CA",
    "sg:tags":[
        "janitor",
        "maintenance"
    ],
    "wof:name":"Linton Insulation Co",
    "wof:placetype":"venue"
},
  "geometry": {"coordinates":[-118.31583000000001,33.974656],"type":"Point"}
}