{
  "type": "Feature",
  "properties": {
    "addr:full":"691 Cragmont Ave Berkeley CA 94708",
    "addr:housenumber":"691",
    "addr:postcode":"94708",
    "addr:street":"Cragmont Ave",
    "iso:country":"US",
    "sg:address":"691 Cragmont Ave",
    "sg:city":"Berkeley",
    "sg:classifiers":[
        {
            "category":"Professional",
            "type":"Services"
        }
    ],
    "sg:phone":"+1 510 526 9075",
    "sg:postcode":"94708",
    "sg:province":"CA",
    "wof:name":"Bruce Stangeland Artist",
    "wof:placetype":"venue"
},
  "geometry": {"coordinates":[-122.268952,37.900246],"type":"Point"}
}