{
  "type": "Feature",
  "properties": {
    "iso:country":"US",
    "sg:address":"1950 Oceanside Blvd",
    "sg:city":"Oceanside",
    "sg:classifiers":[
        {
            "category":"Retail",
            "subcategory":"Auto Repair",
            "type":"Services"
        }
    ],
    "sg:phone":"+1 760 721 8350",
    "sg:postcode":"92054",
    "sg:province":"CA",
    "sg:tags":[
        "automotive",
        "smog",
        "management",
        "automobile"
    ],
    "wof:name":"Smog This",
    "wof:placetype":"venue"
},
  "geometry": {"coordinates":[-117.35379500000001,33.195068],"type":"Point"}
}