{
  "type": "Feature",
  "properties": {
    "iso:country":"US",
    "sg:address":"3722 E Broadway",
    "sg:city":"Long Beach",
    "sg:classifiers":[
        {
            "category":"Professional",
            "subcategory":"Secretarial Services",
            "type":"Services"
        }
    ],
    "sg:phone":"+1 562 439 9200",
    "sg:postcode":"90803",
    "sg:province":"CA",
    "sg:tags":[
        "convention",
        "court",
        "reporter"
    ],
    "wof:name":"Carroll Sells Court Reporters",
    "wof:placetype":"venue"
},
  "geometry": {"coordinates":[-118.148263,33.764373],"type":"Point"}
}