{
  "type": "Feature",
  "properties": {
    "addr:full":"1935 Newport Ave Grover Beach CA 93433",
    "addr:housenumber":"1935",
    "addr:postcode":"93433",
    "addr:street":"Newport Ave",
    "iso:country":"US",
    "sg:address":"1935 Newport Ave",
    "sg:city":"Grover Beach",
    "sg:classifiers":[
        {
            "category":"Organizations",
            "subcategory":"Religious Organization",
            "type":"Services"
        }
    ],
    "sg:phone":"+1 805 489 4608",
    "sg:postcode":"93433",
    "sg:province":"CA",
    "sg:tags":[
        "church"
    ],
    "wof:name":"Bethel Baptist Church",
    "wof:placetype":"venue"
},
  "geometry": {"coordinates":[-120.607198,35.124865],"type":"Point"}
}