{
  "type": "Feature",
  "properties": {
    "addr:full":"110 W C St Ste 2200 San Diego CA 92101",
    "addr:housenumber":"110",
    "addr:postcode":"92101",
    "addr:street":"W C St Ste 2200",
    "iso:country":"US",
    "sg:address":"110 W C St Ste 2200",
    "sg:city":"San Diego",
    "sg:classifiers":[
        {
            "category":"Professional",
            "subcategory":"Lawyer & Legal Services",
            "type":"Services"
        }
    ],
    "sg:phone":"+1 619 269 8074",
    "sg:postcode":"92101",
    "sg:province":"CA",
    "sg:website":"www.spattersonlaw.com/",
    "wof:name":"Stacie L. Patterson",
    "wof:placetype":"venue"
},
  "geometry": {"coordinates":[-117.16412099999999,32.71705],"type":"Point"}
}