{
  "type": "Feature",
  "properties": {
    "iso:country":"US",
    "sg:address":"40740 California Oaks Rd",
    "sg:city":"Murrieta",
    "sg:classifiers":[
        {
            "category":"Health Services",
            "subcategory":"Doctor",
            "type":"Services"
        }
    ],
    "sg:phone":"+1 951 304 2200",
    "sg:postcode":"92562",
    "sg:province":"CA",
    "sg:tags":[
        "physician",
        "surgeon"
    ],
    "wof:name":"Oak Surgery Ctr",
    "wof:placetype":"venue"
},
  "geometry": {"coordinates":[-117.204357,33.57088],"type":"Point"}
}