{
  "type": "Feature",
  "properties": {
    "addr:full":"24145 Magic Mountain Pkwy Santa Clarita CA 91355",
    "addr:housenumber":"24145",
    "addr:postcode":"91355",
    "addr:street":"Magic Mountain Pkwy",
    "iso:country":"US",
    "sg:address":"24145 Magic Mountain Pkwy",
    "sg:city":"Santa Clarita",
    "sg:classifiers":[
        {
            "category":"Shopping",
            "subcategory":"Clothing, Apparel, & Fashions",
            "type":"Retail Goods"
        }
    ],
    "sg:phone":"+1 661 253 3462",
    "sg:postcode":"91355",
    "sg:province":"CA",
    "sg:tags":[
        "furnishing"
    ],
    "sg:website":"www.menswearhouse.com",
    "wof:name":"Men's Wearhouse",
    "wof:placetype":"venue"
},
  "geometry": {"coordinates":[-118.561128,34.41934],"type":"Point"}
}