{
  "type": "Feature",
  "properties": {
    "addr:full":"1999 Monterey Hwy San Jose CA 95112",
    "addr:housenumber":"1999",
    "addr:postcode":"95112",
    "addr:street":"Monterey Hwy",
    "iso:country":"US",
    "sg:address":"1999 Monterey Hwy",
    "sg:city":"San Jose",
    "sg:classifiers":[
        {
            "category":"Manufacturing",
            "subcategory":"Printing",
            "type":"Manufacturing & Wholesale Goods"
        }
    ],
    "sg:phone":"+1 408 292 2800",
    "sg:postcode":"95112",
    "sg:province":"CA",
    "sg:tags":[
        "periodical"
    ],
    "wof:name":"Nha Magazine",
    "wof:placetype":"venue"
},
  "geometry": {"coordinates":[-121.86270500000001,37.305266],"type":"Point"}
}