{
  "type": "Feature",
  "properties": {
    "addr:full":"10 Fullerton Court Sacramento CA 95825",
    "addr:housenumber":"10",
    "addr:postcode":"95825",
    "addr:street":"Fullerton Court",
    "iso:country":"US",
    "sg:address":"10 Fullerton Court",
    "sg:city":"Sacramento",
    "sg:classifiers":[
        {
            "category":"Professional",
            "subcategory":"Employment Agencies",
            "type":"Services"
        }
    ],
    "sg:phone":"+1 916 779 6280",
    "sg:postcode":"95825",
    "sg:province":"CA",
    "wof:name":"Etech Recruiters Dba Etech Resources",
    "wof:placetype":"venue"
},
  "geometry": {"coordinates":[-121.41165700000001,38.572847],"type":"Point"}
}