{
  "type": "Feature",
  "properties": {
    "addr:full":"1450 N Avolencia Dr Fullerton CA 92835",
    "addr:housenumber":"1450",
    "addr:postcode":"92835",
    "addr:street":"N Avolencia Dr",
    "iso:country":"US",
    "sg:address":"1450 N Avolencia Dr",
    "sg:city":"Fullerton",
    "sg:classifiers":[
        {
            "category":"Professional",
            "type":"Services"
        }
    ],
    "sg:phone":"+1 714 447 1516",
    "sg:postcode":"92835",
    "sg:province":"CA",
    "wof:name":"World Trade & Petro Svc",
    "wof:placetype":"venue"
},
  "geometry": {"coordinates":[-117.929118,33.883769],"type":"Point"}
}