{
  "type": "Feature",
  "properties": {
    "addr:full":"3460 El Camino Real Santa Clara CA 95051",
    "addr:housenumber":"3460",
    "addr:postcode":"95051",
    "addr:street":"El Camino Real",
    "iso:country":"US",
    "sg:address":"3460 El Camino Real",
    "sg:city":"Santa Clara",
    "sg:classifiers":[
        {
            "category":"Retail",
            "subcategory":"Portrait Studio",
            "type":"Services"
        },
        {
            "category":"Shopping",
            "subcategory":"Pharmacy",
            "type":"Retail Goods"
        },
        {
            "category":"Food & Beverages",
            "subcategory":"Groceries & Convenience Stores",
            "type":"Retail Goods"
        }
    ],
    "sg:phone":"+1 408 261 1044",
    "sg:postcode":"95051",
    "sg:province":"CA",
    "sg:tags":[
        "photography",
        "drugstore"
    ],
    "sg:website":"www.walgreens.com",
    "wof:name":"Walgreens Drug Store",
    "wof:placetype":"venue"
},
  "geometry": {"coordinates":[-121.991524,37.352288],"type":"Point"}
}