{
  "type": "Feature",
  "properties": {
    "addr:full":"28925 Deer Creek Trl Pine Valley CA 91962",
    "addr:housenumber":"28925",
    "addr:postcode":"91962",
    "addr:street":"Deer Creek Trl",
    "iso:country":"US",
    "sg:address":"28925 Deer Creek Trl",
    "sg:city":"Pine Valley",
    "sg:classifiers":[
        {
            "category":"Banks & Credit Unions",
            "subcategory":"Investment Brokerage",
            "type":"Services"
        }
    ],
    "sg:phone":"+1 619 473 8727",
    "sg:postcode":"91962",
    "sg:province":"CA",
    "sg:tags":[
        "consultant",
        "planning",
        "financial"
    ],
    "wof:name":"Barrett Financial Svc",
    "wof:placetype":"venue"
},
  "geometry": {"coordinates":[-116.52470099999999,32.829022],"type":"Point"}
}