{
  "type": "Feature",
  "properties": {
    "addr:full":"12787 Ramona Ave Chino CA 91710",
    "addr:housenumber":"12787",
    "addr:postcode":"91710",
    "addr:street":"Ramona Ave",
    "iso:country":"US",
    "sg:address":"12787 Ramona Ave",
    "sg:city":"Chino",
    "sg:classifiers":[
        {
            "category":"Retail",
            "subcategory":"Auto Repair",
            "type":"Services"
        }
    ],
    "sg:phone":"+1 909 628 2140",
    "sg:postcode":"91710",
    "sg:province":"CA",
    "sg:tags":[
        "body"
    ],
    "wof:name":"Coast Booth Industries",
    "wof:placetype":"venue"
},
  "geometry": {"coordinates":[-117.70666799999999,34.019443],"type":"Point"}
}