{
  "type": "Feature",
  "properties": {
    "addr:full":"23739 Lake Dr Crestline CA 92325",
    "addr:housenumber":"23739",
    "addr:postcode":"92325",
    "addr:street":"Lake Dr",
    "iso:country":"US",
    "sg:address":"23739 Lake Dr",
    "sg:city":"Crestline",
    "sg:classifiers":[
        {
            "category":"Real Estate",
            "subcategory":"Real Estate Services",
            "type":"Services"
        }
    ],
    "sg:phone":"+1 909 338 5666",
    "sg:postcode":"92325",
    "sg:province":"CA",
    "sg:tags":[
        "management",
        "property"
    ],
    "wof:name":"East Valley Association Of Realtors",
    "wof:placetype":"venue"
},
  "geometry": {"coordinates":[-117.285304,34.242286],"type":"Point"}
}