{
  "type": "Feature",
  "properties": {
    "iso:country":"US",
    "sg:address":"9912 Rush St",
    "sg:city":"South El Monte",
    "sg:classifiers":[
        {
            "category":"Retail",
            "subcategory":"Repair Shop",
            "type":"Services"
        }
    ],
    "sg:phone":"+1 626 454 3822",
    "sg:postcode":"91733",
    "sg:province":"CA",
    "sg:tags":[
        "related"
    ],
    "wof:name":"Andy's Repair & Rebuilt Mchns",
    "wof:placetype":"venue"
},
  "geometry": {"coordinates":[-118.051438,34.051763],"type":"Point"}
}