{
  "type": "Feature",
  "properties": {
    "iso:country":"US",
    "sg:address":"13427 Trillium Ln",
    "sg:city":"Oroville",
    "sg:classifiers":[
        {
            "category":"Manufacturing",
            "subcategory":"Tools & Machinery",
            "type":"Manufacturing & Wholesale Goods"
        }
    ],
    "sg:phone":"+1 530 533 6646",
    "sg:postcode":"95965",
    "sg:province":"CA",
    "sg:tags":[
        "industrial",
        "mfg"
    ],
    "wof:name":"Buffalo Machine & Engineering",
    "wof:placetype":"venue"
},
  "geometry": {"coordinates":[-121.514394,39.792834],"type":"Point"}
}