{
  "type": "Feature",
  "properties": {
    "addr:full":"2771 Clayton Rd Concord CA 94519",
    "addr:housenumber":"2771",
    "addr:postcode":"94519",
    "addr:street":"Clayton Rd",
    "iso:country":"US",
    "sg:address":"2771 Clayton Rd",
    "sg:city":"Concord",
    "sg:classifiers":[
        {
            "category":"Farming",
            "subcategory":"Farm",
            "type":"Manufacturing & Wholesale Goods"
        }
    ],
    "sg:phone":"+1 925 671 2520",
    "sg:postcode":"94519",
    "sg:province":"CA",
    "sg:tags":[
        "grower",
        "hydroponics"
    ],
    "wof:name":"Concord Indoor Garden Ctr",
    "wof:placetype":"venue"
},
  "geometry": {"coordinates":[-122.027266,37.975144],"type":"Point"}
}