{
  "type": "Feature",
  "properties": {
    "addr:full":"207 N Cloverdale Blvd Cloverdale CA 95425",
    "addr:housenumber":"207",
    "addr:postcode":"95425",
    "addr:street":"N Cloverdale Blvd",
    "iso:country":"US",
    "sg:address":"207 N Cloverdale Blvd",
    "sg:city":"Cloverdale",
    "sg:classifiers":[
        {
            "category":"Professional",
            "subcategory":"Business Services",
            "type":"Services"
        }
    ],
    "sg:phone":"+1 707 548 4547",
    "sg:postcode":"95425",
    "sg:province":"CA",
    "sg:tags":[
        "notary"
    ],
    "wof:name":"Carol Tuttle-Mobile Notary",
    "wof:placetype":"venue"
},
  "geometry": {"coordinates":[-123.018824,38.80777],"type":"Point"}
}