{
  "type": "Feature",
  "properties": {
    "addr:full":"1300 Brea Canyon Cut Off Rd Walnut CA 91789",
    "addr:housenumber":"1300",
    "addr:postcode":"91789",
    "addr:street":"Brea Canyon Cut Off Rd",
    "iso:country":"US",
    "sg:address":"1300 Brea Canyon Cut Off Rd",
    "sg:city":"Walnut",
    "sg:classifiers":[
        {
            "category":"Social Services",
            "subcategory":"Child Care",
            "type":"Services"
        }
    ],
    "sg:phone":"+1 909 598 3154",
    "sg:postcode":"91789",
    "sg:province":"CA",
    "wof:name":"Options-Surround Care-Ybarra",
    "wof:placetype":"venue"
},
  "geometry": {"coordinates":[-117.866907,33.982813],"type":"Point"}
}