{
  "type": "Feature",
  "properties": {
    "addr:full":"20409 Prairie St Chatsworth CA 91311",
    "addr:housenumber":"20409",
    "addr:postcode":"91311",
    "addr:street":"Prairie St",
    "iso:country":"US",
    "sg:address":"20409 Prairie St",
    "sg:city":"Chatsworth",
    "sg:classifiers":[
        {
            "category":"Manufacturing",
            "subcategory":"Aerospace",
            "type":"Manufacturing & Wholesale Goods"
        }
    ],
    "sg:phone":"+1 818 407 0291",
    "sg:postcode":"91311",
    "sg:province":"CA",
    "sg:tags":[
        "equipment",
        "aircraft",
        "parts"
    ],
    "sg:website":"www.robertstool.net",
    "wof:name":"Roberts Tool Co Inc",
    "wof:placetype":"venue"
},
  "geometry": {"coordinates":[-118.577822,34.239181],"type":"Point"}
}