{
  "type": "Feature",
  "properties": {
    "addr:full":"14290 Paynes Creek Rd Red Bluff CA 96080",
    "addr:housenumber":"14290",
    "addr:postcode":"96080",
    "addr:street":"Paynes Creek Rd",
    "iso:country":"US",
    "sg:address":"14290 Paynes Creek Rd",
    "sg:city":"Red Bluff",
    "sg:classifiers":[
        {
            "category":"Freight",
            "type":"Transportation"
        }
    ],
    "sg:phone":"+1 530 529 9600",
    "sg:postcode":"96080",
    "sg:province":"CA",
    "sg:tags":[
        "load",
        "truck",
        "broker"
    ],
    "wof:name":"Thornbrue Brokering Service",
    "wof:placetype":"venue"
},
  "geometry": {"coordinates":[-122.19686799999999,40.209223],"type":"Point"}
}