{
  "type": "Feature",
  "properties": {
    "iso:country":"US",
    "sg:address":"2025 W Park Ave",
    "sg:city":"Redlands",
    "sg:classifiers":[
        {
            "category":"Retail",
            "subcategory":"Auto Repair",
            "type":"Services"
        }
    ],
    "sg:phone":"+1 909 335 6000",
    "sg:postcode":"92373",
    "sg:province":"CA",
    "sg:tags":[
        "automobile",
        "customizing"
    ],
    "wof:name":"Deflated Customs",
    "wof:placetype":"venue"
},
  "geometry": {"coordinates":[-117.217493,34.059254],"type":"Point"}
}