{
  "type": "Feature",
  "properties": {
    "iso:country":"US",
    "sg:address":"5387 Poplar Blvd",
    "sg:city":"Los Angeles",
    "sg:classifiers":[
        {
            "category":"Organizations",
            "subcategory":"Religious Organization",
            "type":"Services"
        }
    ],
    "sg:phone":"+1 323 227 0654",
    "sg:postcode":"90032",
    "sg:province":"CA",
    "sg:tags":[
        "church"
    ],
    "wof:name":"Calvary Chapel Assembly Of God",
    "wof:placetype":"venue"
},
  "geometry": {"coordinates":[-118.163719,34.089948],"type":"Point"}
}