{
  "type": "Feature",
  "properties": {
    "iso:country":"US",
    "sg:address":"214 San Diego St",
    "sg:city":"Oceanside",
    "sg:classifiers":[
        {
            "category":"Banks & Credit Unions",
            "subcategory":"Bank",
            "type":"Services"
        }
    ],
    "sg:phone":"+1 760 754 8091",
    "sg:postcode":"92058",
    "sg:province":"CA",
    "sg:tags":[
        "money",
        "order"
    ],
    "wof:name":"Mailboxes Y Mas",
    "wof:placetype":"venue"
},
  "geometry": {"coordinates":[-117.369417,33.2024],"type":"Point"}
}