{
  "type": "Feature",
  "properties": {
    "iso:country":"US",
    "sg:address":"1400 Kifer Rd",
    "sg:city":"Sunnyvale",
    "sg:classifiers":[
        {
            "category":"Utilities",
            "subcategory":"Telephone",
            "type":"Services"
        }
    ],
    "sg:phone":"+1 408 328 4100",
    "sg:postcode":"94086",
    "sg:province":"CA",
    "sg:tags":[
        "distance",
        "long",
        "communication"
    ],
    "wof:name":"Qwest",
    "wof:placetype":"venue"
},
  "geometry": {"coordinates":[-121.99668,37.373755],"type":"Point"}
}