{
  "type": "Feature",
  "properties": {
    "iso:country":"US",
    "sg:address":"1100 Draper St Ste E",
    "sg:city":"Kingsburg",
    "sg:classifiers":[
        {
            "category":"Professional",
            "subcategory":"Engineering",
            "type":"Services"
        }
    ],
    "sg:phone":"+1 559 897 1303",
    "sg:postcode":"93631",
    "sg:province":"CA",
    "sg:tags":[
        "consulting",
        "engineer"
    ],
    "wof:name":"Evulich & Associates",
    "wof:placetype":"venue"
},
  "geometry": {"coordinates":[-119.55645,36.512199],"type":"Point"}
}