{
  "type": "Feature",
  "properties": {
    "iso:country":"US",
    "sg:address":"12490 Los Amigos Rd",
    "sg:city":"Healdsburg",
    "sg:classifiers":[
        {
            "category":"Farming",
            "subcategory":"Vineyard",
            "type":"Manufacturing & Wholesale Goods"
        }
    ],
    "sg:phone":"+1 707 433 2825",
    "sg:postcode":"95448",
    "sg:province":"CA",
    "sg:tags":[
        "grape"
    ],
    "wof:name":"Stone Village Vineyards",
    "wof:placetype":"venue"
},
  "geometry": {"coordinates":[-122.842007,38.585513],"type":"Point"}
}