{
  "type": "Feature",
  "properties": {
    "addr:full":"22631 Lake Forest Dr Lake Forest CA 92630",
    "addr:housenumber":"22631",
    "addr:postcode":"92630",
    "addr:street":"Lake Forest Dr",
    "iso:country":"US",
    "sg:address":"22631 Lake Forest Dr",
    "sg:city":"Lake Forest",
    "sg:classifiers":[
        {
            "category":"Shopping",
            "subcategory":"Stationery & Office Supplies",
            "type":"Retail Goods"
        },
        {
            "category":"Professional",
            "subcategory":"Printing & Photocopies",
            "type":"Services"
        },
        {
            "category":"Shopping",
            "subcategory":"Computers & Home Electronics",
            "type":"Retail Goods"
        },
        {
            "category":"Wholesale",
            "subcategory":"Computers",
            "type":"Manufacturing & Wholesale Goods"
        }
    ],
    "sg:phone":"+1 949 837 3323",
    "sg:postcode":"92630",
    "sg:province":"CA",
    "sg:tags":[
        "equipment"
    ],
    "sg:website":"www.staples.com",
    "wof:name":"Staples",
    "wof:placetype":"venue"
},
  "geometry": {"coordinates":[-117.710168,33.634001],"type":"Point"}
}