{
  "type": "Feature",
  "properties": {
    "addr:full":"1315 Yolo St Newman CA 95360",
    "addr:housenumber":"1315",
    "addr:postcode":"95360",
    "addr:street":"Yolo St",
    "iso:country":"US",
    "sg:address":"1315 Yolo St",
    "sg:city":"Newman",
    "sg:classifiers":[
        {
            "category":"Education",
            "subcategory":"School",
            "type":"Public Place"
        }
    ],
    "sg:phone":"+1 209 862 3286",
    "sg:postcode":"95360",
    "sg:province":"CA",
    "wof:name":"New Beginnings Cmty Day",
    "wof:placetype":"venue"
},
  "geometry": {"coordinates":[-121.029477,37.318461],"type":"Point"}
}