{
  "type": "Feature",
  "properties": {
    "iso:country":"US",
    "sg:address":"635 Jones Way",
    "sg:city":"Sacramento",
    "sg:classifiers":[
        {
            "category":"Wholesale",
            "subcategory":"Furniture",
            "type":"Manufacturing & Wholesale Goods"
        }
    ],
    "sg:phone":"+1 916 441 4789",
    "sg:postcode":"95818",
    "sg:province":"CA",
    "sg:tags":[
        "installation",
        "sales",
        "system"
    ],
    "wof:name":"T & T Group",
    "wof:placetype":"venue"
},
  "geometry": {"coordinates":[-121.51067,38.554666],"type":"Point"}
}