{
  "type": "Feature",
  "properties": {
    "iso:country":"US",
    "sg:address":"12707 High Bluff Dr",
    "sg:city":"San Diego",
    "sg:classifiers":[
        {
            "category":"Professional",
            "subcategory":"Lawyer & Legal Services",
            "type":"Services"
        }
    ],
    "sg:phone":"+1 858 481 7900",
    "sg:postcode":"92130",
    "sg:province":"CA",
    "sg:tags":[
        "attorney"
    ],
    "wof:name":"John R Sorensen",
    "wof:placetype":"venue"
},
  "geometry": {"coordinates":[-117.238972,32.950764],"type":"Point"}
}