{
  "type": "Feature",
  "properties": {
    "iso:country":"US",
    "sg:address":"2305 Cam Ramon",
    "sg:city":"San Ramon",
    "sg:classifiers":[
        {
            "category":"Restaurant",
            "type":"Food & Drink"
        },
        {
            "category":"Wholesale",
            "subcategory":"Dairy",
            "type":"Manufacturing & Wholesale Goods"
        }
    ],
    "sg:phone":"+1 925 242 3400",
    "sg:postcode":"94583",
    "sg:province":"CA",
    "sg:tags":[
        "product",
        "mfg",
        "ice",
        "parlor",
        "desert",
        "cream"
    ],
    "sg:website":"www.dreyers.com",
    "wof:name":"Dreyer's Grand Ice Cream",
    "wof:placetype":"venue"
},
  "geometry": {"coordinates":[-121.96733,37.777013],"type":"Point"}
}