{
  "type": "Feature",
  "properties": {
    "iso:country":"US",
    "sg:address":"428 Norman Rd",
    "sg:city":"Princeton",
    "sg:classifiers":[
        {
            "category":"Education",
            "subcategory":"School",
            "type":"Public Place"
        }
    ],
    "sg:phone":"+1 530 439 2501",
    "sg:postcode":"95932",
    "sg:province":"CA",
    "wof:name":"Princeton Elementary School",
    "wof:placetype":"venue"
},
  "geometry": {"coordinates":[-122.045795,39.406399],"type":"Point"}
}