{
  "type": "Feature",
  "properties": {
    "addr:full":"7270 Victoria Park Ln Etiwanda CA 91739",
    "addr:housenumber":"7270",
    "addr:postcode":"91739",
    "addr:street":"Victoria Park Ln",
    "iso:country":"US",
    "sg:address":"7270 Victoria Park Ln",
    "sg:city":"Etiwanda",
    "sg:classifiers":[
        {
            "category":"Health Services",
            "subcategory":"Chiropractor",
            "type":"Services"
        }
    ],
    "sg:phone":"+1 909 899 5824",
    "sg:postcode":"91739",
    "sg:province":"CA",
    "wof:name":"Marc Chiropractic Svc",
    "wof:placetype":"venue"
},
  "geometry": {"coordinates":[-117.529455,34.122733],"type":"Point"}
}