{
  "type": "Feature",
  "properties": {
    "iso:country":"US",
    "sg:address":"1427 N Long Beach Blvd",
    "sg:city":"Long Beach",
    "sg:classifiers":[
        {
            "category":"Retail",
            "subcategory":"Auto Repair",
            "type":"Services"
        }
    ],
    "sg:phone":"+1 562 489 2877",
    "sg:postcode":"90813",
    "sg:province":"CA",
    "sg:tags":[
        "body",
        "automobile",
        "painting"
    ],
    "wof:name":"Sam's Auto Body",
    "wof:placetype":"venue"
},
  "geometry": {"coordinates":[-118.189459,33.784956],"type":"Point"}
}