{
  "type": "Feature",
  "properties": {
    "addr:full":"6244 Astronaut Ln Citrus Heights CA 95621",
    "addr:housenumber":"6244",
    "addr:postcode":"95621",
    "addr:street":"Astronaut Ln",
    "iso:country":"US",
    "sg:address":"6244 Astronaut Ln",
    "sg:city":"Citrus Heights",
    "sg:classifiers":[
        {
            "category":"Manufacturing",
            "subcategory":"Apparel",
            "type":"Manufacturing & Wholesale Goods"
        }
    ],
    "sg:phone":"+1 916 726 8101",
    "sg:postcode":"95621",
    "sg:province":"CA",
    "wof:name":"Go With Shar",
    "wof:placetype":"venue"
},
  "geometry": {"coordinates":[-121.318645,38.690685],"type":"Point"}
}