{
  "type": "Feature",
  "properties": {
    "addr:full":"2025 McKain St Calabasas CA 91302",
    "addr:housenumber":"2025",
    "addr:postcode":"91302",
    "addr:street":"Mckain St",
    "iso:country":"US",
    "sg:address":"2025 McKain St",
    "sg:city":"Calabasas",
    "sg:classifiers":[
        {
            "category":"Travel",
            "subcategory":"Hotels & Motels",
            "type":"Entertainment"
        }
    ],
    "sg:phone":"+1 818 222 6900",
    "sg:postcode":"91302",
    "sg:province":"CA",
    "wof:name":"Ashram Retreat the",
    "wof:placetype":"venue"
},
  "geometry": {"coordinates":[-118.659606,34.097925],"type":"Point"}
}