{
  "type": "Feature",
  "properties": {
    "iso:country":"US",
    "sg:address":"139 Turquoise Dr",
    "sg:city":"Perris",
    "sg:classifiers":[
        {
            "category":"Transit Center",
            "subcategory":"Freight",
            "type":"Transportation"
        },
        {
            "category":"Freight",
            "type":"Transportation"
        }
    ],
    "sg:phone":"+1 951 657 8159",
    "sg:postcode":"92571",
    "sg:province":"CA",
    "sg:tags":[
        "local",
        "trucking-motor",
        "trucking"
    ],
    "wof:name":"Gbp Trucking Co.",
    "wof:placetype":"venue"
},
  "geometry": {"coordinates":[-117.222764,33.804214],"type":"Point"}
}