{
  "type": "Feature",
  "properties": {
    "addr:full":"9600 Reseda Blvd Northridge CA 91324",
    "addr:housenumber":"9600",
    "addr:postcode":"91324",
    "addr:street":"Reseda Blvd",
    "iso:country":"US",
    "sg:address":"9600 Reseda Blvd",
    "sg:city":"Northridge",
    "sg:classifiers":[
        {
            "category":"Health Services",
            "subcategory":"Doctor",
            "type":"Services"
        }
    ],
    "sg:phone":"+1 818 717 8945",
    "sg:postcode":"91324",
    "sg:province":"CA",
    "sg:tags":[
        "medicine",
        "preventive"
    ],
    "wof:name":"Kim Bok Hee",
    "wof:placetype":"venue"
},
  "geometry": {"coordinates":[-118.53609,34.245473],"type":"Point"}
}