{
  "type": "Feature",
  "properties": {
    "addr:full":"10890 Coloma Road Rancho Cordova CA 95670",
    "addr:housenumber":"10890",
    "addr:postcode":"95670",
    "addr:street":"Coloma Road",
    "iso:country":"US",
    "sg:address":"10890 Coloma Road",
    "sg:city":"Rancho Cordova",
    "sg:classifiers":[
        {
            "category":"Real Estate",
            "subcategory":"Real Estate Operator",
            "type":"Services"
        }
    ],
    "sg:phone":"+1 916 852 8109",
    "sg:postcode":"95670",
    "sg:province":"CA",
    "sg:tags":[
        "apartment"
    ],
    "wof:name":"Gold Crossing Apartments",
    "wof:placetype":"venue"
},
  "geometry": {"coordinates":[-121.281407,38.616502],"type":"Point"}
}