{
  "type": "Feature",
  "properties": {
    "iso:country":"US",
    "sg:address":"2034 Cliff Dr",
    "sg:city":"Santa Barbara",
    "sg:classifiers":[
        {
            "category":"Health Services",
            "subcategory":"Doctor",
            "type":"Services"
        }
    ],
    "sg:phone":"+1 805 965 5223",
    "sg:postcode":"93109",
    "sg:province":"CA",
    "sg:tags":[
        "physician",
        "surgeon"
    ],
    "wof:name":"Advanced Eyecare Optometry",
    "wof:placetype":"venue"
},
  "geometry": {"coordinates":[-119.72573300000001,34.40242],"type":"Point"}
}