{
  "type": "Feature",
  "properties": {
    "addr:full":"2242 Camden Ave Ste 200 San Jose CA 95124",
    "addr:housenumber":"2242",
    "addr:postcode":"95124",
    "addr:street":"Camden Ave Ste 200",
    "iso:country":"US",
    "sg:address":"2242 Camden Ave Ste 200",
    "sg:city":"San Jose",
    "sg:classifiers":[
        {
            "category":"Health Services",
            "subcategory":"Doctor",
            "type":"Services"
        }
    ],
    "sg:phone":"+1 408 377 3776",
    "sg:postcode":"95124",
    "sg:province":"CA",
    "sg:tags":[
        "practice",
        "family"
    ],
    "sg:website":"allaboutfamilyhealth.com/",
    "wof:name":"Svetlana Gorelikova, MD",
    "wof:placetype":"venue"
},
  "geometry": {"coordinates":[-121.940237,37.265027],"type":"Point"}
}