{
  "type": "Feature",
  "properties": {
    "iso:country":"US",
    "sg:address":"6645 Alhambra Ave",
    "sg:city":"Martinez",
    "sg:classifiers":[
        {
            "category":"Wholesale",
            "subcategory":"Stationery",
            "type":"Manufacturing & Wholesale Goods"
        }
    ],
    "sg:phone":"+1 925 933 6328",
    "sg:postcode":"94553",
    "sg:province":"CA",
    "sg:tags":[
        "school",
        "supply"
    ],
    "wof:name":"Neat Solutions For Health",
    "wof:placetype":"venue"
},
  "geometry": {"coordinates":[-122.093651,37.959415],"type":"Point"}
}