{
  "type": "Feature",
  "properties": {
    "iso:country":"US",
    "sg:address":"9117 E Stockton Blvd",
    "sg:city":"Elk Grove",
    "sg:classifiers":[
        {
            "category":"Banks & Credit Unions",
            "subcategory":"Bank",
            "type":"Services"
        }
    ],
    "sg:phone":"+1 916 714 4522",
    "sg:postcode":"95624",
    "sg:province":"CA",
    "sg:tags":[
        "financing"
    ],
    "sg:website":"www.householdfinance.com",
    "wof:name":"Household Finance",
    "wof:placetype":"venue"
},
  "geometry": {"coordinates":[-121.39817499999999,38.430643],"type":"Point"}
}