{
  "type": "Feature",
  "properties": {
    "iso:country":"US",
    "sg:address":"3926 Yana Pl",
    "sg:city":"Davis",
    "sg:classifiers":[
        {
            "category":"Professional",
            "subcategory":"Research",
            "type":"Services"
        }
    ],
    "sg:phone":"+1 530 756 7367",
    "sg:postcode":"95618",
    "sg:province":"CA",
    "sg:tags":[
        "nonphysical",
        "commercial"
    ],
    "wof:name":"Bayer Cropscience Ltd Partnr",
    "wof:placetype":"venue"
},
  "geometry": {"coordinates":[-121.704097,38.54368],"type":"Point"}
}