{
  "type": "Feature",
  "properties": {
    "iso:country":"US",
    "sg:address":"930 Irwin St",
    "sg:city":"San Rafael",
    "sg:classifiers":[
        {
            "category":"Social Services",
            "subcategory":"Job Training",
            "type":"Services"
        }
    ],
    "sg:phone":"+1 415 258 0808",
    "sg:postcode":"94901",
    "sg:province":"CA",
    "sg:tags":[
        "career",
        "counseling",
        "vocational"
    ],
    "wof:name":"Berkley & Brodzinsky Assoc",
    "wof:placetype":"venue"
},
  "geometry": {"coordinates":[-122.520688,37.971909],"type":"Point"}
}