{
  "type": "Feature",
  "properties": {
    "iso:country":"US",
    "sg:address":"1203 S Western Ave",
    "sg:city":"Anaheim",
    "sg:classifiers":[
        {
            "category":"Shopping",
            "subcategory":"Florist",
            "type":"Retail Goods"
        }
    ],
    "sg:phone":"+1 714 220 5939",
    "sg:postcode":"92804",
    "sg:province":"CA",
    "wof:name":"Rosa De Guadlupe Flower Shop",
    "wof:placetype":"venue"
},
  "geometry": {"coordinates":[-118.205866,33.816258],"type":"Point"}
}