{
  "type": "Feature",
  "properties": {
    "addr:full":"146 Cambridge Ave San Leandro CA 94577",
    "addr:housenumber":"146",
    "addr:postcode":"94577",
    "addr:street":"Cambridge Ave",
    "iso:country":"US",
    "sg:address":"146 Cambridge Ave",
    "sg:city":"San Leandro",
    "sg:classifiers":[
        {
            "category":"Real Estate",
            "subcategory":"Real Estate Agent",
            "type":"Services"
        }
    ],
    "sg:phone":"+1 510 569 6501",
    "sg:postcode":"94577",
    "sg:province":"CA",
    "wof:name":"SBSH",
    "wof:placetype":"venue"
},
  "geometry": {"coordinates":[-122.160466,37.735031],"type":"Point"}
}