{
  "type": "Feature",
  "properties": {
    "iso:country":"US",
    "sg:address":"4112 Monterey Hwy",
    "sg:city":"San Jose",
    "sg:classifiers":[
        {
            "category":"Personal",
            "subcategory":"Beauty Salon",
            "type":"Services"
        }
    ],
    "sg:phone":"+1 408 972 2130",
    "sg:postcode":"95111",
    "sg:province":"CA",
    "sg:tags":[
        "school"
    ],
    "wof:name":"Ganayes Academy Of Cosmotology",
    "wof:placetype":"venue"
},
  "geometry": {"coordinates":[-121.835306,37.278202],"type":"Point"}
}