{
  "type": "Feature",
  "properties": {
    "addr:full":"605 8th St Modesto CA 95354",
    "addr:housenumber":"605",
    "addr:postcode":"ca 95354",
    "addr:street":"8Th St",
    "iso:country":"US",
    "sg:address":"605 8th St",
    "sg:city":"Modesto",
    "sg:classifiers":[
        {
            "category":"Autos & Motor Vehicles",
            "subcategory":"Auto Supplies",
            "type":"Retail Goods"
        }
    ],
    "sg:phone":"+1 209 522 6370",
    "sg:postcode":"95354",
    "sg:province":"CA",
    "sg:tags":[
        "equipment",
        "racing",
        "car",
        "automobile"
    ],
    "wof:name":"David's Racing Products",
    "wof:placetype":"venue"
},
  "geometry": {"coordinates":[-120.99875900000001,37.636108],"type":"Point"}
}