{
  "type": "Feature",
  "properties": {
    "addr:full":"43 Roxbury St Santa Clara CA 95050",
    "addr:housenumber":"43",
    "addr:postcode":"95050",
    "addr:street":"Roxbury St",
    "iso:country":"US",
    "sg:address":"43 Roxbury St",
    "sg:city":"Santa Clara",
    "sg:classifiers":[
        {
            "category":"Building & Trades",
            "subcategory":"Construction",
            "type":"Services"
        }
    ],
    "sg:phone":"+1 408 249 2303",
    "sg:postcode":"95050",
    "sg:province":"CA",
    "sg:tags":[
        "concrete",
        "contractor"
    ],
    "wof:name":"Ammann Concrete Construction",
    "wof:placetype":"venue"
},
  "geometry": {"coordinates":[-121.942431,37.338853],"type":"Point"}
}