{
  "type": "Feature",
  "properties": {
    "addr:full":"15280 Via Montana Desert Hot Spgs CA 92240",
    "addr:housenumber":"15280",
    "addr:postcode":"92240",
    "addr:street":"Via Montana Desert Hot Spgs",
    "iso:country":"US",
    "sg:address":"15280 Via Montana",
    "sg:city":"Desert Hot Spgs",
    "sg:classifiers":[
        {
            "category":"Personal",
            "subcategory":"Tattoo Parlor",
            "type":"Services"
        }
    ],
    "sg:phone":"+1 760 251 4988",
    "sg:postcode":"92240",
    "sg:province":"CA",
    "sg:tags":[
        "tattooing"
    ],
    "wof:name":"Eagle's Salon Tatto & Body",
    "wof:placetype":"venue"
},
  "geometry": {"coordinates":[-116.494029,33.937439],"type":"Point"}
}