{
  "type": "Feature",
  "properties": {
    "iso:country":"US",
    "sg:address":"14540 Hamlin St",
    "sg:city":"Van Nuys",
    "sg:classifiers":[
        {
            "category":"Professional",
            "type":"Services"
        }
    ],
    "sg:phone":"+1 818 376 0470",
    "sg:postcode":"91411",
    "sg:province":"CA",
    "sg:tags":[
        "establishment"
    ],
    "wof:name":"Cwca",
    "wof:placetype":"venue"
},
  "geometry": {"coordinates":[-118.45016200000001,34.188591],"type":"Point"}
}