{
  "type": "Feature",
  "properties": {
    "iso:country":"US",
    "sg:address":"2008 Kammerer Ave",
    "sg:city":"San Jose",
    "sg:classifiers":[
        {
            "category":"Organizations",
            "subcategory":"Religious Organization",
            "type":"Services"
        }
    ],
    "sg:phone":"+1 408 923 5271",
    "sg:postcode":"95116",
    "sg:province":"CA",
    "wof:name":"Cityteam Ministries",
    "wof:placetype":"venue"
},
  "geometry": {"coordinates":[-121.844719,37.350268],"type":"Point"}
}