{
  "type": "Feature",
  "properties": {
    "addr:full":"4202 Voltaire St San Diego CA 92107",
    "addr:housenumber":"4202",
    "addr:postcode":"92107",
    "addr:street":"Voltaire St",
    "iso:country":"US",
    "sg:address":"4202 Voltaire St",
    "sg:city":"San Diego",
    "sg:classifiers":[
        {
            "category":"Bars & Pubs",
            "type":"Food & Drink"
        }
    ],
    "sg:phone":"+1 619 224 4979",
    "sg:postcode":"92107",
    "sg:province":"CA",
    "sg:tags":[
        "lounge",
        "diva",
        "cocktail"
    ],
    "wof:name":"Catalina Lounge",
    "wof:placetype":"venue"
},
  "geometry": {"coordinates":[-117.235001,32.743801],"type":"Point"}
}