{
  "type": "Feature",
  "properties": {
    "addr:full":"2005 W Burbank Blvd Burbank CA 91506",
    "addr:housenumber":"2005",
    "addr:postcode":"91506",
    "addr:street":"W Burbank Blvd",
    "iso:country":"US",
    "sg:address":"2005 W Burbank Blvd",
    "sg:city":"Burbank",
    "sg:classifiers":[
        {
            "category":"Wholesale",
            "subcategory":"Machinery & Supplies",
            "type":"Manufacturing & Wholesale Goods"
        }
    ],
    "sg:phone":"+1 818 567 0168",
    "sg:postcode":"91506",
    "sg:province":"CA",
    "sg:tags":[
        "equipment",
        "printing"
    ],
    "wof:name":"M C Enterprises",
    "wof:placetype":"venue"
},
  "geometry": {"coordinates":[-118.333652,34.180305],"type":"Point"}
}