{
  "type": "Feature",
  "properties": {
    "iso:country":"US",
    "sg:address":"327 Cimmaron Cir",
    "sg:city":"Folsom",
    "sg:classifiers":[
        {
            "category":"Real Estate",
            "subcategory":"Architect",
            "type":"Services"
        }
    ],
    "sg:phone":"+1 916 410 0822",
    "sg:postcode":"95630",
    "sg:province":"CA",
    "wof:name":"Cowhie Designs",
    "wof:placetype":"venue"
},
  "geometry": {"coordinates":[-121.157494,38.683921],"type":"Point"}
}