{
  "type": "Feature",
  "properties": {
    "iso:country":"US",
    "sg:address":"9815 Independence Ave",
    "sg:city":"Chatsworth",
    "sg:classifiers":[
        {
            "category":"Autos & Motor Vehicles",
            "subcategory":"Automobile Sales",
            "type":"Retail Goods"
        }
    ],
    "sg:phone":"+1 818 998 8881",
    "sg:postcode":"91311",
    "sg:province":"CA",
    "sg:tags":[
        "car",
        "dealer"
    ],
    "wof:name":"Frontline Auto Mart",
    "wof:placetype":"venue"
},
  "geometry": {"coordinates":[-118.590811,34.24789],"type":"Point"}
}