{
  "type": "Feature",
  "properties": {
    "iso:country":"US",
    "sg:address":"1918 Hopkins St",
    "sg:city":"Berkeley",
    "sg:classifiers":[
        {
            "category":"Professional",
            "subcategory":"Business Services",
            "type":"Services"
        }
    ],
    "sg:phone":"+1 510 525 1961",
    "sg:postcode":"94707",
    "sg:province":"CA",
    "sg:tags":[
        "consultant",
        "coach"
    ],
    "wof:name":"Howell Consulting",
    "wof:placetype":"venue"
},
  "geometry": {"coordinates":[-122.274355,37.885904],"type":"Point"}
}