{
  "type": "Feature",
  "properties": {
    "iso:country":"US",
    "sg:address":"1401 S Brookhurst Rd",
    "sg:city":"Fullerton",
    "sg:classifiers":[
        {
            "category":"Shopping",
            "subcategory":"Pharmacy",
            "type":"Retail Goods"
        }
    ],
    "sg:phone":"+1 714 680 9766",
    "sg:postcode":"92833",
    "sg:province":"CA",
    "wof:name":"Family Meds Pharmacy",
    "wof:placetype":"venue"
},
  "geometry": {"coordinates":[-117.959383,33.859077],"type":"Point"}
}