{
  "type": "Feature",
  "properties": {
    "iso:country":"US",
    "sg:address":"1204 Burlingame Ave #8",
    "sg:city":"Burlingame",
    "sg:classifiers":[
        {
            "category":"Communications",
            "type":"Services"
        }
    ],
    "sg:phone":"+1 650 288 1141",
    "sg:postcode":"94010",
    "sg:province":"CA",
    "sg:tags":[
        "web",
        "design"
    ],
    "sg:website":"www.raddonline.com",
    "wof:name":"RaddOnline",
    "wof:placetype":"venue"
},
  "geometry": {"coordinates":[-122.346279,37.579147],"type":"Point"}
}