{
  "type": "Feature",
  "properties": {
    "iso:country":"US",
    "sg:address":"110 W C St",
    "sg:city":"San Diego",
    "sg:classifiers":[
        {
            "category":"Government",
            "subcategory":"Court House",
            "type":"Public Place"
        }
    ],
    "sg:phone":"+1 619 231 1195",
    "sg:postcode":"92101",
    "sg:province":"CA",
    "sg:tags":[
        "legal"
    ],
    "wof:name":"Dowdy Rhonda A",
    "wof:placetype":"venue"
},
  "geometry": {"coordinates":[-117.164647,32.716813],"type":"Point"}
}