{
  "type": "Feature",
  "properties": {
    "addr:full":"12400 Ventura Boulevard Studio City CA 91604",
    "addr:housenumber":"12400",
    "addr:postcode":"91604",
    "addr:street":"Ventura Boulevard",
    "iso:country":"US",
    "sg:address":"12400 Ventura Boulevard",
    "sg:city":"Studio City",
    "sg:classifiers":[
        {
            "category":"Building & Trades",
            "subcategory":"Landscaping Services",
            "type":"Services"
        }
    ],
    "sg:phone":"+1 818 435 7336",
    "sg:postcode":"91604",
    "sg:province":"CA",
    "sg:website":"landscapinginstudiocity.info",
    "wof:name":"Elite Landscape Maintenance",
    "wof:placetype":"venue"
},
  "geometry": {"coordinates":[-118.40315699999999,34.142589],"type":"Point"}
}