{
  "type": "Feature",
  "properties": {
    "addr:full":"20265 Lake Chabot Rd Castro Valley CA 94546",
    "addr:housenumber":"20265",
    "addr:postcode":"94546",
    "addr:street":"Lake Chabot Rd",
    "iso:country":"US",
    "sg:address":"20265 Lake Chabot Rd",
    "sg:city":"Castro Valley",
    "sg:classifiers":[
        {
            "category":"Health Services",
            "subcategory":"Medical Lab",
            "type":"Services"
        }
    ],
    "sg:phone":"+1 510 889 1279",
    "sg:postcode":"94546",
    "sg:province":"CA",
    "sg:tags":[
        "laboratory"
    ],
    "wof:name":"Castro Valley Dental Lab",
    "wof:placetype":"venue"
},
  "geometry": {"coordinates":[-122.08743,37.698766],"type":"Point"}
}