{
  "type": "Feature",
  "properties": {
    "iso:country":"US",
    "sg:address":"1701 E Edinger Ave Ste D-1",
    "sg:city":"Santa Ana",
    "sg:classifiers":[
        {
            "category":"Home & Garden",
            "subcategory":"Furniture",
            "type":"Retail Goods"
        }
    ],
    "sg:phone":"+1 714 569 0690",
    "sg:postcode":"92705",
    "sg:province":"CA",
    "sg:tags":[
        "store"
    ],
    "sg:website":"www.farbelowretail.com",
    "wof:name":"Far Below Retail",
    "wof:placetype":"venue"
},
  "geometry": {"coordinates":[-117.843587,33.727722],"type":"Point"}
}