{
  "type": "Feature",
  "properties": {
    "addr:full":"571 Foothill Blvd Napa CA 94558",
    "addr:housenumber":"571",
    "addr:postcode":"94558",
    "addr:street":"Foothill Blvd",
    "iso:country":"US",
    "sg:address":"571 Foothill Blvd",
    "sg:city":"Napa",
    "sg:classifiers":[
        {
            "category":"Organizations",
            "subcategory":"Community Association",
            "type":"Services"
        }
    ],
    "sg:phone":"+1 707 226 6897",
    "sg:postcode":"94558",
    "sg:province":"CA",
    "sg:tags":[
        "club"
    ],
    "wof:name":"Napa Valley Wrestling Club",
    "wof:placetype":"venue"
},
  "geometry": {"coordinates":[-122.310169,38.293291],"type":"Point"}
}