{
  "type": "Feature",
  "properties": {
    "addr:full":"71 Daggett Dr San Jose CA 95134",
    "addr:housenumber":"71",
    "addr:postcode":"95134",
    "addr:street":"Daggett Dr",
    "iso:country":"US",
    "sg:address":"71 Daggett Dr",
    "sg:city":"San Jose",
    "sg:classifiers":[
        {
            "category":"Manufacturing",
            "subcategory":"Tools & Machinery",
            "type":"Manufacturing & Wholesale Goods"
        }
    ],
    "sg:phone":"+1 510 353 6000",
    "sg:postcode":"95134",
    "sg:province":"CA",
    "sg:tags":[
        "equipment",
        "system",
        "automation"
    ],
    "sg:website":"www.vikingse.com",
    "wof:name":"DYMATIX",
    "wof:placetype":"venue"
},
  "geometry": {"coordinates":[-121.930065,37.395946],"type":"Point"}
}