{
  "type": "Feature",
  "properties": {
    "iso:country":"US",
    "sg:address":"210 Encinal St",
    "sg:city":"Santa Cruz",
    "sg:classifiers":[
        {
            "category":"Manufacturing",
            "subcategory":"Tools & Machinery",
            "type":"Manufacturing & Wholesale Goods"
        }
    ],
    "sg:phone":"+1 831 427 3774",
    "sg:postcode":"95060",
    "sg:province":"CA",
    "sg:tags":[
        "physician",
        "surgeon"
    ],
    "wof:name":"Donley Battery Co",
    "wof:placetype":"venue"
},
  "geometry": {"coordinates":[-122.03231,36.986602],"type":"Point"}
}