{
  "type": "Feature",
  "properties": {
    "addr:full":"927 6th Ave San Diego CA 92101",
    "addr:housenumber":"927",
    "addr:postcode":"92101",
    "addr:street":"6Th Ave",
    "iso:country":"US",
    "sg:address":"927 6th Ave",
    "sg:city":"San Diego",
    "sg:classifiers":[
        {
            "category":"Travel",
            "subcategory":"Hotels & Motels",
            "type":"Entertainment"
        }
    ],
    "sg:phone":"+1 619 232 1517",
    "sg:postcode":"92101",
    "sg:province":"CA",
    "wof:name":"Beaumanor",
    "wof:placetype":"venue"
},
  "geometry": {"coordinates":[-117.158997,32.715199],"type":"Point"}
}