{
  "type": "Feature",
  "properties": {
    "iso:country":"US",
    "sg:address":"24389 Ave de Los Ninos",
    "sg:city":"Laguna Niguel",
    "sg:classifiers":[
        {
            "category":"Shopping",
            "subcategory":"Computers & Home Electronics",
            "type":"Retail Goods"
        }
    ],
    "sg:phone":"+1 949 842 1781",
    "sg:postcode":"92677",
    "sg:province":"CA",
    "sg:tags":[
        "software"
    ],
    "wof:name":"Wild Water Software Wild Water",
    "wof:placetype":"venue"
},
  "geometry": {"coordinates":[-117.705669,33.566693],"type":"Point"}
}