{
  "type": "Feature",
  "properties": {
    "iso:country":"US",
    "sg:address":"1172 Surfwood Lane",
    "sg:city":"San Diego",
    "sg:classifiers":[
        {
            "category":"Personal",
            "subcategory":"Massage",
            "type":"Services"
        }
    ],
    "sg:phone":"+1 619 946 5465",
    "sg:postcode":"92154",
    "sg:province":"CA",
    "wof:name":"Barnes Tammy Dba Apms",
    "wof:placetype":"venue"
},
  "geometry": {"coordinates":[-117.02346799999999,32.576336],"type":"Point"}
}