{
  "type": "Feature",
  "properties": {
    "addr:full":"17066 Saddleback Ln Grass Valley CA 95949",
    "addr:housenumber":"17066",
    "addr:postcode":"95949",
    "addr:street":"Saddleback Ln",
    "iso:country":"US",
    "sg:address":"17066 Saddleback Ln",
    "sg:city":"Grass Valley",
    "sg:classifiers":[
        {
            "category":"Farming",
            "subcategory":"Farm",
            "type":"Manufacturing & Wholesale Goods"
        }
    ],
    "sg:phone":"+1 530 268 0767",
    "sg:postcode":"95949",
    "sg:province":"CA",
    "wof:name":"Thyme & Thyme Again Herb Farm",
    "wof:placetype":"venue"
},
  "geometry": {"coordinates":[-121.12854,39.065496],"type":"Point"}
}