{
  "type": "Feature",
  "properties": {
    "addr:full":"107 Susan St Vallejo CA 94589",
    "addr:housenumber":"107",
    "addr:postcode":"94589",
    "addr:street":"Susan St",
    "iso:country":"US",
    "sg:address":"107 Susan St",
    "sg:city":"Vallejo",
    "sg:classifiers":[
        {
            "category":"Retail",
            "subcategory":"Auto Repair",
            "type":"Services"
        }
    ],
    "sg:phone":"+1 707 310 4682",
    "sg:postcode":"94589",
    "sg:province":"CA",
    "sg:tags":[
        "lubricating"
    ],
    "wof:name":"Kelesa Services",
    "wof:placetype":"venue"
},
  "geometry": {"coordinates":[-122.265593,38.146644],"type":"Point"}
}