{
  "type": "Feature",
  "properties": {
    "addr:full":"122 S Evergreen Ave Los Angeles CA 90033",
    "addr:housenumber":"122",
    "addr:postcode":"90033",
    "addr:street":"S Evergreen Ave",
    "iso:country":"US",
    "sg:address":"122 S Evergreen Ave",
    "sg:city":"Los Angeles",
    "sg:classifiers":[
        {
            "category":"Education",
            "subcategory":"School",
            "type":"Public Place"
        }
    ],
    "sg:phone":"+1 323 780 8885",
    "sg:postcode":"90033",
    "sg:province":"CA",
    "sg:tags":[
        "academic",
        "special"
    ],
    "wof:name":"Evergreen Academy",
    "wof:placetype":"venue"
},
  "geometry": {"coordinates":[-118.20312,34.039232],"type":"Point"}
}