{
  "type": "Feature",
  "properties": {
    "iso:country":"US",
    "sg:address":"11565 E Sussex Ave",
    "sg:city":"Sanger",
    "sg:classifiers":[
        {
            "category":"Mining & Drilling",
            "type":"Manufacturing & Wholesale Goods"
        }
    ],
    "sg:phone":"+1 559 618 1043",
    "sg:postcode":"93657",
    "sg:province":"CA",
    "sg:tags":[
        "boring",
        "contractor"
    ],
    "wof:name":"Smotherman Drilling & Trenching",
    "wof:placetype":"venue"
},
  "geometry": {"coordinates":[-119.579882,36.791014],"type":"Point"}
}