{
  "type": "Feature",
  "properties": {
    "iso:country":"US",
    "sg:address":"451 Dela Vina Ave",
    "sg:city":"Monterey",
    "sg:classifiers":[
        {
            "category":"Banks & Credit Unions",
            "subcategory":"Financial Services",
            "type":"Services"
        }
    ],
    "sg:phone":"+1 831 372 1030",
    "sg:postcode":"93940",
    "sg:province":"CA",
    "sg:tags":[
        "trust",
        "management"
    ],
    "wof:name":"Susan M Miller",
    "wof:placetype":"venue"
},
  "geometry": {"coordinates":[-121.859899,36.597869],"type":"Point"}
}