{
  "type": "Feature",
  "properties": {
    "addr:full":"15010 S Elm Ave Caruthers CA 93609",
    "addr:housenumber":"15010",
    "addr:postcode":"93609",
    "addr:street":"S Elm Ave",
    "iso:country":"US",
    "sg:address":"15010 S Elm Ave",
    "sg:city":"Caruthers",
    "sg:classifiers":[
        {
            "category":"Food & Beverages",
            "subcategory":"Groceries & Convenience Stores",
            "type":"Retail Goods"
        }
    ],
    "sg:phone":"+1 559 864 3832",
    "sg:postcode":"93609",
    "sg:province":"CA",
    "wof:name":"Elder's Mini Mart",
    "wof:placetype":"venue"
},
  "geometry": {"coordinates":[-119.791,36.517101],"type":"Point"}
}