{
  "type": "Feature",
  "properties": {
    "addr:full":"200 A St Crescent City CA 95531",
    "addr:housenumber":"200",
    "addr:postcode":"95531",
    "addr:street":"A St Crescent",
    "iso:country":"US",
    "sg:address":"200 A St",
    "sg:city":"Crescent City",
    "sg:classifiers":[
        {
            "category":"Health Services",
            "subcategory":"Doctor",
            "type":"Services"
        }
    ],
    "sg:phone":"+1 707 465 6925",
    "sg:postcode":"95531",
    "sg:province":"CA",
    "sg:tags":[
        "clinic"
    ],
    "wof:name":"Del Norte Community Health Ctr",
    "wof:placetype":"venue"
},
  "geometry": {"coordinates":[-124.20411,41.748844],"type":"Point"}
}