{
  "type": "Feature",
  "properties": {
    "addr:full":"23228 Hawthorne Blvd Torrance CA 90505",
    "addr:housenumber":"23228",
    "addr:postcode":"90505",
    "addr:street":"Hawthorne Blvd",
    "iso:country":"US",
    "sg:address":"23228 Hawthorne Blvd",
    "sg:city":"Torrance",
    "sg:classifiers":[
        {
            "category":"Banks & Credit Unions",
            "subcategory":"Investment Brokerage",
            "type":"Services"
        }
    ],
    "sg:phone":"+1 310 326 8848",
    "sg:postcode":"90505",
    "sg:province":"CA",
    "sg:tags":[
        "stock",
        "bond"
    ],
    "wof:name":"Optima Securities Inc",
    "wof:placetype":"venue"
},
  "geometry": {"coordinates":[-118.350917,33.813938],"type":"Point"}
}