{
  "type": "Feature",
  "properties": {
    "iso:country":"US",
    "sg:address":"7041 Koll Center Pkwy",
    "sg:city":"Pleasanton",
    "sg:classifiers":[
        {
            "category":"Real Estate",
            "subcategory":"Real Estate Services",
            "type":"Services"
        }
    ],
    "sg:phone":"+1 925 249 6720",
    "sg:postcode":"94566",
    "sg:province":"CA",
    "sg:tags":[
        "company",
        "title"
    ],
    "wof:name":"Chicago Title Co",
    "wof:placetype":"venue"
},
  "geometry": {"coordinates":[-121.899791,37.662442],"type":"Point"}
}