{
  "type": "Feature",
  "properties": {
    "addr:full":"7041 Koll Center Pkwy Pleasanton CA 94566",
    "addr:postcode":"7041;94566",
    "addr:street":"Center Pkwy",
    "iso:country":"US",
    "sg:address":"7041 Koll Center Pkwy",
    "sg:city":"Pleasanton",
    "sg:classifiers":[
        {
            "category":"Real Estate",
            "subcategory":"Real Estate Services",
            "type":"Services"
        }
    ],
    "sg:phone":"+1 925 249 6720",
    "sg:postcode":"94566",
    "sg:province":"CA",
    "sg:tags":[
        "company",
        "title"
    ],
    "wof:name":"Chicago Title Co",
    "wof:placetype":"venue"
},
  "geometry": {"coordinates":[-121.89979099999999,37.662442],"type":"Point"}
}