{
  "type": "Feature",
  "properties": {
    "iso:country":"US",
    "sg:address":"1740 Tuolumne St",
    "sg:city":"Vallejo",
    "sg:classifiers":[
        {
            "category":"Food & Beverages",
            "subcategory":"Groceries & Convenience Stores",
            "type":"Retail Goods"
        }
    ],
    "sg:phone":"+1 707 645 7305",
    "sg:postcode":"94589",
    "sg:province":"CA",
    "sg:tags":[
        "grocer"
    ],
    "wof:name":"Albertson's",
    "wof:placetype":"venue"
},
  "geometry": {"coordinates":[-122.237945,38.124741],"type":"Point"}
}