{
  "type": "Feature",
  "properties": {
    "addr:full":"2100 Merced St San Leandro CA 94579",
    "addr:housenumber":"2100",
    "addr:postcode":"94579",
    "addr:street":"Merced St",
    "iso:country":"US",
    "sg:address":"2100 Merced St",
    "sg:city":"San Leandro",
    "sg:classifiers":[
        {
            "category":"Organizations",
            "subcategory":"Labor Organization",
            "type":"Services"
        }
    ],
    "sg:phone":"+1 510 895 8853",
    "sg:postcode":"94579",
    "sg:province":"CA",
    "sg:website":"www.teamsters853.org",
    "wof:name":"Teamsters Union",
    "wof:placetype":"venue"
},
  "geometry": {"coordinates":[-122.17088200000001,37.708818],"type":"Point"}
}