{
  "type": "Feature",
  "properties": {
    "addr:full":"620 E Capitol Ave Milpitas CA 95035",
    "addr:housenumber":"620",
    "addr:postcode":"95035",
    "addr:street":"E Capitol Ave",
    "iso:country":"US",
    "sg:address":"620 E Capitol Ave",
    "sg:city":"Milpitas",
    "sg:classifiers":[
        {
            "category":"Utilities",
            "subcategory":"Refuse",
            "type":"Services"
        }
    ],
    "sg:phone":"+1 408 719 1411",
    "sg:postcode":"95035",
    "sg:province":"CA",
    "sg:tags":[
        "dumps"
    ],
    "wof:name":"DMW Dumpsters",
    "wof:placetype":"venue"
},
  "geometry": {"coordinates":[-121.89188799999999,37.40914],"type":"Point"}
}