{
  "type": "Feature",
  "properties": {
    "addr:full":"242 W Alvin Dr Salinas CA 93906",
    "addr:housenumber":"242",
    "addr:postcode":"93906",
    "addr:street":"W Alvin Dr",
    "iso:country":"US",
    "sg:address":"242 W Alvin Dr",
    "sg:city":"Salinas",
    "sg:classifiers":[
        {
            "category":"Travel",
            "subcategory":"Hotels & Motels",
            "type":"Entertainment"
        }
    ],
    "sg:phone":"+1 831 449 2595",
    "sg:postcode":"93906",
    "sg:province":"CA",
    "sg:website":"http://www.lionlamb.org",
    "wof:name":"The Tides Center",
    "wof:placetype":"venue"
},
  "geometry": {"coordinates":[-121.657534,36.707319],"type":"Point"}
}