{
  "type": "Feature",
  "properties": {
    "iso:country":"US",
    "sg:address":"14478 Skyway Rd",
    "sg:city":"Magalia",
    "sg:classifiers":[
        {
            "category":"Health Services",
            "subcategory":"Chiropractor",
            "type":"Services"
        }
    ],
    "sg:phone":"+1 530 873 9113",
    "sg:postcode":"95954",
    "sg:province":"CA",
    "wof:name":"Ken Davis Jr DC",
    "wof:placetype":"venue"
},
  "geometry": {"coordinates":[-121.596389,39.832237],"type":"Point"}
}