{
  "type": "Feature",
  "properties": {
    "addr:full":"1606 N Laurel Ave Los Angeles CA 90046",
    "addr:housenumber":"1606",
    "addr:postcode":"90046",
    "addr:street":"N Laurel Ave",
    "iso:country":"US",
    "sg:address":"1606 N Laurel Ave",
    "sg:city":"Los Angeles",
    "sg:classifiers":[
        {
            "category":"Professional",
            "type":"Services"
        }
    ],
    "sg:phone":"+1 323 650 6443",
    "sg:postcode":"90046",
    "sg:province":"CA",
    "sg:tags":[
        "establishment"
    ],
    "wof:name":"Rapid Annie",
    "wof:placetype":"venue"
},
  "geometry": {"coordinates":[-118.364217,34.101186],"type":"Point"}
}