{
  "type": "Feature",
  "properties": {
    "iso:country":"US",
    "sg:address":"2600 Michelson Drive",
    "sg:city":"Irvine",
    "sg:classifiers":[
        {
            "category":"Professional",
            "subcategory":"Lawyer & Legal Services",
            "type":"Services"
        }
    ],
    "sg:phone":"+1 949 752 8090",
    "sg:postcode":"92612",
    "sg:province":"CA",
    "wof:name":"Knuppel Neil A Professional Corporation",
    "wof:placetype":"venue"
},
  "geometry": {"coordinates":[-117.850273,33.674429],"type":"Point"}
}