{
  "type": "Feature",
  "properties": {
    "iso:country":"US",
    "sg:address":"635 E 1st St",
    "sg:city":"Tustin",
    "sg:classifiers":[
        {
            "category":"Building & Trades",
            "subcategory":"Cleaning & Sanitation",
            "type":"Services"
        }
    ],
    "sg:phone":"+1 714 352 4231",
    "sg:postcode":"92780",
    "sg:province":"CA",
    "sg:tags":[
        "home"
    ],
    "sg:website":"www.tustinwaterdamage.com",
    "wof:name":"Tustin Water Damage",
    "wof:placetype":"venue"
},
  "geometry": {"coordinates":[-117.814804,33.745551],"type":"Point"}
}