{
  "type": "Feature",
  "properties": {
    "iso:country":"US",
    "sg:address":"12316 Venice Blvd",
    "sg:city":"Los Angeles",
    "sg:classifiers":[
        {
            "category":"Shopping",
            "subcategory":"Used Merchandise",
            "type":"Retail Goods"
        }
    ],
    "sg:phone":"+1 310 398 7274",
    "sg:postcode":"90066",
    "sg:province":"CA",
    "sg:tags":[
        "vintage",
        "consignment"
    ],
    "wof:name":"Trash & Treasures Too",
    "wof:placetype":"venue"
},
  "geometry": {"coordinates":[-118.432999,34.004002],"type":"Point"}
}