{
  "type": "Feature",
  "properties": {
    "addr:full":"7901 Oakport St Oakland CA 94621",
    "addr:housenumber":"7901",
    "addr:postcode":"94621",
    "addr:street":"Oakport St",
    "iso:country":"US",
    "sg:address":"7901 Oakport St",
    "sg:city":"Oakland",
    "sg:classifiers":[
        {
            "category":"Banks & Credit Unions",
            "subcategory":"Bank",
            "type":"Services"
        }
    ],
    "sg:phone":"+1 650 574 5746",
    "sg:postcode":"94621",
    "sg:province":"CA",
    "sg:tags":[
        "loan",
        "real estate"
    ],
    "sg:website":"www.calstatefunding.com",
    "wof:name":"Cal-State Funding",
    "wof:placetype":"venue"
},
  "geometry": {"coordinates":[-122.19782600000001,37.739704],"type":"Point"}
}