{
  "type": "Feature",
  "properties": {
    "iso:country":"US",
    "sg:address":"733 Dunn Wy at Orangethorpe Ave",
    "sg:city":"Placentia",
    "sg:classifiers":[
        {
            "category":"Education",
            "subcategory":"Dance Studio",
            "type":"Public Place"
        },
        {
            "category":"Recreation",
            "subcategory":"Dance Hall",
            "type":"Entertainment"
        }
    ],
    "sg:phone":"+1 949 250 3332",
    "sg:postcode":"92870",
    "sg:province":"CA",
    "sg:tags":[
        "club"
    ],
    "sg:website":"atomicballroom.com",
    "wof:name":"ATOMIC Ballroom Placentia",
    "wof:placetype":"venue"
},
  "geometry": {"coordinates":[-117.87995600000001,33.862146],"type":"Point"}
}