{
  "type": "Feature",
  "properties": {
    "iso:country":"US",
    "sg:address":"1040 S Robertson Blvd",
    "sg:city":"Los Angeles",
    "sg:classifiers":[
        {
            "category":"Professional",
            "type":"Services"
        }
    ],
    "sg:phone":"+1 323 665 6851",
    "sg:postcode":"90035",
    "sg:province":"CA",
    "wof:name":"Amandla",
    "wof:placetype":"venue"
},
  "geometry": {"coordinates":[-118.383573,34.058023],"type":"Point"}
}