{
  "type": "Feature",
  "properties": {
    "iso:country":"US",
    "sg:address":"5524 Elvas Ave",
    "sg:city":"Sacramento",
    "sg:classifiers":[
        {
            "category":"Education",
            "subcategory":"School",
            "type":"Public Place"
        }
    ],
    "sg:phone":"+1 916 739 0120",
    "sg:postcode":"95819",
    "sg:province":"CA",
    "wof:name":"TCG Martial Arts Academy",
    "wof:placetype":"venue"
},
  "geometry": {"coordinates":[-121.433409,38.571421],"type":"Point"}
}