{
  "type": "Feature",
  "properties": {
    "addr:full":"4512 S Vermont Ave Los Angeles CA 90037",
    "addr:housenumber":"4512",
    "addr:postcode":"90037",
    "addr:street":"S Vermont Ave",
    "iso:country":"US",
    "sg:address":"4512 S Vermont Ave",
    "sg:city":"Los Angeles",
    "sg:classifiers":[
        {
            "category":"Retail",
            "subcategory":"Repair Shop",
            "type":"Services"
        }
    ],
    "sg:phone":"+1 323 232 6175",
    "sg:postcode":"90037",
    "sg:province":"CA",
    "sg:tags":[
        "appliance"
    ],
    "wof:name":"Sal's Appliances",
    "wof:placetype":"venue"
},
  "geometry": {"coordinates":[-118.29145800000001,34.001761],"type":"Point"}
}