{
  "type": "Feature",
  "properties": {
    "iso:country":"US",
    "sg:address":"1451 W Artesia Blvd",
    "sg:city":"Gardena",
    "sg:classifiers":[
        {
            "category":"Shopping",
            "type":"Retail Goods"
        }
    ],
    "sg:phone":"+1 310 808 1238",
    "sg:postcode":"90248",
    "sg:province":"CA",
    "sg:tags":[
        "communication",
        "merchandise",
        "radiotelephone",
        "cellular",
        "telephone"
    ],
    "wof:name":"Touch Point Wireless and Games",
    "wof:placetype":"venue"
},
  "geometry": {"coordinates":[-118.302105,33.872907],"type":"Point"}
}