{
  "type": "Feature",
  "properties": {
    "iso:country":"US",
    "sg:address":"353 N Pass Ave",
    "sg:city":"Burbank",
    "sg:classifiers":[
        {
            "category":"Restaurant",
            "type":"Food & Drink"
        }
    ],
    "sg:phone":"+1 818 846 2327",
    "sg:postcode":"91505",
    "sg:province":"CA",
    "sg:tags":[
        "breakfast",
        "brunch"
    ],
    "wof:name":"Bea Bea's",
    "wof:placetype":"venue"
},
  "geometry": {"coordinates":[-118.345769,34.155539],"type":"Point"}
}