{
  "type": "Feature",
  "properties": {
    "iso:country":"US",
    "sg:address":"5175 Chapala Dr",
    "sg:city":"Riverside",
    "sg:classifiers":[
        {
            "category":"Professional",
            "subcategory":"Engineering",
            "type":"Services"
        }
    ],
    "sg:phone":"+1 951 784 0706",
    "sg:postcode":"92507",
    "sg:province":"CA",
    "sg:tags":[
        "engineer"
    ],
    "wof:name":"Zand Hossein Assoc",
    "wof:placetype":"venue"
},
  "geometry": {"coordinates":[-117.33990799999999,33.95673],"type":"Point"}
}