{
  "type": "Feature",
  "properties": {
    "iso:country":"US",
    "sg:address":"1420 Yuba St",
    "sg:city":"Redding",
    "sg:classifiers":[
        {
            "category":"Shopping",
            "subcategory":"Used Merchandise",
            "type":"Retail Goods"
        }
    ],
    "sg:phone":"+1 530 245 5832",
    "sg:postcode":"96001",
    "sg:province":"CA",
    "sg:tags":[
        "shop",
        "thrift"
    ],
    "wof:name":"Angels Collection",
    "wof:placetype":"venue"
},
  "geometry": {"coordinates":[-122.39159100000001,40.583142],"type":"Point"}
}