{
  "type": "Feature",
  "properties": {
    "addr:full":"9722 Van Ruiten St Bellflower CA 90706",
    "addr:housenumber":"9722",
    "addr:postcode":"90706",
    "addr:street":"Van Ruiten St",
    "iso:country":"US",
    "sg:address":"9722 Van Ruiten St",
    "sg:city":"Bellflower",
    "sg:classifiers":[
        {
            "category":"Wholesale",
            "subcategory":"Machinery & Supplies",
            "type":"Manufacturing & Wholesale Goods"
        }
    ],
    "sg:phone":"+1 562 867 4128",
    "sg:postcode":"90706",
    "sg:province":"CA",
    "sg:tags":[
        "pump"
    ],
    "wof:name":"C B Pump Inc",
    "wof:placetype":"venue"
},
  "geometry": {"coordinates":[-118.12746,33.90345],"type":"Point"}
}