{
  "type": "Feature",
  "properties": {
    "iso:country":"US",
    "sg:address":"604 E State St",
    "sg:city":"Redlands",
    "sg:classifiers":[
        {
            "category":"Place Of Worship",
            "subcategory":"Church",
            "type":"Public Place"
        },
        {
            "category":"Place Of Worship",
            "type":"Public Place"
        },
        {
            "category":"Organizations",
            "subcategory":"Religious Organization",
            "type":"Services"
        }
    ],
    "sg:phone":"+1 909 824 8272",
    "sg:postcode":"92374",
    "sg:province":"CA",
    "sg:tags":[
        "god",
        "churches-church",
        "churches-pentecostal"
    ],
    "wof:name":"Inland Empire Filipino Sda",
    "wof:placetype":"venue"
},
  "geometry": {"coordinates":[-117.176034,34.056389],"type":"Point"}
}