{
  "type": "Feature",
  "properties": {
    "addr:full":"2929 Leonis Boulevard Los Angeles CA 90058",
    "addr:housenumber":"2929",
    "addr:postcode":"90058",
    "addr:street":"Leonis Boulevard",
    "iso:country":"US",
    "sg:address":"2929 Leonis Boulevard",
    "sg:city":"Los Angeles",
    "sg:classifiers":[
        {
            "category":"Wholesale",
            "subcategory":"Fruits & Vegetables",
            "type":"Manufacturing & Wholesale Goods"
        }
    ],
    "sg:phone":"+1 323 584 0012",
    "sg:postcode":"90058",
    "sg:province":"CA",
    "sg:tags":[
        "veggie"
    ],
    "sg:website":"www.bestorientalproduce.com",
    "wof:name":"Best Oriental Produce",
    "wof:placetype":"venue"
},
  "geometry": {"coordinates":[-118.216095,34.000226],"type":"Point"}
}