{
  "type": "Feature",
  "properties": {
    "addr:full":"450 Sutter St San Francisco CA 94108",
    "addr:housenumber":"450",
    "addr:postcode":"94108",
    "addr:street":"Sutter St",
    "iso:country":"US",
    "sg:address":"450 Sutter St",
    "sg:city":"San Francisco",
    "sg:classifiers":[
        {
            "category":"Health Services",
            "subcategory":"Medical Lab",
            "type":"Services"
        }
    ],
    "sg:phone":"+1 415 392 2233",
    "sg:postcode":"94108",
    "sg:province":"CA",
    "sg:tags":[
        "laboratory"
    ],
    "wof:name":"Den Art Aesthetic Designs SF",
    "wof:placetype":"venue"
},
  "geometry": {"coordinates":[-122.40716,37.789504],"type":"Point"}
}