{
  "type": "Feature",
  "properties": {
    "iso:country":"US",
    "sg:address":"130 Petaluma Ave",
    "sg:city":"Sebastopol",
    "sg:classifiers":[
        {
            "category":"Professional",
            "subcategory":"Research",
            "type":"Services"
        }
    ],
    "sg:phone":"+1 707 829 1999",
    "sg:postcode":"95472",
    "sg:province":"CA",
    "sg:tags":[
        "development",
        "energy",
        "solar"
    ],
    "wof:name":"Cooperative Community Energy",
    "wof:placetype":"venue"
},
  "geometry": {"coordinates":[-122.822745,38.402024],"type":"Point"}
}