{
  "type": "Feature",
  "properties": {
    "addr:full":"807 N Ben Maddox Way Visalia CA 93292",
    "addr:housenumber":"807",
    "addr:postcode":"93292",
    "addr:street":"N Ben Maddox Way",
    "iso:country":"US",
    "sg:address":"807 N Ben Maddox Way",
    "sg:city":"Visalia",
    "sg:classifiers":[
        {
            "category":"Autos & Motor Vehicles",
            "subcategory":"Auto Supplies",
            "type":"Retail Goods"
        }
    ],
    "sg:phone":"+1 559 625 3900",
    "sg:postcode":"93292",
    "sg:province":"CA",
    "sg:tags":[
        "automobile",
        "parts"
    ],
    "wof:name":"NAPA Auto Parts",
    "wof:placetype":"venue"
},
  "geometry": {"coordinates":[-119.278857,36.33636],"type":"Point"}
}