{
  "type": "Feature",
  "properties": {
    "iso:country":"US",
    "sg:address":"24355 Lyons Ave",
    "sg:city":"Newhall",
    "sg:classifiers":[
        {
            "category":"Health Services",
            "subcategory":"Doctor",
            "type":"Services"
        }
    ],
    "sg:phone":"+1 661 288 1811",
    "sg:postcode":"91321",
    "sg:province":"CA",
    "sg:tags":[
        "physician",
        "surgeon"
    ],
    "wof:name":"Pediatric Orthopedic Spine",
    "wof:placetype":"venue"
},
  "geometry": {"coordinates":[-118.560321,34.378595],"type":"Point"}
}