{
  "type": "Feature",
  "properties": {
    "iso:country":"US",
    "sg:address":"3840 Rosin Ct",
    "sg:city":"Sacramento",
    "sg:classifiers":[
        {
            "category":"Fast Food",
            "type":"Food & Drink"
        }
    ],
    "sg:phone":"+1 916 564 1153",
    "sg:postcode":"95834",
    "sg:province":"CA",
    "sg:tags":[
        "take",
        "restaurant"
    ],
    "wof:name":"Kroger",
    "wof:placetype":"venue"
},
  "geometry": {"coordinates":[-121.47562499999999,38.637215],"type":"Point"}
}