{
  "type": "Feature",
  "properties": {
    "iso:country":"US",
    "sg:address":"817 Sutter St",
    "sg:city":"Yreka",
    "sg:classifiers":[
        {
            "category":"Freight",
            "type":"Transportation"
        }
    ],
    "sg:phone":"+1 530 842 1862",
    "sg:postcode":"96097",
    "sg:province":"CA",
    "sg:tags":[
        "trucking"
    ],
    "wof:name":"Paul Hamilton Trucking",
    "wof:placetype":"venue"
},
  "geometry": {"coordinates":[-122.623589,41.709227],"type":"Point"}
}