{
  "type": "Feature",
  "properties": {
    "iso:country":"US",
    "sg:address":"5825 international blvd",
    "sg:city":"Oakland",
    "sg:classifiers":[
        {
            "category":"Autos & Motor Vehicles",
            "subcategory":"Automobile Sales",
            "type":"Retail Goods"
        }
    ],
    "sg:phone":"+1 510 632 8662",
    "sg:postcode":"94621",
    "sg:province":"CA",
    "sg:tags":[
        "car"
    ],
    "wof:name":"L&A Motors",
    "wof:placetype":"venue"
},
  "geometry": {"coordinates":[-122.19999199999999,37.765337],"type":"Point"}
}