{
  "type": "Feature",
  "properties": {
    "addr:full":"2950 Ramona Ave Sacramento CA 95826",
    "addr:housenumber":"2950",
    "addr:postcode":"95826",
    "addr:street":"Ramona Ave",
    "iso:country":"US",
    "sg:address":"2950 Ramona Ave",
    "sg:city":"Sacramento",
    "sg:classifiers":[
        {
            "category":"Wholesale",
            "subcategory":"Non-durable Goods",
            "type":"Manufacturing & Wholesale Goods"
        }
    ],
    "sg:phone":"+1 916 451 1810",
    "sg:postcode":"95826",
    "sg:province":"CA",
    "wof:name":"Great World Co",
    "wof:placetype":"venue"
},
  "geometry": {"coordinates":[-121.41742000000001,38.549277],"type":"Point"}
}