{
  "type": "Feature",
  "properties": {
    "addr:full":"1102 E 17th St Santa Ana CA 92701",
    "addr:housenumber":"1102",
    "addr:postcode":"92701",
    "addr:street":"E 17Th St",
    "iso:country":"US",
    "sg:address":"1102 E 17th St",
    "sg:city":"Santa Ana",
    "sg:classifiers":[
        {
            "category":"Building & Trades",
            "subcategory":"Construction",
            "type":"Services"
        },
        {
            "category":"Retail",
            "subcategory":"Auto Repair",
            "type":"Services"
        }
    ],
    "sg:phone":"+1 714 543 0860",
    "sg:postcode":"92701",
    "sg:province":"CA",
    "sg:tags":[
        "body",
        "shop",
        "painter"
    ],
    "wof:name":"Earl Scheib",
    "wof:placetype":"venue"
},
  "geometry": {"coordinates":[-117.856003,33.7598],"type":"Point"}
}