{
  "type": "Feature",
  "properties": {
    "addr:full":"1240 Brickyard Way Richmond CA 94801",
    "addr:housenumber":"1240",
    "addr:postcode":"94801",
    "addr:street":"Brickyard Way",
    "iso:country":"US",
    "sg:address":"1240 Brickyard Way",
    "sg:city":"Richmond",
    "sg:classifiers":[
        {
            "category":"Building & Trades",
            "subcategory":"Construction",
            "type":"Services"
        }
    ],
    "sg:phone":"+1 510 236 9105",
    "sg:postcode":"94801",
    "sg:province":"CA",
    "sg:tags":[
        "contractor"
    ],
    "wof:name":"Rv Stich Construction",
    "wof:placetype":"venue"
},
  "geometry": {"coordinates":[-122.380301,37.912811],"type":"Point"}
}