{
  "type": "Feature",
  "properties": {
    "addr:full":"1625 Alum Rock Ave San Jose CA 95116",
    "addr:housenumber":"1625",
    "addr:postcode":"95116",
    "addr:street":"Alum Rock Ave",
    "iso:country":"US",
    "sg:address":"1625 Alum Rock Ave",
    "sg:city":"San Jose",
    "sg:classifiers":[
        {
            "category":"Professional",
            "subcategory":"Lawyer & Legal Services",
            "type":"Services"
        }
    ],
    "sg:phone":"+1 408 295 5015",
    "sg:postcode":"95116",
    "sg:province":"CA",
    "sg:tags":[
        "support"
    ],
    "wof:name":"Coast To Coast Legal Services",
    "wof:placetype":"venue"
},
  "geometry": {"coordinates":[-121.857435,37.351961],"type":"Point"}
}