{
  "type": "Feature",
  "properties": {
    "iso:country":"US",
    "sg:address":"84 N Lassen St",
    "sg:city":"Susanville",
    "sg:classifiers":[
        {
            "category":"Organizations",
            "subcategory":"Membership Organization",
            "type":"Services"
        }
    ],
    "sg:phone":"+1 530 257 4929",
    "sg:postcode":"96130",
    "sg:province":"CA",
    "sg:tags":[
        "fraternal"
    ],
    "wof:name":"Lassen Janesville Lodge No 149",
    "wof:placetype":"venue"
},
  "geometry": {"coordinates":[-120.661518,40.419473],"type":"Point"}
}