{
  "type": "Feature",
  "properties": {
    "addr:full":"1440 Broadway Oakland CA 94612",
    "addr:housenumber":"1440",
    "addr:postcode":"94612",
    "addr:street":"Broadway",
    "iso:country":"US",
    "sg:address":"1440 Broadway",
    "sg:city":"Oakland",
    "sg:classifiers":[
        {
            "category":"Banks & Credit Unions",
            "subcategory":"Investment Brokerage",
            "type":"Services"
        }
    ],
    "sg:phone":"+1 510 835 4520",
    "sg:postcode":"94612",
    "sg:province":"CA",
    "sg:tags":[
        "consultant",
        "planning",
        "financial"
    ],
    "wof:name":"CDM & Assoc",
    "wof:placetype":"venue"
},
  "geometry": {"coordinates":[-122.270809,37.804824],"type":"Point"}
}