{
  "type": "Feature",
  "properties": {
    "addr:full":"154 W Live Oak Ave Arcadia CA 91007",
    "addr:housenumber":"154",
    "addr:postcode":"91007",
    "addr:street":"W Live Oak Ave",
    "iso:country":"US",
    "sg:address":"154 W Live Oak Ave",
    "sg:city":"Arcadia",
    "sg:classifiers":[
        {
            "category":"Retail",
            "subcategory":"Auto Repair",
            "type":"Services"
        }
    ],
    "sg:phone":"+1 626 446 4228",
    "sg:postcode":"91007",
    "sg:province":"CA",
    "sg:tags":[
        "repairing",
        "automobile"
    ],
    "sg:website":"www.johnnysautomotive.com",
    "wof:name":"Johnny's Automotive",
    "wof:placetype":"venue"
},
  "geometry": {"coordinates":[-118.036649,34.106475],"type":"Point"}
}