{
  "type": "Feature",
  "properties": {
    "iso:country":"US",
    "sg:address":"4012 Marshall Ave",
    "sg:city":"San Mateo",
    "sg:classifiers":[
        {
            "category":"Building & Trades",
            "subcategory":"Plumbing",
            "type":"Services"
        }
    ],
    "sg:phone":"+1 650 218 8170",
    "sg:postcode":"94403",
    "sg:province":"CA",
    "sg:website":"www.stephenplumbing.com/",
    "wof:name":"Stephen Plumbing Services",
    "wof:placetype":"venue"
},
  "geometry": {"coordinates":[-122.306033,37.526183],"type":"Point"}
}