{
  "type": "Feature",
  "properties": {
    "iso:country":"US",
    "sg:address":"10814-H Jefferson Blvd",
    "sg:city":"Culver City",
    "sg:classifiers":[
        {
            "category":"Restaurant",
            "type":"Food & Drink"
        }
    ],
    "sg:phone":"+1 310 202 0359",
    "sg:postcode":"90230",
    "sg:province":"CA",
    "sg:website":"www.ediblearrangements.com",
    "wof:name":"Edible Arrangements",
    "wof:placetype":"venue"
},
  "geometry": {"coordinates":[-118.39476000000001,34.001194],"type":"Point"}
}