{
  "type": "Feature",
  "properties": {
    "addr:full":"711 E Port Hueneme Rd Port Hueneme CA 93041",
    "addr:housenumber":"711",
    "addr:postcode":"93041",
    "addr:street":"E Port Hueneme Rd",
    "iso:country":"US",
    "sg:address":"711 E Port Hueneme Rd",
    "sg:city":"Port Hueneme",
    "sg:classifiers":[
        {
            "category":"Food & Beverages",
            "subcategory":"Groceries & Convenience Stores",
            "type":"Retail Goods"
        }
    ],
    "sg:phone":"+1 805 488 5012",
    "sg:postcode":"93041",
    "sg:province":"CA",
    "sg:tags":[
        "grocer"
    ],
    "wof:name":"Anacapa Liquor",
    "wof:placetype":"venue"
},
  "geometry": {"coordinates":[-119.18813900000001,34.147414],"type":"Point"}
}