{
  "type": "Feature",
  "properties": {
    "addr:full":"9901 Southland Ct Bakersfield CA 93307",
    "addr:housenumber":"9901",
    "addr:postcode":"93307",
    "addr:street":"Southland Ct",
    "iso:country":"US",
    "sg:address":"9901 Southland Ct",
    "sg:city":"Bakersfield",
    "sg:classifiers":[
        {
            "category":"Building & Trades",
            "subcategory":"Electrical",
            "type":"Services"
        }
    ],
    "sg:phone":"+1 661 599 8160",
    "sg:postcode":"93307",
    "sg:province":"CA",
    "sg:tags":[
        "electrician"
    ],
    "wof:name":"Rsp Electrical",
    "wof:placetype":"venue"
},
  "geometry": {"coordinates":[-119.019096,35.265091],"type":"Point"}
}