{
  "type": "Feature",
  "properties": {
    "iso:country":"US",
    "sg:address":"510 Castillo St",
    "sg:city":"Santa Barbara",
    "sg:classifiers":[
        {
            "category":"Wholesale",
            "subcategory":"Electrical",
            "type":"Manufacturing & Wholesale Goods"
        }
    ],
    "sg:phone":"+1 805 899 4260",
    "sg:postcode":"93101",
    "sg:province":"CA",
    "sg:tags":[
        "equipment",
        "telephone",
        "system"
    ],
    "wof:name":"Crystalvoice Communications",
    "wof:placetype":"venue"
},
  "geometry": {"coordinates":[-119.701137,34.413456],"type":"Point"}
}