{
  "type": "Feature",
  "properties": {
    "iso:country":"US",
    "sg:address":"945 Airport Dr",
    "sg:city":"San Luis Obispo",
    "sg:classifiers":[
        {
            "category":"Home & Garden",
            "subcategory":"Garden Supply",
            "type":"Retail Goods"
        }
    ],
    "sg:phone":"+1 805 541 1126",
    "sg:postcode":"93401",
    "sg:province":"CA",
    "sg:tags":[
        "engine"
    ],
    "wof:name":"SLO Fuel",
    "wof:placetype":"venue"
},
  "geometry": {"coordinates":[-120.64296,35.240842],"type":"Point"}
}