{
  "type": "Feature",
  "properties": {
    "iso:country":"US",
    "sg:address":"2074 Broadway St",
    "sg:city":"Redwood City",
    "sg:classifiers":[
        {
            "category":"Shopping",
            "subcategory":"Jewelry",
            "type":"Retail Goods"
        }
    ],
    "sg:phone":"+1 650 367 1251",
    "sg:postcode":"94063",
    "sg:province":"CA",
    "sg:tags":[
        "jeweler"
    ],
    "wof:name":"Golden Time Svc",
    "wof:placetype":"venue"
},
  "geometry": {"coordinates":[-122.22748300000001,37.486629],"type":"Point"}
}