{
  "type": "Feature",
  "properties": {
    "iso:country":"US",
    "sg:address":"617 Galveston St",
    "sg:city":"West Sacramento",
    "sg:classifiers":[
        {
            "category":"Building & Trades",
            "subcategory":"Construction",
            "type":"Services"
        }
    ],
    "sg:phone":"+1 916 371 0819",
    "sg:postcode":"95691",
    "sg:province":"CA",
    "sg:tags":[
        "general",
        "contractor"
    ],
    "wof:name":"Valley Construction",
    "wof:placetype":"venue"
},
  "geometry": {"coordinates":[-121.55249,38.581798],"type":"Point"}
}