{
  "type": "Feature",
  "properties": {
    "addr:full":"625 North Ave Vista CA 92083",
    "addr:housenumber":"625",
    "addr:postcode":"92083",
    "addr:street":"North Ave",
    "iso:country":"US",
    "sg:address":"625 North Ave",
    "sg:city":"Vista",
    "sg:classifiers":[
        {
            "category":"Building & Trades",
            "subcategory":"Construction",
            "type":"Services"
        }
    ],
    "sg:phone":"+1 760 726 3898",
    "sg:postcode":"92083",
    "sg:province":"CA",
    "sg:tags":[
        "concrete",
        "contractor"
    ],
    "sg:website":"www.sandiegostucco.com",
    "wof:name":"San Diego Stucco Inc",
    "wof:placetype":"venue"
},
  "geometry": {"coordinates":[-117.257435,33.215654],"type":"Point"}
}