{
  "type": "Feature",
  "properties": {
    "iso:country":"US",
    "sg:address":"3913 Fountain Avenue",
    "sg:city":"Los Angeles",
    "sg:classifiers":[
        {
            "category":"Retail",
            "subcategory":"Portrait Studio",
            "type":"Services"
        }
    ],
    "sg:phone":"+1 323 664 0702",
    "sg:postcode":"90029",
    "sg:province":"CA",
    "sg:tags":[
        "photography",
        "store"
    ],
    "wof:name":"Still Moving Pictures",
    "wof:placetype":"venue"
},
  "geometry": {"coordinates":[-118.277517,34.095668],"type":"Point"}
}