{
  "type": "Feature",
  "properties": {
    "addr:full":"14107 Euclid Ave Chino CA 91762",
    "addr:housenumber":"14107",
    "addr:postcode":"91762",
    "addr:street":"Euclid Ave",
    "iso:country":"US",
    "sg:address":"14107 Euclid Ave",
    "sg:city":"Chino",
    "sg:classifiers":[
        {
            "category":"Food & Beverages",
            "subcategory":"Groceries & Convenience Stores",
            "type":"Retail Goods"
        }
    ],
    "sg:phone":"+1 909 597 1912",
    "sg:postcode":"91762",
    "sg:province":"CA",
    "sg:tags":[
        "market"
    ],
    "wof:name":"Mar's Market",
    "wof:placetype":"venue"
},
  "geometry": {"coordinates":[-117.65059100000001,33.99185],"type":"Point"}
}