{
  "type": "Feature",
  "properties": {
    "addr:full":"23012 Ventura Blvd Woodland Hills CA 91364",
    "addr:housenumber":"23012",
    "addr:postcode":"91364",
    "addr:street":"Ventura Blvd",
    "iso:country":"US",
    "sg:address":"23012 Ventura Blvd",
    "sg:city":"Woodland Hills",
    "sg:classifiers":[
        {
            "category":"Real Estate",
            "subcategory":"Real Estate Agent",
            "type":"Services"
        }
    ],
    "sg:phone":"+1 818 225 9952",
    "sg:postcode":"91364",
    "sg:province":"CA",
    "wof:name":"Bailey Moore Properties",
    "wof:placetype":"venue"
},
  "geometry": {"coordinates":[-118.62832,34.164011],"type":"Point"}
}