{
  "type": "Feature",
  "properties": {
    "addr:full":"12465 Mills Ave Chino CA 91710",
    "addr:housenumber":"12465",
    "addr:postcode":"91710",
    "addr:street":"Mills Ave",
    "iso:country":"US",
    "sg:address":"12465 Mills Ave",
    "sg:city":"Chino",
    "sg:classifiers":[
        {
            "category":"Manufacturing",
            "subcategory":"Retail Goods",
            "type":"Manufacturing & Wholesale Goods"
        }
    ],
    "sg:phone":"+1 909 465 0778",
    "sg:postcode":"91710",
    "sg:province":"CA",
    "sg:tags":[
        "manufacturer"
    ],
    "wof:name":"Godiva Manufacturing",
    "wof:placetype":"venue"
},
  "geometry": {"coordinates":[-117.72872099999999,34.02926],"type":"Point"}
}