{
  "type": "Feature",
  "properties": {
    "iso:country":"US",
    "sg:address":"4924 Balboa Blvd",
    "sg:city":"Encino",
    "sg:classifiers":[
        {
            "category":"Professional",
            "type":"Services"
        }
    ],
    "sg:phone":"+1 818 783 8140",
    "sg:postcode":"91316",
    "sg:province":"CA",
    "wof:name":"Full Spectrum Inc",
    "wof:placetype":"venue"
},
  "geometry": {"coordinates":[-118.501003,34.159984],"type":"Point"}
}