{
  "type": "Feature",
  "properties": {
    "iso:country":"US",
    "sg:address":"970 W Glenwood Ave",
    "sg:city":"Turlock",
    "sg:classifiers":[
        {
            "category":"Autos & Motor Vehicles",
            "subcategory":"Auto Supplies",
            "type":"Retail Goods"
        },
        {
            "category":"Retail",
            "subcategory":"Auto Repair",
            "type":"Services"
        }
    ],
    "sg:phone":"+1 209 634 8714",
    "sg:postcode":"95380",
    "sg:province":"CA",
    "sg:tags":[
        "body",
        "lettering",
        "automobile",
        "truck",
        "painting",
        "repairing"
    ],
    "wof:name":"Alex Body Shop",
    "wof:placetype":"venue"
},
  "geometry": {"coordinates":[-120.86117900000001,37.47728],"type":"Point"}
}