{
  "type": "Feature",
  "properties": {
    "addr:full":"4001 Knobcone Ln Placerville CA 95667",
    "addr:housenumber":"4001",
    "addr:postcode":"95667",
    "addr:street":"Knobcone Ln",
    "iso:country":"US",
    "sg:address":"4001 Knobcone Ln",
    "sg:city":"Placerville",
    "sg:classifiers":[
        {
            "category":"Professional",
            "subcategory":"Management & Consulting",
            "type":"Services"
        }
    ],
    "sg:phone":"+1 916 484 6171",
    "sg:postcode":"95667",
    "sg:province":"CA",
    "sg:tags":[
        "consultant",
        "business"
    ],
    "wof:name":"Guidance Counselor-Business",
    "wof:placetype":"venue"
},
  "geometry": {"coordinates":[-120.68324,38.703966],"type":"Point"}
}