{
  "type": "Feature",
  "properties": {
    "addr:full":"444 N B St Sacramento CA 95811",
    "addr:housenumber":"444",
    "addr:postcode":"95811",
    "addr:street":"N B",
    "iso:country":"US",
    "sg:address":"444 N B St",
    "sg:city":"Sacramento",
    "sg:classifiers":[
        {
            "category":"Professional",
            "subcategory":"Lawyer & Legal Services",
            "type":"Services"
        }
    ],
    "sg:phone":"+1 916 444 3072",
    "sg:postcode":"95811",
    "sg:province":"CA",
    "sg:tags":[
        "attorney"
    ],
    "wof:name":"Swanson & Frank",
    "wof:placetype":"venue"
},
  "geometry": {"coordinates":[-121.493368,38.59251],"type":"Point"}
}