{
  "type": "Feature",
  "properties": {
    "addr:full":"655 Pacific Ave Oxnard CA 93030",
    "addr:housenumber":"655",
    "addr:postcode":"93030",
    "addr:street":"Pacific Ave",
    "iso:country":"US",
    "sg:address":"655 Pacific Ave",
    "sg:city":"Oxnard",
    "sg:classifiers":[
        {
            "category":"Wholesale",
            "subcategory":"Auto Parts",
            "type":"Manufacturing & Wholesale Goods"
        }
    ],
    "sg:phone":"+1 805 486 7367",
    "sg:postcode":"93030",
    "sg:province":"CA",
    "sg:tags":[
        "automobile",
        "rebuilt"
    ],
    "wof:name":"Pacific Auto Salvage",
    "wof:placetype":"venue"
},
  "geometry": {"coordinates":[-119.164866,34.195318],"type":"Point"}
}