{
  "type": "Feature",
  "properties": {
    "addr:full":"9841 Airport Boulevard Los Angeles CA 90045",
    "addr:housenumber":"9841",
    "addr:postcode":"90045",
    "addr:street":"Airport Boulevard",
    "iso:country":"US",
    "sg:address":"9841 Airport Boulevard",
    "sg:city":"Los Angeles",
    "sg:classifiers":[
        {
            "category":"Banks & Credit Unions",
            "subcategory":"Atm",
            "type":"Services"
        }
    ],
    "sg:phone":"+1 213 617 7717",
    "sg:postcode":"90045",
    "sg:province":"CA",
    "sg:tags":[
        "bankruptcy"
    ],
    "wof:name":"Parham Teeple Marchisotto A PC",
    "wof:placetype":"venue"
},
  "geometry": {"coordinates":[-118.38605,33.946625],"type":"Point"}
}