{
  "type": "Feature",
  "properties": {
    "addr:full":"2530 E Villa St Pasadena CA 91107",
    "addr:housenumber":"2530",
    "addr:postcode":"91107",
    "addr:street":"E Villa St",
    "iso:country":"US",
    "sg:address":"2530 E Villa St",
    "sg:city":"Pasadena",
    "sg:classifiers":[
        {
            "category":"Health Services",
            "subcategory":"Chiropractor",
            "type":"Services"
        }
    ],
    "sg:phone":"+1 626 577 2574",
    "sg:postcode":"91107",
    "sg:province":"CA",
    "sg:tags":[
        "chiropractic"
    ],
    "wof:name":"Brainerd Lew DC",
    "wof:placetype":"venue"
},
  "geometry": {"coordinates":[-118.098,34.154301],"type":"Point"}
}