{
  "type": "Feature",
  "properties": {
    "addr:full":"55 Devine St San Jose CA 95110",
    "addr:housenumber":"55",
    "addr:postcode":"95110",
    "addr:street":"Devine St",
    "iso:country":"US",
    "sg:address":"55 Devine St",
    "sg:city":"San Jose",
    "sg:classifiers":[
        {
            "category":"Shopping",
            "subcategory":"Clothing, Apparel, & Fashions",
            "type":"Retail Goods"
        },
        {
            "category":"Shopping",
            "subcategory":"Shoes",
            "type":"Retail Goods"
        }
    ],
    "sg:phone":"+1 408 920 6603",
    "sg:postcode":"95110",
    "sg:province":"CA",
    "sg:tags":[
        "men's",
        "clothing",
        "store",
        "women's"
    ],
    "sg:website":"www.puristboutique.com",
    "wof:name":"Purist Boutique",
    "wof:placetype":"venue"
},
  "geometry": {"coordinates":[-121.894093,37.339471],"type":"Point"}
}