{
  "type": "Feature",
  "properties": {
    "addr:full":"1204 E Santa Paula St Santa Paula CA 93060",
    "addr:housenumber":"1204",
    "addr:postcode":"93060",
    "addr:street":"E Santa Paula St",
    "iso:country":"US",
    "sg:address":"1204 E Santa Paula St",
    "sg:city":"Santa Paula",
    "sg:classifiers":[
        {
            "category":"Professional",
            "type":"Services"
        }
    ],
    "sg:phone":"+1 805 525 4050",
    "sg:postcode":"93060",
    "sg:province":"CA",
    "wof:name":"Harvard Ltd",
    "wof:placetype":"venue"
},
  "geometry": {"coordinates":[-119.056513,34.358892],"type":"Point"}
}