{
  "type": "Feature",
  "properties": {
    "addr:full":"1110 Torrey Pines Rd Ste I La Jolla CA 92037",
    "addr:housenumber":"1110",
    "addr:postcode":"92037",
    "addr:street":"Torrey Pines Rd Ste I",
    "iso:country":"US",
    "sg:address":"1110 Torrey Pines Rd Ste I",
    "sg:city":"La Jolla",
    "sg:classifiers":[
        {
            "category":"Wholesale",
            "subcategory":"Scrap",
            "type":"Manufacturing & Wholesale Goods"
        }
    ],
    "sg:phone":"+1 858 864 7763",
    "sg:postcode":"92037",
    "sg:province":"CA",
    "sg:tags":[
        "junk",
        "hauling",
        "removal"
    ],
    "sg:website":"www.junkmd.com",
    "wof:name":"Junk MD",
    "wof:placetype":"venue"
},
  "geometry": {"coordinates":[-117.271807,32.843408],"type":"Point"}
}