{
  "type": "Feature",
  "properties": {
    "iso:country":"US",
    "sg:address":"1275 Alameda St",
    "sg:city":"Wilmington",
    "sg:classifiers":[
        {
            "category":"Wholesale",
            "subcategory":"Electrical",
            "type":"Manufacturing & Wholesale Goods"
        }
    ],
    "sg:phone":"+1 310 834 5209",
    "sg:postcode":"90744",
    "sg:province":"CA",
    "sg:tags":[
        "equipment",
        "electric",
        "supply"
    ],
    "wof:name":"Yukon Equipment & Machinery",
    "wof:placetype":"venue"
},
  "geometry": {"coordinates":[-118.241342,33.791264],"type":"Point"}
}