{
  "type": "Feature",
  "properties": {
    "iso:country":"US",
    "sg:address":"415 W Felicita Ave",
    "sg:city":"Escondido",
    "sg:classifiers":[
        {
            "category":"Restaurant",
            "type":"Food & Drink"
        }
    ],
    "sg:phone":"+1 760 739 8192",
    "sg:postcode":"92025",
    "sg:province":"CA",
    "sg:tags":[
        "chinese"
    ],
    "sg:website":"www.pandaexpress.com",
    "wof:name":"Panda Express",
    "wof:placetype":"venue"
},
  "geometry": {"coordinates":[-117.441396,33.103801],"type":"Point"}
}