{
  "type": "Feature",
  "properties": {
    "addr:full":"505 Minton Ln Mountain View CA 94041",
    "addr:housenumber":"505",
    "addr:postcode":"94041",
    "addr:street":"Minton Ln",
    "iso:country":"US",
    "sg:address":"505 Minton Ln",
    "sg:city":"Mountain View",
    "sg:classifiers":[
        {
            "category":"Manufacturing",
            "subcategory":"Tools & Machinery",
            "type":"Manufacturing & Wholesale Goods"
        }
    ],
    "sg:phone":"+1 408 961 8855",
    "sg:postcode":"94041",
    "sg:province":"CA",
    "sg:tags":[
        "industry",
        "special"
    ],
    "wof:name":"Pacific Western Systems",
    "wof:placetype":"venue"
},
  "geometry": {"coordinates":[-122.075613,37.39254],"type":"Point"}
}