{
  "type": "Feature",
  "properties": {
    "addr:full":"26246 Dolores St Carmel CA 93923",
    "addr:housenumber":"26246",
    "addr:postcode":"93923",
    "addr:street":"Dolores St",
    "iso:country":"US",
    "sg:address":"26246 Dolores St",
    "sg:city":"Carmel",
    "sg:classifiers":[
        {
            "category":"Building & Trades",
            "subcategory":"Construction",
            "type":"Services"
        }
    ],
    "sg:phone":"+1 831 624 5656",
    "sg:postcode":"93923",
    "sg:province":"CA",
    "sg:tags":[
        "contractor"
    ],
    "wof:name":"Brad Dow & Assoc",
    "wof:placetype":"venue"
},
  "geometry": {"coordinates":[-121.922321,36.542583],"type":"Point"}
}