{
  "type": "Feature",
  "properties": {
    "addr:full":"480 San Ramon Valley Blvd Danville CA 94526",
    "addr:housenumber":"480",
    "addr:postcode":"94526",
    "addr:street":"San Ramon Valley Blvd",
    "iso:country":"US",
    "sg:address":"480 San Ramon Valley Blvd",
    "sg:city":"Danville",
    "sg:phone":"+1 925 838 6421",
    "sg:postcode":"94526",
    "sg:province":"CA",
    "wof:name":"El Balazo Danville",
    "wof:placetype":"venue"
},
  "geometry": {"coordinates":[-121.996582,37.818424],"type":"Point"}
}