{
  "type": "Feature",
  "properties": {
    "iso:country":"US",
    "sg:address":"2750 Jackson St",
    "sg:city":"San Francisco",
    "sg:classifiers":[
        {
            "category":"Organizations",
            "subcategory":"Non-profit Organization",
            "type":"Services"
        }
    ],
    "sg:phone":"+1 415 921 3747",
    "sg:postcode":"94115",
    "sg:province":"CA",
    "sg:tags":[
        "elementary",
        "school"
    ],
    "sg:website":"www.townschool.com/",
    "wof:name":"Town School For Boys",
    "wof:placetype":"venue"
},
  "geometry": {"coordinates":[-122.44009200000001,37.791892],"type":"Point"}
}