{
  "type": "Feature",
  "properties": {
    "iso:country":"US",
    "sg:address":"1610 Arden Way Suite 155",
    "sg:city":"Sacramento",
    "sg:classifiers":[
        {
            "category":"Restaurant",
            "type":"Food & Drink"
        }
    ],
    "sg:phone":"+1 916 649 1928",
    "sg:postcode":"95815",
    "sg:province":"CA",
    "wof:name":"Point West Cafe",
    "wof:placetype":"venue"
},
  "geometry": {"coordinates":[-121.42853599999999,38.600206],"type":"Point"}
}