{
  "type": "Feature",
  "properties": {
    "iso:country":"US",
    "sg:address":"3105 Swallows Nest Dr",
    "sg:city":"Sacramento",
    "sg:classifiers":[
        {
            "category":"Real Estate",
            "subcategory":"Real Estate Agent",
            "type":"Services"
        }
    ],
    "sg:phone":"+1 916 920 0859",
    "sg:postcode":"95833",
    "sg:province":"CA",
    "wof:name":"Swallow S Nest Properties",
    "wof:placetype":"venue"
},
  "geometry": {"coordinates":[-121.532439,38.607914],"type":"Point"}
}