{
  "type": "Feature",
  "properties": {
    "iso:country":"US",
    "sg:address":"3211 Scott Boulevard Suite 203",
    "sg:city":"Santa Clara",
    "sg:classifiers":[
        {
            "category":"Manufacturing",
            "subcategory":"Electronics",
            "type":"Manufacturing & Wholesale Goods"
        }
    ],
    "sg:phone":"+1 408 970 8808",
    "sg:postcode":"95054",
    "sg:province":"CA",
    "sg:website":"http://www.quinticcorp.com/",
    "wof:name":"Quintic",
    "wof:placetype":"venue"
},
  "geometry": {"coordinates":[-121.96487999999999,37.39673],"type":"Point"}
}