{
  "type": "Feature",
  "properties": {
    "addr:full":"981 Lakeville St Petaluma CA 94952",
    "addr:housenumber":"981",
    "addr:postcode":"94952",
    "addr:street":"Lakeville St",
    "iso:country":"US",
    "sg:address":"981 Lakeville St",
    "sg:city":"Petaluma",
    "sg:classifiers":[
        {
            "category":"Restaurant",
            "type":"Food & Drink"
        }
    ],
    "sg:phone":"+1 707 769 1862",
    "sg:postcode":"94952",
    "sg:province":"CA",
    "wof:name":"Mc Donald's",
    "wof:placetype":"venue"
},
  "geometry": {"coordinates":[-122.624945,38.235531],"type":"Point"}
}