{
  "type": "Feature",
  "properties": {
    "addr:full":"4266 Napier St San Diego CA 92110",
    "addr:housenumber":"4266",
    "addr:postcode":"92110",
    "addr:street":"Napier St",
    "iso:country":"US",
    "sg:address":"4266 Napier St",
    "sg:city":"San Diego",
    "sg:classifiers":[
        {
            "category":"Manufacturing",
            "subcategory":"Textiles",
            "type":"Manufacturing & Wholesale Goods"
        }
    ],
    "sg:phone":"+1 619 276 1658",
    "sg:postcode":"92110",
    "sg:province":"CA",
    "sg:tags":[
        "mill",
        "fabric"
    ],
    "wof:name":"Flossies Quilting",
    "wof:placetype":"venue"
},
  "geometry": {"coordinates":[-117.204584,32.782687],"type":"Point"}
}