{
  "type": "Feature",
  "properties": {
    "iso:country":"US",
    "sg:address":"870 Washington Heights Rd",
    "sg:city":"El Cajon",
    "sg:classifiers":[
        {
            "category":"Real Estate",
            "subcategory":"Real Estate Agent",
            "type":"Services"
        }
    ],
    "sg:phone":"+1 619 593 8241",
    "sg:postcode":"92019",
    "sg:province":"CA",
    "wof:name":"Talon Group",
    "wof:placetype":"venue"
},
  "geometry": {"coordinates":[-116.942866,32.785072],"type":"Point"}
}