{
  "type": "Feature",
  "properties": {
    "addr:full":"15314 Roxford St Sylmar CA 91342",
    "addr:housenumber":"15314",
    "addr:postcode":"91342",
    "addr:street":"Roxford St",
    "iso:country":"US",
    "sg:address":"15314 Roxford St",
    "sg:city":"Sylmar",
    "sg:classifiers":[
        {
            "category":"Wholesale",
            "subcategory":"Plants",
            "type":"Manufacturing & Wholesale Goods"
        },
        {
            "category":"Building & Trades",
            "subcategory":"Landscaping Services",
            "type":"Services"
        }
    ],
    "sg:phone":"+1 818 367 5378",
    "sg:postcode":"91342",
    "sg:province":"CA",
    "sg:tags":[
        "nursery",
        "tree",
        "supply"
    ],
    "wof:name":"Oriental Gardens Nursery",
    "wof:placetype":"venue"
},
  "geometry": {"coordinates":[-118.466455,34.315879],"type":"Point"}
}