{
  "type": "Feature",
  "properties": {
    "addr:full":"1241 Howard Ave Burlingame CA 94010",
    "addr:housenumber":"1241",
    "addr:postcode":"94010",
    "addr:street":"Howard Ave",
    "iso:country":"US",
    "sg:address":"1241 Howard Ave",
    "sg:city":"Burlingame",
    "sg:classifiers":[
        {
            "category":"Personal",
            "subcategory":"Nail Salon",
            "type":"Services"
        }
    ],
    "sg:phone":"+1 650 347 8812",
    "sg:postcode":"94010",
    "sg:province":"CA",
    "sg:website":"www.bamboobeauty.com/",
    "wof:name":"Bamboo",
    "wof:placetype":"venue"
},
  "geometry": {"coordinates":[-122.345358,37.577453],"type":"Point"}
}