{
  "type": "Feature",
  "properties": {
    "iso:country":"US",
    "sg:address":"2961 Valmere Dr",
    "sg:city":"Malibu",
    "sg:classifiers":[
        {
            "category":"Government",
            "subcategory":"Office",
            "type":"Public Place"
        }
    ],
    "sg:phone":"+1 310 456 8547",
    "sg:postcode":"90265",
    "sg:province":"CA",
    "sg:tags":[
        "international",
        "affairs"
    ],
    "wof:name":"Consulate Luxembourg Honrry",
    "wof:placetype":"venue"
},
  "geometry": {"coordinates":[-118.73999499999999,34.044489],"type":"Point"}
}