{
  "type": "Feature",
  "properties": {
    "addr:full":"20700 Avalon Blvd # 127 Carson CA 90746",
    "addr:housenumber":"20700",
    "addr:postcode":"90746",
    "addr:street":"Avalon Blvd # 127",
    "iso:country":"US",
    "sg:address":"20700 Avalon Blvd # 127",
    "sg:city":"Carson",
    "sg:classifiers":[
        {
            "category":"Shopping",
            "subcategory":"Clothing, Apparel, & Fashions",
            "type":"Retail Goods"
        }
    ],
    "sg:phone":"+1 310 352 6201",
    "sg:postcode":"90746",
    "sg:province":"CA",
    "sg:website":"www.oldnavy.com",
    "wof:name":"Old Navy",
    "wof:placetype":"venue"
},
  "geometry": {"coordinates":[-118.260324,33.842977],"type":"Point"}
}