{
  "type": "Feature",
  "properties": {
    "iso:country":"US",
    "sg:address":"9816 Bus Park Dr",
    "sg:city":"Sacramento",
    "sg:classifiers":[
        {
            "category":"Retail",
            "subcategory":"Auto Repair",
            "type":"Services"
        }
    ],
    "sg:phone":"+1 916 366 7426",
    "sg:postcode":"95827",
    "sg:province":"CA",
    "sg:tags":[
        "glass",
        "coating",
        "tinting"
    ],
    "wof:name":"Rico's Window Coverings",
    "wof:placetype":"venue"
},
  "geometry": {"coordinates":[-121.330451,38.57007],"type":"Point"}
}