{
  "type": "Feature",
  "properties": {
    "addr:full":"6333 Wilshire Blvd Los Angeles CA 90048",
    "addr:housenumber":"6333",
    "addr:postcode":"90048",
    "addr:street":"Wilshire Blvd",
    "iso:country":"US",
    "sg:address":"6333 Wilshire Blvd",
    "sg:city":"Los Angeles",
    "sg:classifiers":[
        {
            "category":"Health Services",
            "subcategory":"Doctor",
            "type":"Services"
        }
    ],
    "sg:phone":"+1 323 651 3198",
    "sg:postcode":"90048",
    "sg:province":"CA",
    "sg:tags":[
        "surgeon",
        "oral"
    ],
    "wof:name":"Pryor Cornelius III DDS",
    "wof:placetype":"venue"
},
  "geometry": {"coordinates":[-118.36599699999999,34.063599],"type":"Point"}
}