{
  "type": "Feature",
  "properties": {
    "iso:country":"US",
    "sg:address":"1341 E Chapman Ave",
    "sg:city":"Orange",
    "sg:classifiers":[
        {
            "category":"Professional",
            "subcategory":"Lawyer & Legal Services",
            "type":"Services"
        }
    ],
    "sg:phone":"+1 714 771 7671",
    "sg:postcode":"92866",
    "sg:province":"CA",
    "wof:name":"Hales Robert E Atty",
    "wof:placetype":"venue"
},
  "geometry": {"coordinates":[-117.83899700000001,33.787998],"type":"Point"}
}