{
  "type": "Feature",
  "properties": {
    "addr:full":"4728 Richmond Ave Fremont CA 94536",
    "addr:housenumber":"4728",
    "addr:postcode":"94536",
    "addr:street":"Richmond Ave",
    "iso:country":"US",
    "sg:address":"4728 Richmond Ave",
    "sg:city":"Fremont",
    "sg:classifiers":[
        {
            "category":"Real Estate",
            "subcategory":"Real Estate Operator",
            "type":"Services"
        }
    ],
    "sg:phone":"+1 510 790 3613",
    "sg:postcode":"94536",
    "sg:province":"CA",
    "sg:tags":[
        "property",
        "lessor"
    ],
    "wof:name":"Ronnoco Properties",
    "wof:placetype":"venue"
},
  "geometry": {"coordinates":[-121.999765,37.542304],"type":"Point"}
}