{
  "type": "Feature",
  "properties": {
    "addr:full":"7135 Amador Plaza Rd Dublin CA 94568",
    "addr:housenumber":"7135",
    "addr:postcode":"94568",
    "addr:street":"Amador Plaza Rd",
    "iso:country":"US",
    "sg:address":"7135 Amador Plaza Rd",
    "sg:city":"Dublin",
    "sg:classifiers":[
        {
            "category":"Shopping",
            "subcategory":"Tobacco",
            "type":"Retail Goods"
        }
    ],
    "sg:phone":"+1 925 829 9615",
    "sg:postcode":"94568",
    "sg:province":"CA",
    "sg:tags":[
        "cigarette",
        "cigar",
        "dealer"
    ],
    "wof:name":"Smoker Friendly",
    "wof:placetype":"venue"
},
  "geometry": {"coordinates":[-121.92752299999999,37.705125],"type":"Point"}
}