{
  "type": "Feature",
  "properties": {
    "iso:country":"US",
    "sg:address":"Arden Fair Mall 1689 Arden Way, Ste 2174",
    "sg:city":"Sacramento",
    "sg:classifiers":[
        {
            "category":"Shopping",
            "type":"Retail Goods"
        }
    ],
    "sg:phone":"+1 916 646 1742",
    "sg:postcode":"95814",
    "sg:province":"CA",
    "sg:website":"www.thingsremembered.com",
    "wof:name":"Things Remembered",
    "wof:placetype":"venue"
},
  "geometry": {"coordinates":[-121.42570499999999,38.60112],"type":"Point"}
}