{
  "type": "Feature",
  "properties": {
    "addr:full":"12370 Hesperia Rd Suite 9 Victorville CA 92395",
    "addr:housenumber":"12370",
    "addr:postcode":"92395",
    "addr:street":"Hesperia Rd Suite 9",
    "iso:country":"US",
    "sg:address":"12370 Hesperia Rd Suite 9",
    "sg:city":"Victorville",
    "sg:classifiers":[
        {
            "category":"Insurance",
            "subcategory":"Insurance Agent",
            "type":"Services"
        },
        {
            "category":"Insurance",
            "subcategory":"Hazard Insurance",
            "type":"Services"
        },
        {
            "category":"Insurance",
            "subcategory":"Title Insurance",
            "type":"Services"
        }
    ],
    "sg:phone":"+1 760 241 7375",
    "sg:postcode":"92395",
    "sg:province":"CA",
    "sg:tags":[
        "business",
        "auto",
        "commercial",
        "homeowner",
        "property",
        "casualty"
    ],
    "sg:website":"http://www.mercuryinsurance.com",
    "wof:name":"Mercury Insurance - Key City Insurance",
    "wof:placetype":"venue"
},
  "geometry": {"coordinates":[-117.29131700000001,34.476042],"type":"Point"}
}