{
  "type": "Feature",
  "properties": {
    "iso:country":"US",
    "sg:address":"2711 Lassiter Ln",
    "sg:city":"Turlock",
    "sg:classifiers":[
        {
            "category":"Retail",
            "subcategory":"Laundry & Dry Cleaning",
            "type":"Services"
        }
    ],
    "sg:phone":"+1 209 667 5351",
    "sg:postcode":"95380",
    "sg:province":"CA",
    "wof:name":"Santos Paul Dairy Towel Svc",
    "wof:placetype":"venue"
},
  "geometry": {"coordinates":[-120.878517,37.485964],"type":"Point"}
}