{
  "type": "Feature",
  "properties": {
    "iso:country":"US",
    "sg:address":"3372 Grand Ave",
    "sg:city":"Huntington Park",
    "sg:classifiers":[
        {
            "category":"Professional",
            "subcategory":"Advertising",
            "type":"Services"
        }
    ],
    "sg:phone":"+1 323 583 1019",
    "sg:postcode":"90255",
    "sg:province":"CA",
    "wof:name":"GMS Advertising",
    "wof:placetype":"venue"
},
  "geometry": {"coordinates":[-118.20737699999999,33.967263],"type":"Point"}
}