{
  "type": "Feature",
  "properties": {
    "addr:full":"510 W Ohio Ave Richmond CA 94804",
    "addr:housenumber":"510",
    "addr:postcode":"94804",
    "addr:street":"W Ohio Ave",
    "iso:country":"US",
    "sg:address":"510 W Ohio Ave",
    "sg:city":"Richmond",
    "sg:classifiers":[
        {
            "category":"Manufacturing",
            "subcategory":"Paper Products",
            "type":"Manufacturing & Wholesale Goods"
        }
    ],
    "sg:phone":"+1 510 215 8999",
    "sg:postcode":"94804",
    "sg:province":"CA",
    "wof:name":"Novacart Inc",
    "wof:placetype":"venue"
},
  "geometry": {"coordinates":[-122.37096200000001,37.930776],"type":"Point"}
}