{
  "type": "Feature",
  "properties": {
    "addr:full":"9121 Folsom Boulevard Suite F Sacramento CA 95826",
    "addr:housenumber":"9121",
    "addr:postcode":"95826",
    "addr:street":"Folsom Boulevard Suite F",
    "iso:country":"US",
    "sg:address":"9121 Folsom Boulevard Suite F",
    "sg:city":"Sacramento",
    "sg:classifiers":[
        {
            "category":"Autos & Motor Vehicles",
            "subcategory":"Automobile Sales",
            "type":"Retail Goods"
        }
    ],
    "sg:phone":"+1 916 369 1177",
    "sg:postcode":"95826",
    "sg:province":"CA",
    "sg:tags":[
        "limo"
    ],
    "wof:name":"A-List Limousine and Town Car Service",
    "wof:placetype":"venue"
},
  "geometry": {"coordinates":[-121.362022,38.559694],"type":"Point"}
}