{
  "type": "Feature",
  "properties": {
    "addr:full":"3170 4th Ave, Suite 200 San Diego CA 92103",
    "addr:housenumber":"3170",
    "addr:postcode":"92103",
    "addr:street":"4Th Ave Suite 200",
    "iso:country":"US",
    "sg:address":"3170 4th Ave, Suite 200",
    "sg:city":"San Diego",
    "sg:classifiers":[
        {
            "category":"Professional",
            "subcategory":"Lawyer & Legal Services",
            "type":"Services"
        }
    ],
    "sg:phone":"+1 619 296 0567",
    "sg:postcode":"92103",
    "sg:province":"CA",
    "sg:website":"crosslawfirmapc.com",
    "wof:name":"The Cross Law Firm, APC",
    "wof:placetype":"venue"
},
  "geometry": {"coordinates":[-117.161539,32.738482],"type":"Point"}
}