{
  "type": "Feature",
  "properties": {
    "addr:full":"5021 Bonniemae Way Sacramento CA 95820",
    "addr:housenumber":"5021",
    "addr:postcode":"95820",
    "addr:street":"Bonniemae Way",
    "iso:country":"US",
    "sg:address":"5021 Bonniemae Way",
    "sg:city":"Sacramento",
    "sg:classifiers":[
        {
            "category":"Banks & Credit Unions",
            "subcategory":"Bank",
            "type":"Services"
        }
    ],
    "sg:phone":"+1 916 452 3970",
    "sg:postcode":"95820",
    "sg:province":"CA",
    "sg:tags":[
        "machine",
        "teller",
        "automated"
    ],
    "wof:name":"California Cash LLC",
    "wof:placetype":"venue"
},
  "geometry": {"coordinates":[-121.451301,38.529877],"type":"Point"}
}