{
  "type": "Feature",
  "properties": {
    "addr:full":"221 Industry Ave La Habra CA 90631",
    "addr:housenumber":"221",
    "addr:postcode":"90631",
    "addr:street":"Industry Ave",
    "iso:country":"US",
    "sg:address":"221 Industry Ave",
    "sg:city":"La Habra",
    "sg:classifiers":[
        {
            "category":"Building & Trades",
            "subcategory":"Electrical",
            "type":"Services"
        }
    ],
    "sg:phone":"+1 714 870 6360",
    "sg:postcode":"90631",
    "sg:province":"CA",
    "sg:tags":[
        "electrical",
        "contractor"
    ],
    "wof:name":"Industrial Cnstr & Elec Inc",
    "wof:placetype":"venue"
},
  "geometry": {"coordinates":[-117.945002,33.917984],"type":"Point"}
}