{
  "type": "Feature",
  "properties": {
    "addr:full":"24895 Mission Blvd Hayward CA 94544",
    "addr:housenumber":"24895",
    "addr:postcode":"94544",
    "addr:street":"Mission Blvd",
    "iso:country":"US",
    "sg:address":"24895 Mission Blvd",
    "sg:city":"Hayward",
    "sg:classifiers":[
        {
            "category":"Autos & Motor Vehicles",
            "subcategory":"Automobile Sales",
            "type":"Retail Goods"
        },
        {
            "category":"Retail",
            "subcategory":"Auto Repair",
            "type":"Services"
        }
    ],
    "sg:phone":"+1 510 582 1300",
    "sg:postcode":"94544",
    "sg:province":"CA",
    "sg:tags":[
        "car"
    ],
    "wof:name":"Honda of Hayward",
    "wof:placetype":"venue"
},
  "geometry": {"coordinates":[-122.07399700000001,37.6604],"type":"Point"}
}