{
  "type": "Feature",
  "properties": {
    "iso:country":"US",
    "sg:address":"1904 Whipple Ave",
    "sg:city":"Redwood City",
    "sg:classifiers":[
        {
            "category":"Professional",
            "subcategory":"Computer Services",
            "type":"Services"
        }
    ],
    "sg:phone":"+1 650 368 7812",
    "sg:postcode":"94062",
    "sg:province":"CA",
    "sg:tags":[
        "consultant",
        "designer"
    ],
    "wof:name":"Turbo Training",
    "wof:placetype":"venue"
},
  "geometry": {"coordinates":[-122.246743,37.484989],"type":"Point"}
}