{
  "type": "Feature",
  "properties": {
    "addr:full":"470 N Mollison Ave El Cajon CA 92021",
    "addr:housenumber":"470",
    "addr:postcode":"92021",
    "addr:street":"N Mollison Ave",
    "iso:country":"US",
    "sg:address":"470 N Mollison Ave",
    "sg:city":"El Cajon",
    "sg:classifiers":[
        {
            "category":"Organizations",
            "subcategory":"Religious Organization",
            "type":"Services"
        }
    ],
    "sg:phone":"+1 619 440 1352",
    "sg:postcode":"92021",
    "sg:province":"CA",
    "sg:tags":[
        "church"
    ],
    "wof:name":"Iglesia De Cristo Ministerios",
    "wof:placetype":"venue"
},
  "geometry": {"coordinates":[-116.95104600000001,32.799444],"type":"Point"}
}