{
  "type": "Feature",
  "properties": {
    "iso:country":"US",
    "sg:address":"26 W Anapamu St",
    "sg:city":"Santa Barbara",
    "sg:classifiers":[
        {
            "category":"Travel",
            "subcategory":"Hotels & Motels",
            "type":"Entertainment"
        }
    ],
    "sg:phone":"+1 805 884 0300",
    "sg:postcode":"93101",
    "sg:province":"CA",
    "sg:tags":[
        "operation"
    ],
    "wof:name":"Hotel Andalucia",
    "wof:placetype":"venue"
},
  "geometry": {"coordinates":[-119.70540800000001,34.422611],"type":"Point"}
}