{
  "type": "Feature",
  "properties": {
    "iso:country":"US",
    "sg:address":"2515 El Camino Real",
    "sg:city":"Santa Clara",
    "sg:classifiers":[
        {
            "category":"Travel",
            "subcategory":"Hotels & Motels",
            "type":"Entertainment"
        }
    ],
    "sg:phone":"+1 408 241 2841",
    "sg:postcode":"95051",
    "sg:province":"CA",
    "sg:website":"www.granadainn.com",
    "wof:name":"Granada Inn Silicon Valley",
    "wof:placetype":"venue"
},
  "geometry": {"coordinates":[-121.971418,37.35235],"type":"Point"}
}