{
  "type": "Feature",
  "properties": {
    "addr:full":"670 18th Ave Menlo Park CA 94025",
    "addr:housenumber":"670",
    "addr:postcode":"94025",
    "addr:street":"18Th Ave",
    "iso:country":"US",
    "sg:address":"670 18th Ave",
    "sg:city":"Menlo Park",
    "sg:classifiers":[
        {
            "category":"Building & Trades",
            "subcategory":"Landscaping Services",
            "type":"Services"
        }
    ],
    "sg:phone":"+1 650 327 4237",
    "sg:postcode":"94025",
    "sg:province":"CA",
    "sg:tags":[
        "designer",
        "landscape"
    ],
    "wof:name":"Susan Edwards Ogle Landscape",
    "wof:placetype":"venue"
},
  "geometry": {"coordinates":[-122.190153,37.472465],"type":"Point"}
}