{
  "type": "Feature",
  "properties": {
    "addr:full":"2331 Hollister Ter Glendale CA 91206",
    "addr:housenumber":"2331",
    "addr:postcode":"91206",
    "addr:street":"Hollister Ter",
    "iso:country":"US",
    "sg:address":"2331 Hollister Ter",
    "sg:city":"Glendale",
    "sg:classifiers":[
        {
            "category":"Manufacturing",
            "subcategory":"Apparel",
            "type":"Manufacturing & Wholesale Goods"
        }
    ],
    "sg:phone":"+1 818 244 6036",
    "sg:postcode":"91206",
    "sg:province":"CA",
    "sg:tags":[
        "outerwear",
        "mfg"
    ],
    "wof:name":"Robin Gaudielue",
    "wof:placetype":"venue"
},
  "geometry": {"coordinates":[-118.214911,34.150891],"type":"Point"}
}