{
  "type": "Feature",
  "properties": {
    "addr:full":"2506 Market St San Diego CA 92102",
    "addr:housenumber":"2506",
    "addr:postcode":"92102",
    "addr:street":"Market St",
    "iso:country":"US",
    "sg:address":"2506 Market St",
    "sg:city":"San Diego",
    "sg:classifiers":[
        {
            "category":"Home & Garden",
            "subcategory":"Garden Supply",
            "type":"Retail Goods"
        }
    ],
    "sg:phone":"+1 619 239 7571",
    "sg:postcode":"92102",
    "sg:province":"CA",
    "sg:website":"www.westairgases.com",
    "wof:name":"WestAir Gases & Equipment",
    "wof:placetype":"venue"
},
  "geometry": {"coordinates":[-117.140013,32.711626],"type":"Point"}
}