{
  "type": "Feature",
  "properties": {
    "iso:country":"US",
    "sg:address":"2150 River Plaza Dr",
    "sg:city":"Sacramento",
    "sg:classifiers":[
        {
            "category":"Banks & Credit Unions",
            "subcategory":"Bank",
            "type":"Services"
        }
    ],
    "sg:phone":"+1 916 564 6650",
    "sg:postcode":"95833",
    "sg:province":"CA",
    "sg:tags":[
        "loan",
        "real estate"
    ],
    "wof:name":"Greg Garrett",
    "wof:placetype":"venue"
},
  "geometry": {"coordinates":[-121.512213,38.605209],"type":"Point"}
}