{
  "type": "Feature",
  "properties": {
    "addr:full":"4303 S Broadway Los Angeles CA 90037",
    "addr:housenumber":"4303",
    "addr:postcode":"90037",
    "addr:street":"S Broadway",
    "iso:country":"US",
    "sg:address":"4303 S Broadway",
    "sg:city":"Los Angeles",
    "sg:classifiers":[
        {
            "category":"Shopping",
            "subcategory":"Clothing, Apparel, & Fashions",
            "type":"Retail Goods"
        }
    ],
    "sg:phone":"+1 323 252 3609",
    "sg:postcode":"90037",
    "sg:province":"CA",
    "sg:tags":[
        "men's",
        "clothing",
        "women's"
    ],
    "sg:website":"www.groovysilk.com",
    "wof:name":"GroovySilk",
    "wof:placetype":"venue"
},
  "geometry": {"coordinates":[-118.278373,34.005424],"type":"Point"}
}