{
  "type": "Feature",
  "properties": {
    "addr:full":"333 E Colorado St Glendale CA 91205",
    "addr:housenumber":"333",
    "addr:postcode":"91205",
    "addr:street":"E Colorado St",
    "iso:country":"US",
    "sg:address":"333 E Colorado St",
    "sg:city":"Glendale",
    "sg:classifiers":[
        {
            "category":"Organizations",
            "subcategory":"Religious Organization",
            "type":"Services"
        }
    ],
    "sg:phone":"+1 818 240 4380",
    "sg:postcode":"91205",
    "sg:province":"CA",
    "sg:tags":[
        "churches-community",
        "christ",
        "church"
    ],
    "wof:name":"United Community Church",
    "wof:placetype":"venue"
},
  "geometry": {"coordinates":[-118.252183,34.142604],"type":"Point"}
}