{
  "type": "Feature",
  "properties": {
    "addr:full":"23881 Via Fabricante Ste 518 Mission Viejo CA 92691",
    "addr:housenumber":"23881",
    "addr:postcode":"92691",
    "addr:street":"Via Fabricante Ste 518",
    "iso:country":"US",
    "sg:address":"23881 Via Fabricante Ste 518",
    "sg:city":"Mission Viejo",
    "sg:classifiers":[
        {
            "category":"Shopping",
            "subcategory":"Clothing, Apparel, & Fashions",
            "type":"Retail Goods"
        }
    ],
    "sg:phone":"+1 949 716 0500",
    "sg:postcode":"92691",
    "sg:province":"CA",
    "sg:tags":[
        "children's",
        "clothing"
    ],
    "sg:website":"www.frogsfrillsanddaffodils.com",
    "wof:name":"Frogs Frills And Daffodils",
    "wof:placetype":"venue"
},
  "geometry": {"coordinates":[-117.681195,33.616744],"type":"Point"}
}