{
  "type": "Feature",
  "properties": {
    "iso:country":"US",
    "sg:address":"5536 Reseda Blvd",
    "sg:city":"Tarzana",
    "sg:classifiers":[
        {
            "category":"Health Services",
            "subcategory":"Medical Lab",
            "type":"Services"
        }
    ],
    "sg:phone":"+1 818 344 9525",
    "sg:postcode":"91356",
    "sg:province":"CA",
    "sg:tags":[
        "laboratory"
    ],
    "wof:name":"Tarzana Advanced Imaging",
    "wof:placetype":"venue"
},
  "geometry": {"coordinates":[-118.535927,34.172772],"type":"Point"}
}