{
  "type": "Feature",
  "properties": {
    "iso:country":"US",
    "sg:address":"201 S Lovekin Blvd",
    "sg:city":"Blythe",
    "sg:classifiers":[
        {
            "category":"Restaurant",
            "type":"Food & Drink"
        }
    ],
    "sg:menulink":"http://www.allmenus.com/ca/palo-verde/123486-quiznos-sub/menu/",
    "sg:phone":"+1 760 921 2760",
    "sg:postcode":"92225",
    "sg:province":"CA",
    "sg:tags":[
        "wrap",
        "american",
        "sandwich"
    ],
    "wof:name":"Quiznos Sub",
    "wof:placetype":"venue"
},
  "geometry": {"coordinates":[-114.60595499999999,33.608275],"type":"Point"}
}