{
  "type": "Feature",
  "properties": {
    "addr:full":"5230 Pacific Concourse Dr Los Angeles CA 90045",
    "addr:housenumber":"5230",
    "addr:postcode":"90045",
    "addr:street":"Pacific Concourse Dr",
    "iso:country":"US",
    "sg:address":"5230 Pacific Concourse Dr",
    "sg:city":"Los Angeles",
    "sg:classifiers":[
        {
            "category":"Restaurant",
            "type":"Food & Drink"
        }
    ],
    "sg:postcode":"90045",
    "sg:province":"CA",
    "sg:tags":[
        "new",
        "american"
    ],
    "wof:name":"Cafe 5230",
    "wof:placetype":"venue"
},
  "geometry": {"coordinates":[-118.37364700000001,33.928341],"type":"Point"}
}