{
  "type": "Feature",
  "properties": {
    "iso:country":"US",
    "sg:address":"16760 Stagg St",
    "sg:city":"Van Nuys",
    "sg:classifiers":[
        {
            "category":"Shopping",
            "subcategory":"Used Merchandise",
            "type":"Retail Goods"
        }
    ],
    "sg:phone":"+1 818 994 8300",
    "sg:postcode":"91406",
    "sg:province":"CA",
    "sg:tags":[
        "carpet",
        "dealer",
        "rug"
    ],
    "wof:name":"A W Carpet",
    "wof:placetype":"venue"
},
  "geometry": {"coordinates":[-118.497285,34.213081],"type":"Point"}
}