{
  "type": "Feature",
  "properties": {
    "addr:full":"48 Main St Winters CA 95694",
    "addr:housenumber":"48",
    "addr:postcode":"95694",
    "addr:street":"Main St",
    "iso:country":"US",
    "sg:address":"48 Main St",
    "sg:city":"Winters",
    "sg:classifiers":[
        {
            "category":"Banks & Credit Unions",
            "subcategory":"Bank",
            "type":"Services"
        }
    ],
    "sg:phone":"+1 530 795 4501",
    "sg:postcode":"95694",
    "sg:province":"CA",
    "wof:name":"First Northern Bank",
    "wof:placetype":"venue"
},
  "geometry": {"coordinates":[-121.969446,38.52154],"type":"Point"}
}