{
  "type": "Feature",
  "properties": {
    "addr:full":"15909 Via Descanso San Lorenzo CA 94580",
    "addr:housenumber":"15909",
    "addr:postcode":"94580",
    "addr:street":"Via Descanso",
    "iso:country":"US",
    "sg:address":"15909 Via Descanso",
    "sg:city":"San Lorenzo",
    "sg:classifiers":[
        {
            "category":"Building & Trades",
            "subcategory":"Construction",
            "type":"Services"
        }
    ],
    "sg:phone":"+1 510 278 0810",
    "sg:postcode":"94580",
    "sg:province":"CA",
    "sg:tags":[
        "resurfacing",
        "laying",
        "refinishing",
        "floor"
    ],
    "wof:name":"Accent Design Custom Flooring",
    "wof:placetype":"venue"
},
  "geometry": {"coordinates":[-122.124582,37.680923],"type":"Point"}
}