{
  "type": "Feature",
  "properties": {
    "iso:country":"US",
    "sg:address":"920 Hampshire Rd",
    "sg:city":"Westlake Village",
    "sg:classifiers":[
        {
            "category":"Professional",
            "subcategory":"Computer Services",
            "type":"Services"
        }
    ],
    "sg:phone":"+1 805 494 4338",
    "sg:postcode":"91361",
    "sg:province":"CA",
    "sg:tags":[
        "programming"
    ],
    "wof:name":"Katana Software",
    "wof:placetype":"venue"
},
  "geometry": {"coordinates":[-118.830452,34.152981],"type":"Point"}
}