{
  "type": "Feature",
  "properties": {
    "addr:full":"1108 W Valley Blvd Ste 6 Alhambra CA 91803",
    "addr:housenumber":"1108",
    "addr:postcode":"91803",
    "addr:street":"W Valley Blvd Ste 6",
    "iso:country":"US",
    "sg:address":"1108 W Valley Blvd Ste 6",
    "sg:city":"Alhambra",
    "sg:classifiers":[
        {
            "category":"Professional",
            "subcategory":"Lawyer & Legal Services",
            "type":"Services"
        }
    ],
    "sg:phone":"+1 626 300 9191",
    "sg:postcode":"91803",
    "sg:province":"CA",
    "sg:tags":[
        "notary"
    ],
    "wof:name":"Asian Link Corp",
    "wof:placetype":"venue"
},
  "geometry": {"coordinates":[-118.13488099999999,34.077767],"type":"Point"}
}