{
  "type": "Feature",
  "properties": {
    "iso:country":"US",
    "sg:address":"6217 Seville Ct",
    "sg:city":"Long Beach",
    "sg:classifiers":[
        {
            "category":"Real Estate",
            "subcategory":"Real Estate Agent",
            "type":"Services"
        }
    ],
    "sg:phone":"+1 562 498 1138",
    "sg:postcode":"90803",
    "sg:province":"CA",
    "wof:name":"Te Ce SA Corp",
    "wof:placetype":"venue"
},
  "geometry": {"coordinates":[-118.117547,33.765475],"type":"Point"}
}