{
  "type": "Feature",
  "properties": {
    "addr:full":"2020 W Foothill Blvd Upland CA 91786",
    "addr:housenumber":"2020",
    "addr:postcode":"91786",
    "addr:street":"W Foothill Blvd",
    "iso:country":"US",
    "sg:address":"2020 W Foothill Blvd",
    "sg:city":"Upland",
    "sg:classifiers":[
        {
            "category":"Autos & Motor Vehicles",
            "subcategory":"Auto Supplies",
            "type":"Retail Goods"
        },
        {
            "category":"Retail",
            "subcategory":"Auto Repair",
            "type":"Services"
        }
    ],
    "sg:phone":"+1 909 981 9777",
    "sg:postcode":"91786",
    "sg:province":"CA",
    "sg:tags":[
        "tire",
        "automobile",
        "retread",
        "accessory",
        "part",
        "brake",
        "recap"
    ],
    "sg:website":"http://www.bigotires.com",
    "wof:name":"Tire Pros Of Upland",
    "wof:placetype":"venue"
},
  "geometry": {"coordinates":[-117.69109,34.106781],"type":"Point"}
}