{
  "type": "Feature",
  "properties": {
    "iso:country":"US",
    "sg:address":"734 A St",
    "sg:city":"San Rafael",
    "sg:classifiers":[
        {
            "category":"Social Services",
            "type":"Services"
        }
    ],
    "sg:phone":"+1 415 457 2464",
    "sg:postcode":"94901",
    "sg:province":"CA",
    "sg:tags":[
        "organization",
        "welfare"
    ],
    "wof:name":"Marin Abused Women's Svc",
    "wof:placetype":"venue"
},
  "geometry": {"coordinates":[-122.528477,37.971006],"type":"Point"}
}