{
  "type": "Feature",
  "properties": {
    "addr:full":"1076 Main St Ramona CA 92065",
    "addr:housenumber":"1076",
    "addr:postcode":"92065",
    "addr:street":"Main St",
    "iso:country":"US",
    "sg:address":"1076 Main St",
    "sg:city":"Ramona",
    "sg:classifiers":[
        {
            "category":"Food & Beverages",
            "subcategory":"Groceries & Convenience Stores",
            "type":"Retail Goods"
        }
    ],
    "sg:phone":"+1 760 789 1712",
    "sg:postcode":"92065",
    "sg:province":"CA",
    "wof:name":"7-Eleven",
    "wof:placetype":"venue"
},
  "geometry": {"coordinates":[-116.86905299999999,33.041776],"type":"Point"}
}