{
  "type": "Feature",
  "properties": {
    "addr:full":"2632 Obelisco Pl Carlsbad CA 92009",
    "addr:housenumber":"2632",
    "addr:postcode":"92009",
    "addr:street":"Obelisco Pl",
    "iso:country":"US",
    "sg:address":"2632 Obelisco Pl",
    "sg:city":"Carlsbad",
    "sg:classifiers":[
        {
            "category":"Health Services",
            "subcategory":"Nursing And Care Facility",
            "type":"Services"
        }
    ],
    "sg:phone":"+1 760 753 2660",
    "sg:postcode":"92009",
    "sg:province":"CA",
    "sg:tags":[
        "home",
        "retirement",
        "community"
    ],
    "wof:name":"Dushan's Retirement Home",
    "wof:placetype":"venue"
},
  "geometry": {"coordinates":[-117.245773,33.101973],"type":"Point"}
}