{
  "type": "Feature",
  "properties": {
    "addr:full":"5355 Mira Sorrento Pl San Diego CA 92121",
    "addr:housenumber":"5355",
    "addr:postcode":"92121",
    "addr:street":"Mira Sorrento Pl",
    "iso:country":"US",
    "sg:address":"5355 Mira Sorrento Pl",
    "sg:city":"San Diego",
    "sg:classifiers":[
        {
            "category":"Utilities",
            "subcategory":"Mobile Phone",
            "type":"Services"
        }
    ],
    "sg:phone":"+1 858 625 7878",
    "sg:postcode":"92121",
    "sg:province":"CA",
    "sg:tags":[
        "provide"
    ],
    "wof:name":"Verizon",
    "wof:placetype":"venue"
},
  "geometry": {"coordinates":[-117.202555,32.894746],"type":"Point"}
}