{
  "type": "Feature",
  "properties": {
    "addr:full":"474 Harvard Ln Santa Barbara CA 93111",
    "addr:housenumber":"474",
    "addr:postcode":"93111",
    "addr:street":"Harvard Ln",
    "iso:country":"US",
    "sg:address":"474 Harvard Ln",
    "sg:city":"Santa Barbara",
    "sg:classifiers":[
        {
            "category":"Building & Trades",
            "subcategory":"Electrical",
            "type":"Services"
        }
    ],
    "sg:phone":"+1 805 683 2041",
    "sg:postcode":"93111",
    "sg:province":"CA",
    "sg:tags":[
        "electric",
        "contractor"
    ],
    "wof:name":"Honeyman Electric",
    "wof:placetype":"venue"
},
  "geometry": {"coordinates":[-119.81108999999999,34.446211],"type":"Point"}
}