{
  "type": "Feature",
  "properties": {
    "iso:country":"US",
    "sg:address":"Lawrence Hall of Science Centennial Dr & Grizzly Peak Blvd",
    "sg:city":"Berkeley",
    "sg:classifiers":[
        {
            "category":"Shopping",
            "subcategory":"Hobbies, Toys, & Games",
            "type":"Retail Goods"
        }
    ],
    "sg:phone":"+1 510 642 1929",
    "sg:postcode":"94702",
    "sg:province":"CA",
    "sg:tags":[
        "toy",
        "store"
    ],
    "sg:website":"lawrencehallofscience.stores.yah...",
    "wof:name":"Discovery Corner",
    "wof:placetype":"venue"
},
  "geometry": {"coordinates":[-122.245974,37.879796],"type":"Point"}
}