{
  "type": "Feature",
  "properties": {
    "addr:full":"6333 W 3rd Street Suite 816 Los Angeles CA 90036",
    "addr:housenumber":"6333",
    "addr:postcode":"90036",
    "addr:street":"W 3Rd Street Suite 816",
    "iso:country":"US",
    "sg:address":"6333 W 3rd Street Suite 816",
    "sg:city":"Los Angeles",
    "sg:classifiers":[
        {
            "category":"Wholesale",
            "subcategory":"Fruits & Vegetables",
            "type":"Manufacturing & Wholesale Goods"
        }
    ],
    "sg:phone":"+1 323 931 3773",
    "sg:postcode":"90036",
    "sg:province":"CA",
    "sg:tags":[
        "veggie"
    ],
    "wof:name":"Farm Fresh",
    "wof:placetype":"venue"
},
  "geometry": {"coordinates":[-118.36009799999999,34.071328],"type":"Point"}
}