{
  "type": "Feature",
  "properties": {
    "iso:country":"US",
    "sg:address":"1214 Oakmead Pkwy",
    "sg:city":"Sunnyvale",
    "sg:classifiers":[
        {
            "category":"Manufacturing",
            "subcategory":"Tools & Machinery",
            "type":"Manufacturing & Wholesale Goods"
        }
    ],
    "sg:phone":"+1 408 737 8522",
    "sg:postcode":"94085",
    "sg:province":"CA",
    "sg:tags":[
        "equipment",
        "laboratory",
        "supply"
    ],
    "sg:website":"www.dionex.com",
    "wof:name":"Dionex Corp",
    "wof:placetype":"venue"
},
  "geometry": {"coordinates":[-121.99335000000001,37.38678],"type":"Point"}
}