{
  "type": "Feature",
  "properties": {
    "iso:country":"US",
    "sg:address":"1375 Blossom Hill Rd",
    "sg:city":"San Jose",
    "sg:classifiers":[
        {
            "category":"Personal",
            "subcategory":"Beauty Salon",
            "type":"Services"
        }
    ],
    "sg:phone":"+1 408 265 5201",
    "sg:postcode":"95118",
    "sg:province":"CA",
    "wof:name":"Lisa Nails",
    "wof:placetype":"venue"
},
  "geometry": {"coordinates":[-121.88819100000001,37.245242],"type":"Point"}
}