{
  "type": "Feature",
  "properties": {
    "iso:country":"US",
    "sg:address":"27932 La Paz Rd",
    "sg:city":"Laguna Niguel",
    "sg:classifiers":[
        {
            "category":"Restaurant",
            "type":"Food & Drink"
        }
    ],
    "sg:phone":"+1 949 362 2800",
    "sg:postcode":"92677",
    "sg:province":"CA",
    "sg:tags":[
        "italian",
        "pizza"
    ],
    "wof:name":"Bella Italian Kitchen Pizza & Pasta",
    "wof:placetype":"venue"
},
  "geometry": {"coordinates":[-117.708737,33.557356],"type":"Point"}
}