{
  "type": "Feature",
  "properties": {
    "addr:full":"320 Tropicana Ranch Rd Colton CA 92324",
    "addr:housenumber":"320",
    "addr:postcode":"92324",
    "addr:street":"Tropicana Ranch Rd",
    "iso:country":"US",
    "sg:address":"320 Tropicana Ranch Rd",
    "sg:city":"Colton",
    "sg:classifiers":[
        {
            "category":"Real Estate",
            "subcategory":"Developer",
            "type":"Services"
        }
    ],
    "sg:phone":"+1 909 825 5296",
    "sg:postcode":"92324",
    "sg:province":"CA",
    "wof:name":"Medlin Development",
    "wof:placetype":"venue"
},
  "geometry": {"coordinates":[-117.333366,34.04369],"type":"Point"}
}