{
  "type": "Feature",
  "properties": {
    "addr:full":"15217 Burbank Blvd Sherman Oaks CA 91411",
    "addr:housenumber":"15217",
    "addr:postcode":"91411",
    "addr:street":"Burbank Blvd",
    "iso:country":"US",
    "sg:address":"15217 Burbank Blvd",
    "sg:city":"Sherman Oaks",
    "sg:classifiers":[
        {
            "category":"Professional",
            "subcategory":"Lawyer & Legal Services",
            "type":"Services"
        }
    ],
    "sg:phone":"+1 818 994 6666",
    "sg:postcode":"91411",
    "sg:province":"CA",
    "sg:tags":[
        "attorney"
    ],
    "wof:name":"Joan M Lauricella Law Offices",
    "wof:placetype":"venue"
},
  "geometry": {"coordinates":[-118.464051,34.172184],"type":"Point"}
}