{
  "type": "Feature",
  "properties": {
    "iso:country":"US",
    "sg:address":"3100 Somis Rd",
    "sg:city":"Somis",
    "sg:classifiers":[
        {
            "category":"Wholesale",
            "subcategory":"Construction Materials",
            "type":"Manufacturing & Wholesale Goods"
        }
    ],
    "sg:phone":"+1 805 386 2113",
    "sg:postcode":"93066",
    "sg:province":"CA",
    "sg:tags":[
        "sand",
        "gravel"
    ],
    "wof:name":"KWIK Kart Ready Mix",
    "wof:placetype":"venue"
},
  "geometry": {"coordinates":[-118.99668699999999,34.254784],"type":"Point"}
}