{
  "type": "Feature",
  "properties": {
    "addr:full":"6070 Stover Ave Riverside CA 92505",
    "addr:housenumber":"6070",
    "addr:postcode":"92505",
    "addr:street":"Stover Ave",
    "iso:country":"US",
    "sg:address":"6070 Stover Ave",
    "sg:city":"Riverside",
    "sg:classifiers":[
        {
            "category":"Autos & Motor Vehicles",
            "subcategory":"Auto Supplies",
            "type":"Retail Goods"
        }
    ],
    "sg:phone":"+1 951 352 0496",
    "sg:postcode":"92505",
    "sg:province":"CA",
    "sg:tags":[
        "equipment",
        "racing",
        "car",
        "automobile"
    ],
    "wof:name":"Hammer Racing Enterprises",
    "wof:placetype":"venue"
},
  "geometry": {"coordinates":[-117.48917,33.943541],"type":"Point"}
}