{
  "type": "Feature",
  "properties": {
    "addr:full":"45630 Citrus Ave Indio CA 92201",
    "addr:housenumber":"45630",
    "addr:postcode":"92201",
    "addr:street":"Citrus Ave",
    "iso:country":"US",
    "sg:address":"45630 Citrus Ave",
    "sg:city":"Indio",
    "sg:classifiers":[
        {
            "category":"Wholesale",
            "subcategory":"Furniture",
            "type":"Manufacturing & Wholesale Goods"
        }
    ],
    "sg:phone":"+1 760 347 7322",
    "sg:postcode":"92201",
    "sg:province":"CA",
    "wof:name":"M B & G Marketing",
    "wof:placetype":"venue"
},
  "geometry": {"coordinates":[-116.201033,33.718007],"type":"Point"}
}