{
  "type": "Feature",
  "properties": {
    "iso:country":"US",
    "sg:address":"520 Tennant Ave",
    "sg:city":"Morgan Hill",
    "sg:classifiers":[
        {
            "category":"Restaurant",
            "type":"Food & Drink"
        }
    ],
    "sg:phone":"+1 408 779 4133",
    "sg:postcode":"95037",
    "sg:province":"CA",
    "sg:tags":[
        "caterer"
    ],
    "wof:name":"Mi Casa Mexican Deli",
    "wof:placetype":"venue"
},
  "geometry": {"coordinates":[-121.634298,37.116186],"type":"Point"}
}