{
  "type": "Feature",
  "properties": {
    "iso:country":"US",
    "sg:address":"381 1st St",
    "sg:city":"Los Altos",
    "sg:classifiers":[
        {
            "category":"Personal",
            "subcategory":"Beauty Salon",
            "type":"Services"
        }
    ],
    "sg:phone":"+1 650 948 3033",
    "sg:postcode":"94022",
    "sg:province":"CA",
    "wof:name":"Salon Elizabeth",
    "wof:placetype":"venue"
},
  "geometry": {"coordinates":[-122.11595800000001,37.375737],"type":"Point"}
}