{
  "type": "Feature",
  "properties": {
    "addr:full":"7616 Alston Ave Hesperia CA 92345",
    "addr:housenumber":"7616",
    "addr:postcode":"92345",
    "addr:street":"Alston Ave",
    "iso:country":"US",
    "sg:address":"7616 Alston Ave",
    "sg:city":"Hesperia",
    "sg:classifiers":[
        {
            "category":"Building & Trades",
            "subcategory":"Construction",
            "type":"Services"
        }
    ],
    "sg:phone":"+1 760 948 9041",
    "sg:postcode":"92345",
    "sg:province":"CA",
    "sg:tags":[
        "concrete",
        "pumping"
    ],
    "wof:name":"Garcia's Concrete Pumping",
    "wof:placetype":"venue"
},
  "geometry": {"coordinates":[-117.298225,34.3907],"type":"Point"}
}