{
  "type": "Feature",
  "properties": {
    "addr:full":"11227 Sheldon St Sun Valley CA 91352",
    "addr:housenumber":"11227",
    "addr:postcode":"91352",
    "addr:street":"Sheldon St",
    "iso:country":"US",
    "sg:address":"11227 Sheldon St",
    "sg:city":"Sun Valley",
    "sg:classifiers":[
        {
            "category":"Building & Trades",
            "subcategory":"Construction",
            "type":"Services"
        }
    ],
    "sg:phone":"+1 818 767 4768",
    "sg:postcode":"91352",
    "sg:province":"CA",
    "sg:tags":[
        "roofing",
        "contractor"
    ],
    "wof:name":"Richter Roofing Co",
    "wof:placetype":"venue"
},
  "geometry": {"coordinates":[-118.376904,34.251691],"type":"Point"}
}