{
  "type": "Feature",
  "properties": {
    "addr:full":"31532 Railroad Canyon Rd Ste 112 Canyon Lake CA 92587",
    "addr:housenumber":"31532",
    "addr:postcode":"92587",
    "addr:street":"Railroad Canyon Rd Ste 112",
    "iso:country":"US",
    "sg:address":"31532 Railroad Canyon Rd Ste 112",
    "sg:city":"Canyon Lake",
    "sg:classifiers":[
        {
            "category":"Health Services",
            "subcategory":"Chiropractor",
            "type":"Services"
        }
    ],
    "sg:phone":"+1 951 244 4040",
    "sg:postcode":"92587",
    "sg:province":"CA",
    "wof:name":"Jc Swink Chiropractic Inc",
    "wof:placetype":"venue"
},
  "geometry": {"coordinates":[-117.25176999999999,33.673112],"type":"Point"}
}