{
  "type": "Feature",
  "properties": {
    "addr:full":"26780 Ynez Ct Ste-D Temecula CA 92591",
    "addr:housenumber":"26780",
    "addr:postcode":"92591",
    "addr:street":"Ynez Ct Ste-D",
    "iso:country":"US",
    "sg:address":"26780 Ynez Ct Ste-D",
    "sg:city":"Temecula",
    "sg:classifiers":[
        {
            "category":"Personal",
            "subcategory":"Beauty Salon",
            "type":"Services"
        }
    ],
    "sg:phone":"+1 951 676 8444",
    "sg:postcode":"92591",
    "sg:province":"CA",
    "wof:name":"Cosa Bella Salon",
    "wof:placetype":"venue"
},
  "geometry": {"coordinates":[-117.15409699999999,33.513287],"type":"Point"}
}