{
  "type": "Feature",
  "properties": {
    "addr:full":"9675 Doreen Dr Cypress CA 90630",
    "addr:housenumber":"9675",
    "addr:postcode":"90630",
    "addr:street":"Doreen Dr",
    "iso:country":"US",
    "sg:address":"9675 Doreen Dr",
    "sg:city":"Cypress",
    "sg:classifiers":[
        {
            "category":"Building & Trades",
            "subcategory":"Construction",
            "type":"Services"
        }
    ],
    "sg:phone":"+1 714 821 3554",
    "sg:postcode":"90630",
    "sg:province":"CA",
    "sg:tags":[
        "contractor"
    ],
    "wof:name":"D B General Contracting",
    "wof:placetype":"venue"
},
  "geometry": {"coordinates":[-118.15208800000001,33.821285],"type":"Point"}
}