{
  "type": "Feature",
  "properties": {
    "addr:full":"6320 Canoga Ave Woodland Hills CA 91367",
    "addr:housenumber":"6320",
    "addr:postcode":"91367",
    "addr:street":"Canoga Ave",
    "iso:country":"US",
    "sg:address":"6320 Canoga Ave",
    "sg:city":"Woodland Hills",
    "sg:classifiers":[
        {
            "category":"Professional",
            "subcategory":"Lawyer & Legal Services",
            "type":"Services"
        }
    ],
    "sg:phone":"+1 818 888 7731",
    "sg:postcode":"91367",
    "sg:province":"CA",
    "sg:tags":[
        "divorce",
        "law",
        "family"
    ],
    "wof:name":"Przelomiec Debra Atty",
    "wof:placetype":"venue"
},
  "geometry": {"coordinates":[-118.596227,34.185596],"type":"Point"}
}