{
  "type": "Feature",
  "properties": {
    "iso:country":"US",
    "sg:address":"30081 Crown Valley Pkwy",
    "sg:city":"Laguna Niguel",
    "sg:classifiers":[
        {
            "category":"Retail",
            "subcategory":"Car Wash",
            "type":"Services"
        }
    ],
    "sg:phone":"+1 949 495 4901",
    "sg:postcode":"92677",
    "sg:province":"CA",
    "sg:tags":[
        "polishing",
        "washing"
    ],
    "wof:name":"Laguna Niguel Car Wash",
    "wof:placetype":"venue"
},
  "geometry": {"coordinates":[-117.709414,33.52825],"type":"Point"}
}