{
  "type": "Feature",
  "properties": {
    "iso:country":"US",
    "sg:address":"158 E Saint Joseph St",
    "sg:city":"Arcadia",
    "sg:classifiers":[
        {
            "category":"Manufacturing",
            "subcategory":"Metals",
            "type":"Manufacturing & Wholesale Goods"
        }
    ],
    "sg:phone":"+1 626 447 0875",
    "sg:postcode":"91006",
    "sg:province":"CA",
    "sg:tags":[
        "mfg",
        "automotive",
        "stampings",
        "metalwork",
        "structural"
    ],
    "wof:name":"Cfd",
    "wof:placetype":"venue"
},
  "geometry": {"coordinates":[-118.02682299999999,34.143326],"type":"Point"}
}