{
  "type": "Feature",
  "properties": {
    "addr:full":"3625 del Amo Blvd Torrance CA 90501",
    "addr:housenumber":"3625",
    "addr:postcode":"90501",
    "addr:street":"Del Amo Blvd",
    "iso:country":"US",
    "sg:address":"3625 del Amo Blvd",
    "sg:city":"Torrance",
    "sg:classifiers":[
        {
            "category":"Insurance",
            "subcategory":"Insurance Agent",
            "type":"Services"
        }
    ],
    "sg:phone":"+1 310 370 7565",
    "sg:postcode":"90501",
    "sg:province":"CA",
    "wof:name":"Denise Waldo Insurance Agency",
    "wof:placetype":"venue"
},
  "geometry": {"coordinates":[-118.35012500000001,33.848644],"type":"Point"}
}