{
  "type": "Feature",
  "properties": {
    "iso:country":"US",
    "sg:address":"6687 Blue Heron Dr",
    "sg:city":"Upper Lake",
    "sg:classifiers":[
        {
            "category":"Real Estate",
            "subcategory":"Real Estate Operator",
            "type":"Services"
        }
    ],
    "sg:phone":"+1 707 274 8278",
    "sg:postcode":"95485",
    "sg:province":"CA",
    "sg:tags":[
        "apartment"
    ],
    "wof:name":"Blue Heron Gardens",
    "wof:placetype":"venue"
},
  "geometry": {"coordinates":[-122.865146,39.121936],"type":"Point"}
}