{
  "type": "Feature",
  "properties": {
    "addr:full":"826 Bay Ave Capitola CA 95010",
    "addr:housenumber":"826",
    "addr:postcode":"95010",
    "addr:street":"Bay Ave",
    "iso:country":"US",
    "sg:address":"826 Bay Ave",
    "sg:city":"Capitola",
    "sg:classifiers":[
        {
            "category":"Government",
            "subcategory":"Post Office",
            "type":"Public Place"
        }
    ],
    "sg:phone":"+1 831 000 1111",
    "sg:postcode":"95010",
    "sg:province":"CA",
    "wof:name":"US Post Office",
    "wof:placetype":"venue"
},
  "geometry": {"coordinates":[-121.956833,36.982673],"type":"Point"}
}