{
  "type": "Feature",
  "properties": {
    "iso:country":"US",
    "sg:address":"10740 Foothill Blvd",
    "sg:city":"Rancho Cucamonga",
    "sg:classifiers":[
        {
            "category":"Shopping",
            "type":"Retail Goods"
        }
    ],
    "sg:phone":"+1 909 948 2427",
    "sg:postcode":"91730",
    "sg:province":"CA",
    "sg:tags":[
        "telephone",
        "cellular"
    ],
    "wof:name":"Verizon Wireless",
    "wof:placetype":"venue"
},
  "geometry": {"coordinates":[-117.567791,34.106572],"type":"Point"}
}