{
  "type": "Feature",
  "properties": {
    "addr:full":"8361 Westminster Blvd Suite 300 Westminster CA 92683",
    "addr:housenumber":"8361",
    "addr:postcode":"92683",
    "addr:street":"Westminster Blvd Suite 300",
    "iso:country":"US",
    "sg:address":"8361 Westminster Blvd Suite 300",
    "sg:city":"Westminster",
    "sg:classifiers":[
        {
            "category":"Banks & Credit Unions",
            "subcategory":"Financial Services",
            "type":"Services"
        }
    ],
    "sg:phone":"+1 714 901 1333",
    "sg:postcode":"92683",
    "sg:province":"CA",
    "sg:website":"www.e-bankcard.com",
    "wof:name":"BankCard Services",
    "wof:placetype":"venue"
},
  "geometry": {"coordinates":[-117.98318,33.759688],"type":"Point"}
}