{
  "type": "Feature",
  "properties": {
    "addr:full":"100 Bayview Cir Ste 500 Newport Beach CA 92660",
    "addr:housenumber":"100",
    "addr:postcode":"92660",
    "addr:street":"Bayview Cir Ste 500",
    "iso:country":"US",
    "sg:address":"100 Bayview Cir Ste 500",
    "sg:city":"Newport Beach",
    "sg:classifiers":[
        {
            "category":"Banks & Credit Unions",
            "subcategory":"Investment Brokerage",
            "type":"Services"
        }
    ],
    "sg:phone":"+1 949 823 7700",
    "sg:postcode":"92660",
    "sg:province":"CA",
    "sg:tags":[
        "investing"
    ],
    "sg:website":"www.hollencrest.com",
    "wof:name":"Hollencrest Securities Llc",
    "wof:placetype":"venue"
},
  "geometry": {"coordinates":[-117.86900300000001,33.655399],"type":"Point"}
}