{
  "type": "Feature",
  "properties": {
    "iso:country":"US",
    "sg:address":"111 N La Cienega",
    "sg:city":"Beverly Hills",
    "sg:classifiers":[
        {
            "category":"Restaurant",
            "type":"Food & Drink"
        }
    ],
    "sg:phone":"+1 310 289 0300",
    "sg:postcode":"90211",
    "sg:province":"CA",
    "sg:tags":[
        "mediterranean"
    ],
    "sg:website":"www.darioushrestaurant.com",
    "wof:name":"Darioush Restaurant",
    "wof:placetype":"venue"
},
  "geometry": {"coordinates":[-118.37632,34.067244],"type":"Point"}
}