{
  "type": "Feature",
  "properties": {
    "iso:country":"US",
    "sg:address":"305 N 2nd Ave",
    "sg:city":"Upland",
    "sg:classifiers":[
        {
            "category":"Real Estate",
            "subcategory":"Real Estate Agent",
            "type":"Services"
        }
    ],
    "sg:phone":"+1 909 985 8960",
    "sg:postcode":"91786",
    "sg:province":"CA",
    "wof:name":"Charter Group",
    "wof:placetype":"venue"
},
  "geometry": {"coordinates":[-117.648504,34.097875],"type":"Point"}
}