{
  "type": "Feature",
  "properties": {
    "addr:full":"469 Center St Riverside CA 92507",
    "addr:housenumber":"469",
    "addr:postcode":"92507",
    "addr:street":"Center St",
    "iso:country":"US",
    "sg:address":"469 Center St",
    "sg:city":"Riverside",
    "sg:classifiers":[
        {
            "category":"Government",
            "subcategory":"Fire Station",
            "type":"Public Place"
        }
    ],
    "sg:phone":"+1 951 784 9117",
    "sg:postcode":"92507",
    "sg:province":"CA",
    "sg:tags":[
        "department",
        "parish",
        "government-county"
    ],
    "sg:website":"http://www.riversideassessor.com",
    "wof:name":"Highgrove Volunteer Fire Dept.",
    "wof:placetype":"venue"
},
  "geometry": {"coordinates":[-117.321546,34.015667],"type":"Point"}
}