{
  "type": "Feature",
  "properties": {
    "addr:full":"3150 Molinaro St Santa Clara CA 95054",
    "addr:housenumber":"3150",
    "addr:postcode":"95054",
    "addr:street":"Molinaro St",
    "iso:country":"US",
    "sg:address":"3150 Molinaro St",
    "sg:city":"Santa Clara",
    "sg:classifiers":[
        {
            "category":"Shopping",
            "subcategory":"Optician",
            "type":"Retail Goods"
        }
    ],
    "sg:phone":"+1 408 988 5861",
    "sg:postcode":"95054",
    "sg:province":"CA",
    "sg:tags":[
        "eyewear"
    ],
    "wof:name":"Bachur & Associates",
    "wof:placetype":"venue"
},
  "geometry": {"coordinates":[-121.94488800000001,37.379421],"type":"Point"}
}