{
  "type": "Feature",
  "properties": {
    "addr:full":"1433 E Cisneros Ln Placentia CA 92870",
    "addr:housenumber":"1433",
    "addr:postcode":"ca 92870",
    "addr:street":"E Cisneros Ln",
    "iso:country":"US",
    "sg:address":"1433 E Cisneros Ln",
    "sg:city":"Placentia",
    "sg:classifiers":[
        {
            "category":"Shopping",
            "type":"Retail Goods"
        }
    ],
    "sg:phone":"+1 714 524 3236",
    "sg:postcode":"92870",
    "sg:province":"CA",
    "sg:tags":[
        "merchandise"
    ],
    "wof:name":"Gsr Marketing",
    "wof:placetype":"venue"
},
  "geometry": {"coordinates":[-117.836339,33.875673],"type":"Point"}
}