{
  "type": "Feature",
  "properties": {
    "iso:country":"US",
    "sg:address":"1432 9th St",
    "sg:city":"Modesto",
    "sg:classifiers":[
        {
            "category":"Autos & Motor Vehicles",
            "subcategory":"Fuel & Gas Station",
            "type":"Retail Goods"
        }
    ],
    "sg:phone":"+1 209 544 6007",
    "sg:postcode":"95354",
    "sg:province":"CA",
    "sg:tags":[
        "oil"
    ],
    "wof:name":"USA Gasoline",
    "wof:placetype":"venue"
},
  "geometry": {"coordinates":[-121.006559,37.644296],"type":"Point"}
}