{
  "type": "Feature",
  "properties": {
    "iso:country":"US",
    "sg:address":"3669 E Thousand Oaks Blvd",
    "sg:city":"Westlake Village",
    "sg:classifiers":[
        {
            "category":"Professional",
            "subcategory":"Accounting & Tax Preparation",
            "type":"Services"
        }
    ],
    "sg:phone":"+1 805 371 0616",
    "sg:postcode":"91362",
    "sg:province":"CA",
    "sg:tags":[
        "consultant"
    ],
    "wof:name":"H & R Block Premium Tax Svc",
    "wof:placetype":"venue"
},
  "geometry": {"coordinates":[-118.830147,34.164913],"type":"Point"}
}