{
  "type": "Feature",
  "properties": {
    "iso:country":"US",
    "sg:address":"1107 Glendon Ave",
    "sg:city":"Los Angeles",
    "sg:classifiers":[
        {
            "category":"Building & Trades",
            "subcategory":"Construction",
            "type":"Services"
        }
    ],
    "sg:phone":"+1 310 208 8108",
    "sg:postcode":"90024",
    "sg:province":"CA",
    "sg:tags":[
        "contractor"
    ],
    "wof:name":"Michael T Morris & Assoc",
    "wof:placetype":"venue"
},
  "geometry": {"coordinates":[-118.444427,34.057744],"type":"Point"}
}