{
  "type": "Feature",
  "properties": {
    "iso:country":"US",
    "sg:address":"Women's Care of Beverly Hills 8920 Wilshire Blvd",
    "sg:city":"Beverly Hills",
    "sg:classifiers":[
        {
            "category":"Health Services",
            "subcategory":"Doctor",
            "type":"Services"
        }
    ],
    "sg:phone":"+1 310 657 1600",
    "sg:postcode":"90211",
    "sg:province":"CA",
    "sg:tags":[
        "obstetrician",
        "gynecologist"
    ],
    "sg:website":"www.womenscareofbeverlyhillsgrou...",
    "wof:name":"Ruth Cousineau, MD",
    "wof:placetype":"venue"
},
  "geometry": {"coordinates":[-118.386495,34.067107],"type":"Point"}
}