{
  "type": "Feature",
  "properties": {
    "addr:full":"18770 Amar Rd Walnut CA 91789",
    "addr:housenumber":"18770",
    "addr:postcode":"91789",
    "addr:street":"Amar Rd",
    "iso:country":"US",
    "sg:address":"18770 Amar Rd",
    "sg:city":"Walnut",
    "sg:classifiers":[
        {
            "category":"Restaurant",
            "type":"Food & Drink"
        }
    ],
    "sg:menulink":"http://www.allmenus.com/ca/east-san-gabriel-valley/73975-dominos-pizza/menu/",
    "sg:phone":"+1 626 913 4044",
    "sg:postcode":"91789",
    "sg:province":"CA",
    "sg:tags":[
        "american",
        "wing",
        "pizza"
    ],
    "wof:name":"Domino's Pizza",
    "wof:placetype":"venue"
},
  "geometry": {"coordinates":[-117.892839,34.028051],"type":"Point"}
}