{
  "type": "Feature",
  "properties": {
    "iso:country":"US",
    "sg:address":"2101 Jamestown Way",
    "sg:city":"Oxnard",
    "sg:classifiers":[
        {
            "category":"Professional",
            "subcategory":"Engineering",
            "type":"Services"
        },
        {
            "category":"Professional",
            "subcategory":"Business Services",
            "type":"Services"
        },
        {
            "category":"Professional",
            "subcategory":"Management & Consulting",
            "type":"Services"
        }
    ],
    "sg:phone":"+1 805 984 1003",
    "sg:postcode":"93035",
    "sg:province":"CA",
    "sg:tags":[
        "consultant",
        "product",
        "engineer",
        "ecological",
        "environmental"
    ],
    "sg:website":"http://www.eremco.com",
    "wof:name":"Eremco Inc",
    "wof:placetype":"venue"
},
  "geometry": {"coordinates":[-119.229257,34.180487],"type":"Point"}
}