{
  "type": "Feature",
  "properties": {
    "addr:full":"2569 N Pima Ave Fresno CA 93722",
    "addr:housenumber":"2569",
    "addr:postcode":"93722",
    "addr:street":"N Pima Ave",
    "iso:country":"US",
    "sg:address":"2569 N Pima Ave",
    "sg:city":"Fresno",
    "sg:classifiers":[
        {
            "category":"Professional",
            "subcategory":"Accounting & Tax Preparation",
            "type":"Services"
        }
    ],
    "sg:phone":"+1 559 275 3448",
    "sg:postcode":"93722",
    "sg:province":"CA",
    "sg:tags":[
        "bookkeeping",
        "billing"
    ],
    "wof:name":"Advaned Med Blling Collections",
    "wof:placetype":"venue"
},
  "geometry": {"coordinates":[-119.87061300000001,36.775002],"type":"Point"}
}