{
  "type": "Feature",
  "properties": {
    "iso:country":"US",
    "sg:address":"8720 Melrose Ave",
    "sg:city":"West Hollywood",
    "sg:classifiers":[
        {
            "category":"Home & Garden",
            "subcategory":"Furniture",
            "type":"Retail Goods"
        }
    ],
    "sg:phone":"+1 310 659 3062",
    "sg:postcode":"90069",
    "sg:province":"CA",
    "sg:tags":[
        "store"
    ],
    "wof:name":"Formations",
    "wof:placetype":"venue"
},
  "geometry": {"coordinates":[-118.385002,34.080898],"type":"Point"}
}