{
  "type": "Feature",
  "properties": {
    "iso:country":"US",
    "sg:address":"2556 Imperial Ave",
    "sg:city":"San Diego",
    "sg:classifiers":[
        {
            "category":"Shopping",
            "subcategory":"Jewelry",
            "type":"Retail Goods"
        }
    ],
    "sg:phone":"+1 619 231 1152",
    "sg:postcode":"92102",
    "sg:province":"CA",
    "wof:name":"Angeles Jewelry",
    "wof:placetype":"venue"
},
  "geometry": {"coordinates":[-117.13862,32.706426],"type":"Point"}
}