{
  "type": "Feature",
  "properties": {
    "iso:country":"US",
    "sg:address":"7313 Melodia Ter",
    "sg:city":"Carlsbad",
    "sg:classifiers":[
        {
            "category":"Building & Trades",
            "subcategory":"Construction",
            "type":"Services"
        }
    ],
    "sg:phone":"+1 760 931 2671",
    "sg:postcode":"92011",
    "sg:province":"CA",
    "sg:tags":[
        "masonry",
        "contractor"
    ],
    "wof:name":"Kennedy Masonry",
    "wof:placetype":"venue"
},
  "geometry": {"coordinates":[-117.29780100000001,33.094193],"type":"Point"}
}