{
  "type": "Feature",
  "properties": {
    "addr:full":"614 College Ave Santa Rosa CA 95404",
    "addr:housenumber":"614",
    "addr:postcode":"95404",
    "addr:street":"College Ave",
    "iso:country":"US",
    "sg:address":"614 College Ave",
    "sg:city":"Santa Rosa",
    "sg:classifiers":[
        {
            "category":"Personal",
            "subcategory":"Beauty Salon",
            "type":"Services"
        }
    ],
    "sg:phone":"+1 707 545 4080",
    "sg:postcode":"95404",
    "sg:province":"CA",
    "wof:name":"Cyndi Stanczyk",
    "wof:placetype":"venue"
},
  "geometry": {"coordinates":[-122.71732299999999,38.445559],"type":"Point"}
}