{
  "type": "Feature",
  "properties": {
    "iso:country":"US",
    "sg:address":"404 Camino del Rio S Ste 100 Studio 4",
    "sg:city":"San Diego",
    "sg:classifiers":[
        {
            "category":"Personal",
            "subcategory":"Beauty Salon",
            "type":"Services"
        }
    ],
    "sg:phone":"+1 619 248 1493",
    "sg:postcode":"92108",
    "sg:province":"CA",
    "sg:tags":[
        "hair"
    ],
    "sg:website":"www.patriciakdesigns.com",
    "wof:name":"Patricia K Designs \u00a0Hair Salon",
    "wof:placetype":"venue"
},
  "geometry": {"coordinates":[-117.16204,32.761378],"type":"Point"}
}