{
  "type": "Feature",
  "properties": {
    "addr:full":"22670 State Rte 26 West Point CA 95255",
    "addr:housenumber":"22670",
    "addr:postcode":"95255",
    "addr:street":"State Rte 26",
    "iso:country":"US",
    "sg:address":"22670 State Rte 26",
    "sg:city":"West Point",
    "sg:classifiers":[
        {
            "category":"Government",
            "subcategory":"Fire Station",
            "type":"Public Place"
        }
    ],
    "sg:phone":"+1 209 293 4222",
    "sg:postcode":"95255",
    "sg:province":"CA",
    "sg:tags":[
        "state",
        "protection"
    ],
    "wof:name":"Forest Fire Station",
    "wof:placetype":"venue"
},
  "geometry": {"coordinates":[-120.53110100000001,38.40651],"type":"Point"}
}