{
  "type": "Feature",
  "properties": {
    "iso:country":"US",
    "sg:address":"195 E Lincoln St",
    "sg:city":"Banning",
    "sg:classifiers":[
        {
            "category":"Health Services",
            "subcategory":"Medical Lab",
            "type":"Services"
        }
    ],
    "sg:phone":"+1 951 849 5879",
    "sg:postcode":"92220",
    "sg:province":"CA",
    "sg:tags":[
        "laboratory"
    ],
    "wof:name":"Haven Laboratory",
    "wof:placetype":"venue"
},
  "geometry": {"coordinates":[-116.876509,33.921813],"type":"Point"}
}