{
  "type": "Feature",
  "properties": {
    "addr:full":"5777 W Century Blvd Los Angeles CA 90045",
    "addr:housenumber":"5777",
    "addr:postcode":"90045",
    "addr:street":"W Century Blvd",
    "iso:country":"US",
    "sg:address":"5777 W Century Blvd",
    "sg:city":"Los Angeles",
    "sg:classifiers":[
        {
            "category":"Professional",
            "subcategory":"Computer Services",
            "type":"Services"
        }
    ],
    "sg:phone":"+1 310 216 4000",
    "sg:postcode":"90045",
    "sg:province":"CA",
    "sg:tags":[
        "consultant",
        "designer"
    ],
    "wof:name":"DGH Consulting Inc",
    "wof:placetype":"venue"
},
  "geometry": {"coordinates":[-118.382222,33.945637],"type":"Point"}
}