{
  "type": "Feature",
  "properties": {
    "iso:country":"US",
    "sg:address":"14568 Vancouver Ave",
    "sg:city":"Fontana",
    "sg:classifiers":[
        {
            "category":"Arts & Performance",
            "subcategory":"Theater",
            "type":"Entertainment"
        }
    ],
    "sg:phone":"+1 909 899 3224",
    "sg:postcode":"92336",
    "sg:province":"CA",
    "sg:tags":[
        "live",
        "music"
    ],
    "wof:name":"Fine Artists Entertainment",
    "wof:placetype":"venue"
},
  "geometry": {"coordinates":[-117.486944,34.159262],"type":"Point"}
}