{
  "type": "Feature",
  "properties": {
    "addr:full":"818 W Las Tunas Dr San Gabriel CA 91776",
    "addr:housenumber":"818",
    "addr:postcode":"91776",
    "addr:street":"W Las Tunas Dr",
    "iso:country":"US",
    "sg:address":"818 W Las Tunas Dr",
    "sg:city":"San Gabriel",
    "sg:classifiers":[
        {
            "category":"Wholesale",
            "subcategory":"Machinery & Supplies",
            "type":"Manufacturing & Wholesale Goods"
        }
    ],
    "sg:phone":"+1 626 570 8700",
    "sg:postcode":"91776",
    "sg:province":"CA",
    "sg:tags":[
        "janitor"
    ],
    "wof:name":"Pacific Sanitary Supply",
    "wof:placetype":"venue"
},
  "geometry": {"coordinates":[-118.11113899999999,34.102282],"type":"Point"}
}