{
  "type": "Feature",
  "properties": {
    "addr:full":"760 Epperson Dr City Of Industry CA 91748",
    "addr:housenumber":"760",
    "addr:postcode":"91748",
    "addr:street":"Epperson Dr",
    "iso:country":"US",
    "sg:address":"760 Epperson Dr",
    "sg:city":"City Of Industry",
    "sg:classifiers":[
        {
            "category":"Manufacturing",
            "subcategory":"Food",
            "type":"Manufacturing & Wholesale Goods"
        }
    ],
    "sg:phone":"+1 626 854 1655",
    "sg:postcode":"91748",
    "sg:province":"CA",
    "sg:tags":[
        "product",
        "manufacturer"
    ],
    "sg:website":"www.morehousefoods.com",
    "wof:name":"Atomic Food Products Inc",
    "wof:placetype":"venue"
},
  "geometry": {"coordinates":[-117.896682,34.002912],"type":"Point"}
}