{
  "type": "Feature",
  "properties": {
    "addr:full":"492 S Madera Ave Kerman CA 93630",
    "addr:housenumber":"492",
    "addr:postcode":"93630",
    "addr:street":"S Madera Ave",
    "iso:country":"US",
    "sg:address":"492 S Madera Ave",
    "sg:city":"Kerman",
    "sg:classifiers":[
        {
            "category":"Shopping",
            "subcategory":"Clothing, Apparel, & Fashions",
            "type":"Retail Goods"
        }
    ],
    "sg:phone":"+1 559 846 5590",
    "sg:postcode":"93630",
    "sg:province":"CA",
    "sg:tags":[
        "family"
    ],
    "wof:name":"Gaytan Sales",
    "wof:placetype":"venue"
},
  "geometry": {"coordinates":[-120.060124,36.727735],"type":"Point"}
}