{
  "type": "Feature",
  "properties": {
    "addr:full":"10736 Jefferson Boulevard Culver City CA 90230",
    "addr:housenumber":"10736",
    "addr:postcode":"90230",
    "addr:street":"Jefferson Boulevard",
    "iso:country":"US",
    "sg:address":"10736 Jefferson Boulevard",
    "sg:city":"Culver City",
    "sg:classifiers":[
        {
            "category":"Freight",
            "type":"Transportation"
        },
        {
            "category":"Professional",
            "subcategory":"Lawyer & Legal Services",
            "type":"Services"
        }
    ],
    "sg:phone":"+1 310 558 4778",
    "sg:postcode":"90230",
    "sg:province":"CA",
    "sg:tags":[
        "notary",
        "shipping"
    ],
    "wof:name":"UPS Store",
    "wof:placetype":"venue"
},
  "geometry": {"coordinates":[-118.394238,34.002591],"type":"Point"}
}