{
  "type": "Feature",
  "properties": {
    "addr:full":"830 N Euclid St Anaheim CA 92801",
    "addr:housenumber":"830",
    "addr:postcode":"92801",
    "addr:street":"N Euclid St",
    "iso:country":"US",
    "sg:address":"830 N Euclid St",
    "sg:city":"Anaheim",
    "sg:classifiers":[
        {
            "category":"Restaurant",
            "type":"Food & Drink"
        }
    ],
    "sg:menulink":"http://www.allmenus.com/ca/anaheim-santa-ana-garden-grove/34020-ihop/menu/",
    "sg:phone":"+1 714 535 3550",
    "sg:postcode":"92801",
    "sg:province":"CA",
    "sg:tags":[
        "sandwich",
        "salad",
        "burger",
        "soup",
        "american",
        "steakhouse",
        "wrap"
    ],
    "wof:name":"IHOP",
    "wof:placetype":"venue"
},
  "geometry": {"coordinates":[-117.941647,33.844003],"type":"Point"}
}