{
  "type": "Feature",
  "properties": {
    "iso:country":"US",
    "sg:address":"762 Fulton St",
    "sg:city":"San Francisco",
    "sg:classifiers":[
        {
            "category":"Professional",
            "type":"Services"
        }
    ],
    "sg:phone":"+1 415 928 8546",
    "sg:postcode":"94102",
    "sg:province":"CA",
    "wof:name":"Caaac",
    "wof:placetype":"venue"
},
  "geometry": {"coordinates":[-122.429149,37.778076],"type":"Point"}
}