{
  "type": "Feature",
  "properties": {
    "iso:country":"US",
    "sg:address":"1224 Tully Rd",
    "sg:city":"Modesto",
    "sg:classifiers":[
        {
            "category":"Personal",
            "subcategory":"Barber",
            "type":"Services"
        }
    ],
    "sg:phone":"+1 209 524 4995",
    "sg:postcode":"95350",
    "sg:province":"CA",
    "wof:name":"Haircutters",
    "wof:placetype":"venue"
},
  "geometry": {"coordinates":[-121.012045,37.66144],"type":"Point"}
}