{
  "type": "Feature",
  "properties": {
    "addr:full":"726 E Chevy Chase Dr Glendale CA 91205",
    "addr:housenumber":"726",
    "addr:postcode":"91205",
    "addr:street":"E Chevy Chase Dr",
    "iso:country":"US",
    "sg:address":"726 E Chevy Chase Dr",
    "sg:city":"Glendale",
    "sg:classifiers":[
        {
            "category":"Professional",
            "subcategory":"Business Services",
            "type":"Services"
        }
    ],
    "sg:phone":"+1 818 547 0367",
    "sg:postcode":"91205",
    "sg:province":"CA",
    "wof:name":"Sari-Sari Phone Card",
    "wof:placetype":"venue"
},
  "geometry": {"coordinates":[-118.248627,34.1336],"type":"Point"}
}