{
  "type": "Feature",
  "properties": {
    "addr:full":"10570 Arlington Ave Riverside CA 92505",
    "addr:housenumber":"10570",
    "addr:postcode":"92505",
    "addr:street":"Arlington Ave",
    "iso:country":"US",
    "sg:address":"10570 Arlington Ave",
    "sg:city":"Riverside",
    "sg:classifiers":[
        {
            "category":"Education",
            "subcategory":"Special Training",
            "type":"Public Place"
        }
    ],
    "sg:phone":"+1 951 687 4125",
    "sg:postcode":"92505",
    "sg:province":"CA",
    "sg:tags":[
        "reading",
        "instruction",
        "improvement"
    ],
    "wof:name":"Arlington Learning Ctr",
    "wof:placetype":"venue"
},
  "geometry": {"coordinates":[-117.484482,33.945737],"type":"Point"}
}