{
  "type": "Feature",
  "properties": {
    "iso:country":"US",
    "sg:address":"5537 N Figueroa St",
    "sg:city":"Los Angeles",
    "sg:classifiers":[
        {
            "category":"Shopping",
            "subcategory":"Jewelry",
            "type":"Retail Goods"
        }
    ],
    "sg:phone":"+1 323 257 3390",
    "sg:postcode":"90042",
    "sg:province":"CA",
    "sg:tags":[
        "jeweler"
    ],
    "wof:name":"Dominguez Jewelry",
    "wof:placetype":"venue"
},
  "geometry": {"coordinates":[-118.19499999999999,34.108799],"type":"Point"}
}