{
  "type": "Feature",
  "properties": {
    "addr:full":"28355 Industry Dr Valencia CA 91355",
    "addr:housenumber":"28355",
    "addr:postcode":"91355",
    "addr:street":"Industry Dr",
    "iso:country":"US",
    "sg:address":"28355 Industry Dr",
    "sg:city":"Valencia",
    "sg:classifiers":[
        {
            "category":"Manufacturing",
            "subcategory":"Printing",
            "type":"Manufacturing & Wholesale Goods"
        }
    ],
    "sg:phone":"+1 661 702 0145",
    "sg:postcode":"91355",
    "sg:province":"CA",
    "sg:tags":[
        "lithographic",
        "commercial"
    ],
    "wof:name":"SIS Screen Printing",
    "wof:placetype":"venue"
},
  "geometry": {"coordinates":[-118.629411,34.450652],"type":"Point"}
}