{
  "type": "Feature",
  "properties": {
    "addr:full":"1066 Wildwood Ave Thousand Oaks CA 91360",
    "addr:housenumber":"1066",
    "addr:postcode":"91360",
    "addr:street":"Wildwood Ave",
    "iso:country":"US",
    "sg:address":"1066 Wildwood Ave",
    "sg:city":"Thousand Oaks",
    "sg:classifiers":[
        {
            "category":"Professional",
            "subcategory":"Management & Consulting",
            "type":"Services"
        }
    ],
    "sg:phone":"+1 805 493 1101",
    "sg:postcode":"91360",
    "sg:province":"CA",
    "sg:tags":[
        "automobile",
        "consultant"
    ],
    "wof:name":"Fleetboss Global Positioning",
    "wof:placetype":"venue"
},
  "geometry": {"coordinates":[-118.894147,34.228312],"type":"Point"}
}