{
  "type": "Feature",
  "properties": {
    "iso:country":"US",
    "sg:address":"480 N. Glassell Street",
    "sg:city":"Anaheim",
    "sg:classifiers":[
        {
            "category":"Restaurant",
            "type":"Food & Drink"
        }
    ],
    "sg:phone":"+1 714 658 5758",
    "sg:postcode":"92806",
    "sg:province":"CA",
    "sg:tags":[
        "traditional",
        "american"
    ],
    "wof:name":"PressBox Sports Bar & Grill",
    "wof:placetype":"venue"
},
  "geometry": {"coordinates":[-117.85391,33.846135],"type":"Point"}
}