{
  "type": "Feature",
  "properties": {
    "addr:full":"1600 W Florida Ave Hemet CA 92543",
    "addr:housenumber":"1600",
    "addr:postcode":"92543",
    "addr:street":"W Florida Ave",
    "iso:country":"US",
    "sg:address":"1600 W Florida Ave",
    "sg:city":"Hemet",
    "sg:classifiers":[
        {
            "category":"Professional",
            "subcategory":"Business Services",
            "type":"Services"
        }
    ],
    "sg:phone":"+1 951 658 7135",
    "sg:postcode":"92543",
    "sg:province":"CA",
    "wof:name":"Avco Financial",
    "wof:placetype":"venue"
},
  "geometry": {"coordinates":[-116.987613,33.747541],"type":"Point"}
}