{
  "type": "Feature",
  "properties": {
    "addr:full":"1130 Peck Rd South El Monte CA 91733",
    "addr:housenumber":"1130",
    "addr:postcode":"91733",
    "addr:street":"Peck Rd",
    "iso:country":"US",
    "sg:address":"1130 Peck Rd",
    "sg:city":"South El Monte",
    "sg:classifiers":[
        {
            "category":"Autos & Motor Vehicles",
            "subcategory":"Fuel & Gas Station",
            "type":"Retail Goods"
        }
    ],
    "sg:phone":"+1 626 279 5425",
    "sg:postcode":"91733",
    "sg:province":"CA",
    "sg:tags":[
        "oil"
    ],
    "wof:name":"Anabi Oil",
    "wof:placetype":"venue"
},
  "geometry": {"coordinates":[-118.038292,34.035843],"type":"Point"}
}