{
  "type": "Feature",
  "properties": {
    "iso:country":"US",
    "sg:address":"15038 Colfax Hwy",
    "sg:city":"Grass Valley",
    "sg:classifiers":[
        {
            "category":"Farming",
            "subcategory":"Livestock Farm",
            "type":"Manufacturing & Wholesale Goods"
        }
    ],
    "sg:phone":"+1 530 273 3231",
    "sg:postcode":"95945",
    "sg:province":"CA",
    "sg:tags":[
        "ranch"
    ],
    "wof:name":"Bracken Ridge Ranch",
    "wof:placetype":"venue"
},
  "geometry": {"coordinates":[-120.986797,39.190606],"type":"Point"}
}