{
  "type": "Feature",
  "properties": {
    "addr:full":"445 S Figueroa St Los Angeles CA 90071",
    "addr:housenumber":"445",
    "addr:postcode":"90071",
    "addr:street":"S Figueroa St",
    "iso:country":"US",
    "sg:address":"445 S Figueroa St",
    "sg:city":"Los Angeles",
    "sg:classifiers":[
        {
            "category":"Restaurant",
            "type":"Food & Drink"
        }
    ],
    "sg:phone":"+1 213 629 1246",
    "sg:postcode":"90071",
    "sg:province":"CA",
    "sg:tags":[
        "fast"
    ],
    "sg:website":"www.kookooroo.com",
    "wof:name":"Koo Koo Roo",
    "wof:placetype":"venue"
},
  "geometry": {"coordinates":[-118.25677,34.052987],"type":"Point"}
}