{
  "type": "Feature",
  "properties": {
    "addr:full":"2030 Dwight Way Apt 304 Berkeley CA 94704",
    "addr:housenumber":"2030;304",
    "addr:postcode":"94704",
    "addr:street":"Dwight Way Apt",
    "iso:country":"US",
    "sg:address":"2030 Dwight Way Apt 304",
    "sg:city":"Berkeley",
    "sg:classifiers":[
        {
            "category":"Health Services",
            "subcategory":"Doctor",
            "type":"Services"
        }
    ],
    "sg:phone":"+1 510 843 5374",
    "sg:postcode":"94704",
    "sg:province":"CA",
    "sg:tags":[
        "physician",
        "surgeon"
    ],
    "wof:name":"A E Bennett Neuropsychiatry",
    "wof:placetype":"venue"
},
  "geometry": {"coordinates":[-122.268219,37.863861],"type":"Point"}
}