{
  "type": "Feature",
  "properties": {
    "iso:country":"US",
    "sg:address":"615 Hobart Terr",
    "sg:city":"Santa Clara",
    "sg:classifiers":[
        {
            "category":"Education",
            "subcategory":"Preschool",
            "type":"Public Place"
        },
        {
            "category":"Education",
            "subcategory":"School",
            "type":"Public Place"
        }
    ],
    "sg:phone":"+1 408 244 5041",
    "sg:postcode":"95051",
    "sg:province":"CA",
    "sg:tags":[
        "high",
        "middle",
        "elementary"
    ],
    "sg:website":"www.edline.net/pages/Carden_Acad...",
    "wof:name":"Carden Academy Of Santa Clara",
    "wof:placetype":"venue"
},
  "geometry": {"coordinates":[-121.978532,37.334284],"type":"Point"}
}