{
  "type": "Feature",
  "properties": {
    "addr:full":"196 W Legion Rd Brawley CA 92227",
    "addr:housenumber":"196",
    "addr:postcode":"92227",
    "addr:street":"W Legion Rd",
    "iso:country":"US",
    "sg:address":"196 W Legion Rd",
    "sg:city":"Brawley",
    "sg:classifiers":[
        {
            "category":"Health Services",
            "subcategory":"Health Practitioner",
            "type":"Services"
        }
    ],
    "sg:phone":"+1 760 344 9093",
    "sg:postcode":"92227",
    "sg:province":"CA",
    "sg:tags":[
        "psychologist"
    ],
    "wof:name":"Zona C Lai PHD",
    "wof:placetype":"venue"
},
  "geometry": {"coordinates":[-115.552942,32.959999],"type":"Point"}
}