{
  "type": "Feature",
  "properties": {
    "iso:country":"US",
    "sg:address":"3037 Sisk Rd",
    "sg:city":"Modesto",
    "sg:classifiers":[
        {
            "category":"Autos & Motor Vehicles",
            "subcategory":"Fuel & Gas Station",
            "type":"Retail Goods"
        }
    ],
    "sg:phone":"+1 209 549 2376",
    "sg:postcode":"95350",
    "sg:province":"CA",
    "sg:tags":[
        "oil"
    ],
    "wof:name":"Vintage 76",
    "wof:placetype":"venue"
},
  "geometry": {"coordinates":[-121.050764,37.684728],"type":"Point"}
}