{
  "type": "Feature",
  "properties": {
    "addr:full":"8321 Burnet Ave North Hills CA 91343",
    "addr:housenumber":"8321",
    "addr:postcode":"91343",
    "addr:street":"Burnet Ave",
    "iso:country":"US",
    "sg:address":"8321 Burnet Ave",
    "sg:city":"North Hills",
    "sg:classifiers":[
        {
            "category":"Building & Trades",
            "subcategory":"Construction",
            "type":"Services"
        }
    ],
    "sg:phone":"+1 818 893 8696",
    "sg:postcode":"91343",
    "sg:province":"CA",
    "sg:tags":[
        "designer"
    ],
    "wof:name":"Leonarda Designs",
    "wof:placetype":"venue"
},
  "geometry": {"coordinates":[-118.46343,34.221775],"type":"Point"}
}