{
  "type": "Feature",
  "properties": {
    "iso:country":"US",
    "sg:address":"517 E Wilson Ave Ste 104",
    "sg:city":"Glendale",
    "sg:classifiers":[
        {
            "category":"Fast Food",
            "type":"Food & Drink"
        }
    ],
    "sg:phone":"+1 818 240 0019",
    "sg:postcode":"91206",
    "sg:province":"CA",
    "sg:tags":[
        "burger"
    ],
    "sg:website":"www.originaltommys.com",
    "wof:name":"Tommy's Original World Famous Hamburgers",
    "wof:placetype":"venue"
},
  "geometry": {"coordinates":[-118.2499,34.148145],"type":"Point"}
}