{
  "type": "Feature",
  "properties": {
    "iso:country":"US",
    "sg:address":"1509 W Cameron Ave",
    "sg:city":"West Covina",
    "sg:classifiers":[
        {
            "category":"Professional",
            "subcategory":"Computer Services",
            "type":"Services"
        }
    ],
    "sg:phone":"+1 626 814 1101",
    "sg:postcode":"91790",
    "sg:province":"CA",
    "sg:tags":[
        "processing",
        "datum"
    ],
    "wof:name":"N P C",
    "wof:placetype":"venue"
},
  "geometry": {"coordinates":[-117.942232,34.068712],"type":"Point"}
}