{
  "type": "Feature",
  "properties": {
    "iso:country":"US",
    "sg:address":"1695 Folsom St",
    "sg:city":"San Francisco",
    "sg:classifiers":[
        {
            "category":"Autos & Motor Vehicles",
            "subcategory":"Automobile Sales",
            "type":"Retail Goods"
        }
    ],
    "sg:phone":"+1 415 863 9300",
    "sg:postcode":"94103",
    "sg:province":"CA",
    "sg:tags":[
        "car",
        "dealer"
    ],
    "wof:name":"MNS Auto Sales",
    "wof:placetype":"venue"
},
  "geometry": {"coordinates":[-122.41501700000001,37.770815],"type":"Point"}
}