{
  "type": "Feature",
  "properties": {
    "iso:country":"US",
    "sg:address":"749 W Fremont Ave",
    "sg:city":"Sunnyvale",
    "sg:classifiers":[
        {
            "category":"Health Services",
            "subcategory":"Chiropractor",
            "type":"Services"
        }
    ],
    "sg:phone":"+1 408 483 1110",
    "sg:postcode":"94087",
    "sg:province":"CA",
    "wof:name":"Chen Chiropractic",
    "wof:placetype":"venue"
},
  "geometry": {"coordinates":[-122.043318,37.352127],"type":"Point"}
}