{
  "type": "Feature",
  "properties": {
    "addr:full":"2528 Griffith St San Francisco CA 94124",
    "addr:housenumber":"2528",
    "addr:postcode":"94124",
    "addr:street":"Griffith St",
    "iso:country":"US",
    "sg:address":"2528 Griffith St",
    "sg:city":"San Francisco",
    "sg:classifiers":[
        {
            "category":"Social Services",
            "subcategory":"Child Care",
            "type":"Services"
        }
    ],
    "sg:phone":"+1 415 822 8270",
    "sg:postcode":"94124",
    "sg:province":"CA",
    "wof:name":"Aaliyah's Daycare",
    "wof:placetype":"venue"
},
  "geometry": {"coordinates":[-122.387213,37.718958],"type":"Point"}
}