{
  "type": "Feature",
  "properties": {
    "addr:full":"1155 Battery St San Francisco CA 94111",
    "addr:housenumber":"1155",
    "addr:postcode":"94111",
    "addr:street":"Battery St",
    "iso:country":"US",
    "sg:address":"1155 Battery St",
    "sg:city":"San Francisco",
    "sg:classifiers":[
        {
            "category":"Building & Trades",
            "subcategory":"Construction",
            "type":"Services"
        }
    ],
    "sg:phone":"+1 415 501 7623",
    "sg:postcode":"94111",
    "sg:province":"CA",
    "sg:tags":[
        "residential"
    ],
    "wof:name":"Colleen Robert Haas",
    "wof:placetype":"venue"
},
  "geometry": {"coordinates":[-122.40179000000001,37.801787],"type":"Point"}
}