{
  "type": "Feature",
  "properties": {
    "addr:full":"39279 Liberty St Fremont CA 94538",
    "addr:housenumber":"39279",
    "addr:postcode":"94538",
    "addr:street":"Liberty St",
    "iso:country":"US",
    "sg:address":"39279 Liberty St",
    "sg:city":"Fremont",
    "sg:classifiers":[
        {
            "category":"Professional",
            "type":"Services"
        }
    ],
    "sg:phone":"+1 510 505 0885",
    "sg:postcode":"94538",
    "sg:province":"CA",
    "sg:tags":[
        "establishment"
    ],
    "wof:name":"Gallagher Jennifer",
    "wof:placetype":"venue"
},
  "geometry": {"coordinates":[-121.983295,37.551502],"type":"Point"}
}