{
  "type": "Feature",
  "properties": {
    "addr:full":"21 Tamal Vista Blvd Corte Madera CA 94925",
    "addr:housenumber":"21",
    "addr:postcode":"94925",
    "addr:street":"Tamal Vista Blvd",
    "iso:country":"US",
    "sg:address":"21 Tamal Vista Blvd",
    "sg:city":"Corte Madera",
    "sg:classifiers":[
        {
            "category":"Health Services",
            "subcategory":"Doctor",
            "type":"Services"
        }
    ],
    "sg:phone":"+1 415 927 2320",
    "sg:postcode":"94925",
    "sg:province":"CA",
    "sg:tags":[
        "physician",
        "surgeon"
    ],
    "wof:name":"Arnold Knepfer MD",
    "wof:placetype":"venue"
},
  "geometry": {"coordinates":[-122.51838600000001,37.929724],"type":"Point"}
}