{
  "type": "Feature",
  "properties": {
    "iso:country":"US",
    "sg:address":"2900 Adams St",
    "sg:city":"Riverside",
    "sg:classifiers":[
        {
            "category":"Communications",
            "subcategory":"Film & Video Production",
            "type":"Services"
        }
    ],
    "sg:phone":"+1 951 687 6654",
    "sg:postcode":"92504",
    "sg:province":"CA",
    "sg:tags":[
        "taping"
    ],
    "wof:name":"Synergy Studios Inc",
    "wof:placetype":"venue"
},
  "geometry": {"coordinates":[-117.416761,33.923822],"type":"Point"}
}