{
  "type": "Feature",
  "properties": {
    "iso:country":"US",
    "sg:address":"5156 Holt Blvd",
    "sg:city":"Montclair",
    "sg:classifiers":[
        {
            "category":"Autos & Motor Vehicles",
            "subcategory":"Recreational Vehicle Sales",
            "type":"Retail Goods"
        }
    ],
    "sg:phone":"+1 909 621 5953",
    "sg:postcode":"91763",
    "sg:province":"CA",
    "sg:tags":[
        "canopy",
        "shell",
        "truck",
        "cap"
    ],
    "wof:name":"Accessory House",
    "wof:placetype":"venue"
},
  "geometry": {"coordinates":[-117.694542,34.063267],"type":"Point"}
}