{
  "type": "Feature",
  "properties": {
    "addr:full":"171 Petaluma Blvd N Petaluma CA 94952",
    "addr:housenumber":"171",
    "addr:postcode":"94952",
    "addr:street":"Petaluma Blvd N",
    "iso:country":"US",
    "sg:address":"171 Petaluma Blvd N",
    "sg:city":"Petaluma",
    "sg:classifiers":[
        {
            "category":"Retail",
            "subcategory":"Repair Shop",
            "type":"Services"
        }
    ],
    "sg:phone":"+1 707 763 9300",
    "sg:postcode":"94952",
    "sg:province":"CA",
    "sg:tags":[
        "part",
        "watch",
        "clock"
    ],
    "wof:name":"Simoni's Clock Shoppe",
    "wof:placetype":"venue"
},
  "geometry": {"coordinates":[-122.6409,38.235282],"type":"Point"}
}