{
  "type": "Feature",
  "properties": {
    "iso:country":"US",
    "sg:address":"2010 Wilshire Blvd",
    "sg:city":"Los Angeles",
    "sg:classifiers":[
        {
            "category":"Health Services",
            "subcategory":"Doctor",
            "type":"Services"
        }
    ],
    "sg:phone":"+1 213 353 1506",
    "sg:postcode":"90057",
    "sg:province":"CA",
    "wof:name":"West Coast Imaging",
    "wof:placetype":"venue"
},
  "geometry": {"coordinates":[-118.275002,34.0574],"type":"Point"}
}