{
  "type": "Feature",
  "properties": {
    "iso:country":"US",
    "sg:address":"7126 Westport St",
    "sg:city":"Riverside",
    "sg:classifiers":[
        {
            "category":"Health Services",
            "subcategory":"Hospital",
            "type":"Services"
        }
    ],
    "sg:phone":"+1 951 776 1168",
    "sg:postcode":"92506",
    "sg:province":"CA",
    "sg:tags":[
        "specialty"
    ],
    "wof:name":"Recovering Alumni of Pacifica",
    "wof:placetype":"venue"
},
  "geometry": {"coordinates":[-117.330223,33.921573],"type":"Point"}
}