{
  "type": "Feature",
  "properties": {
    "iso:country":"US",
    "sg:address":"1611 Montana Ave",
    "sg:city":"Santa Monica",
    "sg:classifiers":[
        {
            "category":"Shopping",
            "subcategory":"Clothing, Apparel, & Fashions",
            "type":"Retail Goods"
        }
    ],
    "sg:phone":"+1 310 319 9546",
    "sg:postcode":"90403",
    "sg:province":"CA",
    "sg:tags":[
        "family"
    ],
    "wof:name":"Yellow Lotus",
    "wof:placetype":"venue"
},
  "geometry": {"coordinates":[-118.492453,34.034478],"type":"Point"}
}