{
  "type": "Feature",
  "properties": {
    "addr:full":"4305 Clayton Rd Concord CA 94521",
    "addr:housenumber":"4305",
    "addr:postcode":"94521",
    "addr:street":"Clayton Rd",
    "iso:country":"US",
    "sg:address":"4305 Clayton Rd",
    "sg:city":"Concord",
    "sg:classifiers":[
        {
            "category":"Retail",
            "subcategory":"Laundry & Dry Cleaning",
            "type":"Services"
        }
    ],
    "sg:phone":"+1 925 676 6947",
    "sg:postcode":"94521",
    "sg:province":"CA",
    "sg:tags":[
        "cleaners"
    ],
    "wof:name":"Market Place Cleaners",
    "wof:placetype":"venue"
},
  "geometry": {"coordinates":[-121.99168400000001,37.96453],"type":"Point"}
}