{
  "type": "Feature",
  "properties": {
    "iso:country":"US",
    "sg:address":"1617 Canyon Dr",
    "sg:city":"Pinole",
    "sg:classifiers":[
        {
            "category":"Real Estate",
            "subcategory":"Real Estate Agent",
            "type":"Services"
        }
    ],
    "sg:phone":"+1 510 724 1679",
    "sg:postcode":"94564",
    "sg:province":"CA",
    "wof:name":"Help U Sell",
    "wof:placetype":"venue"
},
  "geometry": {"coordinates":[-122.301633,37.995383],"type":"Point"}
}