{
  "type": "Feature",
  "properties": {
    "iso:country":"US",
    "sg:address":"4590 MacArthur Blvd",
    "sg:city":"Newport Beach",
    "sg:classifiers":[
        {
            "category":"Professional",
            "subcategory":"Lawyer & Legal Services",
            "type":"Services"
        }
    ],
    "sg:phone":"+1 949 752 2450",
    "sg:postcode":"92660",
    "sg:province":"CA",
    "wof:name":"Browning Ann Attorney",
    "wof:placetype":"venue"
},
  "geometry": {"coordinates":[-117.863998,33.668598],"type":"Point"}
}