{
  "type": "Feature",
  "properties": {
    "iso:country":"US",
    "sg:address":"361 Hospital Rd Ste 428",
    "sg:city":"Newport Beach",
    "sg:classifiers":[
        {
            "category":"Community Center",
            "type":"Public Place"
        }
    ],
    "sg:phone":"+1 949 574 8400",
    "sg:postcode":"92663",
    "sg:province":"CA",
    "sg:tags":[
        "medical"
    ],
    "wof:name":"Institute of Laser Medicine",
    "wof:placetype":"venue"
},
  "geometry": {"coordinates":[-117.931,33.625801],"type":"Point"}
}