{
  "type": "Feature",
  "properties": {
    "addr:full":"319 S Robertson Blvd Los Angeles CA 90048",
    "addr:housenumber":"319",
    "addr:postcode":"90048",
    "addr:street":"S Robertson Blvd",
    "iso:country":"US",
    "sg:address":"319 S Robertson Blvd",
    "sg:city":"Los Angeles",
    "sg:classifiers":[
        {
            "category":"Home & Garden",
            "subcategory":"Furniture",
            "type":"Retail Goods"
        }
    ],
    "sg:phone":"+1 310 247 0100",
    "sg:postcode":"90048",
    "sg:province":"CA",
    "sg:tags":[
        "store"
    ],
    "wof:name":"Designer Imports",
    "wof:placetype":"venue"
},
  "geometry": {"coordinates":[-118.383889,34.072956],"type":"Point"}
}