{
  "type": "Feature",
  "properties": {
    "addr:full":"1600 Naud St Los Angeles CA 90012",
    "addr:housenumber":"1600",
    "addr:postcode":"90012",
    "addr:street":"Naud St",
    "iso:country":"US",
    "sg:address":"1600 Naud St",
    "sg:city":"Los Angeles",
    "sg:classifiers":[
        {
            "category":"Food & Beverages",
            "subcategory":"Meat & Fish",
            "type":"Retail Goods"
        }
    ],
    "sg:phone":"+1 323 276 8070",
    "sg:postcode":"90012",
    "sg:province":"CA",
    "wof:name":"City Glatt Market",
    "wof:placetype":"venue"
},
  "geometry": {"coordinates":[-118.22662099999999,34.068629],"type":"Point"}
}