{
  "type": "Feature",
  "properties": {
    "iso:country":"US",
    "sg:address":"1750 E Monticello Ct",
    "sg:city":"Ontario",
    "sg:classifiers":[
        {
            "category":"Building & Trades",
            "subcategory":"Construction",
            "type":"Services"
        }
    ],
    "sg:phone":"+1 909 923 0562",
    "sg:postcode":"91761",
    "sg:province":"CA",
    "sg:tags":[
        "plating"
    ],
    "wof:name":"Dimad Enterprises Inc",
    "wof:placetype":"venue"
},
  "geometry": {"coordinates":[-117.614531,34.032786],"type":"Point"}
}