{
  "type": "Feature",
  "properties": {
    "addr:full":"190 Borland Ave Auburn CA 95603",
    "addr:housenumber":"190",
    "addr:postcode":"ca 95603",
    "addr:street":"Borland Ave",
    "iso:country":"US",
    "sg:address":"190 Borland Ave",
    "sg:city":"Auburn",
    "sg:classifiers":[
        {
            "category":"Manufacturing",
            "subcategory":"Pottery",
            "type":"Manufacturing & Wholesale Goods"
        }
    ],
    "sg:phone":"+1 530 885 0285",
    "sg:postcode":"95603",
    "sg:province":"CA",
    "wof:name":"Pheiffer Pottery",
    "wof:placetype":"venue"
},
  "geometry": {"coordinates":[-121.064998,38.901764],"type":"Point"}
}