{
  "type": "Feature",
  "properties": {
    "addr:full":"949 University Ave Burbank CA 91504",
    "addr:housenumber":"949",
    "addr:postcode":"91504",
    "addr:street":"University Ave",
    "iso:country":"US",
    "sg:address":"949 University Ave",
    "sg:city":"Burbank",
    "sg:classifiers":[
        {
            "category":"Real Estate",
            "subcategory":"Real Estate Operator",
            "type":"Services"
        }
    ],
    "sg:phone":"+1 818 845 4646",
    "sg:postcode":"91504",
    "sg:province":"CA",
    "sg:tags":[
        "property",
        "lessor"
    ],
    "wof:name":"Cameron Cripps",
    "wof:placetype":"venue"
},
  "geometry": {"coordinates":[-118.313535,34.197807],"type":"Point"}
}