{
  "type": "Feature",
  "properties": {
    "iso:country":"US",
    "sg:address":"544 International Blvd Apt 9",
    "sg:city":"Oakland",
    "sg:classifiers":[
        {
            "category":"Social Services",
            "type":"Services"
        },
        {
            "category":"Health Services",
            "subcategory":"Clinic",
            "type":"Services"
        }
    ],
    "sg:phone":"+1 510 444 1671",
    "sg:postcode":"94606",
    "sg:province":"CA",
    "sg:tags":[
        "information",
        "mental"
    ],
    "wof:name":"Center For Empowering Refugees",
    "wof:placetype":"venue"
},
  "geometry": {"coordinates":[-122.253396,37.795361],"type":"Point"}
}