{
  "type": "Feature",
  "properties": {
    "iso:country":"US",
    "sg:address":"13525 Blackie Rd",
    "sg:city":"Castroville",
    "sg:classifiers":[
        {
            "category":"Manufacturing",
            "subcategory":"Tools & Machinery",
            "type":"Manufacturing & Wholesale Goods"
        }
    ],
    "sg:phone":"+1 831 633 0263",
    "sg:postcode":"95012",
    "sg:province":"CA",
    "sg:tags":[
        "machine",
        "shop"
    ],
    "wof:name":"Ron Witherspoon Inc",
    "wof:placetype":"venue"
},
  "geometry": {"coordinates":[-121.743742,36.75813],"type":"Point"}
}