{
  "type": "Feature",
  "properties": {
    "iso:country":"US",
    "sg:address":"836 Andover Dr",
    "sg:city":"Burbank",
    "sg:classifiers":[
        {
            "category":"Professional",
            "subcategory":"Testing Lab",
            "type":"Services"
        }
    ],
    "sg:phone":"+1 818 567 4509",
    "sg:postcode":"91504",
    "sg:province":"CA",
    "sg:tags":[
        "electrical",
        "system",
        "power"
    ],
    "wof:name":"H M Electric",
    "wof:placetype":"venue"
},
  "geometry": {"coordinates":[-118.314222,34.200691],"type":"Point"}
}