{
  "type": "Feature",
  "properties": {
    "iso:country":"US",
    "sg:address":"15826 Gale Ave",
    "sg:city":"Hacienda Heights",
    "sg:classifiers":[
        {
            "category":"Restaurant",
            "type":"Food & Drink"
        }
    ],
    "sg:phone":"+1 626 330 0010",
    "sg:postcode":"91745",
    "sg:province":"CA",
    "wof:name":"China Wok Fast Food",
    "wof:placetype":"venue"
},
  "geometry": {"coordinates":[-117.961877,34.010438],"type":"Point"}
}