{
  "type": "Feature",
  "properties": {
    "iso:country":"US",
    "sg:address":"813 Van Ness Ave",
    "sg:city":"Torrance",
    "sg:classifiers":[
        {
            "category":"Communications",
            "subcategory":"Film & Video Production",
            "type":"Services"
        },
        {
            "category":"Professional",
            "subcategory":"Advertising",
            "type":"Services"
        }
    ],
    "sg:phone":"+1 310 908 9379",
    "sg:postcode":"90501",
    "sg:province":"CA",
    "sg:tags":[
        "videographers",
        "video/film"
    ],
    "sg:website":"davidkumpe.com",
    "wof:name":"David Kumpe Editing",
    "wof:placetype":"venue"
},
  "geometry": {"coordinates":[-118.318749,33.83905],"type":"Point"}
}