{
  "type": "Feature",
  "properties": {
    "addr:full":"216 E 17th St Costa Mesa CA 92627",
    "addr:housenumber":"216",
    "addr:postcode":"92627",
    "addr:street":"E 17Th St",
    "iso:country":"US",
    "sg:address":"216 E 17th St",
    "sg:city":"Costa Mesa",
    "sg:classifiers":[
        {
            "category":"Retail",
            "subcategory":"Repair Shop",
            "type":"Services"
        }
    ],
    "sg:phone":"+1 949 722 3660",
    "sg:postcode":"92627",
    "sg:province":"CA",
    "sg:tags":[
        "watch"
    ],
    "wof:name":"Time & Gold",
    "wof:placetype":"venue"
},
  "geometry": {"coordinates":[-117.91749900000001,33.634675],"type":"Point"}
}