{
  "type": "Feature",
  "properties": {
    "iso:country":"US",
    "sg:address":"729 Fulton Shipyard Rd",
    "sg:city":"Antioch",
    "sg:classifiers":[
        {
            "category":"Professional",
            "subcategory":"Engineering",
            "type":"Services"
        }
    ],
    "sg:phone":"+1 925 756 2538",
    "sg:postcode":"94509",
    "sg:province":"CA",
    "sg:tags":[
        "engineer"
    ],
    "wof:name":"D Bowman Engineering",
    "wof:placetype":"venue"
},
  "geometry": {"coordinates":[-121.800901,38.01571],"type":"Point"}
}