{
  "type": "Feature",
  "properties": {
    "iso:country":"US",
    "sg:address":"1111 W el Camino Real",
    "sg:city":"Sunnyvale",
    "sg:classifiers":[
        {
            "category":"Manufacturing",
            "subcategory":"Signs",
            "type":"Manufacturing & Wholesale Goods"
        }
    ],
    "sg:phone":"+1 408 732 7446",
    "sg:postcode":"94087",
    "sg:province":"CA",
    "sg:tags":[
        "specialty",
        "mfg"
    ],
    "wof:name":"Peninsula Signs & Graphics",
    "wof:placetype":"venue"
},
  "geometry": {"coordinates":[-122.055924,37.373743],"type":"Point"}
}