{
  "type": "Feature",
  "properties": {
    "iso:country":"US",
    "sg:address":"2000 Main St",
    "sg:city":"Julian",
    "sg:classifiers":[
        {
            "category":"Health Services",
            "subcategory":"Health Practitioner",
            "type":"Services"
        }
    ],
    "sg:phone":"+1 760 765 0806",
    "sg:postcode":"92036",
    "sg:province":"CA",
    "sg:tags":[
        "therapist",
        "physical"
    ],
    "wof:name":"Alpine Physical Thrpy & Wllnss",
    "wof:placetype":"venue"
},
  "geometry": {"coordinates":[-116.600925,33.077623],"type":"Point"}
}