{
  "type": "Feature",
  "properties": {
    "addr:full":"3334 E Miraloma Ave Anaheim CA 92806",
    "addr:housenumber":"3334",
    "addr:postcode":"92806",
    "addr:street":"E Miraloma Ave",
    "iso:country":"US",
    "sg:address":"3334 E Miraloma Ave",
    "sg:city":"Anaheim",
    "sg:classifiers":[
        {
            "category":"Building & Trades",
            "subcategory":"Plumbing",
            "type":"Services"
        }
    ],
    "sg:phone":"+1 714 692 7468",
    "sg:postcode":"92806",
    "sg:province":"CA",
    "sg:tags":[
        "plumbing",
        "contractor"
    ],
    "wof:name":"Barker & Sons Plumbing",
    "wof:placetype":"venue"
},
  "geometry": {"coordinates":[-117.850498,33.860319],"type":"Point"}
}