{
  "type": "Feature",
  "properties": {
    "addr:full":"1861 Rainier Cir Petaluma CA 94954",
    "addr:housenumber":"1861",
    "addr:postcode":"94954",
    "addr:street":"Rainier Cir",
    "iso:country":"US",
    "sg:address":"1861 Rainier Cir",
    "sg:city":"Petaluma",
    "sg:classifiers":[
        {
            "category":"Insurance",
            "subcategory":"Insurance Agent",
            "type":"Services"
        }
    ],
    "sg:phone":"+1 707 769 1998",
    "sg:postcode":"94954",
    "sg:province":"CA",
    "wof:name":"Sonoma Marin Insurance",
    "wof:placetype":"venue"
},
  "geometry": {"coordinates":[-122.628591,38.265507],"type":"Point"}
}