{
  "type": "Feature",
  "properties": {
    "addr:full":"131 S Cornucopia Rd Exeter CA 93221",
    "addr:housenumber":"131",
    "addr:postcode":"93221",
    "addr:street":"S Cornucopia Rd",
    "iso:country":"US",
    "sg:address":"131 S Cornucopia Rd",
    "sg:city":"Exeter",
    "sg:classifiers":[
        {
            "category":"Building & Trades",
            "subcategory":"Construction",
            "type":"Services"
        }
    ],
    "sg:phone":"+1 559 592 6574",
    "sg:postcode":"93221",
    "sg:province":"CA",
    "sg:tags":[
        "house"
    ],
    "wof:name":"Dawson Construction",
    "wof:placetype":"venue"
},
  "geometry": {"coordinates":[-119.167635,36.295482],"type":"Point"}
}