{
  "type": "Feature",
  "properties": {
    "addr:full":"9845 Orr and Day Rd Santa Fe Springs CA 90670",
    "addr:housenumber":"9845",
    "addr:postcode":"90670",
    "addr:street":"Orr And Day Rd",
    "iso:country":"US",
    "sg:address":"9845 Orr and Day Rd",
    "sg:city":"Santa Fe Springs",
    "sg:classifiers":[
        {
            "category":"Organizations",
            "subcategory":"Religious Organization",
            "type":"Services"
        }
    ],
    "sg:phone":"+1 562 948 3601",
    "sg:postcode":"90670",
    "sg:province":"CA",
    "sg:tags":[
        "church"
    ],
    "wof:name":"Bethel Community Church",
    "wof:placetype":"venue"
},
  "geometry": {"coordinates":[-118.088965,33.949746],"type":"Point"}
}