{
  "type": "Feature",
  "properties": {
    "addr:full":"23707 Vanowen St West Hills CA 91307",
    "addr:postcode":"23707;91307",
    "addr:street":"Vanowen St",
    "iso:country":"US",
    "sg:address":"23707 Vanowen St",
    "sg:city":"West Hills",
    "sg:classifiers":[
        {
            "category":"Personal",
            "subcategory":"Nail Salon",
            "type":"Services"
        }
    ],
    "sg:phone":"+1 818 704 0263",
    "sg:postcode":"91307",
    "sg:province":"CA",
    "wof:name":"Nails by Lynn",
    "wof:placetype":"venue"
},
  "geometry": {"coordinates":[-118.64299800000001,34.1931],"type":"Point"}
}