{
  "type": "Feature",
  "properties": {
    "addr:full":"751 4th St Santa Rosa CA 95404",
    "addr:housenumber":"751",
    "addr:postcode":"ca 95404",
    "addr:street":"4Th St",
    "iso:country":"US",
    "sg:address":"751 4th St",
    "sg:city":"Santa Rosa",
    "sg:classifiers":[
        {
            "category":"Social Services",
            "type":"Services"
        }
    ],
    "sg:phone":"+1 707 528 4483",
    "sg:postcode":"95404",
    "sg:province":"CA",
    "sg:tags":[
        "organization",
        "welfare"
    ],
    "wof:name":"United Way",
    "wof:placetype":"venue"
},
  "geometry": {"coordinates":[-122.71151399999999,38.441634],"type":"Point"}
}