{
  "type": "Feature",
  "properties": {
    "iso:country":"US",
    "sg:address":"11245 183rd St",
    "sg:city":"Cerritos",
    "sg:classifiers":[
        {
            "category":"Professional",
            "type":"Services"
        }
    ],
    "sg:phone":"+1 562 366 2054",
    "sg:postcode":"90703",
    "sg:province":"CA",
    "sg:tags":[
        "establishment"
    ],
    "wof:name":"Coyote Nights",
    "wof:placetype":"venue"
},
  "geometry": {"coordinates":[-118.094688,33.865728],"type":"Point"}
}