{
  "type": "Feature",
  "properties": {
    "addr:full":"1645 E St Fresno CA 93706",
    "addr:housenumber":"1645",
    "addr:postcode":"93706",
    "addr:street":"E St",
    "iso:country":"US",
    "sg:address":"1645 E St",
    "sg:city":"Fresno",
    "sg:classifiers":[
        {
            "category":"Professional",
            "subcategory":"Testing Lab",
            "type":"Services"
        }
    ],
    "sg:phone":"+1 800 669 3201",
    "sg:postcode":"93706",
    "sg:province":"CA",
    "sg:tags":[
        "laboratory"
    ],
    "wof:name":"Bsk. & Associates",
    "wof:placetype":"venue"
},
  "geometry": {"coordinates":[-119.80193300000001,36.735171],"type":"Point"}
}