{
  "type": "Feature",
  "properties": {
    "addr:full":"1919 Addison Street Berkeley CA 94704",
    "addr:housenumber":"1919",
    "addr:postcode":"94704",
    "addr:street":"Addison Street",
    "iso:country":"US",
    "sg:address":"1919 Addison Street",
    "sg:city":"Berkeley",
    "sg:classifiers":[
        {
            "category":"Restaurant",
            "type":"Food & Drink"
        }
    ],
    "sg:phone":"+1 510 644 1707",
    "sg:postcode":"94704",
    "sg:province":"CA",
    "sg:website":"letheatrerestaurant.com",
    "wof:name":"Le Theatre",
    "wof:placetype":"venue"
},
  "geometry": {"coordinates":[-122.272003,37.870701],"type":"Point"}
}