{
  "type": "Feature",
  "properties": {
    "iso:country":"US",
    "sg:address":"3132 Williams Rd",
    "sg:city":"San Jose",
    "sg:classifiers":[
        {
            "category":"Restaurant",
            "type":"Food & Drink"
        }
    ],
    "sg:phone":"+1 408 557 8914",
    "sg:postcode":"95117",
    "sg:province":"CA",
    "sg:tags":[
        "american",
        "latin",
        "mexican"
    ],
    "wof:name":"Las Brasas Grill",
    "wof:placetype":"venue"
},
  "geometry": {"coordinates":[-121.951938,37.308833],"type":"Point"}
}