{
  "type": "Feature",
  "properties": {
    "iso:country":"US",
    "sg:address":"648 Vallie Ct",
    "sg:city":"Merced",
    "sg:classifiers":[
        {
            "category":"Wholesale",
            "subcategory":"Non-durable Goods",
            "type":"Manufacturing & Wholesale Goods"
        }
    ],
    "sg:phone":"+1 209 384 7135",
    "sg:postcode":"95340",
    "sg:province":"CA",
    "wof:name":"S A M E Ole Baskets",
    "wof:placetype":"venue"
},
  "geometry": {"coordinates":[-120.463052,37.310203],"type":"Point"}
}