{
  "type": "Feature",
  "properties": {
    "addr:full":"4407 E Village Rd Long Beach CA 90808",
    "addr:housenumber":"4407",
    "addr:postcode":"90808",
    "addr:street":"E Village Rd",
    "iso:country":"US",
    "sg:address":"4407 E Village Rd",
    "sg:city":"Long Beach",
    "sg:classifiers":[
        {
            "category":"Personal",
            "subcategory":"Barber",
            "type":"Services"
        }
    ],
    "sg:phone":"+1 562 425 7788",
    "sg:postcode":"90808",
    "sg:province":"CA",
    "wof:name":"Emanuel's Magic Touch",
    "wof:placetype":"venue"
},
  "geometry": {"coordinates":[-118.141998,33.8335],"type":"Point"}
}