{
  "type": "Feature",
  "properties": {
    "addr:full":"1281 W Rosecrans Ave Apt 101 Gardena CA 90247",
    "addr:housenumber":"1281;101",
    "addr:postcode":"90247",
    "addr:street":"W Rosecrans Ave Apt",
    "iso:country":"US",
    "sg:address":"1281 W Rosecrans Ave Apt 101",
    "sg:city":"Gardena",
    "sg:classifiers":[
        {
            "category":"Real Estate",
            "subcategory":"Real Estate Services",
            "type":"Services"
        },
        {
            "category":"Real Estate",
            "subcategory":"Real Estate Operator",
            "type":"Services"
        }
    ],
    "sg:phone":"+1 310 366 6836",
    "sg:postcode":"90247",
    "sg:province":"CA",
    "sg:tags":[
        "apartment",
        "property",
        "management"
    ],
    "wof:name":"Rosecrans Apartments",
    "wof:placetype":"venue"
},
  "geometry": {"coordinates":[-118.297997,33.901901],"type":"Point"}
}