{
  "type": "Feature",
  "properties": {
    "addr:full":"2991 State Highway 193 Lincoln CA 95648",
    "addr:housenumber":"2991",
    "addr:postcode":"95648",
    "addr:street":"State Highway 193",
    "iso:country":"US",
    "sg:address":"2991 State Highway 193",
    "sg:city":"Lincoln",
    "sg:classifiers":[
        {
            "category":"Building & Trades",
            "subcategory":"Construction",
            "type":"Services"
        }
    ],
    "sg:phone":"+1 916 408 8831",
    "sg:postcode":"95648",
    "sg:province":"CA",
    "sg:tags":[
        "wallcoverings-installation",
        "wallpaper",
        "painting",
        "contractor"
    ],
    "wof:name":"Wall To Wall Painting",
    "wof:placetype":"venue"
},
  "geometry": {"coordinates":[-121.238314,38.886553],"type":"Point"}
}