{
  "type": "Feature",
  "properties": {
    "iso:country":"US",
    "sg:address":"32042 Via Pavo Real",
    "sg:city":"Trabuco Canyon",
    "sg:classifiers":[
        {
            "category":"Manufacturing",
            "subcategory":"Tools & Machinery",
            "type":"Manufacturing & Wholesale Goods"
        }
    ],
    "sg:phone":"+1 949 766 1059",
    "sg:postcode":"92679",
    "sg:province":"CA",
    "sg:tags":[
        "analytical",
        "instrument",
        "mfg"
    ],
    "wof:name":"Hunter Integration Test Engrg",
    "wof:placetype":"venue"
},
  "geometry": {"coordinates":[-117.572855,33.620781],"type":"Point"}
}