{
  "type": "Feature",
  "properties": {
    "addr:full":"3274 E Menlo Ave Fresno CA 93710",
    "addr:housenumber":"3274",
    "addr:postcode":"93710",
    "addr:street":"E Menlo Ave",
    "iso:country":"US",
    "sg:address":"3274 E Menlo Ave",
    "sg:city":"Fresno",
    "sg:classifiers":[
        {
            "category":"Wholesale",
            "subcategory":"Durable Goods & Equipment",
            "type":"Manufacturing & Wholesale Goods"
        }
    ],
    "sg:phone":"+1 559 322 7286",
    "sg:postcode":"93710",
    "sg:province":"CA",
    "sg:tags":[
        "importer"
    ],
    "wof:name":"Sato Trading Co",
    "wof:placetype":"venue"
},
  "geometry": {"coordinates":[-119.729823,36.831208],"type":"Point"}
}