{
  "type": "Feature",
  "properties": {
    "iso:country":"US",
    "sg:address":"1201 1st St",
    "sg:city":"Coronado",
    "sg:classifiers":[
        {
            "category":"Building & Trades",
            "subcategory":"Construction",
            "type":"Services"
        }
    ],
    "sg:phone":"+1 619 437 7910",
    "sg:postcode":"92118",
    "sg:province":"CA",
    "sg:tags":[
        "home",
        "builder"
    ],
    "wof:name":"ANI Homes",
    "wof:placetype":"venue"
},
  "geometry": {"coordinates":[-117.17196199999999,32.698707],"type":"Point"}
}