{
  "type": "Feature",
  "properties": {
    "iso:country":"US",
    "sg:address":"1430 National Ave",
    "sg:city":"San Diego",
    "sg:classifiers":[
        {
            "category":"Manufacturing",
            "subcategory":"Metals",
            "type":"Manufacturing & Wholesale Goods"
        }
    ],
    "sg:phone":"+1 619 233 0118",
    "sg:postcode":"92113",
    "sg:province":"CA",
    "sg:tags":[
        "pipe",
        "threading",
        "cutting"
    ],
    "sg:website":"www.reliablepipe.com",
    "wof:name":"Reliable Pipe Supply Co",
    "wof:placetype":"venue"
},
  "geometry": {"coordinates":[-117.15022,32.704347],"type":"Point"}
}