{
  "type": "Feature",
  "properties": {
    "addr:full":"2650 el Camino Real Redwood City CA 94061",
    "addr:housenumber":"2650",
    "addr:postcode":"94061",
    "addr:street":"El Camino Real",
    "iso:country":"US",
    "sg:address":"2650 el Camino Real",
    "sg:city":"Redwood City",
    "sg:classifiers":[
        {
            "category":"Banks & Credit Unions",
            "subcategory":"Bank",
            "type":"Services"
        }
    ],
    "sg:phone":"+1 650 364 8899",
    "sg:postcode":"94061",
    "sg:province":"CA",
    "sg:tags":[
        "financing"
    ],
    "wof:name":"CSI Communications Group",
    "wof:placetype":"venue"
},
  "geometry": {"coordinates":[-122.215554,37.471842],"type":"Point"}
}