{
  "type": "Feature",
  "properties": {
    "iso:country":"US",
    "sg:address":"7701 Santa Monica Blvd",
    "sg:city":"West Hollywood",
    "sg:classifiers":[
        {
            "category":"Home & Garden",
            "subcategory":"Household Appliances",
            "type":"Retail Goods"
        }
    ],
    "sg:phone":"+1 323 848 7700",
    "sg:postcode":"90046",
    "sg:province":"CA",
    "sg:tags":[
        "repair"
    ],
    "sg:website":"www.appliancepartsstop.com",
    "wof:name":"Universal Appliance Parts",
    "wof:placetype":"venue"
},
  "geometry": {"coordinates":[-118.356829,34.091078],"type":"Point"}
}