{
  "type": "Feature",
  "properties": {
    "addr:full":"1665 Willow St San Jose CA 95125",
    "addr:housenumber":"1665",
    "addr:postcode":"95125",
    "addr:street":"Willow St",
    "iso:country":"US",
    "sg:address":"1665 Willow St",
    "sg:city":"San Jose",
    "sg:classifiers":[
        {
            "category":"Insurance",
            "subcategory":"Insurance Agent",
            "type":"Services"
        }
    ],
    "sg:phone":"+1 408 267 1665",
    "sg:postcode":"95125",
    "sg:province":"CA",
    "wof:name":"New England Financial",
    "wof:placetype":"venue"
},
  "geometry": {"coordinates":[-121.913225,37.303959],"type":"Point"}
}