{
  "type": "Feature",
  "properties": {
    "iso:country":"US",
    "sg:address":"5821 Jameson Ct",
    "sg:city":"Carmichael",
    "sg:classifiers":[
        {
            "category":"Health Services",
            "subcategory":"Doctor",
            "type":"Services"
        }
    ],
    "sg:phone":"+1 916 486 0412",
    "sg:postcode":"95608",
    "sg:province":"CA",
    "sg:tags":[
        "physician",
        "surgeon"
    ],
    "wof:name":"Kamras & Polansky Medical Corp",
    "wof:placetype":"venue"
},
  "geometry": {"coordinates":[-121.327872,38.651171],"type":"Point"}
}