{
  "type": "Feature",
  "properties": {
    "iso:country":"US",
    "sg:address":"3990 Inland Empire Blvd",
    "sg:city":"Ontario",
    "sg:classifiers":[
        {
            "category":"Travel",
            "subcategory":"Hotels & Motels",
            "type":"Entertainment"
        }
    ],
    "sg:phone":"+1 909 944 8900",
    "sg:postcode":"91764",
    "sg:province":"CA",
    "wof:name":"Extended Stay America",
    "wof:placetype":"venue"
},
  "geometry": {"coordinates":[-117.56326799999999,34.06899],"type":"Point"}
}