{
  "type": "Feature",
  "properties": {
    "iso:country":"US",
    "sg:address":"325 Lilac Dr",
    "sg:city":"El Cajon",
    "sg:classifiers":[
        {
            "category":"Professional",
            "type":"Services"
        }
    ],
    "sg:phone":"+1 619 401 2530",
    "sg:postcode":"92021",
    "sg:province":"CA",
    "wof:name":"Mary Esther Rico",
    "wof:placetype":"venue"
},
  "geometry": {"coordinates":[-116.86773100000001,32.809031],"type":"Point"}
}