{
  "type": "Feature",
  "properties": {
    "iso:country":"US",
    "sg:address":"850 E D St",
    "sg:city":"Lemoore",
    "sg:classifiers":[
        {
            "category":"Restaurant",
            "type":"Food & Drink"
        }
    ],
    "sg:phone":"+1 559 924 5395",
    "sg:postcode":"93245",
    "sg:province":"CA",
    "wof:name":"Jaspers Saloon Of Lemoore",
    "wof:placetype":"venue"
},
  "geometry": {"coordinates":[-119.768235,36.299648],"type":"Point"}
}