{
  "type": "Feature",
  "properties": {
    "iso:country":"US",
    "sg:address":"837 N Main St",
    "sg:city":"Yreka",
    "sg:classifiers":[
        {
            "category":"Restaurant",
            "type":"Food & Drink"
        }
    ],
    "sg:phone":"+1 530 842 4721",
    "sg:postcode":"96097",
    "sg:province":"CA",
    "wof:name":"Sterling Holt",
    "wof:placetype":"venue"
},
  "geometry": {"coordinates":[-122.633276,41.74037],"type":"Point"}
}