{
  "type": "Feature",
  "properties": {
    "addr:full":"19620 Stevens Creek Blvd Cupertino CA 95014",
    "addr:housenumber":"19620",
    "addr:postcode":"95014",
    "addr:street":"Stevens Creek Blvd",
    "iso:country":"US",
    "sg:address":"19620 Stevens Creek Blvd",
    "sg:city":"Cupertino",
    "sg:classifiers":[
        {
            "category":"Fast Food",
            "type":"Food & Drink"
        },
        {
            "category":"Restaurant",
            "type":"Food & Drink"
        }
    ],
    "sg:phone":"+1 408 996 9464",
    "sg:postcode":"95014",
    "sg:province":"CA",
    "sg:tags":[
        "chicken",
        "take",
        "wing"
    ],
    "sg:website":"www.wingstop.com",
    "wof:name":"Wingstop",
    "wof:placetype":"venue"
},
  "geometry": {"coordinates":[-122.016525,37.322556],"type":"Point"}
}