{
  "type": "Feature",
  "properties": {
    "iso:country":"US",
    "sg:address":"843 F St",
    "sg:city":"Broderick",
    "sg:classifiers":[
        {
            "category":"Retail",
            "subcategory":"Repair Shop",
            "type":"Services"
        }
    ],
    "sg:phone":"+1 916 372 8494",
    "sg:postcode":"95605",
    "sg:province":"CA",
    "sg:tags":[
        "equipment",
        "electronic",
        "supply"
    ],
    "sg:website":"www.raleys.com",
    "wof:name":"Raley's Point Of Sale",
    "wof:placetype":"venue"
},
  "geometry": {"coordinates":[-121.52109900000001,38.585715],"type":"Point"}
}