{
  "type": "Feature",
  "properties": {
    "addr:full":"8259 Eneva Ln Yucca Valley CA 92284",
    "addr:housenumber":"8259",
    "addr:postcode":"92284",
    "addr:street":"Eneva Ln",
    "iso:country":"US",
    "sg:address":"8259 Eneva Ln",
    "sg:city":"Yucca Valley",
    "sg:classifiers":[
        {
            "category":"Shopping",
            "subcategory":"Used Merchandise",
            "type":"Retail Goods"
        }
    ],
    "sg:phone":"+1 760 369 9600",
    "sg:postcode":"92284",
    "sg:province":"CA",
    "sg:tags":[
        "antique"
    ],
    "wof:name":"Tumbleweed Antiques & Gifts",
    "wof:placetype":"venue"
},
  "geometry": {"coordinates":[-116.456574,34.102417],"type":"Point"}
}