{
  "type": "Feature",
  "properties": {
    "iso:country":"US",
    "sg:address":"217 Winston St",
    "sg:city":"Los Angeles",
    "sg:classifiers":[
        {
            "category":"Wholesale",
            "subcategory":"Electrical",
            "type":"Manufacturing & Wholesale Goods"
        }
    ],
    "sg:phone":"+1 213 687 7101",
    "sg:postcode":"90013",
    "sg:province":"CA",
    "sg:tags":[
        "equipment",
        "electronic",
        "supply"
    ],
    "wof:name":"Global International Trade Inc",
    "wof:placetype":"venue"
},
  "geometry": {"coordinates":[-118.245514,34.045709],"type":"Point"}
}