{
  "type": "Feature",
  "properties": {
    "iso:country":"US",
    "sg:address":"2560 Main St",
    "sg:city":"Ramona",
    "sg:classifiers":[
        {
            "category":"Retail",
            "subcategory":"Auto Repair",
            "type":"Services"
        }
    ],
    "sg:phone":"+1 760 789 3600",
    "sg:postcode":"92065",
    "sg:province":"CA",
    "sg:tags":[
        "brake"
    ],
    "sg:website":"www.ronstires.com",
    "wof:name":"Ron's Tire & Brake Inc",
    "wof:placetype":"venue"
},
  "geometry": {"coordinates":[-116.892793,33.025351],"type":"Point"}
}