{
  "type": "Feature",
  "properties": {
    "iso:country":"US",
    "sg:address":"678 61st St",
    "sg:city":"Oakland",
    "sg:classifiers":[
        {
            "category":"Communications",
            "type":"Services"
        }
    ],
    "sg:phone":"+1 510 991 6685",
    "sg:postcode":"94620",
    "sg:province":"CA",
    "sg:tags":[
        "web",
        "design"
    ],
    "sg:website":"www.studio678.com",
    "wof:name":"Studio 678 Web Design & Development",
    "wof:placetype":"venue"
},
  "geometry": {"coordinates":[-122.267696,37.846516],"type":"Point"}
}