{
  "type": "Feature",
  "properties": {
    "addr:full":"2930 Grace Lane Costa Mesa CA 92626",
    "addr:housenumber":"2930",
    "addr:postcode":"92626",
    "addr:street":"Grace Lane",
    "iso:country":"US",
    "sg:address":"2930 Grace Lane",
    "sg:city":"Costa Mesa",
    "sg:classifiers":[
        {
            "category":"Travel",
            "subcategory":"Hotels & Motels",
            "type":"Entertainment"
        }
    ],
    "sg:phone":"+1 714 708 2155",
    "sg:postcode":"92626",
    "sg:province":"CA",
    "wof:name":"Trend West Resort",
    "wof:placetype":"venue"
},
  "geometry": {"coordinates":[-117.90162599999999,33.678598],"type":"Point"}
}