{
  "type": "Feature",
  "properties": {
    "iso:country":"US",
    "sg:address":"123 S Green St",
    "sg:city":"Tehachapi",
    "sg:classifiers":[
        {
            "category":"Banks & Credit Unions",
            "subcategory":"Investment Brokerage",
            "type":"Services"
        }
    ],
    "sg:phone":"+1 310 556 9688",
    "sg:postcode":"93561",
    "sg:province":"CA",
    "sg:tags":[
        "advisory"
    ],
    "wof:name":"Green St. Energy, Inc.",
    "wof:placetype":"venue"
},
  "geometry": {"coordinates":[-118.44756099999999,35.131848],"type":"Point"}
}