{
  "type": "Feature",
  "properties": {
    "iso:country":"US",
    "sg:address":"1108 N 9th St",
    "sg:city":"Modesto",
    "sg:classifiers":[
        {
            "category":"Wholesale",
            "subcategory":"Motor Vehicles",
            "type":"Manufacturing & Wholesale Goods"
        }
    ],
    "sg:phone":"+1 209 456 1432",
    "sg:postcode":"95350",
    "sg:province":"CA",
    "sg:tags":[
        "automobile",
        "truck",
        "broker"
    ],
    "wof:name":"Automan Auto Wholesale",
    "wof:placetype":"venue"
},
  "geometry": {"coordinates":[-121.02348600000001,37.657365],"type":"Point"}
}