{
  "type": "Feature",
  "properties": {
    "iso:country":"US",
    "sg:address":"6501 Atlantic Ave",
    "sg:city":"Bell",
    "sg:classifiers":[
        {
            "category":"Casinos & Gambling",
            "type":"Entertainment"
        }
    ],
    "sg:phone":"+1 323 560 3502",
    "sg:postcode":"90201",
    "sg:province":"CA",
    "wof:name":"Western Gaming Associates",
    "wof:placetype":"venue"
},
  "geometry": {"coordinates":[-118.18699599999999,33.976898],"type":"Point"}
}