{
  "type": "Feature",
  "properties": {
    "addr:full":"11802 Ivie Acres Ln Herald CA 95638",
    "addr:housenumber":"11802",
    "addr:postcode":"95638",
    "addr:street":"Ivie Acres Ln",
    "iso:country":"US",
    "sg:address":"11802 Ivie Acres Ln",
    "sg:city":"Herald",
    "sg:classifiers":[
        {
            "category":"Freight",
            "type":"Transportation"
        }
    ],
    "sg:phone":"+1 209 748 5858",
    "sg:postcode":"95638",
    "sg:province":"CA",
    "sg:tags":[
        "trucking"
    ],
    "wof:name":"Grace Trucking",
    "wof:placetype":"venue"
},
  "geometry": {"coordinates":[-121.23912300000001,38.283012],"type":"Point"}
}