{
  "type": "Feature",
  "properties": {
    "iso:country":"US",
    "sg:address":"3184 Airway Ave",
    "sg:city":"Costa Mesa",
    "sg:classifiers":[
        {
            "category":"Professional",
            "type":"Services"
        }
    ],
    "sg:phone":"+1 714 850 1511",
    "sg:postcode":"92626",
    "sg:province":"CA",
    "wof:name":"Azusa Ridge 26 A Cal Ltd PA",
    "wof:placetype":"venue"
},
  "geometry": {"coordinates":[-117.86870999999999,33.682955],"type":"Point"}
}