{
  "type": "Feature",
  "properties": {
    "addr:full":"5667 Snell Ave Ste 120 San Jose CA 95101",
    "addr:housenumber":"5667",
    "addr:postcode":"95101",
    "addr:street":"Snell Ave Ste 120",
    "iso:country":"US",
    "sg:address":"5667 Snell Ave Ste 120",
    "sg:city":"San Jose",
    "sg:classifiers":[
        {
            "category":"Government",
            "subcategory":"City Hall",
            "type":"Public Place"
        },
        {
            "category":"Organizations",
            "subcategory":"Non-profit Organization",
            "type":"Services"
        }
    ],
    "sg:phone":"+1 408 849 3746",
    "sg:postcode":"95101",
    "sg:province":"CA",
    "sg:tags":[
        "community",
        "service/non-profit"
    ],
    "wof:name":"Battered Women's Alliance",
    "wof:placetype":"venue"
},
  "geometry": {"coordinates":[-121.830698,37.249976],"type":"Point"}
}