{
  "type": "Feature",
  "properties": {
    "iso:country":"US",
    "sg:address":"4201 Victoria Ave",
    "sg:city":"Oxnard",
    "sg:classifiers":[
        {
            "category":"Military Area",
            "type":"Public Place"
        }
    ],
    "sg:phone":"+1 805 985 7518",
    "sg:postcode":"93035",
    "sg:province":"CA",
    "sg:tags":[
        "force",
        "armed",
        "recruiting"
    ],
    "sg:website":"http://www.uscg.mil",
    "wof:name":"Coast Guard For The Blacktip",
    "wof:placetype":"venue"
},
  "geometry": {"coordinates":[-119.22171,34.16235],"type":"Point"}
}