{
  "type": "Feature",
  "properties": {
    "iso:country":"US",
    "sg:address":"1802 N Vermont Ave",
    "sg:city":"Los Angeles",
    "sg:classifiers":[
        {
            "category":"Restaurant",
            "type":"Food & Drink"
        }
    ],
    "sg:phone":"+1 323 662 1587",
    "sg:postcode":"90027",
    "sg:province":"CA",
    "sg:tags":[
        "french"
    ],
    "sg:website":"www.figarobistrot.com",
    "wof:name":"Figaro Bistrot",
    "wof:placetype":"venue"
},
  "geometry": {"coordinates":[-118.292,34.103699],"type":"Point"}
}