{
  "type": "Feature",
  "properties": {
    "iso:country":"US",
    "sg:address":"2120 S Santa Fe Ave",
    "sg:city":"Visalia",
    "sg:classifiers":[
        {
            "category":"Real Estate",
            "subcategory":"Real Estate Operator",
            "type":"Services"
        }
    ],
    "sg:phone":"+1 559 734 4431",
    "sg:postcode":"93292",
    "sg:province":"CA",
    "sg:tags":[
        "mobile",
        "home",
        "community"
    ],
    "wof:name":"Gold Star Mobile Estates",
    "wof:placetype":"venue"
},
  "geometry": {"coordinates":[-119.287314,36.31154],"type":"Point"}
}