{
  "type": "Feature",
  "properties": {
    "iso:country":"US",
    "sg:address":"4916 Long Beach Blvd",
    "sg:city":"Long Beach",
    "sg:classifiers":[
        {
            "category":"Travel",
            "subcategory":"Hotels & Motels",
            "type":"Entertainment"
        }
    ],
    "sg:phone":"+1 562 428 1743",
    "sg:postcode":"90805",
    "sg:province":"CA",
    "wof:name":"Travel King Motel",
    "wof:placetype":"venue"
},
  "geometry": {"coordinates":[-118.193001,33.8452],"type":"Point"}
}