{
  "type": "Feature",
  "properties": {
    "iso:country":"US",
    "sg:address":"2200 Powell St",
    "sg:city":"Emeryville",
    "sg:classifiers":[
        {
            "category":"Shopping",
            "subcategory":"Computers & Home Electronics",
            "type":"Retail Goods"
        }
    ],
    "sg:phone":"+1 510 547 5580",
    "sg:postcode":"94608",
    "sg:province":"CA",
    "sg:tags":[
        "software"
    ],
    "sg:website":"www.hp.com",
    "wof:name":"Hp Novadigm Inc",
    "wof:placetype":"venue"
},
  "geometry": {"coordinates":[-122.300065,37.837626],"type":"Point"}
}