{
  "type": "Feature",
  "properties": {
    "iso:country":"US",
    "sg:address":"13018 Marlette Dr",
    "sg:city":"La Mirada",
    "sg:classifiers":[
        {
            "category":"Wholesale",
            "subcategory":"Durable Goods & Equipment",
            "type":"Manufacturing & Wholesale Goods"
        }
    ],
    "sg:phone":"+1 562 946 2815",
    "sg:postcode":"90638",
    "sg:province":"CA",
    "sg:tags":[
        "representative",
        "manufacturer"
    ],
    "wof:name":"H & H Outdoor Marketing Co",
    "wof:placetype":"venue"
},
  "geometry": {"coordinates":[-118.028192,33.913013],"type":"Point"}
}