{
  "type": "Feature",
  "properties": {
    "addr:full":"2201 E Chapman Ave Fullerton CA 92831",
    "addr:housenumber":"2201",
    "addr:postcode":"92831",
    "addr:street":"E Chapman Ave",
    "iso:country":"US",
    "sg:address":"2201 E Chapman Ave",
    "sg:city":"Fullerton",
    "sg:classifiers":[
        {
            "category":"Professional",
            "subcategory":"Lawyer & Legal Services",
            "type":"Services"
        }
    ],
    "sg:phone":"+1 714 870 7901",
    "sg:postcode":"92831",
    "sg:province":"CA",
    "sg:tags":[
        "attorney"
    ],
    "wof:name":"Kaveh Ardalan",
    "wof:placetype":"venue"
},
  "geometry": {"coordinates":[-117.89287,33.87421],"type":"Point"}
}