{
  "type": "Feature",
  "properties": {
    "addr:full":"5884 Eden Park Pl San Jose CA 95138",
    "addr:housenumber":"5884",
    "addr:postcode":"95138",
    "addr:street":"Eden Park Pl",
    "iso:country":"US",
    "sg:address":"5884 Eden Park Pl",
    "sg:city":"San Jose",
    "sg:classifiers":[
        {
            "category":"Professional",
            "subcategory":"Art Services",
            "type":"Services"
        }
    ],
    "sg:phone":"+1 408 835 2457",
    "sg:postcode":"95138",
    "sg:province":"CA",
    "sg:tags":[
        "photographer"
    ],
    "sg:website":"www.signetringfilms.com",
    "wof:name":"Signet Ring Films",
    "wof:placetype":"venue"
},
  "geometry": {"coordinates":[-121.77261799999999,37.248828],"type":"Point"}
}