{
  "type": "Feature",
  "properties": {
    "addr:full":"228 Hamilton Avenue Suite 300 Palo Alto CA 94301",
    "addr:housenumber":"228",
    "addr:postcode":"94301",
    "addr:street":"Hamilton Avenue Suite 300",
    "iso:country":"US",
    "sg:address":"228 Hamilton Avenue Suite 300",
    "sg:city":"Palo Alto",
    "sg:classifiers":[
        {
            "category":"Professional",
            "subcategory":"Research",
            "type":"Services"
        }
    ],
    "sg:phone":"+1 650 798 5152",
    "sg:postcode":"94301",
    "sg:province":"CA",
    "sg:website":"https://utilityscalesolar.com/Home_Page.html",
    "wof:name":"Utility Scale Solar",
    "wof:placetype":"venue"
},
  "geometry": {"coordinates":[-122.161148,37.444083],"type":"Point"}
}