{
  "type": "Feature",
  "properties": {
    "iso:country":"US",
    "sg:address":"308 Anza St",
    "sg:city":"San Francisco",
    "sg:classifiers":[
        {
            "category":"Building & Trades",
            "subcategory":"Landscaping Services",
            "type":"Services"
        }
    ],
    "sg:phone":"+1 415 387 1155",
    "sg:postcode":"94118",
    "sg:province":"CA",
    "sg:tags":[
        "designer",
        "landscape"
    ],
    "wof:name":"Stanley's Garden",
    "wof:placetype":"venue"
},
  "geometry": {"coordinates":[-122.45079,37.780707],"type":"Point"}
}