{
  "type": "Feature",
  "properties": {
    "iso:country":"US",
    "sg:address":"300 Plymouth Ave",
    "sg:city":"San Francisco",
    "sg:classifiers":[
        {
            "category":"Restaurant",
            "type":"Food & Drink"
        }
    ],
    "sg:phone":"+1 415 586 8463",
    "sg:postcode":"94112",
    "sg:province":"CA",
    "wof:name":"Miss Addy's",
    "wof:placetype":"venue"
},
  "geometry": {"coordinates":[-122.456061,37.714076],"type":"Point"}
}