{
  "type": "Feature",
  "properties": {
    "iso:country":"US",
    "sg:address":"737 E Lake Ave",
    "sg:city":"Watsonville",
    "sg:classifiers":[
        {
            "category":"Banks & Credit Unions",
            "subcategory":"Bank",
            "type":"Services"
        }
    ],
    "sg:phone":"+1 831 722 5025",
    "sg:postcode":"95076",
    "sg:province":"CA",
    "sg:tags":[
        "mortgage"
    ],
    "wof:name":"Joe Perez",
    "wof:placetype":"venue"
},
  "geometry": {"coordinates":[-121.747213,36.92167],"type":"Point"}
}