{
  "type": "Feature",
  "properties": {
    "addr:full":"11320 Countryside Dr Fontana CA 92337",
    "addr:housenumber":"11320",
    "addr:postcode":"92337",
    "addr:street":"Countryside Dr",
    "iso:country":"US",
    "sg:address":"11320 Countryside Dr",
    "sg:city":"Fontana",
    "sg:classifiers":[
        {
            "category":"Arts & Performance",
            "subcategory":"Theater",
            "type":"Entertainment"
        }
    ],
    "sg:phone":"+1 909 355 4600",
    "sg:postcode":"92337",
    "sg:province":"CA",
    "sg:tags":[
        "bureau"
    ],
    "wof:name":"Ad Entertainment Svc",
    "wof:placetype":"venue"
},
  "geometry": {"coordinates":[-117.50562600000001,34.04693],"type":"Point"}
}