{
  "type": "Feature",
  "properties": {
    "iso:country":"US",
    "sg:address":"716 16th St",
    "sg:city":"San Diego",
    "sg:classifiers":[
        {
            "category":"Professional",
            "subcategory":"Computer Services",
            "type":"Services"
        }
    ],
    "sg:phone":"+1 619 234 7122",
    "sg:postcode":"92101",
    "sg:province":"CA",
    "sg:tags":[
        "repair"
    ],
    "wof:name":"GTM Wholesale",
    "wof:placetype":"venue"
},
  "geometry": {"coordinates":[-117.149473,32.713675],"type":"Point"}
}