{
  "type": "Feature",
  "properties": {
    "addr:full":"915 W Roseburg Ave Modesto CA 95350",
    "addr:housenumber":"915",
    "addr:postcode":"ca 95350",
    "addr:street":"W Roseburg Ave",
    "iso:country":"US",
    "sg:address":"915 W Roseburg Ave",
    "sg:city":"Modesto",
    "sg:classifiers":[
        {
            "category":"Personal",
            "subcategory":"Barber",
            "type":"Services"
        }
    ],
    "sg:phone":"+1 209 522 7364",
    "sg:postcode":"95350",
    "sg:province":"CA",
    "wof:name":"Roseburg Square Barber Shop",
    "wof:placetype":"venue"
},
  "geometry": {"coordinates":[-121.00431399999999,37.660315],"type":"Point"}
}