{
  "type": "Feature",
  "properties": {
    "iso:country":"US",
    "sg:address":"22954 Dracaea Ave",
    "sg:city":"Moreno Valley",
    "sg:classifiers":[
        {
            "category":"Shopping",
            "subcategory":"Music",
            "type":"Retail Goods"
        }
    ],
    "sg:phone":"+1 951 653 7030",
    "sg:postcode":"92553",
    "sg:province":"CA",
    "wof:name":"Final Record Derby",
    "wof:placetype":"venue"
},
  "geometry": {"coordinates":[-117.261849,33.927893],"type":"Point"}
}