{
  "type": "Feature",
  "properties": {
    "iso:country":"US",
    "sg:address":"594 S Coast Hwy 101",
    "sg:city":"Encinitas",
    "sg:classifiers":[
        {
            "category":"Personal",
            "subcategory":"Beauty Salon",
            "type":"Services"
        }
    ],
    "sg:phone":"+1 760 634 1999",
    "sg:postcode":"92024",
    "sg:province":"CA",
    "sg:tags":[
        "hair"
    ],
    "sg:website":"www.detoursalon.com",
    "wof:name":"Detour Salon",
    "wof:placetype":"venue"
},
  "geometry": {"coordinates":[-117.293843,33.044801],"type":"Point"}
}