{
  "type": "Feature",
  "properties": {
    "iso:country":"US",
    "sg:address":"500 Arguello St",
    "sg:city":"Redwood City",
    "sg:classifiers":[
        {
            "category":"Health Services",
            "subcategory":"Doctor",
            "type":"Services"
        }
    ],
    "sg:phone":"+1 650 851 4900",
    "sg:postcode":"94063",
    "sg:province":"CA",
    "sg:tags":[
        "physician",
        "surgeon"
    ],
    "wof:name":"Soar Sports Orthopedic Rehab",
    "wof:placetype":"venue"
},
  "geometry": {"coordinates":[-122.233869,37.487576],"type":"Point"}
}