{
  "type": "Feature",
  "properties": {
    "iso:country":"US",
    "sg:address":"611 I St",
    "sg:city":"Eureka",
    "sg:classifiers":[
        {
            "category":"Real Estate",
            "subcategory":"Real Estate Services",
            "type":"Services"
        }
    ],
    "sg:phone":"+1 707 443 0837",
    "sg:postcode":"95501",
    "sg:province":"CA",
    "sg:tags":[
        "company",
        "title"
    ],
    "sg:website":"www.hltco.com",
    "wof:name":"Humboldt Land Title Co",
    "wof:placetype":"venue"
},
  "geometry": {"coordinates":[-124.162381,40.801453],"type":"Point"}
}