{
  "type": "Feature",
  "properties": {
    "addr:full":"2433 Carleton Street Berkeley CA 94704",
    "addr:housenumber":"2433",
    "addr:postcode":"94704",
    "addr:street":"Carleton Street",
    "iso:country":"US",
    "sg:address":"2433 Carleton Street",
    "sg:city":"Berkeley",
    "sg:classifiers":[
        {
            "category":"Health Services",
            "subcategory":"Clinic",
            "type":"Services"
        }
    ],
    "sg:phone":"+1 510 845 1363",
    "sg:postcode":"94704",
    "sg:province":"CA",
    "sg:tags":[
        "counseling",
        "mental"
    ],
    "wof:name":"Kallinger David PHD",
    "wof:placetype":"venue"
},
  "geometry": {"coordinates":[-122.25900300000001,37.862499],"type":"Point"}
}