{
  "type": "Feature",
  "properties": {
    "iso:country":"US",
    "sg:address":"26692 Pierce Cir",
    "sg:city":"Murrieta",
    "sg:classifiers":[
        {
            "category":"Professional",
            "subcategory":"Computer Services",
            "type":"Services"
        }
    ],
    "sg:phone":"+1 951 304 0375",
    "sg:postcode":"92562",
    "sg:province":"CA",
    "sg:tags":[
        "repair"
    ],
    "wof:name":"4 Tech Computer Company Inc",
    "wof:placetype":"venue"
},
  "geometry": {"coordinates":[-117.17485499999999,33.532173],"type":"Point"}
}