{
  "type": "Feature",
  "properties": {
    "addr:full":"32841 Road 160 Ivanhoe CA 93235",
    "addr:housenumber":"32841",
    "addr:postcode":"93235",
    "addr:street":"Road 160",
    "iso:country":"US",
    "sg:address":"32841 Road 160",
    "sg:city":"Ivanhoe",
    "sg:classifiers":[
        {
            "category":"Fast Food",
            "type":"Food & Drink"
        },
        {
            "category":"Restaurant",
            "type":"Food & Drink"
        }
    ],
    "sg:phone":"+1 559 798 2133",
    "sg:postcode":"93235",
    "sg:province":"CA",
    "sg:tags":[
        "take"
    ],
    "wof:name":"Triangle Drive-In",
    "wof:placetype":"venue"
},
  "geometry": {"coordinates":[-119.215739,36.385425],"type":"Point"}
}