{
  "type": "Feature",
  "properties": {
    "iso:country":"US",
    "sg:address":"520 Broadway, 5th Floor",
    "sg:city":"Santa Monica",
    "sg:classifiers":[
        {
            "category":"Professional",
            "subcategory":"Advertising",
            "type":"Services"
        }
    ],
    "sg:phone":"+1 720 875 5622",
    "sg:postcode":"90401",
    "sg:province":"CA",
    "sg:website":"http://www.ascentmediacorporation.com",
    "wof:name":"Ascent Media Corporation",
    "wof:placetype":"venue"
},
  "geometry": {"coordinates":[-118.494192,34.017177],"type":"Point"}
}