{
  "type": "Feature",
  "properties": {
    "iso:country":"US",
    "sg:address":"3550 E Pico Blvd",
    "sg:city":"Los Angeles",
    "sg:classifiers":[
        {
            "category":"Building & Trades",
            "subcategory":"Construction",
            "type":"Services"
        }
    ],
    "sg:phone":"+1 323 261 7479",
    "sg:postcode":"90023",
    "sg:province":"CA",
    "sg:tags":[
        "carpentry",
        "contractor"
    ],
    "wof:name":"Marcelino Cabinets",
    "wof:placetype":"venue"
},
  "geometry": {"coordinates":[-118.201766,34.017941],"type":"Point"}
}