{
  "type": "Feature",
  "properties": {
    "addr:full":"1534 Timber Creek Dr San Jose CA 95131",
    "addr:housenumber":"1534",
    "addr:postcode":"95131",
    "addr:street":"Timber Creek Dr",
    "iso:country":"US",
    "sg:address":"1534 Timber Creek Dr",
    "sg:city":"San Jose",
    "sg:classifiers":[
        {
            "category":"Freight",
            "type":"Transportation"
        }
    ],
    "sg:phone":"+1 408 748 0870",
    "sg:postcode":"95131",
    "sg:province":"CA",
    "sg:tags":[
        "courier"
    ],
    "wof:name":"Data Courier",
    "wof:placetype":"venue"
},
  "geometry": {"coordinates":[-121.873802,37.390136],"type":"Point"}
}