{
  "type": "Feature",
  "properties": {
    "iso:country":"US",
    "sg:address":"5835 Temple City Blvd",
    "sg:city":"Temple City",
    "sg:classifiers":[
        {
            "category":"Restaurant",
            "type":"Food & Drink"
        }
    ],
    "sg:phone":"+1 626 286 8018",
    "sg:postcode":"91780",
    "sg:province":"CA",
    "sg:tags":[
        "sushi",
        "bar",
        "japanese"
    ],
    "wof:name":"The Sushi",
    "wof:placetype":"venue"
},
  "geometry": {"coordinates":[-118.060697,34.105567],"type":"Point"}
}