{
  "type": "Feature",
  "properties": {
    "iso:country":"US",
    "sg:address":"8222 Vickers St",
    "sg:city":"San Diego",
    "sg:classifiers":[
        {
            "category":"Manufacturing",
            "subcategory":"Textiles",
            "type":"Manufacturing & Wholesale Goods"
        }
    ],
    "sg:phone":"+1 858 565 2944",
    "sg:postcode":"92111",
    "sg:province":"CA",
    "sg:tags":[
        "curtain"
    ],
    "wof:name":"MBF Interiors",
    "wof:placetype":"venue"
},
  "geometry": {"coordinates":[-117.145946,32.827358],"type":"Point"}
}