{
  "type": "Feature",
  "properties": {
    "addr:full":"1835 Whittier Ave Costa Mesa CA 92627",
    "addr:housenumber":"1835",
    "addr:postcode":"92627",
    "addr:street":"Whittier Ave",
    "iso:country":"US",
    "sg:address":"1835 Whittier Ave",
    "sg:city":"Costa Mesa",
    "sg:classifiers":[
        {
            "category":"Building & Trades",
            "subcategory":"Plumbing",
            "type":"Services"
        }
    ],
    "sg:phone":"+1 949 631 2947",
    "sg:postcode":"92627",
    "sg:province":"CA",
    "sg:tags":[
        "plumbing",
        "contractor"
    ],
    "wof:name":"J B Ford Plumbing Inc",
    "wof:placetype":"venue"
},
  "geometry": {"coordinates":[-117.940709,33.641373],"type":"Point"}
}