{
  "type": "Feature",
  "properties": {
    "iso:country":"US",
    "sg:address":"431 Crown Point Cir",
    "sg:city":"Grass Valley",
    "sg:classifiers":[
        {
            "category":"Building & Trades",
            "subcategory":"Construction",
            "type":"Services"
        }
    ],
    "sg:phone":"+1 530 271 1600",
    "sg:postcode":"95945",
    "sg:province":"CA",
    "sg:tags":[
        "water",
        "control",
        "pollution"
    ],
    "wof:name":"7-H Technical Svc Group Inc",
    "wof:placetype":"venue"
},
  "geometry": {"coordinates":[-121.033327,39.219249],"type":"Point"}
}