{
  "type": "Feature",
  "properties": {
    "addr:full":"233 N Tustin St Orange CA 92867",
    "addr:housenumber":"233",
    "addr:postcode":"92867",
    "addr:street":"N Tustin St",
    "iso:country":"US",
    "sg:address":"233 N Tustin St",
    "sg:city":"Orange",
    "sg:classifiers":[
        {
            "category":"Utilities",
            "subcategory":"Recycling",
            "type":"Services"
        },
        {
            "category":"Home & Garden",
            "subcategory":"Furniture",
            "type":"Retail Goods"
        }
    ],
    "sg:phone":"+1 800 476 0444",
    "sg:postcode":"92867",
    "sg:province":"CA",
    "sg:tags":[
        "outdoor",
        "stool",
        "patio",
        "store"
    ],
    "sg:website":"www.witherspoons.com",
    "wof:name":"Witherspoon's Bars Stools & Dinettes",
    "wof:placetype":"venue"
},
  "geometry": {"coordinates":[-117.835999,33.790199],"type":"Point"}
}