{
  "type": "Feature",
  "properties": {
    "iso:country":"US",
    "sg:address":"2200 Cobblestone Ave",
    "sg:city":"Fairfield",
    "sg:classifiers":[
        {
            "category":"Shopping",
            "subcategory":"Clothing, Apparel, & Fashions",
            "type":"Retail Goods"
        }
    ],
    "sg:phone":"+1 707 425 6122",
    "sg:postcode":"94534",
    "sg:province":"CA",
    "sg:tags":[
        "item",
        "boutique"
    ],
    "wof:name":"Claire's",
    "wof:placetype":"venue"
},
  "geometry": {"coordinates":[-122.045253,38.290061],"type":"Point"}
}