{
  "type": "Feature",
  "properties": {
    "addr:full":"13445 Estelle St Corona CA 92879",
    "addr:housenumber":"13445",
    "addr:postcode":"92879",
    "addr:street":"Estelle St",
    "iso:country":"US",
    "sg:address":"13445 Estelle St",
    "sg:city":"Corona",
    "sg:classifiers":[
        {
            "category":"Building & Trades",
            "subcategory":"Plumbing",
            "type":"Services"
        }
    ],
    "sg:phone":"+1 909 620 4699",
    "sg:postcode":"92879",
    "sg:province":"CA",
    "sg:tags":[
        "sheet",
        "work",
        "metal",
        "contractor"
    ],
    "sg:website":"www.jetmanufacturing.com",
    "wof:name":"Jet Manufacturing",
    "wof:placetype":"venue"
},
  "geometry": {"coordinates":[-117.51507100000001,33.88292],"type":"Point"}
}