{
  "type": "Feature",
  "properties": {
    "addr:full":"5512 Sulphur Dr Mira Loma CA 91752",
    "addr:housenumber":"5512",
    "addr:postcode":"91752",
    "addr:street":"Sulphur Dr",
    "iso:country":"US",
    "sg:address":"5512 Sulphur Dr",
    "sg:city":"Mira Loma",
    "sg:classifiers":[
        {
            "category":"Restaurant",
            "type":"Food & Drink"
        }
    ],
    "sg:phone":"+1 951 681 5153",
    "sg:postcode":"91752",
    "sg:province":"CA",
    "sg:tags":[
        "caterer"
    ],
    "wof:name":"Party Productions",
    "wof:placetype":"venue"
},
  "geometry": {"coordinates":[-117.534761,33.987699],"type":"Point"}
}