{
  "type": "Feature",
  "properties": {
    "addr:full":"10741 Taulbee Ct Tustin CA 92782",
    "addr:housenumber":"10741",
    "addr:postcode":"92782",
    "addr:street":"Taulbee Ct",
    "iso:country":"US",
    "sg:address":"10741 Taulbee Ct",
    "sg:city":"Tustin",
    "sg:classifiers":[
        {
            "category":"Manufacturing",
            "subcategory":"Tools & Machinery",
            "type":"Manufacturing & Wholesale Goods"
        }
    ],
    "sg:phone":"+1 714 734 9801",
    "sg:postcode":"92782",
    "sg:province":"CA",
    "sg:tags":[
        "industrial",
        "mfg"
    ],
    "wof:name":"Precision Machine Products",
    "wof:placetype":"venue"
},
  "geometry": {"coordinates":[-117.765297,33.760616],"type":"Point"}
}