{
  "type": "Feature",
  "properties": {
    "addr:full":"21535 Hawthorne Blvd Ste 540 Torrance CA 90503",
    "addr:housenumber":"21535",
    "addr:postcode":"90503",
    "addr:street":"Hawthorne Blvd Ste 540",
    "iso:country":"US",
    "sg:address":"21535 Hawthorne Blvd Ste 540",
    "sg:city":"Torrance",
    "sg:classifiers":[
        {
            "category":"Professional",
            "subcategory":"Accounting & Tax Preparation",
            "type":"Services"
        }
    ],
    "sg:phone":"+1 310 316 7338",
    "sg:postcode":"90503",
    "sg:province":"CA",
    "sg:tags":[
        "accountant"
    ],
    "wof:name":"Therrien Gregory G CPA",
    "wof:placetype":"venue"
},
  "geometry": {"coordinates":[-118.352997,33.832699],"type":"Point"}
}