{
  "type": "Feature",
  "properties": {
    "addr:full":"18881 Beach Blvd Huntington Beach CA 92648",
    "addr:housenumber":"18881",
    "addr:postcode":"92648",
    "addr:street":"Beach Blvd",
    "iso:country":"US",
    "sg:address":"18881 Beach Blvd",
    "sg:city":"Huntington Beach",
    "sg:classifiers":[
        {
            "category":"Autos & Motor Vehicles",
            "subcategory":"Automobile Sales",
            "type":"Retail Goods"
        },
        {
            "category":"Retail",
            "subcategory":"Auto Repair",
            "type":"Services"
        }
    ],
    "sg:phone":"+1 714 847 8555",
    "sg:postcode":"92648",
    "sg:province":"CA",
    "sg:tags":[
        "car"
    ],
    "wof:name":"David Wilson Toyota of Huntington Beach",
    "wof:placetype":"venue"
},
  "geometry": {"coordinates":[-117.988998,33.688599],"type":"Point"}
}