{
  "type": "Feature",
  "properties": {
    "addr:full":"7530 Salton Sea Way Sacramento CA 95831",
    "addr:housenumber":"7530",
    "addr:postcode":"95831",
    "addr:street":"Salton Sea Way",
    "iso:country":"US",
    "sg:address":"7530 Salton Sea Way",
    "sg:city":"Sacramento",
    "sg:classifiers":[
        {
            "category":"Wholesale",
            "subcategory":"Drugs",
            "type":"Manufacturing & Wholesale Goods"
        }
    ],
    "sg:phone":"+1 916 422 8484",
    "sg:postcode":"95831",
    "sg:province":"CA",
    "wof:name":"KY KY Essence",
    "wof:placetype":"venue"
},
  "geometry": {"coordinates":[-121.54405300000001,38.484511],"type":"Point"}
}