{
  "type": "Feature",
  "properties": {
    "addr:full":"3322 David Dr Napa CA 94558",
    "addr:housenumber":"3322",
    "addr:postcode":"94558",
    "addr:street":"David Dr",
    "iso:country":"US",
    "sg:address":"3322 David Dr",
    "sg:city":"Napa",
    "sg:classifiers":[
        {
            "category":"Banks & Credit Unions",
            "subcategory":"Bank",
            "type":"Services"
        }
    ],
    "sg:phone":"+1 707 259 1117",
    "sg:postcode":"94558",
    "sg:province":"CA",
    "sg:tags":[
        "loan",
        "real estate"
    ],
    "wof:name":"Mitchell Mortgage",
    "wof:placetype":"venue"
},
  "geometry": {"coordinates":[-122.335694,38.299507],"type":"Point"}
}