{
  "type": "Feature",
  "properties": {
    "iso:country":"US",
    "sg:address":"275 Shoreline Dr",
    "sg:city":"Redwood City",
    "sg:classifiers":[
        {
            "category":"Professional",
            "subcategory":"Management & Consulting",
            "type":"Services"
        }
    ],
    "sg:phone":"+1 415 771 5530",
    "sg:postcode":"94065",
    "sg:province":"CA",
    "sg:tags":[
        "consultant",
        "broker"
    ],
    "wof:name":"Yessgroup Inc",
    "wof:placetype":"venue"
},
  "geometry": {"coordinates":[-122.26065,37.522855],"type":"Point"}
}