{
  "type": "Feature",
  "properties": {
    "iso:country":"US",
    "sg:address":"3880 San Ysidro Way",
    "sg:city":"Sacramento",
    "sg:classifiers":[
        {
            "category":"Building & Trades",
            "subcategory":"Electrical",
            "type":"Services"
        }
    ],
    "sg:phone":"+1 916 481 0307",
    "sg:postcode":"95864",
    "sg:province":"CA",
    "sg:tags":[
        "electrician"
    ],
    "wof:name":"Doug Milan Electric",
    "wof:placetype":"venue"
},
  "geometry": {"coordinates":[-121.373941,38.583235],"type":"Point"}
}