{
  "type": "Feature",
  "properties": {
    "addr:full":"4001 Gion Ave San Jose CA 95127",
    "addr:housenumber":"4001",
    "addr:postcode":"95127",
    "addr:street":"Gion Ave",
    "iso:country":"US",
    "sg:address":"4001 Gion Ave",
    "sg:city":"San Jose",
    "sg:classifiers":[
        {
            "category":"Personal",
            "subcategory":"Beauty Salon",
            "type":"Services"
        }
    ],
    "sg:phone":"+1 408 929 5351",
    "sg:postcode":"95127",
    "sg:province":"CA",
    "sg:tags":[
        "spa"
    ],
    "wof:name":"Victoria Hair and Nail Salons",
    "wof:placetype":"venue"
},
  "geometry": {"coordinates":[-121.832643,37.371938],"type":"Point"}
}