{
  "type": "Feature",
  "properties": {
    "addr:full":"206 W Poplar St Compton CA 90220",
    "addr:housenumber":"206",
    "addr:postcode":"90220",
    "addr:street":"W Poplar St",
    "iso:country":"US",
    "sg:address":"206 W Poplar St",
    "sg:city":"Compton",
    "sg:classifiers":[
        {
            "category":"Freight",
            "type":"Transportation"
        }
    ],
    "sg:phone":"+1 310 884 9413",
    "sg:postcode":"90220",
    "sg:province":"CA",
    "wof:name":"Marshall 3 Transportation",
    "wof:placetype":"venue"
},
  "geometry": {"coordinates":[-118.22697100000001,33.899883],"type":"Point"}
}