{
  "type": "Feature",
  "properties": {
    "iso:country":"US",
    "sg:address":"1024 Simon Dr",
    "sg:city":"Placerville",
    "sg:classifiers":[
        {
            "category":"Social Services",
            "subcategory":"Adult Care",
            "type":"Services"
        }
    ],
    "sg:phone":"+1 530 295 8172",
    "sg:postcode":"95667",
    "sg:province":"CA",
    "sg:tags":[
        "home",
        "residential"
    ],
    "wof:name":"Sunrise Assisted Living",
    "wof:placetype":"venue"
},
  "geometry": {"coordinates":[-120.795706,38.730564],"type":"Point"}
}