{
  "type": "Feature",
  "properties": {
    "addr:full":"8555C Sunset Blvd West Hollywood CA 90069",
    "addr:housenumber":"8555c",
    "addr:postcode":"90069",
    "addr:street":"Sunset Blvd",
    "iso:country":"US",
    "sg:address":"8555C Sunset Blvd",
    "sg:city":"West Hollywood",
    "sg:classifiers":[
        {
            "category":"Retail",
            "subcategory":"Laundry & Dry Cleaning",
            "type":"Services"
        }
    ],
    "sg:postcode":"90069",
    "sg:province":"CA",
    "wof:name":"Elite Cleaners",
    "wof:placetype":"venue"
},
  "geometry": {"coordinates":[-118.378044,34.093289],"type":"Point"}
}