{
  "type": "Feature",
  "properties": {
    "addr:full":"510 17th St Oakland CA 94612",
    "addr:housenumber":"510",
    "addr:postcode":"94612",
    "addr:street":"17Th St",
    "iso:country":"US",
    "sg:address":"510 17th St",
    "sg:city":"Oakland",
    "sg:classifiers":[
        {
            "category":"Professional",
            "subcategory":"Business Services",
            "type":"Services"
        }
    ],
    "sg:phone":"+1 510 763 0936",
    "sg:postcode":"94612",
    "sg:province":"CA",
    "sg:tags":[
        "interior",
        "consultant",
        "design",
        "decorator"
    ],
    "wof:name":"Space LLC",
    "wof:placetype":"venue"
},
  "geometry": {"coordinates":[-122.271756,37.80712],"type":"Point"}
}