{
  "type": "Feature",
  "properties": {
    "addr:full":"550 N Canyon Pkwy Livermore CA 94551",
    "addr:housenumber":"550",
    "addr:postcode":"94551",
    "addr:street":"N Canyon Pkwy",
    "iso:country":"US",
    "sg:address":"550 N Canyon Pkwy",
    "sg:city":"Livermore",
    "sg:classifiers":[
        {
            "category":"Real Estate",
            "subcategory":"Real Estate Agent",
            "type":"Services"
        }
    ],
    "sg:phone":"+1 209 836 8650",
    "sg:postcode":"94551",
    "sg:province":"CA",
    "wof:name":"Realty World",
    "wof:placetype":"venue"
},
  "geometry": {"coordinates":[-121.806748,37.706125],"type":"Point"}
}