{
  "type": "Feature",
  "properties": {
    "addr:full":"858 Rebecca St El Cajon CA 92019",
    "addr:housenumber":"858",
    "addr:postcode":"92019",
    "addr:street":"Rebecca St",
    "iso:country":"US",
    "sg:address":"858 Rebecca St",
    "sg:city":"El Cajon",
    "sg:classifiers":[
        {
            "category":"Professional",
            "type":"Services"
        }
    ],
    "sg:phone":"+1 619 401 9175",
    "sg:postcode":"92019",
    "sg:province":"CA",
    "wof:name":"Hanna M Esho",
    "wof:placetype":"venue"
},
  "geometry": {"coordinates":[-116.924267,32.78476],"type":"Point"}
}