{
  "type": "Feature",
  "properties": {
    "iso:country":"US",
    "sg:address":"7800 Topanga Canyon Blvd",
    "sg:city":"Canoga Park",
    "sg:classifiers":[
        {
            "category":"Organizations",
            "subcategory":"Membership Organization",
            "type":"Services"
        }
    ],
    "sg:phone":"+1 818 347 7099",
    "sg:postcode":"91304",
    "sg:province":"CA",
    "sg:tags":[
        "athletic"
    ],
    "wof:name":"West Valley Eagles Track Club",
    "wof:placetype":"venue"
},
  "geometry": {"coordinates":[-118.6058,34.208871],"type":"Point"}
}