{
  "type": "Feature",
  "properties": {
    "addr:full":"1716 W Redondo Beach Blvd Gardena CA 90247",
    "addr:housenumber":"1716",
    "addr:postcode":"90247",
    "addr:street":"W Redondo Beach Blvd",
    "iso:country":"US",
    "sg:address":"1716 W Redondo Beach Blvd",
    "sg:city":"Gardena",
    "sg:classifiers":[
        {
            "category":"Restaurant",
            "type":"Food & Drink"
        }
    ],
    "sg:phone":"+1 310 527 2727",
    "sg:postcode":"90247",
    "sg:province":"CA",
    "wof:name":"A Plus",
    "wof:placetype":"venue"
},
  "geometry": {"coordinates":[-118.308121,33.888795],"type":"Point"}
}