{
  "type": "Feature",
  "properties": {
    "iso:country":"US",
    "sg:address":"1915 W Orangewood Ave",
    "sg:city":"Orange",
    "sg:classifiers":[
        {
            "category":"Banks & Credit Unions",
            "subcategory":"Bank",
            "type":"Services"
        }
    ],
    "sg:phone":"+1 714 935 0771",
    "sg:postcode":"92868",
    "sg:province":"CA",
    "sg:tags":[
        "lending",
        "company"
    ],
    "wof:name":"Primerica",
    "wof:placetype":"venue"
},
  "geometry": {"coordinates":[-117.872419,33.795704],"type":"Point"}
}