{
  "type": "Feature",
  "properties": {
    "iso:country":"US",
    "sg:address":"34940 Date St",
    "sg:city":"Yucaipa",
    "sg:classifiers":[
        {
            "category":"Shopping",
            "subcategory":"Crafts & Fabrics",
            "type":"Retail Goods"
        }
    ],
    "sg:phone":"+1 909 797 1385",
    "sg:postcode":"92399",
    "sg:province":"CA",
    "sg:tags":[
        "sewing"
    ],
    "wof:name":"Tommies Traveling Quilt Shoppe",
    "wof:placetype":"venue"
},
  "geometry": {"coordinates":[-117.040226,34.041255],"type":"Point"}
}