{
  "type": "Feature",
  "properties": {
    "addr:full":"575 Orange Ave Coronado CA 92118",
    "addr:housenumber":"575",
    "addr:postcode":"92118",
    "addr:street":"Orange Ave",
    "iso:country":"US",
    "sg:address":"575 Orange Ave",
    "sg:city":"Coronado",
    "sg:classifiers":[
        {
            "category":"Health Services",
            "subcategory":"Chiropractor",
            "type":"Services"
        }
    ],
    "sg:phone":"+1 619 437 8888",
    "sg:postcode":"92118",
    "sg:province":"CA",
    "wof:name":"Potter Chiropractic",
    "wof:placetype":"venue"
},
  "geometry": {"coordinates":[-117.17588000000001,32.692657],"type":"Point"}
}