{
  "type": "Feature",
  "properties": {
    "addr:full":"1415 Ocean Front Walk Venice CA 90291",
    "addr:housenumber":"1415",
    "addr:postcode":"90291",
    "addr:street":"Ocean Front Walk",
    "iso:country":"US",
    "sg:address":"1415 Ocean Front Walk",
    "sg:city":"Venice",
    "sg:classifiers":[
        {
            "category":"Shopping",
            "subcategory":"Gifts & Souvenirs",
            "type":"Retail Goods"
        }
    ],
    "sg:phone":"+1 310 450 8430",
    "sg:postcode":"90291",
    "sg:province":"CA",
    "sg:tags":[
        "shop"
    ],
    "wof:name":"R & R Peace",
    "wof:placetype":"venue"
},
  "geometry": {"coordinates":[-118.474079,33.987546],"type":"Point"}
}