{
  "type": "Feature",
  "properties": {
    "iso:country":"US",
    "sg:address":"5th St & Mission St",
    "sg:city":"Carmel",
    "sg:classifiers":[
        {
            "category":"Restaurant",
            "type":"Food & Drink"
        }
    ],
    "sg:phone":"+1 831 625 0501",
    "sg:postcode":"93921",
    "sg:province":"CA",
    "sg:tags":[
        "french",
        "italian"
    ],
    "sg:website":"www.casanovarestaurant.com",
    "wof:name":"Casanova",
    "wof:placetype":"venue"
},
  "geometry": {"coordinates":[-121.920936,36.556871],"type":"Point"}
}