{
  "type": "Feature",
  "properties": {
    "addr:full":"3001 Red Hill Ave Ste 6-106 Costa Mesa CA 92626",
    "addr:housenumber":"3001",
    "addr:postcode":"92626",
    "addr:street":"Red Hill Ave Ste 6-106",
    "iso:country":"US",
    "sg:address":"3001 Red Hill Ave Ste 6-106",
    "sg:city":"Costa Mesa",
    "sg:classifiers":[
        {
            "category":"Wholesale",
            "subcategory":"Computers",
            "type":"Manufacturing & Wholesale Goods"
        },
        {
            "category":"Professional",
            "subcategory":"Computer Services",
            "type":"Services"
        }
    ],
    "sg:phone":"+1 714 429 0051",
    "sg:postcode":"92626",
    "sg:province":"CA",
    "sg:tags":[
        "repair"
    ],
    "wof:name":"Lasersource",
    "wof:placetype":"venue"
},
  "geometry": {"coordinates":[-117.878664,33.672264],"type":"Point"}
}