{
  "type": "Feature",
  "properties": {
    "iso:country":"US",
    "sg:address":"1415 Jefferson St",
    "sg:city":"Napa",
    "sg:classifiers":[
        {
            "category":"Health Services",
            "subcategory":"Optometrist",
            "type":"Services"
        }
    ],
    "sg:phone":"+1 707 252 3067",
    "sg:postcode":"94559",
    "sg:province":"CA",
    "wof:name":"Kenneth P Lee OD",
    "wof:placetype":"venue"
},
  "geometry": {"coordinates":[-122.293755,38.301344],"type":"Point"}
}