{
  "type": "Feature",
  "properties": {
    "iso:country":"US",
    "sg:address":"Castro Valley Blvd. and Castro Rd.",
    "sg:city":"Castro Valley",
    "sg:classifiers":[
        {
            "category":"Professional",
            "type":"Services"
        }
    ],
    "sg:phone":"+1 510 825 7574",
    "sg:postcode":"94546",
    "sg:province":"CA",
    "sg:website":"www.beam-intl.com",
    "wof:name":"Beam-International",
    "wof:placetype":"venue"
},
  "geometry": {"coordinates":[-122.06246299999999,37.693506],"type":"Point"}
}