{
  "type": "Feature",
  "properties": {
    "iso:country":"US",
    "sg:address":"1330 Fitzgerald Ave",
    "sg:city":"San Francisco",
    "sg:classifiers":[
        {
            "category":"Professional",
            "subcategory":"Management & Consulting",
            "type":"Services"
        }
    ],
    "sg:phone":"+1 415 822 1600",
    "sg:postcode":"94124",
    "sg:province":"CA",
    "sg:tags":[
        "apparel",
        "mfg",
        "belt"
    ],
    "wof:name":"Circa",
    "wof:placetype":"venue"
},
  "geometry": {"coordinates":[-122.394715,37.72292],"type":"Point"}
}