{
  "type": "Feature",
  "properties": {
    "iso:country":"US",
    "sg:address":"449 W Allen Ave",
    "sg:city":"San Dimas",
    "sg:classifiers":[
        {
            "category":"Building & Trades",
            "subcategory":"Construction",
            "type":"Services"
        }
    ],
    "sg:phone":"+1 909 305 9307",
    "sg:postcode":"91773",
    "sg:province":"CA",
    "sg:tags":[
        "maker",
        "cabinet"
    ],
    "wof:name":"A Fresh Kitchen",
    "wof:placetype":"venue"
},
  "geometry": {"coordinates":[-117.815514,34.117638],"type":"Point"}
}