{
  "type": "Feature",
  "properties": {
    "iso:country":"US",
    "sg:address":"1003 Dealy Ln",
    "sg:city":"Napa",
    "sg:classifiers":[
        {
            "category":"Manufacturing",
            "subcategory":"Food",
            "type":"Manufacturing & Wholesale Goods"
        }
    ],
    "sg:phone":"+1 707 257 6043",
    "sg:postcode":"94559",
    "sg:province":"CA",
    "sg:tags":[
        "mfg"
    ],
    "wof:name":"Wine Radio Network",
    "wof:placetype":"venue"
},
  "geometry": {"coordinates":[-122.34134,38.261537],"type":"Point"}
}