{
  "type": "Feature",
  "properties": {
    "iso:country":"US",
    "sg:address":"220 2nd Ave",
    "sg:city":"San Mateo",
    "sg:classifiers":[
        {
            "category":"Personal",
            "subcategory":"Beauty Salon",
            "type":"Services"
        }
    ],
    "sg:phone":"+1 650 685 5662",
    "sg:postcode":"94401",
    "sg:province":"CA",
    "wof:name":"Eliana Hair Studio",
    "wof:placetype":"venue"
},
  "geometry": {"coordinates":[-122.323347,37.566111],"type":"Point"}
}