{
  "type": "Feature",
  "properties": {
    "addr:full":"4815 Whitsett Ave Valley Village CA 91607",
    "addr:housenumber":"4815",
    "addr:postcode":"91607",
    "addr:street":"Whitsett Ave",
    "iso:country":"US",
    "sg:address":"4815 Whitsett Ave",
    "sg:city":"Valley Village",
    "sg:classifiers":[
        {
            "category":"Personal",
            "subcategory":"Barber",
            "type":"Services"
        }
    ],
    "sg:phone":"+1 818 760 1647",
    "sg:postcode":"91607",
    "sg:province":"CA",
    "wof:name":"Continental Hair Styling",
    "wof:placetype":"venue"
},
  "geometry": {"coordinates":[-118.404999,34.158001],"type":"Point"}
}