{
  "type": "Feature",
  "properties": {
    "addr:full":"135 Race St San Jose CA 95126",
    "addr:housenumber":"135",
    "addr:postcode":"95126",
    "addr:street":"Race St",
    "iso:country":"US",
    "sg:address":"135 Race St",
    "sg:city":"San Jose",
    "sg:classifiers":[
        {
            "category":"Personal",
            "type":"Services"
        }
    ],
    "sg:phone":"+1 408 297 0606",
    "sg:postcode":"95126",
    "sg:province":"CA",
    "sg:tags":[
        "local"
    ],
    "sg:website":"tannersengraving.com",
    "wof:name":"Tanner's Engraving",
    "wof:placetype":"venue"
},
  "geometry": {"coordinates":[-121.911886,37.327447],"type":"Point"}
}