{
  "type": "Feature",
  "properties": {
    "iso:country":"US",
    "sg:address":"1990 Grande Cir",
    "sg:city":"Fairfield",
    "sg:classifiers":[
        {
            "category":"Real Estate",
            "subcategory":"Real Estate Operator",
            "type":"Services"
        }
    ],
    "sg:phone":"+1 707 429 3091",
    "sg:postcode":"94533",
    "sg:province":"CA",
    "sg:tags":[
        "apartment"
    ],
    "wof:name":"Grande Vista Apartments",
    "wof:placetype":"venue"
},
  "geometry": {"coordinates":[-122.011511,38.263034],"type":"Point"}
}