{
  "type": "Feature",
  "properties": {
    "iso:country":"US",
    "sg:address":"99 San Mateo Rd",
    "sg:city":"Half Moon Bay",
    "sg:classifiers":[
        {
            "category":"Wholesale",
            "subcategory":"Fruits & Vegetables",
            "type":"Manufacturing & Wholesale Goods"
        }
    ],
    "sg:phone":"+1 650 726 2561",
    "sg:postcode":"94019",
    "sg:province":"CA",
    "sg:tags":[
        "fresh"
    ],
    "wof:name":"TOM & PETES PRODUCE",
    "wof:placetype":"venue"
},
  "geometry": {"coordinates":[-122.432954,37.467943],"type":"Point"}
}