{
  "type": "Feature",
  "properties": {
    "addr:full":"125 E Betteravia Rd Ste E Santa Maria CA 93454",
    "addr:housenumber":"125",
    "addr:postcode":"93454",
    "addr:street":"E Betteravia Rd Ste E",
    "iso:country":"US",
    "sg:address":"125 E Betteravia Rd Ste E",
    "sg:city":"Santa Maria",
    "sg:classifiers":[
        {
            "category":"Personal",
            "subcategory":"Hair Removal",
            "type":"Services"
        },
        {
            "category":"Personal",
            "subcategory":"Skin Care",
            "type":"Services"
        },
        {
            "category":"Personal",
            "subcategory":"Nail Salon",
            "type":"Services"
        }
    ],
    "sg:phone":"+1 805 614 1012",
    "sg:postcode":"93454",
    "sg:province":"CA",
    "wof:name":"BELLA LUNA SALON & SPA",
    "wof:placetype":"venue"
},
  "geometry": {"coordinates":[-120.435464,34.921035],"type":"Point"}
}