{
  "type": "Feature",
  "properties": {
    "iso:country":"US",
    "sg:address":"2040 Petaluma Blvd N",
    "sg:city":"Petaluma",
    "sg:classifiers":[
        {
            "category":"Wholesale",
            "subcategory":"Hardware",
            "type":"Manufacturing & Wholesale Goods"
        }
    ],
    "sg:phone":"+1 707 762 2010",
    "sg:postcode":"94952",
    "sg:province":"CA",
    "sg:tags":[
        "refrigerating"
    ],
    "wof:name":"Jerry's Refrigeration Inc",
    "wof:placetype":"venue"
},
  "geometry": {"coordinates":[-122.650431,38.25423],"type":"Point"}
}