{
  "type": "Feature",
  "properties": {
    "addr:full":"1546 Anna Way Petaluma CA 94954",
    "addr:housenumber":"1546",
    "addr:postcode":"94954",
    "addr:street":"Anna Way",
    "iso:country":"US",
    "sg:address":"1546 Anna Way",
    "sg:city":"Petaluma",
    "sg:classifiers":[
        {
            "category":"Freight",
            "type":"Transportation"
        }
    ],
    "sg:phone":"+1 707 887 1648",
    "sg:postcode":"94954",
    "sg:province":"CA",
    "sg:tags":[
        "operator",
        "trucking"
    ],
    "wof:name":"Anderson Trucking",
    "wof:placetype":"venue"
},
  "geometry": {"coordinates":[-122.605141,38.238445],"type":"Point"}
}