{
  "type": "Feature",
  "properties": {
    "addr:full":"7828 Haven Ave Rancho Cucamonga CA 91730",
    "addr:housenumber":"7828",
    "addr:postcode":"91730",
    "addr:street":"Haven Ave",
    "iso:country":"US",
    "sg:address":"7828 Haven Ave",
    "sg:city":"Rancho Cucamonga",
    "sg:classifiers":[
        {
            "category":"Insurance",
            "subcategory":"Insurance Agent",
            "type":"Services"
        }
    ],
    "sg:phone":"+1 909 481 2443",
    "sg:postcode":"91730",
    "sg:province":"CA",
    "wof:name":"State Farm Insurance",
    "wof:placetype":"venue"
},
  "geometry": {"coordinates":[-117.57592699999999,34.111026],"type":"Point"}
}