{
  "type": "Feature",
  "properties": {
    "iso:country":"US",
    "sg:address":"925 York St",
    "sg:city":"San Francisco",
    "sg:classifiers":[
        {
            "category":"Restaurant",
            "type":"Food & Drink"
        }
    ],
    "sg:phone":"+1 415 647 1786",
    "sg:postcode":"94110",
    "sg:province":"CA",
    "sg:tags":[
        "caterer"
    ],
    "wof:name":"Michele-Catering & Staffing",
    "wof:placetype":"venue"
},
  "geometry": {"coordinates":[-122.40845299999999,37.756451],"type":"Point"}
}