{
  "type": "Feature",
  "properties": {
    "iso:country":"US",
    "sg:address":"12100 Knott St",
    "sg:city":"Garden Grove",
    "sg:classifiers":[
        {
            "category":"Home & Garden",
            "subcategory":"Furniture",
            "type":"Retail Goods"
        }
    ],
    "sg:phone":"+1 714 901 3698",
    "sg:postcode":"92841",
    "sg:province":"CA",
    "sg:tags":[
        "store"
    ],
    "sg:website":"www.mandalayhomefurnishings.com",
    "wof:name":"Mandalay Home Furnishings",
    "wof:placetype":"venue"
},
  "geometry": {"coordinates":[-118.095834,33.786225],"type":"Point"}
}