{
  "type": "Feature",
  "properties": {
    "addr:full":"5808 W Telephone Rd Ventura CA 93003",
    "addr:housenumber":"5808",
    "addr:postcode":"93003",
    "addr:street":"W Telephone Rd",
    "iso:country":"US",
    "sg:address":"5808 W Telephone Rd",
    "sg:city":"Ventura",
    "sg:classifiers":[
        {
            "category":"Banks & Credit Unions",
            "subcategory":"Bank",
            "type":"Services"
        }
    ],
    "sg:phone":"+1 805 339 2600",
    "sg:postcode":"93003",
    "sg:province":"CA",
    "wof:name":"First Bank & Trust",
    "wof:placetype":"venue"
},
  "geometry": {"coordinates":[-119.21265099999999,34.265248],"type":"Point"}
}