{
  "type": "Feature",
  "properties": {
    "iso:country":"US",
    "sg:address":"719 S Main St",
    "sg:city":"Salinas",
    "sg:classifiers":[
        {
            "category":"Travel",
            "subcategory":"Hotels & Motels",
            "type":"Entertainment"
        }
    ],
    "sg:phone":"+1 831 758 8241",
    "sg:postcode":"93901",
    "sg:province":"CA",
    "wof:name":"Willow Lodge",
    "wof:placetype":"venue"
},
  "geometry": {"coordinates":[-121.65601599999999,36.667507],"type":"Point"}
}