{
  "type": "Feature",
  "properties": {
    "iso:country":"US",
    "sg:address":"2979 State St Ste C",
    "sg:city":"Carlsbad",
    "sg:classifiers":[
        {
            "category":"Building & Trades",
            "subcategory":"Landscaping Services",
            "type":"Services"
        }
    ],
    "sg:phone":"+1 760 729 8637",
    "sg:postcode":"92008",
    "sg:province":"CA",
    "sg:tags":[
        "consultant",
        "designer",
        "landscape"
    ],
    "wof:name":"A D L Planning Assts",
    "wof:placetype":"venue"
},
  "geometry": {"coordinates":[-117.348905,33.159803],"type":"Point"}
}