{
  "type": "Feature",
  "properties": {
    "iso:country":"US",
    "sg:address":"137 N Santa Cruz Ave",
    "sg:city":"Los Gatos",
    "sg:classifiers":[
        {
            "category":"Restaurant",
            "type":"Food & Drink"
        }
    ],
    "sg:phone":"+1 408 395 9115",
    "sg:postcode":"95030",
    "sg:province":"CA",
    "sg:tags":[
        "vietnamese"
    ],
    "sg:website":"www.greenpapaya.com",
    "wof:name":"The Green Papaya",
    "wof:placetype":"venue"
},
  "geometry": {"coordinates":[-121.983002,37.225498],"type":"Point"}
}