{
  "type": "Feature",
  "properties": {
    "iso:country":"US",
    "sg:address":"510 Northbay Dr",
    "sg:city":"Napa",
    "sg:classifiers":[
        {
            "category":"Home & Garden",
            "subcategory":"Building Materials",
            "type":"Retail Goods"
        }
    ],
    "sg:phone":"+1 707 224 7849",
    "sg:postcode":"94559",
    "sg:province":"CA",
    "sg:tags":[
        "door"
    ],
    "wof:name":"North Bay Plywood",
    "wof:placetype":"venue"
},
  "geometry": {"coordinates":[-122.280123,38.308665],"type":"Point"}
}