{
  "type": "Feature",
  "properties": {
    "addr:full":"8197 Burloak Way Elk Grove CA 95758",
    "addr:housenumber":"8197",
    "addr:postcode":"95758",
    "addr:street":"Burloak Way",
    "iso:country":"US",
    "sg:address":"8197 Burloak Way",
    "sg:city":"Elk Grove",
    "sg:classifiers":[
        {
            "category":"Professional",
            "subcategory":"Management & Consulting",
            "type":"Services"
        }
    ],
    "sg:phone":"+1 916 919 2853",
    "sg:postcode":"95758",
    "sg:province":"CA",
    "sg:tags":[
        "fuel"
    ],
    "wof:name":"Management Excellence",
    "wof:placetype":"venue"
},
  "geometry": {"coordinates":[-121.40377700000001,38.413645],"type":"Point"}
}