{
  "type": "Feature",
  "properties": {
    "addr:full":"3320 Leonis Blvd Vernon CA 90058",
    "addr:postcode":"3320;90058",
    "addr:street":"Leonis Blvd",
    "iso:country":"US",
    "sg:address":"3320 Leonis Blvd",
    "sg:city":"Vernon",
    "sg:classifiers":[
        {
            "category":"Wholesale",
            "subcategory":"Toys & Hobbies",
            "type":"Manufacturing & Wholesale Goods"
        }
    ],
    "sg:phone":"+1 323 582 8288",
    "sg:postcode":"90058",
    "sg:province":"CA",
    "wof:name":"Angel Plus Inc",
    "wof:placetype":"venue"
},
  "geometry": {"coordinates":[-118.205113,34.000194],"type":"Point"}
}