{
  "type": "Feature",
  "properties": {
    "iso:country":"US",
    "sg:address":"1508 San Mateo St",
    "sg:city":"Oceanside",
    "sg:classifiers":[
        {
            "category":"Manufacturing",
            "subcategory":"Metals",
            "type":"Manufacturing & Wholesale Goods"
        }
    ],
    "sg:phone":"+1 760 757 7440",
    "sg:postcode":"92058",
    "sg:province":"CA",
    "sg:tags":[
        "ornamental",
        "work"
    ],
    "wof:name":"Discount Iron Repairs Plus",
    "wof:placetype":"venue"
},
  "geometry": {"coordinates":[-117.379728,33.213431],"type":"Point"}
}