{
  "type": "Feature",
  "properties": {
    "iso:country":"US",
    "sg:address":"8670 Jenny Ave",
    "sg:city":"San Diego",
    "sg:classifiers":[
        {
            "category":"Social Services",
            "type":"Services"
        }
    ],
    "sg:phone":"+1 858 350 5870",
    "sg:postcode":"92123",
    "sg:province":"CA",
    "sg:tags":[
        "youth",
        "organization",
        "center"
    ],
    "wof:name":"Friends-Rollo United Anglers",
    "wof:placetype":"venue"
},
  "geometry": {"coordinates":[-117.14697200000001,32.794257],"type":"Point"}
}