{
  "type": "Feature",
  "properties": {
    "addr:full":"800 Wilshire Blvd Los Angeles CA 90017",
    "addr:housenumber":"800",
    "addr:postcode":"90017",
    "addr:street":"Wilshire Blvd",
    "iso:country":"US",
    "sg:address":"800 Wilshire Blvd",
    "sg:city":"Los Angeles",
    "sg:classifiers":[
        {
            "category":"Banks & Credit Unions",
            "subcategory":"Investment Brokerage",
            "type":"Services"
        }
    ],
    "sg:phone":"+1 213 683 9052",
    "sg:postcode":"90017",
    "sg:province":"CA",
    "wof:name":"Citicorp",
    "wof:placetype":"venue"
},
  "geometry": {"coordinates":[-118.25867700000001,34.0497],"type":"Point"}
}