{
  "type": "Feature",
  "properties": {
    "addr:full":"2090 del Rio Pl Ontario CA 91761",
    "addr:housenumber":"2090",
    "addr:postcode":"91761",
    "addr:street":"Del Rio Pl",
    "iso:country":"US",
    "sg:address":"2090 del Rio Pl",
    "sg:city":"Ontario",
    "sg:classifiers":[
        {
            "category":"Manufacturing",
            "subcategory":"Metals",
            "type":"Manufacturing & Wholesale Goods"
        },
        {
            "category":"Home & Garden",
            "subcategory":"Building Materials",
            "type":"Retail Goods"
        }
    ],
    "sg:phone":"+1 909 773 0001",
    "sg:postcode":"91761",
    "sg:province":"CA",
    "sg:tags":[
        "metalwork",
        "architectural",
        "mfg"
    ],
    "wof:name":"Pittcon Industries",
    "wof:placetype":"venue"
},
  "geometry": {"coordinates":[-117.603652,34.037341],"type":"Point"}
}