{
  "type": "Feature",
  "properties": {
    "addr:full":"16062 Foothill Blvd Fontana CA 92335",
    "addr:housenumber":"16062",
    "addr:postcode":"92335",
    "addr:street":"Foothill Blvd",
    "iso:country":"US",
    "sg:address":"16062 Foothill Blvd",
    "sg:city":"Fontana",
    "sg:classifiers":[
        {
            "category":"Restaurant",
            "type":"Food & Drink"
        }
    ],
    "sg:menulink":"http://www.allmenus.com/ca/san-bernardino/220364-bakers-drive-thru/menu/",
    "sg:phone":"+1 909 854 5741",
    "sg:postcode":"92335",
    "sg:province":"CA",
    "sg:tags":[
        "american"
    ],
    "wof:name":"Baker's Drive-thru",
    "wof:placetype":"venue"
},
  "geometry": {"coordinates":[-117.45429900000001,34.107003],"type":"Point"}
}