{
  "type": "Feature",
  "properties": {
    "addr:full":"77200 California Dr Palm Desert CA 92211",
    "addr:housenumber":"77200",
    "addr:postcode":"ca 92211",
    "addr:street":"California Dr",
    "iso:country":"US",
    "sg:address":"77200 California Dr",
    "sg:city":"Palm Desert",
    "sg:classifiers":[
        {
            "category":"Sports & Exercise",
            "subcategory":"Golf",
            "type":"Entertainment"
        }
    ],
    "sg:phone":"+1 760 345 2525",
    "sg:postcode":"92211",
    "sg:province":"CA",
    "sg:tags":[
        "course"
    ],
    "wof:name":"Palm Desert Country Club",
    "wof:placetype":"venue"
},
  "geometry": {"coordinates":[-116.31740600000001,33.73831],"type":"Point"}
}