{
  "type": "Feature",
  "properties": {
    "iso:country":"US",
    "sg:address":"3325 Palo Verde Ave Ste 205",
    "sg:city":"Long Beach",
    "sg:classifiers":[
        {
            "category":"Health Services",
            "subcategory":"Doctor",
            "type":"Services"
        }
    ],
    "sg:phone":"+1 562 425 1802",
    "sg:postcode":"90808",
    "sg:province":"CA",
    "sg:tags":[
        "orthopedist"
    ],
    "wof:name":"WEST COAST ORTHOPEDICS",
    "wof:placetype":"venue"
},
  "geometry": {"coordinates":[-118.108005,33.817235],"type":"Point"}
}