{
  "type": "Feature",
  "properties": {
    "iso:country":"US",
    "sg:address":"3448 Villa Ln",
    "sg:city":"Napa",
    "sg:classifiers":[
        {
            "category":"Health Services",
            "subcategory":"Health Practitioner",
            "type":"Services"
        }
    ],
    "sg:phone":"+1 707 251 2000",
    "sg:postcode":"94558",
    "sg:province":"CA",
    "wof:name":"Care Network",
    "wof:placetype":"venue"
},
  "geometry": {"coordinates":[-122.294477,38.325827],"type":"Point"}
}