{
  "type": "Feature",
  "properties": {
    "iso:country":"US",
    "sg:address":"2208 S Hope Pl",
    "sg:city":"Ontario",
    "sg:classifiers":[
        {
            "category":"Professional",
            "subcategory":"Business Services",
            "type":"Services"
        }
    ],
    "sg:phone":"+1 909 947 5026",
    "sg:postcode":"91761",
    "sg:province":"CA",
    "wof:name":"P K Business Svc",
    "wof:placetype":"venue"
},
  "geometry": {"coordinates":[-117.63812299999999,34.033016],"type":"Point"}
}