{
  "type": "Feature",
  "properties": {
    "iso:country":"US",
    "sg:address":"29917 S Chrisman Rd",
    "sg:city":"Tracy",
    "sg:classifiers":[
        {
            "category":"Building & Trades",
            "subcategory":"Landscaping Services",
            "type":"Services"
        }
    ],
    "sg:phone":"+1 209 835 4397",
    "sg:postcode":"95304",
    "sg:province":"CA",
    "sg:tags":[
        "landscape",
        "contractor"
    ],
    "sg:website":"http://www.tracylandscaping.net",
    "wof:name":"Tracy Landscaping",
    "wof:placetype":"venue"
},
  "geometry": {"coordinates":[-121.39799499999999,37.687564],"type":"Point"}
}