{
  "type": "Feature",
  "properties": {
    "iso:country":"US",
    "sg:address":"1405 Lake St",
    "sg:city":"Calistoga",
    "sg:classifiers":[
        {
            "category":"Professional",
            "subcategory":"Computer Services",
            "type":"Services"
        }
    ],
    "sg:phone":"+1 707 942 8653",
    "sg:postcode":"94515",
    "sg:province":"CA",
    "sg:tags":[
        "internet"
    ],
    "wof:name":"Tech Ctr",
    "wof:placetype":"venue"
},
  "geometry": {"coordinates":[-122.58251300000001,38.582521],"type":"Point"}
}