{
  "type": "Feature",
  "properties": {
    "iso:country":"US",
    "sg:address":"2855 Stevens Creek Blvd Suite A157, Valley Fair Mall",
    "sg:city":"San Jose",
    "sg:classifiers":[
        {
            "category":"Restaurant",
            "type":"Food & Drink"
        }
    ],
    "sg:phone":"+1 408 260 0777",
    "sg:postcode":"95109",
    "sg:province":"CA",
    "sg:tags":[
        "sushi",
        "bar",
        "japanese"
    ],
    "wof:name":"Sushi Boat",
    "wof:placetype":"venue"
},
  "geometry": {"coordinates":[-121.944726,37.323438],"type":"Point"}
}