{
  "type": "Feature",
  "properties": {
    "addr:full":"2838 International Blvd Oakland CA 94601",
    "addr:housenumber":"2838",
    "addr:postcode":"94601",
    "addr:street":"International Blvd",
    "iso:country":"US",
    "sg:address":"2838 International Blvd",
    "sg:city":"Oakland",
    "sg:classifiers":[
        {
            "category":"Food & Beverages",
            "subcategory":"Groceries & Convenience Stores",
            "type":"Retail Goods"
        }
    ],
    "sg:phone":"+1 510 536 2638",
    "sg:postcode":"94601",
    "sg:province":"CA",
    "sg:tags":[
        "grocer"
    ],
    "wof:name":"Supermercado Mi Pueblo",
    "wof:placetype":"venue"
},
  "geometry": {"coordinates":[-122.229657,37.77963],"type":"Point"}
}