{
  "type": "Feature",
  "properties": {
    "iso:country":"US",
    "sg:address":"1647 Conway Dr",
    "sg:city":"Escondido",
    "sg:classifiers":[
        {
            "category":"Shopping",
            "subcategory":"Hobbies, Toys, & Games",
            "type":"Retail Goods"
        }
    ],
    "sg:phone":"+1 760 745 2577",
    "sg:postcode":"92027",
    "sg:province":"CA",
    "wof:name":"Crafts Etc",
    "wof:placetype":"venue"
},
  "geometry": {"coordinates":[-117.07452000000001,33.152411],"type":"Point"}
}