{
  "type": "Feature",
  "properties": {
    "iso:country":"US",
    "sg:address":"26055 Bouquet Canyon Rd",
    "sg:city":"Santa Clarita",
    "sg:classifiers":[
        {
            "category":"Retail",
            "subcategory":"Veterinary Services",
            "type":"Services"
        }
    ],
    "sg:phone":"+1 661 259 5288",
    "sg:postcode":"91350",
    "sg:province":"CA",
    "sg:tags":[
        "veterinarian"
    ],
    "sg:website":"www.catdoctorandfriends.com",
    "wof:name":"Thomas Megan DVM",
    "wof:placetype":"venue"
},
  "geometry": {"coordinates":[-118.542473,34.416615],"type":"Point"}
}