{
  "type": "Feature",
  "properties": {
    "addr:full":"653 State St San Diego CA 92101",
    "addr:housenumber":"653",
    "addr:postcode":"92101",
    "addr:street":"State St",
    "iso:country":"US",
    "sg:address":"653 State St",
    "sg:city":"San Diego",
    "sg:classifiers":[
        {
            "category":"Professional",
            "type":"Services"
        }
    ],
    "sg:phone":"+1 619 235 9015",
    "sg:postcode":"92101",
    "sg:province":"CA",
    "sg:tags":[
        "establishment"
    ],
    "wof:name":"Didonato Associates",
    "wof:placetype":"venue"
},
  "geometry": {"coordinates":[-117.166421,32.711971],"type":"Point"}
}