{
  "type": "Feature",
  "properties": {
    "iso:country":"US",
    "sg:address":"10323 Santa Monica Blvd",
    "sg:city":"Los Angeles",
    "sg:classifiers":[
        {
            "category":"Communications",
            "subcategory":"Film & Video Production",
            "type":"Services"
        }
    ],
    "sg:phone":"+1 310 552 1888",
    "sg:postcode":"90025",
    "sg:province":"CA",
    "sg:tags":[
        "motion",
        "picture",
        "casting"
    ],
    "wof:name":"Extra Extra Casting",
    "wof:placetype":"venue"
},
  "geometry": {"coordinates":[-118.421419,34.059461],"type":"Point"}
}