{
  "type": "Feature",
  "properties": {
    "addr:full":"259 Soscol Ave Napa CA 94559",
    "addr:housenumber":"259",
    "addr:postcode":"94559",
    "addr:street":"Soscol Ave",
    "iso:country":"US",
    "sg:address":"259 Soscol Ave",
    "sg:city":"Napa",
    "sg:classifiers":[
        {
            "category":"Utilities",
            "subcategory":"Telephone",
            "type":"Services"
        }
    ],
    "sg:phone":"+1 707 254 0100",
    "sg:postcode":"94559",
    "sg:province":"CA",
    "sg:tags":[
        "communications"
    ],
    "wof:name":"Advanced Telcom Group  Inc",
    "wof:placetype":"venue"
},
  "geometry": {"coordinates":[-122.274524,38.283606],"type":"Point"}
}