{
  "type": "Feature",
  "properties": {
    "iso:country":"US",
    "sg:address":"1119 Colorado Ave",
    "sg:city":"Santa Monica",
    "sg:classifiers":[
        {
            "category":"Real Estate",
            "subcategory":"Architect",
            "type":"Services"
        }
    ],
    "sg:phone":"+1 310 394 9496",
    "sg:postcode":"90401",
    "sg:province":"CA",
    "sg:tags":[
        "building",
        "designer"
    ],
    "wof:name":"Sintesi",
    "wof:placetype":"venue"
},
  "geometry": {"coordinates":[-118.48515,34.019428],"type":"Point"}
}