{
  "type": "Feature",
  "properties": {
    "addr:full":"14624 Lakeshore Dr Clearlake CA 95422",
    "addr:housenumber":"14624",
    "addr:postcode":"95422",
    "addr:street":"Lakeshore Dr",
    "iso:country":"US",
    "sg:address":"14624 Lakeshore Dr",
    "sg:city":"Clearlake",
    "sg:classifiers":[
        {
            "category":"Real Estate",
            "subcategory":"Real Estate Services",
            "type":"Services"
        },
        {
            "category":"Real Estate",
            "subcategory":"Real Estate Agent",
            "type":"Services"
        }
    ],
    "sg:phone":"+1 707 995 8020",
    "sg:postcode":"95422",
    "sg:province":"CA",
    "sg:tags":[
        "buyer",
        "broker"
    ],
    "wof:name":"Greenhouse Realty",
    "wof:placetype":"venue"
},
  "geometry": {"coordinates":[-122.638265,38.950105],"type":"Point"}
}