{
  "type": "Feature",
  "properties": {
    "addr:full":"432 Alvarado St Monterey CA 93940",
    "addr:housenumber":"432",
    "addr:postcode":"93940",
    "addr:street":"Alvarado St",
    "iso:country":"US",
    "sg:address":"432 Alvarado St",
    "sg:city":"Monterey",
    "sg:classifiers":[
        {
            "category":"Shopping",
            "subcategory":"Florist",
            "type":"Retail Goods"
        }
    ],
    "sg:phone":"+1 831 643 1015",
    "sg:postcode":"93940",
    "sg:province":"CA",
    "wof:name":"Swenson & Silacci Flowers",
    "wof:placetype":"venue"
},
  "geometry": {"coordinates":[-121.89501300000001,36.597918],"type":"Point"}
}