{
  "type": "Feature",
  "properties": {
    "iso:country":"US",
    "sg:address":"1235 E D St",
    "sg:city":"Ontario",
    "sg:classifiers":[
        {
            "category":"Wholesale",
            "subcategory":"Chemicals & Plastics",
            "type":"Manufacturing & Wholesale Goods"
        }
    ],
    "sg:phone":"+1 909 648 5961",
    "sg:postcode":"91764",
    "sg:province":"CA",
    "wof:name":"Williams Platinum Shine",
    "wof:placetype":"venue"
},
  "geometry": {"coordinates":[-117.628371,34.067149],"type":"Point"}
}