{
  "type": "Feature",
  "properties": {
    "addr:full":"3357 McGraw Ln Lafayette CA 94549",
    "addr:housenumber":"3357",
    "addr:postcode":"94549",
    "addr:street":"Mcgraw Ln",
    "iso:country":"US",
    "sg:address":"3357 McGraw Ln",
    "sg:city":"Lafayette",
    "sg:classifiers":[
        {
            "category":"Health Services",
            "subcategory":"Doctor",
            "type":"Services"
        }
    ],
    "sg:phone":"+1 925 284 1270",
    "sg:postcode":"94549",
    "sg:province":"CA",
    "wof:name":"Dale M Kaumans DDS PC",
    "wof:placetype":"venue"
},
  "geometry": {"coordinates":[-122.105495,37.915324],"type":"Point"}
}