{
  "type": "Feature",
  "properties": {
    "iso:country":"US",
    "sg:address":"650 S Winchester Blvd",
    "sg:city":"San Jose",
    "sg:classifiers":[
        {
            "category":"Professional",
            "subcategory":"Accounting & Tax Preparation",
            "type":"Services"
        }
    ],
    "sg:phone":"+1 408 244 9197",
    "sg:postcode":"95128",
    "sg:province":"CA",
    "sg:tags":[
        "payroll"
    ],
    "wof:name":"Automatic Business Computing",
    "wof:placetype":"venue"
},
  "geometry": {"coordinates":[-121.950042,37.316035],"type":"Point"}
}