{
  "type": "Feature",
  "properties": {
    "addr:full":"4983 Sonoma Hwy Santa Rosa CA 95409",
    "addr:housenumber":"4983",
    "addr:postcode":"95409",
    "addr:street":"Sonoma Hwy",
    "iso:country":"US",
    "sg:address":"4983 Sonoma Hwy",
    "sg:city":"Santa Rosa",
    "sg:classifiers":[
        {
            "category":"Health Services",
            "subcategory":"Clinic",
            "type":"Services"
        }
    ],
    "sg:phone":"+1 707 538 9442",
    "sg:postcode":"95409",
    "sg:province":"CA",
    "sg:website":"www.ic-network.com",
    "wof:name":"Interstital Cystitis Network",
    "wof:placetype":"venue"
},
  "geometry": {"coordinates":[-122.66267999999999,38.46437],"type":"Point"}
}