{
  "type": "Feature",
  "properties": {
    "addr:full":"180 E Sunnyoaks Ave Campbell CA 95008",
    "addr:housenumber":"180",
    "addr:postcode":"95008",
    "addr:street":"E Sunnyoaks Ave",
    "iso:country":"US",
    "sg:address":"180 E Sunnyoaks Ave",
    "sg:city":"Campbell",
    "sg:classifiers":[
        {
            "category":"Retail",
            "subcategory":"Auto Repair",
            "type":"Services"
        }
    ],
    "sg:phone":"+1 408 866 0928",
    "sg:postcode":"95008",
    "sg:province":"CA",
    "wof:name":"Total Performance",
    "wof:placetype":"venue"
},
  "geometry": {"coordinates":[-121.951708,37.271812],"type":"Point"}
}