{
  "type": "Feature",
  "properties": {
    "iso:country":"US",
    "sg:address":"10423 Hawley Rd",
    "sg:city":"El Cajon",
    "sg:classifiers":[
        {
            "category":"Building & Trades",
            "subcategory":"Construction",
            "type":"Services"
        }
    ],
    "sg:phone":"+1 619 443 4193",
    "sg:postcode":"92021",
    "sg:province":"CA",
    "sg:tags":[
        "concrete",
        "contractor"
    ],
    "wof:name":"All-Crete Concrete Inc",
    "wof:placetype":"venue"
},
  "geometry": {"coordinates":[-116.831139,32.875538],"type":"Point"}
}