{
  "type": "Feature",
  "properties": {
    "iso:country":"US",
    "sg:address":"13641 Magnolia St",
    "sg:city":"Garden Grove",
    "sg:classifiers":[
        {
            "category":"Home & Garden",
            "subcategory":"Household Appliances",
            "type":"Retail Goods"
        },
        {
            "category":"Professional",
            "subcategory":"Computer Services",
            "type":"Services"
        }
    ],
    "sg:phone":"+1 714 867 3301",
    "sg:postcode":"92844",
    "sg:province":"CA",
    "sg:tags":[
        "repair"
    ],
    "sg:website":"phoneservicescenter.tumblr.com/",
    "wof:name":"DVDs N Videos Phone Services Center",
    "wof:placetype":"venue"
},
  "geometry": {"coordinates":[-117.972661,33.764283],"type":"Point"}
}