{
  "type": "Feature",
  "properties": {
    "iso:country":"US",
    "sg:address":"1980 Talshire Ln",
    "sg:city":"Corona",
    "sg:classifiers":[
        {
            "category":"Building & Trades",
            "subcategory":"Electrical",
            "type":"Services"
        }
    ],
    "sg:phone":"+1 951 735 6115",
    "sg:postcode":"92881",
    "sg:province":"CA",
    "sg:tags":[
        "electrician"
    ],
    "wof:name":"Surge Electric Co",
    "wof:placetype":"venue"
},
  "geometry": {"coordinates":[-117.54616900000001,33.854105],"type":"Point"}
}