{
  "type": "Feature",
  "properties": {
    "addr:full":"13110 Spring St Baldwin Park CA 91706",
    "addr:housenumber":"13110",
    "addr:postcode":"91706",
    "addr:street":"Spring St",
    "iso:country":"US",
    "sg:address":"13110 Spring St",
    "sg:city":"Baldwin Park",
    "sg:classifiers":[
        {
            "category":"Wholesale",
            "subcategory":"Drugs",
            "type":"Manufacturing & Wholesale Goods"
        }
    ],
    "sg:phone":"+1 626 962 0070",
    "sg:postcode":"91706",
    "sg:province":"CA",
    "sg:tags":[
        "pharmaceutical",
        "product"
    ],
    "wof:name":"Professional Wholesale",
    "wof:placetype":"venue"
},
  "geometry": {"coordinates":[-117.984116,34.09725],"type":"Point"}
}