{
  "type": "Feature",
  "properties": {
    "iso:country":"US",
    "sg:address":"3526 Bode Dr",
    "sg:city":"South Lake Tahoe",
    "sg:classifiers":[
        {
            "category":"Building & Trades",
            "subcategory":"Construction",
            "type":"Services"
        }
    ],
    "sg:phone":"+1 530 544 6713",
    "sg:postcode":"96150",
    "sg:province":"CA",
    "sg:tags":[
        "excavating",
        "contractor"
    ],
    "wof:name":"O R Coleman Construction Co",
    "wof:placetype":"venue"
},
  "geometry": {"coordinates":[-119.953294,38.928817],"type":"Point"}
}