{
  "type": "Feature",
  "properties": {
    "iso:country":"US",
    "sg:address":"3145 E Olney Ave",
    "sg:city":"Fresno",
    "sg:classifiers":[
        {
            "category":"Food & Beverages",
            "subcategory":"Groceries & Convenience Stores",
            "type":"Retail Goods"
        }
    ],
    "sg:phone":"+1 559 497 5317",
    "sg:postcode":"93725",
    "sg:province":"CA",
    "sg:tags":[
        "grocer"
    ],
    "wof:name":"Tareb Market",
    "wof:placetype":"venue"
},
  "geometry": {"coordinates":[-119.734621,36.681446],"type":"Point"}
}