{
  "type": "Feature",
  "properties": {
    "addr:full":"975 E Green St Ste 201 Pasadena CA 91106",
    "addr:housenumber":"975",
    "addr:postcode":"91106",
    "addr:street":"E Green St Ste 201",
    "iso:country":"US",
    "sg:address":"975 E Green St Ste 201",
    "sg:city":"Pasadena",
    "sg:classifiers":[
        {
            "category":"Real Estate",
            "subcategory":"Real Estate Services",
            "type":"Services"
        }
    ],
    "sg:phone":"+1 626 356 1800",
    "sg:postcode":"91106",
    "sg:province":"CA",
    "sg:tags":[
        "management",
        "property"
    ],
    "wof:name":"Monarch Property Management",
    "wof:placetype":"venue"
},
  "geometry": {"coordinates":[-118.129997,34.1446],"type":"Point"}
}