{
  "type": "Feature",
  "properties": {
    "addr:full":"5100 Birch Street Newport Beach CA 92660",
    "addr:housenumber":"5100",
    "addr:postcode":"92660",
    "addr:street":"Birch Street",
    "iso:country":"US",
    "sg:address":"5100 Birch Street",
    "sg:city":"Newport Beach",
    "sg:classifiers":[
        {
            "category":"Real Estate",
            "subcategory":"Real Estate Services",
            "type":"Services"
        }
    ],
    "sg:phone":"+1 949 223 8820",
    "sg:postcode":"92660",
    "sg:province":"CA",
    "sg:tags":[
        "management",
        "property"
    ],
    "sg:website":"www.barnardventures.com",
    "wof:name":"Barnard Ventures",
    "wof:placetype":"venue"
},
  "geometry": {"coordinates":[-117.858211,33.66577],"type":"Point"}
}