{
  "type": "Feature",
  "properties": {
    "iso:country":"US",
    "sg:address":"671 S Orchard Ave",
    "sg:city":"Ukiah",
    "sg:classifiers":[
        {
            "category":"Government",
            "subcategory":"Post Office",
            "type":"Public Place"
        }
    ],
    "sg:phone":"+1 707 463 1540",
    "sg:postcode":"95482",
    "sg:province":"CA",
    "sg:tags":[
        "postal",
        "us"
    ],
    "wof:name":"US Post Office",
    "wof:placetype":"venue"
},
  "geometry": {"coordinates":[-123.198491,39.145773],"type":"Point"}
}