{
  "type": "Feature",
  "properties": {
    "iso:country":"US",
    "sg:address":"6211 San Pablo Ave",
    "sg:city":"Oakland",
    "sg:classifiers":[
        {
            "category":"Autos & Motor Vehicles",
            "subcategory":"Fuel & Gas Station",
            "type":"Retail Goods"
        }
    ],
    "sg:phone":"+1 510 420 0772",
    "sg:postcode":"94608",
    "sg:province":"CA",
    "sg:website":"www.valero.com/products/pages/ga...",
    "wof:name":"Manjit Valero",
    "wof:placetype":"venue"
},
  "geometry": {"coordinates":[-122.28453500000001,37.844782],"type":"Point"}
}