{
  "type": "Feature",
  "properties": {
    "addr:full":"656 Main St Calpine CA 96124",
    "addr:housenumber":"656",
    "addr:postcode":"96124",
    "addr:street":"Main St",
    "iso:country":"US",
    "sg:address":"656 Main St",
    "sg:city":"Calpine",
    "sg:classifiers":[
        {
            "category":"Professional",
            "subcategory":"Computer Services",
            "type":"Services"
        }
    ],
    "sg:phone":"+1 530 994 9938",
    "sg:postcode":"96124",
    "sg:province":"CA",
    "sg:tags":[
        "consultant",
        "designer"
    ],
    "wof:name":"Kathy Kelley Inc",
    "wof:placetype":"venue"
},
  "geometry": {"coordinates":[-120.449708,39.664902],"type":"Point"}
}