{
  "type": "Feature",
  "properties": {
    "addr:full":"10616 Valley Mall El Monte CA 91731",
    "addr:housenumber":"10616",
    "addr:postcode":"91731",
    "addr:street":"Valley Mall",
    "iso:country":"US",
    "sg:address":"10616 Valley Mall",
    "sg:city":"El Monte",
    "sg:classifiers":[
        {
            "category":"Food & Beverages",
            "subcategory":"Liquor & Beverages",
            "type":"Retail Goods"
        }
    ],
    "sg:phone":"+1 626 442 1408",
    "sg:postcode":"91731",
    "sg:province":"CA",
    "sg:tags":[
        "beer",
        "spirit",
        "wine"
    ],
    "wof:name":"El Monte Liquor & Deli",
    "wof:placetype":"venue"
},
  "geometry": {"coordinates":[-118.041,34.075699],"type":"Point"}
}