{
  "type": "Feature",
  "properties": {
    "iso:country":"US",
    "sg:address":"1546 Bonanza St",
    "sg:city":"Walnut Creek",
    "sg:classifiers":[
        {
            "category":"Restaurant",
            "type":"Food & Drink"
        }
    ],
    "sg:menulink":"http://www.allmenus.com/ca/central-contra-costa/58689-koreana-kitchen/menu/",
    "sg:phone":"+1 925 938 5959",
    "sg:postcode":"94596",
    "sg:province":"CA",
    "sg:tags":[
        "korean",
        "asian"
    ],
    "wof:name":"Koreana Kitchen",
    "wof:placetype":"venue"
},
  "geometry": {"coordinates":[-122.06190100000001,37.899742],"type":"Point"}
}