{
  "type": "Feature",
  "properties": {
    "addr:full":"515 E 6th St Los Angeles CA 90021",
    "addr:housenumber":"515",
    "addr:postcode":"90021",
    "addr:street":"E 6Th St",
    "iso:country":"US",
    "sg:address":"515 E 6th St",
    "sg:city":"Los Angeles",
    "sg:classifiers":[
        {
            "category":"Health Services",
            "subcategory":"Clinic",
            "type":"Services"
        }
    ],
    "sg:phone":"+1 213 622 2639",
    "sg:postcode":"90021",
    "sg:province":"CA",
    "sg:tags":[
        "specialty",
        "outpatient"
    ],
    "wof:name":"J W C H Weingart Clinic",
    "wof:placetype":"venue"
},
  "geometry": {"coordinates":[-118.24442000000001,34.041852],"type":"Point"}
}