{
  "type": "Feature",
  "properties": {
    "addr:full":"1 Washington St Daly City CA 94015",
    "addr:housenumber":"1",
    "addr:postcode":"94015",
    "addr:street":"Washington St",
    "iso:country":"US",
    "sg:address":"1 Washington St",
    "sg:city":"Daly City",
    "sg:classifiers":[
        {
            "category":"Banks & Credit Unions",
            "subcategory":"Bank",
            "type":"Services"
        }
    ],
    "sg:phone":"+1 650 757 8600",
    "sg:postcode":"94015",
    "sg:province":"CA",
    "sg:tags":[
        "loan"
    ],
    "wof:name":"ABS Bancorp Inc",
    "wof:placetype":"venue"
},
  "geometry": {"coordinates":[-122.468688,37.687908],"type":"Point"}
}