{
  "type": "Feature",
  "properties": {
    "addr:full":"5000 Cliff Dr Capitola CA 95010",
    "addr:housenumber":"5000",
    "addr:postcode":"95010",
    "addr:street":"Cliff Dr",
    "iso:country":"US",
    "sg:address":"5000 Cliff Dr",
    "sg:city":"Capitola",
    "sg:classifiers":[
        {
            "category":"Travel",
            "subcategory":"Hotels & Motels",
            "type":"Entertainment"
        }
    ],
    "sg:phone":"+1 831 476 0505",
    "sg:postcode":"95010",
    "sg:province":"CA",
    "wof:name":"Harbor Lights Motel",
    "wof:placetype":"venue"
},
  "geometry": {"coordinates":[-121.954002,36.971401],"type":"Point"}
}