{
  "type": "Feature",
  "properties": {
    "iso:country":"US",
    "sg:address":"45 Ericson Ct",
    "sg:city":"Arcata",
    "sg:classifiers":[
        {
            "category":"Manufacturing",
            "subcategory":"Glass & Minerals",
            "type":"Manufacturing & Wholesale Goods"
        }
    ],
    "sg:phone":"+1 707 825 7500",
    "sg:postcode":"95521",
    "sg:province":"CA",
    "sg:tags":[
        "tile"
    ],
    "sg:website":"www.fireandlight.com",
    "wof:name":"Fire & Light Originals",
    "wof:placetype":"venue"
},
  "geometry": {"coordinates":[-124.069597,40.903061],"type":"Point"}
}