{
  "type": "Feature",
  "properties": {
    "addr:full":"670 S Grand Ave Glendora CA 91740",
    "addr:housenumber":"670",
    "addr:postcode":"91740",
    "addr:street":"S Grand Ave",
    "iso:country":"US",
    "sg:address":"670 S Grand Ave",
    "sg:city":"Glendora",
    "sg:classifiers":[
        {
            "category":"Restaurant",
            "type":"Food & Drink"
        }
    ],
    "sg:phone":"+1 626 852 9283",
    "sg:postcode":"91740",
    "sg:province":"CA",
    "wof:name":"Home Kitchen",
    "wof:placetype":"venue"
},
  "geometry": {"coordinates":[-117.872495,34.128109],"type":"Point"}
}