{
  "type": "Feature",
  "properties": {
    "addr:full":"290 Edgewood Dr. Pacifica, Ca 94044",
    "wof:categories":[
        "education_and_religion:education=school"
    ],
    "wof:name":"Fairmont Elementary School",
    "wof:placetype":"venue"
},
  "geometry": {"coordinates":[-122.48140588174397,37.66119790100014],"type":"Point"}
}