{
  "type": "Feature",
  "properties": {
    "iso:country":"US",
    "sg:address":"533 C St",
    "sg:city":"Eureka",
    "sg:classifiers":[
        {
            "category":"Government",
            "subcategory":"Fire Station",
            "type":"Public Place"
        }
    ],
    "sg:phone":"+1 707 441 4000",
    "sg:postcode":"95501",
    "sg:province":"CA",
    "sg:tags":[
        "department",
        "protection"
    ],
    "wof:name":"Eureka Fire Department",
    "wof:placetype":"venue"
},
  "geometry": {"coordinates":[-124.16902,40.801207],"type":"Point"}
}