{
  "type": "Feature",
  "properties": {
    "iso:country":"US",
    "sg:address":"1373 S Bascom Ave",
    "sg:city":"San Jose",
    "sg:classifiers":[
        {
            "category":"Banks & Credit Unions",
            "subcategory":"Bank",
            "type":"Services"
        }
    ],
    "sg:phone":"+1 408 283 7300",
    "sg:postcode":"95128",
    "sg:province":"CA",
    "sg:tags":[
        "loan",
        "real estate"
    ],
    "wof:name":"Internet Mortgage Solutions",
    "wof:placetype":"venue"
},
  "geometry": {"coordinates":[-121.931769,37.300044],"type":"Point"}
}