{
  "type": "Feature",
  "properties": {
    "iso:country":"US",
    "sg:address":"2141 Palomar Airport Rd Ste 320",
    "sg:city":"Carlsbad",
    "sg:classifiers":[
        {
            "category":"Professional",
            "subcategory":"Lawyer & Legal Services",
            "type":"Services"
        }
    ],
    "sg:phone":"+1 760 651 0142",
    "sg:postcode":"92011",
    "sg:province":"CA",
    "wof:name":"InterContinental IP Law",
    "wof:placetype":"venue"
},
  "geometry": {"coordinates":[-117.275233,33.124141],"type":"Point"}
}