{
  "type": "Feature",
  "properties": {
    "addr:full":"2300 S Macarthur Dr Tracy CA 95376",
    "addr:housenumber":"2300",
    "addr:postcode":"95376",
    "addr:street":"S Macarthur Dr",
    "iso:country":"US",
    "sg:address":"2300 S Macarthur Dr",
    "sg:city":"Tracy",
    "sg:classifiers":[
        {
            "category":"Building & Trades",
            "subcategory":"Construction",
            "type":"Services"
        }
    ],
    "sg:phone":"+1 209 839 0358",
    "sg:postcode":"95376",
    "sg:province":"CA",
    "sg:tags":[
        "tile",
        "dealer"
    ],
    "wof:name":"Divine Tiling & Sealing",
    "wof:placetype":"venue"
},
  "geometry": {"coordinates":[-121.416377,37.725076],"type":"Point"}
}