{
  "type": "Feature",
  "properties": {
    "addr:full":"14114 Bronte Dr Whittier CA 90602",
    "addr:housenumber":"14114",
    "addr:postcode":"90602",
    "addr:street":"Bronte Dr",
    "iso:country":"US",
    "sg:address":"14114 Bronte Dr",
    "sg:city":"Whittier",
    "sg:classifiers":[
        {
            "category":"Manufacturing",
            "subcategory":"Rubber & Plastics",
            "type":"Manufacturing & Wholesale Goods"
        }
    ],
    "sg:phone":"+1 562 692 4865",
    "sg:postcode":"90602",
    "sg:province":"CA",
    "sg:tags":[
        "pressure",
        "laminate"
    ],
    "wof:name":"A L Blair Inc",
    "wof:placetype":"venue"
},
  "geometry": {"coordinates":[-118.01825700000001,33.971608],"type":"Point"}
}