{
  "type": "Feature",
  "properties": {
    "iso:country":"US",
    "sg:address":"1 Garden St",
    "sg:city":"Santa Barbara",
    "sg:classifiers":[
        {
            "category":"Organizations",
            "subcategory":"Professional Association",
            "type":"Services"
        }
    ],
    "sg:phone":"+1 805 965 3021",
    "sg:postcode":"93101",
    "sg:province":"CA",
    "sg:tags":[
        "chambers",
        "commerce"
    ],
    "wof:name":"Santa Barbara Chamber-Commerce",
    "wof:placetype":"venue"
},
  "geometry": {"coordinates":[-119.687224,34.415234],"type":"Point"}
}