{
  "type": "Feature",
  "properties": {
    "iso:country":"US",
    "sg:address":"1741 Esmond Ave",
    "sg:city":"Richmond",
    "sg:classifiers":[
        {
            "category":"Professional",
            "subcategory":"Business Services",
            "type":"Services"
        }
    ],
    "sg:phone":"+1 510 234 7743",
    "sg:postcode":"94801",
    "sg:province":"CA",
    "sg:tags":[
        "event"
    ],
    "wof:name":"Event Extraordinaire",
    "wof:placetype":"venue"
},
  "geometry": {"coordinates":[-122.352711,37.945346],"type":"Point"}
}