{
  "type": "Feature",
  "properties": {
    "addr:full":"455 N Raymond Ave Pasadena CA 91103",
    "addr:housenumber":"455",
    "addr:postcode":"91103",
    "addr:street":"N Raymond Ave",
    "iso:country":"US",
    "sg:address":"455 N Raymond Ave",
    "sg:city":"Pasadena",
    "sg:classifiers":[
        {
            "category":"Real Estate",
            "subcategory":"Real Estate Operator",
            "type":"Services"
        }
    ],
    "sg:phone":"+1 626 793 8030",
    "sg:postcode":"91103",
    "sg:province":"CA",
    "sg:tags":[
        "apartment"
    ],
    "wof:name":"Villa Raymond",
    "wof:placetype":"venue"
},
  "geometry": {"coordinates":[-118.148968,34.153941],"type":"Point"}
}