{
  "type": "Feature",
  "properties": {
    "addr:full":"1200 Howard Ave Burlingame CA 94010",
    "addr:housenumber":"1200",
    "addr:postcode":"94010",
    "addr:street":"Howard Ave",
    "iso:country":"US",
    "sg:address":"1200 Howard Ave",
    "sg:city":"Burlingame",
    "sg:classifiers":[
        {
            "category":"Professional",
            "type":"Services"
        },
        {
            "category":"Real Estate",
            "subcategory":"Real Estate Agent",
            "type":"Services"
        }
    ],
    "sg:phone":"+1 650 347 4888",
    "sg:postcode":"94010",
    "sg:province":"CA",
    "sg:tags":[
        "establishment"
    ],
    "wof:name":"GMAC Premier Properties",
    "wof:placetype":"venue"
},
  "geometry": {"coordinates":[-122.345693,37.577242],"type":"Point"}
}