{
  "type": "Feature",
  "properties": {
    "iso:country":"US",
    "sg:address":"3908 Pso de Olivos",
    "sg:city":"Fallbrook",
    "sg:classifiers":[
        {
            "category":"Building & Trades",
            "subcategory":"Construction",
            "type":"Services"
        }
    ],
    "sg:phone":"+1 760 731 1148",
    "sg:postcode":"92028",
    "sg:province":"CA",
    "sg:tags":[
        "general",
        "contractor"
    ],
    "wof:name":"Eric Puhl Construction",
    "wof:placetype":"venue"
},
  "geometry": {"coordinates":[-117.240362,33.323895],"type":"Point"}
}