{
  "type": "Feature",
  "properties": {
    "addr:full":"800 South B St Ste 200 San Mateo CA 94401",
    "addr:housenumber":"800",
    "addr:postcode":"94401",
    "addr:street":"South B St Ste 200",
    "iso:country":"US",
    "sg:address":"800 South B St Ste 200",
    "sg:city":"San Mateo",
    "sg:classifiers":[
        {
            "category":"Health Services",
            "subcategory":"Dentist",
            "type":"Services"
        }
    ],
    "sg:phone":"+1 650 343 0884",
    "sg:postcode":"94401",
    "sg:province":"CA",
    "sg:tags":[
        "pediatric"
    ],
    "sg:website":"www.nazarethplazadentalgroup.com",
    "wof:name":"Lipumano-Picazo, DDR - Nazareth Plaza Dental Group",
    "wof:placetype":"venue"
},
  "geometry": {"coordinates":[-122.31890799999999,37.561667],"type":"Point"}
}