{
  "type": "Feature",
  "properties": {
    "addr:full":"40125 Los Alamos Rd Murrieta CA 92562",
    "addr:housenumber":"40125",
    "addr:postcode":"92562",
    "addr:street":"Los Alamos Rd",
    "iso:country":"US",
    "sg:address":"40125 Los Alamos Rd",
    "sg:city":"Murrieta",
    "sg:classifiers":[
        {
            "category":"Real Estate",
            "subcategory":"Real Estate Operator",
            "type":"Services"
        }
    ],
    "sg:phone":"+1 951 677 7745",
    "sg:postcode":"92562",
    "sg:province":"CA",
    "sg:tags":[
        "apartment"
    ],
    "wof:name":"Rancho Las Brisas Apartments",
    "wof:placetype":"venue"
},
  "geometry": {"coordinates":[-117.18503699999999,33.569433],"type":"Point"}
}