{
  "type": "Feature",
  "properties": {
    "addr:full":"1430 E Cooley Dr Colton CA 92324",
    "addr:housenumber":"1430",
    "addr:postcode":"92324",
    "addr:street":"E Cooley Dr",
    "iso:country":"US",
    "sg:address":"1430 E Cooley Dr",
    "sg:city":"Colton",
    "sg:classifiers":[
        {
            "category":"Social Services",
            "type":"Services"
        }
    ],
    "sg:phone":"+1 909 433 0767",
    "sg:postcode":"92324",
    "sg:province":"CA",
    "sg:tags":[
        "counselor",
        "marriage",
        "family"
    ],
    "wof:name":"Melody Golden",
    "wof:placetype":"venue"
},
  "geometry": {"coordinates":[-117.30050900000001,34.05991],"type":"Point"}
}