{
  "type": "Feature",
  "properties": {
    "iso:country":"US",
    "sg:address":"1725 S Bascom Ave",
    "sg:city":"Campbell",
    "sg:classifiers":[
        {
            "category":"Professional",
            "type":"Services"
        }
    ],
    "sg:phone":"+1 408 369 8122",
    "sg:postcode":"95008",
    "sg:province":"CA",
    "wof:name":"John Molina",
    "wof:placetype":"venue"
},
  "geometry": {"coordinates":[-121.931845,37.292275],"type":"Point"}
}