{
  "type": "Feature",
  "properties": {
    "addr:full":"425 N Brand Blvd Glendale CA 91203",
    "addr:housenumber":"425",
    "addr:postcode":"91203",
    "addr:street":"N Brand Blvd",
    "iso:country":"US",
    "sg:address":"425 N Brand Blvd",
    "sg:city":"Glendale",
    "sg:classifiers":[
        {
            "category":"Home & Garden",
            "subcategory":"Furniture",
            "type":"Retail Goods"
        }
    ],
    "sg:phone":"+1 818 550 9720",
    "sg:postcode":"91203",
    "sg:province":"CA",
    "sg:tags":[
        "store"
    ],
    "wof:name":"Legacy Furniture",
    "wof:placetype":"venue"
},
  "geometry": {"coordinates":[-118.254997,34.1525],"type":"Point"}
}