{
  "type": "Feature",
  "properties": {
    "addr:full":"8805 Murray Dr La Mesa CA 91942",
    "addr:housenumber":"8805",
    "addr:postcode":"91942",
    "addr:street":"Murray Dr",
    "iso:country":"US",
    "sg:address":"8805 Murray Dr",
    "sg:city":"La Mesa",
    "sg:classifiers":[
        {
            "category":"Shopping",
            "subcategory":"Stationery & Office Supplies",
            "type":"Retail Goods"
        },
        {
            "category":"Professional",
            "subcategory":"Printing & Photocopies",
            "type":"Services"
        }
    ],
    "sg:phone":"+1 619 469 0734",
    "sg:postcode":"91942",
    "sg:province":"CA",
    "sg:tags":[
        "equipment"
    ],
    "wof:name":"Staples the Office Superstore",
    "wof:placetype":"venue"
},
  "geometry": {"coordinates":[-117.008003,32.776501],"type":"Point"}
}