{
  "type": "Feature",
  "properties": {
    "addr:full":"3451 Corvina Dr Rancho Cordova CA 95670",
    "addr:housenumber":"3451",
    "addr:postcode":"95670",
    "addr:street":"Corvina Dr",
    "iso:country":"US",
    "sg:address":"3451 Corvina Dr",
    "sg:city":"Rancho Cordova",
    "sg:classifiers":[
        {
            "category":"Real Estate",
            "subcategory":"Developer",
            "type":"Services"
        }
    ],
    "sg:phone":"+1 916 853 7431",
    "sg:postcode":"95670",
    "sg:province":"CA",
    "wof:name":"Geometra Planning & Permitting",
    "wof:placetype":"venue"
},
  "geometry": {"coordinates":[-121.275502,38.577029],"type":"Point"}
}