{
  "type": "Feature",
  "properties": {
    "iso:country":"US",
    "sg:address":"12806 Mayflower Dr",
    "sg:city":"Nevada City",
    "sg:classifiers":[
        {
            "category":"Building & Trades",
            "subcategory":"Cleaning & Sanitation",
            "type":"Services"
        }
    ],
    "sg:phone":"+1 530 274 8944",
    "sg:postcode":"95959",
    "sg:province":"CA",
    "sg:tags":[
        "house"
    ],
    "wof:name":"All Seasons Cleaning",
    "wof:placetype":"venue"
},
  "geometry": {"coordinates":[-120.985176,39.241517],"type":"Point"}
}