{
  "type": "Feature",
  "properties": {
    "addr:full":"9332 Tech Ctr Dr Sacramento CA 95826",
    "addr:housenumber":"9332",
    "addr:postcode":"95826",
    "addr:street":"Tech Ctr Dr",
    "iso:country":"US",
    "sg:address":"9332 Tech Ctr Dr",
    "sg:city":"Sacramento",
    "sg:classifiers":[
        {
            "category":"Communications",
            "subcategory":"Film & Video Production",
            "type":"Services"
        }
    ],
    "sg:phone":"+1 916 438 5400",
    "sg:postcode":"95826",
    "sg:province":"CA",
    "sg:tags":[
        "video/film"
    ],
    "sg:website":"www.andersonav.com/",
    "wof:name":"Anderson Audio Visual",
    "wof:placetype":"venue"
},
  "geometry": {"coordinates":[-121.350854,38.562639],"type":"Point"}
}