{
  "type": "Feature",
  "properties": {
    "addr:full":"13782 de Foe Ave Sylmar CA 91342",
    "addr:postcode":"13782;91342",
    "addr:street":"De Foe Ave",
    "iso:country":"US",
    "sg:address":"13782 de Foe Ave",
    "sg:city":"Sylmar",
    "sg:classifiers":[
        {
            "category":"Shopping",
            "subcategory":"Computers & Home Electronics",
            "type":"Retail Goods"
        }
    ],
    "sg:phone":"+1 818 367 3875",
    "sg:postcode":"91342",
    "sg:province":"CA",
    "sg:tags":[
        "equipment",
        "dealer"
    ],
    "wof:name":"K M Enterprises",
    "wof:placetype":"venue"
},
  "geometry": {"coordinates":[-118.47152,34.320488],"type":"Point"}
}