{
  "type": "Feature",
  "properties": {
    "iso:country":"US",
    "sg:address":"190 Belgrave Avenue",
    "sg:city":"San Francisco",
    "sg:classifiers":[
        {
            "category":"Real Estate",
            "subcategory":"Architect",
            "type":"Services"
        }
    ],
    "sg:phone":"+1 415 661 5025",
    "sg:postcode":"94117",
    "sg:province":"CA",
    "wof:name":"Belgrave House",
    "wof:placetype":"venue"
},
  "geometry": {"coordinates":[-122.450996,37.759602],"type":"Point"}
}