{
  "type": "Feature",
  "properties": {
    "iso:country":"US",
    "sg:address":"170 Diana St",
    "sg:city":"Encinitas",
    "sg:classifiers":[
        {
            "category":"Personal",
            "subcategory":"Barber",
            "type":"Services"
        }
    ],
    "sg:phone":"+1 760 942 8974",
    "sg:postcode":"92024",
    "sg:province":"CA",
    "wof:name":"Buzz",
    "wof:placetype":"venue"
},
  "geometry": {"coordinates":[-117.304609,33.066895],"type":"Point"}
}