{
  "type": "Feature",
  "properties": {
    "iso:country":"US",
    "sg:address":"3760 N 1st St",
    "sg:city":"Fresno",
    "sg:classifiers":[
        {
            "category":"Professional",
            "type":"Services"
        }
    ],
    "sg:phone":"+1 559 224 7668",
    "sg:postcode":"93726",
    "sg:province":"CA",
    "wof:name":"Roots Pharmaceuticals Inc",
    "wof:placetype":"venue"
},
  "geometry": {"coordinates":[-119.772373,36.785396],"type":"Point"}
}