{
  "type": "Feature",
  "properties": {
    "addr:full":"7744 Fay Avenue La Jolla CA 92037",
    "addr:housenumber":"7744",
    "addr:postcode":"92037",
    "addr:street":"Fay Avenue",
    "iso:country":"US",
    "sg:address":"7744 Fay Avenue",
    "sg:city":"La Jolla",
    "sg:classifiers":[
        {
            "category":"Personal",
            "subcategory":"Beauty Salon",
            "type":"Services"
        }
    ],
    "sg:phone":"+1 858 551 1052",
    "sg:postcode":"92037",
    "sg:province":"CA",
    "sg:tags":[
        "hair"
    ],
    "wof:name":"Salon On Fay",
    "wof:placetype":"venue"
},
  "geometry": {"coordinates":[-117.275338,32.844048],"type":"Point"}
}