{
  "type": "Feature",
  "properties": {
    "iso:country":"US",
    "sg:address":"15 California St",
    "sg:city":"Stockton",
    "sg:classifiers":[
        {
            "category":"Restaurant",
            "type":"Food & Drink"
        }
    ],
    "sg:phone":"+1 209 941 0449",
    "sg:postcode":"95202",
    "sg:province":"CA",
    "wof:name":"Downtown Cafe",
    "wof:placetype":"venue"
},
  "geometry": {"coordinates":[-121.284892,37.954457],"type":"Point"}
}