{
  "type": "Feature",
  "properties": {
    "iso:country":"US",
    "sg:address":"42148 4th St E",
    "sg:city":"Lancaster",
    "sg:classifiers":[
        {
            "category":"Building & Trades",
            "subcategory":"Construction",
            "type":"Services"
        }
    ],
    "sg:phone":"+1 661 942 2169",
    "sg:postcode":"93535",
    "sg:province":"CA",
    "sg:tags":[
        "pipe",
        "line",
        "contractor"
    ],
    "wof:name":"High Sierra General Engrng Inc",
    "wof:placetype":"venue"
},
  "geometry": {"coordinates":[-118.123161,34.648231],"type":"Point"}
}