{
  "type": "Feature",
  "properties": {
    "addr:full":"1104 Scenic Dr Modesto CA 95350",
    "addr:housenumber":"1104",
    "addr:postcode":"ca 95350",
    "addr:street":"Scenic Dr",
    "iso:country":"US",
    "sg:address":"1104 Scenic Dr",
    "sg:city":"Modesto",
    "sg:classifiers":[
        {
            "category":"Professional",
            "type":"Services"
        }
    ],
    "sg:phone":"+1 209 522 8060",
    "sg:postcode":"95350",
    "sg:province":"CA",
    "wof:name":"Your Coordinator",
    "wof:placetype":"venue"
},
  "geometry": {"coordinates":[-120.977779,37.648238],"type":"Point"}
}