{
  "type": "Feature",
  "properties": {
    "addr:full":"3 Harvest Ct Yountville CA 94599",
    "addr:housenumber":"3",
    "addr:postcode":"ca 94599",
    "addr:street":"Harvest Ct",
    "iso:country":"US",
    "sg:address":"3 Harvest Ct",
    "sg:city":"Yountville",
    "sg:classifiers":[
        {
            "category":"Real Estate",
            "subcategory":"Real Estate Services",
            "type":"Services"
        },
        {
            "category":"Real Estate",
            "subcategory":"Real Estate Agent",
            "type":"Services"
        }
    ],
    "sg:phone":"+1 707 944 0888",
    "sg:postcode":"94599",
    "sg:province":"CA",
    "sg:tags":[
        "buyer",
        "management",
        "broker"
    ],
    "wof:name":"Morgan Lanes Real Estate",
    "wof:placetype":"venue"
},
  "geometry": {"coordinates":[-122.357156,38.404222],"type":"Point"}
}