{
  "type": "Feature",
  "properties": {
    "addr:full":"16311 Ventura Blvd Encino CA 91436",
    "addr:housenumber":"16311",
    "addr:postcode":"91436",
    "addr:street":"Ventura Blvd",
    "iso:country":"US",
    "sg:address":"16311 Ventura Blvd",
    "sg:city":"Encino",
    "sg:classifiers":[
        {
            "category":"Personal",
            "subcategory":"Hair Removal",
            "type":"Services"
        }
    ],
    "sg:phone":"+1 818 907 6662",
    "sg:postcode":"91436",
    "sg:province":"CA",
    "sg:tags":[
        "removing"
    ],
    "sg:website":"www.lasersmooth.com",
    "wof:name":"Lasersmooth Medical Assoc Inc",
    "wof:placetype":"venue"
},
  "geometry": {"coordinates":[-118.489954,34.157308],"type":"Point"}
}