{
  "type": "Feature",
  "properties": {
    "addr:full":"1530 S Pearl St Fresno CA 93721",
    "addr:housenumber":"1530",
    "addr:postcode":"93721",
    "addr:street":"S Pearl St",
    "iso:country":"US",
    "sg:address":"1530 S Pearl St",
    "sg:city":"Fresno",
    "sg:classifiers":[
        {
            "category":"Wholesale",
            "subcategory":"Auto Parts",
            "type":"Manufacturing & Wholesale Goods"
        }
    ],
    "sg:phone":"+1 559 268 6648",
    "sg:postcode":"93721",
    "sg:province":"CA",
    "sg:tags":[
        "automobile",
        "supply"
    ],
    "wof:name":"Al's Distributing Inc",
    "wof:placetype":"venue"
},
  "geometry": {"coordinates":[-119.774991,36.727191],"type":"Point"}
}