{
  "type": "Feature",
  "properties": {
    "addr:full":"5015 Foothill Blvd Oakland CA 94601",
    "addr:housenumber":"5015",
    "addr:postcode":"94601",
    "addr:street":"Foothill Blvd",
    "iso:country":"US",
    "sg:address":"5015 Foothill Blvd",
    "sg:city":"Oakland",
    "sg:classifiers":[
        {
            "category":"Shopping",
            "subcategory":"Tobacco",
            "type":"Retail Goods"
        }
    ],
    "sg:phone":"+1 510 535 0716",
    "sg:postcode":"94601",
    "sg:province":"CA",
    "sg:tags":[
        "cigarette",
        "cigar",
        "dealer"
    ],
    "wof:name":"Pete's Smoke Spot",
    "wof:placetype":"venue"
},
  "geometry": {"coordinates":[-122.205253,37.7726],"type":"Point"}
}