{
  "type": "Feature",
  "properties": {
    "addr:full":"1720 Washington Ave Santa Monica CA 90403",
    "addr:housenumber":"1720",
    "addr:postcode":"90403",
    "addr:street":"Washington Ave",
    "iso:country":"US",
    "sg:address":"1720 Washington Ave",
    "sg:city":"Santa Monica",
    "sg:classifiers":[
        {
            "category":"Real Estate",
            "subcategory":"Real Estate Agent",
            "type":"Services"
        }
    ],
    "sg:phone":"+1 310 829 7200",
    "sg:postcode":"90403",
    "sg:province":"CA",
    "wof:name":"Century 21 All Moves Westside",
    "wof:placetype":"venue"
},
  "geometry": {"coordinates":[-118.48885199999999,34.031983],"type":"Point"}
}