{
  "type": "Feature",
  "properties": {
    "addr:full":"325 20th Pl Manhattan Beach CA 90266",
    "addr:housenumber":"325",
    "addr:postcode":"90266",
    "addr:street":"20Th Pl",
    "iso:country":"US",
    "sg:address":"325 20th Pl",
    "sg:city":"Manhattan Beach",
    "sg:classifiers":[
        {
            "category":"Professional",
            "subcategory":"Accounting & Tax Preparation",
            "type":"Services"
        }
    ],
    "sg:phone":"+1 310 796 4518",
    "sg:postcode":"90266",
    "sg:province":"CA",
    "sg:tags":[
        "billing"
    ],
    "wof:name":"Wagner Billing Svc",
    "wof:placetype":"venue"
},
  "geometry": {"coordinates":[-118.412288,33.891166],"type":"Point"}
}