{
  "type": "Feature",
  "properties": {
    "iso:country":"US",
    "sg:address":"8817 Painter Ave",
    "sg:city":"Whittier",
    "sg:classifiers":[
        {
            "category":"Social Services",
            "subcategory":"Adult Care",
            "type":"Services"
        }
    ],
    "sg:phone":"+1 562 789 4138",
    "sg:postcode":"90602",
    "sg:province":"CA",
    "sg:tags":[
        "home",
        "group"
    ],
    "wof:name":"Pen Home",
    "wof:placetype":"venue"
},
  "geometry": {"coordinates":[-118.038871,33.957284],"type":"Point"}
}