{
  "type": "Feature",
  "properties": {
    "iso:country":"US",
    "sg:address":"5800 Auburn Blvd",
    "sg:city":"Sacramento",
    "sg:classifiers":[
        {
            "category":"Building & Trades",
            "subcategory":"Landscaping Services",
            "type":"Services"
        }
    ],
    "sg:phone":"+1 916 338 3421",
    "sg:postcode":"95841",
    "sg:province":"CA",
    "sg:tags":[
        "landscape",
        "contractor"
    ],
    "wof:name":"Landscape Specialties",
    "wof:placetype":"venue"
},
  "geometry": {"coordinates":[-121.328533,38.672841],"type":"Point"}
}