{
  "type": "Feature",
  "properties": {
    "iso:country":"US",
    "sg:address":"696 E Colorado Blvd",
    "sg:city":"Pasadena",
    "sg:classifiers":[
        {
            "category":"Shopping",
            "subcategory":"Used Merchandise",
            "type":"Retail Goods"
        }
    ],
    "sg:phone":"+1 626 795 0818",
    "sg:postcode":"91106",
    "sg:province":"CA",
    "sg:tags":[
        "book",
        "rare",
        "dealer"
    ],
    "wof:name":"Book Alley Too",
    "wof:placetype":"venue"
},
  "geometry": {"coordinates":[-118.135904,34.1458],"type":"Point"}
}