{
  "type": "Feature",
  "properties": {
    "addr:full":"60 Mission Dr Pleasanton CA 94566",
    "addr:housenumber":"60",
    "addr:postcode":"94566",
    "addr:street":"Mission Dr",
    "iso:country":"US",
    "sg:address":"60 Mission Dr",
    "sg:city":"Pleasanton",
    "sg:classifiers":[
        {
            "category":"Manufacturing",
            "subcategory":"Tools & Machinery",
            "type":"Manufacturing & Wholesale Goods"
        }
    ],
    "sg:phone":"+1 925 516 5700",
    "sg:postcode":"94566",
    "sg:province":"CA",
    "sg:tags":[
        "equipment",
        "electric"
    ],
    "wof:name":"Davelaar Sales & Engineering",
    "wof:placetype":"venue"
},
  "geometry": {"coordinates":[-121.878203,37.652475],"type":"Point"}
}