{
  "type": "Feature",
  "properties": {
    "addr:full":"5 Aurora Aliso Viejo CA 92656",
    "addr:housenumber":"5",
    "addr:postcode":"92656",
    "addr:street":"Aurora",
    "iso:country":"US",
    "sg:address":"5 Aurora",
    "sg:city":"Aliso Viejo",
    "sg:classifiers":[
        {
            "category":"Travel",
            "subcategory":"Hotels & Motels",
            "type":"Entertainment"
        }
    ],
    "sg:phone":"+1 949 360 1081",
    "sg:postcode":"92656",
    "sg:province":"CA",
    "sg:tags":[
        "operation"
    ],
    "wof:name":"Sea Crest Pool & Spa",
    "wof:placetype":"venue"
},
  "geometry": {"coordinates":[-117.73640899999999,33.5755],"type":"Point"}
}