{
  "type": "Feature",
  "properties": {
    "addr:full":"545 Contra Costa Blvd Pleasant Hill CA 94523",
    "addr:housenumber":"545",
    "addr:postcode":"94523",
    "addr:street":"Contra Costa Blvd",
    "iso:country":"US",
    "sg:address":"545 Contra Costa Blvd",
    "sg:city":"Pleasant Hill",
    "sg:classifiers":[
        {
            "category":"Shopping",
            "subcategory":"Gifts & Souvenirs",
            "type":"Retail Goods"
        }
    ],
    "sg:phone":"+1 925 685 3500",
    "sg:postcode":"94523",
    "sg:province":"CA",
    "sg:tags":[
        "party",
        "supply"
    ],
    "sg:website":"www.partyamerica.com",
    "wof:name":"Party America",
    "wof:placetype":"venue"
},
  "geometry": {"coordinates":[-122.06658,37.97933],"type":"Point"}
}