{
  "type": "Feature",
  "properties": {
    "iso:country":"US",
    "sg:address":"8225 Alondra Blvd",
    "sg:city":"Paramount",
    "sg:classifiers":[
        {
            "category":"Shopping",
            "subcategory":"Clothing, Apparel, & Fashions",
            "type":"Retail Goods"
        }
    ],
    "sg:phone":"+1 562 259 9982",
    "sg:postcode":"90723",
    "sg:province":"CA",
    "sg:tags":[
        "lingerie"
    ],
    "wof:name":"Ardyss",
    "wof:placetype":"venue"
},
  "geometry": {"coordinates":[-118.155998,33.8894],"type":"Point"}
}