{
  "type": "Feature",
  "properties": {
    "addr:full":"1825 4th St San Rafael CA 94901",
    "addr:housenumber":"1825",
    "addr:postcode":"94901",
    "addr:street":"4Th St",
    "iso:country":"US",
    "sg:address":"1825 4th St",
    "sg:city":"San Rafael",
    "sg:classifiers":[
        {
            "category":"Restaurant",
            "type":"Food & Drink"
        }
    ],
    "sg:menulink":"http://www.allmenus.com/ca/san-rafael/97105-ihop/menu/",
    "sg:phone":"+1 415 485 0870",
    "sg:postcode":"94901",
    "sg:province":"CA",
    "sg:tags":[
        "sandwich",
        "salad",
        "burger",
        "soup",
        "american",
        "steakhouse",
        "wrap"
    ],
    "wof:name":"IHOP",
    "wof:placetype":"venue"
},
  "geometry": {"coordinates":[-122.53953799999999,37.97413],"type":"Point"}
}