{
  "type": "Feature",
  "properties": {
    "iso:country":"US",
    "sg:address":"12411 Saint Mark St",
    "sg:city":"Garden Grove",
    "sg:classifiers":[
        {
            "category":"Food & Beverages",
            "subcategory":"Liquor & Beverages",
            "type":"Retail Goods"
        }
    ],
    "sg:phone":"+1 714 835 1782",
    "sg:postcode":"92845",
    "sg:province":"CA",
    "sg:tags":[
        "alcoholic"
    ],
    "wof:name":"Doras Liquor",
    "wof:placetype":"venue"
},
  "geometry": {"coordinates":[-118.03183799999999,33.781952],"type":"Point"}
}