{
  "type": "Feature",
  "properties": {
    "iso:country":"US",
    "sg:address":"1102 S Pacific Ave",
    "sg:city":"San Pedro",
    "sg:classifiers":[
        {
            "category":"Travel",
            "subcategory":"Travel Agent",
            "type":"Entertainment"
        }
    ],
    "sg:phone":"+1 310 732 5850",
    "sg:postcode":"90731",
    "sg:province":"CA",
    "sg:tags":[
        "agency"
    ],
    "wof:name":"All Ways Travel Services",
    "wof:placetype":"venue"
},
  "geometry": {"coordinates":[-118.287846,33.73493],"type":"Point"}
}