{
  "type": "Feature",
  "properties": {
    "addr:full":"401 Old Newport Blvd Ste 102 Newport Beach CA 92663",
    "addr:housenumber":"401",
    "addr:postcode":"92663",
    "addr:street":"Old Newport Blvd Ste 102",
    "iso:country":"US",
    "sg:address":"401 Old Newport Blvd Ste 102",
    "sg:city":"Newport Beach",
    "sg:classifiers":[
        {
            "category":"Health Services",
            "subcategory":"Doctor",
            "type":"Services"
        }
    ],
    "sg:phone":"+1 949 631 0300",
    "sg:postcode":"92663",
    "sg:province":"CA",
    "sg:tags":[
        "dermatologist"
    ],
    "wof:name":"Dermatology & Laser Clinic Inc",
    "wof:placetype":"venue"
},
  "geometry": {"coordinates":[-117.92694899999999,33.625942],"type":"Point"}
}