{
  "type": "Feature",
  "properties": {
    "iso:country":"US",
    "sg:address":"32234 Pso Adelanto",
    "sg:city":"San Juan Capistrano",
    "sg:classifiers":[
        {
            "category":"Wholesale",
            "subcategory":"Chemicals & Plastics",
            "type":"Manufacturing & Wholesale Goods"
        }
    ],
    "sg:phone":"+1 949 487 9860",
    "sg:postcode":"92675",
    "sg:province":"CA",
    "wof:name":"Ecolotech",
    "wof:placetype":"venue"
},
  "geometry": {"coordinates":[-117.665296,33.495095],"type":"Point"}
}