{
  "type": "Feature",
  "properties": {
    "addr:full":"290 Bristol St Costa Mesa CA 92626",
    "addr:housenumber":"290",
    "addr:postcode":"92626",
    "addr:street":"Bristol St",
    "iso:country":"US",
    "sg:address":"290 Bristol St",
    "sg:city":"Costa Mesa",
    "sg:classifiers":[
        {
            "category":"Restaurant",
            "type":"Food & Drink"
        }
    ],
    "sg:phone":"+1 714 556 3072",
    "sg:postcode":"92626",
    "sg:province":"CA",
    "sg:tags":[
        "breakfast",
        "brunch",
        "diner"
    ],
    "sg:website":"www.dennys.com",
    "wof:name":"Denny's",
    "wof:placetype":"venue"
},
  "geometry": {"coordinates":[-117.882212,33.667269],"type":"Point"}
}