{
  "type": "Feature",
  "properties": {
    "addr:full":"401 Terry Francois Street San Francisco CA 94158",
    "addr:housenumber":"401",
    "addr:postcode":"94158",
    "addr:street":"Terry Francois Street",
    "iso:country":"US",
    "sg:address":"401 Terry Francois Street",
    "sg:city":"San Francisco",
    "sg:classifiers":[
        {
            "category":"Real Estate",
            "subcategory":"Architect",
            "type":"Services"
        }
    ],
    "sg:phone":"+1 415 541 0288",
    "sg:postcode":"94158",
    "sg:province":"CA",
    "sg:website":"www.fillonsolis.com",
    "wof:name":"Fillon Solis Architects",
    "wof:placetype":"venue"
},
  "geometry": {"coordinates":[-122.386763,37.771697],"type":"Point"}
}