{
  "type": "Feature",
  "properties": {
    "iso:country":"US",
    "sg:address":"Hillview Executive Park 830 Hillview Ct #260",
    "sg:city":"Milpitas",
    "sg:classifiers":[
        {
            "category":"Health Services",
            "subcategory":"Clinic",
            "type":"Services"
        }
    ],
    "sg:phone":"+1 408 882 5019",
    "sg:postcode":"95035",
    "sg:province":"CA",
    "sg:tags":[
        "counseling",
        "mental"
    ],
    "wof:name":"Neeta Jha, MS - Family Therapist",
    "wof:placetype":"venue"
},
  "geometry": {"coordinates":[-121.892667,37.435614],"type":"Point"}
}