{
  "type": "Feature",
  "properties": {
    "addr:full":"10601 State Highway 88 Jackson CA 95642",
    "addr:housenumber":"10601",
    "addr:postcode":"95642",
    "addr:street":"State Highway 88",
    "iso:country":"US",
    "sg:address":"10601 State Highway 88",
    "sg:city":"Jackson",
    "sg:classifiers":[
        {
            "category":"Autos & Motor Vehicles",
            "subcategory":"Automobile Sales",
            "type":"Retail Goods"
        }
    ],
    "sg:phone":"+1 209 223 3660",
    "sg:postcode":"95642",
    "sg:province":"CA",
    "sg:tags":[
        "car",
        "used"
    ],
    "wof:name":"Eagle Auto Sales & More",
    "wof:placetype":"venue"
},
  "geometry": {"coordinates":[-120.83389,38.353266],"type":"Point"}
}