{
  "type": "Feature",
  "properties": {
    "iso:country":"US",
    "sg:address":"1410 S 43rd St",
    "sg:city":"San Diego",
    "sg:classifiers":[
        {
            "category":"Government",
            "subcategory":"Police Station",
            "type":"Public Place"
        }
    ],
    "sg:phone":"+1 619 527 5489",
    "sg:postcode":"92113",
    "sg:province":"CA",
    "sg:tags":[
        "protection"
    ],
    "wof:name":"Police- Southcrest Satellite",
    "wof:placetype":"venue"
},
  "geometry": {"coordinates":[-117.10249,32.691629],"type":"Point"}
}