{
  "type": "Feature",
  "properties": {
    "addr:full":"1151 Galleria Blvd Roseville CA 95678",
    "addr:housenumber":"1151",
    "addr:postcode":"95678",
    "addr:street":"Galleria Blvd",
    "iso:country":"US",
    "sg:address":"1151 Galleria Blvd",
    "sg:city":"Roseville",
    "sg:classifiers":[
        {
            "category":"Shopping",
            "subcategory":"Clothing, Apparel, & Fashions",
            "type":"Retail Goods"
        },
        {
            "category":"Shopping",
            "subcategory":"Adult",
            "type":"Retail Goods"
        }
    ],
    "sg:phone":"+1 916 788 0580",
    "sg:postcode":"95678",
    "sg:province":"CA",
    "sg:tags":[
        "girdle",
        "corset",
        "bra"
    ],
    "wof:name":"Hicks Gilly",
    "wof:placetype":"venue"
},
  "geometry": {"coordinates":[-121.265862,38.772129],"type":"Point"}
}