{
  "type": "Feature",
  "properties": {
    "addr:full":"190 Bissell Pl San Jacinto CA 92582",
    "addr:housenumber":"190",
    "addr:postcode":"92582",
    "addr:street":"Bissell Pl",
    "iso:country":"US",
    "sg:address":"190 Bissell Pl",
    "sg:city":"San Jacinto",
    "sg:classifiers":[
        {
            "category":"Manufacturing",
            "subcategory":"Tools & Machinery",
            "type":"Manufacturing & Wholesale Goods"
        }
    ],
    "sg:phone":"+1 951 654 5660",
    "sg:postcode":"92582",
    "sg:province":"CA",
    "sg:tags":[
        "machine",
        "shop"
    ],
    "sg:website":"www.msmw.com",
    "wof:name":"Mojave Southern Machine Works",
    "wof:placetype":"venue"
},
  "geometry": {"coordinates":[-116.975115,33.786207],"type":"Point"}
}