{
  "type": "Feature",
  "properties": {
    "addr:full":"2745 Meadow Lark Drive San Diego CA 92123",
    "addr:housenumber":"2745",
    "addr:postcode":"92123",
    "addr:street":"Meadow Lark Drive",
    "iso:country":"US",
    "sg:address":"2745 Meadow Lark Drive",
    "sg:city":"San Diego",
    "sg:classifiers":[
        {
            "category":"Real Estate",
            "subcategory":"Real Estate Operator",
            "type":"Services"
        }
    ],
    "sg:phone":"+1 858 278 2131",
    "sg:postcode":"92123",
    "sg:province":"CA",
    "sg:tags":[
        "apartment"
    ],
    "wof:name":"Mission Woods Apartment Homes",
    "wof:placetype":"venue"
},
  "geometry": {"coordinates":[-117.15447500000001,32.792297],"type":"Point"}
}