{
  "type": "Feature",
  "properties": {
    "addr:full":"5741 N 1st St Fresno CA 93710",
    "addr:housenumber":"5741",
    "addr:postcode":"93710",
    "addr:street":"N 1St St",
    "iso:country":"US",
    "sg:address":"5741 N 1st St",
    "sg:city":"Fresno",
    "sg:classifiers":[
        {
            "category":"Manufacturing",
            "subcategory":"Printing",
            "type":"Manufacturing & Wholesale Goods"
        },
        {
            "category":"Wholesale",
            "subcategory":"Drugs",
            "type":"Manufacturing & Wholesale Goods"
        },
        {
            "category":"Professional",
            "subcategory":"Printing & Photocopies",
            "type":"Services"
        },
        {
            "category":"Professional",
            "subcategory":"Art Services",
            "type":"Services"
        },
        {
            "category":"Manufacturing",
            "subcategory":"Signs",
            "type":"Manufacturing & Wholesale Goods"
        }
    ],
    "sg:phone":"+1 559 435 6263",
    "sg:postcode":"93710",
    "sg:province":"CA",
    "sg:tags":[
        "graphic",
        "digital",
        "flag",
        "decal",
        "designer",
        "imaging",
        "pennant",
        "banners"
    ],
    "sg:website":"http://www.yellowdoggraphics.com",
    "wof:name":"Yellow Dog Signs & Graphics",
    "wof:placetype":"venue"
},
  "geometry": {"coordinates":[-119.77237599999999,36.822162],"type":"Point"}
}