{
  "type": "Feature",
  "properties": {
    "addr:full":"12251 Pangborn Ave Downey CA 90241",
    "addr:housenumber":"12251",
    "addr:postcode":"90241",
    "addr:street":"Pangborn Ave",
    "iso:country":"US",
    "sg:address":"12251 Pangborn Ave",
    "sg:city":"Downey",
    "sg:classifiers":[
        {
            "category":"Retail",
            "subcategory":"Auto Repair",
            "type":"Services"
        }
    ],
    "sg:phone":"+1 562 861 2345",
    "sg:postcode":"90241",
    "sg:province":"CA",
    "sg:tags":[
        "wrecker"
    ],
    "wof:name":"Doug's Tug",
    "wof:placetype":"venue"
},
  "geometry": {"coordinates":[-118.113489,33.922336],"type":"Point"}
}