{
  "type": "Feature",
  "properties": {
    "addr:full":"929 N Milliken Ave Ontario CA 91764",
    "addr:housenumber":"929",
    "addr:postcode":"91764",
    "addr:street":"N Milliken Ave",
    "iso:country":"US",
    "sg:address":"929 N Milliken Ave",
    "sg:city":"Ontario",
    "sg:classifiers":[
        {
            "category":"Restaurant",
            "type":"Food & Drink"
        }
    ],
    "sg:menulink":"http://www.allmenus.com/ca/ontario/152075-baja-fresh-mexican-grill/menu/",
    "sg:phone":"+1 909 484 6200",
    "sg:postcode":"91764",
    "sg:province":"CA",
    "sg:tags":[
        "mexican"
    ],
    "wof:name":"Baja Fresh Mexican Grill",
    "wof:placetype":"venue"
},
  "geometry": {"coordinates":[-117.558565,34.072863],"type":"Point"}
}