{
  "type": "Feature",
  "properties": {
    "addr:full":"1565 Hollenbeck Avenue Sunnyvale CA 94087",
    "addr:housenumber":"1565",
    "addr:postcode":"94087",
    "addr:street":"Hollenbeck Avenue",
    "iso:country":"US",
    "sg:address":"1565 Hollenbeck Avenue",
    "sg:city":"Sunnyvale",
    "sg:classifiers":[
        {
            "category":"Health Services",
            "subcategory":"Dentist",
            "type":"Services"
        }
    ],
    "sg:phone":"+1 408 732 3264",
    "sg:postcode":"94087",
    "sg:province":"CA",
    "wof:name":"Oyedele Dental Corporation.",
    "wof:placetype":"venue"
},
  "geometry": {"coordinates":[-122.04148600000001,37.341989],"type":"Point"}
}