{
  "type": "Feature",
  "properties": {
    "addr:full":"3855 Wilshire Blvd Los Angeles CA 90010",
    "addr:housenumber":"3855",
    "addr:postcode":"90010",
    "addr:street":"Wilshire Blvd",
    "iso:country":"US",
    "sg:address":"3855 Wilshire Blvd",
    "sg:city":"Los Angeles",
    "sg:classifiers":[
        {
            "category":"Restaurant",
            "type":"Food & Drink"
        }
    ],
    "sg:phone":"+1 213 365 6677",
    "sg:postcode":"90010",
    "sg:province":"CA",
    "sg:tags":[
        "shop",
        "coffee"
    ],
    "wof:name":"ZIP",
    "wof:placetype":"venue"
},
  "geometry": {"coordinates":[-118.311053,34.061768],"type":"Point"}
}