{
  "type": "Feature",
  "properties": {
    "iso:country":"US",
    "sg:address":"17131 Beach Blvd",
    "sg:city":"Huntington Beach",
    "sg:classifiers":[
        {
            "category":"Wholesale",
            "subcategory":"Stationery",
            "type":"Manufacturing & Wholesale Goods"
        }
    ],
    "sg:phone":"+1 714 843 6229",
    "sg:postcode":"92647",
    "sg:province":"CA",
    "sg:tags":[
        "legal",
        "supply"
    ],
    "wof:name":"We The People",
    "wof:placetype":"venue"
},
  "geometry": {"coordinates":[-117.989065,33.714861],"type":"Point"}
}