{
  "type": "Feature",
  "properties": {
    "iso:country":"US",
    "sg:address":"27391 Vista Ave",
    "sg:city":"Perris",
    "sg:classifiers":[
        {
            "category":"Freight",
            "type":"Transportation"
        }
    ],
    "sg:phone":"+1 951 657 8122",
    "sg:postcode":"92570",
    "sg:province":"CA",
    "sg:tags":[
        "broker"
    ],
    "wof:name":"Jerry Reis and Associates",
    "wof:placetype":"venue"
},
  "geometry": {"coordinates":[-117.306931,33.722694],"type":"Point"}
}