{
  "type": "Feature",
  "properties": {
    "addr:full":"27391 Vista Ave Perris CA 92570",
    "addr:housenumber":"27391",
    "addr:postcode":"92570",
    "addr:street":"Vista Ave",
    "iso:country":"US",
    "sg:address":"27391 Vista Ave",
    "sg:city":"Perris",
    "sg:classifiers":[
        {
            "category":"Freight",
            "type":"Transportation"
        }
    ],
    "sg:phone":"+1 951 657 8122",
    "sg:postcode":"92570",
    "sg:province":"CA",
    "sg:tags":[
        "broker"
    ],
    "wof:name":"Jerry Reis and Associates",
    "wof:placetype":"venue"
},
  "geometry": {"coordinates":[-117.30693100000001,33.722694],"type":"Point"}
}