{
  "type": "Feature",
  "properties": {
    "addr:full":"650 Gateway Center Way San Diego CA 92102",
    "addr:housenumber":"650",
    "addr:postcode":"92102",
    "addr:street":"Gateway Center Way",
    "iso:country":"US",
    "sg:address":"650 Gateway Center Way",
    "sg:city":"San Diego",
    "sg:classifiers":[
        {
            "category":"Government",
            "subcategory":"Office",
            "type":"Public Place"
        }
    ],
    "sg:phone":"+1 619 525 3716",
    "sg:postcode":"92102",
    "sg:province":"CA",
    "sg:tags":[
        "commission",
        "housing"
    ],
    "wof:name":"San Diego Housing Commission",
    "wof:placetype":"venue"
},
  "geometry": {"coordinates":[-117.11278,32.714782],"type":"Point"}
}