{
  "type": "Feature",
  "properties": {
    "iso:country":"US",
    "sg:address":"PO Box 3605",
    "sg:city":"Berkeley",
    "sg:classifiers":[
        {
            "category":"Professional",
            "subcategory":"Lawyer & Legal Services",
            "type":"Services"
        }
    ],
    "sg:phone":"+1 510 927 7958",
    "sg:postcode":"94705",
    "sg:province":"CA",
    "sg:tags":[
        "litigation"
    ],
    "sg:website":"www.pro-perlegal.com",
    "wof:name":"Pro Per Legal Assistance",
    "wof:placetype":"venue"
},
  "geometry": {"coordinates":[-122.251209,37.873706],"type":"Point"}
}