{
  "type": "Feature",
  "properties": {
    "iso:country":"US",
    "sg:address":"16200 Sand Canyon Ave",
    "sg:city":"Irvine",
    "sg:classifiers":[
        {
            "category":"Professional",
            "subcategory":"Management & Consulting",
            "type":"Services"
        }
    ],
    "sg:phone":"+1 949 753 2042",
    "sg:postcode":"92618",
    "sg:province":"CA",
    "wof:name":"Sodexho Management Inc",
    "wof:placetype":"venue"
},
  "geometry": {"coordinates":[-117.775221,33.660322],"type":"Point"}
}