{
  "type": "Feature",
  "properties": {
    "addr:full":"1034 2nd St Eureka CA 95501",
    "addr:housenumber":"1034",
    "addr:postcode":"95501",
    "addr:street":"2Nd St",
    "iso:country":"US",
    "sg:address":"1034 2nd St",
    "sg:city":"Eureka",
    "sg:classifiers":[
        {
            "category":"Government",
            "subcategory":"Office",
            "type":"Public Place"
        }
    ],
    "sg:phone":"+1 707 444 6633",
    "sg:postcode":"95501",
    "sg:province":"CA",
    "sg:tags":[
        "county"
    ],
    "wof:name":"Eureka County Film Commission",
    "wof:placetype":"venue"
},
  "geometry": {"coordinates":[-124.160239,40.805187],"type":"Point"}
}