{
  "type": "Feature",
  "properties": {
    "iso:country":"US",
    "sg:address":"6021 Stockton Blvd",
    "sg:city":"Sacramento",
    "sg:classifiers":[
        {
            "category":"Professional",
            "subcategory":"Computer Services",
            "type":"Services"
        }
    ],
    "sg:phone":"+1 916 392 7588",
    "sg:postcode":"95824",
    "sg:province":"CA",
    "wof:name":"Golden Business Computer Ntwrk",
    "wof:placetype":"venue"
},
  "geometry": {"coordinates":[-121.438465,38.516375],"type":"Point"}
}