{
  "type": "Feature",
  "properties": {
    "iso:country":"US",
    "sg:address":"115 Ponderosa Ct",
    "sg:city":"Folsom",
    "sg:classifiers":[
        {
            "category":"Home & Garden",
            "subcategory":"Furniture",
            "type":"Retail Goods"
        }
    ],
    "sg:phone":"+1 916 984 8452",
    "sg:postcode":"95630",
    "sg:province":"CA",
    "sg:tags":[
        "equipment",
        "patio",
        "supply"
    ],
    "wof:name":"EMC Sun Room Patio Covers",
    "wof:placetype":"venue"
},
  "geometry": {"coordinates":[-121.140753,38.678908],"type":"Point"}
}