{
  "type": "Feature",
  "properties": {
    "iso:country":"US",
    "sg:address":"4452 Park Blvd",
    "sg:city":"San Diego",
    "sg:classifiers":[
        {
            "category":"Professional",
            "subcategory":"Detective & Security Services",
            "type":"Services"
        }
    ],
    "sg:phone":"+1 619 296 8111",
    "sg:postcode":"92116",
    "sg:province":"CA",
    "sg:tags":[
        "investigator"
    ],
    "wof:name":"Rimco Realty",
    "wof:placetype":"venue"
},
  "geometry": {"coordinates":[-117.146335,32.758595],"type":"Point"}
}