{
  "type": "Feature",
  "properties": {
    "addr:full":"8271 Melrose Ave Los Angeles CA 90046",
    "addr:housenumber":"8271",
    "addr:postcode":"90046",
    "addr:street":"Melrose Ave",
    "iso:country":"US",
    "sg:address":"8271 Melrose Ave",
    "sg:city":"Los Angeles",
    "sg:classifiers":[
        {
            "category":"Professional",
            "subcategory":"Management & Consulting",
            "type":"Services"
        }
    ],
    "sg:phone":"+1 323 655 6002",
    "sg:postcode":"90046",
    "sg:province":"CA",
    "sg:tags":[
        "fuel"
    ],
    "wof:name":"Joan Sittenfield Management",
    "wof:placetype":"venue"
},
  "geometry": {"coordinates":[-118.36987499999999,34.083762],"type":"Point"}
}