{
  "type": "Feature",
  "properties": {
    "addr:full":"771 Sacramento St San Francisco CA 94108",
    "addr:housenumber":"771",
    "addr:postcode":"94108",
    "addr:street":"Sacramento St",
    "iso:country":"US",
    "sg:address":"771 Sacramento St",
    "sg:city":"San Francisco",
    "sg:classifiers":[
        {
            "category":"Health Services",
            "subcategory":"Doctor",
            "type":"Services"
        }
    ],
    "sg:phone":"+1 415 362 3388",
    "sg:postcode":"94108",
    "sg:province":"CA",
    "sg:tags":[
        "dentist"
    ],
    "wof:name":"CT Dental Group",
    "wof:placetype":"venue"
},
  "geometry": {"coordinates":[-122.40565700000001,37.793207],"type":"Point"}
}