{
  "type": "Feature",
  "properties": {
    "iso:country":"US",
    "sg:address":"717 Corona Dr",
    "sg:city":"Oceanside",
    "sg:classifiers":[
        {
            "category":"Wholesale",
            "subcategory":"Office Equipment",
            "type":"Manufacturing & Wholesale Goods"
        }
    ],
    "sg:phone":"+1 760 940 9123",
    "sg:postcode":"92057",
    "sg:province":"CA",
    "wof:name":"J L Fryson & Associates Inc",
    "wof:placetype":"venue"
},
  "geometry": {"coordinates":[-117.286658,33.242037],"type":"Point"}
}