{
  "type": "Feature",
  "properties": {
    "addr:full":"1444 San Fernando Rd San Fernando CA 91340",
    "addr:housenumber":"1444",
    "addr:postcode":"91340",
    "addr:street":"San Fernando Rd",
    "iso:country":"US",
    "sg:address":"1444 San Fernando Rd",
    "sg:city":"San Fernando",
    "sg:classifiers":[
        {
            "category":"Retail",
            "subcategory":"Auto Repair",
            "type":"Services"
        }
    ],
    "sg:phone":"+1 818 361 4138",
    "sg:postcode":"91340",
    "sg:province":"CA",
    "sg:tags":[
        "repairing",
        "automobile"
    ],
    "wof:name":"Automotive Center",
    "wof:placetype":"venue"
},
  "geometry": {"coordinates":[-118.446314,34.287392],"type":"Point"}
}