{
  "type": "Feature",
  "properties": {
    "addr:full":"9115 Judicial Drive San Diego CA 92122",
    "addr:housenumber":"9115",
    "addr:postcode":"92122",
    "addr:street":"Judicial Drive",
    "iso:country":"US",
    "sg:address":"9115 Judicial Drive",
    "sg:city":"San Diego",
    "sg:classifiers":[
        {
            "category":"Professional",
            "subcategory":"Lawyer & Legal Services",
            "type":"Services"
        }
    ],
    "sg:phone":"+1 858 729 3057",
    "sg:postcode":"92122",
    "sg:province":"CA",
    "wof:name":"Coastal Immigration Law Group, PC",
    "wof:placetype":"venue"
},
  "geometry": {"coordinates":[-117.204127,32.872954],"type":"Point"}
}