{
  "type": "Feature",
  "properties": {
    "iso:country":"US",
    "sg:address":"222 Douglas Blvd",
    "sg:city":"Roseville",
    "sg:classifiers":[
        {
            "category":"Professional",
            "type":"Services"
        }
    ],
    "sg:phone":"+1 916 789 1039",
    "sg:postcode":"95678",
    "sg:province":"CA",
    "wof:name":"Forranos Inc",
    "wof:placetype":"venue"
},
  "geometry": {"coordinates":[-121.28801300000001,38.743828],"type":"Point"}
}