{
  "type": "Feature",
  "properties": {
    "addr:full":"12531 Harbor Blvd Garden Grove CA 92840",
    "addr:housenumber":"12531",
    "addr:postcode":"92840",
    "addr:street":"Harbor Blvd",
    "iso:country":"US",
    "sg:address":"12531 Harbor Blvd",
    "sg:city":"Garden Grove",
    "sg:classifiers":[
        {
            "category":"Restaurant",
            "type":"Food & Drink"
        }
    ],
    "sg:phone":"+1 714 658 8482",
    "sg:postcode":"92840",
    "sg:province":"CA",
    "wof:name":"El Moctezuma #2",
    "wof:placetype":"venue"
},
  "geometry": {"coordinates":[-117.915525,33.780873],"type":"Point"}
}