{
  "type": "Feature",
  "properties": {
    "iso:country":"US",
    "sg:address":"7080 Barton Rd",
    "sg:city":"Granite Bay",
    "sg:classifiers":[
        {
            "category":"Shopping",
            "subcategory":"Hobbies, Toys, & Games",
            "type":"Retail Goods"
        }
    ],
    "sg:phone":"+1 916 791 1597",
    "sg:postcode":"95746",
    "sg:province":"CA",
    "sg:tags":[
        "equipment",
        "ceramic",
        "supply"
    ],
    "wof:name":"Hazel's Ceramics",
    "wof:placetype":"venue"
},
  "geometry": {"coordinates":[-121.19196700000001,38.766522],"type":"Point"}
}