{
  "type": "Feature",
  "properties": {
    "addr:full":"2297 Ringwood Ave San Jose CA 95131",
    "addr:housenumber":"2297",
    "addr:postcode":"95131",
    "addr:street":"Ringwood Ave",
    "iso:country":"US",
    "sg:address":"2297 Ringwood Ave",
    "sg:city":"San Jose",
    "sg:classifiers":[
        {
            "category":"Manufacturing",
            "subcategory":"Furniture",
            "type":"Manufacturing & Wholesale Goods"
        },
        {
            "category":"Manufacturing",
            "subcategory":"Building Materials",
            "type":"Manufacturing & Wholesale Goods"
        }
    ],
    "sg:phone":"+1 408 526 1600",
    "sg:postcode":"95131",
    "sg:province":"CA",
    "sg:tags":[
        "shutter",
        "window",
        "wood",
        "shades",
        "mfg"
    ],
    "wof:name":"Summit Window Products Inc",
    "wof:placetype":"venue"
},
  "geometry": {"coordinates":[-121.895905,37.40351],"type":"Point"}
}