{
  "type": "Feature",
  "properties": {
    "iso:country":"US",
    "sg:address":"1217 Manitou Rd",
    "sg:city":"Santa Barbara",
    "sg:classifiers":[
        {
            "category":"Freight",
            "type":"Transportation"
        }
    ],
    "sg:phone":"+1 805 682 8825",
    "sg:postcode":"93101",
    "sg:province":"CA",
    "sg:tags":[
        "operator",
        "local",
        "trucking"
    ],
    "wof:name":"Boss Trucking",
    "wof:placetype":"venue"
},
  "geometry": {"coordinates":[-119.726633,34.417508],"type":"Point"}
}