{
  "type": "Feature",
  "properties": {
    "addr:full":"14464 Valley Center Dr Victorville CA 92395",
    "addr:housenumber":"14464",
    "addr:postcode":"92395",
    "addr:street":"Valley Center Dr",
    "iso:country":"US",
    "sg:address":"14464 Valley Center Dr",
    "sg:city":"Victorville",
    "sg:classifiers":[
        {
            "category":"Shopping",
            "subcategory":"Used Merchandise",
            "type":"Retail Goods"
        }
    ],
    "sg:phone":"+1 760 243 0306",
    "sg:postcode":"92395",
    "sg:province":"CA",
    "wof:name":"This & That Gallery",
    "wof:placetype":"venue"
},
  "geometry": {"coordinates":[-117.321257,34.510456],"type":"Point"}
}