{
  "type": "Feature",
  "properties": {
    "addr:full":"496 Jefferson Street San Francisco CA 94109",
    "addr:housenumber":"496",
    "addr:postcode":"94109",
    "addr:street":"Jefferson Street",
    "iso:country":"US",
    "sg:address":"496 Jefferson Street",
    "sg:city":"San Francisco",
    "sg:classifiers":[
        {
            "category":"Arts & Performance",
            "subcategory":"Art Gallery",
            "type":"Entertainment"
        }
    ],
    "sg:phone":"+1 415 771 6217",
    "sg:postcode":"94109",
    "sg:province":"CA",
    "wof:name":"Maskell Don & Company",
    "wof:placetype":"venue"
},
  "geometry": {"coordinates":[-122.420998,37.807701],"type":"Point"}
}