{
  "type": "Feature",
  "properties": {
    "iso:country":"US",
    "sg:address":"500 Leavenworth St",
    "sg:city":"San Francisco",
    "sg:classifiers":[
        {
            "category":"Professional",
            "type":"Services"
        }
    ],
    "sg:phone":"+1 415 563 3279",
    "sg:postcode":"94109",
    "sg:province":"CA",
    "sg:tags":[
        "writer"
    ],
    "wof:name":"A Moment In Time",
    "wof:placetype":"venue"
},
  "geometry": {"coordinates":[-122.41471,37.786041],"type":"Point"}
}