{
  "type": "Feature",
  "properties": {
    "addr:full":"1240 S Lorena Street Los Angeles CA 90023",
    "addr:housenumber":"1240",
    "addr:postcode":"90023",
    "addr:street":"S Lorena Street",
    "iso:country":"US",
    "sg:address":"1240 S Lorena Street",
    "sg:city":"Los Angeles",
    "sg:classifiers":[
        {
            "category":"Autos & Motor Vehicles",
            "subcategory":"Auto Supplies",
            "type":"Retail Goods"
        }
    ],
    "sg:phone":"+1 323 266 6759",
    "sg:postcode":"90023",
    "sg:province":"CA",
    "sg:tags":[
        "tire"
    ],
    "wof:name":"Tony's Tires",
    "wof:placetype":"venue"
},
  "geometry": {"coordinates":[-118.205674,34.020476],"type":"Point"}
}