{
  "type": "Feature",
  "properties": {
    "iso:country":"US",
    "sg:address":"823 Magellan Ln",
    "sg:city":"Foster City",
    "sg:classifiers":[
        {
            "category":"Building & Trades",
            "subcategory":"Electrical",
            "type":"Services"
        }
    ],
    "sg:phone":"+1 650 571 0490",
    "sg:postcode":"94404",
    "sg:province":"CA",
    "sg:tags":[
        "electric",
        "contractor"
    ],
    "wof:name":"Pal Consulting-Electrical",
    "wof:placetype":"venue"
},
  "geometry": {"coordinates":[-122.266665,37.550984],"type":"Point"}
}