{
  "type": "Feature",
  "properties": {
    "iso:country":"US",
    "sg:address":"1618 Noriega St",
    "sg:city":"San Francisco",
    "sg:classifiers":[
        {
            "category":"Food & Beverages",
            "subcategory":"Specialty",
            "type":"Retail Goods"
        }
    ],
    "sg:postcode":"94122",
    "sg:province":"CA",
    "sg:tags":[
        "tea",
        "coffee"
    ],
    "sg:website":"www.coffeesf.com",
    "wof:name":"House of Coffee",
    "wof:placetype":"venue"
},
  "geometry": {"coordinates":[-122.48122100000001,37.754292],"type":"Point"}
}