{
  "type": "Feature",
  "properties": {
    "iso:country":"US",
    "sg:address":"708 Montgomery St",
    "sg:city":"San Francisco",
    "sg:classifiers":[
        {
            "category":"Professional",
            "subcategory":"Management & Consulting",
            "type":"Services"
        }
    ],
    "sg:phone":"+1 415 788 7248",
    "sg:postcode":"94111",
    "sg:province":"CA",
    "sg:tags":[
        "consultant",
        "business"
    ],
    "wof:name":"Idiom Brand Identity",
    "wof:placetype":"venue"
},
  "geometry": {"coordinates":[-122.403411,37.796357],"type":"Point"}
}