{
  "type": "Feature",
  "properties": {
    "addr:full":"1702 E 41st Los Angeles CA 90058",
    "addr:housenumber":"1702",
    "addr:postcode":"90058",
    "addr:street":"E 41St",
    "iso:country":"US",
    "sg:address":"1702 E 41st",
    "sg:city":"Los Angeles",
    "sg:classifiers":[
        {
            "category":"Food & Beverages",
            "subcategory":"Farmers Market",
            "type":"Retail Goods"
        },
        {
            "category":"Professional",
            "subcategory":"Business Services",
            "type":"Services"
        }
    ],
    "sg:phone":"+1 800 249 5240",
    "sg:postcode":"90058",
    "sg:province":"CA",
    "sg:tags":[
        "delivery"
    ],
    "sg:website":"www.southcentralfarmers.com/",
    "wof:name":"South Central Farmers' Cooperative",
    "wof:placetype":"venue"
},
  "geometry": {"coordinates":[-118.242828,34.006986],"type":"Point"}
}