{
  "type": "Feature",
  "properties": {
    "addr:full":"3212 N Alameda St Compton CA 90222",
    "addr:housenumber":"3212",
    "addr:postcode":"90222",
    "addr:street":"N Alameda St",
    "iso:country":"US",
    "sg:address":"3212 N Alameda St",
    "sg:city":"Compton",
    "sg:classifiers":[
        {
            "category":"Manufacturing",
            "subcategory":"Metals",
            "type":"Manufacturing & Wholesale Goods"
        }
    ],
    "sg:phone":"+1 310 639 4222",
    "sg:postcode":"90222",
    "sg:province":"CA",
    "sg:tags":[
        "treating",
        "heat"
    ],
    "wof:name":"L & M Steel Co",
    "wof:placetype":"venue"
},
  "geometry": {"coordinates":[-118.223572,33.919977],"type":"Point"}
}