{
  "type": "Feature",
  "properties": {
    "addr:full":"815 W Naomi Ave Ste F Arcadia CA 91007",
    "addr:housenumber":"815",
    "addr:postcode":"91007",
    "addr:street":"W Naomi Ave Ste F",
    "iso:country":"US",
    "sg:address":"815 W Naomi Ave Ste F",
    "sg:city":"Arcadia",
    "sg:classifiers":[
        {
            "category":"Shopping",
            "subcategory":"Mobile Phones",
            "type":"Retail Goods"
        }
    ],
    "sg:phone":"+1 626 446 9033",
    "sg:postcode":"91007",
    "sg:province":"CA",
    "wof:name":"Digital Zone",
    "wof:placetype":"venue"
},
  "geometry": {"coordinates":[-118.054001,34.124199],"type":"Point"}
}