{
  "type": "Feature",
  "properties": {
    "addr:full":"4219 Alderson Ave Baldwin Park CA 91706",
    "addr:housenumber":"4219",
    "addr:postcode":"91706",
    "addr:street":"Alderson Ave",
    "iso:country":"US",
    "sg:address":"4219 Alderson Ave",
    "sg:city":"Baldwin Park",
    "sg:classifiers":[
        {
            "category":"Professional",
            "type":"Services"
        }
    ],
    "sg:phone":"+1 626 480 7714",
    "sg:postcode":"91706",
    "sg:province":"CA",
    "wof:name":"DBR Woodwork",
    "wof:placetype":"venue"
},
  "geometry": {"coordinates":[-117.954843,34.090134],"type":"Point"}
}