{
  "type": "Feature",
  "properties": {
    "addr:full":"1401 Aviation Boulevard Redondo Beach CA 90277",
    "addr:housenumber":"1401",
    "addr:postcode":"90277",
    "addr:street":"Aviation Boulevard",
    "iso:country":"US",
    "sg:address":"1401 Aviation Boulevard",
    "sg:city":"Redondo Beach",
    "sg:classifiers":[
        {
            "category":"Retail",
            "subcategory":"Auto Repair",
            "type":"Services"
        }
    ],
    "sg:phone":"+1 310 376 9416",
    "sg:postcode":"90277",
    "sg:province":"CA",
    "sg:tags":[
        "body",
        "shop"
    ],
    "wof:name":"South Bay Auto",
    "wof:placetype":"venue"
},
  "geometry": {"coordinates":[-118.384866,33.867017],"type":"Point"}
}