{
  "type": "Feature",
  "properties": {
    "addr:full":"9827 Mars Way Sacramento CA 95827",
    "addr:housenumber":"9827",
    "addr:postcode":"95827",
    "addr:street":"Mars Way",
    "iso:country":"US",
    "sg:address":"9827 Mars Way",
    "sg:city":"Sacramento",
    "sg:classifiers":[
        {
            "category":"Freight",
            "type":"Transportation"
        }
    ],
    "sg:phone":"+1 916 364 0561",
    "sg:postcode":"95827",
    "sg:province":"CA",
    "wof:name":"Hot Wheels Transport",
    "wof:placetype":"venue"
},
  "geometry": {"coordinates":[-121.328272,38.563484],"type":"Point"}
}