{
  "type": "Feature",
  "properties": {
    "iso:country":"US",
    "sg:address":"255 N D St",
    "sg:city":"San Bernardino",
    "sg:classifiers":[
        {
            "category":"Professional",
            "type":"Services"
        }
    ],
    "sg:phone":"+1 909 885 0504",
    "sg:postcode":"92401",
    "sg:province":"CA",
    "sg:tags":[
        "establishment"
    ],
    "wof:name":"Moneylite Inc",
    "wof:placetype":"venue"
},
  "geometry": {"coordinates":[-117.29183500000001,34.103562],"type":"Point"}
}