{
  "type": "Feature",
  "properties": {
    "iso:country":"US",
    "sg:address":"145 N Sierra Madre Blvd",
    "sg:city":"Pasadena",
    "sg:classifiers":[
        {
            "category":"Professional",
            "type":"Services"
        }
    ],
    "sg:phone":"+1 626 584 1393",
    "sg:postcode":"91107",
    "sg:province":"CA",
    "wof:name":"Hxn Corporation",
    "wof:placetype":"venue"
},
  "geometry": {"coordinates":[-118.10086699999999,34.149174],"type":"Point"}
}