{
  "type": "Feature",
  "properties": {
    "iso:country":"US",
    "sg:address":"65 N Madison Ave Ste 304",
    "sg:city":"Pasadena",
    "sg:classifiers":[
        {
            "category":"Health Services",
            "subcategory":"Doctor",
            "type":"Services"
        }
    ],
    "sg:phone":"+1 626 585 8821",
    "sg:postcode":"91101",
    "sg:province":"CA",
    "wof:name":"Stern Merle N MD",
    "wof:placetype":"venue"
},
  "geometry": {"coordinates":[-118.138796,34.146888],"type":"Point"}
}