{
  "type": "Feature",
  "properties": {
    "addr:full":"44733 N el Macero Dr El Macero CA 95618",
    "addr:housenumber":"44733",
    "addr:postcode":"95618",
    "addr:street":"N El Macero Dr El Macero",
    "iso:country":"US",
    "sg:address":"44733 N el Macero Dr",
    "sg:city":"El Macero",
    "sg:classifiers":[
        {
            "category":"Government",
            "subcategory":"Office",
            "type":"Public Place"
        }
    ],
    "sg:phone":"+1 530 756 8013",
    "sg:postcode":"95618",
    "sg:province":"CA",
    "sg:tags":[
        "federal",
        "affairs"
    ],
    "wof:name":"New Zealand Consulate",
    "wof:placetype":"venue"
},
  "geometry": {"coordinates":[-121.68092300000001,38.547757],"type":"Point"}
}