{
  "type": "Feature",
  "properties": {
    "iso:country":"US",
    "sg:address":"44733 N el Macero Dr",
    "sg:city":"El Macero",
    "sg:classifiers":[
        {
            "category":"Government",
            "subcategory":"Office",
            "type":"Public Place"
        }
    ],
    "sg:phone":"+1 530 756 8013",
    "sg:postcode":"95618",
    "sg:province":"CA",
    "sg:tags":[
        "federal",
        "affairs"
    ],
    "wof:name":"New Zealand Consulate",
    "wof:placetype":"venue"
},
  "geometry": {"coordinates":[-121.680923,38.547757],"type":"Point"}
}