{
  "type": "Feature",
  "properties": {
    "addr:full":"1050 Sansome St San Francisco CA 94111",
    "addr:housenumber":"1050",
    "addr:postcode":"94111",
    "addr:street":"Sansome St",
    "iso:country":"US",
    "sg:address":"1050 Sansome St",
    "sg:city":"San Francisco",
    "sg:classifiers":[
        {
            "category":"Organizations",
            "subcategory":"Non-profit Organization",
            "type":"Services"
        }
    ],
    "sg:phone":"+1 415 788 2202",
    "sg:postcode":"94111",
    "sg:province":"CA",
    "sg:tags":[
        "fund",
        "raising"
    ],
    "wof:name":"Northern California Chapter",
    "wof:placetype":"venue"
},
  "geometry": {"coordinates":[-122.402456,37.799847],"type":"Point"}
}