{
  "type": "Feature",
  "properties": {
    "iso:country":"US",
    "sg:address":"1688 E 23rd St",
    "sg:city":"Los Angeles",
    "sg:classifiers":[
        {
            "category":"Retail",
            "subcategory":"Laundry & Dry Cleaning",
            "type":"Services"
        }
    ],
    "sg:phone":"+1 323 846 9550",
    "sg:postcode":"90011",
    "sg:province":"CA",
    "wof:name":"Calpad Laundry",
    "wof:placetype":"venue"
},
  "geometry": {"coordinates":[-118.245513,34.016487],"type":"Point"}
}