{
  "type": "Feature",
  "properties": {
    "addr:full":"1109 S Central Ave Glendale CA 91204",
    "addr:housenumber":"1109",
    "addr:postcode":"91204",
    "addr:street":"S Central Ave",
    "iso:country":"US",
    "sg:address":"1109 S Central Ave",
    "sg:city":"Glendale",
    "sg:classifiers":[
        {
            "category":"Health Services",
            "subcategory":"Doctor",
            "type":"Services"
        }
    ],
    "sg:phone":"+1 818 484 8871",
    "sg:postcode":"91204",
    "sg:province":"CA",
    "wof:name":"Valenzuela Severiano Md",
    "wof:placetype":"venue"
},
  "geometry": {"coordinates":[-118.257988,34.133308],"type":"Point"}
}