{
  "type": "Feature",
  "properties": {
    "iso:country":"US",
    "sg:address":"16043 Vanowen St",
    "sg:city":"Van Nuys",
    "sg:classifiers":[
        {
            "category":"Shopping",
            "subcategory":"Used Merchandise",
            "type":"Retail Goods"
        }
    ],
    "sg:phone":"+1 818 997 8498",
    "sg:postcode":"91406",
    "sg:province":"CA",
    "sg:tags":[
        "record",
        "rare"
    ],
    "wof:name":"Discoteca LA Sonrisa Number 2",
    "wof:placetype":"venue"
},
  "geometry": {"coordinates":[-118.482879,34.19398],"type":"Point"}
}