{
  "type": "Feature",
  "properties": {
    "addr:full":"130 W Main St Grass Valley CA 95945",
    "addr:housenumber":"130",
    "addr:postcode":"95945",
    "addr:street":"W Main St",
    "iso:country":"US",
    "sg:address":"130 W Main St",
    "sg:city":"Grass Valley",
    "sg:classifiers":[
        {
            "category":"Shopping",
            "subcategory":"Clothing, Apparel, & Fashions",
            "type":"Retail Goods"
        }
    ],
    "sg:phone":"+1 530 274 9892",
    "sg:postcode":"95945",
    "sg:province":"CA",
    "sg:tags":[
        "sportswear"
    ],
    "wof:name":"Sweats Etc",
    "wof:placetype":"venue"
},
  "geometry": {"coordinates":[-121.06231,39.219191],"type":"Point"}
}