{
  "type": "Feature",
  "properties": {
    "iso:country":"US",
    "sg:address":"1446 Vencil Rd",
    "sg:city":"Holtville",
    "sg:classifiers":[
        {
            "category":"Farming",
            "subcategory":"Farm",
            "type":"Manufacturing & Wholesale Goods"
        }
    ],
    "sg:phone":"+1 760 356 2422",
    "sg:postcode":"92250",
    "sg:province":"CA",
    "wof:name":"Sunrise Acres LLC",
    "wof:placetype":"venue"
},
  "geometry": {"coordinates":[-115.354356,32.738546],"type":"Point"}
}