{
  "type": "Feature",
  "properties": {
    "iso:country":"US",
    "sg:address":"37955 Rd 132",
    "sg:city":"Cutler",
    "sg:phone":"+1 559 734 3993",
    "sg:postcode":"93615",
    "sg:province":"CA",
    "sg:tags":[
        "farm",
        "corn",
        "citrus",
        "fruit",
        "grove",
        "cotton"
    ],
    "wof:name":"Richard Berry & Sons",
    "wof:placetype":"venue"
},
  "geometry": {"coordinates":[-119.27721099999999,36.480438],"type":"Point"}
}