{
  "type": "Feature",
  "properties": {
    "addr:full":"973 Moraga Rd Lafayette CA 94549",
    "addr:housenumber":"973",
    "addr:postcode":"94549",
    "addr:street":"Moraga Rd",
    "iso:country":"US",
    "sg:address":"973 Moraga Rd",
    "sg:city":"Lafayette",
    "sg:classifiers":[
        {
            "category":"Home & Garden",
            "subcategory":"Furniture",
            "type":"Retail Goods"
        }
    ],
    "sg:phone":"+1 925 283 5250",
    "sg:postcode":"94549",
    "sg:province":"CA",
    "wof:name":"Patio World",
    "wof:placetype":"venue"
},
  "geometry": {"coordinates":[-122.11868200000001,37.891204],"type":"Point"}
}