{
  "type": "Feature",
  "properties": {
    "addr:full":"2015 Cloverfield Blvd Santa Monica CA 90404",
    "addr:housenumber":"2015",
    "addr:postcode":"90404",
    "addr:street":"Cloverfield Blvd",
    "iso:country":"US",
    "sg:address":"2015 Cloverfield Blvd",
    "sg:city":"Santa Monica",
    "sg:classifiers":[
        {
            "category":"Insurance",
            "subcategory":"Insurance Agent",
            "type":"Services"
        }
    ],
    "sg:phone":"+1 310 828 1045",
    "sg:postcode":"90404",
    "sg:province":"CA",
    "sg:tags":[
        "processing"
    ],
    "wof:name":"Technosis",
    "wof:placetype":"venue"
},
  "geometry": {"coordinates":[-118.466414,34.022309],"type":"Point"}
}