{
  "type": "Feature",
  "properties": {
    "addr:full":"210 Magnolia Ave Vacaville CA 95688",
    "addr:housenumber":"210",
    "addr:postcode":"95688",
    "addr:street":"Magnolia Ave",
    "iso:country":"US",
    "sg:address":"210 Magnolia Ave",
    "sg:city":"Vacaville",
    "sg:classifiers":[
        {
            "category":"Retail",
            "subcategory":"Laundry & Dry Cleaning",
            "type":"Services"
        }
    ],
    "sg:phone":"+1 707 448 4423",
    "sg:postcode":"95688",
    "sg:province":"CA",
    "sg:tags":[
        "cleaners",
        "rug",
        "carpet"
    ],
    "wof:name":"911 Restoration",
    "wof:placetype":"venue"
},
  "geometry": {"coordinates":[-121.997495,38.354727],"type":"Point"}
}