{
  "type": "Feature",
  "properties": {
    "addr:full":"60 S Lassen St Susanville CA 96130",
    "addr:housenumber":"60",
    "addr:postcode":"96130",
    "addr:street":"S Lassen St",
    "iso:country":"US",
    "sg:address":"60 S Lassen St",
    "sg:city":"Susanville",
    "sg:classifiers":[
        {
            "category":"Professional",
            "subcategory":"Lawyer & Legal Services",
            "type":"Services"
        }
    ],
    "sg:phone":"+1 530 257 7330",
    "sg:postcode":"96130",
    "sg:province":"CA",
    "sg:tags":[
        "attorney"
    ],
    "wof:name":"John Lyman",
    "wof:placetype":"venue"
},
  "geometry": {"coordinates":[-120.662138,40.418033],"type":"Point"}
}