{
  "type": "Feature",
  "properties": {
    "iso:country":"US",
    "sg:address":"1825 Empire Industrial Ct",
    "sg:city":"Santa Rosa",
    "sg:classifiers":[
        {
            "category":"Real Estate",
            "subcategory":"Real Estate Services",
            "type":"Services"
        }
    ],
    "sg:phone":"+1 707 523 8010",
    "sg:postcode":"95403",
    "sg:province":"CA",
    "sg:tags":[
        "company",
        "title"
    ],
    "wof:name":"Financial Title Co",
    "wof:placetype":"venue"
},
  "geometry": {"coordinates":[-122.74775200000001,38.469876],"type":"Point"}
}