{
  "type": "Feature",
  "properties": {
    "addr:full":"2324 Bath St Santa Barbara CA 93105",
    "addr:housenumber":"2324",
    "addr:postcode":"93105",
    "addr:street":"Bath St",
    "iso:country":"US",
    "sg:address":"2324 Bath St",
    "sg:city":"Santa Barbara",
    "sg:classifiers":[
        {
            "category":"Health Services",
            "subcategory":"Health Practitioner",
            "type":"Services"
        }
    ],
    "sg:phone":"+1 805 682 3870",
    "sg:postcode":"93105",
    "sg:province":"CA",
    "sg:tags":[
        "therapist",
        "physical"
    ],
    "wof:name":"Muller & Weber Physical Thrpy",
    "wof:placetype":"venue"
},
  "geometry": {"coordinates":[-119.72323299999999,34.431405],"type":"Point"}
}