{
  "type": "Feature",
  "properties": {
    "addr:full":"102 Cochrane Rd Morgan Hill CA 95037",
    "addr:housenumber":"102",
    "addr:postcode":"95037",
    "addr:street":"Cochrane Rd",
    "iso:country":"US",
    "sg:address":"102 Cochrane Rd",
    "sg:city":"Morgan Hill",
    "sg:classifiers":[
        {
            "category":"Shopping",
            "subcategory":"Florist",
            "type":"Retail Goods"
        }
    ],
    "sg:phone":"+1 408 778 3737",
    "sg:postcode":"95037",
    "sg:province":"CA",
    "wof:name":"Flower's Patch",
    "wof:placetype":"venue"
},
  "geometry": {"coordinates":[-121.66112,37.147274],"type":"Point"}
}