{
  "type": "Feature",
  "properties": {
    "addr:full":"450 Silver Spur Rd Rancho Pls Vrds CA 90275",
    "addr:housenumber":"450",
    "addr:postcode":"90275",
    "addr:street":"Silver Spur Rd",
    "iso:country":"US",
    "sg:address":"450 Silver Spur Rd",
    "sg:city":"Rancho Pls Vrds",
    "sg:classifiers":[
        {
            "category":"Real Estate",
            "subcategory":"Real Estate Agent",
            "type":"Services"
        }
    ],
    "sg:phone":"+1 310 377 1524",
    "sg:postcode":"90275",
    "sg:province":"CA",
    "wof:name":"Duston Real Estate Svc",
    "wof:placetype":"venue"
},
  "geometry": {"coordinates":[-118.37213199999999,33.772444],"type":"Point"}
}