{
  "type": "Feature",
  "properties": {
    "addr:full":"1771 Weiss Ln Penngrove CA 94951",
    "addr:housenumber":"1771",
    "addr:postcode":"94951",
    "addr:street":"Weiss Ln",
    "iso:country":"US",
    "sg:address":"1771 Weiss Ln",
    "sg:city":"Penngrove",
    "sg:classifiers":[
        {
            "category":"Freight",
            "type":"Transportation"
        }
    ],
    "sg:phone":"+1 707 792 0160",
    "sg:postcode":"94951",
    "sg:province":"CA",
    "sg:tags":[
        "operator",
        "local",
        "trucking"
    ],
    "wof:name":"Fuller Moving Services",
    "wof:placetype":"venue"
},
  "geometry": {"coordinates":[-122.67416799999999,38.332165],"type":"Point"}
}