{
  "type": "Feature",
  "properties": {
    "iso:country":"US",
    "sg:address":"10285 San Pablo Ave",
    "sg:city":"El Cerrito",
    "sg:classifiers":[
        {
            "category":"Personal",
            "subcategory":"Massage",
            "type":"Services"
        }
    ],
    "sg:phone":"+1 510 526 5988",
    "sg:postcode":"94530",
    "sg:province":"CA",
    "wof:name":"Jin Jun Massage Therepy",
    "wof:placetype":"venue"
},
  "geometry": {"coordinates":[-122.30525299999999,37.905732],"type":"Point"}
}