{
  "type": "Feature",
  "properties": {
    "iso:country":"US",
    "sg:address":"441 Geary St",
    "sg:city":"San Francisco",
    "sg:classifiers":[
        {
            "category":"Retail",
            "subcategory":"Repair Shop",
            "type":"Services"
        }
    ],
    "sg:phone":"+1 415 345 8921",
    "sg:postcode":"94102",
    "sg:province":"CA",
    "sg:tags":[
        "lock",
        "locksmith"
    ],
    "wof:name":"24-Hours Emergency Locksmith",
    "wof:placetype":"venue"
},
  "geometry": {"coordinates":[-122.410857,37.786954],"type":"Point"}
}