{
  "type": "Feature",
  "properties": {
    "addr:full":"360 E Magnolia Blvd Burbank CA 91502",
    "addr:housenumber":"360",
    "addr:postcode":"91502",
    "addr:street":"E Magnolia Blvd",
    "iso:country":"US",
    "sg:address":"360 E Magnolia Blvd",
    "sg:city":"Burbank",
    "sg:classifiers":[
        {
            "category":"Banks & Credit Unions",
            "subcategory":"Bank",
            "type":"Services"
        },
        {
            "category":"Banks & Credit Unions",
            "subcategory":"Financial Services",
            "type":"Services"
        }
    ],
    "sg:phone":"+1 866 248 4937",
    "sg:postcode":"91502",
    "sg:province":"CA",
    "sg:tags":[
        "saving",
        "loan",
        "commercial",
        "card",
        "mortgage"
    ],
    "sg:website":"http://www.citibank.com",
    "wof:name":"Citibank",
    "wof:placetype":"venue"
},
  "geometry": {"coordinates":[-118.31343099999999,34.181486],"type":"Point"}
}