{
  "type": "Feature",
  "properties": {
    "addr:full":"155 Crescent Ave Portola Valley CA 94028",
    "addr:housenumber":"155",
    "addr:postcode":"94028",
    "addr:street":"Crescent Ave",
    "iso:country":"US",
    "sg:address":"155 Crescent Ave",
    "sg:city":"Portola Valley",
    "sg:classifiers":[
        {
            "category":"Professional",
            "subcategory":"Employment Agencies",
            "type":"Services"
        }
    ],
    "sg:phone":"+1 650 529 9010",
    "sg:postcode":"94028",
    "sg:province":"CA",
    "sg:tags":[
        "opportunity"
    ],
    "wof:name":"Baier Legal Search LLC",
    "wof:placetype":"venue"
},
  "geometry": {"coordinates":[-122.213342,37.369998],"type":"Point"}
}