{
  "type": "Feature",
  "properties": {
    "iso:country":"US",
    "sg:address":"3870 Valley Centre Dr Ste 302",
    "sg:city":"San Diego",
    "sg:classifiers":[
        {
            "category":"Restaurant",
            "type":"Food & Drink"
        }
    ],
    "sg:phone":"+1 858 792 5509",
    "sg:postcode":"92130",
    "sg:province":"CA",
    "sg:tags":[
        "sushi",
        "bar",
        "japanese"
    ],
    "wof:name":"Sushi A La Kaz",
    "wof:placetype":"venue"
},
  "geometry": {"coordinates":[-117.231003,32.937801],"type":"Point"}
}