{
  "type": "Feature",
  "properties": {
    "iso:country":"US",
    "sg:address":"5239 Auburn Blvd",
    "sg:city":"Sacramento",
    "sg:classifiers":[
        {
            "category":"Autos & Motor Vehicles",
            "subcategory":"Auto Supplies",
            "type":"Retail Goods"
        },
        {
            "category":"Retail",
            "subcategory":"Auto Repair",
            "type":"Services"
        }
    ],
    "sg:phone":"+1 916 332 9722",
    "sg:postcode":"95841",
    "sg:province":"CA",
    "sg:tags":[
        "muffler",
        "exhaust",
        "lube",
        "oil",
        "system"
    ],
    "sg:website":"http://www.midas.com",
    "wof:name":"Midas",
    "wof:placetype":"venue"
},
  "geometry": {"coordinates":[-121.34239700000001,38.664678],"type":"Point"}
}