{
  "type": "Feature",
  "properties": {
    "addr:full":"6460 Stockton Blvd Sacramento CA 95823",
    "addr:housenumber":"6460",
    "addr:postcode":"95823",
    "addr:street":"Stockton Blvd",
    "iso:country":"US",
    "sg:address":"6460 Stockton Blvd",
    "sg:city":"Sacramento",
    "sg:classifiers":[
        {
            "category":"Utilities",
            "subcategory":"Mobile Phone",
            "type":"Services"
        }
    ],
    "sg:phone":"+1 916 424 2758",
    "sg:postcode":"95823",
    "sg:province":"CA",
    "sg:tags":[
        "telephone",
        "cellular"
    ],
    "wof:name":"T & P Cellular",
    "wof:placetype":"venue"
},
  "geometry": {"coordinates":[-121.43471700000001,38.507882],"type":"Point"}
}