{
  "type": "Feature",
  "properties": {
    "addr:full":"122 2nd Ave San Mateo CA 94401",
    "addr:housenumber":"122",
    "addr:postcode":"94401",
    "addr:street":"2Nd Ave",
    "iso:country":"US",
    "sg:address":"122 2nd Ave",
    "sg:city":"San Mateo",
    "sg:classifiers":[
        {
            "category":"Organizations",
            "subcategory":"Religious Organization",
            "type":"Services"
        }
    ],
    "sg:phone":"+1 650 347 6605",
    "sg:postcode":"94401",
    "sg:province":"CA",
    "sg:tags":[
        "spiritualist"
    ],
    "wof:name":"Terry Ebinger",
    "wof:placetype":"venue"
},
  "geometry": {"coordinates":[-122.32632,37.56373],"type":"Point"}
}