{
  "type": "Feature",
  "properties": {
    "iso:country":"US",
    "sg:address":"14549 Archwood St",
    "sg:city":"Van Nuys",
    "sg:classifiers":[
        {
            "category":"Real Estate",
            "subcategory":"Real Estate Agent",
            "type":"Services"
        }
    ],
    "sg:phone":"+1 818 997 8033",
    "sg:postcode":"91405",
    "sg:province":"CA",
    "sg:tags":[
        "consultant"
    ],
    "wof:name":"Qes Inc",
    "wof:placetype":"venue"
},
  "geometry": {"coordinates":[-118.450386,34.193011],"type":"Point"}
}