{
  "type": "Feature",
  "properties": {
    "addr:full":"6700 Five Star Blvd Rocklin CA 95677",
    "addr:housenumber":"6700",
    "addr:postcode":"95677",
    "addr:street":"Five Star Blvd",
    "iso:country":"US",
    "sg:address":"6700 Five Star Blvd",
    "sg:city":"Rocklin",
    "sg:classifiers":[
        {
            "category":"Food & Beverages",
            "subcategory":"Groceries & Convenience Stores",
            "type":"Retail Goods"
        }
    ],
    "sg:phone":"+1 916 624 1385",
    "sg:postcode":"95677",
    "sg:province":"CA",
    "wof:name":"Valero",
    "wof:placetype":"venue"
},
  "geometry": {"coordinates":[-121.263927,38.780497],"type":"Point"}
}