{
  "type": "Feature",
  "properties": {
    "iso:country":"US",
    "sg:address":"630 S Glassell St Ste 104",
    "sg:city":"Orange",
    "sg:classifiers":[
        {
            "category":"Autos & Motor Vehicles",
            "subcategory":"Automobile Sales",
            "type":"Retail Goods"
        }
    ],
    "sg:phone":"+1 888 600 9446",
    "sg:postcode":"92866",
    "sg:province":"CA",
    "sg:tags":[
        "car"
    ],
    "wof:name":"Sheltons Motorcars",
    "wof:placetype":"venue"
},
  "geometry": {"coordinates":[-117.853341,33.778046],"type":"Point"}
}