{
  "type": "Feature",
  "properties": {
    "addr:full":"13945 Close St Whittier CA 90605",
    "addr:housenumber":"13945",
    "addr:postcode":"90605",
    "addr:street":"Close St",
    "iso:country":"US",
    "sg:address":"13945 Close St",
    "sg:city":"Whittier",
    "sg:classifiers":[
        {
            "category":"Building & Trades",
            "subcategory":"Construction",
            "type":"Services"
        }
    ],
    "sg:phone":"+1 562 941 2890",
    "sg:postcode":"90605",
    "sg:province":"CA",
    "sg:tags":[
        "home",
        "builder"
    ],
    "wof:name":"Casa Bonita Homes",
    "wof:placetype":"venue"
},
  "geometry": {"coordinates":[-118.037847,33.941093],"type":"Point"}
}