{
  "type": "Feature",
  "properties": {
    "iso:country":"US",
    "sg:address":"2105 Forest Ave",
    "sg:city":"San Jose",
    "sg:classifiers":[
        {
            "category":"Professional",
            "type":"Services"
        }
    ],
    "sg:phone":"+1 408 947 2553",
    "sg:postcode":"95128",
    "sg:province":"CA",
    "wof:name":"Chw South Bay",
    "wof:placetype":"venue"
},
  "geometry": {"coordinates":[-121.93803200000001,37.327126],"type":"Point"}
}