{
  "type": "Feature",
  "properties": {
    "iso:country":"US",
    "sg:address":"20341 Gunstock Rd",
    "sg:city":"Grass Valley",
    "sg:classifiers":[
        {
            "category":"Wholesale",
            "subcategory":"Non-durable Goods",
            "type":"Manufacturing & Wholesale Goods"
        }
    ],
    "sg:phone":"+1 530 913 3105",
    "sg:postcode":"95949",
    "sg:province":"CA",
    "wof:name":"Old West Horseshoeing",
    "wof:placetype":"venue"
},
  "geometry": {"coordinates":[-121.008557,39.076952],"type":"Point"}
}