{
  "type": "Feature",
  "properties": {
    "iso:country":"US",
    "sg:address":"2656 Newport Boulevard",
    "sg:city":"Costa Mesa",
    "sg:classifiers":[
        {
            "category":"Travel",
            "subcategory":"Hotels & Motels",
            "type":"Entertainment"
        }
    ],
    "sg:phone":"+1 949 650 6666",
    "sg:postcode":"92627",
    "sg:province":"CA",
    "wof:name":"Star Inn Best Kept Secret",
    "wof:placetype":"venue"
},
  "geometry": {"coordinates":[-117.894981,33.66479],"type":"Point"}
}