{
  "type": "Feature",
  "properties": {
    "addr:full":"1722 State Hwy 99 Gridley CA 95948",
    "addr:housenumber":"1722",
    "addr:postcode":"95948",
    "addr:street":"State Hwy 99",
    "iso:country":"US",
    "sg:address":"1722 State Hwy 99",
    "sg:city":"Gridley",
    "sg:classifiers":[
        {
            "category":"Autos & Motor Vehicles",
            "subcategory":"Automobile Sales",
            "type":"Retail Goods"
        },
        {
            "category":"Professional",
            "type":"Services"
        }
    ],
    "sg:phone":"+1 530 846 6700",
    "sg:postcode":"95948",
    "sg:province":"CA",
    "sg:tags":[
        "car",
        "dealer"
    ],
    "wof:name":"Lewis Dow Motors Inc",
    "wof:placetype":"venue"
},
  "geometry": {"coordinates":[-121.687838,39.369978],"type":"Point"}
}