{
  "type": "Feature",
  "properties": {
    "addr:city":"San Mateo",
    "addr:full":"1366 Rainbow Dr San Mateo, Ca 94402",
    "addr:house_number":"1366",
    "addr:housenumber":"1366",
    "addr:phone":"+1 650-341-1917",
    "addr:postcode":"94402",
    "addr:road":"Rainbow Dr",
    "addr:state":"CA",
    "addr:street":"Rainbow Dr",
    "iso:country":"US",
    "sg:address":"1366 Rainbow Dr",
    "sg:city":"San Mateo",
    "sg:classifiers":[
        {
            "category":"Museum",
            "type":"Entertainment"
        }
    ],
    "sg:phone":"+1 650 341 1917",
    "sg:postcode":"94402",
    "sg:province":"CA",
    "wof:airports":[
        102527513,
        102531041,
        102528839,
        102529949,
        102533677
    ],
    "wof:name":"Center For American Musical",
    "wof:placetype":"venue"
},
  "geometry": {"coordinates":[-122.34797,37.53223],"type":"Point"}
}