{
  "type": "Feature",
  "properties": {
    "addr:full":"1366 Rainbow Dr San Mateo CA 94402",
    "addr:housenumber":"1366",
    "addr:postcode":"94402",
    "addr:street":"Rainbow Dr",
    "iso:country":"US",
    "sg:address":"1366 Rainbow Dr",
    "sg:city":"San Mateo",
    "sg:classifiers":[
        {
            "category":"Museum",
            "type":"Entertainment"
        }
    ],
    "sg:phone":"+1 650 341 1917",
    "sg:postcode":"94402",
    "sg:province":"CA",
    "wof:name":"Center For American Musical",
    "wof:placetype":"venue"
},
  "geometry": {"coordinates":[-122.34676399999999,37.533041],"type":"Point"}
}