{
  "type": "Feature",
  "properties": {
    "addr:full":"1807 Pacific Coast Hwy Lomita CA 90717",
    "addr:housenumber":"1807",
    "addr:postcode":"90717",
    "addr:street":"Pacific Coast Hwy",
    "iso:country":"US",
    "sg:address":"1807 Pacific Coast Hwy",
    "sg:city":"Lomita",
    "sg:classifiers":[
        {
            "category":"Shopping",
            "subcategory":"Bicycles & Sporting Goods",
            "type":"Retail Goods"
        }
    ],
    "sg:phone":"+1 310 534 2993",
    "sg:postcode":"90717",
    "sg:province":"CA",
    "sg:tags":[
        "tackle",
        "fishing"
    ],
    "wof:name":"Cris's Fishing Tackle",
    "wof:placetype":"venue"
},
  "geometry": {"coordinates":[-118.309524,33.78946],"type":"Point"}
}