{
  "type": "Feature",
  "properties": {
    "iso:country":"US",
    "sg:address":"49 Quail Ct",
    "sg:city":"Walnut Creek",
    "sg:classifiers":[
        {
            "category":"Insurance",
            "subcategory":"Health Insurance",
            "type":"Services"
        },
        {
            "category":"Building & Trades",
            "subcategory":"Construction",
            "type":"Services"
        }
    ],
    "sg:phone":"+1 925 746 5100",
    "sg:postcode":"94596",
    "sg:province":"CA",
    "sg:tags":[
        "plan",
        "contractor"
    ],
    "wof:name":"Integrated Health Care Assn",
    "wof:placetype":"venue"
},
  "geometry": {"coordinates":[-122.055618,37.888353],"type":"Point"}
}