{
  "type": "Feature",
  "properties": {
    "addr:full":"5216 Wall Ave Richmond CA 94804",
    "addr:housenumber":"5216",
    "addr:postcode":"94804",
    "addr:street":"Wall Ave",
    "iso:country":"US",
    "sg:address":"5216 Wall Ave",
    "sg:city":"Richmond",
    "sg:classifiers":[
        {
            "category":"Building & Trades",
            "subcategory":"Construction",
            "type":"Services"
        }
    ],
    "sg:phone":"+1 510 235 2700",
    "sg:postcode":"94804",
    "sg:province":"CA",
    "sg:tags":[
        "general",
        "contractor"
    ],
    "wof:name":"Coleman Construction",
    "wof:placetype":"venue"
},
  "geometry": {"coordinates":[-122.323418,37.927966],"type":"Point"}
}