{
  "type": "Feature",
  "properties": {
    "addr:full":"10775 Chantel Ln Stockton CA 95212",
    "addr:housenumber":"10775",
    "addr:postcode":"95212",
    "addr:street":"Chantel Ln",
    "iso:country":"US",
    "sg:address":"10775 Chantel Ln",
    "sg:city":"Stockton",
    "sg:classifiers":[
        {
            "category":"Building & Trades",
            "subcategory":"Construction",
            "type":"Services"
        }
    ],
    "sg:phone":"+1 209 931 2225",
    "sg:postcode":"95212",
    "sg:province":"CA",
    "sg:tags":[
        "concrete",
        "contractor"
    ],
    "wof:name":"Rd Concrete Construction",
    "wof:placetype":"venue"
},
  "geometry": {"coordinates":[-121.24373199999999,38.055983],"type":"Point"}
}