{
  "type": "Feature",
  "properties": {
    "addr:full":"2999 Regent St Berkeley CA 94705",
    "addr:housenumber":"2999",
    "addr:postcode":"94705",
    "addr:street":"Regent St",
    "iso:country":"US",
    "sg:address":"2999 Regent St",
    "sg:city":"Berkeley",
    "sg:classifiers":[
        {
            "category":"Health Services",
            "subcategory":"Doctor",
            "type":"Services"
        }
    ],
    "sg:phone":"+1 510 549 0734",
    "sg:postcode":"94705",
    "sg:province":"CA",
    "sg:tags":[
        "physician",
        "surgeon"
    ],
    "wof:name":"Ronald L Elson MD",
    "wof:placetype":"venue"
},
  "geometry": {"coordinates":[-122.256834,37.856549],"type":"Point"}
}