{
  "type": "Feature",
  "properties": {
    "iso:country":"US",
    "sg:address":"420 W Pine St",
    "sg:city":"Lodi",
    "sg:classifiers":[
        {
            "category":"Professional",
            "subcategory":"Accounting & Tax Preparation",
            "type":"Services"
        }
    ],
    "sg:phone":"+1 209 334 3497",
    "sg:postcode":"95240",
    "sg:province":"CA",
    "sg:tags":[
        "accountant"
    ],
    "wof:name":"Matthew Mc Gladdery CPA",
    "wof:placetype":"venue"
},
  "geometry": {"coordinates":[-121.278845,38.13434],"type":"Point"}
}