{
  "type": "Feature",
  "properties": {
    "addr:full":"Marukai Shopping Center 19750 Stevens Creek Blvd Cupertino CA 95014",
    "addr:housenumber":"19750",
    "addr:postcode":"95014",
    "addr:street":"Stevens Creek Blvd",
    "iso:country":"US",
    "sg:address":"Marukai Shopping Center 19750 Stevens Creek Blvd",
    "sg:city":"Cupertino",
    "sg:classifiers":[
        {
            "category":"Bakery",
            "type":"Food & Drink"
        }
    ],
    "sg:phone":"+1 408 725 9400",
    "sg:postcode":"95014",
    "sg:province":"CA",
    "wof:name":"Takaki Bakery",
    "wof:placetype":"venue"
},
  "geometry": {"coordinates":[-122.018444,37.321734],"type":"Point"}
}