{
  "type": "Feature",
  "properties": {
    "iso:country":"US",
    "sg:address":"160 E Holt Ave",
    "sg:city":"Pomona",
    "sg:classifiers":[
        {
            "category":"Health Services",
            "subcategory":"Chiropractor",
            "type":"Services"
        }
    ],
    "sg:phone":"+1 909 397 5788",
    "sg:postcode":"91767",
    "sg:province":"CA",
    "wof:name":"Centro De Accidentes",
    "wof:placetype":"venue"
},
  "geometry": {"coordinates":[-117.749452,34.062324],"type":"Point"}
}