{
  "type": "Feature",
  "properties": {
    "iso:country":"US",
    "sg:address":"1707 W Chapman Ave",
    "sg:city":"Orange",
    "sg:classifiers":[
        {
            "category":"Health Services",
            "subcategory":"Chiropractor",
            "type":"Services"
        }
    ],
    "sg:phone":"+1 714 634 8036",
    "sg:postcode":"92868",
    "sg:province":"CA",
    "wof:name":"Chiro Body Care",
    "wof:placetype":"venue"
},
  "geometry": {"coordinates":[-117.871002,33.7878],"type":"Point"}
}