{
  "type": "Feature",
  "properties": {
    "iso:country":"US",
    "sg:address":"3101 Mill Creek Rd",
    "sg:city":"Healdsburg",
    "sg:classifiers":[
        {
            "category":"Building & Trades",
            "subcategory":"Construction",
            "type":"Services"
        }
    ],
    "sg:phone":"+1 707 433 4946",
    "sg:postcode":"95448",
    "sg:province":"CA",
    "sg:tags":[
        "excavation",
        "contractor"
    ],
    "wof:name":"Bertalon Backhoe Service",
    "wof:placetype":"venue"
},
  "geometry": {"coordinates":[-122.916202,38.59461],"type":"Point"}
}