{
  "type": "Feature",
  "properties": {
    "iso:country":"US",
    "sg:address":"170 Maiden Ln",
    "sg:city":"San Francisco",
    "sg:classifiers":[
        {
            "category":"Real Estate",
            "subcategory":"Architect",
            "type":"Services"
        }
    ],
    "sg:phone":"+1 415 391 1080",
    "sg:postcode":"94108",
    "sg:province":"CA",
    "sg:website":"www.hornbergerworstell.com/",
    "wof:name":"Hornberger & Worstell",
    "wof:placetype":"venue"
},
  "geometry": {"coordinates":[-122.406285,37.788099],"type":"Point"}
}