{
  "type": "Feature",
  "properties": {
    "iso:country":"US",
    "sg:address":"22106 Clarendon St",
    "sg:city":"Woodland Hills",
    "sg:classifiers":[
        {
            "category":"Wholesale",
            "subcategory":"Sporting Goods",
            "type":"Manufacturing & Wholesale Goods"
        }
    ],
    "sg:phone":"+1 818 225 8883",
    "sg:postcode":"91367",
    "sg:province":"CA",
    "wof:name":"HTESPUSA Corp",
    "wof:placetype":"venue"
},
  "geometry": {"coordinates":[-118.60717,34.169567],"type":"Point"}
}