{
  "type": "Feature",
  "properties": {
    "addr:full":"15131 Vermont St Westminster CA 92683",
    "addr:housenumber":"15131",
    "addr:postcode":"92683",
    "addr:street":"Vermont St",
    "iso:country":"US",
    "sg:address":"15131 Vermont St",
    "sg:city":"Westminster",
    "sg:classifiers":[
        {
            "category":"Wholesale",
            "subcategory":"Groceries",
            "type":"Manufacturing & Wholesale Goods"
        }
    ],
    "sg:phone":"+1 714 901 1835",
    "sg:postcode":"92683",
    "sg:province":"CA",
    "sg:tags":[
        "general"
    ],
    "wof:name":"Bills & Assoc",
    "wof:placetype":"venue"
},
  "geometry": {"coordinates":[-118.003715,33.74265],"type":"Point"}
}