{
  "type": "Feature",
  "properties": {
    "addr:full":"1221 S El Camino Real San Mateo CA 94402",
    "addr:housenumber":"1221",
    "addr:postcode":"94402",
    "addr:street":"S El Camino Real",
    "iso:country":"US",
    "sg:address":"1221 S El Camino Real",
    "sg:city":"San Mateo",
    "sg:classifiers":[
        {
            "category":"Real Estate",
            "subcategory":"Real Estate Services",
            "type":"Services"
        }
    ],
    "sg:phone":"+1 650 341 2325",
    "sg:postcode":"94402",
    "sg:province":"CA",
    "sg:tags":[
        "management",
        "property"
    ],
    "wof:name":"Beck Bros",
    "wof:placetype":"venue"
},
  "geometry": {"coordinates":[-122.317798,37.555707],"type":"Point"}
}