{
  "type": "Feature",
  "properties": {
    "addr:full":"765 E Foothill Blvd Rialto CA 92376",
    "addr:housenumber":"765",
    "addr:postcode":"92376",
    "addr:street":"E Foothill Blvd",
    "iso:country":"US",
    "sg:address":"765 E Foothill Blvd",
    "sg:city":"Rialto",
    "sg:classifiers":[
        {
            "category":"Fast Food",
            "type":"Food & Drink"
        },
        {
            "category":"Restaurant",
            "type":"Food & Drink"
        }
    ],
    "sg:phone":"+1 909 874 4894",
    "sg:postcode":"92376",
    "sg:province":"CA",
    "sg:tags":[
        "hot",
        "hamburger",
        "dog"
    ],
    "wof:name":"Jim's Burger",
    "wof:placetype":"venue"
},
  "geometry": {"coordinates":[-117.356723,34.10677],"type":"Point"}
}