{
  "type": "Feature",
  "properties": {
    "iso:country":"US",
    "sg:address":"20311 Bermuda St",
    "sg:city":"Chatsworth",
    "sg:classifiers":[
        {
            "category":"Professional",
            "subcategory":"Employment Agencies",
            "type":"Services"
        }
    ],
    "sg:phone":"+1 818 717 9008",
    "sg:postcode":"91311",
    "sg:province":"CA",
    "sg:tags":[
        "opportunity"
    ],
    "wof:name":"Westmore Corp Rj",
    "wof:placetype":"venue"
},
  "geometry": {"coordinates":[-118.576111,34.266275],"type":"Point"}
}