{
  "type": "Feature",
  "properties": {
    "iso:country":"US",
    "sg:address":"702 W Taylor St",
    "sg:city":"San Jose",
    "sg:classifiers":[
        {
            "category":"Shopping",
            "subcategory":"Antiques",
            "type":"Retail Goods"
        },
        {
            "category":"Shopping",
            "subcategory":"Used Merchandise",
            "type":"Retail Goods"
        }
    ],
    "sg:phone":"+1 408 298 7600",
    "sg:postcode":"95126",
    "sg:province":"CA",
    "sg:tags":[
        "vintage",
        "consignment"
    ],
    "wof:name":"The Salvation Army",
    "wof:placetype":"venue"
},
  "geometry": {"coordinates":[-121.914001,37.340401],"type":"Point"}
}