{
  "type": "Feature",
  "properties": {
    "addr:full":"3304 Motor Ave Los Angeles CA 90034",
    "addr:housenumber":"3304",
    "addr:postcode":"90034",
    "addr:street":"Motor Ave",
    "iso:country":"US",
    "sg:address":"3304 Motor Ave",
    "sg:city":"Los Angeles",
    "sg:classifiers":[
        {
            "category":"Shopping",
            "subcategory":"Crafts & Fabrics",
            "type":"Retail Goods"
        }
    ],
    "sg:phone":"+1 310 559 4323",
    "sg:postcode":"90034",
    "sg:province":"CA",
    "sg:tags":[
        "store"
    ],
    "sg:website":"www.normsfoam.com/1401.html",
    "wof:name":"Norm's Foam & Fabric Center",
    "wof:placetype":"venue"
},
  "geometry": {"coordinates":[-118.410511,34.029039],"type":"Point"}
}