{
  "type": "Feature",
  "properties": {
    "iso:country":"US",
    "sg:address":"3111 Los Feliz Blvd",
    "sg:city":"Los Angeles",
    "sg:classifiers":[
        {
            "category":"Insurance",
            "subcategory":"Insurance Agent",
            "type":"Services"
        }
    ],
    "sg:phone":"+1 323 953 0434",
    "sg:postcode":"90039",
    "sg:province":"CA",
    "wof:name":"Special Insurance Svc",
    "wof:placetype":"venue"
},
  "geometry": {"coordinates":[-118.267318,34.124224],"type":"Point"}
}