{
  "type": "Feature",
  "properties": {
    "addr:full":"8792 Cerritos Ave Anaheim CA 92804",
    "addr:housenumber":"8792",
    "addr:postcode":"92804",
    "addr:street":"Cerritos Ave",
    "iso:country":"US",
    "sg:address":"8792 Cerritos Ave",
    "sg:city":"Anaheim",
    "sg:classifiers":[
        {
            "category":"Health Services",
            "subcategory":"Hospice",
            "type":"Services"
        },
        {
            "category":"Social Services",
            "subcategory":"Retirement Home",
            "type":"Services"
        }
    ],
    "sg:phone":"+1 714 952 3795",
    "sg:postcode":"92804",
    "sg:province":"CA",
    "sg:tags":[
        "convalescent",
        "nursing"
    ],
    "wof:name":"Wells House Hospice",
    "wof:placetype":"venue"
},
  "geometry": {"coordinates":[-117.978854,33.810339],"type":"Point"}
}