{
  "type": "Feature",
  "properties": {
    "iso:country":"US",
    "sg:address":"106 S Azusa Ave",
    "sg:city":"Azusa",
    "sg:classifiers":[
        {
            "category":"Autos & Motor Vehicles",
            "subcategory":"Fuel & Gas Station",
            "type":"Retail Goods"
        }
    ],
    "sg:phone":"+1 626 334 2794",
    "sg:postcode":"91702",
    "sg:province":"CA",
    "sg:tags":[
        "oil"
    ],
    "wof:name":"Shell",
    "wof:placetype":"venue"
},
  "geometry": {"coordinates":[-117.90743000000001,34.121031],"type":"Point"}
}