{
  "type": "Feature",
  "properties": {
    "addr:full":"19 W 6th St Stockton CA 95206",
    "addr:housenumber":"19",
    "addr:postcode":"95206",
    "addr:street":"W 6Th St",
    "iso:country":"US",
    "sg:address":"19 W 6th St",
    "sg:city":"Stockton",
    "sg:classifiers":[
        {
            "category":"Real Estate",
            "subcategory":"Real Estate Services",
            "type":"Services"
        },
        {
            "category":"Real Estate",
            "subcategory":"Real Estate Agent",
            "type":"Services"
        }
    ],
    "sg:phone":"+1 209 982 5773",
    "sg:postcode":"95206",
    "sg:province":"CA",
    "sg:tags":[
        "buyer",
        "broker"
    ],
    "wof:name":"Don Cose & Assoc",
    "wof:placetype":"venue"
},
  "geometry": {"coordinates":[-121.28412,37.931209],"type":"Point"}
}