{
  "type": "Feature",
  "properties": {
    "addr:full":"110 S Pine St Santa Maria CA 93458",
    "addr:housenumber":"110",
    "addr:postcode":"93458",
    "addr:street":"S Pine St",
    "iso:country":"US",
    "sg:address":"110 S Pine St",
    "sg:city":"Santa Maria",
    "sg:classifiers":[
        {
            "category":"Restaurant",
            "type":"Food & Drink"
        }
    ],
    "sg:phone":"+1 805 922 5202",
    "sg:postcode":"93458",
    "sg:province":"CA",
    "sg:tags":[
        "eating"
    ],
    "wof:name":"Cafe Off Pine St",
    "wof:placetype":"venue"
},
  "geometry": {"coordinates":[-120.438862,34.952574],"type":"Point"}
}