{
  "type": "Feature",
  "properties": {
    "addr:full":"5995 Brockton Ave Riverside CA 92506",
    "addr:housenumber":"5995",
    "addr:postcode":"92506",
    "addr:street":"Brockton Ave",
    "iso:country":"US",
    "sg:address":"5995 Brockton Ave",
    "sg:city":"Riverside",
    "sg:classifiers":[
        {
            "category":"Health Services",
            "subcategory":"Chiropractor",
            "type":"Services"
        }
    ],
    "sg:phone":"+1 951 323 7783",
    "sg:postcode":"92506",
    "sg:province":"CA",
    "sg:website":"http://www.millenniumchiropractic.info",
    "wof:name":"Millennium Chiropractic",
    "wof:placetype":"venue"
},
  "geometry": {"coordinates":[-117.39671800000001,33.96091],"type":"Point"}
}