{
  "type": "Feature",
  "properties": {
    "addr:full":"10590 Magnolia Ave Riverside CA 92505",
    "addr:housenumber":"10590",
    "addr:postcode":"92505",
    "addr:street":"Magnolia Ave",
    "iso:country":"US",
    "sg:address":"10590 Magnolia Ave",
    "sg:city":"Riverside",
    "sg:classifiers":[
        {
            "category":"Social Services",
            "type":"Services"
        }
    ],
    "sg:phone":"+1 951 353 1024",
    "sg:postcode":"92505",
    "sg:province":"CA",
    "sg:tags":[
        "organization",
        "welfare"
    ],
    "wof:name":"Armenian Relief Society",
    "wof:placetype":"venue"
},
  "geometry": {"coordinates":[-117.464894,33.909863],"type":"Point"}
}