{
  "type": "Feature",
  "properties": {
    "iso:country":"US",
    "sg:address":"6260 Laurel Canyon Blvd Ste 205",
    "sg:city":"North Hollywood",
    "sg:classifiers":[
        {
            "category":"Autos & Motor Vehicles",
            "subcategory":"Automobile Sales",
            "type":"Retail Goods"
        }
    ],
    "sg:phone":"+1 818 769 7019",
    "sg:postcode":"91606",
    "sg:province":"CA",
    "sg:tags":[
        "limo"
    ],
    "sg:website":"www.arrowlimos.com",
    "wof:name":"Arrow Limo Service",
    "wof:placetype":"venue"
},
  "geometry": {"coordinates":[-118.396354,34.184775],"type":"Point"}
}