{
  "type": "Feature",
  "properties": {
    "iso:country":"US",
    "sg:address":"4066 Folsom Dr",
    "sg:city":"Antioch",
    "sg:classifiers":[
        {
            "category":"Social Services",
            "subcategory":"Adult Care",
            "type":"Services"
        }
    ],
    "sg:phone":"+1 925 706 7444",
    "sg:postcode":"94531",
    "sg:province":"CA",
    "sg:tags":[
        "nurses-home"
    ],
    "wof:name":"Health Pass",
    "wof:placetype":"venue"
},
  "geometry": {"coordinates":[-121.765548,37.98699],"type":"Point"}
}