{
  "type": "Feature",
  "properties": {
    "iso:country":"US",
    "sg:address":"405 S Chester Ave",
    "sg:city":"Bakersfield",
    "sg:classifiers":[
        {
            "category":"Real Estate",
            "subcategory":"Real Estate Services",
            "type":"Services"
        },
        {
            "category":"Real Estate",
            "subcategory":"Real Estate Agent",
            "type":"Services"
        }
    ],
    "sg:phone":"+1 661 834 1111",
    "sg:postcode":"93304",
    "sg:province":"CA",
    "sg:tags":[
        "buyer",
        "broker"
    ],
    "wof:name":"Deerot Realty",
    "wof:placetype":"venue"
},
  "geometry": {"coordinates":[-119.018928,35.350319],"type":"Point"}
}