{
  "type": "Feature",
  "properties": {
    "addr:full":"1482 Sylvaner Ave Saint Helena CA 94574",
    "addr:housenumber":"1482",
    "addr:postcode":"94574",
    "addr:street":"Sylvaner Ave",
    "iso:country":"US",
    "sg:address":"1482 Sylvaner Ave",
    "sg:city":"Saint Helena",
    "sg:classifiers":[
        {
            "category":"Manufacturing",
            "subcategory":"Food",
            "type":"Manufacturing & Wholesale Goods"
        }
    ],
    "sg:phone":"+1 707 963 8157",
    "sg:postcode":"94574",
    "sg:province":"CA",
    "sg:tags":[
        "mfg"
    ],
    "wof:name":"Blackford Cellars",
    "wof:placetype":"venue"
},
  "geometry": {"coordinates":[-122.475577,38.495062],"type":"Point"}
}