{
  "type": "Feature",
  "properties": {
    "addr:full":"412 N. cedros Ave Solana Beach CA 92075",
    "addr:housenumber":"412",
    "addr:postcode":"92075",
    "addr:street":"N. Cedros Ave",
    "iso:country":"US",
    "sg:address":"412 N. cedros Ave",
    "sg:city":"Solana Beach",
    "sg:classifiers":[
        {
            "category":"Professional",
            "subcategory":"Research",
            "type":"Services"
        }
    ],
    "sg:phone":"+1 619 236 9924",
    "sg:postcode":"92075",
    "sg:province":"CA",
    "sg:tags":[
        "green-building",
        "sustainability",
        "bamboo",
        "eco-friendly",
        "design",
        "design-materials",
        "wheatboard",
        "cocount-tiles",
        "tiles",
        "surfacing",
        "architecture",
        "interior-design"
    ],
    "sg:website":"http://www.kireiusa.com",
    "wof:name":"Kirei USA",
    "wof:placetype":"venue"
},
  "geometry": {"coordinates":[-117.27298,32.998734],"type":"Point"}
}