{
  "type": "Feature",
  "properties": {
    "addr:full":"6810 Fair Oaks Blvd Carmichael CA 95608",
    "addr:housenumber":"6810",
    "addr:postcode":"95608",
    "addr:street":"Fair Oaks Blvd",
    "iso:country":"US",
    "sg:address":"6810 Fair Oaks Blvd",
    "sg:city":"Carmichael",
    "sg:classifiers":[
        {
            "category":"Home & Garden",
            "subcategory":"Building Materials",
            "type":"Retail Goods"
        }
    ],
    "sg:phone":"+1 916 486 2888",
    "sg:postcode":"95608",
    "sg:province":"CA",
    "sg:tags":[
        "glass",
        "installation",
        "contractor"
    ],
    "wof:name":"Carmichael Glass",
    "wof:placetype":"venue"
},
  "geometry": {"coordinates":[-121.328295,38.62548],"type":"Point"}
}