{
  "type": "Feature",
  "properties": {
    "addr:full":"3350 Naglee Rd Tracy CA 95304",
    "addr:housenumber":"3350",
    "addr:postcode":"95304",
    "addr:street":"Naglee Rd",
    "iso:country":"US",
    "sg:address":"3350 Naglee Rd",
    "sg:city":"Tracy",
    "sg:classifiers":[
        {
            "category":"Shopping",
            "subcategory":"Optical Goods",
            "type":"Retail Goods"
        }
    ],
    "sg:phone":"+1 209 839 8747",
    "sg:postcode":"95304",
    "sg:province":"CA",
    "wof:name":"Sears Optical",
    "wof:placetype":"venue"
},
  "geometry": {"coordinates":[-121.462236,37.760528],"type":"Point"}
}