{
  "type": "Feature",
  "properties": {
    "addr:full":"1150 S Main St Salinas CA 93901",
    "addr:housenumber":"1150",
    "addr:postcode":"93901",
    "addr:street":"S Main St",
    "iso:country":"US",
    "sg:address":"1150 S Main St",
    "sg:city":"Salinas",
    "sg:classifiers":[
        {
            "category":"Food & Beverages",
            "subcategory":"Supermarket",
            "type":"Retail Goods"
        },
        {
            "category":"Shopping",
            "subcategory":"Pharmacy",
            "type":"Retail Goods"
        },
        {
            "category":"Food & Beverages",
            "subcategory":"Groceries & Convenience Stores",
            "type":"Retail Goods"
        }
    ],
    "sg:phone":"+1 831 758 8233",
    "sg:postcode":"93901",
    "sg:province":"CA",
    "sg:tags":[
        "super"
    ],
    "sg:website":"http://national.citysearch.com/profile/external/813449/salinas_ca/save_mart_supermarkets.html?publisher=yellowpages&reference_id=1&placement=ypwebsitemip",
    "wof:name":"Save Mart Supermarkets",
    "wof:placetype":"venue"
},
  "geometry": {"coordinates":[-121.659012,36.658871],"type":"Point"}
}