{
  "type": "Feature",
  "properties": {
    "iso:country":"US",
    "sg:address":"2323 Broadway",
    "sg:city":"San Diego",
    "sg:classifiers":[
        {
            "category":"Arts & Performance",
            "subcategory":"Arts Center",
            "type":"Entertainment"
        }
    ],
    "sg:phone":"+1 619 238 5104",
    "sg:postcode":"92102",
    "sg:province":"CA",
    "sg:tags":[
        "performing"
    ],
    "wof:name":"Ballet Basics",
    "wof:placetype":"venue"
},
  "geometry": {"coordinates":[-117.125,32.717999],"type":"Point"}
}