{
  "type": "Feature",
  "properties": {
    "iso:country":"US",
    "sg:address":"1968 Cummings Dr",
    "sg:city":"Los Angeles",
    "sg:classifiers":[
        {
            "category":"Wholesale",
            "subcategory":"Farm Supplies",
            "type":"Manufacturing & Wholesale Goods"
        }
    ],
    "sg:phone":"+1 323 660 1088",
    "sg:postcode":"90027",
    "sg:province":"CA",
    "sg:tags":[
        "control",
        "equipment",
        "pest"
    ],
    "wof:name":"P S Products Co",
    "wof:placetype":"venue"
},
  "geometry": {"coordinates":[-118.30192,34.106751],"type":"Point"}
}