{
  "type": "Feature",
  "properties": {
    "addr:full":"635 Baker Street Costa Mesa CA 92627",
    "addr:housenumber":"635",
    "addr:postcode":"92627",
    "addr:street":"Baker Street",
    "iso:country":"US",
    "sg:address":"635 Baker Street",
    "sg:city":"Costa Mesa",
    "sg:classifiers":[
        {
            "category":"Arts & Performance",
            "subcategory":"Music",
            "type":"Entertainment"
        }
    ],
    "sg:phone":"+1 714 381 2637",
    "sg:postcode":"92627",
    "sg:province":"CA",
    "sg:tags":[
        "dj"
    ],
    "wof:name":"Save The Rhythm Productions",
    "wof:placetype":"venue"
},
  "geometry": {"coordinates":[-117.88188100000001,33.679202],"type":"Point"}
}