{
  "type": "Feature",
  "properties": {
    "addr:full":"75 Perry St Redwood City CA 94063",
    "addr:housenumber":"75",
    "addr:postcode":"94063",
    "addr:street":"Perry St",
    "iso:country":"US",
    "sg:address":"75 Perry St",
    "sg:city":"Redwood City",
    "sg:classifiers":[
        {
            "category":"Building & Trades",
            "subcategory":"Construction",
            "type":"Services"
        }
    ],
    "sg:phone":"+1 650 368 8912",
    "sg:postcode":"94063",
    "sg:province":"CA",
    "sg:tags":[
        "restoration",
        "cleaning",
        "patio",
        "deck"
    ],
    "wof:name":"Sylvan's Pressure Cleaning",
    "wof:placetype":"venue"
},
  "geometry": {"coordinates":[-122.235226,37.487676],"type":"Point"}
}