{
  "type": "Feature",
  "properties": {
    "iso:country":"US",
    "sg:address":"4555 E Shields Ave",
    "sg:city":"Fresno",
    "sg:classifiers":[
        {
            "category":"Real Estate",
            "subcategory":"Real Estate Operator",
            "type":"Services"
        }
    ],
    "sg:phone":"+1 559 251 3408",
    "sg:postcode":"93726",
    "sg:province":"CA",
    "sg:tags":[
        "apartment"
    ],
    "wof:name":"Capri Nuevo Apartments",
    "wof:placetype":"venue"
},
  "geometry": {"coordinates":[-119.745478,36.779622],"type":"Point"}
}