{
  "type": "Feature",
  "properties": {
    "addr:full":"1551 4th Ave San Diego CA 92101",
    "addr:housenumber":"1551",
    "addr:postcode":"92101",
    "addr:street":"4Th Ave",
    "iso:country":"US",
    "sg:address":"1551 4th Ave",
    "sg:city":"San Diego",
    "sg:classifiers":[
        {
            "category":"Professional",
            "subcategory":"Lawyer & Legal Services",
            "type":"Services"
        }
    ],
    "sg:phone":"+1 619 531 0780",
    "sg:postcode":"92101",
    "sg:province":"CA",
    "sg:tags":[
        "attorney"
    ],
    "wof:name":"Sandra S Schmidt Law Office",
    "wof:placetype":"venue"
},
  "geometry": {"coordinates":[-117.16105899999999,32.72145],"type":"Point"}
}