{
  "type": "Feature",
  "properties": {
    "addr:full":"26222 Hitching Rail Rd Laguna Hills CA 92653",
    "addr:housenumber":"26222",
    "addr:postcode":"92653",
    "addr:street":"Hitching Rail Rd",
    "iso:country":"US",
    "sg:address":"26222 Hitching Rail Rd",
    "sg:city":"Laguna Hills",
    "sg:classifiers":[
        {
            "category":"Professional",
            "type":"Services"
        },
        {
            "category":"Personal",
            "type":"Services"
        }
    ],
    "sg:phone":"+1 949 542 2603",
    "sg:postcode":"92653",
    "sg:province":"CA",
    "sg:tags":[
        "party",
        "wedding",
        "planning",
        "event",
        "caterer"
    ],
    "sg:website":"www.partiesinmotioncatering.com",
    "wof:name":"Parties in Motion Catering",
    "wof:placetype":"venue"
},
  "geometry": {"coordinates":[-117.67567,33.582185],"type":"Point"}
}