{
  "type": "Feature",
  "properties": {
    "iso:country":"US",
    "sg:address":"1820 E Garry Ave",
    "sg:city":"Santa Ana",
    "sg:classifiers":[
        {
            "category":"Health Services",
            "subcategory":"Chiropractor",
            "type":"Services"
        }
    ],
    "sg:phone":"+1 949 250 4582",
    "sg:postcode":"92705",
    "sg:province":"CA",
    "sg:website":"www.thewellnesscenter.com",
    "wof:name":"The Wellness Center",
    "wof:placetype":"venue"
},
  "geometry": {"coordinates":[-117.852997,33.7048],"type":"Point"}
}