{
  "type": "Feature",
  "properties": {
    "iso:country":"US",
    "sg:address":"11683 Cherry Ave",
    "sg:city":"Fontana",
    "sg:classifiers":[
        {
            "category":"Retail",
            "subcategory":"Auto Repair",
            "type":"Services"
        }
    ],
    "sg:phone":"+1 909 823 7753",
    "sg:postcode":"92337",
    "sg:province":"CA",
    "sg:tags":[
        "repairing",
        "automobile"
    ],
    "wof:name":"It Figures",
    "wof:placetype":"venue"
},
  "geometry": {"coordinates":[-117.48679,34.042082],"type":"Point"}
}