{
  "type": "Feature",
  "properties": {
    "iso:country":"US",
    "sg:address":"13058 Loma Rica Dr",
    "sg:city":"Grass Valley",
    "sg:classifiers":[
        {
            "category":"Manufacturing",
            "subcategory":"Metals",
            "type":"Manufacturing & Wholesale Goods"
        }
    ],
    "sg:phone":"+1 530 273 4027",
    "sg:postcode":"95945",
    "sg:province":"CA",
    "sg:tags":[
        "steel"
    ],
    "wof:name":"Noel's Welding Inc",
    "wof:placetype":"venue"
},
  "geometry": {"coordinates":[-121.002119,39.221635],"type":"Point"}
}