{
  "type": "Feature",
  "properties": {
    "iso:country":"US",
    "sg:address":"4570 Van Nuys Blvd",
    "sg:city":"Sherman Oaks",
    "sg:classifiers":[
        {
            "category":"Real Estate",
            "subcategory":"Surveying",
            "type":"Services"
        }
    ],
    "sg:phone":"+1 818 905 1770",
    "sg:postcode":"91403",
    "sg:province":"CA",
    "sg:tags":[
        "report",
        "survey"
    ],
    "wof:name":"Attitude Research",
    "wof:placetype":"venue"
},
  "geometry": {"coordinates":[-118.448618,34.153516],"type":"Point"}
}