{
  "type": "Feature",
  "properties": {
    "addr:full":"2987 Jamacha Rd El Cajon CA 92019",
    "addr:housenumber":"2987",
    "addr:postcode":"92019",
    "addr:street":"Jamacha Rd",
    "iso:country":"US",
    "sg:address":"2987 Jamacha Rd",
    "sg:city":"El Cajon",
    "sg:classifiers":[
        {
            "category":"Shopping",
            "type":"Retail Goods"
        }
    ],
    "sg:phone":"+1 619 670 3190",
    "sg:postcode":"92019",
    "sg:province":"CA",
    "sg:tags":[
        "picture",
        "frame"
    ],
    "sg:website":"www.aaronbrothers.com",
    "wof:name":"Aaron Brothers Inc",
    "wof:placetype":"venue"
},
  "geometry": {"coordinates":[-116.939041,32.740734],"type":"Point"}
}