{
  "type": "Feature",
  "properties": {
    "addr:full":"1 E Ocean Ave Lompoc CA 93436",
    "addr:housenumber":"1",
    "addr:postcode":"93436",
    "addr:street":"E Ocean Ave",
    "iso:country":"US",
    "sg:address":"1 E Ocean Ave",
    "sg:city":"Lompoc",
    "sg:classifiers":[
        {
            "category":"Recreation",
            "type":"Entertainment"
        }
    ],
    "sg:phone":"+1 805 737 0445",
    "sg:postcode":"93436",
    "sg:province":"CA",
    "sg:tags":[
        "aquarium"
    ],
    "wof:name":"Jim's Aquarium Sales & Svc",
    "wof:placetype":"venue"
},
  "geometry": {"coordinates":[-120.457841,34.639023],"type":"Point"}
}