{
  "type": "Feature",
  "properties": {
    "addr:full":"308 E Broadway Glendale CA 91205",
    "addr:housenumber":"308",
    "addr:postcode":"91205",
    "addr:street":"E Broadway",
    "iso:country":"US",
    "sg:address":"308 E Broadway",
    "sg:city":"Glendale",
    "sg:classifiers":[
        {
            "category":"Health Services",
            "subcategory":"Optometrist",
            "type":"Services"
        }
    ],
    "sg:phone":"+1 818 243 1300",
    "sg:postcode":"91205",
    "sg:province":"CA",
    "sg:tags":[
        "ophthalmologist"
    ],
    "sg:website":"www.glenopto.com",
    "wof:name":"Glendale Optometric Center",
    "wof:placetype":"venue"
},
  "geometry": {"coordinates":[-118.25205699999999,34.146314],"type":"Point"}
}