{
  "type": "Feature",
  "properties": {
    "addr:full":"2318 Whitesands Dr Huntington Beach CA 92648",
    "addr:housenumber":"2318",
    "addr:postcode":"92648",
    "addr:street":"Whitesands Dr",
    "iso:country":"US",
    "sg:address":"2318 Whitesands Dr",
    "sg:city":"Huntington Beach",
    "sg:classifiers":[
        {
            "category":"Wholesale",
            "subcategory":"Drugs",
            "type":"Manufacturing & Wholesale Goods"
        }
    ],
    "sg:phone":"+1 714 960 7094",
    "sg:postcode":"92648",
    "sg:province":"CA",
    "wof:name":"Gold Shape USA",
    "wof:placetype":"venue"
},
  "geometry": {"coordinates":[-117.994073,33.678791],"type":"Point"}
}