{
  "type": "Feature",
  "properties": {
    "addr:full":"1775 E Daily Dr Ste H Camarillo CA 93010",
    "addr:housenumber":"1775",
    "addr:postcode":"93010",
    "addr:street":"E Daily Dr Ste H",
    "iso:country":"US",
    "sg:address":"1775 E Daily Dr Ste H",
    "sg:city":"Camarillo",
    "sg:classifiers":[
        {
            "category":"Shopping",
            "subcategory":"Hobbies, Toys, & Games",
            "type":"Retail Goods"
        },
        {
            "category":"Shopping",
            "subcategory":"Crafts & Fabrics",
            "type":"Retail Goods"
        }
    ],
    "sg:phone":"+1 805 445 1305",
    "sg:postcode":"93010",
    "sg:province":"CA",
    "sg:tags":[
        "shop",
        "hobby",
        "model",
        "supply"
    ],
    "sg:website":"http://www.globalhobby.com",
    "wof:name":"Hobby People",
    "wof:placetype":"venue"
},
  "geometry": {"coordinates":[-119.04607900000001,34.217825],"type":"Point"}
}