{
  "type": "Feature",
  "properties": {
    "iso:country":"US",
    "sg:address":"26842 Seco Canyon Rd",
    "sg:city":"Santa Clarita",
    "sg:classifiers":[
        {
            "category":"Personal",
            "subcategory":"Nail Salon",
            "type":"Services"
        }
    ],
    "sg:phone":"+1 661 296 1655",
    "sg:postcode":"91350",
    "sg:province":"CA",
    "wof:name":"Angel Nail",
    "wof:placetype":"venue"
},
  "geometry": {"coordinates":[-118.531998,34.435799],"type":"Point"}
}