{
  "type": "Feature",
  "properties": {
    "addr:full":"701 5th Ave San Diego CA 92101",
    "addr:housenumber":"701",
    "addr:postcode":"92101",
    "addr:street":"5Th Ave",
    "iso:country":"US",
    "sg:address":"701 5th Ave",
    "sg:city":"San Diego",
    "sg:classifiers":[
        {
            "category":"Cinema",
            "subcategory":"Movie Theater",
            "type":"Entertainment"
        }
    ],
    "sg:phone":"+1 619 582 2368",
    "sg:postcode":"92101",
    "sg:province":"CA",
    "sg:website":"www.sdff.org",
    "wof:name":"San Diego Film Festival",
    "wof:placetype":"venue"
},
  "geometry": {"coordinates":[-117.15953399999999,32.712784],"type":"Point"}
}