{
  "type": "Feature",
  "properties": {
    "addr:full":"1000 Bridge Pkwy Redwood City CA 94065",
    "addr:housenumber":"1000",
    "addr:postcode":"94065",
    "addr:street":"Bridge Pkwy",
    "iso:country":"US",
    "sg:address":"1000 Bridge Pkwy",
    "sg:city":"Redwood City",
    "sg:classifiers":[
        {
            "category":"Professional",
            "type":"Services"
        }
    ],
    "sg:phone":"+1 650 596 1800",
    "sg:postcode":"94065",
    "sg:province":"CA",
    "wof:name":"Intalio Inc",
    "wof:placetype":"venue"
},
  "geometry": {"coordinates":[-122.251699,37.527062],"type":"Point"}
}