{
  "type": "Feature",
  "properties": {
    "addr:full":"1330 Contra Costa Ave #J105 San Pablo CA 94806",
    "addr:housenumber":"1330",
    "addr:postcode":"94806",
    "addr:street":"Contra Costa Ave # J105",
    "iso:country":"US",
    "sg:address":"1330 Contra Costa Ave #J105",
    "sg:city":"San Pablo",
    "sg:classifiers":[
        {
            "category":"Building & Trades",
            "subcategory":"Cleaning & Sanitation",
            "type":"Services"
        }
    ],
    "sg:phone":"+1 510 684 2159",
    "sg:postcode":"94806",
    "sg:province":"CA",
    "sg:tags":[
        "home"
    ],
    "wof:name":"Rosanir's Cleaning Services",
    "wof:placetype":"venue"
},
  "geometry": {"coordinates":[-122.32939399999999,37.951738],"type":"Point"}
}