{
  "type": "Feature",
  "properties": {
    "addr:full":"Avenue D & 9th St Treasure Island San Francisco CA 94130",
    "addr:postcode":"94130",
    "addr:street":"Avenue D & 9Th St",
    "iso:country":"US",
    "sg:address":"Avenue D & 9th St Treasure Island",
    "sg:city":"San Francisco",
    "sg:classifiers":[
        {
            "category":"Sports & Exercise",
            "subcategory":"Sports Center",
            "type":"Entertainment"
        }
    ],
    "sg:postcode":"94130",
    "sg:province":"CA",
    "sg:tags":[
        "amateur",
        "team"
    ],
    "sg:website":"www.berkeleyrugby.com/",
    "wof:name":"Berkeley RFC - East Bay Mens Rugby Team",
    "wof:placetype":"venue"
},
  "geometry": {"coordinates":[-122.372669,37.824115],"type":"Point"}
}