{
  "type": "Feature",
  "properties": {
    "iso:country":"US",
    "sg:address":"3126 4th St",
    "sg:city":"Biggs",
    "sg:classifiers":[
        {
            "category":"Farming",
            "subcategory":"Nursery",
            "type":"Manufacturing & Wholesale Goods"
        }
    ],
    "sg:phone":"+1 530 846 4067",
    "sg:postcode":"95917",
    "sg:province":"CA",
    "sg:tags":[
        "ornamental"
    ],
    "wof:name":"Chano Nursery",
    "wof:placetype":"venue"
},
  "geometry": {"coordinates":[-121.710553,39.418804],"type":"Point"}
}