{
  "type": "Feature",
  "properties": {
    "iso:country":"US",
    "sg:address":"8530 Fruitridge Rd",
    "sg:city":"Sacramento",
    "sg:classifiers":[
        {
            "category":"Building & Trades",
            "subcategory":"Landscaping Services",
            "type":"Services"
        }
    ],
    "sg:phone":"+1 916 387 6777",
    "sg:postcode":"95826",
    "sg:province":"CA",
    "wof:name":"Arreolas Complete Ldscp Svc",
    "wof:placetype":"venue"
},
  "geometry": {"coordinates":[-121.389383,38.525106],"type":"Point"}
}