{
  "type": "Feature",
  "properties": {
    "iso:country":"US",
    "sg:address":"769 Westlite Cir",
    "sg:city":"Sacramento",
    "sg:classifiers":[
        {
            "category":"Shopping",
            "subcategory":"Crafts & Fabrics",
            "type":"Retail Goods"
        }
    ],
    "sg:phone":"+1 916 395 9582",
    "sg:postcode":"95831",
    "sg:province":"CA",
    "sg:tags":[
        "embroidery"
    ],
    "wof:name":"Bunka Etcetera",
    "wof:placetype":"venue"
},
  "geometry": {"coordinates":[-121.53273799999999,38.50116],"type":"Point"}
}