{
  "type": "Feature",
  "properties": {
    "addr:full":"721 Pearl Street La Jolla CA 92037",
    "addr:housenumber":"721",
    "addr:postcode":"92037",
    "addr:street":"Pearl Street",
    "iso:country":"US",
    "sg:address":"721 Pearl Street",
    "sg:city":"La Jolla",
    "sg:classifiers":[
        {
            "category":"Personal",
            "subcategory":"Nail Salon",
            "type":"Services"
        }
    ],
    "sg:phone":"+1 858 454 2853",
    "sg:postcode":"92037",
    "sg:province":"CA",
    "sg:website":"www.nancysnailslajolla.com",
    "wof:name":"Nancy's Nails",
    "wof:placetype":"venue"
},
  "geometry": {"coordinates":[-117.27564599999999,32.839752],"type":"Point"}
}