{
  "type": "Feature",
  "properties": {
    "addr:full":"8910 Villa La Jolla Dr La Jolla CA 92037",
    "addr:housenumber":"8910",
    "addr:postcode":"92037",
    "addr:street":"Villa La Jolla Dr",
    "iso:country":"US",
    "sg:address":"8910 Villa La Jolla Dr",
    "sg:city":"La Jolla",
    "sg:classifiers":[
        {
            "category":"Restaurant",
            "type":"Food & Drink"
        }
    ],
    "sg:phone":"+1 858 453 4115",
    "sg:postcode":"92037",
    "sg:province":"CA",
    "sg:tags":[
        "mexican"
    ],
    "wof:name":"El Torito Mexican Restaurant & Cantina",
    "wof:placetype":"venue"
},
  "geometry": {"coordinates":[-117.23400100000001,32.8699],"type":"Point"}
}