{
  "type": "Feature",
  "properties": {
    "iso:country":"US",
    "sg:address":"2849 Lenwood Rd",
    "sg:city":"Barstow",
    "sg:classifiers":[
        {
            "category":"Shopping",
            "subcategory":"Clothing, Apparel, & Fashions",
            "type":"Retail Goods"
        }
    ],
    "sg:phone":"+1 760 253 5333",
    "sg:postcode":"92311",
    "sg:province":"CA",
    "sg:tags":[
        "wear",
        "family"
    ],
    "wof:name":"Polo Ralph Lauren Outlet",
    "wof:placetype":"venue"
},
  "geometry": {"coordinates":[-117.088956,34.854955],"type":"Point"}
}