{
  "type": "Feature",
  "properties": {
    "iso:country":"US",
    "sg:address":"4055 Gage Ave",
    "sg:city":"Bell",
    "sg:classifiers":[
        {
            "category":"Professional",
            "subcategory":"Computer Services",
            "type":"Services"
        }
    ],
    "sg:phone":"+1 323 562 8040",
    "sg:postcode":"90201",
    "sg:province":"CA",
    "sg:tags":[
        "repair"
    ],
    "wof:name":"AYCN Computer System",
    "wof:placetype":"venue"
},
  "geometry": {"coordinates":[-118.194154,33.978862],"type":"Point"}
}