{
  "type": "Feature",
  "properties": {
    "addr:full":"7450 Railroad St Gilroy CA 95020",
    "addr:housenumber":"7450",
    "addr:postcode":"95020",
    "addr:street":"Railroad St",
    "iso:country":"US",
    "sg:address":"7450 Railroad St",
    "sg:city":"Gilroy",
    "sg:classifiers":[
        {
            "category":"Professional",
            "subcategory":"Engineering",
            "type":"Services"
        }
    ],
    "sg:phone":"+1 408 848 6009",
    "sg:postcode":"95020",
    "sg:province":"CA",
    "sg:tags":[
        "consulting",
        "petroleum",
        "engineer"
    ],
    "wof:name":"Redwood Geotechnical Engineeri",
    "wof:placetype":"venue"
},
  "geometry": {"coordinates":[-121.567663,37.007824],"type":"Point"}
}