{
  "type": "Feature",
  "properties": {
    "iso:country":"US",
    "sg:address":"2060 Deer Creek Rd",
    "sg:city":"Shasta Lake",
    "sg:classifiers":[
        {
            "category":"Organizations",
            "subcategory":"Religious Organization",
            "type":"Services"
        }
    ],
    "sg:phone":"+1 530 275 1152",
    "sg:postcode":"96019",
    "sg:province":"CA",
    "sg:tags":[
        "counseling",
        "pastoral",
        "clergy"
    ],
    "wof:name":"Deer Creek Church Of Christ",
    "wof:placetype":"venue"
},
  "geometry": {"coordinates":[-122.36197900000001,40.675187],"type":"Point"}
}