{
  "type": "Feature",
  "properties": {
    "addr:full":"1683 Washington St San Mateo CA 94403",
    "addr:housenumber":"1683",
    "addr:postcode":"94403",
    "addr:street":"Washington St",
    "iso:country":"US",
    "sg:address":"1683 Washington St",
    "sg:city":"San Mateo",
    "sg:classifiers":[
        {
            "category":"Freight",
            "type":"Transportation"
        }
    ],
    "sg:phone":"+1 650 222 7588",
    "sg:postcode":"94403",
    "sg:province":"CA",
    "sg:tags":[
        "operator",
        "local",
        "trucking"
    ],
    "wof:name":"S & K Trucking",
    "wof:placetype":"venue"
},
  "geometry": {"coordinates":[-122.30113299999999,37.560119],"type":"Point"}
}