{
  "type": "Feature",
  "properties": {
    "iso:country":"US",
    "sg:address":"5424 Pirrone Rd",
    "sg:city":"Salida",
    "sg:classifiers":[
        {
            "category":"Social Services",
            "type":"Services"
        }
    ],
    "sg:phone":"+1 209 526 5160",
    "sg:postcode":"95368",
    "sg:province":"CA",
    "sg:tags":[
        "senior",
        "citizen"
    ],
    "wof:name":"Central Valley Seniors",
    "wof:placetype":"venue"
},
  "geometry": {"coordinates":[-121.09530100000001,37.718707],"type":"Point"}
}