{
  "type": "Feature",
  "properties": {
    "iso:country":"US",
    "sg:address":"2217 San Ramon Valley Blvd",
    "sg:city":"San Ramon",
    "sg:classifiers":[
        {
            "category":"Food & Beverages",
            "subcategory":"Groceries & Convenience Stores",
            "type":"Retail Goods"
        }
    ],
    "sg:phone":"+1 925 838 7865",
    "sg:postcode":"94583",
    "sg:province":"CA",
    "sg:tags":[
        "grocer"
    ],
    "wof:name":"Mirch Masala",
    "wof:placetype":"venue"
},
  "geometry": {"coordinates":[-121.978264,37.780424],"type":"Point"}
}