{
  "type": "Feature",
  "properties": {
    "addr:full":"8995 Curbaril Ave Atascadero CA 93422",
    "addr:housenumber":"8995",
    "addr:postcode":"93422",
    "addr:street":"Curbaril Ave",
    "iso:country":"US",
    "sg:address":"8995 Curbaril Ave",
    "sg:city":"Atascadero",
    "sg:classifiers":[
        {
            "category":"Travel",
            "subcategory":"Travel Agent",
            "type":"Entertainment"
        }
    ],
    "sg:phone":"+1 805 466 8640",
    "sg:postcode":"93422",
    "sg:province":"CA",
    "sg:tags":[
        "tours",
        "promoter"
    ],
    "wof:name":"Agostini Guide Svc",
    "wof:placetype":"venue"
},
  "geometry": {"coordinates":[-120.654184,35.481012],"type":"Point"}
}