{
  "type": "Feature",
  "properties": {
    "addr:full":"781 W 2nd St San Bernardino CA 92410",
    "addr:housenumber":"781",
    "addr:postcode":"92410",
    "addr:street":"W 2Nd St",
    "iso:country":"US",
    "sg:address":"781 W 2nd St",
    "sg:city":"San Bernardino",
    "sg:classifiers":[
        {
            "category":"Professional",
            "subcategory":"Accounting & Tax Preparation",
            "type":"Services"
        }
    ],
    "sg:phone":"+1 909 384 9216",
    "sg:postcode":"92410",
    "sg:province":"CA",
    "sg:tags":[
        "payroll"
    ],
    "wof:name":"Continental Consulting Corp",
    "wof:placetype":"venue"
},
  "geometry": {"coordinates":[-117.300422,34.102647],"type":"Point"}
}