{
  "type": "Feature",
  "properties": {
    "addr:full":"7517 1-2 Melrose Ave Los Angeles CA 90046",
    "addr:housenumber":"7517",
    "addr:postcode":"90046",
    "addr:street":"1-2 Melrose Ave",
    "iso:country":"US",
    "sg:address":"7517 1-2 Melrose Ave",
    "sg:city":"Los Angeles",
    "sg:classifiers":[
        {
            "category":"Ice Cream",
            "type":"Food & Drink"
        }
    ],
    "sg:phone":"+1 323 653 5940",
    "sg:postcode":"90046",
    "sg:province":"CA",
    "sg:tags":[
        "frozen",
        "yogurt"
    ],
    "wof:name":"Diet Berry 44",
    "wof:placetype":"venue"
},
  "geometry": {"coordinates":[-118.353673,34.083634],"type":"Point"}
}