{
  "type": "Feature",
  "properties": {
    "addr:full":"14 Cll del Luna Rancho Santa Margarita CA 92688",
    "addr:housenumber":"14",
    "addr:postcode":"92688",
    "addr:street":"Cll Del Luna",
    "iso:country":"US",
    "sg:address":"14 Cll del Luna",
    "sg:city":"Rancho Santa Margarita",
    "sg:classifiers":[
        {
            "category":"Wholesale",
            "subcategory":"Beer",
            "type":"Manufacturing & Wholesale Goods"
        }
    ],
    "sg:phone":"+1 949 766 8574",
    "sg:postcode":"92688",
    "sg:province":"CA",
    "wof:name":"Heineken USA Incorporated",
    "wof:placetype":"venue"
},
  "geometry": {"coordinates":[-117.596435,33.637069],"type":"Point"}
}