{
  "type": "Feature",
  "properties": {
    "iso:country":"US",
    "sg:address":"761 Harvard Ave.",
    "sg:city":"Santa Clara",
    "sg:classifiers":[
        {
            "category":"Building & Trades",
            "subcategory":"Construction",
            "type":"Services"
        }
    ],
    "sg:phone":"+1 408 230 3344",
    "sg:postcode":"95051",
    "sg:province":"CA",
    "sg:tags":[
        "painter"
    ],
    "sg:website":"antique-painting.biz",
    "wof:name":"Antique Painting",
    "wof:placetype":"venue"
},
  "geometry": {"coordinates":[-121.992131,37.336788],"type":"Point"}
}