{
  "type": "Feature",
  "properties": {
    "addr:full":"542 Brannan St. San Francisco CA 94107",
    "addr:housenumber":"542",
    "addr:postcode":"94107",
    "addr:street":"Brannan St.",
    "iso:country":"US",
    "sg:address":"542 Brannan St.",
    "sg:city":"San Francisco",
    "sg:classifiers":[
        {
            "category":"Professional",
            "subcategory":"Computer Services",
            "type":"Services"
        }
    ],
    "sg:postcode":"94107",
    "sg:province":"CA",
    "sg:website":"http://www.backtype.com/",
    "wof:name":"BackType",
    "wof:placetype":"venue"
},
  "geometry": {"coordinates":[-122.398055,37.777375],"type":"Point"}
}