{
  "type": "Feature",
  "properties": {
    "addr:full":"800 Bellevue Rd Atwater CA 95301",
    "addr:housenumber":"800",
    "addr:postcode":"95301",
    "addr:street":"Bellevue Rd",
    "iso:country":"US",
    "sg:address":"800 Bellevue Rd",
    "sg:city":"Atwater",
    "sg:classifiers":[
        {
            "category":"Building & Trades",
            "subcategory":"Construction",
            "type":"Services"
        }
    ],
    "sg:phone":"+1 209 357 1759",
    "sg:postcode":"95301",
    "sg:province":"CA",
    "sg:tags":[
        "home",
        "builder"
    ],
    "wof:name":"E J Franks Construction",
    "wof:placetype":"venue"
},
  "geometry": {"coordinates":[-120.60136,37.360451],"type":"Point"}
}