{
  "type": "Feature",
  "properties": {
    "addr:full":"6580 Leland St Ventura CA 93003",
    "addr:housenumber":"6580",
    "addr:postcode":"93003",
    "addr:street":"Leland St",
    "iso:country":"US",
    "sg:address":"6580 Leland St",
    "sg:city":"Ventura",
    "sg:classifiers":[
        {
            "category":"Autos & Motor Vehicles",
            "subcategory":"Automobile Sales",
            "type":"Retail Goods"
        }
    ],
    "sg:phone":"+1 805 656 9933",
    "sg:postcode":"93003",
    "sg:province":"CA",
    "sg:tags":[
        "car",
        "dealer"
    ],
    "sg:website":"www.venturavolvo.com",
    "wof:name":"Volvo-Ventura",
    "wof:placetype":"venue"
},
  "geometry": {"coordinates":[-119.197546,34.24446],"type":"Point"}
}