{
  "type": "Feature",
  "properties": {
    "addr:full":"7855 La Palma Ave Ste 3 Buena Park CA 90621",
    "addr:housenumber":"7855",
    "addr:postcode":"90621",
    "addr:street":"La Palma Ave Ste 3",
    "iso:country":"US",
    "sg:address":"7855 La Palma Ave Ste 3",
    "sg:city":"Buena Park",
    "sg:classifiers":[
        {
            "category":"Personal",
            "subcategory":"Skin Care",
            "type":"Services"
        }
    ],
    "sg:phone":"+1 714 521 3689",
    "sg:postcode":"90621",
    "sg:province":"CA",
    "sg:website":"www.bodyenvywraps.com",
    "wof:name":"Body Envy Body Wrap",
    "wof:placetype":"venue"
},
  "geometry": {"coordinates":[-117.996219,33.847151],"type":"Point"}
}