{
  "type": "Feature",
  "properties": {
    "addr:full":"1452 Spinel Ct Livermore CA 94550",
    "addr:housenumber":"1452",
    "addr:postcode":"94550",
    "addr:street":"Spinel Ct",
    "iso:country":"US",
    "sg:address":"1452 Spinel Ct",
    "sg:city":"Livermore",
    "sg:classifiers":[
        {
            "category":"Real Estate",
            "subcategory":"Real Estate Agent",
            "type":"Services"
        }
    ],
    "sg:phone":"+1 925 456 6025",
    "sg:postcode":"94550",
    "sg:province":"CA",
    "wof:name":"Canaan Properties",
    "wof:placetype":"venue"
},
  "geometry": {"coordinates":[-121.800051,37.663787],"type":"Point"}
}