{
  "type": "Feature",
  "properties": {
    "addr:full":"1121 Doker Dr Modesto CA 95351",
    "addr:housenumber":"1121",
    "addr:postcode":"ca 95351",
    "addr:street":"Doker Dr",
    "iso:country":"US",
    "sg:address":"1121 Doker Dr",
    "sg:city":"Modesto",
    "sg:classifiers":[
        {
            "category":"Building & Trades",
            "subcategory":"Pest Control",
            "type":"Services"
        }
    ],
    "sg:phone":"+1 209 578 5797",
    "sg:postcode":"95351",
    "sg:province":"CA",
    "wof:name":"Animal Damage Management",
    "wof:placetype":"venue"
},
  "geometry": {"coordinates":[-121.024002,37.647301],"type":"Point"}
}