{
  "type": "Feature",
  "properties": {
    "addr:full":"41501 Co Rd 27 Woodland CA 95776",
    "addr:housenumber":"27",
    "addr:postcode":"41501;95776",
    "addr:street":"Co Rd",
    "iso:country":"US",
    "sg:address":"41501 Co Rd 27",
    "sg:city":"Woodland",
    "sg:classifiers":[
        {
            "category":"Manufacturing",
            "subcategory":"Textiles",
            "type":"Manufacturing & Wholesale Goods"
        },
        {
            "category":"Wholesale",
            "subcategory":"Farm Supplies",
            "type":"Manufacturing & Wholesale Goods"
        }
    ],
    "sg:phone":"+1 530 666 1473",
    "sg:postcode":"95776",
    "sg:province":"CA",
    "sg:tags":[
        "wool",
        "mfg"
    ],
    "wof:name":"Yolo Wool Products Inc",
    "wof:placetype":"venue"
},
  "geometry": {"coordinates":[-121.734712,38.618899],"type":"Point"}
}