{
  "type": "Feature",
  "properties": {
    "iso:country":"US",
    "sg:address":"38710 Rd 140",
    "sg:city":"Cutler",
    "sg:classifiers":[
        {
            "category":"Farming",
            "subcategory":"Farm & Veterinary Services",
            "type":"Manufacturing & Wholesale Goods"
        }
    ],
    "sg:phone":"+1 559 528 4155",
    "sg:postcode":"93615",
    "sg:province":"CA",
    "wof:name":"A & M Farm Svc",
    "wof:placetype":"venue"
},
  "geometry": {"coordinates":[-119.259503,36.486335],"type":"Point"}
}