{
  "type": "Feature",
  "properties": {
    "addr:full":"2625 E 1st St Los Angeles CA 90033",
    "addr:housenumber":"2625",
    "addr:postcode":"90033",
    "addr:street":"E 1St St",
    "iso:country":"US",
    "sg:address":"2625 E 1st St",
    "sg:city":"Los Angeles",
    "sg:classifiers":[
        {
            "category":"Real Estate",
            "subcategory":"Real Estate Agent",
            "type":"Services"
        }
    ],
    "sg:phone":"+1 323 264 4490",
    "sg:postcode":"90033",
    "sg:province":"CA",
    "sg:tags":[
        "consultant"
    ],
    "wof:name":"Hayashi Realty",
    "wof:placetype":"venue"
},
  "geometry": {"coordinates":[-118.20622400000001,34.042245],"type":"Point"}
}