{
  "type": "Feature",
  "properties": {
    "addr:full":"3705 Holden Cir Los Alamitos CA 90720",
    "addr:housenumber":"3705",
    "addr:postcode":"90720",
    "addr:street":"Holden Cir",
    "iso:country":"US",
    "sg:address":"3705 Holden Cir",
    "sg:city":"Los Alamitos",
    "sg:classifiers":[
        {
            "category":"Wholesale",
            "subcategory":"Chemicals & Plastics",
            "type":"Manufacturing & Wholesale Goods"
        }
    ],
    "sg:phone":"+1 562 598 3210",
    "sg:postcode":"90720",
    "sg:province":"CA",
    "sg:tags":[
        "cleaning",
        "compound"
    ],
    "wof:name":"Amway Distributors",
    "wof:placetype":"venue"
},
  "geometry": {"coordinates":[-118.06697,33.816424],"type":"Point"}
}