{
  "type": "Feature",
  "properties": {
    "iso:country":"US",
    "sg:address":"2055 Tice Valley Blvd",
    "sg:city":"Walnut Creek",
    "sg:classifiers":[
        {
            "category":"Government",
            "subcategory":"Office",
            "type":"Public Place"
        }
    ],
    "sg:phone":"+1 925 943 5899",
    "sg:postcode":"94595",
    "sg:province":"CA",
    "sg:tags":[
        "village"
    ],
    "wof:name":"Tice Valley Comm Gymnasium",
    "wof:placetype":"venue"
},
  "geometry": {"coordinates":[-122.071033,37.876531],"type":"Point"}
}