{
  "type": "Feature",
  "properties": {
    "iso:country":"US",
    "sg:address":"5800 el Camino Real",
    "sg:city":"Atascadero",
    "sg:classifiers":[
        {
            "category":"Shopping",
            "subcategory":"Used Merchandise",
            "type":"Retail Goods"
        }
    ],
    "sg:phone":"+1 805 462 0500",
    "sg:postcode":"93422",
    "sg:province":"CA",
    "wof:name":"Village Thrift II",
    "wof:placetype":"venue"
},
  "geometry": {"coordinates":[-120.67343099999999,35.49086],"type":"Point"}
}