{
  "type": "Feature",
  "properties": {
    "addr:full":"330 W Ave 26 Los Angeles CA 90031",
    "addr:housenumber":"330;26",
    "addr:postcode":"90031",
    "addr:street":"W Ave",
    "iso:country":"US",
    "sg:address":"330 W Ave 26",
    "sg:city":"Los Angeles",
    "sg:classifiers":[
        {
            "category":"Building & Trades",
            "subcategory":"Construction",
            "type":"Services"
        }
    ],
    "sg:phone":"+1 323 225 5449",
    "sg:postcode":"90031",
    "sg:province":"CA",
    "sg:tags":[
        "general",
        "contractor"
    ],
    "sg:website":"www.amcalhousing.com",
    "wof:name":"Amcal General Contractors Inc",
    "wof:placetype":"venue"
},
  "geometry": {"coordinates":[-118.218698,34.079831],"type":"Point"}
}