{
  "type": "Feature",
  "properties": {
    "iso:country":"US",
    "sg:address":"1615 Commerce Way",
    "sg:city":"Paso Robles",
    "sg:classifiers":[
        {
            "category":"Home & Garden",
            "subcategory":"Building Materials",
            "type":"Retail Goods"
        }
    ],
    "sg:phone":"+1 805 239 3296",
    "sg:postcode":"93446",
    "sg:province":"CA",
    "sg:tags":[
        "door"
    ],
    "wof:name":"Wood Reflections",
    "wof:placetype":"venue"
},
  "geometry": {"coordinates":[-120.652416,35.614187],"type":"Point"}
}