{
  "type": "Feature",
  "properties": {
    "addr:full":"18411 Crenshaw Blvd Ste 360 Torrance CA 90504",
    "addr:housenumber":"18411",
    "addr:postcode":"90504",
    "addr:street":"Crenshaw Blvd Ste 360",
    "iso:country":"US",
    "sg:address":"18411 Crenshaw Blvd Ste 360",
    "sg:city":"Torrance",
    "sg:classifiers":[
        {
            "category":"Professional",
            "subcategory":"Lawyer & Legal Services",
            "type":"Services"
        }
    ],
    "sg:phone":"+1 310 977 9574",
    "sg:postcode":"90504",
    "sg:province":"CA",
    "sg:tags":[
        "divorce",
        "law",
        "family"
    ],
    "sg:website":"www.paulrorie.com",
    "wof:name":"Paul B. Rorie, Attorney at Law",
    "wof:placetype":"venue"
},
  "geometry": {"coordinates":[-118.32702500000001,33.863326],"type":"Point"}
}