{
  "type": "Feature",
  "properties": {
    "iso:country":"US",
    "sg:address":"608 Sutter St",
    "sg:city":"Folsom",
    "sg:classifiers":[
        {
            "category":"Sports & Exercise",
            "subcategory":"Gym",
            "type":"Entertainment"
        }
    ],
    "sg:phone":"+1 916 351 0226",
    "sg:postcode":"95630",
    "sg:province":"CA",
    "sg:tags":[
        "pilate"
    ],
    "wof:name":"Fortitude Pilates Studio",
    "wof:placetype":"venue"
},
  "geometry": {"coordinates":[-121.176373,38.677888],"type":"Point"}
}