{
  "type": "Feature",
  "properties": {
    "iso:country":"US",
    "sg:address":"845 N Franklin St",
    "sg:city":"Fort Bragg",
    "sg:classifiers":[
        {
            "category":"Professional",
            "type":"Services"
        }
    ],
    "sg:phone":"+1 707 961 0209",
    "sg:postcode":"95437",
    "sg:province":"CA",
    "wof:name":"Creative Quest",
    "wof:placetype":"venue"
},
  "geometry": {"coordinates":[-123.804585,39.451236],"type":"Point"}
}