{
  "type": "Feature",
  "properties": {
    "addr:full":"5242 Katella Ave Ste 106 Los Alamitos CA 90720",
    "addr:housenumber":"5242",
    "addr:postcode":"90720",
    "addr:street":"Katella Ave Ste 106",
    "iso:country":"US",
    "sg:address":"5242 Katella Ave Ste 106",
    "sg:city":"Los Alamitos",
    "sg:classifiers":[
        {
            "category":"Health Services",
            "subcategory":"Doctor",
            "type":"Services"
        },
        {
            "category":"Health Services",
            "subcategory":"Health Practitioner",
            "type":"Services"
        },
        {
            "category":"Personal",
            "subcategory":"Adult",
            "type":"Services"
        }
    ],
    "sg:phone":"+1 562 431 4120",
    "sg:postcode":"90720",
    "sg:province":"CA",
    "sg:tags":[
        "acupuncture",
        "obstetrician",
        "midwife",
        "gynecologist"
    ],
    "sg:website":"drpainovich.com/",
    "wof:name":"Jeannette Painovich, DAOM, LAc",
    "wof:placetype":"venue"
},
  "geometry": {"coordinates":[-118.04034,33.802896],"type":"Point"}
}