{
  "type": "Feature",
  "properties": {
    "addr:full":"10725 Burbank Blvd North Hollywood CA 91601",
    "addr:housenumber":"10725",
    "addr:postcode":"91601",
    "addr:street":"Burbank Blvd",
    "iso:country":"US",
    "sg:address":"10725 Burbank Blvd",
    "sg:city":"North Hollywood",
    "sg:classifiers":[
        {
            "category":"Health Services",
            "subcategory":"Hospital",
            "type":"Services"
        }
    ],
    "sg:phone":"+1 818 760 0253",
    "sg:postcode":"91601",
    "sg:province":"CA",
    "sg:tags":[
        "specialty"
    ],
    "wof:name":"Alcohlcos Annmos Estmos Cntigo",
    "wof:placetype":"venue"
},
  "geometry": {"coordinates":[-118.364085,34.172232],"type":"Point"}
}