{
  "type": "Feature",
  "properties": {
    "iso:country":"US",
    "sg:address":"11315 S Figueroa Street",
    "sg:city":"Los Angeles",
    "sg:classifiers":[
        {
            "category":"Personal",
            "subcategory":"Nail Salon",
            "type":"Services"
        }
    ],
    "sg:phone":"+1 323 779 0308",
    "sg:postcode":"90061",
    "sg:province":"CA",
    "sg:website":"www.nails-express.com",
    "wof:name":"Express Nails",
    "wof:placetype":"venue"
},
  "geometry": {"coordinates":[-118.282616,33.931831],"type":"Point"}
}