{
  "type": "Feature",
  "properties": {
    "addr:full":"142 Longfellow Ct Thousand Oaks CA 91360",
    "addr:housenumber":"142",
    "addr:postcode":"91360",
    "addr:street":"Longfellow Ct",
    "iso:country":"US",
    "sg:address":"142 Longfellow Ct",
    "sg:city":"Thousand Oaks",
    "sg:classifiers":[
        {
            "category":"Professional",
            "type":"Services"
        }
    ],
    "sg:phone":"+1 805 492 3231",
    "sg:postcode":"91360",
    "sg:province":"CA",
    "sg:tags":[
        "establishment"
    ],
    "wof:name":"En Garde Intl",
    "wof:placetype":"venue"
},
  "geometry": {"coordinates":[-118.879328,34.2172],"type":"Point"}
}