{
  "type": "Feature",
  "properties": {
    "addr:full":"1771 Goss Street, Apt E Oakland CA 94607",
    "addr:housenumber":"1771",
    "addr:postcode":"94607",
    "addr:street":"Goss Street Apt E",
    "iso:country":"US",
    "sg:address":"1771 Goss Street, Apt E",
    "sg:city":"Oakland",
    "sg:classifiers":[
        {
            "category":"Banks & Credit Unions",
            "subcategory":"Financial Services",
            "type":"Services"
        },
        {
            "category":"Professional",
            "subcategory":"Lawyer & Legal Services",
            "type":"Services"
        },
        {
            "category":"Professional",
            "subcategory":"Business Services",
            "type":"Services"
        }
    ],
    "sg:phone":"+1 415 742 2632",
    "sg:postcode":"94607",
    "sg:province":"CA",
    "sg:tags":[
        "living",
        "attorney",
        "estate",
        "broker",
        "escrow",
        "planning",
        "notary",
        "trust",
        "probate",
        "public"
    ],
    "wof:name":"GoNotary",
    "wof:placetype":"venue"
},
  "geometry": {"coordinates":[-122.302296,37.807747],"type":"Point"}
}