{
  "type": "Feature",
  "properties": {
    "iso:country":"US",
    "sg:address":"240 N L St",
    "sg:city":"Tulare",
    "sg:classifiers":[
        {
            "category":"Restaurant",
            "type":"Food & Drink"
        }
    ],
    "sg:phone":"+1 559 686 6045",
    "sg:postcode":"93274",
    "sg:province":"CA",
    "sg:tags":[
        "hot",
        "hamburger",
        "dog"
    ],
    "wof:name":"Aero Dog's",
    "wof:placetype":"venue"
},
  "geometry": {"coordinates":[-119.34518799999999,36.210083],"type":"Point"}
}