{
  "type": "Feature",
  "properties": {
    "iso:country":"US",
    "sg:address":"11708 Artesia Blvd",
    "sg:city":"Artesia",
    "sg:classifiers":[
        {
            "category":"Professional",
            "subcategory":"Accounting & Tax Preparation",
            "type":"Services"
        }
    ],
    "sg:phone":"+1 562 860 2309",
    "sg:postcode":"90701",
    "sg:province":"CA",
    "sg:tags":[
        "return",
        "filing"
    ],
    "wof:name":"Cerritos Financial Svc",
    "wof:placetype":"venue"
},
  "geometry": {"coordinates":[-118.08234299999999,33.872938],"type":"Point"}
}