{
  "type": "Feature",
  "properties": {
    "addr:full":"1133 Camelback St Newport Beach CA 92660",
    "addr:housenumber":"1133",
    "addr:postcode":"92660",
    "addr:street":"Camelback St",
    "iso:country":"US",
    "sg:address":"1133 Camelback St",
    "sg:city":"Newport Beach",
    "sg:classifiers":[
        {
            "category":"Building & Trades",
            "subcategory":"Construction",
            "type":"Services"
        }
    ],
    "sg:phone":"+1 714 414 2728",
    "sg:postcode":"92660",
    "sg:province":"CA",
    "sg:tags":[
        "contractor"
    ],
    "sg:website":"www.intercityhvac.com",
    "wof:name":"Intercity Heating And Cooling",
    "wof:placetype":"venue"
},
  "geometry": {"coordinates":[-117.865753,33.639576],"type":"Point"}
}