{
  "type": "Feature",
  "properties": {
    "addr:full":"1999 8th St Los Osos CA 93402",
    "addr:housenumber":"1999",
    "addr:postcode":"93402",
    "addr:street":"8Th St",
    "iso:country":"US",
    "sg:address":"1999 8th St",
    "sg:city":"Los Osos",
    "sg:classifiers":[
        {
            "category":"Professional",
            "type":"Services"
        }
    ],
    "sg:phone":"+1 805 528 4547",
    "sg:postcode":"93402",
    "sg:province":"CA",
    "sg:tags":[
        "consultant",
        "geological"
    ],
    "wof:name":"Geo Solutions Inc",
    "wof:placetype":"venue"
},
  "geometry": {"coordinates":[-120.834417,35.31507],"type":"Point"}
}