{
  "type": "Feature",
  "properties": {
    "addr:full":"560 4th Street San Francisco CA 94107",
    "addr:housenumber":"560",
    "addr:postcode":"94107",
    "addr:street":"4Th Street",
    "iso:country":"US",
    "sg:address":"560 4th Street",
    "sg:city":"San Francisco",
    "sg:classifiers":[
        {
            "category":"Retail",
            "subcategory":"Portrait Studio",
            "type":"Services"
        },
        {
            "category":"Professional",
            "subcategory":"Art Services",
            "type":"Services"
        }
    ],
    "sg:phone":"+1 415 882 9780",
    "sg:postcode":"94107",
    "sg:province":"CA",
    "sg:tags":[
        "photographer",
        "photography",
        "store"
    ],
    "wof:name":"Advertising Photographers of America",
    "wof:placetype":"venue"
},
  "geometry": {"coordinates":[-122.397003,37.7789],"type":"Point"}
}