{
  "type": "Feature",
  "properties": {
    "addr:full":"16250 Paramount Blvd Paramount CA 90723",
    "addr:housenumber":"16250",
    "addr:postcode":"90723",
    "addr:street":"Paramount Blvd",
    "iso:country":"US",
    "sg:address":"16250 Paramount Blvd",
    "sg:city":"Paramount",
    "sg:classifiers":[
        {
            "category":"Shopping",
            "subcategory":"Department Store",
            "type":"Retail Goods"
        }
    ],
    "sg:phone":"+1 562 408 0266",
    "sg:postcode":"90723",
    "sg:province":"CA",
    "sg:tags":[
        "shop"
    ],
    "wof:name":"Big Lots",
    "wof:placetype":"venue"
},
  "geometry": {"coordinates":[-118.159914,33.886869],"type":"Point"}
}