{
  "type": "Feature",
  "properties": {
    "iso:country":"US",
    "sg:address":"711 S 33rd St",
    "sg:city":"Richmond",
    "sg:classifiers":[
        {
            "category":"Personal",
            "type":"Services"
        }
    ],
    "sg:phone":"+1 510 412 9191",
    "sg:postcode":"94804",
    "sg:province":"CA",
    "sg:tags":[
        "mover"
    ],
    "wof:name":"All-Ways Moving & Storage",
    "wof:placetype":"venue"
},
  "geometry": {"coordinates":[-122.337997,37.922298],"type":"Point"}
}