{
  "type": "Feature",
  "properties": {
    "iso:country":"US",
    "sg:address":"111 W Ave Palizada",
    "sg:city":"San Clemente",
    "sg:classifiers":[
        {
            "category":"Shopping",
            "subcategory":"Gifts & Souvenirs",
            "type":"Retail Goods"
        }
    ],
    "sg:phone":"+1 949 492 2270",
    "sg:postcode":"92672",
    "sg:province":"CA",
    "wof:name":"Y Schorsch Gallery & Gifts",
    "wof:placetype":"venue"
},
  "geometry": {"coordinates":[-117.61552500000001,33.429622],"type":"Point"}
}