{
  "type": "Feature",
  "properties": {
    "addr:full":"1590 Berryessa Rd San Jose CA 95133",
    "addr:housenumber":"1590",
    "addr:postcode":"95133",
    "addr:street":"Berryessa Rd",
    "iso:country":"US",
    "sg:address":"1590 Berryessa Rd",
    "sg:city":"San Jose",
    "sg:classifiers":[
        {
            "category":"Shopping",
            "subcategory":"Computers & Home Electronics",
            "type":"Retail Goods"
        }
    ],
    "sg:phone":"+1 408 453 2113",
    "sg:postcode":"95133",
    "sg:province":"CA",
    "wof:name":"Club DJ",
    "wof:placetype":"venue"
},
  "geometry": {"coordinates":[-121.87843599999999,37.369794],"type":"Point"}
}