{
  "type": "Feature",
  "properties": {
    "addr:full":"1401 W 8th St Los Angeles CA 90017",
    "addr:housenumber":"1401",
    "addr:postcode":"90017",
    "addr:street":"W 8Th St",
    "iso:country":"US",
    "sg:address":"1401 W 8th St",
    "sg:city":"Los Angeles",
    "sg:classifiers":[
        {
            "category":"Home & Garden",
            "subcategory":"Furniture",
            "type":"Retail Goods"
        }
    ],
    "sg:phone":"+1 213 413 7768",
    "sg:postcode":"90017",
    "sg:province":"CA",
    "wof:name":"Us Office Furniture",
    "wof:placetype":"venue"
},
  "geometry": {"coordinates":[-118.270678,34.051089],"type":"Point"}
}