{
  "type": "Feature",
  "properties": {
    "iso:country":"US",
    "sg:address":"521 Daggett Ct",
    "sg:city":"Granite Bay",
    "sg:classifiers":[
        {
            "category":"Health Services",
            "subcategory":"Health Practitioner",
            "type":"Services"
        }
    ],
    "sg:phone":"+1 916 797 3307",
    "sg:postcode":"95746",
    "sg:province":"CA",
    "sg:tags":[
        "pathologist",
        "speech"
    ],
    "wof:name":"Nancy Barcal Ma Ccc Slp",
    "wof:placetype":"venue"
},
  "geometry": {"coordinates":[-121.22064399999999,38.720302],"type":"Point"}
}