{
  "type": "Feature",
  "properties": {
    "iso:country":"US",
    "sg:address":"162 Bluebird Dr",
    "sg:city":"Windsor",
    "sg:classifiers":[
        {
            "category":"Manufacturing",
            "subcategory":"Tools & Machinery",
            "type":"Manufacturing & Wholesale Goods"
        }
    ],
    "sg:phone":"+1 707 838 2535",
    "sg:postcode":"95492",
    "sg:province":"CA",
    "sg:tags":[
        "industrial",
        "mfg"
    ],
    "wof:name":"J & B Machining",
    "wof:placetype":"venue"
},
  "geometry": {"coordinates":[-122.802725,38.541741],"type":"Point"}
}