{
  "type": "Feature",
  "properties": {
    "addr:full":"4543 Alhambra Dr Fremont CA 94536",
    "addr:housenumber":"4543",
    "addr:postcode":"94536",
    "addr:street":"Alhambra Dr",
    "iso:country":"US",
    "sg:address":"4543 Alhambra Dr",
    "sg:city":"Fremont",
    "sg:classifiers":[
        {
            "category":"Manufacturing",
            "subcategory":"Tools & Machinery",
            "type":"Manufacturing & Wholesale Goods"
        }
    ],
    "sg:phone":"+1 510 303 2731",
    "sg:postcode":"94536",
    "sg:province":"CA",
    "sg:tags":[
        "machine",
        "mfg"
    ],
    "wof:name":"Apex Replacement Center",
    "wof:placetype":"venue"
},
  "geometry": {"coordinates":[-122.02887699999999,37.559874],"type":"Point"}
}