{
  "type": "Feature",
  "properties": {
    "addr:full":"12845 Poway Rd Poway CA 92064",
    "addr:housenumber":"12845",
    "addr:postcode":"ca 92064",
    "addr:street":"Poway Rd",
    "iso:country":"US",
    "sg:address":"12845 Poway Rd",
    "sg:city":"Poway",
    "sg:classifiers":[
        {
            "category":"Shopping",
            "subcategory":"Used Merchandise",
            "type":"Retail Goods"
        }
    ],
    "sg:phone":"+1 858 576 1700",
    "sg:postcode":"92064",
    "sg:province":"CA",
    "wof:name":"Classic Consignment II",
    "wof:placetype":"venue"
},
  "geometry": {"coordinates":[-117.05164499999999,32.956522],"type":"Point"}
}