{
  "type": "Feature",
  "properties": {
    "addr:full":"8225 McKee Rd Lamont CA 93241",
    "addr:housenumber":"8225",
    "addr:postcode":"93241",
    "addr:street":"Mckee Rd",
    "iso:country":"US",
    "sg:address":"8225 McKee Rd",
    "sg:city":"Lamont",
    "sg:classifiers":[
        {
            "category":"Government",
            "subcategory":"Fire Station",
            "type":"Public Place"
        }
    ],
    "sg:phone":"+1 661 845 1212",
    "sg:postcode":"93241",
    "sg:province":"CA",
    "sg:tags":[
        "protection"
    ],
    "wof:name":"Fire Dept- Station 51",
    "wof:placetype":"venue"
},
  "geometry": {"coordinates":[-118.911968,35.274204],"type":"Point"}
}