{
  "type": "Feature",
  "properties": {
    "iso:country":"US",
    "sg:address":"4600 7th Ave",
    "sg:city":"Sacramento",
    "sg:classifiers":[
        {
            "category":"Restaurant",
            "type":"Food & Drink"
        }
    ],
    "sg:phone":"+1 916 704 0786",
    "sg:postcode":"95820",
    "sg:province":"CA",
    "sg:tags":[
        "parlor",
        "ice",
        "cream"
    ],
    "wof:name":"Top Ice Cream",
    "wof:placetype":"venue"
},
  "geometry": {"coordinates":[-121.447941,38.545204],"type":"Point"}
}