{
  "type": "Feature",
  "properties": {
    "iso:country":"US",
    "sg:address":"665 Valencia St",
    "sg:city":"San Francisco",
    "sg:classifiers":[
        {
            "category":"Restaurant",
            "type":"Food & Drink"
        }
    ],
    "sg:menulink":"http://www.allmenus.com/ca/san-francisco/63200-ny-buffalo-wings/menu/",
    "sg:phone":"+1 415 863 7755",
    "sg:postcode":"94110",
    "sg:province":"CA",
    "sg:tags":[
        "american"
    ],
    "wof:name":"NY Buffalo Wings",
    "wof:placetype":"venue"
},
  "geometry": {"coordinates":[-122.421662,37.762286],"type":"Point"}
}