{
  "type": "Feature",
  "properties": {
    "addr:full":"3007 Teagarden St San Leandro CA 94577",
    "addr:postcode":"3007;94577",
    "addr:street":"Teagarden St",
    "iso:country":"US",
    "sg:address":"3007 Teagarden St",
    "sg:city":"San Leandro",
    "sg:classifiers":[
        {
            "category":"Professional",
            "subcategory":"Computer Services",
            "type":"Services"
        }
    ],
    "sg:phone":"+1 510 429 9411",
    "sg:postcode":"94577",
    "sg:province":"CA",
    "sg:tags":[
        "repair"
    ],
    "wof:name":"Multi Tech Enterprise",
    "wof:placetype":"venue"
},
  "geometry": {"coordinates":[-122.15775499999999,37.705781],"type":"Point"}
}