{
  "type": "Feature",
  "properties": {
    "addr:full":"4810 Tunis Rd Sacramento CA 95835",
    "addr:postcode":"4810;95835",
    "addr:street":"Tunis Rd",
    "iso:country":"US",
    "sg:address":"4810 Tunis Rd",
    "sg:city":"Sacramento",
    "sg:classifiers":[
        {
            "category":"Wholesale",
            "subcategory":"Farm Supplies",
            "type":"Manufacturing & Wholesale Goods"
        },
        {
            "category":"Wholesale",
            "subcategory":"Machinery & Supplies",
            "type":"Manufacturing & Wholesale Goods"
        }
    ],
    "sg:phone":"+1 916 515 8383",
    "sg:postcode":"95835",
    "sg:province":"CA",
    "sg:tags":[
        "equipment",
        "baling"
    ],
    "wof:name":"Euro Manufactoring",
    "wof:placetype":"venue"
},
  "geometry": {"coordinates":[-121.477687,38.656693],"type":"Point"}
}