{
  "type": "Feature",
  "properties": {
    "iso:country":"US",
    "sg:address":"1120 Hopkins Ave",
    "sg:city":"Palo Alto",
    "sg:classifiers":[
        {
            "category":"Social Services",
            "type":"Services"
        }
    ],
    "sg:phone":"+1 650 853 9692",
    "sg:postcode":"94301",
    "sg:province":"CA",
    "sg:tags":[
        "youth",
        "organization",
        "center"
    ],
    "wof:name":"Girl Scouts",
    "wof:placetype":"venue"
},
  "geometry": {"coordinates":[-122.143839,37.444429],"type":"Point"}
}