{
  "type": "Feature",
  "properties": {
    "iso:country":"US",
    "sg:address":"1869 Erringer Rd",
    "sg:city":"Simi Valley",
    "sg:classifiers":[
        {
            "category":"Food & Beverages",
            "subcategory":"Groceries & Convenience Stores",
            "type":"Retail Goods"
        }
    ],
    "sg:phone":"+1 805 582 9023",
    "sg:postcode":"93065",
    "sg:province":"CA",
    "sg:tags":[
        "grocer"
    ],
    "wof:name":"Simi 99 & Market",
    "wof:placetype":"venue"
},
  "geometry": {"coordinates":[-118.761442,34.271514],"type":"Point"}
}