{
  "type": "Feature",
  "properties": {
    "addr:full":"145 George St San Jose CA 95110",
    "addr:housenumber":"145",
    "addr:postcode":"95110",
    "addr:street":"George St",
    "iso:country":"US",
    "sg:address":"145 George St",
    "sg:city":"San Jose",
    "sg:classifiers":[
        {
            "category":"Professional",
            "subcategory":"Lawyer & Legal Services",
            "type":"Services"
        }
    ],
    "sg:phone":"+1 408 642 5125",
    "sg:postcode":"95110",
    "sg:province":"CA",
    "wof:name":"Edgar Law Group Inc",
    "wof:placetype":"venue"
},
  "geometry": {"coordinates":[-121.901523,37.346931],"type":"Point"}
}