{
  "type": "Feature",
  "properties": {
    "addr:full":"518 W 223rd St Carson CA 90745",
    "addr:housenumber":"518",
    "addr:postcode":"90745",
    "addr:street":"W 223Rd St",
    "iso:country":"US",
    "sg:address":"518 W 223rd St",
    "sg:city":"Carson",
    "sg:classifiers":[
        {
            "category":"Wholesale",
            "subcategory":"Apparel",
            "type":"Manufacturing & Wholesale Goods"
        }
    ],
    "sg:phone":"+1 310 212 1252",
    "sg:postcode":"90745",
    "sg:province":"CA",
    "sg:tags":[
        "sportswear"
    ],
    "wof:name":"Internationally Known Clothing",
    "wof:placetype":"venue"
},
  "geometry": {"coordinates":[-118.28448,33.82436],"type":"Point"}
}