{
  "type": "Feature",
  "properties": {
    "addr:full":"1140 W La Veta Ave Orange CA 92868",
    "addr:housenumber":"1140",
    "addr:postcode":"92868",
    "addr:street":"W La Veta Ave",
    "iso:country":"US",
    "sg:address":"1140 W La Veta Ave",
    "sg:city":"Orange",
    "sg:classifiers":[
        {
            "category":"Health Services",
            "subcategory":"Doctor",
            "type":"Services"
        }
    ],
    "sg:phone":"+1 714 835 6500",
    "sg:postcode":"92868",
    "sg:province":"CA",
    "sg:tags":[
        "surgeon",
        "orthopedist",
        "cosmetic"
    ],
    "sg:website":"www.ataleisnikmd.com",
    "wof:name":"Taleisnik Andres, MD",
    "wof:placetype":"venue"
},
  "geometry": {"coordinates":[-117.86509599999999,33.779383],"type":"Point"}
}