{
  "type": "Feature",
  "properties": {
    "addr:full":"13654 Mc Donnell St Moreno Valley CA 92553",
    "addr:housenumber":"13654",
    "addr:postcode":"92553",
    "addr:street":"Mc Donnell St",
    "iso:country":"US",
    "sg:address":"13654 Mc Donnell St",
    "sg:city":"Moreno Valley",
    "sg:classifiers":[
        {
            "category":"Retail",
            "subcategory":"Auto Repair",
            "type":"Services"
        }
    ],
    "sg:phone":"+1 951 688 5287",
    "sg:postcode":"92553",
    "sg:province":"CA",
    "sg:tags":[
        "wrecker"
    ],
    "wof:name":"Adame's Towing",
    "wof:placetype":"venue"
},
  "geometry": {"coordinates":[-117.268197,33.922612],"type":"Point"}
}