{
  "type": "Feature",
  "properties": {
    "iso:country":"US",
    "sg:address":"21688 Gateway Center Dr",
    "sg:city":"Diamond Bar",
    "sg:classifiers":[
        {
            "category":"Insurance",
            "subcategory":"Insurance Agent",
            "type":"Services"
        }
    ],
    "sg:phone":"+1 909 612 3000",
    "sg:postcode":"91765",
    "sg:province":"CA",
    "wof:name":"St Paul Travelers",
    "wof:placetype":"venue"
},
  "geometry": {"coordinates":[-117.83323300000001,34.000101],"type":"Point"}
}