{
  "type": "Feature",
  "properties": {
    "iso:country":"US",
    "sg:address":"919 W Mission St",
    "sg:city":"Santa Barbara",
    "sg:classifiers":[
        {
            "category":"Building & Trades",
            "subcategory":"Cleaning & Sanitation",
            "type":"Services"
        }
    ],
    "sg:phone":"+1 805 687 3818",
    "sg:postcode":"93101",
    "sg:province":"CA",
    "sg:tags":[
        "janitor"
    ],
    "wof:name":"Santa Barbara Cleaning",
    "wof:placetype":"venue"
},
  "geometry": {"coordinates":[-119.724703,34.421274],"type":"Point"}
}