{
  "type": "Feature",
  "properties": {
    "iso:country":"US",
    "sg:address":"1918 W Summerfield Ct",
    "sg:city":"Oakley",
    "sg:classifiers":[
        {
            "category":"Wholesale",
            "subcategory":"Stationery",
            "type":"Manufacturing & Wholesale Goods"
        }
    ],
    "sg:phone":"+1 925 625 5465",
    "sg:postcode":"94561",
    "sg:province":"CA",
    "sg:tags":[
        "supply"
    ],
    "wof:name":"Creative Memories",
    "wof:placetype":"venue"
},
  "geometry": {"coordinates":[-121.729085,38.003093],"type":"Point"}
}