{
  "type": "Feature",
  "properties": {
    "addr:full":"1540 River Park Dr Sacramento CA 95815",
    "addr:housenumber":"1540",
    "addr:postcode":"95815",
    "addr:street":"River Park Dr",
    "iso:country":"US",
    "sg:address":"1540 River Park Dr",
    "sg:city":"Sacramento",
    "sg:classifiers":[
        {
            "category":"Professional",
            "subcategory":"Management & Consulting",
            "type":"Services"
        }
    ],
    "sg:phone":"+1 916 568 0550",
    "sg:postcode":"95815",
    "sg:province":"CA",
    "sg:tags":[
        "report",
        "construction"
    ],
    "wof:name":"Manufacturer's Survey Assocs",
    "wof:placetype":"venue"
},
  "geometry": {"coordinates":[-121.438451,38.596831],"type":"Point"}
}