{
  "type": "Feature",
  "properties": {
    "addr:full":"142 N Magnolia Ave Monrovia CA 91016",
    "addr:housenumber":"142",
    "addr:postcode":"91016",
    "addr:street":"N Magnolia Ave",
    "iso:country":"US",
    "sg:address":"142 N Magnolia Ave",
    "sg:city":"Monrovia",
    "sg:classifiers":[
        {
            "category":"Professional",
            "type":"Services"
        }
    ],
    "sg:phone":"+1 626 358 5569",
    "sg:postcode":"91016",
    "sg:province":"CA",
    "wof:name":"Holly Earle",
    "wof:placetype":"venue"
},
  "geometry": {"coordinates":[-118.005387,34.15376],"type":"Point"}
}