{
  "type": "Feature",
  "properties": {
    "addr:full":"381 W Esplanade Dr Oxnard CA 93036",
    "addr:housenumber":"381",
    "addr:postcode":"93036",
    "addr:street":"W Esplanade Dr",
    "iso:country":"US",
    "sg:address":"381 W Esplanade Dr",
    "sg:city":"Oxnard",
    "sg:classifiers":[
        {
            "category":"Restaurant",
            "type":"Food & Drink"
        }
    ],
    "sg:menulink":"http://www.allmenus.com/ca/oxnard/224484-in--out-burger/menu/",
    "sg:postcode":"93036",
    "sg:province":"CA",
    "sg:tags":[
        "burger",
        "american"
    ],
    "wof:name":"In & Out Burger",
    "wof:placetype":"venue"
},
  "geometry": {"coordinates":[-119.17929100000001,34.234623],"type":"Point"}
}