{
  "type": "Feature",
  "properties": {
    "addr:full":"24234 Barton Rd Loma Linda CA 92354",
    "addr:housenumber":"24234",
    "addr:postcode":"92354",
    "addr:street":"Barton Rd",
    "iso:country":"US",
    "sg:address":"24234 Barton Rd",
    "sg:city":"Loma Linda",
    "sg:classifiers":[
        {
            "category":"Arts & Performance",
            "subcategory":"Theater",
            "type":"Entertainment"
        }
    ],
    "sg:phone":"+1 909 799 0575",
    "sg:postcode":"92354",
    "sg:province":"CA",
    "sg:tags":[
        "production",
        "musical"
    ],
    "wof:name":"Lo-Fi Studios",
    "wof:placetype":"venue"
},
  "geometry": {"coordinates":[-117.27719500000001,34.05181],"type":"Point"}
}