{
  "type": "Feature",
  "properties": {
    "iso:country":"US",
    "sg:address":"1701 N Main St",
    "sg:city":"Santa Ana",
    "sg:classifiers":[
        {
            "category":"Professional",
            "subcategory":"Lawyer & Legal Services",
            "type":"Services"
        }
    ],
    "sg:phone":"+1 714 245 8800",
    "sg:postcode":"92706",
    "sg:province":"CA",
    "sg:tags":[
        "attorney"
    ],
    "wof:name":"Bisom & Cohen",
    "wof:placetype":"venue"
},
  "geometry": {"coordinates":[-117.86756,33.7609],"type":"Point"}
}