{
  "type": "Feature",
  "properties": {
    "iso:country":"US",
    "sg:address":"25 Kendall Ln",
    "sg:city":"Danville",
    "sg:classifiers":[
        {
            "category":"Professional",
            "subcategory":"Management & Consulting",
            "type":"Services"
        }
    ],
    "sg:phone":"+1 925 743 1300",
    "sg:postcode":"94526",
    "sg:province":"CA",
    "sg:tags":[
        "party",
        "planning",
        "event"
    ],
    "wof:name":"Inventive Incentive",
    "wof:placetype":"venue"
},
  "geometry": {"coordinates":[-122.015683,37.834619],"type":"Point"}
}