{
  "type": "Feature",
  "properties": {
    "iso:country":"US",
    "sg:address":"515 Sunrise Ave",
    "sg:city":"Roseville",
    "sg:classifiers":[
        {
            "category":"Organizations",
            "subcategory":"Religious Organization",
            "type":"Services"
        }
    ],
    "sg:phone":"+1 916 782 3186",
    "sg:postcode":"95661",
    "sg:province":"CA",
    "sg:tags":[
        "church"
    ],
    "sg:website":"www.fpcroseville.com",
    "wof:name":"First Presbyterian Church",
    "wof:placetype":"venue"
},
  "geometry": {"coordinates":[-121.271949,38.736845],"type":"Point"}
}