{
  "type": "Feature",
  "properties": {
    "addr:full":"10725 Sutter Ave Pacoima CA 91331",
    "addr:housenumber":"10725",
    "addr:postcode":"91331",
    "addr:street":"Sutter Ave",
    "iso:country":"US",
    "sg:address":"10725 Sutter Ave",
    "sg:city":"Pacoima",
    "sg:classifiers":[
        {
            "category":"Manufacturing",
            "subcategory":"Food",
            "type":"Manufacturing & Wholesale Goods"
        }
    ],
    "sg:phone":"+1 818 899 9574",
    "sg:postcode":"91331",
    "sg:province":"CA",
    "sg:tags":[
        "extract",
        "syrup",
        "flavoring"
    ],
    "sg:website":"www.americanfruits-flavors.com",
    "wof:name":"American Fruit Processors",
    "wof:placetype":"venue"
},
  "geometry": {"coordinates":[-118.419443,34.264703],"type":"Point"}
}