{
  "type": "Feature",
  "properties": {
    "iso:country":"US",
    "sg:address":"3630 Placentia Ct",
    "sg:city":"Chino",
    "sg:classifiers":[
        {
            "category":"Wholesale",
            "subcategory":"Machinery & Supplies",
            "type":"Manufacturing & Wholesale Goods"
        }
    ],
    "sg:phone":"+1 909 627 0948",
    "sg:postcode":"91710",
    "sg:province":"CA",
    "sg:tags":[
        "tool"
    ],
    "sg:website":"www.pacificcoasttools.com",
    "wof:name":"Pacific Coast Air Tool & Supl",
    "wof:placetype":"venue"
},
  "geometry": {"coordinates":[-117.726145,34.023299],"type":"Point"}
}