{
  "type": "Feature",
  "properties": {
    "addr:full":"721 Yarmouth Rd Palos Vrds Ests CA 90274",
    "addr:housenumber":"721",
    "addr:postcode":"90274",
    "addr:street":"Yarmouth Rd",
    "iso:country":"US",
    "sg:address":"721 Yarmouth Rd",
    "sg:city":"Palos Vrds Ests",
    "sg:classifiers":[
        {
            "category":"Food & Beverages",
            "subcategory":"Liquor & Beverages",
            "type":"Retail Goods"
        }
    ],
    "sg:phone":"+1 310 375 2034",
    "sg:postcode":"90274",
    "sg:province":"CA",
    "wof:name":"Lunada Bay Liquor & Deli",
    "wof:placetype":"venue"
},
  "geometry": {"coordinates":[-118.41896300000001,33.77584],"type":"Point"}
}