{
  "type": "Feature",
  "properties": {
    "addr:full":"3712 Thode Way Sacramento CA 95821",
    "addr:housenumber":"3712",
    "addr:postcode":"95821",
    "addr:street":"Thode Way",
    "iso:country":"US",
    "sg:address":"3712 Thode Way",
    "sg:city":"Sacramento",
    "sg:classifiers":[
        {
            "category":"Building & Trades",
            "subcategory":"Construction",
            "type":"Services"
        }
    ],
    "sg:phone":"+1 916 879 2777",
    "sg:postcode":"95821",
    "sg:province":"CA",
    "sg:tags":[
        "handyman"
    ],
    "wof:name":"Schultz Enterprises",
    "wof:placetype":"venue"
},
  "geometry": {"coordinates":[-121.376295,38.634142],"type":"Point"}
}