{
  "type": "Feature",
  "properties": {
    "addr:full":"746 Magnolia Ave Long Beach CA 90813",
    "addr:housenumber":"746",
    "addr:postcode":"90813",
    "addr:street":"Magnolia Ave",
    "iso:country":"US",
    "sg:address":"746 Magnolia Ave",
    "sg:city":"Long Beach",
    "sg:classifiers":[
        {
            "category":"Professional",
            "subcategory":"Computer Services",
            "type":"Services"
        }
    ],
    "sg:phone":"+1 562 437 2371",
    "sg:postcode":"90813",
    "sg:province":"CA",
    "sg:tags":[
        "consultant",
        "designer"
    ],
    "wof:name":"Reliance Consulting",
    "wof:placetype":"venue"
},
  "geometry": {"coordinates":[-118.19794400000001,33.775938],"type":"Point"}
}