{
  "type": "Feature",
  "properties": {
    "addr:full":"156 Stoney Hill Dr Folsom CA 95630",
    "addr:housenumber":"156",
    "addr:postcode":"95630",
    "addr:street":"Stoney Hill Dr",
    "iso:country":"US",
    "sg:address":"156 Stoney Hill Dr",
    "sg:city":"Folsom",
    "sg:classifiers":[
        {
            "category":"Banks & Credit Unions",
            "subcategory":"Bank",
            "type":"Services"
        }
    ],
    "sg:phone":"+1 916 984 0700",
    "sg:postcode":"95630",
    "sg:province":"CA",
    "sg:tags":[
        "loan",
        "real estate"
    ],
    "wof:name":"First California Residential",
    "wof:placetype":"venue"
},
  "geometry": {"coordinates":[-121.12869600000001,38.682334],"type":"Point"}
}