{
  "type": "Feature",
  "properties": {
    "addr:full":"8541 Garden Grove Blvd Garden Grove CA 92844",
    "addr:housenumber":"8541",
    "addr:postcode":"92844",
    "addr:street":"Garden Grove Blvd",
    "iso:country":"US",
    "sg:address":"8541 Garden Grove Blvd",
    "sg:city":"Garden Grove",
    "sg:classifiers":[
        {
            "category":"Personal",
            "type":"Services"
        }
    ],
    "sg:phone":"+1 714 590 9131",
    "sg:postcode":"92844",
    "sg:province":"CA",
    "sg:tags":[
        "towing"
    ],
    "wof:name":"Armstrong Towing & Service",
    "wof:placetype":"venue"
},
  "geometry": {"coordinates":[-117.98400100000001,33.773998],"type":"Point"}
}