{
  "type": "Feature",
  "properties": {
    "iso:country":"US",
    "sg:address":"5224 E Morada Ln",
    "sg:city":"Stockton",
    "sg:classifiers":[
        {
            "category":"Education",
            "subcategory":"School",
            "type":"Public Place"
        }
    ],
    "sg:phone":"+1 209 953 8301",
    "sg:postcode":"95212",
    "sg:province":"CA",
    "wof:name":"Davis Elementary School",
    "wof:placetype":"venue"
},
  "geometry": {"coordinates":[-121.250063,38.037315],"type":"Point"}
}