{
  "type": "Feature",
  "properties": {
    "addr:full":"2330 Vanguard Way Costa Mesa CA 92626",
    "addr:housenumber":"2330",
    "addr:postcode":"92626",
    "addr:street":"Vanguard Way",
    "iso:country":"US",
    "sg:address":"2330 Vanguard Way",
    "sg:city":"Costa Mesa",
    "sg:classifiers":[
        {
            "category":"Professional",
            "subcategory":"Business Services",
            "type":"Services"
        }
    ],
    "sg:phone":"+1 714 545 6766",
    "sg:postcode":"92626",
    "sg:province":"CA",
    "sg:tags":[
        "interior",
        "designer"
    ],
    "wof:name":"Metropolitan Design Group",
    "wof:placetype":"venue"
},
  "geometry": {"coordinates":[-117.90473,33.661039],"type":"Point"}
}