{
  "type": "Feature",
  "properties": {
    "iso:country":"US",
    "sg:address":"6214 Hwy 9",
    "sg:city":"Felton",
    "sg:classifiers":[
        {
            "category":"Health Services",
            "subcategory":"Chiropractor",
            "type":"Services"
        }
    ],
    "sg:phone":"+1 831 335 3569",
    "sg:postcode":"95018",
    "sg:province":"CA",
    "wof:name":"Lund Chiropractic",
    "wof:placetype":"venue"
},
  "geometry": {"coordinates":[-122.073167,37.051439],"type":"Point"}
}