{
  "type": "Feature",
  "properties": {
    "addr:full":"11801 Mulholland Dr Los Angeles CA 90210",
    "addr:housenumber":"11801",
    "addr:postcode":"90210",
    "addr:street":"Mulholland Dr",
    "iso:country":"US",
    "sg:address":"11801 Mulholland Dr",
    "sg:city":"Los Angeles",
    "sg:classifiers":[
        {
            "category":"Park",
            "type":"Public Place"
        }
    ],
    "sg:postcode":"90210",
    "sg:province":"CA",
    "wof:name":"Barbara A Fine Overlook at the Summit",
    "wof:placetype":"venue"
},
  "geometry": {"coordinates":[-118.39769200000001,34.119296],"type":"Point"}
}