{
  "type": "Feature",
  "properties": {
    "addr:full":"4905 N West Ave Fresno CA 93705",
    "addr:housenumber":"4905",
    "addr:postcode":"93705",
    "addr:street":"N West Ave",
    "iso:country":"US",
    "sg:address":"4905 N West Ave",
    "sg:city":"Fresno",
    "sg:classifiers":[
        {
            "category":"Personal",
            "subcategory":"Beauty Salon",
            "type":"Services"
        }
    ],
    "sg:phone":"+1 559 225 2645",
    "sg:postcode":"93705",
    "sg:province":"CA",
    "sg:tags":[
        "spa",
        "day"
    ],
    "wof:name":"Spa Essence",
    "wof:placetype":"venue"
},
  "geometry": {"coordinates":[-119.826459,36.806831],"type":"Point"}
}