{
  "type": "Feature",
  "properties": {
    "iso:country":"US",
    "sg:address":"1819 E Roseville Pkwy",
    "sg:city":"Roseville",
    "sg:classifiers":[
        {
            "category":"Retail",
            "subcategory":"Auto Rental",
            "type":"Services"
        },
        {
            "category":"Local Transit",
            "type":"Transportation"
        }
    ],
    "sg:phone":"+1 916 532 5466",
    "sg:postcode":"95661",
    "sg:province":"CA",
    "sg:tags":[
        "shuttle",
        "limousine"
    ],
    "wof:name":"A2z Limo Inc",
    "wof:placetype":"venue"
},
  "geometry": {"coordinates":[-121.228206,38.731144],"type":"Point"}
}