{
  "type": "Feature",
  "properties": {
    "iso:country":"US",
    "sg:address":"423 N Atlantic Blvd Ste 102",
    "sg:city":"Alhambra",
    "sg:classifiers":[
        {
            "category":"Restaurant",
            "type":"Food & Drink"
        }
    ],
    "sg:phone":"+1 626 284 1295",
    "sg:postcode":"91801",
    "sg:province":"CA",
    "sg:tags":[
        "thai"
    ],
    "wof:name":"Thanh Thai",
    "wof:placetype":"venue"
},
  "geometry": {"coordinates":[-118.134694,34.097171],"type":"Point"}
}