{
  "type": "Feature",
  "properties": {
    "iso:country":"US",
    "sg:address":"17588 Rowland St",
    "sg:city":"City Of Industry",
    "sg:classifiers":[
        {
            "category":"Wholesale",
            "subcategory":"Computers",
            "type":"Manufacturing & Wholesale Goods"
        }
    ],
    "sg:phone":"+1 626 581 7938",
    "sg:postcode":"91748",
    "sg:province":"CA",
    "wof:name":"Alta Media Tech",
    "wof:placetype":"venue"
},
  "geometry": {"coordinates":[-117.921769,34.001683],"type":"Point"}
}