{
  "type": "Feature",
  "properties": {
    "iso:country":"US",
    "sg:address":"101 S Atlantic Blvd",
    "sg:city":"Alhambra",
    "sg:classifiers":[
        {
            "category":"Education",
            "subcategory":"School",
            "type":"Public Place"
        }
    ],
    "sg:phone":"+1 626 570 0204",
    "sg:postcode":"91801",
    "sg:province":"CA",
    "sg:tags":[
        "high",
        "middle",
        "elementary"
    ],
    "wof:name":"First Baptist Church After School Program",
    "wof:placetype":"venue"
},
  "geometry": {"coordinates":[-118.13400300000001,34.090199],"type":"Point"}
}