{
  "type": "Feature",
  "properties": {
    "addr:full":"143 S Cedros Ave Ste V101 Solana Beach CA 92075",
    "addr:housenumber":"143",
    "addr:postcode":"92075",
    "addr:street":"S Cedros Ave Ste V101",
    "iso:country":"US",
    "sg:address":"143 S Cedros Ave Ste V101",
    "sg:city":"Solana Beach",
    "sg:classifiers":[
        {
            "category":"Personal",
            "subcategory":"Beauty Salon",
            "type":"Services"
        }
    ],
    "sg:phone":"+1 858 481 1909",
    "sg:postcode":"92075",
    "sg:province":"CA",
    "sg:tags":[
        "hair"
    ],
    "wof:name":"Fusion Salon and Boutique",
    "wof:placetype":"venue"
},
  "geometry": {"coordinates":[-117.270478,32.991456],"type":"Point"}
}