{
  "type": "Feature",
  "properties": {
    "addr:full":"1394 Borregas Ave Sunnyvale CA 94089",
    "addr:housenumber":"1394",
    "addr:postcode":"94089",
    "addr:street":"Borregas Ave",
    "iso:country":"US",
    "sg:address":"1394 Borregas Ave",
    "sg:city":"Sunnyvale",
    "sg:classifiers":[
        {
            "category":"Professional",
            "subcategory":"Management & Consulting",
            "type":"Services"
        }
    ],
    "sg:phone":"+1 408 541 6188",
    "sg:postcode":"94089",
    "sg:province":"CA",
    "sg:tags":[
        "consultant",
        "telecommunication"
    ],
    "wof:name":"Alpha Telecom",
    "wof:placetype":"venue"
},
  "geometry": {"coordinates":[-122.016558,37.416093],"type":"Point"}
}