{
  "type": "Feature",
  "properties": {
    "iso:country":"US",
    "sg:address":"5792 W Mckinley Ave",
    "sg:city":"Fresno",
    "sg:classifiers":[
        {
            "category":"Professional",
            "subcategory":"Engineering",
            "type":"Services"
        },
        {
            "category":"Building & Trades",
            "subcategory":"Construction",
            "type":"Services"
        }
    ],
    "sg:phone":"+1 559 271 7684",
    "sg:postcode":"93722",
    "sg:province":"CA",
    "sg:tags":[
        "repair",
        "management",
        "energy",
        "systems-service",
        "equipment",
        "solar",
        "engineer"
    ],
    "wof:name":"Solar Shine",
    "wof:placetype":"venue"
},
  "geometry": {"coordinates":[-119.89476999999999,36.764441],"type":"Point"}
}