{
  "type": "Feature",
  "properties": {
    "iso:country":"US",
    "sg:address":"5442 E Ave Palmar",
    "sg:city":"Orange",
    "sg:classifiers":[
        {
            "category":"Professional",
            "type":"Services"
        }
    ],
    "sg:phone":"+1 714 771 1735",
    "sg:postcode":"92869",
    "sg:province":"CA",
    "wof:name":"Thermosil Inc",
    "wof:placetype":"venue"
},
  "geometry": {"coordinates":[-117.794591,33.79121],"type":"Point"}
}