{
  "type": "Feature",
  "properties": {
    "iso:country":"US",
    "sg:address":"31933 Ave la Gaviota",
    "sg:city":"Cathedral City",
    "sg:classifiers":[
        {
            "category":"Health Services",
            "subcategory":"Clinic",
            "type":"Services"
        }
    ],
    "sg:phone":"+1 760 770 4903",
    "sg:postcode":"92234",
    "sg:province":"CA",
    "sg:tags":[
        "home"
    ],
    "wof:name":"Family Home Care",
    "wof:placetype":"venue"
},
  "geometry": {"coordinates":[-116.472216,33.819077],"type":"Point"}
}