{
  "type": "Feature",
  "properties": {
    "addr:full":"261 W Foothill Blvd Rialto CA 92376",
    "addr:housenumber":"261",
    "addr:postcode":"92376",
    "addr:street":"W Foothill Blvd",
    "iso:country":"US",
    "sg:address":"261 W Foothill Blvd",
    "sg:city":"Rialto",
    "sg:classifiers":[
        {
            "category":"Recreation",
            "type":"Entertainment"
        }
    ],
    "sg:phone":"+1 909 873 1376",
    "sg:postcode":"92376",
    "sg:province":"CA",
    "sg:tags":[
        "martial",
        "arts",
        "instruction"
    ],
    "wof:name":"Tiger Lee Martial Arts Studio",
    "wof:placetype":"venue"
},
  "geometry": {"coordinates":[-117.37373599999999,34.106708],"type":"Point"}
}