{
  "type": "Feature",
  "properties": {
    "iso:country":"US",
    "sg:address":"3030 Sepulveda Blvd",
    "sg:city":"Torrance",
    "sg:classifiers":[
        {
            "category":"Shopping",
            "subcategory":"Gifts & Souvenirs",
            "type":"Retail Goods"
        }
    ],
    "sg:phone":"+1 310 325 5959",
    "sg:postcode":"90505",
    "sg:province":"CA",
    "wof:name":"Amie Mon Gift Shop",
    "wof:placetype":"venue"
},
  "geometry": {"coordinates":[-118.343689,33.824849],"type":"Point"}
}