{
  "type": "Feature",
  "properties": {
    "iso:country":"US",
    "sg:address":"2778 Sweetwater Springs Blvd",
    "sg:city":"Spring Valley",
    "sg:classifiers":[
        {
            "category":"Education",
            "subcategory":"Special Training",
            "type":"Public Place"
        }
    ],
    "sg:phone":"+1 619 660 1335",
    "sg:postcode":"91977",
    "sg:province":"CA",
    "sg:tags":[
        "school",
        "instruction",
        "art"
    ],
    "wof:name":"Artistic Creations Art Studio",
    "wof:placetype":"venue"
},
  "geometry": {"coordinates":[-116.970533,32.727384],"type":"Point"}
}