{
  "type": "Feature",
  "properties": {
    "addr:full":"11803 Smith Ave Santa Fe Springs CA 90670",
    "addr:housenumber":"11803",
    "addr:postcode":"90670",
    "addr:street":"Smith Ave",
    "iso:country":"US",
    "sg:address":"11803 Smith Ave",
    "sg:city":"Santa Fe Springs",
    "sg:classifiers":[
        {
            "category":"Professional",
            "subcategory":"Advertising",
            "type":"Services"
        }
    ],
    "sg:phone":"+1 562 801 5397",
    "sg:postcode":"90670",
    "sg:province":"CA",
    "sg:tags":[
        "counselor"
    ],
    "sg:website":"www.jperez.com",
    "wof:name":"J Perez Assoc Inc",
    "wof:placetype":"venue"
},
  "geometry": {"coordinates":[-118.078137,33.949316],"type":"Point"}
}