{
  "type": "Feature",
  "properties": {
    "iso:country":"US",
    "sg:address":"1060 W 9th St",
    "sg:city":"Upland",
    "sg:classifiers":[
        {
            "category":"Retail",
            "subcategory":"Auto Repair",
            "type":"Services"
        }
    ],
    "sg:phone":"+1 909 981 9668",
    "sg:postcode":"91786",
    "sg:province":"CA",
    "sg:tags":[
        "body",
        "automobile",
        "painting"
    ],
    "wof:name":"Steve's Collision & Rstrtn",
    "wof:placetype":"venue"
},
  "geometry": {"coordinates":[-117.668527,34.095961],"type":"Point"}
}