{
  "type": "Feature",
  "properties": {
    "addr:full":"4401 Manchester Ave Ste 203 Encinitas CA 92024",
    "addr:housenumber":"4401",
    "addr:postcode":"92024",
    "addr:street":"Manchester Ave Ste 203",
    "iso:country":"US",
    "sg:address":"4401 Manchester Ave Ste 203",
    "sg:city":"Encinitas",
    "sg:classifiers":[
        {
            "category":"Health Services",
            "subcategory":"Dentist",
            "type":"Services"
        }
    ],
    "sg:phone":"+1 760 753 9036",
    "sg:postcode":"92024",
    "sg:province":"CA",
    "sg:website":"www.encinitas-dentist.net",
    "wof:name":"Dr. Dennis \u00a0F Gile, DDS",
    "wof:placetype":"venue"
},
  "geometry": {"coordinates":[-117.239632,33.035951],"type":"Point"}
}