{
  "type": "Feature",
  "properties": {
    "iso:country":"US",
    "sg:address":"375 3rd St",
    "sg:city":"Oakland",
    "sg:classifiers":[
        {
            "category":"Wholesale",
            "subcategory":"Fruits & Vegetables",
            "type":"Manufacturing & Wholesale Goods"
        }
    ],
    "sg:phone":"+1 510 451 1330",
    "sg:postcode":"94607",
    "sg:province":"CA",
    "sg:tags":[
        "veggie"
    ],
    "wof:name":"G & N Produce Co",
    "wof:placetype":"venue"
},
  "geometry": {"coordinates":[-122.274002,37.796101],"type":"Point"}
}