{
  "type": "Feature",
  "properties": {
    "iso:country":"US",
    "sg:address":"1641 W Main St",
    "sg:city":"Alhambra",
    "sg:classifiers":[
        {
            "category":"Freight",
            "type":"Transportation"
        }
    ],
    "sg:phone":"+1 626 281 5868",
    "sg:postcode":"91801",
    "sg:province":"CA",
    "wof:name":"Sunway Logistics USA Inc",
    "wof:placetype":"venue"
},
  "geometry": {"coordinates":[-118.141595,34.091598],"type":"Point"}
}