{
  "type": "Feature",
  "properties": {
    "addr:full":"912 Manhattan Ave Ste A Manhattan Beach CA 90266",
    "addr:housenumber":"912",
    "addr:postcode":"90266",
    "addr:street":"Manhattan Ave Ste A",
    "iso:country":"US",
    "sg:address":"912 Manhattan Ave Ste A",
    "sg:city":"Manhattan Beach",
    "sg:classifiers":[
        {
            "category":"Shopping",
            "subcategory":"Clothing, Apparel, & Fashions",
            "type":"Retail Goods"
        }
    ],
    "sg:phone":"+1 310 379 5294",
    "sg:postcode":"90266",
    "sg:province":"CA",
    "sg:tags":[
        "accessory",
        "clothing",
        "women's"
    ],
    "wof:name":"Fino Manhattan",
    "wof:placetype":"venue"
},
  "geometry": {"coordinates":[-118.410004,33.883099],"type":"Point"}
}