{
  "type": "Feature",
  "properties": {
    "iso:country":"US",
    "sg:address":"23615 el Toro Rd",
    "sg:city":"Lake Forest",
    "sg:classifiers":[
        {
            "category":"Wholesale",
            "subcategory":"Apparel",
            "type":"Manufacturing & Wholesale Goods"
        }
    ],
    "sg:phone":"+1 949 707 5020",
    "sg:postcode":"92630",
    "sg:province":"CA",
    "sg:tags":[
        "clothing"
    ],
    "wof:name":"Mark & John",
    "wof:placetype":"venue"
},
  "geometry": {"coordinates":[-117.700863,33.62038],"type":"Point"}
}