{
  "type": "Feature",
  "properties": {
    "iso:country":"US",
    "sg:address":"840 46th St",
    "sg:city":"Sacramento",
    "sg:classifiers":[
        {
            "category":"Shopping",
            "subcategory":"Used Merchandise",
            "type":"Retail Goods"
        }
    ],
    "sg:phone":"+1 916 454 5455",
    "sg:postcode":"95819",
    "sg:province":"CA",
    "wof:name":"Stantons Books",
    "wof:placetype":"venue"
},
  "geometry": {"coordinates":[-121.44569799999999,38.56814],"type":"Point"}
}