{
  "type": "Feature",
  "properties": {
    "iso:country":"US",
    "sg:address":"18445 Amistad St",
    "sg:city":"Fountain Valley",
    "sg:classifiers":[
        {
            "category":"Wholesale",
            "subcategory":"Machinery & Supplies",
            "type":"Manufacturing & Wholesale Goods"
        }
    ],
    "sg:phone":"+1 714 968 0105",
    "sg:postcode":"92708",
    "sg:province":"CA",
    "sg:tags":[
        "fire",
        "fighting"
    ],
    "wof:name":"G M R International Equipment",
    "wof:placetype":"venue"
},
  "geometry": {"coordinates":[-117.94387,33.695078],"type":"Point"}
}