{
  "type": "Feature",
  "properties": {
    "addr:full":"507 Russ St Eureka CA 95501",
    "addr:housenumber":"507",
    "addr:postcode":"95501",
    "addr:street":"Russ St",
    "iso:country":"US",
    "sg:address":"507 Russ St",
    "sg:city":"Eureka",
    "sg:classifiers":[
        {
            "category":"Real Estate",
            "subcategory":"Real Estate Agent",
            "type":"Services"
        }
    ],
    "sg:phone":"+1 707 442 8736",
    "sg:postcode":"95501",
    "sg:province":"CA",
    "wof:name":"Donna Brown Realty",
    "wof:placetype":"venue"
},
  "geometry": {"coordinates":[-124.163454,40.782081],"type":"Point"}
}