{
  "type": "Feature",
  "properties": {
    "iso:country":"US",
    "sg:address":"3061 Bostick Ave",
    "sg:city":"Marina",
    "sg:classifiers":[
        {
            "category":"Organizations",
            "subcategory":"Community Association",
            "type":"Services"
        }
    ],
    "sg:phone":"+1 831 646 4535",
    "sg:postcode":"93933",
    "sg:province":"CA",
    "sg:tags":[
        "club"
    ],
    "wof:name":"Lions Club",
    "wof:placetype":"venue"
},
  "geometry": {"coordinates":[-121.783376,36.672637],"type":"Point"}
}