{
  "type": "Feature",
  "properties": {
    "iso:country":"US",
    "sg:address":"627 April Dr",
    "sg:city":"Huntington Beach",
    "sg:classifiers":[
        {
            "category":"Wholesale",
            "subcategory":"Electrical",
            "type":"Manufacturing & Wholesale Goods"
        }
    ],
    "sg:phone":"+1 714 960 5534",
    "sg:postcode":"92648",
    "sg:province":"CA",
    "sg:tags":[
        "equipment"
    ],
    "wof:name":"Tech Sell International",
    "wof:placetype":"venue"
},
  "geometry": {"coordinates":[-117.990195,33.669448],"type":"Point"}
}