{
  "type": "Feature",
  "properties": {
    "iso:country":"US",
    "sg:address":"13003 Rosedale Hwy",
    "sg:city":"Bakersfield",
    "sg:classifiers":[
        {
            "category":"Fast Food",
            "type":"Food & Drink"
        }
    ],
    "sg:phone":"+1 661 587 0110",
    "sg:postcode":"93314",
    "sg:province":"CA",
    "sg:tags":[
        "restaurant"
    ],
    "sg:website":"http://www.mcdonalds.com",
    "wof:name":"McDonald's",
    "wof:placetype":"venue"
},
  "geometry": {"coordinates":[-119.146457,35.383489],"type":"Point"}
}