{
  "type": "Feature",
  "properties": {
    "iso:country":"US",
    "sg:address":"4365 Executive Dr",
    "sg:city":"San Diego",
    "sg:classifiers":[
        {
            "category":"Insurance",
            "subcategory":"Insurance Agent",
            "type":"Services"
        }
    ],
    "sg:phone":"+1 858 535 1800",
    "sg:postcode":"92121",
    "sg:province":"CA",
    "sg:website":"www.hrh.com",
    "wof:name":"Hobbs Group Inc",
    "wof:placetype":"venue"
},
  "geometry": {"coordinates":[-117.211248,32.875009],"type":"Point"}
}