{
  "type": "Feature",
  "properties": {
    "iso:country":"US",
    "sg:address":"3650 South St",
    "sg:city":"Lakewood",
    "sg:classifiers":[
        {
            "category":"Health Services",
            "subcategory":"Doctor",
            "type":"Services"
        }
    ],
    "sg:phone":"+1 562 630 3340",
    "sg:postcode":"90712",
    "sg:province":"CA",
    "sg:tags":[
        "practice",
        "family"
    ],
    "wof:name":"Ayoub Eli MD A Professional Corp",
    "wof:placetype":"venue"
},
  "geometry": {"coordinates":[-118.149352,33.85971],"type":"Point"}
}