{
  "type": "Feature",
  "properties": {
    "addr:full":"1323 Cassland Ct San Jose CA 95131",
    "addr:housenumber":"1323",
    "addr:postcode":"95131",
    "addr:street":"Cassland Ct",
    "iso:country":"US",
    "sg:address":"1323 Cassland Ct",
    "sg:city":"San Jose",
    "sg:classifiers":[
        {
            "category":"Wholesale",
            "subcategory":"Groceries",
            "type":"Manufacturing & Wholesale Goods"
        }
    ],
    "sg:phone":"+1 408 923 7064",
    "sg:postcode":"95131",
    "sg:province":"CA",
    "wof:name":"Edens Organic Baked Goods Inc",
    "wof:placetype":"venue"
},
  "geometry": {"coordinates":[-121.877685,37.379757],"type":"Point"}
}