{
  "type": "Feature",
  "properties": {
    "iso:country":"US",
    "sg:address":"1332 E Alondra Blvd",
    "sg:city":"Compton",
    "sg:classifiers":[
        {
            "category":"Professional",
            "subcategory":"Management & Consulting",
            "type":"Services"
        }
    ],
    "sg:phone":"+1 310 537 2878",
    "sg:postcode":"90221",
    "sg:province":"CA",
    "sg:tags":[
        "construction",
        "contractor"
    ],
    "wof:name":"Sewon Construction",
    "wof:placetype":"venue"
},
  "geometry": {"coordinates":[-118.20765299999999,33.88863],"type":"Point"}
}