{
  "type": "Feature",
  "properties": {
    "addr:full":"400 Capitol Mall Sacramento CA 95814",
    "addr:housenumber":"400",
    "addr:postcode":"95814",
    "addr:street":"Capitol Mall",
    "iso:country":"US",
    "sg:address":"400 Capitol Mall",
    "sg:city":"Sacramento",
    "sg:classifiers":[
        {
            "category":"Professional",
            "subcategory":"Lawyer & Legal Services",
            "type":"Services"
        }
    ],
    "sg:phone":"+1 916 325 1310",
    "sg:postcode":"95814",
    "sg:province":"CA",
    "sg:tags":[
        "plan"
    ],
    "wof:name":"Christopher Morrison Russell",
    "wof:placetype":"venue"
},
  "geometry": {"coordinates":[-121.502922,38.579029],"type":"Point"}
}