{
  "type": "Feature",
  "properties": {
    "addr:full":"5222 Balboa Ave San Diego CA 92117",
    "addr:housenumber":"5222",
    "addr:postcode":"92117",
    "addr:street":"Balboa Ave",
    "iso:country":"US",
    "sg:address":"5222 Balboa Ave",
    "sg:city":"San Diego",
    "sg:classifiers":[
        {
            "category":"Health Services",
            "subcategory":"Doctor",
            "type":"Services"
        }
    ],
    "sg:phone":"+1 858 279 1900",
    "sg:postcode":"92117",
    "sg:province":"CA",
    "sg:tags":[
        "dentist"
    ],
    "wof:name":"Clairemont Dental Group",
    "wof:placetype":"venue"
},
  "geometry": {"coordinates":[-117.18411,32.818587],"type":"Point"}
}