{
  "type": "Feature",
  "properties": {
    "addr:full":"119 10th St Oakland CA 94607",
    "addr:housenumber":"119",
    "addr:postcode":"94607",
    "addr:street":"10Th St",
    "iso:country":"US",
    "sg:address":"119 10th St",
    "sg:city":"Oakland",
    "sg:classifiers":[
        {
            "category":"Home & Garden",
            "subcategory":"Hardware",
            "type":"Retail Goods"
        }
    ],
    "sg:phone":"+1 510 832 8888",
    "sg:postcode":"94607",
    "sg:province":"CA",
    "sg:tags":[
        "store"
    ],
    "wof:name":"American Emperor Corporation",
    "wof:placetype":"venue"
},
  "geometry": {"coordinates":[-122.30999799999999,37.812801],"type":"Point"}
}