{
  "type": "Feature",
  "properties": {
    "addr:full":"1607 Abram Ct San Leandro CA 94577",
    "addr:housenumber":"1607",
    "addr:postcode":"94577",
    "addr:street":"Abram Ct",
    "iso:country":"US",
    "sg:address":"1607 Abram Ct",
    "sg:city":"San Leandro",
    "sg:classifiers":[
        {
            "category":"Manufacturing",
            "subcategory":"Tools & Machinery",
            "type":"Manufacturing & Wholesale Goods"
        }
    ],
    "sg:phone":"+1 510 483 2323",
    "sg:postcode":"94577",
    "sg:province":"CA",
    "sg:tags":[
        "concrete",
        "cutting",
        "breaking",
        "equipment"
    ],
    "sg:website":"www.leitchco.com",
    "wof:name":"Leitch & Co",
    "wof:placetype":"venue"
},
  "geometry": {"coordinates":[-122.171463,37.709798],"type":"Point"}
}