{
  "type": "Feature",
  "properties": {
    "addr:full":"307 E 1st St Santa Ana CA 92701",
    "addr:housenumber":"307",
    "addr:postcode":"92701",
    "addr:street":"E 1St St",
    "iso:country":"US",
    "sg:address":"307 E 1st St",
    "sg:city":"Santa Ana",
    "sg:classifiers":[
        {
            "category":"Shopping",
            "subcategory":"Florist",
            "type":"Retail Goods"
        }
    ],
    "sg:phone":"+1 714 543 6073",
    "sg:postcode":"92701",
    "sg:province":"CA",
    "wof:name":"Grace's Flowers & Gifts",
    "wof:placetype":"venue"
},
  "geometry": {"coordinates":[-117.86467399999999,33.745502],"type":"Point"}
}