{
  "type": "Feature",
  "properties": {
    "iso:country":"US",
    "sg:address":"55 Gate 5 Rd",
    "sg:city":"Sausalito",
    "sg:classifiers":[
        {
            "category":"Manufacturing",
            "subcategory":"Printing",
            "type":"Manufacturing & Wholesale Goods"
        }
    ],
    "sg:phone":"+1 415 332 5390",
    "sg:postcode":"94965",
    "sg:province":"CA",
    "sg:tags":[
        "publisher"
    ],
    "sg:website":"www.uscibooks.com",
    "wof:name":"University Science Books",
    "wof:placetype":"venue"
},
  "geometry": {"coordinates":[-122.502718,37.871223],"type":"Point"}
}