{
  "type": "Feature",
  "properties": {
    "addr:full":"3923 Coleman Ave San Diego CA 92154",
    "addr:housenumber":"3923",
    "addr:postcode":"92154",
    "addr:street":"Coleman Ave",
    "iso:country":"US",
    "sg:address":"3923 Coleman Ave",
    "sg:city":"San Diego",
    "sg:classifiers":[
        {
            "category":"Shopping",
            "subcategory":"Jewelry",
            "type":"Retail Goods"
        }
    ],
    "sg:phone":"+1 619 690 5501",
    "sg:postcode":"92154",
    "sg:province":"CA",
    "sg:tags":[
        "jeweler"
    ],
    "wof:name":"Natures Treasures",
    "wof:placetype":"venue"
},
  "geometry": {"coordinates":[-117.046725,32.582857],"type":"Point"}
}