{
  "type": "Feature",
  "properties": {
    "addr:full":"1773 E Thousand Oaks Blvd Thousand Oaks CA 91362",
    "addr:housenumber":"1773",
    "addr:postcode":"91362",
    "addr:street":"E Thousand Oaks Blvd",
    "iso:country":"US",
    "sg:address":"1773 E Thousand Oaks Blvd",
    "sg:city":"Thousand Oaks",
    "sg:classifiers":[
        {
            "category":"Food & Beverages",
            "subcategory":"Groceries & Convenience Stores",
            "type":"Retail Goods"
        }
    ],
    "sg:phone":"+1 805 497 3220",
    "sg:postcode":"91362",
    "sg:province":"CA",
    "sg:tags":[
        "product"
    ],
    "wof:name":"7 Eleven Food Store 13890",
    "wof:placetype":"venue"
},
  "geometry": {"coordinates":[-118.849564,34.176603],"type":"Point"}
}