{
  "type": "Feature",
  "properties": {
    "addr:full":"2319 E Lincoln Ave Escondido CA 92027",
    "addr:housenumber":"2319",
    "addr:postcode":"92027",
    "addr:street":"E Lincoln Ave",
    "iso:country":"US",
    "sg:address":"2319 E Lincoln Ave",
    "sg:city":"Escondido",
    "sg:classifiers":[
        {
            "category":"Manufacturing",
            "subcategory":"Apparel",
            "type":"Manufacturing & Wholesale Goods"
        }
    ],
    "sg:phone":"+1 760 233 7855",
    "sg:postcode":"92027",
    "sg:province":"CA",
    "sg:tags":[
        "textile",
        "product",
        "fabricated",
        "mfg"
    ],
    "wof:name":"Bumda Ta",
    "wof:placetype":"venue"
},
  "geometry": {"coordinates":[-117.054316,33.152243],"type":"Point"}
}