{
  "type": "Feature",
  "properties": {
    "iso:country":"US",
    "sg:address":"1190 Eagle Tree Ln",
    "sg:city":"Felton",
    "sg:classifiers":[
        {
            "category":"Wholesale",
            "subcategory":"Machinery & Supplies",
            "type":"Manufacturing & Wholesale Goods"
        }
    ],
    "sg:phone":"+1 831 335 4465",
    "sg:postcode":"95018",
    "sg:province":"CA",
    "sg:tags":[
        "salon",
        "beauty"
    ],
    "wof:name":"Devine Salon Products",
    "wof:placetype":"venue"
},
  "geometry": {"coordinates":[-122.02707700000001,37.136764],"type":"Point"}
}