{
  "type": "Feature",
  "properties": {
    "addr:full":"205 13th Street San Francisco CA 94103",
    "addr:housenumber":"205",
    "addr:postcode":"94103",
    "addr:street":"13Th Street",
    "iso:country":"US",
    "sg:address":"205 13th Street",
    "sg:city":"San Francisco",
    "sg:classifiers":[
        {
            "category":"Building & Trades",
            "subcategory":"Construction",
            "type":"Services"
        }
    ],
    "sg:phone":"+1 415 701 8855",
    "sg:postcode":"94103",
    "sg:province":"CA",
    "sg:tags":[
        "interior",
        "design"
    ],
    "wof:name":"Intarch",
    "wof:placetype":"venue"
},
  "geometry": {"coordinates":[-122.41883199999999,37.769703],"type":"Point"}
}