{
  "type": "Feature",
  "properties": {
    "addr:full":"4214 Corte Facil San Diego CA 92130",
    "addr:housenumber":"4214",
    "addr:postcode":"92130",
    "addr:street":"Corte Facil",
    "iso:country":"US",
    "sg:address":"4214 Corte Facil",
    "sg:city":"San Diego",
    "sg:classifiers":[
        {
            "category":"Professional",
            "subcategory":"Lawyer & Legal Services",
            "type":"Services"
        }
    ],
    "sg:phone":"+1 858 794 4660",
    "sg:postcode":"92130",
    "sg:province":"CA",
    "sg:tags":[
        "attorney"
    ],
    "wof:name":"Michael D Hudgins",
    "wof:placetype":"venue"
},
  "geometry": {"coordinates":[-117.222965,32.950977],"type":"Point"}
}