{
  "type": "Feature",
  "properties": {
    "iso:country":"US",
    "sg:address":"1850 Mission St",
    "sg:city":"San Francisco",
    "sg:classifiers":[
        {
            "category":"Organizations",
            "subcategory":"Non-profit Organization",
            "type":"Services"
        }
    ],
    "sg:phone":"+1 415 503 0500",
    "sg:postcode":"94103",
    "sg:province":"CA",
    "sg:website":"www.lacasa.org",
    "wof:name":"LA Casa De Las Madres",
    "wof:placetype":"venue"
},
  "geometry": {"coordinates":[-122.419963,37.767484],"type":"Point"}
}