{
  "type": "Feature",
  "properties": {
    "iso:country":"US",
    "sg:address":"11643 Glenoaks Blvd",
    "sg:city":"Pacoima",
    "sg:classifiers":[
        {
            "category":"Organizations",
            "subcategory":"Non-profit Organization",
            "type":"Services"
        }
    ],
    "sg:phone":"+1 818 897 2609",
    "sg:postcode":"91331",
    "sg:province":"CA",
    "sg:tags":[
        "info",
        "addiction",
        "abuse",
        "treatment",
        "drug"
    ],
    "wof:name":"Via Avanta",
    "wof:placetype":"venue"
},
  "geometry": {"coordinates":[-118.419219,34.280619],"type":"Point"}
}