{
  "type": "Feature",
  "properties": {
    "addr:full":"11949 Jefferson Boulevard Culver City CA 90230",
    "addr:housenumber":"11949",
    "addr:postcode":"90230",
    "addr:street":"Jefferson Boulevard",
    "iso:country":"US",
    "sg:address":"11949 Jefferson Boulevard",
    "sg:city":"Culver City",
    "sg:classifiers":[
        {
            "category":"Professional",
            "subcategory":"Lawyer & Legal Services",
            "type":"Services"
        }
    ],
    "sg:phone":"+1 310 302 0069",
    "sg:postcode":"90230",
    "sg:province":"CA",
    "wof:name":"Richter Axel H Attorney At Law",
    "wof:placetype":"venue"
},
  "geometry": {"coordinates":[-118.404774,33.984107],"type":"Point"}
}