{
  "type": "Feature",
  "properties": {
    "addr:full":"164 E Live Oak Ave Arcadia CA 91006",
    "addr:housenumber":"164",
    "addr:postcode":"91006",
    "addr:street":"E Live Oak Ave",
    "iso:country":"US",
    "sg:address":"164 E Live Oak Ave",
    "sg:city":"Arcadia",
    "sg:classifiers":[
        {
            "category":"Restaurant",
            "type":"Food & Drink"
        }
    ],
    "sg:menulink":"http://www.allmenus.com/ca/upper-san-gabriel-valley/178634-jack-in-the-box/menu/",
    "sg:phone":"+1 626 254 9082",
    "sg:postcode":"91006",
    "sg:province":"CA",
    "sg:tags":[
        "burger",
        "american"
    ],
    "wof:name":"Jack in the Box",
    "wof:placetype":"venue"
},
  "geometry": {"coordinates":[-118.025345,34.108096],"type":"Point"}
}