{
  "type": "Feature",
  "properties": {
    "iso:country":"US",
    "sg:address":"15420 Fairgrove Ave",
    "sg:city":"La Puente",
    "sg:classifiers":[
        {
            "category":"Personal",
            "subcategory":"Shoe Repair & Shine",
            "type":"Services"
        }
    ],
    "sg:phone":"+1 626 918 7150",
    "sg:postcode":"91744",
    "sg:province":"CA",
    "sg:tags":[
        "repairing",
        "boot"
    ],
    "wof:name":"Dick's Shoe & Vacuum Repair",
    "wof:placetype":"venue"
},
  "geometry": {"coordinates":[-117.94815800000001,34.041934],"type":"Point"}
}