{
  "type": "Feature",
  "properties": {
    "iso:country":"US",
    "sg:address":"23 Reed Blvd",
    "sg:city":"Mill Valley",
    "sg:classifiers":[
        {
            "category":"Organizations",
            "subcategory":"Non-profit Organization",
            "type":"Services"
        }
    ],
    "sg:phone":"+1 415 380 1781",
    "sg:postcode":"94941",
    "sg:province":"CA",
    "sg:tags":[
        "human"
    ],
    "wof:name":"ACS State & Local Solutions",
    "wof:placetype":"venue"
},
  "geometry": {"coordinates":[-122.515014,37.901246],"type":"Point"}
}