{
  "type": "Feature",
  "properties": {
    "addr:full":"4791 8th St Carpinteria CA 93013",
    "addr:housenumber":"4791",
    "addr:postcode":"93013",
    "addr:street":"8Th St",
    "iso:country":"US",
    "sg:address":"4791 8th St",
    "sg:city":"Carpinteria",
    "sg:classifiers":[
        {
            "category":"Building & Trades",
            "subcategory":"Construction",
            "type":"Services"
        }
    ],
    "sg:phone":"+1 805 566 0842",
    "sg:postcode":"93013",
    "sg:province":"CA",
    "sg:tags":[
        "roofing",
        "contractor"
    ],
    "wof:name":"Carpinteria Valley Roofing",
    "wof:placetype":"venue"
},
  "geometry": {"coordinates":[-119.523067,34.400246],"type":"Point"}
}