{
  "type": "Feature",
  "properties": {
    "addr:full":"5652 Vonnie Ln Cypress CA 90630",
    "addr:housenumber":"5652",
    "addr:postcode":"90630",
    "addr:street":"Vonnie Ln",
    "iso:country":"US",
    "sg:address":"5652 Vonnie Ln",
    "sg:city":"Cypress",
    "sg:classifiers":[
        {
            "category":"Manufacturing",
            "subcategory":"Apparel",
            "type":"Manufacturing & Wholesale Goods"
        }
    ],
    "sg:phone":"+1 714 527 5519",
    "sg:postcode":"90630",
    "sg:province":"CA",
    "sg:tags":[
        "clothing",
        "mfg"
    ],
    "wof:name":"Bike Boyz Apparel",
    "wof:placetype":"venue"
},
  "geometry": {"coordinates":[-118.03398199999999,33.833887],"type":"Point"}
}