{
  "type": "Feature",
  "properties": {
    "addr:full":"1620 E 2nd St Marketplace, Suite A Beaumont CA 92223",
    "addr:housenumber":"1620",
    "addr:postcode":"92223",
    "addr:street":"E 2Nd St;Suite A",
    "iso:country":"US",
    "sg:address":"1620 E 2nd St Marketplace, Suite A",
    "sg:city":"Beaumont",
    "sg:classifiers":[
        {
            "category":"Health Services",
            "subcategory":"Doctor",
            "type":"Services"
        },
        {
            "category":"Health Services",
            "subcategory":"Dentist",
            "type":"Services"
        }
    ],
    "sg:phone":"+1 951 846 1271",
    "sg:postcode":"92223",
    "sg:province":"CA",
    "sg:tags":[
        "physician",
        "dentists-cosmetic",
        "surgeons",
        "dentists-periodontists",
        "dentists-endodontists",
        "dentistry",
        "surgery",
        "oral",
        "dentists-orthodontists"
    ],
    "wof:name":"Beaumont Smiles",
    "wof:placetype":"venue"
},
  "geometry": {"coordinates":[-116.949917,33.92328],"type":"Point"}
}