{
  "type": "Feature",
  "properties": {
    "addr:full":"731 N Fulton St Fresno CA 93728",
    "addr:housenumber":"731",
    "addr:postcode":"93728",
    "addr:street":"N Fulton St",
    "iso:country":"US",
    "sg:address":"731 N Fulton St",
    "sg:city":"Fresno",
    "sg:classifiers":[
        {
            "category":"Real Estate",
            "subcategory":"Real Estate Agent",
            "type":"Services"
        }
    ],
    "sg:phone":"+1 559 443 2444",
    "sg:postcode":"93728",
    "sg:province":"CA",
    "sg:website":"www.acashdeal.com",
    "wof:name":"Abbots Ford Properties",
    "wof:placetype":"venue"
},
  "geometry": {"coordinates":[-119.800405,36.7524],"type":"Point"}
}