{
  "type": "Feature",
  "properties": {
    "iso:country":"US",
    "sg:address":"9112 Falcon Hill Ct",
    "sg:city":"Elk Grove",
    "sg:classifiers":[
        {
            "category":"Freight",
            "type":"Transportation"
        }
    ],
    "sg:phone":"+1 916 685 8198",
    "sg:postcode":"95624",
    "sg:province":"CA",
    "sg:tags":[
        "operator",
        "local",
        "trucking"
    ],
    "wof:name":"Kimrik Trucking",
    "wof:placetype":"venue"
},
  "geometry": {"coordinates":[-121.361161,38.396286],"type":"Point"}
}