{
  "type": "Feature",
  "properties": {
    "iso:country":"US",
    "sg:address":"5858 Hollywood Blvd",
    "sg:city":"Los Angeles",
    "sg:classifiers":[
        {
            "category":"Manufacturing",
            "subcategory":"Printing",
            "type":"Manufacturing & Wholesale Goods"
        }
    ],
    "sg:phone":"+1 323 465 1350",
    "sg:postcode":"90028",
    "sg:province":"CA",
    "sg:tags":[
        "newspaper"
    ],
    "wof:name":"Amar Pokkhe",
    "wof:placetype":"venue"
},
  "geometry": {"coordinates":[-118.317943,34.101601],"type":"Point"}
}