{
  "type": "Feature",
  "properties": {
    "addr:full":"663 El Camino Real South San Francisco CA 94080",
    "addr:housenumber":"663",
    "addr:postcode":"94080",
    "addr:street":"El Camino Real",
    "iso:country":"US",
    "sg:address":"663 El Camino Real",
    "sg:city":"South San Francisco",
    "sg:classifiers":[
        {
            "category":"Health Services",
            "subcategory":"Dentist",
            "type":"Services"
        }
    ],
    "sg:phone":"+1 650 952 9541",
    "sg:postcode":"94080",
    "sg:province":"CA",
    "wof:name":"Camino Dental Care",
    "wof:placetype":"venue"
},
  "geometry": {"coordinates":[-122.43000000000001,37.649601],"type":"Point"}
}