{
  "type": "Feature",
  "properties": {
    "iso:country":"US",
    "sg:address":"12332 Ventura Blvd",
    "sg:city":"Studio City",
    "sg:classifiers":[
        {
            "category":"Home & Garden",
            "subcategory":"Furniture",
            "type":"Retail Goods"
        }
    ],
    "sg:phone":"+1 818 980 8045",
    "sg:postcode":"91604",
    "sg:province":"CA",
    "sg:tags":[
        "store"
    ],
    "wof:name":"Aminach Usa",
    "wof:placetype":"venue"
},
  "geometry": {"coordinates":[-118.401517,34.142876],"type":"Point"}
}