{
  "type": "Feature",
  "properties": {
    "iso:country":"US",
    "sg:address":"13911 Pioneer Rd",
    "sg:city":"Apple Valley",
    "sg:classifiers":[
        {
            "category":"Education",
            "subcategory":"School",
            "type":"Public Place"
        }
    ],
    "sg:phone":"+1 760 240 3852",
    "sg:postcode":"92307",
    "sg:province":"CA",
    "wof:name":"CCA Vo Prep",
    "wof:placetype":"venue"
},
  "geometry": {"coordinates":[-117.180359,34.506184],"type":"Point"}
}