{
  "type": "Feature",
  "properties": {
    "addr:full":"18 Bay Fair Mall San Leandro CA 94578",
    "addr:housenumber":"18",
    "addr:postcode":"94578",
    "addr:street":"Bay Fair Mall",
    "iso:country":"US",
    "sg:address":"18 Bay Fair Mall",
    "sg:city":"San Leandro",
    "sg:classifiers":[
        {
            "category":"Shopping",
            "subcategory":"Clothing, Apparel, & Fashions",
            "type":"Retail Goods"
        }
    ],
    "sg:phone":"+1 510 276 4530",
    "sg:postcode":"94578",
    "sg:province":"CA",
    "wof:name":"Hollywood Accessories",
    "wof:placetype":"venue"
},
  "geometry": {"coordinates":[-122.126133,37.701926],"type":"Point"}
}