{
  "type": "Feature",
  "properties": {
    "addr:full":"2502 Park Rd Emerald Hills CA 94062",
    "addr:housenumber":"2502",
    "addr:postcode":"94062",
    "addr:street":"Park Rd",
    "iso:country":"US",
    "sg:address":"2502 Park Rd",
    "sg:city":"Emerald Hills",
    "sg:classifiers":[
        {
            "category":"Wholesale",
            "subcategory":"Office Equipment",
            "type":"Manufacturing & Wholesale Goods"
        }
    ],
    "sg:phone":"+1 650 361 8140",
    "sg:postcode":"94062",
    "sg:province":"CA",
    "sg:tags":[
        "scanning",
        "code",
        "bar"
    ],
    "wof:name":"MRA Technologies",
    "wof:placetype":"venue"
},
  "geometry": {"coordinates":[-122.26619700000001,37.467443],"type":"Point"}
}