{
  "type": "Feature",
  "properties": {
    "addr:full":"27030 Victoria Ln Valencia CA 91355",
    "addr:housenumber":"27030",
    "addr:postcode":"91355",
    "addr:street":"Victoria Ln",
    "iso:country":"US",
    "sg:address":"27030 Victoria Ln",
    "sg:city":"Valencia",
    "sg:classifiers":[
        {
            "category":"Real Estate",
            "subcategory":"Real Estate Agent",
            "type":"Services"
        }
    ],
    "sg:phone":"+1 661 510 3467",
    "sg:postcode":"91355",
    "sg:province":"CA",
    "wof:name":"California Pools",
    "wof:placetype":"venue"
},
  "geometry": {"coordinates":[-118.55998099999999,34.430056],"type":"Point"}
}