{
  "type": "Feature",
  "properties": {
    "iso:country":"US",
    "sg:address":"4615 Excelsior Ave",
    "sg:city":"Hanford",
    "sg:classifiers":[
        {
            "category":"Farming",
            "subcategory":"Dairy Farm",
            "type":"Manufacturing & Wholesale Goods"
        }
    ],
    "sg:phone":"+1 559 584 5442",
    "sg:postcode":"93230",
    "sg:province":"CA",
    "wof:name":"Knevelbaard Farms",
    "wof:placetype":"venue"
},
  "geometry": {"coordinates":[-119.541484,36.401352],"type":"Point"}
}