{
  "type": "Feature",
  "properties": {
    "iso:country":"US",
    "sg:address":"101 Green Valley Dr",
    "sg:city":"Gilroy",
    "sg:classifiers":[
        {
            "category":"Real Estate",
            "subcategory":"Real Estate Agent",
            "type":"Services"
        }
    ],
    "sg:phone":"+1 408 848 1151",
    "sg:postcode":"95020",
    "sg:province":"CA",
    "wof:name":"Martin Jeff Real Estate",
    "wof:placetype":"venue"
},
  "geometry": {"coordinates":[-121.60155,37.05438],"type":"Point"}
}