{
  "type": "Feature",
  "properties": {
    "iso:country":"US",
    "sg:address":"1070 E Green St",
    "sg:city":"Pasadena",
    "sg:classifiers":[
        {
            "category":"Real Estate",
            "subcategory":"Real Estate Agent",
            "type":"Services"
        }
    ],
    "sg:phone":"+1 626 395 9541",
    "sg:postcode":"91105",
    "sg:province":"CA",
    "wof:name":"Bankers Realty",
    "wof:placetype":"venue"
},
  "geometry": {"coordinates":[-118.12885300000001,34.144501],"type":"Point"}
}