{
  "type": "Feature",
  "properties": {
    "addr:full":"26893 Bouquet Canyon Rd Santa Clarita CA 91350",
    "addr:housenumber":"26893",
    "addr:postcode":"91350",
    "addr:street":"Bouquet Canyon Rd",
    "iso:country":"US",
    "sg:address":"26893 Bouquet Canyon Rd",
    "sg:city":"Santa Clarita",
    "sg:classifiers":[
        {
            "category":"Professional",
            "subcategory":"Credit Reporting & Collection",
            "type":"Services"
        }
    ],
    "sg:phone":"+1 661 297 9305",
    "sg:postcode":"91350",
    "sg:province":"CA",
    "sg:tags":[
        "agency"
    ],
    "wof:name":"Universal Financial Solutions",
    "wof:placetype":"venue"
},
  "geometry": {"coordinates":[-118.52757699999999,34.433963],"type":"Point"}
}