{
  "type": "Feature",
  "properties": {
    "iso:country":"US",
    "sg:address":"3125 Depot Rd",
    "sg:city":"Hayward",
    "sg:classifiers":[
        {
            "category":"Retail",
            "subcategory":"Auto Repair",
            "type":"Services"
        }
    ],
    "sg:phone":"+1 510 887 9818",
    "sg:postcode":"94545",
    "sg:province":"CA",
    "sg:tags":[
        "body",
        "shop"
    ],
    "sg:website":"www.autocollcenter.com",
    "wof:name":"Automobile Collision Center",
    "wof:placetype":"venue"
},
  "geometry": {"coordinates":[-122.12244699999999,37.639066],"type":"Point"}
}