{
  "type": "Feature",
  "properties": {
    "iso:country":"US",
    "sg:address":"13991 Prairie Avenue",
    "sg:city":"Hawthorne",
    "sg:classifiers":[
        {
            "category":"Food & Beverages",
            "subcategory":"Groceries & Convenience Stores",
            "type":"Retail Goods"
        }
    ],
    "sg:phone":"+1 310 349 0095",
    "sg:postcode":"90250",
    "sg:province":"CA",
    "wof:name":"Aba Discount Market",
    "wof:placetype":"venue"
},
  "geometry": {"coordinates":[-118.34368,33.904516],"type":"Point"}
}