{
  "type": "Feature",
  "properties": {
    "iso:country":"US",
    "sg:address":"761 N Colton Ave",
    "sg:city":"Colton",
    "sg:classifiers":[
        {
            "category":"Retail",
            "subcategory":"Auto Repair",
            "type":"Services"
        }
    ],
    "sg:phone":"+1 909 370 2526",
    "sg:postcode":"92324",
    "sg:province":"CA",
    "sg:tags":[
        "body",
        "automobile",
        "painting"
    ],
    "wof:name":"Colton Auto Body",
    "wof:placetype":"venue"
},
  "geometry": {"coordinates":[-117.314117,34.073927],"type":"Point"}
}