{
  "type": "Feature",
  "properties": {
    "addr:full":"1007 N Lake Ave Pasadena CA 91104",
    "addr:housenumber":"1007",
    "addr:postcode":"91104",
    "addr:street":"N Lake Ave",
    "iso:country":"US",
    "sg:address":"1007 N Lake Ave",
    "sg:city":"Pasadena",
    "sg:classifiers":[
        {
            "category":"Health Services",
            "subcategory":"Clinic",
            "type":"Services"
        }
    ],
    "sg:phone":"+1 626 808 9746",
    "sg:postcode":"91104",
    "sg:province":"CA",
    "sg:tags":[
        "specialty",
        "outpatient"
    ],
    "wof:name":"Pacific Clnics Psdena Calworks",
    "wof:placetype":"venue"
},
  "geometry": {"coordinates":[-118.132569,34.161649],"type":"Point"}
}