{
  "type": "Feature",
  "properties": {
    "addr:full":"4961 Milano Way Martinez CA 94553",
    "addr:housenumber":"4961",
    "addr:postcode":"94553",
    "addr:street":"Milano Way",
    "iso:country":"US",
    "sg:address":"4961 Milano Way",
    "sg:city":"Martinez",
    "sg:classifiers":[
        {
            "category":"Building & Trades",
            "subcategory":"Construction",
            "type":"Services"
        },
        {
            "category":"Professional",
            "subcategory":"Management & Consulting",
            "type":"Services"
        }
    ],
    "sg:phone":"+1 925 228 2377",
    "sg:postcode":"94553",
    "sg:province":"CA",
    "wof:name":"Keegan Construction Services",
    "wof:placetype":"venue"
},
  "geometry": {"coordinates":[-122.08741000000001,37.995178],"type":"Point"}
}