{
  "type": "Feature",
  "properties": {
    "iso:country":"US",
    "sg:address":"1020 S Santa Fe Ave",
    "sg:city":"Vista",
    "sg:classifiers":[
        {
            "category":"Freight",
            "type":"Transportation"
        }
    ],
    "sg:phone":"+1 760 940 1760",
    "sg:postcode":"92084",
    "sg:province":"CA",
    "sg:tags":[
        "mover"
    ],
    "sg:website":"www.internetshipping.com",
    "wof:name":"Southern Winds Intl",
    "wof:placetype":"venue"
},
  "geometry": {"coordinates":[-117.23114700000001,33.192736],"type":"Point"}
}