{
  "type": "Feature",
  "properties": {
    "addr:full":"730 W 6th St Gilroy CA 95020",
    "addr:housenumber":"730",
    "addr:postcode":"95020",
    "addr:street":"W 6Th St",
    "iso:country":"US",
    "sg:address":"730 W 6th St",
    "sg:city":"Gilroy",
    "sg:classifiers":[
        {
            "category":"Social Services",
            "subcategory":"Child Care",
            "type":"Services"
        }
    ],
    "sg:phone":"+1 408 847 1473",
    "sg:postcode":"95020",
    "sg:province":"CA",
    "wof:name":"Judy's Helping Hands Day Care",
    "wof:placetype":"venue"
},
  "geometry": {"coordinates":[-121.57776699999999,37.004083],"type":"Point"}
}