{
  "type": "Feature",
  "properties": {
    "addr:full":"6401 El Cajon Blvd San Diego CA 92115",
    "addr:housenumber":"6401",
    "addr:postcode":"92115",
    "addr:street":"El Cajon Blvd",
    "iso:country":"US",
    "sg:address":"6401 El Cajon Blvd",
    "sg:city":"San Diego",
    "sg:classifiers":[
        {
            "category":"Government",
            "subcategory":"Post Office",
            "type":"Public Place"
        }
    ],
    "sg:phone":"+1 800 275 8777",
    "sg:postcode":"92115",
    "sg:province":"CA",
    "sg:website":"usps.com",
    "wof:name":"US Post Office - Andrew Jackson",
    "wof:placetype":"venue"
},
  "geometry": {"coordinates":[-117.059957,32.764129],"type":"Point"}
}