{
  "type": "Feature",
  "properties": {
    "iso:country":"US",
    "sg:address":"4040 Clipper Ct",
    "sg:city":"Fremont",
    "sg:classifiers":[
        {
            "category":"Utilities",
            "subcategory":"Natural Gas",
            "type":"Services"
        }
    ],
    "sg:phone":"+1 510 413 0240",
    "sg:postcode":"94538",
    "sg:province":"CA",
    "wof:name":"Amescor Acquisition Corp",
    "wof:placetype":"venue"
},
  "geometry": {"coordinates":[-121.94717,37.479259],"type":"Point"}
}