{
  "type": "Feature",
  "properties": {
    "iso:country":"US",
    "sg:address":"40266 Junction Dr",
    "sg:city":"Oakhurst",
    "sg:classifiers":[
        {
            "category":"Insurance",
            "subcategory":"Insurance Agent",
            "type":"Services"
        }
    ],
    "sg:phone":"+1 559 683 7213",
    "sg:postcode":"93644",
    "sg:province":"CA",
    "wof:name":"Foster & Parker Insurance",
    "wof:placetype":"venue"
},
  "geometry": {"coordinates":[-119.659015,37.335828],"type":"Point"}
}