{
  "type": "Feature",
  "properties": {
    "addr:full":"68350 Kieley Rd Cathedral City CA 92234",
    "addr:postcode":"68350;92234",
    "addr:street":"Kieley Rd",
    "iso:country":"US",
    "sg:address":"68350 Kieley Rd",
    "sg:city":"Cathedral City",
    "sg:classifiers":[
        {
            "category":"Retail",
            "subcategory":"Auto Repair",
            "type":"Services"
        }
    ],
    "sg:phone":"+1 760 770 7533",
    "sg:postcode":"92234",
    "sg:province":"CA",
    "sg:tags":[
        "repairing",
        "automobile"
    ],
    "wof:name":"Elite Tire & Automotive",
    "wof:placetype":"venue"
},
  "geometry": {"coordinates":[-116.469067,33.786365],"type":"Point"}
}