{
  "type": "Feature",
  "properties": {
    "addr:full":"2431 Mercantile Dr Rancho Cordova CA 95742",
    "addr:housenumber":"2431",
    "addr:postcode":"95742",
    "addr:street":"Mercantile Dr",
    "iso:country":"US",
    "sg:address":"2431 Mercantile Dr",
    "sg:city":"Rancho Cordova",
    "sg:classifiers":[
        {
            "category":"Professional",
            "subcategory":"Advertising",
            "type":"Services"
        }
    ],
    "sg:phone":"+1 916 631 7400",
    "sg:postcode":"95742",
    "sg:province":"CA",
    "sg:tags":[
        "mail"
    ],
    "sg:website":"www.msimail.net",
    "wof:name":"MSI",
    "wof:placetype":"venue"
},
  "geometry": {"coordinates":[-121.254503,38.61073],"type":"Point"}
}