{
  "type": "Feature",
  "properties": {
    "addr:full":"3410 Gavota Ave San Jose CA 95124",
    "addr:housenumber":"3410",
    "addr:postcode":"95124",
    "addr:street":"Gavota Ave",
    "iso:country":"US",
    "sg:address":"3410 Gavota Ave",
    "sg:city":"San Jose",
    "sg:classifiers":[
        {
            "category":"Professional",
            "subcategory":"Computer Services",
            "type":"Services"
        }
    ],
    "sg:phone":"+1 408 267 1460",
    "sg:postcode":"95124",
    "sg:province":"CA",
    "sg:tags":[
        "repair"
    ],
    "wof:name":"Sasanac It",
    "wof:placetype":"venue"
},
  "geometry": {"coordinates":[-121.90831900000001,37.264934],"type":"Point"}
}