{
  "type": "Feature",
  "properties": {
    "iso:country":"US",
    "sg:address":"3750 Regatta Ct",
    "sg:city":"Redding",
    "sg:classifiers":[
        {
            "category":"Professional",
            "type":"Services"
        }
    ],
    "sg:phone":"+1 530 243 4002",
    "sg:postcode":"96001",
    "sg:province":"CA",
    "wof:name":"Perin Co Inc",
    "wof:placetype":"venue"
},
  "geometry": {"coordinates":[-122.426154,40.579451],"type":"Point"}
}