{
  "type": "Feature",
  "properties": {
    "addr:full":"17335 Nordhoff St Northridge CA 91325",
    "addr:housenumber":"17335",
    "addr:postcode":"91325",
    "addr:street":"Nordhoff St",
    "iso:country":"US",
    "sg:address":"17335 Nordhoff St",
    "sg:city":"Northridge",
    "sg:classifiers":[
        {
            "category":"Building & Trades",
            "subcategory":"Construction",
            "type":"Services"
        }
    ],
    "sg:phone":"+1 818 998 2131",
    "sg:postcode":"91325",
    "sg:province":"CA",
    "sg:tags":[
        "contractor"
    ],
    "wof:name":"California Designs Unlimited",
    "wof:placetype":"venue"
},
  "geometry": {"coordinates":[-118.515017,34.235907],"type":"Point"}
}