{
  "type": "Feature",
  "properties": {
    "addr:full":"1000 Truxtun Ave Bakersfield CA 93301",
    "addr:housenumber":"1000",
    "addr:postcode":"93301",
    "addr:street":"Truxtun Ave",
    "iso:country":"US",
    "sg:address":"1000 Truxtun Ave",
    "sg:city":"Bakersfield",
    "sg:classifiers":[
        {
            "category":"Real Estate",
            "subcategory":"Real Estate Services",
            "type":"Services"
        }
    ],
    "sg:phone":"+1 661 281 0325",
    "sg:postcode":"93301",
    "sg:province":"CA",
    "sg:tags":[
        "loan"
    ],
    "sg:website":"http://www.cbbank.com",
    "wof:name":"Citizens Business Bank",
    "wof:placetype":"venue"
},
  "geometry": {"coordinates":[-119.012962,35.373409],"type":"Point"}
}