{
  "type": "Feature",
  "properties": {
    "addr:full":"840 6th St Norco CA 92860",
    "addr:housenumber":"840",
    "addr:postcode":"92860",
    "addr:street":"6Th St",
    "iso:country":"US",
    "sg:address":"840 6th St",
    "sg:city":"Norco",
    "sg:classifiers":[
        {
            "category":"Food & Beverages",
            "subcategory":"Dairy",
            "type":"Retail Goods"
        }
    ],
    "sg:phone":"+1 951 737 5590",
    "sg:postcode":"92860",
    "sg:province":"CA",
    "sg:tags":[
        "product"
    ],
    "wof:name":"Norco Drive-In Dairy",
    "wof:placetype":"venue"
},
  "geometry": {"coordinates":[-117.54034299999999,33.938348],"type":"Point"}
}