{
  "type": "Feature",
  "properties": {
    "addr:full":"5900 Hollis St Emeryville CA 94608",
    "addr:housenumber":"5900",
    "addr:postcode":"94608",
    "addr:street":"Hollis St",
    "iso:country":"US",
    "sg:address":"5900 Hollis St",
    "sg:city":"Emeryville",
    "sg:classifiers":[
        {
            "category":"Professional",
            "subcategory":"Management & Consulting",
            "type":"Services"
        },
        {
            "category":"Professional",
            "subcategory":"Advertising",
            "type":"Services"
        }
    ],
    "sg:phone":"+1 510 652 4900",
    "sg:postcode":"94608",
    "sg:province":"CA",
    "sg:tags":[
        "marketing",
        "agency",
        "specialty",
        "consultant"
    ],
    "wof:name":"42 Entertainment",
    "wof:placetype":"venue"
},
  "geometry": {"coordinates":[-122.289726,37.841301],"type":"Point"}
}