{
  "type": "Feature",
  "properties": {
    "addr:full":"1680 McKee Rd San Jose CA 95116",
    "addr:housenumber":"1680",
    "addr:postcode":"95116",
    "addr:street":"Mckee Rd",
    "iso:country":"US",
    "sg:address":"1680 McKee Rd",
    "sg:city":"San Jose",
    "sg:classifiers":[
        {
            "category":"Communications",
            "subcategory":"Radio Station",
            "type":"Services"
        }
    ],
    "sg:phone":"+1 408 259 2988",
    "sg:postcode":"95116",
    "sg:province":"CA",
    "sg:tags":[
        "broadcast"
    ],
    "wof:name":"Peoples Radio Inc",
    "wof:placetype":"venue"
},
  "geometry": {"coordinates":[-121.86084099999999,37.358005],"type":"Point"}
}