{
  "type": "Feature",
  "properties": {
    "iso:country":"US",
    "sg:address":"709 N Inglewood Ave",
    "sg:city":"Inglewood",
    "sg:classifiers":[
        {
            "category":"Wholesale",
            "subcategory":"Machinery & Supplies",
            "type":"Manufacturing & Wholesale Goods"
        }
    ],
    "sg:phone":"+1 310 677 5316",
    "sg:postcode":"90302",
    "sg:province":"CA",
    "sg:tags":[
        "salon",
        "beauty"
    ],
    "wof:name":"M B Smile Enterprise",
    "wof:placetype":"venue"
},
  "geometry": {"coordinates":[-118.361199,33.971942],"type":"Point"}
}