{
  "type": "Feature",
  "properties": {
    "addr:full":"725 Washington St # A Oakland CA 94607",
    "addr:housenumber":"725",
    "addr:postcode":"94607",
    "addr:street":"Washington St # A",
    "iso:country":"US",
    "sg:address":"725 Washington St # A",
    "sg:city":"Oakland",
    "sg:classifiers":[
        {
            "category":"Personal",
            "type":"Services"
        }
    ],
    "sg:phone":"+1 510 268 0666",
    "sg:postcode":"94607",
    "sg:province":"CA",
    "sg:tags":[
        "sewing",
        "alteration"
    ],
    "sg:website":"www.doanstailor.com",
    "wof:name":"Doan Tailor",
    "wof:placetype":"venue"
},
  "geometry": {"coordinates":[-122.275317,37.80019],"type":"Point"}
}