{
  "type": "Feature",
  "properties": {
    "iso:country":"US",
    "sg:address":"3391 Thornhill Dr",
    "sg:city":"El Dorado Hills",
    "sg:classifiers":[
        {
            "category":"Professional",
            "subcategory":"Engineering",
            "type":"Services"
        }
    ],
    "sg:phone":"+1 530 677 5906",
    "sg:postcode":"95762",
    "sg:province":"CA",
    "sg:tags":[
        "engineer"
    ],
    "wof:name":"Streng Engineering-Surveying",
    "wof:placetype":"venue"
},
  "geometry": {"coordinates":[-121.014077,38.673119],"type":"Point"}
}