{
  "type": "Feature",
  "properties": {
    "addr:full":"149 S 1st St Ste F Santa Maria CA 93455",
    "addr:housenumber":"149",
    "addr:postcode":"93455",
    "addr:street":"S 1St St Ste F",
    "iso:country":"US",
    "sg:address":"149 S 1st St Ste F",
    "sg:city":"Santa Maria",
    "sg:classifiers":[
        {
            "category":"Shopping",
            "subcategory":"Pets & Pet Supplies",
            "type":"Retail Goods"
        }
    ],
    "sg:phone":"+1 805 937 1916",
    "sg:postcode":"93455",
    "sg:province":"CA",
    "sg:tags":[
        "store"
    ],
    "wof:name":"Dog-Gone Gorgeous",
    "wof:placetype":"venue"
},
  "geometry": {"coordinates":[-120.446265,34.864495],"type":"Point"}
}