{
  "type": "Feature",
  "properties": {
    "addr:full":"151 Blue Ravine Rd Folsom CA 95630",
    "addr:housenumber":"151",
    "addr:postcode":"95630",
    "addr:street":"Blue Ravine Rd",
    "iso:country":"US",
    "sg:address":"151 Blue Ravine Rd",
    "sg:city":"Folsom",
    "sg:classifiers":[
        {
            "category":"Professional",
            "type":"Services"
        }
    ],
    "sg:phone":"+1 916 351 2000",
    "sg:postcode":"95630",
    "sg:province":"CA",
    "sg:tags":[
        "establishment"
    ],
    "sg:website":"www.caiso.com",
    "wof:name":"California Power Exchange",
    "wof:placetype":"venue"
},
  "geometry": {"coordinates":[-121.186255,38.650987],"type":"Point"}
}