{
  "type": "Feature",
  "properties": {
    "iso:country":"US",
    "sg:address":"18804 Nordhoff St",
    "sg:city":"Northridge",
    "sg:classifiers":[
        {
            "category":"Building & Trades",
            "subcategory":"Construction",
            "type":"Services"
        }
    ],
    "sg:phone":"+1 818 718 6544",
    "sg:postcode":"91324",
    "sg:province":"CA",
    "sg:tags":[
        "painter"
    ],
    "wof:name":"D E Jeronimo Painting Co",
    "wof:placetype":"venue"
},
  "geometry": {"coordinates":[-118.544747,34.235412],"type":"Point"}
}