{
  "type": "Feature",
  "properties": {
    "addr:full":"220 Sycamore St Red Bluff CA 96080",
    "addr:housenumber":"220",
    "addr:postcode":"96080",
    "addr:street":"Sycamore St",
    "iso:country":"US",
    "sg:address":"220 Sycamore St",
    "sg:city":"Red Bluff",
    "sg:classifiers":[
        {
            "category":"Organizations",
            "subcategory":"Membership Organization",
            "type":"Services"
        }
    ],
    "sg:phone":"+1 530 527 9639",
    "sg:postcode":"96080",
    "sg:province":"CA",
    "wof:name":"Home Help For Hispanic Mothers",
    "wof:placetype":"venue"
},
  "geometry": {"coordinates":[-122.23188500000001,40.175313],"type":"Point"}
}