{
  "type": "Feature",
  "properties": {
    "iso:country":"US",
    "sg:address":"440 Haight St",
    "sg:city":"San Francisco",
    "sg:classifiers":[
        {
            "category":"Manufacturing",
            "subcategory":"Glass & Minerals",
            "type":"Manufacturing & Wholesale Goods"
        }
    ],
    "sg:phone":"+1 415 255 8582",
    "sg:postcode":"94117",
    "sg:province":"CA",
    "sg:tags":[
        "personal",
        "mfg"
    ],
    "wof:name":"Wonderland Soup",
    "wof:placetype":"venue"
},
  "geometry": {"coordinates":[-122.429918,37.772266],"type":"Point"}
}