{
  "type": "Feature",
  "properties": {
    "addr:full":"3939 J St Sacramento CA 95819",
    "addr:housenumber":"3939",
    "addr:postcode":"95819",
    "addr:street":"J St",
    "iso:country":"US",
    "sg:address":"3939 J St",
    "sg:city":"Sacramento",
    "sg:classifiers":[
        {
            "category":"Health Services",
            "subcategory":"Doctor",
            "type":"Services"
        }
    ],
    "sg:phone":"+1 916 739 1400",
    "sg:postcode":"95819",
    "sg:province":"CA",
    "wof:name":"Nabi Iraj MD F A C S",
    "wof:placetype":"venue"
},
  "geometry": {"coordinates":[-121.453838,38.5699],"type":"Point"}
}