{
  "type": "Feature",
  "properties": {
    "addr:full":"2568 Olympic Dr San Bruno CA 94066",
    "addr:housenumber":"2568",
    "addr:postcode":"94066",
    "addr:street":"Olympic Dr",
    "iso:country":"US",
    "sg:address":"2568 Olympic Dr",
    "sg:city":"San Bruno",
    "sg:classifiers":[
        {
            "category":"Manufacturing",
            "subcategory":"Retail Goods",
            "type":"Manufacturing & Wholesale Goods"
        }
    ],
    "sg:phone":"+1 650 873 5239",
    "sg:postcode":"94066",
    "sg:province":"CA",
    "sg:tags":[
        "product",
        "mfg"
    ],
    "wof:name":"Choi Boiler Services",
    "wof:placetype":"venue"
},
  "geometry": {"coordinates":[-122.455061,37.638034],"type":"Point"}
}