{
  "type": "Feature",
  "properties": {
    "addr:full":"24710 Wilmington Ave Carson CA 90745",
    "addr:housenumber":"24710",
    "addr:postcode":"90745",
    "addr:street":"Wilmington Ave",
    "iso:country":"US",
    "sg:address":"24710 Wilmington Ave",
    "sg:city":"Carson",
    "sg:classifiers":[
        {
            "category":"Railroad",
            "type":"Transportation"
        }
    ],
    "sg:phone":"+1 310 834 4698",
    "sg:postcode":"90745",
    "sg:province":"CA",
    "wof:name":"Lomita Rail Terminal",
    "wof:placetype":"venue"
},
  "geometry": {"coordinates":[-118.258348,33.799505],"type":"Point"}
}