{
  "type": "Feature",
  "properties": {
    "addr:full":"5055 Canyon Crest Dr Riverside CA 92507",
    "addr:housenumber":"5055",
    "addr:postcode":"92507",
    "addr:street":"Canyon Crest Dr",
    "iso:country":"US",
    "sg:address":"5055 Canyon Crest Dr",
    "sg:city":"Riverside",
    "sg:classifiers":[
        {
            "category":"Banks & Credit Unions",
            "subcategory":"Investment Brokerage",
            "type":"Services"
        }
    ],
    "sg:phone":"+1 951 369 3142",
    "sg:postcode":"92507",
    "sg:province":"CA",
    "wof:name":"Broadway Capital & Investments",
    "wof:placetype":"venue"
},
  "geometry": {"coordinates":[-117.331041,33.958429],"type":"Point"}
}