{
  "type": "Feature",
  "properties": {
    "iso:country":"US",
    "sg:address":"17383 W Sunset Blvd",
    "sg:city":"Pacific Plsds",
    "sg:classifiers":[
        {
            "category":"Banks & Credit Unions",
            "subcategory":"Financial Services",
            "type":"Services"
        }
    ],
    "sg:phone":"+1 310 230 8778",
    "sg:postcode":"90272",
    "sg:province":"CA",
    "sg:tags":[
        "investor"
    ],
    "wof:name":"Palisades Investors Inc",
    "wof:placetype":"venue"
},
  "geometry": {"coordinates":[-118.55533,34.039033],"type":"Point"}
}