{
  "type": "Feature",
  "properties": {
    "iso:country":"US",
    "sg:address":"1555 E Highland Ave",
    "sg:city":"Corona",
    "sg:classifiers":[
        {
            "category":"Banks & Credit Unions",
            "subcategory":"Bank",
            "type":"Services"
        }
    ],
    "sg:phone":"+1 951 371 2130",
    "sg:postcode":"92404",
    "sg:province":"CA",
    "sg:website":"www.cbbank.com",
    "wof:name":"Citizens Business Bank",
    "wof:placetype":"venue"
},
  "geometry": {"coordinates":[-117.63640700000001,33.881243],"type":"Point"}
}