{
  "type": "Feature",
  "properties": {
    "iso:country":"US",
    "sg:address":"1931 W Middlefield Rd",
    "sg:city":"Mountain View",
    "sg:classifiers":[
        {
            "category":"Real Estate",
            "subcategory":"Real Estate Agent",
            "type":"Services"
        }
    ],
    "sg:phone":"+1 650 988 0880",
    "sg:postcode":"94043",
    "sg:province":"CA",
    "wof:name":"Business & Real Estate Group",
    "wof:placetype":"venue"
},
  "geometry": {"coordinates":[-122.090194,37.410617],"type":"Point"}
}