{
  "type": "Feature",
  "properties": {
    "addr:full":"6610 Downing Ave Bakersfield CA 93308",
    "addr:housenumber":"6610",
    "addr:postcode":"93308",
    "addr:street":"Downing Ave",
    "iso:country":"US",
    "sg:address":"6610 Downing Ave",
    "sg:city":"Bakersfield",
    "sg:classifiers":[
        {
            "category":"Home & Garden",
            "subcategory":"Building Materials",
            "type":"Retail Goods"
        }
    ],
    "sg:phone":"+1 661 587 6200",
    "sg:postcode":"93308",
    "sg:province":"CA",
    "sg:tags":[
        "door",
        "gate",
        "operating",
        "devices"
    ],
    "wof:name":"Open & Shut Enterprises",
    "wof:placetype":"venue"
},
  "geometry": {"coordinates":[-119.075766,35.390628],"type":"Point"}
}