{
  "type": "Feature",
  "properties": {
    "addr:full":"21 Orinda Way Orinda CA 94563",
    "addr:housenumber":"21",
    "addr:postcode":"94563",
    "addr:street":"Orinda Way",
    "iso:country":"US",
    "sg:address":"21 Orinda Way",
    "sg:city":"Orinda",
    "sg:classifiers":[
        {
            "category":"Building & Trades",
            "subcategory":"Locksmith",
            "type":"Services"
        }
    ],
    "sg:phone":"+1 510 263 3234",
    "sg:postcode":"94563",
    "sg:province":"CA",
    "sg:tags":[
        "key"
    ],
    "wof:name":"Car Locksmith",
    "wof:placetype":"venue"
},
  "geometry": {"coordinates":[-122.188106,37.881309],"type":"Point"}
}