{
  "type": "Feature",
  "properties": {
    "addr:full":"308 Palm Dr Hermosa Beach CA 90254",
    "addr:housenumber":"308",
    "addr:postcode":"90254",
    "addr:street":"Palm Dr",
    "iso:country":"US",
    "sg:address":"308 Palm Dr",
    "sg:city":"Hermosa Beach",
    "sg:classifiers":[
        {
            "category":"Shopping",
            "subcategory":"Computers & Home Electronics",
            "type":"Retail Goods"
        }
    ],
    "sg:phone":"+1 310 372 3998",
    "sg:postcode":"90254",
    "sg:province":"CA",
    "sg:tags":[
        "system"
    ],
    "wof:name":"Imagine Audio",
    "wof:placetype":"venue"
},
  "geometry": {"coordinates":[-118.397738,33.855681],"type":"Point"}
}