{
  "type": "Feature",
  "properties": {
    "iso:country":"US",
    "sg:address":"1220 S Ferris Ave",
    "sg:city":"Los Angeles",
    "sg:classifiers":[
        {
            "category":"Building & Trades",
            "subcategory":"Plumbing",
            "type":"Services"
        }
    ],
    "sg:phone":"+1 310 289 9697",
    "sg:postcode":"90022",
    "sg:province":"CA",
    "wof:name":"Reliance Refreg & Air Cond",
    "wof:placetype":"venue"
},
  "geometry": {"coordinates":[-118.16481899999999,34.017614],"type":"Point"}
}