{
  "type": "Feature",
  "properties": {
    "addr:full":"81 W Putnam Ave Porterville CA 93257",
    "addr:housenumber":"81",
    "addr:postcode":"93257",
    "addr:street":"W Putnam Ave",
    "iso:country":"US",
    "sg:address":"81 W Putnam Ave",
    "sg:city":"Porterville",
    "sg:classifiers":[
        {
            "category":"Wholesale",
            "subcategory":"Fruits & Vegetables",
            "type":"Manufacturing & Wholesale Goods"
        }
    ],
    "sg:phone":"+1 559 784 4600",
    "sg:postcode":"93257",
    "sg:province":"CA",
    "wof:name":"Tulare County Fruit Exchange",
    "wof:placetype":"venue"
},
  "geometry": {"coordinates":[-119.01735100000001,36.069562],"type":"Point"}
}