{
  "type": "Feature",
  "properties": {
    "iso:country":"US",
    "sg:address":"148 W Duarte Rd",
    "sg:city":"Monrovia",
    "sg:classifiers":[
        {
            "category":"Education",
            "subcategory":"School",
            "type":"Public Place"
        }
    ],
    "sg:phone":"+1 626 471 2700",
    "sg:postcode":"91016",
    "sg:province":"CA",
    "wof:name":"Sante Fe Middle School",
    "wof:placetype":"venue"
},
  "geometry": {"coordinates":[-118.003191,34.132122],"type":"Point"}
}