{
  "type": "Feature",
  "properties": {
    "addr:full":"24003-A Ventura Blvd Calabasas CA 91302",
    "addr:housenumber":"24003-a",
    "addr:postcode":"91302",
    "addr:street":"Ventura Blvd",
    "iso:country":"US",
    "sg:address":"24003-A Ventura Blvd",
    "sg:city":"Calabasas",
    "sg:classifiers":[
        {
            "category":"Home & Garden",
            "subcategory":"Household Appliances",
            "type":"Retail Goods"
        }
    ],
    "sg:phone":"+1 818 857 5205",
    "sg:postcode":"91302",
    "sg:province":"CA",
    "sg:tags":[
        "repair"
    ],
    "sg:website":"appliancerepairsincalabasas.blog...",
    "wof:name":"Calabasas Appliance Repair",
    "wof:placetype":"venue"
},
  "geometry": {"coordinates":[-118.65032600000001,34.154693],"type":"Point"}
}