{
  "type": "Feature",
  "properties": {
    "addr:full":"315 E Charter Way Stockton CA 95206",
    "addr:housenumber":"315",
    "addr:postcode":"95206",
    "addr:street":"E Charter Way",
    "iso:country":"US",
    "sg:address":"315 E Charter Way",
    "sg:city":"Stockton",
    "sg:classifiers":[
        {
            "category":"Personal",
            "subcategory":"Beauty Salon",
            "type":"Services"
        }
    ],
    "sg:phone":"+1 209 464 9553",
    "sg:postcode":"95206",
    "sg:province":"CA",
    "wof:name":"Frances Beauty Salons",
    "wof:placetype":"venue"
},
  "geometry": {"coordinates":[-121.282943,37.939539],"type":"Point"}
}