{
  "type": "Feature",
  "properties": {
    "addr:full":"4630 W Jacquelyn Ave Fresno CA 93722",
    "addr:housenumber":"4630",
    "addr:postcode":"93722",
    "addr:street":"W Jacquelyn Ave",
    "iso:country":"US",
    "sg:address":"4630 W Jacquelyn Ave",
    "sg:city":"Fresno",
    "sg:classifiers":[
        {
            "category":"Professional",
            "subcategory":"Engineering",
            "type":"Services"
        }
    ],
    "sg:phone":"+1 559 276 2790",
    "sg:postcode":"93722",
    "sg:province":"CA",
    "sg:tags":[
        "engineer"
    ],
    "sg:website":"www.larsandersen.com",
    "wof:name":"Lars Andersen & Assoc Inc",
    "wof:placetype":"venue"
},
  "geometry": {"coordinates":[-119.878315,36.813371],"type":"Point"}
}