{
  "type": "Feature",
  "properties": {
    "addr:full":"708 S Main St Willits CA 95490",
    "addr:housenumber":"708",
    "addr:postcode":"95490",
    "addr:street":"S Main St",
    "iso:country":"US",
    "sg:address":"708 S Main St",
    "sg:city":"Willits",
    "sg:classifiers":[
        {
            "category":"Restaurant",
            "type":"Food & Drink"
        }
    ],
    "sg:phone":"+1 707 456 9916",
    "sg:postcode":"95490",
    "sg:province":"CA",
    "wof:name":"Country Skillet",
    "wof:placetype":"venue"
},
  "geometry": {"coordinates":[-123.352144,39.404957],"type":"Point"}
}