{
  "type": "Feature",
  "properties": {
    "addr:full":"1001 E Main St Santa Paula CA 93060",
    "addr:housenumber":"1001",
    "addr:postcode":"93060",
    "addr:street":"E Main St",
    "iso:country":"US",
    "sg:address":"1001 E Main St",
    "sg:city":"Santa Paula",
    "sg:classifiers":[
        {
            "category":"Government",
            "subcategory":"Office",
            "type":"Public Place"
        }
    ],
    "sg:phone":"+1 805 933 0076",
    "sg:postcode":"93060",
    "sg:province":"CA",
    "sg:tags":[
        "village"
    ],
    "wof:name":"Santa Paula Union Oil Museum",
    "wof:placetype":"venue"
},
  "geometry": {"coordinates":[-119.059223,34.354255],"type":"Point"}
}