{
  "type": "Feature",
  "properties": {
    "iso:country":"US",
    "sg:address":"2332 McGaw Ave",
    "sg:city":"Irvine",
    "sg:classifiers":[
        {
            "category":"Organizations",
            "subcategory":"Religious Organization",
            "type":"Services"
        }
    ],
    "sg:phone":"+1 949 833 0091",
    "sg:postcode":"92614",
    "sg:province":"CA",
    "sg:tags":[
        "church"
    ],
    "wof:name":"Irvine United Msn Evangel",
    "wof:placetype":"venue"
},
  "geometry": {"coordinates":[-117.841296,33.690123],"type":"Point"}
}