{
  "type": "Feature",
  "properties": {
    "addr:full":"1790 N Broadway Santa Maria CA 93454",
    "addr:housenumber":"1790",
    "addr:postcode":"93454",
    "addr:street":"N Broadway",
    "iso:country":"US",
    "sg:address":"1790 N Broadway",
    "sg:city":"Santa Maria",
    "sg:classifiers":[
        {
            "category":"Autos & Motor Vehicles",
            "subcategory":"Auto Supplies",
            "type":"Retail Goods"
        }
    ],
    "sg:phone":"+1 805 922 8305",
    "sg:postcode":"93454",
    "sg:province":"CA",
    "sg:tags":[
        "automobile",
        "parts"
    ],
    "wof:name":"Kragen Auto Parts",
    "wof:placetype":"venue"
},
  "geometry": {"coordinates":[-120.435464,34.970035],"type":"Point"}
}