{
  "type": "Feature",
  "properties": {
    "iso:country":"US",
    "sg:address":"4990 Wing Way",
    "sg:city":"Paso Robles",
    "sg:classifiers":[
        {
            "category":"Building & Trades",
            "subcategory":"Equipment Rental",
            "type":"Services"
        }
    ],
    "sg:phone":"+1 805 238 1213",
    "sg:postcode":"93446",
    "sg:province":"CA",
    "sg:tags":[
        "aircraft",
        "leasing",
        "charter"
    ],
    "sg:website":"www.flynajc.com",
    "wof:name":"North American Jet Charter",
    "wof:placetype":"venue"
},
  "geometry": {"coordinates":[-120.638535,35.672073],"type":"Point"}
}