{
  "type": "Feature",
  "properties": {
    "addr:full":"151 S Oak Ave Oakdale CA 95361",
    "addr:housenumber":"151",
    "addr:postcode":"95361",
    "addr:street":"S Oak Ave",
    "iso:country":"US",
    "sg:address":"151 S Oak Ave",
    "sg:city":"Oakdale",
    "sg:classifiers":[
        {
            "category":"Building & Trades",
            "subcategory":"Equipment Rental",
            "type":"Services"
        }
    ],
    "sg:phone":"+1 209 847 2626",
    "sg:postcode":"95361",
    "sg:province":"CA",
    "sg:tags":[
        "toilet"
    ],
    "wof:name":"T P Express",
    "wof:placetype":"venue"
},
  "geometry": {"coordinates":[-120.86085300000001,37.759043],"type":"Point"}
}