{
  "type": "Feature",
  "properties": {
    "iso:country":"US",
    "sg:address":"1673 Indian Hill Blvd",
    "sg:city":"Pomona",
    "sg:classifiers":[
        {
            "category":"Food & Beverages",
            "subcategory":"Groceries & Convenience Stores",
            "type":"Retail Goods"
        }
    ],
    "sg:phone":"+1 909 626 7500",
    "sg:postcode":"91767",
    "sg:province":"CA",
    "wof:name":"Mike's Liquor",
    "wof:placetype":"venue"
},
  "geometry": {"coordinates":[-117.71932099999999,34.074627],"type":"Point"}
}