{
  "type": "Feature",
  "properties": {
    "iso:country":"US",
    "sg:address":"16 Fowler Ct",
    "sg:city":"San Rafael",
    "sg:classifiers":[
        {
            "category":"Professional",
            "subcategory":"Employment Agencies",
            "type":"Services"
        }
    ],
    "sg:phone":"+1 415 491 1541",
    "sg:postcode":"94903",
    "sg:province":"CA",
    "sg:tags":[
        "consultant",
        "search",
        "executive"
    ],
    "sg:website":"www.nancysymonds.com",
    "wof:name":"NJS Recruiting Svc",
    "wof:placetype":"venue"
},
  "geometry": {"coordinates":[-122.562507,38.007761],"type":"Point"}
}