{
  "type": "Feature",
  "properties": {
    "addr:full":"5464 Grossmont Center Dr La Mesa CA 91942",
    "addr:housenumber":"5464",
    "addr:postcode":"91942",
    "addr:street":"Grossmont Center Dr",
    "iso:country":"US",
    "sg:address":"5464 Grossmont Center Dr",
    "sg:city":"La Mesa",
    "sg:classifiers":[
        {
            "category":"Professional",
            "subcategory":"Lawyer & Legal Services",
            "type":"Services"
        }
    ],
    "sg:phone":"+1 619 469 9477",
    "sg:postcode":"91942",
    "sg:province":"CA",
    "sg:tags":[
        "divorce",
        "law",
        "family"
    ],
    "wof:name":"Grunbaum Daniel Attorney At Law",
    "wof:placetype":"venue"
},
  "geometry": {"coordinates":[-117.00700399999999,32.7784],"type":"Point"}
}