{
  "type": "Feature",
  "properties": {
    "addr:full":"326 Wilshire Blvd Santa Monica CA 90401",
    "addr:housenumber":"326",
    "addr:postcode":"90401",
    "addr:street":"Wilshire Blvd",
    "iso:country":"US",
    "sg:address":"326 Wilshire Blvd",
    "sg:city":"Santa Monica",
    "sg:classifiers":[
        {
            "category":"Restaurant",
            "type":"Food & Drink"
        }
    ],
    "sg:menulink":"http://www.allmenus.com/ca/santa-monica/6658-pf-changs/menu/",
    "sg:phone":"+1 310 395 1912",
    "sg:postcode":"90401",
    "sg:province":"CA",
    "sg:tags":[
        "japanese",
        "chinese",
        "asian"
    ],
    "wof:name":"P.F. Chang's",
    "wof:placetype":"venue"
},
  "geometry": {"coordinates":[-118.49872000000001,34.01878],"type":"Point"}
}