{
  "type": "Feature",
  "properties": {
    "iso:country":"US",
    "sg:address":"2075 Corte del Nogal",
    "sg:city":"Carlsbad",
    "sg:classifiers":[
        {
            "category":"Professional",
            "subcategory":"Research",
            "type":"Services"
        }
    ],
    "sg:phone":"+1 760 598 6686",
    "sg:postcode":"92011",
    "sg:province":"CA",
    "sg:tags":[
        "development",
        "marketing",
        "product"
    ],
    "wof:name":"Novo Engineering",
    "wof:placetype":"venue"
},
  "geometry": {"coordinates":[-117.277493,33.120348],"type":"Point"}
}