{
  "type": "Feature",
  "properties": {
    "iso:country":"US",
    "sg:address":"707 Letts Ave",
    "sg:city":"Corcoran",
    "sg:classifiers":[
        {
            "category":"Education",
            "subcategory":"School",
            "type":"Public Place"
        }
    ],
    "sg:phone":"+1 559 992 4167",
    "sg:postcode":"93212",
    "sg:province":"CA",
    "wof:name":"John Muir Middle School",
    "wof:placetype":"venue"
},
  "geometry": {"coordinates":[-119.567523,36.103405],"type":"Point"}
}