{
  "type": "Feature",
  "properties": {
    "iso:country":"US",
    "sg:address":"3505 Cadillac Ave Ste K2",
    "sg:city":"Costa Mesa",
    "sg:classifiers":[
        {
            "category":"Home & Garden",
            "subcategory":"Hardware",
            "type":"Retail Goods"
        }
    ],
    "sg:phone":"+1 714 641 9007",
    "sg:postcode":"92626",
    "sg:province":"CA",
    "sg:tags":[
        "store"
    ],
    "wof:name":"Machine Tools Supply",
    "wof:placetype":"venue"
},
  "geometry": {"coordinates":[-117.93172800000001,33.697396],"type":"Point"}
}