{
  "type": "Feature",
  "properties": {
    "addr:full":"926 S Andreasen Dr Escondido CA 92029",
    "addr:housenumber":"926",
    "addr:postcode":"92029",
    "addr:street":"S Andreasen Dr",
    "iso:country":"US",
    "sg:address":"926 S Andreasen Dr",
    "sg:city":"Escondido",
    "sg:classifiers":[
        {
            "category":"Professional",
            "subcategory":"Accounting & Tax Preparation",
            "type":"Services"
        }
    ],
    "sg:phone":"+1 760 432 0774",
    "sg:postcode":"92029",
    "sg:province":"CA",
    "sg:tags":[
        "bookkeeping",
        "general"
    ],
    "wof:name":"Brandon's Best Bookkeeping Svc",
    "wof:placetype":"venue"
},
  "geometry": {"coordinates":[-117.11546800000001,33.11289],"type":"Point"}
}