{
  "type": "Feature",
  "properties": {
    "iso:country":"US",
    "sg:address":"1187 Coast Village Rd",
    "sg:city":"Santa Barbara",
    "sg:classifiers":[
        {
            "category":"Professional",
            "subcategory":"Research",
            "type":"Services"
        }
    ],
    "sg:phone":"+1 805 963 5404",
    "sg:postcode":"93108",
    "sg:province":"CA",
    "wof:name":"CFIDS Research Foundation",
    "wof:placetype":"venue"
},
  "geometry": {"coordinates":[-119.64746,34.421356],"type":"Point"}
}