{
  "type": "Feature",
  "properties": {
    "addr:full":"15559 Farnsworth St San Leandro CA 94579",
    "addr:postcode":"15559;94579",
    "addr:street":"Farnsworth St",
    "iso:country":"US",
    "sg:address":"15559 Farnsworth St",
    "sg:city":"San Leandro",
    "sg:classifiers":[
        {
            "category":"Retail",
            "subcategory":"Repair Shop",
            "type":"Services"
        }
    ],
    "sg:phone":"+1 925 875 9237",
    "sg:postcode":"94579",
    "sg:province":"CA",
    "sg:tags":[
        "jewelry"
    ],
    "wof:name":"Fast Goldsmiths",
    "wof:placetype":"venue"
},
  "geometry": {"coordinates":[-122.150115,37.678917],"type":"Point"}
}