{
  "type": "Feature",
  "properties": {
    "iso:country":"US",
    "sg:address":"10184 7th Ave",
    "sg:city":"Hesperia",
    "sg:classifiers":[
        {
            "category":"Organizations",
            "subcategory":"Religious Organization",
            "type":"Services"
        }
    ],
    "sg:phone":"+1 760 244 9050",
    "sg:postcode":"92345",
    "sg:province":"CA",
    "sg:tags":[
        "church"
    ],
    "sg:website":"www.newlifechapel.com",
    "wof:name":"New Life Chapel",
    "wof:placetype":"venue"
},
  "geometry": {"coordinates":[-117.313609,34.433529],"type":"Point"}
}