{
  "type": "Feature",
  "properties": {
    "addr:full":"5208 Arden Dr Temple City CA 91780",
    "addr:housenumber":"5208",
    "addr:postcode":"91780",
    "addr:street":"Arden Dr",
    "iso:country":"US",
    "sg:address":"5208 Arden Dr",
    "sg:city":"Temple City",
    "sg:classifiers":[
        {
            "category":"Wholesale",
            "subcategory":"Non-durable Goods",
            "type":"Manufacturing & Wholesale Goods"
        }
    ],
    "sg:phone":"+1 626 401 9389",
    "sg:postcode":"91780",
    "sg:province":"CA",
    "wof:name":"Winco Imports Inc",
    "wof:placetype":"venue"
},
  "geometry": {"coordinates":[-118.043526,34.098268],"type":"Point"}
}