{
  "type": "Feature",
  "properties": {
    "addr:full":"8461 Brook Ave Kings Beach CA 96143",
    "addr:housenumber":"8461",
    "addr:postcode":"96143",
    "addr:street":"Brook Ave",
    "iso:country":"US",
    "sg:address":"8461 Brook Ave",
    "sg:city":"Kings Beach",
    "sg:classifiers":[
        {
            "category":"Building & Trades",
            "subcategory":"Cleaning & Sanitation",
            "type":"Services"
        }
    ],
    "sg:phone":"+1 530 546 4224",
    "sg:postcode":"96143",
    "sg:province":"CA",
    "sg:tags":[
        "home"
    ],
    "sg:website":"paulbunyantahoe.com",
    "wof:name":"Paul Bunyan Maintenance Co",
    "wof:placetype":"venue"
},
  "geometry": {"coordinates":[-120.03600299999999,39.276199],"type":"Point"}
}