{
  "type": "Feature",
  "properties": {
    "addr:full":"5920 Wadsworth Ave Highland CA 92346",
    "addr:housenumber":"5920",
    "addr:postcode":"92346",
    "addr:street":"Wadsworth Ave",
    "iso:country":"US",
    "sg:address":"5920 Wadsworth Ave",
    "sg:city":"Highland",
    "sg:classifiers":[
        {
            "category":"Building & Trades",
            "subcategory":"Construction",
            "type":"Services"
        }
    ],
    "sg:phone":"+1 909 862 9265",
    "sg:postcode":"92346",
    "sg:province":"CA",
    "sg:tags":[
        "contractor"
    ],
    "wof:name":"Gilbert Construction Co",
    "wof:placetype":"venue"
},
  "geometry": {"coordinates":[-117.23306599999999,34.144703],"type":"Point"}
}