{
  "type": "Feature",
  "properties": {
    "addr:full":"915 W Arbor Vitae St Inglewood CA 90301",
    "addr:housenumber":"915",
    "addr:postcode":"90301",
    "addr:street":"W Arbor Vitae St",
    "iso:country":"US",
    "sg:address":"915 W Arbor Vitae St",
    "sg:city":"Inglewood",
    "sg:classifiers":[
        {
            "category":"Restaurant",
            "type":"Food & Drink"
        }
    ],
    "sg:phone":"+1 310 670 1014",
    "sg:postcode":"90301",
    "sg:province":"CA",
    "sg:tags":[
        "mexican"
    ],
    "sg:website":"www.menuclub.com/californiaresta...",
    "wof:name":"El Puerto Escondido",
    "wof:placetype":"venue"
},
  "geometry": {"coordinates":[-118.371002,33.952599],"type":"Point"}
}