{
  "type": "Feature",
  "properties": {
    "iso:country":"US",
    "sg:address":"855 East Ave",
    "sg:city":"Chico",
    "sg:classifiers":[
        {
            "category":"Restaurant",
            "type":"Food & Drink"
        }
    ],
    "sg:menulink":"http://www.allmenus.com/ca/chico/135454-jamba-juice/menu/",
    "sg:phone":"+1 530 891 9340",
    "sg:postcode":"95926",
    "sg:province":"CA",
    "sg:tags":[
        "smoothy",
        "juice",
        "american"
    ],
    "wof:name":"Jamba Juice",
    "wof:placetype":"venue"
},
  "geometry": {"coordinates":[-121.84392699999999,39.760873],"type":"Point"}
}