{
  "type": "Feature",
  "properties": {
    "addr:full":"5500 South St Lakewood CA 90713",
    "addr:housenumber":"5500",
    "addr:postcode":"90713",
    "addr:street":"South St",
    "iso:country":"US",
    "sg:address":"5500 South St",
    "sg:city":"Lakewood",
    "sg:classifiers":[
        {
            "category":"Autos & Motor Vehicles",
            "subcategory":"Fuel & Gas Station",
            "type":"Retail Goods"
        }
    ],
    "sg:phone":"+1 562 925 4600",
    "sg:postcode":"90713",
    "sg:province":"CA",
    "wof:name":"South-Bell Mobil",
    "wof:placetype":"venue"
},
  "geometry": {"coordinates":[-118.124674,33.859976],"type":"Point"}
}