{
  "type": "Feature",
  "properties": {
    "iso:country":"US",
    "sg:address":"21425 Avalon Blvd Spc 8",
    "sg:city":"Carson",
    "sg:classifiers":[
        {
            "category":"Building & Trades",
            "subcategory":"Plumbing",
            "type":"Services"
        }
    ],
    "sg:phone":"+1 310 830 9382",
    "sg:postcode":"90745",
    "sg:province":"CA",
    "wof:name":"Action Plumbing & Heating",
    "wof:placetype":"venue"
},
  "geometry": {"coordinates":[-118.263915,33.834099],"type":"Point"}
}