{
  "type": "Feature",
  "properties": {
    "iso:country":"US",
    "sg:address":"900 Coronado St",
    "sg:city":"Needles",
    "sg:classifiers":[
        {
            "category":"Building & Trades",
            "subcategory":"Plumbing",
            "type":"Services"
        }
    ],
    "sg:phone":"+1 928 754 1119",
    "sg:postcode":"92363",
    "sg:province":"CA",
    "sg:tags":[
        "plumbing",
        "contractor"
    ],
    "wof:name":"On Line Plumbing & Heating",
    "wof:placetype":"venue"
},
  "geometry": {"coordinates":[-114.622653,34.837019],"type":"Point"}
}