{
  "type": "Feature",
  "properties": {
    "addr:full":"716 S San Pedro St Los Angeles CA 90014",
    "addr:housenumber":"716",
    "addr:postcode":"90014",
    "addr:street":"S San Pedro St",
    "iso:country":"US",
    "sg:address":"716 S San Pedro St",
    "sg:city":"Los Angeles",
    "sg:classifiers":[
        {
            "category":"Shopping",
            "subcategory":"Clothing, Apparel, & Fashions",
            "type":"Retail Goods"
        }
    ],
    "sg:phone":"+1 213 438 1494",
    "sg:postcode":"90014",
    "sg:province":"CA",
    "sg:tags":[
        "leather"
    ],
    "wof:name":"Exit It USA",
    "wof:placetype":"venue"
},
  "geometry": {"coordinates":[-118.247631,34.039837],"type":"Point"}
}