{
  "type": "Feature",
  "properties": {
    "iso:country":"US",
    "sg:address":"6929 Bertrand Ave",
    "sg:city":"Reseda",
    "sg:classifiers":[
        {
            "category":"Wholesale",
            "subcategory":"Jewelry",
            "type":"Manufacturing & Wholesale Goods"
        },
        {
            "category":"Shopping",
            "subcategory":"Crafts & Fabrics",
            "type":"Retail Goods"
        }
    ],
    "sg:phone":"+1 818 448 3429",
    "sg:postcode":"91335",
    "sg:province":"CA",
    "sg:tags":[
        "bead",
        "beads-wholesale",
        "manufacturer"
    ],
    "wof:name":"Enchanted Bead Garden",
    "wof:placetype":"venue"
},
  "geometry": {"coordinates":[-118.52439200000001,34.196362],"type":"Point"}
}