{
  "type": "Feature",
  "properties": {
    "iso:country":"US",
    "sg:address":"1360 Lincoln Ave",
    "sg:city":"San Rafael",
    "sg:classifiers":[
        {
            "category":"Organizations",
            "subcategory":"Non-profit Organization",
            "type":"Services"
        }
    ],
    "sg:phone":"+1 415 459 9233",
    "sg:postcode":"94901",
    "sg:province":"CA",
    "sg:tags":[
        "information",
        "alcoholism",
        "treatment"
    ],
    "wof:name":"Alano Club Of Marin",
    "wof:placetype":"venue"
},
  "geometry": {"coordinates":[-122.522671,37.976126],"type":"Point"}
}