{
  "type": "Feature",
  "properties": {
    "addr:full":"303 S Elm Dr Beverly Hills CA 90212",
    "addr:housenumber":"303",
    "addr:postcode":"90212",
    "addr:street":"S Elm Dr",
    "iso:country":"US",
    "sg:address":"303 S Elm Dr",
    "sg:city":"Beverly Hills",
    "sg:classifiers":[
        {
            "category":"Professional",
            "subcategory":"Management & Consulting",
            "type":"Services"
        }
    ],
    "sg:phone":"+1 310 553 5051",
    "sg:postcode":"90212",
    "sg:province":"CA",
    "sg:tags":[
        "construction"
    ],
    "wof:name":"Camtech Program Management",
    "wof:placetype":"venue"
},
  "geometry": {"coordinates":[-118.394966,34.059927],"type":"Point"}
}