{
  "type": "Feature",
  "properties": {
    "addr:full":"2985 Bear St Ste B Costa Mesa CA 92626",
    "addr:housenumber":"2985",
    "addr:postcode":"92626",
    "addr:street":"Bear St Ste B Costa",
    "iso:country":"US",
    "sg:address":"2985 Bear St Ste B",
    "sg:city":"Costa Mesa",
    "sg:classifiers":[
        {
            "category":"Education",
            "subcategory":"School",
            "type":"Public Place"
        }
    ],
    "sg:phone":"+1 714 424 5000",
    "sg:postcode":"92626",
    "sg:province":"CA",
    "sg:tags":[
        "high",
        "middle",
        "elementary"
    ],
    "wof:name":"Newport-Mesa Unified School District",
    "wof:placetype":"venue"
},
  "geometry": {"coordinates":[-117.894476,33.67873],"type":"Point"}
}