{
  "type": "Feature",
  "properties": {
    "addr:full":"235 Kansas Street San Francisco CA 94103",
    "addr:housenumber":"235",
    "addr:postcode":"94103",
    "addr:street":"Kansas Street",
    "iso:country":"US",
    "sg:address":"235 Kansas Street",
    "sg:city":"San Francisco",
    "sg:classifiers":[
        {
            "category":"Building & Trades",
            "subcategory":"Construction",
            "type":"Services"
        }
    ],
    "sg:phone":"+1 415 621 6848",
    "sg:postcode":"94103",
    "sg:province":"CA",
    "sg:tags":[
        "interior",
        "design"
    ],
    "wof:name":"Christman & Associates",
    "wof:placetype":"venue"
},
  "geometry": {"coordinates":[-122.403721,37.766849],"type":"Point"}
}