{
  "type": "Feature",
  "properties": {
    "iso:country":"US",
    "sg:address":"23294 Connecticut St",
    "sg:city":"Hayward",
    "sg:classifiers":[
        {
            "category":"Travel",
            "subcategory":"Travel Agent",
            "type":"Entertainment"
        }
    ],
    "sg:phone":"+1 510 786 3000",
    "sg:postcode":"94545",
    "sg:province":"CA",
    "sg:tags":[
        "agency",
        "bureau"
    ],
    "wof:name":"Lets Go Travel",
    "wof:placetype":"venue"
},
  "geometry": {"coordinates":[-122.129385,37.643062],"type":"Point"}
}