{
  "type": "Feature",
  "properties": {
    "iso:country":"US",
    "sg:address":"1070 W 9th St Suite C",
    "sg:city":"Upland",
    "sg:classifiers":[
        {
            "category":"Building & Trades",
            "subcategory":"Construction",
            "type":"Services"
        }
    ],
    "sg:phone":"+1 909 981 7034",
    "sg:postcode":"91786",
    "sg:province":"CA",
    "sg:tags":[
        "altering",
        "consultant",
        "remodeling",
        "contractor"
    ],
    "wof:name":"McGinnis's Remodeling Inc.",
    "wof:placetype":"venue"
},
  "geometry": {"coordinates":[-117.666876,34.096027],"type":"Point"}
}