{
  "type": "Feature",
  "properties": {
    "addr:full":"11217 Barnwall St Norwalk CA 90650",
    "addr:housenumber":"11217",
    "addr:postcode":"90650",
    "addr:street":"Barnwall St",
    "iso:country":"US",
    "sg:address":"11217 Barnwall St",
    "sg:city":"Norwalk",
    "sg:classifiers":[
        {
            "category":"Real Estate",
            "subcategory":"Real Estate Operator",
            "type":"Services"
        }
    ],
    "sg:phone":"+1 562 219 2749",
    "sg:postcode":"90650",
    "sg:province":"CA",
    "sg:tags":[
        "building",
        "apartment"
    ],
    "sg:website":"www.villadelsol-apts.com/",
    "wof:name":"Villa Del Sol Apartments",
    "wof:placetype":"venue"
},
  "geometry": {"coordinates":[-118.09518300000001,33.891693],"type":"Point"}
}