{
  "type": "Feature",
  "properties": {
    "addr:full":"425 Potrero Ave San Francisco CA 94110",
    "addr:housenumber":"425",
    "addr:postcode":"94110",
    "addr:street":"Potrero Ave",
    "iso:country":"US",
    "sg:address":"425 Potrero Ave",
    "sg:city":"San Francisco",
    "sg:classifiers":[
        {
            "category":"Building & Trades",
            "subcategory":"Landscaping Services",
            "type":"Services"
        }
    ],
    "sg:phone":"+1 415 558 8036",
    "sg:postcode":"94110",
    "sg:province":"CA",
    "sg:tags":[
        "landscape",
        "contractor"
    ],
    "wof:name":"Broucaret Landscaping",
    "wof:placetype":"venue"
},
  "geometry": {"coordinates":[-122.407252,37.763512],"type":"Point"}
}