{
  "type": "Feature",
  "properties": {
    "iso:country":"US",
    "sg:address":"356 Jefferson St",
    "sg:city":"Napa",
    "sg:classifiers":[
        {
            "category":"Building & Trades",
            "subcategory":"Landscaping Services",
            "type":"Services"
        }
    ],
    "sg:phone":"+1 707 255 3941",
    "sg:postcode":"94559",
    "sg:province":"CA",
    "sg:tags":[
        "tree"
    ],
    "wof:name":"Professional Tree Service",
    "wof:placetype":"venue"
},
  "geometry": {"coordinates":[-122.294204,38.290387],"type":"Point"}
}