{
  "type": "Feature",
  "properties": {
    "iso:country":"US",
    "sg:address":"3512 Manzana Ct",
    "sg:city":"Camino",
    "sg:classifiers":[
        {
            "category":"Manufacturing",
            "subcategory":"Tools & Machinery",
            "type":"Manufacturing & Wholesale Goods"
        }
    ],
    "sg:phone":"+1 530 644 3875",
    "sg:postcode":"95709",
    "sg:province":"CA",
    "sg:tags":[
        "camera",
        "oral",
        "internal",
        "mfg"
    ],
    "wof:name":"Veratronics Inc",
    "wof:placetype":"venue"
},
  "geometry": {"coordinates":[-120.702988,38.733645],"type":"Point"}
}