{
  "type": "Feature",
  "properties": {
    "addr:full":"3401 Dale Rd Modesto CA 95356",
    "addr:housenumber":"3401",
    "addr:postcode":"ca 95356",
    "addr:street":"Dale Rd",
    "iso:country":"US",
    "sg:address":"3401 Dale Rd",
    "sg:city":"Modesto",
    "sg:classifiers":[
        {
            "category":"Shopping",
            "subcategory":"Shoes",
            "type":"Retail Goods"
        }
    ],
    "sg:phone":"+1 209 577 1484",
    "sg:postcode":"95356",
    "sg:province":"CA",
    "wof:name":"Shoe Box For Men",
    "wof:placetype":"venue"
},
  "geometry": {"coordinates":[-121.049896,37.685802],"type":"Point"}
}