{
  "type": "Feature",
  "properties": {
    "iso:country":"US",
    "sg:address":"201 W Napa St",
    "sg:city":"Sonoma",
    "sg:classifiers":[
        {
            "category":"Food & Beverages",
            "subcategory":"Bakery",
            "type":"Retail Goods"
        }
    ],
    "sg:phone":"+1 707 996 5253",
    "sg:postcode":"95476",
    "sg:province":"CA",
    "wof:name":"Country French Bakery",
    "wof:placetype":"venue"
},
  "geometry": {"coordinates":[-122.461249,38.292232],"type":"Point"}
}