{
  "type": "Feature",
  "properties": {
    "addr:full":"430 Almond Ave Patterson CA 95363",
    "addr:housenumber":"430",
    "addr:postcode":"95363",
    "addr:street":"Almond Ave",
    "iso:country":"US",
    "sg:address":"430 Almond Ave",
    "sg:city":"Patterson",
    "sg:classifiers":[
        {
            "category":"Farming",
            "subcategory":"Dairy Farm",
            "type":"Manufacturing & Wholesale Goods"
        }
    ],
    "sg:phone":"+1 209 892 3056",
    "sg:postcode":"95363",
    "sg:province":"CA",
    "wof:name":"Triangle J",
    "wof:placetype":"venue"
},
  "geometry": {"coordinates":[-121.099327,37.460468],"type":"Point"}
}