{
  "type": "Feature",
  "properties": {
    "addr:full":"135 Clearview Crest Dr Diamond Bar CA 91765",
    "addr:housenumber":"135",
    "addr:postcode":"91765",
    "addr:street":"Clearview Crest Dr",
    "iso:country":"US",
    "sg:address":"135 Clearview Crest Dr",
    "sg:city":"Diamond Bar",
    "sg:classifiers":[
        {
            "category":"Manufacturing",
            "subcategory":"Printing",
            "type":"Manufacturing & Wholesale Goods"
        }
    ],
    "sg:phone":"+1 909 861 9135",
    "sg:postcode":"91765",
    "sg:province":"CA",
    "sg:tags":[
        "commercial",
        "offset"
    ],
    "wof:name":"Eagle Press",
    "wof:placetype":"venue"
},
  "geometry": {"coordinates":[-117.818628,34.021303],"type":"Point"}
}