{
  "type": "Feature",
  "properties": {
    "iso:country":"US",
    "sg:address":"16 Salmon St",
    "sg:city":"San Francisco",
    "sg:classifiers":[
        {
            "category":"Food & Beverages",
            "subcategory":"Specialty",
            "type":"Retail Goods"
        }
    ],
    "sg:phone":"+1 415 829 8203",
    "sg:postcode":"94133",
    "sg:province":"CA",
    "sg:website":"lovejonesfood.com",
    "wof:name":"Lovejones",
    "wof:placetype":"venue"
},
  "geometry": {"coordinates":[-122.412522,37.79625],"type":"Point"}
}