{
  "type": "Feature",
  "properties": {
    "addr:full":"300 E Esplanade Dr Oxnard CA 93036",
    "addr:housenumber":"300",
    "addr:postcode":"93036",
    "addr:street":"E Esplanade Dr",
    "iso:country":"US",
    "sg:address":"300 E Esplanade Dr",
    "sg:city":"Oxnard",
    "sg:classifiers":[
        {
            "category":"Real Estate",
            "subcategory":"Real Estate Agent",
            "type":"Services"
        }
    ],
    "sg:phone":"+1 805 988 8050",
    "sg:postcode":"93036",
    "sg:province":"CA",
    "wof:name":"Colliers Seeley",
    "wof:placetype":"venue"
},
  "geometry": {"coordinates":[-119.170535,34.227916],"type":"Point"}
}