{
  "type": "Feature",
  "properties": {
    "addr:full":"960 Ygnacio Valley Rd Walnut Creek CA 94598",
    "addr:housenumber":"960",
    "addr:postcode":"94598",
    "addr:street":"Valley Rd",
    "iso:country":"US",
    "sg:address":"960 Ygnacio Valley Rd",
    "sg:city":"Walnut Creek",
    "sg:classifiers":[
        {
            "category":"Education",
            "subcategory":"School",
            "type":"Public Place"
        }
    ],
    "sg:phone":"+1 925 944 6850",
    "sg:postcode":"94598",
    "sg:province":"CA",
    "wof:name":"Walnut Creek School District",
    "wof:placetype":"venue"
},
  "geometry": {"coordinates":[-122.055575,37.907913],"type":"Point"}
}