{
  "type": "Feature",
  "properties": {
    "addr:full":"5320 W Rosecrans Ave Lawndale CA 90250",
    "addr:housenumber":"5320",
    "addr:postcode":"ca 90250",
    "addr:street":"W Rosecrans Ave",
    "iso:country":"US",
    "sg:address":"5320 W Rosecrans Ave",
    "sg:city":"Lawndale",
    "sg:classifiers":[
        {
            "category":"Building & Trades",
            "subcategory":"Plumbing",
            "type":"Services"
        }
    ],
    "sg:phone":"+1 310 643 5086",
    "sg:postcode":"90250",
    "sg:province":"CA",
    "sg:tags":[
        "sheet",
        "work",
        "metal",
        "contractor"
    ],
    "wof:name":"Century Parts Inc",
    "wof:placetype":"venue"
},
  "geometry": {"coordinates":[-118.37416,33.901751],"type":"Point"}
}