{
  "type": "Feature",
  "properties": {
    "addr:full":"25780 Whitewood Cir Moreno Valley CA 92553",
    "addr:housenumber":"25780",
    "addr:postcode":"92553",
    "addr:street":"Whitewood Cir",
    "iso:country":"US",
    "sg:address":"25780 Whitewood Cir",
    "sg:city":"Moreno Valley",
    "sg:classifiers":[
        {
            "category":"Building & Trades",
            "subcategory":"Construction",
            "type":"Services"
        }
    ],
    "sg:phone":"+1 714 981 4002",
    "sg:postcode":"92553",
    "sg:province":"CA",
    "sg:tags":[
        "hanging",
        "contractor"
    ],
    "wof:name":"Delarosa Construction",
    "wof:placetype":"venue"
},
  "geometry": {"coordinates":[-117.21282600000001,33.907743],"type":"Point"}
}