{
  "type": "Feature",
  "properties": {
    "addr:full":"1614 S Carlos Ave Ste B Ontario CA 91761",
    "addr:housenumber":"1614",
    "addr:postcode":"91761",
    "addr:street":"S Carlos Ave Ste B",
    "iso:country":"US",
    "sg:address":"1614 S Carlos Ave Ste B",
    "sg:city":"Ontario",
    "sg:classifiers":[
        {
            "category":"Shopping",
            "subcategory":"Computers & Home Electronics",
            "type":"Retail Goods"
        }
    ],
    "sg:phone":"+1 909 923 6640",
    "sg:postcode":"91761",
    "sg:province":"CA",
    "sg:tags":[
        "high",
        "equipment-dealers",
        "fidelity",
        "stereophonic",
        "consumer"
    ],
    "wof:name":"Trinity Sound Company",
    "wof:placetype":"venue"
},
  "geometry": {"coordinates":[-117.60655199999999,34.044449],"type":"Point"}
}