{
  "type": "Feature",
  "properties": {
    "addr:full":"51 Bolinas Rd Fairfax CA 94930",
    "addr:housenumber":"51",
    "addr:postcode":"94930",
    "addr:street":"Bolinas Rd",
    "iso:country":"US",
    "sg:address":"51 Bolinas Rd",
    "sg:city":"Fairfax",
    "sg:classifiers":[
        {
            "category":"Shopping",
            "subcategory":"Gifts & Souvenirs",
            "type":"Retail Goods"
        }
    ],
    "sg:phone":"+1 415 456 4901",
    "sg:postcode":"94930",
    "sg:province":"CA",
    "wof:name":"Artifax",
    "wof:placetype":"venue"
},
  "geometry": {"coordinates":[-122.58920000000001,37.986506],"type":"Point"}
}