{
  "type": "Feature",
  "properties": {
    "iso:country":"US",
    "sg:address":"2330 E Walnut St",
    "sg:city":"Pasadena",
    "sg:classifiers":[
        {
            "category":"Shopping",
            "subcategory":"Pharmacy",
            "type":"Retail Goods"
        }
    ],
    "sg:phone":"+1 626 304 2725",
    "sg:postcode":"91107",
    "sg:province":"CA",
    "sg:tags":[
        "drugstore"
    ],
    "wof:name":"Rite Aid",
    "wof:placetype":"venue"
},
  "geometry": {"coordinates":[-118.101997,34.147999],"type":"Point"}
}