{
  "type": "Feature",
  "properties": {
    "addr:full":"17547 Ventura Blvd Encino CA 91316",
    "addr:housenumber":"17547",
    "addr:postcode":"91316",
    "addr:street":"Ventura Blvd",
    "iso:country":"US",
    "sg:address":"17547 Ventura Blvd",
    "sg:city":"Encino",
    "sg:classifiers":[
        {
            "category":"Professional",
            "subcategory":"Management & Consulting",
            "type":"Services"
        }
    ],
    "sg:phone":"+1 818 995 4700",
    "sg:postcode":"91316",
    "sg:province":"CA",
    "sg:tags":[
        "food",
        "facility"
    ],
    "wof:name":"Ravak",
    "wof:placetype":"venue"
},
  "geometry": {"coordinates":[-118.51604,34.16185],"type":"Point"}
}