{
  "type": "Feature",
  "properties": {
    "iso:country":"US",
    "sg:address":"10521 Humbolt St",
    "sg:city":"Los Alamitos",
    "sg:classifiers":[
        {
            "category":"Manufacturing",
            "subcategory":"Printing",
            "type":"Manufacturing & Wholesale Goods"
        }
    ],
    "sg:phone":"+1 562 936 1388",
    "sg:postcode":"90720",
    "sg:province":"CA",
    "sg:tags":[
        "engraver",
        "wood"
    ],
    "wof:name":"Cypress Engraving",
    "wof:placetype":"venue"
},
  "geometry": {"coordinates":[-118.065715,33.80945],"type":"Point"}
}