{
  "type": "Feature",
  "properties": {
    "addr:full":"1938 N Abbie Way Upland CA 91784",
    "addr:housenumber":"1938",
    "addr:postcode":"91784",
    "addr:street":"N Abbie Way",
    "iso:country":"US",
    "sg:address":"1938 N Abbie Way",
    "sg:city":"Upland",
    "sg:classifiers":[
        {
            "category":"Building & Trades",
            "subcategory":"Electrical",
            "type":"Services"
        }
    ],
    "sg:phone":"+1 909 946 0957",
    "sg:postcode":"91784",
    "sg:province":"CA",
    "sg:tags":[
        "electrical",
        "contractor"
    ],
    "wof:name":"Steve Raasch Electric",
    "wof:placetype":"venue"
},
  "geometry": {"coordinates":[-117.661619,34.133256],"type":"Point"}
}