{
  "type": "Feature",
  "properties": {
    "addr:full":"22230 Needles St Chatsworth CA 91311",
    "addr:postcode":"22230;91311",
    "addr:street":"Needles St",
    "iso:country":"US",
    "sg:address":"22230 Needles St",
    "sg:city":"Chatsworth",
    "sg:classifiers":[
        {
            "category":"Real Estate",
            "subcategory":"Architect",
            "type":"Services"
        }
    ],
    "sg:phone":"+1 818 882 3667",
    "sg:postcode":"91311",
    "sg:province":"CA",
    "wof:name":"Bernkopf Designs",
    "wof:placetype":"venue"
},
  "geometry": {"coordinates":[-118.611721,34.246713],"type":"Point"}
}