{
  "type": "Feature",
  "properties": {
    "addr:full":"313 Robertson Blvd Chowchilla CA 93610",
    "addr:housenumber":"313",
    "addr:postcode":"93610",
    "addr:street":"Robertson Blvd",
    "iso:country":"US",
    "sg:address":"313 Robertson Blvd",
    "sg:city":"Chowchilla",
    "sg:classifiers":[
        {
            "category":"Retail",
            "subcategory":"Portrait Studio",
            "type":"Services"
        }
    ],
    "sg:phone":"+1 559 665 0858",
    "sg:postcode":"93610",
    "sg:province":"CA",
    "sg:tags":[
        "photographer"
    ],
    "sg:website":"www.jgphotography.com",
    "wof:name":"Jeff Gwartney Photography",
    "wof:placetype":"venue"
},
  "geometry": {"coordinates":[-120.260971,37.121995],"type":"Point"}
}