{
  "type": "Feature",
  "properties": {
    "addr:full":"3315 San Felipe Rd San Jose CA 95135",
    "addr:housenumber":"3315",
    "addr:postcode":"95135",
    "addr:street":"San Felipe Rd",
    "iso:country":"US",
    "sg:address":"3315 San Felipe Rd",
    "sg:city":"San Jose",
    "sg:classifiers":[
        {
            "category":"Real Estate",
            "subcategory":"Real Estate Agent",
            "type":"Services"
        }
    ],
    "sg:phone":"+1 408 532 0648",
    "sg:postcode":"95135",
    "sg:province":"CA",
    "sg:tags":[
        "management"
    ],
    "wof:name":"M & N Properties",
    "wof:placetype":"venue"
},
  "geometry": {"coordinates":[-121.78896,37.312477],"type":"Point"}
}