{
  "type": "Feature",
  "properties": {
    "addr:full":"817 N Parkway Dr Fresno CA 93728",
    "addr:housenumber":"817",
    "addr:postcode":"93728",
    "addr:street":"N Parkway Dr",
    "iso:country":"US",
    "sg:address":"817 N Parkway Dr",
    "sg:city":"Fresno",
    "sg:classifiers":[
        {
            "category":"Travel",
            "subcategory":"Hotels & Motels",
            "type":"Entertainment"
        }
    ],
    "sg:phone":"+1 559 268 5371",
    "sg:postcode":"93728",
    "sg:province":"CA",
    "wof:name":"Villa Motel",
    "wof:placetype":"venue"
},
  "geometry": {"coordinates":[-119.827761,36.753111],"type":"Point"}
}