{
  "type": "Feature",
  "properties": {
    "iso:country":"US",
    "sg:address":"5725 Mistridge Drive",
    "sg:city":"Rancho Palos Verdes",
    "sg:classifiers":[
        {
            "category":"Shopping",
            "subcategory":"Books",
            "type":"Retail Goods"
        }
    ],
    "sg:phone":"+1 310 539 7015",
    "sg:postcode":"90275",
    "sg:province":"CA",
    "sg:tags":[
        "bookstore"
    ],
    "wof:name":"Original Books",
    "wof:placetype":"venue"
},
  "geometry": {"coordinates":[-118.377758,33.767434],"type":"Point"}
}