{
  "type": "Feature",
  "properties": {
    "iso:country":"US",
    "sg:address":"22766 Ventura Blvd",
    "sg:city":"Woodland Hills",
    "sg:classifiers":[
        {
            "category":"Home & Garden",
            "subcategory":"Building Materials",
            "type":"Retail Goods"
        }
    ],
    "sg:phone":"+1 818 225 9882",
    "sg:postcode":"91364",
    "sg:province":"CA",
    "sg:tags":[
        "equipment",
        "fixture",
        "lighting"
    ],
    "sg:website":"www.delightville.com",
    "wof:name":"De Light Ville",
    "wof:placetype":"venue"
},
  "geometry": {"coordinates":[-118.623001,34.166199],"type":"Point"}
}