{
  "type": "Feature",
  "properties": {
    "addr:full":"15213 Green Valley Dr Chino Hills CA 91709",
    "addr:housenumber":"15213",
    "addr:postcode":"91709",
    "addr:street":"Green Valley Dr",
    "iso:country":"US",
    "sg:address":"15213 Green Valley Dr",
    "sg:city":"Chino Hills",
    "sg:classifiers":[
        {
            "category":"Shopping",
            "subcategory":"Clothing, Apparel, & Fashions",
            "type":"Retail Goods"
        }
    ],
    "sg:phone":"+1 909 762 5314",
    "sg:postcode":"91709",
    "sg:province":"CA",
    "wof:name":"Bishop Clothing Co",
    "wof:placetype":"venue"
},
  "geometry": {"coordinates":[-117.735027,33.979172],"type":"Point"}
}