{
  "type": "Feature",
  "properties": {
    "addr:full":"2270 Via Cascabel Escondido CA 92027",
    "addr:housenumber":"2270",
    "addr:postcode":"92027",
    "addr:street":"Via Cascabel",
    "iso:country":"US",
    "sg:address":"2270 Via Cascabel",
    "sg:city":"Escondido",
    "sg:classifiers":[
        {
            "category":"Banks & Credit Unions",
            "subcategory":"Financial Services",
            "type":"Services"
        }
    ],
    "sg:phone":"+1 760 746 8380",
    "sg:postcode":"92027",
    "sg:province":"CA",
    "sg:tags":[
        "trust",
        "management"
    ],
    "wof:name":"Buskirk Family Trust",
    "wof:placetype":"venue"
},
  "geometry": {"coordinates":[-117.027242,33.112022],"type":"Point"}
}