{
  "type": "Feature",
  "properties": {
    "addr:full":"16960 Bernardo Center Dr San Diego CA 92128",
    "addr:housenumber":"16960",
    "addr:postcode":"92128",
    "addr:street":"Bernardo Center Dr",
    "iso:country":"US",
    "sg:address":"16960 Bernardo Center Dr",
    "sg:city":"San Diego",
    "sg:classifiers":[
        {
            "category":"Government",
            "subcategory":"Post Office",
            "type":"Public Place"
        }
    ],
    "sg:phone":"+1 858 487 0857",
    "sg:postcode":"92128",
    "sg:province":"CA",
    "wof:name":"US Post Office",
    "wof:placetype":"venue"
},
  "geometry": {"coordinates":[-117.074451,33.022701],"type":"Point"}
}