{
  "type": "Feature",
  "properties": {
    "addr:full":"11253 Brockway Rd Truckee CA 96161",
    "addr:housenumber":"11253",
    "addr:postcode":"96161",
    "addr:street":"Brockway Rd",
    "iso:country":"US",
    "sg:address":"11253 Brockway Rd",
    "sg:city":"Truckee",
    "sg:classifiers":[
        {
            "category":"Restaurant",
            "type":"Food & Drink"
        }
    ],
    "sg:phone":"+1 530 550 1269",
    "sg:postcode":"96161",
    "sg:province":"CA",
    "sg:tags":[
        "thai",
        "asian",
        "pan"
    ],
    "wof:name":"Thai Delicacy",
    "wof:placetype":"venue"
},
  "geometry": {"coordinates":[-120.164163,39.321973],"type":"Point"}
}