{
  "type": "Feature",
  "properties": {
    "addr:full":"1884 Balsley Ct Hanford CA 93230",
    "addr:housenumber":"1884",
    "addr:postcode":"ca 93230",
    "addr:street":"Balsley Ct",
    "iso:country":"US",
    "sg:address":"1884 Balsley Ct",
    "sg:city":"Hanford",
    "sg:classifiers":[
        {
            "category":"Professional",
            "subcategory":"Business Services",
            "type":"Services"
        }
    ],
    "sg:phone":"+1 559 582 0895",
    "sg:postcode":"93230",
    "sg:province":"CA",
    "sg:tags":[
        "inspection"
    ],
    "wof:name":"Rs Testing",
    "wof:placetype":"venue"
},
  "geometry": {"coordinates":[-119.676271,36.312245],"type":"Point"}
}