{
  "type": "Feature",
  "properties": {
    "iso:country":"US",
    "sg:address":"6 Venture",
    "sg:city":"Irvine",
    "sg:classifiers":[
        {
            "category":"Shopping",
            "subcategory":"Computers & Home Electronics",
            "type":"Retail Goods"
        }
    ],
    "sg:phone":"+1 949 789 0500",
    "sg:postcode":"92618",
    "sg:province":"CA",
    "sg:tags":[
        "software"
    ],
    "sg:website":"www.alteer.com",
    "wof:name":"Alteer Corp",
    "wof:placetype":"venue"
},
  "geometry": {"coordinates":[-117.752307,33.659741],"type":"Point"}
}