{
  "type": "Feature",
  "properties": {
    "addr:full":"810 W Collins Ave Orange CA 92867",
    "addr:housenumber":"810",
    "addr:postcode":"92867",
    "addr:street":"W Collins Ave",
    "iso:country":"US",
    "sg:address":"810 W Collins Ave",
    "sg:city":"Orange",
    "sg:classifiers":[
        {
            "category":"Wholesale",
            "subcategory":"Machinery & Supplies",
            "type":"Manufacturing & Wholesale Goods"
        }
    ],
    "sg:phone":"+1 714 744 3524",
    "sg:postcode":"92867",
    "sg:province":"CA",
    "sg:tags":[
        "machine",
        "tool"
    ],
    "wof:name":"Dan's Machine Tool Repair",
    "wof:placetype":"venue"
},
  "geometry": {"coordinates":[-117.860587,33.802323],"type":"Point"}
}