{
  "type": "Feature",
  "properties": {
    "iso:country":"US",
    "sg:address":"33046 Cll Aviador",
    "sg:city":"San Juan Capistrano",
    "sg:classifiers":[
        {
            "category":"Manufacturing",
            "subcategory":"Printing",
            "type":"Manufacturing & Wholesale Goods"
        }
    ],
    "sg:phone":"+1 949 661 5151",
    "sg:postcode":"92675",
    "sg:province":"CA",
    "sg:tags":[
        "periodical"
    ],
    "wof:name":"Emap Publishing",
    "wof:placetype":"venue"
},
  "geometry": {"coordinates":[-117.67473200000001,33.483117],"type":"Point"}
}