{
  "type": "Feature",
  "properties": {
    "addr:full":"3390 Golden Heights Dr Redding CA 96003",
    "addr:housenumber":"3390",
    "addr:postcode":"96003",
    "addr:street":"Golden Heights Dr",
    "iso:country":"US",
    "sg:address":"3390 Golden Heights Dr",
    "sg:city":"Redding",
    "sg:classifiers":[
        {
            "category":"Retail",
            "subcategory":"Auto Repair",
            "type":"Services"
        }
    ],
    "sg:phone":"+1 530 243 0135",
    "sg:postcode":"96003",
    "sg:province":"CA",
    "sg:tags":[
        "repairing",
        "automobile"
    ],
    "wof:name":"Ultimate Garage Floors",
    "wof:placetype":"venue"
},
  "geometry": {"coordinates":[-122.40331999999999,40.618162],"type":"Point"}
}