{
  "type": "Feature",
  "properties": {
    "iso:country":"US",
    "sg:address":"604 Pine Ave",
    "sg:city":"Long Beach",
    "sg:classifiers":[
        {
            "category":"Communications",
            "subcategory":"Newspaper",
            "type":"Services"
        }
    ],
    "sg:phone":"+1 562 499 1415",
    "sg:postcode":"90802",
    "sg:province":"CA",
    "sg:tags":[
        "print",
        "medium"
    ],
    "wof:name":"El Economico",
    "wof:placetype":"venue"
},
  "geometry": {"coordinates":[-118.193001,33.774899],"type":"Point"}
}