{
  "type": "Feature",
  "properties": {
    "iso:country":"US",
    "sg:address":"422 Glenneyre St",
    "sg:city":"Laguna Beach",
    "sg:classifiers":[
        {
            "category":"Professional",
            "type":"Services"
        }
    ],
    "sg:phone":"+1 949 376 5188",
    "sg:postcode":"92651",
    "sg:province":"CA",
    "sg:tags":[
        "establishment"
    ],
    "wof:name":"Laguna Broadcasting Network",
    "wof:placetype":"venue"
},
  "geometry": {"coordinates":[-117.78065100000001,33.540529],"type":"Point"}
}