{
  "type": "Feature",
  "properties": {
    "iso:country":"US",
    "sg:address":"4132 Manzanita Avenue",
    "sg:city":"Carmichael",
    "sg:classifiers":[
        {
            "category":"Personal",
            "subcategory":"Barber",
            "type":"Services"
        }
    ],
    "sg:phone":"+1 916 482 0182",
    "sg:postcode":"95608",
    "sg:province":"CA",
    "wof:name":"Supercuts",
    "wof:placetype":"venue"
},
  "geometry": {"coordinates":[-121.32794,38.639258],"type":"Point"}
}