{
  "type": "Feature",
  "properties": {
    "iso:country":"US",
    "sg:address":"6277 Van Nuys Blvd #118",
    "sg:city":"Van Nuys",
    "sg:classifiers":[
        {
            "category":"Real Estate",
            "subcategory":"Architect",
            "type":"Services"
        }
    ],
    "sg:phone":"+1 818 374 1300",
    "sg:postcode":"91401",
    "sg:province":"CA",
    "wof:name":"GM Modern Design",
    "wof:placetype":"venue"
},
  "geometry": {"coordinates":[-118.44905199999999,34.184441],"type":"Point"}
}