{
  "type": "Feature",
  "properties": {
    "iso:country":"US",
    "sg:address":"11008 Riverside Dr",
    "sg:city":"North Hollywood",
    "sg:classifiers":[
        {
            "category":"Arts & Performance",
            "subcategory":"Art Gallery",
            "type":"Entertainment"
        }
    ],
    "sg:phone":"+1 818 509 3990",
    "sg:postcode":"91602",
    "sg:province":"CA",
    "wof:name":"Lensmaster Inc",
    "wof:placetype":"venue"
},
  "geometry": {"coordinates":[-118.370758,34.152288],"type":"Point"}
}