{
  "type": "Feature",
  "properties": {
    "iso:country":"US",
    "sg:address":"5959 W. Century Blvd",
    "sg:city":"Los Angeles",
    "sg:classifiers":[
        {
            "category":"Professional",
            "subcategory":"Computer Services",
            "type":"Services"
        }
    ],
    "sg:phone":"+1 888 452 1505",
    "sg:postcode":"90045",
    "sg:province":"CA",
    "sg:tags":[
        "virtual-phone-numbers",
        "toll-free-numbers",
        "call-forwarding",
        "international-phone-service",
        "business-toll-free",
        "business-phone-numbers",
        "800-numbers",
        "virtual-numbers",
        "international-call-forwarding",
        "international-phone-numbers"
    ],
    "sg:website":"http://www.tollfreeforwarding.com",
    "wof:name":"TollFreeForwarding",
    "wof:placetype":"venue"
},
  "geometry": {"coordinates":[-118.390107,33.945561],"type":"Point"}
}