{
  "type": "Feature",
  "properties": {
    "addr:full":"10918 Northshore Sq Cupertino CA 95014",
    "addr:housenumber":"10918",
    "addr:postcode":"95014",
    "addr:street":"Northshore Sq",
    "iso:country":"US",
    "sg:address":"10918 Northshore Sq",
    "sg:city":"Cupertino",
    "sg:classifiers":[
        {
            "category":"Food & Beverages",
            "subcategory":"Groceries & Convenience Stores",
            "type":"Retail Goods"
        }
    ],
    "sg:phone":"+1 408 865 0290",
    "sg:postcode":"95014",
    "sg:province":"CA",
    "sg:tags":[
        "product"
    ],
    "wof:name":"Stauffer Biscuit Co",
    "wof:placetype":"venue"
},
  "geometry": {"coordinates":[-122.02539400000001,37.337019],"type":"Point"}
}