{
  "type": "Feature",
  "properties": {
    "iso:country":"US",
    "sg:address":"8150 Garvey Ave Ste 113A",
    "sg:city":"Rosemead",
    "sg:classifiers":[
        {
            "category":"Ice Cream",
            "type":"Food & Drink"
        }
    ],
    "sg:phone":"+1 626 927 9704",
    "sg:postcode":"91770",
    "sg:province":"CA",
    "sg:tags":[
        "frozen",
        "yogurt"
    ],
    "sg:website":"www.myyolove.com",
    "wof:name":"YoLove Frozen Yogurt",
    "wof:placetype":"venue"
},
  "geometry": {"coordinates":[-118.09134,34.061377],"type":"Point"}
}