{
  "type": "Feature",
  "properties": {
    "addr:full":"4532 Arden Way Sacramento CA 95864",
    "addr:housenumber":"4532",
    "addr:postcode":"95864",
    "addr:street":"Arden Way",
    "iso:country":"US",
    "sg:address":"4532 Arden Way",
    "sg:city":"Sacramento",
    "sg:classifiers":[
        {
            "category":"Education",
            "subcategory":"Dance Studio",
            "type":"Public Place"
        }
    ],
    "sg:phone":"+1 916 485 3500",
    "sg:postcode":"95864",
    "sg:province":"CA",
    "sg:tags":[
        "instruction",
        "dancing"
    ],
    "wof:name":"Ballroom Dance Ctr",
    "wof:placetype":"venue"
},
  "geometry": {"coordinates":[-121.356893,38.595366],"type":"Point"}
}