{
  "type": "Feature",
  "properties": {
    "addr:full":"4039 Eagle Rock Blvd Los Angeles CA 90065",
    "addr:housenumber":"4039",
    "addr:postcode":"90065",
    "addr:street":"Eagle Rock Blvd",
    "iso:country":"US",
    "sg:address":"4039 Eagle Rock Blvd",
    "sg:city":"Los Angeles",
    "sg:classifiers":[
        {
            "category":"Retail",
            "subcategory":"Auto Repair",
            "type":"Services"
        }
    ],
    "sg:phone":"+1 323 259 0373",
    "sg:postcode":"90065",
    "sg:province":"CA",
    "wof:name":"Frank & Harold Auto Repair",
    "wof:placetype":"venue"
},
  "geometry": {"coordinates":[-118.227997,34.1208],"type":"Point"}
}