{
  "type": "Feature",
  "properties": {
    "iso:country":"US",
    "sg:address":"2101 K St",
    "sg:city":"Sacramento",
    "sg:classifiers":[
        {
            "category":"Manufacturing",
            "subcategory":"Printing",
            "type":"Manufacturing & Wholesale Goods"
        }
    ],
    "sg:phone":"+1 916 444 2840",
    "sg:postcode":"95816",
    "sg:province":"CA",
    "sg:tags":[
        "publisher"
    ],
    "sg:website":"www.statenet.com",
    "wof:name":"California Journal",
    "wof:placetype":"venue"
},
  "geometry": {"coordinates":[-121.477708,38.574881],"type":"Point"}
}