{
  "type": "Feature",
  "properties": {
    "addr:full":"1700 Esplanade Chico CA 95926",
    "addr:housenumber":"1700",
    "addr:postcode":"95926",
    "addr:street":"Esplanade Chico",
    "iso:country":"US",
    "sg:address":"1700 Esplanade",
    "sg:city":"Chico",
    "sg:classifiers":[
        {
            "category":"Health Services",
            "subcategory":"Doctor",
            "type":"Services"
        }
    ],
    "sg:phone":"+1 530 332 5715",
    "sg:postcode":"95926",
    "sg:province":"CA",
    "sg:tags":[
        "physician",
        "surgeon"
    ],
    "wof:name":"Breast Center Of Northern Ca",
    "wof:placetype":"venue"
},
  "geometry": {"coordinates":[-121.85064800000001,39.744667],"type":"Point"}
}