{
  "type": "Feature",
  "properties": {
    "iso:country":"US",
    "sg:address":"1300 S Anaheim Blvd",
    "sg:city":"Anaheim",
    "sg:classifiers":[
        {
            "category":"Sports & Exercise",
            "subcategory":"Bicycle Rental",
            "type":"Entertainment"
        },
        {
            "category":"Retail",
            "subcategory":"Auto Repair",
            "type":"Services"
        }
    ],
    "sg:phone":"+1 714 632 8075",
    "sg:postcode":"92805",
    "sg:province":"CA",
    "sg:tags":[
        "bike",
        "motorcycle"
    ],
    "sg:website":"www.rentrtoyz.com",
    "wof:name":"Sand & Sea Toyz Rentals",
    "wof:placetype":"venue"
},
  "geometry": {"coordinates":[-117.906814,33.816709],"type":"Point"}
}