{
  "type": "Feature",
  "properties": {
    "iso:country":"US",
    "sg:address":"116 Ventura Ave",
    "sg:city":"Oxnard",
    "sg:classifiers":[
        {
            "category":"Manufacturing",
            "subcategory":"Printing",
            "type":"Manufacturing & Wholesale Goods"
        }
    ],
    "sg:phone":"+1 805 984 2790",
    "sg:postcode":"93035",
    "sg:province":"CA",
    "sg:tags":[
        "printer"
    ],
    "wof:name":"Precious Images",
    "wof:placetype":"venue"
},
  "geometry": {"coordinates":[-119.21691300000001,34.152587],"type":"Point"}
}