{
  "type": "Feature",
  "properties": {
    "iso:country":"US",
    "sg:address":"7435 Lincoln Ave",
    "sg:city":"Riverside",
    "sg:classifiers":[
        {
            "category":"Organizations",
            "subcategory":"Religious Organization",
            "type":"Services"
        }
    ],
    "sg:phone":"+1 951 358 0953",
    "sg:postcode":"92504",
    "sg:province":"CA",
    "sg:tags":[
        "church"
    ],
    "wof:name":"Mt Olive Christian Church",
    "wof:placetype":"venue"
},
  "geometry": {"coordinates":[-117.398715,33.929486],"type":"Point"}
}