{
  "type": "Feature",
  "properties": {
    "addr:full":"301 S State St Ukiah CA 95482",
    "addr:housenumber":"301",
    "addr:postcode":"ca 95482",
    "addr:street":"S State St",
    "iso:country":"US",
    "sg:address":"301 S State St",
    "sg:city":"Ukiah",
    "sg:classifiers":[
        {
            "category":"Social Services",
            "type":"Services"
        }
    ],
    "sg:phone":"+1 707 462 3041",
    "sg:postcode":"95482",
    "sg:province":"CA",
    "sg:tags":[
        "organization",
        "welfare"
    ],
    "sg:website":"www.communitycare707.com",
    "wof:name":"Community Care",
    "wof:placetype":"venue"
},
  "geometry": {"coordinates":[-123.207239,39.14873],"type":"Point"}
}