{
  "type": "Feature",
  "properties": {
    "addr:full":"40396 State Hwy 41 Oakhurst CA 93644",
    "addr:housenumber":"40396",
    "addr:postcode":"93644",
    "addr:street":"State Hwy 41",
    "iso:country":"US",
    "sg:address":"40396 State Hwy 41",
    "sg:city":"Oakhurst",
    "sg:classifiers":[
        {
            "category":"Shopping",
            "subcategory":"Bicycles & Sporting Goods",
            "type":"Retail Goods"
        }
    ],
    "sg:phone":"+1 559 683 2900",
    "sg:postcode":"93644",
    "sg:province":"CA",
    "sg:tags":[
        "gun",
        "gunsmith"
    ],
    "wof:name":"Sportsmen's Den",
    "wof:placetype":"venue"
},
  "geometry": {"coordinates":[-119.647183,37.334278],"type":"Point"}
}