{
  "type": "Feature",
  "properties": {
    "iso:country":"US",
    "sg:address":"120 Village Pl",
    "sg:city":"Orinda",
    "sg:classifiers":[
        {
            "category":"Banks & Credit Unions",
            "subcategory":"Investment Brokerage",
            "type":"Services"
        }
    ],
    "sg:phone":"+1 925 253 8880",
    "sg:postcode":"94553",
    "sg:province":"CA",
    "sg:tags":[
        "advisory",
        "financial"
    ],
    "wof:name":"Reynold Financial Management",
    "wof:placetype":"venue"
},
  "geometry": {"coordinates":[-122.113584,37.999205],"type":"Point"}
}