{
  "type": "Feature",
  "properties": {
    "iso:country":"US",
    "sg:address":"17777 Main St Ste H",
    "sg:city":"Irvine",
    "sg:classifiers":[
        {
            "category":"Professional",
            "subcategory":"Computer Services",
            "type":"Services"
        }
    ],
    "sg:phone":"+1 949 863 1905",
    "sg:postcode":"92614",
    "sg:province":"CA",
    "sg:tags":[
        "repair"
    ],
    "wof:name":"Newport Office Equipment",
    "wof:placetype":"venue"
},
  "geometry": {"coordinates":[-117.857821,33.686749],"type":"Point"}
}