{
  "type": "Feature",
  "properties": {
    "iso:country":"US",
    "sg:address":"25500 Hawthorne Blvd",
    "sg:city":"Torrance",
    "sg:classifiers":[
        {
            "category":"Professional",
            "subcategory":"Accounting & Tax Preparation",
            "type":"Services"
        }
    ],
    "sg:phone":"+1 310 373 8804",
    "sg:postcode":"90505",
    "sg:province":"CA",
    "sg:tags":[
        "accountant"
    ],
    "wof:name":"Theodore Y Hanasono Accntncy",
    "wof:placetype":"venue"
},
  "geometry": {"coordinates":[-118.348966,33.794585],"type":"Point"}
}