{
  "type": "Feature",
  "properties": {
    "addr:full":"246 N Western Ave Los Angeles CA 90004",
    "addr:housenumber":"246",
    "addr:postcode":"90004",
    "addr:street":"N Western Ave",
    "iso:country":"US",
    "sg:address":"246 N Western Ave",
    "sg:city":"Los Angeles",
    "sg:classifiers":[
        {
            "category":"Wholesale",
            "subcategory":"Machinery & Supplies",
            "type":"Manufacturing & Wholesale Goods"
        }
    ],
    "sg:phone":"+1 323 462 7457",
    "sg:postcode":"90004",
    "sg:province":"CA",
    "sg:tags":[
        "equipment",
        "establishment"
    ],
    "wof:name":"Innovative Beauty Supply",
    "wof:placetype":"venue"
},
  "geometry": {"coordinates":[-118.309062,34.073777],"type":"Point"}
}