{
  "type": "Feature",
  "properties": {
    "iso:country":"US",
    "sg:address":"2803 G St",
    "sg:city":"Merced",
    "sg:classifiers":[
        {
            "category":"Manufacturing",
            "subcategory":"Signs",
            "type":"Manufacturing & Wholesale Goods"
        }
    ],
    "sg:phone":"+1 209 385 0733",
    "sg:postcode":"95340",
    "sg:province":"CA",
    "sg:tags":[
        "specialty",
        "mfg"
    ],
    "wof:name":"Sign Graphics",
    "wof:placetype":"venue"
},
  "geometry": {"coordinates":[-120.469538,37.310187],"type":"Point"}
}