{
  "type": "Feature",
  "properties": {
    "iso:country":"US",
    "sg:address":"933 Tuttle Ave",
    "sg:city":"Simi Valley",
    "sg:classifiers":[
        {
            "category":"Professional",
            "subcategory":"Computer Services",
            "type":"Services"
        }
    ],
    "sg:phone":"+1 805 584 9904",
    "sg:postcode":"93065",
    "sg:province":"CA",
    "sg:tags":[
        "consultant",
        "designer"
    ],
    "wof:name":"Embedded Systems Products",
    "wof:placetype":"venue"
},
  "geometry": {"coordinates":[-118.78484,34.25469],"type":"Point"}
}