{
  "type": "Feature",
  "properties": {
    "addr:full":"411 Woodview Dr Morgan Hill CA 95037",
    "addr:housenumber":"411",
    "addr:postcode":"95037",
    "addr:street":"Woodview Dr",
    "iso:country":"US",
    "sg:address":"411 Woodview Dr",
    "sg:city":"Morgan Hill",
    "sg:classifiers":[
        {
            "category":"Freight",
            "type":"Transportation"
        }
    ],
    "sg:phone":"+1 408 782 8883",
    "sg:postcode":"95037",
    "sg:province":"CA",
    "sg:tags":[
        "general"
    ],
    "sg:website":"www.cochranestorage.com",
    "wof:name":"Cochrane Road Self Storage",
    "wof:placetype":"venue"
},
  "geometry": {"coordinates":[-121.65952299999999,37.148943],"type":"Point"}
}