{
  "type": "Feature",
  "properties": {
    "addr:full":"650 Canyon Oaks Dr Oakland CA 94605",
    "addr:housenumber":"650",
    "addr:postcode":"94605",
    "addr:street":"Canyon Oaks Dr",
    "iso:country":"US",
    "sg:address":"650 Canyon Oaks Dr",
    "sg:city":"Oakland",
    "sg:classifiers":[
        {
            "category":"Shopping",
            "subcategory":"Gifts & Souvenirs",
            "type":"Retail Goods"
        }
    ],
    "sg:phone":"+1 510 569 2435",
    "sg:postcode":"94605",
    "sg:province":"CA",
    "sg:tags":[
        "shop"
    ],
    "wof:name":"Anpu Gifts",
    "wof:placetype":"venue"
},
  "geometry": {"coordinates":[-122.145888,37.773721],"type":"Point"}
}