{
  "type": "Feature",
  "properties": {
    "iso:country":"US",
    "sg:address":"1424 4th St",
    "sg:city":"Santa Monica",
    "sg:classifiers":[
        {
            "category":"Real Estate",
            "subcategory":"Architect",
            "type":"Services"
        }
    ],
    "sg:phone":"+1 310 394 3500",
    "sg:postcode":"90401",
    "sg:province":"CA",
    "wof:name":"Bielski Ladowicz Architects",
    "wof:placetype":"venue"
},
  "geometry": {"coordinates":[-118.493965,34.015352],"type":"Point"}
}