{
  "type": "Feature",
  "properties": {
    "iso:country":"US",
    "sg:address":"2179 Via Teca",
    "sg:city":"San Clemente",
    "sg:phone":"+1 949 498 9494",
    "sg:postcode":"92673",
    "sg:province":"CA",
    "sg:tags":[
        "leather"
    ],
    "wof:name":"Perceptions By Janet",
    "wof:placetype":"venue"
},
  "geometry": {"coordinates":[-117.623504,33.445416],"type":"Point"}
}