{
  "type": "Feature",
  "properties": {
    "addr:full":"665 Sanitarium Rd Deer Park CA 94576",
    "addr:housenumber":"665",
    "addr:postcode":"94576",
    "addr:street":"Sanitarium Rd",
    "iso:country":"US",
    "sg:address":"665 Sanitarium Rd",
    "sg:city":"Deer Park",
    "sg:classifiers":[
        {
            "category":"Health Services",
            "subcategory":"Doctor",
            "type":"Services"
        }
    ],
    "sg:phone":"+1 707 963 6300",
    "sg:postcode":"94576",
    "sg:province":"CA",
    "sg:tags":[
        "physician",
        "surgeon"
    ],
    "wof:name":"St Helena Hospital",
    "wof:placetype":"venue"
},
  "geometry": {"coordinates":[-122.47599099999999,38.543948],"type":"Point"}
}