{
  "type": "Feature",
  "properties": {
    "iso:country":"US",
    "sg:address":"2033 Arden Way",
    "sg:city":"Sacramento",
    "sg:classifiers":[
        {
            "category":"Personal",
            "subcategory":"Tanning Parlor",
            "type":"Services"
        }
    ],
    "sg:phone":"+1 916 922 7400",
    "sg:postcode":"95825",
    "sg:province":"CA",
    "sg:website":"www.amazingtans.com",
    "wof:name":"Amazing Tans",
    "wof:placetype":"venue"
},
  "geometry": {"coordinates":[-121.41848400000001,38.597112],"type":"Point"}
}