{
  "type": "Feature",
  "properties": {
    "addr:full":"1220 N St Sacramento CA 95814",
    "addr:housenumber":"1220",
    "addr:postcode":"95814",
    "addr:street":"N St",
    "iso:country":"US",
    "sg:address":"1220 N St",
    "sg:city":"Sacramento",
    "sg:classifiers":[
        {
            "category":"Restaurant",
            "type":"Food & Drink"
        }
    ],
    "sg:postcode":"95814",
    "sg:province":"CA",
    "wof:name":"Buy California Bistro",
    "wof:placetype":"venue"
},
  "geometry": {"coordinates":[-121.492384,38.575011],"type":"Point"}
}