{
  "type": "Feature",
  "properties": {
    "addr:full":"8647 S Sepulveda Blvd Los Angeles CA 90045",
    "addr:housenumber":"8647",
    "addr:postcode":"90045",
    "addr:street":"S Sepulveda Blvd",
    "iso:country":"US",
    "sg:address":"8647 S Sepulveda Blvd",
    "sg:city":"Los Angeles",
    "sg:classifiers":[
        {
            "category":"Food & Beverages",
            "subcategory":"Bakery",
            "type":"Retail Goods"
        },
        {
            "category":"Bakery",
            "type":"Food & Drink"
        }
    ],
    "sg:phone":"+1 310 641 9200",
    "sg:postcode":"90045",
    "sg:province":"CA",
    "sg:tags":[
        "sandwich"
    ],
    "sg:website":"www.panera.com/",
    "wof:name":"Panera Bread",
    "wof:placetype":"venue"
},
  "geometry": {"coordinates":[-118.39631799999999,33.958565],"type":"Point"}
}