{
  "type": "Feature",
  "properties": {
    "iso:country":"US",
    "sg:address":"217 W E St",
    "sg:city":"Brawley",
    "sg:classifiers":[
        {
            "category":"Farming",
            "subcategory":"Farm & Veterinary Services",
            "type":"Manufacturing & Wholesale Goods"
        }
    ],
    "sg:phone":"+1 760 344 0846",
    "sg:postcode":"92227",
    "sg:province":"CA",
    "sg:tags":[
        "aerial",
        "applicator"
    ],
    "wof:name":"Chaparral Applicators",
    "wof:placetype":"venue"
},
  "geometry": {"coordinates":[-115.54768199999999,32.979869],"type":"Point"}
}