{
  "type": "Feature",
  "properties": {
    "addr:full":"2330 Rainbow Avenue Sacramento CA 95821",
    "addr:housenumber":"2330",
    "addr:postcode":"95821",
    "addr:street":"Rainbow Avenue",
    "iso:country":"US",
    "sg:address":"2330 Rainbow Avenue",
    "sg:city":"Sacramento",
    "sg:classifiers":[
        {
            "category":"Building & Trades",
            "subcategory":"Construction",
            "type":"Services"
        }
    ],
    "sg:phone":"+1 916 284 6843",
    "sg:postcode":"95821",
    "sg:province":"CA",
    "sg:tags":[
        "air",
        "heating",
        "conditioning/hvac"
    ],
    "wof:name":"Performance Plus Heating & Air Conditioning",
    "wof:placetype":"venue"
},
  "geometry": {"coordinates":[-121.409431,38.619083],"type":"Point"}
}