{
  "type": "Feature",
  "properties": {
    "iso:country":"US",
    "sg:address":"2943 E Garnet Ln",
    "sg:city":"Orange",
    "sg:classifiers":[
        {
            "category":"Shopping",
            "type":"Retail Goods"
        }
    ],
    "sg:phone":"+1 714 532 4532",
    "sg:postcode":"92869",
    "sg:province":"CA",
    "sg:tags":[
        "merchandise"
    ],
    "wof:name":"Play N Things Co",
    "wof:placetype":"venue"
},
  "geometry": {"coordinates":[-117.821889,33.776463],"type":"Point"}
}