{
  "type": "Feature",
  "properties": {
    "addr:full":"14845 Jeffrey Road Irvine CA 92618",
    "addr:housenumber":"14845",
    "addr:postcode":"92618",
    "addr:street":"Jeffrey Road",
    "iso:country":"US",
    "sg:address":"14845 Jeffrey Road",
    "sg:city":"Irvine",
    "sg:classifiers":[
        {
            "category":"Banks & Credit Unions",
            "subcategory":"Bank",
            "type":"Services"
        }
    ],
    "sg:phone":"+1 949 733 8818",
    "sg:postcode":"92618",
    "sg:province":"CA",
    "wof:name":"East West Bank Br 68",
    "wof:placetype":"venue"
},
  "geometry": {"coordinates":[-117.771432,33.686805],"type":"Point"}
}