{
  "type": "Feature",
  "properties": {
    "iso:country":"US",
    "sg:address":"3189 Cam del Zuro",
    "sg:city":"Thousand Oaks",
    "sg:classifiers":[
        {
            "category":"Shopping",
            "subcategory":"Computers & Home Electronics",
            "type":"Retail Goods"
        }
    ],
    "sg:phone":"+1 805 492 6306",
    "sg:postcode":"91360",
    "sg:province":"CA",
    "sg:tags":[
        "equipment",
        "dealer"
    ],
    "wof:name":"Aztec Data Supply",
    "wof:placetype":"venue"
},
  "geometry": {"coordinates":[-118.860334,34.222929],"type":"Point"}
}