{
  "type": "Feature",
  "properties": {
    "iso:country":"US",
    "sg:address":"1015 Anderson St",
    "sg:city":"Red Bluff",
    "sg:classifiers":[
        {
            "category":"Manufacturing",
            "subcategory":"Rubber & Plastics",
            "type":"Manufacturing & Wholesale Goods"
        }
    ],
    "sg:phone":"+1 530 528 1299",
    "sg:postcode":"96080",
    "sg:province":"CA",
    "sg:tags":[
        "product",
        "mfg"
    ],
    "wof:name":"Camelot Plastics Inc",
    "wof:placetype":"venue"
},
  "geometry": {"coordinates":[-122.241839,40.152051],"type":"Point"}
}