{
  "type": "Feature",
  "properties": {
    "addr:full":"87 Yosemite Rd San Rafael CA 94903",
    "addr:housenumber":"87",
    "addr:postcode":"94903",
    "addr:street":"Yosemite Rd",
    "iso:country":"US",
    "sg:address":"87 Yosemite Rd",
    "sg:city":"San Rafael",
    "sg:classifiers":[
        {
            "category":"Shopping",
            "subcategory":"Music",
            "type":"Retail Goods"
        }
    ],
    "sg:phone":"+1 415 499 5605",
    "sg:postcode":"94903",
    "sg:province":"CA",
    "sg:tags":[
        "compact",
        "record",
        "disc",
        "tape"
    ],
    "wof:name":"Tapes By Tricia",
    "wof:placetype":"venue"
},
  "geometry": {"coordinates":[-122.53028,38.010329],"type":"Point"}
}