{
  "type": "Feature",
  "properties": {
    "addr:full":"3455 Homestead Rd Santa Clara CA 95051",
    "addr:housenumber":"3455",
    "addr:postcode":"95051",
    "addr:street":"Homestead Rd",
    "iso:country":"US",
    "sg:address":"3455 Homestead Rd",
    "sg:city":"Santa Clara",
    "sg:classifiers":[
        {
            "category":"Wholesale",
            "subcategory":"Home Furnishings",
            "type":"Manufacturing & Wholesale Goods"
        }
    ],
    "sg:phone":"+1 408 554 5812",
    "sg:postcode":"95051",
    "sg:province":"CA",
    "wof:name":"Blue Oceans",
    "wof:placetype":"venue"
},
  "geometry": {"coordinates":[-121.991713,37.337948],"type":"Point"}
}