{
  "type": "Feature",
  "properties": {
    "iso:country":"US",
    "sg:address":"2370 Telegraph Ave",
    "sg:city":"Oakland",
    "sg:classifiers":[
        {
            "category":"Wholesale",
            "subcategory":"Non-durable Goods",
            "type":"Manufacturing & Wholesale Goods"
        }
    ],
    "sg:phone":"+1 510 986 0910",
    "sg:postcode":"94612",
    "sg:province":"CA",
    "wof:name":"Merchant Group",
    "wof:placetype":"venue"
},
  "geometry": {"coordinates":[-122.268553,37.813704],"type":"Point"}
}