{
  "type": "Feature",
  "properties": {
    "iso:country":"US",
    "sg:address":"564 el camino real",
    "sg:city":"Belmont",
    "sg:classifiers":[
        {
            "category":"Autos & Motor Vehicles",
            "subcategory":"Automobile Sales",
            "type":"Retail Goods"
        },
        {
            "category":"Autos & Motor Vehicles",
            "subcategory":"Auto Supplies",
            "type":"Retail Goods"
        },
        {
            "category":"Retail",
            "subcategory":"Auto Repair",
            "type":"Services"
        }
    ],
    "sg:phone":"+1 650 592 9932",
    "sg:postcode":"94002",
    "sg:province":"CA",
    "sg:tags":[
        "wheel",
        "automotive",
        "tire"
    ],
    "wof:name":"belmont tires wheels and service",
    "wof:placetype":"venue"
},
  "geometry": {"coordinates":[-122.28076,37.523855],"type":"Point"}
}