{
  "type": "Feature",
  "properties": {
    "iso:country":"US",
    "sg:address":"14265 Van Nuys Blvd # 83",
    "sg:city":"Arleta",
    "sg:classifiers":[
        {
            "category":"Recreation",
            "subcategory":"Picnic Area",
            "type":"Entertainment"
        },
        {
            "category":"Community Center",
            "type":"Public Place"
        }
    ],
    "sg:phone":"+1 818 302 6695",
    "sg:postcode":"91331",
    "sg:province":"CA",
    "sg:tags":[
        "amusement",
        "arcade"
    ],
    "wof:name":"Tournament Grounds",
    "wof:placetype":"venue"
},
  "geometry": {"coordinates":[-118.444023,34.25012],"type":"Point"}
}