{
  "type": "Feature",
  "properties": {
    "addr:full":"800 N Anaheim Blvd Anaheim CA 92805",
    "addr:housenumber":"800",
    "addr:postcode":"92805",
    "addr:street":"N Anaheim Blvd",
    "iso:country":"US",
    "sg:address":"800 N Anaheim Blvd",
    "sg:city":"Anaheim",
    "sg:classifiers":[
        {
            "category":"Food & Beverages",
            "subcategory":"Liquor & Beverages",
            "type":"Retail Goods"
        }
    ],
    "sg:phone":"+1 714 991 4471",
    "sg:postcode":"92805",
    "sg:province":"CA",
    "sg:tags":[
        "beer",
        "spirit",
        "wine"
    ],
    "wof:name":"Brook House Liquors",
    "wof:placetype":"venue"
},
  "geometry": {"coordinates":[-117.917,33.844501],"type":"Point"}
}