{
  "type": "Feature",
  "properties": {
    "addr:full":"3392 East Ter Lafayette CA 94549",
    "addr:housenumber":"3392",
    "addr:postcode":"94549",
    "addr:street":"East Ter",
    "iso:country":"US",
    "sg:address":"3392 East Ter",
    "sg:city":"Lafayette",
    "sg:classifiers":[
        {
            "category":"Health Services",
            "subcategory":"Doctor",
            "type":"Services"
        }
    ],
    "sg:phone":"+1 707 372 1528",
    "sg:postcode":"94549",
    "sg:province":"CA",
    "sg:tags":[
        "gynecology",
        "physician",
        "surgeons",
        "obstetrics"
    ],
    "wof:name":"Homayoon Etemadi",
    "wof:placetype":"venue"
},
  "geometry": {"coordinates":[-122.109042,37.880013],"type":"Point"}
}