{
  "type": "Feature",
  "properties": {
    "addr:full":"2450 Foothill Blvd Calistoga CA 94515",
    "addr:housenumber":"2450",
    "addr:postcode":"94515",
    "addr:street":"Foothill Blvd",
    "iso:country":"US",
    "sg:address":"2450 Foothill Blvd",
    "sg:city":"Calistoga",
    "sg:classifiers":[
        {
            "category":"Professional",
            "subcategory":"Accounting & Tax Preparation",
            "type":"Services"
        }
    ],
    "sg:phone":"+1 707 942 6228",
    "sg:postcode":"94515",
    "sg:province":"CA",
    "sg:tags":[
        "bookkeeping",
        "general"
    ],
    "wof:name":"D Jean Jarvis Bookkeeping Svc",
    "wof:placetype":"venue"
},
  "geometry": {"coordinates":[-122.59632499999999,38.581315],"type":"Point"}
}