{
  "type": "Feature",
  "properties": {
    "iso:country":"US",
    "sg:address":"25828 Redlands Blvd",
    "sg:city":"Redlands",
    "sg:classifiers":[
        {
            "category":"Health Services",
            "subcategory":"Doctor",
            "type":"Services"
        }
    ],
    "sg:phone":"+1 909 799 5308",
    "sg:postcode":"92373",
    "sg:province":"CA",
    "sg:tags":[
        "physician",
        "surgeon"
    ],
    "wof:name":"Kaiser Permenente Hosp Clinic",
    "wof:placetype":"venue"
},
  "geometry": {"coordinates":[-117.243598,34.063128],"type":"Point"}
}