{
  "type": "Feature",
  "properties": {
    "iso:country":"US",
    "sg:address":"318 Stealth Ct",
    "sg:city":"Livermore",
    "sg:classifiers":[
        {
            "category":"Manufacturing",
            "subcategory":"Tools & Machinery",
            "type":"Manufacturing & Wholesale Goods"
        },
        {
            "category":"Wholesale",
            "subcategory":"Machinery & Supplies",
            "type":"Manufacturing & Wholesale Goods"
        },
        {
            "category":"Building & Trades",
            "subcategory":"Equipment Rental",
            "type":"Services"
        }
    ],
    "sg:phone":"+1 888 537 9208",
    "sg:postcode":"94551",
    "sg:province":"CA",
    "sg:tags":[
        "construction",
        "industrial",
        "contractors'"
    ],
    "sg:website":"http://www.crescorent.com",
    "wof:name":"Cresco Equipment Rentals",
    "wof:placetype":"venue"
},
  "geometry": {"coordinates":[-121.797388,37.696226],"type":"Point"}
}