{
  "type": "Feature",
  "properties": {
    "addr:full":"25250 Madison Ave Murrieta CA 92562",
    "addr:housenumber":"25250",
    "addr:postcode":"92562",
    "addr:street":"Madison Ave",
    "iso:country":"US",
    "sg:address":"25250 Madison Ave",
    "sg:city":"Murrieta",
    "sg:classifiers":[
        {
            "category":"Restaurant",
            "type":"Food & Drink"
        }
    ],
    "sg:menulink":"http://www.allmenus.com/ca/murrieta/164374-wienerschnitzel/menu/",
    "sg:phone":"+1 951 461 9697",
    "sg:postcode":"92562",
    "sg:province":"CA",
    "sg:tags":[
        "sandwich",
        "dog",
        "burger",
        "hot",
        "wrap",
        "american"
    ],
    "wof:name":"Wienerschnitzel",
    "wof:placetype":"venue"
},
  "geometry": {"coordinates":[-117.19771,33.555305],"type":"Point"}
}