{
  "type": "Feature",
  "properties": {
    "iso:country":"US",
    "sg:address":"27680 Marguerite Pkwy Ste A",
    "sg:city":"Mission Viejo",
    "sg:classifiers":[
        {
            "category":"Food & Beverages",
            "subcategory":"Bakery",
            "type":"Retail Goods"
        }
    ],
    "sg:phone":"+1 949 347 9057",
    "sg:postcode":"92692",
    "sg:province":"CA",
    "sg:tags":[
        "sandwich"
    ],
    "sg:website":"www.subway.com/",
    "wof:name":"Subway",
    "wof:placetype":"venue"
},
  "geometry": {"coordinates":[-117.657973,33.561983],"type":"Point"}
}