{
  "type": "Feature",
  "properties": {
    "addr:full":"1965 Market St San Francisco CA 94103",
    "addr:housenumber":"1965",
    "addr:postcode":"94103",
    "addr:street":"Market St",
    "iso:country":"US",
    "sg:address":"1965 Market St",
    "sg:city":"San Francisco",
    "sg:classifiers":[
        {
            "category":"Banks & Credit Unions",
            "subcategory":"Financial Services",
            "type":"Services"
        }
    ],
    "sg:phone":"+1 415 431 5331",
    "sg:postcode":"94103",
    "sg:province":"CA",
    "sg:website":"www.hrblock.com",
    "wof:name":"H & R Block",
    "wof:placetype":"venue"
},
  "geometry": {"coordinates":[-122.42600299999999,37.7696],"type":"Point"}
}