{
  "type": "Feature",
  "properties": {
    "addr:full":"957 W Alisal St Salinas CA 93901",
    "addr:housenumber":"957",
    "addr:postcode":"93901",
    "addr:street":"W Alisal St",
    "iso:country":"US",
    "sg:address":"957 W Alisal St",
    "sg:city":"Salinas",
    "sg:classifiers":[
        {
            "category":"Restaurant",
            "type":"Food & Drink"
        }
    ],
    "sg:phone":"+1 831 753 1798",
    "sg:postcode":"93901",
    "sg:province":"CA",
    "wof:name":"El Farro Taqueria",
    "wof:placetype":"venue"
},
  "geometry": {"coordinates":[-121.674177,36.668216],"type":"Point"}
}