{
  "type": "Feature",
  "properties": {
    "iso:country":"US",
    "sg:address":"635 E 14th St",
    "sg:city":"San Leandro",
    "sg:classifiers":[
        {
            "category":"Food & Beverages",
            "subcategory":"Ethnic Foods",
            "type":"Retail Goods"
        }
    ],
    "sg:phone":"+1 510 878 2355",
    "sg:postcode":"94577",
    "sg:province":"CA",
    "sg:tags":[
        "soul"
    ],
    "wof:name":"House of Soul Food",
    "wof:placetype":"venue"
},
  "geometry": {"coordinates":[-122.16052000000001,37.730435],"type":"Point"}
}