{
  "type": "Feature",
  "properties": {
    "addr:full":"8356 Topanga Canyon Blvd Canoga Park CA 91304",
    "addr:housenumber":"8356",
    "addr:postcode":"91304",
    "addr:street":"Topanga Canyon Blvd",
    "iso:country":"US",
    "sg:address":"8356 Topanga Canyon Blvd",
    "sg:city":"Canoga Park",
    "sg:classifiers":[
        {
            "category":"Food & Beverages",
            "subcategory":"Liquor & Beverages",
            "type":"Retail Goods"
        }
    ],
    "sg:phone":"+1 818 340 3929",
    "sg:postcode":"91304",
    "sg:province":"CA",
    "sg:tags":[
        "beer",
        "spirit",
        "wine"
    ],
    "wof:name":"Tally-Ho Liquor",
    "wof:placetype":"venue"
},
  "geometry": {"coordinates":[-118.606003,34.220501],"type":"Point"}
}