{
  "type": "Feature",
  "properties": {
    "addr:full":"5831 Huntington Ave Richmond CA 94804",
    "addr:housenumber":"5831",
    "addr:postcode":"94804",
    "addr:street":"Huntington Ave",
    "iso:country":"US",
    "sg:address":"5831 Huntington Ave",
    "sg:city":"Richmond",
    "sg:classifiers":[
        {
            "category":"Building & Trades",
            "subcategory":"Plumbing",
            "type":"Services"
        }
    ],
    "sg:phone":"+1 510 524 1220",
    "sg:postcode":"94804",
    "sg:province":"CA",
    "wof:name":"Nova Engineering",
    "wof:placetype":"venue"
},
  "geometry": {"coordinates":[-122.30999799999999,37.907299],"type":"Point"}
}