{
  "type": "Feature",
  "properties": {
    "iso:country":"US",
    "sg:address":"901 Bay Shore Blvd",
    "sg:city":"San Francisco",
    "sg:classifiers":[
        {
            "category":"Wholesale",
            "subcategory":"Furniture",
            "type":"Manufacturing & Wholesale Goods"
        }
    ],
    "sg:phone":"+1 415 467 8188",
    "sg:postcode":"94124",
    "sg:province":"CA",
    "sg:tags":[
        "bathroom",
        "fixture",
        "accessory"
    ],
    "wof:name":"Eaststar Building Supply Co",
    "wof:placetype":"venue"
},
  "geometry": {"coordinates":[-122.4034,37.730658],"type":"Point"}
}