{
  "type": "Feature",
  "properties": {
    "iso:country":"US",
    "sg:address":"2000 Van Ness Ave Ste 608 Suite 475",
    "sg:city":"San Francisco",
    "sg:classifiers":[
        {
            "category":"Professional",
            "subcategory":"Employment Agencies",
            "type":"Services"
        }
    ],
    "sg:phone":"+1 415 885 1534",
    "sg:postcode":"94109",
    "sg:province":"CA",
    "wof:name":"Med Staff Healthcare Solutions",
    "wof:placetype":"venue"
},
  "geometry": {"coordinates":[-122.422662,37.794173],"type":"Point"}
}