{
  "type": "Feature",
  "properties": {
    "iso:country":"US",
    "sg:address":"2085 W Ave 140th",
    "sg:city":"San Leandro",
    "sg:classifiers":[
        {
            "category":"Freight",
            "type":"Transportation"
        }
    ],
    "sg:phone":"+1 510 614 4300",
    "sg:postcode":"94577",
    "sg:province":"CA",
    "sg:tags":[
        "warehouse",
        "facility"
    ],
    "wof:name":"R D Kincaide Inc",
    "wof:placetype":"venue"
},
  "geometry": {"coordinates":[-122.166427,37.701096],"type":"Point"}
}