{
  "type": "Feature",
  "properties": {
    "addr:full":"3330 Portola Dr Santa Cruz CA 95062",
    "addr:housenumber":"3330",
    "addr:postcode":"95062",
    "addr:street":"Portola Dr",
    "iso:country":"US",
    "sg:address":"3330 Portola Dr",
    "sg:city":"Santa Cruz",
    "sg:classifiers":[
        {
            "category":"Health Services",
            "subcategory":"Doctor",
            "type":"Services"
        }
    ],
    "sg:phone":"+1 831 476 1541",
    "sg:postcode":"95062",
    "sg:province":"CA",
    "sg:tags":[
        "dentist"
    ],
    "wof:name":"Yien & Yien",
    "wof:placetype":"venue"
},
  "geometry": {"coordinates":[-121.97084,36.963364],"type":"Point"}
}