{
  "type": "Feature",
  "properties": {
    "addr:full":"1332 de la Vina St Santa Barbara CA 93101",
    "addr:housenumber":"1332",
    "addr:postcode":"93101",
    "addr:street":"De La Vina St",
    "iso:country":"US",
    "sg:address":"1332 de la Vina St",
    "sg:city":"Santa Barbara",
    "sg:classifiers":[
        {
            "category":"Professional",
            "subcategory":"Accounting & Tax Preparation",
            "type":"Services"
        }
    ],
    "sg:phone":"+1 805 966 0201",
    "sg:postcode":"93101",
    "sg:province":"CA",
    "sg:tags":[
        "payroll"
    ],
    "wof:name":"Joseph P Kennedy & Assoc",
    "wof:placetype":"venue"
},
  "geometry": {"coordinates":[-119.708882,34.422844],"type":"Point"}
}