{
  "type": "Feature",
  "properties": {
    "addr:full":"3290 Carlsbad Blvd Carlsbad CA 92008",
    "addr:housenumber":"3290",
    "addr:postcode":"92008",
    "addr:street":"Carlsbad Blvd",
    "iso:country":"US",
    "sg:address":"3290 Carlsbad Blvd",
    "sg:city":"Carlsbad",
    "sg:classifiers":[
        {
            "category":"Restaurant",
            "type":"Food & Drink"
        }
    ],
    "sg:phone":"+1 760 434 6000",
    "sg:postcode":"92008",
    "sg:province":"CA",
    "sg:tags":[
        "steakhouse"
    ],
    "sg:website":"www.dinisbistro.com/",
    "wof:name":"Dini's by the Sea",
    "wof:placetype":"venue"
},
  "geometry": {"coordinates":[-117.35022600000001,33.154015],"type":"Point"}
}