{
  "type": "Feature",
  "properties": {
    "iso:country":"US",
    "sg:address":"4456 Black Ave",
    "sg:city":"Pleasanton",
    "sg:classifiers":[
        {
            "category":"Building & Trades",
            "subcategory":"Construction",
            "type":"Services"
        }
    ],
    "sg:phone":"+1 925 417 8750",
    "sg:postcode":"94566",
    "sg:province":"CA",
    "sg:tags":[
        "contractor"
    ],
    "wof:name":"Westbrook Development",
    "wof:placetype":"venue"
},
  "geometry": {"coordinates":[-121.877154,37.672121],"type":"Point"}
}