{
  "type": "Feature",
  "properties": {
    "addr:full":"12240 Venice Blvd Los Angeles CA 90066",
    "addr:housenumber":"12240",
    "addr:postcode":"90066",
    "addr:street":"Venice Blvd",
    "iso:country":"US",
    "sg:address":"12240 Venice Blvd",
    "sg:city":"Los Angeles",
    "sg:classifiers":[
        {
            "category":"Building & Trades",
            "subcategory":"Construction",
            "type":"Services"
        }
    ],
    "sg:phone":"+1 310 397 0644",
    "sg:postcode":"90066",
    "sg:province":"CA",
    "sg:tags":[
        "contractor"
    ],
    "wof:name":"Steve Morris Construction",
    "wof:placetype":"venue"
},
  "geometry": {"coordinates":[-118.431659,34.004562],"type":"Point"}
}