{
  "type": "Feature",
  "properties": {
    "addr:full":"2114 Pico Blvd Santa Monica CA 90405",
    "addr:housenumber":"2114",
    "addr:postcode":"90405",
    "addr:street":"Pico Blvd",
    "iso:country":"US",
    "sg:address":"2114 Pico Blvd",
    "sg:city":"Santa Monica",
    "sg:classifiers":[
        {
            "category":"Communications",
            "subcategory":"Film & Video Production",
            "type":"Services"
        }
    ],
    "sg:phone":"+1 310 392 6392",
    "sg:postcode":"90405",
    "sg:province":"CA",
    "sg:tags":[
        "motion",
        "picture",
        "sound"
    ],
    "wof:name":"Dewey Warren Sound Design Std",
    "wof:placetype":"venue"
},
  "geometry": {"coordinates":[-118.467558,34.020341],"type":"Point"}
}