{
  "type": "Feature",
  "properties": {
    "iso:country":"US",
    "sg:address":"1379 Cll Crisantemo",
    "sg:city":"Thousand Oaks",
    "sg:classifiers":[
        {
            "category":"Home & Garden",
            "subcategory":"Home Furnishings",
            "type":"Retail Goods"
        }
    ],
    "sg:phone":"+1 805 492 5678",
    "sg:postcode":"91360",
    "sg:province":"CA",
    "sg:tags":[
        "venetian",
        "blind"
    ],
    "wof:name":"Brighter Blind Cleaning",
    "wof:placetype":"venue"
},
  "geometry": {"coordinates":[-118.855836,34.210867],"type":"Point"}
}