{
  "type": "Feature",
  "properties": {
    "addr:full":"4614 Maleza Pl Tarzana CA 91356",
    "addr:housenumber":"4614",
    "addr:postcode":"91356",
    "addr:street":"Maleza Pl",
    "iso:country":"US",
    "sg:address":"4614 Maleza Pl",
    "sg:city":"Tarzana",
    "sg:classifiers":[
        {
            "category":"Professional",
            "subcategory":"Art Services",
            "type":"Services"
        }
    ],
    "sg:phone":"+1 818 344 3536",
    "sg:postcode":"91356",
    "sg:province":"CA",
    "sg:tags":[
        "designer",
        "display",
        "producer"
    ],
    "wof:name":"Kitty Curcio Designs",
    "wof:placetype":"venue"
},
  "geometry": {"coordinates":[-118.54659599999999,34.153784],"type":"Point"}
}