{
  "type": "Feature",
  "properties": {
    "iso:country":"US",
    "sg:address":"1565 Alvarado St",
    "sg:city":"San Leandro",
    "sg:classifiers":[
        {
            "category":"Wholesale",
            "subcategory":"Machinery & Supplies",
            "type":"Manufacturing & Wholesale Goods"
        }
    ],
    "sg:phone":"+1 510 678 3451",
    "sg:postcode":"94577",
    "sg:province":"CA",
    "sg:tags":[
        "machine",
        "tool"
    ],
    "sg:website":"www.performancemachinetools.com",
    "wof:name":"Performance Machine Tools",
    "wof:placetype":"venue"
},
  "geometry": {"coordinates":[-122.161762,37.71981],"type":"Point"}
}