{
  "type": "Feature",
  "properties": {
    "addr:full":"1738 W River Ave Porterville CA 93257",
    "addr:housenumber":"1738",
    "addr:postcode":"93257",
    "addr:street":"W River Ave",
    "iso:country":"US",
    "sg:address":"1738 W River Ave",
    "sg:city":"Porterville",
    "sg:classifiers":[
        {
            "category":"Building & Trades",
            "subcategory":"Construction",
            "type":"Services"
        }
    ],
    "sg:phone":"+1 559 789 9557",
    "sg:postcode":"93257",
    "sg:province":"CA",
    "sg:tags":[
        "contractor"
    ],
    "wof:name":"J Brooke Roofing",
    "wof:placetype":"venue"
},
  "geometry": {"coordinates":[-119.05642,36.056852],"type":"Point"}
}