{
  "type": "Feature",
  "properties": {
    "iso:country":"US",
    "sg:address":"1738 W River Ave",
    "sg:city":"Porterville",
    "sg:classifiers":[
        {
            "category":"Building & Trades",
            "subcategory":"Construction",
            "type":"Services"
        }
    ],
    "sg:phone":"+1 559 789 9557",
    "sg:postcode":"93257",
    "sg:province":"CA",
    "sg:tags":[
        "contractor"
    ],
    "wof:name":"J Brooke Roofing",
    "wof:placetype":"venue"
},
  "geometry": {"coordinates":[-119.05642,36.056852],"type":"Point"}
}