{
  "type": "Feature",
  "properties": {
    "addr:full":"21 Duffy Pl San Rafael CA 94901",
    "addr:housenumber":"21",
    "addr:postcode":"94901",
    "addr:street":"Duffy Pl",
    "iso:country":"US",
    "sg:address":"21 Duffy Pl",
    "sg:city":"San Rafael",
    "sg:classifiers":[
        {
            "category":"Building & Trades",
            "subcategory":"Construction",
            "type":"Services"
        }
    ],
    "sg:phone":"+1 415 458 8011",
    "sg:postcode":"94901",
    "sg:province":"CA",
    "sg:tags":[
        "maker",
        "cabinet"
    ],
    "wof:name":"I K Design Inc",
    "wof:placetype":"venue"
},
  "geometry": {"coordinates":[-122.52313700000001,37.967667],"type":"Point"}
}