{
  "type": "Feature",
  "properties": {
    "iso:country":"US",
    "sg:address":"846 Portola Rd",
    "sg:city":"Portola Valley",
    "sg:classifiers":[
        {
            "category":"Professional",
            "subcategory":"Art Services",
            "type":"Services"
        }
    ],
    "sg:phone":"+1 650 851 8584",
    "sg:postcode":"94028",
    "sg:province":"CA",
    "sg:tags":[
        "graphic",
        "designer"
    ],
    "sg:website":"www.ritualhut.com",
    "wof:name":"Karen Olsen Design",
    "wof:placetype":"venue"
},
  "geometry": {"coordinates":[-122.231722,37.382979],"type":"Point"}
}