{
  "type": "Feature",
  "properties": {
    "iso:country":"US",
    "sg:address":"970 Monterey St",
    "sg:city":"San Luis Obispo",
    "sg:classifiers":[
        {
            "category":"Utilities",
            "subcategory":"Refuse",
            "type":"Services"
        }
    ],
    "sg:phone":"+1 805 543 0473",
    "sg:postcode":"93401",
    "sg:province":"CA",
    "sg:tags":[
        "leasing",
        "container",
        "including",
        "roll",
        "garbage"
    ],
    "wof:name":"Coastal Rolloff Service",
    "wof:placetype":"venue"
},
  "geometry": {"coordinates":[-120.661463,35.281771],"type":"Point"}
}