{
  "type": "Feature",
  "properties": {
    "addr:full":"7434 Mesa College Drive San Diego CA 92111",
    "addr:housenumber":"7434",
    "addr:postcode":"92111",
    "addr:street":"Mesa College Drive",
    "iso:country":"US",
    "sg:address":"7434 Mesa College Drive",
    "sg:city":"San Diego",
    "sg:classifiers":[
        {
            "category":"Real Estate",
            "subcategory":"Real Estate Operator",
            "type":"Services"
        }
    ],
    "sg:phone":"+1 858 576 6396",
    "sg:postcode":"92111",
    "sg:province":"CA",
    "sg:tags":[
        "apartment"
    ],
    "wof:name":"Parkridge Manor Apartments",
    "wof:placetype":"venue"
},
  "geometry": {"coordinates":[-117.160849,32.802009],"type":"Point"}
}