{
  "type": "Feature",
  "properties": {
    "addr:full":"15488 S Western Avenue Gardena CA 90249",
    "addr:housenumber":"15488",
    "addr:postcode":"90249",
    "addr:street":"S Western Avenue",
    "iso:country":"US",
    "sg:address":"15488 S Western Avenue",
    "sg:city":"Gardena",
    "sg:classifiers":[
        {
            "category":"Cinema",
            "subcategory":"Movie Rental",
            "type":"Entertainment"
        }
    ],
    "sg:phone":"+1 310 327 5811",
    "sg:postcode":"90249",
    "sg:province":"CA",
    "sg:tags":[
        "game",
        "video"
    ],
    "wof:name":"Video Japan",
    "wof:placetype":"venue"
},
  "geometry": {"coordinates":[-118.309276,33.890339],"type":"Point"}
}