{
  "type": "Feature",
  "properties": {
    "iso:country":"US",
    "sg:address":"3225 Hunter St",
    "sg:city":"Los Angeles",
    "sg:classifiers":[
        {
            "category":"Education",
            "subcategory":"School",
            "type":"Public Place"
        }
    ],
    "sg:phone":"+1 323 881 9591",
    "sg:postcode":"90023",
    "sg:province":"CA",
    "wof:name":"S E A Charter School",
    "wof:placetype":"venue"
},
  "geometry": {"coordinates":[-118.208,34.021198],"type":"Point"}
}