{
  "type": "Feature",
  "properties": {
    "iso:country":"US",
    "sg:address":"920 S Capitol Ave",
    "sg:city":"San Jose",
    "sg:classifiers":[
        {
            "category":"Organizations",
            "subcategory":"Religious Organization",
            "type":"Services"
        }
    ],
    "sg:phone":"+1 408 251 1515",
    "sg:postcode":"95127",
    "sg:province":"CA",
    "wof:name":"Templo Juan 3-16 Inc",
    "wof:placetype":"venue"
},
  "geometry": {"coordinates":[-121.827003,37.3517],"type":"Point"}
}