{
  "type": "Feature",
  "properties": {
    "iso:country":"US",
    "sg:address":"10001 Pioneer Blvd",
    "sg:city":"Santa Fe Springs",
    "sg:classifiers":[
        {
            "category":"Wholesale",
            "subcategory":"Auto Parts",
            "type":"Manufacturing & Wholesale Goods"
        }
    ],
    "sg:phone":"+1 562 949 9494",
    "sg:postcode":"90670",
    "sg:province":"CA",
    "sg:tags":[
        "automobile",
        "supply"
    ],
    "wof:name":"Downey Off Road Mfg",
    "wof:placetype":"venue"
},
  "geometry": {"coordinates":[-118.079937,33.946774],"type":"Point"}
}