{
  "type": "Feature",
  "properties": {
    "iso:country":"US",
    "sg:address":"755 Herrick Ave",
    "sg:city":"Eureka",
    "sg:classifiers":[
        {
            "category":"Government",
            "subcategory":"Fire Station",
            "type":"Public Place"
        }
    ],
    "sg:phone":"+1 707 445 4902",
    "sg:postcode":"95503",
    "sg:province":"CA",
    "sg:tags":[
        "protection"
    ],
    "wof:name":"Humboldt Fire Prtctn Byview",
    "wof:placetype":"venue"
},
  "geometry": {"coordinates":[-124.179424,40.757596],"type":"Point"}
}