{
  "type": "Feature",
  "properties": {
    "iso:country":"US",
    "sg:address":"750 N Los Robles Ave",
    "sg:city":"Pasadena",
    "sg:classifiers":[
        {
            "category":"Education",
            "subcategory":"School",
            "type":"Public Place"
        }
    ],
    "sg:phone":"+1 626 795 8519",
    "sg:postcode":"91104",
    "sg:province":"CA",
    "wof:name":"Madison High West-Childrens",
    "wof:placetype":"venue"
},
  "geometry": {"coordinates":[-118.141458,34.158941],"type":"Point"}
}