{
  "type": "Feature",
  "properties": {
    "addr:full":"380 Industrial Rd San Carlos CA 94070",
    "addr:housenumber":"380",
    "addr:postcode":"94070",
    "addr:street":"Industrial Rd",
    "iso:country":"US",
    "sg:address":"380 Industrial Rd",
    "sg:city":"San Carlos",
    "sg:classifiers":[
        {
            "category":"Wholesale",
            "subcategory":"Hardware",
            "type":"Manufacturing & Wholesale Goods"
        }
    ],
    "sg:phone":"+1 650 592 0636",
    "sg:postcode":"94070",
    "sg:province":"CA",
    "sg:tags":[
        "plumbing",
        "fixture",
        "supply"
    ],
    "wof:name":"Crest Good Mfg Co",
    "wof:placetype":"venue"
},
  "geometry": {"coordinates":[-122.25934100000001,37.513015],"type":"Point"}
}