{
  "type": "Feature",
  "properties": {
    "iso:country":"US",
    "sg:address":"1025 Lone Palm Ave",
    "sg:city":"Modesto",
    "sg:classifiers":[
        {
            "category":"Building & Trades",
            "subcategory":"Plumbing",
            "type":"Services"
        }
    ],
    "sg:phone":"+1 209 527 5969",
    "sg:postcode":"95351",
    "sg:province":"CA",
    "sg:tags":[
        "plumber",
        "contractor"
    ],
    "wof:name":"Sesser And Johnson Plumbing",
    "wof:placetype":"venue"
},
  "geometry": {"coordinates":[-121.02339600000001,37.648873],"type":"Point"}
}