{
  "type": "Feature",
  "properties": {
    "addr:full":"2115 N Wilmington Ave Compton CA 90222",
    "addr:housenumber":"2115",
    "addr:postcode":"90222",
    "addr:street":"N Wilmington Ave",
    "iso:country":"US",
    "sg:address":"2115 N Wilmington Ave",
    "sg:city":"Compton",
    "sg:classifiers":[
        {
            "category":"Organizations",
            "subcategory":"Religious Organization",
            "type":"Services"
        }
    ],
    "sg:phone":"+1 310 639 9452",
    "sg:postcode":"90222",
    "sg:province":"CA",
    "sg:tags":[
        "church"
    ],
    "wof:name":"St Martin's Episcopal Church",
    "wof:placetype":"venue"
},
  "geometry": {"coordinates":[-118.239154,33.912129],"type":"Point"}
}