{
  "type": "Feature",
  "properties": {
    "iso:country":"US",
    "sg:address":"1638 Trinity St",
    "sg:city":"Los Angeles",
    "sg:classifiers":[
        {
            "category":"Shopping",
            "subcategory":"Crafts & Fabrics",
            "type":"Retail Goods"
        }
    ],
    "sg:phone":"+1 213 747 5795",
    "sg:postcode":"90015",
    "sg:province":"CA",
    "sg:tags":[
        "sewing"
    ],
    "wof:name":"Cristy Bias & Stitches",
    "wof:placetype":"venue"
},
  "geometry": {"coordinates":[-118.258921,34.028694],"type":"Point"}
}