{
  "type": "Feature",
  "properties": {
    "iso:country":"US",
    "sg:address":"16860 Joleen Way",
    "sg:city":"Morgan Hill",
    "sg:classifiers":[
        {
            "category":"Retail",
            "subcategory":"Auto Repair",
            "type":"Services"
        }
    ],
    "sg:phone":"+1 408 778 5035",
    "sg:postcode":"95037",
    "sg:province":"CA",
    "sg:tags":[
        "automobile",
        "smog"
    ],
    "wof:name":"TNT Smog",
    "wof:placetype":"venue"
},
  "geometry": {"coordinates":[-121.638144,37.128052],"type":"Point"}
}