{
  "type": "Feature",
  "properties": {
    "iso:country":"US",
    "sg:address":"36 Saint James Dr",
    "sg:city":"Santa Rosa",
    "sg:classifiers":[
        {
            "category":"Personal",
            "subcategory":"Beauty Salon",
            "type":"Services"
        }
    ],
    "sg:phone":"+1 707 535 0620",
    "sg:postcode":"95476",
    "sg:province":"CA",
    "wof:name":"Lewis Tussey 36 St James",
    "wof:placetype":"venue"
},
  "geometry": {"coordinates":[-122.48562800000001,38.261024],"type":"Point"}
}