{
  "type": "Feature",
  "properties": {
    "addr:full":"1186 Glendale Galleria Glendale CA 91210",
    "addr:housenumber":"1186",
    "addr:postcode":"91210",
    "addr:street":"Glendale Galleria",
    "iso:country":"US",
    "sg:address":"1186 Glendale Galleria",
    "sg:city":"Glendale",
    "sg:classifiers":[
        {
            "category":"Arts & Performance",
            "subcategory":"Art Gallery",
            "type":"Entertainment"
        }
    ],
    "sg:phone":"+1 818 242 4242",
    "sg:postcode":"91210",
    "sg:province":"CA",
    "wof:name":"Glendale Galleria",
    "wof:placetype":"venue"
},
  "geometry": {"coordinates":[-118.25905899999999,34.146649],"type":"Point"}
}