{
  "type": "Feature",
  "properties": {
    "addr:full":"326 S Miraleste Dr San Pedro CA 90732",
    "addr:housenumber":"326",
    "addr:postcode":"90732",
    "addr:street":"S Miraleste Dr",
    "iso:country":"US",
    "sg:address":"326 S Miraleste Dr",
    "sg:city":"San Pedro",
    "sg:classifiers":[
        {
            "category":"Manufacturing",
            "subcategory":"Metals",
            "type":"Manufacturing & Wholesale Goods"
        }
    ],
    "sg:phone":"+1 310 519 8926",
    "sg:postcode":"90732",
    "sg:province":"CA",
    "sg:tags":[
        "tool",
        "mfg"
    ],
    "wof:name":"APA Group International Corp",
    "wof:placetype":"venue"
},
  "geometry": {"coordinates":[-118.31868,33.738518],"type":"Point"}
}