{
  "type": "Feature",
  "properties": {
    "iso:country":"US",
    "sg:address":"2020 S Robertson Blvd",
    "sg:city":"Los Angeles",
    "sg:classifiers":[
        {
            "category":"Professional",
            "subcategory":"Management & Consulting",
            "type":"Services"
        }
    ],
    "sg:phone":"+1 310 840 5785",
    "sg:postcode":"90034",
    "sg:province":"CA",
    "wof:name":"Eliassian Development Corp",
    "wof:placetype":"venue"
},
  "geometry": {"coordinates":[-118.38749199999999,34.041329],"type":"Point"}
}