{
  "type": "Feature",
  "properties": {
    "iso:country":"US",
    "sg:address":"2801 Redwood Pkwy",
    "sg:city":"Vallejo",
    "sg:classifiers":[
        {
            "category":"Real Estate",
            "subcategory":"Real Estate Agent",
            "type":"Services"
        }
    ],
    "sg:phone":"+1 707 645 0967",
    "sg:postcode":"94591",
    "sg:province":"CA",
    "wof:name":"Patton Real Estate Co",
    "wof:placetype":"venue"
},
  "geometry": {"coordinates":[-122.227676,38.123463],"type":"Point"}
}