{
  "type": "Feature",
  "properties": {
    "iso:country":"US",
    "sg:address":"2420 Turning Trail Rd",
    "sg:city":"Chula Vista",
    "sg:classifiers":[
        {
            "category":"Banks & Credit Unions",
            "subcategory":"Bank",
            "type":"Services"
        }
    ],
    "sg:phone":"+1 619 271 2369",
    "sg:postcode":"91914",
    "sg:province":"CA",
    "sg:tags":[
        "loan",
        "real estate"
    ],
    "wof:name":"S R Financial",
    "wof:placetype":"venue"
},
  "geometry": {"coordinates":[-116.963433,32.66276],"type":"Point"}
}