{
  "type": "Feature",
  "properties": {
    "addr:full":"7551 Broadway Lemon Grove CA 91945",
    "addr:housenumber":"7551",
    "addr:postcode":"91945",
    "addr:street":"Broadway",
    "iso:country":"US",
    "sg:address":"7551 Broadway",
    "sg:city":"Lemon Grove",
    "sg:classifiers":[
        {
            "category":"Home & Garden",
            "subcategory":"Furniture",
            "type":"Retail Goods"
        }
    ],
    "sg:phone":"+1 619 469 9945",
    "sg:postcode":"91945",
    "sg:province":"CA",
    "sg:tags":[
        "store"
    ],
    "sg:website":"www.furnituredepotlg.com",
    "wof:name":"Furniture Depot",
    "wof:placetype":"venue"
},
  "geometry": {"coordinates":[-117.03600299999999,32.742699],"type":"Point"}
}