{
  "type": "Feature",
  "properties": {
    "addr:full":"1215 Seward St Los Angeles CA 90038",
    "addr:housenumber":"1215",
    "addr:postcode":"90038",
    "addr:street":"Seward St",
    "iso:country":"US",
    "sg:address":"1215 Seward St",
    "sg:city":"Los Angeles",
    "sg:classifiers":[
        {
            "category":"Wholesale",
            "subcategory":"Durable Goods & Equipment",
            "type":"Manufacturing & Wholesale Goods"
        }
    ],
    "sg:phone":"+1 323 465 6636",
    "sg:postcode":"90038",
    "sg:province":"CA",
    "sg:tags":[
        "importer"
    ],
    "wof:name":"K S Brothers African Imports",
    "wof:placetype":"venue"
},
  "geometry": {"coordinates":[-118.33326,34.093042],"type":"Point"}
}