{
  "type": "Feature",
  "properties": {
    "iso:country":"US",
    "sg:address":"155 Balboa St",
    "sg:city":"San Marcos",
    "sg:classifiers":[
        {
            "category":"Wholesale",
            "subcategory":"Stationery",
            "type":"Manufacturing & Wholesale Goods"
        }
    ],
    "sg:phone":"+1 760 591 3411",
    "sg:postcode":"92069",
    "sg:province":"CA",
    "sg:tags":[
        "supply"
    ],
    "wof:name":"Xrefurb Center",
    "wof:placetype":"venue"
},
  "geometry": {"coordinates":[-117.192219,33.148828],"type":"Point"}
}