{
  "type": "Feature",
  "properties": {
    "iso:country":"US",
    "sg:address":"561 Webster St",
    "sg:city":"San Francisco",
    "sg:classifiers":[
        {
            "category":"Restaurant",
            "type":"Food & Drink"
        }
    ],
    "sg:phone":"+1 415 431 1387",
    "sg:postcode":"94117",
    "sg:province":"CA",
    "sg:tags":[
        "shop",
        "coffee"
    ],
    "wof:name":"Goodday Cafe",
    "wof:placetype":"venue"
},
  "geometry": {"coordinates":[-122.42961,37.77592],"type":"Point"}
}