{
  "type": "Feature",
  "properties": {
    "addr:full":"1012 Post Street San Francisco CA 94109",
    "addr:housenumber":"1012",
    "addr:postcode":"94109",
    "addr:street":"Post Street",
    "iso:country":"US",
    "sg:address":"1012 Post Street",
    "sg:city":"San Francisco",
    "sg:classifiers":[
        {
            "category":"Food & Beverages",
            "subcategory":"Groceries & Convenience Stores",
            "type":"Retail Goods"
        }
    ],
    "sg:phone":"+1 415 441 2536",
    "sg:postcode":"94109",
    "sg:province":"CA",
    "wof:name":"S & B Grocery & Liquor Store",
    "wof:placetype":"venue"
},
  "geometry": {"coordinates":[-122.418999,37.787102],"type":"Point"}
}