{
  "type": "Feature",
  "properties": {
    "iso:country":"US",
    "sg:address":"24410 Mural Ct",
    "sg:city":"Moreno Valley",
    "sg:classifiers":[
        {
            "category":"Building & Trades",
            "subcategory":"Landscaping Services",
            "type":"Services"
        }
    ],
    "sg:phone":"+1 951 488 0834",
    "sg:postcode":"92553",
    "sg:province":"CA",
    "sg:tags":[
        "designer",
        "landscape"
    ],
    "wof:name":"Dinar's Landscaping & Quality",
    "wof:placetype":"venue"
},
  "geometry": {"coordinates":[-117.23577,33.913031],"type":"Point"}
}