{
  "type": "Feature",
  "properties": {
    "iso:country":"US",
    "sg:address":"23805 Clinton Keith Rd",
    "sg:city":"Wildomar",
    "sg:classifiers":[
        {
            "category":"Food & Beverages",
            "subcategory":"Groceries & Convenience Stores",
            "type":"Retail Goods"
        }
    ],
    "sg:phone":"+1 951 600 4620",
    "sg:postcode":"92595",
    "sg:province":"CA",
    "sg:tags":[
        "grocer"
    ],
    "wof:name":"Albertsons",
    "wof:placetype":"venue"
},
  "geometry": {"coordinates":[-117.241277,33.597566],"type":"Point"}
}