{
  "type": "Feature",
  "properties": {
    "iso:country":"US",
    "sg:address":"420 E St",
    "sg:city":"Santa Rosa",
    "sg:classifiers":[
        {
            "category":"Banks & Credit Unions",
            "subcategory":"Bank",
            "type":"Services"
        }
    ],
    "sg:phone":"+1 707 526 4900",
    "sg:postcode":"95404",
    "sg:province":"CA",
    "sg:tags":[
        "loan",
        "real estate"
    ],
    "wof:name":"Home Savings Mortgage",
    "wof:placetype":"venue"
},
  "geometry": {"coordinates":[-122.710886,38.445458],"type":"Point"}
}