{
  "type": "Feature",
  "properties": {
    "iso:country":"US",
    "sg:address":"3461 Via Lido",
    "sg:city":"Newport Beach",
    "sg:classifiers":[
        {
            "category":"Restaurant",
            "type":"Food & Drink"
        }
    ],
    "sg:phone":"+1 949 723 8777",
    "sg:postcode":"92663",
    "sg:province":"CA",
    "sg:tags":[
        "traditional",
        "american",
        "diner"
    ],
    "sg:website":"woodysdiners.com",
    "wof:name":"Woody's Diner",
    "wof:placetype":"venue"
},
  "geometry": {"coordinates":[-117.92938100000001,33.618152],"type":"Point"}
}