{
  "type": "Feature",
  "properties": {
    "iso:country":"US",
    "sg:address":"5193 Saddle Brook Dr",
    "sg:city":"Oakland",
    "sg:classifiers":[
        {
            "category":"Health Services",
            "subcategory":"Doctor",
            "type":"Services"
        }
    ],
    "sg:phone":"+1 510 437 4835",
    "sg:postcode":"94619",
    "sg:province":"CA",
    "sg:tags":[
        "physician",
        "surgeon",
        "neurology",
        "surgeons"
    ],
    "wof:name":"Moure Neurosurgery",
    "wof:placetype":"venue"
},
  "geometry": {"coordinates":[-122.146843,37.790782],"type":"Point"}
}