{
  "type": "Feature",
  "properties": {
    "addr:full":"712 E Clayton Ave Fresno CA 93725",
    "addr:housenumber":"712",
    "addr:postcode":"93725",
    "addr:street":"E Clayton Ave",
    "iso:country":"US",
    "sg:address":"712 E Clayton Ave",
    "sg:city":"Fresno",
    "sg:classifiers":[
        {
            "category":"Local Transit",
            "type":"Transportation"
        }
    ],
    "sg:phone":"+1 559 237 4395",
    "sg:postcode":"93725",
    "sg:province":"CA",
    "wof:name":"Everyday Trucking",
    "wof:placetype":"venue"
},
  "geometry": {"coordinates":[-119.776222,36.641606],"type":"Point"}
}