{
  "type": "Feature",
  "properties": {
    "iso:country":"US",
    "sg:address":"24811 Railroad Ave",
    "sg:city":"Newhall",
    "sg:classifiers":[
        {
            "category":"Professional",
            "type":"Services"
        }
    ],
    "sg:phone":"+1 661 799 7005",
    "sg:postcode":"91321",
    "sg:province":"CA",
    "sg:tags":[
        "caterer"
    ],
    "wof:name":"Custom Catering",
    "wof:placetype":"venue"
},
  "geometry": {"coordinates":[-118.532213,34.385883],"type":"Point"}
}