{
  "type": "Feature",
  "properties": {
    "iso:country":"US",
    "sg:address":"1405 Huntington Avenue Suite 202",
    "sg:city":"South San Francisco",
    "sg:classifiers":[
        {
            "category":"Professional",
            "subcategory":"Lawyer & Legal Services",
            "type":"Services"
        }
    ],
    "sg:phone":"+1 650 871 0602",
    "sg:postcode":"94080",
    "sg:province":"CA",
    "sg:tags":[
        "divorce",
        "law",
        "family"
    ],
    "sg:website":"www.eileenavilalaw.com/",
    "wof:name":"Eileen Avila",
    "wof:placetype":"venue"
},
  "geometry": {"coordinates":[-122.420068,37.641896],"type":"Point"}
}