{
  "type": "Feature",
  "properties": {
    "addr:full":"611 E 20th St Oakland CA 94606",
    "addr:housenumber":"611",
    "addr:postcode":"94606",
    "addr:street":"E 20Th St",
    "iso:country":"US",
    "sg:address":"611 E 20th St",
    "sg:city":"Oakland",
    "sg:classifiers":[
        {
            "category":"Communications",
            "type":"Services"
        }
    ],
    "sg:phone":"+1 510 465 7181",
    "sg:postcode":"94606",
    "sg:province":"CA",
    "sg:tags":[
        "communication"
    ],
    "wof:name":"Effective Links Communications",
    "wof:placetype":"venue"
},
  "geometry": {"coordinates":[-122.246742,37.798227],"type":"Point"}
}