{
  "type": "Feature",
  "properties": {
    "iso:country":"US",
    "sg:address":"8500 Florence Avenue",
    "sg:city":"Downey",
    "sg:classifiers":[
        {
            "category":"Health Services",
            "subcategory":"Doctor",
            "type":"Services"
        }
    ],
    "sg:phone":"+1 562 869 4579",
    "sg:postcode":"90240",
    "sg:province":"CA",
    "sg:website":"www.mishalbenderobgyn.com",
    "wof:name":"Bender Gill MD Facog",
    "wof:placetype":"venue"
},
  "geometry": {"coordinates":[-118.121788,33.949708],"type":"Point"}
}