{
  "type": "Feature",
  "properties": {
    "addr:full":"1351 Tourney Dr San Jose CA 95131",
    "addr:housenumber":"1351",
    "addr:postcode":"95131",
    "addr:street":"Tourney Dr",
    "iso:country":"US",
    "sg:address":"1351 Tourney Dr",
    "sg:city":"San Jose",
    "sg:classifiers":[
        {
            "category":"Professional",
            "type":"Services"
        }
    ],
    "sg:phone":"+1 408 347 9902",
    "sg:postcode":"95131",
    "sg:province":"CA",
    "wof:name":"Catherine Loera",
    "wof:placetype":"venue"
},
  "geometry": {"coordinates":[-121.86982999999999,37.38551],"type":"Point"}
}