{
  "type": "Feature",
  "properties": {
    "addr:full":"2860 E Lincoln Ave Anaheim CA 92806",
    "addr:housenumber":"2860",
    "addr:postcode":"92806",
    "addr:street":"E Lincoln Ave",
    "iso:country":"US",
    "sg:address":"2860 E Lincoln Ave",
    "sg:city":"Anaheim",
    "sg:classifiers":[
        {
            "category":"Retail",
            "subcategory":"Auto Repair",
            "type":"Services"
        }
    ],
    "sg:phone":"+1 714 630 0336",
    "sg:postcode":"92806",
    "sg:province":"CA",
    "wof:name":"Reliable Auto Care",
    "wof:placetype":"venue"
},
  "geometry": {"coordinates":[-117.86900300000001,33.836498],"type":"Point"}
}