{
  "type": "Feature",
  "properties": {
    "iso:country":"US",
    "sg:address":"6709 Watt Ave",
    "sg:city":"North Highlands",
    "sg:classifiers":[
        {
            "category":"Autos & Motor Vehicles",
            "subcategory":"Automobile Sales",
            "type":"Retail Goods"
        }
    ],
    "sg:phone":"+1 916 348 0374",
    "sg:postcode":"95660",
    "sg:province":"CA",
    "sg:tags":[
        "automotive"
    ],
    "sg:website":"www.jiffylubeca.com/locations/de...",
    "wof:name":"Jiffy Lube # 384",
    "wof:placetype":"venue"
},
  "geometry": {"coordinates":[-121.383247,38.688968],"type":"Point"}
}