{
  "type": "Feature",
  "properties": {
    "iso:country":"US",
    "sg:address":"1800 N Highland Ave",
    "sg:city":"Los Angeles",
    "sg:classifiers":[
        {
            "category":"Professional",
            "subcategory":"Lawyer & Legal Services",
            "type":"Services"
        }
    ],
    "sg:phone":"+1 323 468 9772",
    "sg:postcode":"90028",
    "sg:province":"CA",
    "sg:tags":[
        "attorney"
    ],
    "wof:name":"Taheri Payman Law Offices",
    "wof:placetype":"venue"
},
  "geometry": {"coordinates":[-118.337474,34.10505],"type":"Point"}
}