{
  "type": "Feature",
  "properties": {
    "iso:country":"US",
    "sg:address":"1100 Cole Ave",
    "sg:city":"Clovis",
    "sg:classifiers":[
        {
            "category":"Building & Trades",
            "subcategory":"Construction",
            "type":"Services"
        }
    ],
    "sg:phone":"+1 559 291 6655",
    "sg:postcode":"93612",
    "sg:province":"CA",
    "sg:tags":[
        "downspout",
        "gutter",
        "or",
        "contractor"
    ],
    "wof:name":"American Seamless Rain Gutter",
    "wof:placetype":"venue"
},
  "geometry": {"coordinates":[-119.695244,36.816304],"type":"Point"}
}