{
  "type": "Feature",
  "properties": {
    "addr:full":"1323 16th Avenue Apt 3 San Francisco CA 94122",
    "addr:housenumber":"1323;3",
    "addr:postcode":"94122",
    "addr:street":"16Th Avenue Apt",
    "iso:country":"US",
    "sg:address":"1323 16th Avenue Apt 3",
    "sg:city":"San Francisco",
    "sg:classifiers":[
        {
            "category":"Building & Trades",
            "subcategory":"Electrical",
            "type":"Services"
        }
    ],
    "sg:phone":"+1 415 566 1545",
    "sg:postcode":"94122",
    "sg:province":"CA",
    "sg:tags":[
        "electrician"
    ],
    "wof:name":"Holec Electric",
    "wof:placetype":"venue"
},
  "geometry": {"coordinates":[-122.47399900000001,37.763302],"type":"Point"}
}