{
  "type": "Feature",
  "properties": {
    "addr:full":"4905 Claremont Ave Stockton CA 95207",
    "addr:housenumber":"4905",
    "addr:postcode":"95207",
    "addr:street":"Claremont Ave",
    "iso:country":"US",
    "sg:address":"4905 Claremont Ave",
    "sg:city":"Stockton",
    "sg:classifiers":[
        {
            "category":"Wholesale",
            "subcategory":"Auto Parts",
            "type":"Manufacturing & Wholesale Goods"
        }
    ],
    "sg:phone":"+1 209 477 9000",
    "sg:postcode":"95207",
    "sg:province":"CA",
    "sg:tags":[
        "supply"
    ],
    "wof:name":"Brannon Tire",
    "wof:placetype":"venue"
},
  "geometry": {"coordinates":[-121.31017300000001,37.997653],"type":"Point"}
}