{
  "type": "Feature",
  "properties": {
    "iso:country":"US",
    "sg:address":"940 E Pine St",
    "sg:city":"Lodi",
    "sg:classifiers":[
        {
            "category":"Manufacturing",
            "subcategory":"Rubber & Plastics",
            "type":"Manufacturing & Wholesale Goods"
        }
    ],
    "sg:phone":"+1 209 334 4904",
    "sg:postcode":"95240",
    "sg:province":"CA",
    "sg:tags":[
        "supply"
    ],
    "wof:name":"Plug-It Products",
    "wof:placetype":"venue"
},
  "geometry": {"coordinates":[-121.252765,38.13392],"type":"Point"}
}