{
  "type": "Feature",
  "properties": {
    "addr:full":"9637 Bolsa Avenue Suite # A Westminster CA 92683",
    "addr:housenumber":"9637",
    "addr:postcode":"92683",
    "addr:street":"Bolsa Avenue Suite # A",
    "iso:country":"US",
    "sg:address":"9637 Bolsa Avenue Suite # A",
    "sg:city":"Westminster",
    "sg:classifiers":[
        {
            "category":"Restaurant",
            "type":"Food & Drink"
        }
    ],
    "sg:phone":"+1 714 531 9300",
    "sg:postcode":"92683",
    "sg:province":"CA",
    "sg:tags":[
        "vietnamese"
    ],
    "wof:name":"Tan Phat",
    "wof:placetype":"venue"
},
  "geometry": {"coordinates":[-117.96013000000001,33.745022],"type":"Point"}
}