{
  "type": "Feature",
  "properties": {
    "iso:country":"US",
    "sg:address":"1939 Harrison St Ste 200",
    "sg:city":"Oakland",
    "sg:classifiers":[
        {
            "category":"Professional",
            "subcategory":"Lawyer & Legal Services",
            "type":"Services"
        }
    ],
    "sg:phone":"+1 510 444 6044",
    "sg:postcode":"94612",
    "sg:province":"CA",
    "wof:name":"Hand Margaret M",
    "wof:placetype":"venue"
},
  "geometry": {"coordinates":[-122.26528,37.806927],"type":"Point"}
}