{
  "type": "Feature",
  "properties": {
    "addr:full":"17442 Sherman Way Van Nuys CA 91406",
    "addr:housenumber":"17442",
    "addr:postcode":"91406",
    "addr:street":"Sherman Way",
    "iso:country":"US",
    "sg:address":"17442 Sherman Way",
    "sg:city":"Van Nuys",
    "sg:classifiers":[
        {
            "category":"Real Estate",
            "subcategory":"Real Estate Agent",
            "type":"Services"
        }
    ],
    "sg:phone":"+1 818 344 3005",
    "sg:postcode":"91406",
    "sg:province":"CA",
    "sg:tags":[
        "management"
    ],
    "wof:name":"Deels Properties LP",
    "wof:placetype":"venue"
},
  "geometry": {"coordinates":[-118.512565,34.201024],"type":"Point"}
}