{
  "type": "Feature",
  "properties": {
    "iso:country":"US",
    "sg:address":"10540 Burbank Blvd",
    "sg:city":"North Hollywood",
    "sg:classifiers":[
        {
            "category":"Health Services",
            "subcategory":"Doctor",
            "type":"Services"
        }
    ],
    "sg:phone":"+1 818 760 0704",
    "sg:postcode":"91601",
    "sg:province":"CA",
    "wof:name":"Universal Medical Services",
    "wof:placetype":"venue"
},
  "geometry": {"coordinates":[-118.361,34.172298],"type":"Point"}
}