{
  "type": "Feature",
  "properties": {
    "addr:full":"225 Linden Ave San Bruno CA 94066",
    "addr:housenumber":"225",
    "addr:postcode":"94066",
    "addr:street":"Linden Ave",
    "iso:country":"US",
    "sg:address":"225 Linden Ave",
    "sg:city":"San Bruno",
    "sg:classifiers":[
        {
            "category":"Building & Trades",
            "subcategory":"Cleaning & Sanitation",
            "type":"Services"
        }
    ],
    "sg:phone":"+1 650 583 5855",
    "sg:postcode":"94066",
    "sg:province":"CA",
    "sg:tags":[
        "janitor"
    ],
    "wof:name":"Garibay Services",
    "wof:placetype":"venue"
},
  "geometry": {"coordinates":[-122.410993,37.619094],"type":"Point"}
}