{
  "type": "Feature",
  "properties": {
    "iso:country":"US",
    "sg:address":"900 Santa Monica Blvd",
    "sg:city":"Santa Monica",
    "sg:classifiers":[
        {
            "category":"Autos & Motor Vehicles",
            "subcategory":"Automobile Sales",
            "type":"Retail Goods"
        }
    ],
    "sg:phone":"+1 310 394 1888",
    "sg:postcode":"90401",
    "sg:province":"CA",
    "sg:tags":[
        "car",
        "dealer"
    ],
    "wof:name":"Infiniti Of Santa Monica",
    "wof:placetype":"venue"
},
  "geometry": {"coordinates":[-118.489966,34.020647],"type":"Point"}
}