{
  "type": "Feature",
  "properties": {
    "iso:country":"US",
    "sg:address":"23956 Clawiter Rd",
    "sg:city":"Hayward",
    "sg:classifiers":[
        {
            "category":"Manufacturing",
            "subcategory":"Retail Goods",
            "type":"Manufacturing & Wholesale Goods"
        }
    ],
    "sg:phone":"+1 510 785 8415",
    "sg:postcode":"94545",
    "sg:province":"CA",
    "sg:tags":[
        "marking",
        "devices"
    ],
    "wof:name":"Marpak Inc",
    "wof:placetype":"venue"
},
  "geometry": {"coordinates":[-122.11983,37.645129],"type":"Point"}
}