{
  "type": "Feature",
  "properties": {
    "addr:full":"1951 Rigoletto Dr San Jose CA 95122",
    "addr:housenumber":"1951",
    "addr:postcode":"95122",
    "addr:street":"Rigoletto Dr",
    "iso:country":"US",
    "sg:address":"1951 Rigoletto Dr",
    "sg:city":"San Jose",
    "sg:classifiers":[
        {
            "category":"Building & Trades",
            "subcategory":"Landscaping Services",
            "type":"Services"
        }
    ],
    "sg:phone":"+1 408 644 1357",
    "sg:postcode":"95122",
    "sg:province":"CA",
    "wof:name":"Bernal Garden Services",
    "wof:placetype":"venue"
},
  "geometry": {"coordinates":[-121.81876699999999,37.320934],"type":"Point"}
}