{
  "type": "Feature",
  "properties": {
    "addr:full":"11879 Kemper Rd Auburn CA 95603",
    "addr:housenumber":"11879",
    "addr:postcode":"ca 95603",
    "addr:street":"Kemper Rd",
    "iso:country":"US",
    "sg:address":"11879 Kemper Rd",
    "sg:city":"Auburn",
    "sg:classifiers":[
        {
            "category":"Insurance",
            "subcategory":"Insurance Agent",
            "type":"Services"
        }
    ],
    "sg:phone":"+1 530 823 6492",
    "sg:postcode":"95603",
    "sg:province":"CA",
    "wof:name":"Robert Vaughan Insurance",
    "wof:placetype":"venue"
},
  "geometry": {"coordinates":[-121.091657,38.931409],"type":"Point"}
}