{
  "type": "Feature",
  "properties": {
    "iso:country":"US",
    "sg:address":"2975 Mission St",
    "sg:city":"San Francisco",
    "sg:classifiers":[
        {
            "category":"Shopping",
            "type":"Retail Goods"
        }
    ],
    "sg:phone":"+1 415 642 0751",
    "sg:postcode":"94110",
    "sg:province":"CA",
    "sg:tags":[
        "wedding",
        "supply"
    ],
    "wof:name":"Designer Sisters",
    "wof:placetype":"venue"
},
  "geometry": {"coordinates":[-122.418152,37.750254],"type":"Point"}
}