{
  "type": "Feature",
  "properties": {
    "addr:full":"51 Moraga Way Orinda CA 94563",
    "addr:housenumber":"51",
    "addr:postcode":"94563",
    "addr:street":"Moraga Way",
    "iso:country":"US",
    "sg:address":"51 Moraga Way",
    "sg:city":"Orinda",
    "sg:classifiers":[
        {
            "category":"Real Estate",
            "subcategory":"Real Estate Agent",
            "type":"Services"
        }
    ],
    "sg:phone":"+1 510 846 6577",
    "sg:postcode":"94563",
    "sg:province":"CA",
    "sg:website":"www.prurealty.com/melissaescaron",
    "wof:name":"Melissa Escaron",
    "wof:placetype":"venue"
},
  "geometry": {"coordinates":[-122.181139,37.878836],"type":"Point"}
}