{
  "type": "Feature",
  "properties": {
    "addr:full":"711 Keifer Ave Gridley CA 95948",
    "addr:housenumber":"711",
    "addr:postcode":"95948",
    "addr:street":"Keifer Ave",
    "iso:country":"US",
    "sg:address":"711 Keifer Ave",
    "sg:city":"Gridley",
    "sg:phone":"+1 530 846 5462",
    "sg:postcode":"95948",
    "sg:province":"CA",
    "sg:tags":[
        "farm",
        "grove",
        "nut",
        "rice",
        "tree"
    ],
    "wof:name":"Penning Brothers",
    "wof:placetype":"venue"
},
  "geometry": {"coordinates":[-121.654962,39.352604],"type":"Point"}
}