{
  "type": "Feature",
  "properties": {
    "addr:full":"13512 Lakewood Blvd Bellflower CA 90706",
    "addr:housenumber":"13512",
    "addr:postcode":"90706",
    "addr:street":"Lakewood Blvd",
    "iso:country":"US",
    "sg:address":"13512 Lakewood Blvd",
    "sg:city":"Bellflower",
    "sg:classifiers":[
        {
            "category":"Retail",
            "subcategory":"Auto Repair",
            "type":"Services"
        }
    ],
    "sg:phone":"+1 562 633 0643",
    "sg:postcode":"90706",
    "sg:province":"CA",
    "sg:tags":[
        "repairing",
        "automobile"
    ],
    "wof:name":"Rubio's Transmission",
    "wof:placetype":"venue"
},
  "geometry": {"coordinates":[-118.142725,33.904241],"type":"Point"}
}