{
  "type": "Feature",
  "properties": {
    "iso:country":"US",
    "sg:address":"2085 E Foothill Blvd",
    "sg:city":"Pasadena",
    "sg:classifiers":[
        {
            "category":"Shopping",
            "subcategory":"Used Merchandise",
            "type":"Retail Goods"
        }
    ],
    "sg:phone":"+1 626 584 0700",
    "sg:postcode":"91107",
    "sg:province":"CA",
    "sg:tags":[
        "fixture",
        "store"
    ],
    "wof:name":"Cal-State Store Fixtures Inc",
    "wof:placetype":"venue"
},
  "geometry": {"coordinates":[-118.106423,34.149706],"type":"Point"}
}