{
  "type": "Feature",
  "properties": {
    "iso:country":"US",
    "sg:address":"3653 Veteran Ave",
    "sg:city":"Los Angeles",
    "sg:classifiers":[
        {
            "category":"Utilities",
            "subcategory":"Mobile Phone",
            "type":"Services"
        }
    ],
    "sg:phone":"+1 310 280 0608",
    "sg:postcode":"90034",
    "sg:province":"CA",
    "sg:tags":[
        "communication",
        "radiotelephone"
    ],
    "wof:name":"Tier Wireless",
    "wof:placetype":"venue"
},
  "geometry": {"coordinates":[-118.414787,34.018548],"type":"Point"}
}