{
  "type": "Feature",
  "properties": {
    "addr:full":"18603 Bold St Rowland Heights CA 91748",
    "addr:housenumber":"18603",
    "addr:postcode":"91748",
    "addr:street":"Bold St",
    "iso:country":"US",
    "sg:address":"18603 Bold St",
    "sg:city":"Rowland Heights",
    "sg:classifiers":[
        {
            "category":"Freight",
            "type":"Transportation"
        }
    ],
    "sg:phone":"+1 626 965 5292",
    "sg:postcode":"91748",
    "sg:province":"CA",
    "wof:name":"Paz Transportation",
    "wof:placetype":"venue"
},
  "geometry": {"coordinates":[-117.898133,33.993397],"type":"Point"}
}