{
  "type": "Feature",
  "properties": {
    "iso:country":"US",
    "sg:address":"5038 W Ave N",
    "sg:city":"Palmdale",
    "sg:classifiers":[
        {
            "category":"Food & Beverages",
            "subcategory":"Groceries & Convenience Stores",
            "type":"Retail Goods"
        }
    ],
    "sg:phone":"+1 661 718 3732",
    "sg:postcode":"93551",
    "sg:province":"CA",
    "sg:tags":[
        "grocer"
    ],
    "sg:website":"www.albertsons.com",
    "wof:name":"Albertson's",
    "wof:placetype":"venue"
},
  "geometry": {"coordinates":[-118.219666,34.630825],"type":"Point"}
}