{
  "type": "Feature",
  "properties": {
    "iso:country":"US",
    "sg:address":"10 Jackson St",
    "sg:city":"Los Gatos",
    "sg:classifiers":[
        {
            "category":"Personal",
            "subcategory":"Massage",
            "type":"Services"
        }
    ],
    "sg:phone":"+1 408 395 7222",
    "sg:postcode":"95030",
    "sg:province":"CA",
    "sg:website":"insideandoutbodytherapy.com",
    "wof:name":"Inside and Out Body Therapy",
    "wof:placetype":"venue"
},
  "geometry": {"coordinates":[-121.97461699999999,37.220438],"type":"Point"}
}