{
  "type": "Feature",
  "properties": {
    "addr:full":"32 Willow St Salinas CA 93901",
    "addr:housenumber":"32",
    "addr:postcode":"93901",
    "addr:street":"Willow St",
    "iso:country":"US",
    "sg:address":"32 Willow St",
    "sg:city":"Salinas",
    "sg:classifiers":[
        {
            "category":"Home & Garden",
            "subcategory":"Household Appliances",
            "type":"Retail Goods"
        }
    ],
    "sg:phone":"+1 831 394 0581",
    "sg:postcode":"93901",
    "sg:province":"CA",
    "sg:tags":[
        "cleaners",
        "vacuum"
    ],
    "wof:name":"Electrolux Sales & Svc",
    "wof:placetype":"venue"
},
  "geometry": {"coordinates":[-121.654419,36.666318],"type":"Point"}
}