{
  "type": "Feature",
  "properties": {
    "addr:full":"357 Travis Dr Los Osos CA 93402",
    "addr:housenumber":"357",
    "addr:postcode":"93402",
    "addr:street":"Travis Dr",
    "iso:country":"US",
    "sg:address":"357 Travis Dr",
    "sg:city":"Los Osos",
    "sg:classifiers":[
        {
            "category":"Professional",
            "type":"Services"
        }
    ],
    "sg:phone":"+1 805 528 1321",
    "sg:postcode":"93402",
    "sg:province":"CA",
    "sg:tags":[
        "establishment"
    ],
    "wof:name":"Solo Creations Inc",
    "wof:placetype":"venue"
},
  "geometry": {"coordinates":[-120.848266,35.302962],"type":"Point"}
}