{
  "type": "Feature",
  "properties": {
    "iso:country":"US",
    "sg:address":"421 W Ocean Ave Ste 401",
    "sg:city":"Lompoc",
    "sg:classifiers":[
        {
            "category":"Food & Beverages",
            "subcategory":"Supermarket",
            "type":"Retail Goods"
        },
        {
            "category":"Food & Beverages",
            "subcategory":"Groceries & Convenience Stores",
            "type":"Retail Goods"
        }
    ],
    "sg:phone":"+1 805 736 9388",
    "sg:postcode":"93436",
    "sg:province":"CA",
    "sg:tags":[
        "super"
    ],
    "wof:name":"Cat's Market & Deli",
    "wof:placetype":"venue"
},
  "geometry": {"coordinates":[-120.462372,34.639019],"type":"Point"}
}