{
  "type": "Feature",
  "properties": {
    "iso:country":"US",
    "sg:address":"1825 W Pier D St",
    "sg:city":"Long Beach",
    "sg:classifiers":[
        {
            "category":"Manufacturing",
            "subcategory":"Watercraft",
            "type":"Manufacturing & Wholesale Goods"
        }
    ],
    "sg:phone":"+1 562 901 2470",
    "sg:postcode":"90802",
    "sg:province":"CA",
    "sg:tags":[
        "marina",
        "boating",
        "operation",
        "repair"
    ],
    "sg:website":"www.gambolindustries.com",
    "wof:name":"Gambol Industries Inc",
    "wof:placetype":"venue"
},
  "geometry": {"coordinates":[-118.218002,33.766201],"type":"Point"}
}