{
  "type": "Feature",
  "properties": {
    "iso:country":"US",
    "sg:address":"2575 Monument Blvd",
    "sg:city":"Concord",
    "sg:classifiers":[
        {
            "category":"Retail",
            "subcategory":"Auto Repair",
            "type":"Services"
        }
    ],
    "sg:phone":"+1 925 825 2099",
    "sg:postcode":"94520",
    "sg:province":"CA",
    "sg:tags":[
        "body",
        "automobile",
        "painting"
    ],
    "wof:name":"Pacific Auto Body Shop",
    "wof:placetype":"venue"
},
  "geometry": {"coordinates":[-122.031695,37.963657],"type":"Point"}
}