{
  "type": "Feature",
  "properties": {
    "addr:full":"9900 Redstone Dr Sacramento CA 95827",
    "addr:housenumber":"9900",
    "addr:postcode":"95827",
    "addr:street":"Redstone Dr",
    "iso:country":"US",
    "sg:address":"9900 Redstone Dr",
    "sg:city":"Sacramento",
    "sg:classifiers":[
        {
            "category":"Shopping",
            "subcategory":"Clothing, Apparel, & Fashions",
            "type":"Retail Goods"
        }
    ],
    "sg:phone":"+1 916 416 5478",
    "sg:postcode":"95827",
    "sg:province":"CA",
    "wof:name":"Jani Serv Maricela's Clothing",
    "wof:placetype":"venue"
},
  "geometry": {"coordinates":[-121.326509,38.561156],"type":"Point"}
}