{
  "type": "Feature",
  "properties": {
    "addr:full":"1411 E Wilshire Ave Santa Ana CA 92705",
    "addr:housenumber":"1411",
    "addr:postcode":"92705",
    "addr:street":"E Wilshire Ave",
    "iso:country":"US",
    "sg:address":"1411 E Wilshire Ave",
    "sg:city":"Santa Ana",
    "sg:classifiers":[
        {
            "category":"Home & Garden",
            "subcategory":"Carpets & Floor Coverings",
            "type":"Retail Goods"
        }
    ],
    "sg:phone":"+1 714 647 0999",
    "sg:postcode":"92705",
    "sg:province":"CA",
    "sg:tags":[
        "flooring"
    ],
    "wof:name":"Progressive Floor Covering",
    "wof:placetype":"venue"
},
  "geometry": {"coordinates":[-117.851488,33.729376],"type":"Point"}
}