{
  "type": "Feature",
  "properties": {
    "iso:country":"US",
    "sg:address":"3212 S Main St",
    "sg:city":"Santa Ana",
    "sg:classifiers":[
        {
            "category":"Home & Garden",
            "subcategory":"Furniture",
            "type":"Retail Goods"
        }
    ],
    "sg:phone":"+1 619 516 4766",
    "sg:postcode":"92707",
    "sg:province":"CA",
    "wof:name":"Queens Iron",
    "wof:placetype":"venue"
},
  "geometry": {"coordinates":[-117.868157,33.704488],"type":"Point"}
}