{
  "type": "Feature",
  "properties": {
    "iso:country":"US",
    "sg:address":"595 Buck Ave Ste G",
    "sg:city":"Vacaville",
    "sg:classifiers":[
        {
            "category":"Personal",
            "subcategory":"Massage",
            "type":"Services"
        }
    ],
    "sg:phone":"+1 707 628 3346",
    "sg:postcode":"95688",
    "sg:province":"CA",
    "wof:name":"Massage For Health & Wellness",
    "wof:placetype":"venue"
},
  "geometry": {"coordinates":[-122.007188,38.3556],"type":"Point"}
}