{
  "type": "Feature",
  "properties": {
    "addr:full":"750 S Lincoln Ave Corona CA 92882",
    "addr:housenumber":"750",
    "addr:postcode":"92882",
    "addr:street":"S Lincoln Ave",
    "iso:country":"US",
    "sg:address":"750 S Lincoln Ave",
    "sg:city":"Corona",
    "sg:classifiers":[
        {
            "category":"Building & Trades",
            "subcategory":"Construction",
            "type":"Services"
        }
    ],
    "sg:phone":"+1 951 808 4251",
    "sg:postcode":"92882",
    "sg:province":"CA",
    "sg:tags":[
        "roofing",
        "contractor"
    ],
    "wof:name":"A1 Quality Roofing",
    "wof:placetype":"venue"
},
  "geometry": {"coordinates":[-117.58350799999999,33.875678],"type":"Point"}
}