{
  "type": "Feature",
  "properties": {
    "addr:full":"5901 W Olympic Blvd Los Angeles CA 90036",
    "addr:housenumber":"5901",
    "addr:postcode":"90036",
    "addr:street":"W Olympic Blvd",
    "iso:country":"US",
    "sg:address":"5901 W Olympic Blvd",
    "sg:city":"Los Angeles",
    "sg:classifiers":[
        {
            "category":"Health Services",
            "subcategory":"Doctor",
            "type":"Services"
        }
    ],
    "sg:phone":"+1 323 937 5151",
    "sg:postcode":"90036",
    "sg:province":"CA",
    "sg:tags":[
        "clinic"
    ],
    "sg:website":"www.beermedicalgroup.com",
    "wof:name":"Beer Medical Group",
    "wof:placetype":"venue"
},
  "geometry": {"coordinates":[-118.36084099999999,34.057684],"type":"Point"}
}