{
  "type": "Feature",
  "properties": {
    "iso:country":"US",
    "sg:address":"1900 E Warner Ave",
    "sg:city":"Santa Ana",
    "sg:classifiers":[
        {
            "category":"Building & Trades",
            "subcategory":"Construction",
            "type":"Services"
        }
    ],
    "sg:phone":"+1 949 474 2333",
    "sg:postcode":"92705",
    "sg:province":"CA",
    "sg:tags":[
        "contractor"
    ],
    "sg:website":"www.gentosi.com",
    "wof:name":"Gentosi Builders",
    "wof:placetype":"venue"
},
  "geometry": {"coordinates":[-117.846001,33.715698],"type":"Point"}
}