{
  "type": "Feature",
  "properties": {
    "addr:full":"4779 Quadres Ct Fremont CA 94538",
    "addr:housenumber":"4779",
    "addr:postcode":"94538",
    "addr:street":"Quadres Ct",
    "iso:country":"US",
    "sg:address":"4779 Quadres Ct",
    "sg:city":"Fremont",
    "sg:classifiers":[
        {
            "category":"Wholesale",
            "subcategory":"Non-durable Goods",
            "type":"Manufacturing & Wholesale Goods"
        }
    ],
    "sg:phone":"+1 510 501 0557",
    "sg:postcode":"94538",
    "sg:province":"CA",
    "wof:name":"Rose Trading",
    "wof:placetype":"venue"
},
  "geometry": {"coordinates":[-121.994636,37.538104],"type":"Point"}
}