{
  "type": "Feature",
  "properties": {
    "addr:full":"3222 Winona Way North Highlands CA 95660",
    "addr:housenumber":"3222",
    "addr:postcode":"95660",
    "addr:street":"Winona Way",
    "iso:country":"US",
    "sg:address":"3222 Winona Way",
    "sg:city":"North Highlands",
    "sg:classifiers":[
        {
            "category":"Building & Trades",
            "subcategory":"Construction",
            "type":"Services"
        }
    ],
    "sg:phone":"+1 916 331 5934",
    "sg:postcode":"95660",
    "sg:province":"CA",
    "sg:tags":[
        "contractor"
    ],
    "wof:name":"HD Supply Repair & Remodel",
    "wof:placetype":"venue"
},
  "geometry": {"coordinates":[-121.389618,38.651514],"type":"Point"}
}