{
  "type": "Feature",
  "properties": {
    "addr:full":"19486 Beach Boulevard Huntington Beach CA 92648",
    "addr:housenumber":"19486",
    "addr:postcode":"92648",
    "addr:street":"Beach Boulevard",
    "iso:country":"US",
    "sg:address":"19486 Beach Boulevard",
    "sg:city":"Huntington Beach",
    "sg:classifiers":[
        {
            "category":"Retail",
            "subcategory":"Laundry & Dry Cleaning",
            "type":"Services"
        }
    ],
    "sg:phone":"+1 714 963 2653",
    "sg:postcode":"92648",
    "sg:province":"CA",
    "wof:name":"Rose Cleaners",
    "wof:placetype":"venue"
},
  "geometry": {"coordinates":[-117.988709,33.679796],"type":"Point"}
}