{
  "type": "Feature",
  "properties": {
    "iso:country":"US",
    "sg:address":"21720 Golden Star Blvd",
    "sg:city":"Tehachapi",
    "sg:classifiers":[
        {
            "category":"Banks & Credit Unions",
            "subcategory":"Financial Services",
            "type":"Services"
        }
    ],
    "sg:phone":"+1 661 822 3625",
    "sg:postcode":"93561",
    "sg:province":"CA",
    "sg:tags":[
        "investment",
        "closed"
    ],
    "wof:name":"Golden State Investors",
    "wof:placetype":"venue"
},
  "geometry": {"coordinates":[-118.486907,35.139393],"type":"Point"}
}