{
  "type": "Feature",
  "properties": {
    "addr:full":"2415 Campus Dr Ste 120 Irvine CA 92612",
    "addr:housenumber":"2415",
    "addr:postcode":"92612",
    "addr:street":"Campus Dr Ste 120",
    "iso:country":"US",
    "sg:address":"2415 Campus Dr Ste 120",
    "sg:city":"Irvine",
    "sg:classifiers":[
        {
            "category":"Professional",
            "subcategory":"Lawyer & Legal Services",
            "type":"Services"
        }
    ],
    "sg:phone":"+1 949 660 1740",
    "sg:postcode":"92612",
    "sg:province":"CA",
    "wof:name":"Peterson R Thomas atty",
    "wof:placetype":"venue"
},
  "geometry": {"coordinates":[-117.858937,33.669621],"type":"Point"}
}