{
  "type": "Feature",
  "properties": {
    "addr:full":"1030 E Valley Blvd Alhambra CA 91801",
    "addr:housenumber":"1030",
    "addr:postcode":"91801",
    "addr:street":"E Valley Blvd",
    "iso:country":"US",
    "sg:address":"1030 E Valley Blvd",
    "sg:city":"Alhambra",
    "sg:classifiers":[
        {
            "category":"Building & Trades",
            "subcategory":"Construction",
            "type":"Services"
        }
    ],
    "sg:phone":"+1 626 289 7210",
    "sg:postcode":"91801",
    "sg:province":"CA",
    "sg:tags":[
        "contractor"
    ],
    "wof:name":"Fuentes General Contracting",
    "wof:placetype":"venue"
},
  "geometry": {"coordinates":[-118.113343,34.078992],"type":"Point"}
}