{
  "type": "Feature",
  "properties": {
    "iso:country":"US",
    "sg:address":"1433 11th St",
    "sg:city":"Arcata",
    "sg:classifiers":[
        {
            "category":"Professional",
            "subcategory":"Art Services",
            "type":"Services"
        }
    ],
    "sg:phone":"+1 707 822 5258",
    "sg:postcode":"95521",
    "sg:province":"CA",
    "sg:tags":[
        "photographer"
    ],
    "wof:name":"Luna Photography",
    "wof:placetype":"venue"
},
  "geometry": {"coordinates":[-124.092505,40.871904],"type":"Point"}
}