{
  "type": "Feature",
  "properties": {
    "iso:country":"US",
    "sg:address":"711 W 17th St",
    "sg:city":"Costa Mesa",
    "sg:classifiers":[
        {
            "category":"Personal",
            "type":"Services"
        }
    ],
    "sg:phone":"+1 949 548 6447",
    "sg:postcode":"92627",
    "sg:province":"CA",
    "sg:tags":[
        "make",
        "permanent"
    ],
    "wof:name":"IIPC",
    "wof:placetype":"venue"
},
  "geometry": {"coordinates":[-117.931523,33.636041],"type":"Point"}
}