{
  "type": "Feature",
  "properties": {
    "iso:country":"US",
    "sg:address":"9330 Scranton Rd",
    "sg:city":"San Diego",
    "sg:classifiers":[
        {
            "category":"Professional",
            "subcategory":"Advertising",
            "type":"Services"
        }
    ],
    "sg:phone":"+1 858 799 2301",
    "sg:postcode":"92121",
    "sg:province":"CA",
    "wof:name":"EASSIST.NET",
    "wof:placetype":"venue"
},
  "geometry": {"coordinates":[-117.201612,32.892312],"type":"Point"}
}