{
  "type": "Feature",
  "properties": {
    "addr:full":"18220 S Broadway St Gardena CA 90248",
    "addr:housenumber":"18220",
    "addr:postcode":"90248",
    "addr:street":"S Broadway St",
    "iso:country":"US",
    "sg:address":"18220 S Broadway St",
    "sg:city":"Gardena",
    "sg:classifiers":[
        {
            "category":"Retail",
            "subcategory":"Repair Shop",
            "type":"Services"
        },
        {
            "category":"Wholesale",
            "subcategory":"Electrical",
            "type":"Manufacturing & Wholesale Goods"
        }
    ],
    "sg:phone":"+1 310 532 3211",
    "sg:postcode":"90248",
    "sg:province":"CA",
    "sg:tags":[
        "equipment",
        "communications",
        "radio",
        "system",
        "communication"
    ],
    "sg:website":"www.advancedelectronics.com",
    "wof:name":"Advanced Electronics Inc",
    "wof:placetype":"venue"
},
  "geometry": {"coordinates":[-118.278454,33.870292],"type":"Point"}
}