{
  "type": "Feature",
  "properties": {
    "addr:full":"8451 Miralani Dr San Diego CA 92126",
    "addr:housenumber":"8451",
    "addr:postcode":"92126",
    "addr:street":"Miralani Dr",
    "iso:country":"US",
    "sg:address":"8451 Miralani Dr",
    "sg:city":"San Diego",
    "sg:classifiers":[
        {
            "category":"Home & Garden",
            "subcategory":"Building Materials",
            "type":"Retail Goods"
        }
    ],
    "sg:phone":"+1 858 578 8000",
    "sg:postcode":"92126",
    "sg:province":"CA",
    "sg:tags":[
        "plumbing",
        "fixture",
        "supply"
    ],
    "sg:website":"www.sdwater.com",
    "wof:name":"San Diego Water Conservation",
    "wof:placetype":"venue"
},
  "geometry": {"coordinates":[-117.140372,32.896024],"type":"Point"}
}