{
  "type": "Feature",
  "properties": {
    "addr:full":"1649 Honeysuckle Ct Encinitas CA 92024",
    "addr:housenumber":"1649",
    "addr:postcode":"92024",
    "addr:street":"Honeysuckle Ct",
    "iso:country":"US",
    "sg:address":"1649 Honeysuckle Ct",
    "sg:city":"Encinitas",
    "sg:classifiers":[
        {
            "category":"Building & Trades",
            "subcategory":"Plumbing",
            "type":"Services"
        }
    ],
    "sg:phone":"+1 760 942 6160",
    "sg:postcode":"92024",
    "sg:province":"CA",
    "sg:tags":[
        "plumbing",
        "contractor"
    ],
    "wof:name":"County Wide Water Heaters",
    "wof:placetype":"venue"
},
  "geometry": {"coordinates":[-117.257806,33.058323],"type":"Point"}
}