{
  "type": "Feature",
  "properties": {
    "iso:country":"US",
    "sg:address":"731 9th St",
    "sg:city":"Richmond",
    "sg:classifiers":[
        {
            "category":"Building & Trades",
            "subcategory":"Cleaning & Sanitation",
            "type":"Services"
        }
    ],
    "sg:phone":"+1 510 235 1491",
    "sg:postcode":"94801",
    "sg:province":"CA",
    "sg:tags":[
        "house",
        "maintenance"
    ],
    "wof:name":"Frank's House Cleaning",
    "wof:placetype":"venue"
},
  "geometry": {"coordinates":[-122.36094,37.943868],"type":"Point"}
}