{
  "type": "Feature",
  "properties": {
    "iso:country":"US",
    "sg:address":"22320 Foothill Blvd Ste 430",
    "sg:city":"Hayward",
    "sg:classifiers":[
        {
            "category":"Professional",
            "subcategory":"Accounting & Tax Preparation",
            "type":"Services"
        }
    ],
    "sg:phone":"+1 510 582 8400",
    "sg:postcode":"94541",
    "sg:province":"CA",
    "sg:tags":[
        "accountant"
    ],
    "wof:name":"Hansen & Company",
    "wof:placetype":"venue"
},
  "geometry": {"coordinates":[-122.089996,37.6745],"type":"Point"}
}