{
  "type": "Feature",
  "properties": {
    "addr:full":"18406 Wisteria St Hesperia CA 92345",
    "addr:housenumber":"18406",
    "addr:postcode":"92345",
    "addr:street":"Wisteria St",
    "iso:country":"US",
    "sg:address":"18406 Wisteria St",
    "sg:city":"Hesperia",
    "sg:classifiers":[
        {
            "category":"Shopping",
            "type":"Retail Goods"
        }
    ],
    "sg:phone":"+1 760 244 8515",
    "sg:postcode":"92345",
    "sg:province":"CA",
    "sg:tags":[
        "merchandise"
    ],
    "sg:website":"http://www.ironartshop.com",
    "wof:name":"Iron Art Shop",
    "wof:placetype":"venue"
},
  "geometry": {"coordinates":[-117.263408,34.444209],"type":"Point"}
}