{
  "type": "Feature",
  "properties": {
    "iso:country":"US",
    "sg:address":"1661 Cascade Blvd",
    "sg:city":"Shasta Lake",
    "sg:classifiers":[
        {
            "category":"Retail",
            "subcategory":"Auto Repair",
            "type":"Services"
        }
    ],
    "sg:phone":"+1 530 275 1475",
    "sg:postcode":"96019",
    "sg:province":"CA",
    "sg:tags":[
        "repairing",
        "automobile"
    ],
    "wof:name":"Northern Automotive",
    "wof:placetype":"venue"
},
  "geometry": {"coordinates":[-122.35048,40.680092],"type":"Point"}
}