{
  "type": "Feature",
  "properties": {
    "addr:full":"9420 Reseda Blvd Northridge CA 91324",
    "addr:housenumber":"9420",
    "addr:postcode":"91324",
    "addr:street":"Reseda Blvd",
    "iso:country":"US",
    "sg:address":"9420 Reseda Blvd",
    "sg:city":"Northridge",
    "sg:classifiers":[
        {
            "category":"Manufacturing",
            "subcategory":"Printing",
            "type":"Manufacturing & Wholesale Goods"
        }
    ],
    "sg:phone":"+1 818 886 2120",
    "sg:postcode":"91324",
    "sg:province":"CA",
    "sg:tags":[
        "commercial"
    ],
    "wof:name":"Avanti Press",
    "wof:placetype":"venue"
},
  "geometry": {"coordinates":[-118.53601399999999,34.242381],"type":"Point"}
}