{
  "type": "Feature",
  "properties": {
    "iso:country":"US",
    "sg:address":"555 Broadway",
    "sg:city":"Chula Vista",
    "sg:classifiers":[
        {
            "category":"Shopping",
            "subcategory":"Mobile Phones",
            "type":"Retail Goods"
        }
    ],
    "sg:phone":"+1 619 422 4079",
    "sg:postcode":"91910",
    "sg:province":"CA",
    "wof:name":"T Mobile",
    "wof:placetype":"venue"
},
  "geometry": {"coordinates":[-117.08899700000001,32.629002],"type":"Point"}
}