{
  "type": "Feature",
  "properties": {
    "addr:full":"3475 E Colorado Blvd Pasadena CA 91107",
    "addr:housenumber":"3475",
    "addr:postcode":"91107",
    "addr:street":"E Colorado Blvd",
    "iso:country":"US",
    "sg:address":"3475 E Colorado Blvd",
    "sg:city":"Pasadena",
    "sg:classifiers":[
        {
            "category":"Autos & Motor Vehicles",
            "subcategory":"Automobile Sales",
            "type":"Retail Goods"
        },
        {
            "category":"Retail",
            "subcategory":"Auto Rental",
            "type":"Services"
        }
    ],
    "sg:phone":"+1 626 795 3381",
    "sg:postcode":"91107",
    "sg:province":"CA",
    "sg:tags":[
        "car"
    ],
    "wof:name":"Cadillac Symes Sales & Leasing Inc",
    "wof:placetype":"venue"
},
  "geometry": {"coordinates":[-118.079002,34.146301],"type":"Point"}
}