{
  "type": "Feature",
  "properties": {
    "addr:full":"2463 Ocala Ave San Jose CA 95122",
    "addr:housenumber":"2463",
    "addr:postcode":"95122",
    "addr:street":"Ocala Ave",
    "iso:country":"US",
    "sg:address":"2463 Ocala Ave",
    "sg:city":"San Jose",
    "sg:classifiers":[
        {
            "category":"Freight",
            "type":"Transportation"
        }
    ],
    "sg:phone":"+1 408 729 3108",
    "sg:postcode":"95122",
    "sg:province":"CA",
    "sg:tags":[
        "operator",
        "local",
        "trucking"
    ],
    "wof:name":"Lucas Trucking",
    "wof:placetype":"venue"
},
  "geometry": {"coordinates":[-121.82280799999999,37.339084],"type":"Point"}
}