{
  "type": "Feature",
  "properties": {
    "addr:full":"1900 Blue Gum Ave Modesto CA 95358",
    "addr:housenumber":"1900",
    "addr:postcode":"ca 95358",
    "addr:street":"Blue Gum Ave",
    "iso:country":"US",
    "sg:address":"1900 Blue Gum Ave",
    "sg:city":"Modesto",
    "sg:classifiers":[
        {
            "category":"Manufacturing",
            "subcategory":"Tools & Machinery",
            "type":"Manufacturing & Wholesale Goods"
        }
    ],
    "sg:phone":"+1 209 527 5223",
    "sg:postcode":"95358",
    "sg:province":"CA",
    "sg:tags":[
        "air",
        "parts",
        "conditioning",
        "supply"
    ],
    "wof:name":"Johnstone Supply",
    "wof:placetype":"venue"
},
  "geometry": {"coordinates":[-121.036349,37.660406],"type":"Point"}
}