{
  "type": "Feature",
  "properties": {
    "addr:full":"25850 Karisa Cir Moreno Valley CA 92551",
    "addr:housenumber":"25850",
    "addr:postcode":"92551",
    "addr:street":"Karisa Cir",
    "iso:country":"US",
    "sg:address":"25850 Karisa Cir",
    "sg:city":"Moreno Valley",
    "sg:classifiers":[
        {
            "category":"Building & Trades",
            "subcategory":"Construction",
            "type":"Services"
        }
    ],
    "sg:phone":"+1 951 242 8550",
    "sg:postcode":"92551",
    "sg:province":"CA",
    "sg:tags":[
        "contractor"
    ],
    "wof:name":"A & A Building Cleaning",
    "wof:placetype":"venue"
},
  "geometry": {"coordinates":[-117.212372,33.894433],"type":"Point"}
}