{
  "type": "Feature",
  "properties": {
    "iso:country":"US",
    "sg:address":"3814 Montaro Ln",
    "sg:city":"Stockton",
    "sg:classifiers":[
        {
            "category":"Freight",
            "type":"Transportation"
        }
    ],
    "sg:phone":"+1 209 609 1269",
    "sg:postcode":"95212",
    "sg:province":"CA",
    "wof:name":"Perez & Sons Transportation",
    "wof:placetype":"venue"
},
  "geometry": {"coordinates":[-121.26343199999999,38.037549],"type":"Point"}
}