{
  "type": "Feature",
  "properties": {
    "addr:full":"4111 S Central Ave Los Angeles CA 90011",
    "addr:housenumber":"4111",
    "addr:postcode":"90011",
    "addr:street":"S Central Ave",
    "iso:country":"US",
    "sg:address":"4111 S Central Ave",
    "sg:city":"Los Angeles",
    "sg:classifiers":[
        {
            "category":"Autos & Motor Vehicles",
            "subcategory":"Automobile Sales",
            "type":"Retail Goods"
        }
    ],
    "sg:phone":"+1 323 233 5536",
    "sg:postcode":"90011",
    "sg:province":"CA",
    "sg:tags":[
        "car",
        "dealer"
    ],
    "wof:name":"PCS Auto Svc",
    "wof:placetype":"venue"
},
  "geometry": {"coordinates":[-118.256569,34.008558],"type":"Point"}
}