{
  "type": "Feature",
  "properties": {
    "addr:full":"7441 Auburn Blvd Citrus Heights CA 95610",
    "addr:housenumber":"7441",
    "addr:postcode":"95610",
    "addr:street":"Auburn Blvd",
    "iso:country":"US",
    "sg:address":"7441 Auburn Blvd",
    "sg:city":"Citrus Heights",
    "sg:classifiers":[
        {
            "category":"Retail",
            "subcategory":"Auto Repair",
            "type":"Services"
        }
    ],
    "sg:phone":"+1 916 722 4863",
    "sg:postcode":"95610",
    "sg:province":"CA",
    "sg:tags":[
        "repairing",
        "automobile"
    ],
    "wof:name":"Derek's Auto Svc",
    "wof:placetype":"venue"
},
  "geometry": {"coordinates":[-121.29044500000001,38.70113],"type":"Point"}
}