{
  "type": "Feature",
  "properties": {
    "iso:country":"US",
    "sg:address":"1233 Oak Ave",
    "sg:city":"Carlsbad",
    "sg:classifiers":[
        {
            "category":"Manufacturing",
            "subcategory":"Toys & Sporting Goods",
            "type":"Manufacturing & Wholesale Goods"
        }
    ],
    "sg:phone":"+1 760 434 5934",
    "sg:postcode":"92008",
    "sg:province":"CA",
    "sg:tags":[
        "mfg"
    ],
    "wof:name":"Dan Foam",
    "wof:placetype":"venue"
},
  "geometry": {"coordinates":[-117.338195,33.163934],"type":"Point"}
}