{
  "type": "Feature",
  "properties": {
    "iso:country":"US",
    "sg:address":"37767 Fremont Blvd",
    "sg:city":"Fremont",
    "sg:classifiers":[
        {
            "category":"Real Estate",
            "subcategory":"Real Estate Operator",
            "type":"Services"
        }
    ],
    "sg:phone":"+1 510 797 5099",
    "sg:postcode":"94536",
    "sg:province":"CA",
    "sg:tags":[
        "apartment"
    ],
    "wof:name":"Pepper Tree Apartments",
    "wof:placetype":"venue"
},
  "geometry": {"coordinates":[-122.002118,37.555577],"type":"Point"}
}