{
  "type": "Feature",
  "properties": {
    "iso:country":"US",
    "sg:address":"6154 Pso Jaquita",
    "sg:city":"Carlsbad",
    "sg:classifiers":[
        {
            "category":"Retail",
            "subcategory":"Animal Services",
            "type":"Services"
        }
    ],
    "sg:phone":"+1 760 476 9413",
    "sg:postcode":"92009",
    "sg:province":"CA",
    "wof:name":"Affection Dog Training",
    "wof:placetype":"venue"
},
  "geometry": {"coordinates":[-117.241743,33.125675],"type":"Point"}
}