{
  "type": "Feature",
  "properties": {
    "addr:full":"11622 Salinaz Ave Garden Grove CA 92843",
    "addr:housenumber":"11622",
    "addr:postcode":"92843",
    "addr:street":"Salinaz Ave",
    "iso:country":"US",
    "sg:address":"11622 Salinaz Ave",
    "sg:city":"Garden Grove",
    "sg:classifiers":[
        {
            "category":"Professional",
            "type":"Services"
        }
    ],
    "sg:phone":"+1 714 636 3808",
    "sg:postcode":"92843",
    "sg:province":"CA",
    "sg:tags":[
        "instrument",
        "teacher",
        "musical"
    ],
    "wof:name":"GOVA",
    "wof:placetype":"venue"
},
  "geometry": {"coordinates":[-117.927001,33.76407],"type":"Point"}
}