{
  "type": "Feature",
  "properties": {
    "iso:country":"US",
    "sg:address":"255 Forest Ave",
    "sg:city":"Laguna Beach",
    "sg:classifiers":[
        {
            "category":"Organizations",
            "subcategory":"Community Association",
            "type":"Services"
        }
    ],
    "sg:phone":"+1 949 376 0245",
    "sg:postcode":"92651",
    "sg:province":"CA",
    "sg:tags":[
        "club"
    ],
    "wof:name":"Boardriders Club",
    "wof:placetype":"venue"
},
  "geometry": {"coordinates":[-117.782917,33.542499],"type":"Point"}
}