{
  "type": "Feature",
  "properties": {
    "addr:full":"1810 W Fremont St Stockton CA 95203",
    "addr:housenumber":"1810",
    "addr:postcode":"95203",
    "addr:street":"W Fremont St",
    "iso:country":"US",
    "sg:address":"1810 W Fremont St",
    "sg:city":"Stockton",
    "sg:classifiers":[
        {
            "category":"Shopping",
            "type":"Retail Goods"
        }
    ],
    "sg:phone":"+1 209 467 7727",
    "sg:postcode":"95203",
    "sg:province":"CA",
    "sg:tags":[
        "spa",
        "hot",
        "tub"
    ],
    "sg:website":"www.heavenlyspa.com",
    "wof:name":"Heavenly Spa & Stove",
    "wof:placetype":"venue"
},
  "geometry": {"coordinates":[-121.31992700000001,37.955512],"type":"Point"}
}