{
  "type": "Feature",
  "properties": {
    "iso:country":"US",
    "sg:address":"5001 Windplay Dr",
    "sg:city":"El Dorado Hills",
    "sg:classifiers":[
        {
            "category":"Wholesale",
            "subcategory":"Electrical",
            "type":"Manufacturing & Wholesale Goods"
        }
    ],
    "sg:phone":"+1 916 941 8099",
    "sg:postcode":"95762",
    "sg:province":"CA",
    "sg:tags":[
        "control",
        "security",
        "system"
    ],
    "wof:name":"Access Systems",
    "wof:placetype":"venue"
},
  "geometry": {"coordinates":[-121.071224,38.636984],"type":"Point"}
}