{
  "type": "Feature",
  "properties": {
    "addr:full":"1200 N Alvarado St Los Angeles CA 90026",
    "addr:housenumber":"1200",
    "addr:postcode":"90026",
    "addr:street":"N Alvarado St",
    "iso:country":"US",
    "sg:address":"1200 N Alvarado St",
    "sg:city":"Los Angeles",
    "sg:classifiers":[
        {
            "category":"Arts & Performance",
            "subcategory":"Art Gallery",
            "type":"Entertainment"
        }
    ],
    "sg:phone":"+1 213 483 8761",
    "sg:postcode":"90026",
    "sg:province":"CA",
    "sg:website":"machineproject.com/",
    "wof:name":"Machine Project",
    "wof:placetype":"venue"
},
  "geometry": {"coordinates":[-118.26286399999999,34.078137],"type":"Point"}
}