{
  "type": "Feature",
  "properties": {
    "addr:full":"4640 Admiralty Way Marina del Rey CA 90292",
    "addr:housenumber":"4640",
    "addr:postcode":"90292",
    "addr:street":"Admiralty Way",
    "iso:country":"US",
    "sg:address":"4640 Admiralty Way",
    "sg:city":"Marina del Rey",
    "sg:classifiers":[
        {
            "category":"Health Services",
            "subcategory":"Dentist",
            "type":"Services"
        }
    ],
    "sg:phone":"+1 310 821 0839",
    "sg:postcode":"90292",
    "sg:province":"CA",
    "wof:name":"Heather Winther, DDS",
    "wof:placetype":"venue"
},
  "geometry": {"coordinates":[-118.441039,33.981348],"type":"Point"}
}