{
  "type": "Feature",
  "properties": {
    "iso:country":"US",
    "sg:address":"246 W el Roblar Dr",
    "sg:city":"Ojai",
    "sg:classifiers":[
        {
            "category":"Food & Beverages",
            "subcategory":"Groceries & Convenience Stores",
            "type":"Retail Goods"
        }
    ],
    "sg:phone":"+1 805 646 1021",
    "sg:postcode":"93023",
    "sg:province":"CA",
    "wof:name":"Tony's American Gas",
    "wof:placetype":"venue"
},
  "geometry": {"coordinates":[-119.27776799999999,34.4489],"type":"Point"}
}