{
  "type": "Feature",
  "properties": {
    "iso:country":"US",
    "sg:address":"831 E Ave K",
    "sg:city":"Lancaster",
    "sg:classifiers":[
        {
            "category":"Shopping",
            "subcategory":"Pharmacy",
            "type":"Retail Goods"
        }
    ],
    "sg:phone":"+1 661 940 1626",
    "sg:postcode":"93535",
    "sg:province":"CA",
    "sg:website":"www.wallgreens.com",
    "wof:name":"Walgreens",
    "wof:placetype":"venue"
},
  "geometry": {"coordinates":[-118.112668,34.675043],"type":"Point"}
}