{
  "type": "Feature",
  "properties": {
    "iso:country":"US",
    "sg:address":"7977 Broadway Ave Ste B",
    "sg:city":"Lemon Grove",
    "sg:classifiers":[
        {
            "category":"Restaurant",
            "type":"Food & Drink"
        }
    ],
    "sg:phone":"+1 619 462 1792",
    "sg:postcode":"91945",
    "sg:province":"CA",
    "sg:tags":[
        "seafood",
        "mexican"
    ],
    "wof:name":"Los Rios Mexican & Seafood",
    "wof:placetype":"venue"
},
  "geometry": {"coordinates":[-117.048142,32.715147],"type":"Point"}
}