{
  "type": "Feature",
  "properties": {
    "addr:full":"155 Estates Dr Danville CA 94526",
    "addr:housenumber":"155",
    "addr:postcode":"94526",
    "addr:street":"Estates Dr",
    "iso:country":"US",
    "sg:address":"155 Estates Dr",
    "sg:city":"Danville",
    "sg:classifiers":[
        {
            "category":"Professional",
            "type":"Services"
        }
    ],
    "sg:phone":"+1 925 685 7979",
    "sg:postcode":"94526",
    "sg:province":"CA",
    "wof:name":"Cities of Refuge",
    "wof:placetype":"venue"
},
  "geometry": {"coordinates":[-121.996937,37.816471],"type":"Point"}
}