{
  "type": "Feature",
  "properties": {
    "iso:country":"US",
    "sg:address":"973 Enterprise Way",
    "sg:city":"Napa",
    "sg:classifiers":[
        {
            "category":"Building & Trades",
            "subcategory":"Construction",
            "type":"Services"
        }
    ],
    "sg:phone":"+1 707 224 6210",
    "sg:postcode":"94558",
    "sg:province":"CA",
    "sg:tags":[
        "pipe",
        "line",
        "contractor"
    ],
    "wof:name":"Cal Smith & Sons Inc",
    "wof:placetype":"venue"
},
  "geometry": {"coordinates":[-122.276113,38.258913],"type":"Point"}
}