{
  "type": "Feature",
  "properties": {
    "addr:full":"145 S Maclay St San Fernando CA 91340",
    "addr:housenumber":"145",
    "addr:postcode":"91340",
    "addr:street":"S Maclay St",
    "iso:country":"US",
    "sg:address":"145 S Maclay St",
    "sg:city":"San Fernando",
    "sg:classifiers":[
        {
            "category":"Food & Beverages",
            "subcategory":"Specialty",
            "type":"Retail Goods"
        }
    ],
    "sg:phone":"+1 818 361 4680",
    "sg:postcode":"91340",
    "sg:province":"CA",
    "sg:tags":[
        "health",
        "diet"
    ],
    "wof:name":"Plaza Nutrition Ctr",
    "wof:placetype":"venue"
},
  "geometry": {"coordinates":[-118.441496,34.283265],"type":"Point"}
}