{
  "type": "Feature",
  "properties": {
    "iso:country":"US",
    "sg:address":"5600 Ave Encinas",
    "sg:city":"Carlsbad",
    "sg:classifiers":[
        {
            "category":"Farming",
            "subcategory":"Nursery",
            "type":"Manufacturing & Wholesale Goods"
        }
    ],
    "sg:phone":"+1 760 930 9644",
    "sg:postcode":"92008",
    "sg:province":"CA",
    "sg:tags":[
        "ornamental"
    ],
    "wof:name":"O&J Growers",
    "wof:placetype":"venue"
},
  "geometry": {"coordinates":[-117.325232,33.124411],"type":"Point"}
}