{
  "type": "Feature",
  "properties": {
    "addr:full":"6281 Beach Blvd Ste 325 Buena Park CA 90621",
    "addr:housenumber":"6281",
    "addr:postcode":"90621",
    "addr:street":"Beach Blvd Ste 325",
    "iso:country":"US",
    "sg:address":"6281 Beach Blvd Ste 325",
    "sg:city":"Buena Park",
    "sg:classifiers":[
        {
            "category":"Professional",
            "subcategory":"Lawyer & Legal Services",
            "type":"Services"
        }
    ],
    "sg:phone":"+1 714 786 6835",
    "sg:postcode":"90621",
    "sg:province":"CA",
    "sg:website":"www.medinalawgroup.net",
    "wof:name":"Law Office Of Charles Medina",
    "wof:placetype":"venue"
},
  "geometry": {"coordinates":[-118.000135,33.869275],"type":"Point"}
}