{
  "type": "Feature",
  "properties": {
    "iso:country":"US",
    "sg:address":"1320 N Wilton Pl",
    "sg:city":"Los Angeles",
    "sg:classifiers":[
        {
            "category":"Communications",
            "subcategory":"Film & Video Production",
            "type":"Services"
        }
    ],
    "sg:phone":"+1 323 962 7010",
    "sg:postcode":"90028",
    "sg:province":"CA",
    "sg:tags":[
        "motion",
        "picture"
    ],
    "wof:name":"Media Shop",
    "wof:placetype":"venue"
},
  "geometry": {"coordinates":[-118.313583,34.095811],"type":"Point"}
}