{
  "type": "Feature",
  "properties": {
    "iso:country":"US",
    "sg:address":"30009 Rd 196",
    "sg:city":"Exeter",
    "sg:classifiers":[
        {
            "category":"Shopping",
            "subcategory":"Bicycles & Sporting Goods",
            "type":"Retail Goods"
        }
    ],
    "sg:phone":"+1 559 592 5223",
    "sg:postcode":"93221",
    "sg:province":"CA",
    "wof:name":"High Sierra Firearms",
    "wof:placetype":"venue"
},
  "geometry": {"coordinates":[-119.134591,36.340393],"type":"Point"}
}