{
  "type": "Feature",
  "properties": {
    "iso:country":"US",
    "sg:address":"7003 Topanga Canyon Blvd",
    "sg:city":"Canoga Park",
    "sg:classifiers":[
        {
            "category":"Wholesale",
            "subcategory":"Painting Supplies",
            "type":"Manufacturing & Wholesale Goods"
        }
    ],
    "sg:phone":"+1 818 598 0401",
    "sg:postcode":"91303",
    "sg:province":"CA",
    "sg:tags":[
        "paint"
    ],
    "wof:name":"Dunn-Edwards Paints",
    "wof:placetype":"venue"
},
  "geometry": {"coordinates":[-118.60592,34.199154],"type":"Point"}
}