{
  "type": "Feature",
  "properties": {
    "iso:country":"US",
    "sg:address":"26500 Encinal Rd",
    "sg:city":"Salinas",
    "sg:classifiers":[
        {
            "category":"Farming",
            "subcategory":"Nursery",
            "type":"Manufacturing & Wholesale Goods"
        }
    ],
    "sg:phone":"+1 831 422 4813",
    "sg:postcode":"93908",
    "sg:province":"CA",
    "sg:tags":[
        "florist",
        "rose",
        "grower"
    ],
    "wof:name":"Central Coast Greenhouse",
    "wof:placetype":"venue"
},
  "geometry": {"coordinates":[-121.501167,36.62432],"type":"Point"}
}