{
  "type": "Feature",
  "properties": {
    "addr:full":"3030 McMillan Ave San Luis Obispo CA 93401",
    "addr:housenumber":"3030",
    "addr:postcode":"93401",
    "addr:street":"Mcmillan Ave",
    "iso:country":"US",
    "sg:address":"3030 McMillan Ave",
    "sg:city":"San Luis Obispo",
    "sg:classifiers":[
        {
            "category":"Shopping",
            "subcategory":"Clothing, Apparel, & Fashions",
            "type":"Retail Goods"
        }
    ],
    "sg:phone":"+1 805 541 5756",
    "sg:postcode":"93401",
    "sg:province":"CA",
    "wof:name":"Resurrection Rodeo",
    "wof:placetype":"venue"
},
  "geometry": {"coordinates":[-120.64803000000001,35.262589],"type":"Point"}
}