{
  "type": "Feature",
  "properties": {
    "iso:country":"US",
    "sg:address":"1755 Indian Hill Blvd",
    "sg:city":"Pomona",
    "sg:classifiers":[
        {
            "category":"Restaurant",
            "type":"Food & Drink"
        }
    ],
    "sg:phone":"+1 909 626 2122",
    "sg:postcode":"91767",
    "sg:province":"CA",
    "wof:name":"Carl's Jr",
    "wof:placetype":"venue"
},
  "geometry": {"coordinates":[-117.719325,34.078517],"type":"Point"}
}