{
  "type": "Feature",
  "properties": {
    "addr:full":"7601 Imperial Hwy Downey CA 90242",
    "addr:housenumber":"7601",
    "addr:postcode":"90242",
    "addr:street":"Imperial Hwy",
    "iso:country":"US",
    "sg:address":"7601 Imperial Hwy",
    "sg:city":"Downey",
    "sg:classifiers":[
        {
            "category":"Health Services",
            "subcategory":"Doctor",
            "type":"Services"
        }
    ],
    "sg:phone":"+1 562 803 6691",
    "sg:postcode":"90242",
    "sg:province":"CA",
    "sg:website":"www.ca.gov",
    "wof:name":"California State of",
    "wof:placetype":"venue"
},
  "geometry": {"coordinates":[-118.141998,33.9221],"type":"Point"}
}