{
  "type": "Feature",
  "properties": {
    "addr:full":"22760 Hawthorne Blvd Torrance CA 90505",
    "addr:housenumber":"22760",
    "addr:postcode":"90505",
    "addr:street":"Hawthorne Blvd",
    "iso:country":"US",
    "sg:address":"22760 Hawthorne Blvd",
    "sg:city":"Torrance",
    "sg:classifiers":[
        {
            "category":"Travel",
            "subcategory":"Travel Agent",
            "type":"Entertainment"
        }
    ],
    "sg:phone":"+1 310 791 4660",
    "sg:postcode":"90505",
    "sg:province":"CA",
    "sg:tags":[
        "agency"
    ],
    "wof:name":"Edelweiss Travel",
    "wof:placetype":"venue"
},
  "geometry": {"coordinates":[-118.35089000000001,33.819202],"type":"Point"}
}