{
  "type": "Feature",
  "properties": {
    "addr:full":"16179 Mozart Ave Los Gatos CA 95032",
    "addr:housenumber":"16179",
    "addr:postcode":"95032",
    "addr:street":"Mozart Ave",
    "iso:country":"US",
    "sg:address":"16179 Mozart Ave",
    "sg:city":"Los Gatos",
    "sg:classifiers":[
        {
            "category":"Building & Trades",
            "subcategory":"Construction",
            "type":"Services"
        }
    ],
    "sg:phone":"+1 408 356 1219",
    "sg:postcode":"95032",
    "sg:province":"CA",
    "sg:tags":[
        "paving",
        "contractor"
    ],
    "wof:name":"Lee H Evans Asphalt Paving",
    "wof:placetype":"venue"
},
  "geometry": {"coordinates":[-121.950906,37.25552],"type":"Point"}
}