{
  "type": "Feature",
  "properties": {
    "addr:full":"4214 el Molino Blvd Chino Hills CA 91709",
    "addr:housenumber":"4214",
    "addr:postcode":"91709",
    "addr:street":"El Molino Blvd",
    "iso:country":"US",
    "sg:address":"4214 el Molino Blvd",
    "sg:city":"Chino Hills",
    "sg:classifiers":[
        {
            "category":"Wholesale",
            "subcategory":"Medical Equipment & Supplies",
            "type":"Manufacturing & Wholesale Goods"
        }
    ],
    "sg:phone":"+1 909 606 2781",
    "sg:postcode":"91709",
    "sg:province":"CA",
    "wof:name":"Sun Systems Inc",
    "wof:placetype":"venue"
},
  "geometry": {"coordinates":[-117.710022,33.974203],"type":"Point"}
}