{
  "type": "Feature",
  "properties": {
    "iso:country":"US",
    "sg:address":"2440 Crazy Horse Ln",
    "sg:city":"Norco",
    "sg:classifiers":[
        {
            "category":"Building & Trades",
            "subcategory":"Electrical",
            "type":"Services"
        }
    ],
    "sg:phone":"+1 951 279 1722",
    "sg:postcode":"92860",
    "sg:province":"CA",
    "sg:tags":[
        "electrical",
        "electric",
        "contractor"
    ],
    "wof:name":"Sparky's Electric",
    "wof:placetype":"venue"
},
  "geometry": {"coordinates":[-117.569076,33.933347],"type":"Point"}
}