{
  "type": "Feature",
  "properties": {
    "iso:country":"US",
    "sg:address":"1308 67th St",
    "sg:city":"Emeryville",
    "sg:classifiers":[
        {
            "category":"Manufacturing",
            "subcategory":"Tools & Machinery",
            "type":"Manufacturing & Wholesale Goods"
        }
    ],
    "sg:phone":"+1 510 652 8847",
    "sg:postcode":"94608",
    "sg:province":"CA",
    "sg:tags":[
        "equipment",
        "pump",
        "pumping",
        "mfg"
    ],
    "wof:name":"Challenge Manufacturing Co",
    "wof:placetype":"venue"
},
  "geometry": {"coordinates":[-122.29108600000001,37.849193],"type":"Point"}
}