{
  "type": "Feature",
  "properties": {
    "iso:country":"US",
    "sg:address":"432 E 9th St",
    "sg:city":"Los Angeles",
    "sg:classifiers":[
        {
            "category":"Shopping",
            "subcategory":"Crafts & Fabrics",
            "type":"Retail Goods"
        }
    ],
    "sg:phone":"+1 213 629 5255",
    "sg:postcode":"90015",
    "sg:province":"CA",
    "sg:tags":[
        "shop",
        "sewing"
    ],
    "wof:name":"Tex Carmel Fabric",
    "wof:placetype":"venue"
},
  "geometry": {"coordinates":[-118.25201800000001,34.038755],"type":"Point"}
}