{
  "type": "Feature",
  "properties": {
    "addr:full":"5225 Shattuck Ave Oakland CA 94609",
    "addr:housenumber":"5225",
    "addr:postcode":"94609",
    "addr:street":"Shattuck Ave",
    "iso:country":"US",
    "sg:address":"5225 Shattuck Ave",
    "sg:city":"Oakland",
    "sg:classifiers":[
        {
            "category":"Retail",
            "subcategory":"Auto Repair",
            "type":"Services"
        }
    ],
    "sg:phone":"+1 510 985 1010",
    "sg:postcode":"94609",
    "sg:province":"CA",
    "sg:tags":[
        "automobile",
        "oil",
        "change",
        "lubrication"
    ],
    "sg:website":"www.speedoilchangecenter.com",
    "wof:name":"Pennzoil Speed Oil Change Center",
    "wof:placetype":"venue"
},
  "geometry": {"coordinates":[-122.264999,37.839802],"type":"Point"}
}