{
  "type": "Feature",
  "properties": {
    "addr:full":"1 Ferry Building  San Francisco CA 94111",
    "addr:housenumber":"1",
    "addr:postcode":"94111",
    "addr:street":"Ferry Building",
    "iso:country":"US",
    "sg:address":"1 Ferry Building ",
    "sg:city":"San Francisco",
    "sg:classifiers":[
        {
            "category":"Restaurant",
            "type":"Food & Drink"
        }
    ],
    "sg:menulink":"http://www.allmenus.com/ca/san-francisco/61840-san-francisco-fish-company/menu/",
    "sg:phone":"+1 415 399 1111",
    "sg:postcode":"94111",
    "sg:province":"CA",
    "sg:tags":[
        "seafood",
        "american"
    ],
    "wof:name":"San Francisco Fish Company",
    "wof:placetype":"venue"
},
  "geometry": {"coordinates":[-122.3937,37.7955],"type":"Point"}
}