{
  "type": "Feature",
  "properties": {
    "iso:country":"US",
    "sg:address":"528 Amalia Ave",
    "sg:city":"Los Angeles",
    "sg:classifiers":[
        {
            "category":"Health Services",
            "subcategory":"Doctor",
            "type":"Services"
        }
    ],
    "sg:phone":"+1 323 263 1677",
    "sg:postcode":"90022",
    "sg:province":"CA",
    "sg:tags":[
        "dentist"
    ],
    "wof:name":"Ramiro S Sanchez DDS",
    "wof:placetype":"venue"
},
  "geometry": {"coordinates":[-118.154196,34.026591],"type":"Point"}
}