{
  "type": "Feature",
  "properties": {
    "addr:full":"3714 Leticia St Chino CA 91710",
    "addr:housenumber":"3714",
    "addr:postcode":"91710",
    "addr:street":"Leticia St",
    "iso:country":"US",
    "sg:address":"3714 Leticia St",
    "sg:city":"Chino",
    "sg:classifiers":[
        {
            "category":"Organizations",
            "subcategory":"Religious Organization",
            "type":"Services"
        }
    ],
    "sg:phone":"+1 909 591 9757",
    "sg:postcode":"91710",
    "sg:province":"CA",
    "sg:tags":[
        "church"
    ],
    "wof:name":"Harvest Light Community Church",
    "wof:placetype":"venue"
},
  "geometry": {"coordinates":[-117.722813,34.007761],"type":"Point"}
}