{
  "type": "Feature",
  "properties": {
    "addr:full":"1701 Lombard Street San Francisco CA 94123",
    "addr:housenumber":"1701",
    "addr:postcode":"94123",
    "addr:street":"Lombard Street",
    "iso:country":"US",
    "sg:address":"1701 Lombard Street",
    "sg:city":"San Francisco",
    "sg:classifiers":[
        {
            "category":"Retail",
            "subcategory":"Laundry & Dry Cleaning",
            "type":"Services"
        }
    ],
    "sg:phone":"+1 415 922 0766",
    "sg:postcode":"94123",
    "sg:province":"CA",
    "wof:name":"Lombard Cleaners",
    "wof:placetype":"venue"
},
  "geometry": {"coordinates":[-122.43000000000001,37.800499],"type":"Point"}
}