{
  "type": "Feature",
  "properties": {
    "addr:full":"73061 el Paseo Palm Desert CA 92260",
    "addr:housenumber":"73061",
    "addr:postcode":"ca 92260",
    "addr:street":"El Paseo",
    "iso:country":"US",
    "sg:address":"73061 el Paseo",
    "sg:city":"Palm Desert",
    "sg:classifiers":[
        {
            "category":"Personal",
            "subcategory":"Beauty Salon",
            "type":"Services"
        }
    ],
    "sg:phone":"+1 760 770 8879",
    "sg:postcode":"92260",
    "sg:province":"CA",
    "wof:name":"Alexandre Studio Salon",
    "wof:placetype":"venue"
},
  "geometry": {"coordinates":[-116.389881,33.719672],"type":"Point"}
}