{
  "type": "Feature",
  "properties": {
    "addr:full":"1817 E Grand Ave Escondido CA 92027",
    "addr:housenumber":"1817",
    "addr:postcode":"92027",
    "addr:street":"E Grand Ave",
    "iso:country":"US",
    "sg:address":"1817 E Grand Ave",
    "sg:city":"Escondido",
    "sg:classifiers":[
        {
            "category":"Real Estate",
            "subcategory":"Real Estate Operator",
            "type":"Services"
        }
    ],
    "sg:phone":"+1 760 747 3900",
    "sg:postcode":"92027",
    "sg:province":"CA",
    "sg:tags":[
        "condominium"
    ],
    "wof:name":"Pepperwood Meadows",
    "wof:placetype":"venue"
},
  "geometry": {"coordinates":[-117.052964,33.132689],"type":"Point"}
}