{
  "type": "Feature",
  "properties": {
    "iso:country":"US",
    "sg:address":"1860 N Main St",
    "sg:city":"Salinas",
    "sg:classifiers":[
        {
            "category":"Shopping",
            "subcategory":"Computers & Home Electronics",
            "type":"Retail Goods"
        }
    ],
    "sg:phone":"+1 831 444 6399",
    "sg:postcode":"93906",
    "sg:province":"CA",
    "sg:tags":[
        "equipment",
        "dealer"
    ],
    "wof:name":"SHR Computing",
    "wof:placetype":"venue"
},
  "geometry": {"coordinates":[-121.65538100000001,36.717752],"type":"Point"}
}