{
  "type": "Feature",
  "properties": {
    "iso:country":"US",
    "sg:address":"1102 Sanchez St",
    "sg:city":"San Francisco",
    "sg:classifiers":[
        {
            "category":"Health Services",
            "subcategory":"Clinic",
            "type":"Services"
        }
    ],
    "sg:phone":"+1 415 706 0845",
    "sg:postcode":"94114",
    "sg:province":"CA",
    "sg:tags":[
        "counseling",
        "mental"
    ],
    "wof:name":"David Coates, MFT",
    "wof:placetype":"venue"
},
  "geometry": {"coordinates":[-122.429794,37.751331],"type":"Point"}
}