{
  "type": "Feature",
  "properties": {
    "addr:full":"3338 Cowley Way San Diego CA 92117",
    "addr:housenumber":"3338",
    "addr:postcode":"92117",
    "addr:street":"Cowley Way",
    "iso:country":"US",
    "sg:address":"3338 Cowley Way",
    "sg:city":"San Diego",
    "sg:classifiers":[
        {
            "category":"Professional",
            "type":"Services"
        }
    ],
    "sg:phone":"+1 619 276 7649",
    "sg:postcode":"92117",
    "sg:province":"CA",
    "wof:name":"Caltone",
    "wof:placetype":"venue"
},
  "geometry": {"coordinates":[-117.195303,32.80394],"type":"Point"}
}