{
  "type": "Feature",
  "properties": {
    "iso:country":"US",
    "sg:address":"25422 Trabuco Rd",
    "sg:city":"Lake Forest",
    "sg:classifiers":[
        {
            "category":"Health Services",
            "subcategory":"Health Practitioner",
            "type":"Services"
        }
    ],
    "sg:phone":"+1 949 951 5971",
    "sg:postcode":"92630",
    "sg:province":"CA",
    "sg:tags":[
        "hypnotist"
    ],
    "wof:name":"Visual Arts Hypnotherapy",
    "wof:placetype":"venue"
},
  "geometry": {"coordinates":[-117.68738500000001,33.648758],"type":"Point"}
}