{
  "type": "Feature",
  "properties": {
    "addr:full":"135 E. Commonwealth Ave Fullerton CA 92832",
    "addr:housenumber":"135",
    "addr:postcode":"92832",
    "addr:street":"E. Commonwealth Ave",
    "iso:country":"US",
    "sg:address":"135 E. Commonwealth Ave",
    "sg:city":"Fullerton",
    "sg:classifiers":[
        {
            "category":"Personal",
            "subcategory":"Barber",
            "type":"Services"
        }
    ],
    "sg:phone":"+1 714 626 0097",
    "sg:postcode":"92832",
    "sg:province":"CA",
    "sg:website":"www.theclassicbarbers.com",
    "wof:name":"Classic Barbers",
    "wof:placetype":"venue"
},
  "geometry": {"coordinates":[-117.922473,33.870423],"type":"Point"}
}