{
  "type": "Feature",
  "properties": {
    "addr:full":"20 Pleasant Valley Dr Walnut Creek CA 94597",
    "addr:housenumber":"20",
    "addr:postcode":"94597",
    "addr:street":"Pleasant Valley Dr",
    "iso:country":"US",
    "sg:address":"20 Pleasant Valley Dr",
    "sg:city":"Walnut Creek",
    "sg:classifiers":[
        {
            "category":"Personal",
            "type":"Services"
        }
    ],
    "sg:phone":"+1 925 708 5367",
    "sg:postcode":"94597",
    "sg:province":"CA",
    "sg:tags":[
        "therapist",
        "massage"
    ],
    "wof:name":"Divine Touch",
    "wof:placetype":"venue"
},
  "geometry": {"coordinates":[-122.064408,37.932233],"type":"Point"}
}