{
  "type": "Feature",
  "properties": {
    "addr:full":"73416 Joshua Tree St Palm Desert CA 92260",
    "addr:housenumber":"73416",
    "addr:postcode":"92260",
    "addr:street":"Joshua Tree St",
    "iso:country":"US",
    "sg:address":"73416 Joshua Tree St",
    "sg:city":"Palm Desert",
    "sg:classifiers":[
        {
            "category":"Building & Trades",
            "subcategory":"Construction",
            "type":"Services"
        }
    ],
    "sg:phone":"+1 760 831 0647",
    "sg:postcode":"92260",
    "sg:province":"CA",
    "sg:tags":[
        "hanging",
        "contractor"
    ],
    "wof:name":"Ken Ealy Painting",
    "wof:placetype":"venue"
},
  "geometry": {"coordinates":[-116.38484,33.717085],"type":"Point"}
}