{
  "type": "Feature",
  "properties": {
    "iso:country":"US",
    "sg:address":"2732 24th St",
    "sg:city":"San Francisco",
    "sg:classifiers":[
        {
            "category":"Restaurant",
            "type":"Food & Drink"
        }
    ],
    "sg:menulink":"http://www.allmenus.com/ca/san-francisco/81817-manivanh/menu/",
    "sg:phone":"+1 415 824 6059",
    "sg:postcode":"94110",
    "sg:province":"CA",
    "sg:tags":[
        "thai",
        "asian"
    ],
    "wof:name":"Manivanh",
    "wof:placetype":"venue"
},
  "geometry": {"coordinates":[-122.407006,37.752957],"type":"Point"}
}