{
  "type": "Feature",
  "properties": {
    "iso:country":"US",
    "sg:address":"2501 Winchester Blvd",
    "sg:city":"Campbell",
    "sg:classifiers":[
        {
            "category":"Cinema",
            "subcategory":"Movie Theater",
            "type":"Entertainment"
        }
    ],
    "sg:phone":"+1 408 378 2434",
    "sg:postcode":"95008",
    "sg:province":"CA",
    "wof:name":"Movie Bargain Cinemas",
    "wof:placetype":"venue"
},
  "geometry": {"coordinates":[-121.949755,37.279471],"type":"Point"}
}