{
  "type": "Feature",
  "properties": {
    "addr:full":"2811 McKee Road San Jose CA 95127",
    "addr:housenumber":"2811",
    "addr:postcode":"95127",
    "addr:street":"Mckee Road",
    "iso:country":"US",
    "sg:address":"2811 McKee Road",
    "sg:city":"San Jose",
    "sg:classifiers":[
        {
            "category":"Real Estate",
            "subcategory":"Real Estate Operator",
            "type":"Services"
        }
    ],
    "sg:phone":"+1 408 272 5205",
    "sg:postcode":"95127",
    "sg:province":"CA",
    "sg:tags":[
        "apartment"
    ],
    "sg:website":"www.peppertree-apartments.com",
    "wof:name":"Peppertree Apartments",
    "wof:placetype":"venue"
},
  "geometry": {"coordinates":[-121.83927799999999,37.368746],"type":"Point"}
}