{
  "type": "Feature",
  "properties": {
    "addr:full":"3326 Nyeland Ave Oxnard CA 93036",
    "addr:housenumber":"3326",
    "addr:postcode":"93036",
    "addr:street":"Nyeland Ave",
    "iso:country":"US",
    "sg:address":"3326 Nyeland Ave",
    "sg:city":"Oxnard",
    "sg:classifiers":[
        {
            "category":"Education",
            "subcategory":"Special Training",
            "type":"Public Place"
        },
        {
            "category":"Organizations",
            "subcategory":"Religious Organization",
            "type":"Services"
        }
    ],
    "sg:phone":"+1 805 485 7072",
    "sg:postcode":"93036",
    "sg:province":"CA",
    "sg:tags":[
        "school",
        "specialty"
    ],
    "wof:name":"Channel Islands Bible College & Seminary",
    "wof:placetype":"venue"
},
  "geometry": {"coordinates":[-119.136036,34.223868],"type":"Point"}
}