{
  "type": "Feature",
  "properties": {
    "iso:country":"US",
    "sg:address":"370 Amapola Ave",
    "sg:city":"Torrance",
    "sg:classifiers":[
        {
            "category":"Banks & Credit Unions",
            "subcategory":"Financial Services",
            "type":"Services"
        }
    ],
    "sg:phone":"+1 310 642 0200",
    "sg:postcode":"90501",
    "sg:province":"CA",
    "sg:tags":[
        "sell",
        "management",
        "investment",
        "computing"
    ],
    "wof:name":"Nova Communications Limited",
    "wof:placetype":"venue"
},
  "geometry": {"coordinates":[-118.323387,33.844828],"type":"Point"}
}