{
  "type": "Feature",
  "properties": {
    "iso:country":"US",
    "sg:address":"509 N Van Ness Ave",
    "sg:city":"Fresno",
    "sg:classifiers":[
        {
            "category":"Shopping",
            "subcategory":"Music",
            "type":"Retail Goods"
        }
    ],
    "sg:phone":"+1 559 237 6976",
    "sg:postcode":"93728",
    "sg:province":"CA",
    "sg:tags":[
        "video",
        "disc",
        "tape",
        "cassette"
    ],
    "wof:name":"M & T Video",
    "wof:placetype":"venue"
},
  "geometry": {"coordinates":[-119.798952,36.752871],"type":"Point"}
}