{
  "type": "Feature",
  "properties": {
    "iso:country":"US",
    "sg:address":"939 Addison St",
    "sg:city":"Berkeley",
    "sg:classifiers":[
        {
            "category":"Building & Trades",
            "subcategory":"Landscaping Services",
            "type":"Services"
        }
    ],
    "sg:phone":"+1 510 841 1541",
    "sg:postcode":"94710",
    "sg:province":"CA",
    "wof:name":"Well-Tended Garden",
    "wof:placetype":"venue"
},
  "geometry": {"coordinates":[-122.294257,37.8674],"type":"Point"}
}