{
  "type": "Feature",
  "properties": {
    "iso:country":"US",
    "sg:address":"2150 E Tahquitz Canyon Way",
    "sg:city":"Palm Springs",
    "sg:classifiers":[
        {
            "category":"Social Services",
            "type":"Services"
        }
    ],
    "sg:phone":"+1 760 323 8016",
    "sg:postcode":"92262",
    "sg:province":"CA",
    "sg:tags":[
        "counselor",
        "marriage",
        "family"
    ],
    "wof:name":"Inland Psychotherapy Group",
    "wof:placetype":"venue"
},
  "geometry": {"coordinates":[-116.522157,33.823238],"type":"Point"}
}