{
  "type": "Feature",
  "properties": {
    "iso:country":"US",
    "sg:address":"4990 Vanderbilt St",
    "sg:city":"Ontario",
    "sg:classifiers":[
        {
            "category":"Professional",
            "subcategory":"Advertising",
            "type":"Services"
        }
    ],
    "sg:phone":"+1 909 605 8977",
    "sg:postcode":"91761",
    "sg:province":"CA",
    "sg:tags":[
        "distribution"
    ],
    "wof:name":"North American Composites",
    "wof:placetype":"venue"
},
  "geometry": {"coordinates":[-117.543294,34.045146],"type":"Point"}
}