{
  "type": "Feature",
  "properties": {
    "iso:country":"US",
    "sg:address":"3335 Homestead Rd",
    "sg:city":"Santa Clara",
    "sg:classifiers":[
        {
            "category":"Freight",
            "type":"Transportation"
        }
    ],
    "sg:phone":"+1 408 781 1169",
    "sg:postcode":"95051",
    "sg:province":"CA",
    "sg:tags":[
        "operator",
        "trucking"
    ],
    "wof:name":"Los Gatos Saratoga Haulin",
    "wof:placetype":"venue"
},
  "geometry": {"coordinates":[-121.989519,37.337939],"type":"Point"}
}