{
  "type": "Feature",
  "properties": {
    "iso:country":"US",
    "sg:address":"5409 Oneill Ct",
    "sg:city":"Bakersfield",
    "sg:classifiers":[
        {
            "category":"Shopping",
            "type":"Retail Goods"
        }
    ],
    "sg:phone":"+1 661 837 0533",
    "sg:postcode":"93307",
    "sg:province":"CA",
    "sg:tags":[
        "merchandising"
    ],
    "wof:name":"Three Js Afrcan Amercn Gift Sp",
    "wof:placetype":"venue"
},
  "geometry": {"coordinates":[-119.02021000000001,35.305441],"type":"Point"}
}