{
  "type": "Feature",
  "properties": {
    "iso:country":"US",
    "sg:address":"481 Twin View Blvd",
    "sg:city":"Redding",
    "sg:classifiers":[
        {
            "category":"Building & Trades",
            "subcategory":"Cleaning & Sanitation",
            "type":"Services"
        }
    ],
    "sg:phone":"+1 530 246 7585",
    "sg:postcode":"96003",
    "sg:province":"CA",
    "sg:tags":[
        "janitor"
    ],
    "wof:name":"Hernandez Janitorial Svc",
    "wof:placetype":"venue"
},
  "geometry": {"coordinates":[-122.373974,40.615702],"type":"Point"}
}