{
  "type": "Feature",
  "properties": {
    "iso:country":"US",
    "sg:address":"14072 Magnolia St",
    "sg:city":"Westminster",
    "sg:classifiers":[
        {
            "category":"Shopping",
            "subcategory":"Beauty & Cosmetics",
            "type":"Retail Goods"
        }
    ],
    "sg:phone":"+1 714 899 3641",
    "sg:postcode":"92683",
    "sg:province":"CA",
    "sg:tags":[
        "supply"
    ],
    "wof:name":"DK Beauty Supply",
    "wof:placetype":"venue"
},
  "geometry": {"coordinates":[-117.97232,33.757891],"type":"Point"}
}