{
  "type": "Feature",
  "properties": {
    "addr:full":"2210 Foxhill Dr Martinez CA 94553",
    "addr:housenumber":"2210",
    "addr:postcode":"94553",
    "addr:street":"Foxhill Dr",
    "iso:country":"US",
    "sg:address":"2210 Foxhill Dr",
    "sg:city":"Martinez",
    "sg:classifiers":[
        {
            "category":"Travel",
            "subcategory":"Travel Agent",
            "type":"Entertainment"
        }
    ],
    "sg:phone":"+1 925 370 2277",
    "sg:postcode":"94553",
    "sg:province":"CA",
    "sg:tags":[
        "agency"
    ],
    "wof:name":"Prima Travel",
    "wof:placetype":"venue"
},
  "geometry": {"coordinates":[-122.082734,37.993165],"type":"Point"}
}