{
  "type": "Feature",
  "properties": {
    "addr:full":"2605 Morena Blvd San Diego CA 92110",
    "addr:housenumber":"2605",
    "addr:postcode":"92110",
    "addr:street":"Morena Blvd",
    "iso:country":"US",
    "sg:address":"2605 Morena Blvd",
    "sg:city":"San Diego",
    "sg:classifiers":[
        {
            "category":"Restaurant",
            "type":"Food & Drink"
        }
    ],
    "sg:menulink":"http://www.allmenus.com/ca/san-diego/178832-jack-in-the-box/menu/",
    "sg:phone":"+1 619 276 5720",
    "sg:postcode":"92110",
    "sg:province":"CA",
    "sg:tags":[
        "burger",
        "american"
    ],
    "wof:name":"Jack in the Box",
    "wof:placetype":"venue"
},
  "geometry": {"coordinates":[-117.204944,32.790071],"type":"Point"}
}