{
  "type": "Feature",
  "properties": {
    "addr:full":"216 Cayuga St Santa Cruz CA 95062",
    "addr:housenumber":"216",
    "addr:postcode":"95062",
    "addr:street":"Cayuga St",
    "iso:country":"US",
    "sg:address":"216 Cayuga St",
    "sg:city":"Santa Cruz",
    "sg:classifiers":[
        {
            "category":"Building & Trades",
            "subcategory":"Landscaping Services",
            "type":"Services"
        }
    ],
    "sg:phone":"+1 831 429 1500",
    "sg:postcode":"95062",
    "sg:province":"CA",
    "sg:tags":[
        "tree"
    ],
    "wof:name":"Locatelli Valley Tree Svc",
    "wof:placetype":"venue"
},
  "geometry": {"coordinates":[-122.010385,36.969524],"type":"Point"}
}