{
  "type": "Feature",
  "properties": {
    "addr:full":"1592 Union St Ste 295 San Francisco CA 94123",
    "addr:housenumber":"1592",
    "addr:postcode":"94123",
    "addr:street":"Union St Ste 295",
    "iso:country":"US",
    "sg:address":"1592 Union St Ste 295",
    "sg:city":"San Francisco",
    "sg:classifiers":[
        {
            "category":"Transit Center",
            "subcategory":"Passenger",
            "type":"Transportation"
        },
        {
            "category":"Recreation",
            "subcategory":"Dance Hall",
            "type":"Entertainment"
        }
    ],
    "sg:phone":"+1 415 567 2789",
    "sg:postcode":"94123",
    "sg:province":"CA",
    "sg:tags":[
        "club"
    ],
    "sg:website":"www.partyex.com",
    "wof:name":"Party Express",
    "wof:placetype":"venue"
},
  "geometry": {"coordinates":[-122.425386,37.798464],"type":"Point"}
}