{
  "type": "Feature",
  "properties": {
    "iso:country":"US",
    "sg:address":"799 W Imperial Hwy",
    "sg:city":"Brea",
    "sg:classifiers":[
        {
            "category":"Shopping",
            "subcategory":"Pets & Pet Supplies",
            "type":"Retail Goods"
        }
    ],
    "sg:phone":"+1 714 529 8811",
    "sg:postcode":"92821",
    "sg:province":"CA",
    "sg:tags":[
        "furnishing",
        "dog",
        "store",
        "cat"
    ],
    "wof:name":"Happy Fish Pets",
    "wof:placetype":"venue"
},
  "geometry": {"coordinates":[-117.909576,33.917431],"type":"Point"}
}