{
  "type": "Feature",
  "properties": {
    "iso:country":"US",
    "sg:address":"941 N Mansfield Ave",
    "sg:city":"Los Angeles",
    "sg:classifiers":[
        {
            "category":"Shopping",
            "subcategory":"Computers & Home Electronics",
            "type":"Retail Goods"
        }
    ],
    "sg:phone":"+1 323 465 9769",
    "sg:postcode":"90038",
    "sg:province":"CA",
    "sg:tags":[
        "equipment",
        "satellite",
        "system"
    ],
    "wof:name":"Satellite Films",
    "wof:placetype":"venue"
},
  "geometry": {"coordinates":[-118.3407,34.088176],"type":"Point"}
}