{
  "type": "Feature",
  "properties": {
    "addr:full":"12226 Alondra Blvd Norwalk CA 90650",
    "addr:housenumber":"12226",
    "addr:postcode":"90650",
    "addr:street":"Alondra Blvd",
    "iso:country":"US",
    "sg:address":"12226 Alondra Blvd",
    "sg:city":"Norwalk",
    "sg:classifiers":[
        {
            "category":"Social Services",
            "subcategory":"Child Care",
            "type":"Services"
        }
    ],
    "sg:phone":"+1 562 926 5542",
    "sg:postcode":"90650",
    "sg:province":"CA",
    "sg:tags":[
        "elementary",
        "kindergarten",
        "school",
        "academic"
    ],
    "wof:name":"Faith Preschool",
    "wof:placetype":"venue"
},
  "geometry": {"coordinates":[-118.07199900000001,33.887501],"type":"Point"}
}