{
  "type": "Feature",
  "properties": {
    "iso:country":"US",
    "sg:address":"535 W Allen Ave",
    "sg:city":"San Dimas",
    "sg:classifiers":[
        {
            "category":"Home & Garden",
            "subcategory":"Garden Supply",
            "type":"Retail Goods"
        },
        {
            "category":"Building & Trades",
            "subcategory":"Landscaping Services",
            "type":"Services"
        }
    ],
    "sg:phone":"+1 626 335 1452",
    "sg:postcode":"91773",
    "sg:province":"CA",
    "sg:tags":[
        "sprinkler"
    ],
    "wof:name":"Landworks Landscape",
    "wof:placetype":"venue"
},
  "geometry": {"coordinates":[-117.817002,34.117637],"type":"Point"}
}