{
  "type": "Feature",
  "properties": {
    "addr:full":"13447 Burbank Blvd Sherman Oaks CA 91401",
    "addr:housenumber":"13447",
    "addr:postcode":"91401",
    "addr:street":"Burbank Blvd",
    "iso:country":"US",
    "sg:address":"13447 Burbank Blvd",
    "sg:city":"Sherman Oaks",
    "sg:classifiers":[
        {
            "category":"Real Estate",
            "subcategory":"Real Estate Services",
            "type":"Services"
        }
    ],
    "sg:phone":"+1 818 781 0092",
    "sg:postcode":"91401",
    "sg:province":"CA",
    "sg:tags":[
        "management",
        "property"
    ],
    "wof:name":"Yale Management Services Inc",
    "wof:placetype":"venue"
},
  "geometry": {"coordinates":[-118.425957,34.172277],"type":"Point"}
}