{
  "type": "Feature",
  "properties": {
    "iso:country":"US",
    "sg:address":"4302 Atlantic Ave",
    "sg:city":"Long Beach",
    "sg:classifiers":[
        {
            "category":"Shopping",
            "subcategory":"Books",
            "type":"Retail Goods"
        },
        {
            "category":"Shopping",
            "subcategory":"Comic Books",
            "type":"Retail Goods"
        }
    ],
    "sg:phone":"+1 562 448 2262",
    "sg:postcode":"90807",
    "sg:province":"CA",
    "sg:tags":[
        "bookstore"
    ],
    "sg:website":"www.aCastleofBooks.com",
    "wof:name":"A Castle of Books",
    "wof:placetype":"venue"
},
  "geometry": {"coordinates":[-118.18492,33.834381],"type":"Point"}
}