{
  "type": "Feature",
  "properties": {
    "addr:full":"3750 University Ave Suite 400 Riverside CA 92501",
    "addr:housenumber":"3750",
    "addr:postcode":"92501",
    "addr:street":"University Ave Suite 400",
    "iso:country":"US",
    "sg:address":"3750 University Ave Suite 400",
    "sg:city":"Riverside",
    "sg:classifiers":[
        {
            "category":"Professional",
            "subcategory":"Lawyer & Legal Services",
            "type":"Services"
        }
    ],
    "sg:phone":"+1 951 686 1450",
    "sg:postcode":"92501",
    "sg:province":"CA",
    "sg:tags":[
        "litigation",
        "tort",
        "attorney"
    ],
    "wof:name":"Knox , Parissh A. - Best Best & Krieger",
    "wof:placetype":"venue"
},
  "geometry": {"coordinates":[-117.375092,33.982205],"type":"Point"}
}