{
  "type": "Feature",
  "properties": {
    "addr:full":"4228 N Figueroa St Los Angeles CA 90065",
    "addr:housenumber":"4228",
    "addr:postcode":"90065",
    "addr:street":"N Figueroa St",
    "iso:country":"US",
    "sg:address":"4228 N Figueroa St",
    "sg:city":"Los Angeles",
    "sg:classifiers":[
        {
            "category":"Restaurant",
            "type":"Food & Drink"
        }
    ],
    "sg:menulink":"http://www.allmenus.com/ca/los-angeles/178100-jack-in-the-box/menu/",
    "sg:phone":"+1 323 227 1710",
    "sg:postcode":"90065",
    "sg:province":"CA",
    "sg:tags":[
        "burger",
        "american"
    ],
    "wof:name":"Jack in the Box",
    "wof:placetype":"venue"
},
  "geometry": {"coordinates":[-118.20846899999999,34.094137],"type":"Point"}
}