{
  "type": "Feature",
  "properties": {
    "iso:country":"US",
    "sg:address":"2111 W Magnolia Blvd # A",
    "sg:city":"Burbank",
    "sg:classifiers":[
        {
            "category":"Personal",
            "subcategory":"Shoe Repair & Shine",
            "type":"Services"
        }
    ],
    "sg:phone":"+1 818 845 1686",
    "sg:postcode":"91506",
    "sg:province":"CA",
    "sg:website":"www.johnsshoerepair.com",
    "wof:name":"John's Shoe Repair",
    "wof:placetype":"venue"
},
  "geometry": {"coordinates":[-118.331208,34.173422],"type":"Point"}
}