{
  "type": "Feature",
  "properties": {
    "addr:full":"3682 Edmonton Way Concord CA 94520",
    "addr:housenumber":"3682",
    "addr:postcode":"94520",
    "addr:street":"Edmonton Way",
    "iso:country":"US",
    "sg:address":"3682 Edmonton Way",
    "sg:city":"Concord",
    "sg:classifiers":[
        {
            "category":"Building & Trades",
            "subcategory":"Construction",
            "type":"Services"
        }
    ],
    "sg:phone":"+1 925 671 2202",
    "sg:postcode":"94520",
    "sg:province":"CA",
    "sg:tags":[
        "contractor"
    ],
    "wof:name":"Quality Plastering",
    "wof:placetype":"venue"
},
  "geometry": {"coordinates":[-122.032167,38.004431],"type":"Point"}
}