{
  "type": "Feature",
  "properties": {
    "addr:full":"956 E Jefferson Blvd Los Angeles CA 90011",
    "addr:housenumber":"956",
    "addr:postcode":"90011",
    "addr:street":"E Jefferson Blvd",
    "iso:country":"US",
    "sg:address":"956 E Jefferson Blvd",
    "sg:city":"Los Angeles",
    "sg:classifiers":[
        {
            "category":"Restaurant",
            "type":"Food & Drink"
        }
    ],
    "sg:phone":"+1 323 232 0240",
    "sg:postcode":"90011",
    "sg:province":"CA",
    "sg:tags":[
        "parlor",
        "ice",
        "cream"
    ],
    "wof:name":"Mary's Paleteria",
    "wof:placetype":"venue"
},
  "geometry": {"coordinates":[-118.259811,34.013012],"type":"Point"}
}