{
  "type": "Feature",
  "properties": {
    "iso:country":"US",
    "sg:address":"3550 Wilshire Blvd",
    "sg:city":"Los Angeles",
    "sg:classifiers":[
        {
            "category":"Health Services",
            "subcategory":"Dentist",
            "type":"Services"
        }
    ],
    "sg:phone":"+1 213 251 0066",
    "sg:postcode":"90010",
    "sg:province":"CA",
    "wof:name":"Lee S Yun DDS Inc",
    "wof:placetype":"venue"
},
  "geometry": {"coordinates":[-118.301988,34.160287],"type":"Point"}
}