{
  "type": "Feature",
  "properties": {
    "addr:full":"1100 S Amphlett Blvd San Mateo CA 94402",
    "addr:housenumber":"1100",
    "addr:postcode":"94402",
    "addr:street":"S Amphlett Blvd",
    "iso:country":"US",
    "sg:address":"1100 S Amphlett Blvd",
    "sg:city":"San Mateo",
    "sg:classifiers":[
        {
            "category":"Wholesale",
            "subcategory":"Groceries",
            "type":"Manufacturing & Wholesale Goods"
        }
    ],
    "sg:phone":"+1 650 401 5999",
    "sg:postcode":"94402",
    "sg:province":"CA",
    "sg:tags":[
        "baker"
    ],
    "wof:name":"Saint Chocolate",
    "wof:placetype":"venue"
},
  "geometry": {"coordinates":[-122.304873,37.562084],"type":"Point"}
}