{
  "type": "Feature",
  "properties": {
    "iso:country":"US",
    "sg:address":"1055 W Ave M",
    "sg:city":"Lancaster",
    "sg:classifiers":[
        {
            "category":"Health Services",
            "subcategory":"Health Practitioner",
            "type":"Services"
        }
    ],
    "sg:phone":"+1 661 945 2226",
    "sg:postcode":"93534",
    "sg:province":"CA",
    "sg:tags":[
        "psychotherapist"
    ],
    "wof:name":"Angela Williams",
    "wof:placetype":"venue"
},
  "geometry": {"coordinates":[-118.148407,34.645875],"type":"Point"}
}