{
  "type": "Feature",
  "properties": {
    "addr:full":"804 F St Fresno CA 93706",
    "addr:housenumber":"804",
    "addr:postcode":"93706",
    "addr:street":"F St",
    "iso:country":"US",
    "sg:address":"804 F St",
    "sg:city":"Fresno",
    "sg:classifiers":[
        {
            "category":"Retail",
            "subcategory":"Auto Repair",
            "type":"Services"
        }
    ],
    "sg:phone":"+1 559 233 3271",
    "sg:postcode":"93706",
    "sg:province":"CA",
    "sg:tags":[
        "wrecker"
    ],
    "wof:name":"Felix Auto Mechanic & Towing",
    "wof:placetype":"venue"
},
  "geometry": {"coordinates":[-119.793739,36.729495],"type":"Point"}
}