{
  "type": "Feature",
  "properties": {
    "iso:country":"US",
    "sg:address":"1945 Palm Ave",
    "sg:city":"San Mateo",
    "sg:classifiers":[
        {
            "category":"Home & Garden",
            "subcategory":"Household Appliances",
            "type":"Retail Goods"
        }
    ],
    "sg:phone":"+1 650 576 7821",
    "sg:postcode":"94403",
    "sg:province":"CA",
    "sg:tags":[
        "repair"
    ],
    "wof:name":"Best One Home Appliance",
    "wof:placetype":"venue"
},
  "geometry": {"coordinates":[-122.308841,37.549887],"type":"Point"}
}