{
  "type": "Feature",
  "properties": {
    "addr:full":"2694 Bishop Dr San Ramon CA 94583",
    "addr:housenumber":"2694",
    "addr:postcode":"94583",
    "addr:street":"Bishop Dr",
    "iso:country":"US",
    "sg:address":"2694 Bishop Dr",
    "sg:city":"San Ramon",
    "sg:classifiers":[
        {
            "category":"Banks & Credit Unions",
            "subcategory":"Investment Brokerage",
            "type":"Services"
        }
    ],
    "sg:phone":"+1 925 275 8989",
    "sg:postcode":"94583",
    "sg:province":"CA",
    "sg:tags":[
        "management"
    ],
    "wof:name":"Raymond James Financial Svc",
    "wof:placetype":"venue"
},
  "geometry": {"coordinates":[-121.960239,37.763691],"type":"Point"}
}