{
  "type": "Feature",
  "properties": {
    "addr:full":"226 Benito Avenue Santa Cruz CA 95062",
    "addr:housenumber":"226",
    "addr:postcode":"95062",
    "addr:street":"Benito Avenue",
    "iso:country":"US",
    "sg:address":"226 Benito Avenue",
    "sg:city":"Santa Cruz",
    "sg:classifiers":[
        {
            "category":"Retail",
            "subcategory":"Auto Repair",
            "type":"Services"
        }
    ],
    "sg:phone":"+1 831 427 1221",
    "sg:postcode":"95062",
    "sg:province":"CA",
    "wof:name":"Tim's Auto Electric Specialist",
    "wof:placetype":"venue"
},
  "geometry": {"coordinates":[-122.011815,36.98042],"type":"Point"}
}