{
  "type": "Feature",
  "properties": {
    "addr:full":"20251 Ventura Blvd Woodland Hills CA 91364",
    "addr:housenumber":"20251",
    "addr:postcode":"91364",
    "addr:street":"Ventura Blvd",
    "iso:country":"US",
    "sg:address":"20251 Ventura Blvd",
    "sg:city":"Woodland Hills",
    "sg:classifiers":[
        {
            "category":"Personal",
            "subcategory":"Beauty Salon",
            "type":"Services"
        }
    ],
    "sg:phone":"+1 818 313 9928",
    "sg:postcode":"91364",
    "sg:province":"CA",
    "wof:name":"Millennium Hair Studio",
    "wof:placetype":"venue"
},
  "geometry": {"coordinates":[-118.572451,34.170672],"type":"Point"}
}