{
  "type": "Feature",
  "properties": {
    "addr:full":"24901 Santa Clara St Hayward CA 94544",
    "addr:housenumber":"24901",
    "addr:postcode":"94544",
    "addr:street":"Santa Clara St",
    "iso:country":"US",
    "sg:address":"24901 Santa Clara St",
    "sg:city":"Hayward",
    "sg:classifiers":[
        {
            "category":"Shopping",
            "subcategory":"Mobile Phones",
            "type":"Retail Goods"
        }
    ],
    "sg:phone":"+1 510 785 2376",
    "sg:postcode":"94544",
    "sg:province":"CA",
    "wof:name":"Radioshack",
    "wof:placetype":"venue"
},
  "geometry": {"coordinates":[-122.093002,37.650002],"type":"Point"}
}