{
  "type": "Feature",
  "properties": {
    "addr:full":"5295 Cameron Dr Apt 210 Buena Park CA 90621",
    "addr:housenumber":"5295;210",
    "addr:postcode":"90621",
    "addr:street":"Cameron Dr Apt",
    "iso:country":"US",
    "sg:address":"5295 Cameron Dr Apt 210",
    "sg:city":"Buena Park",
    "sg:classifiers":[
        {
            "category":"Real Estate",
            "subcategory":"Real Estate Operator",
            "type":"Services"
        }
    ],
    "sg:phone":"+1 714 521 6942",
    "sg:postcode":"90621",
    "sg:province":"CA",
    "sg:tags":[
        "apartment"
    ],
    "wof:name":"Country Club Apartments",
    "wof:placetype":"venue"
},
  "geometry": {"coordinates":[-117.99099699999999,33.8825],"type":"Point"}
}