{
  "type": "Feature",
  "properties": {
    "iso:country":"US",
    "sg:address":"1400 S Atlantic Ave",
    "sg:city":"Compton",
    "sg:classifiers":[
        {
            "category":"Retail",
            "subcategory":"Auto Repair",
            "type":"Services"
        }
    ],
    "sg:phone":"+1 310 830 5000",
    "sg:postcode":"90221",
    "sg:province":"CA",
    "sg:tags":[
        "truck"
    ],
    "sg:website":"www.container.com",
    "wof:name":"Martin Container Inc",
    "wof:placetype":"venue"
},
  "geometry": {"coordinates":[-118.188905,33.883645],"type":"Point"}
}