{
  "type": "Feature",
  "properties": {
    "iso:country":"US",
    "sg:address":"425 Anderson Ave",
    "sg:city":"Winters",
    "sg:classifiers":[
        {
            "category":"Education",
            "subcategory":"School",
            "type":"Public Place"
        }
    ],
    "sg:phone":"+1 530 795 6130",
    "sg:postcode":"95694",
    "sg:province":"CA",
    "wof:name":"Winters Middle School",
    "wof:placetype":"venue"
},
  "geometry": {"coordinates":[-121.978836,38.527269],"type":"Point"}
}