{
  "type": "Feature",
  "properties": {
    "iso:country":"US",
    "sg:address":"40531 State Hwy 41",
    "sg:city":"Oakhurst",
    "sg:classifiers":[
        {
            "category":"Personal",
            "subcategory":"Beauty Salon",
            "type":"Services"
        }
    ],
    "sg:phone":"+1 559 683 5566",
    "sg:postcode":"93644",
    "sg:province":"CA",
    "wof:name":"Bonnie's Cutting Edge Salon",
    "wof:placetype":"venue"
},
  "geometry": {"coordinates":[-119.64538400000001,37.336308],"type":"Point"}
}