{
  "type": "Feature",
  "properties": {
    "iso:country":"US",
    "sg:address":"742 Arctic Ave",
    "sg:city":"Santa Maria",
    "sg:classifiers":[
        {
            "category":"Retail",
            "subcategory":"Repair Shop",
            "type":"Services"
        }
    ],
    "sg:phone":"+1 805 928 2028",
    "sg:postcode":"93454",
    "sg:province":"CA",
    "sg:tags":[
        "work",
        "carpentry"
    ],
    "wof:name":"Holenda Eric F Pano Furn Rfini",
    "wof:placetype":"venue"
},
  "geometry": {"coordinates":[-120.425636,34.946042],"type":"Point"}
}