{
  "type": "Feature",
  "properties": {
    "addr:full":"515 San Ramon Valley Blvd Danville CA 94526",
    "addr:housenumber":"515",
    "addr:postcode":"94526",
    "addr:street":"San Ramon Valley Blvd",
    "iso:country":"US",
    "sg:address":"515 San Ramon Valley Blvd",
    "sg:city":"Danville",
    "sg:classifiers":[
        {
            "category":"Restaurant",
            "type":"Food & Drink"
        }
    ],
    "sg:phone":"+1 925 838 8144",
    "sg:postcode":"94526",
    "sg:province":"CA",
    "wof:name":"Marcello's Restaurant",
    "wof:placetype":"venue"
},
  "geometry": {"coordinates":[-121.996655,37.816892],"type":"Point"}
}