{
  "type": "Feature",
  "properties": {
    "addr:full":"1425 E Main St Grass Valley CA 95945",
    "addr:housenumber":"1425",
    "addr:postcode":"95945",
    "addr:street":"E Main St",
    "iso:country":"US",
    "sg:address":"1425 E Main St",
    "sg:city":"Grass Valley",
    "sg:classifiers":[
        {
            "category":"Retail",
            "subcategory":"Auto Repair",
            "type":"Services"
        }
    ],
    "sg:phone":"+1 530 273 3110",
    "sg:postcode":"95945",
    "sg:province":"CA",
    "sg:tags":[
        "repairing",
        "automobile"
    ],
    "wof:name":"Karl's Smog & Repair",
    "wof:placetype":"venue"
},
  "geometry": {"coordinates":[-121.04575800000001,39.231931],"type":"Point"}
}