{
  "type": "Feature",
  "properties": {
    "addr:full":"21188 Calistoga St Middletown CA 95461",
    "addr:housenumber":"21188",
    "addr:postcode":"95461",
    "addr:street":"Calistoga St",
    "iso:country":"US",
    "sg:address":"21188 Calistoga St",
    "sg:city":"Middletown",
    "sg:classifiers":[
        {
            "category":"Food & Beverages",
            "subcategory":"Liquor & Beverages",
            "type":"Retail Goods"
        }
    ],
    "sg:phone":"+1 707 987 3194",
    "sg:postcode":"95461",
    "sg:province":"CA",
    "wof:name":"Noble's Liquor",
    "wof:placetype":"venue"
},
  "geometry": {"coordinates":[-122.61519800000001,38.752495],"type":"Point"}
}