{
  "type": "Feature",
  "properties": {
    "addr:full":"485 Piney Way Morro Bay CA 93442",
    "addr:housenumber":"485",
    "addr:postcode":"93442",
    "addr:street":"Piney Way",
    "iso:country":"US",
    "sg:address":"485 Piney Way",
    "sg:city":"Morro Bay",
    "sg:classifiers":[
        {
            "category":"Organizations",
            "subcategory":"Religious Organization",
            "type":"Services"
        }
    ],
    "sg:phone":"+1 805 772 8659",
    "sg:postcode":"93442",
    "sg:province":"CA",
    "sg:tags":[
        "church"
    ],
    "wof:name":"Presbyterian Church-Morro Bay",
    "wof:placetype":"venue"
},
  "geometry": {"coordinates":[-120.845529,35.361871],"type":"Point"}
}