{
  "type": "Feature",
  "properties": {
    "iso:country":"US",
    "sg:address":"9921 C St",
    "sg:city":"Oakland",
    "sg:classifiers":[
        {
            "category":"Shopping",
            "subcategory":"Hobbies, Toys, & Games",
            "type":"Retail Goods"
        }
    ],
    "sg:phone":"+1 510 562 3209",
    "sg:postcode":"94603",
    "sg:province":"CA",
    "sg:tags":[
        "craft"
    ],
    "wof:name":"M L Enterprises",
    "wof:placetype":"venue"
},
  "geometry": {"coordinates":[-122.174144,37.741567],"type":"Point"}
}