{
  "type": "Feature",
  "properties": {
    "addr:full":"12021 Woodruff Ave Downey CA 90241",
    "addr:housenumber":"12021",
    "addr:postcode":"90241",
    "addr:street":"Woodruff Ave",
    "iso:country":"US",
    "sg:address":"12021 Woodruff Ave",
    "sg:city":"Downey",
    "sg:classifiers":[
        {
            "category":"Professional",
            "subcategory":"Employment Agencies",
            "type":"Services"
        }
    ],
    "sg:phone":"+1 562 803 6195",
    "sg:postcode":"90241",
    "sg:province":"CA",
    "sg:tags":[
        "help",
        "contractor"
    ],
    "wof:name":"Source One Staffing",
    "wof:placetype":"venue"
},
  "geometry": {"coordinates":[-118.116753,33.925518],"type":"Point"}
}