{
  "type": "Feature",
  "properties": {
    "iso:country":"US",
    "sg:address":"11270 W Olympic Blvd",
    "sg:city":"Los Angeles",
    "sg:classifiers":[
        {
            "category":"Shopping",
            "subcategory":"Department Store",
            "type":"Retail Goods"
        }
    ],
    "sg:phone":"+1 310 312 1266",
    "sg:postcode":"90064",
    "sg:province":"CA",
    "sg:tags":[
        "discount"
    ],
    "wof:name":"Marshalls",
    "wof:placetype":"venue"
},
  "geometry": {"coordinates":[-118.440901,34.038353],"type":"Point"}
}