{
  "type": "Feature",
  "properties": {
    "iso:country":"US",
    "sg:address":"432 E Amerige Ave",
    "sg:city":"Fullerton",
    "sg:classifiers":[
        {
            "category":"Professional",
            "type":"Services"
        }
    ],
    "sg:phone":"+1 714 526 7901",
    "sg:postcode":"92832",
    "sg:province":"CA",
    "wof:name":"B G P Creations",
    "wof:placetype":"venue"
},
  "geometry": {"coordinates":[-117.916185,33.871362],"type":"Point"}
}