{
  "type": "Feature",
  "properties": {
    "iso:country":"US",
    "sg:address":"155 Bovet Rd Suite 200",
    "sg:city":"San Mateo",
    "sg:classifiers":[
        {
            "category":"Real Estate",
            "subcategory":"Real Estate Agent",
            "type":"Services"
        }
    ],
    "sg:phone":"+1 877 237 9499",
    "sg:postcode":"94402",
    "sg:province":"CA",
    "sg:website":"www.realtorraj.com",
    "wof:name":"Raj Vaswani Realtor",
    "wof:placetype":"venue"
},
  "geometry": {"coordinates":[-122.316982,37.549475],"type":"Point"}
}