{
  "type": "Feature",
  "properties": {
    "iso:country":"US",
    "sg:address":"133 E Duarte Rd",
    "sg:city":"Arcadia",
    "sg:classifiers":[
        {
            "category":"Utilities",
            "subcategory":"Telephone",
            "type":"Services"
        }
    ],
    "sg:phone":"+1 626 574 0551",
    "sg:postcode":"91006",
    "sg:province":"CA",
    "sg:tags":[
        "web",
        "design",
        "hosting"
    ],
    "wof:name":"Dapp Hosting",
    "wof:placetype":"venue"
},
  "geometry": {"coordinates":[-118.025876,34.130339],"type":"Point"}
}