{
  "type": "Feature",
  "properties": {
    "iso:country":"US",
    "sg:address":"2040 Polk St",
    "sg:city":"San Francisco",
    "sg:classifiers":[
        {
            "category":"Professional",
            "subcategory":"Management & Consulting",
            "type":"Services"
        }
    ],
    "sg:phone":"+1 415 979 0611",
    "sg:postcode":"94109",
    "sg:province":"CA",
    "sg:tags":[
        "consultant",
        "publishing"
    ],
    "wof:name":"KTWT Productions Video",
    "wof:placetype":"venue"
},
  "geometry": {"coordinates":[-122.421634,37.795582],"type":"Point"}
}