{
  "type": "Feature",
  "properties": {
    "iso:country":"US",
    "sg:address":"750 E 8th St",
    "sg:city":"Los Angeles",
    "sg:classifiers":[
        {
            "category":"Shopping",
            "subcategory":"Discount & Variety Stores",
            "type":"Retail Goods"
        }
    ],
    "sg:phone":"+1 213 624 0802",
    "sg:postcode":"90021",
    "sg:province":"CA",
    "sg:tags":[
        "wholesale"
    ],
    "sg:website":"www.victortext.com",
    "wof:name":"Victor Textiles",
    "wof:placetype":"venue"
},
  "geometry": {"coordinates":[-118.24804,34.037078],"type":"Point"}
}