{
  "type": "Feature",
  "properties": {
    "iso:country":"US",
    "sg:address":"14081 Magnolia St",
    "sg:city":"Westminster",
    "sg:classifiers":[
        {
            "category":"Wholesale",
            "subcategory":"Durable Goods & Equipment",
            "type":"Manufacturing & Wholesale Goods"
        }
    ],
    "sg:phone":"+1 714 898 6226",
    "sg:postcode":"92683",
    "sg:province":"CA",
    "wof:name":"Ascot Technologies",
    "wof:placetype":"venue"
},
  "geometry": {"coordinates":[-117.97241,33.757519],"type":"Point"}
}