{
  "type": "Feature",
  "properties": {
    "addr:full":"27580 Schulte Rd Carmel CA 93923",
    "addr:postcode":"27580;93923",
    "addr:street":"Schulte Rd",
    "iso:country":"US",
    "sg:address":"27580 Schulte Rd",
    "sg:city":"Carmel",
    "sg:classifiers":[
        {
            "category":"Professional",
            "subcategory":"Business Services",
            "type":"Services"
        }
    ],
    "sg:phone":"+1 831 624 3637",
    "sg:postcode":"93923",
    "sg:province":"CA",
    "sg:tags":[
        "interior",
        "consultant",
        "design",
        "decorator"
    ],
    "wof:name":"Meredith Design Co",
    "wof:placetype":"venue"
},
  "geometry": {"coordinates":[-121.835492,36.525611],"type":"Point"}
}