{
  "type": "Feature",
  "properties": {
    "addr:full":"897 Independence Ave Mountain View CA 94303",
    "addr:housenumber":"897",
    "addr:postcode":"94303",
    "addr:street":"Independence Ave",
    "iso:country":"US",
    "sg:address":"897 Independence Ave",
    "sg:city":"Mountain View",
    "sg:classifiers":[
        {
            "category":"Health Services",
            "subcategory":"Doctor",
            "type":"Services"
        }
    ],
    "sg:phone":"+1 650 424 8900",
    "sg:postcode":"94303",
    "sg:province":"CA",
    "sg:tags":[
        "clinic"
    ],
    "wof:name":"3 I Medical Corp",
    "wof:placetype":"venue"
},
  "geometry": {"coordinates":[-122.09717000000001,37.41675],"type":"Point"}
}