{
  "type": "Feature",
  "properties": {
    "iso:country":"US",
    "sg:address":"9612 Hunt Avenue",
    "sg:city":"South Gate",
    "sg:classifiers":[
        {
            "category":"Building & Trades",
            "subcategory":"Construction",
            "type":"Services"
        }
    ],
    "sg:phone":"+1 323 249 9393",
    "sg:postcode":"90280",
    "sg:province":"CA",
    "sg:tags":[
        "contractor"
    ],
    "wof:name":"Bejarano Construcion",
    "wof:placetype":"venue"
},
  "geometry": {"coordinates":[-118.19217,33.945841],"type":"Point"}
}