{
  "type": "Feature",
  "properties": {
    "addr:full":"1290 B St Hayward CA 94541",
    "addr:housenumber":"1290",
    "addr:postcode":"94541",
    "addr:street":"B St",
    "iso:country":"US",
    "sg:address":"1290 B St",
    "sg:city":"Hayward",
    "sg:classifiers":[
        {
            "category":"Real Estate",
            "subcategory":"Real Estate Operator",
            "type":"Services"
        }
    ],
    "sg:phone":"+1 510 889 8409",
    "sg:postcode":"94541",
    "sg:province":"CA",
    "sg:tags":[
        "apartment"
    ],
    "wof:name":"Garwood Glen Townhomes",
    "wof:placetype":"venue"
},
  "geometry": {"coordinates":[-122.078946,37.675416],"type":"Point"}
}