{
  "type": "Feature",
  "properties": {
    "addr:full":"1747 S Claudina Way Anaheim CA 92805",
    "addr:housenumber":"1747",
    "addr:postcode":"92805",
    "addr:street":"S Claudina Way",
    "iso:country":"US",
    "sg:address":"1747 S Claudina Way",
    "sg:city":"Anaheim",
    "sg:classifiers":[
        {
            "category":"Building & Trades",
            "subcategory":"Plumbing",
            "type":"Services"
        }
    ],
    "sg:phone":"+1 714 635 8282",
    "sg:postcode":"92805",
    "sg:province":"CA",
    "sg:tags":[
        "conditioning",
        "air",
        "system",
        "contractor"
    ],
    "wof:name":"Aire Aide Co",
    "wof:placetype":"venue"
},
  "geometry": {"coordinates":[-117.90136800000001,33.805721],"type":"Point"}
}