{
  "type": "Feature",
  "properties": {
    "iso:country":"US",
    "sg:address":"1119 Neatherly Cir",
    "sg:city":"Corona",
    "sg:classifiers":[
        {
            "category":"Professional",
            "subcategory":"Lawyer & Legal Services",
            "type":"Services"
        }
    ],
    "sg:phone":"+1 951 734 4631",
    "sg:postcode":"92880",
    "sg:province":"CA",
    "sg:tags":[
        "attorney"
    ],
    "wof:name":"Ralph O Lewis Law Offices",
    "wof:placetype":"venue"
},
  "geometry": {"coordinates":[-117.580278,33.904514],"type":"Point"}
}