{
  "type": "Feature",
  "properties": {
    "addr:full":"678 4th St Hermosa Beach CA 90254",
    "addr:housenumber":"678",
    "addr:postcode":"90254",
    "addr:street":"4Th St",
    "iso:country":"US",
    "sg:address":"678 4th St",
    "sg:city":"Hermosa Beach",
    "sg:classifiers":[
        {
            "category":"Recreation",
            "type":"Entertainment"
        }
    ],
    "sg:phone":"+1 310 798 0575",
    "sg:postcode":"90254",
    "sg:province":"CA",
    "sg:tags":[
        "club",
        "travel"
    ],
    "wof:name":"Club Jet",
    "wof:placetype":"venue"
},
  "geometry": {"coordinates":[-118.39187200000001,33.857682],"type":"Point"}
}