{
  "type": "Feature",
  "properties": {
    "iso:country":"US",
    "sg:address":"300 E D St",
    "sg:city":"Petaluma",
    "sg:classifiers":[
        {
            "category":"Manufacturing",
            "subcategory":"Motor Vehicles & Parts",
            "type":"Manufacturing & Wholesale Goods"
        }
    ],
    "sg:phone":"+1 800 464 9994",
    "sg:postcode":"94952",
    "sg:province":"CA",
    "sg:tags":[
        "manufacturer",
        "electric",
        "controls-wholesale"
    ],
    "wof:name":"Electrical Equip. Co. Inc.",
    "wof:placetype":"venue"
},
  "geometry": {"coordinates":[-122.635071,38.235779],"type":"Point"}
}