{
  "type": "Feature",
  "properties": {
    "iso:country":"US",
    "sg:address":"2732 Cohasset Rd",
    "sg:city":"Chico",
    "sg:classifiers":[
        {
            "category":"Banks & Credit Unions",
            "subcategory":"Investment Brokerage",
            "type":"Services"
        }
    ],
    "sg:phone":"+1 530 891 0717",
    "sg:postcode":"95973",
    "sg:province":"CA",
    "sg:tags":[
        "consultant",
        "planning",
        "financial"
    ],
    "wof:name":"Spelts Wealth Management",
    "wof:placetype":"venue"
},
  "geometry": {"coordinates":[-121.843476,39.765347],"type":"Point"}
}