{
  "type": "Feature",
  "properties": {
    "addr:full":"800 Wilshire Blvd Los Angeles CA 90017",
    "addr:housenumber":"800",
    "addr:postcode":"90017",
    "addr:street":"Wilshire Blvd",
    "iso:country":"US",
    "sg:address":"800 Wilshire Blvd",
    "sg:city":"Los Angeles",
    "sg:classifiers":[
        {
            "category":"Professional",
            "subcategory":"Lawyer & Legal Services",
            "type":"Services"
        }
    ],
    "sg:phone":"+1 213 629 5700",
    "sg:postcode":"90017",
    "sg:province":"CA",
    "sg:tags":[
        "law"
    ],
    "wof:name":"Clark & Trevithick A Prof Corp",
    "wof:placetype":"venue"
},
  "geometry": {"coordinates":[-118.25867700000001,34.0497],"type":"Point"}
}