{
  "type": "Feature",
  "properties": {
    "addr:full":"7777 Industry Ave Pico Rivera CA 90660",
    "addr:housenumber":"7777",
    "addr:postcode":"90660",
    "addr:street":"Industry Ave",
    "iso:country":"US",
    "sg:address":"7777 Industry Ave",
    "sg:city":"Pico Rivera",
    "sg:classifiers":[
        {
            "category":"Professional",
            "subcategory":"Business Services",
            "type":"Services"
        }
    ],
    "sg:phone":"+1 562 942 2200",
    "sg:postcode":"90660",
    "sg:province":"CA",
    "sg:tags":[
        "water",
        "treatment"
    ],
    "wof:name":"Ionics Ultrapure Water Corp",
    "wof:placetype":"venue"
},
  "geometry": {"coordinates":[-118.114664,33.974053],"type":"Point"}
}