{
  "type": "Feature",
  "properties": {
    "addr:full":"6395 Blue Jay Dr Buena Park CA 90620",
    "addr:housenumber":"6395",
    "addr:postcode":"90620",
    "addr:street":"Blue Jay Dr",
    "iso:country":"US",
    "sg:address":"6395 Blue Jay Dr",
    "sg:city":"Buena Park",
    "sg:classifiers":[
        {
            "category":"Manufacturing",
            "subcategory":"Food",
            "type":"Manufacturing & Wholesale Goods"
        }
    ],
    "sg:phone":"+1 714 994 5739",
    "sg:postcode":"90620",
    "sg:province":"CA",
    "sg:tags":[
        "preparation",
        "mfg"
    ],
    "wof:name":"Natures Heritage",
    "wof:placetype":"venue"
},
  "geometry": {"coordinates":[-118.023753,33.858395],"type":"Point"}
}