{
  "type": "Feature",
  "properties": {
    "addr:full":"1714 Lemon St Vallejo CA 94590",
    "addr:housenumber":"1714",
    "addr:postcode":"94590",
    "addr:street":"Lemon St",
    "iso:country":"US",
    "sg:address":"1714 Lemon St",
    "sg:city":"Vallejo",
    "sg:classifiers":[
        {
            "category":"Building & Trades",
            "subcategory":"Construction",
            "type":"Services"
        }
    ],
    "sg:phone":"+1 707 643 1750",
    "sg:postcode":"94590",
    "sg:province":"CA",
    "sg:tags":[
        "contractor"
    ],
    "wof:name":"J L Smith Construction",
    "wof:placetype":"venue"
},
  "geometry": {"coordinates":[-122.23193499999999,38.094397],"type":"Point"}
}