{
  "type": "Feature",
  "properties": {
    "iso:country":"US",
    "sg:address":"2784 Gateway Rd",
    "sg:city":"Carlsbad",
    "sg:classifiers":[
        {
            "category":"Real Estate",
            "subcategory":"Real Estate Agent",
            "type":"Services"
        }
    ],
    "sg:phone":"+1 760 268 0621",
    "sg:postcode":"92009",
    "sg:province":"CA",
    "wof:name":"Kelly Capital Group",
    "wof:placetype":"venue"
},
  "geometry": {"coordinates":[-117.24824700000001,33.129051],"type":"Point"}
}