{
  "type": "Feature",
  "properties": {
    "addr:full":"24239 Hesperian Blvd Hayward CA 94545",
    "addr:housenumber":"24239",
    "addr:postcode":"94545",
    "addr:street":"Hesperian Blvd",
    "iso:country":"US",
    "sg:address":"24239 Hesperian Blvd",
    "sg:city":"Hayward",
    "sg:classifiers":[
        {
            "category":"Health Services",
            "subcategory":"Dentist",
            "type":"Services"
        }
    ],
    "sg:phone":"+1 510 786 2587",
    "sg:postcode":"94545",
    "sg:province":"CA",
    "wof:name":"Senn Silvano C DDS Serra Park Dental Group",
    "wof:placetype":"venue"
},
  "geometry": {"coordinates":[-122.10900100000001,37.6511],"type":"Point"}
}