{
  "type": "Feature",
  "properties": {
    "iso:country":"US",
    "sg:address":"891 Higuera St",
    "sg:city":"San Luis Obispo",
    "sg:classifiers":[
        {
            "category":"Restaurant",
            "type":"Food & Drink"
        }
    ],
    "sg:phone":"+1 805 544 8786",
    "sg:postcode":"93401",
    "sg:province":"CA",
    "sg:tags":[
        "pizza"
    ],
    "wof:name":"Pizza Solo",
    "wof:placetype":"venue"
},
  "geometry": {"coordinates":[-120.662523,35.279866],"type":"Point"}
}