{
  "type": "Feature",
  "properties": {
    "addr:full":"169 Angela Dr Los Altos CA 94022",
    "addr:housenumber":"169",
    "addr:postcode":"94022",
    "addr:street":"Angela Dr",
    "iso:country":"US",
    "sg:address":"169 Angela Dr",
    "sg:city":"Los Altos",
    "sg:classifiers":[
        {
            "category":"Professional",
            "subcategory":"Management & Consulting",
            "type":"Services"
        }
    ],
    "sg:phone":"+1 650 949 5737",
    "sg:postcode":"94022",
    "sg:province":"CA",
    "sg:tags":[
        "counselor",
        "public",
        "relations"
    ],
    "wof:name":"Putman Resources",
    "wof:placetype":"venue"
},
  "geometry": {"coordinates":[-122.11131,37.383045],"type":"Point"}
}