{
  "type": "Feature",
  "properties": {
    "addr:full":"303 Linda Dr Hollister CA 95023",
    "addr:housenumber":"303",
    "addr:postcode":"hollister ca 95023",
    "addr:street":"Linda Dr",
    "iso:country":"US",
    "sg:address":"303 Linda Dr",
    "sg:city":"Hollister",
    "sg:classifiers":[
        {
            "category":"Building & Trades",
            "subcategory":"Construction",
            "type":"Services"
        }
    ],
    "sg:phone":"+1 831 636 5827",
    "sg:postcode":"95023",
    "sg:province":"CA",
    "sg:tags":[
        "house",
        "commercial"
    ],
    "wof:name":"Hough Construction Co Inc",
    "wof:placetype":"venue"
},
  "geometry": {"coordinates":[-121.353167,36.805779],"type":"Point"}
}