{
  "type": "Feature",
  "properties": {
    "iso:country":"US",
    "sg:address":"930 Oak St",
    "sg:city":"Bakersfield",
    "sg:classifiers":[
        {
            "category":"Real Estate",
            "subcategory":"Real Estate Agent",
            "type":"Services"
        }
    ],
    "sg:phone":"+1 661 321 9908",
    "sg:postcode":"93304",
    "sg:province":"CA",
    "wof:name":"Tony Diaz",
    "wof:placetype":"venue"
},
  "geometry": {"coordinates":[-119.038707,35.366102],"type":"Point"}
}