{
  "type": "Feature",
  "properties": {
    "addr:full":"6319 N Fresno St Fresno CA 93710",
    "addr:housenumber":"6319",
    "addr:postcode":"93710",
    "addr:street":"N Fresno",
    "iso:country":"US",
    "sg:address":"6319 N Fresno St",
    "sg:city":"Fresno",
    "sg:classifiers":[
        {
            "category":"Health Services",
            "subcategory":"Doctor",
            "type":"Services"
        }
    ],
    "sg:phone":"+1 559 438 6177",
    "sg:postcode":"93710",
    "sg:province":"CA",
    "sg:tags":[
        "dentist"
    ],
    "wof:name":"Jeff Arkelian DDS",
    "wof:placetype":"venue"
},
  "geometry": {"coordinates":[-119.78138,36.828035],"type":"Point"}
}