{
  "type": "Feature",
  "properties": {
    "addr:full":"1141 College View Dr Monterey Park CA 91754",
    "addr:housenumber":"1141",
    "addr:postcode":"91754",
    "addr:street":"College View Dr",
    "iso:country":"US",
    "sg:address":"1141 College View Dr",
    "sg:city":"Monterey Park",
    "sg:classifiers":[
        {
            "category":"Health Services",
            "subcategory":"Hospital",
            "type":"Services"
        }
    ],
    "sg:phone":"+1 626 572 6545",
    "sg:postcode":"91754",
    "sg:province":"CA",
    "sg:tags":[
        "general"
    ],
    "wof:name":"Health Alliance Services",
    "wof:placetype":"venue"
},
  "geometry": {"coordinates":[-118.14606000000001,34.042127],"type":"Point"}
}