{
  "type": "Feature",
  "properties": {
    "iso:country":"US",
    "sg:address":"12526 High Bluff Drive Suite 290",
    "sg:city":"San Diego",
    "sg:classifiers":[
        {
            "category":"Banks & Credit Unions",
            "subcategory":"Bank",
            "type":"Services"
        }
    ],
    "sg:phone":"+1 858 704 0300",
    "sg:postcode":"92130",
    "sg:province":"CA",
    "sg:website":"www.cariscompany.com",
    "wof:name":"Caris & Company",
    "wof:placetype":"venue"
},
  "geometry": {"coordinates":[-117.240723,32.945327],"type":"Point"}
}