{
  "type": "Feature",
  "properties": {
    "addr:full":"5100 S Broadway Los Angeles CA 90037",
    "addr:housenumber":"5100",
    "addr:postcode":"90037",
    "addr:street":"S Broadway",
    "iso:country":"US",
    "sg:address":"5100 S Broadway",
    "sg:city":"Los Angeles",
    "sg:classifiers":[
        {
            "category":"Organizations",
            "subcategory":"Religious Organization",
            "type":"Services"
        }
    ],
    "sg:phone":"+1 323 231 2414",
    "sg:postcode":"90037",
    "sg:province":"CA",
    "sg:tags":[
        "church"
    ],
    "wof:name":"Mision Bautisti El Paraiso",
    "wof:placetype":"venue"
},
  "geometry": {"coordinates":[-118.27831,33.995748],"type":"Point"}
}