{
  "type": "Feature",
  "properties": {
    "addr:full":"4180 La Jolla Village Dr Ste 540 La Jolla CA 92037",
    "addr:housenumber":"4180",
    "addr:postcode":"92037",
    "addr:street":"La Jolla Village Dr Ste 540",
    "iso:country":"US",
    "sg:address":"4180 La Jolla Village Dr Ste 540",
    "sg:city":"La Jolla",
    "sg:classifiers":[
        {
            "category":"Professional",
            "subcategory":"Lawyer & Legal Services",
            "type":"Services"
        }
    ],
    "sg:phone":"+1 858 626 2880",
    "sg:postcode":"92037",
    "sg:province":"CA",
    "wof:name":"Moore Brewer & Burbott",
    "wof:placetype":"venue"
},
  "geometry": {"coordinates":[-117.21700300000001,32.872101],"type":"Point"}
}