{
  "type": "Feature",
  "properties": {
    "iso:country":"US",
    "sg:address":"22774 Confidence Rd",
    "sg:city":"Twain Harte",
    "sg:classifiers":[
        {
            "category":"Personal",
            "subcategory":"Massage",
            "type":"Services"
        },
        {
            "category":"Building & Trades",
            "subcategory":"Construction",
            "type":"Services"
        }
    ],
    "sg:phone":"+1 209 586 3163",
    "sg:postcode":"95383",
    "sg:province":"CA",
    "sg:tags":[
        "contractor"
    ],
    "wof:name":"Brewer Construction",
    "wof:placetype":"venue"
},
  "geometry": {"coordinates":[-120.20492900000001,38.035556],"type":"Point"}
}