{
  "type": "Feature",
  "properties": {
    "iso:country":"US",
    "sg:address":"351 Santa Barbara",
    "sg:city":"Irvine",
    "sg:classifiers":[
        {
            "category":"Professional",
            "subcategory":"Computer Services",
            "type":"Services"
        }
    ],
    "sg:phone":"+1 949 679 8658",
    "sg:postcode":"92606",
    "sg:province":"CA",
    "sg:tags":[
        "consultant"
    ],
    "wof:name":"Bales & Assoc",
    "wof:placetype":"venue"
},
  "geometry": {"coordinates":[-117.808525,33.685729],"type":"Point"}
}