{
  "type": "Feature",
  "properties": {
    "iso:country":"US",
    "sg:address":"677 Saint Helena Hwy",
    "sg:city":"St Helena",
    "sg:classifiers":[
        {
            "category":"Manufacturing",
            "subcategory":"Food",
            "type":"Manufacturing & Wholesale Goods"
        }
    ],
    "sg:phone":"+1 707 967 8032",
    "sg:postcode":"94574",
    "sg:province":"CA",
    "sg:tags":[
        "winery"
    ],
    "sg:website":"www.florasprings.com",
    "wof:name":"Flora Springs Winery",
    "wof:placetype":"venue"
},
  "geometry": {"coordinates":[-122.449304,38.488231],"type":"Point"}
}