{
  "type": "Feature",
  "properties": {
    "addr:full":"84628 Guitron St Coachella CA 92236",
    "addr:housenumber":"84628",
    "addr:postcode":"92236",
    "addr:street":"Guitron St",
    "iso:country":"US",
    "sg:address":"84628 Guitron St",
    "sg:city":"Coachella",
    "sg:classifiers":[
        {
            "category":"Social Services",
            "subcategory":"Child Care",
            "type":"Services"
        }
    ],
    "sg:phone":"+1 760 398 2667",
    "sg:postcode":"92236",
    "sg:province":"CA",
    "sg:tags":[
        "nursery",
        "day"
    ],
    "wof:name":"Borja Family Child Care",
    "wof:placetype":"venue"
},
  "geometry": {"coordinates":[-116.18699700000001,33.689522],"type":"Point"}
}