{
  "type": "Feature",
  "properties": {
    "iso:country":"US",
    "sg:address":"4121 Westerly Pl Ste 116",
    "sg:city":"Newport Beach",
    "sg:classifiers":[
        {
            "category":"Health Services",
            "subcategory":"Chiropractor",
            "type":"Services"
        }
    ],
    "sg:phone":"+1 949 945 1425",
    "sg:postcode":"92660",
    "sg:province":"CA",
    "wof:name":"Pollack Chiropractic Corp",
    "wof:placetype":"venue"
},
  "geometry": {"coordinates":[-117.86739799999999,33.664591],"type":"Point"}
}