{
  "type": "Feature",
  "properties": {
    "addr:full":"1123 W Acacia Ave Hemet CA 92543",
    "addr:housenumber":"1123",
    "addr:postcode":"92543",
    "addr:street":"W Acacia Ave",
    "iso:country":"US",
    "sg:address":"1123 W Acacia Ave",
    "sg:city":"Hemet",
    "sg:classifiers":[
        {
            "category":"Organizations",
            "subcategory":"Religious Organization",
            "type":"Services"
        }
    ],
    "sg:phone":"+1 951 652 9456",
    "sg:postcode":"92543",
    "sg:province":"CA",
    "wof:name":"Tract Stop",
    "wof:placetype":"venue"
},
  "geometry": {"coordinates":[-116.98179,33.74377],"type":"Point"}
}