{
  "type": "Feature",
  "properties": {
    "iso:country":"US",
    "sg:address":"4350 Executive Drive",
    "sg:city":"San Diego",
    "sg:classifiers":[
        {
            "category":"Shopping",
            "subcategory":"Music",
            "type":"Retail Goods"
        }
    ],
    "sg:phone":"+1 858 455 5223",
    "sg:postcode":"92121",
    "sg:province":"CA",
    "sg:tags":[
        "dvd's"
    ],
    "wof:name":"Netgenics",
    "wof:placetype":"venue"
},
  "geometry": {"coordinates":[-117.211928,32.875134],"type":"Point"}
}