{
  "type": "Feature",
  "properties": {
    "addr:full":"35 Korite Rancho Santa Margarita CA 92688",
    "addr:housenumber":"35",
    "addr:postcode":"92688",
    "addr:street":"Korite",
    "iso:country":"US",
    "sg:address":"35 Korite",
    "sg:city":"Rancho Santa Margarita",
    "sg:classifiers":[
        {
            "category":"Professional",
            "type":"Services"
        }
    ],
    "sg:phone":"+1 949 459 5810",
    "sg:postcode":"92688",
    "sg:province":"CA",
    "wof:name":"Cleantec Inc",
    "wof:placetype":"venue"
},
  "geometry": {"coordinates":[-117.60899999999999,33.657698],"type":"Point"}
}