{
  "type": "Feature",
  "properties": {
    "iso:country":"US",
    "sg:address":"1830 Lincoln Blvd",
    "sg:city":"Santa Monica",
    "sg:classifiers":[
        {
            "category":"Professional",
            "subcategory":"Computer Services",
            "type":"Services"
        }
    ],
    "sg:phone":"+1 310 396 2019",
    "sg:postcode":"90404",
    "sg:province":"CA",
    "wof:name":"United Computer & Networking",
    "wof:placetype":"venue"
},
  "geometry": {"coordinates":[-118.48358399999999,34.012776],"type":"Point"}
}