{
  "type": "Feature",
  "properties": {
    "addr:full":"8470 Deervale Rd Dublin CA 94568",
    "addr:postcode":"8470;94568",
    "addr:street":"Deervale Rd",
    "iso:country":"US",
    "sg:address":"8470 Deervale Rd",
    "sg:city":"Dublin",
    "sg:classifiers":[
        {
            "category":"Building & Trades",
            "subcategory":"Construction",
            "type":"Services"
        }
    ],
    "sg:phone":"+1 925 361 0792",
    "sg:postcode":"94568",
    "sg:province":"CA",
    "sg:tags":[
        "handyman"
    ],
    "wof:name":"American Dream Handyman",
    "wof:placetype":"venue"
},
  "geometry": {"coordinates":[-121.938558,37.718315],"type":"Point"}
}