{
  "type": "Feature",
  "properties": {
    "addr:full":"3291 1/2 N San Fernando Rd Los Angeles CA 90065",
    "addr:housenumber":"3291 1 / 2",
    "addr:postcode":"90065",
    "addr:street":"N San Fernando Rd",
    "iso:country":"US",
    "sg:address":"3291 1/2 N San Fernando Rd",
    "sg:city":"Los Angeles",
    "sg:classifiers":[
        {
            "category":"Bakery",
            "type":"Food & Drink"
        }
    ],
    "sg:phone":"+1 323 255 6150",
    "sg:postcode":"90065",
    "sg:province":"CA",
    "sg:website":"www.sweettoothbakery.com",
    "wof:name":"Sweet Tooth Bakery",
    "wof:placetype":"venue"
},
  "geometry": {"coordinates":[-118.248536,34.117581],"type":"Point"}
}