{
  "type": "Feature",
  "properties": {
    "addr:full":"3976 S Figueroa St Los Angeles CA 90037",
    "addr:housenumber":"3976",
    "addr:postcode":"90037",
    "addr:street":"S Figueroa St",
    "iso:country":"US",
    "sg:address":"3976 S Figueroa St",
    "sg:city":"Los Angeles",
    "sg:classifiers":[
        {
            "category":"Bakery",
            "type":"Food & Drink"
        }
    ],
    "sg:phone":"+1 213 748 8614",
    "sg:postcode":"90037",
    "sg:province":"CA",
    "wof:name":"Crystal Bakery Inc",
    "wof:placetype":"venue"
},
  "geometry": {"coordinates":[-118.28299699999999,34.011799],"type":"Point"}
}