{
  "type": "Feature",
  "properties": {
    "addr:full":"3311 Grand Ave Oakland CA 94610",
    "addr:housenumber":"3311",
    "addr:postcode":"94610",
    "addr:street":"Grand Ave",
    "iso:country":"US",
    "sg:address":"3311 Grand Ave",
    "sg:city":"Oakland",
    "sg:classifiers":[
        {
            "category":"Restaurant",
            "type":"Food & Drink"
        }
    ],
    "sg:phone":"+1 510 763 6733",
    "sg:postcode":"94610",
    "sg:province":"CA",
    "sg:tags":[
        "deli",
        "delicatessen"
    ],
    "wof:name":"Jenny's Cafe",
    "wof:placetype":"venue"
},
  "geometry": {"coordinates":[-122.24708,37.812822],"type":"Point"}
}