{
  "type": "Feature",
  "properties": {
    "addr:full":"41135 Sandalwood Cir Murrieta CA 92562",
    "addr:housenumber":"41135",
    "addr:postcode":"92562",
    "addr:street":"Sandalwood Cir",
    "iso:country":"US",
    "sg:address":"41135 Sandalwood Cir",
    "sg:city":"Murrieta",
    "sg:classifiers":[
        {
            "category":"Manufacturing",
            "subcategory":"Tools & Machinery",
            "type":"Manufacturing & Wholesale Goods"
        }
    ],
    "sg:phone":"+1 951 600 1060",
    "sg:postcode":"92562",
    "sg:province":"CA",
    "sg:tags":[
        "machine",
        "shop"
    ],
    "wof:name":"P S Mfg",
    "wof:placetype":"venue"
},
  "geometry": {"coordinates":[-117.17370099999999,33.53418],"type":"Point"}
}