{
  "type": "Feature",
  "properties": {
    "addr:full":"1473 Rosewood Pl Corona CA 92880",
    "addr:housenumber":"1473",
    "addr:postcode":"92880",
    "addr:street":"Rosewood Pl",
    "iso:country":"US",
    "sg:address":"1473 Rosewood Pl",
    "sg:city":"Corona",
    "sg:classifiers":[
        {
            "category":"Building & Trades",
            "subcategory":"Landscaping Services",
            "type":"Services"
        }
    ],
    "sg:phone":"+1 951 549 1884",
    "sg:postcode":"92880",
    "sg:province":"CA",
    "sg:tags":[
        "landscape",
        "contractor"
    ],
    "wof:name":"AMD Landscape",
    "wof:placetype":"venue"
},
  "geometry": {"coordinates":[-117.584658,33.902669],"type":"Point"}
}