{
  "type": "Feature",
  "properties": {
    "addr:full":"150 Pierre Rd Walnut CA 91789",
    "addr:housenumber":"150",
    "addr:postcode":"91789",
    "addr:street":"Pierre Rd",
    "iso:country":"US",
    "sg:address":"150 Pierre Rd",
    "sg:city":"Walnut",
    "sg:classifiers":[
        {
            "category":"Personal",
            "subcategory":"Beauty Salon",
            "type":"Services"
        }
    ],
    "sg:phone":"+1 909 594 4669",
    "sg:postcode":"91789",
    "sg:province":"CA",
    "wof:name":"Anna Hair Design",
    "wof:placetype":"venue"
},
  "geometry": {"coordinates":[-117.850154,34.017168],"type":"Point"}
}