{
  "type": "Feature",
  "properties": {
    "iso:country":"US",
    "sg:address":"2082 SE Bristol St",
    "sg:city":"Newport Beach",
    "sg:classifiers":[
        {
            "category":"Manufacturing",
            "subcategory":"Tools & Machinery",
            "type":"Manufacturing & Wholesale Goods"
        }
    ],
    "sg:phone":"+1 949 660 1545",
    "sg:postcode":"92660",
    "sg:province":"CA",
    "sg:tags":[
        "machine",
        "mfg"
    ],
    "wof:name":"General Binding Corporation",
    "wof:placetype":"venue"
},
  "geometry": {"coordinates":[-117.878284,33.663939],"type":"Point"}
}