{
  "type": "Feature",
  "properties": {
    "addr:full":"525 S Main St Willits CA 95490",
    "addr:housenumber":"525",
    "addr:postcode":"95490",
    "addr:street":"S Main St",
    "iso:country":"US",
    "sg:address":"525 S Main St",
    "sg:city":"Willits",
    "sg:classifiers":[
        {
            "category":"Shopping",
            "type":"Retail Goods"
        }
    ],
    "sg:phone":"+1 707 459 4777",
    "sg:postcode":"95490",
    "sg:province":"CA",
    "sg:tags":[
        "telephone",
        "cellular"
    ],
    "wof:name":"Direct TV-Willits Satellite TV",
    "wof:placetype":"venue"
},
  "geometry": {"coordinates":[-123.352081,39.406442],"type":"Point"}
}