{
  "type": "Feature",
  "properties": {
    "addr:full":"108 N Ynez Ave Monterey Park CA 91754",
    "addr:housenumber":"108",
    "addr:postcode":"91754",
    "addr:street":"N Ynez Ave",
    "iso:country":"US",
    "sg:address":"108 N Ynez Ave",
    "sg:city":"Monterey Park",
    "sg:classifiers":[
        {
            "category":"Professional",
            "type":"Services"
        }
    ],
    "sg:phone":"+1 626 288 0688",
    "sg:postcode":"91754",
    "sg:province":"CA",
    "wof:name":"Asiamerica Dev Prj Rosemea",
    "wof:placetype":"venue"
},
  "geometry": {"coordinates":[-118.129053,34.063614],"type":"Point"}
}