{
  "type": "Feature",
  "properties": {
    "iso:country":"US",
    "sg:address":"4301 Clayton Rd",
    "sg:city":"Concord",
    "sg:classifiers":[
        {
            "category":"Restaurant",
            "type":"Food & Drink"
        }
    ],
    "sg:phone":"+1 925 521 9224",
    "sg:postcode":"94521",
    "sg:province":"CA",
    "wof:name":"Buttercup Grill & Bar",
    "wof:placetype":"venue"
},
  "geometry": {"coordinates":[-121.991484,37.964379],"type":"Point"}
}