{
  "type": "Feature",
  "properties": {
    "addr:full":"1019 E St Reedley CA 93654",
    "addr:housenumber":"1019",
    "addr:postcode":"93654",
    "addr:street":"E St",
    "iso:country":"US",
    "sg:address":"1019 E St",
    "sg:city":"Reedley",
    "sg:classifiers":[
        {
            "category":"Health Services",
            "subcategory":"Doctor",
            "type":"Services"
        }
    ],
    "sg:phone":"+1 559 638 3314",
    "sg:postcode":"93654",
    "sg:province":"CA",
    "sg:tags":[
        "dentist"
    ],
    "wof:name":"Stephen J Ikemiya Dental Ofc",
    "wof:placetype":"venue"
},
  "geometry": {"coordinates":[-119.449056,36.597937],"type":"Point"}
}