{
  "type": "Feature",
  "properties": {
    "addr:full":"28306 Industrial Blvd Hayward CA 94545",
    "addr:housenumber":"28306",
    "addr:postcode":"94545",
    "addr:street":"Industrial Blvd",
    "iso:country":"US",
    "sg:address":"28306 Industrial Blvd",
    "sg:city":"Hayward",
    "sg:classifiers":[
        {
            "category":"Utilities",
            "subcategory":"Cable",
            "type":"Services"
        }
    ],
    "sg:phone":"+1 510 783 1283",
    "sg:postcode":"94545",
    "sg:province":"CA",
    "sg:tags":[
        "television"
    ],
    "wof:name":"Smart Connect Telecomm",
    "wof:placetype":"venue"
},
  "geometry": {"coordinates":[-122.090147,37.616759],"type":"Point"}
}