{
  "type": "Feature",
  "properties": {
    "iso:country":"US",
    "sg:address":"303 W Noble Ave",
    "sg:city":"Visalia",
    "sg:classifiers":[
        {
            "category":"Insurance",
            "subcategory":"Insurance Agent",
            "type":"Services"
        }
    ],
    "sg:phone":"+1 559 732 4168",
    "sg:postcode":"93277",
    "sg:province":"CA",
    "wof:name":"Stanley R Vollmer Insurance",
    "wof:placetype":"venue"
},
  "geometry": {"coordinates":[-119.296002,36.326362],"type":"Point"}
}