{
  "type": "Feature",
  "properties": {
    "iso:country":"US",
    "sg:address":"250 E D St",
    "sg:city":"Upland",
    "sg:classifiers":[
        {
            "category":"Health Services",
            "subcategory":"Doctor",
            "type":"Services"
        }
    ],
    "sg:phone":"+1 909 982 4169",
    "sg:postcode":"91786",
    "sg:province":"CA",
    "sg:tags":[
        "dentist"
    ],
    "sg:website":"www.tomkepic.com",
    "wof:name":"Thomas J Kepic DDS",
    "wof:placetype":"venue"
},
  "geometry": {"coordinates":[-117.647722,34.098403],"type":"Point"}
}