{
  "type": "Feature",
  "properties": {
    "iso:country":"US",
    "sg:address":"3998 18th St",
    "sg:city":"San Francisco",
    "sg:classifiers":[
        {
            "category":"Food & Beverages",
            "subcategory":"Groceries & Convenience Stores",
            "type":"Retail Goods"
        }
    ],
    "sg:phone":"+1 415 552 8611",
    "sg:postcode":"94114",
    "sg:province":"CA",
    "sg:website":"www.7-eleven.com",
    "wof:name":"7-Eleven",
    "wof:placetype":"venue"
},
  "geometry": {"coordinates":[-122.432824,37.761041],"type":"Point"}
}