{
  "type": "Feature",
  "properties": {
    "addr:full":"42458 Bob Hope Dr Rancho Mirage CA 92270",
    "addr:housenumber":"42458",
    "addr:postcode":"92270",
    "addr:street":"Bob Hope Dr",
    "iso:country":"US",
    "sg:address":"42458 Bob Hope Dr",
    "sg:city":"Rancho Mirage",
    "sg:classifiers":[
        {
            "category":"Shopping",
            "subcategory":"Florist",
            "type":"Retail Goods"
        }
    ],
    "sg:phone":"+1 760 568 6929",
    "sg:postcode":"92270",
    "sg:province":"CA",
    "wof:name":"J Ballow Signature Florist",
    "wof:placetype":"venue"
},
  "geometry": {"coordinates":[-116.40821099999999,33.738161],"type":"Point"}
}