{
  "type": "Feature",
  "properties": {
    "addr:full":"6141 Magnolia Ave Riverside CA 92506",
    "addr:housenumber":"6141",
    "addr:postcode":"92506",
    "addr:street":"Magnolia Ave",
    "iso:country":"US",
    "sg:address":"6141 Magnolia Ave",
    "sg:city":"Riverside",
    "sg:classifiers":[
        {
            "category":"Personal",
            "subcategory":"Beauty Salon",
            "type":"Services"
        }
    ],
    "sg:phone":"+1 951 682 1110",
    "sg:postcode":"92506",
    "sg:province":"CA",
    "sg:tags":[
        "manicuring"
    ],
    "wof:name":"Top Hair Nails",
    "wof:placetype":"venue"
},
  "geometry": {"coordinates":[-117.394025,33.957543],"type":"Point"}
}