{
  "type": "Feature",
  "properties": {
    "addr:full":"41700 Corporate Way Palm Desert CA 92260",
    "addr:housenumber":"41700",
    "addr:postcode":"ca 92260",
    "addr:street":"Corporate Way",
    "iso:country":"US",
    "sg:address":"41700 Corporate Way",
    "sg:city":"Palm Desert",
    "sg:classifiers":[
        {
            "category":"Manufacturing",
            "subcategory":"Jewelry",
            "type":"Manufacturing & Wholesale Goods"
        }
    ],
    "sg:phone":"+1 760 346 6926",
    "sg:postcode":"92260",
    "sg:province":"CA",
    "sg:tags":[
        "ware",
        "mineral",
        "mfg"
    ],
    "wof:name":"Awards By Powers",
    "wof:placetype":"venue"
},
  "geometry": {"coordinates":[-116.36238,33.747095],"type":"Point"}
}