{
  "type": "Feature",
  "properties": {
    "addr:full":"5730 Soquel Dr Soquel CA 95073",
    "addr:housenumber":"5730",
    "addr:postcode":"95073",
    "addr:street":"Soquel Dr",
    "iso:country":"US",
    "sg:address":"5730 Soquel Dr",
    "sg:city":"Soquel",
    "sg:classifiers":[
        {
            "category":"Building & Trades",
            "subcategory":"Landscaping Services",
            "type":"Services"
        }
    ],
    "sg:phone":"+1 831 462 3767",
    "sg:postcode":"95073",
    "sg:province":"CA",
    "wof:name":"Marathon Gardening",
    "wof:placetype":"venue"
},
  "geometry": {"coordinates":[-121.940056,36.987702],"type":"Point"}
}