{
  "type": "Feature",
  "properties": {
    "addr:full":"777 E Channel Islands Blvd Oxnard CA 93033",
    "addr:housenumber":"777",
    "addr:postcode":"93033",
    "addr:street":"E Channel Islands Blvd",
    "iso:country":"US",
    "sg:address":"777 E Channel Islands Blvd",
    "sg:city":"Oxnard",
    "sg:classifiers":[
        {
            "category":"Freight",
            "type":"Transportation"
        }
    ],
    "sg:phone":"+1 805 247 0609",
    "sg:postcode":"93033",
    "sg:province":"CA",
    "sg:tags":[
        "commercial",
        "storage",
        "general"
    ],
    "wof:name":"Lions Gate Self Storage",
    "wof:placetype":"venue"
},
  "geometry": {"coordinates":[-119.167784,34.173451],"type":"Point"}
}