{
  "type": "Feature",
  "properties": {
    "iso:country":"US",
    "sg:address":"214 Bassett St",
    "sg:city":"King City",
    "sg:classifiers":[
        {
            "category":"Wholesale",
            "subcategory":"Stationery",
            "type":"Manufacturing & Wholesale Goods"
        }
    ],
    "sg:phone":"+1 831 386 0835",
    "sg:postcode":"93930",
    "sg:province":"CA",
    "sg:tags":[
        "corp",
        "seal"
    ],
    "wof:name":"Hernadez Services",
    "wof:placetype":"venue"
},
  "geometry": {"coordinates":[-121.124467,36.212697],"type":"Point"}
}