{
  "type": "Feature",
  "properties": {
    "iso:country":"US",
    "sg:address":"7717 Fay Ave",
    "sg:city":"La Jolla",
    "sg:classifiers":[
        {
            "category":"Wholesale",
            "subcategory":"Home Furnishings",
            "type":"Manufacturing & Wholesale Goods"
        }
    ],
    "sg:phone":"+1 858 459 8642",
    "sg:postcode":"92037",
    "sg:province":"CA",
    "sg:tags":[
        "linen"
    ],
    "wof:name":"Martha Smith Fine Linens",
    "wof:placetype":"venue"
},
  "geometry": {"coordinates":[-117.275081,32.844594],"type":"Point"}
}