{
  "type": "Feature",
  "properties": {
    "addr:full":"590 Taylor Way San Carlos CA 94070",
    "addr:housenumber":"590",
    "addr:postcode":"94070",
    "addr:street":"Taylor Way",
    "iso:country":"US",
    "sg:address":"590 Taylor Way",
    "sg:city":"San Carlos",
    "sg:classifiers":[
        {
            "category":"Building & Trades",
            "subcategory":"Plumbing",
            "type":"Services"
        }
    ],
    "sg:phone":"+1 650 591 2693",
    "sg:postcode":"94070",
    "sg:province":"CA",
    "sg:tags":[
        "contractor"
    ],
    "wof:name":"Rebholtz Mechanical",
    "wof:placetype":"venue"
},
  "geometry": {"coordinates":[-122.262152,37.515236],"type":"Point"}
}