{
  "type": "Feature",
  "properties": {
    "addr:full":"23992 Aliso Creek Road Laguna Beach CA 92677",
    "addr:housenumber":"23992",
    "addr:postcode":"92677",
    "addr:street":"Aliso Creek Road",
    "iso:country":"US",
    "sg:address":"23992 Aliso Creek Road",
    "sg:city":"Laguna Beach",
    "sg:classifiers":[
        {
            "category":"Personal",
            "subcategory":"Shoe Repair & Shine",
            "type":"Services"
        }
    ],
    "sg:phone":"+1 949 643 1851",
    "sg:postcode":"92677",
    "sg:province":"CA",
    "wof:name":"Choice Shoe Repair",
    "wof:placetype":"venue"
},
  "geometry": {"coordinates":[-117.709763,33.55848],"type":"Point"}
}