{
  "type": "Feature",
  "properties": {
    "iso:country":"US",
    "sg:address":"8835 Olive Ln",
    "sg:city":"Santee",
    "sg:classifiers":[
        {
            "category":"Education",
            "subcategory":"Preschool",
            "type":"Public Place"
        },
        {
            "category":"Education",
            "subcategory":"School",
            "type":"Public Place"
        }
    ],
    "sg:phone":"+1 619 448 4767",
    "sg:postcode":"92071",
    "sg:province":"CA",
    "sg:tags":[
        "elementary"
    ],
    "wof:name":"Community Day Care Pre-School",
    "wof:placetype":"venue"
},
  "geometry": {"coordinates":[-116.987999,32.836399],"type":"Point"}
}