{
  "type": "Feature",
  "properties": {
    "iso:country":"US",
    "sg:address":"145 Westchester Dr",
    "sg:city":"Los Gatos",
    "sg:classifiers":[
        {
            "category":"Professional",
            "subcategory":"Employment Agencies",
            "type":"Services"
        }
    ],
    "sg:phone":"+1 408 358 1778",
    "sg:postcode":"95032",
    "sg:province":"CA",
    "sg:tags":[
        "consultant",
        "search",
        "executive"
    ],
    "wof:name":"Visadept",
    "wof:placetype":"venue"
},
  "geometry": {"coordinates":[-121.943442,37.239989],"type":"Point"}
}