{
  "type": "Feature",
  "properties": {
    "addr:full":"84 Keyes Street San Jose CA 95112",
    "addr:housenumber":"84",
    "addr:postcode":"95112",
    "addr:street":"Keyes Street",
    "iso:country":"US",
    "sg:address":"84 Keyes Street",
    "sg:city":"San Jose",
    "sg:classifiers":[
        {
            "category":"Restaurant",
            "type":"Food & Drink"
        }
    ],
    "sg:phone":"+1 408 947 9165",
    "sg:postcode":"95112",
    "sg:province":"CA",
    "sg:tags":[
        "mexican"
    ],
    "wof:name":"Carnitas El Rincon",
    "wof:placetype":"venue"
},
  "geometry": {"coordinates":[-121.876553,37.320573],"type":"Point"}
}