{
  "type": "Feature",
  "properties": {
    "addr:full":"13764 Jurupa Ave Fontana CA 92337",
    "addr:housenumber":"13764",
    "addr:postcode":"92337",
    "addr:street":"Jurupa Ave",
    "iso:country":"US",
    "sg:address":"13764 Jurupa Ave",
    "sg:city":"Fontana",
    "sg:classifiers":[
        {
            "category":"Freight",
            "type":"Transportation"
        }
    ],
    "sg:phone":"+1 909 357 2260",
    "sg:postcode":"92337",
    "sg:province":"CA",
    "sg:tags":[
        "specializing",
        "h",
        "storage",
        "cement",
        "trucking",
        "without",
        "local"
    ],
    "wof:name":"Valencia Trucking Corporation",
    "wof:placetype":"venue"
},
  "geometry": {"coordinates":[-117.505048,34.048219],"type":"Point"}
}