{
  "type": "Feature",
  "properties": {
    "addr:full":"320 E Bellevue Ave San Mateo CA 94401",
    "addr:housenumber":"320",
    "addr:postcode":"94401",
    "addr:street":"E Bellevue Ave",
    "iso:country":"US",
    "sg:address":"320 E Bellevue Ave",
    "sg:city":"San Mateo",
    "sg:classifiers":[
        {
            "category":"Wholesale",
            "subcategory":"Electrical",
            "type":"Manufacturing & Wholesale Goods"
        }
    ],
    "sg:phone":"+1 650 344 1416",
    "sg:postcode":"94401",
    "sg:province":"CA",
    "sg:tags":[
        "equipment",
        "electronic",
        "supply"
    ],
    "wof:name":"Polar Instruments Inc",
    "wof:placetype":"venue"
},
  "geometry": {"coordinates":[-122.33365000000001,37.573688],"type":"Point"}
}