{
  "type": "Feature",
  "properties": {
    "iso:country":"US",
    "sg:address":"4431 Slauson Ave",
    "sg:city":"Maywood",
    "sg:classifiers":[
        {
            "category":"Health Services",
            "subcategory":"Doctor",
            "type":"Services"
        }
    ],
    "sg:phone":"+1 323 560 8880",
    "sg:postcode":"90270",
    "sg:province":"CA",
    "sg:tags":[
        "medicine",
        "physician",
        "practice",
        "surgeons",
        "family"
    ],
    "wof:name":"Clinica Familiar De Los Latinos",
    "wof:placetype":"venue"
},
  "geometry": {"coordinates":[-118.186735,33.987257],"type":"Point"}
}