{
  "type": "Feature",
  "properties": {
    "addr:full":"24 E Cota St Santa Barbara CA 93101",
    "addr:housenumber":"24",
    "addr:postcode":"93101",
    "addr:street":"E Cota St",
    "iso:country":"US",
    "sg:address":"24 E Cota St",
    "sg:city":"Santa Barbara",
    "sg:classifiers":[
        {
            "category":"Professional",
            "type":"Services"
        }
    ],
    "sg:phone":"+1 805 564 8020",
    "sg:postcode":"93101",
    "sg:province":"CA",
    "sg:tags":[
        "establishment"
    ],
    "wof:name":"Serein Capital",
    "wof:placetype":"venue"
},
  "geometry": {"coordinates":[-119.69579,34.418512],"type":"Point"}
}