{
  "type": "Feature",
  "properties": {
    "addr:full":"3251 20th Ave San Francisco CA 94132",
    "addr:housenumber":"3251",
    "addr:postcode":"94132",
    "addr:street":"20Th Ave",
    "iso:country":"US",
    "sg:address":"3251 20th Ave",
    "sg:city":"San Francisco",
    "sg:classifiers":[
        {
            "category":"Coffee & Tea",
            "type":"Food & Drink"
        },
        {
            "category":"Shopping",
            "subcategory":"Books",
            "type":"Retail Goods"
        }
    ],
    "sg:phone":"+1 415 731 0665",
    "sg:postcode":"94132",
    "sg:province":"CA",
    "sg:tags":[
        "mags",
        "video",
        "books",
        "music"
    ],
    "sg:website":"www.bordersstores.com",
    "wof:name":"Borders",
    "wof:placetype":"venue"
},
  "geometry": {"coordinates":[-122.476766,37.728557],"type":"Point"}
}