{
  "type": "Feature",
  "properties": {
    "iso:country":"US",
    "sg:address":"2820 E Main St",
    "sg:city":"Barstow",
    "sg:classifiers":[
        {
            "category":"Building & Trades",
            "subcategory":"Construction",
            "type":"Services"
        }
    ],
    "sg:phone":"+1 760 256 0411",
    "sg:postcode":"92311",
    "sg:province":"CA",
    "sg:tags":[
        "product",
        "asphalt"
    ],
    "wof:name":"Yeager Skanska Inc",
    "wof:placetype":"venue"
},
  "geometry": {"coordinates":[-116.99368200000001,34.885447],"type":"Point"}
}