{
  "type": "Feature",
  "properties": {
    "addr:full":"3305 W Harvard St Santa Ana CA 92704",
    "addr:housenumber":"3305",
    "addr:postcode":"92704",
    "addr:street":"W Harvard St",
    "iso:country":"US",
    "sg:address":"3305 W Harvard St",
    "sg:city":"Santa Ana",
    "sg:classifiers":[
        {
            "category":"Shopping",
            "subcategory":"Antiques",
            "type":"Retail Goods"
        }
    ],
    "sg:phone":"+1 714 546 1720",
    "sg:postcode":"92704",
    "sg:province":"CA",
    "wof:name":"Y & L Antique Furniture",
    "wof:placetype":"venue"
},
  "geometry": {"coordinates":[-117.91300200000001,33.7201],"type":"Point"}
}