{
  "type": "Feature",
  "properties": {
    "addr:full":"110 Ridge Rd Sutter Creek CA 95685",
    "addr:housenumber":"110",
    "addr:postcode":"95685",
    "addr:street":"Ridge Rd",
    "iso:country":"US",
    "sg:address":"110 Ridge Rd",
    "sg:city":"Sutter Creek",
    "sg:classifiers":[
        {
            "category":"Retail",
            "subcategory":"Car Wash",
            "type":"Services"
        }
    ],
    "sg:phone":"+1 209 267 9826",
    "sg:postcode":"95685",
    "sg:province":"CA",
    "sg:tags":[
        "polishing",
        "washing"
    ],
    "wof:name":"Sutter Creek Car Wash",
    "wof:placetype":"venue"
},
  "geometry": {"coordinates":[-120.80155000000001,38.379062],"type":"Point"}
}