{
  "type": "Feature",
  "properties": {
    "addr:full":"17381 Nichols St Ste F Huntington Beach CA 92647",
    "addr:housenumber":"17381",
    "addr:postcode":"92647",
    "addr:street":"Nichols St Ste F",
    "iso:country":"US",
    "sg:address":"17381 Nichols St Ste F",
    "sg:city":"Huntington Beach",
    "sg:classifiers":[
        {
            "category":"Shopping",
            "subcategory":"Antiques",
            "type":"Retail Goods"
        }
    ],
    "sg:phone":"+1 714 847 0908",
    "sg:postcode":"92647",
    "sg:province":"CA",
    "wof:name":"Sunset Strip",
    "wof:placetype":"venue"
},
  "geometry": {"coordinates":[-117.996002,33.710499],"type":"Point"}
}