{
  "type": "Feature",
  "properties": {
    "iso:country":"US",
    "sg:address":"1670 Locust St",
    "sg:city":"Walnut Creek",
    "sg:classifiers":[
        {
            "category":"Restaurant",
            "type":"Food & Drink"
        }
    ],
    "sg:phone":"+1 925 933 8883",
    "sg:postcode":"94596",
    "sg:province":"CA",
    "wof:name":"Mariposa Chinese Cuisine",
    "wof:placetype":"venue"
},
  "geometry": {"coordinates":[-122.063101,37.901668],"type":"Point"}
}