{
  "type": "Feature",
  "properties": {
    "addr:full":"2009 E Montclair Plaza Ln Montclair CA 91763",
    "addr:housenumber":"2009",
    "addr:postcode":"91763",
    "addr:street":"E Montclair Plaza Ln",
    "iso:country":"US",
    "sg:address":"2009 E Montclair Plaza Ln",
    "sg:city":"Montclair",
    "sg:classifiers":[
        {
            "category":"Shopping",
            "subcategory":"Jewelry",
            "type":"Retail Goods"
        }
    ],
    "sg:phone":"+1 909 624 9828",
    "sg:postcode":"91763",
    "sg:province":"CA",
    "sg:tags":[
        "jeweler"
    ],
    "wof:name":"Romano's Jewelers",
    "wof:placetype":"venue"
},
  "geometry": {"coordinates":[-117.69083999999999,34.087187],"type":"Point"}
}