{
  "type": "Feature",
  "properties": {
    "iso:country":"US",
    "sg:address":"10705 Rush St",
    "sg:city":"South El Monte",
    "sg:classifiers":[
        {
            "category":"Wholesale",
            "subcategory":"Non-durable Goods",
            "type":"Manufacturing & Wholesale Goods"
        }
    ],
    "sg:phone":"+1 626 279 5258",
    "sg:postcode":"91733",
    "sg:province":"CA",
    "wof:name":"Platinum Time Corp",
    "wof:placetype":"venue"
},
  "geometry": {"coordinates":[-118.04213300000001,34.051924],"type":"Point"}
}