{
  "type": "Feature",
  "properties": {
    "addr:full":"19123 Bloomfield Ave Cerritos CA 90703",
    "addr:housenumber":"19123",
    "addr:postcode":"ca 90703",
    "addr:street":"Bloomfield Ave",
    "iso:country":"US",
    "sg:address":"19123 Bloomfield Ave",
    "sg:city":"Cerritos",
    "sg:classifiers":[
        {
            "category":"Health Services",
            "subcategory":"Chiropractor",
            "type":"Services"
        }
    ],
    "sg:phone":"+1 562 809 1833",
    "sg:postcode":"90703",
    "sg:province":"CA",
    "wof:name":"Kwon Chiropractic Center",
    "wof:placetype":"venue"
},
  "geometry": {"coordinates":[-118.064003,33.857201],"type":"Point"}
}