{
  "type": "Feature",
  "properties": {
    "iso:country":"US",
    "sg:address":"3000 N Fresno St",
    "sg:city":"Fresno",
    "sg:classifiers":[
        {
            "category":"Health Services",
            "subcategory":"Optometrist",
            "type":"Services"
        }
    ],
    "sg:phone":"+1 559 221 1414",
    "sg:postcode":"93703",
    "sg:province":"CA",
    "wof:name":"Stephen Parker OD",
    "wof:placetype":"venue"
},
  "geometry": {"coordinates":[-119.781463,36.779598],"type":"Point"}
}