{
  "type": "Feature",
  "properties": {
    "iso:country":"US",
    "sg:address":"6960 Eastside Ct",
    "sg:city":"Orangevale",
    "sg:classifiers":[
        {
            "category":"Professional",
            "subcategory":"Business Services",
            "type":"Services"
        }
    ],
    "sg:phone":"+1 916 988 9723",
    "sg:postcode":"95662",
    "sg:province":"CA",
    "sg:tags":[
        "interior",
        "consultant",
        "design",
        "decorator"
    ],
    "wof:name":"Design Creations",
    "wof:placetype":"venue"
},
  "geometry": {"coordinates":[-121.24255700000001,38.692476],"type":"Point"}
}