{
  "type": "Feature",
  "properties": {
    "addr:full":"3121 W Benjamin Holt Dr Stockton CA 95219",
    "addr:housenumber":"3121",
    "addr:postcode":"95219",
    "addr:street":"W Benjamin Holt Dr",
    "iso:country":"US",
    "sg:address":"3121 W Benjamin Holt Dr",
    "sg:city":"Stockton",
    "sg:classifiers":[
        {
            "category":"Restaurant",
            "type":"Food & Drink"
        }
    ],
    "sg:phone":"+1 209 957 0536",
    "sg:postcode":"95219",
    "sg:province":"CA",
    "sg:website":"www.lebistrostockton.com",
    "wof:name":"Le Bistro Banquets",
    "wof:placetype":"venue"
},
  "geometry": {"coordinates":[-121.35561800000001,38.005282],"type":"Point"}
}