{
  "type": "Feature",
  "properties": {
    "addr:full":"4345 Mission Bay Dr. San Diego CA 92109",
    "addr:housenumber":"4345",
    "addr:postcode":"92109",
    "addr:street":"Mission Bay Dr.",
    "iso:country":"US",
    "sg:address":"4345 Mission Bay Dr.",
    "sg:city":"San Diego",
    "sg:classifiers":[
        {
            "category":"Travel",
            "subcategory":"Hotels & Motels",
            "type":"Entertainment"
        }
    ],
    "sg:phone":"+1 858 273 1121",
    "sg:postcode":"92109",
    "sg:province":"CA",
    "wof:name":"Pacific Coast Inn and Suites",
    "wof:placetype":"venue"
},
  "geometry": {"coordinates":[-117.212739,32.799875],"type":"Point"}
}