{
  "type": "Feature",
  "properties": {
    "addr:full":"765 Nevada St Gridley CA 95948",
    "addr:housenumber":"765",
    "addr:postcode":"95948",
    "addr:street":"Nevada St",
    "iso:country":"US",
    "sg:address":"765 Nevada St",
    "sg:city":"Gridley",
    "sg:classifiers":[
        {
            "category":"Organizations",
            "subcategory":"Religious Organization",
            "type":"Services"
        }
    ],
    "sg:phone":"+1 530 846 4002",
    "sg:postcode":"95948",
    "sg:province":"CA",
    "sg:tags":[
        "church"
    ],
    "wof:name":"First Christian Church",
    "wof:placetype":"venue"
},
  "geometry": {"coordinates":[-121.705033,39.365287],"type":"Point"}
}