{
  "type": "Feature",
  "properties": {
    "addr:full":"9630 Kiefer Blvd Sacramento CA 95827",
    "addr:housenumber":"9630",
    "addr:postcode":"95827",
    "addr:street":"Kiefer Blvd",
    "iso:country":"US",
    "sg:address":"9630 Kiefer Blvd",
    "sg:city":"Sacramento",
    "sg:classifiers":[
        {
            "category":"Banks & Credit Unions",
            "subcategory":"Financial Services",
            "type":"Services"
        }
    ],
    "sg:phone":"+1 916 362 1500",
    "sg:postcode":"95827",
    "sg:province":"CA",
    "sg:tags":[
        "broker",
        "mortgage"
    ],
    "wof:name":"Ardent Mortgage",
    "wof:placetype":"venue"
},
  "geometry": {"coordinates":[-121.337087,38.543656],"type":"Point"}
}