{
  "type": "Feature",
  "properties": {
    "addr:full":"787 S H St Livermore CA 94550",
    "addr:housenumber":"787",
    "addr:postcode":"94550",
    "addr:street":"S H St",
    "iso:country":"US",
    "sg:address":"787 S H St",
    "sg:city":"Livermore",
    "sg:phone":"+1 925 892 8888",
    "sg:postcode":"94550",
    "sg:province":"CA",
    "sg:tags":[
        "farm",
        "corn",
        "tree",
        "cash",
        "grove",
        "grain",
        "nut"
    ],
    "wof:name":"Torrison Ranch John",
    "wof:placetype":"venue"
},
  "geometry": {"coordinates":[-121.764037,37.677374],"type":"Point"}
}