{
  "type": "Feature",
  "properties": {
    "addr:full":"545 Laurel St Petaluma CA 94952",
    "addr:housenumber":"545",
    "addr:postcode":"94952",
    "addr:street":"Laurel St",
    "iso:country":"US",
    "sg:address":"545 Laurel St",
    "sg:city":"Petaluma",
    "sg:classifiers":[
        {
            "category":"Shopping",
            "subcategory":"Used Merchandise",
            "type":"Retail Goods"
        }
    ],
    "sg:phone":"+1 707 762 7299",
    "sg:postcode":"94952",
    "sg:province":"CA",
    "wof:name":"North of South Trading",
    "wof:placetype":"venue"
},
  "geometry": {"coordinates":[-122.652649,38.239689],"type":"Point"}
}