{
  "type": "Feature",
  "properties": {
    "iso:country":"US",
    "sg:address":"100 N 1st St",
    "sg:city":"Burbank",
    "sg:classifiers":[
        {
            "category":"Insurance",
            "subcategory":"Hazard Insurance",
            "type":"Services"
        }
    ],
    "sg:phone":"+1 818 841 1866",
    "sg:postcode":"91502",
    "sg:province":"CA",
    "sg:tags":[
        "casualty"
    ],
    "sg:website":"www.hsb.com",
    "wof:name":"Hartford Steam Boiler Ins Co",
    "wof:placetype":"venue"
},
  "geometry": {"coordinates":[-118.310174,34.179812],"type":"Point"}
}