{
  "type": "Feature",
  "properties": {
    "addr:full":"2757 Leonis Blvd Los Angeles CA 90058",
    "addr:housenumber":"2757",
    "addr:postcode":"90058",
    "addr:street":"Leonis Blvd",
    "iso:country":"US",
    "sg:address":"2757 Leonis Blvd",
    "sg:city":"Los Angeles",
    "sg:classifiers":[
        {
            "category":"Retail",
            "subcategory":"Auto Rental",
            "type":"Services"
        }
    ],
    "sg:phone":"+1 323 582 7271",
    "sg:postcode":"90058",
    "sg:province":"CA",
    "sg:tags":[
        "leasing",
        "driver",
        "truck",
        "no"
    ],
    "wof:name":"Paclease",
    "wof:placetype":"venue"
},
  "geometry": {"coordinates":[-118.220873,34.00011],"type":"Point"}
}