{
  "type": "Feature",
  "properties": {
    "iso:country":"US",
    "sg:address":"1010 Fair Ave Ste D",
    "sg:city":"Santa Cruz",
    "sg:classifiers":[
        {
            "category":"Shopping",
            "subcategory":"Jewelry",
            "type":"Retail Goods"
        },
        {
            "category":"Personal",
            "subcategory":"Piercing",
            "type":"Services"
        }
    ],
    "sg:phone":"+1 831 676 8048",
    "sg:postcode":"95060",
    "sg:province":"CA",
    "sg:website":"waybodyarts.wordpress.com",
    "wof:name":"WAY Body Arts",
    "wof:placetype":"venue"
},
  "geometry": {"coordinates":[-122.04561200000001,36.958894],"type":"Point"}
}