{
  "type": "Feature",
  "properties": {
    "iso:country":"US",
    "sg:address":"716 Basswood Ave",
    "sg:city":"Imperial Beach",
    "sg:classifiers":[
        {
            "category":"Wholesale",
            "subcategory":"Home Furnishings",
            "type":"Manufacturing & Wholesale Goods"
        }
    ],
    "sg:phone":"+1 619 423 2070",
    "sg:postcode":"91932",
    "sg:province":"CA",
    "sg:tags":[
        "picture",
        "frame"
    ],
    "wof:name":"Artco Picture Frames",
    "wof:placetype":"venue"
},
  "geometry": {"coordinates":[-117.11784400000001,32.590354],"type":"Point"}
}