{
  "type": "Feature",
  "properties": {
    "addr:full":"2018 Berryhill Ave Tulare CA 93274",
    "addr:housenumber":"2018",
    "addr:postcode":"93274",
    "addr:street":"Berryhill Ave",
    "iso:country":"US",
    "sg:address":"2018 Berryhill Ave",
    "sg:city":"Tulare",
    "sg:classifiers":[
        {
            "category":"Professional",
            "subcategory":"Computer Services",
            "type":"Services"
        }
    ],
    "sg:phone":"+1 559 358 0219",
    "sg:postcode":"93274",
    "sg:province":"CA",
    "sg:tags":[
        "home",
        "consulting",
        "page",
        "dev",
        "internet"
    ],
    "wof:name":"Mystic Web Designs",
    "wof:placetype":"venue"
},
  "geometry": {"coordinates":[-119.375292,36.224502],"type":"Point"}
}