{
  "type": "Feature",
  "properties": {
    "iso:country":"US",
    "sg:address":"450 Helen Dr",
    "sg:city":"Ripon",
    "sg:classifiers":[
        {
            "category":"Health Services",
            "subcategory":"Doctor",
            "type":"Services"
        }
    ],
    "sg:phone":"+1 209 599 7867",
    "sg:postcode":"95366",
    "sg:province":"CA",
    "sg:tags":[
        "physician",
        "surgeon"
    ],
    "wof:name":"Agapito Campa",
    "wof:placetype":"venue"
},
  "geometry": {"coordinates":[-121.11873900000001,37.749978],"type":"Point"}
}