{
  "type": "Feature",
  "properties": {
    "addr:full":"727 N Ave 51 Los Angeles CA 90042",
    "addr:housenumber":"727;51",
    "addr:postcode":"90042",
    "addr:street":"N Ave",
    "iso:country":"US",
    "sg:address":"727 N Ave 51",
    "sg:city":"Los Angeles",
    "sg:classifiers":[
        {
            "category":"Building & Trades",
            "subcategory":"Construction",
            "type":"Services"
        }
    ],
    "sg:phone":"+1 323 353 6494",
    "sg:postcode":"90042",
    "sg:province":"CA",
    "sg:tags":[
        "painter"
    ],
    "wof:name":"New Millenium Painting",
    "wof:placetype":"venue"
},
  "geometry": {"coordinates":[-118.205427,34.114846],"type":"Point"}
}