{
  "type": "Feature",
  "properties": {
    "addr:full":"31579 Castaic Rd Castaic CA 91384",
    "addr:housenumber":"31579",
    "addr:postcode":"91384",
    "addr:street":"Castaic Rd",
    "iso:country":"US",
    "sg:address":"31579 Castaic Rd",
    "sg:city":"Castaic",
    "sg:classifiers":[
        {
            "category":"Bars & Pubs",
            "subcategory":"Nightclub",
            "type":"Food & Drink"
        }
    ],
    "sg:phone":"+1 661 295 8755",
    "sg:postcode":"91384",
    "sg:province":"CA",
    "sg:tags":[
        "nightlife"
    ],
    "wof:name":"Howie's Pub",
    "wof:placetype":"venue"
},
  "geometry": {"coordinates":[-118.61900300000001,34.492199],"type":"Point"}
}