{
  "type": "Feature",
  "properties": {
    "addr:full":"633 N Main St Porterville CA 93257",
    "addr:housenumber":"633",
    "addr:postcode":"93257",
    "addr:street":"N Main St",
    "iso:country":"US",
    "sg:address":"633 N Main St",
    "sg:city":"Porterville",
    "sg:classifiers":[
        {
            "category":"Personal",
            "subcategory":"Beauty Salon",
            "type":"Services"
        }
    ],
    "sg:phone":"+1 559 784 1602",
    "sg:postcode":"93257",
    "sg:province":"CA",
    "wof:name":"Jamie's Beauty Boutique",
    "wof:placetype":"venue"
},
  "geometry": {"coordinates":[-119.01833600000001,36.078083],"type":"Point"}
}