{
  "type": "Feature",
  "properties": {
    "iso:country":"US",
    "sg:address":"2205 Hilltop Dr",
    "sg:city":"Redding",
    "sg:classifiers":[
        {
            "category":"Manufacturing",
            "subcategory":"Lumber",
            "type":"Manufacturing & Wholesale Goods"
        }
    ],
    "sg:phone":"+1 541 915 4200",
    "sg:postcode":"96002",
    "sg:province":"CA",
    "sg:tags":[
        "fire",
        "logging",
        "fighting"
    ],
    "wof:name":"Barry Brown Inc",
    "wof:placetype":"venue"
},
  "geometry": {"coordinates":[-122.35785300000001,40.573045],"type":"Point"}
}