{
  "type": "Feature",
  "properties": {
    "addr:full":"8649 Gunner Way Fair Oaks CA 95628",
    "addr:housenumber":"8649",
    "addr:postcode":"95628",
    "addr:street":"Gunner Way",
    "iso:country":"US",
    "sg:address":"8649 Gunner Way",
    "sg:city":"Fair Oaks",
    "sg:classifiers":[
        {
            "category":"Building & Trades",
            "subcategory":"Construction",
            "type":"Services"
        }
    ],
    "sg:phone":"+1 916 966 7285",
    "sg:postcode":"95628",
    "sg:province":"CA",
    "sg:tags":[
        "contractor"
    ],
    "wof:name":"Kearney Paul Inc",
    "wof:placetype":"venue"
},
  "geometry": {"coordinates":[-121.23984,38.658112],"type":"Point"}
}