{
  "type": "Feature",
  "properties": {
    "iso:country":"US",
    "sg:address":"7730 Burnet Ave",
    "sg:city":"Van Nuys",
    "sg:classifiers":[
        {
            "category":"Building & Trades",
            "subcategory":"Plumbing",
            "type":"Services"
        }
    ],
    "sg:phone":"+1 818 894 5154",
    "sg:postcode":"91405",
    "sg:province":"CA",
    "sg:tags":[
        "plumbing",
        "contractor"
    ],
    "wof:name":"Stevenson Plumbing",
    "wof:placetype":"venue"
},
  "geometry": {"coordinates":[-118.462851,34.21152],"type":"Point"}
}