{
  "type": "Feature",
  "properties": {
    "addr:full":"4343 Nobel Dr San Diego CA 92122",
    "addr:housenumber":"4343",
    "addr:postcode":"92122",
    "addr:street":"Nobel Dr",
    "iso:country":"US",
    "sg:address":"4343 Nobel Dr",
    "sg:city":"San Diego",
    "sg:classifiers":[
        {
            "category":"Local Transit",
            "type":"Transportation"
        }
    ],
    "sg:phone":"+1 858 558 1277",
    "sg:postcode":"92122",
    "sg:province":"CA",
    "wof:name":"Afkham Iraj",
    "wof:placetype":"venue"
},
  "geometry": {"coordinates":[-117.212205,32.867036],"type":"Point"}
}