{
  "type": "Feature",
  "properties": {
    "iso:country":"US",
    "sg:address":"2331 29th St",
    "sg:city":"Santa Monica",
    "sg:classifiers":[
        {
            "category":"Building & Trades",
            "subcategory":"Construction",
            "type":"Services"
        }
    ],
    "sg:phone":"+1 310 399 0888",
    "sg:postcode":"90405",
    "sg:province":"CA",
    "sg:tags":[
        "contractor"
    ],
    "wof:name":"Silverman Roofing & Cnstr",
    "wof:placetype":"venue"
},
  "geometry": {"coordinates":[-118.458297,34.023691],"type":"Point"}
}