{
  "type": "Feature",
  "properties": {
    "addr:full":"1100 S San Pedro St Los Angeles CA 90015",
    "addr:housenumber":"1100",
    "addr:postcode":"90015",
    "addr:street":"S San Pedro St",
    "iso:country":"US",
    "sg:address":"1100 S San Pedro St",
    "sg:city":"Los Angeles",
    "sg:classifiers":[
        {
            "category":"Shopping",
            "subcategory":"Clothing, Apparel, & Fashions",
            "type":"Retail Goods"
        }
    ],
    "sg:phone":"+1 213 741 0100",
    "sg:postcode":"90015",
    "sg:province":"CA",
    "sg:tags":[
        "accessory",
        "clothing",
        "women's"
    ],
    "wof:name":"Good Time USA",
    "wof:placetype":"venue"
},
  "geometry": {"coordinates":[-118.251897,34.034467],"type":"Point"}
}