{
  "type": "Feature",
  "properties": {
    "addr:full":"8753 Industrial Ln Rancho Cucamonga CA 91730",
    "addr:housenumber":"8753",
    "addr:postcode":"91730",
    "addr:street":"Industrial Ln",
    "iso:country":"US",
    "sg:address":"8753 Industrial Ln",
    "sg:city":"Rancho Cucamonga",
    "sg:classifiers":[
        {
            "category":"Manufacturing",
            "subcategory":"Electronics",
            "type":"Manufacturing & Wholesale Goods"
        }
    ],
    "sg:phone":"+1 909 286 6516",
    "sg:postcode":"91730",
    "sg:province":"CA",
    "sg:tags":[
        "equipment",
        "electronic",
        "supply"
    ],
    "wof:name":"Microtech Solutions Group",
    "wof:placetype":"venue"
},
  "geometry": {"coordinates":[-117.59645,34.094822],"type":"Point"}
}