{
  "type": "Feature",
  "properties": {
    "iso:country":"US",
    "sg:address":"232 E Sepulveda Blvd",
    "sg:city":"Carson",
    "sg:classifiers":[
        {
            "category":"Personal",
            "subcategory":"Nail Salon",
            "type":"Services"
        }
    ],
    "sg:phone":"+1 310 513 8960",
    "sg:postcode":"90745",
    "sg:province":"CA",
    "wof:name":"Skin Care Nails & Spa",
    "wof:placetype":"venue"
},
  "geometry": {"coordinates":[-118.272044,33.807967],"type":"Point"}
}