{
  "type": "Feature",
  "properties": {
    "addr:full":"654 Mission St, San Francisco, CA 94105",
    "addr:housenumber":"654",
    "addr:postcode":"94105",
    "addr:street":"mission st",
    "iso:country":"US",
    "wof:name":"St. Clare Coffee",
    "wof:placetype":"venue"
},
  "geometry": {"coordinates":[-122.401235,37.787183],"type":"Point"}
}