{
  "type": "Feature",
  "properties": {
    "addr:full":"351 Gabilan Dr Soledad CA 93960",
    "addr:housenumber":"351",
    "addr:postcode":"93960",
    "addr:street":"Gabilan Dr",
    "iso:country":"US",
    "sg:address":"351 Gabilan Dr",
    "sg:city":"Soledad",
    "sg:classifiers":[
        {
            "category":"Sports & Exercise",
            "subcategory":"Gym",
            "type":"Entertainment"
        }
    ],
    "sg:phone":"+1 831 678 3990",
    "sg:postcode":"93960",
    "sg:province":"CA",
    "sg:tags":[
        "club",
        "health",
        "studio",
        "gymnasium"
    ],
    "wof:name":"Circuit Ladies Fitness",
    "wof:placetype":"venue"
},
  "geometry": {"coordinates":[-121.326317,36.435895],"type":"Point"}
}