{
  "type": "Feature",
  "properties": {
    "addr:full":"13785 Via Real Desert Hot Spgs CA 92240",
    "addr:housenumber":"13785",
    "addr:postcode":"92240",
    "addr:street":"Via Real;Hot Spgs",
    "iso:country":"US",
    "sg:address":"13785 Via Real",
    "sg:city":"Desert Hot Spgs",
    "sg:classifiers":[
        {
            "category":"Social Services",
            "subcategory":"Job Training",
            "type":"Services"
        }
    ],
    "sg:phone":"+1 760 329 8403",
    "sg:postcode":"92240",
    "sg:province":"CA",
    "sg:tags":[
        "rehabilitation"
    ],
    "sg:website":"www.angelview.org",
    "wof:name":"Angel View Crippled Children's",
    "wof:placetype":"venue"
},
  "geometry": {"coordinates":[-116.512326,33.948413],"type":"Point"}
}