{
  "type": "Feature",
  "properties": {
    "iso:country":"US",
    "sg:address":"3177 Glendale Blvd",
    "sg:city":"Los Angeles",
    "sg:classifiers":[
        {
            "category":"Manufacturing",
            "subcategory":"Printing",
            "type":"Manufacturing & Wholesale Goods"
        }
    ],
    "sg:phone":"+1 323 662 4511",
    "sg:postcode":"90039",
    "sg:province":"CA",
    "sg:tags":[
        "label"
    ],
    "sg:website":"www.aklabels.com",
    "wof:name":"A & K Labels Inc",
    "wof:placetype":"venue"
},
  "geometry": {"coordinates":[-118.262001,34.116798],"type":"Point"}
}