{
  "type": "Feature",
  "properties": {
    "addr:full":"10 Nautilus Pl Pittsburg CA 94565",
    "addr:housenumber":"10",
    "addr:postcode":"94565",
    "addr:street":"Nautilus Pl",
    "iso:country":"US",
    "sg:address":"10 Nautilus Pl",
    "sg:city":"Pittsburg",
    "sg:classifiers":[
        {
            "category":"Shopping",
            "subcategory":"Clothing, Apparel, & Fashions",
            "type":"Retail Goods"
        }
    ],
    "sg:phone":"+1 925 439 2746",
    "sg:postcode":"94565",
    "sg:province":"CA",
    "wof:name":"Bridal Beginnings",
    "wof:placetype":"venue"
},
  "geometry": {"coordinates":[-121.92136000000001,38.024842],"type":"Point"}
}