{
  "type": "Feature",
  "properties": {
    "addr:full":"504 Sun Tree Ct Roseville CA 95661",
    "addr:housenumber":"504",
    "addr:postcode":"95661",
    "addr:street":"Sun Tree Ct",
    "iso:country":"US",
    "sg:address":"504 Sun Tree Ct",
    "sg:city":"Roseville",
    "sg:classifiers":[
        {
            "category":"Social Services",
            "subcategory":"Adult Care",
            "type":"Services"
        }
    ],
    "sg:phone":"+1 916 772 2159",
    "sg:postcode":"95661",
    "sg:province":"CA",
    "sg:tags":[
        "home",
        "residential"
    ],
    "wof:name":"LA Rotonda",
    "wof:placetype":"venue"
},
  "geometry": {"coordinates":[-121.270217,38.724236],"type":"Point"}
}