{
  "type": "Feature",
  "properties": {
    "addr:full":"2025 N Long Beach Blvd Compton CA 90221",
    "addr:housenumber":"2025",
    "addr:postcode":"90221",
    "addr:street":"N Long Beach Blvd",
    "iso:country":"US",
    "sg:address":"2025 N Long Beach Blvd",
    "sg:city":"Compton",
    "sg:classifiers":[
        {
            "category":"Shopping",
            "type":"Retail Goods"
        },
        {
            "category":"Shopping",
            "subcategory":"Florist",
            "type":"Retail Goods"
        }
    ],
    "sg:phone":"+1 310 632 5268",
    "sg:postcode":"90221",
    "sg:province":"CA",
    "sg:tags":[
        "plant",
        "flower",
        "tree",
        "artificial"
    ],
    "wof:name":"Lucy's Flowers",
    "wof:placetype":"venue"
},
  "geometry": {"coordinates":[-118.208958,33.909977],"type":"Point"}
}