{
  "type": "Feature",
  "properties": {
    "addr:full":"81 E Daily Dr Camarillo CA 93010",
    "addr:housenumber":"81",
    "addr:postcode":"93010",
    "addr:street":"E Daily Dr",
    "iso:country":"US",
    "sg:address":"81 E Daily Dr",
    "sg:city":"Camarillo",
    "sg:classifiers":[
        {
            "category":"Personal",
            "subcategory":"Beauty Salon",
            "type":"Services"
        }
    ],
    "sg:phone":"+1 805 388 8166",
    "sg:postcode":"93010",
    "sg:province":"CA",
    "sg:tags":[
        "nail",
        "manicuring"
    ],
    "wof:name":"Nails by Julie",
    "wof:placetype":"venue"
},
  "geometry": {"coordinates":[-119.069,34.221901],"type":"Point"}
}