{
  "type": "Feature",
  "properties": {
    "addr:full":"18981 Gravel Plant Rd Redding CA 96002",
    "addr:housenumber":"18981",
    "addr:postcode":"96002",
    "addr:street":"Gravel Plant Rd",
    "iso:country":"US",
    "sg:address":"18981 Gravel Plant Rd",
    "sg:city":"Redding",
    "sg:classifiers":[
        {
            "category":"Building & Trades",
            "subcategory":"Construction",
            "type":"Services"
        }
    ],
    "sg:phone":"+1 530 224 9303",
    "sg:postcode":"96002",
    "sg:province":"CA",
    "sg:tags":[
        "industrial"
    ],
    "wof:name":"Built Well Steel Building Mate",
    "wof:placetype":"venue"
},
  "geometry": {"coordinates":[-122.35692,40.50839],"type":"Point"}
}