{
  "type": "Feature",
  "properties": {
    "iso:country":"US",
    "sg:address":"7565 Acama St",
    "sg:city":"San Diego",
    "sg:classifiers":[
        {
            "category":"Professional",
            "subcategory":"Research",
            "type":"Services"
        }
    ],
    "sg:phone":"+1 858 578 9361",
    "sg:postcode":"92126",
    "sg:province":"CA",
    "sg:tags":[
        "environmental",
        "ecological"
    ],
    "wof:name":"Craig R Lorenz & Assoc",
    "wof:placetype":"venue"
},
  "geometry": {"coordinates":[-117.15901100000001,32.926529],"type":"Point"}
}