{
  "type": "Feature",
  "properties": {
    "iso:country":"US",
    "sg:address":"2321 Rosecrans Ave",
    "sg:city":"El Segundo",
    "sg:classifiers":[
        {
            "category":"Government",
            "subcategory":"Office",
            "type":"Public Place"
        }
    ],
    "sg:phone":"+1 310 643 3636",
    "sg:postcode":"90266",
    "sg:province":"CA",
    "sg:tags":[
        "legislative",
        "body"
    ],
    "wof:name":"Jane Harman",
    "wof:placetype":"venue"
},
  "geometry": {"coordinates":[-118.382273,33.901973],"type":"Point"}
}