{
  "type": "Feature",
  "properties": {
    "iso:country":"US",
    "sg:address":"696 Dunraven Ct",
    "sg:city":"San Jose",
    "sg:classifiers":[
        {
            "category":"Shopping",
            "subcategory":"Hobbies, Toys, & Games",
            "type":"Retail Goods"
        }
    ],
    "sg:phone":"+1 408 227 4443",
    "sg:postcode":"95136",
    "sg:province":"CA",
    "wof:name":"Wood Crafts",
    "wof:placetype":"venue"
},
  "geometry": {"coordinates":[-121.855317,37.262349],"type":"Point"}
}