{
  "type": "Feature",
  "properties": {
    "iso:country":"US",
    "sg:address":"9637 Arrow Rte",
    "sg:city":"Rancho Cucamonga",
    "sg:classifiers":[
        {
            "category":"Home & Garden",
            "subcategory":"Furniture",
            "type":"Retail Goods"
        }
    ],
    "sg:phone":"+1 909 941 6978",
    "sg:postcode":"91730",
    "sg:province":"CA",
    "wof:name":"Vinyard Manor",
    "wof:placetype":"venue"
},
  "geometry": {"coordinates":[-117.595646,34.099248],"type":"Point"}
}