{
  "type": "Feature",
  "properties": {
    "iso:country":"US",
    "sg:address":"Washington & Normandie",
    "sg:city":"Los Angeles",
    "sg:classifiers":[
        {
            "category":"Restaurant",
            "type":"Food & Drink"
        },
        {
            "category":"Food Court",
            "type":"Food & Drink"
        }
    ],
    "sg:postcode":"90018",
    "sg:province":"CA",
    "sg:tags":[
        "mexican",
        "stand"
    ],
    "wof:name":"Street Taco Shop",
    "wof:placetype":"venue"
},
  "geometry": {"coordinates":[-118.30034000000001,34.039965],"type":"Point"}
}