{
  "type": "Feature",
  "properties": {
    "iso:country":"US",
    "sg:address":"3419 Faith Home Rd",
    "sg:city":"Ceres",
    "sg:classifiers":[
        {
            "category":"Farming",
            "subcategory":"Orchard",
            "type":"Manufacturing & Wholesale Goods"
        }
    ],
    "sg:phone":"+1 209 537 0778",
    "sg:postcode":"95307",
    "sg:province":"CA",
    "sg:tags":[
        "grove",
        "nut",
        "fruit",
        "tree"
    ],
    "wof:name":"Grubeck Fruit Ranch Inc",
    "wof:placetype":"venue"
},
  "geometry": {"coordinates":[-120.92050500000001,37.584999],"type":"Point"}
}