{
  "type": "Feature",
  "properties": {
    "iso:country":"US",
    "sg:address":"3051 S Alameda St",
    "sg:city":"Vernon",
    "sg:classifiers":[
        {
            "category":"Shopping",
            "subcategory":"Crafts & Fabrics",
            "type":"Retail Goods"
        }
    ],
    "sg:phone":"+1 323 235 0909",
    "sg:postcode":"90058",
    "sg:province":"CA",
    "sg:tags":[
        "knit"
    ],
    "wof:name":"Fabconx",
    "wof:placetype":"venue"
},
  "geometry": {"coordinates":[-118.23967,34.010345],"type":"Point"}
}