{
  "type": "Feature",
  "properties": {
    "iso:country":"US",
    "sg:address":"6406 Van Nuys Blvd",
    "sg:city":"Van Nuys",
    "sg:classifiers":[
        {
            "category":"Shopping",
            "subcategory":"Music",
            "type":"Retail Goods"
        }
    ],
    "sg:phone":"+1 818 997 3665",
    "sg:postcode":"91401",
    "sg:province":"CA",
    "sg:tags":[
        "tape",
        "bookstore",
        "disc",
        "video",
        "cassette"
    ],
    "wof:name":"Diamond Adult World",
    "wof:placetype":"venue"
},
  "geometry": {"coordinates":[-118.44899700000001,34.186901],"type":"Point"}
}