{
  "type": "Feature",
  "properties": {
    "addr:full":"83460 Capricorn Ave Indio CA 92201",
    "addr:housenumber":"83460",
    "addr:postcode":"92201",
    "addr:street":"Capricorn Ave",
    "iso:country":"US",
    "sg:address":"83460 Capricorn Ave",
    "sg:city":"Indio",
    "sg:classifiers":[
        {
            "category":"Freight",
            "type":"Transportation"
        }
    ],
    "sg:phone":"+1 760 347 3646",
    "sg:postcode":"92201",
    "sg:province":"CA",
    "sg:tags":[
        "petroleum"
    ],
    "wof:name":"RR Petroleum Transport",
    "wof:placetype":"venue"
},
  "geometry": {"coordinates":[-116.20956099999999,33.710446],"type":"Point"}
}