{
  "type": "Feature",
  "properties": {
    "addr:full":"1833 10th Ave Rm 26 Oakland CA 94606",
    "addr:housenumber":"1833;26",
    "addr:postcode":"94606",
    "addr:street":"10Th Ave Rm",
    "iso:country":"US",
    "sg:address":"1833 10th Ave Rm 26",
    "sg:city":"Oakland",
    "sg:classifiers":[
        {
            "category":"Social Services",
            "type":"Services"
        },
        {
            "category":"Professional",
            "subcategory":"Employment Agencies",
            "type":"Services"
        }
    ],
    "sg:phone":"+1 415 717 5445",
    "sg:postcode":"94606",
    "sg:province":"CA",
    "sg:tags":[
        "workers'",
        "placement",
        "volunteer"
    ],
    "wof:name":"Knowledge Is The Key Foundation Inc",
    "wof:placetype":"venue"
},
  "geometry": {"coordinates":[-122.24567999999999,37.794927],"type":"Point"}
}