{
  "type": "Feature",
  "properties": {
    "iso:country":"US",
    "sg:address":"901 U St",
    "sg:city":"Sacramento",
    "sg:classifiers":[
        {
            "category":"Banks & Credit Unions",
            "subcategory":"Investment Brokerage",
            "type":"Services"
        },
        {
            "category":"Banks & Credit Unions",
            "subcategory":"Financial Services",
            "type":"Services"
        }
    ],
    "sg:phone":"+1 916 443 6688",
    "sg:postcode":"95818",
    "sg:province":"CA",
    "sg:tags":[
        "advisory",
        "management"
    ],
    "wof:name":"Tl Investment & Development Inc",
    "wof:placetype":"venue"
},
  "geometry": {"coordinates":[-121.500038,38.56855],"type":"Point"}
}