{
  "type": "Feature",
  "properties": {
    "iso:country":"US",
    "sg:address":"4330 Barranca Pkwy Suite 220",
    "sg:city":"Irvine",
    "sg:classifiers":[
        {
            "category":"Health Services",
            "subcategory":"Dentist",
            "type":"Services"
        }
    ],
    "sg:phone":"+1 949 857 9220",
    "sg:postcode":"92604",
    "sg:province":"CA",
    "wof:name":"Dr Shawn Loo",
    "wof:placetype":"venue"
},
  "geometry": {"coordinates":[-117.804649,33.681155],"type":"Point"}
}