{
  "type": "Feature",
  "properties": {
    "iso:country":"US",
    "sg:address":"3077 Clairemont Dr Ste 103",
    "sg:city":"San Diego",
    "sg:classifiers":[
        {
            "category":"Education",
            "subcategory":"Kindergarten",
            "type":"Public Place"
        }
    ],
    "sg:phone":"+1 619 275 3711",
    "sg:postcode":"92117",
    "sg:province":"CA",
    "sg:tags":[
        "school",
        "driving"
    ],
    "sg:website":"www.goldenstatedrivingschool.com",
    "wof:name":"Golden State Driving School",
    "wof:placetype":"venue"
},
  "geometry": {"coordinates":[-117.193138,32.796519],"type":"Point"}
}