{
  "type": "Feature",
  "properties": {
    "addr:full":"424 Nord Ave Chico CA 95926",
    "addr:housenumber":"424",
    "addr:postcode":"95926",
    "addr:street":"Nord Ave",
    "iso:country":"US",
    "sg:address":"424 Nord Ave",
    "sg:city":"Chico",
    "sg:classifiers":[
        {
            "category":"Shopping",
            "type":"Retail Goods"
        }
    ],
    "sg:phone":"+1 530 891 5555",
    "sg:postcode":"95926",
    "sg:province":"CA",
    "sg:tags":[
        "trophy",
        "medal",
        "award"
    ],
    "wof:name":"Awards Co",
    "wof:placetype":"venue"
},
  "geometry": {"coordinates":[-121.854034,39.727956],"type":"Point"}
}