{
  "type": "Feature",
  "properties": {
    "addr:full":"3303 Harbor Blvd Ste F7 Costa Mesa CA 92626",
    "addr:housenumber":"3303",
    "addr:postcode":"92626",
    "addr:street":"Harbor Blvd Ste F7",
    "iso:country":"US",
    "sg:address":"3303 Harbor Blvd Ste F7",
    "sg:city":"Costa Mesa",
    "sg:classifiers":[
        {
            "category":"Home & Garden",
            "subcategory":"Furniture",
            "type":"Retail Goods"
        }
    ],
    "sg:phone":"+1 714 655 9118",
    "sg:postcode":"92626",
    "sg:province":"CA",
    "sg:tags":[
        "store"
    ],
    "sg:website":"www.wallbedsnmore.com",
    "wof:name":"Wallbeds N More",
    "wof:placetype":"venue"
},
  "geometry": {"coordinates":[-117.921195,33.692638],"type":"Point"}
}