{
  "type": "Feature",
  "properties": {
    "iso:country":"US",
    "sg:address":"3548 Meeker Ave",
    "sg:city":"El Monte",
    "sg:classifiers":[
        {
            "category":"Wholesale",
            "subcategory":"Electrical",
            "type":"Manufacturing & Wholesale Goods"
        }
    ],
    "sg:phone":"+1 626 279 9688",
    "sg:postcode":"91731",
    "sg:province":"CA",
    "sg:tags":[
        "game",
        "video"
    ],
    "wof:name":"Sun Team Technology USA Corp",
    "wof:placetype":"venue"
},
  "geometry": {"coordinates":[-118.02867999999999,34.070677],"type":"Point"}
}