{
  "type": "Feature",
  "properties": {
    "addr:full":"5130 E La Palma Ave Anaheim CA 92807",
    "addr:housenumber":"5130",
    "addr:postcode":"92807",
    "addr:street":"E La Palma Ave",
    "iso:country":"US",
    "sg:address":"5130 E La Palma Ave",
    "sg:city":"Anaheim",
    "sg:classifiers":[
        {
            "category":"Organizations",
            "subcategory":"Religious Organization",
            "type":"Services"
        }
    ],
    "sg:phone":"+1 714 695 0668",
    "sg:postcode":"92807",
    "sg:province":"CA",
    "wof:name":"Breath of the Spirit Internatl Ministries",
    "wof:placetype":"venue"
},
  "geometry": {"coordinates":[-117.804001,33.859501],"type":"Point"}
}