{
  "type": "Feature",
  "properties": {
    "addr:full":"3703 Avocado Blvd La Mesa CA 91941",
    "addr:housenumber":"3703",
    "addr:postcode":"91941",
    "addr:street":"Avocado Blvd",
    "iso:country":"US",
    "sg:address":"3703 Avocado Blvd",
    "sg:city":"La Mesa",
    "sg:classifiers":[
        {
            "category":"Shopping",
            "subcategory":"Jewelry",
            "type":"Retail Goods"
        },
        {
            "category":"Shopping",
            "subcategory":"Used Merchandise",
            "type":"Retail Goods"
        }
    ],
    "sg:phone":"+1 619 660 7787",
    "sg:postcode":"91941",
    "sg:province":"CA",
    "sg:tags":[
        "vintage",
        "consignment"
    ],
    "wof:name":"Rodeo Drive Fashion Resale Boutique",
    "wof:placetype":"venue"
},
  "geometry": {"coordinates":[-116.962997,32.746899],"type":"Point"}
}