{
  "type": "Feature",
  "properties": {
    "addr:full":"2618 Pine Lawn Dr La Crescenta CA 91214",
    "addr:housenumber":"2618",
    "addr:postcode":"91214",
    "addr:street":"Pine Lawn Dr",
    "iso:country":"US",
    "sg:address":"2618 Pine Lawn Dr",
    "sg:city":"La Crescenta",
    "sg:classifiers":[
        {
            "category":"Professional",
            "subcategory":"Computer Services",
            "type":"Services"
        }
    ],
    "sg:phone":"+1 818 957 7000",
    "sg:postcode":"91214",
    "sg:province":"CA",
    "sg:tags":[
        "consultant",
        "designer",
        "datum",
        "system"
    ],
    "sg:website":"www.santikian.com",
    "wof:name":"Loritech LLC",
    "wof:placetype":"venue"
},
  "geometry": {"coordinates":[-118.237098,34.243518],"type":"Point"}
}