{
  "type": "Feature",
  "properties": {
    "iso:country":"US",
    "sg:address":"20 Maldonado Ave",
    "sg:city":"Sonoma",
    "sg:classifiers":[
        {
            "category":"Farming",
            "subcategory":"Vineyard",
            "type":"Manufacturing & Wholesale Goods"
        }
    ],
    "sg:phone":"+1 707 938 1482",
    "sg:postcode":"95476",
    "sg:province":"CA",
    "wof:name":"Berthoud Vineyards & Winery",
    "wof:placetype":"venue"
},
  "geometry": {"coordinates":[-122.47752699999999,38.312273],"type":"Point"}
}