{
  "type": "Feature",
  "properties": {
    "iso:country":"US",
    "sg:address":"331 N Central Ave",
    "sg:city":"Glendale",
    "sg:classifiers":[
        {
            "category":"Home & Garden",
            "subcategory":"Furniture",
            "type":"Retail Goods"
        }
    ],
    "sg:phone":"+1 818 507 6488",
    "sg:postcode":"91203",
    "sg:province":"CA",
    "sg:tags":[
        "store"
    ],
    "wof:name":"Best Buy Furniture",
    "wof:placetype":"venue"
},
  "geometry": {"coordinates":[-118.25808499999999,34.150776],"type":"Point"}
}