{
  "type": "Feature",
  "properties": {
    "iso:country":"US",
    "sg:address":"10726 McCune Ave",
    "sg:city":"Los Angeles",
    "sg:classifiers":[
        {
            "category":"Professional",
            "type":"Services"
        }
    ],
    "sg:phone":"+1 310 397 6478",
    "sg:postcode":"90034",
    "sg:province":"CA",
    "wof:name":"Medi-Coach",
    "wof:placetype":"venue"
},
  "geometry": {"coordinates":[-118.408417,34.019688],"type":"Point"}
}