{
  "type": "Feature",
  "properties": {
    "addr:full":"6151 Power Inn Rd Sacramento CA 95824",
    "addr:housenumber":"6151",
    "addr:postcode":"95824",
    "addr:street":"Power Inn Rd",
    "iso:country":"US",
    "sg:address":"6151 Power Inn Rd",
    "sg:city":"Sacramento",
    "sg:classifiers":[
        {
            "category":"Manufacturing",
            "subcategory":"Retail Goods",
            "type":"Manufacturing & Wholesale Goods"
        }
    ],
    "sg:phone":"+1 916 383 0777",
    "sg:postcode":"95824",
    "sg:province":"CA",
    "sg:tags":[
        "casket"
    ],
    "sg:website":"http://www.pettigrewcaskets.com",
    "wof:name":"Pettigrew & Sons Casket Co",
    "wof:placetype":"venue"
},
  "geometry": {"coordinates":[-121.409074,38.515405],"type":"Point"}
}