{
  "type": "Feature",
  "properties": {
    "addr:full":"21188 Hawthorne Blvd Torrance CA 90503",
    "addr:housenumber":"21188",
    "addr:postcode":"90503",
    "addr:street":"Hawthorne Blvd",
    "iso:country":"US",
    "sg:address":"21188 Hawthorne Blvd",
    "sg:city":"Torrance",
    "sg:classifiers":[
        {
            "category":"Building & Trades",
            "subcategory":"Construction",
            "type":"Services"
        }
    ],
    "sg:phone":"+1 310 371 6591",
    "sg:postcode":"90503",
    "sg:province":"CA",
    "sg:tags":[
        "co",
        "prop"
    ],
    "wof:name":"Jewell Land Co",
    "wof:placetype":"venue"
},
  "geometry": {"coordinates":[-118.35352899999999,33.839314],"type":"Point"}
}