{
  "type": "Feature",
  "properties": {
    "addr:full":"45 Clover Rd Tracy CA 95376",
    "addr:housenumber":"45",
    "addr:postcode":"95376",
    "addr:street":"Clover Rd",
    "iso:country":"US",
    "sg:address":"45 Clover Rd",
    "sg:city":"Tracy",
    "sg:classifiers":[
        {
            "category":"Freight",
            "type":"Transportation"
        }
    ],
    "sg:phone":"+1 209 832 9950",
    "sg:postcode":"95376",
    "sg:province":"CA",
    "sg:tags":[
        "delivery"
    ],
    "wof:name":"Deliver Ease",
    "wof:placetype":"venue"
},
  "geometry": {"coordinates":[-121.426151,37.761487],"type":"Point"}
}