{
  "type": "Feature",
  "properties": {
    "iso:country":"US",
    "sg:address":"1050 W Bush St",
    "sg:city":"Lemoore",
    "sg:classifiers":[
        {
            "category":"Organizations",
            "subcategory":"Religious Organization",
            "type":"Services"
        }
    ],
    "sg:phone":"+1 559 924 3458",
    "sg:postcode":"93245",
    "sg:province":"CA",
    "sg:tags":[
        "church"
    ],
    "sg:website":"www.lemoorebaptist.com",
    "wof:name":"First Baptist Church",
    "wof:placetype":"venue"
},
  "geometry": {"coordinates":[-119.79809899999999,36.298274],"type":"Point"}
}