{
  "type": "Feature",
  "properties": {
    "iso:country":"US",
    "sg:address":"732 N Diamond Bar Blvd",
    "sg:city":"Diamond Bar",
    "sg:classifiers":[
        {
            "category":"Real Estate",
            "subcategory":"Architect",
            "type":"Services"
        }
    ],
    "sg:phone":"+1 909 860 5853",
    "sg:postcode":"91765",
    "sg:province":"CA",
    "wof:name":"Dante Aguilos Architects",
    "wof:placetype":"venue"
},
  "geometry": {"coordinates":[-117.808984,34.031502],"type":"Point"}
}