{
  "type": "Feature",
  "properties": {
    "addr:full":"5741 Buckingham Pkwy Ste E Culver City CA 90230",
    "addr:housenumber":"5741",
    "addr:postcode":"90230",
    "addr:street":"Buckingham Pkwy Ste E",
    "iso:country":"US",
    "sg:address":"5741 Buckingham Pkwy Ste E",
    "sg:city":"Culver City",
    "sg:classifiers":[
        {
            "category":"Museum",
            "type":"Entertainment"
        }
    ],
    "sg:phone":"+1 310 216 1600",
    "sg:postcode":"90230",
    "sg:province":"CA",
    "sg:website":"www.wendemuseum.org/",
    "wof:name":"Wende Museum",
    "wof:placetype":"venue"
},
  "geometry": {"coordinates":[-118.382091,33.990697],"type":"Point"}
}