{
  "type": "Feature",
  "properties": {
    "addr:full":"93 N 14th St San Jose CA 95112",
    "addr:housenumber":"93",
    "addr:postcode":"95112",
    "addr:street":"N 14Th St",
    "iso:country":"US",
    "sg:address":"93 N 14th St",
    "sg:city":"San Jose",
    "sg:classifiers":[
        {
            "category":"Health Services",
            "subcategory":"Doctor",
            "type":"Services"
        },
        {
            "category":"Health Services",
            "subcategory":"Health Practitioner",
            "type":"Services"
        }
    ],
    "sg:phone":"+1 408 294 3922",
    "sg:postcode":"95112",
    "sg:province":"CA",
    "sg:tags":[
        "therapy",
        "physical"
    ],
    "wof:name":"Carr Richard P Physical-Occupational Therapy",
    "wof:placetype":"venue"
},
  "geometry": {"coordinates":[-121.87799800000001,37.343399],"type":"Point"}
}