{
  "type": "Feature",
  "properties": {
    "iso:country":"US",
    "sg:address":"4483 N Cedar Ave",
    "sg:city":"Fresno",
    "sg:classifiers":[
        {
            "category":"Restaurant",
            "type":"Food & Drink"
        }
    ],
    "sg:phone":"+1 559 229 8733",
    "sg:postcode":"93726",
    "sg:province":"CA",
    "wof:name":"Dari-Delite",
    "wof:placetype":"venue"
},
  "geometry": {"coordinates":[-119.754295,36.801214],"type":"Point"}
}