{
  "type": "Feature",
  "properties": {
    "addr:full":"533 Mar Vista Dr Los Osos CA 93402",
    "addr:housenumber":"533",
    "addr:postcode":"93402",
    "addr:street":"Mar Vista Dr",
    "iso:country":"US",
    "sg:address":"533 Mar Vista Dr",
    "sg:city":"Los Osos",
    "sg:classifiers":[
        {
            "category":"Manufacturing",
            "subcategory":"Apparel",
            "type":"Manufacturing & Wholesale Goods"
        }
    ],
    "sg:phone":"+1 805 528 4787",
    "sg:postcode":"93402",
    "sg:province":"CA",
    "wof:name":"Bayside Embroidery",
    "wof:placetype":"venue"
},
  "geometry": {"coordinates":[-120.844955,35.309449],"type":"Point"}
}