{
  "type": "Feature",
  "properties": {
    "iso:country":"US",
    "sg:address":"251 Boeing Ave",
    "sg:city":"Chico",
    "sg:classifiers":[
        {
            "category":"Freight",
            "type":"Transportation"
        }
    ],
    "sg:phone":"+1 530 342 1869",
    "sg:postcode":"95973",
    "sg:province":"CA",
    "sg:tags":[
        "mover"
    ],
    "sg:website":"www.bradysmoving.com",
    "wof:name":"Brady's Moving & Storage Inc",
    "wof:placetype":"venue"
},
  "geometry": {"coordinates":[-121.849633,39.795512],"type":"Point"}
}