{
  "type": "Feature",
  "properties": {
    "iso:country":"US",
    "sg:address":"143 S Main St",
    "sg:city":"Milpitas",
    "sg:classifiers":[
        {
            "category":"Health Services",
            "subcategory":"Health Practitioner",
            "type":"Services"
        }
    ],
    "sg:phone":"+1 408 586 8818",
    "sg:postcode":"95035",
    "sg:province":"CA",
    "sg:tags":[
        "acupuncture",
        "medicine",
        "alternative"
    ],
    "wof:name":"Icare Acupuncture",
    "wof:placetype":"venue"
},
  "geometry": {"coordinates":[-121.906294,37.428568],"type":"Point"}
}