{
  "type": "Feature",
  "properties": {
    "addr:full":"PO Box 53510 San Jose CA 95153",
    "addr:housenumber":"po box 53510",
    "addr:postcode":"95153",
    "iso:country":"US",
    "sg:address":"PO Box 53510",
    "sg:city":"San Jose",
    "sg:classifiers":[
        {
            "category":"Utilities",
            "type":"Services"
        }
    ],
    "sg:phone":"+1 408 881 1000",
    "sg:postcode":"95153",
    "sg:province":"CA",
    "sg:tags":[
        "provider",
        "internet"
    ],
    "wof:name":"Internet Hotline",
    "wof:placetype":"venue"
},
  "geometry": {"coordinates":[-121.847139,37.24892],"type":"Point"}
}