{
  "type": "Feature",
  "properties": {
    "iso:country":"US",
    "sg:address":"1331 W Foothill Blvd",
    "sg:city":"Azusa",
    "sg:classifiers":[
        {
            "category":"Home & Garden",
            "subcategory":"Home Furnishings",
            "type":"Retail Goods"
        },
        {
            "category":"Home & Garden",
            "subcategory":"Building Materials",
            "type":"Retail Goods"
        },
        {
            "category":"Manufacturing",
            "subcategory":"Building Materials",
            "type":"Manufacturing & Wholesale Goods"
        }
    ],
    "sg:phone":"+1 626 815 4973",
    "sg:postcode":"91702",
    "sg:province":"CA",
    "sg:tags":[
        "solid",
        "top",
        "counter",
        "surface",
        "improvement",
        "refacing",
        "resurfacing",
        "cabinets-refinishing",
        "kitchen"
    ],
    "wof:name":"Inland Counter Tops",
    "wof:placetype":"venue"
},
  "geometry": {"coordinates":[-117.926666,34.133701],"type":"Point"}
}