{
  "type": "Feature",
  "properties": {
    "addr:full":"18936 Roscoe Blvd Northridge CA 91324",
    "addr:housenumber":"18936",
    "addr:postcode":"91324",
    "addr:street":"Roscoe Blvd",
    "iso:country":"US",
    "sg:address":"18936 Roscoe Blvd",
    "sg:city":"Northridge",
    "sg:classifiers":[
        {
            "category":"Home & Garden",
            "subcategory":"Garden Supply",
            "type":"Retail Goods"
        }
    ],
    "sg:phone":"+1 818 998 3305",
    "sg:postcode":"91324",
    "sg:province":"CA",
    "sg:tags":[
        "nurseryman"
    ],
    "wof:name":"Westhills Nursery",
    "wof:placetype":"venue"
},
  "geometry": {"coordinates":[-118.549013,34.220457],"type":"Point"}
}