{
  "type": "Feature",
  "properties": {
    "iso:country":"US",
    "sg:address":"9032 Woodman Ave",
    "sg:city":"Arleta",
    "sg:classifiers":[
        {
            "category":"Shopping",
            "subcategory":"Bicycles & Sporting Goods",
            "type":"Retail Goods"
        }
    ],
    "sg:phone":"+1 818 894 8222",
    "sg:postcode":"91331",
    "sg:province":"CA",
    "wof:name":"Rudy's Bike Shop",
    "wof:placetype":"venue"
},
  "geometry": {"coordinates":[-118.439876,34.234589],"type":"Point"}
}