{
  "type": "Feature",
  "properties": {
    "iso:country":"US",
    "sg:address":"1639 E Artesia Blvd",
    "sg:city":"Long Beach",
    "sg:classifiers":[
        {
            "category":"Utilities",
            "subcategory":"Mobile Phone",
            "type":"Services"
        }
    ],
    "sg:phone":"+1 562 728 5674",
    "sg:postcode":"90805",
    "sg:province":"CA",
    "sg:tags":[
        "communication",
        "radiotelephone"
    ],
    "wof:name":"S & V Cellulars",
    "wof:placetype":"venue"
},
  "geometry": {"coordinates":[-118.172288,33.874702],"type":"Point"}
}