{
  "type": "Feature",
  "properties": {
    "addr:full":"3317 Arden Rd Hayward CA 94545",
    "addr:housenumber":"3317",
    "addr:postcode":"94545",
    "addr:street":"Arden Rd",
    "iso:country":"US",
    "sg:address":"3317 Arden Rd",
    "sg:city":"Hayward",
    "sg:classifiers":[
        {
            "category":"Manufacturing",
            "subcategory":"Printing",
            "type":"Manufacturing & Wholesale Goods"
        }
    ],
    "sg:phone":"+1 510 489 3026",
    "sg:postcode":"94545",
    "sg:province":"CA",
    "sg:tags":[
        "newspaper",
        "publishing"
    ],
    "wof:name":"Alameda Newspapers Inc",
    "wof:placetype":"venue"
},
  "geometry": {"coordinates":[-122.11140899999999,37.621346],"type":"Point"}
}