{
  "type": "Feature",
  "properties": {
    "addr:full":"3707 Meadow View Dr Redding CA 96002",
    "addr:housenumber":"3707",
    "addr:postcode":"96002",
    "addr:street":"Meadow View Dr",
    "iso:country":"US",
    "sg:address":"3707 Meadow View Dr",
    "sg:city":"Redding",
    "sg:classifiers":[
        {
            "category":"Manufacturing",
            "subcategory":"Printing",
            "type":"Manufacturing & Wholesale Goods"
        }
    ],
    "sg:phone":"+1 530 365 2788",
    "sg:postcode":"96002",
    "sg:province":"CA",
    "sg:tags":[
        "printer"
    ],
    "wof:name":"Ly Ro Printing",
    "wof:placetype":"venue"
},
  "geometry": {"coordinates":[-122.32009100000001,40.498058],"type":"Point"}
}