{
  "type": "Feature",
  "properties": {
    "addr:full":"135 W 30th St National City CA 91950",
    "addr:housenumber":"135",
    "addr:postcode":"91950",
    "addr:street":"W 30Th St",
    "iso:country":"US",
    "sg:address":"135 W 30th St",
    "sg:city":"National City",
    "sg:classifiers":[
        {
            "category":"Home & Garden",
            "subcategory":"Building Materials",
            "type":"Retail Goods"
        }
    ],
    "sg:phone":"+1 619 477 2393",
    "sg:postcode":"91950",
    "sg:province":"CA",
    "sg:tags":[
        "roofing"
    ],
    "sg:website":"www.abcsupply.com",
    "wof:name":"ABC Supply Co",
    "wof:placetype":"venue"
},
  "geometry": {"coordinates":[-117.102518,32.656342],"type":"Point"}
}