{
  "type": "Feature",
  "properties": {
    "addr:full":"88 W Colorado Blvd Pasadena CA 91105",
    "addr:housenumber":"88",
    "addr:postcode":"91105",
    "addr:street":"W Colorado Blvd",
    "iso:country":"US",
    "sg:address":"88 W Colorado Blvd",
    "sg:city":"Pasadena",
    "sg:classifiers":[
        {
            "category":"Restaurant",
            "type":"Food & Drink"
        }
    ],
    "sg:phone":"+1 626 844 8889",
    "sg:postcode":"91105",
    "sg:province":"CA",
    "wof:name":"J J Steak House",
    "wof:placetype":"venue"
},
  "geometry": {"coordinates":[-118.15141,34.145766],"type":"Point"}
}