{
  "type": "Feature",
  "properties": {
    "addr:full":"12201 Sheridan Ln Garden Grove CA 92840",
    "addr:housenumber":"12201",
    "addr:postcode":"92840",
    "addr:street":"Sheridan Ln",
    "iso:country":"US",
    "sg:address":"12201 Sheridan Ln",
    "sg:city":"Garden Grove",
    "sg:classifiers":[
        {
            "category":"Wholesale",
            "subcategory":"Medical Equipment & Supplies",
            "type":"Manufacturing & Wholesale Goods"
        }
    ],
    "sg:phone":"+1 714 530 0767",
    "sg:postcode":"92840",
    "sg:province":"CA",
    "sg:tags":[
        "hospital"
    ],
    "wof:name":"Frank Barker Associates Inc",
    "wof:placetype":"venue"
},
  "geometry": {"coordinates":[-117.95619499999999,33.787608],"type":"Point"}
}