{
  "type": "Feature",
  "properties": {
    "iso:country":"US",
    "sg:address":"1414 Everett St",
    "sg:city":"Alameda",
    "sg:classifiers":[
        {
            "category":"Personal",
            "subcategory":"Hair Removal",
            "type":"Services"
        }
    ],
    "sg:phone":"+1 510 865 0900",
    "sg:postcode":"94501",
    "sg:province":"CA",
    "sg:website":"www.hair-be-gone.com",
    "wof:name":"Susan Parks, Registered Electrologist",
    "wof:placetype":"venue"
},
  "geometry": {"coordinates":[-122.240274,37.763752],"type":"Point"}
}