{
  "type": "Feature",
  "properties": {
    "addr:full":"1244 Santa Anita Ave South El Monte CA 91733",
    "addr:housenumber":"1244",
    "addr:postcode":"91733",
    "addr:street":"Santa Anita Ave",
    "iso:country":"US",
    "sg:address":"1244 Santa Anita Ave",
    "sg:city":"South El Monte",
    "sg:classifiers":[
        {
            "category":"Wholesale",
            "subcategory":"Durable Goods & Equipment",
            "type":"Manufacturing & Wholesale Goods"
        }
    ],
    "sg:phone":"+1 626 443 4488",
    "sg:postcode":"91733",
    "sg:province":"CA",
    "sg:tags":[
        "importer"
    ],
    "wof:name":"Far Away Landscaping Intl Inc",
    "wof:placetype":"venue"
},
  "geometry": {"coordinates":[-118.04652900000001,34.043603],"type":"Point"}
}