{
  "type": "Feature",
  "properties": {
    "addr:full":"13382 Goldenwest St Westminster CA 92683",
    "addr:housenumber":"13382",
    "addr:postcode":"92683",
    "addr:street":"Goldenwest St",
    "iso:country":"US",
    "sg:address":"13382 Goldenwest St",
    "sg:city":"Westminster",
    "sg:classifiers":[
        {
            "category":"Wholesale",
            "subcategory":"Electrical",
            "type":"Manufacturing & Wholesale Goods"
        }
    ],
    "sg:phone":"+1 714 776 2611",
    "sg:postcode":"92683",
    "sg:province":"CA",
    "sg:tags":[
        "alarm",
        "burglar",
        "system"
    ],
    "wof:name":"ASA Alarm Systems Inc",
    "wof:placetype":"venue"
},
  "geometry": {"coordinates":[-118.00729,33.76818],"type":"Point"}
}