{
  "type": "Feature",
  "properties": {
    "addr:full":"1206 W Malboro Ave Anaheim CA 92801",
    "addr:housenumber":"1206",
    "addr:postcode":"92801",
    "addr:street":"W Malboro Ave",
    "iso:country":"US",
    "sg:address":"1206 W Malboro Ave",
    "sg:city":"Anaheim",
    "sg:classifiers":[
        {
            "category":"Freight",
            "type":"Transportation"
        }
    ],
    "sg:phone":"+1 714 635 7630",
    "sg:postcode":"92801",
    "sg:province":"CA",
    "sg:tags":[
        "operator",
        "local",
        "trucking"
    ],
    "wof:name":"Primero Trucking",
    "wof:placetype":"venue"
},
  "geometry": {"coordinates":[-117.937291,33.851329],"type":"Point"}
}