{
  "type": "Feature",
  "properties": {
    "addr:full":"2352 Highgate Rd Westlake Village CA 91361",
    "addr:housenumber":"2352",
    "addr:postcode":"91361",
    "addr:street":"Highgate Rd",
    "iso:country":"US",
    "sg:address":"2352 Highgate Rd",
    "sg:city":"Westlake Village",
    "sg:classifiers":[
        {
            "category":"Professional",
            "subcategory":"Management & Consulting",
            "type":"Services"
        }
    ],
    "sg:phone":"+1 805 494 0076",
    "sg:postcode":"91361",
    "sg:province":"CA",
    "sg:tags":[
        "scaffolding"
    ],
    "wof:name":"Janson & Company",
    "wof:placetype":"venue"
},
  "geometry": {"coordinates":[-118.834639,34.141681],"type":"Point"}
}