{
  "type": "Feature",
  "properties": {
    "addr:full":"4061 Greenwood Rd South Lake Tahoe CA 96150",
    "addr:housenumber":"4061",
    "addr:postcode":"96150",
    "addr:street":"Greenwood Rd",
    "iso:country":"US",
    "sg:address":"4061 Greenwood Rd",
    "sg:city":"South Lake Tahoe",
    "sg:classifiers":[
        {
            "category":"Building & Trades",
            "subcategory":"Construction",
            "type":"Services"
        }
    ],
    "sg:phone":"+1 530 544 2494",
    "sg:postcode":"96150",
    "sg:province":"CA",
    "sg:tags":[
        "paving",
        "contractor"
    ],
    "wof:name":"Olsen Paving & Sealcoating",
    "wof:placetype":"venue"
},
  "geometry": {"coordinates":[-119.949056,38.958889],"type":"Point"}
}