{
  "type": "Feature",
  "properties": {
    "addr:full":"5114 Commerce Dr Baldwin Park CA 91706",
    "addr:housenumber":"5114",
    "addr:postcode":"91706",
    "addr:street":"Commerce Dr",
    "iso:country":"US",
    "sg:address":"5114 Commerce Dr",
    "sg:city":"Baldwin Park",
    "sg:classifiers":[
        {
            "category":"Communications",
            "subcategory":"Film & Video Production",
            "type":"Services"
        }
    ],
    "sg:phone":"+1 626 813 0050",
    "sg:postcode":"91706",
    "sg:province":"CA",
    "sg:tags":[
        "audio"
    ],
    "wof:name":"Magic Film Co",
    "wof:placetype":"venue"
},
  "geometry": {"coordinates":[-117.97721199999999,34.102115],"type":"Point"}
}