{
  "type": "Feature",
  "properties": {
    "iso:country":"US",
    "sg:address":"485 Oak St",
    "sg:city":"San Francisco",
    "sg:classifiers":[
        {
            "category":"Professional",
            "subcategory":"Advertising",
            "type":"Services"
        }
    ],
    "sg:phone":"+1 415 255 8440",
    "sg:postcode":"94102",
    "sg:province":"CA",
    "sg:tags":[
        "counselor"
    ],
    "wof:name":"Creation",
    "wof:placetype":"venue"
},
  "geometry": {"coordinates":[-122.426411,37.774494],"type":"Point"}
}