{
  "type": "Feature",
  "properties": {
    "addr:full":"75135 Sheryl Ave Palm Desert CA 92211",
    "addr:postcode":"75135;ca 92211",
    "addr:street":"Sheryl Ave",
    "iso:country":"US",
    "sg:address":"75135 Sheryl Ave",
    "sg:city":"Palm Desert",
    "sg:classifiers":[
        {
            "category":"Building & Trades",
            "subcategory":"Construction",
            "type":"Services"
        }
    ],
    "sg:phone":"+1 760 340 1291",
    "sg:postcode":"92211",
    "sg:province":"CA",
    "sg:tags":[
        "planning",
        "remodeling",
        "kitchen"
    ],
    "wof:name":"Inspirations",
    "wof:placetype":"venue"
},
  "geometry": {"coordinates":[-116.35425499999999,33.737653],"type":"Point"}
}