{
  "type": "Feature",
  "properties": {
    "iso:country":"US",
    "sg:address":"1723 Mission St",
    "sg:city":"Santa Cruz",
    "sg:classifiers":[
        {
            "category":"Coffee & Tea",
            "type":"Food & Drink"
        }
    ],
    "sg:phone":"+1 831 425 6583",
    "sg:postcode":"95060",
    "sg:province":"CA",
    "wof:name":"Coffeetopia Inc",
    "wof:placetype":"venue"
},
  "geometry": {"coordinates":[-122.041,36.965099],"type":"Point"}
}