{
  "type": "Feature",
  "properties": {
    "addr:full":"6018 Gregory Ave Whittier CA 90601",
    "addr:housenumber":"6018",
    "addr:postcode":"90601",
    "addr:street":"Gregory Ave",
    "iso:country":"US",
    "sg:address":"6018 Gregory Ave",
    "sg:city":"Whittier",
    "sg:classifiers":[
        {
            "category":"Shopping",
            "type":"Retail Goods"
        }
    ],
    "sg:phone":"+1 562 699 0071",
    "sg:postcode":"90601",
    "sg:province":"CA",
    "sg:tags":[
        "merchandise"
    ],
    "wof:name":"Dm",
    "wof:placetype":"venue"
},
  "geometry": {"coordinates":[-118.04699100000001,33.98745],"type":"Point"}
}