{
  "type": "Feature",
  "properties": {
    "iso:country":"US",
    "sg:address":"26096 Getty Dr",
    "sg:city":"Laguna Niguel",
    "sg:classifiers":[
        {
            "category":"Wholesale",
            "subcategory":"Hardware",
            "type":"Manufacturing & Wholesale Goods"
        }
    ],
    "sg:phone":"+1 949 348 0506",
    "sg:postcode":"92677",
    "sg:province":"CA",
    "wof:name":"Crest Hardware",
    "wof:placetype":"venue"
},
  "geometry": {"coordinates":[-117.676414,33.560744],"type":"Point"}
}