{
  "type": "Feature",
  "properties": {
    "iso:country":"US",
    "sg:address":"4200 California St",
    "sg:city":"San Francisco",
    "sg:classifiers":[
        {
            "category":"Health Services",
            "subcategory":"Chiropractor",
            "type":"Services"
        }
    ],
    "sg:phone":"+1 415 668 2863",
    "sg:postcode":"94118",
    "sg:province":"CA",
    "wof:name":"Chiropractor Health Ctr",
    "wof:placetype":"venue"
},
  "geometry": {"coordinates":[-122.463503,37.785131],"type":"Point"}
}