{
  "type": "Feature",
  "properties": {
    "addr:full":"224 Vernon St Roseville CA 95678",
    "addr:housenumber":"224",
    "addr:postcode":"95678",
    "addr:street":"Vernon St",
    "iso:country":"US",
    "sg:address":"224 Vernon St",
    "sg:city":"Roseville",
    "sg:classifiers":[
        {
            "category":"Banks & Credit Unions",
            "subcategory":"Investment Brokerage",
            "type":"Services"
        }
    ],
    "sg:phone":"+1 916 774 4243",
    "sg:postcode":"95678",
    "sg:province":"CA",
    "sg:tags":[
        "advisory",
        "financial"
    ],
    "wof:name":"American Financial Solutions",
    "wof:placetype":"venue"
},
  "geometry": {"coordinates":[-121.28384699999999,38.749227],"type":"Point"}
}