{
  "type": "Feature",
  "properties": {
    "addr:full":"8643 Hollywood Blvd West Hollywood CA 90069",
    "addr:housenumber":"8643",
    "addr:postcode":"90069",
    "addr:street":"Hollywood Blvd",
    "iso:country":"US",
    "sg:address":"8643 Hollywood Blvd",
    "sg:city":"West Hollywood",
    "sg:classifiers":[
        {
            "category":"Health Services",
            "subcategory":"Health Practitioner",
            "type":"Services"
        }
    ],
    "sg:phone":"+1 310 657 1830",
    "sg:postcode":"90069",
    "sg:province":"CA",
    "sg:tags":[
        "psychotherapist"
    ],
    "wof:name":"William O Erwin",
    "wof:placetype":"venue"
},
  "geometry": {"coordinates":[-118.37808699999999,34.097505],"type":"Point"}
}