{
  "type": "Feature",
  "properties": {
    "addr:full":"7 Thomas Dr Mill Valley CA 94941",
    "addr:housenumber":"7",
    "addr:postcode":"94941",
    "addr:street":"Thomas Dr",
    "iso:country":"US",
    "sg:address":"7 Thomas Dr",
    "sg:city":"Mill Valley",
    "sg:classifiers":[
        {
            "category":"Education",
            "subcategory":"School",
            "type":"Public Place"
        }
    ],
    "sg:phone":"+1 415 383 5777",
    "sg:postcode":"94941",
    "sg:province":"CA",
    "wof:name":"Montessori School-Mill Valley",
    "wof:placetype":"venue"
},
  "geometry": {"coordinates":[-122.51366899999999,37.906323],"type":"Point"}
}