{
  "type": "Feature",
  "properties": {
    "iso:country":"US",
    "sg:address":"1348 Green Ct",
    "sg:city":"Seaside",
    "sg:classifiers":[
        {
            "category":"Health Services",
            "subcategory":"Clinic",
            "type":"Services"
        }
    ],
    "sg:phone":"+1 831 899 4019",
    "sg:postcode":"93955",
    "sg:province":"CA",
    "sg:tags":[
        "medical",
        "examination"
    ],
    "wof:name":"Portamedic",
    "wof:placetype":"venue"
},
  "geometry": {"coordinates":[-121.83761699999999,36.600607],"type":"Point"}
}