{
  "type": "Feature",
  "properties": {
    "iso:country":"US",
    "sg:address":"2295 Honolulu Ave",
    "sg:city":"Montrose",
    "sg:classifiers":[
        {
            "category":"Shopping",
            "subcategory":"Clothing, Apparel, & Fashions",
            "type":"Retail Goods"
        }
    ],
    "sg:phone":"+1 818 249 3951",
    "sg:postcode":"91020",
    "sg:province":"CA",
    "sg:tags":[
        "lingerie"
    ],
    "wof:name":"Faye's Intimate Apparel",
    "wof:placetype":"venue"
},
  "geometry": {"coordinates":[-118.227997,34.205399],"type":"Point"}
}