{
  "type": "Feature",
  "properties": {
    "iso:country":"US",
    "sg:address":"1791 Erringer Rd",
    "sg:city":"Simi Valley",
    "sg:classifiers":[
        {
            "category":"Professional",
            "subcategory":"Lawyer & Legal Services",
            "type":"Services"
        }
    ],
    "sg:phone":"+1 805 583 5400",
    "sg:postcode":"93065",
    "sg:province":"CA",
    "sg:tags":[
        "attorney"
    ],
    "sg:website":"www.similaw.com",
    "wof:name":"Huber & Takasugi Law Offices",
    "wof:placetype":"venue"
},
  "geometry": {"coordinates":[-118.761436,34.269026],"type":"Point"}
}