{
  "type": "Feature",
  "properties": {
    "addr:full":"1150 Dell Ave Campbell CA 95008",
    "addr:housenumber":"1150",
    "addr:postcode":"95008",
    "addr:street":"Dell Ave",
    "iso:country":"US",
    "sg:address":"1150 Dell Ave",
    "sg:city":"Campbell",
    "sg:classifiers":[
        {
            "category":"Manufacturing",
            "subcategory":"Tools & Machinery",
            "type":"Manufacturing & Wholesale Goods"
        }
    ],
    "sg:phone":"+1 408 379 6550",
    "sg:postcode":"95008",
    "sg:province":"CA",
    "sg:tags":[
        "machine",
        "shop"
    ],
    "sg:website":"www.champcompany.com",
    "wof:name":"Champ Co",
    "wof:placetype":"venue"
},
  "geometry": {"coordinates":[-121.953394,37.267891],"type":"Point"}
}