{
  "type": "Feature",
  "properties": {
    "iso:country":"US",
    "sg:address":"576 E el Camino Real",
    "sg:city":"Sunnyvale",
    "sg:classifiers":[
        {
            "category":"Retail",
            "subcategory":"Photofinishing",
            "type":"Services"
        }
    ],
    "sg:phone":"+1 408 739 4672",
    "sg:postcode":"94087",
    "sg:province":"CA",
    "sg:tags":[
        "photo",
        "finishing"
    ],
    "wof:name":"Longs Drug",
    "wof:placetype":"venue"
},
  "geometry": {"coordinates":[-122.026517,37.363052],"type":"Point"}
}