{
  "type": "Feature",
  "properties": {
    "addr:full":"1103 Airport Blvd Burlingame CA 94010",
    "addr:housenumber":"1103",
    "addr:postcode":"94010",
    "addr:street":"Airport Blvd",
    "iso:country":"US",
    "sg:address":"1103 Airport Blvd",
    "sg:city":"Burlingame",
    "sg:classifiers":[
        {
            "category":"Professional",
            "subcategory":"Engineering",
            "type":"Services"
        },
        {
            "category":"Utilities",
            "subcategory":"Water",
            "type":"Services"
        }
    ],
    "sg:phone":"+1 650 342 3727",
    "sg:postcode":"94010",
    "sg:province":"CA",
    "sg:tags":[
        "supply",
        "engineer"
    ],
    "wof:name":"Veolia Water North America Ope",
    "wof:placetype":"venue"
},
  "geometry": {"coordinates":[-122.358574,37.591807],"type":"Point"}
}