{
  "type": "Feature",
  "properties": {
    "iso:country":"US",
    "sg:address":"1439 W Beverly Blvd",
    "sg:city":"Montebello",
    "sg:classifiers":[
        {
            "category":"Banks & Credit Unions",
            "subcategory":"Financial Services",
            "type":"Services"
        }
    ],
    "sg:phone":"+1 323 869 9611",
    "sg:postcode":"90640",
    "sg:province":"CA",
    "sg:tags":[
        "broker",
        "mortgage"
    ],
    "wof:name":"Fast Track Funding",
    "wof:placetype":"venue"
},
  "geometry": {"coordinates":[-118.113998,34.0187],"type":"Point"}
}