{
  "type": "Feature",
  "properties": {
    "addr:full":"18972 Beach Blvd Huntington Beach CA 92648",
    "addr:housenumber":"18972",
    "addr:postcode":"92648",
    "addr:street":"Beach Blvd",
    "iso:country":"US",
    "sg:address":"18972 Beach Blvd",
    "sg:city":"Huntington Beach",
    "sg:classifiers":[
        {
            "category":"Autos & Motor Vehicles",
            "subcategory":"Fuel & Gas Station",
            "type":"Retail Goods"
        }
    ],
    "sg:phone":"+1 714 593 8516",
    "sg:postcode":"92648",
    "sg:province":"CA",
    "sg:website":"www.ampm.com",
    "wof:name":"Sharda AMPM",
    "wof:placetype":"venue"
},
  "geometry": {"coordinates":[-117.98846899999999,33.68708],"type":"Point"}
}