{
  "type": "Feature",
  "properties": {
    "iso:country":"US",
    "sg:address":"875 39th Ave",
    "sg:city":"San Francisco",
    "sg:classifiers":[
        {
            "category":"Professional",
            "type":"Services"
        }
    ],
    "sg:phone":"+1 415 749 1978",
    "sg:postcode":"94121",
    "sg:province":"CA",
    "wof:name":"Venus Superstar",
    "wof:placetype":"venue"
},
  "geometry": {"coordinates":[-122.49933900000001,37.77329],"type":"Point"}
}