{
  "type": "Feature",
  "properties": {
    "iso:country":"US",
    "sg:address":"14610 Hawthorne Blvd",
    "sg:city":"Lawndale",
    "sg:classifiers":[
        {
            "category":"Health Services",
            "subcategory":"Dentist",
            "type":"Services"
        }
    ],
    "sg:phone":"+1 310 676 4746",
    "sg:postcode":"90260",
    "sg:province":"CA",
    "wof:name":"Smolkin Darin DDS MS",
    "wof:placetype":"venue"
},
  "geometry": {"coordinates":[-118.352215,33.899099],"type":"Point"}
}