{
  "type": "Feature",
  "properties": {
    "addr:full":"5335 Paseo Del Norte Carlsbad CA 92008",
    "addr:housenumber":"5335",
    "addr:postcode":"92008",
    "addr:street":"Paseo Del Norte",
    "iso:country":"US",
    "sg:address":"5335 Paseo Del Norte",
    "sg:city":"Carlsbad",
    "sg:classifiers":[
        {
            "category":"Autos & Motor Vehicles",
            "subcategory":"Automobile Sales",
            "type":"Retail Goods"
        }
    ],
    "sg:phone":"+1 760 438 1066",
    "sg:postcode":"92008",
    "sg:province":"CA",
    "sg:tags":[
        "car"
    ],
    "wof:name":"Weseloh Chevrolet",
    "wof:placetype":"venue"
},
  "geometry": {"coordinates":[-117.325996,33.132801],"type":"Point"}
}