{
  "type": "Feature",
  "properties": {
    "iso:country":"US",
    "sg:address":"17100 Gillette Ave",
    "sg:city":"Irvine",
    "sg:classifiers":[
        {
            "category":"Shopping",
            "subcategory":"Computers & Home Electronics",
            "type":"Retail Goods"
        }
    ],
    "sg:phone":"+1 949 263 8484",
    "sg:postcode":"92614",
    "sg:province":"CA",
    "sg:tags":[
        "software"
    ],
    "wof:name":"Enterprise Solutions & Tech",
    "wof:placetype":"venue"
},
  "geometry": {"coordinates":[-117.848445,33.697584],"type":"Point"}
}