{
  "type": "Feature",
  "properties": {
    "addr:full":"4727 Artesia Blvd Ste 103 Lawndale CA 90260",
    "addr:housenumber":"4727",
    "addr:postcode":"ca 90260",
    "addr:street":"Artesia Blvd Ste 103",
    "iso:country":"US",
    "sg:address":"4727 Artesia Blvd Ste 103",
    "sg:city":"Lawndale",
    "sg:classifiers":[
        {
            "category":"Insurance",
            "subcategory":"Hazard Insurance",
            "type":"Services"
        }
    ],
    "sg:phone":"+1 424 247 7114",
    "sg:postcode":"90260",
    "sg:province":"CA",
    "wof:name":"State Farm Insurance",
    "wof:placetype":"venue"
},
  "geometry": {"coordinates":[-118.360142,33.873152],"type":"Point"}
}