{
  "type": "Feature",
  "properties": {
    "iso:country":"US",
    "sg:address":"4125 S Figueroa St",
    "sg:city":"Los Angeles",
    "sg:classifiers":[
        {
            "category":"Autos & Motor Vehicles",
            "subcategory":"Automobile Sales",
            "type":"Retail Goods"
        }
    ],
    "sg:phone":"+1 213 413 4949",
    "sg:postcode":"90037",
    "sg:province":"CA",
    "sg:tags":[
        "car",
        "dealer"
    ],
    "wof:name":"S M Auto Sales",
    "wof:placetype":"venue"
},
  "geometry": {"coordinates":[-118.282799,34.009117],"type":"Point"}
}