{
  "type": "Feature",
  "properties": {
    "iso:country":"US",
    "sg:address":"908 Park Row",
    "sg:city":"Salinas",
    "sg:classifiers":[
        {
            "category":"Professional",
            "type":"Services"
        }
    ],
    "sg:phone":"+1 831 422 3693",
    "sg:postcode":"93901",
    "sg:province":"CA",
    "wof:name":"Petra Bianchi Macfarlane",
    "wof:placetype":"venue"
},
  "geometry": {"coordinates":[-121.659316,36.663965],"type":"Point"}
}