{
  "type": "Feature",
  "properties": {
    "addr:full":"458 W Arrow Hwy Covina CA 91722",
    "addr:housenumber":"458",
    "addr:postcode":"91722",
    "addr:street":"W Arrow Hwy",
    "iso:country":"US",
    "sg:address":"458 W Arrow Hwy",
    "sg:city":"Covina",
    "sg:classifiers":[
        {
            "category":"Restaurant",
            "type":"Food & Drink"
        }
    ],
    "sg:phone":"+1 626 967 5847",
    "sg:postcode":"91722",
    "sg:province":"CA",
    "wof:name":"Lotus Garden Restaurant",
    "wof:placetype":"venue"
},
  "geometry": {"coordinates":[-117.90094000000001,34.106689],"type":"Point"}
}