{
  "type": "Feature",
  "properties": {
    "iso:country":"US",
    "sg:address":"1315 O St",
    "sg:city":"Firebaugh",
    "sg:classifiers":[
        {
            "category":"Education",
            "subcategory":"Library",
            "type":"Public Place"
        }
    ],
    "sg:phone":"+1 559 659 2820",
    "sg:postcode":"93622",
    "sg:province":"CA",
    "wof:name":"Firebaugh Branch Library",
    "wof:placetype":"venue"
},
  "geometry": {"coordinates":[-120.45414100000001,36.856777],"type":"Point"}
}