{
  "type": "Feature",
  "properties": {
    "iso:country":"US",
    "sg:address":"1625 The Alameda",
    "sg:city":"San Jose",
    "sg:classifiers":[
        {
            "category":"Professional",
            "subcategory":"Lawyer & Legal Services",
            "type":"Services"
        }
    ],
    "sg:phone":"+1 408 271 1917",
    "sg:postcode":"95126",
    "sg:province":"CA",
    "sg:tags":[
        "attorney"
    ],
    "wof:name":"Brian E Hawes Law Offices",
    "wof:placetype":"venue"
},
  "geometry": {"coordinates":[-121.917016,37.33553],"type":"Point"}
}