{
  "type": "Feature",
  "properties": {
    "iso:country":"US",
    "sg:address":"20817 S Western Ave",
    "sg:city":"Torrance",
    "sg:classifiers":[
        {
            "category":"Manufacturing",
            "subcategory":"Printing",
            "type":"Manufacturing & Wholesale Goods"
        }
    ],
    "sg:phone":"+1 310 222 8639",
    "sg:postcode":"90501",
    "sg:province":"CA",
    "sg:tags":[
        "printer"
    ],
    "wof:name":"Japan Graphics",
    "wof:placetype":"venue"
},
  "geometry": {"coordinates":[-118.309314,33.841005],"type":"Point"}
}