{
  "type": "Feature",
  "properties": {
    "iso:country":"US",
    "sg:address":"592 Carlsbad Village Dr",
    "sg:city":"Carlsbad",
    "sg:classifiers":[
        {
            "category":"Insurance",
            "subcategory":"Insurance Agent",
            "type":"Services"
        }
    ],
    "sg:phone":"+1 760 720 9588",
    "sg:postcode":"92008",
    "sg:province":"CA",
    "wof:name":"Ncpa Insurance Svc",
    "wof:placetype":"venue"
},
  "geometry": {"coordinates":[-117.348709,33.15964],"type":"Point"}
}