{
  "type": "Feature",
  "properties": {
    "addr:full":"170 S Spring St Blythe CA 92225",
    "addr:housenumber":"170",
    "addr:postcode":"92225",
    "addr:street":"S Spring St",
    "iso:country":"US",
    "sg:address":"170 S Spring St",
    "sg:city":"Blythe",
    "sg:classifiers":[
        {
            "category":"Real Estate",
            "subcategory":"Real Estate Services",
            "type":"Services"
        },
        {
            "category":"Real Estate",
            "subcategory":"Real Estate Operator",
            "type":"Services"
        }
    ],
    "sg:phone":"+1 760 922 2131",
    "sg:postcode":"92225",
    "sg:province":"CA",
    "sg:tags":[
        "vacancy",
        "apartment",
        "rental",
        "finder",
        "listing"
    ],
    "wof:name":"El Solano Motor Inn",
    "wof:placetype":"venue"
},
  "geometry": {"coordinates":[-114.598167,33.608984],"type":"Point"}
}