{
  "type": "Feature",
  "properties": {
    "iso:country":"US",
    "sg:address":"725 E Broadway",
    "sg:city":"Glendale",
    "sg:classifiers":[
        {
            "category":"Arena",
            "subcategory":"Sports Club",
            "type":"Entertainment"
        }
    ],
    "sg:phone":"+1 818 242 3684",
    "sg:postcode":"91205",
    "sg:province":"CA",
    "sg:tags":[
        "martial art"
    ],
    "wof:name":"Bejanian Brothers'world Class Training Center",
    "wof:placetype":"venue"
},
  "geometry": {"coordinates":[-118.246002,34.1464],"type":"Point"}
}