{
  "type": "Feature",
  "properties": {
    "addr:full":"5252 Balboa Avenue San Diego CA 92117",
    "addr:housenumber":"5252",
    "addr:postcode":"92117",
    "addr:street":"Balboa Avenue",
    "iso:country":"US",
    "sg:address":"5252 Balboa Avenue",
    "sg:city":"San Diego",
    "sg:classifiers":[
        {
            "category":"Professional",
            "subcategory":"Lawyer & Legal Services",
            "type":"Services"
        },
        {
            "category":"Banks & Credit Unions",
            "subcategory":"Atm",
            "type":"Services"
        }
    ],
    "sg:phone":"+1 858 278 3880",
    "sg:postcode":"92117",
    "sg:province":"CA",
    "sg:tags":[
        "personal",
        "injury",
        "bankruptcy"
    ],
    "sg:website":"www.styerslaw.com",
    "wof:name":"Styers Jeffery S Attorney",
    "wof:placetype":"venue"
},
  "geometry": {"coordinates":[-117.183252,32.818907],"type":"Point"}
}