{
  "type": "Feature",
  "properties": {
    "addr:full":"13422 Alondra Blvd Cerritos CA 90703",
    "addr:housenumber":"13422",
    "addr:postcode":"ca 90703",
    "addr:street":"Alondra Blvd",
    "iso:country":"US",
    "sg:address":"13422 Alondra Blvd",
    "sg:city":"Cerritos",
    "sg:classifiers":[
        {
            "category":"Professional",
            "subcategory":"Management & Consulting",
            "type":"Services"
        }
    ],
    "sg:phone":"+1 626 215 9296",
    "sg:postcode":"90703",
    "sg:province":"CA",
    "sg:tags":[
        "consultant",
        "business"
    ],
    "wof:name":"Ultraspec",
    "wof:placetype":"venue"
},
  "geometry": {"coordinates":[-118.045464,33.887787],"type":"Point"}
}