{
  "type": "Feature",
  "properties": {
    "addr:full":"201 5th St Hollister CA 95023",
    "addr:housenumber":"201",
    "addr:postcode":"hollister ca 95023",
    "addr:street":"5Th St",
    "iso:country":"US",
    "sg:address":"201 5th St",
    "sg:city":"Hollister",
    "sg:classifiers":[
        {
            "category":"Bars & Pubs",
            "type":"Food & Drink"
        }
    ],
    "sg:phone":"+1 831 637 7188",
    "sg:postcode":"95023",
    "sg:province":"CA",
    "sg:tags":[
        "lounge",
        "cocktail"
    ],
    "wof:name":"Whiskey Creek Saloon",
    "wof:placetype":"venue"
},
  "geometry": {"coordinates":[-121.402051,36.851467],"type":"Point"}
}