{
  "type": "Feature",
  "properties": {
    "iso:country":"US",
    "sg:address":"838 W 19th St",
    "sg:city":"Merced",
    "sg:classifiers":[
        {
            "category":"Building & Trades",
            "subcategory":"Pest Control",
            "type":"Services"
        }
    ],
    "sg:phone":"+1 209 381 0917",
    "sg:postcode":"95340",
    "sg:province":"CA",
    "wof:name":"Agri-Tech Consulting",
    "wof:placetype":"venue"
},
  "geometry": {"coordinates":[-120.48781700000001,37.30536],"type":"Point"}
}