{
  "type": "Feature",
  "properties": {
    "addr:full":"2332 5th St Berkeley CA 94710",
    "addr:housenumber":"2332",
    "addr:postcode":"94710",
    "addr:street":"5Th St",
    "iso:country":"US",
    "sg:address":"2332 5th St",
    "sg:city":"Berkeley",
    "sg:classifiers":[
        {
            "category":"Real Estate",
            "subcategory":"Real Estate Agent",
            "type":"Services"
        }
    ],
    "sg:phone":"+1 510 527 3400",
    "sg:postcode":"94710",
    "sg:province":"CA",
    "sg:website":"http://www.norheimyost.com",
    "wof:name":"Norheim & Yost",
    "wof:placetype":"venue"
},
  "geometry": {"coordinates":[-122.297189,37.862696],"type":"Point"}
}