{
  "type": "Feature",
  "properties": {
    "iso:country":"US",
    "sg:address":"1760 Creekside Oaks Dr #280",
    "sg:city":"Sacramento",
    "sg:classifiers":[
        {
            "category":"Professional",
            "subcategory":"Engineering",
            "type":"Services"
        }
    ],
    "sg:phone":"+1 916 920 2020",
    "sg:postcode":"95833",
    "sg:province":"CA",
    "sg:tags":[
        "civil",
        "consulting",
        "engineer",
        "structural"
    ],
    "sg:website":"http://www.cyseng.com",
    "wof:name":"CYS Structural Engineers Inc",
    "wof:placetype":"venue"
},
  "geometry": {"coordinates":[-121.500973,38.609202],"type":"Point"}
}