{
  "type": "Feature",
  "properties": {
    "iso:country":"US",
    "sg:address":"14532 Friar St",
    "sg:city":"Van Nuys",
    "sg:classifiers":[
        {
            "category":"Wholesale",
            "subcategory":"Non-durable Goods",
            "type":"Manufacturing & Wholesale Goods"
        }
    ],
    "sg:phone":"+1 818 285 2511",
    "sg:postcode":"91411",
    "sg:province":"CA",
    "wof:name":"Lotusmood Music",
    "wof:placetype":"venue"
},
  "geometry": {"coordinates":[-118.450307,34.185595],"type":"Point"}
}