{
  "type": "Feature",
  "properties": {
    "iso:country":"US",
    "sg:address":"11563 Willowood Ct",
    "sg:city":"Moorpark",
    "sg:classifiers":[
        {
            "category":"Autos & Motor Vehicles",
            "subcategory":"Auto Supplies",
            "type":"Retail Goods"
        },
        {
            "category":"Manufacturing",
            "subcategory":"Petroleum Products",
            "type":"Manufacturing & Wholesale Goods"
        }
    ],
    "sg:phone":"+1 805 529 6560",
    "sg:postcode":"93021",
    "sg:province":"CA",
    "sg:tags":[
        "lubricating",
        "oil",
        "lubricant"
    ],
    "wof:name":"Pch Enterprises",
    "wof:placetype":"venue"
},
  "geometry": {"coordinates":[-118.90618000000001,34.275711],"type":"Point"}
}