{
  "type": "Feature",
  "properties": {
    "addr:full":"1150 Bryson Ave Simi Valley CA 93065",
    "addr:housenumber":"1150",
    "addr:postcode":"93065",
    "addr:street":"Bryson Ave",
    "iso:country":"US",
    "sg:address":"1150 Bryson Ave",
    "sg:city":"Simi Valley",
    "sg:classifiers":[
        {
            "category":"Professional",
            "subcategory":"Management & Consulting",
            "type":"Services"
        }
    ],
    "sg:phone":"+1 805 526 6922",
    "sg:postcode":"93065",
    "sg:province":"CA",
    "sg:tags":[
        "party",
        "planning"
    ],
    "sg:website":"www.greatparty.com",
    "wof:name":"Cari'd Away Events",
    "wof:placetype":"venue"
},
  "geometry": {"coordinates":[-118.78290699999999,34.26063],"type":"Point"}
}