{
  "type": "Feature",
  "properties": {
    "iso:country":"US",
    "sg:address":"9545 1/2 Telegraph Rd",
    "sg:city":"Pico Rivera",
    "sg:classifiers":[
        {
            "category":"Home & Garden",
            "subcategory":"Furniture",
            "type":"Retail Goods"
        }
    ],
    "sg:phone":"+1 562 949 3264",
    "sg:postcode":"90660",
    "sg:province":"CA",
    "sg:tags":[
        "store"
    ],
    "wof:name":"Gonzalez Furniture",
    "wof:placetype":"venue"
},
  "geometry": {"coordinates":[-118.099114,33.953443],"type":"Point"}
}