{
  "type": "Feature",
  "properties": {
    "addr:full":"1075 Tully Rd Ste E San Jose CA 95122",
    "addr:housenumber":"1075",
    "addr:postcode":"95122",
    "addr:street":"Tully Rd Ste E",
    "iso:country":"US",
    "sg:address":"1075 Tully Rd Ste E",
    "sg:city":"San Jose",
    "sg:classifiers":[
        {
            "category":"Food & Beverages",
            "subcategory":"Meat & Fish",
            "type":"Retail Goods"
        }
    ],
    "sg:phone":"+1 408 999 0393",
    "sg:postcode":"95122",
    "sg:province":"CA",
    "sg:tags":[
        "shop"
    ],
    "wof:name":"Mercado Y Carniceria Moreno",
    "wof:placetype":"venue"
},
  "geometry": {"coordinates":[-121.83785,37.314449],"type":"Point"}
}