{
  "type": "Feature",
  "properties": {
    "iso:country":"US",
    "sg:address":"2814 Sepulveda Blvd # B",
    "sg:city":"Torrance",
    "sg:classifiers":[
        {
            "category":"Personal",
            "subcategory":"Beauty Salon",
            "type":"Services"
        }
    ],
    "sg:phone":"+1 310 257 4900",
    "sg:postcode":"90505",
    "sg:province":"CA",
    "sg:tags":[
        "hair"
    ],
    "wof:name":"Park Jun Beauty Lab",
    "wof:placetype":"venue"
},
  "geometry": {"coordinates":[-118.335668,33.822609],"type":"Point"}
}