{
  "type": "Feature",
  "properties": {
    "iso:country":"US",
    "sg:address":"425 Virginia St",
    "sg:city":"Vallejo",
    "sg:classifiers":[
        {
            "category":"Real Estate",
            "subcategory":"Real Estate Agent",
            "type":"Services"
        }
    ],
    "sg:phone":"+1 707 644 7653",
    "sg:postcode":"94590",
    "sg:province":"CA",
    "wof:name":"Exit Realty",
    "wof:placetype":"venue"
},
  "geometry": {"coordinates":[-122.25618299999999,38.102027],"type":"Point"}
}