{
  "type": "Feature",
  "properties": {
    "addr:full":"5634 Weber Rd Vacaville CA 95687",
    "addr:housenumber":"5634",
    "addr:postcode":"95687",
    "addr:street":"Weber Rd",
    "iso:country":"US",
    "sg:address":"5634 Weber Rd",
    "sg:city":"Vacaville",
    "sg:classifiers":[
        {
            "category":"Farming",
            "subcategory":"Nursery",
            "type":"Manufacturing & Wholesale Goods"
        }
    ],
    "sg:phone":"+1 707 678 3000",
    "sg:postcode":"95687",
    "sg:province":"CA",
    "sg:tags":[
        "greenhouse"
    ],
    "wof:name":"Baraka Farms KAJ Inc",
    "wof:placetype":"venue"
},
  "geometry": {"coordinates":[-121.894907,38.402349],"type":"Point"}
}