{
  "type": "Feature",
  "properties": {
    "iso:country":"US",
    "sg:address":"100 Old Airport Rd",
    "sg:city":"Auburn",
    "sg:classifiers":[
        {
            "category":"Retail",
            "subcategory":"Veterinary Services",
            "type":"Services"
        }
    ],
    "sg:phone":"+1 530 823 6306",
    "sg:postcode":"95603",
    "sg:province":"CA",
    "wof:name":"Bowman Veterinary Hospital",
    "wof:placetype":"venue"
},
  "geometry": {"coordinates":[-121.051248,38.941131],"type":"Point"}
}