{
  "type": "Feature",
  "properties": {
    "addr:full":"14336 Brookhurst St Garden Grove CA 92843",
    "addr:housenumber":"14336",
    "addr:postcode":"92843",
    "addr:street":"Brookhurst St",
    "iso:country":"US",
    "sg:address":"14336 Brookhurst St",
    "sg:city":"Garden Grove",
    "sg:classifiers":[
        {
            "category":"Shopping",
            "subcategory":"Florist",
            "type":"Retail Goods"
        }
    ],
    "sg:phone":"+1 714 531 0341",
    "sg:postcode":"92843",
    "sg:province":"CA",
    "wof:name":"Le's Florist Boutique",
    "wof:placetype":"venue"
},
  "geometry": {"coordinates":[-117.95500199999999,33.7547],"type":"Point"}
}