{
  "type": "Feature",
  "properties": {
    "addr:full":"6415 Variel Ave Woodland Hills CA 91367",
    "addr:housenumber":"6415",
    "addr:postcode":"91367",
    "addr:street":"Variel Ave",
    "iso:country":"US",
    "sg:address":"6415 Variel Ave",
    "sg:city":"Woodland Hills",
    "sg:classifiers":[
        {
            "category":"Professional",
            "subcategory":"Art Services",
            "type":"Services"
        }
    ],
    "sg:phone":"+1 818 346 6412",
    "sg:postcode":"91367",
    "sg:province":"CA",
    "sg:tags":[
        "graphic",
        "designer"
    ],
    "wof:name":"Image & Form",
    "wof:placetype":"venue"
},
  "geometry": {"coordinates":[-118.592862,34.184407],"type":"Point"}
}