{
  "type": "Feature",
  "properties": {
    "addr:full":"1521 N Carpenter Rd Modesto CA 95351",
    "addr:housenumber":"1521",
    "addr:postcode":"ca 95351",
    "addr:street":"N Carpenter Rd",
    "iso:country":"US",
    "sg:address":"1521 N Carpenter Rd",
    "sg:city":"Modesto",
    "sg:classifiers":[
        {
            "category":"Health Services",
            "subcategory":"Doctor",
            "type":"Services"
        }
    ],
    "sg:phone":"+1 209 575 7520",
    "sg:postcode":"95351",
    "sg:province":"CA",
    "wof:name":"Patel Sanjay R MD",
    "wof:placetype":"venue"
},
  "geometry": {"coordinates":[-121.028999,37.653198],"type":"Point"}
}