{
  "type": "Feature",
  "properties": {
    "addr:full":"404 N Main St Manteca CA 95336",
    "addr:housenumber":"404",
    "addr:postcode":"95336",
    "addr:street":"N Main St",
    "iso:country":"US",
    "sg:address":"404 N Main St",
    "sg:city":"Manteca",
    "sg:classifiers":[
        {
            "category":"Insurance",
            "subcategory":"Insurance Agent",
            "type":"Services"
        }
    ],
    "sg:phone":"+1 209 823 2896",
    "sg:postcode":"95336",
    "sg:province":"CA",
    "wof:name":"V I F Insurance Brokerage",
    "wof:placetype":"venue"
},
  "geometry": {"coordinates":[-121.216736,37.804606],"type":"Point"}
}