{
  "type": "Feature",
  "properties": {
    "addr:full":"372 Barber Ln Milpitas CA 95035",
    "addr:housenumber":"372",
    "addr:postcode":"95035",
    "addr:street":"Barber Ln",
    "iso:country":"US",
    "sg:address":"372 Barber Ln",
    "sg:city":"Milpitas",
    "sg:classifiers":[
        {
            "category":"Juice Bar",
            "subcategory":"None",
            "type":"Food & Drink"
        },
        {
            "category":"Food & Beverages",
            "subcategory":"Candy",
            "type":"Retail Goods"
        },
        {
            "category":"Coffee & Tea",
            "type":"Food & Drink"
        }
    ],
    "sg:phone":"+1 408 428 0880",
    "sg:postcode":"95035",
    "sg:province":"CA",
    "sg:tags":[
        "smoothy",
        "store"
    ],
    "wof:name":"Sweetheart Candies",
    "wof:placetype":"venue"
},
  "geometry": {"coordinates":[-121.917643,37.421263],"type":"Point"}
}