{
  "type": "Feature",
  "properties": {
    "addr:full":"13081 Lompico Rd Felton CA 95018",
    "addr:housenumber":"13081",
    "addr:postcode":"95018",
    "addr:street":"Lompico Rd",
    "iso:country":"US",
    "sg:address":"13081 Lompico Rd",
    "sg:city":"Felton",
    "sg:classifiers":[
        {
            "category":"Building & Trades",
            "subcategory":"Construction",
            "type":"Services"
        }
    ],
    "sg:phone":"+1 831 335 2667",
    "sg:postcode":"95018",
    "sg:province":"CA",
    "sg:tags":[
        "altering",
        "remodeling",
        "contractor"
    ],
    "wof:name":"Leo Webber Construction",
    "wof:placetype":"venue"
},
  "geometry": {"coordinates":[-122.04989399999999,37.117832],"type":"Point"}
}