{
  "type": "Feature",
  "properties": {
    "addr:full":"37589 Niles Blvd Fremont CA 94536",
    "addr:housenumber":"37589",
    "addr:postcode":"94536",
    "addr:street":"Niles Blvd",
    "iso:country":"US",
    "sg:address":"37589 Niles Blvd",
    "sg:city":"Fremont",
    "sg:classifiers":[
        {
            "category":"Shopping",
            "subcategory":"Antiques",
            "type":"Retail Goods"
        }
    ],
    "sg:phone":"+1 510 793 8847",
    "sg:postcode":"94536",
    "sg:province":"CA",
    "sg:tags":[
        "dealers-wholesale"
    ],
    "wof:name":"Iron Dog",
    "wof:placetype":"venue"
},
  "geometry": {"coordinates":[-121.978182,37.57676],"type":"Point"}
}