{
  "type": "Feature",
  "properties": {
    "iso:country":"US",
    "sg:address":"1575 Cll Joaquin",
    "sg:city":"San Luis Obispo",
    "sg:classifiers":[
        {
            "category":"Restaurant",
            "type":"Food & Drink"
        }
    ],
    "sg:phone":"+1 805 541 2940",
    "sg:postcode":"93405",
    "sg:province":"CA",
    "sg:website":"www.margiesdiner.com",
    "wof:name":"Margie's Diner-San Luis Obispo",
    "wof:placetype":"venue"
},
  "geometry": {"coordinates":[-120.683601,35.242969],"type":"Point"}
}