{
  "type": "Feature",
  "properties": {
    "addr:full":"8425 Fullbright Ave Winnetka CA 91306",
    "addr:housenumber":"8425",
    "addr:postcode":"91306",
    "addr:street":"Fullbright Ave",
    "iso:country":"US",
    "sg:address":"8425 Fullbright Ave",
    "sg:city":"Winnetka",
    "sg:phone":"+1 818 341 5281",
    "sg:postcode":"91306",
    "sg:province":"CA",
    "wof:name":"The Water Guys",
    "wof:placetype":"venue"
},
  "geometry": {"coordinates":[-118.57741,34.223204],"type":"Point"}
}