{
  "type": "Feature",
  "properties": {
    "addr:full":"21717 Ferrero Pkwy Walnut CA 91789",
    "addr:postcode":"21717;91789",
    "addr:street":"Ferrero Pkwy",
    "iso:country":"US",
    "sg:address":"21717 Ferrero Pkwy",
    "sg:city":"Walnut",
    "sg:classifiers":[
        {
            "category":"Shopping",
            "subcategory":"Bicycles & Sporting Goods",
            "type":"Retail Goods"
        }
    ],
    "sg:phone":"+1 909 595 8797",
    "sg:postcode":"91789",
    "sg:province":"CA",
    "wof:name":"Murray Bicycles",
    "wof:placetype":"venue"
},
  "geometry": {"coordinates":[-117.83448799999999,34.026903],"type":"Point"}
}