{
  "type": "Feature",
  "properties": {
    "addr:full":"40605 Via Malagas Murrieta CA 92562",
    "addr:housenumber":"40605",
    "addr:postcode":"92562",
    "addr:street":"Via Malagas",
    "iso:country":"US",
    "sg:address":"40605 Via Malagas",
    "sg:city":"Murrieta",
    "sg:classifiers":[
        {
            "category":"Banks & Credit Unions",
            "subcategory":"Financial Services",
            "type":"Services"
        }
    ],
    "sg:phone":"+1 951 677 7262",
    "sg:postcode":"92562",
    "sg:province":"CA",
    "sg:tags":[
        "trust",
        "management"
    ],
    "wof:name":"Villa Frank S Marie G Trust",
    "wof:placetype":"venue"
},
  "geometry": {"coordinates":[-117.207504,33.579668],"type":"Point"}
}