{
  "type": "Feature",
  "properties": {
    "iso:country":"US",
    "sg:address":"3500 Data Dr",
    "sg:city":"Rancho Cordova",
    "sg:classifiers":[
        {
            "category":"Wholesale",
            "subcategory":"Non-durable Goods",
            "type":"Manufacturing & Wholesale Goods"
        }
    ],
    "sg:phone":"+1 916 501 7536",
    "sg:postcode":"95670",
    "sg:province":"CA",
    "wof:name":"California Tiles Distributors",
    "wof:placetype":"venue"
},
  "geometry": {"coordinates":[-121.295486,38.582435],"type":"Point"}
}