{
  "type": "Feature",
  "properties": {
    "addr:full":"12759 Foothill Blvd Rancho Cucamonga CA 91730",
    "addr:housenumber":"12759",
    "addr:postcode":"91730",
    "addr:street":"Foothill Blvd",
    "iso:country":"US",
    "sg:address":"12759 Foothill Blvd",
    "sg:city":"Rancho Cucamonga",
    "sg:classifiers":[
        {
            "category":"Shopping",
            "subcategory":"Computers & Home Electronics",
            "type":"Retail Goods"
        }
    ],
    "sg:phone":"+1 909 463 9850",
    "sg:postcode":"91730",
    "sg:province":"CA",
    "wof:name":"Technologybeyondcom",
    "wof:placetype":"venue"
},
  "geometry": {"coordinates":[-117.53,34.106244],"type":"Point"}
}