{
  "type": "Feature",
  "properties": {
    "iso:country":"US",
    "sg:address":"7220 Topanga Canyon Blvd",
    "sg:city":"Canoga Park",
    "sg:classifiers":[
        {
            "category":"Autos & Motor Vehicles",
            "subcategory":"Auto Supplies",
            "type":"Retail Goods"
        }
    ],
    "sg:phone":"+1 818 999 6511",
    "sg:postcode":"91303",
    "sg:province":"CA",
    "sg:tags":[
        "automobile",
        "alarm"
    ],
    "wof:name":"Precision Auto Sound & SEC",
    "wof:placetype":"venue"
},
  "geometry": {"coordinates":[-118.60577600000001,34.201284],"type":"Point"}
}