{
  "type": "Feature",
  "properties": {
    "iso:country":"US",
    "sg:address":"8304 Hwy 79",
    "sg:city":"Descanso",
    "sg:classifiers":[
        {
            "category":"Retail",
            "subcategory":"Auto Repair",
            "type":"Services"
        }
    ],
    "sg:phone":"+1 619 445 4324",
    "sg:postcode":"91916",
    "sg:province":"CA",
    "sg:tags":[
        "repairing",
        "automobile"
    ],
    "wof:name":"John's Auto & Truck Repair",
    "wof:placetype":"venue"
},
  "geometry": {"coordinates":[-116.61925599999999,32.836622],"type":"Point"}
}