{
  "type": "Feature",
  "properties": {
    "iso:country":"US",
    "sg:address":"13819 Foothill Blvd",
    "sg:city":"Fontana",
    "sg:classifiers":[
        {
            "category":"Health Services",
            "subcategory":"Chiropractor",
            "type":"Services"
        }
    ],
    "sg:phone":"+1 909 232 8949",
    "sg:postcode":"92335",
    "sg:province":"CA",
    "sg:tags":[
        "chiropractic"
    ],
    "wof:name":"CCST Financial Management Inc Direct Credit",
    "wof:placetype":"venue"
},
  "geometry": {"coordinates":[-117.503584,34.106439],"type":"Point"}
}