{
  "type": "Feature",
  "properties": {
    "iso:country":"US",
    "sg:address":"603 Natoma St",
    "sg:city":"San Francisco",
    "sg:classifiers":[
        {
            "category":"Professional",
            "subcategory":"Computer Services",
            "type":"Services"
        }
    ],
    "sg:phone":"+1 415 255 8555",
    "sg:postcode":"94103",
    "sg:province":"CA",
    "sg:tags":[
        "graphics"
    ],
    "wof:name":"Signum Visual Concepts Inc",
    "wof:placetype":"venue"
},
  "geometry": {"coordinates":[-122.412069,37.776644],"type":"Point"}
}