{
  "type": "Feature",
  "properties": {
    "addr:full":"15435 Jeffrey Rd. Ste 8105 Irvine CA 92604",
    "addr:housenumber":"15435",
    "addr:postcode":"92604",
    "addr:street":"Jeffrey Rd. Ste 8105",
    "iso:country":"US",
    "sg:address":"15435 Jeffrey Rd. Ste 8105",
    "sg:city":"Irvine",
    "sg:classifiers":[
        {
            "category":"Sports & Exercise",
            "subcategory":"Gym",
            "type":"Entertainment"
        }
    ],
    "sg:phone":"+1 949 331 3559",
    "sg:postcode":"92604",
    "sg:province":"CA",
    "sg:tags":[
        "pilate"
    ],
    "sg:website":"www.coresolutionspilates.com",
    "wof:name":"Core Solutions Pilates and Wellness",
    "wof:placetype":"venue"
},
  "geometry": {"coordinates":[-117.778835,33.680334],"type":"Point"}
}