{
  "type": "Feature",
  "properties": {
    "iso:country":"US",
    "sg:address":"5755 E Kings Canyon Rd",
    "sg:city":"Fresno",
    "sg:classifiers":[
        {
            "category":"Insurance",
            "subcategory":"Insurance Agent",
            "type":"Services"
        }
    ],
    "sg:phone":"+1 559 255 1861",
    "sg:postcode":"93727",
    "sg:province":"CA",
    "wof:name":"Allstate Insurance",
    "wof:placetype":"venue"
},
  "geometry": {"coordinates":[-119.695582,36.736059],"type":"Point"}
}