{
  "type": "Feature",
  "properties": {
    "addr:full":"8383 Wilshire Blvd Beverly Hills CA 90211",
    "addr:housenumber":"8383",
    "addr:postcode":"90211",
    "addr:street":"Wilshire Blvd",
    "iso:country":"US",
    "sg:address":"8383 Wilshire Blvd",
    "sg:city":"Beverly Hills",
    "sg:classifiers":[
        {
            "category":"Real Estate",
            "subcategory":"Real Estate Operator",
            "type":"Services"
        }
    ],
    "sg:phone":"+1 323 937 6468",
    "sg:postcode":"90211",
    "sg:province":"CA",
    "sg:tags":[
        "building",
        "apartment"
    ],
    "wof:name":"The Eberly Company",
    "wof:placetype":"venue"
},
  "geometry": {"coordinates":[-118.37348,34.064694],"type":"Point"}
}