{
  "type": "Feature",
  "properties": {
    "addr:full":"28083 Moulton Pkwy Laguna Niguel CA 92677",
    "addr:postcode":"28083;92677",
    "addr:street":"Moulton Pkwy",
    "iso:country":"US",
    "sg:address":"28083 Moulton Pkwy",
    "sg:city":"Laguna Niguel",
    "sg:classifiers":[
        {
            "category":"Restaurant",
            "type":"Food & Drink"
        }
    ],
    "sg:phone":"+1 949 831 0110",
    "sg:postcode":"92677",
    "sg:province":"CA",
    "wof:name":"New York Pizzeria",
    "wof:placetype":"venue"
},
  "geometry": {"coordinates":[-117.69879899999999,33.555642],"type":"Point"}
}