{
  "type": "Feature",
  "properties": {
    "iso:country":"US",
    "sg:address":"28083 Moulton Pkwy",
    "sg:city":"Laguna Niguel",
    "sg:classifiers":[
        {
            "category":"Restaurant",
            "type":"Food & Drink"
        }
    ],
    "sg:phone":"+1 949 831 0110",
    "sg:postcode":"92677",
    "sg:province":"CA",
    "wof:name":"New York Pizzeria",
    "wof:placetype":"venue"
},
  "geometry": {"coordinates":[-117.698799,33.555642],"type":"Point"}
}