{
  "type": "Feature",
  "properties": {
    "iso:country":"US",
    "sg:address":"12211 State Highway 33",
    "sg:city":"Gustine",
    "sg:classifiers":[
        {
            "category":"Fast Food",
            "type":"Food & Drink"
        },
        {
            "category":"Restaurant",
            "type":"Food & Drink"
        }
    ],
    "sg:phone":"+1 209 826 1531",
    "sg:postcode":"95322",
    "sg:province":"CA",
    "sg:tags":[
        "american",
        "hot",
        "hamburger",
        "dog"
    ],
    "sg:website":"http://www.bk.com",
    "wof:name":"Burger King",
    "wof:placetype":"venue"
},
  "geometry": {"coordinates":[-121.015625,37.110977],"type":"Point"}
}