{
  "type": "Feature",
  "properties": {
    "iso:country":"US",
    "sg:address":"118 Patrician Way",
    "sg:city":"Pasadena",
    "sg:classifiers":[
        {
            "category":"Professional",
            "subcategory":"Business Services",
            "type":"Services"
        }
    ],
    "sg:phone":"+1 626 795 0770",
    "sg:postcode":"91105",
    "sg:province":"CA",
    "sg:tags":[
        "inspection"
    ],
    "wof:name":"American International Inspctn",
    "wof:placetype":"venue"
},
  "geometry": {"coordinates":[-118.178892,34.145767],"type":"Point"}
}