{
  "type": "Feature",
  "properties": {
    "iso:country":"US",
    "sg:address":"40 Monte Vista Ave",
    "sg:city":"Larkspur",
    "sg:classifiers":[
        {
            "category":"Manufacturing",
            "subcategory":"Food",
            "type":"Manufacturing & Wholesale Goods"
        }
    ],
    "sg:phone":"+1 415 721 7301",
    "sg:postcode":"94939",
    "sg:province":"CA",
    "sg:tags":[
        "preparation",
        "mfg"
    ],
    "wof:name":"Tea Purveyors",
    "wof:placetype":"venue"
},
  "geometry": {"coordinates":[-122.533888,37.931487],"type":"Point"}
}