{
  "type": "Feature",
  "properties": {
    "iso:country":"US",
    "sg:address":"9560 Wilshire Blvd",
    "sg:city":"Beverly Hills",
    "sg:classifiers":[
        {
            "category":"Shopping",
            "subcategory":"Clothing, Apparel, & Fashions",
            "type":"Retail Goods"
        }
    ],
    "sg:phone":"+1 310 550 4500",
    "sg:postcode":"90212",
    "sg:province":"CA",
    "sg:tags":[
        "item",
        "boutique"
    ],
    "wof:name":"Burberry",
    "wof:placetype":"venue"
},
  "geometry": {"coordinates":[-118.4016,34.066994],"type":"Point"}
}