{
  "type": "Feature",
  "properties": {
    "iso:country":"US",
    "sg:address":"310 N Palm St",
    "sg:city":"Brea",
    "sg:classifiers":[
        {
            "category":"Manufacturing",
            "subcategory":"Printing",
            "type":"Manufacturing & Wholesale Goods"
        }
    ],
    "sg:phone":"+1 562 694 6860",
    "sg:postcode":"92821",
    "sg:province":"CA",
    "sg:tags":[
        "commercial"
    ],
    "wof:name":"Paul & Son Engraving",
    "wof:placetype":"venue"
},
  "geometry": {"coordinates":[-117.924261,33.924047],"type":"Point"}
}