{
  "type": "Feature",
  "properties": {
    "iso:country":"US",
    "sg:address":"501 E Jefferson Blvd",
    "sg:city":"Los Angeles",
    "sg:classifiers":[
        {
            "category":"Manufacturing",
            "subcategory":"Apparel",
            "type":"Manufacturing & Wholesale Goods"
        }
    ],
    "sg:phone":"+1 323 233 3053",
    "sg:postcode":"90011",
    "sg:province":"CA",
    "sg:tags":[
        "sewing",
        "contractor"
    ],
    "wof:name":"Johna Little",
    "wof:placetype":"venue"
},
  "geometry": {"coordinates":[-118.265252,34.015373],"type":"Point"}
}