{
  "type": "Feature",
  "properties": {
    "iso:country":"US",
    "sg:address":"120 W Harding Way",
    "sg:city":"Stockton",
    "sg:classifiers":[
        {
            "category":"Restaurant",
            "type":"Food & Drink"
        }
    ],
    "sg:menulink":"http://www.allmenus.com/ca/stockton/61833-susys/menu/",
    "sg:phone":"+1 209 463 0360",
    "sg:postcode":"95204",
    "sg:province":"CA",
    "sg:tags":[
        "mexican"
    ],
    "wof:name":"Susy's",
    "wof:placetype":"venue"
},
  "geometry": {"coordinates":[-121.29677700000001,37.967015],"type":"Point"}
}