{
  "type": "Feature",
  "properties": {
    "addr:full":"2270 15th Ave San Francisco CA 94116",
    "addr:housenumber":"2270",
    "addr:postcode":"94116",
    "addr:street":"15Th Ave",
    "iso:country":"US",
    "sg:address":"2270 15th Ave",
    "sg:city":"San Francisco",
    "sg:classifiers":[
        {
            "category":"Shopping",
            "subcategory":"Jewelry",
            "type":"Retail Goods"
        }
    ],
    "sg:phone":"+1 415 665 2914",
    "sg:postcode":"94116",
    "sg:province":"CA",
    "wof:name":"Elsies Gem Creations",
    "wof:placetype":"venue"
},
  "geometry": {"coordinates":[-122.47121,37.746446],"type":"Point"}
}