{
  "type": "Feature",
  "properties": {
    "addr:full":"13251 Ventura Blvd Studio City CA 91604",
    "addr:housenumber":"13251",
    "addr:postcode":"91604",
    "addr:street":"Ventura Blvd",
    "iso:country":"US",
    "sg:address":"13251 Ventura Blvd",
    "sg:city":"Studio City",
    "sg:classifiers":[
        {
            "category":"Professional",
            "subcategory":"Business Services",
            "type":"Services"
        }
    ],
    "sg:phone":"+1 818 762 2593",
    "sg:postcode":"91604",
    "sg:province":"CA",
    "sg:tags":[
        "interior",
        "consultant",
        "design",
        "decorator"
    ],
    "wof:name":"Indesign Design Consultants",
    "wof:placetype":"venue"
},
  "geometry": {"coordinates":[-118.422445,34.146639],"type":"Point"}
}