{
  "type": "Feature",
  "properties": {
    "addr:full":"2170 S Harbor Blvd Anaheim CA 92802",
    "addr:housenumber":"2170",
    "addr:postcode":"92802",
    "addr:street":"S Harbor Blvd",
    "iso:country":"US",
    "sg:address":"2170 S Harbor Blvd",
    "sg:city":"Anaheim",
    "sg:classifiers":[
        {
            "category":"Autos & Motor Vehicles",
            "subcategory":"Automobile Sales",
            "type":"Retail Goods"
        },
        {
            "category":"Local Transit",
            "type":"Transportation"
        }
    ],
    "sg:phone":"+1 714 748 4252",
    "sg:postcode":"92802",
    "sg:province":"CA",
    "sg:tags":[
        "public",
        "limo"
    ],
    "wof:name":"Orange County Motor Coach",
    "wof:placetype":"venue"
},
  "geometry": {"coordinates":[-117.914868,33.793809],"type":"Point"}
}