{
  "type": "Feature",
  "properties": {
    "iso:country":"US",
    "sg:address":"8501 Wilshire Boulevard",
    "sg:city":"Beverly Hills",
    "sg:classifiers":[
        {
            "category":"Health Services",
            "subcategory":"Doctor",
            "type":"Services"
        }
    ],
    "sg:phone":"+1 310 854 4949",
    "sg:postcode":"90211",
    "sg:province":"CA",
    "sg:tags":[
        "practice",
        "family"
    ],
    "wof:name":"California Clinical Trials",
    "wof:placetype":"venue"
},
  "geometry": {"coordinates":[-118.37624,34.065251],"type":"Point"}
}