{
  "type": "Feature",
  "properties": {
    "iso:country":"US",
    "sg:address":"1508 Alhambra Blvd",
    "sg:city":"Sacramento",
    "sg:classifiers":[
        {
            "category":"Health Services",
            "subcategory":"Doctor",
            "type":"Services"
        }
    ],
    "sg:phone":"+1 916 734 3787",
    "sg:postcode":"95816",
    "sg:province":"CA",
    "sg:tags":[
        "physician",
        "surgeon"
    ],
    "wof:name":"Radiodiagnosis & Therapy",
    "wof:placetype":"venue"
},
  "geometry": {"coordinates":[-121.46786,38.566869],"type":"Point"}
}