{
  "type": "Feature",
  "properties": {
    "addr:full":"351 Main St Watsonville CA 95076",
    "addr:housenumber":"351",
    "addr:postcode":"95076",
    "addr:street":"Main St",
    "iso:country":"US",
    "sg:address":"351 Main St",
    "sg:city":"Watsonville",
    "sg:classifiers":[
        {
            "category":"Shopping",
            "subcategory":"Clothing, Apparel, & Fashions",
            "type":"Retail Goods"
        }
    ],
    "sg:phone":"+1 831 724 3655",
    "sg:postcode":"95076",
    "sg:province":"CA",
    "sg:tags":[
        "furnishing"
    ],
    "wof:name":"L A Men's Wear",
    "wof:placetype":"venue"
},
  "geometry": {"coordinates":[-121.756761,36.910019],"type":"Point"}
}