{
  "type": "Feature",
  "properties": {
    "addr:full":"1002 Broadway Ave Stockton CA 95205",
    "addr:housenumber":"1002",
    "addr:postcode":"95205",
    "addr:street":"Broadway Ave",
    "iso:country":"US",
    "sg:address":"1002 Broadway Ave",
    "sg:city":"Stockton",
    "sg:classifiers":[
        {
            "category":"Education",
            "subcategory":"Special Training",
            "type":"Public Place"
        }
    ],
    "sg:phone":"+1 209 465 1191",
    "sg:postcode":"95205",
    "sg:province":"CA",
    "sg:tags":[
        "instruction",
        "driving"
    ],
    "sg:website":"www.wptruckschool.com",
    "wof:name":"Western Pacific Truck School",
    "wof:placetype":"venue"
},
  "geometry": {"coordinates":[-121.240639,37.953693],"type":"Point"}
}