{
  "type": "Feature",
  "properties": {
    "iso:country":"US",
    "sg:address":"1110 Fullerton Rd",
    "sg:city":"City Of Industry",
    "sg:classifiers":[
        {
            "category":"Wholesale",
            "subcategory":"Hardware",
            "type":"Manufacturing & Wholesale Goods"
        }
    ],
    "sg:phone":"+1 626 810 8811",
    "sg:postcode":"91748",
    "sg:province":"CA",
    "sg:tags":[
        "tool"
    ],
    "wof:name":"King Machinery Inc",
    "wof:placetype":"venue"
},
  "geometry": {"coordinates":[-117.904846,33.996922],"type":"Point"}
}