{
  "type": "Feature",
  "properties": {
    "iso:country":"US",
    "sg:address":"1610 S Riverside Ave",
    "sg:city":"Rialto",
    "sg:classifiers":[
        {
            "category":"Retail",
            "subcategory":"Portrait Studio",
            "type":"Services"
        },
        {
            "category":"Professional",
            "subcategory":"Art Services",
            "type":"Services"
        }
    ],
    "sg:phone":"+1 909 820 7072",
    "sg:postcode":"92376",
    "sg:province":"CA",
    "sg:tags":[
        "rental",
        "photographers-portrait",
        "photographic",
        "darkroom"
    ],
    "wof:name":"Cpi",
    "wof:placetype":"venue"
},
  "geometry": {"coordinates":[-117.370374,34.073135],"type":"Point"}
}