{
  "type": "Feature",
  "properties": {
    "iso:country":"US",
    "sg:address":"320 S Garfield Ave",
    "sg:city":"Alhambra",
    "sg:classifiers":[
        {
            "category":"Government",
            "subcategory":"Office",
            "type":"Public Place"
        }
    ],
    "sg:phone":"+1 626 458 4524",
    "sg:postcode":"91801",
    "sg:province":"CA",
    "sg:tags":[
        "legislative",
        "body"
    ],
    "wof:name":"Congressman Matthew G Martinez",
    "wof:placetype":"venue"
},
  "geometry": {"coordinates":[-118.124111,34.09139],"type":"Point"}
}