{
  "type": "Feature",
  "properties": {
    "addr:full":"6606 Pacific Boulevard Huntington Park CA 90255",
    "addr:housenumber":"6606",
    "addr:postcode":"90255",
    "addr:street":"Pacific Boulevard;Park",
    "iso:country":"US",
    "sg:address":"6606 Pacific Boulevard",
    "sg:city":"Huntington Park",
    "sg:classifiers":[
        {
            "category":"Education",
            "subcategory":"Kindergarten",
            "type":"Public Place"
        }
    ],
    "sg:phone":"+1 323 588 3352",
    "sg:postcode":"90255",
    "sg:province":"CA",
    "sg:tags":[
        "school",
        "driving"
    ],
    "wof:name":"Nancy's Driving School",
    "wof:placetype":"venue"
},
  "geometry": {"coordinates":[-118.22511299999999,33.979271],"type":"Point"}
}