{
  "type": "Feature",
  "properties": {
    "addr:full":"5415 Mountain View Ave Riverside CA 92504",
    "addr:housenumber":"5415",
    "addr:postcode":"92504",
    "addr:street":"Mountain View Ave",
    "iso:country":"US",
    "sg:address":"5415 Mountain View Ave",
    "sg:city":"Riverside",
    "sg:classifiers":[
        {
            "category":"Building & Trades",
            "subcategory":"Landscaping Services",
            "type":"Services"
        }
    ],
    "sg:phone":"+1 951 274 9339",
    "sg:postcode":"92504",
    "sg:province":"CA",
    "sg:tags":[
        "tree"
    ],
    "wof:name":"Robert C Boudreau Arborist",
    "wof:placetype":"venue"
},
  "geometry": {"coordinates":[-117.421249,33.960708],"type":"Point"}
}