{
  "type": "Feature",
  "properties": {
    "iso:country":"US",
    "sg:address":"14550 Chase St",
    "sg:city":"Panorama City",
    "sg:classifiers":[
        {
            "category":"Restaurant",
            "type":"Food & Drink"
        }
    ],
    "sg:phone":"+1 818 895 5045",
    "sg:postcode":"91402",
    "sg:province":"CA",
    "wof:name":"Mc Donald's",
    "wof:placetype":"venue"
},
  "geometry": {"coordinates":[-118.449658,34.224686],"type":"Point"}
}