{
  "type": "Feature",
  "properties": {
    "addr:full":"3440 Sandrock Rd San Diego CA 92123",
    "addr:housenumber":"3440",
    "addr:postcode":"92123",
    "addr:street":"Sandrock Rd",
    "iso:country":"US",
    "sg:address":"3440 Sandrock Rd",
    "sg:city":"San Diego",
    "sg:classifiers":[
        {
            "category":"Government",
            "subcategory":"Office",
            "type":"Public Place"
        }
    ],
    "sg:phone":"+1 858 573 1396",
    "sg:postcode":"92123",
    "sg:province":"CA",
    "sg:tags":[
        "general"
    ],
    "wof:name":"Public Library",
    "wof:placetype":"venue"
},
  "geometry": {"coordinates":[-117.14018299999999,32.805021],"type":"Point"}
}