{
  "type": "Feature",
  "properties": {
    "addr:full":"323 Cll Villario San Clemente CA 92672",
    "addr:housenumber":"323",
    "addr:postcode":"92672",
    "addr:street":"Cll Villario",
    "iso:country":"US",
    "sg:address":"323 Cll Villario",
    "sg:city":"San Clemente",
    "sg:classifiers":[
        {
            "category":"Professional",
            "type":"Services"
        }
    ],
    "sg:phone":"+1 949 492 1325",
    "sg:postcode":"92672",
    "sg:province":"CA",
    "wof:name":"Gotch Corp",
    "wof:placetype":"venue"
},
  "geometry": {"coordinates":[-117.610017,33.437228],"type":"Point"}
}