{
  "type": "Feature",
  "properties": {
    "addr:full":"2375 Lawrence St Ceres CA 95307",
    "addr:housenumber":"2375",
    "addr:postcode":"95307",
    "addr:street":"Lawrence St",
    "iso:country":"US",
    "sg:address":"2375 Lawrence St",
    "sg:city":"Ceres",
    "sg:classifiers":[
        {
            "category":"Restaurant",
            "type":"Food & Drink"
        }
    ],
    "sg:phone":"+1 209 537 2671",
    "sg:postcode":"95307",
    "sg:province":"CA",
    "sg:tags":[
        "mexican"
    ],
    "wof:name":"Alfonso's Mexican Grill",
    "wof:placetype":"venue"
},
  "geometry": {"coordinates":[-120.952003,37.590199],"type":"Point"}
}