{
  "type": "Feature",
  "properties": {
    "iso:country":"US",
    "sg:address":"265 Tipping Way",
    "sg:city":"Ben Lomond",
    "sg:classifiers":[
        {
            "category":"Real Estate",
            "subcategory":"Architect",
            "type":"Services"
        }
    ],
    "sg:phone":"+1 831 336 5094",
    "sg:postcode":"95005",
    "sg:province":"CA",
    "sg:website":"www.kittyhillresortforcats.com",
    "wof:name":"Harriet J Butts",
    "wof:placetype":"venue"
},
  "geometry": {"coordinates":[-122.079632,37.071637],"type":"Point"}
}