{
  "type": "Feature",
  "properties": {
    "iso:country":"US",
    "sg:address":"1 Orinda Way Ste 6",
    "sg:city":"Orinda",
    "sg:classifiers":[
        {
            "category":"Education",
            "subcategory":"Special Training",
            "type":"Public Place"
        },
        {
            "category":"Arena",
            "subcategory":"Sports Club",
            "type":"Entertainment"
        }
    ],
    "sg:phone":"+1 925 254 5244",
    "sg:postcode":"94563",
    "sg:province":"CA",
    "sg:tags":[
        "instruction",
        "equipment",
        "self defense",
        "martial art"
    ],
    "wof:name":"Lamorinda Martial Arts Studio",
    "wof:placetype":"venue"
},
  "geometry": {"coordinates":[-122.18499799999999,37.880299],"type":"Point"}
}