{
  "type": "Feature",
  "properties": {
    "addr:full":"5630 Atlantic Ave Long Beach CA 90805",
    "addr:housenumber":"5630",
    "addr:postcode":"90805",
    "addr:street":"Atlantic Ave",
    "iso:country":"US",
    "sg:address":"5630 Atlantic Ave",
    "sg:city":"Long Beach",
    "sg:classifiers":[
        {
            "category":"Building & Trades",
            "subcategory":"Construction",
            "type":"Services"
        }
    ],
    "sg:phone":"+1 562 728 0742",
    "sg:postcode":"90805",
    "sg:province":"CA",
    "sg:tags":[
        "resurfacing",
        "laying",
        "refinishing",
        "floor"
    ],
    "wof:name":"Priscilla's Hardwood Floors",
    "wof:placetype":"venue"
},
  "geometry": {"coordinates":[-118.184893,33.859765],"type":"Point"}
}