{
  "type": "Feature",
  "properties": {
    "addr:full":"6074 Malburg Way Los Angeles CA 90058",
    "addr:housenumber":"6074",
    "addr:postcode":"90058",
    "addr:street":"Malburg Way",
    "iso:country":"US",
    "sg:address":"6074 Malburg Way",
    "sg:city":"Los Angeles",
    "sg:classifiers":[
        {
            "category":"Professional",
            "subcategory":"Lawyer & Legal Services",
            "type":"Services"
        }
    ],
    "sg:phone":"+1 323 588 9579",
    "sg:postcode":"90058",
    "sg:province":"CA",
    "wof:name":"Gibson Dunn & Crutcher Llp",
    "wof:placetype":"venue"
},
  "geometry": {"coordinates":[-118.20553,33.987126],"type":"Point"}
}