{
  "type": "Feature",
  "properties": {
    "iso:country":"US",
    "sg:address":"Pier 38",
    "sg:city":"San Francisco",
    "sg:classifiers":[
        {
            "category":"Professional",
            "subcategory":"Computer Services",
            "type":"Services"
        }
    ],
    "sg:postcode":"94110",
    "sg:province":"CA",
    "sg:website":"http://txteagle.com/",
    "wof:name":"txteagle",
    "wof:placetype":"venue"
},
  "geometry": {"coordinates":[-122.394324,37.794996],"type":"Point"}
}