{
  "type": "Feature",
  "properties": {
    "addr:full":"1032 Los Osos Valley Rd Los Osos CA 93402",
    "addr:housenumber":"1032",
    "addr:postcode":"93402",
    "addr:street":"Los Osos Valley Rd",
    "iso:country":"US",
    "sg:address":"1032 Los Osos Valley Rd",
    "sg:city":"Los Osos",
    "sg:classifiers":[
        {
            "category":"Shopping",
            "subcategory":"Florist",
            "type":"Retail Goods"
        }
    ],
    "sg:phone":"+1 805 528 4990",
    "sg:postcode":"93402",
    "sg:province":"CA",
    "wof:name":"Los Osos Flower Market",
    "wof:placetype":"venue"
},
  "geometry": {"coordinates":[-120.831839,35.31107],"type":"Point"}
}