{
  "type": "Feature",
  "properties": {
    "addr:full":"1636 Decker Canyon Rd Malibu CA 90265",
    "addr:housenumber":"1636",
    "addr:postcode":"90265",
    "addr:street":"Decker Canyon Rd",
    "iso:country":"US",
    "sg:address":"1636 Decker Canyon Rd",
    "sg:city":"Malibu",
    "sg:classifiers":[
        {
            "category":"Professional",
            "subcategory":"Art Services",
            "type":"Services"
        }
    ],
    "sg:phone":"+1 310 457 6535",
    "sg:postcode":"90265",
    "sg:province":"CA",
    "sg:tags":[
        "graphic",
        "design"
    ],
    "wof:name":"Robert Weil Graphics",
    "wof:placetype":"venue"
},
  "geometry": {"coordinates":[-118.87785100000001,34.082294],"type":"Point"}
}