{
  "type": "Feature",
  "properties": {
    "addr:full":"412 Skycrest Dr Danville CA 94506",
    "addr:housenumber":"412",
    "addr:postcode":"94506",
    "addr:street":"Skycrest Dr",
    "iso:country":"US",
    "sg:address":"412 Skycrest Dr",
    "sg:city":"Danville",
    "sg:classifiers":[
        {
            "category":"Professional",
            "subcategory":"Computer Services",
            "type":"Services"
        }
    ],
    "sg:phone":"+1 925 648 1288",
    "sg:postcode":"94506",
    "sg:province":"CA",
    "sg:tags":[
        "information",
        "technology"
    ],
    "wof:name":"Blue Heron Consulting",
    "wof:placetype":"venue"
},
  "geometry": {"coordinates":[-121.906104,37.794448],"type":"Point"}
}