{
  "type": "Feature",
  "properties": {
    "iso:country":"US",
    "sg:address":"38 Laurel Glen Ter",
    "sg:city":"San Rafael",
    "sg:classifiers":[
        {
            "category":"Home & Garden",
            "subcategory":"Home Furnishings",
            "type":"Retail Goods"
        }
    ],
    "sg:phone":"+1 415 863 2086",
    "sg:postcode":"94903",
    "sg:province":"CA",
    "wof:name":"P Cimarelli",
    "wof:placetype":"venue"
},
  "geometry": {"coordinates":[-122.526777,37.992105],"type":"Point"}
}