{
  "type": "Feature",
  "properties": {
    "iso:country":"US",
    "sg:address":"1119 Lafayette St",
    "sg:city":"Alameda",
    "sg:classifiers":[
        {
            "category":"Organizations",
            "subcategory":"Religious Organization",
            "type":"Services"
        }
    ],
    "sg:phone":"+1 510 864 1394",
    "sg:postcode":"94501",
    "sg:province":"CA",
    "sg:tags":[
        "church"
    ],
    "wof:name":"Alameda Catholic Youth",
    "wof:placetype":"venue"
},
  "geometry": {"coordinates":[-122.255206,37.766649],"type":"Point"}
}