{
  "type": "Feature",
  "properties": {
    "iso:country":"US",
    "sg:address":"2025 Westwind Dr",
    "sg:city":"Bakersfield",
    "sg:classifiers":[
        {
            "category":"Social Services",
            "type":"Services"
        }
    ],
    "sg:phone":"+1 661 328 9286",
    "sg:postcode":"93301",
    "sg:province":"CA",
    "sg:tags":[
        "counselor",
        "marriage",
        "family"
    ],
    "wof:name":"Michael Sampley & Assoc",
    "wof:placetype":"venue"
},
  "geometry": {"coordinates":[-119.042614,35.377019],"type":"Point"}
}