{
  "type": "Feature",
  "properties": {
    "addr:full":"2028 Woodard Rd San Jose CA 95124",
    "addr:housenumber":"2028",
    "addr:postcode":"95124",
    "addr:street":"Woodard Rd",
    "iso:country":"US",
    "sg:address":"2028 Woodard Rd",
    "sg:city":"San Jose",
    "sg:classifiers":[
        {
            "category":"Utilities",
            "type":"Services"
        }
    ],
    "sg:phone":"+1 408 558 1900",
    "sg:postcode":"95124",
    "sg:province":"CA",
    "sg:tags":[
        "sweeping"
    ],
    "wof:name":"Pro Sweep Inc",
    "wof:placetype":"venue"
},
  "geometry": {"coordinates":[-121.932209,37.260191],"type":"Point"}
}