{
  "type": "Feature",
  "properties": {
    "iso:country":"US",
    "sg:address":"2305 Wilshire Blvd",
    "sg:city":"Santa Monica",
    "sg:classifiers":[
        {
            "category":"Travel",
            "subcategory":"Travel Agent",
            "type":"Entertainment"
        }
    ],
    "sg:phone":"+1 310 315 9100",
    "sg:postcode":"90403",
    "sg:province":"CA",
    "sg:tags":[
        "agency",
        "bureau"
    ],
    "wof:name":"British West Indies Intl",
    "wof:placetype":"venue"
},
  "geometry": {"coordinates":[-118.479957,34.03406],"type":"Point"}
}