{
  "type": "Feature",
  "properties": {
    "addr:full":"1700 Porter Way Stockton CA 95207",
    "addr:housenumber":"1700",
    "addr:postcode":"95207",
    "addr:street":"Porter Way",
    "iso:country":"US",
    "sg:address":"1700 Porter Way",
    "sg:city":"Stockton",
    "sg:classifiers":[
        {
            "category":"Social Services",
            "subcategory":"Child Care",
            "type":"Services"
        }
    ],
    "sg:phone":"+1 209 951 7664",
    "sg:postcode":"95207",
    "sg:province":"CA",
    "wof:name":"Head Start Child Development",
    "wof:placetype":"venue"
},
  "geometry": {"coordinates":[-121.3302,38.003592],"type":"Point"}
}