{
  "type": "Feature",
  "properties": {
    "addr:full":"506 N Garfield Ave Alhambra CA 91801",
    "addr:housenumber":"506",
    "addr:postcode":"91801",
    "addr:street":"N Garfield Ave",
    "iso:country":"US",
    "sg:address":"506 N Garfield Ave",
    "sg:city":"Alhambra",
    "sg:classifiers":[
        {
            "category":"Professional",
            "subcategory":"Lawyer & Legal Services",
            "type":"Services"
        }
    ],
    "sg:phone":"+1 626 281 1683",
    "sg:postcode":"91801",
    "sg:province":"CA",
    "wof:name":"Law Office of Peter Kam",
    "wof:placetype":"venue"
},
  "geometry": {"coordinates":[-118.129997,34.099899],"type":"Point"}
}