{
  "type": "Feature",
  "properties": {
    "iso:country":"US",
    "sg:address":"341 N Azusa Ave",
    "sg:city":"West Covina",
    "sg:classifiers":[
        {
            "category":"Real Estate",
            "subcategory":"Real Estate Agent",
            "type":"Services"
        }
    ],
    "sg:phone":"+1 626 332 2277",
    "sg:postcode":"91791",
    "sg:province":"CA",
    "sg:website":"www.mastersrealestate.com",
    "wof:name":"Re/Max",
    "wof:placetype":"venue"
},
  "geometry": {"coordinates":[-117.907799,34.076594],"type":"Point"}
}