{
  "type": "Feature",
  "properties": {
    "addr:full":"517 2nd St Santa Rosa CA 95401",
    "addr:housenumber":"517",
    "addr:postcode":"ca 95401",
    "addr:street":"2Nd St",
    "iso:country":"US",
    "sg:address":"517 2nd St",
    "sg:city":"Santa Rosa",
    "sg:classifiers":[
        {
            "category":"Home & Garden",
            "subcategory":"Carpets & Floor Coverings",
            "type":"Retail Goods"
        }
    ],
    "sg:phone":"+1 707 542 0100",
    "sg:postcode":"95401",
    "sg:province":"CA",
    "sg:tags":[
        "dealer",
        "rug"
    ],
    "wof:name":"Kirkess Floorcoverings",
    "wof:placetype":"venue"
},
  "geometry": {"coordinates":[-122.713655,38.438782],"type":"Point"}
}