{
  "type": "Feature",
  "properties": {
    "iso:country":"US",
    "sg:address":"16161 Ventura Blvd",
    "sg:city":"Encino",
    "sg:classifiers":[
        {
            "category":"Insurance",
            "subcategory":"Insurance Agent",
            "type":"Services"
        }
    ],
    "sg:phone":"+1 818 788 9611",
    "sg:postcode":"91436",
    "sg:province":"CA",
    "wof:name":"Petrie & Assoc Inc",
    "wof:placetype":"venue"
},
  "geometry": {"coordinates":[-118.486876,34.15686],"type":"Point"}
}