{
  "type": "Feature",
  "properties": {
    "iso:country":"US",
    "sg:address":"365 Van Ness Way",
    "sg:city":"Torrance",
    "sg:classifiers":[
        {
            "category":"Retail",
            "subcategory":"Repair Shop",
            "type":"Services"
        }
    ],
    "sg:phone":"+1 310 212 0912",
    "sg:postcode":"90501",
    "sg:province":"CA",
    "sg:website":"www.gaugerepairservice.com",
    "wof:name":"Gauge Repair Svc",
    "wof:placetype":"venue"
},
  "geometry": {"coordinates":[-118.318912,33.84618],"type":"Point"}
}