{
  "type": "Feature",
  "properties": {
    "iso:country":"US",
    "sg:address":"4343 Del Mar Trails Rd",
    "sg:city":"San Diego",
    "sg:classifiers":[
        {
            "category":"Education",
            "subcategory":"School",
            "type":"Public Place"
        }
    ],
    "sg:phone":"+1 858 847 3016",
    "sg:postcode":"92130",
    "sg:province":"CA",
    "sg:website":"www.ndasd.org",
    "wof:name":"Notre Dame Academy",
    "wof:placetype":"venue"
},
  "geometry": {"coordinates":[-117.22458,32.94459],"type":"Point"}
}