{
  "type": "Feature",
  "properties": {
    "addr:full":"30086 Jon Christian Pl Temecula CA 92591",
    "addr:postcode":"30086;92591",
    "addr:street":"Christian Pl",
    "iso:country":"US",
    "sg:address":"30086 Jon Christian Pl",
    "sg:city":"Temecula",
    "sg:classifiers":[
        {
            "category":"Professional",
            "type":"Services"
        }
    ],
    "sg:phone":"+1 951 506 5877",
    "sg:postcode":"92591",
    "sg:province":"CA",
    "wof:name":"Clare Wilson",
    "wof:placetype":"venue"
},
  "geometry": {"coordinates":[-117.136442,33.537195],"type":"Point"}
}