{
  "type": "Feature",
  "properties": {
    "addr:full":"530 Alameda del Prado Novato CA 94949",
    "addr:housenumber":"530",
    "addr:postcode":"94949",
    "addr:street":"Alameda Del Prado",
    "iso:country":"US",
    "sg:address":"530 Alameda del Prado",
    "sg:city":"Novato",
    "sg:classifiers":[
        {
            "category":"Personal",
            "subcategory":"Tanning Parlor",
            "type":"Services"
        }
    ],
    "sg:phone":"+1 415 382 9826",
    "sg:postcode":"94949",
    "sg:province":"CA",
    "sg:tags":[
        "salon"
    ],
    "wof:name":"Jamaica Me Tan",
    "wof:placetype":"venue"
},
  "geometry": {"coordinates":[-122.540514,38.065542],"type":"Point"}
}