{
  "type": "Feature",
  "properties": {
    "addr:full":"1829 W El Segundo Blvd Compton CA 90222",
    "addr:housenumber":"1829",
    "addr:postcode":"90222",
    "addr:street":"W El Segundo Blvd",
    "iso:country":"US",
    "sg:address":"1829 W El Segundo Blvd",
    "sg:city":"Compton",
    "sg:classifiers":[
        {
            "category":"Retail",
            "subcategory":"Auto Repair",
            "type":"Services"
        }
    ],
    "sg:phone":"+1 310 632 5978",
    "sg:postcode":"90222",
    "sg:province":"CA",
    "sg:tags":[
        "body",
        "shop"
    ],
    "sg:website":"www.martintruckbody.net",
    "wof:name":"Martin Truck Body",
    "wof:placetype":"venue"
},
  "geometry": {"coordinates":[-118.252336,33.916881],"type":"Point"}
}