{
  "type": "Feature",
  "properties": {
    "addr:full":"579 Ofarrell St San Francisco CA 94102",
    "addr:housenumber":"579",
    "addr:postcode":"94102",
    "addr:street":"Ofarrell St",
    "iso:country":"US",
    "sg:address":"579 Ofarrell St",
    "sg:city":"San Francisco",
    "sg:classifiers":[
        {
            "category":"Travel",
            "subcategory":"Hotels & Motels",
            "type":"Entertainment"
        }
    ],
    "sg:phone":"+1 415 441 9636",
    "sg:postcode":"94102",
    "sg:province":"CA",
    "wof:name":"Sonny Hotel",
    "wof:placetype":"venue"
},
  "geometry": {"coordinates":[-122.41404,37.785597],"type":"Point"}
}