{
  "type": "Feature",
  "properties": {
    "addr:full":"9279 Campo Rd Spring Valley CA 91977",
    "addr:housenumber":"9279",
    "addr:postcode":"91977",
    "addr:street":"Campo Rd",
    "iso:country":"US",
    "sg:address":"9279 Campo Rd",
    "sg:city":"Spring Valley",
    "sg:classifiers":[
        {
            "category":"Retail",
            "subcategory":"Animal Services",
            "type":"Services"
        }
    ],
    "sg:phone":"+1 619 463 1722",
    "sg:postcode":"91977",
    "sg:province":"CA",
    "sg:tags":[
        "pet",
        "boarding/pet",
        "sitting"
    ],
    "sg:website":"www.springcreekkennel.com/",
    "wof:name":"Spring Creek Kennel and Cattery",
    "wof:placetype":"venue"
},
  "geometry": {"coordinates":[-116.997212,32.750049],"type":"Point"}
}