{
  "type": "Feature",
  "properties": {
    "addr:full":"254 S Avenue 24 Los Angeles CA 90031",
    "addr:housenumber":"254;24",
    "addr:postcode":"90031",
    "addr:street":"S Avenue",
    "iso:country":"US",
    "sg:address":"254 S Avenue 24",
    "sg:city":"Los Angeles",
    "sg:classifiers":[
        {
            "category":"Banks & Credit Unions",
            "subcategory":"Investment Brokerage",
            "type":"Services"
        }
    ],
    "sg:phone":"+1 323 227 1529",
    "sg:postcode":"90031",
    "sg:province":"CA",
    "sg:tags":[
        "investing"
    ],
    "wof:name":"Hansa Investments",
    "wof:placetype":"venue"
},
  "geometry": {"coordinates":[-118.21700300000001,34.071999],"type":"Point"}
}