{
  "type": "Feature",
  "properties": {
    "addr:full":"13141 del Monte Dr Seal Beach CA 90740",
    "addr:housenumber":"13141",
    "addr:postcode":"90740",
    "addr:street":"Del Monte Dr",
    "iso:country":"US",
    "sg:address":"13141 del Monte Dr",
    "sg:city":"Seal Beach",
    "sg:classifiers":[
        {
            "category":"Organizations",
            "subcategory":"Religious Organization",
            "type":"Services"
        }
    ],
    "sg:phone":"+1 562 596 8518",
    "sg:postcode":"90740",
    "sg:province":"CA",
    "sg:tags":[
        "church"
    ],
    "wof:name":"Assembly Of God",
    "wof:placetype":"venue"
},
  "geometry": {"coordinates":[-118.081867,33.771969],"type":"Point"}
}