{
  "type": "Feature",
  "properties": {
    "iso:country":"US",
    "sg:address":"1440 W Brooks St",
    "sg:city":"Ontario",
    "sg:classifiers":[
        {
            "category":"Retail",
            "subcategory":"Repair Shop",
            "type":"Services"
        }
    ],
    "sg:phone":"+1 909 460 0266",
    "sg:postcode":"91762",
    "sg:province":"CA",
    "sg:tags":[
        "scooter",
        "motorcycle",
        "motor"
    ],
    "wof:name":"Bill Chambers Racing",
    "wof:placetype":"venue"
},
  "geometry": {"coordinates":[-117.679363,34.061901],"type":"Point"}
}