{
  "type": "Feature",
  "properties": {
    "iso:country":"US",
    "sg:address":"37180 Oak View Rd",
    "sg:city":"Yucaipa",
    "sg:classifiers":[
        {
            "category":"Professional",
            "subcategory":"Management & Consulting",
            "type":"Services"
        }
    ],
    "sg:phone":"+1 909 790 2591",
    "sg:postcode":"92399",
    "sg:province":"CA",
    "sg:tags":[
        "retail",
        "direct",
        "sales"
    ],
    "wof:name":"Suzis Purple Box",
    "wof:placetype":"venue"
},
  "geometry": {"coordinates":[-116.99807,34.015558],"type":"Point"}
}