{
  "type": "Feature",
  "properties": {
    "iso:country":"US",
    "sg:address":"3453 W Ramsey St",
    "sg:city":"Banning",
    "sg:classifiers":[
        {
            "category":"Home & Garden",
            "subcategory":"Furniture",
            "type":"Retail Goods"
        }
    ],
    "sg:phone":"+1 951 922 1428",
    "sg:postcode":"92220",
    "sg:province":"CA",
    "wof:name":"Ortega's Furniture",
    "wof:placetype":"venue"
},
  "geometry": {"coordinates":[-116.92121400000001,33.926892],"type":"Point"}
}