{
  "type": "Feature",
  "properties": {
    "iso:country":"US",
    "sg:address":"1068 Cam Ricardo",
    "sg:city":"San Jose",
    "sg:classifiers":[
        {
            "category":"Professional",
            "subcategory":"Management & Consulting",
            "type":"Services"
        }
    ],
    "sg:phone":"+1 408 279 8182",
    "sg:postcode":"95125",
    "sg:province":"CA",
    "wof:name":"Facilities In Motion",
    "wof:placetype":"venue"
},
  "geometry": {"coordinates":[-121.906919,37.308312],"type":"Point"}
}