{
  "type": "Feature",
  "properties": {
    "iso:country":"US",
    "sg:address":"732 Alene Ave",
    "sg:city":"Ridgecrest",
    "sg:classifiers":[
        {
            "category":"Professional",
            "type":"Services"
        }
    ],
    "sg:phone":"+1 760 446 4915",
    "sg:postcode":"93555",
    "sg:province":"CA",
    "wof:name":"Joel Cash",
    "wof:placetype":"venue"
},
  "geometry": {"coordinates":[-117.683882,35.649934],"type":"Point"}
}