{
  "type": "Feature",
  "properties": {
    "addr:full":"Guarantee Mortgage 636 Fourth Street San Francisco CA 94107",
    "addr:housenumber":"636",
    "addr:postcode":"94107",
    "addr:street":"Fourth Street",
    "iso:country":"US",
    "sg:address":"Guarantee Mortgage 636 Fourth Street",
    "sg:city":"San Francisco",
    "sg:classifiers":[
        {
            "category":"Banks & Credit Unions",
            "subcategory":"Financial Services",
            "type":"Services"
        }
    ],
    "sg:phone":"+1 415 309 0157",
    "sg:postcode":"94107",
    "sg:province":"CA",
    "sg:tags":[
        "broker",
        "mortgage"
    ],
    "sg:website":"www.sfhomeloans.com",
    "wof:name":"Sergei Andruha",
    "wof:placetype":"venue"
},
  "geometry": {"coordinates":[-122.396011,37.777885],"type":"Point"}
}