{
  "type": "Feature",
  "properties": {
    "addr:full":"2930 Rowena Ave Los Angeles CA 90039",
    "addr:housenumber":"2930",
    "addr:postcode":"90039",
    "addr:street":"Rowena Ave",
    "iso:country":"US",
    "sg:address":"2930 Rowena Ave",
    "sg:city":"Los Angeles",
    "sg:classifiers":[
        {
            "category":"Shopping",
            "type":"Retail Goods"
        }
    ],
    "sg:phone":"+1 323 660 1460",
    "sg:postcode":"90039",
    "sg:province":"CA",
    "wof:name":"Further Casa",
    "wof:placetype":"venue"
},
  "geometry": {"coordinates":[-118.268997,34.108601],"type":"Point"}
}