{
  "type": "Feature",
  "properties": {
    "iso:country":"US",
    "sg:address":"26660 Patrick Ave",
    "sg:city":"Hayward",
    "sg:classifiers":[
        {
            "category":"Health Services",
            "subcategory":"Nursing And Care Facility",
            "type":"Services"
        }
    ],
    "sg:phone":"+1 510 782 1845",
    "sg:postcode":"94544",
    "sg:province":"CA",
    "sg:tags":[
        "skilled"
    ],
    "wof:name":"Hayward Care Center",
    "wof:placetype":"venue"
},
  "geometry": {"coordinates":[-122.079607,37.638033],"type":"Point"}
}