{
  "type": "Feature",
  "properties": {
    "iso:country":"US",
    "sg:address":"73700 el Paseo",
    "sg:city":"Palm Desert",
    "sg:classifiers":[
        {
            "category":"Professional",
            "subcategory":"Business Services",
            "type":"Services"
        }
    ],
    "sg:phone":"+1 760 341 7737",
    "sg:postcode":"92260",
    "sg:province":"CA",
    "sg:tags":[
        "interior",
        "consultant",
        "design",
        "decorator"
    ],
    "wof:name":"Cantalini Associates Interior",
    "wof:placetype":"venue"
},
  "geometry": {"coordinates":[-116.377675,33.719795],"type":"Point"}
}