{
  "type": "Feature",
  "properties": {
    "addr:full":"100 W Las Palmas Ave Patterson CA 95363",
    "addr:housenumber":"100",
    "addr:postcode":"95363",
    "addr:street":"W Las Palmas Ave",
    "iso:country":"US",
    "sg:address":"100 W Las Palmas Ave",
    "sg:city":"Patterson",
    "sg:classifiers":[
        {
            "category":"Food & Beverages",
            "subcategory":"Fruits & Vegetables",
            "type":"Retail Goods"
        }
    ],
    "sg:phone":"+1 209 892 3046",
    "sg:postcode":"95363",
    "sg:province":"CA",
    "sg:tags":[
        "produce"
    ],
    "wof:name":"Del Puerto Marketing",
    "wof:placetype":"venue"
},
  "geometry": {"coordinates":[-121.128489,37.472293],"type":"Point"}
}