{
  "type": "Feature",
  "properties": {
    "addr:full":"6585 Foothill Blvd Tujunga CA 91042",
    "addr:housenumber":"6585",
    "addr:postcode":"91042",
    "addr:street":"Foothill Blvd",
    "iso:country":"US",
    "sg:address":"6585 Foothill Blvd",
    "sg:city":"Tujunga",
    "sg:classifiers":[
        {
            "category":"Restaurant",
            "type":"Food & Drink"
        }
    ],
    "sg:menulink":"http://www.allmenus.com/ca/san-fernando-valley/198050-kfc---kentucky-fried-chicken/menu/",
    "sg:phone":"+1 818 352 3283",
    "sg:postcode":"91042",
    "sg:province":"CA",
    "sg:tags":[
        "american",
        "chicken"
    ],
    "wof:name":"KFC - Kentucky Fried Chicken",
    "wof:placetype":"venue"
},
  "geometry": {"coordinates":[-118.275464,34.246197],"type":"Point"}
}