{
  "type": "Feature",
  "properties": {
    "iso:country":"US",
    "sg:address":"418 N Glendale Ave",
    "sg:city":"Glendale",
    "sg:classifiers":[
        {
            "category":"Banks & Credit Unions",
            "subcategory":"Bank",
            "type":"Services"
        }
    ],
    "sg:phone":"+1 818 240 2190",
    "sg:postcode":"91206",
    "sg:province":"CA",
    "sg:tags":[
        "loan"
    ],
    "wof:name":"Processing Center",
    "wof:placetype":"venue"
},
  "geometry": {"coordinates":[-118.243741,34.153189],"type":"Point"}
}