{
  "type": "Feature",
  "properties": {
    "iso:country":"US",
    "sg:address":"590 E Arrow Hwy",
    "sg:city":"San Dimas",
    "sg:classifiers":[
        {
            "category":"Wholesale",
            "subcategory":"Hardware",
            "type":"Manufacturing & Wholesale Goods"
        }
    ],
    "sg:phone":"+1 909 599 6800",
    "sg:postcode":"91773",
    "sg:province":"CA",
    "sg:tags":[
        "air",
        "parts",
        "conditioning",
        "supply"
    ],
    "wof:name":"Fred Carreon Sheet Metal Fab",
    "wof:placetype":"venue"
},
  "geometry": {"coordinates":[-117.79974900000001,34.102874],"type":"Point"}
}