{
  "type": "Feature",
  "properties": {
    "addr:full":"2253 E Warner Ave Fresno CA 93710",
    "addr:housenumber":"2253",
    "addr:postcode":"93710",
    "addr:street":"E Warner Ave",
    "iso:country":"US",
    "sg:address":"2253 E Warner Ave",
    "sg:city":"Fresno",
    "sg:classifiers":[
        {
            "category":"Insurance",
            "subcategory":"Insurance Agent",
            "type":"Services"
        }
    ],
    "sg:phone":"+1 559 433 4821",
    "sg:postcode":"93710",
    "sg:province":"CA",
    "wof:name":"Wayne Easley",
    "wof:placetype":"venue"
},
  "geometry": {"coordinates":[-119.74876500000001,36.836436],"type":"Point"}
}