{
  "type": "Feature",
  "properties": {
    "addr:full":"1911 Ocean St Oceano CA 93445",
    "addr:housenumber":"1911",
    "addr:postcode":"93445",
    "addr:street":"Ocean St",
    "iso:country":"US",
    "sg:address":"1911 Ocean St",
    "sg:city":"Oceano",
    "sg:classifiers":[
        {
            "category":"Organizations",
            "subcategory":"Religious Organization",
            "type":"Services"
        }
    ],
    "sg:phone":"+1 805 489 1678",
    "sg:postcode":"93445",
    "sg:province":"CA",
    "sg:tags":[
        "church"
    ],
    "wof:name":"Open Door Church",
    "wof:placetype":"venue"
},
  "geometry": {"coordinates":[-120.610698,35.100219],"type":"Point"}
}