{
  "type": "Feature",
  "properties": {
    "addr:full":"7710 Balboa Ave San Diego CA 92111",
    "addr:housenumber":"7710",
    "addr:postcode":"92111",
    "addr:street":"Balboa Ave",
    "iso:country":"US",
    "sg:address":"7710 Balboa Ave",
    "sg:city":"San Diego",
    "sg:classifiers":[
        {
            "category":"Professional",
            "subcategory":"Accounting & Tax Preparation",
            "type":"Services"
        }
    ],
    "sg:phone":"+1 858 560 6431",
    "sg:postcode":"92111",
    "sg:province":"CA",
    "sg:tags":[
        "accountant"
    ],
    "wof:name":"Wallace David R CPA",
    "wof:placetype":"venue"
},
  "geometry": {"coordinates":[-117.157903,32.822209],"type":"Point"}
}