{
  "type": "Feature",
  "properties": {
    "addr:full":"4105 W Magnolia Blvd Burbank CA 91505",
    "addr:housenumber":"4105",
    "addr:postcode":"91505",
    "addr:street":"W Magnolia Blvd",
    "iso:country":"US",
    "sg:address":"4105 W Magnolia Blvd",
    "sg:city":"Burbank",
    "sg:classifiers":[
        {
            "category":"Real Estate",
            "subcategory":"Real Estate Services",
            "type":"Services"
        }
    ],
    "sg:phone":"+1 818 845 9700",
    "sg:postcode":"91505",
    "sg:province":"CA",
    "sg:website":"www.mediawestrealty.com",
    "wof:name":"Media West Realty",
    "wof:placetype":"venue"
},
  "geometry": {"coordinates":[-118.351454,34.166675],"type":"Point"}
}