{
  "type": "Feature",
  "properties": {
    "iso:country":"US",
    "sg:address":"2305 W Chapman Ave",
    "sg:city":"Orange",
    "sg:classifiers":[
        {
            "category":"Donuts",
            "subcategory":"None",
            "type":"Food & Drink"
        }
    ],
    "sg:phone":"+1 714 634 2196",
    "sg:postcode":"92868",
    "sg:province":"CA",
    "wof:name":"Jax Donuts No 19",
    "wof:placetype":"venue"
},
  "geometry": {"coordinates":[-117.876999,33.7878],"type":"Point"}
}