{
  "type": "Feature",
  "properties": {
    "addr:full":"2442 Waterloo Rd Stockton CA 95205",
    "addr:housenumber":"2442",
    "addr:postcode":"95205",
    "addr:street":"Waterloo Rd",
    "iso:country":"US",
    "sg:address":"2442 Waterloo Rd",
    "sg:city":"Stockton",
    "sg:classifiers":[
        {
            "category":"Retail",
            "subcategory":"Repair Shop",
            "type":"Services"
        },
        {
            "category":"Autos & Motor Vehicles",
            "subcategory":"Motorcycle Sales",
            "type":"Retail Goods"
        }
    ],
    "sg:phone":"+1 209 948 5361",
    "sg:postcode":"95205",
    "sg:province":"CA",
    "sg:tags":[
        "scooter"
    ],
    "wof:name":"Burton's Cycle Shop",
    "wof:placetype":"venue"
},
  "geometry": {"coordinates":[-121.26236400000001,37.976495],"type":"Point"}
}