{
  "type": "Feature",
  "properties": {
    "iso:country":"US",
    "sg:address":"641 Quarry Rd",
    "sg:city":"San Carlos",
    "sg:classifiers":[
        {
            "category":"Retail",
            "subcategory":"Repair Shop",
            "type":"Services"
        }
    ],
    "sg:phone":"+1 650 508 0844",
    "sg:postcode":"94070",
    "sg:province":"CA",
    "sg:tags":[
        "door"
    ],
    "wof:name":"Interior Door Replacement Co",
    "wof:placetype":"venue"
},
  "geometry": {"coordinates":[-122.268512,37.516107],"type":"Point"}
}