{
  "type": "Feature",
  "properties": {
    "addr:full":"4131 S Shingle Rd Shingle Springs CA 95682",
    "addr:housenumber":"4131",
    "addr:postcode":"95682",
    "addr:street":"S Shingle Rd",
    "iso:country":"US",
    "sg:address":"4131 S Shingle Rd",
    "sg:city":"Shingle Springs",
    "sg:classifiers":[
        {
            "category":"Restaurant",
            "type":"Food & Drink"
        }
    ],
    "sg:phone":"+1 530 677 0252",
    "sg:postcode":"95682",
    "sg:province":"CA",
    "wof:name":"Los Tres Amigos",
    "wof:placetype":"venue"
},
  "geometry": {"coordinates":[-120.936531,38.660156],"type":"Point"}
}