{
  "type": "Feature",
  "properties": {
    "addr:full":"15329 Palmdale Rd Victorville CA 92392",
    "addr:postcode":"15329;92392",
    "addr:street":"Palmdale Rd",
    "iso:country":"US",
    "sg:address":"15329 Palmdale Rd",
    "sg:city":"Victorville",
    "sg:classifiers":[
        {
            "category":"Cinema",
            "subcategory":"Movie Rental",
            "type":"Entertainment"
        }
    ],
    "sg:phone":"+1 760 843 3486",
    "sg:postcode":"92392",
    "sg:province":"CA",
    "sg:tags":[
        "leasing",
        "video",
        "disc",
        "tape"
    ],
    "wof:name":"Cinemax Video",
    "wof:placetype":"venue"
},
  "geometry": {"coordinates":[-117.327871,34.506962],"type":"Point"}
}