{
  "type": "Feature",
  "properties": {
    "iso:country":"US",
    "sg:address":"1091 S Hope St",
    "sg:city":"El Centro",
    "sg:classifiers":[
        {
            "category":"Home & Garden",
            "subcategory":"Household Appliances",
            "type":"Retail Goods"
        }
    ],
    "sg:phone":"+1 760 352 4700",
    "sg:postcode":"92243",
    "sg:province":"CA",
    "wof:name":"I V Appliance Svc",
    "wof:placetype":"venue"
},
  "geometry": {"coordinates":[-115.53952099999999,32.782266],"type":"Point"}
}