{
  "type": "Feature",
  "properties": {
    "addr:full":"2055 N Garey Ave Pomona CA 91767",
    "addr:housenumber":"2055",
    "addr:postcode":"91767",
    "addr:street":"N Garey Ave",
    "iso:country":"US",
    "sg:address":"2055 N Garey Ave",
    "sg:city":"Pomona",
    "sg:classifiers":[
        {
            "category":"Banks & Credit Unions",
            "subcategory":"Bank",
            "type":"Services"
        }
    ],
    "sg:phone":"+1 909 593 2212",
    "sg:postcode":"91767",
    "sg:province":"CA",
    "sg:tags":[
        "loan"
    ],
    "wof:name":"Trust Acceptance",
    "wof:placetype":"venue"
},
  "geometry": {"coordinates":[-117.751752,34.085211],"type":"Point"}
}