{
  "type": "Feature",
  "properties": {
    "addr:full":"24600 Silver Cloud Ct Monterey CA 93940",
    "addr:housenumber":"24600",
    "addr:postcode":"93940",
    "addr:street":"Silver Cloud Ct",
    "iso:country":"US",
    "sg:address":"24600 Silver Cloud Ct",
    "sg:city":"Monterey",
    "sg:classifiers":[
        {
            "category":"Banks & Credit Unions",
            "subcategory":"Investment Brokerage",
            "type":"Services"
        }
    ],
    "sg:phone":"+1 831 655 5211",
    "sg:postcode":"93940",
    "sg:province":"CA",
    "sg:tags":[
        "security"
    ],
    "sg:website":"www.agedwards.com",
    "wof:name":"A G Edwards & Sons Inc",
    "wof:placetype":"venue"
},
  "geometry": {"coordinates":[-121.804642,36.572488],"type":"Point"}
}