{
  "type": "Feature",
  "properties": {
    "iso:country":"US",
    "sg:address":"508 N Spaulding Ave",
    "sg:city":"Los Angeles",
    "sg:classifiers":[
        {
            "category":"Insurance",
            "subcategory":"Insurance Agent",
            "type":"Services"
        }
    ],
    "sg:phone":"+1 323 872 1548",
    "sg:postcode":"90036",
    "sg:province":"CA",
    "wof:name":"Linda Butler",
    "wof:placetype":"venue"
},
  "geometry": {"coordinates":[-118.357289,34.081674],"type":"Point"}
}