{
  "type": "Feature",
  "properties": {
    "addr:full":"14333 Dickens St Sherman Oaks CA 91423",
    "addr:housenumber":"14333",
    "addr:postcode":"91423",
    "addr:street":"Dickens St",
    "iso:country":"US",
    "sg:address":"14333 Dickens St",
    "sg:city":"Sherman Oaks",
    "sg:classifiers":[
        {
            "category":"Real Estate",
            "subcategory":"Real Estate Operator",
            "type":"Services"
        }
    ],
    "sg:phone":"+1 818 990 8375",
    "sg:postcode":"91423",
    "sg:province":"CA",
    "sg:tags":[
        "apartment"
    ],
    "wof:name":"Dickens Apartments",
    "wof:placetype":"venue"
},
  "geometry": {"coordinates":[-118.444012,34.148967],"type":"Point"}
}