{
  "type": "Feature",
  "properties": {
    "iso:country":"US",
    "sg:address":"1050 E Duane Ave",
    "sg:city":"Sunnyvale",
    "sg:classifiers":[
        {
            "category":"Wholesale",
            "subcategory":"Toys & Hobbies",
            "type":"Manufacturing & Wholesale Goods"
        },
        {
            "category":"Professional",
            "type":"Services"
        }
    ],
    "sg:phone":"+1 408 737 8168",
    "sg:postcode":"94085",
    "sg:province":"CA",
    "wof:name":"Anime Palace",
    "wof:placetype":"venue"
},
  "geometry": {"coordinates":[-121.99708,37.3868],"type":"Point"}
}