{
  "type": "Feature",
  "properties": {
    "addr:full":"740 S La Brea Avenue Los Angeles CA 90036",
    "addr:housenumber":"740",
    "addr:postcode":"90036",
    "addr:street":"S;Brea Avenue",
    "iso:country":"US",
    "sg:address":"740 S La Brea Avenue",
    "sg:city":"Los Angeles",
    "sg:classifiers":[
        {
            "category":"Restaurant",
            "type":"Food & Drink"
        }
    ],
    "sg:phone":"+1 323 936 7788",
    "sg:postcode":"90036",
    "sg:province":"CA",
    "wof:name":"Cafe La Brea",
    "wof:placetype":"venue"
},
  "geometry": {"coordinates":[-118.344437,34.061527],"type":"Point"}
}