{
  "type": "Feature",
  "properties": {
    "iso:country":"US",
    "sg:address":"1713 N Orange Dr",
    "sg:city":"Los Angeles",
    "sg:classifiers":[
        {
            "category":"Manufacturing",
            "subcategory":"Printing",
            "type":"Manufacturing & Wholesale Goods"
        }
    ],
    "sg:phone":"+1 323 465 5102",
    "sg:postcode":"90028",
    "sg:province":"CA",
    "sg:tags":[
        "typographer"
    ],
    "wof:name":"Printing Images",
    "wof:placetype":"venue"
},
  "geometry": {"coordinates":[-118.341825,34.103805],"type":"Point"}
}