{
  "type": "Feature",
  "properties": {
    "iso:country":"US",
    "sg:address":"3201 Ulloa Street",
    "sg:city":"San Francisco",
    "sg:classifiers":[
        {
            "category":"Social Services",
            "subcategory":"Child Care",
            "type":"Services"
        }
    ],
    "sg:phone":"+1 415 681 6606",
    "sg:postcode":"94116",
    "sg:province":"CA",
    "sg:tags":[
        "day"
    ],
    "wof:name":"Grace Infant Care Center",
    "wof:placetype":"venue"
},
  "geometry": {"coordinates":[-122.49099699999999,37.740501],"type":"Point"}
}