{
  "type": "Feature",
  "properties": {
    "addr:full":"5159 S Verdun Ave Los Angeles CA 90043",
    "addr:housenumber":"5159",
    "addr:postcode":"90043",
    "addr:street":"S Verdun Ave",
    "iso:country":"US",
    "sg:address":"5159 S Verdun Ave",
    "sg:city":"Los Angeles",
    "sg:classifiers":[
        {
            "category":"Health Services",
            "subcategory":"Doctor",
            "type":"Services"
        }
    ],
    "sg:phone":"+1 323 293 0103",
    "sg:postcode":"90043",
    "sg:province":"CA",
    "sg:tags":[
        "physician",
        "surgeon"
    ],
    "wof:name":"Tyron C Reece MD",
    "wof:placetype":"venue"
},
  "geometry": {"coordinates":[-118.348681,33.992847],"type":"Point"}
}