{
  "type": "Feature",
  "properties": {
    "iso:country":"US",
    "sg:address":"9284 Orangevale Ave",
    "sg:city":"Orangevale",
    "sg:classifiers":[
        {
            "category":"Building & Trades",
            "subcategory":"Construction",
            "type":"Services"
        }
    ],
    "sg:phone":"+1 916 987 1095",
    "sg:postcode":"95662",
    "sg:province":"CA",
    "sg:tags":[
        "contractor"
    ],
    "wof:name":"All Metal Fences",
    "wof:placetype":"venue"
},
  "geometry": {"coordinates":[-121.20911700000001,38.681814],"type":"Point"}
}