{
  "type": "Feature",
  "properties": {
    "iso:country":"US",
    "sg:address":"4131 Parker Ave",
    "sg:city":"Bakersfield",
    "sg:classifiers":[
        {
            "category":"Building & Trades",
            "subcategory":"Construction",
            "type":"Services"
        }
    ],
    "sg:phone":"+1 661 831 4103",
    "sg:postcode":"93309",
    "sg:province":"CA",
    "sg:tags":[
        "masonry",
        "contractor"
    ],
    "wof:name":"Southwest Masonry",
    "wof:placetype":"venue"
},
  "geometry": {"coordinates":[-119.050487,35.335932],"type":"Point"}
}