{
  "type": "Feature",
  "properties": {
    "iso:country":"US",
    "sg:address":"1719 Broadway",
    "sg:city":"Oakland",
    "sg:classifiers":[
        {
            "category":"Sports & Exercise",
            "subcategory":"Bicycle Rental",
            "type":"Entertainment"
        }
    ],
    "sg:phone":"+1 510 645 1111",
    "sg:postcode":"94620",
    "sg:province":"CA",
    "sg:tags":[
        "wear"
    ],
    "wof:name":"Players",
    "wof:placetype":"venue"
},
  "geometry": {"coordinates":[-122.269595,37.806873],"type":"Point"}
}