{
  "type": "Feature",
  "properties": {
    "iso:country":"US",
    "sg:address":"7170 Broadway",
    "sg:city":"Lemon Grove",
    "sg:classifiers":[
        {
            "category":"Building & Trades",
            "subcategory":"Cleaning & Sanitation",
            "type":"Services"
        }
    ],
    "sg:phone":"+1 619 750 5190",
    "sg:postcode":"91945",
    "sg:province":"CA",
    "sg:tags":[
        "janitor"
    ],
    "wof:name":"Elegance Janitorial Svc",
    "wof:placetype":"venue"
},
  "geometry": {"coordinates":[-117.04540900000001,32.742582],"type":"Point"}
}