{
  "type": "Feature",
  "properties": {
    "addr:full":"16th St & Noe San Francisco CA 94114",
    "addr:postcode":"94114",
    "addr:street":"16Th St &",
    "iso:country":"US",
    "sg:address":"16th St & Noe",
    "sg:city":"San Francisco",
    "sg:classifiers":[
        {
            "category":"Sports & Exercise",
            "subcategory":"Gym",
            "type":"Entertainment"
        },
        {
            "category":"Health Services",
            "subcategory":"Health Practitioner",
            "type":"Services"
        }
    ],
    "sg:phone":"+1 415 286 4777",
    "sg:postcode":"94114",
    "sg:province":"CA",
    "sg:tags":[
        "trainer",
        "therapy",
        "physical"
    ],
    "wof:name":"Results Fitness",
    "wof:placetype":"venue"
},
  "geometry": {"coordinates":[-122.433106,37.764243],"type":"Point"}
}