{
  "type": "Feature",
  "properties": {
    "iso:country":"US",
    "sg:address":"953 W Owens Ave",
    "sg:city":"Tulare",
    "sg:classifiers":[
        {
            "category":"Building & Trades",
            "subcategory":"Construction",
            "type":"Services"
        }
    ],
    "sg:phone":"+1 559 686 4279",
    "sg:postcode":"93274",
    "sg:province":"CA",
    "sg:tags":[
        "restoration",
        "cleaning",
        "patio",
        "deck"
    ],
    "wof:name":"J R's Mobile Wash",
    "wof:placetype":"venue"
},
  "geometry": {"coordinates":[-119.36088700000001,36.202086],"type":"Point"}
}