{
  "type": "Feature",
  "properties": {
    "addr:full":"6112 S St Andrews Pl Los Angeles CA 90047",
    "addr:housenumber":"6112",
    "addr:postcode":"90047",
    "addr:street":"S St;Pl",
    "iso:country":"US",
    "sg:address":"6112 S St Andrews Pl",
    "sg:city":"Los Angeles",
    "sg:classifiers":[
        {
            "category":"Building & Trades",
            "subcategory":"Construction",
            "type":"Services"
        }
    ],
    "sg:phone":"+1 323 733 0455",
    "sg:postcode":"90047",
    "sg:province":"CA",
    "sg:tags":[
        "contractor"
    ],
    "wof:name":"Professional Ironworks",
    "wof:placetype":"venue"
},
  "geometry": {"coordinates":[-118.31092,33.983903],"type":"Point"}
}