{
  "type": "Feature",
  "properties": {
    "iso:country":"US",
    "sg:address":"331 W Olive Street",
    "sg:city":"Inglewood",
    "sg:classifiers":[
        {
            "category":"Education",
            "subcategory":"School",
            "type":"Public Place"
        }
    ],
    "sg:phone":"+1 310 680 5420",
    "sg:postcode":"90301",
    "sg:province":"CA",
    "sg:tags":[
        "high",
        "middle",
        "elementary"
    ],
    "wof:name":"Inglewood Unified School District",
    "wof:placetype":"venue"
},
  "geometry": {"coordinates":[-118.360325,33.960275],"type":"Point"}
}