{
  "type": "Feature",
  "properties": {
    "addr:full":"535 Stanford Ave Los Angeles CA 90013",
    "addr:housenumber":"535",
    "addr:postcode":"90013",
    "addr:street":"Stanford Ave",
    "iso:country":"US",
    "sg:address":"535 Stanford Ave",
    "sg:city":"Los Angeles",
    "sg:classifiers":[
        {
            "category":"Wholesale",
            "subcategory":"Seafood",
            "type":"Manufacturing & Wholesale Goods"
        }
    ],
    "sg:phone":"+1 213 896 0357",
    "sg:postcode":"90013",
    "sg:province":"CA",
    "wof:name":"Harbor Marine Products Inc",
    "wof:placetype":"venue"
},
  "geometry": {"coordinates":[-118.242424,34.041426],"type":"Point"}
}