{
  "type": "Feature",
  "properties": {
    "addr:full":"685 Kings Row Unit D San Jose CA 95190",
    "addr:housenumber":"685;unit d",
    "addr:postcode":"95190",
    "addr:street":"Kings",
    "iso:country":"US",
    "sg:address":"685 Kings Row Unit D",
    "sg:city":"San Jose",
    "sg:classifiers":[
        {
            "category":"Building & Trades",
            "subcategory":"Construction",
            "type":"Services"
        }
    ],
    "sg:phone":"+1 408 422 7940",
    "sg:postcode":"95190",
    "sg:province":"CA",
    "sg:tags":[
        "interior",
        "design",
        "contractor"
    ],
    "sg:website":"www.fernandezbrothers.com",
    "wof:name":"Fernandez Brothers Cabinets",
    "wof:placetype":"venue"
},
  "geometry": {"coordinates":[-121.899472,37.372661],"type":"Point"}
}