{
  "type": "Feature",
  "properties": {
    "addr:full":"6014 Clark Rd Paradise CA 95969",
    "addr:housenumber":"6014",
    "addr:postcode":"95969",
    "addr:street":"Clark Rd",
    "iso:country":"US",
    "sg:address":"6014 Clark Rd",
    "sg:city":"Paradise",
    "sg:classifiers":[
        {
            "category":"Banks & Credit Unions",
            "subcategory":"Investment Brokerage",
            "type":"Services"
        }
    ],
    "sg:phone":"+1 530 872 7000",
    "sg:postcode":"95969",
    "sg:province":"CA",
    "sg:tags":[
        "stock",
        "bond"
    ],
    "wof:name":"Edward Jones Co",
    "wof:placetype":"venue"
},
  "geometry": {"coordinates":[-121.605881,39.760615],"type":"Point"}
}