{
  "type": "Feature",
  "properties": {
    "iso:country":"US",
    "sg:address":"9019 Park Plaza Dr",
    "sg:city":"La Mesa",
    "sg:classifiers":[
        {
            "category":"Professional",
            "type":"Services"
        }
    ],
    "sg:phone":"+1 619 433 4001",
    "sg:postcode":"91942",
    "sg:province":"CA",
    "wof:name":"Mbyft Inc",
    "wof:placetype":"venue"
},
  "geometry": {"coordinates":[-117.002825,32.791835],"type":"Point"}
}