{
  "type": "Feature",
  "properties": {
    "iso:country":"US",
    "sg:address":"41109 Sandalwood Cir",
    "sg:city":"Murrieta",
    "sg:classifiers":[
        {
            "category":"Retail",
            "subcategory":"Auto Repair",
            "type":"Services"
        }
    ],
    "sg:phone":"+1 951 506 1302",
    "sg:postcode":"92562",
    "sg:province":"CA",
    "sg:tags":[
        "repairing",
        "automobile"
    ],
    "wof:name":"Dick's Diversified Auto Svc",
    "wof:placetype":"venue"
},
  "geometry": {"coordinates":[-117.173587,33.534286],"type":"Point"}
}