{
  "type": "Feature",
  "properties": {
    "addr:full":"12099 W Washington Blvd Los Angeles CA 90066",
    "addr:housenumber":"12099",
    "addr:postcode":"90066",
    "addr:street":"W Washington Blvd",
    "iso:country":"US",
    "sg:address":"12099 W Washington Blvd",
    "sg:city":"Los Angeles",
    "sg:classifiers":[
        {
            "category":"Health Services",
            "subcategory":"Health Practitioner",
            "type":"Services"
        },
        {
            "category":"Health Services",
            "subcategory":"Chiropractor",
            "type":"Services"
        }
    ],
    "sg:phone":"+1 310 390 9018",
    "sg:postcode":"90066",
    "sg:province":"CA",
    "sg:tags":[
        "nutritionist"
    ],
    "wof:name":"Luther Kenneth Dr",
    "wof:placetype":"venue"
},
  "geometry": {"coordinates":[-118.42435,33.997445],"type":"Point"}
}