{
  "type": "Feature",
  "properties": {
    "iso:country":"US",
    "sg:address":"16601 Ventura Blvd",
    "sg:city":"Encino",
    "sg:classifiers":[
        {
            "category":"Professional",
            "subcategory":"Lawyer & Legal Services",
            "type":"Services"
        }
    ],
    "sg:phone":"+1 818 783 9300",
    "sg:postcode":"91436",
    "sg:province":"CA",
    "sg:tags":[
        "attorney"
    ],
    "sg:website":"www.theofanislaw.com",
    "wof:name":"Theofanis Davidson",
    "wof:placetype":"venue"
},
  "geometry": {"coordinates":[-118.49605,34.1581],"type":"Point"}
}