{
  "type": "Feature",
  "properties": {
    "iso:country":"US",
    "sg:address":"9255 W Sunset Blvd Ste 720",
    "sg:city":"Los Angeles",
    "sg:classifiers":[
        {
            "category":"Professional",
            "subcategory":"Lawyer & Legal Services",
            "type":"Services"
        }
    ],
    "sg:phone":"+1 310 273 9501",
    "sg:postcode":"90069",
    "sg:province":"CA",
    "sg:website":"www.topgundui.com",
    "wof:name":"Berman Myles L Law Offices of",
    "wof:placetype":"venue"
},
  "geometry": {"coordinates":[-118.393827,34.0902],"type":"Point"}
}