{
  "type": "Feature",
  "properties": {
    "addr:full":"9450 7th St Rancho Cucamonga CA 91730",
    "addr:housenumber":"9450",
    "addr:postcode":"91730",
    "addr:street":"7Th St",
    "iso:country":"US",
    "sg:address":"9450 7th St",
    "sg:city":"Rancho Cucamonga",
    "sg:classifiers":[
        {
            "category":"Wholesale",
            "subcategory":"Hardware",
            "type":"Manufacturing & Wholesale Goods"
        }
    ],
    "sg:phone":"+1 909 481 7331",
    "sg:postcode":"91730",
    "sg:province":"CA",
    "wof:name":"Star Hardware Inc",
    "wof:placetype":"venue"
},
  "geometry": {"coordinates":[-117.600009,34.088508],"type":"Point"}
}