{
  "type": "Feature",
  "properties": {
    "addr:full":"6323 Nancy Ridge Dr San Diego CA 92121",
    "addr:housenumber":"6323",
    "addr:postcode":"92121",
    "addr:street":"Nancy Ridge Dr",
    "iso:country":"US",
    "sg:address":"6323 Nancy Ridge Dr",
    "sg:city":"San Diego",
    "sg:classifiers":[
        {
            "category":"Shopping",
            "subcategory":"Gifts & Souvenirs",
            "type":"Retail Goods"
        }
    ],
    "sg:phone":"+1 858 693 3344",
    "sg:postcode":"92121",
    "sg:province":"CA",
    "sg:tags":[
        "party",
        "supply"
    ],
    "wof:name":"Exclamations Party Favors",
    "wof:placetype":"venue"
},
  "geometry": {"coordinates":[-117.187062,32.88876],"type":"Point"}
}