{
  "type": "Feature",
  "properties": {
    "addr:full":"2300 E Main St Barstow CA 92311",
    "addr:housenumber":"2300",
    "addr:postcode":"92311",
    "addr:street":"E Main St",
    "iso:country":"US",
    "sg:address":"2300 E Main St",
    "sg:city":"Barstow",
    "sg:classifiers":[
        {
            "category":"Autos & Motor Vehicles",
            "subcategory":"Automobile Sales",
            "type":"Retail Goods"
        }
    ],
    "sg:phone":"+1 760 252 7237",
    "sg:postcode":"92311",
    "sg:province":"CA",
    "sg:tags":[
        "car",
        "dealer"
    ],
    "wof:name":"Mirage Motor Sports",
    "wof:placetype":"venue"
},
  "geometry": {"coordinates":[-116.993748,34.885434],"type":"Point"}
}