{
  "type": "Feature",
  "properties": {
    "addr:full":"100 Hegenberger Rd Oakland CA 94621",
    "addr:housenumber":"100",
    "addr:postcode":"94621",
    "addr:street":"Hegenberger Rd",
    "iso:country":"US",
    "sg:address":"100 Hegenberger Rd",
    "sg:city":"Oakland",
    "sg:classifiers":[
        {
            "category":"Professional",
            "subcategory":"Detective & Security Services",
            "type":"Services"
        }
    ],
    "sg:phone":"+1 510 562 7606",
    "sg:postcode":"94621",
    "sg:province":"CA",
    "sg:tags":[
        "car"
    ],
    "wof:name":"Guardsmark Llc",
    "wof:placetype":"venue"
},
  "geometry": {"coordinates":[-122.19887799999999,37.731028],"type":"Point"}
}