{
  "type": "Feature",
  "properties": {
    "iso:country":"US",
    "sg:address":"2390 Redlands Dr",
    "sg:city":"Newport Beach",
    "sg:classifiers":[
        {
            "category":"Professional",
            "subcategory":"Art Services",
            "type":"Services"
        }
    ],
    "sg:phone":"+1 949 645 5382",
    "sg:postcode":"92660",
    "sg:province":"CA",
    "sg:tags":[
        "photographer"
    ],
    "sg:website":"www.jennifergilmore.com",
    "wof:name":"Jennifer Gilmore Photography",
    "wof:placetype":"venue"
},
  "geometry": {"coordinates":[-117.89439,33.650543],"type":"Point"}
}