{
  "type": "Feature",
  "properties": {
    "iso:country":"US",
    "sg:address":"2415 High School Ave",
    "sg:city":"Concord",
    "sg:classifiers":[
        {
            "category":"Health Services",
            "subcategory":"Doctor",
            "type":"Services"
        }
    ],
    "sg:phone":"+1 925 687 9650",
    "sg:postcode":"94520",
    "sg:province":"CA",
    "sg:tags":[
        "physician",
        "surgeon"
    ],
    "wof:name":"Gastroenterology Medical Group",
    "wof:placetype":"venue"
},
  "geometry": {"coordinates":[-122.034586,37.98492],"type":"Point"}
}