{
  "type": "Feature",
  "properties": {
    "iso:country":"US",
    "sg:address":"642 Plumas St",
    "sg:city":"Yuba City",
    "sg:classifiers":[
        {
            "category":"Shopping",
            "type":"Retail Goods"
        }
    ],
    "sg:phone":"+1 530 751 0433",
    "sg:postcode":"95991",
    "sg:province":"CA",
    "sg:tags":[
        "art",
        "gallery",
        "dealer"
    ],
    "wof:name":"Visions Gallery",
    "wof:placetype":"venue"
},
  "geometry": {"coordinates":[-121.615937,39.136585],"type":"Point"}
}