{
  "type": "Feature",
  "properties": {
    "addr:full":"4621 Hillard Ave La Canada Fltrdg CA 91011",
    "addr:housenumber":"4621",
    "addr:postcode":"91011",
    "addr:street":"Hillard Ave La",
    "iso:country":"US",
    "sg:address":"4621 Hillard Ave",
    "sg:city":"La Canada Fltrdg",
    "sg:classifiers":[
        {
            "category":"Education",
            "subcategory":"Special Training",
            "type":"Public Place"
        }
    ],
    "sg:phone":"+1 818 952 0272",
    "sg:postcode":"91011",
    "sg:province":"CA",
    "sg:tags":[
        "instruction",
        "music"
    ],
    "wof:name":"Elizabeth Jones Education Svc",
    "wof:placetype":"venue"
},
  "geometry": {"coordinates":[-118.215493,34.214005],"type":"Point"}
}