{
  "type": "Feature",
  "properties": {
    "addr:full":"1233 W Memory Ln Santa Ana CA 92706",
    "addr:housenumber":"1233",
    "addr:postcode":"92706",
    "addr:street":"W Memory Ln",
    "iso:country":"US",
    "sg:address":"1233 W Memory Ln",
    "sg:city":"Santa Ana",
    "sg:classifiers":[
        {
            "category":"Shopping",
            "subcategory":"Florist",
            "type":"Retail Goods"
        }
    ],
    "sg:phone":"+1 714 541 9304",
    "sg:postcode":"92706",
    "sg:province":"CA",
    "wof:name":"Fiesta Florist",
    "wof:placetype":"venue"
},
  "geometry": {"coordinates":[-117.88400300000001,33.772999],"type":"Point"}
}