{
  "type": "Feature",
  "properties": {
    "addr:full":"13351 Marty Ln Garden Grove CA 92843",
    "addr:housenumber":"13351",
    "addr:postcode":"92843",
    "addr:street":"Marty Ln",
    "iso:country":"US",
    "sg:address":"13351 Marty Ln",
    "sg:city":"Garden Grove",
    "sg:classifiers":[
        {
            "category":"Wholesale",
            "subcategory":"Machinery & Supplies",
            "type":"Manufacturing & Wholesale Goods"
        }
    ],
    "sg:phone":"+1 714 740 2061",
    "sg:postcode":"92843",
    "sg:province":"CA",
    "sg:tags":[
        "equipment",
        "printing"
    ],
    "wof:name":"24 Hr Svc",
    "wof:placetype":"venue"
},
  "geometry": {"coordinates":[-117.895743,33.769463],"type":"Point"}
}