{
  "type": "Feature",
  "properties": {
    "addr:full":"24 San Carlos Ave El Cerrito CA 94530",
    "addr:housenumber":"24",
    "addr:postcode":"94530",
    "addr:street":"San Carlos Ave",
    "iso:country":"US",
    "sg:address":"24 San Carlos Ave",
    "sg:city":"El Cerrito",
    "sg:classifiers":[
        {
            "category":"Organizations",
            "subcategory":"Religious Organization",
            "type":"Services"
        }
    ],
    "sg:phone":"+1 510 524 1540",
    "sg:postcode":"94530",
    "sg:province":"CA",
    "wof:name":"Home Of The Buddhas",
    "wof:placetype":"venue"
},
  "geometry": {"coordinates":[-122.288901,37.898339],"type":"Point"}
}