{
  "type": "Feature",
  "properties": {
    "iso:country":"US",
    "sg:address":"409 Cambridge Ave",
    "sg:city":"Palo Alto",
    "sg:classifiers":[
        {
            "category":"Health Services",
            "subcategory":"Doctor",
            "type":"Services"
        }
    ],
    "sg:phone":"+1 650 326 6319",
    "sg:postcode":"94306",
    "sg:province":"CA",
    "sg:tags":[
        "dentist"
    ],
    "wof:name":"Kris S Hamamoto DDS",
    "wof:placetype":"venue"
},
  "geometry": {"coordinates":[-122.145309,37.42725],"type":"Point"}
}