{
  "type": "Feature",
  "properties": {
    "addr:full":"444 Banning Way Vallejo CA 94591",
    "addr:housenumber":"444",
    "addr:postcode":"94591",
    "addr:street":"Banning Way",
    "iso:country":"US",
    "sg:address":"444 Banning Way",
    "sg:city":"Vallejo",
    "sg:classifiers":[
        {
            "category":"Building & Trades",
            "subcategory":"Construction",
            "type":"Services"
        }
    ],
    "sg:phone":"+1 707 427 8000",
    "sg:postcode":"94591",
    "sg:province":"CA",
    "sg:tags":[
        "roofing",
        "industrial",
        "contractors-commercial",
        "contractor"
    ],
    "wof:name":"Price Is Right Roofing & Construction",
    "wof:placetype":"venue"
},
  "geometry": {"coordinates":[-122.215062,38.09316],"type":"Point"}
}