{
  "type": "Feature",
  "properties": {
    "addr:full":"5411 Tyrone Ave Ste 301 Van Nuys CA 91401",
    "addr:housenumber":"5411",
    "addr:postcode":"91401",
    "addr:street":"Tyrone Ave Ste 301",
    "iso:country":"US",
    "sg:address":"5411 Tyrone Ave Ste 301",
    "sg:city":"Van Nuys",
    "sg:classifiers":[
        {
            "category":"Home & Garden",
            "subcategory":"Household Appliances",
            "type":"Retail Goods"
        }
    ],
    "sg:phone":"+1 877 228 8092",
    "sg:postcode":"91401",
    "sg:province":"CA",
    "sg:tags":[
        "repair"
    ],
    "sg:website":"www.LermanAppliances.com",
    "wof:name":"Lerman Appliances",
    "wof:placetype":"venue"
},
  "geometry": {"coordinates":[-118.44463,34.169031],"type":"Point"}
}