{
  "type": "Feature",
  "properties": {
    "addr:full":"10970 Venice Blvd Los Angeles CA 90034",
    "addr:housenumber":"10970",
    "addr:postcode":"90034",
    "addr:street":"Venice Blvd",
    "iso:country":"US",
    "sg:address":"10970 Venice Blvd",
    "sg:city":"Los Angeles",
    "sg:classifiers":[
        {
            "category":"Autos & Motor Vehicles",
            "subcategory":"Automobile Sales",
            "type":"Retail Goods"
        },
        {
            "category":"Taxi",
            "type":"Transportation"
        }
    ],
    "sg:phone":"+1 310 666 6289",
    "sg:postcode":"90034",
    "sg:province":"CA",
    "sg:tags":[
        "limo"
    ],
    "sg:website":"www.blueangelslimo.com",
    "wof:name":"Blue Angels Limo Service",
    "wof:placetype":"venue"
},
  "geometry": {"coordinates":[-118.41365500000001,34.014805],"type":"Point"}
}