{
  "type": "Feature",
  "properties": {
    "iso:country":"US",
    "sg:address":"601 Morey Ave",
    "sg:city":"Sacramento",
    "sg:classifiers":[
        {
            "category":"Organizations",
            "subcategory":"Religious Organization",
            "type":"Services"
        }
    ],
    "sg:phone":"+1 916 924 7057",
    "sg:postcode":"95838",
    "sg:province":"CA",
    "sg:tags":[
        "church"
    ],
    "wof:name":"First Samoan Assembly Of God",
    "wof:placetype":"venue"
},
  "geometry": {"coordinates":[-121.450281,38.634755],"type":"Point"}
}