{
  "type": "Feature",
  "properties": {
    "iso:country":"US",
    "sg:address":"64 Fairbanks",
    "sg:city":"Irvine",
    "sg:classifiers":[
        {
            "category":"Wholesale",
            "subcategory":"Machinery & Supplies",
            "type":"Manufacturing & Wholesale Goods"
        }
    ],
    "sg:phone":"+1 949 837 1290",
    "sg:postcode":"92618",
    "sg:province":"CA",
    "sg:tags":[
        "equipment",
        "establishment"
    ],
    "wof:name":"Essential Product Distributor",
    "wof:placetype":"venue"
},
  "geometry": {"coordinates":[-117.711432,33.660511],"type":"Point"}
}