{
  "type": "Feature",
  "properties": {
    "addr:full":"2601 Airport Drive Suite 380 Torrance CA 90505 ",
    "addr:housenumber":"2601",
    "addr:postcode":"90505",
    "addr:street":"Airport Drive Suite 380",
    "iso:country":"US",
    "sg:address":"2601 Airport Drive Suite 380",
    "sg:city":"Torrance",
    "sg:classifiers":[
        {
            "category":"Professional",
            "subcategory":"Computer Services",
            "type":"Services"
        }
    ],
    "sg:phone":"+1 310 602 4010",
    "sg:postcode":"90505 ",
    "sg:province":"CA",
    "sg:website":"http://www.bqe.com",
    "wof:name":"BQE Software",
    "wof:placetype":"venue"
},
  "geometry": {"coordinates":[-118.32943,33.792395],"type":"Point"}
}