{
  "type": "Feature",
  "properties": {
    "addr:full":"10937 Venice Blvd Los Angeles CA 90034",
    "addr:housenumber":"10937",
    "addr:postcode":"90034",
    "addr:street":"Venice Blvd",
    "iso:country":"US",
    "sg:address":"10937 Venice Blvd",
    "sg:city":"Los Angeles",
    "sg:classifiers":[
        {
            "category":"Freight",
            "type":"Transportation"
        }
    ],
    "sg:phone":"+1 310 842 7875",
    "sg:postcode":"90034",
    "sg:province":"CA",
    "sg:tags":[
        "operator",
        "local",
        "trucking"
    ],
    "wof:name":"Urgente Express",
    "wof:placetype":"venue"
},
  "geometry": {"coordinates":[-118.412584,34.015708],"type":"Point"}
}