{
  "type": "Feature",
  "properties": {
    "addr:full":"1505 Tennessee St Vallejo CA 94590",
    "addr:housenumber":"1505",
    "addr:postcode":"94590",
    "addr:street":"Tennessee St",
    "iso:country":"US",
    "sg:address":"1505 Tennessee St",
    "sg:city":"Vallejo",
    "sg:classifiers":[
        {
            "category":"Shopping",
            "subcategory":"Computers & Home Electronics",
            "type":"Retail Goods"
        }
    ],
    "sg:phone":"+1 707 554 0700",
    "sg:postcode":"94590",
    "sg:province":"CA",
    "sg:tags":[
        "equipment",
        "satellite",
        "system"
    ],
    "wof:name":"Go Wireless",
    "wof:placetype":"venue"
},
  "geometry": {"coordinates":[-122.23935,38.109709],"type":"Point"}
}