{
  "type": "Feature",
  "properties": {
    "addr:full":"1220 3rd Street Promenade Santa Monica CA 90401",
    "addr:housenumber":"1220",
    "addr:postcode":"90401",
    "addr:street":"3Rd Street Promenade",
    "iso:country":"US",
    "sg:address":"1220 3rd Street Promenade",
    "sg:city":"Santa Monica",
    "sg:classifiers":[
        {
            "category":"Shopping",
            "subcategory":"Department Store",
            "type":"Retail Goods"
        }
    ],
    "sg:phone":"+1 310 587 3525",
    "sg:postcode":"90401",
    "sg:province":"CA",
    "wof:name":"Von Dutch Originals",
    "wof:placetype":"venue"
},
  "geometry": {"coordinates":[-118.497975,34.01722],"type":"Point"}
}