{
  "type": "Feature",
  "properties": {
    "addr:full":"2150 E South St Long Beach CA 90805",
    "addr:housenumber":"2150 e",
    "addr:postcode":"90805",
    "addr:street":"South St",
    "iso:country":"US",
    "sg:address":"2150 E South St",
    "sg:city":"Long Beach",
    "sg:classifiers":[
        {
            "category":"Restaurant",
            "type":"Food & Drink"
        }
    ],
    "sg:phone":"+1 562 531 3838",
    "sg:postcode":"90805",
    "sg:province":"CA",
    "wof:name":"Golden Chinese Express",
    "wof:placetype":"venue"
},
  "geometry": {"coordinates":[-118.16562,33.860064],"type":"Point"}
}