{
  "type": "Feature",
  "properties": {
    "addr:full":"458 Vis Trucha Newport Beach CA 92660",
    "addr:housenumber":"458",
    "addr:postcode":"92660",
    "addr:street":"Vis Trucha",
    "iso:country":"US",
    "sg:address":"458 Vis Trucha",
    "sg:city":"Newport Beach",
    "sg:classifiers":[
        {
            "category":"Professional",
            "type":"Services"
        }
    ],
    "sg:phone":"+1 949 644 8634",
    "sg:postcode":"92660",
    "sg:province":"CA",
    "wof:name":"Can",
    "wof:placetype":"venue"
},
  "geometry": {"coordinates":[-117.876514,33.642316],"type":"Point"}
}