{
  "type": "Feature",
  "properties": {
    "addr:full":"125 N Tustin St Ste G Orange CA 92867",
    "addr:housenumber":"125",
    "addr:postcode":"92867",
    "addr:street":"N Tustin St Ste G",
    "iso:country":"US",
    "sg:address":"125 N Tustin St Ste G",
    "sg:city":"Orange",
    "sg:classifiers":[
        {
            "category":"Personal",
            "subcategory":"Tattoo Parlor",
            "type":"Services"
        },
        {
            "category":"Personal",
            "subcategory":"Piercing",
            "type":"Services"
        }
    ],
    "sg:phone":"+1 714 744 8288",
    "sg:postcode":"92867",
    "sg:province":"CA",
    "sg:website":"www.outerlimitstattoo.com/orange...",
    "wof:name":"Outer Limits Tattoo & Body Piercing",
    "wof:placetype":"venue"
},
  "geometry": {"coordinates":[-117.83573800000001,33.788355],"type":"Point"}
}