{
  "type": "Feature",
  "properties": {
    "iso:country":"US",
    "sg:address":"5945 Almaden Expy",
    "sg:city":"San Jose",
    "sg:classifiers":[
        {
            "category":"Personal",
            "subcategory":"Beauty Salon",
            "type":"Services"
        }
    ],
    "sg:phone":"+1 408 997 0362",
    "sg:postcode":"95120",
    "sg:province":"CA",
    "wof:name":"Kim Skeen",
    "wof:placetype":"venue"
},
  "geometry": {"coordinates":[-121.87280699999999,37.235332],"type":"Point"}
}