{
  "type": "Feature",
  "properties": {
    "iso:country":"US",
    "sg:address":"14548 Baseline Ave",
    "sg:city":"Fontana",
    "sg:classifiers":[
        {
            "category":"Shopping",
            "type":"Retail Goods"
        }
    ],
    "sg:phone":"+1 909 985 7243",
    "sg:postcode":"92336",
    "sg:province":"CA",
    "sg:tags":[
        "communication",
        "radiotelephone",
        "merchandise"
    ],
    "wof:name":"Foothill Cellular & Paging",
    "wof:placetype":"venue"
},
  "geometry": {"coordinates":[-117.48523299999999,34.121506],"type":"Point"}
}