{
  "type": "Feature",
  "properties": {
    "addr:full":"3625 Macarthur Blvd Oakland CA 94619",
    "addr:housenumber":"3625",
    "addr:postcode":"94619",
    "addr:street":"Macarthur Blvd",
    "iso:country":"US",
    "sg:address":"3625 Macarthur Blvd",
    "sg:city":"Oakland",
    "sg:classifiers":[
        {
            "category":"Social Services",
            "subcategory":"Child Care",
            "type":"Services"
        }
    ],
    "sg:phone":"+1 510 482 7507",
    "sg:postcode":"94619",
    "sg:province":"CA",
    "wof:name":"Color Me Children Preschool",
    "wof:placetype":"venue"
},
  "geometry": {"coordinates":[-122.199826,37.792746],"type":"Point"}
}