{
  "type": "Feature",
  "properties": {
    "addr:full":"5575 Hollister Ave Goleta CA 93117",
    "addr:housenumber":"5575",
    "addr:postcode":"93117",
    "addr:street":"Hollister Ave",
    "iso:country":"US",
    "sg:address":"5575 Hollister Ave",
    "sg:city":"Goleta",
    "sg:classifiers":[
        {
            "category":"Health Services",
            "subcategory":"Health Practitioner",
            "type":"Services"
        }
    ],
    "sg:phone":"+1 805 681 8708",
    "sg:postcode":"93117",
    "sg:province":"CA",
    "sg:tags":[
        "therapist",
        "physical"
    ],
    "wof:name":"S & P Physical Therapy",
    "wof:placetype":"venue"
},
  "geometry": {"coordinates":[-119.818397,34.435337],"type":"Point"}
}