{
  "type": "Feature",
  "properties": {
    "addr:full":"1014 Dwight Ave Half Moon Bay CA 94019",
    "addr:housenumber":"1014",
    "addr:postcode":"94019",
    "addr:street":"Dwight Ave",
    "iso:country":"US",
    "sg:address":"1014 Dwight Ave",
    "sg:city":"Half Moon Bay",
    "sg:classifiers":[
        {
            "category":"Restaurant",
            "type":"Food & Drink"
        }
    ],
    "sg:phone":"+1 650 726 0370",
    "sg:postcode":"94019",
    "sg:province":"CA",
    "sg:tags":[
        "caterer"
    ],
    "wof:name":"Diamen Catering",
    "wof:placetype":"venue"
},
  "geometry": {"coordinates":[-122.437224,37.475918],"type":"Point"}
}