{
  "type": "Feature",
  "properties": {
    "addr:full":"9453 Gierson Ave Chatsworth CA 91311",
    "addr:housenumber":"9453",
    "addr:postcode":"91311",
    "addr:street":"Gierson Ave",
    "iso:country":"US",
    "sg:address":"9453 Gierson Ave",
    "sg:city":"Chatsworth",
    "sg:classifiers":[
        {
            "category":"Health Services",
            "subcategory":"Doctor",
            "type":"Services"
        }
    ],
    "sg:phone":"+1 310 434 0040",
    "sg:postcode":"91311",
    "sg:province":"CA",
    "sg:tags":[
        "dentist"
    ],
    "wof:name":"David Rudolph DDS",
    "wof:placetype":"venue"
},
  "geometry": {"coordinates":[-118.61160700000001,34.242274],"type":"Point"}
}