{
  "type": "Feature",
  "properties": {
    "iso:country":"US",
    "sg:address":"26580 Ynez Rd",
    "sg:city":"Temecula",
    "sg:classifiers":[
        {
            "category":"Restaurant",
            "type":"Food & Drink"
        }
    ],
    "sg:menulink":"http://www.allmenus.com/ca/murrieta/163919-togos-eatery/menu/",
    "sg:phone":"+1 951 296 0432",
    "sg:postcode":"92591",
    "sg:province":"CA",
    "sg:tags":[
        "wrap",
        "american",
        "sandwich"
    ],
    "wof:name":"Togo's Eatery",
    "wof:placetype":"venue"
},
  "geometry": {"coordinates":[-117.15648899999999,33.520425],"type":"Point"}
}