{
  "type": "Feature",
  "properties": {
    "addr:full":"2111 W Crescent Ave Anaheim CA 92801",
    "addr:housenumber":"2111",
    "addr:postcode":"92801",
    "addr:street":"W Crescent Ave",
    "iso:country":"US",
    "sg:address":"2111 W Crescent Ave",
    "sg:city":"Anaheim",
    "sg:classifiers":[
        {
            "category":"Wholesale",
            "subcategory":"Home Furnishings",
            "type":"Manufacturing & Wholesale Goods"
        }
    ],
    "sg:phone":"+1 714 633 6073",
    "sg:postcode":"92801",
    "sg:province":"CA",
    "wof:name":"Budget Blinds of Orange",
    "wof:placetype":"venue"
},
  "geometry": {"coordinates":[-117.955473,33.839835],"type":"Point"}
}