{
  "type": "Feature",
  "properties": {
    "addr:full":"842 N Central Ave Campbell CA 95008",
    "addr:housenumber":"842",
    "addr:postcode":"95008",
    "addr:street":"N Central Ave",
    "iso:country":"US",
    "sg:address":"842 N Central Ave",
    "sg:city":"Campbell",
    "sg:classifiers":[
        {
            "category":"Shopping",
            "subcategory":"Hobbies, Toys, & Games",
            "type":"Retail Goods"
        }
    ],
    "sg:phone":"+1 408 374 6080",
    "sg:postcode":"95008",
    "sg:province":"CA",
    "wof:name":"Raindrop Entertainment",
    "wof:placetype":"venue"
},
  "geometry": {"coordinates":[-121.943479,37.301365],"type":"Point"}
}