{
  "type": "Feature",
  "properties": {
    "addr:full":"1000 Main St Chico CA 95928",
    "addr:housenumber":"1000",
    "addr:postcode":"95928",
    "addr:street":"Main St",
    "iso:country":"US",
    "sg:address":"1000 Main St",
    "sg:city":"Chico",
    "sg:classifiers":[
        {
            "category":"Retail",
            "subcategory":"Laundry & Dry Cleaning",
            "type":"Services"
        }
    ],
    "sg:phone":"+1 530 342 1883",
    "sg:postcode":"95928",
    "sg:province":"CA",
    "sg:tags":[
        "cleaners"
    ],
    "wof:name":"Lobdell Cleaners",
    "wof:placetype":"venue"
},
  "geometry": {"coordinates":[-121.83391399999999,39.725082],"type":"Point"}
}