{
  "type": "Feature",
  "properties": {
    "addr:full":"5400 Winchester Ct Merced CA 95301",
    "addr:housenumber":"5400",
    "addr:postcode":"95301",
    "addr:street":"Winchester Ct",
    "iso:country":"US",
    "sg:address":"5400 Winchester Ct",
    "sg:city":"Merced",
    "sg:classifiers":[
        {
            "category":"Professional",
            "subcategory":"Business Services",
            "type":"Services"
        }
    ],
    "sg:phone":"+1 209 357 2444",
    "sg:postcode":"95301",
    "sg:province":"CA",
    "sg:tags":[
        "interior",
        "consultant",
        "design",
        "decorator"
    ],
    "wof:name":"Sherry Ketner Interior Design",
    "wof:placetype":"venue"
},
  "geometry": {"coordinates":[-120.585953,37.311154],"type":"Point"}
}