{
  "type": "Feature",
  "properties": {
    "addr:full":"667 Walnut St San Jose CA 95110",
    "addr:housenumber":"667",
    "addr:postcode":"95110",
    "addr:street":"Walnut St",
    "iso:country":"US",
    "sg:address":"667 Walnut St",
    "sg:city":"San Jose",
    "sg:classifiers":[
        {
            "category":"Home & Garden",
            "subcategory":"Building Materials",
            "type":"Retail Goods"
        }
    ],
    "sg:phone":"+1 408 292 8111",
    "sg:postcode":"95110",
    "sg:province":"CA",
    "sg:tags":[
        "door"
    ],
    "wof:name":"Industrial Door Svc Inc",
    "wof:placetype":"venue"
},
  "geometry": {"coordinates":[-121.909398,37.342783],"type":"Point"}
}