{
  "type": "Feature",
  "properties": {
    "addr:full":"14 Sudbury Pl Laguna Niguel CA 92677",
    "addr:housenumber":"14",
    "addr:postcode":"92677",
    "addr:street":"Sudbury Pl",
    "iso:country":"US",
    "sg:address":"14 Sudbury Pl",
    "sg:city":"Laguna Niguel",
    "sg:classifiers":[
        {
            "category":"Professional",
            "type":"Services"
        }
    ],
    "sg:phone":"+1 949 872 7446",
    "sg:postcode":"92677",
    "sg:province":"CA",
    "wof:name":"South Orange County Mobile Not",
    "wof:placetype":"venue"
},
  "geometry": {"coordinates":[-117.70715300000001,33.499929],"type":"Point"}
}