{
  "type": "Feature",
  "properties": {
    "addr:full":"7930 Florence Ave Downey CA 90240",
    "addr:housenumber":"7930",
    "addr:postcode":"90240",
    "addr:street":"Florence Ave",
    "iso:country":"US",
    "sg:address":"7930 Florence Ave",
    "sg:city":"Downey",
    "sg:classifiers":[
        {
            "category":"Fast Food",
            "type":"Food & Drink"
        },
        {
            "category":"Food & Beverages",
            "subcategory":"Bakery",
            "type":"Retail Goods"
        }
    ],
    "sg:phone":"+1 562 806 8399",
    "sg:postcode":"90240",
    "sg:province":"CA",
    "sg:tags":[
        "sandwich"
    ],
    "sg:website":"www.subway.com",
    "wof:name":"Subway",
    "wof:placetype":"venue"
},
  "geometry": {"coordinates":[-118.130661,33.953883],"type":"Point"}
}