{
  "type": "Feature",
  "properties": {
    "addr:full":"555 E Hardy St Inglewood CA 90301",
    "addr:housenumber":"555",
    "addr:postcode":"90301",
    "addr:street":"E Hardy St",
    "iso:country":"US",
    "sg:address":"555 E Hardy St",
    "sg:city":"Inglewood",
    "sg:classifiers":[
        {
            "category":"Professional",
            "subcategory":"Research",
            "type":"Services"
        }
    ],
    "sg:phone":"+1 310 673 2299",
    "sg:postcode":"90301",
    "sg:province":"CA",
    "sg:tags":[
        "development",
        "laboratory"
    ],
    "wof:name":"Centinela Biomechanical Labs",
    "wof:placetype":"venue"
},
  "geometry": {"coordinates":[-118.348191,33.949166],"type":"Point"}
}