{
  "type": "Feature",
  "properties": {
    "iso:country":"US",
    "sg:address":"42 S Plano St",
    "sg:city":"Porterville",
    "sg:classifiers":[
        {
            "category":"Arts & Performance",
            "subcategory":"Theater",
            "type":"Entertainment"
        }
    ],
    "sg:phone":"+1 559 781 7177",
    "sg:postcode":"93257",
    "sg:province":"CA",
    "wof:name":"Barn Theater",
    "wof:placetype":"venue"
},
  "geometry": {"coordinates":[-119.008008,36.063708],"type":"Point"}
}