{
  "type": "Feature",
  "properties": {
    "addr:full":"1888 S Pacific Coast Hwy Redondo Beach CA 90277",
    "addr:housenumber":"1888",
    "addr:postcode":"90277",
    "addr:street":"S Pacific Coast Hwy",
    "iso:country":"US",
    "sg:address":"1888 S Pacific Coast Hwy",
    "sg:city":"Redondo Beach",
    "sg:classifiers":[
        {
            "category":"Restaurant",
            "type":"Food & Drink"
        }
    ],
    "sg:menulink":"http://www.allmenus.com/ca/south-bay-cities/150234-subway/menu/",
    "sg:phone":"+1 310 540 7821",
    "sg:postcode":"90277",
    "sg:province":"CA",
    "sg:tags":[
        "american",
        "sandwich"
    ],
    "wof:name":"Subway",
    "wof:placetype":"venue"
},
  "geometry": {"coordinates":[-118.37738,33.816065],"type":"Point"}
}