{
  "type": "Feature",
  "properties": {
    "addr:full":"12626 Riverside Dr North Hollywood CA 91607",
    "addr:housenumber":"12626",
    "addr:postcode":"91607",
    "addr:street":"Riverside Dr",
    "iso:country":"US",
    "sg:address":"12626 Riverside Dr",
    "sg:city":"North Hollywood",
    "sg:classifiers":[
        {
            "category":"Health Services",
            "subcategory":"Doctor",
            "type":"Services"
        }
    ],
    "sg:phone":"+1 818 980 7076",
    "sg:postcode":"91607",
    "sg:province":"CA",
    "sg:tags":[
        "physician",
        "surgeon"
    ],
    "wof:name":"Mid-Valley Pulmonary Medical",
    "wof:placetype":"venue"
},
  "geometry": {"coordinates":[-118.407759,34.157542],"type":"Point"}
}