{
  "type": "Feature",
  "properties": {
    "addr:full":"1528 Versailles Ave Alameda CA 94501",
    "addr:housenumber":"1528",
    "addr:postcode":"94501",
    "addr:street":"Versailles Ave",
    "iso:country":"US",
    "sg:address":"1528 Versailles Ave",
    "sg:city":"Alameda",
    "sg:classifiers":[
        {
            "category":"Real Estate",
            "subcategory":"Architect",
            "type":"Services"
        }
    ],
    "sg:phone":"+1 510 865 4213",
    "sg:postcode":"94501",
    "sg:province":"CA",
    "sg:tags":[
        "architects'",
        "specification",
        "builders'",
        "construction",
        "architectural",
        "engineer"
    ],
    "sg:website":"http://www.michaelhartigan.com",
    "wof:name":"Micahel Hartigan Aia Architect",
    "wof:placetype":"venue"
},
  "geometry": {"coordinates":[-122.235761,37.762446],"type":"Point"}
}