{
  "type": "Feature",
  "properties": {
    "iso:country":"US",
    "sg:address":"3027 Dalen Pl",
    "sg:city":"San Diego",
    "sg:classifiers":[
        {
            "category":"Real Estate",
            "subcategory":"Real Estate Agent",
            "type":"Services"
        }
    ],
    "sg:phone":"+1 858 558 4488",
    "sg:postcode":"92122",
    "sg:province":"CA",
    "sg:tags":[
        "consultant"
    ],
    "wof:name":"Goodwin & Assoc Hospitality",
    "wof:placetype":"venue"
},
  "geometry": {"coordinates":[-117.221527,32.843492],"type":"Point"}
}