{
  "type": "Feature",
  "properties": {
    "addr:full":"2739 S Robertson Blvd Los Angeles CA 90034",
    "addr:housenumber":"2739",
    "addr:postcode":"90034",
    "addr:street":"S Robertson Blvd",
    "iso:country":"US",
    "sg:address":"2739 S Robertson Blvd",
    "sg:city":"Los Angeles",
    "sg:classifiers":[
        {
            "category":"Shopping",
            "subcategory":"Used Merchandise",
            "type":"Retail Goods"
        }
    ],
    "sg:phone":"+1 310 826 1170",
    "sg:postcode":"90034",
    "sg:province":"CA",
    "wof:name":"Antiques Plus",
    "wof:placetype":"venue"
},
  "geometry": {"coordinates":[-118.388856,34.036883],"type":"Point"}
}