{
  "type": "Feature",
  "properties": {
    "addr:full":"1806 S Myrtle Ave Monrovia CA 91016",
    "addr:housenumber":"1806",
    "addr:postcode":"91016",
    "addr:street":"S Myrtle Ave",
    "iso:country":"US",
    "sg:address":"1806 S Myrtle Ave",
    "sg:city":"Monrovia",
    "sg:classifiers":[
        {
            "category":"Wholesale",
            "subcategory":"Apparel",
            "type":"Manufacturing & Wholesale Goods"
        }
    ],
    "sg:phone":"+1 626 256 4190",
    "sg:postcode":"91016",
    "sg:province":"CA",
    "sg:tags":[
        "infant",
        "wear"
    ],
    "wof:name":"RSDG",
    "wof:placetype":"venue"
},
  "geometry": {"coordinates":[-118.001169,34.130538],"type":"Point"}
}