{
  "type": "Feature",
  "properties": {
    "iso:country":"US",
    "sg:address":"8401 S Gate Ave",
    "sg:city":"South Gate",
    "sg:classifiers":[
        {
            "category":"Shopping",
            "subcategory":"Florist",
            "type":"Retail Goods"
        }
    ],
    "sg:phone":"+1 323 567 1466",
    "sg:postcode":"90280",
    "sg:province":"CA",
    "wof:name":"State Street Flowers & More",
    "wof:placetype":"venue"
},
  "geometry": {"coordinates":[-118.213677,33.960501],"type":"Point"}
}