{
  "type": "Feature",
  "properties": {
    "addr:full":"65 Soda Bay Rd Lakeport CA 95453",
    "addr:postcode":"95453",
    "addr:street":"Soda Bay Rd",
    "iso:country":"US",
    "sg:address":"65 Soda Bay Rd",
    "sg:city":"Lakeport",
    "sg:classifiers":[
        {
            "category":"Wholesale",
            "subcategory":"Electrical",
            "type":"Manufacturing & Wholesale Goods"
        }
    ],
    "sg:phone":"+1 707 263 7002",
    "sg:postcode":"95453",
    "sg:province":"CA",
    "sg:tags":[
        "equipment",
        "electric",
        "supply"
    ],
    "wof:name":"Lake County Electric Supply",
    "wof:placetype":"venue"
},
  "geometry": {"coordinates":[-122.909131,39.013007],"type":"Point"}
}