{
  "type": "Feature",
  "properties": {
    "iso:country":"US",
    "sg:address":"20 Corporate Plaza Dr",
    "sg:city":"Newport Beach",
    "sg:classifiers":[
        {
            "category":"Banks & Credit Unions",
            "subcategory":"Bank",
            "type":"Services"
        }
    ],
    "sg:phone":"+1 949 729 0668",
    "sg:postcode":"92660",
    "sg:province":"CA",
    "sg:tags":[
        "escrow"
    ],
    "wof:name":"Central Escrow Inc",
    "wof:placetype":"venue"
},
  "geometry": {"coordinates":[-117.876946,33.609168],"type":"Point"}
}