{
  "type": "Feature",
  "properties": {
    "addr:full":"3926 Linwood Ave Oakland CA 94602",
    "addr:housenumber":"3926",
    "addr:postcode":"94602",
    "addr:street":"Linwood Ave",
    "iso:country":"US",
    "sg:address":"3926 Linwood Ave",
    "sg:city":"Oakland",
    "sg:classifiers":[
        {
            "category":"Shopping",
            "subcategory":"Used Merchandise",
            "type":"Retail Goods"
        }
    ],
    "sg:phone":"+1 510 530 3946",
    "sg:postcode":"94602",
    "sg:province":"CA",
    "sg:tags":[
        "book"
    ],
    "wof:name":"Little Book Shop",
    "wof:placetype":"venue"
},
  "geometry": {"coordinates":[-122.22005,37.804183],"type":"Point"}
}