{
  "type": "Feature",
  "properties": {
    "addr:full":"4044 Broadway St Eureka CA 95503",
    "addr:housenumber":"4044",
    "addr:postcode":"95503",
    "addr:street":"Broadway St",
    "iso:country":"US",
    "sg:address":"4044 Broadway St",
    "sg:city":"Eureka",
    "sg:classifiers":[
        {
            "category":"Retail",
            "subcategory":"Auto Repair",
            "type":"Services"
        }
    ],
    "sg:phone":"+1 707 268 2420",
    "sg:postcode":"95503",
    "sg:province":"CA",
    "sg:tags":[
        "automobile",
        "lubrication"
    ],
    "wof:name":"Broadway 76 Quick Lube",
    "wof:placetype":"venue"
},
  "geometry": {"coordinates":[-124.191531,40.770064],"type":"Point"}
}