{
  "type": "Feature",
  "properties": {
    "addr:full":"500 El Camino Real Santa Clara University Santa Clara CA 95053",
    "addr:housenumber":"500",
    "addr:postcode":"95053",
    "addr:street":"El Camino Real",
    "iso:country":"US",
    "sg:address":"500 El Camino Real Santa Clara University",
    "sg:city":"Santa Clara",
    "sg:classifiers":[
        {
            "category":"Place Of Worship",
            "subcategory":"Church",
            "type":"Public Place"
        }
    ],
    "sg:phone":"+1 408 554 4023",
    "sg:postcode":"95053",
    "sg:province":"CA",
    "sg:website":"www.scu.edu/mission/",
    "wof:name":"Santa Clara University's Mission Church",
    "wof:placetype":"venue"
},
  "geometry": {"coordinates":[-121.937462,37.352077],"type":"Point"}
}