{
  "type": "Feature",
  "properties": {
    "addr:full":"36101 Bob Hope Dr Rancho Mirage CA 92270",
    "addr:housenumber":"36101",
    "addr:postcode":"92270",
    "addr:street":"Bob Hope Dr",
    "iso:country":"US",
    "sg:address":"36101 Bob Hope Dr",
    "sg:city":"Rancho Mirage",
    "sg:classifiers":[
        {
            "category":"Restaurant",
            "type":"Food & Drink"
        }
    ],
    "sg:menulink":"http://www.allmenus.com/ca/cathedral-city-palm-desert/239988-panda-express/menu/",
    "sg:phone":"+1 760 770 3345",
    "sg:postcode":"92270",
    "sg:province":"CA",
    "sg:tags":[
        "asian",
        "chinese"
    ],
    "wof:name":"Panda Express",
    "wof:placetype":"venue"
},
  "geometry": {"coordinates":[-116.407472,33.786237],"type":"Point"}
}