{
  "type": "Feature",
  "properties": {
    "addr:full":"4794 Orkney Pl Shasta Lake CA 96019",
    "addr:housenumber":"4794",
    "addr:postcode":"96019",
    "addr:street":"Orkney Pl",
    "iso:country":"US",
    "sg:address":"4794 Orkney Pl",
    "sg:city":"Shasta Lake",
    "sg:classifiers":[
        {
            "category":"Building & Trades",
            "subcategory":"Construction",
            "type":"Services"
        }
    ],
    "sg:phone":"+1 530 275 6698",
    "sg:postcode":"96019",
    "sg:province":"CA",
    "sg:tags":[
        "repairing",
        "remodeling",
        "contractor"
    ],
    "wof:name":"Godman Construction",
    "wof:placetype":"venue"
},
  "geometry": {"coordinates":[-122.360224,40.662374],"type":"Point"}
}