{
  "type": "Feature",
  "properties": {
    "addr:full":"31840 Ave el Mundo Cathedral City CA 92234",
    "addr:housenumber":"31840",
    "addr:postcode":"92234",
    "addr:street":"Ave El",
    "iso:country":"US",
    "sg:address":"31840 Ave el Mundo",
    "sg:city":"Cathedral City",
    "sg:classifiers":[
        {
            "category":"Shopping",
            "type":"Retail Goods"
        }
    ],
    "sg:phone":"+1 760 321 1218",
    "sg:postcode":"92234",
    "sg:province":"CA",
    "sg:tags":[
        "merchandise"
    ],
    "wof:name":"Cheryls House & Pet Care",
    "wof:placetype":"venue"
},
  "geometry": {"coordinates":[-116.469166,33.818408],"type":"Point"}
}