{
  "type": "Feature",
  "properties": {
    "addr:full":"5033 Rockvalley Rd Rancho Palos Verdes CA 90275",
    "addr:housenumber":"5033",
    "addr:postcode":"90275",
    "addr:street":"Rockvalley Rd",
    "iso:country":"US",
    "sg:address":"5033 Rockvalley Rd",
    "sg:city":"Rancho Palos Verdes",
    "sg:classifiers":[
        {
            "category":"Government",
            "subcategory":"Office",
            "type":"Public Place"
        }
    ],
    "sg:phone":"+1 310 377 8987",
    "sg:postcode":"90275",
    "sg:province":"CA",
    "sg:tags":[
        "consulting",
        "business",
        "utility"
    ],
    "wof:name":"Jacki Bacharach and Associate",
    "wof:placetype":"venue"
},
  "geometry": {"coordinates":[-118.368461,33.783352],"type":"Point"}
}