{
  "type": "Feature",
  "properties": {
    "addr:full":"3453 Stewarton Dr El Sobrante CA 94803",
    "addr:housenumber":"3453",
    "addr:postcode":"94803",
    "addr:street":"Stewarton Dr El Sobrante",
    "iso:country":"US",
    "sg:address":"3453 Stewarton Dr",
    "sg:city":"El Sobrante",
    "sg:classifiers":[
        {
            "category":"Shopping",
            "subcategory":"Jewelry",
            "type":"Retail Goods"
        }
    ],
    "sg:phone":"+1 510 223 1163",
    "sg:postcode":"94803",
    "sg:province":"CA",
    "wof:name":"E J Enterprises",
    "wof:placetype":"venue"
},
  "geometry": {"coordinates":[-122.28827800000001,37.975807],"type":"Point"}
}