{
  "type": "Feature",
  "properties": {
    "iso:country":"US",
    "sg:address":"3453 Stewarton Dr",
    "sg:city":"El Sobrante",
    "sg:classifiers":[
        {
            "category":"Shopping",
            "subcategory":"Jewelry",
            "type":"Retail Goods"
        }
    ],
    "sg:phone":"+1 510 223 1163",
    "sg:postcode":"94803",
    "sg:province":"CA",
    "wof:name":"E J Enterprises",
    "wof:placetype":"venue"
},
  "geometry": {"coordinates":[-122.288278,37.975807],"type":"Point"}
}