{
  "type": "Feature",
  "properties": {
    "addr:full":"2210 W Artesia Blvd Torrance CA 90504",
    "addr:housenumber":"2210",
    "addr:postcode":"90504",
    "addr:street":"W Artesia Blvd",
    "iso:country":"US",
    "sg:address":"2210 W Artesia Blvd",
    "sg:city":"Torrance",
    "sg:classifiers":[
        {
            "category":"Restaurant",
            "type":"Food & Drink"
        }
    ],
    "sg:phone":"+1 310 217 1000",
    "sg:postcode":"90504",
    "sg:province":"CA",
    "sg:tags":[
        "hawaiian"
    ],
    "sg:website":"www.thelofthawaii.com",
    "wof:name":"Loft Hawaiian Restaurant",
    "wof:placetype":"venue"
},
  "geometry": {"coordinates":[-118.317898,33.872783],"type":"Point"}
}