{
  "type": "Feature",
  "properties": {
    "addr:full":"34664 County Line Rd Yucaipa CA 92399",
    "addr:housenumber":"34664",
    "addr:postcode":"92399",
    "addr:street":"County Line Rd",
    "iso:country":"US",
    "sg:address":"34664 County Line Rd",
    "sg:city":"Yucaipa",
    "sg:classifiers":[
        {
            "category":"Insurance",
            "subcategory":"Hazard Insurance",
            "type":"Services"
        }
    ],
    "sg:phone":"+1 909 795 7420",
    "sg:postcode":"92399",
    "sg:province":"CA",
    "wof:name":"Aflac",
    "wof:placetype":"venue"
},
  "geometry": {"coordinates":[-117.049081,34.004242],"type":"Point"}
}