{
  "type": "Feature",
  "properties": {
    "addr:full":"214 Union St Watsonville CA 95076",
    "addr:housenumber":"214",
    "addr:postcode":"95076",
    "addr:street":"Union St",
    "iso:country":"US",
    "sg:address":"214 Union St",
    "sg:city":"Watsonville",
    "sg:classifiers":[
        {
            "category":"Social Services",
            "type":"Services"
        }
    ],
    "sg:phone":"+1 831 724 3922",
    "sg:postcode":"95076",
    "sg:province":"CA",
    "sg:tags":[
        "organization",
        "welfare"
    ],
    "wof:name":"Salvation Army",
    "wof:placetype":"venue"
},
  "geometry": {"coordinates":[-121.75358900000001,36.908812],"type":"Point"}
}