{
  "type": "Feature",
  "properties": {
    "addr:full":"3200 W Temple St Historic Filipinotown Los Angeles CA 90026",
    "addr:housenumber":"3200",
    "addr:postcode":"90026",
    "addr:street":"W Temple St",
    "iso:country":"US",
    "sg:address":"3200 W Temple St Historic Filipinotown",
    "sg:city":"Los Angeles",
    "sg:classifiers":[
        {
            "category":"Organizations",
            "subcategory":"Non-profit Organization",
            "type":"Services"
        }
    ],
    "sg:phone":"+1 213 382 1819",
    "sg:postcode":"90026",
    "sg:province":"CA",
    "sg:tags":[
        "service/non-profit",
        "community"
    ],
    "sg:website":"www.esipa.org",
    "wof:name":"Search to Involve Pilipino Americans - SIPA",
    "wof:placetype":"venue"
},
  "geometry": {"coordinates":[-118.28163499999999,34.075252],"type":"Point"}
}