{
  "type": "Feature",
  "properties": {
    "iso:country":"US",
    "sg:address":"3002 N Victoria Dr",
    "sg:city":"Alpine",
    "sg:classifiers":[
        {
            "category":"Home & Garden",
            "subcategory":"Carpets & Floor Coverings",
            "type":"Retail Goods"
        }
    ],
    "sg:phone":"+1 619 445 8555",
    "sg:postcode":"91901",
    "sg:province":"CA",
    "sg:tags":[
        "dealer",
        "rug"
    ],
    "wof:name":"R B Floorcovering",
    "wof:placetype":"venue"
},
  "geometry": {"coordinates":[-116.75699,32.849177],"type":"Point"}
}