{
  "type": "Feature",
  "properties": {
    "iso:country":"US",
    "sg:address":"650 International Blvd Ste C",
    "sg:city":"Oakland",
    "sg:classifiers":[
        {
            "category":"Shopping",
            "subcategory":"Pharmacy",
            "type":"Retail Goods"
        }
    ],
    "sg:phone":"+1 510 451 9202",
    "sg:postcode":"94606",
    "sg:province":"CA",
    "sg:tags":[
        "drugstore"
    ],
    "wof:name":"Pacific Pharmacy",
    "wof:placetype":"venue"
},
  "geometry": {"coordinates":[-122.252461,37.79474],"type":"Point"}
}