{
  "type": "Feature",
  "properties": {
    "addr:full":"530 Oak Grove Ave Menlo Park CA 94025",
    "addr:housenumber":"530",
    "addr:postcode":"94025",
    "addr:street":"Oak Grove Ave",
    "iso:country":"US",
    "sg:address":"530 Oak Grove Ave",
    "sg:city":"Menlo Park",
    "sg:classifiers":[
        {
            "category":"Building & Trades",
            "subcategory":"Landscaping Services",
            "type":"Services"
        }
    ],
    "sg:phone":"+1 650 322 7698",
    "sg:postcode":"94025",
    "sg:province":"CA",
    "sg:tags":[
        "designer",
        "architect",
        "landscape"
    ],
    "sg:website":"www.californiaeclectic.com",
    "wof:name":"Peter Shaw Wright Associates",
    "wof:placetype":"venue"
},
  "geometry": {"coordinates":[-122.18344,37.455629],"type":"Point"}
}