{
  "type": "Feature",
  "properties": {
    "addr:full":"17671 Irvine Blvd Ste 207 Tustin CA 92780",
    "addr:housenumber":"17671",
    "addr:postcode":"92780",
    "addr:street":"Irvine Blvd Ste 207",
    "iso:country":"US",
    "sg:address":"17671 Irvine Blvd Ste 207",
    "sg:city":"Tustin",
    "sg:classifiers":[
        {
            "category":"Professional",
            "subcategory":"Lawyer & Legal Services",
            "type":"Services"
        }
    ],
    "sg:phone":"+1 714 838 0654",
    "sg:postcode":"92780",
    "sg:province":"CA",
    "wof:name":"Gans & Rosenfield LLP",
    "wof:placetype":"venue"
},
  "geometry": {"coordinates":[-117.82449099999999,33.748517],"type":"Point"}
}