{
  "type": "Feature",
  "properties": {
    "iso:country":"US",
    "sg:address":"680 Union Ave",
    "sg:city":"Pomona",
    "sg:classifiers":[
        {
            "category":"Wholesale",
            "subcategory":"Machinery & Supplies",
            "type":"Manufacturing & Wholesale Goods"
        }
    ],
    "sg:phone":"+1 909 469 2641",
    "sg:postcode":"91768",
    "sg:province":"CA",
    "sg:tags":[
        "equipment",
        "industrial"
    ],
    "wof:name":"Valley Industrial Packaging",
    "wof:placetype":"venue"
},
  "geometry": {"coordinates":[-117.783179,34.062665],"type":"Point"}
}