{
  "type": "Feature",
  "properties": {
    "addr:full":"2631 Oswell St Bakersfield CA 93306",
    "addr:housenumber":"2631",
    "addr:postcode":"93306",
    "addr:street":"Oswell St",
    "iso:country":"US",
    "sg:address":"2631 Oswell St",
    "sg:city":"Bakersfield",
    "sg:classifiers":[
        {
            "category":"Bakery",
            "type":"Food & Drink"
        }
    ],
    "sg:menulink":"http://www.allmenus.com/ca/bakersfield/106736-marie-callenders/menu/",
    "sg:phone":"+1 661 872 1051",
    "sg:postcode":"93306",
    "sg:province":"CA",
    "sg:tags":[
        "american",
        "pastry"
    ],
    "wof:name":"Marie Callender's",
    "wof:placetype":"venue"
},
  "geometry": {"coordinates":[-118.94934000000001,35.394179],"type":"Point"}
}