{
  "type": "Feature",
  "properties": {
    "iso:country":"US",
    "sg:address":"569 W Clover Rd",
    "sg:city":"Tracy",
    "sg:classifiers":[
        {
            "category":"Coffee & Tea",
            "type":"Food & Drink"
        }
    ],
    "sg:menulink":"http://www.allmenus.com/ca/tracy/118595-starbucks-coffee/menu/",
    "sg:phone":"+1 209 221 6755",
    "sg:postcode":"95376",
    "sg:province":"CA",
    "sg:tags":[
        "american"
    ],
    "wof:name":"Starbucks Coffee",
    "wof:placetype":"venue"
},
  "geometry": {"coordinates":[-121.43437400000001,37.761438],"type":"Point"}
}