{
  "type": "Feature",
  "properties": {
    "addr:full":"1401 Maricopa Hwy Ojai CA 93023",
    "addr:housenumber":"1401",
    "addr:postcode":"93023",
    "addr:street":"Maricopa Hwy",
    "iso:country":"US",
    "sg:address":"1401 Maricopa Hwy",
    "sg:city":"Ojai",
    "sg:classifiers":[
        {
            "category":"Social Services",
            "type":"Services"
        }
    ],
    "sg:phone":"+1 805 640 9553",
    "sg:postcode":"93023",
    "sg:province":"CA",
    "sg:tags":[
        "youth",
        "organization",
        "center"
    ],
    "wof:name":"Oaji Valley Youth Nordhoff",
    "wof:placetype":"venue"
},
  "geometry": {"coordinates":[-119.270433,34.445969],"type":"Point"}
}