{
  "type": "Feature",
  "properties": {
    "addr:full":"23681 La Palma Ave Ste D Yorba Linda CA 92887",
    "addr:housenumber":"23681",
    "addr:postcode":"92887",
    "addr:street":"La Palma Ave Ste D",
    "iso:country":"US",
    "sg:address":"23681 La Palma Ave Ste D",
    "sg:city":"Yorba Linda",
    "sg:classifiers":[
        {
            "category":"Health Services",
            "subcategory":"Dentist",
            "type":"Services"
        }
    ],
    "sg:phone":"+1 714 692 4004",
    "sg:postcode":"92887",
    "sg:province":"CA",
    "wof:name":"Azizi M DDS MS",
    "wof:placetype":"venue"
},
  "geometry": {"coordinates":[-117.723033,33.871369],"type":"Point"}
}