{
  "type": "Feature",
  "properties": {
    "iso:country":"US",
    "sg:address":"1501 E Alondra Blvd",
    "sg:city":"Compton",
    "sg:classifiers":[
        {
            "category":"Home & Garden",
            "subcategory":"Carpets & Floor Coverings",
            "type":"Retail Goods"
        }
    ],
    "sg:phone":"+1 310 537 6261",
    "sg:postcode":"90221",
    "sg:province":"CA",
    "wof:name":"Hollywood Carpet",
    "wof:placetype":"venue"
},
  "geometry": {"coordinates":[-118.205108,33.888698],"type":"Point"}
}