{
  "type": "Feature",
  "properties": {
    "iso:country":"US",
    "sg:address":"124 Abbott St",
    "sg:city":"Salinas",
    "sg:classifiers":[
        {
            "category":"Food & Beverages",
            "subcategory":"Liquor & Beverages",
            "type":"Retail Goods"
        }
    ],
    "sg:phone":"+1 831 424 5552",
    "sg:postcode":"93901",
    "sg:province":"CA",
    "sg:tags":[
        "delicatessen"
    ],
    "wof:name":"La Estrella Liquors & Deli",
    "wof:placetype":"venue"
},
  "geometry": {"coordinates":[-121.647322,36.67033],"type":"Point"}
}