{
  "type": "Feature",
  "properties": {
    "iso:country":"US",
    "sg:address":"272 Forest Ave",
    "sg:city":"Laguna Beach",
    "sg:classifiers":[
        {
            "category":"Shopping",
            "type":"Retail Goods"
        }
    ],
    "sg:phone":"+1 949 497 8700",
    "sg:postcode":"92651",
    "sg:province":"CA",
    "sg:tags":[
        "art",
        "gallery",
        "dealer"
    ],
    "wof:name":"Art For The Soul",
    "wof:placetype":"venue"
},
  "geometry": {"coordinates":[-117.782617,33.543216],"type":"Point"}
}