{
  "type": "Feature",
  "properties": {
    "iso:country":"US",
    "sg:address":"1157 N Red Gum St",
    "sg:city":"Anaheim",
    "sg:classifiers":[
        {
            "category":"Building & Trades",
            "subcategory":"Construction",
            "type":"Services"
        }
    ],
    "sg:phone":"+1 714 630 7630",
    "sg:postcode":"92806",
    "sg:province":"CA",
    "sg:tags":[
        "house",
        "family",
        "contractor"
    ],
    "wof:name":"Nicholas Lane Contractors Inc",
    "wof:placetype":"venue"
},
  "geometry": {"coordinates":[-117.864271,33.851297],"type":"Point"}
}