{
  "type": "Feature",
  "properties": {
    "addr:full":"666 N Fairoaks Ave Sunnyvale CA 94085",
    "addr:housenumber":"666",
    "addr:postcode":"94085",
    "addr:street":"N Fairoaks Ave",
    "iso:country":"US",
    "sg:address":"666 N Fairoaks Ave",
    "sg:city":"Sunnyvale",
    "sg:classifiers":[
        {
            "category":"Restaurant",
            "type":"Food & Drink"
        },
        {
            "category":"Food & Beverages",
            "subcategory":"Groceries & Convenience Stores",
            "type":"Retail Goods"
        }
    ],
    "sg:phone":"+1 408 736 3793",
    "sg:postcode":"94085",
    "sg:province":"CA",
    "sg:tags":[
        "mexican"
    ],
    "sg:website":"www.chavezsuper.com",
    "wof:name":"Chavez Supermarket & Taqueria",
    "wof:placetype":"venue"
},
  "geometry": {"coordinates":[-122.012001,37.391602],"type":"Point"}
}