{
  "type": "Feature",
  "properties": {
    "addr:full":"28700 Ave 5 Madera CA 93637",
    "addr:housenumber":"28700",
    "addr:postcode":"93637",
    "addr:street":"Ave 5",
    "iso:country":"US",
    "sg:address":"28700 Ave 5",
    "sg:city":"Madera",
    "sg:classifiers":[
        {
            "category":"Farming",
            "subcategory":"Livestock Farm",
            "type":"Manufacturing & Wholesale Goods"
        }
    ],
    "sg:phone":"+1 559 673 7473",
    "sg:postcode":"93637",
    "sg:province":"CA",
    "sg:tags":[
        "animal",
        "general"
    ],
    "wof:name":"Riverbend Ranch",
    "wof:placetype":"venue"
},
  "geometry": {"coordinates":[-120.027912,36.822242],"type":"Point"}
}