{
  "type": "Feature",
  "properties": {
    "addr:full":"17315 Penn Valley Dr Penn Valley CA 95946",
    "addr:housenumber":"17315",
    "addr:postcode":"95946",
    "addr:street":"Penn Valley Dr",
    "iso:country":"US",
    "sg:address":"17315 Penn Valley Dr",
    "sg:city":"Penn Valley",
    "sg:classifiers":[
        {
            "category":"Banks & Credit Unions",
            "subcategory":"Bank",
            "type":"Services"
        }
    ],
    "sg:phone":"+1 530 432 2960",
    "sg:postcode":"95946",
    "sg:province":"CA",
    "sg:tags":[
        "loan",
        "real estate"
    ],
    "wof:name":"American Sierra Mortgage",
    "wof:placetype":"venue"
},
  "geometry": {"coordinates":[-121.174795,39.198527],"type":"Point"}
}