{
  "type": "Feature",
  "properties": {
    "iso:country":"US",
    "sg:address":"1047 Lincoln Avenue",
    "sg:city":"San Jose",
    "sg:classifiers":[
        {
            "category":"Professional",
            "subcategory":"Accounting & Tax Preparation",
            "type":"Services"
        }
    ],
    "sg:phone":"+1 408 294 2225",
    "sg:postcode":"95125",
    "sg:province":"CA",
    "sg:tags":[
        "accountant"
    ],
    "sg:website":"www.thesiressgroup.com",
    "wof:name":"The Siress Group",
    "wof:placetype":"venue"
},
  "geometry": {"coordinates":[-121.90285,37.310927],"type":"Point"}
}