{
  "type": "Feature",
  "properties": {
    "iso:country":"US",
    "sg:address":"1666 Shattuck Ave Suite 2",
    "sg:city":"Berkeley",
    "sg:classifiers":[
        {
            "category":"Banks & Credit Unions",
            "subcategory":"Investment Brokerage",
            "type":"Services"
        }
    ],
    "sg:phone":"+1 510 981 1876",
    "sg:postcode":"94709",
    "sg:province":"CA",
    "sg:tags":[
        "investing",
        "advisory"
    ],
    "sg:website":"www.kspcapital.com",
    "wof:name":"K S P Capital Mngmnt",
    "wof:placetype":"venue"
},
  "geometry": {"coordinates":[-122.269031,37.877123],"type":"Point"}
}