{
  "type": "Feature",
  "properties": {
    "iso:country":"US",
    "sg:address":"164 S Alice Cir",
    "sg:city":"Anaheim",
    "sg:classifiers":[
        {
            "category":"Manufacturing",
            "subcategory":"Tools & Machinery",
            "type":"Manufacturing & Wholesale Goods"
        }
    ],
    "sg:phone":"+1 714 632 9306",
    "sg:postcode":"92806",
    "sg:province":"CA",
    "sg:tags":[
        "textile",
        "mfg"
    ],
    "wof:name":"Gill Engineering",
    "wof:placetype":"venue"
},
  "geometry": {"coordinates":[-117.868492,33.839721],"type":"Point"}
}