{
  "type": "Feature",
  "properties": {
    "addr:full":"7077 N Millbrook Ave Fresno CA 93720",
    "addr:housenumber":"7077",
    "addr:postcode":"93720",
    "addr:street":"N Millbrook Ave",
    "iso:country":"US",
    "sg:address":"7077 N Millbrook Ave",
    "sg:city":"Fresno",
    "sg:classifiers":[
        {
            "category":"Autos & Motor Vehicles",
            "subcategory":"Automobile Sales",
            "type":"Retail Goods"
        }
    ],
    "sg:phone":"+1 559 446 1811",
    "sg:postcode":"93720",
    "sg:province":"CA",
    "sg:tags":[
        "car",
        "dealer"
    ],
    "wof:name":"Auto Shack",
    "wof:placetype":"venue"
},
  "geometry": {"coordinates":[-119.76571800000001,36.840725],"type":"Point"}
}