{
  "type": "Feature",
  "properties": {
    "iso:country":"US",
    "sg:address":"1100 W Clark Ave",
    "sg:city":"Burbank",
    "sg:classifiers":[
        {
            "category":"Arts & Performance",
            "subcategory":"Arts Center",
            "type":"Entertainment"
        }
    ],
    "sg:phone":"+1 818 238 9998",
    "sg:postcode":"91506",
    "sg:province":"CA",
    "sg:tags":[
        "performing"
    ],
    "wof:name":"Grove Theatre Center",
    "wof:placetype":"venue"
},
  "geometry": {"coordinates":[-118.319,34.1731],"type":"Point"}
}