{
  "type": "Feature",
  "properties": {
    "iso:country":"US",
    "sg:address":"102 E Fremont Ave",
    "sg:city":"Sunnyvale",
    "sg:classifiers":[
        {
            "category":"Restaurant",
            "type":"Food & Drink"
        }
    ],
    "sg:phone":"+1 408 245 2751",
    "sg:postcode":"94087",
    "sg:province":"CA",
    "sg:tags":[
        "traditional",
        "american",
        "steakhouse",
        "barbeque"
    ],
    "wof:name":"Longhorn Charcoal Pit",
    "wof:placetype":"venue"
},
  "geometry": {"coordinates":[-122.032077,37.352059],"type":"Point"}
}