{
  "type": "Feature",
  "properties": {
    "addr:full":"13223 Iona Ave Hanford CA 93230",
    "addr:housenumber":"13223",
    "addr:postcode":"ca 93230",
    "addr:street":"Iona Ave",
    "iso:country":"US",
    "sg:address":"13223 Iona Ave",
    "sg:city":"Hanford",
    "sg:classifiers":[
        {
            "category":"Freight",
            "type":"Transportation"
        }
    ],
    "sg:phone":"+1 559 582 3034",
    "sg:postcode":"93230",
    "sg:province":"CA",
    "sg:tags":[
        "trucking"
    ],
    "wof:name":"Pereira Hay Company",
    "wof:placetype":"venue"
},
  "geometry": {"coordinates":[-119.698821,36.283784],"type":"Point"}
}