{
  "type": "Feature",
  "properties": {
    "iso:country":"US",
    "sg:address":"7920 Silverton Ave",
    "sg:city":"San Diego",
    "sg:classifiers":[
        {
            "category":"Building & Trades",
            "subcategory":"Electrical",
            "type":"Services"
        },
        {
            "category":"Shopping",
            "subcategory":"Computers & Home Electronics",
            "type":"Retail Goods"
        }
    ],
    "sg:phone":"+1 858 578 4380",
    "sg:postcode":"92126",
    "sg:province":"CA",
    "sg:tags":[
        "electrical",
        "system",
        "contractor"
    ],
    "sg:website":"www.soundideas-av.com",
    "wof:name":"Sound Ideas",
    "wof:placetype":"venue"
},
  "geometry": {"coordinates":[-117.153042,32.890977],"type":"Point"}
}