{
  "type": "Feature",
  "properties": {
    "addr:full":"777 Kains Ave San Bruno CA 94066",
    "addr:housenumber":"777",
    "addr:postcode":"94066",
    "addr:street":"Kains Ave",
    "iso:country":"US",
    "sg:address":"777 Kains Ave",
    "sg:city":"San Bruno",
    "sg:classifiers":[
        {
            "category":"Retail",
            "subcategory":"Repair Shop",
            "type":"Services"
        }
    ],
    "sg:phone":"+1 650 827 9905",
    "sg:postcode":"94066",
    "sg:province":"CA",
    "sg:tags":[
        "equipment",
        "photographic"
    ],
    "wof:name":"Fix & Focus Repair Service",
    "wof:placetype":"venue"
},
  "geometry": {"coordinates":[-122.41629399999999,37.626845],"type":"Point"}
}