{
  "type": "Feature",
  "properties": {
    "iso:country":"US",
    "sg:address":"11555 Palm Dr",
    "sg:city":"Desert Hot Spgs",
    "sg:classifiers":[
        {
            "category":"Education",
            "subcategory":"School",
            "type":"Public Place"
        }
    ],
    "sg:phone":"+1 760 251 7226",
    "sg:postcode":"92240",
    "sg:province":"CA",
    "wof:name":"Las Brisas High School",
    "wof:placetype":"venue"
},
  "geometry": {"coordinates":[-116.501444,33.964688],"type":"Point"}
}