{
  "type": "Feature",
  "properties": {
    "iso:country":"US",
    "sg:address":"4425 Bellevue Ct",
    "sg:city":"Turlock",
    "sg:classifiers":[
        {
            "category":"Organizations",
            "subcategory":"Community Association",
            "type":"Services"
        }
    ],
    "sg:phone":"+1 209 667 9504",
    "sg:postcode":"95382",
    "sg:province":"CA",
    "wof:name":"A Way Out Community Development Program",
    "wof:placetype":"venue"
},
  "geometry": {"coordinates":[-120.849723,37.533743],"type":"Point"}
}