{
  "type": "Feature",
  "properties": {
    "addr:full":"13626 Pomerado Rd Poway CA 92064",
    "addr:housenumber":"13626",
    "addr:postcode":"ca 92064",
    "addr:street":"Pomerado Rd",
    "iso:country":"US",
    "sg:address":"13626 Pomerado Rd",
    "sg:city":"Poway",
    "sg:classifiers":[
        {
            "category":"Autos & Motor Vehicles",
            "subcategory":"Fuel & Gas Station",
            "type":"Retail Goods"
        },
        {
            "category":"Banks & Credit Unions",
            "subcategory":"Financial Services",
            "type":"Services"
        },
        {
            "category":"Banks & Credit Unions",
            "subcategory":"Atm",
            "type":"Services"
        },
        {
            "category":"Food & Beverages",
            "subcategory":"Groceries & Convenience Stores",
            "type":"Retail Goods"
        }
    ],
    "sg:phone":"+1 858 748 0711",
    "sg:postcode":"92064",
    "sg:province":"CA",
    "sg:tags":[
        "money",
        "location",
        "order"
    ],
    "sg:website":"http://www.7-eleven.com",
    "wof:name":"7-Eleven",
    "wof:placetype":"venue"
},
  "geometry": {"coordinates":[-117.06249200000001,32.961678],"type":"Point"}
}