{
  "type": "Feature",
  "properties": {
    "addr:full":"5850 Canoga Ave Woodland Hills CA 91367",
    "addr:housenumber":"5850",
    "addr:postcode":"91367",
    "addr:street":"Canoga Ave",
    "iso:country":"US",
    "sg:address":"5850 Canoga Ave",
    "sg:city":"Woodland Hills",
    "sg:classifiers":[
        {
            "category":"Professional",
            "subcategory":"Lawyer & Legal Services",
            "type":"Services"
        }
    ],
    "sg:phone":"+1 818 710 2777",
    "sg:postcode":"91367",
    "sg:province":"CA",
    "wof:name":"Freeman and Freeman Law Offices of",
    "wof:placetype":"venue"
},
  "geometry": {"coordinates":[-118.59699999999999,34.1763],"type":"Point"}
}