{
  "type": "Feature",
  "properties": {
    "iso:country":"US",
    "sg:address":"1108 S A St",
    "sg:city":"Madera",
    "sg:classifiers":[
        {
            "category":"Organizations",
            "subcategory":"Religious Organization",
            "type":"Services"
        }
    ],
    "sg:phone":"+1 559 674 1268",
    "sg:postcode":"93638",
    "sg:province":"CA",
    "sg:tags":[
        "god",
        "churches-church"
    ],
    "sg:website":"http://eclkc.ohs.acf.hhs.gov/hslc/",
    "wof:name":"Eastside Head Start",
    "wof:placetype":"venue"
},
  "geometry": {"coordinates":[-120.04424899999999,36.956292],"type":"Point"}
}