{
  "type": "Feature",
  "properties": {
    "addr:full":"3751 Mary Ln Escondido CA 92025",
    "addr:housenumber":"3751",
    "addr:postcode":"92025",
    "addr:street":"Mary Ln",
    "iso:country":"US",
    "sg:address":"3751 Mary Ln",
    "sg:city":"Escondido",
    "sg:classifiers":[
        {
            "category":"Social Services",
            "subcategory":"Child Care",
            "type":"Services"
        }
    ],
    "sg:phone":"+1 760 489 2322",
    "sg:postcode":"92025",
    "sg:province":"CA",
    "wof:name":"Children's World Learning Ctr",
    "wof:placetype":"venue"
},
  "geometry": {"coordinates":[-117.05586599999999,33.077813],"type":"Point"}
}