{
  "type": "Feature",
  "properties": {
    "addr:full":"10 College Pkwy, Folsom, CA",
    "iso:country":"US",
    "name:eng_x_preferred":[
        "Harris Center"
    ],
    "wof:name":"Harris Center",
    "wof:placetype":"venue"
},
  "geometry": {"coordinates":[-121.129412,38.662528],"type":"Point"}
}