{
  "type": "Feature",
  "properties": {
    "iso:country":"US",
    "sg:address":"9845 Topanga Canyon Blvd",
    "sg:city":"Chatsworth",
    "sg:classifiers":[
        {
            "category":"Restaurant",
            "type":"Food & Drink"
        }
    ],
    "sg:menulink":"http://www.allmenus.com/ca/san-fernando-valley/150156-subway/menu/",
    "sg:phone":"+1 818 700 1526",
    "sg:postcode":"91311",
    "sg:province":"CA",
    "sg:tags":[
        "american",
        "sandwich"
    ],
    "wof:name":"Subway",
    "wof:placetype":"venue"
},
  "geometry": {"coordinates":[-118.606126,34.249632],"type":"Point"}
}