{
  "type": "Feature",
  "properties": {
    "iso:country":"US",
    "sg:address":"13313 Yukon Ave",
    "sg:city":"Hawthorne",
    "sg:classifiers":[
        {
            "category":"Personal",
            "subcategory":"Beauty Salon",
            "type":"Services"
        }
    ],
    "sg:phone":"+1 310 676 4140",
    "sg:postcode":"90250",
    "sg:province":"CA",
    "wof:name":"Daisy Beauty Shop",
    "wof:placetype":"venue"
},
  "geometry": {"coordinates":[-118.335233,33.910778],"type":"Point"}
}