{
  "type": "Feature",
  "properties": {
    "addr:full":"12424 Philadelphia St Whittier CA 90601",
    "addr:housenumber":"12424",
    "addr:postcode":"90601",
    "addr:street":"Philadelphia St",
    "iso:country":"US",
    "sg:address":"12424 Philadelphia St",
    "sg:city":"Whittier",
    "sg:classifiers":[
        {
            "category":"Restaurant",
            "type":"Food & Drink"
        }
    ],
    "sg:phone":"+1 562 698 9088",
    "sg:postcode":"90601",
    "sg:province":"CA",
    "wof:name":"Elva's Restaurant",
    "wof:placetype":"venue"
},
  "geometry": {"coordinates":[-118.043404,33.979046],"type":"Point"}
}