{
  "type": "Feature",
  "properties": {
    "iso:country":"US",
    "sg:address":"4969 Van Nuys Blvd",
    "sg:city":"Sherman Oaks",
    "sg:classifiers":[
        {
            "category":"Retail",
            "subcategory":"Auto Repair",
            "type":"Services"
        }
    ],
    "sg:phone":"+1 818 986 7664",
    "sg:postcode":"91403",
    "sg:province":"CA",
    "sg:tags":[
        "automobile",
        "testing",
        "emission"
    ],
    "wof:name":"15 Minute Smog Check & Test",
    "wof:placetype":"venue"
},
  "geometry": {"coordinates":[-118.448772,34.15997],"type":"Point"}
}