{
  "type": "Feature",
  "properties": {
    "iso:country":"US",
    "sg:address":"1600 W Mahalo Pl",
    "sg:city":"Compton",
    "sg:classifiers":[
        {
            "category":"Wholesale",
            "subcategory":"Machinery & Supplies",
            "type":"Manufacturing & Wholesale Goods"
        }
    ],
    "sg:phone":"+1 310 763 1530",
    "sg:postcode":"90220",
    "sg:province":"CA",
    "sg:tags":[
        "fastener",
        "industrial"
    ],
    "sg:website":"www.tengco.com",
    "wof:name":"Tengco Inc",
    "wof:placetype":"venue"
},
  "geometry": {"coordinates":[-118.24657500000001,33.871109],"type":"Point"}
}