{
  "type": "Feature",
  "properties": {
    "iso:country":"US",
    "sg:address":"2413 S Walker Ave",
    "sg:city":"San Pedro",
    "sg:classifiers":[
        {
            "category":"Food & Beverages",
            "subcategory":"Groceries & Convenience Stores",
            "type":"Retail Goods"
        }
    ],
    "sg:phone":"+1 310 832 8660",
    "sg:postcode":"90731",
    "sg:province":"CA",
    "wof:name":"Busy Bee Market",
    "wof:placetype":"venue"
},
  "geometry": {"coordinates":[-118.30342400000001,33.72339],"type":"Point"}
}