{
  "type": "Feature",
  "properties": {
    "iso:country":"US",
    "sg:address":"23325 del Lago Dr",
    "sg:city":"Laguna Hills",
    "sg:classifiers":[
        {
            "category":"Manufacturing",
            "subcategory":"Rubber & Plastics",
            "type":"Manufacturing & Wholesale Goods"
        }
    ],
    "sg:phone":"+1 949 472 8118",
    "sg:postcode":"92653",
    "sg:province":"CA",
    "sg:tags":[
        "gasket"
    ],
    "wof:name":"Chavers Gasket Corp",
    "wof:placetype":"venue"
},
  "geometry": {"coordinates":[-117.72706599999999,33.628048],"type":"Point"}
}