{
  "type": "Feature",
  "properties": {
    "iso:country":"US",
    "sg:address":"3507 Folkstone Ct",
    "sg:city":"Burbank",
    "sg:classifiers":[
        {
            "category":"Manufacturing",
            "subcategory":"Retail Goods",
            "type":"Manufacturing & Wholesale Goods"
        }
    ],
    "sg:phone":"+1 818 516 1024",
    "sg:postcode":"91504",
    "sg:province":"CA",
    "sg:tags":[
        "product",
        "mfg"
    ],
    "wof:name":"Sharae Creations",
    "wof:placetype":"venue"
},
  "geometry": {"coordinates":[-118.335135,34.219726],"type":"Point"}
}