{
  "type": "Feature",
  "properties": {
    "iso:country":"US",
    "sg:address":"2459 Huntington Dr",
    "sg:city":"San Marino",
    "sg:classifiers":[
        {
            "category":"Home & Garden",
            "subcategory":"Furniture",
            "type":"Retail Goods"
        }
    ],
    "sg:phone":"+1 626 795 3820",
    "sg:postcode":"91108",
    "sg:province":"CA",
    "sg:tags":[
        "store"
    ],
    "wof:name":"Morten & Murphy-Mfr Rep",
    "wof:placetype":"venue"
},
  "geometry": {"coordinates":[-118.102997,34.123199],"type":"Point"}
}