{
  "type": "Feature",
  "properties": {
    "iso:country":"US",
    "sg:address":"1717 N California Blvd",
    "sg:city":"Walnut Creek",
    "sg:classifiers":[
        {
            "category":"Health Services",
            "subcategory":"Clinic",
            "type":"Services"
        }
    ],
    "sg:phone":"+1 925 944 5779",
    "sg:postcode":"94596",
    "sg:province":"CA",
    "sg:tags":[
        "home"
    ],
    "wof:name":"INTERIM Assisted Care",
    "wof:placetype":"venue"
},
  "geometry": {"coordinates":[-122.065534,37.904676],"type":"Point"}
}