{
  "type": "Feature",
  "properties": {
    "addr:full":"106 Pasatiempo Dr Santa Cruz CA 95060",
    "addr:housenumber":"106",
    "addr:postcode":"95060",
    "addr:street":"Pasatiempo Dr",
    "iso:country":"US",
    "sg:address":"106 Pasatiempo Dr",
    "sg:city":"Santa Cruz",
    "sg:classifiers":[
        {
            "category":"Professional",
            "subcategory":"Management & Consulting",
            "type":"Services"
        }
    ],
    "sg:phone":"+1 831 425 1839",
    "sg:postcode":"95060",
    "sg:province":"CA",
    "sg:tags":[
        "marketing",
        "consultant"
    ],
    "sg:website":"www.mbaseminar.com",
    "wof:name":"Intelligent Resources Corp",
    "wof:placetype":"venue"
},
  "geometry": {"coordinates":[-122.032712,37.011843],"type":"Point"}
}