{
  "type": "Feature",
  "properties": {
    "iso:country":"US",
    "sg:address":"4510 E Pacific Coast Hwy Ste 270",
    "sg:city":"Long Beach",
    "sg:classifiers":[
        {
            "category":"Professional",
            "subcategory":"Accounting & Tax Preparation",
            "type":"Services"
        }
    ],
    "sg:phone":"+1 562 498 0997",
    "sg:postcode":"90804",
    "sg:province":"CA",
    "sg:tags":[
        "accountant"
    ],
    "wof:name":"Gray Mark Certified Public Accountants",
    "wof:placetype":"venue"
},
  "geometry": {"coordinates":[-118.15300000000001,33.783901],"type":"Point"}
}