{
  "type": "Feature",
  "properties": {
    "iso:country":"US",
    "sg:address":"2616 W 54th St",
    "sg:city":"Los Angeles",
    "sg:classifiers":[
        {
            "category":"Personal",
            "subcategory":"Beauty Salon",
            "type":"Services"
        }
    ],
    "sg:phone":"+1 323 294 3401",
    "sg:postcode":"90043",
    "sg:province":"CA",
    "wof:name":"Shello Images",
    "wof:placetype":"venue"
},
  "geometry": {"coordinates":[-118.32237600000001,33.993105],"type":"Point"}
}