{
  "type": "Feature",
  "properties": {
    "addr:full":"3325 E 7th St Long Beach CA 90804",
    "addr:housenumber":"3325",
    "addr:postcode":"90804",
    "addr:street":"E 7Th St",
    "iso:country":"US",
    "sg:address":"3325 E 7th St",
    "sg:city":"Long Beach",
    "sg:classifiers":[
        {
            "category":"Personal",
            "subcategory":"Beauty Salon",
            "type":"Services"
        }
    ],
    "sg:phone":"+1 562 438 3760",
    "sg:postcode":"90804",
    "sg:province":"CA",
    "sg:tags":[
        "nail",
        "manicuring"
    ],
    "wof:name":"Pink Nails",
    "wof:placetype":"venue"
},
  "geometry": {"coordinates":[-118.15300000000001,33.775398],"type":"Point"}
}