{
  "type": "Feature",
  "properties": {
    "addr:full":"1043 Garland Ave San Jose CA 95126",
    "addr:housenumber":"1043",
    "addr:postcode":"95126",
    "addr:street":"Garland Ave",
    "iso:country":"US",
    "sg:address":"1043 Garland Ave",
    "sg:city":"San Jose",
    "sg:classifiers":[
        {
            "category":"Home & Garden",
            "subcategory":"Furniture",
            "type":"Retail Goods"
        }
    ],
    "sg:phone":"+1 408 297 0343",
    "sg:postcode":"95126",
    "sg:province":"CA",
    "sg:tags":[
        "equipment",
        "kitchen",
        "cabinet"
    ],
    "wof:name":"Cabinet Guy Construction",
    "wof:placetype":"venue"
},
  "geometry": {"coordinates":[-121.91107599999999,37.32981],"type":"Point"}
}