{
  "type": "Feature",
  "properties": {
    "addr:full":"5074 Las Lindas Way Riverside CA 92505",
    "addr:housenumber":"5074",
    "addr:postcode":"92505",
    "addr:street":"Las Lindas Way",
    "iso:country":"US",
    "sg:address":"5074 Las Lindas Way",
    "sg:city":"Riverside",
    "sg:classifiers":[
        {
            "category":"Building & Trades",
            "subcategory":"Construction",
            "type":"Services"
        }
    ],
    "sg:phone":"+1 951 334 8434",
    "sg:postcode":"92505",
    "sg:province":"CA",
    "sg:tags":[
        "contractor"
    ],
    "wof:name":"Riley Tile Installation",
    "wof:placetype":"venue"
},
  "geometry": {"coordinates":[-117.49976599999999,33.919464],"type":"Point"}
}