{
  "type": "Feature",
  "properties": {
    "iso:country":"US",
    "sg:address":"1101 E 18th St",
    "sg:city":"Antioch",
    "sg:classifiers":[
        {
            "category":"Food & Beverages",
            "subcategory":"Groceries & Convenience Stores",
            "type":"Retail Goods"
        }
    ],
    "sg:phone":"+1 925 757 5478",
    "sg:postcode":"94509",
    "sg:province":"CA",
    "wof:name":"7-Eleven",
    "wof:placetype":"venue"
},
  "geometry": {"coordinates":[-121.787367,38.004192],"type":"Point"}
}