{
  "type": "Feature",
  "properties": {
    "addr:full":"598 E El Camino Real Sunnyvale CA 94087",
    "addr:housenumber":"598",
    "addr:postcode":"94087",
    "addr:street":"E El Camino Real",
    "iso:country":"US",
    "sg:address":"598 E El Camino Real",
    "sg:city":"Sunnyvale",
    "sg:classifiers":[
        {
            "category":"Professional",
            "type":"Services"
        },
        {
            "category":"Professional",
            "subcategory":"Business Services",
            "type":"Services"
        },
        {
            "category":"Freight",
            "type":"Transportation"
        },
        {
            "category":"Professional",
            "subcategory":"Printing & Photocopies",
            "type":"Services"
        },
        {
            "category":"Shopping",
            "subcategory":"Stationery & Office Supplies",
            "type":"Retail Goods"
        },
        {
            "category":"Manufacturing",
            "subcategory":"Printing",
            "type":"Manufacturing & Wholesale Goods"
        },
        {
            "category":"Manufacturing",
            "subcategory":"Signs",
            "type":"Manufacturing & Wholesale Goods"
        }
    ],
    "sg:phone":"+1 408 530 0111",
    "sg:postcode":"94087",
    "sg:province":"CA",
    "sg:tags":[
        "machine",
        "document",
        "duplicating",
        "shipping",
        "materials-shipping",
        "packaging",
        "packing",
        "imaging",
        "copying",
        "digital",
        "copy"
    ],
    "sg:website":"www.fedex.com/us/office/",
    "wof:name":"FedEx Office Print & Ship Center",
    "wof:placetype":"venue"
},
  "geometry": {"coordinates":[-122.02521400000001,37.36174],"type":"Point"}
}