{
  "type": "Feature",
  "properties": {
    "addr:full":"2560 Macgregor Ct Napa CA 94558",
    "addr:housenumber":"2560",
    "addr:postcode":"94558",
    "addr:street":"Macgregor Ct",
    "iso:country":"US",
    "sg:address":"2560 Macgregor Ct",
    "sg:city":"Napa",
    "sg:classifiers":[
        {
            "category":"Bars & Pubs",
            "type":"Food & Drink"
        },
        {
            "category":"Restaurant",
            "type":"Food & Drink"
        },
        {
            "category":"Bars & Pubs",
            "subcategory":"Lounge",
            "type":"Food & Drink"
        }
    ],
    "sg:phone":"+1 707 252 7118",
    "sg:postcode":"94558",
    "sg:province":"CA",
    "sg:tags":[
        "cocktail"
    ],
    "wof:name":"Old Adobe Bar & Grille",
    "wof:placetype":"venue"
},
  "geometry": {"coordinates":[-122.32296100000001,38.316431],"type":"Point"}
}