{
  "type": "Feature",
  "properties": {
    "addr:full":"1929 Zonal Ave Los Angeles CA 90033",
    "addr:housenumber":"1929",
    "addr:postcode":"90033",
    "addr:street":"Zonal Ave",
    "iso:country":"US",
    "sg:address":"1929 Zonal Ave",
    "sg:city":"Los Angeles",
    "sg:classifiers":[
        {
            "category":"Professional",
            "subcategory":"Research",
            "type":"Services"
        }
    ],
    "sg:phone":"+1 323 221 7818",
    "sg:postcode":"90033",
    "sg:province":"CA",
    "wof:name":"Vascular Biology Institute",
    "wof:placetype":"venue"
},
  "geometry": {"coordinates":[-118.208443,34.061053],"type":"Point"}
}