{
  "type": "Feature",
  "properties": {
    "iso:country":"US",
    "sg:address":"23648 Tiara St",
    "sg:city":"Woodland Hills",
    "sg:classifiers":[
        {
            "category":"Wholesale",
            "subcategory":"Photographic Equipment",
            "type":"Manufacturing & Wholesale Goods"
        }
    ],
    "sg:phone":"+1 818 888 1801",
    "sg:postcode":"91367",
    "sg:province":"CA",
    "sg:tags":[
        "photo"
    ],
    "wof:name":"J Huber Service Co",
    "wof:placetype":"venue"
},
  "geometry": {"coordinates":[-118.642246,34.178461],"type":"Point"}
}