{
  "type": "Feature",
  "properties": {
    "addr:full":"3519 La Grande Blvd. Sacramento CA 95823",
    "addr:housenumber":"3519",
    "addr:postcode":"95823",
    "addr:street":"La Grande Blvd.",
    "iso:country":"US",
    "sg:address":"3519 La Grande Blvd.",
    "sg:city":"Sacramento",
    "sg:classifiers":[
        {
            "category":"Professional",
            "type":"Services"
        },
        {
            "category":"Communications",
            "subcategory":"Newspaper",
            "type":"Services"
        }
    ],
    "sg:phone":"+1 916 428 4804",
    "sg:postcode":"95823",
    "sg:province":"CA",
    "sg:tags":[
        "print",
        "medium"
    ],
    "sg:website":"www.silkscreenpro.com/",
    "wof:name":"Silk Screen Pros",
    "wof:placetype":"venue"
},
  "geometry": {"coordinates":[-121.46818399999999,38.507201],"type":"Point"}
}