{
  "type": "Feature",
  "properties": {
    "iso:country":"US",
    "sg:address":"110 Adams Ln",
    "sg:city":"Grass Valley",
    "sg:classifiers":[
        {
            "category":"Building & Trades",
            "subcategory":"Construction",
            "type":"Services"
        }
    ],
    "sg:phone":"+1 530 272 8259",
    "sg:postcode":"95945",
    "sg:province":"CA",
    "sg:tags":[
        "awning",
        "canopy"
    ],
    "wof:name":"Blue Sky Awning Cleaning",
    "wof:placetype":"venue"
},
  "geometry": {"coordinates":[-121.061258,39.205902],"type":"Point"}
}