{
  "type": "Feature",
  "properties": {
    "addr:full":"3325 Myrtle Avenue North Highlands CA 95660",
    "addr:housenumber":"3325",
    "addr:postcode":"95660",
    "addr:street":"Myrtle Avenue",
    "iso:country":"US",
    "sg:address":"3325 Myrtle Avenue",
    "sg:city":"North Highlands",
    "sg:classifiers":[
        {
            "category":"Social Services",
            "subcategory":"Child Care",
            "type":"Services"
        }
    ],
    "sg:phone":"+1 916 344 6259",
    "sg:postcode":"95660",
    "sg:province":"CA",
    "sg:tags":[
        "day"
    ],
    "wof:name":"Beanstalk",
    "wof:placetype":"venue"
},
  "geometry": {"coordinates":[-121.387552,38.654445],"type":"Point"}
}