{
  "type": "Feature",
  "properties": {
    "iso:country":"US",
    "sg:address":"9401 Waples St",
    "sg:city":"San Diego",
    "sg:classifiers":[
        {
            "category":"Professional",
            "subcategory":"Research",
            "type":"Services"
        }
    ],
    "sg:phone":"+1 858 812 1500",
    "sg:postcode":"92121",
    "sg:province":"CA",
    "wof:name":"Novartis Institute For Functio",
    "wof:placetype":"venue"
},
  "geometry": {"coordinates":[-117.184718,32.901561],"type":"Point"}
}