{
  "type": "Feature",
  "properties": {
    "iso:country":"US",
    "sg:address":"1 E Anapamu St",
    "sg:city":"Santa Barbara",
    "sg:classifiers":[
        {
            "category":"Social Services",
            "type":"Services"
        }
    ],
    "sg:phone":"+1 805 884 8085",
    "sg:postcode":"93101",
    "sg:province":"CA",
    "sg:tags":[
        "individual",
        "family"
    ],
    "wof:name":"Children & Families Commission",
    "wof:placetype":"venue"
},
  "geometry": {"coordinates":[-119.703309,34.424431],"type":"Point"}
}