{
  "type": "Feature",
  "properties": {
    "iso:country":"US",
    "sg:address":"5680 7th St",
    "sg:city":"Keyes",
    "sg:classifiers":[
        {
            "category":"Education",
            "subcategory":"School",
            "type":"Public Place"
        }
    ],
    "sg:phone":"+1 209 667 1660",
    "sg:postcode":"95328",
    "sg:province":"CA",
    "wof:name":"Keyes Union Elem School",
    "wof:placetype":"venue"
},
  "geometry": {"coordinates":[-120.910136,37.552391],"type":"Point"}
}