{
  "type": "Feature",
  "properties": {
    "iso:country":"US",
    "sg:address":"424 2nd St",
    "sg:city":"Davis",
    "sg:classifiers":[
        {
            "category":"Health Services",
            "subcategory":"Clinic",
            "type":"Services"
        }
    ],
    "sg:phone":"+1 530 753 9613",
    "sg:postcode":"95616",
    "sg:province":"CA",
    "sg:tags":[
        "specialty",
        "outpatient"
    ],
    "wof:name":"Sacramnto Dvis Psychatric Svcs",
    "wof:placetype":"venue"
},
  "geometry": {"coordinates":[-121.742419,38.542937],"type":"Point"}
}