{
  "type": "Feature",
  "properties": {
    "addr:full":"1100 S Central Ave Ste D Glendale CA 91204",
    "addr:housenumber":"1100",
    "addr:postcode":"91204",
    "addr:street":"S Central Ave Ste D",
    "iso:country":"US",
    "sg:address":"1100 S Central Ave Ste D",
    "sg:city":"Glendale",
    "sg:classifiers":[
        {
            "category":"Restaurant",
            "type":"Food & Drink"
        }
    ],
    "sg:phone":"+1 818 240 1556",
    "sg:postcode":"91204",
    "sg:province":"CA",
    "sg:tags":[
        "sushi",
        "bar",
        "japanese"
    ],
    "wof:name":"Tottori Sushi & BBQ",
    "wof:placetype":"venue"
},
  "geometry": {"coordinates":[-118.257822,34.133491],"type":"Point"}
}