{
  "type": "Feature",
  "properties": {
    "iso:country":"US",
    "sg:address":"500 Hotel Cir N",
    "sg:city":"San Diego",
    "sg:classifiers":[
        {
            "category":"Arts & Performance",
            "subcategory":"Arts Center",
            "type":"Entertainment"
        }
    ],
    "sg:phone":"+1 619 297 5277",
    "sg:postcode":"92108",
    "sg:province":"CA",
    "sg:tags":[
        "performing"
    ],
    "wof:name":"Dixieland Jazz Society America's Finest City",
    "wof:placetype":"venue"
},
  "geometry": {"coordinates":[-117.168999,32.7612],"type":"Point"}
}