{
  "type": "Feature",
  "properties": {
    "iso:country":"US",
    "sg:address":"659 45th Ave",
    "sg:city":"San Francisco",
    "sg:classifiers":[
        {
            "category":"Social Services",
            "subcategory":"Adult Care",
            "type":"Services"
        }
    ],
    "sg:phone":"+1 415 752 3227",
    "sg:postcode":"94121",
    "sg:province":"CA",
    "sg:tags":[
        "home",
        "residential"
    ],
    "wof:name":"Sutro Heights Non-Ambulatory",
    "wof:placetype":"venue"
},
  "geometry": {"coordinates":[-122.506023,37.776424],"type":"Point"}
}