{
  "type": "Feature",
  "properties": {
    "addr:full":"15650 Vineyard Blvd Morgan Hill CA 95037",
    "addr:housenumber":"15650",
    "addr:postcode":"95037",
    "addr:street":"Vineyard Blvd",
    "iso:country":"US",
    "sg:address":"15650 Vineyard Blvd",
    "sg:city":"Morgan Hill",
    "sg:classifiers":[
        {
            "category":"Professional",
            "subcategory":"Business Services",
            "type":"Services"
        }
    ],
    "sg:phone":"+1 408 779 2566",
    "sg:postcode":"95037",
    "sg:province":"CA",
    "wof:name":"China Business With USA",
    "wof:placetype":"venue"
},
  "geometry": {"coordinates":[-121.640754,37.111025],"type":"Point"}
}