{
  "type": "Feature",
  "properties": {
    "addr:full":"2800 Miner St San Pedro CA 90731",
    "addr:housenumber":"2800",
    "addr:postcode":"90731",
    "addr:street":"Miner St",
    "iso:country":"US",
    "sg:address":"2800 Miner St",
    "sg:city":"San Pedro",
    "sg:classifiers":[
        {
            "category":"Autos & Motor Vehicles",
            "subcategory":"Boat Sales",
            "type":"Retail Goods"
        }
    ],
    "sg:phone":"+1 310 547 4415",
    "sg:postcode":"90731",
    "sg:province":"CA",
    "sg:tags":[
        "yacht"
    ],
    "sg:website":"www.spyachts.com",
    "wof:name":"San Pedro Yacht Sales Inc",
    "wof:placetype":"venue"
},
  "geometry": {"coordinates":[-118.27528100000001,33.716576],"type":"Point"}
}