{
  "type": "Feature",
  "properties": {
    "addr:full":"1032 Broadway Ave Stockton CA 95205",
    "addr:housenumber":"1032",
    "addr:postcode":"95205",
    "addr:street":"Broadway Ave",
    "iso:country":"US",
    "sg:address":"1032 Broadway Ave",
    "sg:city":"Stockton",
    "sg:classifiers":[
        {
            "category":"Manufacturing",
            "subcategory":"Tools & Machinery",
            "type":"Manufacturing & Wholesale Goods"
        }
    ],
    "sg:phone":"+1 209 463 1545",
    "sg:postcode":"95205",
    "sg:province":"CA",
    "sg:tags":[
        "textile",
        "sewing",
        "mfg"
    ],
    "wof:name":"Gilmore Looms",
    "wof:placetype":"venue"
},
  "geometry": {"coordinates":[-121.240906,37.954093],"type":"Point"}
}