{
  "type": "Feature",
  "properties": {
    "iso:country":"US",
    "sg:address":"2323 Honolulu Ave",
    "sg:city":"Montrose",
    "sg:classifiers":[
        {
            "category":"Ice Cream",
            "type":"Food & Drink"
        }
    ],
    "sg:phone":"+1 818 248 1004",
    "sg:postcode":"91020",
    "sg:province":"CA",
    "sg:tags":[
        "frozen",
        "yogurt"
    ],
    "sg:website":"www.paradis-icecream.com",
    "wof:name":"Paradis",
    "wof:placetype":"venue"
},
  "geometry": {"coordinates":[-118.228945,34.206162],"type":"Point"}
}