{
  "type": "Feature",
  "properties": {
    "iso:country":"US",
    "sg:address":"4411 Don Zarembo Dr",
    "sg:city":"Los Angeles",
    "sg:classifiers":[
        {
            "category":"Professional",
            "subcategory":"Accounting & Tax Preparation",
            "type":"Services"
        }
    ],
    "sg:phone":"+1 323 294 8161",
    "sg:postcode":"90008",
    "sg:province":"CA",
    "sg:tags":[
        "return",
        "filing"
    ],
    "wof:name":"Thompson's Tax & Bookkeeping",
    "wof:placetype":"venue"
},
  "geometry": {"coordinates":[-118.352512,34.00528],"type":"Point"}
}