{
  "type": "Feature",
  "properties": {
    "addr:full":"1093 Kraftile Rd Fremont CA 94536",
    "addr:housenumber":"1093",
    "addr:postcode":"94536",
    "addr:street":"Kraftile Rd",
    "iso:country":"US",
    "sg:address":"1093 Kraftile Rd",
    "sg:city":"Fremont",
    "sg:classifiers":[
        {
            "category":"Shopping",
            "subcategory":"Beauty & Cosmetics",
            "type":"Retail Goods"
        },
        {
            "category":"Personal",
            "subcategory":"Beauty Salon",
            "type":"Services"
        }
    ],
    "sg:phone":"+1 510 388 5932",
    "sg:postcode":"94536",
    "sg:province":"CA",
    "sg:tags":[
        "perfume",
        "cosmetics-wholesale",
        "salons-equipment",
        "manufacturer",
        "supply"
    ],
    "wof:name":"Two Cosmetics, Inc.",
    "wof:placetype":"venue"
},
  "geometry": {"coordinates":[-122.00635800000001,37.583047],"type":"Point"}
}