{
  "type": "Feature",
  "properties": {
    "iso:country":"US",
    "sg:address":"8622 Rubio Ave",
    "sg:city":"North Hills",
    "sg:classifiers":[
        {
            "category":"Building & Trades",
            "subcategory":"Construction",
            "type":"Services"
        }
    ],
    "sg:phone":"+1 818 893 8887",
    "sg:postcode":"91343",
    "sg:province":"CA",
    "sg:tags":[
        "designer",
        "dealer",
        "pool",
        "swimming"
    ],
    "wof:name":"Westlake Pools",
    "wof:placetype":"venue"
},
  "geometry": {"coordinates":[-118.49642299999999,34.227352],"type":"Point"}
}