{
  "type": "Feature",
  "properties": {
    "iso:country":"US",
    "sg:address":"624 Dory Ln",
    "sg:city":"Redwood City",
    "sg:classifiers":[
        {
            "category":"Manufacturing",
            "subcategory":"Chemicals & Compounds",
            "type":"Manufacturing & Wholesale Goods"
        }
    ],
    "sg:phone":"+1 650 508 9453",
    "sg:postcode":"94065",
    "sg:province":"CA",
    "sg:tags":[
        "preparation",
        "pharmaceutical",
        "mfg"
    ],
    "wof:name":"Oshadha Therapeutics",
    "wof:placetype":"venue"
},
  "geometry": {"coordinates":[-122.246493,37.530348],"type":"Point"}
}