{
  "type": "Feature",
  "properties": {
    "iso:country":"US",
    "sg:address":"4342 Lankershim Blvd",
    "sg:city":"North Hollywood",
    "sg:classifiers":[
        {
            "category":"Arts & Performance",
            "subcategory":"Theater",
            "type":"Entertainment"
        }
    ],
    "sg:phone":"+1 818 506 8188",
    "sg:postcode":"91602",
    "sg:province":"CA",
    "sg:tags":[
        "talent",
        "agency",
        "casting"
    ],
    "sg:website":"www.bbamodels.com",
    "wof:name":"Bobby Ball Agency",
    "wof:placetype":"venue"
},
  "geometry": {"coordinates":[-118.364956,34.148989],"type":"Point"}
}