{
  "type": "Feature",
  "properties": {
    "iso:country":"US",
    "sg:address":"4431 Corporate Center Dr",
    "sg:city":"Los Alamitos",
    "sg:classifiers":[
        {
            "category":"Autos & Motor Vehicles",
            "subcategory":"Auto Supplies",
            "type":"Retail Goods"
        }
    ],
    "sg:phone":"+1 714 527 9400",
    "sg:postcode":"90720",
    "sg:province":"CA",
    "sg:tags":[
        "automobile",
        "parts"
    ],
    "wof:name":"Applied Rotor Technology",
    "wof:placetype":"venue"
},
  "geometry": {"coordinates":[-118.057073,33.808325],"type":"Point"}
}