{
  "type": "Feature",
  "properties": {
    "iso:country":"US",
    "sg:address":"4050 International Blvd",
    "sg:city":"Oakland",
    "sg:classifiers":[
        {
            "category":"Banks & Credit Unions",
            "subcategory":"Financial Services",
            "type":"Services"
        }
    ],
    "sg:phone":"+1 510 532 2688",
    "sg:postcode":"94601",
    "sg:province":"CA",
    "sg:tags":[
        "international",
        "trade"
    ],
    "wof:name":"Dall Dall Lay Trading Co",
    "wof:placetype":"venue"
},
  "geometry": {"coordinates":[-122.21677699999999,37.773322],"type":"Point"}
}