{
  "type": "Feature",
  "properties": {
    "addr:full":"660 California St San Francisco CA 94108",
    "addr:housenumber":"660",
    "addr:postcode":"94108",
    "addr:street":"California St",
    "iso:country":"US",
    "sg:address":"660 California St",
    "sg:city":"San Francisco",
    "sg:classifiers":[
        {
            "category":"Shopping",
            "subcategory":"Books",
            "type":"Retail Goods"
        }
    ],
    "sg:phone":"+1 415 288 3844",
    "sg:postcode":"94108",
    "sg:province":"CA",
    "sg:tags":[
        "dealer"
    ],
    "wof:name":"Paulist Center Bookstore",
    "wof:placetype":"venue"
},
  "geometry": {"coordinates":[-122.404951,37.792672],"type":"Point"}
}