{
  "type": "Feature",
  "properties": {
    "iso:country":"US",
    "sg:address":"20639 Hatton St",
    "sg:city":"Winnetka",
    "sg:classifiers":[
        {
            "category":"Wholesale",
            "subcategory":"Sporting Goods",
            "type":"Manufacturing & Wholesale Goods"
        }
    ],
    "sg:phone":"+1 818 340 3927",
    "sg:postcode":"91306",
    "sg:province":"CA",
    "wof:name":"Advanced Aquatic Engineering",
    "wof:placetype":"venue"
},
  "geometry": {"coordinates":[-118.583607,34.209861],"type":"Point"}
}