{
  "type": "Feature",
  "properties": {
    "addr:full":"1530 Main St Ramona CA 92065",
    "addr:housenumber":"1530",
    "addr:postcode":"92065",
    "addr:street":"Main St",
    "iso:country":"US",
    "sg:address":"1530 Main St",
    "sg:city":"Ramona",
    "sg:classifiers":[
        {
            "category":"Personal",
            "subcategory":"Beauty Salon",
            "type":"Services"
        }
    ],
    "sg:phone":"+1 760 789 2729",
    "sg:postcode":"92065",
    "sg:province":"CA",
    "sg:tags":[
        "hair",
        "stylist"
    ],
    "wof:name":"Hair Etc",
    "wof:placetype":"venue"
},
  "geometry": {"coordinates":[-116.876987,33.037371],"type":"Point"}
}