{
  "type": "Feature",
  "properties": {
    "iso:country":"US",
    "sg:address":"5006 Encinita Ave",
    "sg:city":"Temple City",
    "sg:classifiers":[
        {
            "category":"Building & Trades",
            "subcategory":"Construction",
            "type":"Services"
        }
    ],
    "sg:phone":"+1 626 292 7482",
    "sg:postcode":"91780",
    "sg:province":"CA",
    "sg:tags":[
        "maker",
        "cabinet"
    ],
    "wof:name":"Suarez Custom Cabinets",
    "wof:placetype":"venue"
},
  "geometry": {"coordinates":[-118.067897,34.092836],"type":"Point"}
}