{
  "type": "Feature",
  "properties": {
    "addr:full":"2051 Tully Rd Modesto CA 95350",
    "addr:housenumber":"2051",
    "addr:postcode":"ca 95350",
    "addr:street":"Tully Rd",
    "iso:country":"US",
    "sg:address":"2051 Tully Rd",
    "sg:city":"Modesto",
    "sg:classifiers":[
        {
            "category":"Shopping",
            "type":"Retail Goods"
        }
    ],
    "sg:phone":"+1 209 492 0917",
    "sg:postcode":"95350",
    "sg:province":"CA",
    "wof:name":"DD's Discounts",
    "wof:placetype":"venue"
},
  "geometry": {"coordinates":[-121.012283,37.673593],"type":"Point"}
}