{
  "type": "Feature",
  "properties": {
    "iso:country":"US",
    "sg:address":"3535 Stine Rd",
    "sg:city":"Bakersfield",
    "sg:classifiers":[
        {
            "category":"Professional",
            "type":"Services"
        }
    ],
    "sg:phone":"+1 661 833 2619",
    "sg:postcode":"93309",
    "sg:province":"CA",
    "wof:name":"Karen Brown Indvdlly As A Prtn",
    "wof:placetype":"venue"
},
  "geometry": {"coordinates":[-119.056746,35.324478],"type":"Point"}
}