{
  "type": "Feature",
  "properties": {
    "addr:full":"721 E 12th Street Los Angeles CA 90021",
    "addr:housenumber":"721",
    "addr:postcode":"90021",
    "addr:street":"E 12Th Street",
    "iso:country":"US",
    "sg:address":"721 E 12th Street",
    "sg:city":"Los Angeles",
    "sg:classifiers":[
        {
            "category":"Shopping",
            "subcategory":"Clothing, Apparel, & Fashions",
            "type":"Retail Goods"
        }
    ],
    "sg:phone":"+1 213 746 4363",
    "sg:postcode":"90021",
    "sg:province":"CA",
    "sg:tags":[
        "clothing",
        "women's"
    ],
    "wof:name":"Christiana",
    "wof:placetype":"venue"
},
  "geometry": {"coordinates":[-118.25232099999999,34.033223],"type":"Point"}
}