{
  "type": "Feature",
  "properties": {
    "addr:full":"376 Grand Ave Oakland CA 94610",
    "addr:housenumber":"376",
    "addr:postcode":"94610",
    "addr:street":"Grand Ave",
    "iso:country":"US",
    "sg:address":"376 Grand Ave",
    "sg:city":"Oakland",
    "sg:classifiers":[
        {
            "category":"Personal",
            "subcategory":"Beauty Salon",
            "type":"Services"
        }
    ],
    "sg:phone":"+1 510 502 1266",
    "sg:postcode":"94610",
    "sg:province":"CA",
    "sg:tags":[
        "hair"
    ],
    "wof:name":"Ora Tifffany's Salon",
    "wof:placetype":"venue"
},
  "geometry": {"coordinates":[-122.25487699999999,37.809181],"type":"Point"}
}