{
  "type": "Feature",
  "properties": {
    "iso:country":"US",
    "sg:address":"250 S Hillview Dr",
    "sg:city":"Milpitas",
    "sg:classifiers":[
        {
            "category":"Manufacturing",
            "subcategory":"Printing",
            "type":"Manufacturing & Wholesale Goods"
        }
    ],
    "sg:phone":"+1 408 262 8455",
    "sg:postcode":"95035",
    "sg:province":"CA",
    "sg:tags":[
        "printer"
    ],
    "wof:name":"Hillview Printing & Copy Ctr",
    "wof:placetype":"venue"
},
  "geometry": {"coordinates":[-121.89252999999999,37.431261],"type":"Point"}
}