{
  "type": "Feature",
  "properties": {
    "iso:country":"US",
    "sg:address":"2441 W 205th St",
    "sg:city":"Torrance",
    "sg:classifiers":[
        {
            "category":"Home & Garden",
            "subcategory":"Building Materials",
            "type":"Retail Goods"
        }
    ],
    "sg:phone":"+1 310 787 2310",
    "sg:postcode":"90501",
    "sg:province":"CA",
    "sg:tags":[
        "door"
    ],
    "sg:website":"www.amidoors.com",
    "wof:name":"AMI Doors & Equipment",
    "wof:placetype":"venue"
},
  "geometry": {"coordinates":[-118.32435700000001,33.845407],"type":"Point"}
}