{
  "type": "Feature",
  "properties": {
    "iso:country":"US",
    "sg:address":"545 E Miner Ave",
    "sg:city":"Stockton",
    "sg:classifiers":[
        {
            "category":"Retail",
            "subcategory":"Auto Repair",
            "type":"Services"
        }
    ],
    "sg:phone":"+1 209 466 2568",
    "sg:postcode":"95202",
    "sg:province":"CA",
    "sg:tags":[
        "repairing",
        "automobile"
    ],
    "wof:name":"Chet's Auto Svc & Repair",
    "wof:placetype":"venue"
},
  "geometry": {"coordinates":[-121.28416900000001,37.956859],"type":"Point"}
}