{
  "type": "Feature",
  "properties": {
    "addr:full":"524 W Commonwealth Ave Ste L Fullerton CA 92832",
    "addr:housenumber":"524",
    "addr:postcode":"92832",
    "addr:street":"W Commonwealth Ave Ste L",
    "iso:country":"US",
    "sg:address":"524 W Commonwealth Ave Ste L",
    "sg:city":"Fullerton",
    "sg:classifiers":[
        {
            "category":"Professional",
            "subcategory":"Computer Services",
            "type":"Services"
        }
    ],
    "sg:phone":"+1 714 871 4122",
    "sg:postcode":"92832",
    "sg:province":"CA",
    "sg:tags":[
        "repair"
    ],
    "wof:name":"Cal Computer International",
    "wof:placetype":"venue"
},
  "geometry": {"coordinates":[-117.933998,33.870201],"type":"Point"}
}