{
  "type": "Feature",
  "properties": {
    "iso:country":"US",
    "sg:address":"52050 Industrial Way",
    "sg:city":"Coachella",
    "sg:classifiers":[
        {
            "category":"Home & Garden",
            "subcategory":"Building Materials",
            "type":"Retail Goods"
        },
        {
            "category":"Building & Trades",
            "subcategory":"Construction",
            "type":"Services"
        }
    ],
    "sg:phone":"+1 760 398 8293",
    "sg:postcode":"92236",
    "sg:province":"CA",
    "sg:tags":[
        "top",
        "counter",
        "improvement",
        "tile-contractors",
        "granite",
        "contractor",
        "mason"
    ],
    "sg:website":"http://santarosamg.com",
    "wof:name":"J & G Santa Rosa Marble & Granite, Inc.",
    "wof:placetype":"venue"
},
  "geometry": {"coordinates":[-116.16267999999999,33.670789],"type":"Point"}
}