{
  "type": "Feature",
  "properties": {
    "iso:country":"US",
    "sg:address":"4636 Vineta Ave",
    "sg:city":"La Canada Flintridge",
    "sg:classifiers":[
        {
            "category":"Banks & Credit Unions",
            "subcategory":"Financial Services",
            "type":"Services"
        }
    ],
    "sg:phone":"+1 818 952 8600",
    "sg:postcode":"91011",
    "sg:province":"CA",
    "sg:tags":[
        "broker",
        "mortgage"
    ],
    "wof:name":"Showcase Properties",
    "wof:placetype":"venue"
},
  "geometry": {"coordinates":[-118.187504,34.202127],"type":"Point"}
}