{
  "type": "Feature",
  "properties": {
    "iso:country":"US",
    "sg:address":"2247 Old Middlefield Way Ste B",
    "sg:city":"Mountain View",
    "sg:classifiers":[
        {
            "category":"Retail",
            "subcategory":"Auto Repair",
            "type":"Services"
        }
    ],
    "sg:phone":"+1 650 694 7987",
    "sg:postcode":"94043",
    "sg:province":"CA",
    "sg:website":"lousauto.com",
    "wof:name":"Lou's Automotive",
    "wof:placetype":"venue"
},
  "geometry": {"coordinates":[-122.095973,37.413871],"type":"Point"}
}