{
  "type": "Feature",
  "properties": {
    "iso:country":"US",
    "sg:address":"384 Miller Ave",
    "sg:city":"Mill Valley",
    "sg:classifiers":[
        {
            "category":"Food & Beverages",
            "subcategory":"Specialty",
            "type":"Retail Goods"
        }
    ],
    "sg:phone":"+1 415 388 4600",
    "sg:postcode":"94941",
    "sg:province":"CA",
    "sg:tags":[
        "tea",
        "coffee"
    ],
    "wof:name":"Phillips Coffee & Tea",
    "wof:placetype":"venue"
},
  "geometry": {"coordinates":[-122.536377,37.89683],"type":"Point"}
}