{
  "type": "Feature",
  "properties": {
    "addr:full":"3463 Sassafras Dr San Jose CA 95111",
    "addr:housenumber":"3463",
    "addr:postcode":"95111",
    "addr:street":"Sassafras Dr",
    "iso:country":"US",
    "sg:address":"3463 Sassafras Dr",
    "sg:city":"San Jose",
    "sg:classifiers":[
        {
            "category":"Building & Trades",
            "subcategory":"Construction",
            "type":"Services"
        }
    ],
    "sg:phone":"+1 408 661 3528",
    "sg:postcode":"95111",
    "sg:province":"CA",
    "sg:tags":[
        "handyman"
    ],
    "wof:name":"Do It All Handyman Svc",
    "wof:placetype":"venue"
},
  "geometry": {"coordinates":[-121.83029500000001,37.28883],"type":"Point"}
}