{
  "type": "Feature",
  "properties": {
    "addr:full":"1165 Airport Blvd South San Francisco CA 94080",
    "addr:housenumber":"1165",
    "addr:postcode":"94080",
    "addr:street":"Airport Blvd",
    "iso:country":"US",
    "sg:address":"1165 Airport Blvd",
    "sg:city":"South San Francisco",
    "sg:classifiers":[
        {
            "category":"Restaurant",
            "type":"Food & Drink"
        }
    ],
    "sg:phone":"+1 650 763 1025",
    "sg:postcode":"94080",
    "sg:province":"CA",
    "sg:tags":[
        "brazilian"
    ],
    "sg:website":"www.cafedicasa.net",
    "wof:name":"Cafe di Casa",
    "wof:placetype":"venue"
},
  "geometry": {"coordinates":[-122.40009999999999,37.664016],"type":"Point"}
}