{
  "type": "Feature",
  "properties": {
    "addr:full":"110 Asher Ave Taft CA 93268",
    "addr:housenumber":"110",
    "addr:postcode":"93268",
    "addr:street":"Asher Ave",
    "iso:country":"US",
    "sg:address":"110 Asher Ave",
    "sg:city":"Taft",
    "sg:classifiers":[
        {
            "category":"Social Services",
            "type":"Services"
        }
    ],
    "sg:phone":"+1 661 763 4888",
    "sg:postcode":"93268",
    "sg:province":"CA",
    "sg:tags":[
        "organization",
        "welfare"
    ],
    "wof:name":"NEEDS Ctr",
    "wof:placetype":"venue"
},
  "geometry": {"coordinates":[-119.45989299999999,35.136749],"type":"Point"}
}