{
  "type": "Feature",
  "properties": {
    "iso:country":"US",
    "sg:address":"16776 Bernardo Center Dr",
    "sg:city":"San Diego",
    "sg:classifiers":[
        {
            "category":"Real Estate",
            "subcategory":"Real Estate Agent",
            "type":"Services"
        }
    ],
    "sg:phone":"+1 858 485 8184",
    "sg:postcode":"92128",
    "sg:province":"CA",
    "sg:website":"www.c21paradigm.com",
    "wof:name":"Century 21",
    "wof:placetype":"venue"
},
  "geometry": {"coordinates":[-117.076049,33.017077],"type":"Point"}
}