{
  "type": "Feature",
  "properties": {
    "iso:country":"US",
    "sg:address":"3447 Investment Blvd Ste 5",
    "sg:city":"Hayward",
    "sg:classifiers":[
        {
            "category":"Building & Trades",
            "subcategory":"Construction",
            "type":"Services"
        }
    ],
    "sg:phone":"+1 510 886 4771",
    "sg:postcode":"94545",
    "sg:province":"CA",
    "sg:tags":[
        "handyman",
        "contractor"
    ],
    "sg:website":"www.homeremodelingsolutions.net",
    "wof:name":"Home Remodeling Solutions",
    "wof:placetype":"venue"
},
  "geometry": {"coordinates":[-122.118859,37.625703],"type":"Point"}
}