{
  "type": "Feature",
  "properties": {
    "iso:country":"US",
    "sg:address":"9275 Sky Park Ct",
    "sg:city":"San Diego",
    "sg:classifiers":[
        {
            "category":"Coffee & Tea",
            "type":"Food & Drink"
        },
        {
            "category":"Deli",
            "type":"Food & Drink"
        }
    ],
    "sg:phone":"+1 858 277 9275",
    "sg:postcode":"92123",
    "sg:province":"CA",
    "sg:website":"www.goodonyadeli.com",
    "wof:name":"GoodOnYa",
    "wof:placetype":"venue"
},
  "geometry": {"coordinates":[-117.12469900000001,32.815776],"type":"Point"}
}