{
  "type": "Feature",
  "properties": {
    "addr:full":"3167 Verdugo Rd Los Angeles CA 90065",
    "addr:housenumber":"3167",
    "addr:postcode":"90065",
    "addr:street":"Verdugo Rd",
    "iso:country":"US",
    "sg:address":"3167 Verdugo Rd",
    "sg:city":"Los Angeles",
    "sg:classifiers":[
        {
            "category":"Professional",
            "subcategory":"Printing & Photocopies",
            "type":"Services"
        }
    ],
    "sg:phone":"+1 818 956 8322",
    "sg:postcode":"90065",
    "sg:province":"CA",
    "sg:tags":[
        "binding"
    ],
    "wof:name":"West Coast Binding",
    "wof:placetype":"venue"
},
  "geometry": {"coordinates":[-118.23616,34.111561],"type":"Point"}
}