{
  "type": "Feature",
  "properties": {
    "addr:full":"2186 Geary Blvd. Ste 214 San Francisco CA 94199",
    "addr:housenumber":"2186",
    "addr:postcode":"94199",
    "addr:street":"Geary Blvd. Ste 214",
    "iso:country":"US",
    "sg:address":"2186 Geary Blvd. Ste 214",
    "sg:city":"San Francisco",
    "sg:classifiers":[
        {
            "category":"Health Services",
            "subcategory":"Doctor",
            "type":"Services"
        }
    ],
    "sg:phone":"+1 415 922 3255",
    "sg:postcode":"94199",
    "sg:province":"CA",
    "wof:name":"Stuart M Rosenberg, MD",
    "wof:placetype":"venue"
},
  "geometry": {"coordinates":[-122.43929300000001,37.783699],"type":"Point"}
}