{
  "type": "Feature",
  "properties": {
    "addr:full":"111 W Bastanchury Rd Fullerton CA 92835",
    "addr:housenumber":"111",
    "addr:postcode":"92835",
    "addr:street":"W Bastanchury Rd",
    "iso:country":"US",
    "sg:address":"111 W Bastanchury Rd",
    "sg:city":"Fullerton",
    "sg:classifiers":[
        {
            "category":"Banks & Credit Unions",
            "subcategory":"Bank",
            "type":"Services"
        }
    ],
    "sg:phone":"+1 714 449 7744",
    "sg:postcode":"92835",
    "sg:province":"CA",
    "sg:tags":[
        "escrow"
    ],
    "sg:website":"www.leaderescrow.com",
    "wof:name":"Leader Escrow",
    "wof:placetype":"venue"
},
  "geometry": {"coordinates":[-117.93052,33.89466],"type":"Point"}
}