{
  "type": "Feature",
  "properties": {
    "addr:full":"15030 Ventura Blvd Sherman Oaks CA 91403",
    "addr:housenumber":"15030",
    "addr:postcode":"91403",
    "addr:street":"Ventura Blvd",
    "iso:country":"US",
    "sg:address":"15030 Ventura Blvd",
    "sg:city":"Sherman Oaks",
    "sg:classifiers":[
        {
            "category":"Personal",
            "subcategory":"Beauty Salon",
            "type":"Services"
        }
    ],
    "sg:phone":"+1 818 995 8303",
    "sg:postcode":"91403",
    "sg:province":"CA",
    "wof:name":"Michael Joseph Furie Salon",
    "wof:placetype":"venue"
},
  "geometry": {"coordinates":[-118.46113099999999,34.152882],"type":"Point"}
}