{
  "type": "Feature",
  "properties": {
    "addr:full":"223 Dennis Drive Daly City CA 94015",
    "addr:housenumber":"223",
    "addr:postcode":"94015",
    "addr:street":"Dennis Drive",
    "iso:country":"US",
    "sg:address":"223 Dennis Drive",
    "sg:city":"Daly City",
    "sg:classifiers":[
        {
            "category":"Taxi",
            "type":"Transportation"
        },
        {
            "category":"Airline",
            "type":"Transportation"
        }
    ],
    "sg:phone":"+1 650 878 0251",
    "sg:postcode":"94015",
    "sg:province":"CA",
    "sg:tags":[
        "shuttle",
        "airport"
    ],
    "wof:name":"Any Limo",
    "wof:placetype":"venue"
},
  "geometry": {"coordinates":[-122.46134600000001,37.65298],"type":"Point"}
}