{
  "type": "Feature",
  "properties": {
    "addr:full":"2450 White Rd Irvine CA 92614",
    "addr:housenumber":"2450",
    "addr:postcode":"92614",
    "addr:street":"White Rd",
    "iso:country":"US",
    "sg:address":"2450 White Rd",
    "sg:city":"Irvine",
    "sg:classifiers":[
        {
            "category":"Banks & Credit Unions",
            "subcategory":"Bank",
            "type":"Services"
        }
    ],
    "sg:phone":"+1 949 419 0232",
    "sg:postcode":"92614",
    "sg:province":"CA",
    "sg:tags":[
        "escrow"
    ],
    "wof:name":"Main Street Escrow",
    "wof:placetype":"venue"
},
  "geometry": {"coordinates":[-117.842072,33.679336],"type":"Point"}
}