{
  "type": "Feature",
  "properties": {
    "iso:country":"US",
    "sg:address":"418 Broad St",
    "sg:city":"Nevada City",
    "sg:classifiers":[
        {
            "category":"Shopping",
            "subcategory":"Used Merchandise",
            "type":"Retail Goods"
        }
    ],
    "sg:phone":"+1 530 265 0241",
    "sg:postcode":"95959",
    "sg:province":"CA",
    "sg:tags":[
        "book",
        "rare",
        "dealer"
    ],
    "wof:name":"Mountain House Books",
    "wof:placetype":"venue"
},
  "geometry": {"coordinates":[-121.021194,39.263882],"type":"Point"}
}