{
  "type": "Feature",
  "properties": {
    "addr:full":"5303 Holt Blvd Montclair CA 91763",
    "addr:housenumber":"5303",
    "addr:postcode":"91763",
    "addr:street":"Holt Blvd",
    "iso:country":"US",
    "sg:address":"5303 Holt Blvd",
    "sg:city":"Montclair",
    "sg:classifiers":[
        {
            "category":"Personal",
            "subcategory":"Beauty Salon",
            "type":"Services"
        }
    ],
    "sg:phone":"+1 909 399 5848",
    "sg:postcode":"91763",
    "sg:province":"CA",
    "wof:name":"Salon 909",
    "wof:placetype":"venue"
},
  "geometry": {"coordinates":[-117.687775,34.06318],"type":"Point"}
}