{
  "type": "Feature",
  "properties": {
    "iso:country":"US",
    "sg:address":"1517 Cabrillo Ave",
    "sg:city":"Torrance",
    "sg:classifiers":[
        {
            "category":"Retail",
            "subcategory":"Self-service Laundry",
            "type":"Services"
        }
    ],
    "sg:phone":"+1 310 328 7353",
    "sg:postcode":"90501",
    "sg:province":"CA",
    "sg:tags":[
        "dry",
        "cleaning"
    ],
    "wof:name":"J D Coin Laundry",
    "wof:placetype":"venue"
},
  "geometry": {"coordinates":[-118.31448399999999,33.832835],"type":"Point"}
}