{
  "type": "Feature",
  "properties": {
    "iso:country":"US",
    "sg:address":"1459 Humboldt Rd",
    "sg:city":"Chico",
    "sg:classifiers":[
        {
            "category":"Social Services",
            "type":"Services"
        }
    ],
    "sg:phone":"+1 530 893 5650",
    "sg:postcode":"95928",
    "sg:province":"CA",
    "sg:tags":[
        "organization",
        "welfare"
    ],
    "wof:name":"Living & Loving Project",
    "wof:placetype":"venue"
},
  "geometry": {"coordinates":[-121.807238,39.737166],"type":"Point"}
}