{
  "type": "Feature",
  "properties": {
    "addr:full":"25000 W Ave Stanford Valencia CA 91355",
    "addr:housenumber":"25000",
    "addr:postcode":"91355",
    "addr:street":"W Ave",
    "iso:country":"US",
    "sg:address":"25000 W Ave Stanford",
    "sg:city":"Valencia",
    "sg:classifiers":[
        {
            "category":"Professional",
            "type":"Services"
        }
    ],
    "sg:phone":"+1 661 702 9434",
    "sg:postcode":"91355",
    "sg:province":"CA",
    "wof:name":"Semi Net Inc",
    "wof:placetype":"venue"
},
  "geometry": {"coordinates":[-118.57507,34.436651],"type":"Point"}
}