{
  "type": "Feature",
  "properties": {
    "addr:full":"308 N Chester Ave Pasadena CA 91106",
    "addr:housenumber":"308",
    "addr:postcode":"91106",
    "addr:street":"N Chester Ave",
    "iso:country":"US",
    "sg:address":"308 N Chester Ave",
    "sg:city":"Pasadena",
    "sg:classifiers":[
        {
            "category":"Professional",
            "subcategory":"Business Services",
            "type":"Services"
        }
    ],
    "sg:phone":"+1 626 795 7507",
    "sg:postcode":"91106",
    "sg:province":"CA",
    "wof:name":"Barbara Tharp & Assoc",
    "wof:placetype":"venue"
},
  "geometry": {"coordinates":[-118.124222,34.150576],"type":"Point"}
}