{
  "type": "Feature",
  "properties": {
    "addr:full":"19930 Collier Ave Lake Elsinore CA 92530",
    "addr:housenumber":"19930",
    "addr:postcode":"92530",
    "addr:street":"Collier Ave",
    "iso:country":"US",
    "sg:address":"19930 Collier Ave",
    "sg:city":"Lake Elsinore",
    "sg:classifiers":[
        {
            "category":"Food & Beverages",
            "subcategory":"Groceries & Convenience Stores",
            "type":"Retail Goods"
        }
    ],
    "sg:phone":"+1 951 471 1520",
    "sg:postcode":"92530",
    "sg:province":"CA",
    "wof:name":"Rts Partnership",
    "wof:placetype":"venue"
},
  "geometry": {"coordinates":[-117.327003,33.678299],"type":"Point"}
}