{
  "type": "Feature",
  "properties": {
    "iso:country":"US",
    "sg:address":"3001 Capitol Ave",
    "sg:city":"Sacramento",
    "sg:classifiers":[
        {
            "category":"Banks & Credit Unions",
            "subcategory":"Bank",
            "type":"Services"
        }
    ],
    "sg:phone":"+1 916 440 4904",
    "sg:postcode":"95816",
    "sg:province":"CA",
    "wof:name":"Wells Fargo Bank",
    "wof:placetype":"venue"
},
  "geometry": {"coordinates":[-121.466652,38.569448],"type":"Point"}
}