{
  "type": "Feature",
  "properties": {
    "iso:country":"US",
    "sg:address":"1352 6th St",
    "sg:city":"Los Osos",
    "sg:classifiers":[
        {
            "category":"Building & Trades",
            "subcategory":"Construction",
            "type":"Services"
        }
    ],
    "sg:phone":"+1 805 534 0417",
    "sg:postcode":"93402",
    "sg:province":"CA",
    "sg:tags":[
        "residential"
    ],
    "wof:name":"Artisan Woodworks",
    "wof:placetype":"venue"
},
  "geometry": {"coordinates":[-120.836459,35.3271],"type":"Point"}
}