{
  "type": "Feature",
  "properties": {
    "addr:full":"3415 Chino Ave Chino CA 91710",
    "addr:housenumber":"3415",
    "addr:postcode":"91710",
    "addr:street":"Chino Ave",
    "iso:country":"US",
    "sg:address":"3415 Chino Ave",
    "sg:city":"Chino",
    "sg:classifiers":[
        {
            "category":"Animal Shelter",
            "type":"Public Place"
        },
        {
            "category":"Shopping",
            "subcategory":"Pets & Pet Supplies",
            "type":"Retail Goods"
        },
        {
            "category":"Retail",
            "subcategory":"Veterinary Services",
            "type":"Services"
        }
    ],
    "sg:phone":"+1 909 591 1805",
    "sg:postcode":"91710",
    "sg:province":"CA",
    "sg:tags":[
        "hospital",
        "dog",
        "cat",
        "clinic",
        "veterinarian",
        "grooming",
        "kennel"
    ],
    "sg:website":"http://www.chinohillssmallanimalhospital.com",
    "wof:name":"Chino Hills Small Animal Hospital",
    "wof:placetype":"venue"
},
  "geometry": {"coordinates":[-117.730495,34.011568],"type":"Point"}
}