{
  "type": "Feature",
  "properties": {
    "iso:country":"US",
    "sg:address":"151 N Robertson Boulevard",
    "sg:city":"Beverly Hills",
    "sg:classifiers":[
        {
            "category":"Building & Trades",
            "subcategory":"Construction",
            "type":"Services"
        }
    ],
    "sg:phone":"+1 310 659 0030",
    "sg:postcode":"90211",
    "sg:province":"CA",
    "sg:tags":[
        "interior",
        "design"
    ],
    "wof:name":"M A Glatt & Associates.",
    "wof:placetype":"venue"
},
  "geometry": {"coordinates":[-118.383861,34.068233],"type":"Point"}
}