{
  "type": "Feature",
  "properties": {
    "iso:country":"US",
    "sg:address":"1324 5th St",
    "sg:city":"Santa Monica",
    "sg:classifiers":[
        {
            "category":"Education",
            "subcategory":"Library",
            "type":"Public Place"
        }
    ],
    "sg:phone":"+1 310 458 8600",
    "sg:postcode":"90401",
    "sg:province":"CA",
    "sg:website":"www.smplkids.net",
    "wof:name":"Santa Monica Public Library",
    "wof:placetype":"venue"
},
  "geometry": {"coordinates":[-118.49458300000001,34.017452],"type":"Point"}
}