{
  "type": "Feature",
  "properties": {
    "addr:full":"5071 Rodeo Circle Antioch CA 94531",
    "addr:housenumber":"5071",
    "addr:postcode":"ca 94531",
    "addr:street":"Rodeo Circle",
    "iso:country":"US",
    "sg:address":"5071 Rodeo Circle",
    "sg:city":"Antioch",
    "sg:classifiers":[
        {
            "category":"Professional",
            "subcategory":"Research",
            "type":"Services"
        }
    ],
    "sg:postcode":"94531",
    "sg:province":"CA",
    "sg:tags":[
        "energy-savings",
        "energy-monitoring",
        "energy-efficiency",
        "guaranteed-energy-savings"
    ],
    "sg:website":"http://www.econexusinc.com",
    "wof:name":"EcoNexus",
    "wof:placetype":"venue"
},
  "geometry": {"coordinates":[-121.75884000000001,37.969107],"type":"Point"}
}