{
  "type": "Feature",
  "properties": {
    "iso:country":"US",
    "sg:address":"4565 Ruffner St",
    "sg:city":"San Diego",
    "sg:classifiers":[
        {
            "category":"Real Estate",
            "subcategory":"Real Estate Services",
            "type":"Services"
        }
    ],
    "sg:phone":"+1 858 278 1125",
    "sg:postcode":"92111",
    "sg:province":"CA",
    "wof:name":"Kim Jae Real Estate Agent",
    "wof:placetype":"venue"
},
  "geometry": {"coordinates":[-117.15711,32.823661],"type":"Point"}
}