{
  "type": "Feature",
  "properties": {
    "addr:full":"15164 Montalvo Rd Saratoga CA 95070",
    "addr:housenumber":"15164",
    "addr:postcode":"95070",
    "addr:street":"Montalvo Rd",
    "iso:country":"US",
    "sg:address":"15164 Montalvo Rd",
    "sg:city":"Saratoga",
    "sg:classifiers":[
        {
            "category":"Shopping",
            "subcategory":"Gifts & Souvenirs",
            "type":"Retail Goods"
        }
    ],
    "sg:phone":"+1 408 867 1811",
    "sg:postcode":"95070",
    "sg:province":"CA",
    "sg:tags":[
        "shop"
    ],
    "wof:name":"Bambi's",
    "wof:placetype":"venue"
},
  "geometry": {"coordinates":[-122.029308,37.247425],"type":"Point"}
}