{
  "type": "Feature",
  "properties": {
    "addr:full":"3915 Palazzo Ct Stockton CA 95212",
    "addr:housenumber":"3915",
    "addr:postcode":"95212",
    "addr:street":"Palazzo Ct",
    "iso:country":"US",
    "sg:address":"3915 Palazzo Ct",
    "sg:city":"Stockton",
    "sg:classifiers":[
        {
            "category":"Building & Trades",
            "subcategory":"Electrical",
            "type":"Services"
        }
    ],
    "sg:phone":"+1 209 423 3333",
    "sg:postcode":"95212",
    "sg:province":"CA",
    "sg:tags":[
        "electrician"
    ],
    "wof:name":"Ricardo H Cortez Electric",
    "wof:placetype":"venue"
},
  "geometry": {"coordinates":[-121.263071,38.038342],"type":"Point"}
}