{
  "type": "Feature",
  "properties": {
    "addr:full":"7971 N Blackstone Ave Fresno CA 93720",
    "addr:housenumber":"7971",
    "addr:postcode":"93720",
    "addr:street":"N Blackstone Ave",
    "iso:country":"US",
    "sg:address":"7971 N Blackstone Ave",
    "sg:city":"Fresno",
    "sg:classifiers":[
        {
            "category":"Ice Cream",
            "type":"Food & Drink"
        }
    ],
    "sg:menulink":"http://www.allmenus.com/ca/fresno/183836-cold-stone-creamery/menu/",
    "sg:phone":"+1 559 449 8155",
    "sg:postcode":"93720",
    "sg:province":"CA",
    "sg:tags":[
        "smoothy",
        "juice",
        "american"
    ],
    "wof:name":"Cold Stone Creamery",
    "wof:placetype":"venue"
},
  "geometry": {"coordinates":[-119.791051,36.851354],"type":"Point"}
}