{
  "type": "Feature",
  "properties": {
    "iso:country":"US",
    "sg:address":"1213 Grass Valley Hwy",
    "sg:city":"Auburn",
    "sg:classifiers":[
        {
            "category":"Retail",
            "subcategory":"Portrait Studio",
            "type":"Services"
        }
    ],
    "sg:phone":"+1 530 823 3686",
    "sg:postcode":"95603",
    "sg:province":"CA",
    "sg:tags":[
        "photographer"
    ],
    "wof:name":"Images In Photography",
    "wof:placetype":"venue"
},
  "geometry": {"coordinates":[-121.083745,38.923599],"type":"Point"}
}