{
  "type": "Feature",
  "properties": {
    "addr:full":"460 5th Ave Gaslamp Quarter San Diego CA 92101",
    "addr:housenumber":"460",
    "addr:postcode":"92101",
    "addr:street":"5Th Ave",
    "iso:country":"US",
    "sg:address":"460 5th Ave Gaslamp Quarter",
    "sg:city":"San Diego",
    "sg:classifiers":[
        {
            "category":"Shopping",
            "subcategory":"Optician",
            "type":"Retail Goods"
        }
    ],
    "sg:phone":"+1 619 231 0192",
    "sg:postcode":"92101",
    "sg:province":"CA",
    "sg:tags":[
        "eyewear"
    ],
    "wof:name":"Oakley Store",
    "wof:placetype":"venue"
},
  "geometry": {"coordinates":[-117.160104,32.710015],"type":"Point"}
}