{
  "type": "Feature",
  "properties": {
    "iso:country":"US",
    "sg:address":"4148 Kilt Cir",
    "sg:city":"El Dorado Hills",
    "sg:classifiers":[
        {
            "category":"Wholesale",
            "subcategory":"Durable Goods & Equipment",
            "type":"Manufacturing & Wholesale Goods"
        }
    ],
    "sg:phone":"+1 916 939 4433",
    "sg:postcode":"95762",
    "sg:province":"CA",
    "sg:tags":[
        "importer"
    ],
    "wof:name":"Grand Effect",
    "wof:placetype":"venue"
},
  "geometry": {"coordinates":[-121.065292,38.709252],"type":"Point"}
}