{
  "type": "Feature",
  "properties": {
    "addr:full":"2870 Gold Tailings Court Rancho Cordova CA 95670",
    "addr:housenumber":"2870",
    "addr:postcode":"95670",
    "addr:street":"Gold Tailings Court",
    "iso:country":"US",
    "sg:address":"2870 Gold Tailings Court",
    "sg:city":"Rancho Cordova",
    "sg:classifiers":[
        {
            "category":"Professional",
            "subcategory":"Accounting & Tax Preparation",
            "type":"Services"
        }
    ],
    "sg:phone":"+1 916 638 1188",
    "sg:postcode":"95670",
    "sg:province":"CA",
    "sg:tags":[
        "accountant"
    ],
    "wof:name":"Walden James P",
    "wof:placetype":"venue"
},
  "geometry": {"coordinates":[-121.26794,38.598133],"type":"Point"}
}