{
  "type": "Feature",
  "properties": {
    "iso:country":"US",
    "sg:address":"330 Primrose Rd Ste 402",
    "sg:city":"Burlingame",
    "sg:classifiers":[
        {
            "category":"Professional",
            "subcategory":"Management & Consulting",
            "type":"Services"
        },
        {
            "category":"Professional",
            "subcategory":"Employment Agencies",
            "type":"Services"
        }
    ],
    "sg:phone":"+1 650 685 2600",
    "sg:postcode":"94010",
    "sg:province":"CA",
    "sg:tags":[
        "consultant",
        "search",
        "executive",
        "opportunity"
    ],
    "wof:name":"Trilogy Venture Search",
    "wof:placetype":"venue"
},
  "geometry": {"coordinates":[-122.34829999999999,37.577948],"type":"Point"}
}