{
  "type": "Feature",
  "properties": {
    "iso:country":"US",
    "sg:address":"999 Commercial St",
    "sg:city":"Palo Alto",
    "sg:classifiers":[
        {
            "category":"Local Transit",
            "type":"Transportation"
        }
    ],
    "sg:phone":"+1 650 320 0055",
    "sg:postcode":"94303",
    "sg:province":"CA",
    "sg:tags":[
        "limousine"
    ],
    "wof:name":"Corporate Airport Trnsprtn Svc",
    "wof:placetype":"venue"
},
  "geometry": {"coordinates":[-122.10025,37.421769],"type":"Point"}
}