{
  "type": "Feature",
  "properties": {
    "addr:full":"150 Santa Clara Ave Oakland CA 94610",
    "addr:housenumber":"150",
    "addr:postcode":"94610",
    "addr:street":"Santa Clara Ave",
    "iso:country":"US",
    "sg:address":"150 Santa Clara Ave",
    "sg:city":"Oakland",
    "sg:classifiers":[
        {
            "category":"Food & Beverages",
            "subcategory":"Bakery",
            "type":"Retail Goods"
        }
    ],
    "sg:phone":"+1 510 428 1822",
    "sg:postcode":"94610",
    "sg:province":"CA",
    "sg:tags":[
        "cake",
        "baker",
        "pastry",
        "wedding"
    ],
    "sg:website":"www.ladyfingersbakery.com",
    "wof:name":"Ladyfingers Bakery",
    "wof:placetype":"venue"
},
  "geometry": {"coordinates":[-122.253077,37.818822],"type":"Point"}
}