{
  "type": "Feature",
  "properties": {
    "iso:country":"US",
    "sg:address":"1415 Lawrence Dr",
    "sg:city":"Newbury Park",
    "sg:classifiers":[
        {
            "category":"Wholesale",
            "subcategory":"Electrical",
            "type":"Manufacturing & Wholesale Goods"
        }
    ],
    "sg:phone":"+1 805 499 0377",
    "sg:postcode":"91320",
    "sg:province":"CA",
    "sg:tags":[
        "equipment",
        "contractor"
    ],
    "wof:name":"Light & Sound Design",
    "wof:placetype":"venue"
},
  "geometry": {"coordinates":[-118.929848,34.194217],"type":"Point"}
}