{
  "type": "Feature",
  "properties": {
    "addr:full":"1133 Columbia St San Diego CA 92101",
    "addr:housenumber":"1133",
    "addr:postcode":"92101",
    "addr:street":"Columbia St",
    "iso:country":"US",
    "sg:address":"1133 Columbia St",
    "sg:city":"San Diego",
    "sg:classifiers":[
        {
            "category":"Professional",
            "subcategory":"Lawyer & Legal Services",
            "type":"Services"
        }
    ],
    "sg:phone":"+1 619 238 5600",
    "sg:postcode":"92101",
    "sg:province":"CA",
    "sg:tags":[
        "divorce",
        "law",
        "family"
    ],
    "wof:name":"Absolute Executive",
    "wof:placetype":"venue"
},
  "geometry": {"coordinates":[-117.16724600000001,32.717361],"type":"Point"}
}