{
  "type": "Feature",
  "properties": {
    "iso:country":"US",
    "sg:address":"1965 Georgetta Dr",
    "sg:city":"San Jose",
    "sg:classifiers":[
        {
            "category":"Real Estate",
            "subcategory":"Real Estate Agent",
            "type":"Services"
        }
    ],
    "sg:phone":"+1 408 269 8181",
    "sg:postcode":"95125",
    "sg:province":"CA",
    "wof:name":"Midstate Equipment",
    "wof:placetype":"venue"
},
  "geometry": {"coordinates":[-121.909609,37.285012],"type":"Point"}
}