{
  "type": "Feature",
  "properties": {
    "iso:country":"US",
    "sg:address":"21414 Grace Ave",
    "sg:city":"Carson",
    "sg:classifiers":[
        {
            "category":"Wholesale",
            "subcategory":"Plants",
            "type":"Manufacturing & Wholesale Goods"
        },
        {
            "category":"Farming",
            "subcategory":"Nursery",
            "type":"Manufacturing & Wholesale Goods"
        }
    ],
    "sg:phone":"+1 310 834 2925",
    "sg:postcode":"90745",
    "sg:province":"CA",
    "sg:tags":[
        "tree",
        "grower",
        "stock"
    ],
    "wof:name":"Sugimoto Nursery Inc",
    "wof:placetype":"venue"
},
  "geometry": {"coordinates":[-118.267954,33.833928],"type":"Point"}
}