{
  "type": "Feature",
  "properties": {
    "iso:country":"US",
    "sg:address":"1522 Westwood Blvd",
    "sg:city":"Los Angeles",
    "sg:classifiers":[
        {
            "category":"Home & Garden",
            "subcategory":"Carpets & Floor Coverings",
            "type":"Retail Goods"
        }
    ],
    "sg:phone":"+1 323 879 5087",
    "sg:postcode":"90024",
    "sg:province":"CA",
    "sg:tags":[
        "dealer",
        "rug"
    ],
    "wof:name":"Upright Drapery & Carpet Stds",
    "wof:placetype":"venue"
},
  "geometry": {"coordinates":[-118.43977,34.053195],"type":"Point"}
}