{
  "type": "Feature",
  "properties": {
    "iso:country":"US",
    "sg:address":"260 Maple Ave",
    "sg:city":"S San Francisco",
    "sg:classifiers":[
        {
            "category":"Wholesale",
            "subcategory":"Groceries",
            "type":"Manufacturing & Wholesale Goods"
        }
    ],
    "sg:phone":"+1 650 225 9698",
    "sg:postcode":"94080",
    "sg:province":"CA",
    "sg:tags":[
        "grocer"
    ],
    "wof:name":"J M T Trading Co",
    "wof:placetype":"venue"
},
  "geometry": {"coordinates":[-122.412486,37.65539],"type":"Point"}
}