{
  "type": "Feature",
  "properties": {
    "addr:full":"569 E el Camino Real Sunnyvale CA 94087",
    "addr:housenumber":"569",
    "addr:postcode":"94087",
    "addr:street":"E El Camino Real",
    "iso:country":"US",
    "sg:address":"569 E el Camino Real",
    "sg:city":"Sunnyvale",
    "sg:classifiers":[
        {
            "category":"Wholesale",
            "subcategory":"Sporting Goods",
            "type":"Manufacturing & Wholesale Goods"
        }
    ],
    "sg:phone":"+1 408 730 8424",
    "sg:postcode":"94087",
    "sg:province":"CA",
    "sg:tags":[
        "equipment",
        "pool",
        "swimming"
    ],
    "wof:name":"Leslie's Swimming Pool Supply",
    "wof:placetype":"venue"
},
  "geometry": {"coordinates":[-122.026267,37.363011],"type":"Point"}
}