{
  "type": "Feature",
  "properties": {
    "iso:country":"US",
    "sg:address":"18008 Clarkdale Ave",
    "sg:city":"Artesia",
    "sg:classifiers":[
        {
            "category":"Professional",
            "type":"Services"
        }
    ],
    "sg:phone":"+1 562 924 5015",
    "sg:postcode":"90701",
    "sg:province":"CA",
    "wof:name":"Manuel D Sousa",
    "wof:placetype":"venue"
},
  "geometry": {"coordinates":[-118.07965900000001,33.866742],"type":"Point"}
}