{
  "type": "Feature",
  "properties": {
    "addr:full":"1046 Geer Rd Turlock CA 95380",
    "addr:housenumber":"1046",
    "addr:postcode":"95380",
    "addr:street":"Geer Rd",
    "iso:country":"US",
    "sg:address":"1046 Geer Rd",
    "sg:city":"Turlock",
    "sg:classifiers":[
        {
            "category":"Health Services",
            "subcategory":"Chiropractor",
            "type":"Services"
        }
    ],
    "sg:phone":"+1 209 417 1873",
    "sg:postcode":"95380",
    "sg:province":"CA",
    "sg:tags":[
        "chiropractic"
    ],
    "wof:name":"Crawford Chiropractic",
    "wof:placetype":"venue"
},
  "geometry": {"coordinates":[-120.84880099999999,37.502885],"type":"Point"}
}