{
  "type": "Feature",
  "properties": {
    "iso:country":"US",
    "sg:address":"1416 Alamo Dr",
    "sg:city":"Vacaville",
    "sg:classifiers":[
        {
            "category":"Retail",
            "subcategory":"Laundry & Dry Cleaning",
            "type":"Services"
        }
    ],
    "sg:phone":"+1 707 469 6289",
    "sg:postcode":"95687",
    "sg:province":"CA",
    "sg:tags":[
        "cleaners",
        "rug",
        "carpet"
    ],
    "wof:name":"A Top Of The Line Co",
    "wof:placetype":"venue"
},
  "geometry": {"coordinates":[-121.985293,38.335535],"type":"Point"}
}