{
  "type": "Feature",
  "properties": {
    "iso:country":"US",
    "sg:address":"2001 S Garey Ave",
    "sg:city":"Pomona",
    "sg:classifiers":[
        {
            "category":"Travel",
            "subcategory":"Travel Agent",
            "type":"Entertainment"
        }
    ],
    "sg:phone":"+1 909 628 9282",
    "sg:postcode":"91766",
    "sg:province":"CA",
    "sg:tags":[
        "agency",
        "bureau"
    ],
    "wof:name":"Acapulco Travel & Insurance",
    "wof:placetype":"venue"
},
  "geometry": {"coordinates":[-117.749381,34.035236],"type":"Point"}
}