{
  "type": "Feature",
  "properties": {
    "iso:country":"US",
    "sg:address":"Pure Skin Care Studio 1719 Professional Dr",
    "sg:city":"Sacramento",
    "sg:classifiers":[
        {
            "category":"Personal",
            "subcategory":"Beauty Salon",
            "type":"Services"
        },
        {
            "category":"Personal",
            "subcategory":"Hair Removal",
            "type":"Services"
        },
        {
            "category":"Personal",
            "subcategory":"Skin Care",
            "type":"Services"
        }
    ],
    "sg:phone":"+1 916 483 4983",
    "sg:postcode":"95825",
    "sg:province":"CA",
    "sg:tags":[
        "makeup",
        "artist"
    ],
    "sg:website":"kimshak.com",
    "wof:name":"Kim Shak",
    "wof:placetype":"venue"
},
  "geometry": {"coordinates":[-121.38708099999999,38.596521],"type":"Point"}
}