{
  "type": "Feature",
  "properties": {
    "addr:full":"16962 Goldenwest Street Huntington Beach CA 92647",
    "addr:housenumber":"16962",
    "addr:postcode":"92647",
    "addr:street":"Goldenwest Street",
    "iso:country":"US",
    "sg:address":"16962 Goldenwest Street",
    "sg:city":"Huntington Beach",
    "sg:classifiers":[
        {
            "category":"Home & Garden",
            "subcategory":"Household Appliances",
            "type":"Retail Goods"
        }
    ],
    "sg:phone":"+1 714 243 8415",
    "sg:postcode":"92647",
    "sg:province":"CA",
    "sg:tags":[
        "repair"
    ],
    "wof:name":"Huntington Beach Appliance Repair",
    "wof:placetype":"venue"
},
  "geometry": {"coordinates":[-118.006497,33.716013],"type":"Point"}
}