{
  "type": "Feature",
  "properties": {
    "iso:country":"US",
    "sg:address":"724 Gravenstein Hwy N",
    "sg:city":"Sebastopol",
    "sg:classifiers":[
        {
            "category":"Autos & Motor Vehicles",
            "subcategory":"Auto Supplies",
            "type":"Retail Goods"
        },
        {
            "category":"Wholesale",
            "subcategory":"Auto Parts",
            "type":"Manufacturing & Wholesale Goods"
        }
    ],
    "sg:phone":"+1 707 829 0650",
    "sg:postcode":"95472",
    "sg:province":"CA",
    "sg:tags":[
        "body",
        "automobile",
        "truck",
        "equipment",
        "accessory"
    ],
    "sg:website":"http://www.oreillyauto.com?utm_source=yellowpages&utm_medium=iyp&utm_campaign=2586",
    "wof:name":"Kragen O'ReillyAuto Parts",
    "wof:placetype":"venue"
},
  "geometry": {"coordinates":[-122.838882,38.40792],"type":"Point"}
}