{
  "type": "Feature",
  "properties": {
    "addr:full":"2887 McLaughlin Ave San Jose CA 95121",
    "addr:housenumber":"2887",
    "addr:postcode":"95121",
    "addr:street":"Mclaughlin Ave",
    "iso:country":"US",
    "sg:address":"2887 McLaughlin Ave",
    "sg:city":"San Jose",
    "sg:classifiers":[
        {
            "category":"Park",
            "type":"Public Place"
        }
    ],
    "sg:phone":"+1 408 578 8059",
    "sg:postcode":"95121",
    "sg:province":"CA",
    "wof:name":"Tower Picnic & Event Facility",
    "wof:placetype":"venue"
},
  "geometry": {"coordinates":[-121.827003,37.3055],"type":"Point"}
}