{
  "type": "Feature",
  "properties": {
    "addr:full":"6268 Long Beach Blvd Long Beach CA 90805",
    "addr:housenumber":"6268",
    "addr:postcode":"90805",
    "addr:street":"Long Beach Blvd",
    "iso:country":"US",
    "sg:address":"6268 Long Beach Blvd",
    "sg:city":"Long Beach",
    "sg:classifiers":[
        {
            "category":"Travel",
            "subcategory":"Hotels & Motels",
            "type":"Entertainment"
        }
    ],
    "sg:phone":"+1 562 422 3724",
    "sg:postcode":"90805",
    "sg:province":"CA",
    "wof:name":"Joyland Motel",
    "wof:placetype":"venue"
},
  "geometry": {"coordinates":[-118.200996,33.8685],"type":"Point"}
}