{
  "type": "Feature",
  "properties": {
    "iso:country":"US",
    "sg:address":"1805 Quicker Rd",
    "sg:city":"El Cajon",
    "sg:classifiers":[
        {
            "category":"Building & Trades",
            "subcategory":"Construction",
            "type":"Services"
        }
    ],
    "sg:phone":"+1 619 444 0022",
    "sg:postcode":"92021",
    "sg:province":"CA",
    "sg:tags":[
        "tile",
        "dealer"
    ],
    "wof:name":"Enduro Tile Co",
    "wof:placetype":"venue"
},
  "geometry": {"coordinates":[-116.910383,32.814403],"type":"Point"}
}