{
  "type": "Feature",
  "properties": {
    "iso:country":"US",
    "sg:address":"5435 Balboa Blvd",
    "sg:city":"Encino",
    "sg:classifiers":[
        {
            "category":"Banks & Credit Unions",
            "subcategory":"Investment Brokerage",
            "type":"Services"
        }
    ],
    "sg:phone":"+1 818 990 9784",
    "sg:postcode":"91316",
    "sg:province":"CA",
    "sg:tags":[
        "consultant",
        "planning",
        "financial"
    ],
    "wof:name":"National Planning Corp",
    "wof:placetype":"venue"
},
  "geometry": {"coordinates":[-118.501167,34.170111],"type":"Point"}
}