{
  "type": "Feature",
  "properties": {
    "iso:country":"US",
    "sg:address":"534 S Wilton Pl",
    "sg:city":"Los Angeles",
    "sg:classifiers":[
        {
            "category":"Shopping",
            "subcategory":"Catalog Store",
            "type":"Retail Goods"
        }
    ],
    "sg:phone":"+1 213 381 9400",
    "sg:postcode":"90020",
    "sg:province":"CA",
    "sg:tags":[
        "mail",
        "house"
    ],
    "wof:name":"Eves Boutique",
    "wof:placetype":"venue"
},
  "geometry": {"coordinates":[-118.313965,34.064015],"type":"Point"}
}