{
  "type": "Feature",
  "properties": {
    "addr:full":"735 Larkin Street San Francisco CA 94109",
    "addr:housenumber":"735",
    "addr:postcode":"94109",
    "addr:street":"Larkin Street",
    "iso:country":"US",
    "sg:address":"735 Larkin Street",
    "sg:city":"San Francisco",
    "sg:classifiers":[
        {
            "category":"Health Services",
            "subcategory":"Dentist",
            "type":"Services"
        }
    ],
    "sg:phone":"+1 415 885 4564",
    "sg:postcode":"94109",
    "sg:province":"CA",
    "wof:name":"Pacific Dental Services",
    "wof:placetype":"venue"
},
  "geometry": {"coordinates":[-122.41799899999999,37.784801],"type":"Point"}
}