{
  "type": "Feature",
  "properties": {
    "addr:full":"73255 El Paseo Palm Desert CA 92260",
    "addr:housenumber":"73255",
    "addr:postcode":"ca 92260",
    "addr:street":"El Paseo",
    "iso:country":"US",
    "sg:address":"73255 El Paseo",
    "sg:city":"Palm Desert",
    "sg:classifiers":[
        {
            "category":"Health Services",
            "subcategory":"Doctor",
            "type":"Services"
        }
    ],
    "sg:phone":"+1 760 423 8746",
    "sg:postcode":"92260",
    "sg:province":"CA",
    "wof:name":"Madrid Medical",
    "wof:placetype":"venue"
},
  "geometry": {"coordinates":[-116.386002,33.7197],"type":"Point"}
}