{
  "type": "Feature",
  "properties": {
    "iso:country":"US",
    "sg:address":"17215 Corby Ave",
    "sg:city":"Artesia",
    "sg:classifiers":[
        {
            "category":"Freight",
            "type":"Transportation"
        }
    ],
    "sg:phone":"+1 562 865 2252",
    "sg:postcode":"90701",
    "sg:province":"CA",
    "sg:tags":[
        "special"
    ],
    "wof:name":"Perry Art",
    "wof:placetype":"venue"
},
  "geometry": {"coordinates":[-118.08323799999999,33.873139],"type":"Point"}
}