{
  "type": "Feature",
  "properties": {
    "iso:country":"US",
    "sg:address":"3159 Corporate Pl",
    "sg:city":"Hayward",
    "sg:classifiers":[
        {
            "category":"Professional",
            "subcategory":"Computer Services",
            "type":"Services"
        }
    ],
    "sg:phone":"+1 510 264 5400",
    "sg:postcode":"94545",
    "sg:province":"CA",
    "sg:tags":[
        "communications",
        "datum",
        "system"
    ],
    "wof:name":"Airlink Communications Inc",
    "wof:placetype":"venue"
},
  "geometry": {"coordinates":[-122.11073,37.625118],"type":"Point"}
}