{
  "type": "Feature",
  "properties": {
    "addr:full":"3737 Crenshaw Boulevard Los Angeles CA 90016",
    "addr:housenumber":"3737",
    "addr:postcode":"90016",
    "addr:street":"Crenshaw Boulevard",
    "iso:country":"US",
    "sg:address":"3737 Crenshaw Boulevard",
    "sg:city":"Los Angeles",
    "sg:classifiers":[
        {
            "category":"Retail",
            "subcategory":"Auto Repair",
            "type":"Services"
        }
    ],
    "sg:phone":"+1 323 290 1125",
    "sg:postcode":"90016",
    "sg:province":"CA",
    "wof:name":"Pep Boys Automotive Supercenters",
    "wof:placetype":"venue"
},
  "geometry": {"coordinates":[-118.33506800000001,34.019375],"type":"Point"}
}