{
  "type": "Feature",
  "properties": {
    "addr:full":"34040 Date Palm Dr Cathedral City CA 92234",
    "addr:housenumber":"34040",
    "addr:postcode":"92234",
    "addr:street":"Date Palm Dr",
    "iso:country":"US",
    "sg:address":"34040 Date Palm Dr",
    "sg:city":"Cathedral City",
    "sg:classifiers":[
        {
            "category":"Home & Garden",
            "subcategory":"Building Materials",
            "type":"Retail Goods"
        }
    ],
    "sg:phone":"+1 760 328 0888",
    "sg:postcode":"92234",
    "sg:province":"CA",
    "sg:tags":[
        "glass",
        "window",
        "plate"
    ],
    "wof:name":"Palm Springs Mirror & Glass",
    "wof:placetype":"venue"
},
  "geometry": {"coordinates":[-116.45798600000001,33.798122],"type":"Point"}
}