{
  "type": "Feature",
  "properties": {
    "addr:full":"4001 B St Oakland CA 94601",
    "addr:housenumber":"4001",
    "addr:postcode":"94601",
    "addr:street":"B St",
    "iso:country":"US",
    "sg:address":"4001 B St",
    "sg:city":"Oakland",
    "sg:classifiers":[
        {
            "category":"Bakery",
            "type":"Food & Drink"
        }
    ],
    "sg:phone":"+1 510 601 7780",
    "sg:postcode":"94601",
    "sg:province":"CA",
    "wof:name":"Just Desserts",
    "wof:placetype":"venue"
},
  "geometry": {"coordinates":[-122.218002,37.779701],"type":"Point"}
}