{
  "type": "Feature",
  "properties": {
    "iso:country":"US",
    "sg:address":"2146 S Atlantic Boulevard",
    "sg:city":"Los Angeles",
    "sg:classifiers":[
        {
            "category":"Retail",
            "subcategory":"Auto Repair",
            "type":"Services"
        }
    ],
    "sg:phone":"+1 323 268 1266",
    "sg:postcode":"90040",
    "sg:province":"CA",
    "wof:name":"Paul's Automatic Transmission & Webb's Auto and Truck",
    "wof:placetype":"venue"
},
  "geometry": {"coordinates":[-118.16160600000001,34.007331],"type":"Point"}
}