{
  "type": "Feature",
  "properties": {
    "iso:country":"US",
    "sg:address":"4475 Mission Boulevard",
    "sg:city":"San Diego",
    "sg:classifiers":[
        {
            "category":"Shopping",
            "subcategory":"Shoes",
            "type":"Retail Goods"
        }
    ],
    "sg:phone":"+1 858 581 6010",
    "sg:postcode":"92109",
    "sg:province":"CA",
    "sg:tags":[
        "store"
    ],
    "wof:name":"Skechers USA",
    "wof:placetype":"venue"
},
  "geometry": {"coordinates":[-117.25536099999999,32.79624],"type":"Point"}
}