{
  "type": "Feature",
  "properties": {
    "addr:full":"1451 Yosemite Ave San Jose CA 95126",
    "addr:housenumber":"1451",
    "addr:postcode":"95126",
    "addr:street":"Yosemite Ave",
    "iso:country":"US",
    "sg:address":"1451 Yosemite Ave",
    "sg:city":"San Jose",
    "sg:classifiers":[
        {
            "category":"Building & Trades",
            "subcategory":"Construction",
            "type":"Services"
        },
        {
            "category":"Home & Garden",
            "subcategory":"Furniture",
            "type":"Retail Goods"
        }
    ],
    "sg:phone":"+1 408 971 8257",
    "sg:postcode":"95126",
    "sg:province":"CA",
    "sg:tags":[
        "interior",
        "design",
        "store"
    ],
    "wof:name":"North Arrow Designs",
    "wof:placetype":"venue"
},
  "geometry": {"coordinates":[-121.91621499999999,37.326178],"type":"Point"}
}