{
  "type": "Feature",
  "properties": {
    "iso:country":"US",
    "sg:address":"8048 San Miguel Canyon Rd",
    "sg:city":"Salinas",
    "sg:classifiers":[
        {
            "category":"Health Services",
            "subcategory":"Optometrist",
            "type":"Services"
        }
    ],
    "sg:phone":"+1 831 663 3276",
    "sg:postcode":"93907",
    "sg:province":"CA",
    "sg:website":"www.prunedalevisioncenter.com",
    "wof:name":"Willa Hisle, OD",
    "wof:placetype":"venue"
},
  "geometry": {"coordinates":[-121.665395,36.800833],"type":"Point"}
}