{
  "type": "Feature",
  "properties": {
    "addr:full":"3333 Bear St Costa Mesa CA 92626",
    "addr:housenumber":"3333",
    "addr:postcode":"92626",
    "addr:street":"Bear St",
    "iso:country":"US",
    "sg:address":"3333 Bear St",
    "sg:city":"Costa Mesa",
    "sg:classifiers":[
        {
            "category":"Restaurant",
            "type":"Food & Drink"
        }
    ],
    "sg:menulink":"http://www.allmenus.com/ca/central-coast/238673-wahoos-fish-taco/menu/",
    "sg:phone":"+1 714 549 0565",
    "sg:postcode":"92626",
    "sg:province":"CA",
    "sg:tags":[
        "seafood",
        "mexican",
        "american"
    ],
    "wof:name":"Wahoo's Fish Taco",
    "wof:placetype":"venue"
},
  "geometry": {"coordinates":[-117.892763,33.691584],"type":"Point"}
}