{
  "type": "Feature",
  "properties": {
    "addr:full":"1103 Toro St San Luis Obispo CA 93401",
    "addr:housenumber":"1103",
    "addr:postcode":"93401",
    "addr:street":"Toro St",
    "iso:country":"US",
    "sg:address":"1103 Toro St",
    "sg:city":"San Luis Obispo",
    "sg:classifiers":[
        {
            "category":"Government",
            "subcategory":"Office",
            "type":"Public Place"
        }
    ],
    "sg:phone":"+1 805 781 4190",
    "sg:postcode":"93401",
    "sg:province":"CA",
    "wof:name":"San Luis Obispo Co Mental Hlth",
    "wof:placetype":"venue"
},
  "geometry": {"coordinates":[-120.657939,35.282738],"type":"Point"}
}