{
  "type": "Feature",
  "properties": {
    "addr:full":"21781 Ventura Blvd San Fernando Valley CA 91364",
    "addr:housenumber":"21781",
    "addr:postcode":"91364",
    "addr:street":"Ventura Blvd",
    "iso:country":"US",
    "sg:address":"21781 Ventura Blvd",
    "sg:city":"San Fernando Valley",
    "sg:classifiers":[
        {
            "category":"Building & Trades",
            "subcategory":"Construction",
            "type":"Services"
        }
    ],
    "sg:phone":"+1 818 493 1453",
    "sg:postcode":"91364",
    "sg:province":"CA",
    "sg:tags":[
        "contractor"
    ],
    "sg:website":"woodlandhillswaterdamage.com",
    "wof:name":"Woodland Hills Water Damage",
    "wof:placetype":"venue"
},
  "geometry": {"coordinates":[-118.60193,34.168391],"type":"Point"}
}