{
  "type": "Feature",
  "properties": {
    "addr:full":"3016 Serbian Pl San Diego CA 92117",
    "addr:housenumber":"3016",
    "addr:postcode":"92117",
    "addr:street":"Serbian Pl",
    "iso:country":"US",
    "sg:address":"3016 Serbian Pl",
    "sg:city":"San Diego",
    "sg:classifiers":[
        {
            "category":"Professional",
            "type":"Services"
        }
    ],
    "sg:phone":"+1 858 576 2369",
    "sg:postcode":"92117",
    "sg:province":"CA",
    "wof:name":"South Mission Bch 8 A Cal Ltd",
    "wof:placetype":"venue"
},
  "geometry": {"coordinates":[-117.204846,32.794757],"type":"Point"}
}