{
  "type": "Feature",
  "properties": {
    "iso:country":"US",
    "sg:address":"1465 Haight St",
    "sg:city":"San Francisco",
    "sg:classifiers":[
        {
            "category":"Shopping",
            "type":"Retail Goods"
        }
    ],
    "sg:phone":"+1 415 551 1070",
    "sg:postcode":"94117",
    "sg:province":"CA",
    "sg:tags":[
        "shop",
        "merchandise",
        "beauty"
    ],
    "wof:name":"Body Time",
    "wof:placetype":"venue"
},
  "geometry": {"coordinates":[-122.446102,37.770066],"type":"Point"}
}