{
  "type": "Feature",
  "properties": {
    "iso:country":"US",
    "sg:address":"17770 Valley Blvd",
    "sg:city":"Bloomington",
    "sg:classifiers":[
        {
            "category":"Autos & Motor Vehicles",
            "subcategory":"Automobile Sales",
            "type":"Retail Goods"
        }
    ],
    "sg:phone":"+1 909 421 2320",
    "sg:postcode":"92316",
    "sg:province":"CA",
    "sg:tags":[
        "car",
        "dealer"
    ],
    "wof:name":"Rancho Los Amigos",
    "wof:placetype":"venue"
},
  "geometry": {"coordinates":[-117.410785,34.070515],"type":"Point"}
}