{
  "type": "Feature",
  "properties": {
    "addr:full":"4674 19th St San Francisco CA 94114",
    "addr:housenumber":"4674",
    "addr:postcode":"94114",
    "addr:street":"19Th St",
    "iso:country":"US",
    "sg:address":"4674 19th St",
    "sg:city":"San Francisco",
    "sg:classifiers":[
        {
            "category":"Professional",
            "subcategory":"Business Services",
            "type":"Services"
        }
    ],
    "sg:phone":"+1 415 626 0460",
    "sg:postcode":"94114",
    "sg:province":"CA",
    "sg:tags":[
        "sales",
        "estate"
    ],
    "wof:name":"Graceful Exits",
    "wof:placetype":"venue"
},
  "geometry": {"coordinates":[-122.44153,37.759065],"type":"Point"}
}