{
  "type": "Feature",
  "properties": {
    "iso:country":"US",
    "sg:address":"3664 Meder Rd",
    "sg:city":"Shingle Springs",
    "sg:classifiers":[
        {
            "category":"Food & Beverages",
            "subcategory":"Specialty",
            "type":"Retail Goods"
        }
    ],
    "sg:phone":"+1 916 492 7672",
    "sg:postcode":"95682",
    "sg:province":"CA",
    "sg:tags":[
        "product",
        "health",
        "care"
    ],
    "wof:name":"K & K Enterprises",
    "wof:placetype":"venue"
},
  "geometry": {"coordinates":[-120.952343,38.677738],"type":"Point"}
}