{
  "type": "Feature",
  "properties": {
    "addr:full":"5860 W Las Positas Blvd Pleasanton CA 94588",
    "addr:housenumber":"5860",
    "addr:postcode":"94588",
    "addr:street":"W Las Positas Blvd",
    "iso:country":"US",
    "sg:address":"5860 W Las Positas Blvd",
    "sg:city":"Pleasanton",
    "sg:classifiers":[
        {
            "category":"Professional",
            "subcategory":"Management & Consulting",
            "type":"Services"
        }
    ],
    "sg:phone":"+1 925 468 7676",
    "sg:postcode":"94588",
    "sg:province":"CA",
    "sg:tags":[
        "consultant",
        "telecommunication"
    ],
    "wof:name":"Serrato Consulting Corp",
    "wof:placetype":"venue"
},
  "geometry": {"coordinates":[-121.896613,37.684228],"type":"Point"}
}