{
  "type": "Feature",
  "properties": {
    "iso:country":"US",
    "sg:address":"1568 Highland Dr",
    "sg:city":"Solana Beach",
    "sg:classifiers":[
        {
            "category":"Professional",
            "subcategory":"Business Services",
            "type":"Services"
        }
    ],
    "sg:phone":"+1 858 847 0038",
    "sg:postcode":"92075",
    "sg:province":"CA",
    "sg:tags":[
        "consultant",
        "production",
        "music"
    ],
    "wof:name":"Sota Music Inc",
    "wof:placetype":"venue"
},
  "geometry": {"coordinates":[-117.242035,32.990814],"type":"Point"}
}