{
  "type": "Feature",
  "properties": {
    "iso:country":"US",
    "sg:address":"10895 Lorenson Rd",
    "sg:city":"Auburn",
    "sg:classifiers":[
        {
            "category":"Farming",
            "subcategory":"Livestock Farm",
            "type":"Manufacturing & Wholesale Goods"
        }
    ],
    "sg:phone":"+1 530 823 3559",
    "sg:postcode":"95602",
    "sg:province":"CA",
    "sg:tags":[
        "specialty",
        "animal"
    ],
    "wof:name":"Williams Llama Hacienda",
    "wof:placetype":"venue"
},
  "geometry": {"coordinates":[-121.12511499999999,38.974434],"type":"Point"}
}