{
  "type": "Feature",
  "properties": {
    "addr:full":"2009 Venice Blvd Los Angeles CA 90006",
    "addr:housenumber":"2009",
    "addr:postcode":"90006",
    "addr:street":"Venice Blvd",
    "iso:country":"US",
    "sg:address":"2009 Venice Blvd",
    "sg:city":"Los Angeles",
    "sg:classifiers":[
        {
            "category":"Wholesale",
            "subcategory":"Machinery & Supplies",
            "type":"Manufacturing & Wholesale Goods"
        },
        {
            "category":"Shopping",
            "type":"Retail Goods"
        }
    ],
    "sg:phone":"+1 323 733 2739",
    "sg:postcode":"90006",
    "sg:province":"CA",
    "sg:tags":[
        "janitor",
        "establishment",
        "merchandise"
    ],
    "wof:name":"Cleanroom Janitorial Supply Co",
    "wof:placetype":"venue"
},
  "geometry": {"coordinates":[-118.300607,34.043792],"type":"Point"}
}