{
  "type": "Feature",
  "properties": {
    "iso:country":"US",
    "sg:address":"8430 Old Redwood Hwy",
    "sg:city":"Windsor",
    "sg:classifiers":[
        {
            "category":"Restaurant",
            "type":"Food & Drink"
        }
    ],
    "sg:phone":"+1 707 836 8421",
    "sg:postcode":"95492",
    "sg:province":"CA",
    "wof:name":"Diana's Market Y Taqueria",
    "wof:placetype":"venue"
},
  "geometry": {"coordinates":[-122.800951,38.543691],"type":"Point"}
}