{
  "type": "Feature",
  "properties": {
    "addr:full":"7058 N Cedar Ave Fresno CA 93720",
    "addr:housenumber":"7058",
    "addr:postcode":"93720",
    "addr:street":"N Cedar Ave",
    "iso:country":"US",
    "sg:address":"7058 N Cedar Ave",
    "sg:city":"Fresno",
    "sg:classifiers":[
        {
            "category":"Restaurant",
            "type":"Food & Drink"
        }
    ],
    "sg:phone":"+1 559 297 1110",
    "sg:postcode":"93720",
    "sg:province":"CA",
    "sg:tags":[
        "eating"
    ],
    "wof:name":"Dai Ichi USA",
    "wof:placetype":"venue"
},
  "geometry": {"coordinates":[-119.755506,36.839919],"type":"Point"}
}