{
  "type": "Feature",
  "properties": {
    "addr:full":"1249 Denver Ln El Cajon CA 92021",
    "addr:housenumber":"1249",
    "addr:postcode":"92021",
    "addr:street":"Denver Ln",
    "iso:country":"US",
    "sg:address":"1249 Denver Ln",
    "sg:city":"El Cajon",
    "sg:classifiers":[
        {
            "category":"Building & Trades",
            "subcategory":"Construction",
            "type":"Services"
        }
    ],
    "sg:phone":"+1 619 588 1565",
    "sg:postcode":"92021",
    "sg:province":"CA",
    "sg:tags":[
        "handyman"
    ],
    "wof:name":"Deneen Plumbing",
    "wof:placetype":"venue"
},
  "geometry": {"coordinates":[-116.94936,32.811881],"type":"Point"}
}