{
  "type": "Feature",
  "properties": {
    "addr:full":"719 Alta Vista Dr Vista CA 92084",
    "addr:housenumber":"719",
    "addr:postcode":"92084",
    "addr:street":"Alta Vista Dr",
    "iso:country":"US",
    "sg:address":"719 Alta Vista Dr",
    "sg:city":"Vista",
    "sg:classifiers":[
        {
            "category":"Professional",
            "subcategory":"Computer Services",
            "type":"Services"
        }
    ],
    "sg:phone":"+1 760 414 9001",
    "sg:postcode":"92084",
    "sg:province":"CA",
    "sg:tags":[
        "datum"
    ],
    "wof:name":"Efmpro",
    "wof:placetype":"venue"
},
  "geometry": {"coordinates":[-117.234874,33.204125],"type":"Point"}
}