{
  "type": "Feature",
  "properties": {
    "iso:country":"US",
    "sg:address":"26975 Murrieta Rd",
    "sg:city":"Romoland",
    "sg:classifiers":[
        {
            "category":"Home & Garden",
            "subcategory":"Garden Supply",
            "type":"Retail Goods"
        }
    ],
    "sg:phone":"+1 951 679 4116",
    "sg:postcode":"92585",
    "sg:province":"CA",
    "sg:tags":[
        "tree",
        "christmas"
    ],
    "wof:name":"Western Pines",
    "wof:placetype":"venue"
},
  "geometry": {"coordinates":[-117.206287,33.729349],"type":"Point"}
}