{
  "type": "Feature",
  "properties": {
    "addr:full":"415 W Rialto Ave Rialto CA 92376",
    "addr:housenumber":"415",
    "addr:postcode":"92376",
    "addr:street":"W Rialto Ave",
    "iso:country":"US",
    "sg:address":"415 W Rialto Ave",
    "sg:city":"Rialto",
    "sg:classifiers":[
        {
            "category":"Manufacturing",
            "subcategory":"Tools & Machinery",
            "type":"Manufacturing & Wholesale Goods"
        }
    ],
    "sg:phone":"+1 909 875 3080",
    "sg:postcode":"92376",
    "sg:province":"CA",
    "sg:tags":[
        "industrial",
        "mfg",
        "contractor",
        "trade"
    ],
    "wof:name":"Scheidecker Fabrications",
    "wof:placetype":"venue"
},
  "geometry": {"coordinates":[-117.378576,34.099445],"type":"Point"}
}