{
  "type": "Feature",
  "properties": {
    "iso:country":"US",
    "sg:address":"1892 Vicente Dr",
    "sg:city":"San Luis Obispo",
    "sg:classifiers":[
        {
            "category":"Retail",
            "subcategory":"Portrait Studio",
            "type":"Services"
        }
    ],
    "sg:phone":"+1 805 786 4766",
    "sg:postcode":"93405",
    "sg:province":"CA",
    "sg:tags":[
        "photographer"
    ],
    "wof:name":"Laura Dicksinson Photography",
    "wof:placetype":"venue"
},
  "geometry": {"coordinates":[-120.686494,35.255024],"type":"Point"}
}