{
  "type": "Feature",
  "properties": {
    "addr:full":"24301 Southland Dr Hayward CA 94545",
    "addr:housenumber":"24301",
    "addr:postcode":"94545",
    "addr:street":"Southland Dr",
    "iso:country":"US",
    "sg:address":"24301 Southland Dr",
    "sg:city":"Hayward",
    "sg:classifiers":[
        {
            "category":"Real Estate",
            "subcategory":"Real Estate Agent",
            "type":"Services"
        }
    ],
    "sg:phone":"+1 510 940 0170",
    "sg:postcode":"94545",
    "sg:province":"CA",
    "wof:name":"Fineza Home Loans & Realty Inc",
    "wof:placetype":"venue"
},
  "geometry": {"coordinates":[-122.10513400000001,37.654247],"type":"Point"}
}