{
  "type": "Feature",
  "properties": {
    "addr:full":"1005 Railroad St Paso Robles CA 93446",
    "addr:housenumber":"1005",
    "addr:postcode":"93446",
    "addr:street":"Railroad St",
    "iso:country":"US",
    "sg:address":"1005 Railroad St",
    "sg:city":"Paso Robles",
    "sg:classifiers":[
        {
            "category":"Professional",
            "subcategory":"Engineering",
            "type":"Services"
        }
    ],
    "sg:phone":"+1 805 238 5427",
    "sg:postcode":"93446",
    "sg:province":"CA",
    "sg:tags":[
        "engineer"
    ],
    "wof:name":"Emk & Assoc Inc",
    "wof:placetype":"venue"
},
  "geometry": {"coordinates":[-120.688129,35.625244],"type":"Point"}
}