{
  "type": "Feature",
  "properties": {
    "addr:full":"3073 Pine St San Francisco CA 94115",
    "addr:housenumber":"3073",
    "addr:postcode":"94115",
    "addr:street":"Pine St",
    "iso:country":"US",
    "sg:address":"3073 Pine St",
    "sg:city":"San Francisco",
    "sg:classifiers":[
        {
            "category":"Sports & Exercise",
            "subcategory":"Gym",
            "type":"Entertainment"
        }
    ],
    "sg:phone":"+1 415 370 4445",
    "sg:postcode":"94115",
    "sg:province":"CA",
    "sg:tags":[
        "trainer"
    ],
    "sg:website":"www.fluxfitness.com",
    "wof:name":"Flux Fitness",
    "wof:placetype":"venue"
},
  "geometry": {"coordinates":[-122.44637400000001,37.786317],"type":"Point"}
}