{
  "type": "Feature",
  "properties": {
    "addr:full":"4657 Badger Rd Santa Rosa CA 95409",
    "addr:housenumber":"4657",
    "addr:postcode":"95409",
    "addr:street":"Badger Rd",
    "iso:country":"US",
    "sg:address":"4657 Badger Rd",
    "sg:city":"Santa Rosa",
    "sg:classifiers":[
        {
            "category":"Social Services",
            "subcategory":"Child Care",
            "type":"Services"
        }
    ],
    "sg:phone":"+1 707 539 1612",
    "sg:postcode":"95409",
    "sg:province":"CA",
    "sg:tags":[
        "kindergarten",
        "academic",
        "school"
    ],
    "wof:name":"Brush Creek Nursery School",
    "wof:placetype":"venue"
},
  "geometry": {"coordinates":[-122.670406,38.482268],"type":"Point"}
}