{
  "type": "Feature",
  "properties": {
    "addr:full":"1140 Lincoln Ave San Jose CA 95125",
    "addr:housenumber":"1140",
    "addr:postcode":"95125",
    "addr:street":"Lincoln Ave",
    "iso:country":"US",
    "sg:address":"1140 Lincoln Ave",
    "sg:city":"San Jose",
    "sg:classifiers":[
        {
            "category":"Restaurant",
            "type":"Food & Drink"
        },
        {
            "category":"Food & Beverages",
            "subcategory":"Fruits & Vegetables",
            "type":"Retail Goods"
        }
    ],
    "sg:menulink":"http://www.allmenus.com/ca/san-jose/135669-jamba-juice/menu/",
    "sg:phone":"+1 408 795 1577",
    "sg:postcode":"95125",
    "sg:province":"CA",
    "sg:tags":[
        "smoothy",
        "juice",
        "american"
    ],
    "wof:name":"Jamba Juice",
    "wof:placetype":"venue"
},
  "geometry": {"coordinates":[-121.899997,37.307626],"type":"Point"}
}