{
  "type": "Feature",
  "properties": {
    "addr:full":"2450 Pulgas Ave East Palo Alto CA 94303",
    "addr:postcode":"2450;94303",
    "addr:street":"Pulgas Ave",
    "iso:country":"US",
    "sg:address":"2450 Pulgas Ave",
    "sg:city":"East Palo Alto",
    "sg:classifiers":[
        {
            "category":"Wholesale",
            "subcategory":"Metals & Minerals",
            "type":"Manufacturing & Wholesale Goods"
        }
    ],
    "sg:phone":"+1 650 324 1654",
    "sg:postcode":"94303",
    "sg:province":"CA",
    "sg:tags":[
        "steel",
        "warehouse"
    ],
    "sg:website":"www.borrmannsteel.com",
    "wof:name":"R E Borrmann's Steel Co",
    "wof:placetype":"venue"
},
  "geometry": {"coordinates":[-122.13055300000001,37.470653],"type":"Point"}
}