{
  "type": "Feature",
  "properties": {
    "iso:country":"US",
    "sg:address":"401 N Kenwood St",
    "sg:city":"Glendale",
    "sg:classifiers":[
        {
            "category":"Real Estate",
            "subcategory":"Developer",
            "type":"Services"
        },
        {
            "category":"Building & Trades",
            "subcategory":"Construction",
            "type":"Services"
        }
    ],
    "sg:phone":"+1 818 500 7766",
    "sg:postcode":"91206",
    "sg:province":"CA",
    "sg:tags":[
        "general",
        "contractor"
    ],
    "wof:name":"Victor Minassian Inc",
    "wof:placetype":"venue"
},
  "geometry": {"coordinates":[-118.2514,34.15471],"type":"Point"}
}