{
  "type": "Feature",
  "properties": {
    "addr:full":"14374 Saratoga Ave Saratoga CA 95070",
    "addr:housenumber":"14374",
    "addr:postcode":"95070",
    "addr:street":"Saratoga Ave",
    "iso:country":"US",
    "sg:address":"14374 Saratoga Ave",
    "sg:city":"Saratoga",
    "sg:classifiers":[
        {
            "category":"Government",
            "subcategory":"Police Station",
            "type":"Public Place"
        }
    ],
    "sg:phone":"+1 408 868 6600",
    "sg:postcode":"95070",
    "sg:province":"CA",
    "sg:tags":[
        "sheriff"
    ],
    "wof:name":"Santa Clara County Sheriff",
    "wof:placetype":"venue"
},
  "geometry": {"coordinates":[-122.03154000000001,37.259281],"type":"Point"}
}