{
  "type": "Feature",
  "properties": {
    "iso:country":"US",
    "sg:address":"7739 Santa Monica Blvd",
    "sg:city":"Los Angeles",
    "sg:classifiers":[
        {
            "category":"Wholesale",
            "subcategory":"Apparel",
            "type":"Manufacturing & Wholesale Goods"
        }
    ],
    "sg:phone":"+1 323 654 7103",
    "sg:postcode":"90046",
    "sg:province":"CA",
    "sg:tags":[
        "outerwear"
    ],
    "wof:name":"Good Old Times Inc",
    "wof:placetype":"venue"
},
  "geometry": {"coordinates":[-118.357721,34.090873],"type":"Point"}
}