{
  "type": "Feature",
  "properties": {
    "addr:full":"8806 Horner St Los Angeles CA 90035",
    "addr:housenumber":"8806",
    "addr:postcode":"90035",
    "addr:street":"Horner St",
    "iso:country":"US",
    "sg:address":"8806 Horner St",
    "sg:city":"Los Angeles",
    "sg:classifiers":[
        {
            "category":"Real Estate",
            "subcategory":"Architect",
            "type":"Services"
        }
    ],
    "sg:phone":"+1 310 492 0541",
    "sg:postcode":"90035",
    "sg:province":"CA",
    "wof:name":"Pancino Architech",
    "wof:placetype":"venue"
},
  "geometry": {"coordinates":[-118.386349,34.051562],"type":"Point"}
}