{
  "type": "Feature",
  "properties": {
    "iso:country":"US",
    "sg:address":"23842 Via el Rocio",
    "sg:city":"Mission Viejo",
    "sg:classifiers":[
        {
            "category":"Professional",
            "type":"Services"
        }
    ],
    "sg:phone":"+1 949 380 4117",
    "sg:postcode":"92691",
    "sg:province":"CA",
    "wof:name":"Sofia Marble & Granite",
    "wof:placetype":"venue"
},
  "geometry": {"coordinates":[-117.65935,33.617732],"type":"Point"}
}