{
  "type": "Feature",
  "properties": {
    "iso:country":"US",
    "sg:address":"760 E Colorado St",
    "sg:city":"Pasadena",
    "sg:classifiers":[
        {
            "category":"Shopping",
            "subcategory":"Clothing, Apparel, & Fashions",
            "type":"Retail Goods"
        },
        {
            "category":"Personal",
            "subcategory":"Beauty Salon",
            "type":"Services"
        },
        {
            "category":"Personal",
            "subcategory":"Piercing",
            "type":"Services"
        }
    ],
    "sg:phone":"+1 626 793 8930",
    "sg:postcode":"91101",
    "sg:province":"CA",
    "sg:tags":[
        "hair"
    ],
    "sg:website":"www.anomaly2.com",
    "wof:name":"Anomaly Studios",
    "wof:placetype":"venue"
},
  "geometry": {"coordinates":[-118.13469600000001,34.14557],"type":"Point"}
}