{
  "type": "Feature",
  "properties": {
    "iso:country":"US",
    "sg:address":"2525 Main St",
    "sg:city":"Santa Monica",
    "sg:classifiers":[
        {
            "category":"Shopping",
            "subcategory":"Clothing, Apparel, & Fashions",
            "type":"Retail Goods"
        }
    ],
    "sg:phone":"+1 310 396 7614",
    "sg:postcode":"90405",
    "sg:province":"CA",
    "wof:name":"Suji",
    "wof:placetype":"venue"
},
  "geometry": {"coordinates":[-118.48515,34.003723],"type":"Point"}
}