{
  "type": "Feature",
  "properties": {
    "iso:country":"US",
    "sg:address":"940 6th St",
    "sg:city":"Los Banos",
    "sg:classifiers":[
        {
            "category":"Food & Beverages",
            "subcategory":"Specialty",
            "type":"Retail Goods"
        }
    ],
    "sg:phone":"+1 209 826 8503",
    "sg:postcode":"93635",
    "sg:province":"CA",
    "wof:name":"Health Time",
    "wof:placetype":"venue"
},
  "geometry": {"coordinates":[-120.84805900000001,37.060497],"type":"Point"}
}