{
  "type": "Feature",
  "properties": {
    "addr:full":"1930 Erringer Rd Simi Valley CA 93065",
    "addr:postcode":"1930;93065",
    "addr:street":"Erringer Rd",
    "iso:country":"US",
    "sg:address":"1930 Erringer Rd",
    "sg:city":"Simi Valley",
    "sg:classifiers":[
        {
            "category":"Restaurant",
            "type":"Food & Drink"
        }
    ],
    "sg:phone":"+1 805 522 9285",
    "sg:postcode":"93065",
    "sg:province":"CA",
    "wof:name":"Dimitris Cafe",
    "wof:placetype":"venue"
},
  "geometry": {"coordinates":[-118.761289,34.270784],"type":"Point"}
}