{
  "type": "Feature",
  "properties": {
    "addr:full":"433 Callan Ave San Leandro CA 94577",
    "addr:housenumber":"433",
    "addr:postcode":"94577",
    "addr:street":"Callan Ave",
    "iso:country":"US",
    "sg:address":"433 Callan Ave",
    "sg:city":"San Leandro",
    "sg:classifiers":[
        {
            "category":"Professional",
            "subcategory":"Lawyer & Legal Services",
            "type":"Services"
        }
    ],
    "sg:phone":"+1 510 812 3811",
    "sg:postcode":"94577",
    "sg:province":"CA",
    "sg:tags":[
        "attorney"
    ],
    "wof:name":"Sarah Lawrence",
    "wof:placetype":"venue"
},
  "geometry": {"coordinates":[-122.151675,37.727055],"type":"Point"}
}