{
  "type": "Feature",
  "properties": {
    "iso:country":"US",
    "sg:address":"27264 Camp Plenty Rd Ste 100",
    "sg:city":"Santa Clarita",
    "sg:classifiers":[
        {
            "category":"Autos & Motor Vehicles",
            "subcategory":"Auto Supplies",
            "type":"Retail Goods"
        },
        {
            "category":"Retail",
            "subcategory":"Auto Repair",
            "type":"Services"
        }
    ],
    "sg:phone":"+1 661 250 0055",
    "sg:postcode":"91351",
    "sg:province":"CA",
    "sg:tags":[
        "tire"
    ],
    "wof:name":"Euro Tech Auto Repair & Tire",
    "wof:placetype":"venue"
},
  "geometry": {"coordinates":[-118.476074,34.416815],"type":"Point"}
}