{
  "type": "Feature",
  "properties": {
    "addr:full":"123 N E St Madera CA 93638",
    "addr:housenumber":"123",
    "addr:postcode":"93638",
    "addr:street":"N E St",
    "iso:country":"US",
    "sg:address":"123 N E St",
    "sg:city":"Madera",
    "sg:classifiers":[
        {
            "category":"Taxi",
            "type":"Transportation"
        }
    ],
    "sg:phone":"+1 559 674 2411",
    "sg:postcode":"93638",
    "sg:province":"CA",
    "sg:tags":[
        "taxicab"
    ],
    "wof:name":"Madera Cab Co",
    "wof:placetype":"venue"
},
  "geometry": {"coordinates":[-120.060231,36.96268],"type":"Point"}
}