{
  "type": "Feature",
  "properties": {
    "iso:country":"US",
    "sg:address":"13144 W California Ave",
    "sg:city":"Kerman",
    "sg:classifiers":[
        {
            "category":"Farming",
            "subcategory":"Farm",
            "type":"Manufacturing & Wholesale Goods"
        }
    ],
    "sg:phone":"+1 559 846 7509",
    "sg:postcode":"93630",
    "sg:province":"CA",
    "sg:tags":[
        "crop",
        "general"
    ],
    "wof:name":"John P Nale",
    "wof:placetype":"venue"
},
  "geometry": {"coordinates":[-120.02637,36.720471],"type":"Point"}
}