{
  "type": "Feature",
  "properties": {
    "iso:country":"US",
    "sg:address":"615 Schwerin St",
    "sg:city":"Daly City",
    "sg:classifiers":[
        {
            "category":"Food & Beverages",
            "subcategory":"Groceries & Convenience Stores",
            "type":"Retail Goods"
        }
    ],
    "sg:phone":"+1 415 468 3318",
    "sg:postcode":"94014",
    "sg:province":"CA",
    "sg:tags":[
        "grocer"
    ],
    "wof:name":"Sun Valley Dairy Market",
    "wof:placetype":"venue"
},
  "geometry": {"coordinates":[-122.41300200000001,37.707001],"type":"Point"}
}