{
  "type": "Feature",
  "properties": {
    "iso:country":"US",
    "sg:address":"1121 L Street",
    "sg:city":"Sacramento",
    "sg:classifiers":[
        {
            "category":"Professional",
            "subcategory":"Lawyer & Legal Services",
            "type":"Services"
        }
    ],
    "sg:phone":"+1 916 448 5100",
    "sg:postcode":"95814",
    "sg:province":"CA",
    "wof:name":"Hiestand Fred J Atty",
    "wof:placetype":"venue"
},
  "geometry": {"coordinates":[-121.49278,38.577684],"type":"Point"}
}