{
  "type": "Feature",
  "properties": {
    "iso:country":"US",
    "sg:address":"43805 Corte Amaya",
    "sg:city":"Temecula",
    "sg:classifiers":[
        {
            "category":"Shopping",
            "subcategory":"Computers & Home Electronics",
            "type":"Retail Goods"
        }
    ],
    "sg:phone":"+1 951 551 4586",
    "sg:postcode":"92592",
    "sg:province":"CA",
    "wof:name":"Hayes Communications",
    "wof:placetype":"venue"
},
  "geometry": {"coordinates":[-117.104894,33.489467],"type":"Point"}
}