{
  "type": "Feature",
  "properties": {
    "addr:full":"665 Chestnut St San Francisco CA 94133",
    "addr:housenumber":"665",
    "addr:postcode":"94133",
    "addr:street":"Chestnut St",
    "iso:country":"US",
    "sg:address":"665 Chestnut St",
    "sg:city":"San Francisco",
    "sg:classifiers":[
        {
            "category":"Shopping",
            "type":"Retail Goods"
        }
    ],
    "sg:phone":"+1 415 292 8905",
    "sg:postcode":"94133",
    "sg:province":"CA",
    "sg:tags":[
        "webbing"
    ],
    "sg:website":"www.drivespeed.com",
    "wof:name":"Drivespeed Designs",
    "wof:placetype":"venue"
},
  "geometry": {"coordinates":[-122.414348,37.803554],"type":"Point"}
}