{
  "type": "Feature",
  "properties": {
    "iso:country":"US",
    "sg:address":"910 Begonia Ct",
    "sg:city":"Carlsbad",
    "sg:classifiers":[
        {
            "category":"Banks & Credit Unions",
            "subcategory":"Financial Services",
            "type":"Services"
        }
    ],
    "sg:phone":"+1 760 438 0141",
    "sg:postcode":"92011",
    "sg:province":"CA",
    "sg:tags":[
        "trust",
        "management"
    ],
    "wof:name":"Cothran Executive Trust",
    "wof:placetype":"venue"
},
  "geometry": {"coordinates":[-117.301952,33.099442],"type":"Point"}
}