{
  "type": "Feature",
  "properties": {
    "iso:country":"US",
    "sg:address":"1516 Lombard St Ste 5",
    "sg:city":"San Francisco",
    "sg:classifiers":[
        {
            "category":"Building & Trades",
            "subcategory":"Construction",
            "type":"Services"
        },
        {
            "category":"Real Estate",
            "subcategory":"Architect",
            "type":"Services"
        }
    ],
    "sg:phone":"+1 415 269 3879",
    "sg:postcode":"94123",
    "sg:province":"CA",
    "sg:tags":[
        "interior",
        "design"
    ],
    "sg:website":"www.wdavidseidel.com",
    "wof:name":"David W. Seidel, AIA",
    "wof:placetype":"venue"
},
  "geometry": {"coordinates":[-122.426582,37.801325],"type":"Point"}
}