{
  "type": "Feature",
  "properties": {
    "addr:full":"633 Kensington Rd Santa Monica CA 90405",
    "addr:housenumber":"633",
    "addr:postcode":"90405",
    "addr:street":"Kensington Rd",
    "iso:country":"US",
    "sg:address":"633 Kensington Rd",
    "sg:city":"Santa Monica",
    "sg:classifiers":[
        {
            "category":"Government",
            "subcategory":"Office",
            "type":"Public Place"
        }
    ],
    "sg:phone":"+1 310 581 2679",
    "sg:postcode":"90405",
    "sg:province":"CA",
    "sg:tags":[
        "village"
    ],
    "wof:name":"City Of Santa Monica",
    "wof:placetype":"venue"
},
  "geometry": {"coordinates":[-118.480867,34.008287],"type":"Point"}
}