{
  "type": "Feature",
  "properties": {
    "iso:country":"US",
    "sg:address":"205 S Dewitt Way",
    "sg:city":"Yreka",
    "sg:classifiers":[
        {
            "category":"Professional",
            "type":"Services"
        }
    ],
    "sg:phone":"+1 530 841 1848",
    "sg:postcode":"96097",
    "sg:province":"CA",
    "sg:tags":[
        "establishment"
    ],
    "wof:name":"Tallerico & Assoc",
    "wof:placetype":"venue"
},
  "geometry": {"coordinates":[-122.650929,41.73236],"type":"Point"}
}