{
  "type": "Feature",
  "properties": {
    "iso:country":"US",
    "sg:address":"3151 Franklin St",
    "sg:city":"San Francisco",
    "sg:classifiers":[
        {
            "category":"Food & Beverages",
            "subcategory":"Specialty",
            "type":"Retail Goods"
        },
        {
            "category":"Food & Beverages",
            "subcategory":"Liquor & Beverages",
            "type":"Retail Goods"
        }
    ],
    "sg:phone":"+1 415 771 7224",
    "sg:postcode":"94123",
    "sg:province":"CA",
    "sg:tags":[
        "gourmet",
        "shop",
        "alcoholic"
    ],
    "wof:name":"Etruria",
    "wof:placetype":"venue"
},
  "geometry": {"coordinates":[-122.426753,37.803445],"type":"Point"}
}