{
  "type": "Feature",
  "properties": {
    "iso:country":"US",
    "sg:address":"7424 Jackson Dr",
    "sg:city":"San Diego",
    "sg:classifiers":[
        {
            "category":"Personal",
            "subcategory":"Barber",
            "type":"Services"
        }
    ],
    "sg:phone":"+1 619 644 3669",
    "sg:postcode":"92119",
    "sg:province":"CA",
    "wof:name":"Jenna's Barber Shoppe",
    "wof:placetype":"venue"
},
  "geometry": {"coordinates":[-117.04499800000001,32.8032],"type":"Point"}
}