{
  "type": "Feature",
  "properties": {
    "addr:full":"26492 Pacific St Highland CA 92346",
    "addr:housenumber":"26492",
    "addr:postcode":"92346",
    "addr:street":"Pacific St",
    "iso:country":"US",
    "sg:address":"26492 Pacific St",
    "sg:city":"Highland",
    "sg:classifiers":[
        {
            "category":"Food & Beverages",
            "subcategory":"Groceries & Convenience Stores",
            "type":"Retail Goods"
        }
    ],
    "sg:phone":"+1 909 862 7935",
    "sg:postcode":"92346",
    "sg:province":"CA",
    "wof:name":"Pacific Market",
    "wof:placetype":"venue"
},
  "geometry": {"coordinates":[-117.22744,34.128647],"type":"Point"}
}