{
  "type": "Feature",
  "properties": {
    "addr:full":"9839 Sunland Blvd Sunland CA 91040",
    "addr:housenumber":"9839",
    "addr:postcode":"91040",
    "addr:street":"Sunland Blvd",
    "iso:country":"US",
    "sg:address":"9839 Sunland Blvd",
    "sg:city":"Sunland",
    "sg:classifiers":[
        {
            "category":"Farming",
            "subcategory":"Farm",
            "type":"Manufacturing & Wholesale Goods"
        }
    ],
    "sg:phone":"+1 818 352 6575",
    "sg:postcode":"91040",
    "sg:province":"CA",
    "sg:tags":[
        "crop",
        "general"
    ],
    "wof:name":"Hilltop Farm",
    "wof:placetype":"venue"
},
  "geometry": {"coordinates":[-118.34865499999999,34.248134],"type":"Point"}
}