{
  "type": "Feature",
  "properties": {
    "iso:country":"US",
    "sg:address":"1755 Euclid Ave",
    "sg:city":"San Diego",
    "sg:classifiers":[
        {
            "category":"Professional",
            "type":"Services"
        }
    ],
    "sg:phone":"+1 619 262 0268",
    "sg:postcode":"92105",
    "sg:province":"CA",
    "wof:name":"Master Lee Creation",
    "wof:placetype":"venue"
},
  "geometry": {"coordinates":[-117.084856,32.724017],"type":"Point"}
}