{
  "type": "Feature",
  "properties": {
    "addr:full":"12036 State Rte 155 Glennville CA 93226",
    "addr:housenumber":"12036",
    "addr:postcode":"93226",
    "addr:street":"State Rte 155",
    "iso:country":"US",
    "sg:address":"12036 State Rte 155",
    "sg:city":"Glennville",
    "sg:classifiers":[
        {
            "category":"Travel",
            "subcategory":"Hotels & Motels",
            "type":"Entertainment"
        }
    ],
    "sg:phone":"+1 661 536 9100",
    "sg:postcode":"93226",
    "sg:province":"CA",
    "wof:name":"Bunk House",
    "wof:placetype":"venue"
},
  "geometry": {"coordinates":[-118.72693599999999,35.71797],"type":"Point"}
}