{
  "type": "Feature",
  "properties": {
    "addr:full":"1224 W Lewis St San Diego CA 92103",
    "addr:housenumber":"1224",
    "addr:postcode":"92103",
    "addr:street":"W Lewis St",
    "iso:country":"US",
    "sg:address":"1224 W Lewis St",
    "sg:city":"San Diego",
    "sg:classifiers":[
        {
            "category":"Building & Trades",
            "subcategory":"Construction",
            "type":"Services"
        }
    ],
    "sg:phone":"+1 619 294 5812",
    "sg:postcode":"92103",
    "sg:province":"CA",
    "sg:tags":[
        "residential"
    ],
    "wof:name":"Wayne Norquist General Contrs",
    "wof:placetype":"venue"
},
  "geometry": {"coordinates":[-117.17435999999999,32.751849],"type":"Point"}
}