{
  "type": "Feature",
  "properties": {
    "iso:country":"US",
    "sg:address":"1605 Bellevue Rd",
    "sg:city":"Atwater",
    "sg:classifiers":[
        {
            "category":"Home & Garden",
            "subcategory":"Furniture",
            "type":"Retail Goods"
        }
    ],
    "sg:phone":"+1 209 357 4193",
    "sg:postcode":"95301",
    "sg:province":"CA",
    "wof:name":"LA Bodega Furniture",
    "wof:placetype":"venue"
},
  "geometry": {"coordinates":[-120.613905,37.360409],"type":"Point"}
}