{
  "type": "Feature",
  "properties": {
    "iso:country":"US",
    "sg:address":"325 N Sacramento St",
    "sg:city":"Lodi",
    "sg:classifiers":[
        {
            "category":"Manufacturing",
            "subcategory":"Glass & Minerals",
            "type":"Manufacturing & Wholesale Goods"
        }
    ],
    "sg:phone":"+1 209 369 4751",
    "sg:postcode":"95240",
    "sg:province":"CA",
    "sg:tags":[
        "concrete",
        "brick",
        "prod",
        "block"
    ],
    "wof:name":"Thompson Roofing",
    "wof:placetype":"venue"
},
  "geometry": {"coordinates":[-121.271959,38.13854],"type":"Point"}
}