{
  "type": "Feature",
  "properties": {
    "iso:country":"US",
    "sg:address":"674 Kirkland Dr Ste 3",
    "sg:city":"Sunnyvale",
    "sg:classifiers":[
        {
            "category":"Professional",
            "subcategory":"Art Services",
            "type":"Services"
        },
        {
            "category":"Communications",
            "type":"Services"
        }
    ],
    "sg:phone":"+1 408 341 9805",
    "sg:postcode":"94087",
    "sg:province":"CA",
    "sg:tags":[
        "photographer",
        "graphic",
        "design",
        "web"
    ],
    "sg:website":"www.lalynnidesigns.com",
    "wof:name":"La Lynni Designs",
    "wof:placetype":"venue"
},
  "geometry": {"coordinates":[-122.039451,37.340583],"type":"Point"}
}