{
  "type": "Feature",
  "properties": {
    "addr:full":"3105 Panorama Dr Tahoe City CA 96145",
    "addr:housenumber":"3105",
    "addr:postcode":"96145",
    "addr:street":"Panorama Dr",
    "iso:country":"US",
    "sg:address":"3105 Panorama Dr",
    "sg:city":"Tahoe City",
    "sg:classifiers":[
        {
            "category":"Home & Garden",
            "subcategory":"Garden Supply",
            "type":"Retail Goods"
        }
    ],
    "sg:phone":"+1 530 583 4080",
    "sg:postcode":"96145",
    "sg:province":"CA",
    "sg:tags":[
        "sprinkler"
    ],
    "wof:name":"Tahoe Landscaping Co",
    "wof:placetype":"venue"
},
  "geometry": {"coordinates":[-120.109122,39.188998],"type":"Point"}
}