{
  "type": "Feature",
  "properties": {
    "iso:country":"US",
    "sg:address":"1526 N Dinuba Blvd",
    "sg:city":"Visalia",
    "sg:classifiers":[
        {
            "category":"Utilities",
            "subcategory":"Refuse",
            "type":"Services"
        }
    ],
    "sg:phone":"+1 559 627 6411",
    "sg:postcode":"93291",
    "sg:province":"CA",
    "sg:tags":[
        "recycling",
        "can",
        "aluminum"
    ],
    "wof:name":"B C Recycling",
    "wof:placetype":"venue"
},
  "geometry": {"coordinates":[-119.29677700000001,36.343968],"type":"Point"}
}