{
  "type": "Feature",
  "properties": {
    "addr:full":"7500 Mission Gorge Rd San Diego CA 92120",
    "addr:housenumber":"7500",
    "addr:postcode":"92120",
    "addr:street":"Mission Gorge Rd",
    "iso:country":"US",
    "sg:address":"7500 Mission Gorge Rd",
    "sg:city":"San Diego",
    "sg:classifiers":[
        {
            "category":"Wholesale",
            "subcategory":"Construction Materials",
            "type":"Manufacturing & Wholesale Goods"
        }
    ],
    "sg:phone":"+1 619 265 0296",
    "sg:postcode":"92120",
    "sg:province":"CA",
    "wof:name":"Canyon Rock & Asphalt",
    "wof:placetype":"venue"
},
  "geometry": {"coordinates":[-117.074642,32.807899],"type":"Point"}
}