{
  "type": "Feature",
  "properties": {
    "addr:full":"426 E Pico Blvd Los Angeles CA 90015",
    "addr:housenumber":"426",
    "addr:postcode":"90015",
    "addr:street":"E Pico Blvd",
    "iso:country":"US",
    "sg:address":"426 E Pico Blvd",
    "sg:city":"Los Angeles",
    "sg:classifiers":[
        {
            "category":"Manufacturing",
            "subcategory":"Apparel",
            "type":"Manufacturing & Wholesale Goods"
        }
    ],
    "sg:phone":"+1 213 748 7778",
    "sg:postcode":"90015",
    "sg:province":"CA",
    "sg:tags":[
        "clothes",
        "accessory"
    ],
    "wof:name":"Kid's Paradise",
    "wof:placetype":"venue"
},
  "geometry": {"coordinates":[-118.256169,34.033978],"type":"Point"}
}