{
  "type": "Feature",
  "properties": {
    "addr:full":"10117 Mills Station Rd Sacramento CA 95827",
    "addr:housenumber":"10117",
    "addr:postcode":"95827",
    "addr:street":"Mills Station Rd",
    "iso:country":"US",
    "sg:address":"10117 Mills Station Rd",
    "sg:city":"Sacramento",
    "sg:classifiers":[
        {
            "category":"Home & Garden",
            "subcategory":"Building Materials",
            "type":"Retail Goods"
        }
    ],
    "sg:phone":"+1 916 857 1614",
    "sg:postcode":"95827",
    "sg:province":"CA",
    "sg:tags":[
        "paint"
    ],
    "wof:name":"Warehouse Paint Stores",
    "wof:placetype":"venue"
},
  "geometry": {"coordinates":[-121.311673,38.582498],"type":"Point"}
}