{
  "type": "Feature",
  "properties": {
    "addr:full":"11595 White Ave Apt 51 Adelanto CA 92301",
    "addr:housenumber":"11595;51",
    "addr:postcode":"92301",
    "addr:street":"White Ave Apt",
    "iso:country":"US",
    "sg:address":"11595 White Ave Apt 51",
    "sg:city":"Adelanto",
    "sg:classifiers":[
        {
            "category":"Restaurant",
            "type":"Food & Drink"
        }
    ],
    "sg:phone":"+1 760 694 3300",
    "sg:postcode":"92301",
    "sg:province":"CA",
    "wof:name":"El Nuevo Comienzo",
    "wof:placetype":"venue"
},
  "geometry": {"coordinates":[-117.411874,34.584628],"type":"Point"}
}