{
  "type": "Feature",
  "properties": {
    "addr:full":"1116 N Purdue Ave Clovis CA 93611",
    "addr:housenumber":"1116",
    "addr:postcode":"93611",
    "addr:street":"N Purdue Ave",
    "iso:country":"US",
    "sg:address":"1116 N Purdue Ave",
    "sg:city":"Clovis",
    "sg:classifiers":[
        {
            "category":"Professional",
            "type":"Services"
        }
    ],
    "sg:phone":"+1 559 908 8135",
    "sg:postcode":"93611",
    "sg:province":"CA",
    "wof:name":"Determination-Magazine",
    "wof:placetype":"venue"
},
  "geometry": {"coordinates":[-119.689779,36.850536],"type":"Point"}
}