{
  "type": "Feature",
  "properties": {
    "addr:full":"9064 Brooks Rd S Windsor CA 95492",
    "addr:housenumber":"9064",
    "addr:postcode":"95492",
    "addr:street":"Brooks Rd",
    "iso:country":"US",
    "sg:address":"9064 Brooks Rd S",
    "sg:city":"Windsor",
    "sg:phone":"+1 707 836 9111",
    "sg:postcode":"95492",
    "sg:province":"CA",
    "wof:name":"Windsor Bicycle Center",
    "wof:placetype":"venue"
},
  "geometry": {"coordinates":[-122.80740900000001,38.550787],"type":"Point"}
}