{
  "type": "Feature",
  "properties": {
    "iso:country":"US",
    "sg:address":"2010 Haffley Ave",
    "sg:city":"National City",
    "sg:classifiers":[
        {
            "category":"Manufacturing",
            "subcategory":"Wood Products",
            "type":"Manufacturing & Wholesale Goods"
        }
    ],
    "sg:phone":"+1 619 474 6441",
    "sg:postcode":"91950",
    "sg:province":"CA",
    "sg:tags":[
        "lumber"
    ],
    "wof:name":"S D Wood Preserving Co",
    "wof:placetype":"venue"
},
  "geometry": {"coordinates":[-117.112949,32.6599],"type":"Point"}
}