{
  "type": "Feature",
  "properties": {
    "addr:full":"6382 Clark Rd Paradise CA 95969",
    "addr:housenumber":"6382",
    "addr:postcode":"95969",
    "addr:street":"Clark Rd",
    "iso:country":"US",
    "sg:address":"6382 Clark Rd",
    "sg:city":"Paradise",
    "sg:classifiers":[
        {
            "category":"Retail",
            "subcategory":"Funeral Services",
            "type":"Services"
        },
        {
            "category":"Cemetery",
            "type":"Public Place"
        }
    ],
    "sg:phone":"+1 530 877 4923",
    "sg:postcode":"95969",
    "sg:province":"CA",
    "sg:tags":[
        "director",
        "embalmer",
        "crematory"
    ],
    "wof:name":"Rose Chapel Mortuary-Crematory",
    "wof:placetype":"venue"
},
  "geometry": {"coordinates":[-121.598106,39.770088],"type":"Point"}
}