{
  "type": "Feature",
  "properties": {
    "iso:country":"US",
    "sg:address":"1429 Lanfair St",
    "sg:city":"Redlands",
    "sg:classifiers":[
        {
            "category":"Health Services",
            "subcategory":"Clinic",
            "type":"Services"
        }
    ],
    "sg:phone":"+1 909 915 4544",
    "sg:postcode":"92374",
    "sg:province":"CA",
    "sg:tags":[
        "welfare"
    ],
    "wof:name":"Jnv Medical Diagnostics",
    "wof:placetype":"venue"
},
  "geometry": {"coordinates":[-117.16779,34.072871],"type":"Point"}
}