{
  "type": "Feature",
  "properties": {
    "addr:full":"808 Lassen Dr Hanford CA 93230",
    "addr:housenumber":"808",
    "addr:postcode":"ca 93230",
    "addr:street":"Lassen Dr",
    "iso:country":"US",
    "sg:address":"808 Lassen Dr",
    "sg:city":"Hanford",
    "sg:classifiers":[
        {
            "category":"Communications",
            "subcategory":"Film & Video Production",
            "type":"Services"
        }
    ],
    "sg:phone":"+1 559 582 7710",
    "sg:postcode":"93230",
    "sg:province":"CA",
    "sg:tags":[
        "taping"
    ],
    "wof:name":"Dos Oakies Productions",
    "wof:placetype":"venue"
},
  "geometry": {"coordinates":[-119.628032,36.333231],"type":"Point"}
}