{
  "type": "Feature",
  "properties": {
    "addr:full":"2027 Placentia Ave Costa Mesa CA 92627",
    "addr:housenumber":"2027",
    "addr:postcode":"92627",
    "addr:street":"Placentia Ave",
    "iso:country":"US",
    "sg:address":"2027 Placentia Ave",
    "sg:city":"Costa Mesa",
    "sg:classifiers":[
        {
            "category":"Building & Trades",
            "subcategory":"Construction",
            "type":"Services"
        }
    ],
    "sg:phone":"+1 949 723 5550",
    "sg:postcode":"92627",
    "sg:province":"CA",
    "sg:tags":[
        "heavy",
        "cargo",
        "handler",
        "marine"
    ],
    "wof:name":"Swift Slip Dock and Pier Bldrs",
    "wof:placetype":"venue"
},
  "geometry": {"coordinates":[-117.93206000000001,33.64702],"type":"Point"}
}