{
  "type": "Feature",
  "properties": {
    "iso:country":"US",
    "sg:address":"995 Montague Expwy Suite 112",
    "sg:city":"Milpitas",
    "sg:classifiers":[
        {
            "category":"Health Services",
            "subcategory":"Dentist",
            "type":"Services"
        }
    ],
    "sg:phone":"+1 408 719 1005",
    "sg:postcode":"95035",
    "sg:province":"CA",
    "wof:name":"Thelma C Dawana DDS",
    "wof:placetype":"venue"
},
  "geometry": {"coordinates":[-121.886533,37.412589],"type":"Point"}
}