{
  "type": "Feature",
  "properties": {
    "addr:full":"2440 Wilbur St Oakland CA 94602",
    "addr:housenumber":"2440",
    "addr:postcode":"94602",
    "addr:street":"Wilbur St",
    "iso:country":"US",
    "sg:address":"2440 Wilbur St",
    "sg:city":"Oakland",
    "sg:classifiers":[
        {
            "category":"Building & Trades",
            "subcategory":"Cleaning & Sanitation",
            "type":"Services"
        }
    ],
    "sg:phone":"+1 510 482 8560",
    "sg:postcode":"94602",
    "sg:province":"CA",
    "sg:tags":[
        "janitorial"
    ],
    "wof:name":"Manos Janitorial",
    "wof:placetype":"venue"
},
  "geometry": {"coordinates":[-122.21014700000001,37.803427],"type":"Point"}
}