{
  "type": "Feature",
  "properties": {
    "addr:full":"16003 Quantico Rd Apple Valley CA 92307",
    "addr:housenumber":"16003",
    "addr:postcode":"92307",
    "addr:street":"Quantico Rd",
    "iso:country":"US",
    "sg:address":"16003 Quantico Rd",
    "sg:city":"Apple Valley",
    "sg:classifiers":[
        {
            "category":"Banks & Credit Unions",
            "subcategory":"Bank",
            "type":"Services"
        }
    ],
    "sg:phone":"+1 760 243 2140",
    "sg:postcode":"92307",
    "sg:province":"CA",
    "wof:name":"Desert Community Bank",
    "wof:placetype":"venue"
},
  "geometry": {"coordinates":[-117.270685,34.541595],"type":"Point"}
}