{
  "type": "Feature",
  "properties": {
    "iso:country":"US",
    "sg:address":"214 Winston St",
    "sg:city":"Los Angeles",
    "sg:classifiers":[
        {
            "category":"Shopping",
            "subcategory":"Jewelry",
            "type":"Retail Goods"
        }
    ],
    "sg:phone":"+1 213 892 0414",
    "sg:postcode":"90013",
    "sg:province":"CA",
    "wof:name":"Mi Casa",
    "wof:placetype":"venue"
},
  "geometry": {"coordinates":[-118.246583,34.046237],"type":"Point"}
}