{
  "type": "Feature",
  "properties": {
    "addr:full":"5460 Florin Rd Sacramento CA 95823",
    "addr:housenumber":"5460",
    "addr:postcode":"95823",
    "addr:street":"Florin Rd",
    "iso:country":"US",
    "sg:address":"5460 Florin Rd",
    "sg:city":"Sacramento",
    "sg:classifiers":[
        {
            "category":"Restaurant",
            "type":"Food & Drink"
        }
    ],
    "sg:menulink":"http://www.allmenus.com/ca/sacramento/8199-dennys/menu/",
    "sg:phone":"+1 916 428 2187",
    "sg:postcode":"95823",
    "sg:province":"CA",
    "sg:tags":[
        "american",
        "diner"
    ],
    "wof:name":"Denny's",
    "wof:placetype":"venue"
},
  "geometry": {"coordinates":[-121.442204,38.49562],"type":"Point"}
}