{
  "type": "Feature",
  "properties": {
    "iso:country":"US",
    "sg:address":"710 W 18th St",
    "sg:city":"Merced",
    "sg:classifiers":[
        {
            "category":"Social Services",
            "subcategory":"Adult Care",
            "type":"Services"
        }
    ],
    "sg:phone":"+1 209 723 2093",
    "sg:postcode":"95340",
    "sg:province":"CA",
    "sg:tags":[
        "foster"
    ],
    "wof:name":"Approachable Foster Family",
    "wof:placetype":"venue"
},
  "geometry": {"coordinates":[-120.487229,37.303967],"type":"Point"}
}