{
  "type": "Feature",
  "properties": {
    "addr:full":"325 Henry St Vallejo CA 94591",
    "addr:housenumber":"325",
    "addr:postcode":"94591",
    "addr:street":"Henry St",
    "iso:country":"US",
    "sg:address":"325 Henry St",
    "sg:city":"Vallejo",
    "sg:classifiers":[
        {
            "category":"Personal",
            "subcategory":"Beauty Salon",
            "type":"Services"
        }
    ],
    "sg:phone":"+1 707 649 1676",
    "sg:postcode":"94591",
    "sg:province":"CA",
    "wof:name":"One Step Beyond",
    "wof:placetype":"venue"
},
  "geometry": {"coordinates":[-122.228162,38.111925],"type":"Point"}
}