{
  "type": "Feature",
  "properties": {
    "iso:country":"US",
    "sg:address":"9151 Greenspot Rd",
    "sg:city":"Mentone",
    "sg:classifiers":[
        {
            "category":"Farming",
            "subcategory":"Poultry Farm",
            "type":"Manufacturing & Wholesale Goods"
        }
    ],
    "sg:phone":"+1 909 793 3801",
    "sg:postcode":"92359",
    "sg:province":"CA",
    "sg:tags":[
        "citrus",
        "grove",
        "chicken",
        "fruit",
        "egg"
    ],
    "wof:name":"Arnott Poultry & Citrus Ranch",
    "wof:placetype":"venue"
},
  "geometry": {"coordinates":[-117.112872,34.086941],"type":"Point"}
}