{
  "type": "Feature",
  "properties": {
    "addr:full":"27737 Bouquet Canyon Rd, # 124 Santa Clarita CA 91350",
    "addr:housenumber":"27737",
    "addr:postcode":"91350",
    "addr:street":"Bouquet Canyon Rd # 124",
    "iso:country":"US",
    "sg:address":"27737 Bouquet Canyon Rd, # 124",
    "sg:city":"Santa Clarita",
    "sg:classifiers":[
        {
            "category":"Shopping",
            "subcategory":"Pets & Pet Supplies",
            "type":"Retail Goods"
        }
    ],
    "sg:phone":"+1 661 296 2020",
    "sg:postcode":"91350",
    "sg:province":"CA",
    "sg:tags":[
        "groomers"
    ],
    "wof:name":"Precious Pets",
    "wof:placetype":"venue"
},
  "geometry": {"coordinates":[-118.50760200000001,34.445306],"type":"Point"}
}