{
  "type": "Feature",
  "properties": {
    "iso:country":"US",
    "sg:address":"1944 E Pico Ave",
    "sg:city":"Fresno",
    "sg:classifiers":[
        {
            "category":"Building & Trades",
            "subcategory":"Landscaping Services",
            "type":"Services"
        }
    ],
    "sg:phone":"+1 559 225 1271",
    "sg:postcode":"93726",
    "sg:province":"CA",
    "wof:name":"A A A Gardening & Lawn Care",
    "wof:placetype":"venue"
},
  "geometry": {"coordinates":[-119.787178,36.802013],"type":"Point"}
}