{
  "type": "Feature",
  "properties": {
    "iso:country":"US",
    "sg:address":"1250 Oakmead Parkway  Suite 210",
    "sg:city":"Sunnyvale",
    "sg:classifiers":[
        {
            "category":"Professional",
            "subcategory":"Computer Services",
            "type":"Services"
        }
    ],
    "sg:postcode":"94085",
    "sg:province":"CA",
    "sg:tags":[
        "web-2-0",
        "rich-media",
        "internet-radio",
        "playlists",
        "social-networks",
        "social-networking",
        "music",
        "videos",
        "films",
        "entertainment",
        "real-time",
        "portal",
        "artists",
        "events",
        "collaboration",
        "broadcasting",
        "film-producers",
        "directors",
        "actors",
        "bands"
    ],
    "sg:website":"http://www.ibuddz.com",
    "wof:name":"iBuddz",
    "wof:placetype":"venue"
},
  "geometry": {"coordinates":[-121.99093499999999,37.386715],"type":"Point"}
}