{
  "type": "Feature",
  "properties": {
    "addr:full":"32 Carr Dr Moraga CA 94556",
    "addr:housenumber":"32",
    "addr:postcode":"94556",
    "addr:street":"Carr Dr",
    "iso:country":"US",
    "sg:address":"32 Carr Dr",
    "sg:city":"Moraga",
    "sg:classifiers":[
        {
            "category":"Wholesale",
            "subcategory":"Construction Materials",
            "type":"Manufacturing & Wholesale Goods"
        }
    ],
    "sg:phone":"+1 925 376 7188",
    "sg:postcode":"94556",
    "sg:province":"CA",
    "wof:name":"Shi Haw Stone Co Ltd",
    "wof:placetype":"venue"
},
  "geometry": {"coordinates":[-122.123659,37.83177],"type":"Point"}
}