{
  "type": "Feature",
  "properties": {
    "addr:full":"6325 Topanga Canyon Blvd Ste 301 Woodland Hills CA 91367",
    "addr:housenumber":"6325",
    "addr:postcode":"91367",
    "addr:street":"Topanga Canyon Blvd Ste 301",
    "iso:country":"US",
    "sg:address":"6325 Topanga Canyon Blvd Ste 301",
    "sg:city":"Woodland Hills",
    "sg:classifiers":[
        {
            "category":"Health Services",
            "subcategory":"Doctor",
            "type":"Services"
        }
    ],
    "sg:phone":"+1 818 884 9290",
    "sg:postcode":"91367",
    "sg:province":"CA",
    "sg:tags":[
        "dermatologist"
    ],
    "wof:name":"Laser Rejuvenation Institute",
    "wof:placetype":"venue"
},
  "geometry": {"coordinates":[-118.606003,34.185398],"type":"Point"}
}