{
  "type": "Feature",
  "properties": {
    "iso:country":"US",
    "sg:address":"550 Water St Ste A",
    "sg:city":"Santa Cruz",
    "sg:classifiers":[
        {
            "category":"Health Services",
            "subcategory":"Doctor",
            "type":"Services"
        }
    ],
    "sg:phone":"+1 831 425 0420",
    "sg:postcode":"95060",
    "sg:province":"CA",
    "sg:tags":[
        "practice",
        "family"
    ],
    "wof:name":"Steven Cortes, MD",
    "wof:placetype":"venue"
},
  "geometry": {"coordinates":[-122.01911800000001,36.979659],"type":"Point"}
}