{
  "type": "Feature",
  "properties": {
    "iso:country":"US",
    "sg:address":"2640 Mercantile Dr",
    "sg:city":"Rancho Cordova",
    "sg:classifiers":[
        {
            "category":"Home & Garden",
            "subcategory":"Furniture",
            "type":"Retail Goods"
        }
    ],
    "sg:phone":"+1 916 635 4787",
    "sg:postcode":"95742",
    "sg:province":"CA",
    "sg:tags":[
        "equipment",
        "kitchen",
        "cabinet"
    ],
    "wof:name":"Special Wood Products",
    "wof:placetype":"venue"
},
  "geometry": {"coordinates":[-121.261095,38.604396],"type":"Point"}
}