{
  "type": "Feature",
  "properties": {
    "iso:country":"US",
    "sg:address":"8100 E Zayante Rd",
    "sg:city":"Felton",
    "sg:classifiers":[
        {
            "category":"Wholesale",
            "subcategory":"Machinery & Supplies",
            "type":"Manufacturing & Wholesale Goods"
        }
    ],
    "sg:phone":"+1 831 335 9161",
    "sg:postcode":"95018",
    "sg:province":"CA",
    "sg:tags":[
        "pump"
    ],
    "wof:name":"Martin Whittingham Pumps",
    "wof:placetype":"venue"
},
  "geometry": {"coordinates":[-122.056346,37.071322],"type":"Point"}
}