{
  "type": "Feature",
  "properties": {
    "addr:full":"125 Ordway St San Francisco CA 94134",
    "addr:housenumber":"125",
    "addr:postcode":"94134",
    "addr:street":"Ordway St",
    "iso:country":"US",
    "sg:address":"125 Ordway St",
    "sg:city":"San Francisco",
    "sg:classifiers":[
        {
            "category":"Shopping",
            "type":"Retail Goods"
        }
    ],
    "sg:phone":"+1 415 330 0717",
    "sg:postcode":"94134",
    "sg:province":"CA",
    "sg:tags":[
        "art",
        "gallery",
        "dealer"
    ],
    "wof:name":"Arts Grafika Fine Orginal Prnt",
    "wof:placetype":"venue"
},
  "geometry": {"coordinates":[-122.402371,37.719915],"type":"Point"}
}