{
  "type": "Feature",
  "properties": {
    "addr:full":"18716 Ventura Blvd Tarzana CA 91356",
    "addr:housenumber":"18716",
    "addr:postcode":"91356",
    "addr:street":"Ventura Blvd",
    "iso:country":"US",
    "sg:address":"18716 Ventura Blvd",
    "sg:city":"Tarzana",
    "sg:classifiers":[
        {
            "category":"Shopping",
            "subcategory":"Clothing, Apparel, & Fashions",
            "type":"Retail Goods"
        }
    ],
    "sg:phone":"+1 818 708 3293",
    "sg:postcode":"91356",
    "sg:province":"CA",
    "sg:tags":[
        "infant",
        "wear"
    ],
    "sg:website":"www.childrensplace.com",
    "wof:name":"Children's Place",
    "wof:placetype":"venue"
},
  "geometry": {"coordinates":[-118.54255000000001,34.171305],"type":"Point"}
}