{
  "type": "Feature",
  "properties": {
    "addr:full":"465 California St Ste 1200 San Francisco CA 94110",
    "addr:housenumber":"465",
    "addr:postcode":"94110",
    "addr:street":"California St Ste 1200",
    "iso:country":"US",
    "sg:address":"465 California St Ste 1200",
    "sg:city":"San Francisco",
    "sg:classifiers":[
        {
            "category":"Professional",
            "type":"Services"
        }
    ],
    "sg:phone":"+1 415 677 0966",
    "sg:postcode":"94110",
    "sg:province":"CA",
    "sg:website":"www.bdearch.com",
    "wof:name":"BDE Architecture",
    "wof:placetype":"venue"
},
  "geometry": {"coordinates":[-122.402129,37.792541],"type":"Point"}
}