{
  "type": "Feature",
  "properties": {
    "iso:country":"US",
    "sg:address":"16609 Cerise Ave",
    "sg:city":"Torrance",
    "sg:classifiers":[
        {
            "category":"Travel",
            "subcategory":"Travel Agent",
            "type":"Entertainment"
        }
    ],
    "sg:phone":"+1 310 271 3436",
    "sg:postcode":"90504",
    "sg:province":"CA",
    "sg:tags":[
        "agency"
    ],
    "wof:name":"GBS Travel Inc",
    "wof:placetype":"venue"
},
  "geometry": {"coordinates":[-118.333032,33.878149],"type":"Point"}
}