{
  "type": "Feature",
  "properties": {
    "addr:full":"13308 Maclay St San Fernando CA 91340",
    "addr:housenumber":"13308",
    "addr:postcode":"91340",
    "addr:street":"Maclay St",
    "iso:country":"US",
    "sg:address":"13308 Maclay St",
    "sg:city":"San Fernando",
    "sg:classifiers":[
        {
            "category":"Organizations",
            "subcategory":"Community Association",
            "type":"Services"
        }
    ],
    "sg:phone":"+1 818 361 9855",
    "sg:postcode":"91340",
    "sg:province":"CA",
    "sg:tags":[
        "fraternal"
    ],
    "wof:name":"Knights Of Columbus",
    "wof:placetype":"venue"
},
  "geometry": {"coordinates":[-118.423193,34.296444],"type":"Point"}
}