{
  "type": "Feature",
  "properties": {
    "iso:country":"US",
    "sg:address":"1911 Douglas Blvd",
    "sg:city":"Roseville",
    "sg:classifiers":[
        {
            "category":"Freight",
            "type":"Transportation"
        }
    ],
    "sg:phone":"+1 916 786 3882",
    "sg:postcode":"95661",
    "sg:province":"CA",
    "wof:name":"Millennium Transportation",
    "wof:placetype":"venue"
},
  "geometry": {"coordinates":[-121.253227,38.744332],"type":"Point"}
}