{
  "type": "Feature",
  "properties": {
    "iso:country":"US",
    "sg:address":"1149 B St",
    "sg:city":"Hayward",
    "sg:classifiers":[
        {
            "category":"Restaurant",
            "type":"Food & Drink"
        }
    ],
    "sg:phone":"+1 510 581 6580",
    "sg:postcode":"94541",
    "sg:province":"CA",
    "sg:tags":[
        "thai"
    ],
    "wof:name":"Paya Thai",
    "wof:placetype":"venue"
},
  "geometry": {"coordinates":[-122.08000199999999,37.674999],"type":"Point"}
}