{
  "type": "Feature",
  "properties": {
    "iso:country":"US",
    "sg:address":"1057 Village Ln",
    "sg:city":"Chico",
    "sg:classifiers":[
        {
            "category":"Health Services",
            "subcategory":"Doctor",
            "type":"Services"
        }
    ],
    "sg:phone":"+1 530 343 7306",
    "sg:postcode":"95926",
    "sg:province":"CA",
    "sg:tags":[
        "dentist"
    ],
    "wof:name":"David C Brown DDS",
    "wof:placetype":"venue"
},
  "geometry": {"coordinates":[-121.825284,39.749088],"type":"Point"}
}