{
  "type": "Feature",
  "properties": {
    "iso:country":"US",
    "sg:address":"8315 Avalon Blvd",
    "sg:city":"Los Angeles",
    "sg:classifiers":[
        {
            "category":"Real Estate",
            "subcategory":"Real Estate Agent",
            "type":"Services"
        }
    ],
    "sg:phone":"+1 323 971 8211",
    "sg:postcode":"90003",
    "sg:province":"CA",
    "wof:name":"W A Ayers Real Estate Svc",
    "wof:placetype":"venue"
},
  "geometry": {"coordinates":[-118.265202,33.962983],"type":"Point"}
}