{
  "type": "Feature",
  "properties": {
    "iso:country":"US",
    "sg:address":"15623 Village Dr",
    "sg:city":"Victorville",
    "sg:classifiers":[
        {
            "category":"Restaurant",
            "type":"Food & Drink"
        }
    ],
    "sg:phone":"+1 866 786 1564",
    "sg:postcode":"92394",
    "sg:province":"CA",
    "sg:tags":[
        "mexican"
    ],
    "wof:name":"Los Sanchez Mexican Restaurant",
    "wof:placetype":"venue"
},
  "geometry": {"coordinates":[-117.31627400000001,34.534789],"type":"Point"}
}