{
  "type": "Feature",
  "properties": {
    "iso:country":"US",
    "sg:address":"7507 Rio Dixon Rd",
    "sg:city":"Dixon",
    "sg:classifiers":[
        {
            "category":"Building & Trades",
            "subcategory":"Construction",
            "type":"Services"
        }
    ],
    "sg:phone":"+1 707 678 8100",
    "sg:postcode":"95620",
    "sg:province":"CA",
    "sg:tags":[
        "equipment",
        "station"
    ],
    "sg:website":"www.alphapetro.com",
    "wof:name":"Alpha Petroleum Svc Inc",
    "wof:placetype":"venue"
},
  "geometry": {"coordinates":[-121.822726,38.424352],"type":"Point"}
}