{
  "type": "Feature",
  "properties": {
    "iso:country":"US",
    "sg:address":"600 Avenida del Sol",
    "sg:city":"Corona",
    "sg:classifiers":[
        {
            "category":"Manufacturing",
            "subcategory":"Metals",
            "type":"Manufacturing & Wholesale Goods"
        }
    ],
    "sg:phone":"+1 951 734 9655",
    "sg:postcode":"92882",
    "sg:province":"CA",
    "sg:tags":[
        "steel",
        "erectors"
    ],
    "wof:name":"Alco Engineering",
    "wof:placetype":"venue"
},
  "geometry": {"coordinates":[-117.576714,33.845989],"type":"Point"}
}