{
  "type": "Feature",
  "properties": {
    "iso:country":"US",
    "sg:address":"6011 Variel Ave",
    "sg:city":"Woodland Hills",
    "sg:classifiers":[
        {
            "category":"Shopping",
            "subcategory":"Computers & Home Electronics",
            "type":"Retail Goods"
        }
    ],
    "sg:phone":"+1 818 654 9959",
    "sg:postcode":"91367",
    "sg:province":"CA",
    "sg:tags":[
        "equipment",
        "dealer"
    ],
    "sg:website":"www.lamicrogroup.com",
    "wof:name":"L A Micro Group",
    "wof:placetype":"venue"
},
  "geometry": {"coordinates":[-118.592856,34.182677],"type":"Point"}
}