{
  "type": "Feature",
  "properties": {
    "addr:full":"750 Cypress Ave San Bruno CA 94066",
    "addr:housenumber":"750",
    "addr:postcode":"94066",
    "addr:street":"Cypress Ave",
    "iso:country":"US",
    "sg:address":"750 Cypress Ave",
    "sg:city":"San Bruno",
    "sg:classifiers":[
        {
            "category":"Professional",
            "type":"Services"
        }
    ],
    "sg:phone":"+1 650 869 4160",
    "sg:postcode":"94066",
    "sg:province":"CA",
    "sg:tags":[
        "writer"
    ],
    "wof:name":"Sponsor Write",
    "wof:placetype":"venue"
},
  "geometry": {"coordinates":[-122.42032399999999,37.625367],"type":"Point"}
}