{
  "type": "Feature",
  "properties": {
    "addr:full":"187 E Wilbur Rd Thousand Oaks CA 91360",
    "addr:housenumber":"187",
    "addr:postcode":"91360",
    "addr:street":"E Wilbur Rd",
    "iso:country":"US",
    "sg:address":"187 E Wilbur Rd",
    "sg:city":"Thousand Oaks",
    "sg:classifiers":[
        {
            "category":"Insurance",
            "subcategory":"Insurance Agent",
            "type":"Services"
        }
    ],
    "sg:phone":"+1 805 374 7846",
    "sg:postcode":"91360",
    "sg:province":"CA",
    "wof:name":"State Farm Insurance",
    "wof:placetype":"venue"
},
  "geometry": {"coordinates":[-118.874589,34.186668],"type":"Point"}
}