{
  "type": "Feature",
  "properties": {
    "addr:full":"4038 Promontory St San Diego CA 92109",
    "addr:housenumber":"4038",
    "addr:postcode":"92109",
    "addr:street":"Promontory St",
    "iso:country":"US",
    "sg:address":"4038 Promontory St",
    "sg:city":"San Diego",
    "sg:classifiers":[
        {
            "category":"Professional",
            "subcategory":"Business Services",
            "type":"Services"
        }
    ],
    "sg:phone":"+1 858 490 1098",
    "sg:postcode":"92109",
    "sg:province":"CA",
    "sg:tags":[
        "broker",
        "merchandise"
    ],
    "wof:name":"Lighthouse Brokerage Group",
    "wof:placetype":"venue"
},
  "geometry": {"coordinates":[-117.23991599999999,32.793108],"type":"Point"}
}