{
  "type": "Feature",
  "properties": {
    "iso:country":"US",
    "sg:address":"4941 Whittier Blvd",
    "sg:city":"Los Angeles",
    "sg:classifiers":[
        {
            "category":"Personal",
            "subcategory":"Beauty Salon",
            "type":"Services"
        }
    ],
    "sg:phone":"+1 323 267 8150",
    "sg:postcode":"90022",
    "sg:province":"CA",
    "wof:name":"Strand's Beauty Salon",
    "wof:placetype":"venue"
},
  "geometry": {"coordinates":[-118.163207,34.02174],"type":"Point"}
}