{
  "type": "Feature",
  "properties": {
    "addr:full":"20656 Redwood Rd Castro Valley CA 94546",
    "addr:housenumber":"20656",
    "addr:postcode":"94546",
    "addr:street":"Redwood Rd",
    "iso:country":"US",
    "sg:address":"20656 Redwood Rd",
    "sg:city":"Castro Valley",
    "sg:classifiers":[
        {
            "category":"Real Estate",
            "subcategory":"Real Estate Agent",
            "type":"Services"
        }
    ],
    "sg:phone":"+1 510 582 4000",
    "sg:postcode":"94546",
    "sg:province":"CA",
    "wof:name":"Bigelow Richard G Realtor",
    "wof:placetype":"venue"
},
  "geometry": {"coordinates":[-122.07399700000001,37.696602],"type":"Point"}
}