{
  "type": "Feature",
  "properties": {
    "addr:full":"14802 Espola Rd Poway CA 92064",
    "addr:housenumber":"14802",
    "addr:postcode":"ca 92064",
    "addr:street":"Espola Rd",
    "iso:country":"US",
    "sg:address":"14802 Espola Rd",
    "sg:city":"Poway",
    "sg:classifiers":[
        {
            "category":"Manufacturing",
            "subcategory":"Metals",
            "type":"Manufacturing & Wholesale Goods"
        },
        {
            "category":"Wholesale",
            "subcategory":"Hardware",
            "type":"Manufacturing & Wholesale Goods"
        }
    ],
    "sg:phone":"+1 858 748 7359",
    "sg:postcode":"92064",
    "sg:province":"CA",
    "sg:tags":[
        "equipment",
        "heating"
    ],
    "sg:website":"www.gotoevo.com",
    "wof:name":"Evolution Control Inc",
    "wof:placetype":"venue"
},
  "geometry": {"coordinates":[-117.023398,32.983541],"type":"Point"}
}