{
  "type": "Feature",
  "properties": {
    "addr:full":"1191 E Springville Ave Porterville CA 93257",
    "addr:housenumber":"1191",
    "addr:postcode":"93257",
    "addr:street":"E Springville Ave",
    "iso:country":"US",
    "sg:address":"1191 E Springville Ave",
    "sg:city":"Porterville",
    "sg:classifiers":[
        {
            "category":"Autos & Motor Vehicles",
            "subcategory":"Auto Supplies",
            "type":"Retail Goods"
        },
        {
            "category":"Retail",
            "subcategory":"Auto Repair",
            "type":"Services"
        }
    ],
    "sg:phone":"+1 559 781 1308",
    "sg:postcode":"93257",
    "sg:province":"CA",
    "sg:tags":[
        "tire"
    ],
    "wof:name":"Maciel Auto Repair",
    "wof:placetype":"venue"
},
  "geometry": {"coordinates":[-118.98866099999999,36.055094],"type":"Point"}
}