{
  "type": "Feature",
  "properties": {
    "iso:country":"US",
    "sg:address":"28 Jewell St",
    "sg:city":"San Rafael",
    "sg:classifiers":[
        {
            "category":"Building & Trades",
            "subcategory":"Plumbing",
            "type":"Services"
        }
    ],
    "sg:phone":"+1 415 499 0111",
    "sg:postcode":"94901",
    "sg:province":"CA",
    "sg:tags":[
        "plumbing",
        "contractor"
    ],
    "sg:website":"www.lehmannplumbing.com",
    "wof:name":"Lehmann Plumbing Inc",
    "wof:placetype":"venue"
},
  "geometry": {"coordinates":[-122.511092,37.974155],"type":"Point"}
}