{
  "type": "Feature",
  "properties": {
    "addr:full":"7947 Mission Center Ct San Diego CA 92108",
    "addr:housenumber":"7947",
    "addr:postcode":"92108",
    "addr:street":"Mission Center Ct",
    "iso:country":"US",
    "sg:address":"7947 Mission Center Ct",
    "sg:city":"San Diego",
    "sg:classifiers":[
        {
            "category":"Government",
            "subcategory":"Office",
            "type":"Public Place"
        }
    ],
    "sg:phone":"+1 619 557 4120",
    "sg:postcode":"92108",
    "sg:province":"CA",
    "wof:name":"San Diego Refugee Employment",
    "wof:placetype":"venue"
},
  "geometry": {"coordinates":[-117.154098,32.773476],"type":"Point"}
}