{
  "type": "Feature",
  "properties": {
    "iso:country":"US",
    "sg:address":"55 US Hwy 50",
    "sg:city":"Stateline",
    "sg:classifiers":[
        {
            "category":"Travel",
            "subcategory":"Hotels & Motels",
            "type":"Entertainment"
        }
    ],
    "sg:phone":"+1 775 588 3515",
    "sg:postcode":"89448",
    "sg:province":"CA",
    "sg:website":"www.caesars.com",
    "wof:name":"Caesars Tahoe",
    "wof:placetype":"venue"
},
  "geometry": {"coordinates":[-119.939308,38.963253],"type":"Point"}
}