{
  "type": "Feature",
  "properties": {
    "addr:full":"869 W Lacey Blvd Hanford CA 93230",
    "addr:housenumber":"869",
    "addr:postcode":"ca 93230",
    "addr:street":"W Lacey Blvd",
    "iso:country":"US",
    "sg:address":"869 W Lacey Blvd",
    "sg:city":"Hanford",
    "sg:classifiers":[
        {
            "category":"Health Services",
            "subcategory":"Clinic",
            "type":"Services"
        },
        {
            "category":"Community Center",
            "type":"Public Place"
        }
    ],
    "sg:phone":"+1 559 582 9313",
    "sg:postcode":"93230",
    "sg:province":"CA",
    "sg:tags":[
        "medical"
    ],
    "wof:name":"Hanford Urgent Care",
    "wof:placetype":"venue"
},
  "geometry": {"coordinates":[-119.657601,36.32806],"type":"Point"}
}