{
  "type": "Feature",
  "properties": {
    "iso:country":"US",
    "sg:address":"5115 Douglas Fir Rd",
    "sg:city":"Calabasas",
    "sg:classifiers":[
        {
            "category":"Building & Trades",
            "subcategory":"Cleaning & Sanitation",
            "type":"Services"
        }
    ],
    "sg:phone":"+1 818 591 0788",
    "sg:postcode":"91302",
    "sg:province":"CA",
    "sg:tags":[
        "chemical"
    ],
    "wof:name":"Silver Sales",
    "wof:placetype":"venue"
},
  "geometry": {"coordinates":[-118.648426,34.156233],"type":"Point"}
}