{
  "type": "Feature",
  "properties": {
    "addr:full":"9252 Garden Grove Blvd Ste 29 Garden Grove CA 92844",
    "addr:housenumber":"9252",
    "addr:postcode":"92844",
    "addr:street":"Garden Grove Blvd Ste 29",
    "iso:country":"US",
    "sg:address":"9252 Garden Grove Blvd Ste 29",
    "sg:city":"Garden Grove",
    "sg:classifiers":[
        {
            "category":"Bars & Pubs",
            "type":"Food & Drink"
        },
        {
            "category":"Restaurant",
            "type":"Food & Drink"
        }
    ],
    "sg:phone":"+1 714 638 7818",
    "sg:postcode":"92844",
    "sg:province":"CA",
    "sg:tags":[
        "korean"
    ],
    "wof:name":"The Past Memories",
    "wof:placetype":"venue"
},
  "geometry": {"coordinates":[-117.969826,33.773884],"type":"Point"}
}