{
  "type": "Feature",
  "properties": {
    "iso:country":"US",
    "sg:address":"545 Saratoga Ave",
    "sg:city":"Santa Clara",
    "sg:classifiers":[
        {
            "category":"Health Services",
            "subcategory":"Medical Lab",
            "type":"Services"
        }
    ],
    "sg:phone":"+1 408 241 6767",
    "sg:postcode":"95050",
    "sg:province":"CA",
    "sg:tags":[
        "laboratory"
    ],
    "wof:name":"Den Frog Dental Lab",
    "wof:placetype":"venue"
},
  "geometry": {"coordinates":[-121.957825,37.337603],"type":"Point"}
}