{
  "type": "Feature",
  "properties": {
    "addr:full":"61 Rickenbacker Cir Livermore CA 94550",
    "addr:housenumber":"61",
    "addr:postcode":"94550",
    "addr:street":"Rickenbacker Cir",
    "iso:country":"US",
    "sg:address":"61 Rickenbacker Cir",
    "sg:city":"Livermore",
    "sg:classifiers":[
        {
            "category":"Home & Garden",
            "subcategory":"Mobile Homes",
            "type":"Retail Goods"
        }
    ],
    "sg:phone":"+1 925 606 9001",
    "sg:postcode":"94550",
    "sg:province":"CA",
    "sg:tags":[
        "commercial",
        "unit"
    ],
    "wof:name":"Quick Set Construction Co Inc",
    "wof:placetype":"venue"
},
  "geometry": {"coordinates":[-121.80434700000001,37.690906],"type":"Point"}
}