{
  "type": "Feature",
  "properties": {
    "iso:country":"US",
    "sg:address":"32920 Mission Trl",
    "sg:city":"Lake Elsinore",
    "sg:classifiers":[
        {
            "category":"Autos & Motor Vehicles",
            "subcategory":"Auto Supplies",
            "type":"Retail Goods"
        }
    ],
    "sg:phone":"+1 951 674 8838",
    "sg:postcode":"92530",
    "sg:province":"CA",
    "sg:tags":[
        "tire"
    ],
    "wof:name":"Tire Stop",
    "wof:placetype":"venue"
},
  "geometry": {"coordinates":[-117.291443,33.642285],"type":"Point"}
}