{
  "type": "Feature",
  "properties": {
    "addr:full":"274 Bon Air Rd Greenbrae CA 94939",
    "addr:housenumber":"274",
    "addr:postcode":"94939",
    "addr:street":"Bon Air Rd",
    "iso:country":"US",
    "sg:address":"274 Bon Air Rd",
    "sg:city":"Greenbrae",
    "sg:classifiers":[
        {
            "category":"Restaurant",
            "type":"Food & Drink"
        }
    ],
    "sg:phone":"+1 415 461 1731",
    "sg:postcode":"94939",
    "sg:province":"CA",
    "wof:name":"Papa Murphy's Take 'N' Bake",
    "wof:placetype":"venue"
},
  "geometry": {"coordinates":[-122.53926199999999,37.943967],"type":"Point"}
}