{
  "type": "Feature",
  "properties": {
    "addr:full":"338 Westbrook Pl Costa Mesa CA 92626",
    "addr:housenumber":"338",
    "addr:postcode":"92626",
    "addr:street":"Westbrook Pl",
    "iso:country":"US",
    "sg:address":"338 Westbrook Pl",
    "sg:city":"Costa Mesa",
    "sg:classifiers":[
        {
            "category":"Shopping",
            "type":"Retail Goods"
        }
    ],
    "sg:phone":"+1 714 751 2428",
    "sg:postcode":"92626",
    "sg:province":"CA",
    "sg:tags":[
        "merchandise"
    ],
    "wof:name":"Harber Ranch",
    "wof:placetype":"venue"
},
  "geometry": {"coordinates":[-117.914383,33.665346],"type":"Point"}
}