{
  "type": "Feature",
  "properties": {
    "addr:full":"6254 Santa Teresa Blvd San Jose CA 95119",
    "addr:housenumber":"6254",
    "addr:postcode":"95119",
    "addr:street":"Santa Teresa Blvd",
    "iso:country":"US",
    "sg:address":"6254 Santa Teresa Blvd",
    "sg:city":"San Jose",
    "sg:classifiers":[
        {
            "category":"Real Estate",
            "subcategory":"Real Estate Operator",
            "type":"Services"
        }
    ],
    "sg:phone":"+1 408 613 2607",
    "sg:postcode":"95119",
    "sg:province":"CA",
    "sg:tags":[
        "apartment"
    ],
    "wof:name":"Santa Teresa Apartments",
    "wof:placetype":"venue"
},
  "geometry": {"coordinates":[-121.796997,37.236801],"type":"Point"}
}