{
  "type": "Feature",
  "properties": {
    "iso:country":"US",
    "sg:address":"2727 W 6th Street",
    "sg:city":"Los Angeles",
    "sg:classifiers":[
        {
            "category":"Food & Beverages",
            "subcategory":"Specialty",
            "type":"Retail Goods"
        }
    ],
    "sg:phone":"+1 213 738 7378",
    "sg:postcode":"90057",
    "sg:province":"CA",
    "wof:name":"Oasis Snack Shop",
    "wof:placetype":"venue"
},
  "geometry": {"coordinates":[-118.282284,34.062769],"type":"Point"}
}