{
  "type": "Feature",
  "properties": {
    "addr:full":"4400 E. Gage Ave Bell CA 90201",
    "addr:housenumber":"4400",
    "addr:postcode":"90201",
    "addr:street":"E. Gage Ave",
    "iso:country":"US",
    "sg:address":"4400 E. Gage Ave",
    "sg:city":"Bell",
    "sg:classifiers":[
        {
            "category":"Building & Trades",
            "subcategory":"Locksmith",
            "type":"Services"
        }
    ],
    "sg:phone":"+1 323 798 9056",
    "sg:postcode":"90201",
    "sg:province":"CA",
    "sg:tags":[
        "key"
    ],
    "wof:name":"Emergency Locksmith",
    "wof:placetype":"venue"
},
  "geometry": {"coordinates":[-118.189116,33.977942],"type":"Point"}
}