{
  "type": "Feature",
  "properties": {
    "iso:country":"US",
    "sg:address":"860 Via de la Paz",
    "sg:city":"Pacific Palisades",
    "sg:classifiers":[
        {
            "category":"Personal",
            "subcategory":"Shoe Repair & Shine",
            "type":"Services"
        }
    ],
    "sg:phone":"+1 310 454 3847",
    "sg:postcode":"90272",
    "sg:province":"CA",
    "sg:tags":[
        "parlor",
        "shoes"
    ],
    "wof:name":"Palisades Shoe Repair",
    "wof:placetype":"venue"
},
  "geometry": {"coordinates":[-118.527335,34.045669],"type":"Point"}
}