{
  "type": "Feature",
  "properties": {
    "addr:full":"616 E 18th St Antioch CA 94509",
    "addr:housenumber":"616",
    "addr:postcode":"ca 94509",
    "addr:street":"E 18Th St",
    "iso:country":"US",
    "sg:address":"616 E 18th St",
    "sg:city":"Antioch",
    "sg:classifiers":[
        {
            "category":"Retail",
            "subcategory":"Repair Shop",
            "type":"Services"
        }
    ],
    "sg:phone":"+1 925 757 0405",
    "sg:postcode":"94509",
    "sg:province":"CA",
    "sg:tags":[
        "repairing",
        "lawn",
        "mower"
    ],
    "wof:name":"Mello's Lawnmower & Saw Shop",
    "wof:placetype":"venue"
},
  "geometry": {"coordinates":[-121.794178,38.004829],"type":"Point"}
}