{
  "type": "Feature",
  "properties": {
    "addr:full":"701 School St Napa CA 94559",
    "addr:housenumber":"701",
    "addr:postcode":"94559",
    "addr:street":"School St",
    "iso:country":"US",
    "sg:address":"701 School St",
    "sg:city":"Napa",
    "sg:classifiers":[
        {
            "category":"Social Services",
            "type":"Services"
        }
    ],
    "sg:phone":"+1 707 253 9401",
    "sg:postcode":"94559",
    "sg:province":"CA",
    "sg:tags":[
        "counselor",
        "marriage",
        "family"
    ],
    "wof:name":"Joni N Yacoe",
    "wof:placetype":"venue"
},
  "geometry": {"coordinates":[-122.288251,38.295809],"type":"Point"}
}