{
  "type": "Feature",
  "properties": {
    "addr:full":"112 W 6th St Oxnard CA 93030",
    "addr:housenumber":"112",
    "addr:postcode":"93030",
    "addr:street":"W 6Th St",
    "iso:country":"US",
    "sg:address":"112 W 6th St",
    "sg:city":"Oxnard",
    "sg:classifiers":[
        {
            "category":"Shopping",
            "subcategory":"Jewelry",
            "type":"Retail Goods"
        }
    ],
    "sg:phone":"+1 805 486 1099",
    "sg:postcode":"93030",
    "sg:province":"CA",
    "sg:tags":[
        "jeweler"
    ],
    "wof:name":"Angelica's Joyeria",
    "wof:placetype":"venue"
},
  "geometry": {"coordinates":[-119.177836,34.196278],"type":"Point"}
}