{
  "type": "Feature",
  "properties": {
    "addr:full":"11701 Stuart Dr Garden Grove CA 92843",
    "addr:housenumber":"11701",
    "addr:postcode":"92843",
    "addr:street":"Stuart Dr",
    "iso:country":"US",
    "sg:address":"11701 Stuart Dr",
    "sg:city":"Garden Grove",
    "sg:classifiers":[
        {
            "category":"Retail",
            "subcategory":"Laundry & Dry Cleaning",
            "type":"Services"
        }
    ],
    "sg:phone":"+1 714 636 7758",
    "sg:postcode":"92843",
    "sg:province":"CA",
    "sg:tags":[
        "valet"
    ],
    "wof:name":"Alliance Valet Parking",
    "wof:placetype":"venue"
},
  "geometry": {"coordinates":[-117.926261,33.773148],"type":"Point"}
}