{
  "type": "Feature",
  "properties": {
    "addr:full":"650 Castro St Mountain View CA 94041",
    "addr:housenumber":"650",
    "addr:postcode":"94041",
    "addr:street":"Castro St",
    "iso:country":"US",
    "sg:address":"650 Castro St",
    "sg:city":"Mountain View",
    "sg:classifiers":[
        {
            "category":"Wholesale",
            "subcategory":"Construction Materials",
            "type":"Manufacturing & Wholesale Goods"
        }
    ],
    "sg:phone":"+1 650 605 6400",
    "sg:postcode":"94041",
    "sg:province":"CA",
    "sg:tags":[
        "fence"
    ],
    "wof:name":"Invisible It",
    "wof:placetype":"venue"
},
  "geometry": {"coordinates":[-122.08305300000001,37.387363],"type":"Point"}
}