{
  "type": "Feature",
  "properties": {
    "addr:full":"990 W Fremont Ave Ste U-1 Sunnyvale CA 94087",
    "addr:housenumber":"990",
    "addr:postcode":"94087",
    "addr:street":"W Fremont Ave Ste U-1",
    "iso:country":"US",
    "sg:address":"990 W Fremont Ave Ste U-1",
    "sg:city":"Sunnyvale",
    "sg:classifiers":[
        {
            "category":"Health Services",
            "subcategory":"Dentist",
            "type":"Services"
        }
    ],
    "sg:phone":"+1 408 739 4224",
    "sg:postcode":"94087",
    "sg:province":"CA",
    "sg:tags":[
        "orthodontist"
    ],
    "sg:website":"www.kellerortho.com",
    "wof:name":"Rebecca B. Keller, DDS, MSD",
    "wof:placetype":"venue"
},
  "geometry": {"coordinates":[-122.05437499999999,37.351068],"type":"Point"}
}