{
  "type": "Feature",
  "properties": {
    "iso:country":"US",
    "sg:address":"3838 Jackson St",
    "sg:city":"Riverside",
    "sg:classifiers":[
        {
            "category":"Professional",
            "subcategory":"Business Services",
            "type":"Services"
        }
    ],
    "sg:phone":"+1 951 351 0788",
    "sg:postcode":"92503",
    "sg:province":"CA",
    "wof:name":"Business Link System",
    "wof:placetype":"venue"
},
  "geometry": {"coordinates":[-117.439408,33.924861],"type":"Point"}
}