{
  "type": "Feature",
  "properties": {
    "addr:full":"4755 Auburn Blvd Sacramento CA 95841",
    "addr:housenumber":"4755",
    "addr:postcode":"95841",
    "addr:street":"Auburn Blvd",
    "iso:country":"US",
    "sg:address":"4755 Auburn Blvd",
    "sg:city":"Sacramento",
    "sg:classifiers":[
        {
            "category":"Home & Garden",
            "subcategory":"Hardware",
            "type":"Retail Goods"
        }
    ],
    "sg:phone":"+1 916 334 4451",
    "sg:postcode":"95841",
    "sg:province":"CA",
    "sg:tags":[
        "tool",
        "used"
    ],
    "wof:name":"Tool Store",
    "wof:placetype":"venue"
},
  "geometry": {"coordinates":[-121.351387,38.65664],"type":"Point"}
}