{
  "type": "Feature",
  "properties": {
    "iso:country":"US",
    "sg:address":"3110 Sunrise Blvd",
    "sg:city":"Rancho Cordova",
    "sg:classifiers":[
        {
            "category":"Coffee & Tea",
            "type":"Food & Drink"
        }
    ],
    "sg:menulink":"http://www.allmenus.com/ca/mather/108147-starbucks-coffee/menu/",
    "sg:phone":"+1 916 859 0163",
    "sg:postcode":"95742",
    "sg:province":"CA",
    "sg:tags":[
        "american"
    ],
    "wof:name":"Starbucks Coffee",
    "wof:placetype":"venue"
},
  "geometry": {"coordinates":[-121.26553800000001,38.58947],"type":"Point"}
}