{
  "type": "Feature",
  "properties": {
    "addr:full":"6351 San Harco Cir Buena Park CA 90620",
    "addr:housenumber":"6351",
    "addr:postcode":"90620",
    "addr:street":"San Harco Cir",
    "iso:country":"US",
    "sg:address":"6351 San Harco Cir",
    "sg:city":"Buena Park",
    "sg:classifiers":[
        {
            "category":"Professional",
            "type":"Services"
        }
    ],
    "sg:phone":"+1 714 484 7620",
    "sg:postcode":"90620",
    "sg:province":"CA",
    "wof:name":"F Z Disposal",
    "wof:placetype":"venue"
},
  "geometry": {"coordinates":[-118.022206,33.834097],"type":"Point"}
}