{
  "type": "Feature",
  "properties": {
    "addr:full":"6345 Balboa Blvd Encino CA 91316",
    "addr:housenumber":"6345",
    "addr:postcode":"91316",
    "addr:street":"Balboa Blvd",
    "iso:country":"US",
    "sg:address":"6345 Balboa Blvd",
    "sg:city":"Encino",
    "sg:classifiers":[
        {
            "category":"Banks & Credit Unions",
            "subcategory":"Investment Brokerage",
            "type":"Services"
        }
    ],
    "sg:phone":"+1 818 264 7633",
    "sg:postcode":"91316",
    "sg:province":"CA",
    "wof:name":"Investment & Real Estate Svc",
    "wof:placetype":"venue"
},
  "geometry": {"coordinates":[-118.501181,34.181201],"type":"Point"}
}