{
  "type": "Feature",
  "properties": {
    "addr:full":"13949 Perris Blvd Moreno Valley CA 92553",
    "addr:housenumber":"13949",
    "addr:postcode":"92553",
    "addr:street":"Perris Blvd",
    "iso:country":"US",
    "sg:address":"13949 Perris Blvd",
    "sg:city":"Moreno Valley",
    "sg:classifiers":[
        {
            "category":"Restaurant",
            "type":"Food & Drink"
        }
    ],
    "sg:phone":"+1 951 247 1014",
    "sg:postcode":"92553",
    "sg:province":"CA",
    "wof:name":"KFC",
    "wof:placetype":"venue"
},
  "geometry": {"coordinates":[-117.226427,33.918656],"type":"Point"}
}