{
  "type": "Feature",
  "properties": {
    "iso:country":"US",
    "sg:address":"330 Townsend St #114",
    "sg:city":"San Francisco",
    "sg:classifiers":[
        {
            "category":"Banks & Credit Unions",
            "subcategory":"Financial Services",
            "type":"Services"
        }
    ],
    "sg:phone":"+1 415 512 7517",
    "sg:postcode":"94107",
    "sg:province":"CA",
    "sg:tags":[
        "broker",
        "mortgage"
    ],
    "sg:website":"www.bridgelinecg.com",
    "wof:name":"Bridgeline Capital Group, Inc",
    "wof:placetype":"venue"
},
  "geometry": {"coordinates":[-122.395703,37.776542],"type":"Point"}
}