{
  "type": "Feature",
  "properties": {
    "addr:full":"545 W 4th St San Dimas CA 91773",
    "addr:housenumber":"545",
    "addr:postcode":"91773",
    "addr:street":"W 4Th St",
    "iso:country":"US",
    "sg:address":"545 W 4th St",
    "sg:city":"San Dimas",
    "sg:classifiers":[
        {
            "category":"Building & Trades",
            "subcategory":"Plumbing",
            "type":"Services"
        }
    ],
    "sg:phone":"+1 909 592 4245",
    "sg:postcode":"91773",
    "sg:province":"CA",
    "sg:tags":[
        "conditioning",
        "air",
        "system",
        "contractor"
    ],
    "wof:name":"Paul's Air",
    "wof:placetype":"venue"
},
  "geometry": {"coordinates":[-117.81716400000001,34.110764],"type":"Point"}
}