{
  "type": "Feature",
  "properties": {
    "addr:full":"2050 Potomac Ave Bakersfield CA 93307",
    "addr:housenumber":"2050",
    "addr:postcode":"93307",
    "addr:street":"Potomac Ave",
    "iso:country":"US",
    "sg:address":"2050 Potomac Ave",
    "sg:city":"Bakersfield",
    "sg:classifiers":[
        {
            "category":"Food & Beverages",
            "subcategory":"Groceries & Convenience Stores",
            "type":"Retail Goods"
        }
    ],
    "sg:phone":"+1 661 322 8280",
    "sg:postcode":"93307",
    "sg:province":"CA",
    "sg:tags":[
        "grocer"
    ],
    "wof:name":"Potomac Market",
    "wof:placetype":"venue"
},
  "geometry": {"coordinates":[-118.973625,35.364937],"type":"Point"}
}