{
  "type": "Feature",
  "properties": {
    "addr:full":"3700 Campus Drive Suite 200 Newport Beach CA 92660",
    "addr:housenumber":"3700",
    "addr:postcode":"beach ca 92660",
    "addr:street":"Campus Drive Suite 200",
    "iso:country":"US",
    "sg:address":"3700 Campus Drive Suite 200",
    "sg:city":"Newport Beach",
    "sg:classifiers":[
        {
            "category":"Professional",
            "subcategory":"Lawyer & Legal Services",
            "type":"Services"
        },
        {
            "category":"Building & Trades",
            "subcategory":"Construction",
            "type":"Services"
        }
    ],
    "sg:phone":"+1 949 833 3240",
    "sg:postcode":"92660",
    "sg:province":"CA",
    "sg:tags":[
        "contractor"
    ],
    "wof:name":"Petrossi & Associates",
    "wof:placetype":"venue"
},
  "geometry": {"coordinates":[-117.874467,33.662764],"type":"Point"}
}