{
  "type": "Feature",
  "properties": {
    "iso:country":"US",
    "sg:address":"930 Pine St 202",
    "sg:city":"San Francisco",
    "sg:classifiers":[
        {
            "category":"Personal",
            "type":"Services"
        },
        {
            "category":"Professional",
            "subcategory":"Art Services",
            "type":"Services"
        }
    ],
    "sg:phone":"+1 415 218 9571",
    "sg:postcode":"94108",
    "sg:province":"CA",
    "sg:tags":[
        "graphic",
        "planning",
        "design",
        "wedding",
        "party",
        "event"
    ],
    "sg:website":"www.thegalagirls.com/",
    "wof:name":"The Gala Girls",
    "wof:placetype":"venue"
},
  "geometry": {"coordinates":[-122.41131300000001,37.791068],"type":"Point"}
}