{
  "type": "Feature",
  "properties": {
    "iso:country":"US",
    "sg:address":"472 Burlington Dr",
    "sg:city":"Vacaville",
    "sg:classifiers":[
        {
            "category":"Freight",
            "type":"Transportation"
        }
    ],
    "sg:phone":"+1 707 449 3792",
    "sg:postcode":"95687",
    "sg:province":"CA",
    "sg:tags":[
        "operator",
        "local",
        "storage",
        "trucking"
    ],
    "wof:name":"Abraham Torres Trucking",
    "wof:placetype":"venue"
},
  "geometry": {"coordinates":[-121.97752,38.342933],"type":"Point"}
}