{
  "type": "Feature",
  "properties": {
    "iso:country":"US",
    "sg:address":"9114 Adams Ave Ste 161",
    "sg:city":"Huntington Beach",
    "sg:classifiers":[
        {
            "category":"Social Services",
            "subcategory":"Job Training",
            "type":"Services"
        }
    ],
    "sg:phone":"+1 714 536 8004",
    "sg:postcode":"92646",
    "sg:province":"CA",
    "sg:tags":[
        "career",
        "counseling"
    ],
    "wof:name":"Kathy Marks Enterprise",
    "wof:placetype":"venue"
},
  "geometry": {"coordinates":[-117.969916,33.671271],"type":"Point"}
}