{
  "type": "Feature",
  "properties": {
    "iso:country":"US",
    "sg:address":"7115 C Street",
    "sg:city":"El Cerrito",
    "sg:classifiers":[
        {
            "category":"Park",
            "type":"Public Place"
        }
    ],
    "sg:phone":"+1 510 559 7000",
    "sg:postcode":"94530",
    "sg:province":"CA",
    "sg:website":"www.el-cerrito.org/recreation/",
    "wof:name":"Harding Park and Clubhouse",
    "wof:placetype":"venue"
},
  "geometry": {"coordinates":[-122.29433400000001,37.90115],"type":"Point"}
}