{
  "type": "Feature",
  "properties": {
    "addr:full":"1640 W F St Oakdale CA 95361",
    "addr:housenumber":"1640",
    "addr:postcode":"95361",
    "addr:street":"W F St",
    "iso:country":"US",
    "sg:address":"1640 W F St",
    "sg:city":"Oakdale",
    "sg:classifiers":[
        {
            "category":"Real Estate",
            "subcategory":"Real Estate Agent",
            "type":"Services"
        }
    ],
    "sg:phone":"+1 209 847 7555",
    "sg:postcode":"95361",
    "sg:province":"CA",
    "sg:website":"www.erastargate.com",
    "wof:name":"Era Stargate Realty",
    "wof:placetype":"venue"
},
  "geometry": {"coordinates":[-120.866243,37.758656],"type":"Point"}
}