{
  "type": "Feature",
  "properties": {
    "addr:full":"353 Sacramento Street Suite 1300 San Francisco CA 94111",
    "addr:housenumber":"353",
    "addr:postcode":"94111",
    "addr:street":"Sacramento Street Suite 1300",
    "iso:country":"US",
    "sg:address":"353 Sacramento Street Suite 1300",
    "sg:city":"San Francisco",
    "sg:classifiers":[
        {
            "category":"Professional",
            "subcategory":"Lawyer & Legal Services",
            "type":"Services"
        }
    ],
    "sg:phone":"+1 415 398 1800",
    "sg:postcode":"94111",
    "sg:province":"CA",
    "sg:website":"www.balglobal.com",
    "wof:name":"Berry Appleman & Leiden LLP",
    "wof:placetype":"venue"
},
  "geometry": {"coordinates":[-122.399002,37.794201],"type":"Point"}
}