{
  "type": "Feature",
  "properties": {
    "addr:full":"2154 Hill Rd Williams CA 95987",
    "addr:housenumber":"2154",
    "addr:postcode":"95987",
    "addr:street":"Hill Rd",
    "iso:country":"US",
    "sg:address":"2154 Hill Rd",
    "sg:city":"Williams",
    "sg:classifiers":[
        {
            "category":"Professional",
            "subcategory":"Employment Agencies",
            "type":"Services"
        }
    ],
    "sg:phone":"+1 530 458 5325",
    "sg:postcode":"95987",
    "sg:province":"CA",
    "sg:tags":[
        "opportunity"
    ],
    "wof:name":"Sandoval Labor Contractor",
    "wof:placetype":"venue"
},
  "geometry": {"coordinates":[-122.19840600000001,39.115811],"type":"Point"}
}