{
  "type": "Feature",
  "properties": {
    "addr:full":"14375 Monte Vista Ave Chino CA 91710",
    "addr:housenumber":"14375",
    "addr:postcode":"91710",
    "addr:street":"Monte Vista Ave",
    "iso:country":"US",
    "sg:address":"14375 Monte Vista Ave",
    "sg:city":"Chino",
    "sg:classifiers":[
        {
            "category":"Shopping",
            "subcategory":"Crafts & Fabrics",
            "type":"Retail Goods"
        }
    ],
    "sg:phone":"+1 909 591 6099",
    "sg:postcode":"91710",
    "sg:province":"CA",
    "sg:tags":[
        "supplies-wholesale",
        "florists'",
        "manufacturer"
    ],
    "sg:website":"http://www.farrandenterprises.com",
    "wof:name":"Rainbow Plastic Pots",
    "wof:placetype":"venue"
},
  "geometry": {"coordinates":[-117.69775199999999,33.992231],"type":"Point"}
}