{
  "type": "Feature",
  "properties": {
    "addr:full":"1501 W 10th St Antioch CA 94509",
    "addr:housenumber":"1501",
    "addr:postcode":"ca 94509",
    "addr:street":"W 10Th St",
    "iso:country":"US",
    "sg:address":"1501 W 10th St",
    "sg:city":"Antioch",
    "sg:classifiers":[
        {
            "category":"Autos & Motor Vehicles",
            "subcategory":"Automobile Sales",
            "type":"Retail Goods"
        }
    ],
    "sg:phone":"+1 925 706 8202",
    "sg:postcode":"94509",
    "sg:province":"CA",
    "sg:tags":[
        "car",
        "dealer"
    ],
    "wof:name":"Antioch Ford Used Cars",
    "wof:placetype":"venue"
},
  "geometry": {"coordinates":[-121.828998,38.012499],"type":"Point"}
}