{
  "type": "Feature",
  "properties": {
    "addr:full":"1065 Memorex Dr Santa Clara CA 95050",
    "addr:housenumber":"1065",
    "addr:postcode":"95050",
    "addr:street":"Memorex Dr",
    "iso:country":"US",
    "sg:address":"1065 Memorex Dr",
    "sg:city":"Santa Clara",
    "sg:classifiers":[
        {
            "category":"Manufacturing",
            "subcategory":"Tools & Machinery",
            "type":"Manufacturing & Wholesale Goods"
        }
    ],
    "sg:phone":"+1 408 727 7732",
    "sg:postcode":"95050",
    "sg:province":"CA",
    "sg:tags":[
        "machine",
        "shop"
    ],
    "wof:name":"W S Tooling Co",
    "wof:placetype":"venue"
},
  "geometry": {"coordinates":[-121.949517,37.36272],"type":"Point"}
}