{
  "type": "Feature",
  "properties": {
    "iso:country":"US",
    "sg:address":"22996 el Toro Rd",
    "sg:city":"Lake Forest",
    "sg:classifiers":[
        {
            "category":"Wholesale",
            "subcategory":"Electrical",
            "type":"Manufacturing & Wholesale Goods"
        }
    ],
    "sg:phone":"+1 949 583 9991",
    "sg:postcode":"92630",
    "sg:province":"CA",
    "sg:tags":[
        "communication",
        "radio",
        "system"
    ],
    "wof:name":"Spectra Link Corp",
    "wof:placetype":"venue"
},
  "geometry": {"coordinates":[-117.62810899999999,33.669998],"type":"Point"}
}