{
  "type": "Feature",
  "properties": {
    "iso:country":"US",
    "sg:address":"2840 Avenida De Portugal",
    "sg:city":"San Diego",
    "sg:classifiers":[
        {
            "category":"Education",
            "subcategory":"Special Training",
            "type":"Public Place"
        }
    ],
    "sg:phone":"+1 619 995 5349",
    "sg:postcode":"92106",
    "sg:province":"CA",
    "sg:tags":[
        "tutor",
        "private"
    ],
    "wof:name":"Virginia Paul",
    "wof:placetype":"venue"
},
  "geometry": {"coordinates":[-117.230158,32.721211],"type":"Point"}
}