{
  "type": "Feature",
  "properties": {
    "addr:full":"8900 Westminster Blvd Westminster CA 92683",
    "addr:housenumber":"8900",
    "addr:postcode":"92683",
    "addr:street":"Westminster Blvd",
    "iso:country":"US",
    "sg:address":"8900 Westminster Blvd",
    "sg:city":"Westminster",
    "sg:classifiers":[
        {
            "category":"Food & Beverages",
            "subcategory":"Groceries & Convenience Stores",
            "type":"Retail Goods"
        }
    ],
    "sg:phone":"+1 714 903 0908",
    "sg:postcode":"92683",
    "sg:province":"CA",
    "wof:name":"Vinh Phat Supermarket",
    "wof:placetype":"venue"
},
  "geometry": {"coordinates":[-117.97399900000001,33.7593],"type":"Point"}
}