{
  "type": "Feature",
  "properties": {
    "iso:country":"US",
    "sg:address":"1620 V St",
    "sg:city":"Merced",
    "sg:classifiers":[
        {
            "category":"Autos & Motor Vehicles",
            "subcategory":"Automobile Sales",
            "type":"Retail Goods"
        }
    ],
    "sg:phone":"+1 209 384 2000",
    "sg:postcode":"95340",
    "sg:province":"CA",
    "sg:tags":[
        "car",
        "dealer"
    ],
    "sg:website":"www.mercedvw.com",
    "wof:name":"Merced KIA",
    "wof:placetype":"venue"
},
  "geometry": {"coordinates":[-120.498806,37.306122],"type":"Point"}
}