{
  "type": "Feature",
  "properties": {
    "addr:full":"2540 Main Street Irvine CA 92614",
    "addr:housenumber":"2540",
    "addr:postcode":"92614",
    "addr:street":"Main Street",
    "iso:country":"US",
    "sg:address":"2540 Main Street",
    "sg:city":"Irvine",
    "sg:classifiers":[
        {
            "category":"Banks & Credit Unions",
            "subcategory":"Bank",
            "type":"Services"
        }
    ],
    "sg:phone":"+1 949 862 7430",
    "sg:postcode":"92614",
    "sg:province":"CA",
    "wof:name":"Wells Fargo Bank Na",
    "wof:placetype":"venue"
},
  "geometry": {"coordinates":[-117.84424,33.682713],"type":"Point"}
}