{
  "type": "Feature",
  "properties": {
    "addr:full":"8685 Wilshire Boulevard Beverly Hills CA 90211",
    "addr:housenumber":"8685",
    "addr:postcode":"90211",
    "addr:street":"Wilshire Boulevard",
    "iso:country":"US",
    "sg:address":"8685 Wilshire Boulevard",
    "sg:city":"Beverly Hills",
    "sg:classifiers":[
        {
            "category":"Building & Trades",
            "subcategory":"Locksmith",
            "type":"Services"
        }
    ],
    "sg:phone":"+1 310 499 0764",
    "sg:postcode":"90211",
    "sg:province":"CA",
    "sg:tags":[
        "key"
    ],
    "wof:name":"7 Day Fast Locks & Locksmith",
    "wof:placetype":"venue"
},
  "geometry": {"coordinates":[-118.381015,34.066441],"type":"Point"}
}