{
  "type": "Feature",
  "properties": {
    "iso:country":"US",
    "sg:address":"5555 Jackson Dr",
    "sg:city":"La Mesa",
    "sg:classifiers":[
        {
            "category":"Retail",
            "subcategory":"Auto Rental",
            "type":"Services"
        }
    ],
    "sg:phone":"+1 619 460 1911",
    "sg:postcode":"91942",
    "sg:province":"CA",
    "sg:tags":[
        "renting",
        "truck",
        "leasing"
    ],
    "wof:name":"U-Haul Co",
    "wof:placetype":"venue"
},
  "geometry": {"coordinates":[-117.01879700000001,32.780584],"type":"Point"}
}