{
  "type": "Feature",
  "properties": {
    "addr:full":"129 E Arrow Hwy San Dimas CA 91773",
    "addr:housenumber":"129",
    "addr:postcode":"91773",
    "addr:street":"E Arrow Hwy",
    "iso:country":"US",
    "sg:address":"129 E Arrow Hwy",
    "sg:city":"San Dimas",
    "sg:classifiers":[
        {
            "category":"Professional",
            "subcategory":"Advertising",
            "type":"Services"
        }
    ],
    "sg:phone":"+1 909 394 3155",
    "sg:postcode":"91773",
    "sg:province":"CA",
    "sg:tags":[
        "counselor"
    ],
    "sg:website":"www.strodeandlee.com",
    "wof:name":"Strode & Lee",
    "wof:placetype":"venue"
},
  "geometry": {"coordinates":[-117.803257,34.103033],"type":"Point"}
}