{
  "type": "Feature",
  "properties": {
    "iso:country":"US",
    "sg:address":"155 E Ave I",
    "sg:city":"Lancaster",
    "sg:classifiers":[
        {
            "category":"Government",
            "subcategory":"Office",
            "type":"Public Place"
        }
    ],
    "sg:phone":"+1 661 948 6060",
    "sg:postcode":"93535",
    "sg:province":"CA",
    "sg:tags":[
        "agricultural",
        "fair",
        "fairground"
    ],
    "wof:name":"50th Dstrict-Antelope Vly Fair",
    "wof:placetype":"venue"
},
  "geometry": {"coordinates":[-118.126172,34.704126],"type":"Point"}
}