{
  "type": "Feature",
  "properties": {
    "addr:full":"22340 Gilmore Ranch Rd Red Bluff CA 96080",
    "addr:housenumber":"22340",
    "addr:postcode":"96080",
    "addr:street":"Gilmore Ranch Rd",
    "iso:country":"US",
    "sg:address":"22340 Gilmore Ranch Rd",
    "sg:city":"Red Bluff",
    "sg:classifiers":[
        {
            "category":"Farming",
            "subcategory":"Crops",
            "type":"Manufacturing & Wholesale Goods"
        }
    ],
    "sg:phone":"+1 530 529 3188",
    "sg:postcode":"96080",
    "sg:province":"CA",
    "sg:tags":[
        "grove",
        "nut",
        "tree"
    ],
    "wof:name":"Gage Oscella",
    "wof:placetype":"venue"
},
  "geometry": {"coordinates":[-122.204701,40.17139],"type":"Point"}
}