{
  "type": "Feature",
  "properties": {
    "addr:full":"6601 Koll Center Pkwy Pleasanton CA 94566",
    "addr:housenumber":"6601",
    "addr:postcode":"94566",
    "addr:street":"Koll Center Pkwy",
    "iso:country":"US",
    "sg:address":"6601 Koll Center Pkwy",
    "sg:city":"Pleasanton",
    "sg:classifiers":[
        {
            "category":"Professional",
            "subcategory":"Lawyer & Legal Services",
            "type":"Services"
        }
    ],
    "sg:phone":"+1 925 249 0745",
    "sg:postcode":"94566",
    "sg:province":"CA",
    "sg:tags":[
        "attorney"
    ],
    "wof:name":"D James Chung Law Offices",
    "wof:placetype":"venue"
},
  "geometry": {"coordinates":[-121.897121,37.660047],"type":"Point"}
}