{
  "type": "Feature",
  "properties": {
    "iso:country":"US",
    "sg:address":"3608 Keystone Ave",
    "sg:city":"Los Angeles",
    "sg:classifiers":[
        {
            "category":"Health Services",
            "subcategory":"Dentist",
            "type":"Services"
        }
    ],
    "sg:phone":"+1 310 837 7613",
    "sg:postcode":"90034",
    "sg:province":"CA",
    "wof:name":"Nolan Robert N DDS",
    "wof:placetype":"venue"
},
  "geometry": {"coordinates":[-118.40922999999999,34.365867],"type":"Point"}
}