{
  "type": "Feature",
  "properties": {
    "iso:country":"US",
    "sg:address":"13668 Paseo Terrano",
    "sg:city":"Salinas",
    "sg:classifiers":[
        {
            "category":"Utilities",
            "subcategory":"Water",
            "type":"Services"
        }
    ],
    "sg:phone":"+1 831 484 9381",
    "sg:postcode":"93908",
    "sg:province":"CA",
    "sg:tags":[
        "company-utility",
        "system",
        "supply"
    ],
    "wof:name":"Rjr Mutual Water Company",
    "wof:placetype":"venue"
},
  "geometry": {"coordinates":[-121.733391,36.563091],"type":"Point"}
}