{
  "type": "Feature",
  "properties": {
    "addr:full":"42307 4th St E Lancaster CA 93535",
    "addr:housenumber":"42307",
    "addr:postcode":"93535",
    "addr:street":"4Th St E",
    "iso:country":"US",
    "sg:address":"42307 4th St E",
    "sg:city":"Lancaster",
    "sg:classifiers":[
        {
            "category":"Manufacturing",
            "subcategory":"Building Materials",
            "type":"Manufacturing & Wholesale Goods"
        }
    ],
    "sg:phone":"+1 661 940 8100",
    "sg:postcode":"93535",
    "sg:province":"CA",
    "wof:name":"Advanced Truss Systems",
    "wof:placetype":"venue"
},
  "geometry": {"coordinates":[-118.12335,34.651412],"type":"Point"}
}