{
  "type": "Feature",
  "properties": {
    "iso:country":"US",
    "sg:address":"250 Bryant Cmn",
    "sg:city":"Fremont",
    "sg:classifiers":[
        {
            "category":"Local Transit",
            "type":"Transportation"
        }
    ],
    "sg:phone":"+1 510 490 7410",
    "sg:postcode":"94539",
    "sg:province":"CA",
    "sg:tags":[
        "passenger"
    ],
    "wof:name":"Avalon Limousine Service",
    "wof:placetype":"venue"
},
  "geometry": {"coordinates":[-121.920848,37.533937],"type":"Point"}
}