{
  "type": "Feature",
  "properties": {
    "addr:full":"11222 La Cienega Blvd Ste 471 Inglewood CA 90304",
    "addr:housenumber":"11222",
    "addr:postcode":"90304",
    "addr:street":"La Cienega Blvd Ste 471",
    "iso:country":"US",
    "sg:address":"11222 La Cienega Blvd Ste 471",
    "sg:city":"Inglewood",
    "sg:classifiers":[
        {
            "category":"Freight",
            "type":"Transportation"
        }
    ],
    "sg:phone":"+1 310 342 7055",
    "sg:postcode":"90304",
    "sg:province":"CA",
    "sg:tags":[
        "shipping"
    ],
    "sg:website":"www.frtit.com",
    "wof:name":"Freight It, Inc",
    "wof:placetype":"venue"
},
  "geometry": {"coordinates":[-118.369614,33.931999],"type":"Point"}
}