{
  "type": "Feature",
  "properties": {
    "iso:country":"US",
    "sg:address":"2801 Prospect Park Dr",
    "sg:city":"Rancho Cordova",
    "sg:classifiers":[
        {
            "category":"Shopping",
            "subcategory":"Clothing, Apparel, & Fashions",
            "type":"Retail Goods"
        }
    ],
    "sg:phone":"+1 916 635 8218",
    "sg:postcode":"95670",
    "sg:province":"CA",
    "sg:tags":[
        "alteration"
    ],
    "wof:name":"Perfect Fit Alterations",
    "wof:placetype":"venue"
},
  "geometry": {"coordinates":[-121.278401,38.594704],"type":"Point"}
}