{
  "type": "Feature",
  "properties": {
    "addr:full":"2005 Cottontail Creek Road Cayucos CA 93430",
    "addr:housenumber":"2005",
    "addr:postcode":"93430",
    "addr:street":"Cottontail Creek Road",
    "iso:country":"US",
    "sg:address":"2005 Cottontail Creek Road",
    "sg:city":"Cayucos",
    "sg:classifiers":[
        {
            "category":"Travel",
            "subcategory":"Hotels & Motels",
            "type":"Entertainment"
        }
    ],
    "sg:phone":"+1 805 995 1787",
    "sg:postcode":"93430",
    "sg:province":"CA",
    "sg:tags":[
        "house",
        "guest"
    ],
    "sg:website":"www.cottontailcreek.com",
    "wof:name":"Cottontail Creek Ranch",
    "wof:placetype":"venue"
},
  "geometry": {"coordinates":[-120.880375,35.484476],"type":"Point"}
}