{
  "type": "Feature",
  "properties": {
    "iso:country":"US",
    "sg:address":"2900 E Jurupa St",
    "sg:city":"Ontario",
    "sg:classifiers":[
        {
            "category":"Freight",
            "type":"Transportation"
        }
    ],
    "sg:phone":"+1 909 390 3825",
    "sg:postcode":"91761",
    "sg:province":"CA",
    "sg:tags":[
        "operator",
        "trucking"
    ],
    "wof:name":"Interstate Dist Co",
    "wof:placetype":"venue"
},
  "geometry": {"coordinates":[-117.58566399999999,34.048386],"type":"Point"}
}