{
  "type": "Feature",
  "properties": {
    "addr:full":"131 London St San Francisco CA 94112",
    "addr:housenumber":"131",
    "addr:postcode":"94112",
    "addr:street":"London St",
    "iso:country":"US",
    "sg:address":"131 London St",
    "sg:city":"San Francisco",
    "sg:classifiers":[
        {
            "category":"Wholesale",
            "subcategory":"Vending Machines",
            "type":"Manufacturing & Wholesale Goods"
        }
    ],
    "sg:phone":"+1 415 333 0392",
    "sg:postcode":"94112",
    "sg:province":"CA",
    "sg:tags":[
        "operator"
    ],
    "wof:name":"Pierce Vending",
    "wof:placetype":"venue"
},
  "geometry": {"coordinates":[-122.432295,37.726663],"type":"Point"}
}