{
  "type": "Feature",
  "properties": {
    "addr:full":"14435 Hamlin St Van Nuys CA 91401",
    "addr:housenumber":"14435",
    "addr:postcode":"91401",
    "addr:street":"Hamlin St",
    "iso:country":"US",
    "sg:address":"14435 Hamlin St",
    "sg:city":"Van Nuys",
    "sg:classifiers":[
        {
            "category":"Health Services",
            "subcategory":"Clinic",
            "type":"Services"
        }
    ],
    "sg:phone":"+1 818 780 2240",
    "sg:postcode":"91401",
    "sg:province":"CA",
    "wof:name":"Premiere Health Providers",
    "wof:placetype":"venue"
},
  "geometry": {"coordinates":[-118.448089,34.188742],"type":"Point"}
}