{
  "type": "Feature",
  "properties": {
    "addr:full":"1258 N Union St Stockton CA 95205",
    "addr:housenumber":"1258",
    "addr:postcode":"95205",
    "addr:street":"N Union St",
    "iso:country":"US",
    "sg:address":"1258 N Union St",
    "sg:city":"Stockton",
    "sg:classifiers":[
        {
            "category":"Home & Garden",
            "subcategory":"Household Appliances",
            "type":"Retail Goods"
        }
    ],
    "sg:phone":"+1 209 521 4921",
    "sg:postcode":"95205",
    "sg:province":"CA",
    "sg:tags":[
        "equipment",
        "air",
        "filtration",
        "purification"
    ],
    "wof:name":"Breathe Easy",
    "wof:placetype":"venue"
},
  "geometry": {"coordinates":[-121.28051000000001,37.968755],"type":"Point"}
}