{
  "type": "Feature",
  "properties": {
    "addr:full":"520 S Palmetto Ave Ontario CA 91762",
    "addr:housenumber":"520",
    "addr:postcode":"91762",
    "addr:street":"S Palmetto Ave",
    "iso:country":"US",
    "sg:address":"520 S Palmetto Ave",
    "sg:city":"Ontario",
    "sg:classifiers":[
        {
            "category":"Building & Trades",
            "subcategory":"Construction",
            "type":"Services"
        }
    ],
    "sg:phone":"+1 909 983 6601",
    "sg:postcode":"91762",
    "sg:province":"CA",
    "sg:tags":[
        "contractor"
    ],
    "wof:name":"Barber & Assoc",
    "wof:placetype":"venue"
},
  "geometry": {"coordinates":[-117.667768,34.057192],"type":"Point"}
}