{
  "type": "Feature",
  "properties": {
    "iso:country":"US",
    "sg:address":"353 Broadway",
    "sg:city":"Chula Vista",
    "sg:classifiers":[
        {
            "category":"Shopping",
            "subcategory":"Mobile Phones",
            "type":"Retail Goods"
        }
    ],
    "sg:phone":"+1 619 409 9898",
    "sg:postcode":"91910",
    "sg:province":"CA",
    "wof:name":"Millennium Wireless",
    "wof:placetype":"venue"
},
  "geometry": {"coordinates":[-117.091666,32.636594],"type":"Point"}
}