{
  "type": "Feature",
  "properties": {
    "addr:full":"304 Hillcrest Ave Marina CA 93933",
    "addr:housenumber":"304",
    "addr:postcode":"93933",
    "addr:street":"Hillcrest Ave",
    "iso:country":"US",
    "sg:address":"304 Hillcrest Ave",
    "sg:city":"Marina",
    "sg:classifiers":[
        {
            "category":"Government",
            "subcategory":"Office",
            "type":"Public Place"
        }
    ],
    "sg:phone":"+1 831 884 9542",
    "sg:postcode":"93933",
    "sg:province":"CA",
    "sg:tags":[
        "village"
    ],
    "wof:name":"Marina City Teen Ctr",
    "wof:placetype":"venue"
},
  "geometry": {"coordinates":[-121.794639,36.677901],"type":"Point"}
}