{
  "type": "Feature",
  "properties": {
    "iso:country":"US",
    "sg:address":"10 N East St",
    "sg:city":"Woodland",
    "sg:classifiers":[
        {
            "category":"Shopping",
            "subcategory":"Bicycles & Sporting Goods",
            "type":"Retail Goods"
        }
    ],
    "sg:phone":"+1 530 666 4467",
    "sg:postcode":"95776",
    "sg:province":"CA",
    "wof:name":"Singletrack Society The",
    "wof:placetype":"venue"
},
  "geometry": {"coordinates":[-121.76522199999999,38.687129],"type":"Point"}
}