{
  "type": "Feature",
  "properties": {
    "addr:full":"73766 Hwy 111 Palm Desert CA 92260",
    "addr:housenumber":"73766",
    "addr:postcode":"ca 92260",
    "addr:street":"Hwy 111",
    "iso:country":"US",
    "sg:address":"73766 Hwy 111",
    "sg:city":"Palm Desert",
    "sg:classifiers":[
        {
            "category":"Building & Trades",
            "subcategory":"Cleaning & Sanitation",
            "type":"Services"
        }
    ],
    "sg:phone":"+1 760 837 1800",
    "sg:postcode":"92260",
    "sg:province":"CA",
    "sg:tags":[
        "janitor"
    ],
    "wof:name":"Professional Touch Janitorial",
    "wof:placetype":"venue"
},
  "geometry": {"coordinates":[-116.380805,33.721425],"type":"Point"}
}