{
  "type": "Feature",
  "properties": {
    "addr:full":"3710 Dorisa Ave Oakland CA 94605",
    "addr:housenumber":"3710",
    "addr:postcode":"94605",
    "addr:street":"Dorisa Ave",
    "iso:country":"US",
    "sg:address":"3710 Dorisa Ave",
    "sg:city":"Oakland",
    "sg:classifiers":[
        {
            "category":"Education",
            "subcategory":"School",
            "type":"Public Place"
        }
    ],
    "sg:phone":"+1 510 635 7922",
    "sg:postcode":"94605",
    "sg:province":"CA",
    "sg:tags":[
        "high",
        "middle",
        "elementary"
    ],
    "wof:name":"St Paschal Baylon School",
    "wof:placetype":"venue"
},
  "geometry": {"coordinates":[-122.147003,37.755901],"type":"Point"}
}