{
  "type": "Feature",
  "properties": {
    "addr:full":"4536 Auburn Boulevard Sacramento CA 95841",
    "addr:housenumber":"4536",
    "addr:postcode":"95841",
    "addr:street":"Auburn Boulevard",
    "iso:country":"US",
    "sg:address":"4536 Auburn Boulevard",
    "sg:city":"Sacramento",
    "sg:classifiers":[
        {
            "category":"Retail",
            "subcategory":"Auto Repair",
            "type":"Services"
        }
    ],
    "sg:phone":"+1 916 488 7827",
    "sg:postcode":"95841",
    "sg:province":"CA",
    "sg:tags":[
        "shop",
        "detailing",
        "body",
        "automobile",
        "customizing"
    ],
    "sg:website":"redstarautoworks.com/index.php?o...",
    "wof:name":"Red Star Auto Works",
    "wof:placetype":"venue"
},
  "geometry": {"coordinates":[-121.359038,38.649208],"type":"Point"}
}