{
  "type": "Feature",
  "properties": {
    "iso:country":"US",
    "sg:address":"1611 E Sycamore Ave",
    "sg:city":"El Segundo",
    "sg:classifiers":[
        {
            "category":"Social Services",
            "subcategory":"Child Care",
            "type":"Services"
        },
        {
            "category":"Education",
            "subcategory":"Preschool",
            "type":"Public Place"
        },
        {
            "category":"Education",
            "subcategory":"School",
            "type":"Public Place"
        }
    ],
    "sg:phone":"+1 310 615 0211",
    "sg:postcode":"90245",
    "sg:province":"CA",
    "sg:tags":[
        "elementary",
        "day"
    ],
    "wof:name":"St John's Lutheran Pre-School",
    "wof:placetype":"venue"
},
  "geometry": {"coordinates":[-118.399002,33.9282],"type":"Point"}
}