{
  "type": "Feature",
  "properties": {
    "iso:country":"US",
    "sg:address":"495 Embarcadero",
    "sg:city":"Morro Bay",
    "sg:classifiers":[
        {
            "category":"Building & Trades",
            "subcategory":"Construction",
            "type":"Services"
        }
    ],
    "sg:phone":"+1 805 772 7472",
    "sg:postcode":"93442",
    "sg:province":"CA",
    "sg:tags":[
        "designer",
        "marine",
        "contractor"
    ],
    "wof:name":"Associated Pacific Constructor",
    "wof:placetype":"venue"
},
  "geometry": {"coordinates":[-120.852074,35.361087],"type":"Point"}
}