{
  "type": "Feature",
  "properties": {
    "iso:country":"US",
    "sg:address":"1848 Saratoga Ave Bldg 3",
    "sg:city":"Saratoga",
    "sg:classifiers":[
        {
            "category":"Health Services",
            "subcategory":"Dentist",
            "type":"Services"
        }
    ],
    "sg:phone":"+1 408 364 2447",
    "sg:postcode":"95070",
    "sg:province":"CA",
    "sg:website":"mysaratogadental.com/",
    "wof:name":"V Miles Lew DDS",
    "wof:placetype":"venue"
},
  "geometry": {"coordinates":[-122.023015,37.263832],"type":"Point"}
}