{
  "type": "Feature",
  "properties": {
    "addr:full":"22648 Mission Blvd Hayward CA 94541",
    "addr:housenumber":"22648",
    "addr:postcode":"94541",
    "addr:street":"Mission Blvd",
    "iso:country":"US",
    "sg:address":"22648 Mission Blvd",
    "sg:city":"Hayward",
    "sg:classifiers":[
        {
            "category":"Bars & Pubs",
            "type":"Food & Drink"
        }
    ],
    "sg:phone":"+1 510 727 1487",
    "sg:postcode":"94541",
    "sg:province":"CA",
    "sg:tags":[
        "lounge",
        "nightlife",
        "cocktail"
    ],
    "wof:name":"Uncle Roy's",
    "wof:placetype":"venue"
},
  "geometry": {"coordinates":[-122.084,37.6717],"type":"Point"}
}