{
  "type": "Feature",
  "properties": {
    "iso:country":"US",
    "sg:address":"315 Roosevelt St",
    "sg:city":"Calexico",
    "sg:classifiers":[
        {
            "category":"Manufacturing",
            "subcategory":"Printing",
            "type":"Manufacturing & Wholesale Goods"
        }
    ],
    "sg:phone":"+1 760 768 1342",
    "sg:postcode":"92231",
    "sg:province":"CA",
    "sg:tags":[
        "newspaper"
    ],
    "wof:name":"El Lechugon",
    "wof:placetype":"venue"
},
  "geometry": {"coordinates":[-115.503463,32.678275],"type":"Point"}
}