{
  "type": "Feature",
  "properties": {
    "addr:full":"6837 Reseda Blvd Reseda CA 91335",
    "addr:housenumber":"6837",
    "addr:postcode":"91335",
    "addr:street":"Reseda Blvd",
    "iso:country":"US",
    "sg:address":"6837 Reseda Blvd",
    "sg:city":"Reseda",
    "sg:classifiers":[
        {
            "category":"Wholesale",
            "subcategory":"Furniture",
            "type":"Manufacturing & Wholesale Goods"
        }
    ],
    "sg:phone":"+1 818 881 1388",
    "sg:postcode":"91335",
    "sg:province":"CA",
    "wof:name":"Romani",
    "wof:placetype":"venue"
},
  "geometry": {"coordinates":[-118.53611100000001,34.195001],"type":"Point"}
}