{
  "type": "Feature",
  "properties": {
    "iso:country":"US",
    "sg:address":"2666 del Mar Heights Rd",
    "sg:city":"Del Mar",
    "sg:classifiers":[
        {
            "category":"Real Estate",
            "subcategory":"Real Estate Agent",
            "type":"Services"
        }
    ],
    "sg:phone":"+1 858 259 0222",
    "sg:postcode":"92014",
    "sg:province":"CA",
    "wof:name":"Century 21",
    "wof:placetype":"venue"
},
  "geometry": {"coordinates":[-117.247055,32.948829],"type":"Point"}
}