{
  "type": "Feature",
  "properties": {
    "iso:country":"US",
    "sg:address":"1000 Appollo Way",
    "sg:city":"Sacramento",
    "sg:classifiers":[
        {
            "category":"Social Services",
            "subcategory":"Child Care",
            "type":"Services"
        }
    ],
    "sg:phone":"+1 916 448 9740",
    "sg:postcode":"95822",
    "sg:province":"CA",
    "wof:name":"Infant Care By Dianna Carson",
    "wof:placetype":"venue"
},
  "geometry": {"coordinates":[-121.519194,38.529945],"type":"Point"}
}