{
  "type": "Feature",
  "properties": {
    "addr:full":"2841 N Arrowhead Ave San Bernardino CA 92405",
    "addr:housenumber":"2841",
    "addr:postcode":"92405",
    "addr:street":"N Arrowhead Ave",
    "iso:country":"US",
    "sg:address":"2841 N Arrowhead Ave",
    "sg:city":"San Bernardino",
    "sg:classifiers":[
        {
            "category":"Professional",
            "subcategory":"Computer Services",
            "type":"Services"
        }
    ],
    "sg:phone":"+1 909 708 7349",
    "sg:postcode":"92405",
    "sg:province":"CA",
    "sg:tags":[
        "website",
        "design"
    ],
    "wof:name":"CNC New Media",
    "wof:placetype":"venue"
},
  "geometry": {"coordinates":[-117.289556,34.143685],"type":"Point"}
}