{
  "type": "Feature",
  "properties": {
    "iso:country":"US",
    "sg:address":"4404 Ming Ave",
    "sg:city":"Bakersfield",
    "sg:classifiers":[
        {
            "category":"Professional",
            "subcategory":"Business Services",
            "type":"Services"
        }
    ],
    "sg:phone":"+1 661 837 0187",
    "sg:postcode":"93309",
    "sg:province":"CA",
    "sg:tags":[
        "sportswear",
        "embroidery"
    ],
    "wof:name":"Sportswear Mart",
    "wof:placetype":"venue"
},
  "geometry": {"coordinates":[-119.051239,35.339661],"type":"Point"}
}