{
  "type": "Feature",
  "properties": {
    "iso:country":"US",
    "sg:address":"10950 Washington Blvd",
    "sg:city":"Culver City",
    "sg:classifiers":[
        {
            "category":"Restaurant",
            "type":"Food & Drink"
        }
    ],
    "sg:phone":"+1 310 836 2523",
    "sg:postcode":"90232",
    "sg:province":"CA",
    "wof:name":"On Higher Grounds",
    "wof:placetype":"venue"
},
  "geometry": {"coordinates":[-118.409969,34.012482],"type":"Point"}
}