{
  "type": "Feature",
  "properties": {
    "addr:full":"2089 Tapscott Ave El Cerrito CA 94530",
    "addr:housenumber":"2089",
    "addr:postcode":"94530",
    "addr:street":"Tapscott Ave",
    "iso:country":"US",
    "sg:address":"2089 Tapscott Ave",
    "sg:city":"El Cerrito",
    "sg:classifiers":[
        {
            "category":"Education",
            "subcategory":"School",
            "type":"Public Place"
        }
    ],
    "sg:phone":"+1 510 235 3173",
    "sg:postcode":"94530",
    "sg:province":"CA",
    "wof:name":"Roeper Consultation Services",
    "wof:placetype":"venue"
},
  "geometry": {"coordinates":[-122.31413000000001,37.928394],"type":"Point"}
}