{
  "type": "Feature",
  "properties": {
    "addr:full":"1425 S Mariposa Ave Los Angeles CA 90006",
    "addr:housenumber":"1425",
    "addr:postcode":"90006",
    "addr:street":"S Mariposa Ave",
    "iso:country":"US",
    "sg:address":"1425 S Mariposa Ave",
    "sg:city":"Los Angeles",
    "sg:classifiers":[
        {
            "category":"Real Estate",
            "subcategory":"Real Estate Operator",
            "type":"Services"
        }
    ],
    "sg:phone":"+1 323 870 6868",
    "sg:postcode":"90006",
    "sg:province":"CA",
    "sg:tags":[
        "building",
        "apartment"
    ],
    "wof:name":"St Sophia Residence",
    "wof:placetype":"venue"
},
  "geometry": {"coordinates":[-118.29873000000001,34.046548],"type":"Point"}
}