{
  "type": "Feature",
  "properties": {
    "addr:full":"1345 Kansas St San Francisco CA 94107",
    "addr:housenumber":"1345",
    "addr:postcode":"94107",
    "addr:street":"Kansas St",
    "iso:country":"US",
    "sg:address":"1345 Kansas St",
    "sg:city":"San Francisco",
    "sg:classifiers":[
        {
            "category":"Organizations",
            "subcategory":"Religious Organization",
            "type":"Services"
        }
    ],
    "sg:phone":"+1 415 282 2006",
    "sg:postcode":"94107",
    "sg:province":"CA",
    "sg:tags":[
        "church"
    ],
    "wof:name":"House Of God In San Francisco",
    "wof:placetype":"venue"
},
  "geometry": {"coordinates":[-122.402283,37.752539],"type":"Point"}
}