{
  "type": "Feature",
  "properties": {
    "iso:country":"US",
    "sg:address":"1345 Kansas St",
    "sg:city":"San Francisco",
    "sg:classifiers":[
        {
            "category":"Organizations",
            "subcategory":"Religious Organization",
            "type":"Services"
        }
    ],
    "sg:phone":"+1 415 282 2006",
    "sg:postcode":"94107",
    "sg:province":"CA",
    "sg:tags":[
        "church"
    ],
    "wof:name":"House Of God In San Francisco",
    "wof:placetype":"venue"
},
  "geometry": {"coordinates":[-122.402283,37.752539],"type":"Point"}
}