{
  "type": "Feature",
  "properties": {
    "iso:country":"US",
    "sg:address":"1120 N Front St",
    "sg:city":"Earlimart",
    "sg:classifiers":[
        {
            "category":"Place Of Worship",
            "subcategory":"Church",
            "type":"Public Place"
        },
        {
            "category":"Place Of Worship",
            "type":"Public Place"
        }
    ],
    "sg:phone":"+1 661 849 5433",
    "sg:postcode":"93219",
    "sg:province":"CA",
    "sg:tags":[
        "churches-apostolic",
        "churches-pentecostal-apostolic"
    ],
    "wof:name":"Apostolic Community Life Center",
    "wof:placetype":"venue"
},
  "geometry": {"coordinates":[-119.27623800000001,35.893328],"type":"Point"}
}