{
  "type": "Feature",
  "properties": {
    "addr:full":"1060 E Washington St Colton CA 92324",
    "addr:housenumber":"1060",
    "addr:postcode":"92324",
    "addr:street":"E Washington St",
    "iso:country":"US",
    "sg:address":"1060 E Washington St",
    "sg:city":"Colton",
    "sg:classifiers":[
        {
            "category":"Education",
            "subcategory":"Vocational School",
            "type":"Public Place"
        }
    ],
    "sg:phone":"+1 909 422 0300",
    "sg:postcode":"92324",
    "sg:province":"CA",
    "sg:website":"www.turnkeyinstitute.com",
    "wof:name":"Turnkey Construction Mgmt Inst",
    "wof:placetype":"venue"
},
  "geometry": {"coordinates":[-117.309209,34.04821],"type":"Point"}
}