{
  "type": "Feature",
  "properties": {
    "addr:full":"14766 Dalmatian Dr Grass Valley CA 95945",
    "addr:postcode":"14766;95945",
    "addr:street":"Dalmatian Dr",
    "iso:country":"US",
    "sg:address":"14766 Dalmatian Dr",
    "sg:city":"Grass Valley",
    "sg:classifiers":[
        {
            "category":"Professional",
            "subcategory":"Management & Consulting",
            "type":"Services"
        }
    ],
    "sg:phone":"+1 530 477 0933",
    "sg:postcode":"95945",
    "sg:province":"CA",
    "sg:tags":[
        "marketing",
        "consultant"
    ],
    "wof:name":"Vico Marketing Svc",
    "wof:placetype":"venue"
},
  "geometry": {"coordinates":[-120.980397,39.18455],"type":"Point"}
}