{
  "type": "Feature",
  "properties": {
    "iso:country":"US",
    "sg:address":"378 Villa Point Dr",
    "sg:city":"Newport Beach",
    "sg:classifiers":[
        {
            "category":"Professional",
            "type":"Services"
        }
    ],
    "sg:phone":"+1 949 307 7366",
    "sg:postcode":"92660",
    "sg:province":"CA",
    "wof:name":"Nuways 2000",
    "wof:placetype":"venue"
},
  "geometry": {"coordinates":[-117.884456,33.612873],"type":"Point"}
}