{
  "type": "Feature",
  "properties": {
    "iso:country":"US",
    "sg:address":"1305 E Victoria St",
    "sg:city":"Carson",
    "sg:classifiers":[
        {
            "category":"Building & Trades",
            "subcategory":"Construction",
            "type":"Services"
        }
    ],
    "sg:phone":"+1 310 635 7830",
    "sg:postcode":"90746",
    "sg:province":"CA",
    "sg:tags":[
        "home",
        "builder"
    ],
    "wof:name":"K Hovnanian Co",
    "wof:placetype":"venue"
},
  "geometry": {"coordinates":[-118.24271899999999,33.86772],"type":"Point"}
}