{
  "type": "Feature",
  "properties": {
    "addr:full":"1033 E Scotts Ave Stockton CA 95205",
    "addr:housenumber":"1033",
    "addr:postcode":"95205",
    "addr:street":"E Scotts Ave",
    "iso:country":"US",
    "sg:address":"1033 E Scotts Ave",
    "sg:city":"Stockton",
    "sg:classifiers":[
        {
            "category":"Wholesale",
            "subcategory":"Auto Parts",
            "type":"Manufacturing & Wholesale Goods"
        }
    ],
    "sg:phone":"+1 209 931 2470",
    "sg:postcode":"95205",
    "sg:province":"CA",
    "sg:tags":[
        "body",
        "automobile",
        "shop"
    ],
    "wof:name":"Airgas NCN",
    "wof:placetype":"venue"
},
  "geometry": {"coordinates":[-121.276224,37.947714],"type":"Point"}
}