{
  "type": "Feature",
  "properties": {
    "iso:country":"US",
    "sg:address":"5020 Dantes View Dr",
    "sg:city":"Agoura Hills",
    "sg:classifiers":[
        {
            "category":"Building & Trades",
            "subcategory":"Construction",
            "type":"Services"
        }
    ],
    "sg:phone":"+1 818 597 1898",
    "sg:postcode":"91301",
    "sg:province":"CA",
    "sg:tags":[
        "contractor"
    ],
    "wof:name":"Carsten Cramer",
    "wof:placetype":"venue"
},
  "geometry": {"coordinates":[-118.715356,34.140826],"type":"Point"}
}