{
  "type": "Feature",
  "properties": {
    "iso:country":"US",
    "sg:address":"3080 Rodeo Ln",
    "sg:city":"Livermore",
    "sg:classifiers":[
        {
            "category":"Building & Trades",
            "subcategory":"Construction",
            "type":"Services"
        }
    ],
    "sg:phone":"+1 925 449 1612",
    "sg:postcode":"94550",
    "sg:province":"CA",
    "sg:tags":[
        "home",
        "builder"
    ],
    "wof:name":"Quality Builders",
    "wof:placetype":"venue"
},
  "geometry": {"coordinates":[-121.756406,37.672951],"type":"Point"}
}