{
  "type": "Feature",
  "properties": {
    "iso:country":"US",
    "sg:address":"995 Higuera St",
    "sg:city":"San Luis Obispo",
    "sg:classifiers":[
        {
            "category":"Banks & Credit Unions",
            "subcategory":"Bank",
            "type":"Services"
        }
    ],
    "sg:phone":"+1 805 541 6100",
    "sg:postcode":"93401",
    "sg:province":"CA",
    "sg:website":"www.firstbankslo.com",
    "wof:name":"First Bank Of San Luis Obispo",
    "wof:placetype":"venue"
},
  "geometry": {"coordinates":[-120.661036,35.280819],"type":"Point"}
}