{
  "type": "Feature",
  "properties": {
    "iso:country":"US",
    "sg:address":"2061 Grandview Dr",
    "sg:city":"Camarillo",
    "sg:classifiers":[
        {
            "category":"Professional",
            "subcategory":"Advertising",
            "type":"Services"
        }
    ],
    "sg:phone":"+1 805 484 6700",
    "sg:postcode":"93010",
    "sg:province":"CA",
    "sg:website":"www.seniorhosting.com",
    "wof:name":"SENIORHOSTING.COM",
    "wof:placetype":"venue"
},
  "geometry": {"coordinates":[-119.042558,34.214286],"type":"Point"}
}