{
  "type": "Feature",
  "properties": {
    "addr:full":"350 Raymor Ave Corona CA 92879",
    "addr:housenumber":"350",
    "addr:postcode":"92879",
    "addr:street":"Raymor Ave",
    "iso:country":"US",
    "sg:address":"350 Raymor Ave",
    "sg:city":"Corona",
    "sg:classifiers":[
        {
            "category":"Home & Garden",
            "subcategory":"Carpets & Floor Coverings",
            "type":"Retail Goods"
        }
    ],
    "sg:phone":"+1 714 527 2962",
    "sg:postcode":"92879",
    "sg:province":"CA",
    "sg:tags":[
        "dealer",
        "rug"
    ],
    "wof:name":"Star Brite Carpet & Upholstery",
    "wof:placetype":"venue"
},
  "geometry": {"coordinates":[-117.564637,33.856816],"type":"Point"}
}