{
  "type": "Feature",
  "properties": {
    "iso:country":"US",
    "sg:address":"1812 4th St",
    "sg:city":"Berkeley",
    "sg:classifiers":[
        {
            "category":"Shopping",
            "subcategory":"Hobbies, Toys, & Games",
            "type":"Retail Goods"
        }
    ],
    "sg:phone":"+1 510 849 1930",
    "sg:postcode":"94710",
    "sg:province":"CA",
    "sg:tags":[
        "toy",
        "store"
    ],
    "sg:website":"www.thearktoys.com",
    "wof:name":"The Ark Toy Store",
    "wof:placetype":"venue"
},
  "geometry": {"coordinates":[-122.30031700000001,37.868803],"type":"Point"}
}