{
  "type": "Feature",
  "properties": {
    "addr:full":"1 Sun Valley Mall Concord CA 94520",
    "addr:housenumber":"1",
    "addr:postcode":"94520",
    "addr:street":"Sun Valley Mall",
    "iso:country":"US",
    "sg:address":"1 Sun Valley Mall",
    "sg:city":"Concord",
    "sg:classifiers":[
        {
            "category":"Restaurant",
            "type":"Food & Drink"
        }
    ],
    "sg:menulink":"http://www.allmenus.com/ca/central-contra-costa/141557-manchu-wok/menu/",
    "sg:phone":"+1 925 689 7004",
    "sg:postcode":"94520",
    "sg:province":"CA",
    "sg:tags":[
        "asian",
        "chinese"
    ],
    "wof:name":"Manchu Wok",
    "wof:placetype":"venue"
},
  "geometry": {"coordinates":[-122.0626,37.967099],"type":"Point"}
}