{
  "type": "Feature",
  "properties": {
    "iso:country":"US",
    "sg:address":"2618 Sheridan Way",
    "sg:city":"Stockton",
    "sg:classifiers":[
        {
            "category":"Professional",
            "subcategory":"Business Services",
            "type":"Services"
        }
    ],
    "sg:phone":"+1 209 946 3046",
    "sg:postcode":"95207",
    "sg:province":"CA",
    "sg:tags":[
        "consultant",
        "coach"
    ],
    "sg:website":"http://www.navyleague-richmond.com",
    "wof:name":"Navy League Of The United States, Inc",
    "wof:placetype":"venue"
},
  "geometry": {"coordinates":[-121.34541299999999,38.004279],"type":"Point"}
}