{
  "type": "Feature",
  "properties": {
    "iso:country":"US",
    "sg:address":"4202 Alhambra Ave",
    "sg:city":"Martinez",
    "sg:classifiers":[
        {
            "category":"Landmark",
            "subcategory":"Historic",
            "type":"Public Place"
        }
    ],
    "sg:phone":"+1 925 228 8860",
    "sg:postcode":"94553",
    "sg:province":"CA",
    "sg:tags":[
        "historical"
    ],
    "wof:name":"United States Government",
    "wof:placetype":"venue"
},
  "geometry": {"coordinates":[-122.13062499999999,37.992051],"type":"Point"}
}