{
  "type": "Feature",
  "properties": {
    "addr:full":"24025 Newhall Ranch Rd Valencia CA 91355",
    "addr:housenumber":"24025",
    "addr:postcode":"91355",
    "addr:street":"Newhall Ranch Rd",
    "iso:country":"US",
    "sg:address":"24025 Newhall Ranch Rd",
    "sg:city":"Valencia",
    "sg:classifiers":[
        {
            "category":"Restaurant",
            "type":"Food & Drink"
        }
    ],
    "sg:phone":"+1 661 799 8888",
    "sg:postcode":"91355",
    "sg:province":"CA",
    "sg:tags":[
        "italian"
    ],
    "sg:website":"www.frankiesonmelrose.com/",
    "wof:name":"Frankies New York Italian Restaurant",
    "wof:placetype":"venue"
},
  "geometry": {"coordinates":[-118.558103,34.431654],"type":"Point"}
}