{
  "type": "Feature",
  "properties": {
    "addr:full":"7028 Bright Ave Whittier CA 90602",
    "addr:housenumber":"7028",
    "addr:postcode":"90602",
    "addr:street":"Bright Ave",
    "iso:country":"US",
    "sg:address":"7028 Bright Ave",
    "sg:city":"Whittier",
    "sg:classifiers":[
        {
            "category":"Real Estate",
            "subcategory":"Real Estate Agent",
            "type":"Services"
        }
    ],
    "sg:phone":"+1 562 945 9095",
    "sg:postcode":"90602",
    "sg:province":"CA",
    "sg:tags":[
        "management"
    ],
    "wof:name":"David Rego Development",
    "wof:placetype":"venue"
},
  "geometry": {"coordinates":[-118.036069,33.978396],"type":"Point"}
}