{
  "type": "Feature",
  "properties": {
    "iso:country":"US",
    "sg:address":"16163 Main St",
    "sg:city":"Hesperia",
    "sg:classifiers":[
        {
            "category":"Wholesale",
            "subcategory":"Non-durable Goods",
            "type":"Manufacturing & Wholesale Goods"
        },
        {
            "category":"Personal",
            "subcategory":"Barber",
            "type":"Services"
        }
    ],
    "sg:phone":"+1 760 244 4003",
    "sg:postcode":"92345",
    "sg:province":"CA",
    "sg:tags":[
        "beauty",
        "supply",
        "equipment",
        "salons-equipment",
        "supplies-wholesale",
        "manufacturer"
    ],
    "wof:name":"Thania's Beauty Supply",
    "wof:placetype":"venue"
},
  "geometry": {"coordinates":[-117.310091,34.422803],"type":"Point"}
}