{
  "type": "Feature",
  "properties": {
    "addr:full":"3875 Mission Ave Oceanside CA 92054",
    "addr:housenumber":"3875",
    "addr:postcode":"92054",
    "addr:street":"Mission Ave",
    "iso:country":"US",
    "sg:address":"3875 Mission Ave",
    "sg:city":"Oceanside",
    "sg:classifiers":[
        {
            "category":"Shopping",
            "subcategory":"Pets & Pet Supplies",
            "type":"Retail Goods"
        }
    ],
    "sg:phone":"+1 760 754 1211",
    "sg:postcode":"92054",
    "sg:province":"CA",
    "sg:tags":[
        "store"
    ],
    "wof:name":"Petco",
    "wof:placetype":"venue"
},
  "geometry": {"coordinates":[-117.327003,33.2276],"type":"Point"}
}