{
  "type": "Feature",
  "properties": {
    "iso:country":"US",
    "sg:address":"392 S Tumbleweed Rd",
    "sg:city":"Bishop",
    "sg:classifiers":[
        {
            "category":"Building & Trades",
            "subcategory":"Landscaping Services",
            "type":"Services"
        }
    ],
    "sg:phone":"+1 760 873 8720",
    "sg:postcode":"93514",
    "sg:province":"CA",
    "sg:tags":[
        "tree"
    ],
    "wof:name":"Owens Valley Tree Svc",
    "wof:placetype":"venue"
},
  "geometry": {"coordinates":[-118.437358,37.357106],"type":"Point"}
}