{
  "type": "Feature",
  "properties": {
    "addr:full":"2127 Grass Valley Hwy Auburn CA 95603",
    "addr:housenumber":"2127",
    "addr:postcode":"ca 95603",
    "addr:street":"Grass Valley Hwy",
    "iso:country":"US",
    "sg:address":"2127 Grass Valley Hwy",
    "sg:city":"Auburn",
    "sg:classifiers":[
        {
            "category":"Retail",
            "subcategory":"Auto Repair",
            "type":"Services"
        }
    ],
    "sg:phone":"+1 530 885 0775",
    "sg:postcode":"95603",
    "sg:province":"CA",
    "sg:tags":[
        "muffler",
        "exhaust",
        "system"
    ],
    "wof:name":"American Muffler",
    "wof:placetype":"venue"
},
  "geometry": {"coordinates":[-121.091122,38.932728],"type":"Point"}
}