{
  "type": "Feature",
  "properties": {
    "addr:full":"26850 Sun City Blvd Sun City CA 92586",
    "addr:housenumber":"26850",
    "addr:postcode":"92586",
    "addr:street":"Sun City Blvd",
    "iso:country":"US",
    "sg:address":"26850 Sun City Blvd",
    "sg:city":"Sun City",
    "sg:classifiers":[
        {
            "category":"Organizations",
            "subcategory":"Community Association",
            "type":"Services"
        }
    ],
    "sg:phone":"+1 951 672 6898",
    "sg:postcode":"92586",
    "sg:province":"CA",
    "sg:tags":[
        "club"
    ],
    "wof:name":"Sun City Lawn Bowls Club",
    "wof:placetype":"venue"
},
  "geometry": {"coordinates":[-117.192853,33.708801],"type":"Point"}
}