{
  "type": "Feature",
  "properties": {
    "iso:country":"US",
    "sg:address":"3920 Elderbank Dr",
    "sg:city":"Los Angeles",
    "sg:classifiers":[
        {
            "category":"Travel",
            "subcategory":"Hotels & Motels",
            "type":"Entertainment"
        }
    ],
    "sg:phone":"+1 323 225 2762",
    "sg:postcode":"90031",
    "sg:province":"CA",
    "sg:tags":[
        "breakfast",
        "accommodation",
        "bed"
    ],
    "wof:name":"Edlerbank House",
    "wof:placetype":"venue"
},
  "geometry": {"coordinates":[-118.198436,34.09309],"type":"Point"}
}