{
  "type": "Feature",
  "properties": {
    "iso:country":"US",
    "sg:address":"1212 N Broadway",
    "sg:city":"Santa Ana",
    "sg:classifiers":[
        {
            "category":"Health Services",
            "subcategory":"Chiropractor",
            "type":"Services"
        }
    ],
    "sg:phone":"+1 714 373 9966",
    "sg:postcode":"92701",
    "sg:province":"CA",
    "wof:name":"Cueva Chiropractic",
    "wof:placetype":"venue"
},
  "geometry": {"coordinates":[-117.86977400000001,33.7552],"type":"Point"}
}