{
  "type": "Feature",
  "properties": {
    "iso:country":"US",
    "sg:address":"5522 Garfield Ave",
    "sg:city":"Sacramento",
    "sg:phone":"+1 916 338 1885",
    "sg:postcode":"95841",
    "sg:province":"CA",
    "wof:name":"Elite Progressive School",
    "wof:placetype":"venue"
},
  "geometry": {"coordinates":[-121.33667,38.666971],"type":"Point"}
}