{
  "type": "Feature",
  "properties": {
    "iso:country":"US",
    "sg:address":"407 Fairway Dr",
    "sg:city":"Bakersfield",
    "sg:classifiers":[
        {
            "category":"Professional",
            "subcategory":"Business Services",
            "type":"Services"
        }
    ],
    "sg:phone":"+1 661 836 1100",
    "sg:postcode":"93309",
    "sg:province":"CA",
    "sg:tags":[
        "interior",
        "consultant",
        "design",
        "decorator"
    ],
    "wof:name":"Pauline Singleton Interiors",
    "wof:placetype":"venue"
},
  "geometry": {"coordinates":[-119.07615800000001,35.347788],"type":"Point"}
}