{
  "type": "Feature",
  "properties": {
    "iso:country":"US",
    "sg:address":"13339 Hoy Rd",
    "sg:city":"Red Bluff",
    "sg:classifiers":[
        {
            "category":"Farming",
            "subcategory":"Farm & Veterinary Services",
            "type":"Manufacturing & Wholesale Goods"
        }
    ],
    "sg:phone":"+1 530 527 3037",
    "sg:postcode":"96080",
    "sg:province":"CA",
    "sg:tags":[
        "process",
        "almond",
        "walnut"
    ],
    "wof:name":"Quality Nut Co",
    "wof:placetype":"venue"
},
  "geometry": {"coordinates":[-122.199991,40.173205],"type":"Point"}
}