{
  "type": "Feature",
  "properties": {
    "iso:country":"US",
    "sg:address":"777 Campus Commons Rd",
    "sg:city":"Sacramento",
    "sg:classifiers":[
        {
            "category":"Professional",
            "type":"Services"
        }
    ],
    "sg:phone":"+1 916 565 7416",
    "sg:postcode":"95825",
    "sg:province":"CA",
    "sg:tags":[
        "establishment"
    ],
    "wof:name":"WORKSMART-Easi",
    "wof:placetype":"venue"
},
  "geometry": {"coordinates":[-121.415553,38.569148],"type":"Point"}
}