{
  "type": "Feature",
  "properties": {
    "iso:country":"US",
    "sg:address":"1570 Pam Ln",
    "sg:city":"San Jose",
    "sg:classifiers":[
        {
            "category":"Building & Trades",
            "subcategory":"Construction",
            "type":"Services"
        }
    ],
    "sg:phone":"+1 408 997 3164",
    "sg:postcode":"95120",
    "sg:province":"CA",
    "sg:tags":[
        "roofing",
        "contractor"
    ],
    "wof:name":"Worrell Fred Roofing Co",
    "wof:placetype":"venue"
},
  "geometry": {"coordinates":[-121.899002,37.2309],"type":"Point"}
}