{
  "type": "Feature",
  "properties": {
    "addr:full":"2068 Hillhurst Ave Los Angeles CA 90027",
    "addr:housenumber":"2068",
    "addr:postcode":"90027",
    "addr:street":"Hillhurst Ave",
    "iso:country":"US",
    "sg:address":"2068 Hillhurst Ave",
    "sg:city":"Los Angeles",
    "sg:classifiers":[
        {
            "category":"Personal",
            "subcategory":"Nail Salon",
            "type":"Services"
        }
    ],
    "sg:phone":"+1 323 664 3029",
    "sg:postcode":"90027",
    "sg:province":"CA",
    "wof:name":"Leo's Hair Studio",
    "wof:placetype":"venue"
},
  "geometry": {"coordinates":[-118.287003,34.1096],"type":"Point"}
}