{
  "type": "Feature",
  "properties": {
    "iso:country":"US",
    "sg:address":"2549 Sierra Way",
    "sg:city":"La Verne",
    "sg:classifiers":[
        {
            "category":"Wholesale",
            "subcategory":"Durable Goods & Equipment",
            "type":"Manufacturing & Wholesale Goods"
        }
    ],
    "sg:phone":"+1 909 392 7373",
    "sg:postcode":"91750",
    "sg:province":"CA",
    "sg:tags":[
        "importer"
    ],
    "wof:name":"San Chien Intl",
    "wof:placetype":"venue"
},
  "geometry": {"coordinates":[-117.763935,34.095005],"type":"Point"}
}