{
  "type": "Feature",
  "properties": {
    "iso:country":"US",
    "sg:address":"212 S Main St",
    "sg:city":"Fort Bragg",
    "sg:classifiers":[
        {
            "category":"Retail",
            "subcategory":"Laundry & Dry Cleaning",
            "type":"Services"
        }
    ],
    "sg:phone":"+1 707 964 6407",
    "sg:postcode":"95437",
    "sg:province":"CA",
    "sg:tags":[
        "cleaners",
        "rug",
        "carpet"
    ],
    "wof:name":"Dwain Ray's Quality Carpet Svc",
    "wof:placetype":"venue"
},
  "geometry": {"coordinates":[-123.80580500000001,39.440294],"type":"Point"}
}