{
  "type": "Feature",
  "properties": {
    "iso:country":"US",
    "sg:address":"629 S Atlantic Blvd",
    "sg:city":"Los Angeles",
    "sg:classifiers":[
        {
            "category":"Wholesale",
            "subcategory":"Toys & Hobbies",
            "type":"Manufacturing & Wholesale Goods"
        }
    ],
    "sg:phone":"+1 323 980 5114",
    "sg:postcode":"90022",
    "sg:province":"CA",
    "sg:tags":[
        "wholesaler"
    ],
    "wof:name":"Planeta Auto Wholesale Inc",
    "wof:placetype":"venue"
},
  "geometry": {"coordinates":[-118.156578,34.02281],"type":"Point"}
}