{
  "type": "Feature",
  "properties": {
    "iso:country":"US",
    "sg:address":"76 Country Club Dr",
    "sg:city":"Willow Creek",
    "sg:classifiers":[
        {
            "category":"Real Estate",
            "subcategory":"Real Estate Agent",
            "type":"Services"
        }
    ],
    "sg:phone":"+1 530 629 3177",
    "sg:postcode":"95573",
    "sg:province":"CA",
    "wof:name":"Ming Tree-Willow Creek Rl Est",
    "wof:placetype":"venue"
},
  "geometry": {"coordinates":[-123.62926400000001,40.940448],"type":"Point"}
}