{
  "type": "Feature",
  "properties": {
    "addr:full":"8460 Reseda Blvd Northridge CA 91324",
    "addr:housenumber":"8460",
    "addr:postcode":"91324",
    "addr:street":"Reseda Blvd",
    "iso:country":"US",
    "sg:address":"8460 Reseda Blvd",
    "sg:city":"Northridge",
    "sg:classifiers":[
        {
            "category":"Restaurant",
            "type":"Food & Drink"
        }
    ],
    "sg:phone":"+1 818 709 1797",
    "sg:postcode":"91324",
    "sg:province":"CA",
    "sg:tags":[
        "house",
        "steak",
        "barbecue"
    ],
    "wof:name":"Chaw Chaw Barbeque",
    "wof:placetype":"venue"
},
  "geometry": {"coordinates":[-118.53608,34.22421],"type":"Point"}
}