{
  "type": "Feature",
  "properties": {
    "addr:full":"3510 Summit Dr Redding CA 96001",
    "addr:housenumber":"3510",
    "addr:postcode":"96001",
    "addr:street":"Summit Dr",
    "iso:country":"US",
    "sg:address":"3510 Summit Dr",
    "sg:city":"Redding",
    "sg:classifiers":[
        {
            "category":"Building & Trades",
            "subcategory":"Construction",
            "type":"Services"
        }
    ],
    "sg:phone":"+1 530 244 2855",
    "sg:postcode":"96001",
    "sg:province":"CA",
    "sg:tags":[
        "general",
        "contractor"
    ],
    "wof:name":"Salmon Creek Construction",
    "wof:placetype":"venue"
},
  "geometry": {"coordinates":[-122.39778099999999,40.562635],"type":"Point"}
}