{
  "type": "Feature",
  "properties": {
    "iso:country":"US",
    "sg:address":"10060 Orr Springs Rd",
    "sg:city":"Ukiah",
    "sg:classifiers":[
        {
            "category":"Travel",
            "subcategory":"Travel Agent",
            "type":"Entertainment"
        }
    ],
    "sg:phone":"+1 707 462 4654",
    "sg:postcode":"95482",
    "sg:province":"CA",
    "sg:tags":[
        "operator",
        "tour"
    ],
    "wof:name":"Ascent Tours",
    "wof:placetype":"venue"
},
  "geometry": {"coordinates":[-123.327979,39.219139],"type":"Point"}
}