{
  "type": "Feature",
  "properties": {
    "iso:country":"US",
    "sg:address":"1190 W Foothill Blvd",
    "sg:city":"Azusa",
    "sg:classifiers":[
        {
            "category":"Restaurant",
            "type":"Food & Drink"
        }
    ],
    "sg:phone":"+1 626 334 5340",
    "sg:postcode":"91702",
    "sg:province":"CA",
    "wof:name":"Carl's Jr",
    "wof:placetype":"venue"
},
  "geometry": {"coordinates":[-117.929354,34.133502],"type":"Point"}
}