{
  "type": "Feature",
  "properties": {
    "addr:full":"5260 Guessman Ave La Mesa CA 91942",
    "addr:housenumber":"5260",
    "addr:postcode":"91942",
    "addr:street":"Guessman Ave",
    "iso:country":"US",
    "sg:address":"5260 Guessman Ave",
    "sg:city":"La Mesa",
    "sg:classifiers":[
        {
            "category":"Utilities",
            "subcategory":"Electric",
            "type":"Services"
        }
    ],
    "sg:phone":"+1 619 985 7475",
    "sg:postcode":"91942",
    "sg:province":"CA",
    "wof:name":"Jesse Electric Company",
    "wof:placetype":"venue"
},
  "geometry": {"coordinates":[-117.040469,32.773523],"type":"Point"}
}