{
  "type": "Feature",
  "properties": {
    "addr:full":"1551 W Ramsey St Banning CA 92220",
    "addr:housenumber":"1551",
    "addr:postcode":"92220",
    "addr:street":"W Ramsey St",
    "iso:country":"US",
    "sg:address":"1551 W Ramsey St",
    "sg:city":"Banning",
    "sg:classifiers":[
        {
            "category":"Travel",
            "subcategory":"Hotels & Motels",
            "type":"Entertainment"
        }
    ],
    "sg:phone":"+1 951 849 9044",
    "sg:postcode":"92220",
    "sg:province":"CA",
    "wof:name":"Margarita Motel",
    "wof:placetype":"venue"
},
  "geometry": {"coordinates":[-116.893703,33.925496],"type":"Point"}
}