{
  "type": "Feature",
  "properties": {
    "iso:country":"US",
    "sg:address":"20712 Indian Ocean Dr",
    "sg:city":"Lake Forest",
    "sg:classifiers":[
        {
            "category":"Building & Trades",
            "subcategory":"Landscaping Services",
            "type":"Services"
        }
    ],
    "sg:phone":"+1 949 348 8218",
    "sg:postcode":"92630",
    "sg:province":"CA",
    "sg:tags":[
        "sod",
        "sodding"
    ],
    "sg:website":"www.esandbags.com",
    "wof:name":"SODSALES.COM",
    "wof:placetype":"venue"
},
  "geometry": {"coordinates":[-117.678546,33.661396],"type":"Point"}
}