{
  "type": "Feature",
  "properties": {
    "addr:full":"460 N Indian Hill Blvd Claremont CA 91711",
    "addr:housenumber":"460",
    "addr:postcode":"91711",
    "addr:street":"N Indian Hill Blvd",
    "iso:country":"US",
    "sg:address":"460 N Indian Hill Blvd",
    "sg:city":"Claremont",
    "sg:classifiers":[
        {
            "category":"Health Services",
            "subcategory":"Doctor",
            "type":"Services"
        }
    ],
    "sg:phone":"+1 909 626 5662",
    "sg:postcode":"91711",
    "sg:province":"CA",
    "sg:tags":[
        "dentist"
    ],
    "wof:name":"David G Seccombe DDS",
    "wof:placetype":"venue"
},
  "geometry": {"coordinates":[-117.719262,34.098108],"type":"Point"}
}