{
  "type": "Feature",
  "properties": {
    "addr:full":"2750 Whispering Hills Dr San Jose CA 95148",
    "addr:housenumber":"2750",
    "addr:postcode":"95148",
    "addr:street":"Whispering Hills Dr",
    "iso:country":"US",
    "sg:address":"2750 Whispering Hills Dr",
    "sg:city":"San Jose",
    "sg:classifiers":[
        {
            "category":"Building & Trades",
            "subcategory":"Electrical",
            "type":"Services"
        }
    ],
    "sg:phone":"+1 408 238 0662",
    "sg:postcode":"95148",
    "sg:province":"CA",
    "sg:tags":[
        "electrical",
        "contractor"
    ],
    "wof:name":"AA Electrical Servic",
    "wof:placetype":"venue"
},
  "geometry": {"coordinates":[-121.80680599999999,37.318655],"type":"Point"}
}