{
  "type": "Feature",
  "properties": {
    "iso:country":"US",
    "sg:address":"3511 El Camino Real",
    "sg:city":"Santa Clara",
    "sg:classifiers":[
        {
            "category":"Shopping",
            "subcategory":"Clothing, Apparel, & Fashions",
            "type":"Retail Goods"
        },
        {
            "category":"Shopping",
            "subcategory":"Tobacco",
            "type":"Retail Goods"
        }
    ],
    "sg:phone":"+1 408 241 0947",
    "sg:postcode":"95051",
    "sg:province":"CA",
    "sg:tags":[
        "shop",
        "accessory",
        "clothing",
        "women's"
    ],
    "wof:name":"Tobacco City",
    "wof:placetype":"venue"
},
  "geometry": {"coordinates":[-121.99299600000001,37.352299],"type":"Point"}
}