{
  "type": "Feature",
  "properties": {
    "iso:country":"US",
    "sg:address":"2450 Orange Ave",
    "sg:city":"Signal Hill",
    "sg:classifiers":[
        {
            "category":"Building & Trades",
            "subcategory":"Construction",
            "type":"Services"
        }
    ],
    "sg:phone":"+1 562 427 1604",
    "sg:postcode":"90755",
    "sg:province":"CA",
    "sg:tags":[
        "roofing",
        "contractor"
    ],
    "wof:name":"Bonded Roofing",
    "wof:placetype":"venue"
},
  "geometry": {"coordinates":[-118.17626,33.802162],"type":"Point"}
}