{
  "type": "Feature",
  "properties": {
    "addr:full":"547 Arden Ave Glendale CA 91203",
    "addr:housenumber":"547",
    "addr:postcode":"91203",
    "addr:street":"Arden Ave",
    "iso:country":"US",
    "sg:address":"547 Arden Ave",
    "sg:city":"Glendale",
    "sg:classifiers":[
        {
            "category":"Retail",
            "subcategory":"Repair Shop",
            "type":"Services"
        }
    ],
    "sg:phone":"+1 818 240 2666",
    "sg:postcode":"91203",
    "sg:province":"CA",
    "sg:tags":[
        "pipe",
        "leak",
        "locating"
    ],
    "sg:website":"www.goldak.com",
    "wof:name":"Goldak",
    "wof:placetype":"venue"
},
  "geometry": {"coordinates":[-118.265646,34.158317],"type":"Point"}
}