{
  "type": "Feature",
  "properties": {
    "addr:full":"317 E Santa Ana Blvd Santa Ana CA 92701",
    "addr:housenumber":"317",
    "addr:postcode":"92701",
    "addr:street":"E Santa Ana Blvd",
    "iso:country":"US",
    "sg:address":"317 E Santa Ana Blvd",
    "sg:city":"Santa Ana",
    "sg:classifiers":[
        {
            "category":"Education",
            "subcategory":"Special Training",
            "type":"Public Place"
        }
    ],
    "sg:phone":"+1 714 547 6064",
    "sg:postcode":"92701",
    "sg:province":"CA",
    "sg:tags":[
        "educational"
    ],
    "wof:name":"Spurgeon-Summit Par",
    "wof:placetype":"venue"
},
  "geometry": {"coordinates":[-117.864712,33.749804],"type":"Point"}
}