{
  "type": "Feature",
  "properties": {
    "iso:country":"US",
    "sg:address":"1415 5th Ave",
    "sg:city":"San Rafael",
    "sg:classifiers":[
        {
            "category":"Shopping",
            "subcategory":"Clothing, Apparel, & Fashions",
            "type":"Retail Goods"
        }
    ],
    "sg:phone":"+1 415 454 6422",
    "sg:postcode":"94901",
    "sg:province":"CA",
    "sg:tags":[
        "theatrical",
        "costume"
    ],
    "wof:name":"Belrose Costume Shop",
    "wof:placetype":"venue"
},
  "geometry": {"coordinates":[-122.532966,37.974546],"type":"Point"}
}