{
  "type": "Feature",
  "properties": {
    "addr:full":"9080 Artesia Blvd Bellflower CA 90707",
    "addr:housenumber":"9080",
    "addr:postcode":"90707",
    "addr:street":"Artesia Blvd",
    "iso:country":"US",
    "sg:address":"9080 Artesia Blvd",
    "sg:city":"Bellflower",
    "sg:classifiers":[
        {
            "category":"Bars & Pubs",
            "subcategory":"Lounge",
            "type":"Food & Drink"
        },
        {
            "category":"Bars & Pubs",
            "subcategory":"Sports Bar",
            "type":"Food & Drink"
        }
    ],
    "sg:phone":"+1 562 900 9370",
    "sg:postcode":"90707",
    "sg:province":"CA",
    "sg:tags":[
        "karaoke"
    ],
    "sg:website":"www.mybottomsup.com",
    "wof:name":"Bottoms Up Bar",
    "wof:placetype":"venue"
},
  "geometry": {"coordinates":[-118.139743,33.874618],"type":"Point"}
}