{
  "type": "Feature",
  "properties": {
    "addr:full":"6247 E North Ave Fresno CA 93725",
    "addr:housenumber":"6247",
    "addr:postcode":"93725",
    "addr:street":"E North Ave",
    "iso:country":"US",
    "sg:address":"6247 E North Ave",
    "sg:city":"Fresno",
    "sg:classifiers":[
        {
            "category":"Farming",
            "subcategory":"Vineyard",
            "type":"Manufacturing & Wholesale Goods"
        }
    ],
    "sg:phone":"+1 559 499 0675",
    "sg:postcode":"93725",
    "sg:province":"CA",
    "sg:tags":[
        "grape"
    ],
    "wof:name":"CD Sihota",
    "wof:placetype":"venue"
},
  "geometry": {"coordinates":[-119.67692700000001,36.692736],"type":"Point"}
}