{
  "type": "Feature",
  "properties": {
    "iso:country":"US",
    "sg:address":"32432 Alipaz St",
    "sg:city":"San Juan Cpstrno",
    "sg:classifiers":[
        {
            "category":"Building & Trades",
            "subcategory":"Construction",
            "type":"Services"
        }
    ],
    "sg:phone":"+1 949 443 0636",
    "sg:postcode":"92675",
    "sg:province":"CA",
    "sg:tags":[
        "painter"
    ],
    "wof:name":"A A Paint & Drywall Inc",
    "wof:placetype":"venue"
},
  "geometry": {"coordinates":[-117.67211,33.49078],"type":"Point"}
}