{
  "type": "Feature",
  "properties": {
    "addr:full":"1234 S Wright St Santa Ana CA 92705",
    "addr:housenumber":"1234",
    "addr:postcode":"92705",
    "addr:street":"S Wright St",
    "iso:country":"US",
    "sg:address":"1234 S Wright St",
    "sg:city":"Santa Ana",
    "sg:classifiers":[
        {
            "category":"Wholesale",
            "subcategory":"Auto Parts",
            "type":"Manufacturing & Wholesale Goods"
        }
    ],
    "sg:phone":"+1 714 835 2722",
    "sg:postcode":"92705",
    "sg:province":"CA",
    "sg:tags":[
        "equipment",
        "repair",
        "automotive"
    ],
    "wof:name":"G J L Automotive Equipment Co",
    "wof:placetype":"venue"
},
  "geometry": {"coordinates":[-117.84717499999999,33.732461],"type":"Point"}
}