{
  "type": "Feature",
  "properties": {
    "addr:full":"526 B St Davis CA 95616",
    "addr:housenumber":"526",
    "addr:postcode":"95616",
    "addr:street":"B St",
    "iso:country":"US",
    "sg:address":"526 B St",
    "sg:city":"Davis",
    "sg:classifiers":[
        {
            "category":"Education",
            "subcategory":"School",
            "type":"Public Place"
        }
    ],
    "sg:phone":"+1 530 757 5300",
    "sg:postcode":"95616",
    "sg:province":"CA",
    "wof:name":"Davis Joint Unified School District",
    "wof:placetype":"venue"
},
  "geometry": {"coordinates":[-121.745621,38.547139],"type":"Point"}
}