{
  "type": "Feature",
  "properties": {
    "addr:full":"3651 J St Sacramento CA 95816",
    "addr:housenumber":"3651",
    "addr:postcode":"95816",
    "addr:street":"J St",
    "iso:country":"US",
    "sg:address":"3651 J St",
    "sg:city":"Sacramento",
    "sg:classifiers":[
        {
            "category":"Bars & Pubs",
            "type":"Food & Drink"
        }
    ],
    "sg:phone":"+1 916 455 7155",
    "sg:postcode":"95816",
    "sg:province":"CA",
    "wof:name":"Bonn Lair",
    "wof:placetype":"venue"
},
  "geometry": {"coordinates":[-121.457441,38.570714],"type":"Point"}
}