{
  "type": "Feature",
  "properties": {
    "iso:country":"US",
    "sg:address":"2021 Fulton Ave",
    "sg:city":"Sacramento",
    "sg:classifiers":[
        {
            "category":"Retail",
            "subcategory":"Auto Repair",
            "type":"Services"
        }
    ],
    "sg:phone":"+1 916 973 8300",
    "sg:postcode":"95825",
    "sg:province":"CA",
    "wof:name":"Clutch House",
    "wof:placetype":"venue"
},
  "geometry": {"coordinates":[-121.402,38.602001],"type":"Point"}
}