{
  "type": "Feature",
  "properties": {
    "addr:full":"471 Emerson St Palo Alto CA 94301",
    "addr:housenumber":"471",
    "addr:postcode":"94301",
    "addr:street":"Emerson St",
    "iso:country":"US",
    "sg:address":"471 Emerson St",
    "sg:city":"Palo Alto",
    "sg:classifiers":[
        {
            "category":"Banks & Credit Unions",
            "subcategory":"Financial Services",
            "type":"Services"
        }
    ],
    "sg:phone":"+1 650 854 6685",
    "sg:postcode":"94301",
    "sg:province":"CA",
    "sg:tags":[
        "investment",
        "closed"
    ],
    "wof:name":"Shoreline Venture Management",
    "wof:placetype":"venue"
},
  "geometry": {"coordinates":[-122.163094,37.444968],"type":"Point"}
}