{
  "type": "Feature",
  "properties": {
    "addr:full":"6351 Scarlett Ct Dublin CA 94568",
    "addr:housenumber":"6351",
    "addr:postcode":"94568",
    "addr:street":"Scarlett Ct",
    "iso:country":"US",
    "sg:address":"6351 Scarlett Ct",
    "sg:city":"Dublin",
    "sg:classifiers":[
        {
            "category":"Building & Trades",
            "subcategory":"Electrical",
            "type":"Services"
        }
    ],
    "sg:phone":"+1 925 556 9440",
    "sg:postcode":"94568",
    "sg:province":"CA",
    "sg:tags":[
        "electric",
        "contractor"
    ],
    "wof:name":"Northern States Electric",
    "wof:placetype":"venue"
},
  "geometry": {"coordinates":[-121.909035,37.70514],"type":"Point"}
}