{
  "type": "Feature",
  "properties": {
    "iso:country":"US",
    "sg:address":"4601 W Walnut St Ste 5",
    "sg:city":"Soquel",
    "sg:classifiers":[
        {
            "category":"Real Estate",
            "subcategory":"Real Estate Services",
            "type":"Services"
        },
        {
            "category":"Banks & Credit Unions",
            "subcategory":"Financial Services",
            "type":"Services"
        }
    ],
    "sg:phone":"+1 831 465 1074",
    "sg:postcode":"95073",
    "sg:province":"CA",
    "sg:tags":[
        "loan"
    ],
    "sg:website":"http://www.mbrllc.com",
    "wof:name":"Coastal Processing",
    "wof:placetype":"venue"
},
  "geometry": {"coordinates":[-121.95829000000001,36.985859],"type":"Point"}
}