{
  "type": "Feature",
  "properties": {
    "addr:full":"1620 S Lewis St Anaheim CA 92805",
    "addr:housenumber":"1620",
    "addr:postcode":"92805",
    "addr:street":"S Lewis St",
    "iso:country":"US",
    "sg:address":"1620 S Lewis St",
    "sg:city":"Anaheim",
    "sg:classifiers":[
        {
            "category":"Home & Garden",
            "subcategory":"Building Materials",
            "type":"Retail Goods"
        }
    ],
    "sg:phone":"+1 714 978 6403",
    "sg:postcode":"92805",
    "sg:province":"CA",
    "sg:tags":[
        "supply"
    ],
    "sg:website":"www.arizonatile.com",
    "wof:name":"Arizona Tile",
    "wof:placetype":"venue"
},
  "geometry": {"coordinates":[-117.89572099999999,33.807666],"type":"Point"}
}