{
  "type": "Feature",
  "properties": {
    "addr:full":"44739 Date Ave Lancaster CA 93534",
    "addr:housenumber":"44739",
    "addr:postcode":"93534",
    "addr:street":"Date Ave",
    "iso:country":"US",
    "sg:address":"44739 Date Ave",
    "sg:city":"Lancaster",
    "sg:classifiers":[
        {
            "category":"Organizations",
            "subcategory":"Non-profit Organization",
            "type":"Services"
        }
    ],
    "sg:phone":"+1 661 942 2229",
    "sg:postcode":"93534",
    "sg:province":"CA",
    "sg:tags":[
        "social"
    ],
    "wof:name":"Abortion Alternatives",
    "wof:placetype":"venue"
},
  "geometry": {"coordinates":[-118.14035,34.695046],"type":"Point"}
}