{
  "type": "Feature",
  "properties": {
    "addr:full":"2310 Glendale Galleria Glendale CA 91210",
    "addr:housenumber":"2310",
    "addr:postcode":"91210",
    "addr:street":"Glendale Galleria",
    "iso:country":"US",
    "sg:address":"2310 Glendale Galleria",
    "sg:city":"Glendale",
    "sg:classifiers":[
        {
            "category":"Arts & Performance",
            "subcategory":"Art Gallery",
            "type":"Entertainment"
        },
        {
            "category":"Shopping",
            "subcategory":"Bicycles & Sporting Goods",
            "type":"Retail Goods"
        },
        {
            "category":"Arena",
            "subcategory":"Stadium",
            "type":"Entertainment"
        }
    ],
    "sg:phone":"+1 818 507 0664",
    "sg:postcode":"91210",
    "sg:province":"CA",
    "sg:website":"www.oldprogallery.com",
    "wof:name":"Old Pro Gallery",
    "wof:placetype":"venue"
},
  "geometry": {"coordinates":[-118.25973,34.144441],"type":"Point"}
}