{
  "type": "Feature",
  "properties": {
    "iso:country":"US",
    "sg:address":"805 B St",
    "sg:city":"Hayward",
    "sg:classifiers":[
        {
            "category":"Banks & Credit Unions",
            "subcategory":"Bank",
            "type":"Services"
        }
    ],
    "sg:phone":"+1 510 727 1600",
    "sg:postcode":"94541",
    "sg:province":"CA",
    "wof:name":"Business Bank of California",
    "wof:placetype":"venue"
},
  "geometry": {"coordinates":[-122.084999,37.6716],"type":"Point"}
}