{
  "type": "Feature",
  "properties": {
    "addr:full":"8923 Palmerson Dr Antelope CA 95843",
    "addr:housenumber":"8923",
    "addr:postcode":"95843",
    "addr:street":"Palmerson Dr",
    "iso:country":"US",
    "sg:address":"8923 Palmerson Dr",
    "sg:city":"Antelope",
    "sg:classifiers":[
        {
            "category":"Retail",
            "subcategory":"Laundry & Dry Cleaning",
            "type":"Services"
        }
    ],
    "sg:phone":"+1 916 725 0896",
    "sg:postcode":"95843",
    "sg:province":"CA",
    "sg:tags":[
        "cleaners",
        "rug",
        "carpet"
    ],
    "wof:name":"Kal Kleen Carpet & Upholstery",
    "wof:placetype":"venue"
},
  "geometry": {"coordinates":[-121.343906,38.723534],"type":"Point"}
}