{
  "type": "Feature",
  "properties": {
    "addr:full":"3424 College Ave Lemon Grove CA 91946",
    "addr:housenumber":"3424",
    "addr:postcode":"91946",
    "addr:street":"College Ave",
    "iso:country":"US",
    "sg:address":"3424 College Ave",
    "sg:city":"Lemon Grove",
    "sg:classifiers":[
        {
            "category":"Shopping",
            "subcategory":"Department Store",
            "type":"Retail Goods"
        }
    ],
    "sg:phone":"+1 619 471 0025",
    "sg:postcode":"91946",
    "sg:province":"CA",
    "sg:website":"www.target.com",
    "wof:name":"Target",
    "wof:placetype":"venue"
},
  "geometry": {"coordinates":[-117.049812,32.740807],"type":"Point"}
}