{
  "type": "Feature",
  "properties": {
    "addr:full":"2141 E Philadelphia St Ontario CA 91761",
    "addr:housenumber":"2141 e",
    "addr:postcode":"91761",
    "addr:street":"Philadelphia St",
    "iso:country":"US",
    "sg:address":"2141 E Philadelphia St",
    "sg:city":"Ontario",
    "sg:classifiers":[
        {
            "category":"Home & Garden",
            "subcategory":"Home Furnishings",
            "type":"Retail Goods"
        }
    ],
    "sg:phone":"+1 909 923 6240",
    "sg:postcode":"91761",
    "sg:province":"CA",
    "sg:tags":[
        "bathroom",
        "fixture",
        "accessory"
    ],
    "sg:website":"www.masterbuilding.com",
    "wof:name":"Master Building Specialties",
    "wof:placetype":"venue"
},
  "geometry": {"coordinates":[-117.610539,34.034168],"type":"Point"}
}