{
  "type": "Feature",
  "properties": {
    "addr:full":"6271 W Bullard Ave Fresno CA 93722",
    "addr:housenumber":"6271",
    "addr:postcode":"93722",
    "addr:street":"W Bullard Ave",
    "iso:country":"US",
    "sg:address":"6271 W Bullard Ave",
    "sg:city":"Fresno",
    "sg:classifiers":[
        {
            "category":"Building & Trades",
            "subcategory":"Construction",
            "type":"Services"
        }
    ],
    "sg:phone":"+1 559 276 0398",
    "sg:postcode":"93722",
    "sg:province":"CA",
    "sg:tags":[
        "industrial"
    ],
    "wof:name":"Roll Off Systems",
    "wof:placetype":"venue"
},
  "geometry": {"coordinates":[-119.912744,36.822362],"type":"Point"}
}