{
  "type": "Feature",
  "properties": {
    "addr:full":"3351 Business Dr Sacramento CA 95820",
    "addr:housenumber":"3351",
    "addr:postcode":"95820",
    "addr:street":"Business Dr",
    "iso:country":"US",
    "sg:address":"3351 Business Dr",
    "sg:city":"Sacramento",
    "sg:classifiers":[
        {
            "category":"Manufacturing",
            "subcategory":"Printing",
            "type":"Manufacturing & Wholesale Goods"
        }
    ],
    "sg:phone":"+1 916 457 7166",
    "sg:postcode":"95820",
    "sg:province":"CA",
    "sg:tags":[
        "lithographic",
        "screen",
        "commercial"
    ],
    "wof:name":"Sam's T-Shirt Printing",
    "wof:placetype":"venue"
},
  "geometry": {"coordinates":[-121.41882699999999,38.542406],"type":"Point"}
}