{
  "type": "Feature",
  "properties": {
    "addr:full":"1529 W Florence Avenue Los Angeles CA 90047",
    "addr:housenumber":"1529",
    "addr:postcode":"90047",
    "addr:street":"W Florence Avenue",
    "iso:country":"US",
    "sg:address":"1529 W Florence Avenue",
    "sg:city":"Los Angeles",
    "sg:classifiers":[
        {
            "category":"Restaurant",
            "type":"Food & Drink"
        }
    ],
    "sg:phone":"+1 323 753 3538",
    "sg:postcode":"90047",
    "sg:province":"CA",
    "wof:name":"Las Hadas Seafood",
    "wof:placetype":"venue"
},
  "geometry": {"coordinates":[-118.30338500000001,33.974462],"type":"Point"}
}