{
  "type": "Feature",
  "properties": {
    "addr:full":"6670 Amador Plaza Rd Dublin CA 94568",
    "addr:housenumber":"6670",
    "addr:postcode":"94568",
    "addr:street":"Amador Plaza Rd",
    "iso:country":"US",
    "sg:address":"6670 Amador Plaza Rd",
    "sg:city":"Dublin",
    "sg:classifiers":[
        {
            "category":"Professional",
            "subcategory":"Engineering",
            "type":"Services"
        }
    ],
    "sg:phone":"+1 925 829 0772",
    "sg:postcode":"94568",
    "sg:province":"CA",
    "sg:tags":[
        "engineer"
    ],
    "sg:website":"www.beldeninc.com",
    "wof:name":"Belden Consulting Engineers",
    "wof:placetype":"venue"
},
  "geometry": {"coordinates":[-121.926152,37.703399],"type":"Point"}
}