{
  "type": "Feature",
  "properties": {
    "addr:full":"7563 Tujunga Ave North Hollywood CA 91605",
    "addr:housenumber":"7563",
    "addr:postcode":"91605",
    "addr:street":"Tujunga Ave",
    "iso:country":"US",
    "sg:address":"7563 Tujunga Ave",
    "sg:city":"North Hollywood",
    "sg:classifiers":[
        {
            "category":"Building & Trades",
            "subcategory":"Electrical",
            "type":"Services"
        }
    ],
    "sg:phone":"+1 818 765 9060",
    "sg:postcode":"91605",
    "sg:province":"CA",
    "sg:tags":[
        "booth",
        "equipment",
        "telephone",
        "pay"
    ],
    "wof:name":"California Payphone Network",
    "wof:placetype":"venue"
},
  "geometry": {"coordinates":[-118.379127,34.207973],"type":"Point"}
}