{
  "type": "Feature",
  "properties": {
    "iso:country":"US",
    "sg:address":"834 1/2 E Avenue R Q 6",
    "sg:city":"Palmdale",
    "sg:classifiers":[
        {
            "category":"Personal",
            "subcategory":"Beauty Salon",
            "type":"Services"
        }
    ],
    "sg:phone":"+1 661 224 1790",
    "sg:postcode":"93550",
    "sg:province":"CA",
    "wof:name":"Shinny Nails",
    "wof:placetype":"venue"
},
  "geometry": {"coordinates":[-118.11476500000001,34.57259],"type":"Point"}
}