{
  "type": "Feature",
  "properties": {
    "iso:country":"US",
    "sg:address":"4004 Orange Ave",
    "sg:city":"Long Beach",
    "sg:classifiers":[
        {
            "category":"Insurance",
            "subcategory":"Insurance Agent",
            "type":"Services"
        }
    ],
    "sg:phone":"+1 562 427 2014",
    "sg:postcode":"90807",
    "sg:province":"CA",
    "wof:name":"Bob Simmons Agency",
    "wof:placetype":"venue"
},
  "geometry": {"coordinates":[-118.176224,33.83239],"type":"Point"}
}