{
  "type": "Feature",
  "properties": {
    "addr:full":"3305 Matterhorn Way Ceres CA 95307",
    "addr:housenumber":"3305",
    "addr:postcode":"95307",
    "addr:street":"Matterhorn Way",
    "iso:country":"US",
    "sg:address":"3305 Matterhorn Way",
    "sg:city":"Ceres",
    "sg:classifiers":[
        {
            "category":"Travel",
            "subcategory":"Travel Agent",
            "type":"Entertainment"
        }
    ],
    "sg:phone":"+1 209 544 6131",
    "sg:postcode":"95307",
    "sg:province":"CA",
    "sg:tags":[
        "agency"
    ],
    "wof:name":"Champalao Travel",
    "wof:placetype":"venue"
},
  "geometry": {"coordinates":[-120.93323100000001,37.608685],"type":"Point"}
}