{
  "type": "Feature",
  "properties": {
    "addr:full":"9401 Oak Glen Rd Cherry Valley CA 92223",
    "addr:housenumber":"9401",
    "addr:postcode":"92223",
    "addr:street":"Oak Glen Rd",
    "iso:country":"US",
    "sg:address":"9401 Oak Glen Rd",
    "sg:city":"Cherry Valley",
    "sg:classifiers":[
        {
            "category":"Museum",
            "type":"Entertainment"
        }
    ],
    "sg:phone":"+1 951 845 2626",
    "sg:postcode":"92223",
    "sg:province":"CA",
    "sg:website":"www.edward-deanmuseum.org",
    "wof:name":"Edward-Dean Museum of Decorative Arts",
    "wof:placetype":"venue"
},
  "geometry": {"coordinates":[-116.970001,33.984699],"type":"Point"}
}