{
  "type": "Feature",
  "properties": {
    "iso:country":"US",
    "sg:address":"4280 Missouri Flat Rd",
    "sg:city":"Placerville",
    "sg:classifiers":[
        {
            "category":"Restaurant",
            "type":"Food & Drink"
        }
    ],
    "sg:phone":"+1 530 626 5269",
    "sg:postcode":"95667",
    "sg:province":"CA",
    "wof:name":"Panda Express 1790",
    "wof:placetype":"venue"
},
  "geometry": {"coordinates":[-120.83078500000001,38.706467],"type":"Point"}
}