{
  "type": "Feature",
  "properties": {
    "addr:full":"3040 H St Bakersfield CA 93301",
    "addr:housenumber":"3040",
    "addr:postcode":"93301",
    "addr:street":"H St",
    "iso:country":"US",
    "sg:address":"3040 H St",
    "sg:city":"Bakersfield",
    "sg:classifiers":[
        {
            "category":"Professional",
            "subcategory":"Testing Lab",
            "type":"Services"
        }
    ],
    "sg:phone":"+1 661 863 0158",
    "sg:postcode":"93301",
    "sg:province":"CA",
    "sg:tags":[
        "equipment",
        "laboratory",
        "industrial",
        "mfg"
    ],
    "sg:website":"www.nwmetrology.com",
    "wof:name":"Northwest Metrology",
    "wof:placetype":"venue"
},
  "geometry": {"coordinates":[-119.02105299999999,35.387378],"type":"Point"}
}