{
  "type": "Feature",
  "properties": {
    "addr:full":"4821 Freeport Blvd Sacramento CA 95822",
    "addr:housenumber":"4821",
    "addr:postcode":"95822",
    "addr:street":"Freeport Blvd",
    "iso:country":"US",
    "sg:address":"4821 Freeport Blvd",
    "sg:city":"Sacramento",
    "sg:classifiers":[
        {
            "category":"Retail",
            "subcategory":"Laundry & Dry Cleaning",
            "type":"Services"
        }
    ],
    "sg:phone":"+1 916 451 7017",
    "sg:postcode":"95822",
    "sg:province":"CA",
    "wof:name":"Swansons Cleaners",
    "wof:placetype":"venue"
},
  "geometry": {"coordinates":[-121.495003,38.5313],"type":"Point"}
}