{
  "type": "Feature",
  "properties": {
    "iso:country":"US",
    "sg:address":"4850 Olivehurst Ave",
    "sg:city":"Olivehurst",
    "sg:classifiers":[
        {
            "category":"Social Services",
            "type":"Services"
        }
    ],
    "sg:phone":"+1 530 740 7767",
    "sg:postcode":"95961",
    "sg:province":"CA",
    "sg:tags":[
        "organization",
        "welfare"
    ],
    "wof:name":"ABC Olivehurst Family Rsrc",
    "wof:placetype":"venue"
},
  "geometry": {"coordinates":[-121.551711,39.094912],"type":"Point"}
}