{
  "type": "Feature",
  "properties": {
    "iso:country":"US",
    "sg:address":"2621 Santa Monica Blvd",
    "sg:city":"Santa Monica",
    "sg:classifiers":[
        {
            "category":"Manufacturing",
            "subcategory":"Signs",
            "type":"Manufacturing & Wholesale Goods"
        }
    ],
    "sg:phone":"+1 310 828 3427",
    "sg:postcode":"90404",
    "sg:province":"CA",
    "wof:name":"Hana Graphics",
    "wof:placetype":"venue"
},
  "geometry": {"coordinates":[-118.473581,34.033959],"type":"Point"}
}