{
  "type": "Feature",
  "properties": {
    "addr:full":"1299 Cam del Rio S San Diego CA 92108",
    "addr:housenumber":"1299",
    "addr:postcode":"92108",
    "addr:street":"Cam Del Rio S",
    "iso:country":"US",
    "sg:address":"1299 Cam del Rio S",
    "sg:city":"San Diego",
    "sg:classifiers":[
        {
            "category":"Bars & Pubs",
            "type":"Food & Drink"
        }
    ],
    "sg:phone":"+1 619 299 3544",
    "sg:postcode":"92108",
    "sg:province":"CA",
    "sg:tags":[
        "discotheque"
    ],
    "wof:name":"Rio Club",
    "wof:placetype":"venue"
},
  "geometry": {"coordinates":[-117.141144,32.768414],"type":"Point"}
}