{
  "type": "Feature",
  "properties": {
    "iso:country":"US",
    "sg:address":"9725 Alder Ave",
    "sg:city":"Bloomington",
    "sg:classifiers":[
        {
            "category":"Utilities",
            "subcategory":"Water",
            "type":"Services"
        },
        {
            "category":"Organizations",
            "subcategory":"Non-profit Organization",
            "type":"Services"
        }
    ],
    "sg:phone":"+1 909 877 0516",
    "sg:postcode":"92316",
    "sg:province":"CA",
    "sg:tags":[
        "company-utility",
        "supply"
    ],
    "wof:name":"Marygold Mutual Water Co Inc",
    "wof:placetype":"venue"
},
  "geometry": {"coordinates":[-117.418251,34.077002],"type":"Point"}
}