{
  "type": "Feature",
  "properties": {
    "iso:country":"US",
    "sg:address":"509 E Montecito St. 2nd Fl.",
    "sg:city":"Santa Barbara",
    "sg:classifiers":[
        {
            "category":"Professional",
            "subcategory":"Computer Services",
            "type":"Services"
        }
    ],
    "sg:postcode":"93103",
    "sg:province":"CA",
    "sg:tags":[
        "find",
        "compare",
        "comparison",
        "find--the--best--findthebest",
        "top-ten",
        "database",
        "facts",
        "semantic-web",
        "best-of",
        "reviews"
    ],
    "sg:website":"http://www.FindTheBest.com",
    "wof:name":"FindTheBest",
    "wof:placetype":"venue"
},
  "geometry": {"coordinates":[-119.686283,34.421231],"type":"Point"}
}