{
  "type": "Feature",
  "properties": {
    "addr:full":"27135 Silver Oak Lane Canyon Country CA 91387",
    "addr:housenumber":"27135",
    "addr:postcode":"91387",
    "addr:street":"Silver Oak Lane",
    "iso:country":"US",
    "sg:address":"27135 Silver Oak Lane",
    "sg:city":"Canyon Country",
    "sg:classifiers":[
        {
            "category":"Professional",
            "subcategory":"Art Services",
            "type":"Services"
        }
    ],
    "sg:phone":"+1 661 852 8727",
    "sg:postcode":"91387",
    "sg:province":"CA",
    "sg:tags":[
        "photographer"
    ],
    "wof:name":"Picture Me Parties",
    "wof:placetype":"venue"
},
  "geometry": {"coordinates":[-118.45564,34.405977],"type":"Point"}
}