{
  "type": "Feature",
  "properties": {
    "addr:full":"25716 Baseline St San Bernardino CA 92410",
    "addr:housenumber":"25716",
    "addr:postcode":"92410",
    "addr:street":"Baseline St",
    "iso:country":"US",
    "sg:address":"25716 Baseline St",
    "sg:city":"San Bernardino",
    "sg:classifiers":[
        {
            "category":"Banks & Credit Unions",
            "subcategory":"Bank",
            "type":"Services"
        }
    ],
    "sg:phone":"+1 909 884 5088",
    "sg:postcode":"92410",
    "sg:province":"CA",
    "sg:tags":[
        "cashing",
        "check"
    ],
    "wof:name":"USA Checks Cashed",
    "wof:placetype":"venue"
},
  "geometry": {"coordinates":[-117.24189200000001,34.121388],"type":"Point"}
}