{
  "type": "Feature",
  "properties": {
    "iso:country":"US",
    "sg:address":"1015 Main St",
    "sg:city":"Susanville",
    "sg:classifiers":[
        {
            "category":"Shopping",
            "subcategory":"Shoes",
            "type":"Retail Goods"
        }
    ],
    "sg:phone":"+1 530 252 1015",
    "sg:postcode":"96130",
    "sg:province":"CA",
    "sg:tags":[
        "boot"
    ],
    "wof:name":"Susanville Boots & Saddles",
    "wof:placetype":"venue"
},
  "geometry": {"coordinates":[-120.657814,40.417691],"type":"Point"}
}