{
  "type": "Feature",
  "properties": {
    "addr:full":"13787 Comstock Rd Linden CA 95236",
    "addr:housenumber":"13787",
    "addr:postcode":"95236",
    "addr:street":"Comstock Rd",
    "iso:country":"US",
    "sg:address":"13787 Comstock Rd",
    "sg:city":"Linden",
    "sg:classifiers":[
        {
            "category":"Farming",
            "subcategory":"Orchard",
            "type":"Manufacturing & Wholesale Goods"
        }
    ],
    "sg:phone":"+1 209 931 4727",
    "sg:postcode":"95236",
    "sg:province":"CA",
    "sg:tags":[
        "fruit",
        "tree"
    ],
    "wof:name":"Elliot Orchards",
    "wof:placetype":"venue"
},
  "geometry": {"coordinates":[-121.13117699999999,38.044268],"type":"Point"}
}