{
  "type": "Feature",
  "properties": {
    "iso:country":"US",
    "sg:address":"25140 Hwy 94",
    "sg:city":"Potrero",
    "sg:classifiers":[
        {
            "category":"Manufacturing",
            "subcategory":"Retail Goods",
            "type":"Manufacturing & Wholesale Goods"
        }
    ],
    "sg:phone":"+1 619 478 5843",
    "sg:postcode":"91963",
    "sg:province":"CA",
    "sg:tags":[
        "manufacturer"
    ],
    "wof:name":"PEK Products",
    "wof:placetype":"venue"
},
  "geometry": {"coordinates":[-116.60779599999999,32.60431],"type":"Point"}
}