{
  "type": "Feature",
  "properties": {
    "iso:country":"US",
    "sg:address":"3740 Sierra Ave",
    "sg:city":"Fontana",
    "sg:classifiers":[
        {
            "category":"Autos & Motor Vehicles",
            "subcategory":"Fuel & Gas Station",
            "type":"Retail Goods"
        }
    ],
    "sg:phone":"+1 909 428 0222",
    "sg:postcode":"92336",
    "sg:province":"CA",
    "sg:tags":[
        "oil"
    ],
    "wof:name":"SSA Enterprise Inc",
    "wof:placetype":"venue"
},
  "geometry": {"coordinates":[-117.438486,34.184718],"type":"Point"}
}