{
  "type": "Feature",
  "properties": {
    "addr:full":"1618 1/2 W 134th St Gardena CA 90249",
    "addr:housenumber":"1618 1 / 2",
    "addr:postcode":"90249",
    "addr:street":"W 134Th St",
    "iso:country":"US",
    "sg:address":"1618 1/2 W 134th St",
    "sg:city":"Gardena",
    "sg:classifiers":[
        {
            "category":"Building & Trades",
            "subcategory":"Construction",
            "type":"Services"
        }
    ],
    "sg:phone":"+1 310 286 6400",
    "sg:postcode":"90249",
    "sg:province":"CA",
    "sg:tags":[
        "contractor"
    ],
    "wof:name":"Hospitality Restoration & Builders",
    "wof:placetype":"venue"
},
  "geometry": {"coordinates":[-118.305083,33.910786],"type":"Point"}
}