{
  "type": "Feature",
  "properties": {
    "addr:full":"11116 Rives Avenue Downey CA 90241",
    "addr:housenumber":"11116",
    "addr:postcode":"90241",
    "addr:street":"Rives Avenue",
    "iso:country":"US",
    "sg:address":"11116 Rives Avenue",
    "sg:city":"Downey",
    "sg:classifiers":[
        {
            "category":"Health Services",
            "subcategory":"Dentist",
            "type":"Services"
        }
    ],
    "sg:phone":"+1 562 862 4892",
    "sg:postcode":"90241",
    "sg:province":"CA",
    "wof:name":"Sullivan Michael E DDS",
    "wof:placetype":"venue"
},
  "geometry": {"coordinates":[-118.141615,33.945284],"type":"Point"}
}