{
  "type": "Feature",
  "properties": {
    "iso:country":"US",
    "sg:address":"2105 S Bascom Ave Ste 170",
    "sg:city":"Campbell",
    "sg:classifiers":[
        {
            "category":"Professional",
            "type":"Services"
        }
    ],
    "sg:phone":"+1 408 316 6775",
    "sg:postcode":"95008",
    "sg:province":"CA",
    "sg:website":"www.lglifecoach.com",
    "wof:name":"Laura Gordon",
    "wof:placetype":"venue"
},
  "geometry": {"coordinates":[-121.93288200000001,37.285154],"type":"Point"}
}