{
  "type": "Feature",
  "properties": {
    "addr:full":"2201 Belmont Ln Redondo Beach CA 90278",
    "addr:housenumber":"2201",
    "addr:postcode":"90278",
    "addr:street":"Belmont Ln",
    "iso:country":"US",
    "sg:address":"2201 Belmont Ln",
    "sg:city":"Redondo Beach",
    "sg:classifiers":[
        {
            "category":"Building & Trades",
            "subcategory":"Construction",
            "type":"Services"
        }
    ],
    "sg:phone":"+1 310 370 4669",
    "sg:postcode":"90278",
    "sg:province":"CA",
    "sg:tags":[
        "coping",
        "plastering",
        "tiling",
        "pool",
        "swimming"
    ],
    "wof:name":"Superior Pools Inc",
    "wof:placetype":"venue"
},
  "geometry": {"coordinates":[-118.37059499999999,33.863358],"type":"Point"}
}