{
  "type": "Feature",
  "properties": {
    "addr:full":"1237 Fortna Ave Woodland CA 95776",
    "addr:housenumber":"1237",
    "addr:postcode":"95776",
    "addr:street":"Fortna Ave",
    "iso:country":"US",
    "sg:address":"1237 Fortna Ave",
    "sg:city":"Woodland",
    "sg:classifiers":[
        {
            "category":"Retail",
            "subcategory":"Auto Repair",
            "type":"Services"
        }
    ],
    "sg:phone":"+1 530 666 0962",
    "sg:postcode":"95776",
    "sg:province":"CA",
    "sg:tags":[
        "wrecker"
    ],
    "wof:name":"Morgan Towing & Mufflers",
    "wof:placetype":"venue"
},
  "geometry": {"coordinates":[-121.762232,38.690092],"type":"Point"}
}