{
  "type": "Feature",
  "properties": {
    "iso:country":"US",
    "sg:address":"3627 Calmbrook Ln",
    "sg:city":"Diamond Bar",
    "sg:classifiers":[
        {
            "category":"Real Estate",
            "subcategory":"Real Estate Agent",
            "type":"Services"
        }
    ],
    "sg:phone":"+1 909 860 0215",
    "sg:postcode":"91765",
    "sg:province":"CA",
    "wof:name":"Alfa Investment & Finance",
    "wof:placetype":"venue"
},
  "geometry": {"coordinates":[-117.845232,33.96136],"type":"Point"}
}