{
  "type": "Feature",
  "properties": {
    "addr:full":"3553 Crownridge Dr Sherman Oaks CA 91403",
    "addr:housenumber":"3553",
    "addr:postcode":"91403",
    "addr:street":"Crownridge Dr",
    "iso:country":"US",
    "sg:address":"3553 Crownridge Dr",
    "sg:city":"Sherman Oaks",
    "sg:classifiers":[
        {
            "category":"Professional",
            "subcategory":"Lawyer & Legal Services",
            "type":"Services"
        }
    ],
    "sg:phone":"+1 818 995 6692",
    "sg:postcode":"91403",
    "sg:province":"CA",
    "sg:tags":[
        "attorney"
    ],
    "wof:name":"Norman Goldberg Attorney",
    "wof:placetype":"venue"
},
  "geometry": {"coordinates":[-118.475403,34.135662],"type":"Point"}
}