{
  "type": "Feature",
  "properties": {
    "iso:country":"US",
    "sg:address":"4561 N Blackstone Ave",
    "sg:city":"Fresno",
    "sg:classifiers":[
        {
            "category":"Professional",
            "subcategory":"Advertising",
            "type":"Services"
        }
    ],
    "sg:phone":"+1 559 226 3101",
    "sg:postcode":"93726",
    "sg:province":"CA",
    "wof:name":"Be-Bop Productions",
    "wof:placetype":"venue"
},
  "geometry": {"coordinates":[-119.790548,36.800198],"type":"Point"}
}