{
  "type": "Feature",
  "properties": {
    "iso:country":"US",
    "sg:address":"5110 Westminster Ave",
    "sg:city":"Santa Ana",
    "sg:classifiers":[
        {
            "category":"Health Services",
            "subcategory":"Health Practitioner",
            "type":"Services"
        }
    ],
    "sg:phone":"+1 714 636 6816",
    "sg:postcode":"92703",
    "sg:province":"CA",
    "sg:tags":[
        "acupuncture"
    ],
    "wof:name":"Lan Pao Phong Acupuncture Clinic",
    "wof:placetype":"venue"
},
  "geometry": {"coordinates":[-117.902,33.748699],"type":"Point"}
}