{
  "type": "Feature",
  "properties": {
    "addr:full":"450 E 8th St National City CA 91950",
    "addr:housenumber":"450",
    "addr:postcode":"91950",
    "addr:street":"E 8Th St",
    "iso:country":"US",
    "sg:address":"450 E 8th St",
    "sg:city":"National City",
    "sg:classifiers":[
        {
            "category":"Food & Beverages",
            "subcategory":"Bakery",
            "type":"Retail Goods"
        }
    ],
    "sg:phone":"+1 619 477 8506",
    "sg:postcode":"91950",
    "sg:province":"CA",
    "sg:tags":[
        "baker"
    ],
    "wof:name":"Gemmae Bakeshop & Cafe",
    "wof:placetype":"venue"
},
  "geometry": {"coordinates":[-117.10178399999999,32.677267],"type":"Point"}
}