{
  "type": "Feature",
  "properties": {
    "addr:full":"990 A St San Rafael CA 94901",
    "addr:housenumber":"990",
    "addr:postcode":"94901",
    "addr:street":"A St",
    "iso:country":"US",
    "sg:address":"990 A St",
    "sg:city":"San Rafael",
    "sg:classifiers":[
        {
            "category":"Wholesale",
            "subcategory":"Hardware",
            "type":"Manufacturing & Wholesale Goods"
        }
    ],
    "sg:phone":"+1 415 456 9800",
    "sg:postcode":"94901",
    "sg:province":"CA",
    "sg:tags":[
        "tool"
    ],
    "wof:name":"Local Toolbox",
    "wof:placetype":"venue"
},
  "geometry": {"coordinates":[-122.52829,37.972233],"type":"Point"}
}