{
  "type": "Feature",
  "properties": {
    "addr:full":"235 S Citrus Ave West Covina CA 91791",
    "addr:housenumber":"235",
    "addr:postcode":"91791",
    "addr:street":"S Citrus Ave",
    "iso:country":"US",
    "sg:address":"235 S Citrus Ave",
    "sg:city":"West Covina",
    "sg:classifiers":[
        {
            "category":"Real Estate",
            "subcategory":"Real Estate Agent",
            "type":"Services"
        }
    ],
    "sg:phone":"+1 626 966 3688",
    "sg:postcode":"91791",
    "sg:province":"CA",
    "sg:tags":[
        "broker"
    ],
    "wof:name":"Coldwell Banker",
    "wof:placetype":"venue"
},
  "geometry": {"coordinates":[-117.890176,34.069876],"type":"Point"}
}