{
  "type": "Feature",
  "properties": {
    "addr:full":"1976 Hacienda Dr Vista CA 92081",
    "addr:housenumber":"1976",
    "addr:postcode":"92081",
    "addr:street":"Hacienda Dr",
    "iso:country":"US",
    "sg:address":"1976 Hacienda Dr",
    "sg:city":"Vista",
    "sg:classifiers":[
        {
            "category":"Health Services",
            "subcategory":"Health Practitioner",
            "type":"Services"
        }
    ],
    "sg:phone":"+1 760 758 4770",
    "sg:postcode":"92081",
    "sg:province":"CA",
    "sg:tags":[
        "therapy",
        "physical"
    ],
    "wof:name":"Bernave James R Rpt Inc",
    "wof:placetype":"venue"
},
  "geometry": {"coordinates":[-117.283997,33.185398],"type":"Point"}
}