{
  "type": "Feature",
  "properties": {
    "iso:country":"US",
    "sg:address":"8607 1/2 Imperial Hwy",
    "sg:city":"Downey",
    "sg:classifiers":[
        {
            "category":"Shopping",
            "subcategory":"Mobile Phones",
            "type":"Retail Goods"
        },
        {
            "category":"Education",
            "subcategory":"School",
            "type":"Public Place"
        }
    ],
    "sg:phone":"+1 562 904 4009",
    "sg:postcode":"90242",
    "sg:province":"CA",
    "wof:name":"G S A T",
    "wof:placetype":"venue"
},
  "geometry": {"coordinates":[-118.14169699999999,33.918877],"type":"Point"}
}