{
  "type": "Feature",
  "properties": {
    "iso:country":"US",
    "sg:address":"1318 Fong St",
    "sg:city":"Folsom",
    "sg:classifiers":[
        {
            "category":"Shopping",
            "subcategory":"Bicycles & Sporting Goods",
            "type":"Retail Goods"
        }
    ],
    "sg:phone":"+1 916 985 0175",
    "sg:postcode":"95630",
    "sg:province":"CA",
    "sg:tags":[
        "equipment",
        "golf",
        "supply"
    ],
    "wof:name":"Golfee Carts",
    "wof:placetype":"venue"
},
  "geometry": {"coordinates":[-121.1824,38.672459],"type":"Point"}
}