{
  "type": "Feature",
  "properties": {
    "addr:full":"3116 E Chapman Ave Orange CA 92869",
    "addr:housenumber":"3116",
    "addr:postcode":"92869",
    "addr:street":"E Chapman Ave",
    "iso:country":"US",
    "sg:address":"3116 E Chapman Ave",
    "sg:city":"Orange",
    "sg:classifiers":[
        {
            "category":"Arts & Performance",
            "subcategory":"Arts Center",
            "type":"Entertainment"
        }
    ],
    "sg:phone":"+1 714 744 6015",
    "sg:postcode":"92869",
    "sg:province":"CA",
    "sg:tags":[
        "performing"
    ],
    "wof:name":"Phill's Ballroom Dance Studio",
    "wof:placetype":"venue"
},
  "geometry": {"coordinates":[-117.81999999999999,33.787701],"type":"Point"}
}