{
  "type": "Feature",
  "properties": {
    "iso:country":"US",
    "sg:address":"2014 Del Paso Blvd Ste B",
    "sg:city":"Sacramento",
    "sg:classifiers":[
        {
            "category":"Education",
            "subcategory":"Music School",
            "type":"Public Place"
        }
    ],
    "sg:phone":"+1 916 595 8531",
    "sg:postcode":"95815",
    "sg:province":"CA",
    "sg:tags":[
        "instrument",
        "teacher",
        "musical"
    ],
    "sg:website":"www.luthiery.woodyboyd.net",
    "wof:name":"Boyd Luthiery",
    "wof:placetype":"venue"
},
  "geometry": {"coordinates":[-121.452545,38.60923],"type":"Point"}
}