{
  "type": "Feature",
  "properties": {
    "iso:country":"US",
    "sg:address":"4111 W Redondo Beach Blvd",
    "sg:city":"Torrance",
    "sg:classifiers":[
        {
            "category":"Retail",
            "subcategory":"Auto Rental",
            "type":"Services"
        }
    ],
    "sg:phone":"+1 310 542 2277",
    "sg:postcode":"90501",
    "sg:province":"CA",
    "sg:tags":[
        "car"
    ],
    "wof:name":"Go Rent A Car",
    "wof:placetype":"venue"
},
  "geometry": {"coordinates":[-118.31500200000001,33.827599],"type":"Point"}
}