{
  "type": "Feature",
  "properties": {
    "addr:full":"624 Irving St San Francisco CA 94122",
    "addr:housenumber":"624",
    "addr:postcode":"94122",
    "addr:street":"Irving St",
    "iso:country":"US",
    "sg:address":"624 Irving St",
    "sg:city":"San Francisco",
    "sg:classifiers":[
        {
            "category":"Restaurant",
            "type":"Food & Drink"
        }
    ],
    "sg:menulink":"http://www.allmenus.com/ca/san-francisco/44518-crepevine-restaurant/menu/",
    "sg:phone":"+1 415 681 5858",
    "sg:postcode":"94122",
    "sg:province":"CA",
    "sg:tags":[
        "american"
    ],
    "wof:name":"Crepevine Restaurant",
    "wof:placetype":"venue"
},
  "geometry": {"coordinates":[-122.464536,37.764167],"type":"Point"}
}