{
  "type": "Feature",
  "properties": {
    "addr:full":"1227 Knox St Torrance CA 90502",
    "addr:housenumber":"1227",
    "addr:postcode":"90502",
    "addr:street":"Knox St",
    "iso:country":"US",
    "sg:address":"1227 Knox St",
    "sg:city":"Torrance",
    "sg:classifiers":[
        {
            "category":"Professional",
            "subcategory":"Management & Consulting",
            "type":"Services"
        },
        {
            "category":"Professional",
            "subcategory":"Advertising",
            "type":"Services"
        }
    ],
    "sg:phone":"+1 310 324 9903",
    "sg:postcode":"90502",
    "sg:province":"CA",
    "sg:tags":[
        "counselor",
        "medium",
        "public",
        "relations",
        "broker"
    ],
    "sg:website":"www.prietive-group.com",
    "wof:name":"Prietive Group Inc",
    "wof:placetype":"venue"
},
  "geometry": {"coordinates":[-118.297797,33.854303],"type":"Point"}
}