{
  "type": "Feature",
  "properties": {
    "addr:full":"1485 Chester Ave Arcata CA 95521",
    "addr:housenumber":"1485",
    "addr:postcode":"95521",
    "addr:street":"Chester Ave",
    "iso:country":"US",
    "sg:address":"1485 Chester Ave",
    "sg:city":"Arcata",
    "sg:classifiers":[
        {
            "category":"Building & Trades",
            "subcategory":"Cleaning & Sanitation",
            "type":"Services"
        }
    ],
    "sg:phone":"+1 707 822 7819",
    "sg:postcode":"95521",
    "sg:province":"CA",
    "sg:tags":[
        "janitor"
    ],
    "wof:name":"Arcata Cleaning Co",
    "wof:placetype":"venue"
},
  "geometry": {"coordinates":[-124.065502,40.858408],"type":"Point"}
}