{
  "type": "Feature",
  "properties": {
    "addr:full":"8302 Seven Hills Dr Bakersfield CA 93312",
    "addr:housenumber":"8302",
    "addr:postcode":"93312",
    "addr:street":"Seven Hills Dr",
    "iso:country":"US",
    "sg:address":"8302 Seven Hills Dr",
    "sg:city":"Bakersfield",
    "sg:classifiers":[
        {
            "category":"Building & Trades",
            "subcategory":"Electrical",
            "type":"Services"
        }
    ],
    "sg:phone":"+1 661 587 1355",
    "sg:postcode":"93312",
    "sg:province":"CA",
    "sg:tags":[
        "electric",
        "contractor"
    ],
    "wof:name":"JTI Electrical & Instruments",
    "wof:placetype":"venue"
},
  "geometry": {"coordinates":[-119.094784,35.384339],"type":"Point"}
}