{
  "type": "Feature",
  "properties": {
    "addr:full":"988 S Fair Oaks Ave Pasadena CA 91105",
    "addr:housenumber":"988",
    "addr:postcode":"91105",
    "addr:street":"S Fair Oaks Ave",
    "iso:country":"US",
    "sg:address":"988 S Fair Oaks Ave",
    "sg:city":"Pasadena",
    "sg:classifiers":[
        {
            "category":"Health Services",
            "subcategory":"Doctor",
            "type":"Services"
        }
    ],
    "sg:phone":"+1 626 799 4194",
    "sg:postcode":"91105",
    "sg:province":"CA",
    "wof:name":"Ella Shadmon, MD",
    "wof:placetype":"venue"
},
  "geometry": {"coordinates":[-118.15030899999999,34.128832],"type":"Point"}
}