{
  "type": "Feature",
  "properties": {
    "iso:country":"US",
    "sg:address":"3010 Oakmead Village Dr",
    "sg:city":"Santa Clara",
    "sg:classifiers":[
        {
            "category":"Professional",
            "type":"Services"
        }
    ],
    "sg:phone":"+1 408 986 8031",
    "sg:postcode":"95051",
    "sg:province":"CA",
    "sg:tags":[
        "technical",
        "preparation",
        "manual"
    ],
    "sg:website":"www.ghz.com",
    "wof:name":"Advanced Power Technology RF",
    "wof:placetype":"venue"
},
  "geometry": {"coordinates":[-121.98151900000001,37.376562],"type":"Point"}
}