{
  "type": "Feature",
  "properties": {
    "iso:country":"US",
    "sg:address":"11500 Sunrise Gold Cir",
    "sg:city":"Rancho Cordova",
    "sg:classifiers":[
        {
            "category":"Building & Trades",
            "subcategory":"Construction",
            "type":"Services"
        }
    ],
    "sg:phone":"+1 916 861 7800",
    "sg:postcode":"95742",
    "sg:province":"CA",
    "sg:tags":[
        "repairing",
        "remodeling",
        "contractor"
    ],
    "wof:name":"Your Energy Source",
    "wof:placetype":"venue"
},
  "geometry": {"coordinates":[-121.26206500000001,38.597867],"type":"Point"}
}