{
  "type": "Feature",
  "properties": {
    "addr:full":"1145 Hartnell Ave Redding CA 96002",
    "addr:housenumber":"1145",
    "addr:postcode":"96002",
    "addr:street":"Hartnell Ave",
    "iso:country":"US",
    "sg:address":"1145 Hartnell Ave",
    "sg:city":"Redding",
    "sg:classifiers":[
        {
            "category":"Education",
            "subcategory":"Vocational School",
            "type":"Public Place"
        }
    ],
    "sg:phone":"+1 530 223 5391",
    "sg:postcode":"96002",
    "sg:province":"CA",
    "sg:tags":[
        "real estate"
    ],
    "wof:name":"Real Estate Careers",
    "wof:placetype":"venue"
},
  "geometry": {"coordinates":[-122.353039,40.563733],"type":"Point"}
}