{
  "type": "Feature",
  "properties": {
    "iso:country":"US",
    "sg:address":"1820 41st Ave Ste G",
    "sg:city":"Capitola",
    "sg:classifiers":[
        {
            "category":"Restaurant",
            "type":"Food & Drink"
        }
    ],
    "sg:phone":"+1 831 462 5288",
    "sg:postcode":"95010",
    "sg:province":"CA",
    "sg:tags":[
        "asian",
        "pan",
        "japanese"
    ],
    "wof:name":"Miyako Japanese Restaurant",
    "wof:placetype":"venue"
},
  "geometry": {"coordinates":[-121.964996,36.9757],"type":"Point"}
}