{
  "type": "Feature",
  "properties": {
    "addr:full":"7901 W 3rd St Los Angeles CA 90048",
    "addr:housenumber":"7901",
    "addr:postcode":"90048",
    "addr:street":"W 3Rd St",
    "iso:country":"US",
    "sg:address":"7901 W 3rd St",
    "sg:city":"Los Angeles",
    "sg:classifiers":[
        {
            "category":"Professional",
            "type":"Services"
        }
    ],
    "sg:phone":"+1 323 939 6701",
    "sg:postcode":"90048",
    "sg:province":"CA",
    "wof:name":"Lopez Trees",
    "wof:placetype":"venue"
},
  "geometry": {"coordinates":[-118.363677,34.071826],"type":"Point"}
}