{
  "type": "Feature",
  "properties": {
    "iso:country":"US",
    "sg:address":"1391 Via de Los Reyes",
    "sg:city":"San Jose",
    "sg:classifiers":[
        {
            "category":"Wholesale",
            "subcategory":"Toys & Hobbies",
            "type":"Manufacturing & Wholesale Goods"
        }
    ],
    "sg:phone":"+1 408 927 5839",
    "sg:postcode":"95120",
    "sg:province":"CA",
    "sg:tags":[
        "wholesaler"
    ],
    "sg:website":"www.genassis.com",
    "wof:name":"Genassis",
    "wof:placetype":"venue"
},
  "geometry": {"coordinates":[-121.889491,37.226489],"type":"Point"}
}