{
  "type": "Feature",
  "properties": {
    "addr:full":"1391 Via de Los Reyes San Jose CA 95120",
    "addr:housenumber":"1391",
    "addr:postcode":"95120",
    "addr:street":"Via De Los Reyes",
    "iso:country":"US",
    "sg:address":"1391 Via de Los Reyes",
    "sg:city":"San Jose",
    "sg:classifiers":[
        {
            "category":"Wholesale",
            "subcategory":"Toys & Hobbies",
            "type":"Manufacturing & Wholesale Goods"
        }
    ],
    "sg:phone":"+1 408 927 5839",
    "sg:postcode":"95120",
    "sg:province":"CA",
    "sg:tags":[
        "wholesaler"
    ],
    "sg:website":"www.genassis.com",
    "wof:name":"Genassis",
    "wof:placetype":"venue"
},
  "geometry": {"coordinates":[-121.88949100000001,37.226489],"type":"Point"}
}