{
  "type": "Feature",
  "properties": {
    "iso:country":"US",
    "sg:address":"4433 S Alameda St",
    "sg:city":"Los Angeles",
    "sg:classifiers":[
        {
            "category":"Shopping",
            "subcategory":"Clothing, Apparel, & Fashions",
            "type":"Retail Goods"
        }
    ],
    "sg:phone":"+1 323 232 6884",
    "sg:postcode":"90058",
    "sg:province":"CA",
    "sg:tags":[
        "children's",
        "infant",
        "clothing",
        "wear"
    ],
    "wof:name":"Infantiles Erick",
    "wof:placetype":"venue"
},
  "geometry": {"coordinates":[-118.238998,34.003601],"type":"Point"}
}