{
  "type": "Feature",
  "properties": {
    "addr:full":"5921 Tupelo Dr Citrus Heights CA 95621",
    "addr:housenumber":"5921",
    "addr:postcode":"95621",
    "addr:street":"Tupelo Dr",
    "iso:country":"US",
    "sg:address":"5921 Tupelo Dr",
    "sg:city":"Citrus Heights",
    "sg:classifiers":[
        {
            "category":"Government",
            "subcategory":"Office",
            "type":"Public Place"
        }
    ],
    "sg:phone":"+1 916 654 2431",
    "sg:postcode":"95621",
    "sg:province":"CA",
    "sg:tags":[
        "development"
    ],
    "wof:name":"Developmental Services CA Dept",
    "wof:placetype":"venue"
},
  "geometry": {"coordinates":[-121.325292,38.698749],"type":"Point"}
}