{
  "type": "Feature",
  "properties": {
    "addr:full":"1157 Jay St Colusa CA 95932",
    "addr:housenumber":"1157",
    "addr:postcode":"95932",
    "addr:street":"Jay St",
    "iso:country":"US",
    "sg:address":"1157 Jay St",
    "sg:city":"Colusa",
    "sg:classifiers":[
        {
            "category":"Manufacturing",
            "subcategory":"Buildings",
            "type":"Manufacturing & Wholesale Goods"
        },
        {
            "category":"Building & Trades",
            "subcategory":"Construction",
            "type":"Services"
        }
    ],
    "sg:phone":"+1 530 501 5867",
    "sg:postcode":"95932",
    "sg:province":"CA",
    "sg:tags":[
        "home",
        "builder",
        "contractor"
    ],
    "wof:name":"Fasaro Construction",
    "wof:placetype":"venue"
},
  "geometry": {"coordinates":[-122.01730000000001,39.215169],"type":"Point"}
}