{
  "type": "Feature",
  "properties": {
    "iso:country":"US",
    "sg:address":"6227 Ivar Ave",
    "sg:city":"Temple City",
    "sg:classifiers":[
        {
            "category":"Wholesale",
            "subcategory":"Chemicals & Plastics",
            "type":"Manufacturing & Wholesale Goods"
        }
    ],
    "sg:phone":"+1 626 285 9968",
    "sg:postcode":"91780",
    "sg:province":"CA",
    "sg:tags":[
        "scrap",
        "export"
    ],
    "wof:name":"Toptrade Recycling (usa) Inc",
    "wof:placetype":"venue"
},
  "geometry": {"coordinates":[-118.076148,34.110849],"type":"Point"}
}