{
  "type": "Feature",
  "properties": {
    "iso:country":"US",
    "sg:address":"435 de la Vina St",
    "sg:city":"Santa Barbara",
    "sg:classifiers":[
        {
            "category":"Food & Beverages",
            "subcategory":"Groceries & Convenience Stores",
            "type":"Retail Goods"
        }
    ],
    "sg:phone":"+1 805 965 3959",
    "sg:postcode":"93101",
    "sg:province":"CA",
    "sg:tags":[
        "grocer"
    ],
    "wof:name":"Brownie's Market",
    "wof:placetype":"venue"
},
  "geometry": {"coordinates":[-119.69710600000001,34.414057],"type":"Point"}
}