{
  "type": "Feature",
  "properties": {
    "iso:country":"US",
    "sg:address":"57 Post St",
    "sg:city":"San Francisco",
    "sg:classifiers":[
        {
            "category":"Professional",
            "subcategory":"Lawyer & Legal Services",
            "type":"Services"
        }
    ],
    "sg:phone":"+1 415 986 7300",
    "sg:postcode":"94104",
    "sg:province":"CA",
    "sg:tags":[
        "attorney"
    ],
    "sg:website":"www.halversonassociates.com",
    "wof:name":"Halverson & Assoc",
    "wof:placetype":"venue"
},
  "geometry": {"coordinates":[-122.403405,37.788859],"type":"Point"}
}