{
  "type": "Feature",
  "properties": {
    "addr:full":"13301 Brookhurst St Garden Grove CA 92843",
    "addr:housenumber":"13301",
    "addr:postcode":"92843",
    "addr:street":"Brookhurst St",
    "iso:country":"US",
    "sg:address":"13301 Brookhurst St",
    "sg:city":"Garden Grove",
    "sg:classifiers":[
        {
            "category":"Insurance",
            "subcategory":"Health Insurance",
            "type":"Services"
        }
    ],
    "sg:phone":"+1 714 537 8391",
    "sg:postcode":"92843",
    "sg:province":"CA",
    "sg:tags":[
        "market"
    ],
    "wof:name":"Everlasting Life Chinese Herb",
    "wof:placetype":"venue"
},
  "geometry": {"coordinates":[-117.95500199999999,33.769402],"type":"Point"}
}