{
  "type": "Feature",
  "properties": {
    "addr:full":"1510 Newlands Ave Burlingame CA 94010",
    "addr:housenumber":"1510",
    "addr:postcode":"94010",
    "addr:street":"Newlands Ave",
    "iso:country":"US",
    "sg:address":"1510 Newlands Ave",
    "sg:city":"Burlingame",
    "sg:classifiers":[
        {
            "category":"Social Services",
            "subcategory":"Adult Care",
            "type":"Services"
        }
    ],
    "sg:phone":"+1 650 579 1915",
    "sg:postcode":"94010",
    "sg:province":"CA",
    "sg:tags":[
        "home",
        "residential"
    ],
    "wof:name":"Acacia Manor Care Home",
    "wof:placetype":"venue"
},
  "geometry": {"coordinates":[-122.346992,37.574356],"type":"Point"}
}