{
  "type": "Feature",
  "properties": {
    "addr:full":"713 S Pine Dr Fullerton CA 92833",
    "addr:housenumber":"713",
    "addr:postcode":"92833",
    "addr:street":"S Pine Dr",
    "iso:country":"US",
    "sg:address":"713 S Pine Dr",
    "sg:city":"Fullerton",
    "sg:classifiers":[
        {
            "category":"Professional",
            "subcategory":"Computer Services",
            "type":"Services"
        }
    ],
    "sg:phone":"+1 714 526 0567",
    "sg:postcode":"92833",
    "sg:province":"CA",
    "sg:tags":[
        "repair"
    ],
    "wof:name":"Fullerton Computer",
    "wof:placetype":"venue"
},
  "geometry": {"coordinates":[-117.967215,33.862947],"type":"Point"}
}