{
  "type": "Feature",
  "properties": {
    "addr:full":"330 Primrose Rd Burlingame CA 94010",
    "addr:housenumber":"330",
    "addr:postcode":"94010",
    "addr:street":"Primrose Rd",
    "iso:country":"US",
    "sg:address":"330 Primrose Rd",
    "sg:city":"Burlingame",
    "sg:classifiers":[
        {
            "category":"Banks & Credit Unions",
            "subcategory":"Bank",
            "type":"Services"
        }
    ],
    "sg:phone":"+1 650 347 7753",
    "sg:postcode":"94010",
    "sg:province":"CA",
    "sg:tags":[
        "brokerage",
        "loan",
        "real estate"
    ],
    "wof:name":"Nor Pen Investment & Loan Co",
    "wof:placetype":"venue"
},
  "geometry": {"coordinates":[-122.348429,37.578103],"type":"Point"}
}