{
  "type": "Feature",
  "properties": {
    "iso:country":"US",
    "sg:address":"22400 Lucerne St",
    "sg:city":"Carson",
    "sg:classifiers":[
        {
            "category":"Wholesale",
            "subcategory":"Metals & Minerals",
            "type":"Manufacturing & Wholesale Goods"
        }
    ],
    "sg:phone":"+1 323 775 7344",
    "sg:postcode":"90745",
    "sg:province":"CA",
    "sg:tags":[
        "center"
    ],
    "wof:name":"Crucible Service Centers",
    "wof:placetype":"venue"
},
  "geometry": {"coordinates":[-118.250519,33.823685],"type":"Point"}
}