{
  "type": "Feature",
  "properties": {
    "addr:full":"12145 Devries Rd Lodi CA 95242",
    "addr:housenumber":"12145",
    "addr:postcode":"95242",
    "addr:street":"Devries Rd",
    "iso:country":"US",
    "sg:address":"12145 Devries Rd",
    "sg:city":"Lodi",
    "sg:classifiers":[
        {
            "category":"Farming",
            "subcategory":"Farm & Veterinary Services",
            "type":"Manufacturing & Wholesale Goods"
        }
    ],
    "sg:phone":"+1 209 368 5889",
    "sg:postcode":"95242",
    "sg:province":"CA",
    "sg:tags":[
        "aerial",
        "applicator"
    ],
    "wof:name":"San Joaquin Air",
    "wof:placetype":"venue"
},
  "geometry": {"coordinates":[-121.35227999999999,38.096226],"type":"Point"}
}