{
  "type": "Feature",
  "properties": {
    "iso:country":"US",
    "sg:address":"8117 Melrose Ave",
    "sg:city":"Los Angeles",
    "sg:classifiers":[
        {
            "category":"Home & Garden",
            "subcategory":"Furniture",
            "type":"Retail Goods"
        }
    ],
    "sg:phone":"+1 323 852 1308",
    "sg:postcode":"90046",
    "sg:province":"CA",
    "wof:name":"Dragon Fly Furniture",
    "wof:placetype":"venue"
},
  "geometry": {"coordinates":[-118.366648,34.083811],"type":"Point"}
}