{
  "type": "Feature",
  "properties": {
    "addr:full":"707 E Buckingham Way Fresno CA 93704",
    "addr:housenumber":"707",
    "addr:postcode":"93704",
    "addr:street":"E Buckingham Way",
    "iso:country":"US",
    "sg:address":"707 E Buckingham Way",
    "sg:city":"Fresno",
    "sg:classifiers":[
        {
            "category":"Real Estate",
            "subcategory":"Real Estate Agent",
            "type":"Services"
        }
    ],
    "sg:phone":"+1 559 227 4658",
    "sg:postcode":"93704",
    "sg:province":"CA",
    "wof:name":"Abercrombie Associates Inc",
    "wof:placetype":"venue"
},
  "geometry": {"coordinates":[-119.799603,36.793162],"type":"Point"}
}