{
  "type": "Feature",
  "properties": {
    "iso:country":"US",
    "sg:address":"10818 Artesia Blvd",
    "sg:city":"Cerritos",
    "sg:classifiers":[
        {
            "category":"Education",
            "subcategory":"School",
            "type":"Public Place"
        }
    ],
    "sg:phone":"+1 562 860 0556",
    "sg:postcode":"90703",
    "sg:province":"CA",
    "sg:tags":[
        "high",
        "middle",
        "elementary"
    ],
    "wof:name":"Bellflower Christian School",
    "wof:placetype":"venue"
},
  "geometry": {"coordinates":[-118.102997,33.872898],"type":"Point"}
}