{
  "type": "Feature",
  "properties": {
    "addr:full":"26881 Ruether Ave Canyon Country CA 91351",
    "addr:housenumber":"26881",
    "addr:postcode":"91351",
    "addr:street":"Ruether Ave",
    "iso:country":"US",
    "sg:address":"26881 Ruether Ave",
    "sg:city":"Canyon Country",
    "sg:classifiers":[
        {
            "category":"Shopping",
            "subcategory":"Computers & Home Electronics",
            "type":"Retail Goods"
        }
    ],
    "sg:phone":"+1 661 299 2600",
    "sg:postcode":"91351",
    "sg:province":"CA",
    "sg:tags":[
        "equipment",
        "dealer"
    ],
    "wof:name":"Computer Supply Outlet Inc",
    "wof:placetype":"venue"
},
  "geometry": {"coordinates":[-118.498524,34.422431],"type":"Point"}
}