{
  "type": "Feature",
  "properties": {
    "iso:country":"US",
    "sg:address":"8315 Buckhorn St",
    "sg:city":"San Diego",
    "sg:classifiers":[
        {
            "category":"Retail",
            "subcategory":"Auto Repair",
            "type":"Services"
        }
    ],
    "sg:phone":"+1 858 467 0700",
    "sg:postcode":"92111",
    "sg:province":"CA",
    "sg:tags":[
        "body",
        "automobile",
        "painting"
    ],
    "wof:name":"All American Paint & Body",
    "wof:placetype":"venue"
},
  "geometry": {"coordinates":[-117.146176,32.825851],"type":"Point"}
}