{
  "type": "Feature",
  "properties": {
    "addr:full":"585 Bille Rd Paradise CA 95969",
    "addr:housenumber":"585",
    "addr:postcode":"95969",
    "addr:street":"Bille Rd",
    "iso:country":"US",
    "sg:address":"585 Bille Rd",
    "sg:city":"Paradise",
    "sg:classifiers":[
        {
            "category":"Social Services",
            "subcategory":"Adult Care",
            "type":"Services"
        }
    ],
    "sg:phone":"+1 530 872 9002",
    "sg:postcode":"95969",
    "sg:province":"CA",
    "sg:tags":[
        "home",
        "residential"
    ],
    "wof:name":"Mountain Meadow Lodge",
    "wof:placetype":"venue"
},
  "geometry": {"coordinates":[-121.629141,39.77056],"type":"Point"}
}