{
  "type": "Feature",
  "properties": {
    "iso:country":"US",
    "sg:address":"2216 Courtland Ave",
    "sg:city":"Oakland",
    "sg:classifiers":[
        {
            "category":"Building & Trades",
            "subcategory":"Cleaning & Sanitation",
            "type":"Services"
        }
    ],
    "sg:phone":"+1 510 434 9295",
    "sg:postcode":"94601",
    "sg:province":"CA",
    "sg:tags":[
        "janitorial"
    ],
    "wof:name":"One Way Janitorial",
    "wof:placetype":"venue"
},
  "geometry": {"coordinates":[-122.207497,37.777544],"type":"Point"}
}