{
  "type": "Feature",
  "properties": {
    "iso:country":"US",
    "sg:address":"2904 Rowena Ave",
    "sg:city":"Los Angeles",
    "sg:classifiers":[
        {
            "category":"Health Services",
            "subcategory":"Chiropractor",
            "type":"Services"
        }
    ],
    "sg:phone":"+1 323 660 2370",
    "sg:postcode":"90039",
    "sg:province":"CA",
    "wof:name":"Jones Carol Ann DC",
    "wof:placetype":"venue"
},
  "geometry": {"coordinates":[-118.26799800000001,34.108398],"type":"Point"}
}