{
  "type": "Feature",
  "properties": {
    "addr:full":"703 Sherwood Way Madera CA 93638",
    "addr:housenumber":"703",
    "addr:postcode":"93638",
    "addr:street":"Sherwood Way",
    "iso:country":"US",
    "sg:address":"703 Sherwood Way",
    "sg:city":"Madera",
    "sg:classifiers":[
        {
            "category":"Government",
            "subcategory":"Office",
            "type":"Public Place"
        }
    ],
    "sg:phone":"+1 559 674 8412",
    "sg:postcode":"93638",
    "sg:province":"CA",
    "sg:tags":[
        "village"
    ],
    "wof:name":"Madera City Office",
    "wof:placetype":"venue"
},
  "geometry": {"coordinates":[-120.05622700000001,36.977291],"type":"Point"}
}