{
  "type": "Feature",
  "properties": {
    "addr:full":"320 N Verdugo Rd Glendale CA 91206",
    "addr:housenumber":"320",
    "addr:postcode":"91206",
    "addr:street":"N Verdugo Rd",
    "iso:country":"US",
    "sg:address":"320 N Verdugo Rd",
    "sg:city":"Glendale",
    "sg:classifiers":[
        {
            "category":"Health Services",
            "subcategory":"Dentist",
            "type":"Services"
        }
    ],
    "sg:phone":"+1 818 548 0608",
    "sg:postcode":"91206",
    "sg:province":"CA",
    "wof:name":"Saint Terese Dental Clinic",
    "wof:placetype":"venue"
},
  "geometry": {"coordinates":[-118.236,34.1558],"type":"Point"}
}