{
  "type": "Feature",
  "properties": {
    "iso:country":"US",
    "sg:address":"32999 Yucaipa Blvd. #112",
    "sg:city":"Yucaipa",
    "sg:classifiers":[
        {
            "category":"Restaurant",
            "type":"Food & Drink"
        }
    ],
    "sg:phone":"+1 909 797 2000",
    "sg:postcode":"92399",
    "sg:province":"CA",
    "wof:name":"Mike's ''Philly Style'' Steaks & Hoagies",
    "wof:placetype":"venue"
},
  "geometry": {"coordinates":[-117.083984,34.032908],"type":"Point"}
}