{
  "type": "Feature",
  "properties": {
    "addr:full":"1783 Shawness Ct Westlake Village CA 91362",
    "addr:housenumber":"1783",
    "addr:postcode":"91362",
    "addr:street":"Shawness Ct",
    "iso:country":"US",
    "sg:address":"1783 Shawness Ct",
    "sg:city":"Westlake Village",
    "sg:classifiers":[
        {
            "category":"Professional",
            "subcategory":"Lawyer & Legal Services",
            "type":"Services"
        }
    ],
    "sg:phone":"+1 805 496 0409",
    "sg:postcode":"91362",
    "sg:province":"CA",
    "sg:tags":[
        "attorney"
    ],
    "wof:name":"Rackohn & Rackohn",
    "wof:placetype":"venue"
},
  "geometry": {"coordinates":[-118.806563,34.195204],"type":"Point"}
}