{
  "type": "Feature",
  "properties": {
    "addr:full":"544 N Puente Ave La Puente CA 91746",
    "addr:housenumber":"544",
    "addr:postcode":"91746",
    "addr:street":"N Puente Ave",
    "iso:country":"US",
    "sg:address":"544 N Puente Ave",
    "sg:city":"La Puente",
    "sg:classifiers":[
        {
            "category":"Personal",
            "subcategory":"Beauty Salon",
            "type":"Services"
        }
    ],
    "sg:phone":"+1 626 934 9366",
    "sg:postcode":"91746",
    "sg:province":"CA",
    "sg:tags":[
        "manicuring"
    ],
    "wof:name":"Nancy's Nails",
    "wof:placetype":"venue"
},
  "geometry": {"coordinates":[-117.982601,34.049475],"type":"Point"}
}