{
  "type": "Feature",
  "properties": {
    "iso:country":"US",
    "sg:address":"1330 Northridge Shopping Ctr",
    "sg:city":"Salinas",
    "sg:classifiers":[
        {
            "category":"Restaurant",
            "type":"Food & Drink"
        }
    ],
    "sg:phone":"+1 831 443 4905",
    "sg:postcode":"93906",
    "sg:province":"CA",
    "wof:name":"McDonalds",
    "wof:placetype":"venue"
},
  "geometry": {"coordinates":[-121.656893,36.720714],"type":"Point"}
}