{
  "type": "Feature",
  "properties": {
    "addr:full":"1163 Grass Valley Hwy Auburn CA 95603",
    "addr:housenumber":"1163",
    "addr:postcode":"ca 95603",
    "addr:street":"Grass Valley Hwy",
    "iso:country":"US",
    "sg:address":"1163 Grass Valley Hwy",
    "sg:city":"Auburn",
    "sg:classifiers":[
        {
            "category":"Home & Garden",
            "subcategory":"Home Furnishings",
            "type":"Retail Goods"
        }
    ],
    "sg:phone":"+1 530 823 3396",
    "sg:postcode":"95603",
    "sg:province":"CA",
    "sg:tags":[
        "stove",
        "wood",
        "burning"
    ],
    "wof:name":"Hearth & Home",
    "wof:placetype":"venue"
},
  "geometry": {"coordinates":[-121.08322099999999,38.92276],"type":"Point"}
}