{
  "type": "Feature",
  "properties": {
    "iso:country":"US",
    "sg:address":"324 Barca Ave",
    "sg:city":"La Puente",
    "sg:classifiers":[
        {
            "category":"Freight",
            "type":"Transportation"
        }
    ],
    "sg:phone":"+1 626 810 1058",
    "sg:postcode":"91744",
    "sg:province":"CA",
    "sg:tags":[
        "operator",
        "local",
        "trucking"
    ],
    "wof:name":"Delmar Delivery Service",
    "wof:placetype":"venue"
},
  "geometry": {"coordinates":[-117.905268,34.012416],"type":"Point"}
}