{
  "type": "Feature",
  "properties": {
    "iso:country":"US",
    "sg:address":"1537 N Baker St",
    "sg:city":"Santa Ana",
    "sg:classifiers":[
        {
            "category":"Personal",
            "subcategory":"Hair Removal",
            "type":"Services"
        }
    ],
    "sg:phone":"+1 714 540 3283",
    "sg:postcode":"92706",
    "sg:province":"CA",
    "wof:name":"Mesa Verde Electrology Clinic",
    "wof:placetype":"venue"
},
  "geometry": {"coordinates":[-117.883003,33.758801],"type":"Point"}
}