{
  "type": "Feature",
  "properties": {
    "addr:full":"11151 Amherst Ave Montclair CA 91763",
    "addr:housenumber":"11151",
    "addr:postcode":"91763",
    "addr:street":"Amherst Ave",
    "iso:country":"US",
    "sg:address":"11151 Amherst Ave",
    "sg:city":"Montclair",
    "sg:classifiers":[
        {
            "category":"Professional",
            "subcategory":"Business Services",
            "type":"Services"
        }
    ],
    "sg:phone":"+1 909 613 0863",
    "sg:postcode":"91763",
    "sg:province":"CA",
    "wof:name":"R T Raulston Enterprises",
    "wof:placetype":"venue"
},
  "geometry": {"coordinates":[-117.709895,34.051055],"type":"Point"}
}