{
  "type": "Feature",
  "properties": {
    "addr:full":"208 Cll Serrento Goleta CA 93117",
    "addr:housenumber":"208",
    "addr:postcode":"93117",
    "addr:street":"Cll Serrento",
    "iso:country":"US",
    "sg:address":"208 Cll Serrento",
    "sg:city":"Goleta",
    "sg:classifiers":[
        {
            "category":"Professional",
            "subcategory":"Computer Services",
            "type":"Services"
        }
    ],
    "sg:phone":"+1 805 685 2408",
    "sg:postcode":"93117",
    "sg:province":"CA",
    "sg:tags":[
        "related"
    ],
    "wof:name":"Smith Computer Services",
    "wof:placetype":"venue"
},
  "geometry": {"coordinates":[-119.90168300000001,34.439474],"type":"Point"}
}