{
  "type": "Feature",
  "properties": {
    "addr:full":"2225 Quinn Ave Santa Clara CA 95051",
    "addr:housenumber":"2225",
    "addr:postcode":"95051",
    "addr:street":"Quinn Ave",
    "iso:country":"US",
    "sg:address":"2225 Quinn Ave",
    "sg:city":"Santa Clara",
    "sg:classifiers":[
        {
            "category":"Banks & Credit Unions",
            "subcategory":"Bank",
            "type":"Services"
        }
    ],
    "sg:phone":"+1 408 277 7338",
    "sg:postcode":"95051",
    "sg:province":"CA",
    "sg:tags":[
        "national",
        "commercial"
    ],
    "wof:name":"Bank of America",
    "wof:placetype":"venue"
},
  "geometry": {"coordinates":[-121.972281,37.362377],"type":"Point"}
}