{
  "type": "Feature",
  "properties": {
    "addr:full":"3040 E Miraloma Ave Anaheim CA 92806",
    "addr:housenumber":"3040",
    "addr:postcode":"92806",
    "addr:street":"E Miraloma Ave",
    "iso:country":"US",
    "sg:address":"3040 E Miraloma Ave",
    "sg:city":"Anaheim",
    "sg:classifiers":[
        {
            "category":"Retail",
            "subcategory":"Auto Rental",
            "type":"Services"
        }
    ],
    "sg:phone":"+1 714 666 3100",
    "sg:postcode":"92806",
    "sg:province":"CA",
    "sg:tags":[
        "car"
    ],
    "sg:website":"www.hertzequip.com",
    "wof:name":"Hertz Equipment Rental",
    "wof:placetype":"venue"
},
  "geometry": {"coordinates":[-117.862999,33.8573],"type":"Point"}
}