{
  "type": "Feature",
  "properties": {
    "addr:full":"24701 Raymond Way Lake Forest CA 92630",
    "addr:housenumber":"24701",
    "addr:postcode":"92630",
    "addr:street":"Raymond Way",
    "iso:country":"US",
    "sg:address":"24701 Raymond Way",
    "sg:city":"Lake Forest",
    "sg:classifiers":[
        {
            "category":"Building & Trades",
            "subcategory":"Construction",
            "type":"Services"
        }
    ],
    "sg:phone":"+1 949 581 9062",
    "sg:postcode":"92630",
    "sg:province":"CA",
    "sg:tags":[
        "handyman"
    ],
    "wof:name":"Haskins Enterprises",
    "wof:placetype":"venue"
},
  "geometry": {"coordinates":[-117.69926,33.61965],"type":"Point"}
}