{
  "type": "Feature",
  "properties": {
    "iso:country":"US",
    "sg:address":"336 W Providencia Ave",
    "sg:city":"Burbank",
    "sg:classifiers":[
        {
            "category":"Professional",
            "type":"Services"
        }
    ],
    "sg:phone":"+1 818 845 8533",
    "sg:postcode":"91506",
    "sg:province":"CA",
    "sg:tags":[
        "establishment"
    ],
    "wof:name":"A & A Arrangement",
    "wof:placetype":"venue"
},
  "geometry": {"coordinates":[-118.312371,34.169078],"type":"Point"}
}