{
  "type": "Feature",
  "properties": {
    "addr:full":"7021 Mount Aukum Rd Somerset CA 95684",
    "addr:housenumber":"7021",
    "addr:postcode":"95684",
    "addr:street":"Mount Aukum Rd",
    "iso:country":"US",
    "sg:address":"7021 Mount Aukum Rd",
    "sg:city":"Somerset",
    "sg:classifiers":[
        {
            "category":"Farming",
            "subcategory":"Farm",
            "type":"Manufacturing & Wholesale Goods"
        }
    ],
    "sg:phone":"+1 530 620 5025",
    "sg:postcode":"95684",
    "sg:province":"CA",
    "wof:name":"Somerset Farm Gardens",
    "wof:placetype":"venue"
},
  "geometry": {"coordinates":[-120.716067,38.600929],"type":"Point"}
}