{
  "type": "Feature",
  "properties": {
    "iso:country":"US",
    "sg:address":"735 12th St",
    "sg:city":"Eureka",
    "sg:classifiers":[
        {
            "category":"Personal",
            "subcategory":"Massage",
            "type":"Services"
        },
        {
            "category":"Health Services",
            "subcategory":"Clinic",
            "type":"Services"
        },
        {
            "category":"Health Services",
            "subcategory":"Health Practitioner",
            "type":"Services"
        }
    ],
    "sg:phone":"+1 707 834 4643",
    "sg:postcode":"95501",
    "sg:province":"CA",
    "sg:tags":[
        "therapist",
        "therapy",
        "physical"
    ],
    "wof:name":"Jamie Bellermann",
    "wof:placetype":"venue"
},
  "geometry": {"coordinates":[-124.16203400000001,40.796587],"type":"Point"}
}