{
  "type": "Feature",
  "properties": {
    "addr:full":"636 N Plymouth Blvd Los Angeles CA 90004",
    "addr:housenumber":"636",
    "addr:postcode":"90004",
    "addr:street":"N Plymouth Blvd",
    "iso:country":"US",
    "sg:address":"636 N Plymouth Blvd",
    "sg:city":"Los Angeles",
    "sg:classifiers":[
        {
            "category":"Real Estate",
            "subcategory":"Real Estate Operator",
            "type":"Services"
        }
    ],
    "sg:phone":"+1 323 469 1870",
    "sg:postcode":"90004",
    "sg:province":"CA",
    "sg:tags":[
        "apartment"
    ],
    "wof:name":"Plymouth Court Llc",
    "wof:placetype":"venue"
},
  "geometry": {"coordinates":[-118.320999,34.082401],"type":"Point"}
}