{
  "type": "Feature",
  "properties": {
    "addr:full":"4619 Spyres Way Modesto CA 95356",
    "addr:housenumber":"4619",
    "addr:postcode":"ca 95356",
    "addr:street":"Spyres Way",
    "iso:country":"US",
    "sg:address":"4619 Spyres Way",
    "sg:city":"Modesto",
    "sg:classifiers":[
        {
            "category":"Building & Trades",
            "subcategory":"Construction",
            "type":"Services"
        },
        {
            "category":"Home & Garden",
            "subcategory":"Furniture",
            "type":"Retail Goods"
        }
    ],
    "sg:phone":"+1 209 342 9063",
    "sg:postcode":"95356",
    "sg:province":"CA",
    "sg:tags":[
        "equipment",
        "cabinet",
        "contractor",
        "carpentry",
        "kitchen"
    ],
    "wof:name":"D & S Custom Countertops",
    "wof:placetype":"venue"
},
  "geometry": {"coordinates":[-120.997451,37.706429],"type":"Point"}
}