{
  "type": "Feature",
  "properties": {
    "addr:full":"1600 Stokes Street Apt 10 San Jose CA 95126",
    "addr:housenumber":"1600;10",
    "addr:postcode":"95126",
    "addr:street":"Stokes Street Apt;Jose",
    "iso:country":"US",
    "sg:address":"1600 Stokes Street Apt 10",
    "sg:city":"San Jose",
    "sg:classifiers":[
        {
            "category":"Real Estate",
            "subcategory":"Real Estate Operator",
            "type":"Services"
        }
    ],
    "sg:phone":"+1 408 971 6653",
    "sg:postcode":"95126",
    "sg:province":"CA",
    "sg:tags":[
        "apartment"
    ],
    "wof:name":"Westwood Apartments",
    "wof:placetype":"venue"
},
  "geometry": {"coordinates":[-121.921672,37.301481],"type":"Point"}
}