{
  "type": "Feature",
  "properties": {
    "addr:full":"1363 Turlock Lane San Jose CA 95132",
    "addr:housenumber":"1363",
    "addr:postcode":"95132",
    "addr:street":"Turlock Lane",
    "iso:country":"US",
    "sg:address":"1363 Turlock Lane",
    "sg:city":"San Jose",
    "sg:classifiers":[
        {
            "category":"Organizations",
            "subcategory":"Religious Organization",
            "type":"Services"
        }
    ],
    "sg:phone":"+1 408 926 3472",
    "sg:postcode":"95132",
    "sg:province":"CA",
    "wof:name":"Lewis Memorial Christian Methodist Episcopal Church",
    "wof:placetype":"venue"
},
  "geometry": {"coordinates":[-121.85553400000001,37.399329],"type":"Point"}
}