{
  "type": "Feature",
  "properties": {
    "addr:full":"5955 de Soto Ave Woodland Hills CA 91303",
    "addr:housenumber":"5955",
    "addr:postcode":"91303",
    "addr:street":"De Soto Ave",
    "iso:country":"US",
    "sg:address":"5955 de Soto Ave",
    "sg:city":"Woodland Hills",
    "sg:classifiers":[
        {
            "category":"Banks & Credit Unions",
            "subcategory":"Bank",
            "type":"Services"
        }
    ],
    "sg:phone":"+1 818 382 7870",
    "sg:postcode":"91303",
    "sg:province":"CA",
    "sg:tags":[
        "consumer",
        "finance"
    ],
    "wof:name":"Western Financial Services",
    "wof:placetype":"venue"
},
  "geometry": {"coordinates":[-118.59031299999999,34.178123],"type":"Point"}
}