{
  "type": "Feature",
  "properties": {
    "iso:country":"US",
    "sg:address":"1755 E Daily Dr",
    "sg:city":"Camarillo",
    "sg:classifiers":[
        {
            "category":"Restaurant",
            "type":"Food & Drink"
        }
    ],
    "sg:phone":"+1 805 987 7995",
    "sg:postcode":"93010",
    "sg:province":"CA",
    "wof:name":"Sizzler",
    "wof:placetype":"venue"
},
  "geometry": {"coordinates":[-119.04538100000001,34.217862],"type":"Point"}
}