{
  "type": "Feature",
  "properties": {
    "addr:full":"200 Northstar Dr Truckee CA 96160",
    "addr:housenumber":"200",
    "addr:postcode":"96160",
    "addr:street":"Northstar Dr",
    "iso:country":"US",
    "sg:address":"200 Northstar Dr",
    "sg:city":"Truckee",
    "sg:classifiers":[
        {
            "category":"Autos & Motor Vehicles",
            "subcategory":"Fuel & Gas Station",
            "type":"Retail Goods"
        }
    ],
    "sg:phone":"+1 530 562 2496",
    "sg:postcode":"96160",
    "sg:province":"CA",
    "wof:name":"Northstar Gas Station",
    "wof:placetype":"venue"
},
  "geometry": {"coordinates":[-120.108088,39.285841],"type":"Point"}
}