{
  "type": "Feature",
  "properties": {
    "addr:full":"822 Pine St Mt Shasta CA 96067",
    "addr:housenumber":"822",
    "addr:postcode":"96067",
    "addr:street":"Pine St",
    "iso:country":"US",
    "sg:address":"822 Pine St",
    "sg:city":"Mt Shasta",
    "sg:classifiers":[
        {
            "category":"Health Services",
            "subcategory":"Doctor",
            "type":"Services"
        }
    ],
    "sg:phone":"+1 530 926 4528",
    "sg:postcode":"96067",
    "sg:province":"CA",
    "sg:tags":[
        "physician",
        "surgeon"
    ],
    "wof:name":"Siskiyou Medical Group",
    "wof:placetype":"venue"
},
  "geometry": {"coordinates":[-122.320302,41.316783],"type":"Point"}
}