{
  "type": "Feature",
  "properties": {
    "addr:full":"10261 S de Anza Blvd Cupertino CA 95014",
    "addr:housenumber":"10261",
    "addr:postcode":"95014",
    "addr:street":"S De Anza Blvd",
    "iso:country":"US",
    "sg:address":"10261 S de Anza Blvd",
    "sg:city":"Cupertino",
    "sg:classifiers":[
        {
            "category":"Shopping",
            "subcategory":"Crafts & Fabrics",
            "type":"Retail Goods"
        }
    ],
    "sg:phone":"+1 408 255 5270",
    "sg:postcode":"95014",
    "sg:province":"CA",
    "sg:tags":[
        "material",
        "quilting",
        "supply"
    ],
    "sg:website":"www.whiffletreequilts.com",
    "wof:name":"Whiffle Tree Quilts",
    "wof:placetype":"venue"
},
  "geometry": {"coordinates":[-122.032285,37.318069],"type":"Point"}
}