{
  "type": "Feature",
  "properties": {
    "addr:full":"10301 Viretta Ln Los Angeles CA 90077",
    "addr:housenumber":"10301",
    "addr:postcode":"90077",
    "addr:street":"Viretta Ln",
    "iso:country":"US",
    "sg:address":"10301 Viretta Ln",
    "sg:city":"Los Angeles",
    "sg:classifiers":[
        {
            "category":"Wholesale",
            "subcategory":"Electrical",
            "type":"Manufacturing & Wholesale Goods"
        }
    ],
    "sg:phone":"+1 310 474 8483",
    "sg:postcode":"90077",
    "sg:province":"CA",
    "sg:tags":[
        "equipment",
        "professional"
    ],
    "wof:name":"Pincu Thomas L & Associates",
    "wof:placetype":"venue"
},
  "geometry": {"coordinates":[-118.444298,34.103653],"type":"Point"}
}