{
  "type": "Feature",
  "properties": {
    "iso:country":"US",
    "sg:address":"4688 Convoy St Ste 106",
    "sg:city":"San Diego",
    "sg:classifiers":[
        {
            "category":"Shopping",
            "subcategory":"Hobbies, Toys, & Games",
            "type":"Retail Goods"
        },
        {
            "category":"Shopping",
            "subcategory":"Music",
            "type":"Retail Goods"
        },
        {
            "category":"Wholesale",
            "subcategory":"Stationery",
            "type":"Manufacturing & Wholesale Goods"
        }
    ],
    "sg:phone":"+1 858 277 0911",
    "sg:postcode":"92111",
    "sg:province":"CA",
    "sg:tags":[
        "toy",
        "store",
        "dvd's",
        "card"
    ],
    "wof:name":"Style Gifts",
    "wof:placetype":"venue"
},
  "geometry": {"coordinates":[-117.154726,32.826375],"type":"Point"}
}