{
  "type": "Feature",
  "properties": {
    "iso:country":"US",
    "sg:address":"2291 W 205th St",
    "sg:city":"Torrance",
    "sg:classifiers":[
        {
            "category":"Shopping",
            "subcategory":"Catalog Store",
            "type":"Retail Goods"
        }
    ],
    "sg:phone":"+1 310 782 0100",
    "sg:postcode":"90501",
    "sg:province":"CA",
    "sg:tags":[
        "mail",
        "order"
    ],
    "wof:name":"Nack USA Inc",
    "wof:placetype":"venue"
},
  "geometry": {"coordinates":[-118.326049,33.845392],"type":"Point"}
}