{
  "type": "Feature",
  "properties": {
    "addr:full":"939 Dartmouth St San Francisco CA 94134",
    "addr:housenumber":"939",
    "addr:postcode":"94134",
    "addr:street":"Dartmouth St",
    "iso:country":"US",
    "sg:address":"939 Dartmouth St",
    "sg:city":"San Francisco",
    "sg:classifiers":[
        {
            "category":"Building & Trades",
            "subcategory":"Construction",
            "type":"Services"
        }
    ],
    "sg:phone":"+1 415 584 1182",
    "sg:postcode":"94134",
    "sg:province":"CA",
    "sg:tags":[
        "painter"
    ],
    "wof:name":"Bloom Painting",
    "wof:placetype":"venue"
},
  "geometry": {"coordinates":[-122.408776,37.719233],"type":"Point"}
}