{
  "type": "Feature",
  "properties": {
    "iso:country":"US",
    "sg:address":"11324 Long Beach Blvd",
    "sg:city":"Lynwood",
    "sg:classifiers":[
        {
            "category":"Shopping",
            "subcategory":"Crafts & Fabrics",
            "type":"Retail Goods"
        }
    ],
    "sg:phone":"+1 310 608 1588",
    "sg:postcode":"90262",
    "sg:province":"CA",
    "sg:tags":[
        "art",
        "supply"
    ],
    "wof:name":"Lynwood Craft",
    "wof:placetype":"venue"
},
  "geometry": {"coordinates":[-118.21064200000001,33.928273],"type":"Point"}
}