{
  "type": "Feature",
  "properties": {
    "addr:full":"152 N Coast Hwy 101 Encinitas CA 92024",
    "addr:housenumber":"152",
    "addr:postcode":"92024",
    "addr:street":"N Coast Hwy 101",
    "iso:country":"US",
    "sg:address":"152 N Coast Hwy 101",
    "sg:city":"Encinitas",
    "sg:classifiers":[
        {
            "category":"Real Estate",
            "subcategory":"Real Estate Services",
            "type":"Services"
        }
    ],
    "sg:phone":"+1 760 753 4101",
    "sg:postcode":"92024",
    "sg:province":"CA",
    "wof:name":"Shamrock Trailer Park",
    "wof:placetype":"venue"
},
  "geometry": {"coordinates":[-117.295841,33.051305],"type":"Point"}
}