{
  "type": "Feature",
  "properties": {
    "iso:country":"US",
    "sg:address":"1004 N Euclid St",
    "sg:city":"Anaheim",
    "sg:classifiers":[
        {
            "category":"Health Services",
            "subcategory":"Doctor",
            "type":"Services"
        }
    ],
    "sg:phone":"+1 714 776 3551",
    "sg:postcode":"92801",
    "sg:province":"CA",
    "sg:tags":[
        "surgeon",
        "oral"
    ],
    "wof:name":"Family Denist Center Touchard Cecil DDS",
    "wof:placetype":"venue"
},
  "geometry": {"coordinates":[-117.942001,33.8461],"type":"Point"}
}