{
  "type": "Feature",
  "properties": {
    "addr:full":"41607 Margarita Rd Temecula CA 92591",
    "addr:housenumber":"41607",
    "addr:postcode":"92591",
    "addr:street":"Margarita Rd",
    "iso:country":"US",
    "sg:address":"41607 Margarita Rd",
    "sg:city":"Temecula",
    "sg:classifiers":[
        {
            "category":"Real Estate",
            "subcategory":"Developer",
            "type":"Services"
        }
    ],
    "sg:phone":"+1 951 699 4385",
    "sg:postcode":"92591",
    "sg:province":"CA",
    "wof:name":"Pacific Century Commercial",
    "wof:placetype":"venue"
},
  "geometry": {"coordinates":[-117.14994799999999,33.516312],"type":"Point"}
}