{
  "type": "Feature",
  "properties": {
    "addr:full":"3307 Broadway St Sacramento CA 95817",
    "addr:housenumber":"3307",
    "addr:postcode":"95817",
    "addr:street":"Broadway St",
    "iso:country":"US",
    "sg:address":"3307 Broadway St",
    "sg:city":"Sacramento",
    "sg:classifiers":[
        {
            "category":"Social Services",
            "subcategory":"Job Training",
            "type":"Services"
        }
    ],
    "sg:phone":"+1 916 451 4915",
    "sg:postcode":"95817",
    "sg:province":"CA",
    "sg:tags":[
        "rehabilitation"
    ],
    "wof:name":"Moore & Moore Rehab Consltng",
    "wof:placetype":"venue"
},
  "geometry": {"coordinates":[-121.469872,38.5533],"type":"Point"}
}