{
  "type": "Feature",
  "properties": {
    "iso:country":"US",
    "sg:address":"5189 Verdugo Way",
    "sg:city":"Camarillo",
    "sg:classifiers":[
        {
            "category":"Education",
            "subcategory":"School",
            "type":"Public Place"
        }
    ],
    "sg:phone":"+1 805 383 1919",
    "sg:postcode":"93012",
    "sg:province":"CA",
    "wof:name":"Ventura County Special Educ",
    "wof:placetype":"venue"
},
  "geometry": {"coordinates":[-118.999525,34.21402],"type":"Point"}
}