{
  "type": "Feature",
  "properties": {
    "addr:full":"14254 Live Oak Ave Baldwin Park CA 91706",
    "addr:housenumber":"14254",
    "addr:postcode":"91706",
    "addr:street":"Live Oak Ave",
    "iso:country":"US",
    "sg:address":"14254 Live Oak Ave",
    "sg:city":"Baldwin Park",
    "sg:classifiers":[
        {
            "category":"Manufacturing",
            "subcategory":"Glass & Minerals",
            "type":"Manufacturing & Wholesale Goods"
        }
    ],
    "sg:phone":"+1 626 472 7157",
    "sg:postcode":"91706",
    "sg:province":"CA",
    "sg:tags":[
        "tile"
    ],
    "wof:name":"K J Patterson Inc",
    "wof:placetype":"venue"
},
  "geometry": {"coordinates":[-117.963866,34.106802],"type":"Point"}
}