{
  "type": "Feature",
  "properties": {
    "addr:full":"900 J St Sacramento CA 95814",
    "addr:housenumber":"900",
    "addr:postcode":"95814",
    "addr:street":"J St",
    "iso:country":"US",
    "sg:address":"900 J St",
    "sg:city":"Sacramento",
    "sg:classifiers":[
        {
            "category":"Social Services",
            "type":"Services"
        }
    ],
    "sg:phone":"+1 916 447 0503",
    "sg:postcode":"95814",
    "sg:province":"CA",
    "sg:tags":[
        "human"
    ],
    "wof:name":"Housing Calif.",
    "wof:placetype":"venue"
},
  "geometry": {"coordinates":[-121.494781,38.580681],"type":"Point"}
}