{
  "type": "Feature",
  "properties": {
    "iso:country":"US",
    "sg:address":"20 Joseph Ct",
    "sg:city":"San Rafael",
    "sg:classifiers":[
        {
            "category":"Building & Trades",
            "subcategory":"Construction",
            "type":"Services"
        }
    ],
    "sg:phone":"+1 415 927 3482",
    "sg:postcode":"94903",
    "sg:province":"CA",
    "sg:tags":[
        "contractor"
    ],
    "wof:name":"Northern Pacific Roofing",
    "wof:placetype":"venue"
},
  "geometry": {"coordinates":[-122.540088,38.013312],"type":"Point"}
}