{
  "type": "Feature",
  "properties": {
    "addr:full":"675 37th St Oakland CA 94609",
    "addr:housenumber":"675",
    "addr:postcode":"94609",
    "addr:street":"37Th St",
    "iso:country":"US",
    "sg:address":"675 37th St",
    "sg:city":"Oakland",
    "sg:classifiers":[
        {
            "category":"Manufacturing",
            "subcategory":"Glass & Minerals",
            "type":"Manufacturing & Wholesale Goods"
        },
        {
            "category":"Shopping",
            "subcategory":"Gifts & Souvenirs",
            "type":"Retail Goods"
        }
    ],
    "sg:phone":"+1 510 601 7955",
    "sg:postcode":"94609",
    "sg:province":"CA",
    "sg:tags":[
        "mfg",
        "art",
        "blown"
    ],
    "wof:name":"Charles Vannatta Glass",
    "wof:placetype":"venue"
},
  "geometry": {"coordinates":[-122.27154400000001,37.826559],"type":"Point"}
}