{
  "type": "Feature",
  "properties": {
    "iso:country":"US",
    "sg:address":"247 N Main St",
    "sg:city":"Fort Bragg",
    "sg:classifiers":[
        {
            "category":"Utilities",
            "subcategory":"Mobile Phone",
            "type":"Services"
        }
    ],
    "sg:phone":"+1 707 964 1666",
    "sg:postcode":"95437",
    "sg:province":"CA",
    "sg:tags":[
        "communication",
        "radiotelephone"
    ],
    "wof:name":"United States Cellular Corp",
    "wof:placetype":"venue"
},
  "geometry": {"coordinates":[-123.80609,39.443561],"type":"Point"}
}