{
  "type": "Feature",
  "properties": {
    "addr:full":"12011 Sherman Rd North Hollywood CA 91605",
    "addr:housenumber":"12011",
    "addr:postcode":"91605",
    "addr:street":"Sherman Rd",
    "iso:country":"US",
    "sg:address":"12011 Sherman Rd",
    "sg:city":"North Hollywood",
    "sg:classifiers":[
        {
            "category":"Manufacturing",
            "subcategory":"Printing",
            "type":"Manufacturing & Wholesale Goods"
        }
    ],
    "sg:phone":"+1 818 765 4550",
    "sg:postcode":"91605",
    "sg:province":"CA",
    "sg:tags":[
        "commercial"
    ],
    "wof:name":"Chatsworth Collections",
    "wof:placetype":"venue"
},
  "geometry": {"coordinates":[-118.392478,34.202044],"type":"Point"}
}