{
  "type": "Feature",
  "properties": {
    "addr:full":"20005 Piedra Dr Tehachapi CA 93561",
    "addr:postcode":"20005;93561",
    "addr:street":"Piedra Dr",
    "iso:country":"US",
    "sg:address":"20005 Piedra Dr",
    "sg:city":"Tehachapi",
    "sg:classifiers":[
        {
            "category":"Building & Trades",
            "subcategory":"Construction",
            "type":"Services"
        }
    ],
    "sg:phone":"+1 661 822 3332",
    "sg:postcode":"93561",
    "sg:province":"CA",
    "sg:tags":[
        "contractor"
    ],
    "wof:name":"Sid Davis Construction",
    "wof:placetype":"venue"
},
  "geometry": {"coordinates":[-118.486279,35.137386],"type":"Point"}
}