{
  "type": "Feature",
  "properties": {
    "iso:country":"US",
    "sg:address":"1738 Parker Polich Ct",
    "sg:city":"Tracy",
    "sg:classifiers":[
        {
            "category":"Wholesale",
            "subcategory":"Machinery & Supplies",
            "type":"Manufacturing & Wholesale Goods"
        }
    ],
    "sg:phone":"+1 209 832 1228",
    "sg:postcode":"95376",
    "sg:province":"CA",
    "sg:tags":[
        "salon",
        "beauty"
    ],
    "wof:name":"Advantage Distribution Group",
    "wof:placetype":"venue"
},
  "geometry": {"coordinates":[-121.447828,37.722475],"type":"Point"}
}