{
  "type": "Feature",
  "properties": {
    "iso:country":"US",
    "sg:address":"2377 E Colorado Blvd",
    "sg:city":"Pasadena",
    "sg:classifiers":[
        {
            "category":"Fast Food",
            "type":"Food & Drink"
        },
        {
            "category":"Food & Beverages",
            "subcategory":"Bakery",
            "type":"Retail Goods"
        }
    ],
    "sg:phone":"+1 626 796 3002",
    "sg:postcode":"91107",
    "sg:province":"CA",
    "sg:tags":[
        "sandwich"
    ],
    "sg:website":"www.subway.com",
    "wof:name":"Subway",
    "wof:placetype":"venue"
},
  "geometry": {"coordinates":[-118.100998,34.146198],"type":"Point"}
}