{
  "type": "Feature",
  "properties": {
    "addr:full":"124 E Santa Clara St San Jose CA 95113",
    "addr:housenumber":"124",
    "addr:postcode":"95113",
    "addr:street":"E Santa Clara St",
    "iso:country":"US",
    "sg:address":"124 E Santa Clara St",
    "sg:city":"San Jose",
    "sg:classifiers":[
        {
            "category":"Banks & Credit Unions",
            "subcategory":"Bank",
            "type":"Services"
        }
    ],
    "sg:phone":"+1 408 279 2101",
    "sg:postcode":"95113",
    "sg:province":"CA",
    "sg:tags":[
        "money",
        "transfer"
    ],
    "wof:name":"Western Union",
    "wof:placetype":"venue"
},
  "geometry": {"coordinates":[-121.887811,37.337365],"type":"Point"}
}