{
  "type": "Feature",
  "properties": {
    "addr:full":"100 View St Mountain View CA 94041",
    "addr:housenumber":"100",
    "addr:postcode":"94041",
    "addr:street":"View St",
    "iso:country":"US",
    "sg:address":"100 View St",
    "sg:city":"Mountain View",
    "sg:classifiers":[
        {
            "category":"Professional",
            "subcategory":"Computer Services",
            "type":"Services"
        }
    ],
    "sg:phone":"+1 650 625 9831",
    "sg:postcode":"94041",
    "sg:province":"CA",
    "sg:tags":[
        "consultant",
        "designer"
    ],
    "wof:name":"Jasper Design Automation",
    "wof:placetype":"venue"
},
  "geometry": {"coordinates":[-122.076352,37.393467],"type":"Point"}
}