{
  "type": "Feature",
  "properties": {
    "iso:country":"US",
    "sg:address":"1620 Easter Pl",
    "sg:city":"Escondido",
    "sg:classifiers":[
        {
            "category":"Real Estate",
            "subcategory":"Real Estate Agent",
            "type":"Services"
        }
    ],
    "sg:phone":"+1 760 745 4198",
    "sg:postcode":"92029",
    "sg:province":"CA",
    "sg:tags":[
        "business"
    ],
    "wof:name":"Allgaier & Assoc",
    "wof:placetype":"venue"
},
  "geometry": {"coordinates":[-117.1013,33.101218],"type":"Point"}
}