{
  "type": "Feature",
  "properties": {
    "addr:full":"2450 20th Ave San Francisco CA 94116",
    "addr:housenumber":"2450",
    "addr:postcode":"94116",
    "addr:street":"20Th Ave",
    "iso:country":"US",
    "sg:address":"2450 20th Ave",
    "sg:city":"San Francisco",
    "sg:classifiers":[
        {
            "category":"Manufacturing",
            "subcategory":"Printing",
            "type":"Manufacturing & Wholesale Goods"
        }
    ],
    "sg:phone":"+1 415 242 0463",
    "sg:postcode":"94116",
    "sg:province":"CA",
    "sg:tags":[
        "book"
    ],
    "wof:name":"Delta Credit Resources",
    "wof:placetype":"venue"
},
  "geometry": {"coordinates":[-122.47660999999999,37.742094],"type":"Point"}
}