{
  "type": "Feature",
  "properties": {
    "iso:country":"US",
    "sg:address":"573 Rambleton Dr",
    "sg:city":"Vacaville",
    "sg:classifiers":[
        {
            "category":"Shopping",
            "subcategory":"Used Merchandise",
            "type":"Retail Goods"
        }
    ],
    "sg:phone":"+1 707 451 7642",
    "sg:postcode":"95688",
    "sg:province":"CA",
    "sg:tags":[
        "business"
    ],
    "wof:name":"Jean Schweizer Appraiser",
    "wof:placetype":"venue"
},
  "geometry": {"coordinates":[-121.985857,38.384731],"type":"Point"}
}