{
  "type": "Feature",
  "properties": {
    "addr:full":"9332 Royal Palm Blvd Garden Grove CA 92841",
    "addr:housenumber":"9332",
    "addr:postcode":"92841",
    "addr:street":"Royal Palm Blvd",
    "iso:country":"US",
    "sg:address":"9332 Royal Palm Blvd",
    "sg:city":"Garden Grove",
    "sg:classifiers":[
        {
            "category":"Real Estate",
            "subcategory":"Real Estate Agent",
            "type":"Services"
        }
    ],
    "sg:phone":"+1 714 373 1415",
    "sg:postcode":"92841",
    "sg:province":"CA",
    "wof:name":"Sure",
    "wof:placetype":"venue"
},
  "geometry": {"coordinates":[-117.970204,33.79438],"type":"Point"}
}