{
  "type": "Feature",
  "properties": {
    "addr:full":"23347 San Fernando Rd Newhall CA 91321",
    "addr:housenumber":"23347",
    "addr:postcode":"91321",
    "addr:street":"San Fernando Rd",
    "iso:country":"US",
    "sg:address":"23347 San Fernando Rd",
    "sg:city":"Newhall",
    "sg:classifiers":[
        {
            "category":"Manufacturing",
            "subcategory":"Tools & Machinery",
            "type":"Manufacturing & Wholesale Goods"
        }
    ],
    "sg:phone":"+1 661 259 8891",
    "sg:postcode":"91321",
    "sg:province":"CA",
    "sg:tags":[
        "repair",
        "automotive",
        "instrument"
    ],
    "wof:name":"Redline Gauge Works",
    "wof:placetype":"venue"
},
  "geometry": {"coordinates":[-118.50714000000001,34.362752],"type":"Point"}
}