{
  "type": "Feature",
  "properties": {
    "addr:full":"231 Riverside Rd Watsonville CA 95076",
    "addr:housenumber":"231",
    "addr:postcode":"95076",
    "addr:street":"Riverside Rd",
    "iso:country":"US",
    "sg:address":"231 Riverside Rd",
    "sg:city":"Watsonville",
    "sg:classifiers":[
        {
            "category":"Professional",
            "subcategory":"Business Services",
            "type":"Services"
        }
    ],
    "sg:phone":"+1 831 724 6072",
    "sg:postcode":"95076",
    "sg:province":"CA",
    "sg:tags":[
        "specializing",
        "food",
        "wei"
    ],
    "wof:name":"Walker Street Scales",
    "wof:placetype":"venue"
},
  "geometry": {"coordinates":[-121.733637,36.916252],"type":"Point"}
}