{
  "type": "Feature",
  "properties": {
    "addr:full":"336 W Main St Merced CA 95340",
    "addr:housenumber":"336",
    "addr:postcode":"95340",
    "addr:street":"W Main St",
    "iso:country":"US",
    "sg:address":"336 W Main St",
    "sg:city":"Merced",
    "sg:classifiers":[
        {
            "category":"Retail",
            "subcategory":"Repair Shop",
            "type":"Services"
        }
    ],
    "sg:phone":"+1 209 725 0505",
    "sg:postcode":"95340",
    "sg:province":"CA",
    "sg:tags":[
        "upholsterer"
    ],
    "wof:name":"Main Street Upholstery",
    "wof:placetype":"venue"
},
  "geometry": {"coordinates":[-120.48090999999999,37.300514],"type":"Point"}
}