{
  "type": "Feature",
  "properties": {
    "addr:full":"9363 19th St Alta Loma CA 91701",
    "addr:housenumber":"9363",
    "addr:postcode":"91701",
    "addr:street":"19Th St",
    "iso:country":"US",
    "sg:address":"9363 19th St",
    "sg:city":"Alta Loma",
    "sg:classifiers":[
        {
            "category":"Building & Trades",
            "subcategory":"Plumbing",
            "type":"Services"
        }
    ],
    "sg:phone":"+1 909 945 0566",
    "sg:postcode":"91701",
    "sg:province":"CA",
    "sg:tags":[
        "conditioning",
        "air",
        "system",
        "contractor"
    ],
    "wof:name":"Ron's Refrigeration",
    "wof:placetype":"venue"
},
  "geometry": {"coordinates":[-117.60183600000001,34.132616],"type":"Point"}
}