{
  "type": "Feature",
  "properties": {
    "addr:full":"22600 Lambert Street Suite 1001 Lake Forest CA 92630",
    "addr:housenumber":"22600",
    "addr:postcode":"92630",
    "addr:street":"Lambert Street Suite 1001",
    "iso:country":"US",
    "sg:address":"22600 Lambert Street Suite 1001",
    "sg:city":"Lake Forest",
    "sg:classifiers":[
        {
            "category":"Shopping",
            "subcategory":"Music",
            "type":"Retail Goods"
        }
    ],
    "sg:phone":"+1 949 597 8941",
    "sg:postcode":"92630",
    "sg:province":"CA",
    "sg:tags":[
        "dvd's"
    ],
    "wof:name":"Active Technology",
    "wof:placetype":"venue"
},
  "geometry": {"coordinates":[-117.714705,33.63427],"type":"Point"}
}