{
  "type": "Feature",
  "properties": {
    "iso:country":"US",
    "sg:address":"470 S Bedford Dr",
    "sg:city":"Beverly Hills",
    "sg:classifiers":[
        {
            "category":"Real Estate",
            "subcategory":"Real Estate Agent",
            "type":"Services"
        }
    ],
    "sg:phone":"+1 310 552 3105",
    "sg:postcode":"90212",
    "sg:province":"CA",
    "wof:name":"Mike Bignucolo & Assoc",
    "wof:placetype":"venue"
},
  "geometry": {"coordinates":[-118.404451,34.059045],"type":"Point"}
}