{
  "type": "Feature",
  "properties": {
    "iso:country":"US",
    "sg:address":"7633 Southfront Rd",
    "sg:city":"Livermore",
    "sg:classifiers":[
        {
            "category":"Professional",
            "type":"Services"
        },
        {
            "category":"Deli",
            "type":"Food & Drink"
        },
        {
            "category":"Restaurant",
            "type":"Food & Drink"
        },
        {
            "category":"Coffee & Tea",
            "type":"Food & Drink"
        }
    ],
    "sg:phone":"+1 925 960 0636",
    "sg:postcode":"94551",
    "sg:province":"CA",
    "sg:tags":[
        "delicatessen",
        "espresso",
        "caterer"
    ],
    "wof:name":"Olive Tree Cafe & Catering",
    "wof:placetype":"venue"
},
  "geometry": {"coordinates":[-121.70283999999999,37.715331],"type":"Point"}
}