{
  "type": "Feature",
  "properties": {
    "addr:full":"7121 Canoga Ave Canoga Park CA 91308",
    "addr:housenumber":"7121",
    "addr:postcode":"91308",
    "addr:street":"Canoga Ave",
    "iso:country":"US",
    "sg:address":"7121 Canoga Ave",
    "sg:city":"Canoga Park",
    "sg:classifiers":[
        {
            "category":"Retail",
            "subcategory":"Auto Repair",
            "type":"Services"
        }
    ],
    "sg:phone":"+1 800 801 8582",
    "sg:postcode":"91308",
    "sg:province":"CA",
    "sg:website":"www.123tool.com",
    "wof:name":"Exclusive German Auto",
    "wof:placetype":"venue"
},
  "geometry": {"coordinates":[-118.59775,34.199836],"type":"Point"}
}