{
  "type": "Feature",
  "properties": {
    "iso:country":"US",
    "sg:address":"303 West Joaquin Ave Suite 110",
    "sg:city":"San Leandro",
    "sg:classifiers":[
        {
            "category":"Government",
            "subcategory":"City Hall",
            "type":"Public Place"
        }
    ],
    "sg:phone":"+1 510 618 1580",
    "sg:postcode":"94577",
    "sg:province":"CA",
    "sg:website":"www.eastbayinnovations.com",
    "wof:name":"East Bay Innovations",
    "wof:placetype":"venue"
},
  "geometry": {"coordinates":[-122.157096,37.723369],"type":"Point"}
}