{
  "type": "Feature",
  "properties": {
    "addr:full":"23272 Mill Creek Drive Laguna Hills CA 92653",
    "addr:housenumber":"23272",
    "addr:postcode":"92653",
    "addr:street":"Mill Creek Drive",
    "iso:country":"US",
    "sg:address":"23272 Mill Creek Drive",
    "sg:city":"Laguna Hills",
    "sg:classifiers":[
        {
            "category":"Professional",
            "subcategory":"Accounting & Tax Preparation",
            "type":"Services"
        }
    ],
    "sg:phone":"+1 949 598 2300",
    "sg:postcode":"92653",
    "sg:province":"CA",
    "sg:tags":[
        "accountant"
    ],
    "wof:name":"Triggs William A CPA",
    "wof:placetype":"venue"
},
  "geometry": {"coordinates":[-117.73615100000001,33.624602],"type":"Point"}
}