{
  "type": "Feature",
  "properties": {
    "addr:full":"5150 Candlewood St Ste 3 Lakewood CA 90712",
    "addr:housenumber":"5150",
    "addr:postcode":"90712",
    "addr:street":"Candlewood St Ste 3",
    "iso:country":"US",
    "sg:address":"5150 Candlewood St Ste 3",
    "sg:city":"Lakewood",
    "sg:classifiers":[
        {
            "category":"Real Estate",
            "subcategory":"Real Estate Services",
            "type":"Services"
        },
        {
            "category":"Real Estate",
            "subcategory":"Real Estate Agent",
            "type":"Services"
        }
    ],
    "sg:phone":"+1 562 804 4747",
    "sg:postcode":"90712",
    "sg:province":"CA",
    "sg:tags":[
        "buyer",
        "management",
        "broker"
    ],
    "wof:name":"The Alonzo Group",
    "wof:placetype":"venue"
},
  "geometry": {"coordinates":[-118.132999,33.853655],"type":"Point"}
}