{
  "type": "Feature",
  "properties": {
    "iso:country":"US",
    "sg:address":"4445 Granite Dr",
    "sg:city":"Rocklin",
    "sg:classifiers":[
        {
            "category":"Wholesale",
            "subcategory":"Auto Parts",
            "type":"Manufacturing & Wholesale Goods"
        }
    ],
    "sg:phone":"+1 916 625 9355",
    "sg:postcode":"95677",
    "sg:province":"CA",
    "sg:tags":[
        "supply"
    ],
    "wof:name":"Central 4 Wheel Drive",
    "wof:placetype":"venue"
},
  "geometry": {"coordinates":[-121.21821,38.794551],"type":"Point"}
}