{
  "type": "Feature",
  "properties": {
    "addr:full":"2147 Princeton Way Redding CA 96003",
    "addr:housenumber":"2147",
    "addr:postcode":"96003",
    "addr:street":"Princeton Way",
    "iso:country":"US",
    "sg:address":"2147 Princeton Way",
    "sg:city":"Redding",
    "sg:classifiers":[
        {
            "category":"Shopping",
            "subcategory":"Clothing, Apparel, & Fashions",
            "type":"Retail Goods"
        }
    ],
    "sg:phone":"+1 530 953 8199",
    "sg:postcode":"96003",
    "sg:province":"CA",
    "sg:tags":[
        "infant",
        "wear"
    ],
    "wof:name":"Baby Bits",
    "wof:placetype":"venue"
},
  "geometry": {"coordinates":[-122.331417,40.609955],"type":"Point"}
}