{
  "type": "Feature",
  "properties": {
    "iso:country":"US",
    "sg:address":"3723 W Magnolia Blvd",
    "sg:city":"Burbank",
    "sg:classifiers":[
        {
            "category":"Retail",
            "subcategory":"Laundry & Dry Cleaning",
            "type":"Services"
        }
    ],
    "sg:phone":"+1 818 845 5769",
    "sg:postcode":"91505",
    "sg:province":"CA",
    "wof:name":"Aviva Cleaners",
    "wof:placetype":"venue"
},
  "geometry": {"coordinates":[-118.34699999999999,34.167599],"type":"Point"}
}