{
  "type": "Feature",
  "properties": {
    "iso:country":"US",
    "sg:address":"3199 A-3 Airport Loop Drive",
    "sg:city":"Costa Mesa",
    "sg:classifiers":[
        {
            "category":"Communications",
            "type":"Services"
        }
    ],
    "sg:postcode":"92707",
    "sg:province":"CA",
    "sg:tags":[
        "medium",
        "mass"
    ],
    "sg:website":"www.innovatemedia.com",
    "wof:name":"Innovate Media",
    "wof:placetype":"venue"
},
  "geometry": {"coordinates":[-117.866688,33.685708],"type":"Point"}
}