{
  "type": "Feature",
  "properties": {
    "addr:full":"2290 del Monte Dr San Pablo CA 94806",
    "addr:housenumber":"2290",
    "addr:postcode":"94806",
    "addr:street":"Del Monte Dr",
    "iso:country":"US",
    "sg:address":"2290 del Monte Dr",
    "sg:city":"San Pablo",
    "sg:classifiers":[
        {
            "category":"Building & Trades",
            "subcategory":"Landscaping Services",
            "type":"Services"
        }
    ],
    "sg:phone":"+1 510 724 8595",
    "sg:postcode":"94806",
    "sg:province":"CA",
    "sg:tags":[
        "landscape"
    ],
    "wof:name":"T&T Landscaping",
    "wof:placetype":"venue"
},
  "geometry": {"coordinates":[-122.315758,38.008056],"type":"Point"}
}