{
  "type": "Feature",
  "properties": {
    "iso:country":"US",
    "sg:address":"2786 Martin Luther King Jr Way",
    "sg:city":"Oakland",
    "sg:classifiers":[
        {
            "category":"Restaurant",
            "type":"Food & Drink"
        }
    ],
    "sg:phone":"+1 510 251 1175",
    "sg:postcode":"94612",
    "sg:province":"CA",
    "sg:tags":[
        "traditional",
        "american"
    ],
    "wof:name":"BZ Cafe and Grill",
    "wof:placetype":"venue"
},
  "geometry": {"coordinates":[-122.271203,37.818011],"type":"Point"}
}