{
  "type": "Feature",
  "properties": {
    "addr:full":"9432 Bellanca Avenue Los Angeles CA 90045",
    "addr:housenumber":"9432",
    "addr:postcode":"90045",
    "addr:street":"Bellanca Avenue",
    "iso:country":"US",
    "sg:address":"9432 Bellanca Avenue",
    "sg:city":"Los Angeles",
    "sg:classifiers":[
        {
            "category":"Wholesale",
            "subcategory":"Fruits & Vegetables",
            "type":"Manufacturing & Wholesale Goods"
        }
    ],
    "sg:phone":"+1 310 216 7575",
    "sg:postcode":"90045",
    "sg:province":"CA",
    "sg:tags":[
        "veggie"
    ],
    "sg:website":"www.gourmettrading.net",
    "wof:name":"Nzg Gourmet Trading",
    "wof:placetype":"venue"
},
  "geometry": {"coordinates":[-118.37981499999999,33.950725],"type":"Point"}
}