{
  "type": "Feature",
  "properties": {
    "iso:country":"US",
    "sg:address":"76 San Pablo Ave",
    "sg:city":"San Rafael",
    "sg:classifiers":[
        {
            "category":"Banks & Credit Unions",
            "subcategory":"Investment Brokerage",
            "type":"Services"
        }
    ],
    "sg:phone":"+1 415 256 2400",
    "sg:postcode":"94903",
    "sg:province":"CA",
    "sg:tags":[
        "consultant",
        "financing"
    ],
    "sg:website":"www.rochoncap.com",
    "wof:name":"Rochon Capital Group",
    "wof:placetype":"venue"
},
  "geometry": {"coordinates":[-122.527829,37.995719],"type":"Point"}
}