{
  "type": "Feature",
  "properties": {
    "iso:country":"US",
    "sfac:artist":"Bufano, Beniamino",
    "sfac:created_at":"01/01/1970 12:32:15 AM +0000",
    "sfac:credit_line":"WPA",
    "sfac:display_dimensions":"36\" (L) x 36\" (H)",
    "sfac:location_description":"Public Display : District 6 : Valencia Gardens",
    "sfac:medium":"Granite",
    "sfac:revision":"2-99bb20f1aec903f665e3f7173a548f93",
    "sfac:title":"Butterfly",
    "wof:name":"Butterfly",
    "wof:placetype":"venue"
},
  "geometry": {"coordinates":[-122.4233043,37.7665965],"type":"Point"}
}