{
  "type": "Feature",
  "properties": {
    "addr:full":"12038 Ventura Blvd Studio City CA 91604",
    "addr:housenumber":"12038",
    "addr:postcode":"91604",
    "addr:street":"Ventura Blvd",
    "iso:country":"US",
    "sg:address":"12038 Ventura Blvd",
    "sg:city":"Studio City",
    "sg:classifiers":[
        {
            "category":"Shopping",
            "subcategory":"Bicycles & Sporting Goods",
            "type":"Retail Goods"
        }
    ],
    "sg:phone":"+1 818 752 9123",
    "sg:postcode":"91604",
    "sg:province":"CA",
    "wof:name":"Play It Again Sports",
    "wof:placetype":"venue"
},
  "geometry": {"coordinates":[-118.393997,34.143799],"type":"Point"}
}