{
  "type": "Feature",
  "properties": {
    "iso:country":"US",
    "sg:address":"218 E Grand Ave",
    "sg:city":"Escondido",
    "sg:classifiers":[
        {
            "category":"Real Estate",
            "subcategory":"Real Estate Agent",
            "type":"Services"
        }
    ],
    "sg:phone":"+1 760 741 1776",
    "sg:postcode":"92025",
    "sg:province":"CA",
    "wof:name":"1776 Realty",
    "wof:placetype":"venue"
},
  "geometry": {"coordinates":[-117.078999,33.122969],"type":"Point"}
}