{
  "type": "Feature",
  "properties": {
    "addr:full":"40811 Grimmer Blvd Fremont CA 94538",
    "addr:postcode":"40811;94538",
    "addr:street":"Grimmer Blvd",
    "iso:country":"US",
    "sg:address":"40811 Grimmer Blvd",
    "sg:city":"Fremont",
    "sg:classifiers":[
        {
            "category":"Personal",
            "subcategory":"Beauty Salon",
            "type":"Services"
        },
        {
            "category":"Personal",
            "subcategory":"Hair Removal",
            "type":"Services"
        },
        {
            "category":"Personal",
            "subcategory":"Skin Care",
            "type":"Services"
        },
        {
            "category":"Personal",
            "subcategory":"Tanning Parlor",
            "type":"Services"
        }
    ],
    "sg:phone":"+1 510 440 1333",
    "sg:postcode":"94538",
    "sg:province":"CA",
    "sg:tags":[
        "body",
        "wrap",
        "stylist"
    ],
    "sg:website":"http://www.levisagesalon.com",
    "wof:name":"Le Visage Salon",
    "wof:placetype":"venue"
},
  "geometry": {"coordinates":[-121.96801499999999,37.53336],"type":"Point"}
}