{
  "type": "Feature",
  "properties": {
    "iso:country":"US",
    "sg:address":"2007 Jensen Ave",
    "sg:city":"Sanger",
    "sg:classifiers":[
        {
            "category":"Professional",
            "subcategory":"Business Services",
            "type":"Services"
        }
    ],
    "sg:phone":"+1 559 875 7568",
    "sg:postcode":"93657",
    "sg:province":"CA",
    "sg:tags":[
        "process",
        "server"
    ],
    "wof:name":"E C Process Server",
    "wof:placetype":"venue"
},
  "geometry": {"coordinates":[-119.566571,36.706713],"type":"Point"}
}