{
  "type": "Feature",
  "properties": {
    "addr:full":"455 Grant Ave Palo Alto CA 94306",
    "addr:housenumber":"455",
    "addr:postcode":"94306",
    "addr:street":"Grant Ave",
    "iso:country":"US",
    "sg:address":"455 Grant Ave",
    "sg:city":"Palo Alto",
    "sg:classifiers":[
        {
            "category":"Personal",
            "subcategory":"Beauty Salon",
            "type":"Services"
        }
    ],
    "sg:phone":"+1 650 328 6444",
    "sg:postcode":"94306",
    "sg:province":"CA",
    "wof:name":"Esther",
    "wof:placetype":"venue"
},
  "geometry": {"coordinates":[-122.143252,37.424847],"type":"Point"}
}