{
  "type": "Feature",
  "properties": {
    "addr:full":"3291 Skypark Dr Torrance CA 90505",
    "addr:housenumber":"3291",
    "addr:postcode":"90505",
    "addr:street":"Skypark Dr",
    "iso:country":"US",
    "sg:address":"3291 Skypark Dr",
    "sg:city":"Torrance",
    "sg:classifiers":[
        {
            "category":"Health Services",
            "subcategory":"Doctor",
            "type":"Services"
        }
    ],
    "sg:phone":"+1 310 325 4517",
    "sg:postcode":"90505",
    "sg:province":"CA",
    "wof:name":"Parsa K Peter MD",
    "wof:placetype":"venue"
},
  "geometry": {"coordinates":[-118.345001,33.808899],"type":"Point"}
}