{
  "type": "Feature",
  "properties": {
    "addr:full":"1409 28th Street Sacramento CA 95816",
    "addr:housenumber":"1409",
    "addr:postcode":"95816",
    "addr:street":"28Th Street",
    "iso:country":"US",
    "sg:address":"1409 28th Street",
    "sg:city":"Sacramento",
    "sg:classifiers":[
        {
            "category":"Health Services",
            "subcategory":"Doctor",
            "type":"Services"
        }
    ],
    "sg:phone":"+1 916 451 5294",
    "sg:postcode":"95816",
    "sg:province":"CA",
    "wof:name":"Wenokur Bruce DO Mph",
    "wof:placetype":"venue"
},
  "geometry": {"coordinates":[-121.471267,38.56906],"type":"Point"}
}