{
  "type": "Feature",
  "properties": {
    "addr:full":"1604 Montecito Rd Ramona CA 92065",
    "addr:housenumber":"1604",
    "addr:postcode":"92065",
    "addr:street":"Montecito Rd",
    "iso:country":"US",
    "sg:address":"1604 Montecito Rd",
    "sg:city":"Ramona",
    "sg:classifiers":[
        {
            "category":"Building & Trades",
            "subcategory":"Electrical",
            "type":"Services"
        }
    ],
    "sg:phone":"+1 760 789 9357",
    "sg:postcode":"92065",
    "sg:province":"CA",
    "sg:tags":[
        "electrician"
    ],
    "wof:name":"Steve Gow Electric",
    "wof:placetype":"venue"
},
  "geometry": {"coordinates":[-116.879648,33.040292],"type":"Point"}
}