{
  "type": "Feature",
  "properties": {
    "addr:full":"6226 Industrial Way Livermore CA 94551",
    "addr:housenumber":"6226",
    "addr:postcode":"94551",
    "addr:street":"Industrial Way",
    "iso:country":"US",
    "sg:address":"6226 Industrial Way",
    "sg:city":"Livermore",
    "sg:classifiers":[
        {
            "category":"Building & Trades",
            "subcategory":"Plumbing",
            "type":"Services"
        }
    ],
    "sg:phone":"+1 925 371 0220",
    "sg:postcode":"94551",
    "sg:province":"CA",
    "sg:tags":[
        "sheet",
        "work",
        "metal",
        "contractor"
    ],
    "sg:website":"www.ronnunes.com",
    "wof:name":"Ron Nunes Enterprises",
    "wof:placetype":"venue"
},
  "geometry": {"coordinates":[-121.72168600000001,37.704875],"type":"Point"}
}