{
  "type": "Feature",
  "properties": {
    "iso:country":"US",
    "sg:address":"1101 Molino Ave",
    "sg:city":"Long Beach",
    "sg:classifiers":[
        {
            "category":"Organizations",
            "subcategory":"Non-profit Organization",
            "type":"Services"
        }
    ],
    "sg:phone":"+1 562 434 9089",
    "sg:postcode":"90804",
    "sg:province":"CA",
    "sg:tags":[
        "social"
    ],
    "wof:name":"Artability Artists",
    "wof:placetype":"venue"
},
  "geometry": {"coordinates":[-118.161115,33.782598],"type":"Point"}
}