{
  "type": "Feature",
  "properties": {
    "addr:full":"640 S Broadway Los Angeles CA 90014",
    "addr:housenumber":"640",
    "addr:postcode":"90014",
    "addr:street":"S Broadway",
    "iso:country":"US",
    "sg:address":"640 S Broadway",
    "sg:city":"Los Angeles",
    "sg:classifiers":[
        {
            "category":"Shopping",
            "subcategory":"Jewelry",
            "type":"Retail Goods"
        }
    ],
    "sg:phone":"+1 213 896 9225",
    "sg:postcode":"90014",
    "sg:province":"CA",
    "sg:tags":[
        "jeweler"
    ],
    "wof:name":"Lupita's Jewelry",
    "wof:placetype":"venue"
},
  "geometry": {"coordinates":[-118.25285599999999,34.045753],"type":"Point"}
}