{
  "type": "Feature",
  "properties": {
    "addr:full":"12925 Riverside Dr. Suite 200 Sherman Oaks CA 91423",
    "addr:housenumber":"12925",
    "addr:postcode":"91423",
    "addr:street":"Riverside Dr. Suite 200",
    "iso:country":"US",
    "sg:address":"12925 Riverside Dr. Suite 200",
    "sg:city":"Sherman Oaks",
    "sg:classifiers":[
        {
            "category":"Professional",
            "subcategory":"Computer Services",
            "type":"Services"
        }
    ],
    "sg:phone":"+1 949 254 9280",
    "sg:postcode":"91423",
    "sg:province":"CA",
    "sg:tags":[
        "social-media",
        "consumer-generated-media",
        "social-web",
        "live-monitoring",
        "business-intelligence",
        "web-analytics",
        "predictive-analytics"
    ],
    "sg:website":"http://www.wisewindow.com",
    "wof:name":"WiseWindow",
    "wof:placetype":"venue"
},
  "geometry": {"coordinates":[-118.41409299999999,34.157688],"type":"Point"}
}