{
  "type": "Feature",
  "properties": {
    "addr:full":"200 Rossi Ave Antioch CA 94509",
    "addr:housenumber":"200",
    "addr:postcode":"ca 94509",
    "addr:street":"Rossi Ave",
    "iso:country":"US",
    "sg:address":"200 Rossi Ave",
    "sg:city":"Antioch",
    "sg:classifiers":[
        {
            "category":"Building & Trades",
            "subcategory":"Pest Control",
            "type":"Services"
        },
        {
            "category":"Building & Trades",
            "subcategory":"Construction",
            "type":"Services"
        }
    ],
    "sg:phone":"+1 925 778 9711",
    "sg:postcode":"94509",
    "sg:province":"CA",
    "sg:tags":[
        "repair",
        "damage",
        "structural"
    ],
    "wof:name":"We Kill Termite Control Co",
    "wof:placetype":"venue"
},
  "geometry": {"coordinates":[-121.809105,38.00031],"type":"Point"}
}