{
  "type": "Feature",
  "properties": {
    "iso:country":"US",
    "sg:address":"202 Fern St",
    "sg:city":"Newport Beach",
    "sg:classifiers":[
        {
            "category":"Building & Trades",
            "subcategory":"Construction",
            "type":"Services"
        }
    ],
    "sg:phone":"+1 714 505 2946",
    "sg:postcode":"92663",
    "sg:province":"CA",
    "sg:tags":[
        "concrete",
        "contractor"
    ],
    "wof:name":"Grout Savers",
    "wof:placetype":"venue"
},
  "geometry": {"coordinates":[-117.95231,33.629295],"type":"Point"}
}