{
  "type": "Feature",
  "properties": {
    "addr:full":"400 Main St El Segundo CA 90245",
    "addr:housenumber":"400",
    "addr:postcode":"90245",
    "addr:street":"Main St",
    "iso:country":"US",
    "sg:address":"400 Main St",
    "sg:city":"El Segundo",
    "sg:classifiers":[
        {
            "category":"Restaurant",
            "type":"Food & Drink"
        }
    ],
    "sg:phone":"+1 310 322 2666",
    "sg:postcode":"90245",
    "sg:province":"CA",
    "sg:tags":[
        "pizza"
    ],
    "wof:name":"Stuft-Pizza",
    "wof:placetype":"venue"
},
  "geometry": {"coordinates":[-118.416,33.921001],"type":"Point"}
}