{
  "type": "Feature",
  "properties": {
    "addr:full":"1061 Sonoma Blvd Vallejo CA 94590",
    "addr:housenumber":"1061",
    "addr:postcode":"94590",
    "addr:street":"Sonoma Blvd",
    "iso:country":"US",
    "sg:address":"1061 Sonoma Blvd",
    "sg:city":"Vallejo",
    "sg:classifiers":[
        {
            "category":"Building & Trades",
            "subcategory":"Construction",
            "type":"Services"
        }
    ],
    "sg:phone":"+1 707 645 8480",
    "sg:postcode":"94590",
    "sg:province":"CA",
    "sg:tags":[
        "paving",
        "contractor"
    ],
    "wof:name":"NRA Construction Inc",
    "wof:placetype":"venue"
},
  "geometry": {"coordinates":[-122.249709,38.09335],"type":"Point"}
}