{
  "type": "Feature",
  "properties": {
    "addr:full":"1420 C St Eureka CA 95501",
    "addr:housenumber":"1420",
    "addr:postcode":"95501",
    "addr:street":"C St",
    "iso:country":"US",
    "sg:address":"1420 C St",
    "sg:city":"Eureka",
    "sg:classifiers":[
        {
            "category":"Travel",
            "subcategory":"Hotels & Motels",
            "type":"Entertainment"
        }
    ],
    "sg:phone":"+1 707 444 1310",
    "sg:postcode":"95501",
    "sg:province":"CA",
    "sg:tags":[
        "breakfast",
        "accommodation",
        "bed"
    ],
    "sg:website":"www.halcyoninn.com",
    "wof:name":"A Halcyon Inn",
    "wof:placetype":"venue"
},
  "geometry": {"coordinates":[-124.16860699999999,40.793695],"type":"Point"}
}