{
  "type": "Feature",
  "properties": {
    "addr:full":"2543 Luciernaga St Carlsbad CA 92009",
    "addr:housenumber":"2543",
    "addr:postcode":"92009",
    "addr:street":"Luciernaga St",
    "iso:country":"US",
    "sg:address":"2543 Luciernaga St",
    "sg:city":"Carlsbad",
    "sg:classifiers":[
        {
            "category":"Shopping",
            "subcategory":"Pets & Pet Supplies",
            "type":"Retail Goods"
        },
        {
            "category":"Retail",
            "subcategory":"Pet Boarding",
            "type":"Services"
        }
    ],
    "sg:phone":"+1 760 703 3050",
    "sg:postcode":"92009",
    "sg:province":"CA",
    "sg:tags":[
        "walker",
        "dog",
        "boarding/pet",
        "sitting"
    ],
    "sg:website":"lacostapetsitters.com",
    "wof:name":"La Costa Petsitters",
    "wof:placetype":"venue"
},
  "geometry": {"coordinates":[-117.24952,33.103869],"type":"Point"}
}