{
  "type": "Feature",
  "properties": {
    "iso:country":"US",
    "sg:address":"7260 San Ramon Rd",
    "sg:city":"Dublin",
    "sg:classifiers":[
        {
            "category":"Home & Garden",
            "subcategory":"Home Furnishings",
            "type":"Retail Goods"
        }
    ],
    "sg:phone":"+1 925 355 0500",
    "sg:postcode":"94568",
    "sg:province":"CA",
    "sg:tags":[
        "pottery"
    ],
    "wof:name":"Napa Valley Pottery & Floral",
    "wof:placetype":"venue"
},
  "geometry": {"coordinates":[-121.935947,37.702358],"type":"Point"}
}