{
  "type": "Feature",
  "properties": {
    "addr:full":"4622 College Ave San Diego CA 92115",
    "addr:housenumber":"4622",
    "addr:postcode":"92115",
    "addr:street":"College Ave",
    "iso:country":"US",
    "sg:address":"4622 College Ave",
    "sg:city":"San Diego",
    "sg:classifiers":[
        {
            "category":"Autos & Motor Vehicles",
            "subcategory":"Automobile Sales",
            "type":"Retail Goods"
        }
    ],
    "sg:phone":"+1 619 567 5817",
    "sg:postcode":"92115",
    "sg:province":"CA",
    "sg:tags":[
        "limo"
    ],
    "sg:website":"www.sandiegocalimo.com/",
    "wof:name":"All Time Limo Services, LLC",
    "wof:placetype":"venue"
},
  "geometry": {"coordinates":[-117.067252,32.762008],"type":"Point"}
}