{
  "type": "Feature",
  "properties": {
    "addr:full":"4317 Wincanton Rd Salida CA 95368",
    "addr:postcode":"4317;95368",
    "addr:street":"Wincanton Rd",
    "iso:country":"US",
    "sg:address":"4317 Wincanton Rd",
    "sg:city":"Salida",
    "sg:classifiers":[
        {
            "category":"Shopping",
            "subcategory":"Hobbies, Toys, & Games",
            "type":"Retail Goods"
        }
    ],
    "sg:phone":"+1 209 545 8616",
    "sg:postcode":"95368",
    "sg:province":"CA",
    "sg:tags":[
        "craft"
    ],
    "wof:name":"Unique Creations By Pam",
    "wof:placetype":"venue"
},
  "geometry": {"coordinates":[-121.07526799999999,37.699568],"type":"Point"}
}