{
  "type": "Feature",
  "properties": {
    "iso:country":"US",
    "sg:address":"4105 E Broadway",
    "sg:city":"Long Beach",
    "sg:classifiers":[
        {
            "category":"Insurance",
            "subcategory":"Insurance Agent",
            "type":"Services"
        }
    ],
    "sg:phone":"+1 562 438 2135",
    "sg:postcode":"90803",
    "sg:province":"CA",
    "wof:name":"CIMS Insurance",
    "wof:placetype":"venue"
},
  "geometry": {"coordinates":[-118.143754,33.764516],"type":"Point"}
}