{
  "type": "Feature",
  "properties": {
    "iso:country":"US",
    "sg:address":"2775 Cottage Way Ste 17",
    "sg:city":"Sacramento",
    "sg:classifiers":[
        {
            "category":"Professional",
            "subcategory":"Lawyer & Legal Services",
            "type":"Services"
        }
    ],
    "sg:phone":"+1 916 922 6693",
    "sg:postcode":"95825",
    "sg:province":"CA",
    "wof:name":"Law Office Of Arturo Benavidez",
    "wof:placetype":"venue"
},
  "geometry": {"coordinates":[-121.397954,38.603554],"type":"Point"}
}