{
  "type": "Feature",
  "properties": {
    "addr:full":"1180 N Indian Canyon Dr Ste 210 Palm Springs CA 92262",
    "addr:housenumber":"1180",
    "addr:postcode":"92262",
    "addr:street":"N Indian Canyon Dr Ste 210",
    "iso:country":"US",
    "sg:address":"1180 N Indian Canyon Dr Ste 210",
    "sg:city":"Palm Springs",
    "sg:classifiers":[
        {
            "category":"Health Services",
            "subcategory":"Doctor",
            "type":"Services"
        }
    ],
    "sg:phone":"+1 760 323 2225",
    "sg:postcode":"92262",
    "sg:province":"CA",
    "wof:name":"Mahapatra Ava MD",
    "wof:placetype":"venue"
},
  "geometry": {"coordinates":[-116.545998,33.8395],"type":"Point"}
}