{
  "type": "Feature",
  "properties": {
    "addr:full":"7600 Auburn Blvd Citrus Heights CA 95610",
    "addr:housenumber":"7600",
    "addr:postcode":"95610",
    "addr:street":"Auburn Blvd",
    "iso:country":"US",
    "sg:address":"7600 Auburn Blvd",
    "sg:city":"Citrus Heights",
    "sg:classifiers":[
        {
            "category":"Organizations",
            "subcategory":"Religious Organization",
            "type":"Services"
        }
    ],
    "sg:phone":"+1 916 726 3100",
    "sg:postcode":"95610",
    "sg:province":"CA",
    "sg:tags":[
        "church"
    ],
    "sg:website":"www.pioneerbaptist.com",
    "wof:name":"Pioneer Baptist Church",
    "wof:placetype":"venue"
},
  "geometry": {"coordinates":[-121.290396,38.705663],"type":"Point"}
}