{
  "type": "Feature",
  "properties": {
    "addr:full":"1401 Riverside Dr Susanville CA 96130",
    "addr:housenumber":"1401",
    "addr:postcode":"96130",
    "addr:street":"Riverside Dr",
    "iso:country":"US",
    "sg:address":"1401 Riverside Dr",
    "sg:city":"Susanville",
    "sg:classifiers":[
        {
            "category":"Organizations",
            "subcategory":"Religious Organization",
            "type":"Services"
        }
    ],
    "sg:phone":"+1 530 257 5195",
    "sg:postcode":"96130",
    "sg:province":"CA",
    "sg:tags":[
        "church"
    ],
    "wof:name":"Susanville Church-Nazarene",
    "wof:placetype":"venue"
},
  "geometry": {"coordinates":[-120.655344,40.413518],"type":"Point"}
}