{
  "type": "Feature",
  "properties": {
    "iso:country":"US",
    "sg:address":"503 N Fairfax Ave",
    "sg:city":"Los Angeles",
    "sg:classifiers":[
        {
            "category":"Shopping",
            "subcategory":"Shoes",
            "type":"Retail Goods"
        }
    ],
    "sg:phone":"+1 323 782 8616",
    "sg:postcode":"90036",
    "sg:province":"CA",
    "sg:tags":[
        "store"
    ],
    "sg:website":"www.flightclubla.com/",
    "wof:name":"Flight Club Los Angeles",
    "wof:placetype":"venue"
},
  "geometry": {"coordinates":[-118.361455,34.080512],"type":"Point"}
}