{
  "type": "Feature",
  "properties": {
    "iso:country":"US",
    "sg:address":"150 N Date St",
    "sg:city":"Escondido",
    "sg:classifiers":[
        {
            "category":"Professional",
            "subcategory":"Accounting & Tax Preparation",
            "type":"Services"
        }
    ],
    "sg:phone":"+1 760 746 4433",
    "sg:postcode":"92025",
    "sg:province":"CA",
    "sg:tags":[
        "accountant"
    ],
    "wof:name":"Howe & Howe",
    "wof:placetype":"venue"
},
  "geometry": {"coordinates":[-117.070382,33.126818],"type":"Point"}
}