{
  "type": "Feature",
  "properties": {
    "addr:full":"10076 Magnolia Ave Riverside CA 92503",
    "addr:housenumber":"10076",
    "addr:postcode":"92503",
    "addr:street":"Magnolia Ave",
    "iso:country":"US",
    "sg:address":"10076 Magnolia Ave",
    "sg:city":"Riverside",
    "sg:classifiers":[
        {
            "category":"Professional",
            "subcategory":"Lawyer & Legal Services",
            "type":"Services"
        }
    ],
    "sg:phone":"+1 951 352 9999",
    "sg:postcode":"92503",
    "sg:province":"CA",
    "sg:tags":[
        "naturalization",
        "immigration"
    ],
    "wof:name":"Latino Service",
    "wof:placetype":"venue"
},
  "geometry": {"coordinates":[-117.45731600000001,33.914157],"type":"Point"}
}