{
  "type": "Feature",
  "properties": {
    "addr:full":"171 Old Stage Rd Salinas CA 93908",
    "addr:housenumber":"171",
    "addr:postcode":"93908",
    "addr:street":"Old Stage Rd",
    "iso:country":"US",
    "sg:address":"171 Old Stage Rd",
    "sg:city":"Salinas",
    "sg:classifiers":[
        {
            "category":"Retail",
            "subcategory":"Animal Services",
            "type":"Services"
        }
    ],
    "sg:phone":"+1 831 442 2353",
    "sg:postcode":"93908",
    "sg:province":"CA",
    "wof:name":"Belmont Training Stables",
    "wof:placetype":"venue"
},
  "geometry": {"coordinates":[-121.569766,36.797939],"type":"Point"}
}