{
  "type": "Feature",
  "properties": {
    "addr:full":"2770 Vail Ave Los Angeles CA 90040",
    "addr:housenumber":"2770",
    "addr:postcode":"90040",
    "addr:street":"Vail Ave",
    "iso:country":"US",
    "sg:address":"2770 Vail Ave",
    "sg:city":"Los Angeles",
    "sg:classifiers":[
        {
            "category":"Freight",
            "type":"Transportation"
        },
        {
            "category":"Manufacturing",
            "subcategory":"Printing",
            "type":"Manufacturing & Wholesale Goods"
        }
    ],
    "sg:phone":"+1 323 778 0600",
    "sg:postcode":"90040",
    "sg:province":"CA",
    "sg:tags":[
        "delivery",
        "printer"
    ],
    "wof:name":"Ad Craft Business Mail",
    "wof:placetype":"venue"
},
  "geometry": {"coordinates":[-118.130663,33.991564],"type":"Point"}
}