{
  "type": "Feature",
  "properties": {
    "iso:country":"US",
    "sg:address":"460 Main St",
    "sg:city":"Placerville",
    "sg:classifiers":[
        {
            "category":"Shopping",
            "subcategory":"Clothing, Apparel, & Fashions",
            "type":"Retail Goods"
        },
        {
            "category":"Personal",
            "type":"Services"
        }
    ],
    "sg:phone":"+1 530 626 4865",
    "sg:postcode":"95667",
    "sg:province":"CA",
    "sg:tags":[
        "dressmaker",
        "tailor",
        "alterations-clothing"
    ],
    "wof:name":"Rose Alteration",
    "wof:placetype":"venue"
},
  "geometry": {"coordinates":[-120.80072699999999,38.729205],"type":"Point"}
}