{
  "type": "Feature",
  "properties": {
    "iso:country":"US",
    "sg:address":"1457 E Mission Blvd",
    "sg:city":"Pomona",
    "sg:classifiers":[
        {
            "category":"Building & Trades",
            "subcategory":"Construction",
            "type":"Services"
        }
    ],
    "sg:phone":"+1 909 629 6233",
    "sg:postcode":"91766",
    "sg:province":"CA",
    "sg:tags":[
        "excavating",
        "contractor"
    ],
    "wof:name":"Clark & Sons",
    "wof:placetype":"venue"
},
  "geometry": {"coordinates":[-117.72675099999999,34.055748],"type":"Point"}
}