{
  "type": "Feature",
  "properties": {
    "iso:country":"US",
    "sg:address":"1014 Cedar St",
    "sg:city":"Santa Cruz",
    "sg:classifiers":[
        {
            "category":"Shopping",
            "subcategory":"Books",
            "type":"Retail Goods"
        }
    ],
    "sg:phone":"+1 831 429 6636",
    "sg:postcode":"95060",
    "sg:province":"CA",
    "wof:name":"Herland Womens Book",
    "wof:placetype":"venue"
},
  "geometry": {"coordinates":[-122.027883,36.975708],"type":"Point"}
}