{
  "type": "Feature",
  "properties": {
    "addr:full":"12098 Oak Mill Dr Fort Jones CA 96032",
    "addr:housenumber":"12098",
    "addr:postcode":"96032",
    "addr:street":"Oak Mill Dr Fort Jones",
    "iso:country":"US",
    "sg:address":"12098 Oak Mill Dr",
    "sg:city":"Fort Jones",
    "sg:classifiers":[
        {
            "category":"Building & Trades",
            "subcategory":"Construction",
            "type":"Services"
        }
    ],
    "sg:phone":"+1 530 468 2307",
    "sg:postcode":"96032",
    "sg:province":"CA",
    "sg:tags":[
        "general",
        "contractor"
    ],
    "wof:name":"A1A Construction",
    "wof:placetype":"venue"
},
  "geometry": {"coordinates":[-122.842251,41.609792],"type":"Point"}
}