{
  "type": "Feature",
  "properties": {
    "iso:country":"US",
    "sg:address":"1450 Frazze Road",
    "sg:city":"San Diego",
    "sg:classifiers":[
        {
            "category":"Personal",
            "subcategory":"Beauty Salon",
            "type":"Services"
        }
    ],
    "sg:phone":"+1 619 630 5816",
    "sg:postcode":"92123",
    "sg:province":"CA",
    "sg:tags":[
        "hair"
    ],
    "sg:website":"www.pleasantexperiencehairstudio...",
    "wof:name":"Pleasant Experience Hair Studio",
    "wof:placetype":"venue"
},
  "geometry": {"coordinates":[-117.15926899999999,32.773326],"type":"Point"}
}