{
  "type": "Feature",
  "properties": {
    "addr:full":"930 W Washington Ave Escondido CA 92025",
    "addr:housenumber":"930",
    "addr:postcode":"92025",
    "addr:street":"W Washington Ave",
    "iso:country":"US",
    "sg:address":"930 W Washington Ave",
    "sg:city":"Escondido",
    "sg:classifiers":[
        {
            "category":"Professional",
            "subcategory":"Detective & Security Services",
            "type":"Services"
        }
    ],
    "sg:phone":"+1 760 737 0084",
    "sg:postcode":"92025",
    "sg:province":"CA",
    "sg:tags":[
        "information",
        "bureau"
    ],
    "wof:name":"German Import Auto Servic",
    "wof:placetype":"venue"
},
  "geometry": {"coordinates":[-117.096609,33.122999],"type":"Point"}
}