{
  "type": "Feature",
  "properties": {
    "addr:full":"5026 Brophy Dr Fremont CA 94536",
    "addr:housenumber":"5026",
    "addr:postcode":"94536",
    "addr:street":"Brophy Dr",
    "iso:country":"US",
    "sg:address":"5026 Brophy Dr",
    "sg:city":"Fremont",
    "sg:classifiers":[
        {
            "category":"Wholesale",
            "subcategory":"Apparel",
            "type":"Manufacturing & Wholesale Goods"
        }
    ],
    "sg:phone":"+1 510 797 4944",
    "sg:postcode":"94536",
    "sg:province":"CA",
    "sg:tags":[
        "piece"
    ],
    "wof:name":"Lj Galliett Design",
    "wof:placetype":"venue"
},
  "geometry": {"coordinates":[-122.00182599999999,37.536348],"type":"Point"}
}