{
  "type": "Feature",
  "properties": {
    "addr:full":"33133 Agua Dulce Canyon Rd Santa Clarita CA 91390",
    "addr:housenumber":"33133",
    "addr:postcode":"91390",
    "addr:street":"Agua Dulce Canyon Rd",
    "iso:country":"US",
    "sg:address":"33133 Agua Dulce Canyon Rd",
    "sg:city":"Santa Clarita",
    "sg:classifiers":[
        {
            "category":"Building & Trades",
            "subcategory":"Construction",
            "type":"Services"
        }
    ],
    "sg:phone":"+1 661 296 9334",
    "sg:postcode":"91390",
    "sg:province":"CA",
    "sg:tags":[
        "contractor"
    ],
    "wof:name":"Esther Pools Inc",
    "wof:placetype":"venue"
},
  "geometry": {"coordinates":[-118.326256,34.491248],"type":"Point"}
}