{
  "type": "Feature",
  "properties": {
    "addr:full":"150 E Cross Ave Tulare CA 93274",
    "addr:housenumber":"150",
    "addr:postcode":"93274",
    "addr:street":"E Cross Ave",
    "iso:country":"US",
    "sg:address":"150 E Cross Ave",
    "sg:city":"Tulare",
    "sg:classifiers":[
        {
            "category":"Restaurant",
            "type":"Food & Drink"
        }
    ],
    "sg:menulink":"http://www.allmenus.com/ca/tulare/75484-round-table-pizza/menu/",
    "sg:phone":"+1 559 686 2222",
    "sg:postcode":"93274",
    "sg:province":"CA",
    "sg:tags":[
        "american",
        "pizza"
    ],
    "wof:name":"Round Table Pizza",
    "wof:placetype":"venue"
},
  "geometry": {"coordinates":[-119.34806500000001,36.213133],"type":"Point"}
}