{
  "type": "Feature",
  "properties": {
    "iso:country":"US",
    "sg:address":"844 E Lancaster Blvd",
    "sg:city":"Lancaster",
    "sg:classifiers":[
        {
            "category":"Cinema",
            "subcategory":"Movie Theater",
            "type":"Entertainment"
        }
    ],
    "sg:phone":"+1 661 949 7800",
    "sg:postcode":"93535",
    "sg:province":"CA",
    "wof:name":"One Nation Cinemaworks",
    "wof:placetype":"venue"
},
  "geometry": {"coordinates":[-118.112954,34.696764],"type":"Point"}
}