{
  "type": "Feature",
  "properties": {
    "iso:country":"US",
    "sg:address":"12027 Paramount Blvd",
    "sg:city":"Downey",
    "sg:classifiers":[
        {
            "category":"Real Estate",
            "subcategory":"Real Estate Agent",
            "type":"Services"
        }
    ],
    "sg:phone":"+1 562 862 7373",
    "sg:postcode":"90242",
    "sg:province":"CA",
    "sg:website":"www.century21-prorealty.com",
    "wof:name":"Pro Realty",
    "wof:placetype":"venue"
},
  "geometry": {"coordinates":[-118.14606499999999,33.931808],"type":"Point"}
}