{
  "type": "Feature",
  "properties": {
    "iso:country":"US",
    "sg:address":"23565 Moulton Pkwy Ste A",
    "sg:city":"Laguna Hills",
    "sg:classifiers":[
        {
            "category":"Education",
            "subcategory":"Vocational School",
            "type":"Public Place"
        }
    ],
    "sg:phone":"+1 949 951 8883",
    "sg:postcode":"92653",
    "sg:province":"CA",
    "sg:tags":[
        "cosmetology"
    ],
    "sg:website":"www.lfbc4me.com",
    "wof:name":"Lake Forest Beauty College",
    "wof:placetype":"venue"
},
  "geometry": {"coordinates":[-117.731561,33.620858],"type":"Point"}
}