{
  "type": "Feature",
  "properties": {
    "iso:country":"US",
    "sg:address":"8919 Garvey Ave",
    "sg:city":"Rosemead",
    "sg:classifiers":[
        {
            "category":"Professional",
            "subcategory":"Business Services",
            "type":"Services"
        }
    ],
    "sg:phone":"+1 626 280 5509",
    "sg:postcode":"91770",
    "sg:province":"CA",
    "sg:tags":[
        "embroidery"
    ],
    "wof:name":"Golsen Stitch Co Inc",
    "wof:placetype":"venue"
},
  "geometry": {"coordinates":[-118.07559999999999,34.062674],"type":"Point"}
}