{
  "type": "Feature",
  "properties": {
    "addr:full":"153 Townsend Street San Francisco CA 94107",
    "addr:housenumber":"153",
    "addr:postcode":"94107",
    "addr:street":"Townsend Street",
    "iso:country":"US",
    "sg:address":"153 Townsend Street",
    "sg:city":"San Francisco",
    "sg:classifiers":[
        {
            "category":"Real Estate",
            "subcategory":"Architect",
            "type":"Services"
        }
    ],
    "sg:phone":"+1 415 247 9700",
    "sg:postcode":"94107",
    "sg:province":"CA",
    "wof:name":"Kling",
    "wof:placetype":"venue"
},
  "geometry": {"coordinates":[-122.391588,37.779746],"type":"Point"}
}