{
  "type": "Feature",
  "properties": {
    "iso:country":"US",
    "sg:address":"16345 Shady Bend",
    "sg:city":"Ramona",
    "sg:classifiers":[
        {
            "category":"Building & Trades",
            "subcategory":"Electrical",
            "type":"Services"
        }
    ],
    "sg:phone":"+1 760 789 8538",
    "sg:postcode":"92065",
    "sg:province":"CA",
    "sg:tags":[
        "electrical",
        "contractor"
    ],
    "wof:name":"West Coast Cabling Inc",
    "wof:placetype":"venue"
},
  "geometry": {"coordinates":[-116.941503,33.012414],"type":"Point"}
}