{
  "type": "Feature",
  "properties": {
    "iso:country":"US",
    "sg:address":"1 Airport Dr",
    "sg:city":"Oakland",
    "sg:classifiers":[
        {
            "category":"Restaurant",
            "type":"Food & Drink"
        }
    ],
    "sg:phone":"+1 510 567 9803",
    "sg:postcode":"94621",
    "sg:province":"CA",
    "sg:tags":[
        "shop",
        "coffee"
    ],
    "wof:name":"Island Expresso",
    "wof:placetype":"venue"
},
  "geometry": {"coordinates":[-122.200145,37.729542],"type":"Point"}
}