{
  "type": "Feature",
  "properties": {
    "iso:country":"US",
    "sg:address":"625 Glendora Ave",
    "sg:city":"La Puente",
    "sg:classifiers":[
        {
            "category":"Professional",
            "type":"Services"
        }
    ],
    "sg:phone":"+1 626 369 0060",
    "sg:postcode":"91744",
    "sg:province":"CA",
    "sg:tags":[
        "establishment"
    ],
    "wof:name":"Jugos Morelos",
    "wof:placetype":"venue"
},
  "geometry": {"coordinates":[-117.950733,34.029135],"type":"Point"}
}