{
  "type": "Feature",
  "properties": {
    "addr:full":"2251 90th Ave Oakland CA 94603",
    "addr:housenumber":"2251",
    "addr:postcode":"94603",
    "addr:street":"90Th Ave",
    "iso:country":"US",
    "sg:address":"2251 90th Ave",
    "sg:city":"Oakland",
    "sg:classifiers":[
        {
            "category":"Building & Trades",
            "subcategory":"Landscaping Services",
            "type":"Services"
        }
    ],
    "sg:phone":"+1 510 205 4897",
    "sg:postcode":"94603",
    "sg:province":"CA",
    "sg:tags":[
        "tree",
        "gardener"
    ],
    "wof:name":"Guerreros Tree and Gardening",
    "wof:placetype":"venue"
},
  "geometry": {"coordinates":[-122.164817,37.754348],"type":"Point"}
}