{
  "type": "Feature",
  "properties": {
    "iso:country":"US",
    "sg:address":"25091 Copa del Oro Dr",
    "sg:city":"Hayward",
    "sg:classifiers":[
        {
            "category":"Real Estate",
            "subcategory":"Real Estate Agent",
            "type":"Services"
        }
    ],
    "sg:phone":"+1 510 783 7353",
    "sg:postcode":"94545",
    "sg:province":"CA",
    "wof:name":"Phil Cal Realty",
    "wof:placetype":"venue"
},
  "geometry": {"coordinates":[-122.102193,37.643698],"type":"Point"}
}