{
  "type": "Feature",
  "properties": {
    "iso:country":"US",
    "sg:address":"8939 S Sepulveda Blvd",
    "sg:city":"Los Angeles",
    "sg:classifiers":[
        {
            "category":"Health Services",
            "subcategory":"Clinic",
            "type":"Services"
        }
    ],
    "sg:phone":"+1 310 337 7315",
    "sg:postcode":"90045",
    "sg:province":"CA",
    "sg:tags":[
        "medical"
    ],
    "sg:website":"www.robertgramlichmd.com/",
    "wof:name":"Gramlich Robert",
    "wof:placetype":"venue"
},
  "geometry": {"coordinates":[-118.396004,33.955399],"type":"Point"}
}