{
  "type": "Feature",
  "properties": {
    "addr:full":"220 Juana Ave San Leandro CA 94577",
    "addr:housenumber":"220",
    "addr:postcode":"94577",
    "addr:street":"Juana Ave",
    "iso:country":"US",
    "sg:address":"220 Juana Ave",
    "sg:city":"San Leandro",
    "sg:classifiers":[
        {
            "category":"Professional",
            "subcategory":"Lawyer & Legal Services",
            "type":"Services"
        }
    ],
    "sg:phone":"+1 510 357 4970",
    "sg:postcode":"94577",
    "sg:province":"CA",
    "wof:name":"Corbett Kevin M Attorney At Law",
    "wof:placetype":"venue"
},
  "geometry": {"coordinates":[-122.152,37.723801],"type":"Point"}
}