{
  "type": "Feature",
  "properties": {
    "iso:country":"US",
    "sg:address":"460 Barbera Ave",
    "sg:city":"Madera",
    "sg:classifiers":[
        {
            "category":"Retail",
            "subcategory":"Auto Repair",
            "type":"Services"
        }
    ],
    "sg:phone":"+1 559 674 1619",
    "sg:postcode":"93637",
    "sg:province":"CA",
    "sg:tags":[
        "truck"
    ],
    "wof:name":"Trigloff Mobile Truck Repair",
    "wof:placetype":"venue"
},
  "geometry": {"coordinates":[-120.094334,36.947476],"type":"Point"}
}