{
  "type": "Feature",
  "properties": {
    "addr:full":"1063 W 6th St Ste 105 Ontario CA 91762",
    "addr:housenumber":"1063",
    "addr:postcode":"91762",
    "addr:street":"W 6Th St Ste 105",
    "iso:country":"US",
    "sg:address":"1063 W 6th St Ste 105",
    "sg:city":"Ontario",
    "sg:classifiers":[
        {
            "category":"Banks & Credit Unions",
            "subcategory":"Financial Services",
            "type":"Services"
        }
    ],
    "sg:phone":"+1 909 395 5366",
    "sg:postcode":"91762",
    "sg:province":"CA",
    "sg:tags":[
        "escrow"
    ],
    "wof:name":"Castlehead Escrows",
    "wof:placetype":"venue"
},
  "geometry": {"coordinates":[-117.66938500000001,34.085132],"type":"Point"}
}