{
  "type": "Feature",
  "properties": {
    "addr:full":"4422 Glacier Ave San Diego CA 92120",
    "addr:housenumber":"4422",
    "addr:postcode":"92120",
    "addr:street":"Glacier Ave",
    "iso:country":"US",
    "sg:address":"4422 Glacier Ave",
    "sg:city":"San Diego",
    "sg:classifiers":[
        {
            "category":"Real Estate",
            "subcategory":"Architect",
            "type":"Services"
        }
    ],
    "sg:phone":"+1 619 528 2955",
    "sg:postcode":"92120",
    "sg:province":"CA",
    "wof:name":"Glanz Architectural Insprtns",
    "wof:placetype":"venue"
},
  "geometry": {"coordinates":[-117.09771499999999,32.788767],"type":"Point"}
}