{
  "type": "Feature",
  "properties": {
    "iso:country":"US",
    "sg:address":"2461 Santa Monica Blvd",
    "sg:city":"Santa Monica",
    "sg:classifiers":[
        {
            "category":"Professional",
            "subcategory":"Business Services",
            "type":"Services"
        }
    ],
    "sg:phone":"+1 310 315 1818",
    "sg:postcode":"90404",
    "sg:province":"CA",
    "sg:tags":[
        "box",
        "mail"
    ],
    "wof:name":"Mail In The Box",
    "wof:placetype":"venue"
},
  "geometry": {"coordinates":[-118.475863,34.032083],"type":"Point"}
}