{
  "type": "Feature",
  "properties": {
    "addr:full":"3801 Sacramento St 3rd Floor San Francisco CA 94118",
    "addr:housenumber":"3801;3rd",
    "addr:postcode":"94118",
    "addr:street":"Sacramento St;Floor",
    "iso:country":"US",
    "sg:address":"3801 Sacramento St 3rd Floor",
    "sg:city":"San Francisco",
    "sg:classifiers":[
        {
            "category":"Health Services",
            "subcategory":"Doctor",
            "type":"Services"
        }
    ],
    "sg:phone":"+1 415 600 2402",
    "sg:postcode":"94118",
    "sg:province":"CA",
    "sg:tags":[
        "medicine",
        "internal"
    ],
    "sg:website":"www.thedoctorforyou.com/",
    "wof:name":"Eugene Lee, MD",
    "wof:placetype":"venue"
},
  "geometry": {"coordinates":[-122.455448,37.786829],"type":"Point"}
}