{
  "type": "Feature",
  "properties": {
    "iso:country":"US",
    "sg:address":"650 N Commercial Rd",
    "sg:city":"Palm Springs",
    "sg:classifiers":[
        {
            "category":"Freight",
            "type":"Transportation"
        }
    ],
    "sg:phone":"+1 760 325 1762",
    "sg:postcode":"92262",
    "sg:province":"CA",
    "sg:tags":[
        "courier",
        "air"
    ],
    "wof:name":"UPS",
    "wof:placetype":"venue"
},
  "geometry": {"coordinates":[-116.516151,33.830856],"type":"Point"}
}