{
  "type": "Feature",
  "properties": {
    "iso:country":"US",
    "sg:address":"888 Mahler Rd",
    "sg:city":"Burlingame",
    "sg:classifiers":[
        {
            "category":"Wholesale",
            "subcategory":"Durable Goods & Equipment",
            "type":"Manufacturing & Wholesale Goods"
        }
    ],
    "sg:phone":"+1 650 692 5212",
    "sg:postcode":"94010",
    "sg:province":"CA",
    "sg:tags":[
        "importer"
    ],
    "wof:name":"Granite Art",
    "wof:placetype":"venue"
},
  "geometry": {"coordinates":[-122.366646,37.597767],"type":"Point"}
}