{
  "type": "Feature",
  "properties": {
    "addr:full":"635 N St Sanger CA 93657",
    "addr:housenumber":"635",
    "addr:postcode":"ca 93657",
    "addr:street":"N St",
    "iso:country":"US",
    "sg:address":"635 N St",
    "sg:city":"Sanger",
    "sg:classifiers":[
        {
            "category":"Professional",
            "subcategory":"Art Services",
            "type":"Services"
        }
    ],
    "sg:phone":"+1 559 225 8000",
    "sg:postcode":"93657",
    "sg:province":"CA",
    "sg:tags":[
        "photographer"
    ],
    "wof:name":"Curtis Aviation School",
    "wof:placetype":"venue"
},
  "geometry": {"coordinates":[-119.557462,36.706791],"type":"Point"}
}