{
  "type": "Feature",
  "properties": {
    "iso:country":"US",
    "sg:address":"5260 E 2nd St",
    "sg:city":"Long Beach",
    "sg:classifiers":[
        {
            "category":"Restaurant",
            "type":"Food & Drink"
        }
    ],
    "sg:phone":"+1 562 439 1950",
    "sg:postcode":"90803",
    "sg:province":"CA",
    "wof:name":"Sushi Saurus",
    "wof:placetype":"venue"
},
  "geometry": {"coordinates":[-118.13348000000001,33.759612],"type":"Point"}
}