{
  "type": "Feature",
  "properties": {
    "addr:full":"5751 Jeffries Ranch Rd Oceanside CA 92057",
    "addr:housenumber":"5751",
    "addr:postcode":"92057",
    "addr:street":"Jeffries Ranch Rd",
    "iso:country":"US",
    "sg:address":"5751 Jeffries Ranch Rd",
    "sg:city":"Oceanside",
    "sg:classifiers":[
        {
            "category":"Retail",
            "subcategory":"Auto Repair",
            "type":"Services"
        }
    ],
    "sg:phone":"+1 760 631 0510",
    "sg:postcode":"92057",
    "sg:province":"CA",
    "sg:tags":[
        "body",
        "painting",
        "repairing",
        "automobile"
    ],
    "wof:name":"The Ding Man",
    "wof:placetype":"venue"
},
  "geometry": {"coordinates":[-117.258944,33.252124],"type":"Point"}
}