{
  "type": "Feature",
  "properties": {
    "iso:country":"US",
    "sg:address":"23655 Via Del Rio",
    "sg:city":"Yorba Linda",
    "sg:classifiers":[
        {
            "category":"Education",
            "subcategory":"Special Training",
            "type":"Public Place"
        }
    ],
    "sg:phone":"+1 714 692 9508",
    "sg:postcode":"92887",
    "sg:province":"CA",
    "sg:tags":[
        "tutoring"
    ],
    "wof:name":"Kumon Center of East Yorba Linda",
    "wof:placetype":"venue"
},
  "geometry": {"coordinates":[-117.73763,33.882446],"type":"Point"}
}