{
  "type": "Feature",
  "properties": {
    "addr:full":"8018 Sunnybrae Ave Winnetka CA 91306",
    "addr:housenumber":"8018",
    "addr:postcode":"91306",
    "addr:street":"Sunnybrae Ave",
    "iso:country":"US",
    "sg:address":"8018 Sunnybrae Ave",
    "sg:city":"Winnetka",
    "sg:classifiers":[
        {
            "category":"Manufacturing",
            "subcategory":"Textiles",
            "type":"Manufacturing & Wholesale Goods"
        }
    ],
    "sg:phone":"+1 818 882 9222",
    "sg:postcode":"91306",
    "sg:province":"CA",
    "sg:tags":[
        "plant",
        "silk",
        "finishing",
        "fiber"
    ],
    "wof:name":"Springsteen Silks",
    "wof:placetype":"venue"
},
  "geometry": {"coordinates":[-118.58076699999999,34.218096],"type":"Point"}
}