{
  "type": "Feature",
  "properties": {
    "addr:full":"2736 W Orangethorpe Ave Fullerton CA 92833",
    "addr:housenumber":"2736",
    "addr:postcode":"92833",
    "addr:street":"W Orangethorpe Ave",
    "iso:country":"US",
    "sg:address":"2736 W Orangethorpe Ave",
    "sg:city":"Fullerton",
    "sg:classifiers":[
        {
            "category":"Wholesale",
            "subcategory":"Non-durable Goods",
            "type":"Manufacturing & Wholesale Goods"
        }
    ],
    "sg:phone":"+1 714 447 9255",
    "sg:postcode":"92833",
    "sg:province":"CA",
    "wof:name":"Qasem Imports & Exports",
    "wof:placetype":"venue"
},
  "geometry": {"coordinates":[-117.976418,33.859033],"type":"Point"}
}