{
  "type": "Feature",
  "properties": {
    "addr:full":"151 24th Ave San Francisco CA 94121",
    "addr:housenumber":"151",
    "addr:postcode":"94121",
    "addr:street":"24Th Ave",
    "iso:country":"US",
    "sg:address":"151 24th Ave",
    "sg:city":"San Francisco",
    "sg:classifiers":[
        {
            "category":"Manufacturing",
            "subcategory":"Printing",
            "type":"Manufacturing & Wholesale Goods"
        }
    ],
    "sg:phone":"+1 415 332 6427",
    "sg:postcode":"94121",
    "sg:province":"CA",
    "sg:tags":[
        "organization",
        "religious",
        "publishing"
    ],
    "wof:name":"Lightchild Publishing",
    "wof:placetype":"venue"
},
  "geometry": {"coordinates":[-122.48408000000001,37.785795],"type":"Point"}
}