{
  "type": "Feature",
  "properties": {
    "iso:country":"US",
    "sg:address":"5306 Lindbergh Ln",
    "sg:city":"Bell",
    "sg:classifiers":[
        {
            "category":"Freight",
            "type":"Transportation"
        }
    ],
    "sg:phone":"+1 323 261 9992",
    "sg:postcode":"90201",
    "sg:province":"CA",
    "wof:name":"Fast Freight Svc Inc",
    "wof:placetype":"venue"
},
  "geometry": {"coordinates":[-118.169284,33.994704],"type":"Point"}
}