{
  "type": "Feature",
  "properties": {
    "addr:full":"13535 Crenshaw Blvd Hawthorne CA 90250",
    "addr:housenumber":"13535",
    "addr:postcode":"90250",
    "addr:street":"Crenshaw Blvd",
    "iso:country":"US",
    "sg:address":"13535 Crenshaw Blvd",
    "sg:city":"Hawthorne",
    "sg:classifiers":[
        {
            "category":"Retail",
            "subcategory":"Car Wash",
            "type":"Services"
        }
    ],
    "sg:phone":"+1 310 810 6511",
    "sg:postcode":"90250",
    "sg:province":"CA",
    "sg:tags":[
        "automobile",
        "detail",
        "clean"
    ],
    "wof:name":"Galaxy Auto Detail",
    "wof:placetype":"venue"
},
  "geometry": {"coordinates":[-118.326509,33.906903],"type":"Point"}
}