{
  "type": "Feature",
  "properties": {
    "iso:country":"US",
    "sg:address":"3562 California Ave",
    "sg:city":"Long Beach",
    "sg:classifiers":[
        {
            "category":"Retail",
            "subcategory":"Repair Shop",
            "type":"Services"
        }
    ],
    "sg:phone":"+1 562 572 9980",
    "sg:postcode":"90807",
    "sg:province":"CA",
    "sg:tags":[
        "lock",
        "locksmith"
    ],
    "wof:name":"Van's Lock Shop",
    "wof:placetype":"venue"
},
  "geometry": {"coordinates":[-118.180591,33.82083],"type":"Point"}
}