{
  "type": "Feature",
  "properties": {
    "addr:full":"4755 Schaefer Ave Chino CA 91710",
    "addr:housenumber":"4755",
    "addr:postcode":"91710",
    "addr:street":"Schaefer Ave",
    "iso:country":"US",
    "sg:address":"4755 Schaefer Ave",
    "sg:city":"Chino",
    "sg:classifiers":[
        {
            "category":"Home & Garden",
            "subcategory":"Building Materials",
            "type":"Retail Goods"
        }
    ],
    "sg:phone":"+1 909 627 3354",
    "sg:postcode":"91710",
    "sg:province":"CA",
    "sg:tags":[
        "glass",
        "window",
        "plate"
    ],
    "wof:name":"Goodwine Glass",
    "wof:placetype":"venue"
},
  "geometry": {"coordinates":[-117.701122,34.004417],"type":"Point"}
}