{
  "type": "Feature",
  "properties": {
    "addr:full":"8003 Atlantic Ave Cudahy CA 90201",
    "addr:housenumber":"8003",
    "addr:postcode":"90201",
    "addr:street":"Atlantic Ave",
    "iso:country":"US",
    "sg:address":"8003 Atlantic Ave",
    "sg:city":"Cudahy",
    "sg:classifiers":[
        {
            "category":"Health Services",
            "subcategory":"Dentist",
            "type":"Services"
        }
    ],
    "sg:phone":"+1 323 560 6000",
    "sg:postcode":"90201",
    "sg:province":"CA",
    "wof:name":"Cudahy Family Dental Group",
    "wof:placetype":"venue"
},
  "geometry": {"coordinates":[-118.185997,33.961899],"type":"Point"}
}