{
  "type": "Feature",
  "properties": {
    "iso:country":"US",
    "sg:address":"331 W Main St",
    "sg:city":"El Centro",
    "sg:classifiers":[
        {
            "category":"Manufacturing",
            "subcategory":"Motor Vehicles & Parts",
            "type":"Manufacturing & Wholesale Goods"
        }
    ],
    "sg:phone":"+1 760 353 4024",
    "sg:postcode":"92243",
    "sg:province":"CA",
    "sg:tags":[
        "automobile",
        "supply"
    ],
    "wof:name":"High N Low Motorsports",
    "wof:placetype":"venue"
},
  "geometry": {"coordinates":[-115.550713,32.792839],"type":"Point"}
}