{
  "type": "Feature",
  "properties": {
    "iso:country":"US",
    "sg:address":"1000 Edwards Dr",
    "sg:city":"Turlock",
    "sg:classifiers":[
        {
            "category":"Freight",
            "type":"Transportation"
        }
    ],
    "sg:phone":"+1 209 632 3274",
    "sg:postcode":"95380",
    "sg:province":"CA",
    "sg:tags":[
        "operator",
        "local",
        "hauling",
        "trucking"
    ],
    "wof:name":"C & G Enterprise",
    "wof:placetype":"venue"
},
  "geometry": {"coordinates":[-120.829102,37.502097],"type":"Point"}
}