{
  "type": "Feature",
  "properties": {
    "iso:country":"US",
    "sg:address":"8349 Mira Mesa Blvd",
    "sg:city":"San Diego",
    "sg:classifiers":[
        {
            "category":"Restaurant",
            "type":"Food & Drink"
        }
    ],
    "sg:menulink":"http://www.allmenus.com/ca/san-diego/168810-el-pollo-loco/menu/",
    "sg:phone":"+1 858 578 7553",
    "sg:postcode":"92126",
    "sg:province":"CA",
    "sg:tags":[
        "american",
        "mexican",
        "tex-mex"
    ],
    "wof:name":"El Pollo Loco",
    "wof:placetype":"venue"
},
  "geometry": {"coordinates":[-117.144553,32.911741],"type":"Point"}
}