{
  "type": "Feature",
  "properties": {
    "iso:country":"US",
    "sg:address":"21371 Aqueduct Cir",
    "sg:city":"Pine Grove",
    "sg:classifiers":[
        {
            "category":"Building & Trades",
            "subcategory":"Landscaping Services",
            "type":"Services"
        }
    ],
    "sg:phone":"+1 209 296 6800",
    "sg:postcode":"95665",
    "sg:province":"CA",
    "sg:tags":[
        "construction"
    ],
    "wof:name":"Landscapes By Lundquist",
    "wof:placetype":"venue"
},
  "geometry": {"coordinates":[-120.631275,38.396551],"type":"Point"}
}