{
  "type": "Feature",
  "properties": {
    "iso:country":"US",
    "sg:address":"34 Dormody Ct",
    "sg:city":"Monterey",
    "sg:classifiers":[
        {
            "category":"Health Services",
            "subcategory":"Doctor",
            "type":"Services"
        }
    ],
    "sg:phone":"+1 831 656 9394",
    "sg:postcode":"93940",
    "sg:province":"CA",
    "sg:tags":[
        "dentist"
    ],
    "wof:name":"Curtis E Jansen DDS",
    "wof:placetype":"venue"
},
  "geometry": {"coordinates":[-121.896197,36.594384],"type":"Point"}
}