{
  "type": "Feature",
  "properties": {
    "addr:full":"11521 Blocker Dr Auburn CA 95603",
    "addr:housenumber":"11521",
    "addr:postcode":"ca 95603",
    "addr:street":"Blocker Dr",
    "iso:country":"US",
    "sg:address":"11521 Blocker Dr",
    "sg:city":"Auburn",
    "sg:classifiers":[
        {
            "category":"Building & Trades",
            "subcategory":"Construction",
            "type":"Services"
        }
    ],
    "sg:phone":"+1 530 885 8117",
    "sg:postcode":"95603",
    "sg:province":"CA",
    "sg:tags":[
        "management"
    ],
    "wof:name":"Dudek & Associates",
    "wof:placetype":"venue"
},
  "geometry": {"coordinates":[-121.08449400000001,38.901962],"type":"Point"}
}