{
  "type": "Feature",
  "properties": {
    "addr:full":"22414 Normandie Ave Torrance CA 90502",
    "addr:housenumber":"22414",
    "addr:postcode":"90502",
    "addr:street":"Normandie Ave",
    "iso:country":"US",
    "sg:address":"22414 Normandie Ave",
    "sg:city":"Torrance",
    "sg:classifiers":[
        {
            "category":"Recreation",
            "type":"Entertainment"
        }
    ],
    "sg:phone":"+1 310 533 6900",
    "sg:postcode":"90502",
    "sg:province":"CA",
    "sg:tags":[
        "scooter",
        "motorcycle",
        "motor"
    ],
    "wof:name":"Bandit Customs",
    "wof:placetype":"venue"
},
  "geometry": {"coordinates":[-118.299024,33.822433],"type":"Point"}
}