{
  "type": "Feature",
  "properties": {
    "addr:full":"7168 Via Romera San Jose CA 95139",
    "addr:housenumber":"7168",
    "addr:postcode":"95139",
    "addr:street":"Via Romera",
    "iso:country":"US",
    "sg:address":"7168 Via Romera",
    "sg:city":"San Jose",
    "sg:classifiers":[
        {
            "category":"Freight",
            "type":"Transportation"
        }
    ],
    "sg:phone":"+1 408 224 6927",
    "sg:postcode":"95139",
    "sg:province":"CA",
    "sg:tags":[
        "operator",
        "local",
        "trucking"
    ],
    "wof:name":"Juan Dominguez",
    "wof:placetype":"venue"
},
  "geometry": {"coordinates":[-121.76932600000001,37.228965],"type":"Point"}
}