{
  "type": "Feature",
  "properties": {
    "iso:country":"US",
    "sg:address":"2498 Pleasant Hill Rd",
    "sg:city":"Pleasant Hill",
    "sg:classifiers":[
        {
            "category":"Food & Beverages",
            "subcategory":"Fruits & Vegetables",
            "type":"Retail Goods"
        }
    ],
    "sg:phone":"+1 925 934 7262",
    "sg:postcode":"94523",
    "sg:province":"CA",
    "sg:tags":[
        "produce"
    ],
    "wof:name":"Mangini Fruit Stand",
    "wof:placetype":"venue"
},
  "geometry": {"coordinates":[-122.084892,37.952233],"type":"Point"}
}