{
  "type": "Feature",
  "properties": {
    "iso:country":"US",
    "sg:address":"545 S Murphy Ave",
    "sg:city":"Sunnyvale",
    "sg:classifiers":[
        {
            "category":"Wholesale",
            "subcategory":"Durable Goods & Equipment",
            "type":"Manufacturing & Wholesale Goods"
        }
    ],
    "sg:phone":"+1 408 202 7375",
    "sg:postcode":"94086",
    "sg:province":"CA",
    "sg:tags":[
        "room",
        "drafting"
    ],
    "wof:name":"Advanced Repro Supply",
    "wof:placetype":"venue"
},
  "geometry": {"coordinates":[-122.03268300000001,37.369469],"type":"Point"}
}