{
  "type": "Feature",
  "properties": {
    "iso:country":"US",
    "sg:address":"941 E 3rd St",
    "sg:city":"Los Angeles",
    "sg:classifiers":[
        {
            "category":"Wholesale",
            "subcategory":"Apparel",
            "type":"Manufacturing & Wholesale Goods"
        }
    ],
    "sg:phone":"+1 213 346 8270",
    "sg:postcode":"90013",
    "sg:province":"CA",
    "wof:name":"Shyan Inc",
    "wof:placetype":"venue"
},
  "geometry": {"coordinates":[-118.233456,34.046052],"type":"Point"}
}