{
  "type": "Feature",
  "properties": {
    "addr:full":"10514 1/2 Long Beach Blvd Lynwood CA 90262",
    "addr:housenumber":"10514 1 / 2",
    "addr:postcode":"90262",
    "addr:street":"Long Beach Blvd",
    "iso:country":"US",
    "sg:address":"10514 1/2 Long Beach Blvd",
    "sg:city":"Lynwood",
    "sg:classifiers":[
        {
            "category":"Building & Trades",
            "subcategory":"Construction",
            "type":"Services"
        }
    ],
    "sg:phone":"+1 323 566 2435",
    "sg:postcode":"90262",
    "sg:province":"CA",
    "sg:tags":[
        "contractor"
    ],
    "wof:name":"Diaz Construction",
    "wof:placetype":"venue"
},
  "geometry": {"coordinates":[-118.21366,33.938489],"type":"Point"}
}