{
  "type": "Feature",
  "properties": {
    "addr:full":"224 Anacapa St Santa Barbara CA 93101",
    "addr:housenumber":"224",
    "addr:postcode":"93101",
    "addr:street":"Anacapa St",
    "iso:country":"US",
    "sg:address":"224 Anacapa St",
    "sg:city":"Santa Barbara",
    "sg:classifiers":[
        {
            "category":"Recreation",
            "type":"Entertainment"
        }
    ],
    "sg:phone":"+1 805 564 8839",
    "sg:postcode":"93101",
    "sg:province":"CA",
    "sg:tags":[
        "psychic",
        "medium"
    ],
    "wof:name":"Synergy Of Avalon",
    "wof:placetype":"venue"
},
  "geometry": {"coordinates":[-119.69146499999999,34.415815],"type":"Point"}
}