{
  "type": "Feature",
  "properties": {
    "addr:full":"714 S Hill Street Suite 305 Los Angeles CA 90014",
    "addr:housenumber":"714",
    "addr:postcode":"90014",
    "addr:street":"S Hill Street Suite 305",
    "iso:country":"US",
    "sg:address":"714 S Hill Street Suite 305",
    "sg:city":"Los Angeles",
    "sg:classifiers":[
        {
            "category":"Shopping",
            "subcategory":"Jewelry",
            "type":"Retail Goods"
        }
    ],
    "sg:phone":"+1 213 489 6605",
    "sg:postcode":"90014",
    "sg:province":"CA",
    "wof:name":"Sadco Jewelry",
    "wof:placetype":"venue"
},
  "geometry": {"coordinates":[-118.254623,34.045702],"type":"Point"}
}