{
  "type": "Feature",
  "properties": {
    "iso:country":"US",
    "sg:address":"2321 Rosecrans Ave Ste 4250",
    "sg:city":"El Segundo",
    "sg:classifiers":[
        {
            "category":"Real Estate",
            "subcategory":"Real Estate Services",
            "type":"Services"
        }
    ],
    "sg:phone":"+1 310 725 9584",
    "sg:postcode":"90245",
    "sg:province":"CA",
    "sg:tags":[
        "management",
        "property"
    ],
    "wof:name":"Alcole Properties",
    "wof:placetype":"venue"
},
  "geometry": {"coordinates":[-118.381202,33.902096],"type":"Point"}
}