{
  "type": "Feature",
  "properties": {
    "iso:country":"US",
    "sg:address":"10811 Washington Boulevard",
    "sg:city":"Culver City",
    "sg:classifiers":[
        {
            "category":"Health Services",
            "subcategory":"Clinic",
            "type":"Services"
        }
    ],
    "sg:phone":"+1 310 876 4052",
    "sg:postcode":"90232",
    "sg:province":"CA",
    "sg:tags":[
        "counseling",
        "mental"
    ],
    "wof:name":"Rebecca J Danelski, LCSW",
    "wof:placetype":"venue"
},
  "geometry": {"coordinates":[-118.407658,34.015298],"type":"Point"}
}