{
  "type": "Feature",
  "properties": {
    "addr:full":"2345 Yale St Palo Alto CA 94306",
    "addr:housenumber":"2345",
    "addr:postcode":"94306",
    "addr:street":"Yale St",
    "iso:country":"US",
    "sg:address":"2345 Yale St",
    "sg:city":"Palo Alto",
    "sg:classifiers":[
        {
            "category":"Professional",
            "subcategory":"Computer Services",
            "type":"Services"
        }
    ],
    "sg:phone":"+1 650 855 0250",
    "sg:postcode":"94306",
    "sg:province":"CA",
    "sg:tags":[
        "consultant",
        "designer"
    ],
    "sg:website":"www.cooperinteractiondesign.com",
    "wof:name":"Cooper Interaction Design",
    "wof:placetype":"venue"
},
  "geometry": {"coordinates":[-122.146917,37.424429],"type":"Point"}
}