{
  "type": "Feature",
  "properties": {
    "addr:full":"400 Yacht St Wilmington CA 90744",
    "addr:housenumber":"400",
    "addr:postcode":"90744",
    "addr:street":"Yacht St",
    "iso:country":"US",
    "sg:address":"400 Yacht St",
    "sg:city":"Wilmington",
    "sg:classifiers":[
        {
            "category":"Government",
            "subcategory":"Fire Station",
            "type":"Public Place"
        }
    ],
    "sg:phone":"+1 310 548 7516",
    "sg:postcode":"90744",
    "sg:province":"CA",
    "sg:tags":[
        "protection"
    ],
    "wof:name":"Lacty Fire Battalion",
    "wof:placetype":"venue"
},
  "geometry": {"coordinates":[-118.257155,33.764895],"type":"Point"}
}