{
  "type": "Feature",
  "properties": {
    "addr:full":"4801 Feather River Blvd # 31 Oroville CA 95965",
    "addr:housenumber":"4801",
    "addr:postcode":"95965",
    "addr:street":"Feather River Blvd # 31",
    "iso:country":"US",
    "sg:address":"4801 Feather River Blvd # 31",
    "sg:city":"Oroville",
    "sg:classifiers":[
        {
            "category":"Autos & Motor Vehicles",
            "subcategory":"Boat Sales",
            "type":"Retail Goods"
        },
        {
            "category":"Manufacturing",
            "subcategory":"Watercraft",
            "type":"Manufacturing & Wholesale Goods"
        },
        {
            "category":"Marine",
            "type":"Transportation"
        }
    ],
    "sg:phone":"+1 530 532 4800",
    "sg:postcode":"95965",
    "sg:province":"CA",
    "sg:tags":[
        "distributor",
        "equipment",
        "builder",
        "manufacturer",
        "supply"
    ],
    "wof:name":"Campbell Craft",
    "wof:placetype":"venue"
},
  "geometry": {"coordinates":[-121.577011,39.46449],"type":"Point"}
}