{
  "type": "Feature",
  "properties": {
    "addr:full":"320 W Vernon Avenue Los Angeles CA 90037",
    "addr:housenumber":"320",
    "addr:postcode":"90037",
    "addr:street":"W Vernon Avenue",
    "iso:country":"US",
    "sg:address":"320 W Vernon Avenue",
    "sg:city":"Los Angeles",
    "sg:classifiers":[
        {
            "category":"Restaurant",
            "type":"Food & Drink"
        }
    ],
    "sg:phone":"+1 323 231 1728",
    "sg:postcode":"90037",
    "sg:province":"CA",
    "wof:name":"La Flor Blanca Restaurant",
    "wof:placetype":"venue"
},
  "geometry": {"coordinates":[-118.278603,34.003903],"type":"Point"}
}