{
  "type": "Feature",
  "properties": {
    "addr:full":"2408 Allen Rd Bakersfield CA 93314",
    "addr:housenumber":"2408",
    "addr:postcode":"93314",
    "addr:street":"Allen Rd",
    "iso:country":"US",
    "sg:address":"2408 Allen Rd",
    "sg:city":"Bakersfield",
    "sg:classifiers":[
        {
            "category":"Organizations",
            "subcategory":"Religious Organization",
            "type":"Services"
        }
    ],
    "sg:phone":"+1 661 589 9675",
    "sg:postcode":"93314",
    "sg:province":"CA",
    "sg:tags":[
        "church"
    ],
    "wof:name":"Joy Community Church",
    "wof:placetype":"venue"
},
  "geometry": {"coordinates":[-119.145448,35.380081],"type":"Point"}
}