{
  "type": "Feature",
  "properties": {
    "iso:country":"US",
    "sg:address":"18514 Centennial St",
    "sg:city":"Hesperia",
    "sg:classifiers":[
        {
            "category":"Travel",
            "subcategory":"Travel Agent",
            "type":"Entertainment"
        }
    ],
    "sg:phone":"+1 760 956 1784",
    "sg:postcode":"92345",
    "sg:province":"CA",
    "sg:tags":[
        "agency",
        "bureau"
    ],
    "wof:name":"Navigators",
    "wof:placetype":"venue"
},
  "geometry": {"coordinates":[-117.256977,34.40963],"type":"Point"}
}