{
  "type": "Feature",
  "properties": {
    "addr:full":"2435 Venice Dr E South Lake Tahoe CA 96150",
    "addr:housenumber":"2435",
    "addr:postcode":"96150",
    "addr:street":"Venice Dr E",
    "iso:country":"US",
    "sg:address":"2435 Venice Dr E",
    "sg:city":"South Lake Tahoe",
    "sg:classifiers":[
        {
            "category":"Professional",
            "type":"Services"
        }
    ],
    "sg:phone":"+1 530 541 1912",
    "sg:postcode":"96150",
    "sg:province":"CA",
    "sg:tags":[
        "establishment"
    ],
    "wof:name":"Hampson Roy C & Assoc Civil",
    "wof:placetype":"venue"
},
  "geometry": {"coordinates":[-120.003792,38.930222],"type":"Point"}
}