{
  "type": "Feature",
  "properties": {
    "addr:full":"268 N El Camino Real Encinitas CA 92024",
    "addr:housenumber":"268",
    "addr:postcode":"92024",
    "addr:street":"N El Camino Real",
    "iso:country":"US",
    "sg:address":"268 N El Camino Real",
    "sg:city":"Encinitas",
    "sg:classifiers":[
        {
            "category":"Restaurant",
            "type":"Food & Drink"
        }
    ],
    "sg:phone":"+1 760 635 3863",
    "sg:postcode":"92024",
    "sg:province":"CA",
    "sg:tags":[
        "mexican"
    ],
    "sg:website":"www.chipotle.com/",
    "wof:name":"Chipotle",
    "wof:placetype":"venue"
},
  "geometry": {"coordinates":[-117.261002,33.052799],"type":"Point"}
}