{
  "type": "Feature",
  "properties": {
    "iso:country":"US",
    "sg:address":"1667 Euclid Ave",
    "sg:city":"San Diego",
    "sg:classifiers":[
        {
            "category":"Personal",
            "subcategory":"Beauty Salon",
            "type":"Services"
        }
    ],
    "sg:phone":"+1 619 263 7209",
    "sg:postcode":"92105",
    "sg:province":"CA",
    "wof:name":"Ebony Beauty Salon",
    "wof:placetype":"venue"
},
  "geometry": {"coordinates":[-117.084867,32.723448],"type":"Point"}
}