{
  "type": "Feature",
  "properties": {
    "addr:full":"2231 Rutherford Rd Carlsbad CA 92008",
    "addr:housenumber":"2231",
    "addr:postcode":"92008",
    "addr:street":"Rutherford Rd",
    "iso:country":"US",
    "sg:address":"2231 Rutherford Rd",
    "sg:city":"Carlsbad",
    "sg:classifiers":[
        {
            "category":"Banks & Credit Unions",
            "subcategory":"Bank",
            "type":"Services"
        }
    ],
    "sg:phone":"+1 760 431 3464",
    "sg:postcode":"92008",
    "sg:province":"CA",
    "sg:tags":[
        "loan",
        "real estate"
    ],
    "wof:name":"Seattle Mortgage Co",
    "wof:placetype":"venue"
},
  "geometry": {"coordinates":[-117.279219,33.13167],"type":"Point"}
}