{
  "type": "Feature",
  "properties": {
    "addr:full":"9645 Alondra Blvd Bellflower CA 90706",
    "addr:housenumber":"9645",
    "addr:postcode":"90706",
    "addr:street":"Alondra Blvd",
    "iso:country":"US",
    "sg:address":"9645 Alondra Blvd",
    "sg:city":"Bellflower",
    "sg:classifiers":[
        {
            "category":"Restaurant",
            "type":"Food & Drink"
        }
    ],
    "sg:phone":"+1 562 866 8381",
    "sg:postcode":"90706",
    "sg:province":"CA",
    "sg:tags":[
        "mexican"
    ],
    "wof:name":"Alberts Mexican Food",
    "wof:placetype":"venue"
},
  "geometry": {"coordinates":[-118.128747,33.889597],"type":"Point"}
}