{
  "type": "Feature",
  "properties": {
    "addr:full":"1438 E Anaheim St Long Beach CA 90813",
    "addr:housenumber":"1438",
    "addr:postcode":"90813",
    "addr:street":"E Anaheim St",
    "iso:country":"US",
    "sg:address":"1438 E Anaheim St",
    "sg:city":"Long Beach",
    "sg:classifiers":[
        {
            "category":"Personal",
            "subcategory":"Beauty Salon",
            "type":"Services"
        }
    ],
    "sg:phone":"+1 562 599 7343",
    "sg:postcode":"90813",
    "sg:province":"CA",
    "wof:name":"Sala De Belleza LA Ruana",
    "wof:placetype":"venue"
},
  "geometry": {"coordinates":[-118.173148,33.782532],"type":"Point"}
}