{
  "type": "Feature",
  "properties": {
    "addr:full":"43645 Monterey Ave Ste D Palm Desert CA 92260",
    "addr:housenumber":"43645",
    "addr:postcode":"ca 92260",
    "addr:street":"Monterey Ave Ste D",
    "iso:country":"US",
    "sg:address":"43645 Monterey Ave Ste D",
    "sg:city":"Palm Desert",
    "sg:classifiers":[
        {
            "category":"Banks & Credit Unions",
            "subcategory":"Financial Services",
            "type":"Services"
        }
    ],
    "sg:phone":"+1 760 776 1661",
    "sg:postcode":"92260",
    "sg:province":"CA",
    "sg:tags":[
        "broker",
        "mortgage"
    ],
    "sg:website":"www.mmchomeloans.com",
    "wof:name":"Millennium Mortgage",
    "wof:placetype":"venue"
},
  "geometry": {"coordinates":[-116.39099899999999,33.731499],"type":"Point"}
}