{
  "type": "Feature",
  "properties": {
    "acgov:api":"0.0",
    "acgov:type":"9 to 12",
    "addr:full":"1530 34th Avenue Oakland CA",
    "wof:categories":[
        "education_and_religion:education=school"
    ],
    "wof:name":"Saint Elizabeth High",
    "wof:placetype":"venue"
},
  "geometry": {"coordinates":[-122.22257369826423,37.7788302565173],"type":"Point"}
}