{
  "type": "Feature",
  "properties": {
    "addr:full":"3098 N Ashford Ave Rialto CA 92377",
    "addr:housenumber":"3098",
    "addr:postcode":"92377",
    "addr:street":"N Ashford Ave",
    "iso:country":"US",
    "sg:address":"3098 N Ashford Ave",
    "sg:city":"Rialto",
    "sg:classifiers":[
        {
            "category":"Building & Trades",
            "subcategory":"Electrical",
            "type":"Services"
        }
    ],
    "sg:phone":"+1 909 822 3738",
    "sg:postcode":"92377",
    "sg:province":"CA",
    "sg:tags":[
        "electrician",
        "electric",
        "contractor"
    ],
    "wof:name":"Etcu Electric",
    "wof:placetype":"venue"
},
  "geometry": {"coordinates":[-117.40451,34.1558],"type":"Point"}
}