{
  "type": "Feature",
  "properties": {
    "addr:full":"42219 59th St W Lancaster CA 93536",
    "addr:housenumber":"42219",
    "addr:postcode":"93536",
    "addr:street":"59Th St W",
    "iso:country":"US",
    "sg:address":"42219 59th St W",
    "sg:city":"Lancaster",
    "sg:classifiers":[
        {
            "category":"Professional",
            "subcategory":"Management & Consulting",
            "type":"Services"
        }
    ],
    "sg:phone":"+1 661 722 5741",
    "sg:postcode":"93536",
    "sg:province":"CA",
    "sg:tags":[
        "business"
    ],
    "wof:name":"T M Wiley Consulting",
    "wof:placetype":"venue"
},
  "geometry": {"coordinates":[-118.2355,34.649858],"type":"Point"}
}