{
  "type": "Feature",
  "properties": {
    "iso:country":"US",
    "sg:address":"1045 College Ave",
    "sg:city":"Santa Rosa",
    "sg:classifiers":[
        {
            "category":"Real Estate",
            "subcategory":"Real Estate Agent",
            "type":"Services"
        }
    ],
    "sg:phone":"+1 707 522 6868",
    "sg:postcode":"95404",
    "sg:province":"CA",
    "wof:name":"Levy Martin & Assoc RE Ser",
    "wof:placetype":"venue"
},
  "geometry": {"coordinates":[-122.709182,38.445491],"type":"Point"}
}