{
  "type": "Feature",
  "properties": {
    "iso:country":"US",
    "sg:address":"912 76th Ave",
    "sg:city":"Oakland",
    "sg:classifiers":[
        {
            "category":"Retail",
            "subcategory":"Auto Repair",
            "type":"Services"
        }
    ],
    "sg:phone":"+1 510 639 0794",
    "sg:postcode":"94621",
    "sg:province":"CA",
    "sg:tags":[
        "body",
        "automobile",
        "painting"
    ],
    "wof:name":"J & M Auto Body Repair",
    "wof:placetype":"venue"
},
  "geometry": {"coordinates":[-122.191096,37.753983],"type":"Point"}
}