{
  "type": "Feature",
  "properties": {
    "iso:country":"US",
    "sg:address":"2500 Marconi Avenue Suite 200",
    "sg:city":"Sacramento",
    "sg:classifiers":[
        {
            "category":"Real Estate",
            "subcategory":"Real Estate Services",
            "type":"Services"
        },
        {
            "category":"Banks & Credit Unions",
            "subcategory":"Investment Brokerage",
            "type":"Services"
        },
        {
            "category":"Banks & Credit Unions",
            "subcategory":"Financial Services",
            "type":"Services"
        }
    ],
    "sg:phone":"+1 916 481 0546",
    "sg:postcode":"95821",
    "sg:province":"CA",
    "sg:tags":[
        "property",
        "management"
    ],
    "wof:name":"Canyon Investments",
    "wof:placetype":"venue"
},
  "geometry": {"coordinates":[-121.403308,38.618021],"type":"Point"}
}