{
  "type": "Feature",
  "properties": {
    "iso:country":"US",
    "sg:address":"5104 W Washington Blvd",
    "sg:city":"Los Angeles",
    "sg:classifiers":[
        {
            "category":"Retail",
            "subcategory":"Repair Shop",
            "type":"Services"
        }
    ],
    "sg:phone":"+1 323 931 1055",
    "sg:postcode":"90016",
    "sg:province":"CA",
    "sg:tags":[
        "refrigeration"
    ],
    "wof:name":"Cold Service",
    "wof:placetype":"venue"
},
  "geometry": {"coordinates":[-118.351646,34.040981],"type":"Point"}
}