{
  "type": "Feature",
  "properties": {
    "iso:country":"US",
    "sg:address":"2973 Shattuck Ave",
    "sg:city":"Berkeley",
    "sg:phone":"+1 510 845 3922",
    "sg:postcode":"94705",
    "sg:province":"CA",
    "wof:name":"Vogue Cleaners",
    "wof:placetype":"venue"
},
  "geometry": {"coordinates":[-122.266566,37.855666],"type":"Point"}
}