{
  "type": "Feature",
  "properties": {
    "addr:full":"1398 Industrial Park Ave Redlands CA 92374",
    "addr:housenumber":"1398",
    "addr:postcode":"92374",
    "addr:street":"Industrial Park Ave",
    "iso:country":"US",
    "sg:address":"1398 Industrial Park Ave",
    "sg:city":"Redlands",
    "sg:classifiers":[
        {
            "category":"Wholesale",
            "subcategory":"Apparel",
            "type":"Manufacturing & Wholesale Goods"
        }
    ],
    "sg:phone":"+1 909 307 8772",
    "sg:postcode":"92374",
    "sg:province":"CA",
    "wof:name":"Jeany's",
    "wof:placetype":"venue"
},
  "geometry": {"coordinates":[-117.203658,34.064462],"type":"Point"}
}