{
  "type": "Feature",
  "properties": {
    "iso:country":"US",
    "sg:address":"4203 Genesee Ave Ste 103",
    "sg:city":"San Diego",
    "sg:classifiers":[
        {
            "category":"Professional",
            "subcategory":"Lawyer & Legal Services",
            "type":"Services"
        }
    ],
    "sg:phone":"+1 858 541 1882",
    "sg:postcode":"92117",
    "sg:province":"CA",
    "sg:tags":[
        "notary"
    ],
    "wof:name":"Postal Annex",
    "wof:placetype":"venue"
},
  "geometry": {"coordinates":[-117.18188499999999,32.819489],"type":"Point"}
}