{
  "type": "Feature",
  "properties": {
    "iso:country":"US",
    "sg:address":"9591 Kiefer Blvd",
    "sg:city":"Sacramento",
    "sg:classifiers":[
        {
            "category":"Government",
            "subcategory":"Office",
            "type":"Public Place"
        }
    ],
    "sg:phone":"+1 916 875 5077",
    "sg:postcode":"95827",
    "sg:province":"CA",
    "wof:name":"Sacramento County Pub Defender",
    "wof:placetype":"venue"
},
  "geometry": {"coordinates":[-121.343346,38.545406],"type":"Point"}
}