{
  "type": "Feature",
  "properties": {
    "iso:country":"US",
    "sg:address":"10344 W Olympic Boulevard",
    "sg:city":"Los Angeles",
    "sg:classifiers":[
        {
            "category":"Government",
            "subcategory":"Office",
            "type":"Public Place"
        }
    ],
    "sg:phone":"+1 310 277 5388",
    "sg:postcode":"90064",
    "sg:province":"CA",
    "sg:tags":[
        "smog",
        "check"
    ],
    "wof:name":"Smog Smogs",
    "wof:placetype":"venue"
},
  "geometry": {"coordinates":[-118.417955,34.052115],"type":"Point"}
}