{
  "type": "Feature",
  "properties": {
    "iso:country":"US",
    "sg:address":"4316 Marina City Dr",
    "sg:city":"Marina Del Rey",
    "sg:classifiers":[
        {
            "category":"Professional",
            "type":"Services"
        }
    ],
    "sg:phone":"+1 310 277 4668",
    "sg:postcode":"90292",
    "sg:province":"CA",
    "wof:name":"Gene Kelly Foundation",
    "wof:placetype":"venue"
},
  "geometry": {"coordinates":[-118.453566,33.98465],"type":"Point"}
}