{
  "type": "Feature",
  "properties": {
    "addr:full":"26691 Plaza Ste 200 Mission Viejo CA 92691",
    "addr:housenumber":"26691",
    "addr:postcode":"92691",
    "addr:street":"Plaza Ste 200",
    "iso:country":"US",
    "sg:address":"26691 Plaza Ste 200",
    "sg:city":"Mission Viejo",
    "sg:classifiers":[
        {
            "category":"Professional",
            "subcategory":"Lawyer & Legal Services",
            "type":"Services"
        }
    ],
    "sg:phone":"+1 949 582 1544",
    "sg:postcode":"92691",
    "sg:province":"CA",
    "sg:tags":[
        "personal",
        "injury"
    ],
    "wof:name":"Mosher & Skorina",
    "wof:placetype":"venue"
},
  "geometry": {"coordinates":[-117.664001,33.565498],"type":"Point"}
}