{
  "type": "Feature",
  "properties": {
    "addr:full":"150 W Industrial Way Benicia CA 94510",
    "addr:housenumber":"150",
    "addr:postcode":"94510",
    "addr:street":"W Industrial Way",
    "iso:country":"US",
    "sg:address":"150 W Industrial Way",
    "sg:city":"Benicia",
    "sg:classifiers":[
        {
            "category":"Freight",
            "type":"Transportation"
        }
    ],
    "sg:phone":"+1 707 747 3200",
    "sg:postcode":"94510",
    "sg:province":"CA",
    "sg:tags":[
        "water"
    ],
    "wof:name":"Seariver Maritime Inc",
    "wof:placetype":"venue"
},
  "geometry": {"coordinates":[-122.136149,38.083338],"type":"Point"}
}