{
  "type": "Feature",
  "properties": {
    "addr:full":"233 el Camino Real Millbrae CA 94030",
    "addr:housenumber":"233",
    "addr:postcode":"94030",
    "addr:street":"El Camino Real",
    "iso:country":"US",
    "sg:address":"233 el Camino Real",
    "sg:city":"Millbrae",
    "sg:classifiers":[
        {
            "category":"Travel",
            "subcategory":"Travel Agent",
            "type":"Entertainment"
        }
    ],
    "sg:phone":"+1 415 982 0186",
    "sg:postcode":"94030",
    "sg:province":"CA",
    "sg:tags":[
        "cruise",
        "air"
    ],
    "sg:website":"www.ritztours.com",
    "wof:name":"Ritz Tours & Travel Inc",
    "wof:placetype":"venue"
},
  "geometry": {"coordinates":[-122.390056,37.600606],"type":"Point"}
}