{
  "type": "Feature",
  "properties": {
    "addr:full":"580 Harlan St San Leandro CA 94577",
    "addr:housenumber":"580",
    "addr:postcode":"94577",
    "addr:street":"Harlan St",
    "iso:country":"US",
    "sg:address":"580 Harlan St",
    "sg:city":"San Leandro",
    "sg:classifiers":[
        {
            "category":"Building & Trades",
            "subcategory":"Construction",
            "type":"Services"
        }
    ],
    "sg:phone":"+1 510 357 3274",
    "sg:postcode":"94577",
    "sg:province":"CA",
    "sg:tags":[
        "fence",
        "contractor"
    ],
    "wof:name":"J & R Fence Co",
    "wof:placetype":"venue"
},
  "geometry": {"coordinates":[-122.156148,37.717016],"type":"Point"}
}