{
  "type": "Feature",
  "properties": {
    "iso:country":"US",
    "sg:address":"9728 Magellan Dr",
    "sg:city":"Loomis",
    "sg:classifiers":[
        {
            "category":"Professional",
            "subcategory":"Computer Services",
            "type":"Services"
        }
    ],
    "sg:phone":"+1 916 652 8588",
    "sg:postcode":"95650",
    "sg:province":"CA",
    "sg:tags":[
        "consultant",
        "designer"
    ],
    "wof:name":"Intel Corp",
    "wof:placetype":"venue"
},
  "geometry": {"coordinates":[-121.116818,38.817408],"type":"Point"}
}