{
  "type": "Feature",
  "properties": {
    "iso:country":"US",
    "sg:address":"13212 Sherman Way",
    "sg:city":"North Hollywood",
    "sg:classifiers":[
        {
            "category":"Retail",
            "subcategory":"Auto Repair",
            "type":"Services"
        }
    ],
    "sg:phone":"+1 818 764 1195",
    "sg:postcode":"91605",
    "sg:province":"CA",
    "sg:tags":[
        "repairing",
        "automobile"
    ],
    "wof:name":"Peter's Automotive",
    "wof:placetype":"venue"
},
  "geometry": {"coordinates":[-118.419375,34.201118],"type":"Point"}
}