{
  "type": "Feature",
  "properties": {
    "addr:full":"6240 Hidden Valley Rd Fallbrook CA 92028",
    "addr:housenumber":"6240",
    "addr:postcode":"92028",
    "addr:street":"Hidden Valley Rd",
    "iso:country":"US",
    "sg:address":"6240 Hidden Valley Rd",
    "sg:city":"Fallbrook",
    "sg:classifiers":[
        {
            "category":"Professional",
            "subcategory":"Management & Consulting",
            "type":"Services"
        }
    ],
    "sg:phone":"+1 760 724 2044",
    "sg:postcode":"92028",
    "sg:province":"CA",
    "sg:tags":[
        "marketing",
        "consultant"
    ],
    "wof:name":"Hula Moons",
    "wof:placetype":"venue"
},
  "geometry": {"coordinates":[-117.27376,33.290143],"type":"Point"}
}