{
  "type": "Feature",
  "properties": {
    "iso:country":"US",
    "sg:address":"1022 E Cambridge Ave",
    "sg:city":"Fresno",
    "sg:classifiers":[
        {
            "category":"Professional",
            "subcategory":"Management & Consulting",
            "type":"Services"
        }
    ],
    "sg:phone":"+1 559 228 3518",
    "sg:postcode":"93704",
    "sg:province":"CA",
    "sg:tags":[
        "consultant",
        "security",
        "system"
    ],
    "wof:name":"Action Security Co",
    "wof:placetype":"venue"
},
  "geometry": {"coordinates":[-119.798512,36.769439],"type":"Point"}
}