{
  "type": "Feature",
  "properties": {
    "addr:full":"4143 Shook Rd Sebastopol CA 95472",
    "addr:housenumber":"4143",
    "addr:postcode":"95472",
    "addr:street":"Shook Rd",
    "iso:country":"US",
    "sg:address":"4143 Shook Rd",
    "sg:city":"Sebastopol",
    "sg:classifiers":[
        {
            "category":"Home & Garden",
            "subcategory":"Carpets & Floor Coverings",
            "type":"Retail Goods"
        }
    ],
    "sg:phone":"+1 707 478 9810",
    "sg:postcode":"95472",
    "sg:province":"CA",
    "sg:tags":[
        "distributor",
        "rug",
        "manufacturer"
    ],
    "wof:name":"Red Hot Carpet Care",
    "wof:placetype":"venue"
},
  "geometry": {"coordinates":[-122.871056,38.446404],"type":"Point"}
}