{
  "type": "Feature",
  "properties": {
    "iso:country":"US",
    "sg:address":"170 Coolwater Ln",
    "sg:city":"Barstow",
    "sg:classifiers":[
        {
            "category":"Travel",
            "subcategory":"Hotels & Motels",
            "type":"Entertainment"
        }
    ],
    "sg:phone":"+1 760 256 8443",
    "sg:postcode":"92311",
    "sg:province":"CA",
    "wof:name":"Super 8 Motel",
    "wof:placetype":"venue"
},
  "geometry": {"coordinates":[-117.003988,34.893858],"type":"Point"}
}