{
  "type": "Feature",
  "properties": {
    "addr:full":"6640 Sepulveda Blvd Van Nuys CA 91411",
    "addr:housenumber":"6640",
    "addr:postcode":"91411",
    "addr:street":"Sepulveda Blvd",
    "iso:country":"US",
    "sg:address":"6640 Sepulveda Blvd",
    "sg:city":"Van Nuys",
    "sg:classifiers":[
        {
            "category":"Real Estate",
            "subcategory":"Real Estate Operator",
            "type":"Services"
        }
    ],
    "sg:phone":"+1 818 785 2029",
    "sg:postcode":"91411",
    "sg:province":"CA",
    "sg:tags":[
        "apartment"
    ],
    "wof:name":"Estancia Apartments",
    "wof:placetype":"venue"
},
  "geometry": {"coordinates":[-118.466109,34.191362],"type":"Point"}
}