{
  "type": "Feature",
  "properties": {
    "iso:country":"US",
    "sg:address":"2830 Orbiter St",
    "sg:city":"Brea",
    "sg:classifiers":[
        {
            "category":"Manufacturing",
            "subcategory":"Printing",
            "type":"Manufacturing & Wholesale Goods"
        }
    ],
    "sg:phone":"+1 714 996 8900",
    "sg:postcode":"92821",
    "sg:province":"CA",
    "sg:tags":[
        "specializing",
        "publisher",
        "ad",
        "weekly"
    ],
    "wof:name":"Potpourri Shopper Inc",
    "wof:placetype":"venue"
},
  "geometry": {"coordinates":[-117.85925899999999,33.914274],"type":"Point"}
}