{
  "type": "Feature",
  "properties": {
    "iso:country":"US",
    "sg:address":"18 Richardson Rd",
    "sg:city":"Novato",
    "sg:classifiers":[
        {
            "category":"Professional",
            "subcategory":"Research",
            "type":"Services"
        }
    ],
    "sg:phone":"+1 415 457 3430",
    "sg:postcode":"94949",
    "sg:province":"CA",
    "sg:tags":[
        "market",
        "analysis"
    ],
    "wof:name":"Wiredresponses",
    "wof:placetype":"venue"
},
  "geometry": {"coordinates":[-122.509649,38.051662],"type":"Point"}
}