{
  "type": "Feature",
  "properties": {
    "addr:full":"139 S Main Ave Fallbrook CA 92028",
    "addr:housenumber":"139",
    "addr:postcode":"92028",
    "addr:street":"S Main Ave",
    "iso:country":"US",
    "sg:address":"139 S Main Ave",
    "sg:city":"Fallbrook",
    "sg:classifiers":[
        {
            "category":"Banks & Credit Unions",
            "subcategory":"Bank",
            "type":"Services"
        }
    ],
    "sg:phone":"+1 760 728 9585",
    "sg:postcode":"92028",
    "sg:province":"CA",
    "wof:name":"Inland Empire National Bank",
    "wof:placetype":"venue"
},
  "geometry": {"coordinates":[-117.25099899999999,33.381302],"type":"Point"}
}