{
  "type": "Feature",
  "properties": {
    "addr:full":"1013 Orange Ave Coronado CA 92118",
    "addr:housenumber":"1013",
    "addr:postcode":"92118",
    "addr:street":"Orange Ave",
    "iso:country":"US",
    "sg:address":"1013 Orange Ave",
    "sg:city":"Coronado",
    "sg:classifiers":[
        {
            "category":"Shopping",
            "subcategory":"Clothing, Apparel, & Fashions",
            "type":"Retail Goods"
        }
    ],
    "sg:phone":"+1 619 435 4035",
    "sg:postcode":"92118",
    "sg:province":"CA",
    "wof:name":"Sacha's Boutique Resort",
    "wof:placetype":"venue"
},
  "geometry": {"coordinates":[-117.179827,32.685204],"type":"Point"}
}