{
  "type": "Feature",
  "properties": {
    "addr:full":"660 Sacramento St San Francisco CA 94111",
    "addr:housenumber":"660",
    "addr:postcode":"94111",
    "addr:street":"Sacramento St",
    "iso:country":"US",
    "sg:address":"660 Sacramento St",
    "sg:city":"San Francisco",
    "sg:classifiers":[
        {
            "category":"Wholesale",
            "subcategory":"Construction Materials",
            "type":"Manufacturing & Wholesale Goods"
        },
        {
            "category":"Banks & Credit Unions",
            "subcategory":"Investment Brokerage",
            "type":"Services"
        }
    ],
    "sg:phone":"+1 415 765 0475",
    "sg:postcode":"94111",
    "sg:province":"CA",
    "sg:tags":[
        "product",
        "management",
        "based",
        "wood",
        "real estate",
        "investor"
    ],
    "wof:name":"Kinkosha Inc",
    "wof:placetype":"venue"
},
  "geometry": {"coordinates":[-122.40333099999999,37.793832],"type":"Point"}
}