{
  "type": "Feature",
  "properties": {
    "addr:full":"8823 Sunland Blvd Sun Valley CA 91352",
    "addr:housenumber":"8823",
    "addr:postcode":"91352",
    "addr:street":"Sunland Blvd",
    "iso:country":"US",
    "sg:address":"8823 Sunland Blvd",
    "sg:city":"Sun Valley",
    "sg:classifiers":[
        {
            "category":"Restaurant",
            "type":"Food & Drink"
        }
    ],
    "sg:menulink":"http://www.allmenus.com/ca/san-fernando-valley/213394-taco-bell/menu/",
    "sg:phone":"+1 818 768 0599",
    "sg:postcode":"91352",
    "sg:province":"CA",
    "sg:tags":[
        "mexican"
    ],
    "wof:name":"Taco Bell",
    "wof:placetype":"venue"
},
  "geometry": {"coordinates":[-118.36675700000001,34.229412],"type":"Point"}
}