{
  "type": "Feature",
  "properties": {
    "iso:country":"US",
    "sg:address":"2565 Puesta del Sol",
    "sg:city":"Santa Barbara",
    "sg:classifiers":[
        {
            "category":"Professional",
            "subcategory":"Research",
            "type":"Services"
        }
    ],
    "sg:phone":"+1 805 682 2065",
    "sg:postcode":"93105",
    "sg:province":"CA",
    "sg:tags":[
        "environmental",
        "ecological"
    ],
    "wof:name":"Storrer Enviornmental Svc",
    "wof:placetype":"venue"
},
  "geometry": {"coordinates":[-119.71499,34.44156],"type":"Point"}
}