{
  "type": "Feature",
  "properties": {
    "addr:full":"2568 Baseline St Highland CA 92346",
    "addr:housenumber":"2568",
    "addr:postcode":"92346",
    "addr:street":"Baseline St",
    "iso:country":"US",
    "sg:address":"2568 Baseline St",
    "sg:city":"Highland",
    "sg:classifiers":[
        {
            "category":"Real Estate",
            "subcategory":"Real Estate Operator",
            "type":"Services"
        }
    ],
    "sg:phone":"+1 909 862 1378",
    "sg:postcode":"92346",
    "sg:province":"CA",
    "sg:tags":[
        "apartment"
    ],
    "wof:name":"Royal Palm Apartments",
    "wof:placetype":"venue"
},
  "geometry": {"coordinates":[-117.22856,34.121283],"type":"Point"}
}