{
  "type": "Feature",
  "properties": {
    "iso:country":"US",
    "sg:address":"11725 Garden Grove Blvd",
    "sg:city":"Garden Grove",
    "sg:classifiers":[
        {
            "category":"Shopping",
            "type":"Retail Goods"
        }
    ],
    "sg:phone":"+1 714 539 0767",
    "sg:postcode":"92843",
    "sg:province":"CA",
    "sg:tags":[
        "merchandise"
    ],
    "wof:name":"ARC One",
    "wof:placetype":"venue"
},
  "geometry": {"coordinates":[-117.927892,33.774386],"type":"Point"}
}