{
  "type": "Feature",
  "properties": {
    "iso:country":"US",
    "sg:address":"4509 E Slauson Ave",
    "sg:city":"Maywood",
    "sg:classifiers":[
        {
            "category":"Insurance",
            "subcategory":"Insurance Agent",
            "type":"Services"
        }
    ],
    "sg:phone":"+1 323 771 7071",
    "sg:postcode":"90270",
    "sg:province":"CA",
    "sg:tags":[
        "consultant"
    ],
    "wof:name":"SDS Insurance",
    "wof:placetype":"venue"
},
  "geometry": {"coordinates":[-118.183514,33.986999],"type":"Point"}
}