{
  "type": "Feature",
  "properties": {
    "addr:full":"1040 N San Dimas Canyon Rd San Dimas CA 91773",
    "addr:housenumber":"1040",
    "addr:postcode":"91773",
    "addr:street":"N San;Canyon Rd",
    "iso:country":"US",
    "sg:address":"1040 N San Dimas Canyon Rd",
    "sg:city":"San Dimas",
    "sg:classifiers":[
        {
            "category":"Professional",
            "subcategory":"Accounting & Tax Preparation",
            "type":"Services"
        }
    ],
    "sg:phone":"+1 909 542 1040",
    "sg:postcode":"91773",
    "sg:province":"CA",
    "sg:tags":[
        "accountant"
    ],
    "wof:name":"Wallenbrock & Seltzer",
    "wof:placetype":"venue"
},
  "geometry": {"coordinates":[-117.793882,34.120042],"type":"Point"}
}