{
  "type": "Feature",
  "properties": {
    "addr:full":"16638 Tracy St Victorville CA 92395",
    "addr:housenumber":"16638",
    "addr:postcode":"92395",
    "addr:street":"Tracy St",
    "iso:country":"US",
    "sg:address":"16638 Tracy St",
    "sg:city":"Victorville",
    "sg:classifiers":[
        {
            "category":"Retail",
            "subcategory":"Repair Shop",
            "type":"Services"
        }
    ],
    "sg:phone":"+1 760 243 1500",
    "sg:postcode":"92395",
    "sg:province":"CA",
    "sg:tags":[
        "scooter",
        "motorcycle",
        "motor"
    ],
    "wof:name":"Scooter Tramps",
    "wof:placetype":"venue"
},
  "geometry": {"coordinates":[-117.301039,34.529352],"type":"Point"}
}