{
  "type": "Feature",
  "properties": {
    "addr:full":"8523 Canoga Ave Canoga Park CA 91304",
    "addr:housenumber":"8523",
    "addr:postcode":"91304",
    "addr:street":"Canoga Ave",
    "iso:country":"US",
    "sg:address":"8523 Canoga Ave",
    "sg:city":"Canoga Park",
    "sg:classifiers":[
        {
            "category":"Wholesale",
            "subcategory":"Hardware",
            "type":"Manufacturing & Wholesale Goods"
        }
    ],
    "sg:phone":"+1 818 772 6215",
    "sg:postcode":"91304",
    "sg:province":"CA",
    "sg:tags":[
        "heater"
    ],
    "wof:name":"Kappl Heating & Air Condition",
    "wof:placetype":"venue"
},
  "geometry": {"coordinates":[-118.59762499999999,34.227794],"type":"Point"}
}