{
  "type": "Feature",
  "properties": {
    "iso:country":"US",
    "sg:address":"125 W Neal St",
    "sg:city":"Pleasanton",
    "sg:classifiers":[
        {
            "category":"Building & Trades",
            "subcategory":"Construction",
            "type":"Services"
        }
    ],
    "sg:phone":"+1 925 462 3785",
    "sg:postcode":"94566",
    "sg:province":"CA",
    "sg:tags":[
        "contractor"
    ],
    "wof:name":"Mct Development",
    "wof:placetype":"venue"
},
  "geometry": {"coordinates":[-121.874915,37.660286],"type":"Point"}
}