{
  "type": "Feature",
  "properties": {
    "addr:full":"2200 Mission College Blvd Santa Clara CA 95054",
    "addr:housenumber":"2200",
    "addr:postcode":"95054",
    "addr:street":"Mission College Blvd",
    "iso:country":"US",
    "sg:address":"2200 Mission College Blvd",
    "sg:city":"Santa Clara",
    "sg:classifiers":[
        {
            "category":"Government",
            "subcategory":"Office",
            "type":"Public Place"
        }
    ],
    "sg:phone":"+1 408 765 9918",
    "sg:postcode":"95054",
    "sg:province":"CA",
    "wof:name":"Housing Trust-Santa Clara Cnty",
    "wof:placetype":"venue"
},
  "geometry": {"coordinates":[-121.963686,37.388577],"type":"Point"}
}