{
  "type": "Feature",
  "properties": {
    "iso:country":"US",
    "sg:address":"8462 Santa Monica Blvd",
    "sg:city":"West Hollywood",
    "sg:classifiers":[
        {
            "category":"Personal",
            "subcategory":"Beauty Salon",
            "type":"Services"
        }
    ],
    "sg:phone":"+1 323 804 3120",
    "sg:postcode":"90069",
    "sg:province":"CA",
    "sg:tags":[
        "hair"
    ],
    "wof:name":"Atelier Beauty Salon",
    "wof:placetype":"venue"
},
  "geometry": {"coordinates":[-118.375,34.09],"type":"Point"}
}