{
  "type": "Feature",
  "properties": {
    "addr:full":"437 N Alice Ave Dinuba CA 93618",
    "addr:housenumber":"437",
    "addr:postcode":"93618",
    "addr:street":"N Alice Ave",
    "iso:country":"US",
    "sg:address":"437 N Alice Ave",
    "sg:city":"Dinuba",
    "sg:classifiers":[
        {
            "category":"Freight",
            "type":"Transportation"
        }
    ],
    "sg:phone":"+1 559 805 4979",
    "sg:postcode":"93618",
    "sg:province":"CA",
    "sg:tags":[
        "operator",
        "local",
        "trucking"
    ],
    "wof:name":"Juan J Carrillo Trucking",
    "wof:placetype":"venue"
},
  "geometry": {"coordinates":[-119.40417600000001,36.54904],"type":"Point"}
}