{
  "type": "Feature",
  "properties": {
    "addr:full":"3050 Los Feliz Boulevard Los Angeles CA 90039",
    "addr:housenumber":"3050",
    "addr:postcode":"90039",
    "addr:street":"Los Feliz Boulevard",
    "iso:country":"US",
    "sg:address":"3050 Los Feliz Boulevard",
    "sg:city":"Los Angeles",
    "sg:classifiers":[
        {
            "category":"Autos & Motor Vehicles",
            "subcategory":"Fuel & Gas Station",
            "type":"Retail Goods"
        },
        {
            "category":"Food & Beverages",
            "subcategory":"Groceries & Convenience Stores",
            "type":"Retail Goods"
        }
    ],
    "sg:phone":"+1 323 661 4027",
    "sg:postcode":"90039",
    "sg:province":"CA",
    "wof:name":"Simon's Chevron",
    "wof:placetype":"venue"
},
  "geometry": {"coordinates":[-118.26602099999999,34.124969],"type":"Point"}
}