{
  "type": "Feature",
  "properties": {
    "iso:country":"US",
    "sg:address":"8710 S Gate Ave",
    "sg:city":"South Gate",
    "sg:classifiers":[
        {
            "category":"Banks & Credit Unions",
            "subcategory":"Bank",
            "type":"Services"
        }
    ],
    "sg:phone":"+1 562 776 0129",
    "sg:postcode":"90280",
    "sg:province":"CA",
    "wof:name":"Union Bank Of California",
    "wof:placetype":"venue"
},
  "geometry": {"coordinates":[-118.21430700000001,33.956198],"type":"Point"}
}