{
  "type": "Feature",
  "properties": {
    "iso:country":"US",
    "sg:address":"3350 Barham Blvd",
    "sg:city":"Los Angeles",
    "sg:classifiers":[
        {
            "category":"Communications",
            "type":"Services"
        }
    ],
    "sg:phone":"+1 323 512 8800",
    "sg:postcode":"90068",
    "sg:province":"CA",
    "sg:tags":[
        "recording",
        "rehearsal",
        "studio"
    ],
    "wof:name":"Persona Music Productions & Studios",
    "wof:placetype":"venue"
},
  "geometry": {"coordinates":[-118.344002,34.131802],"type":"Point"}
}