{
  "type": "Feature",
  "properties": {
    "iso:country":"US",
    "sg:address":"3374 Onyx Cir",
    "sg:city":"Simi Valley",
    "sg:classifiers":[
        {
            "category":"Manufacturing",
            "subcategory":"Metals",
            "type":"Manufacturing & Wholesale Goods"
        }
    ],
    "sg:phone":"+1 805 527 5754",
    "sg:postcode":"93063",
    "sg:province":"CA",
    "sg:tags":[
        "engraver"
    ],
    "wof:name":"MKM Enterprise",
    "wof:placetype":"venue"
},
  "geometry": {"coordinates":[-118.731623,34.287007],"type":"Point"}
}