{
  "type": "Feature",
  "properties": {
    "iso:country":"US",
    "sg:address":"36429 Colbert St",
    "sg:city":"Newark",
    "sg:classifiers":[
        {
            "category":"Retail",
            "subcategory":"Car Wash",
            "type":"Services"
        }
    ],
    "sg:phone":"+1 510 583 1840",
    "sg:postcode":"94560",
    "sg:province":"CA",
    "sg:tags":[
        "automobile",
        "detail",
        "clean"
    ],
    "wof:name":"Hernan's Auto Detailing",
    "wof:placetype":"venue"
},
  "geometry": {"coordinates":[-122.04531,37.534489],"type":"Point"}
}