{
  "type": "Feature",
  "properties": {
    "iso:country":"US",
    "sg:address":"695 de Long Ave",
    "sg:city":"Novato",
    "sg:classifiers":[
        {
            "category":"Building & Trades",
            "subcategory":"Electrical",
            "type":"Services"
        }
    ],
    "sg:phone":"+1 415 892 7721",
    "sg:postcode":"94945",
    "sg:province":"CA",
    "sg:tags":[
        "electric",
        "contractor"
    ],
    "wof:name":"Shields Electrical Svc",
    "wof:placetype":"venue"
},
  "geometry": {"coordinates":[-122.56140000000001,38.104862],"type":"Point"}
}