{
  "type": "Feature",
  "properties": {
    "addr:full":"896 4th St Hollister CA 95023",
    "addr:housenumber":"896",
    "addr:postcode":"hollister ca 95023",
    "addr:street":"4Th St",
    "iso:country":"US",
    "sg:address":"896 4th St",
    "sg:city":"Hollister",
    "sg:classifiers":[
        {
            "category":"Wholesale",
            "subcategory":"Auto Parts",
            "type":"Manufacturing & Wholesale Goods"
        }
    ],
    "sg:phone":"+1 831 638 1282",
    "sg:postcode":"95023",
    "sg:province":"CA",
    "sg:tags":[
        "tire"
    ],
    "wof:name":"Camacho Tires",
    "wof:placetype":"venue"
},
  "geometry": {"coordinates":[-121.411044,36.85276],"type":"Point"}
}