{
  "type": "Feature",
  "properties": {
    "addr:full":"10123 Oakdale Ave Chatsworth CA 91311",
    "addr:housenumber":"10123",
    "addr:postcode":"91311",
    "addr:street":"Oakdale Ave",
    "iso:country":"US",
    "sg:address":"10123 Oakdale Ave",
    "sg:city":"Chatsworth",
    "sg:classifiers":[
        {
            "category":"Health Services",
            "subcategory":"Health Practitioner",
            "type":"Services"
        }
    ],
    "sg:phone":"+1 818 700 0873",
    "sg:postcode":"91311",
    "sg:province":"CA",
    "sg:tags":[
        "therapist",
        "physical"
    ],
    "wof:name":"Physical FACILITIES-Nawa",
    "wof:placetype":"venue"
},
  "geometry": {"coordinates":[-118.566768,34.25503],"type":"Point"}
}