{
  "type": "Feature",
  "properties": {
    "addr:full":"17707 Crenshaw Blvd Torrance CA 90504",
    "addr:housenumber":"17707",
    "addr:postcode":"90504",
    "addr:street":"Crenshaw Blvd",
    "iso:country":"US",
    "sg:address":"17707 Crenshaw Blvd",
    "sg:city":"Torrance",
    "sg:classifiers":[
        {
            "category":"Building & Trades",
            "subcategory":"Construction",
            "type":"Services"
        }
    ],
    "sg:phone":"+1 310 214 4144",
    "sg:postcode":"90504",
    "sg:province":"CA",
    "sg:tags":[
        "painter"
    ],
    "sg:website":"www.colorfulchoice.com",
    "wof:name":"Colorful Choice Painting Co",
    "wof:placetype":"venue"
},
  "geometry": {"coordinates":[-118.326537,33.869686],"type":"Point"}
}