{
  "type": "Feature",
  "properties": {
    "addr:full":"5221 Zelzah Ave Encino CA 91316",
    "addr:housenumber":"5221",
    "addr:postcode":"91316",
    "addr:street":"Zelzah Ave",
    "iso:country":"US",
    "sg:address":"5221 Zelzah Ave",
    "sg:city":"Encino",
    "sg:classifiers":[
        {
            "category":"Real Estate",
            "subcategory":"Real Estate Services",
            "type":"Services"
        },
        {
            "category":"Real Estate",
            "subcategory":"Real Estate Operator",
            "type":"Services"
        }
    ],
    "sg:phone":"+1 818 881 1176",
    "sg:postcode":"91316",
    "sg:province":"CA",
    "sg:tags":[
        "apartment",
        "vacancy",
        "listing",
        "rental",
        "finder"
    ],
    "wof:name":"Urov Apartments",
    "wof:placetype":"venue"
},
  "geometry": {"coordinates":[-118.52202,34.165695],"type":"Point"}
}