{
  "type": "Feature",
  "properties": {
    "iso:country":"US",
    "sg:address":"1805 Lake Tahoe Blvd",
    "sg:city":"South Lake Tahoe",
    "sg:classifiers":[
        {
            "category":"Building & Trades",
            "subcategory":"Construction",
            "type":"Services"
        }
    ],
    "sg:phone":"+1 530 577 9041",
    "sg:postcode":"96150",
    "sg:province":"CA",
    "sg:tags":[
        "painter"
    ],
    "wof:name":"Larry Schaffer Painting & Deco",
    "wof:placetype":"venue"
},
  "geometry": {"coordinates":[-120.01026,38.910382],"type":"Point"}
}