{
  "type": "Feature",
  "properties": {
    "addr:full":"110 S Maple Ave South San Francisco CA 94080",
    "addr:housenumber":"110",
    "addr:postcode":"94080",
    "addr:street":"S Maple Ave",
    "iso:country":"US",
    "sg:address":"110 S Maple Ave",
    "sg:city":"South San Francisco",
    "sg:classifiers":[
        {
            "category":"Building & Trades",
            "subcategory":"Construction",
            "type":"Services"
        }
    ],
    "sg:phone":"+1 650 583 8580",
    "sg:postcode":"94080",
    "sg:province":"CA",
    "sg:tags":[
        "air",
        "heating",
        "conditioning/hvac"
    ],
    "wof:name":"Nelson-Kent Air Inc",
    "wof:placetype":"venue"
},
  "geometry": {"coordinates":[-122.415001,37.648602],"type":"Point"}
}