{
  "type": "Feature",
  "properties": {
    "addr:full":"1110 Main St Watsonville CA 95076",
    "addr:housenumber":"1110",
    "addr:postcode":"95076",
    "addr:street":"Main St",
    "iso:country":"US",
    "sg:address":"1110 Main St",
    "sg:city":"Watsonville",
    "sg:classifiers":[
        {
            "category":"Communications",
            "subcategory":"Radio Station",
            "type":"Services"
        }
    ],
    "sg:phone":"+1 831 763 1075",
    "sg:postcode":"95076",
    "sg:province":"CA",
    "sg:tags":[
        "broadcast"
    ],
    "wof:name":"New Wave Brdcstng Inc",
    "wof:placetype":"venue"
},
  "geometry": {"coordinates":[-121.77059300000001,36.916422],"type":"Point"}
}