{
  "type": "Feature",
  "properties": {
    "addr:full":"21855 Avalon Blvd Ste 6 Carson CA 90745",
    "addr:housenumber":"21855",
    "addr:postcode":"90745",
    "addr:street":"Avalon Blvd Ste 6",
    "iso:country":"US",
    "sg:address":"21855 Avalon Blvd Ste 6",
    "sg:city":"Carson",
    "sg:classifiers":[
        {
            "category":"Personal",
            "subcategory":"Beauty Salon",
            "type":"Services"
        }
    ],
    "sg:phone":"+1 310 903 6042",
    "sg:postcode":"90745",
    "sg:province":"CA",
    "sg:tags":[
        "hair"
    ],
    "sg:website":"www.studio6salon.com/default.html",
    "wof:name":"Studio 6 Salon",
    "wof:placetype":"venue"
},
  "geometry": {"coordinates":[-118.263614,33.829422],"type":"Point"}
}