{
  "type": "Feature",
  "properties": {
    "addr:full":"1754 Laurel St San Carlos CA 94070",
    "addr:housenumber":"1754",
    "addr:postcode":"94070",
    "addr:street":"Laurel St",
    "iso:country":"US",
    "sg:address":"1754 Laurel St",
    "sg:city":"San Carlos",
    "sg:classifiers":[
        {
            "category":"Restaurant",
            "type":"Food & Drink"
        }
    ],
    "sg:menulink":"http://www.allmenus.com/ca/san-mateo/279448-michas/menu/",
    "sg:phone":"+1 650 595 5776",
    "sg:postcode":"94070",
    "sg:province":"CA",
    "sg:tags":[
        "barbecue",
        "american"
    ],
    "wof:name":"Micha's",
    "wof:placetype":"venue"
},
  "geometry": {"coordinates":[-122.245818,37.493653],"type":"Point"}
}