{
  "type": "Feature",
  "properties": {
    "addr:full":"23924 Summerhill Ln. Santa Clarita CA 91354",
    "addr:housenumber":"23924",
    "addr:postcode":"91354",
    "addr:street":"Summerhill Ln.",
    "iso:country":"US",
    "sg:address":"23924 Summerhill Ln.",
    "sg:city":"Santa Clarita",
    "sg:classifiers":[
        {
            "category":"Education",
            "subcategory":"Special Training",
            "type":"Public Place"
        }
    ],
    "sg:phone":"+1 661 513 9937",
    "sg:postcode":"91354",
    "sg:province":"CA",
    "sg:tags":[
        "school",
        "art"
    ],
    "sg:website":"www.fineartclasses.com",
    "wof:name":"Mission Renaissance Fine Art Classes",
    "wof:placetype":"venue"
},
  "geometry": {"coordinates":[-118.553344,34.446487],"type":"Point"}
}