{
  "type": "Feature",
  "properties": {
    "iso:country":"US",
    "sg:address":"1505 E Burnett St",
    "sg:city":"Signal Hill",
    "sg:classifiers":[
        {
            "category":"Retail",
            "subcategory":"Auto Repair",
            "type":"Services"
        }
    ],
    "sg:phone":"+1 562 427 5569",
    "sg:postcode":"90755",
    "sg:province":"CA",
    "sg:tags":[
        "repairing",
        "automobile",
        "radiator"
    ],
    "wof:name":"Tempco Radiator Corp",
    "wof:placetype":"venue"
},
  "geometry": {"coordinates":[-118.172059,33.800808],"type":"Point"}
}