{
  "type": "Feature",
  "properties": {
    "addr:full":"650 E Hospitality Ln San Bernardino CA 92408",
    "addr:housenumber":"650",
    "addr:postcode":"92408",
    "addr:street":"E Hospitality Ln",
    "iso:country":"US",
    "sg:address":"650 E Hospitality Ln",
    "sg:city":"San Bernardino",
    "sg:classifiers":[
        {
            "category":"Restaurant",
            "type":"Food & Drink"
        }
    ],
    "sg:phone":"+1 909 381 1467",
    "sg:postcode":"92408",
    "sg:province":"CA",
    "wof:name":"Burger King",
    "wof:placetype":"venue"
},
  "geometry": {"coordinates":[-117.271443,34.06589],"type":"Point"}
}