{
  "type": "Feature",
  "properties": {
    "iso:country":"US",
    "sg:address":"1007 Van Buren St",
    "sg:city":"Fairfield",
    "sg:classifiers":[
        {
            "category":"Building & Trades",
            "subcategory":"Construction",
            "type":"Services"
        }
    ],
    "sg:phone":"+1 707 429 8782",
    "sg:postcode":"94533",
    "sg:province":"CA",
    "sg:tags":[
        "concrete",
        "contractor"
    ],
    "wof:name":"Vc Concrete",
    "wof:placetype":"venue"
},
  "geometry": {"coordinates":[-122.051534,38.25439],"type":"Point"}
}