{
  "type": "Feature",
  "properties": {
    "iso:country":"US",
    "sg:address":"2303 Ulric St",
    "sg:city":"San Diego",
    "sg:classifiers":[
        {
            "category":"Home & Garden",
            "subcategory":"Home Furnishings",
            "type":"Retail Goods"
        }
    ],
    "sg:phone":"+1 858 337 4308",
    "sg:postcode":"92111",
    "sg:province":"CA",
    "sg:tags":[
        "venetian",
        "blind"
    ],
    "wof:name":"Ky's Mini Blinds",
    "wof:placetype":"venue"
},
  "geometry": {"coordinates":[-117.16949099999999,32.78629],"type":"Point"}
}