{
  "type": "Feature",
  "properties": {
    "iso:country":"US",
    "sg:address":"19925 Stevens Creek Blvd",
    "sg:city":"Cupertino",
    "sg:classifiers":[
        {
            "category":"Wholesale",
            "subcategory":"Auto Parts",
            "type":"Manufacturing & Wholesale Goods"
        }
    ],
    "sg:phone":"+1 408 725 7191",
    "sg:postcode":"95014",
    "sg:province":"CA",
    "wof:name":"Auto Parts & Accessories Whl",
    "wof:placetype":"venue"
},
  "geometry": {"coordinates":[-122.022649,37.32292],"type":"Point"}
}