{
  "type": "Feature",
  "properties": {
    "iso:country":"US",
    "sg:address":"2701 N Santa Fe Avenue",
    "sg:city":"Compton",
    "sg:classifiers":[
        {
            "category":"Bakery",
            "type":"Food & Drink"
        }
    ],
    "sg:phone":"+1 310 537 0361",
    "sg:postcode":"90222",
    "sg:province":"CA",
    "wof:name":"Ruben's Bakery and Mexican Food",
    "wof:placetype":"venue"
},
  "geometry": {"coordinates":[-118.217684,33.916822],"type":"Point"}
}