{
  "type": "Feature",
  "properties": {
    "addr:full":"13323 W Washington Boulevard Los Angeles CA 90066",
    "addr:housenumber":"13323",
    "addr:postcode":"90066",
    "addr:street":"W Washington Boulevard",
    "iso:country":"US",
    "sg:address":"13323 W Washington Boulevard",
    "sg:city":"Los Angeles",
    "sg:classifiers":[
        {
            "category":"Building & Trades",
            "subcategory":"Construction",
            "type":"Services"
        }
    ],
    "sg:phone":"+1 310 822 8285",
    "sg:postcode":"90066",
    "sg:province":"CA",
    "sg:tags":[
        "contractor"
    ],
    "wof:name":"Sos Enterprises",
    "wof:placetype":"venue"
},
  "geometry": {"coordinates":[-118.44331099999999,33.992719],"type":"Point"}
}