{
  "type": "Feature",
  "properties": {
    "addr:full":"13325 Monterey Hwy San Martin CA 95046",
    "addr:housenumber":"13325",
    "addr:postcode":"95046",
    "addr:street":"Monterey Hwy",
    "iso:country":"US",
    "sg:address":"13325 Monterey Hwy",
    "sg:city":"San Martin",
    "sg:classifiers":[
        {
            "category":"Restaurant",
            "type":"Food & Drink"
        }
    ],
    "sg:phone":"+1 408 683 2118",
    "sg:postcode":"95046",
    "sg:province":"CA",
    "wof:name":"El Pato Loco",
    "wof:placetype":"venue"
},
  "geometry": {"coordinates":[-121.613146,37.08968],"type":"Point"}
}