{
  "type": "Feature",
  "properties": {
    "iso:country":"US",
    "sg:address":"460 Avalani Ave",
    "sg:city":"San Jose",
    "sg:classifiers":[
        {
            "category":"Real Estate",
            "subcategory":"Real Estate Agent",
            "type":"Services"
        }
    ],
    "sg:phone":"+1 408 258 8051",
    "sg:postcode":"95133",
    "sg:province":"CA",
    "wof:name":"Alpha Property Development",
    "wof:placetype":"venue"
},
  "geometry": {"coordinates":[-121.862312,37.363747],"type":"Point"}
}