{
  "type": "Feature",
  "properties": {
    "iso:country":"US",
    "sg:address":"3179 College Ave",
    "sg:city":"Berkeley",
    "sg:classifiers":[
        {
            "category":"Health Services",
            "subcategory":"Health Practitioner",
            "type":"Services"
        }
    ],
    "sg:phone":"+1 510 601 1140",
    "sg:postcode":"94705",
    "sg:province":"CA",
    "sg:tags":[
        "psychologist"
    ],
    "wof:name":"Irene Sardanis PHD",
    "wof:placetype":"venue"
},
  "geometry": {"coordinates":[-122.252669,37.853361],"type":"Point"}
}