{
  "type": "Feature",
  "properties": {
    "iso:country":"US",
    "sg:address":"340 Lorton Ave",
    "sg:city":"Burlingame",
    "sg:classifiers":[
        {
            "category":"Health Services",
            "subcategory":"Chiropractor",
            "type":"Services"
        }
    ],
    "sg:phone":"+1 650 343 3444",
    "sg:postcode":"94010",
    "sg:province":"CA",
    "wof:name":"Danli Chiropractic & Wellness",
    "wof:placetype":"venue"
},
  "geometry": {"coordinates":[-122.347143,37.580256],"type":"Point"}
}