{
  "type": "Feature",
  "properties": {
    "addr:full":"2119 Manzanita Dr Arnold CA 95223",
    "addr:housenumber":"2119",
    "addr:postcode":"95223",
    "addr:street":"Manzanita Dr",
    "iso:country":"US",
    "sg:address":"2119 Manzanita Dr",
    "sg:city":"Arnold",
    "sg:classifiers":[
        {
            "category":"Professional",
            "type":"Services"
        }
    ],
    "sg:phone":"+1 209 795 4910",
    "sg:postcode":"95223",
    "sg:province":"CA",
    "sg:tags":[
        "establishment"
    ],
    "wof:name":"Bowers Office Ctr",
    "wof:placetype":"venue"
},
  "geometry": {"coordinates":[-120.332061,38.240541],"type":"Point"}
}