{
  "type": "Feature",
  "properties": {
    "iso:country":"US",
    "sg:address":"3721 N Country Club Dr",
    "sg:city":"Long Beach",
    "sg:classifiers":[
        {
            "category":"Building & Trades",
            "subcategory":"Cleaning & Sanitation",
            "type":"Services"
        }
    ],
    "sg:phone":"+1 562 427 1705",
    "sg:postcode":"90807",
    "sg:province":"CA",
    "sg:tags":[
        "janitor"
    ],
    "wof:name":"Ildefonso Quinones",
    "wof:placetype":"venue"
},
  "geometry": {"coordinates":[-118.197643,33.824911],"type":"Point"}
}