{
  "type": "Feature",
  "properties": {
    "iso:country":"US",
    "sg:address":"5722 Telephone Rd",
    "sg:city":"Ventura",
    "sg:classifiers":[
        {
            "category":"Shopping",
            "subcategory":"Hobbies, Toys, & Games",
            "type":"Retail Goods"
        },
        {
            "category":"Shopping",
            "subcategory":"Crafts & Fabrics",
            "type":"Retail Goods"
        }
    ],
    "sg:phone":"+1 805 339 9580",
    "sg:postcode":"93003",
    "sg:province":"CA",
    "sg:tags":[
        "shop",
        "toy",
        "supply",
        "hobby",
        "model",
        "store"
    ],
    "sg:website":"http://www.games-workshop.com",
    "wof:name":"Games Workshop",
    "wof:placetype":"venue"
},
  "geometry": {"coordinates":[-119.214792,34.264997],"type":"Point"}
}