{
  "type": "Feature",
  "properties": {
    "iso:country":"US",
    "sg:address":"399 Joost Ave",
    "sg:city":"San Francisco",
    "sg:classifiers":[
        {
            "category":"Professional",
            "subcategory":"Lawyer & Legal Services",
            "type":"Services"
        }
    ],
    "sg:phone":"+1 415 334 6317",
    "sg:postcode":"94131",
    "sg:province":"CA",
    "sg:tags":[
        "attorney"
    ],
    "wof:name":"Mary C Dunlap",
    "wof:placetype":"venue"
},
  "geometry": {"coordinates":[-122.442027,37.732357],"type":"Point"}
}