{
  "type": "Feature",
  "properties": {
    "addr:full":"1772 Union St San Francisco CA 94123",
    "addr:housenumber":"1772",
    "addr:postcode":"94123",
    "addr:street":"Union St",
    "iso:country":"US",
    "sg:address":"1772 Union St",
    "sg:city":"San Francisco",
    "sg:classifiers":[
        {
            "category":"Home & Garden",
            "subcategory":"Furniture",
            "type":"Retail Goods"
        }
    ],
    "sg:phone":"+1 415 922 7424",
    "sg:postcode":"94123",
    "sg:province":"CA",
    "sg:tags":[
        "futon"
    ],
    "wof:name":"Momen Futon",
    "wof:placetype":"venue"
},
  "geometry": {"coordinates":[-122.427971,37.798153],"type":"Point"}
}