{
  "type": "Feature",
  "properties": {
    "iso:country":"US",
    "sg:address":"750 Warfield Ave",
    "sg:city":"Piedmont",
    "sg:classifiers":[
        {
            "category":"Real Estate",
            "subcategory":"Real Estate Operator",
            "type":"Services"
        }
    ],
    "sg:phone":"+1 510 272 9664",
    "sg:postcode":"94610",
    "sg:province":"CA",
    "sg:tags":[
        "apartment"
    ],
    "wof:name":"Grandview Apartments",
    "wof:placetype":"venue"
},
  "geometry": {"coordinates":[-122.245003,37.8125],"type":"Point"}
}