{
  "type": "Feature",
  "properties": {
    "addr:full":"126 W 3rd St Chico CA 95928",
    "addr:housenumber":"126",
    "addr:postcode":"95928",
    "addr:street":"W 3Rd St",
    "iso:country":"US",
    "sg:address":"126 W 3rd St",
    "sg:city":"Chico",
    "sg:classifiers":[
        {
            "category":"Shopping",
            "subcategory":"Clothing, Apparel, & Fashions",
            "type":"Retail Goods"
        }
    ],
    "sg:phone":"+1 530 895 3850",
    "sg:postcode":"95928",
    "sg:province":"CA",
    "wof:name":"Milenas Tayloring Cstm Design",
    "wof:placetype":"venue"
},
  "geometry": {"coordinates":[-121.84031899999999,39.729239],"type":"Point"}
}