{
  "type": "Feature",
  "properties": {
    "addr:full":"329 Festival Dr Oceanside CA 92057",
    "addr:housenumber":"329",
    "addr:postcode":"92057",
    "addr:street":"Festival Dr",
    "iso:country":"US",
    "sg:address":"329 Festival Dr",
    "sg:city":"Oceanside",
    "sg:classifiers":[
        {
            "category":"Building & Trades",
            "subcategory":"Construction",
            "type":"Services"
        }
    ],
    "sg:phone":"+1 760 439 2337",
    "sg:postcode":"92057",
    "sg:province":"CA",
    "sg:tags":[
        "hanging",
        "contractor"
    ],
    "wof:name":"Ace Painting & Construction",
    "wof:placetype":"venue"
},
  "geometry": {"coordinates":[-117.318257,33.252218],"type":"Point"}
}