{
  "type": "Feature",
  "properties": {
    "addr:full":"2911 Adams Ave San Diego CA 92116",
    "addr:housenumber":"2911",
    "addr:postcode":"92116",
    "addr:street":"Adams Ave",
    "iso:country":"US",
    "sg:address":"2911 Adams Ave",
    "sg:city":"San Diego",
    "sg:classifiers":[
        {
            "category":"Health Services",
            "subcategory":"Doctor",
            "type":"Services"
        }
    ],
    "sg:phone":"+1 619 280 4580",
    "sg:postcode":"92116",
    "sg:province":"CA",
    "sg:tags":[
        "physician",
        "surgeon"
    ],
    "wof:name":"Adams Avenue Medical Clinic",
    "wof:placetype":"venue"
},
  "geometry": {"coordinates":[-117.130987,32.76281],"type":"Point"}
}