{
  "type": "Feature",
  "properties": {
    "addr:full":"2109 E Valley Pkwy Escondido CA 92027",
    "addr:housenumber":"2109",
    "addr:postcode":"92027",
    "addr:street":"E Valley Pkwy",
    "iso:country":"US",
    "sg:address":"2109 E Valley Pkwy",
    "sg:city":"Escondido",
    "sg:classifiers":[
        {
            "category":"Retail",
            "subcategory":"Auto Repair",
            "type":"Services"
        }
    ],
    "sg:phone":"+1 760 741 1236",
    "sg:postcode":"92027",
    "sg:province":"CA",
    "sg:tags":[
        "automotive",
        "general"
    ],
    "wof:name":"Valvoline Instant Oil Change",
    "wof:placetype":"venue"
},
  "geometry": {"coordinates":[-117.050619,33.137862],"type":"Point"}
}