{
  "type": "Feature",
  "properties": {
    "iso:country":"US",
    "sg:address":"38 N Hill Ave",
    "sg:city":"Pasadena",
    "sg:classifiers":[
        {
            "category":"Retail",
            "subcategory":"Auto Repair",
            "type":"Services"
        }
    ],
    "sg:phone":"+1 626 796 5329",
    "sg:postcode":"91106",
    "sg:province":"CA",
    "sg:tags":[
        "automobile",
        "top",
        "upholstery"
    ],
    "wof:name":"Ken Sorensen Top Shop",
    "wof:placetype":"venue"
},
  "geometry": {"coordinates":[-118.12127700000001,34.146667],"type":"Point"}
}