{
  "type": "Feature",
  "properties": {
    "addr:full":"38671 Bears Paw Dr Murrieta CA 92562",
    "addr:postcode":"38671;92562",
    "addr:street":"Paw Dr",
    "iso:country":"US",
    "sg:address":"38671 Bears Paw Dr",
    "sg:city":"Murrieta",
    "sg:classifiers":[
        {
            "category":"Wholesale",
            "subcategory":"Toys & Hobbies",
            "type":"Manufacturing & Wholesale Goods"
        }
    ],
    "sg:phone":"+1 951 677 5010",
    "sg:postcode":"92562",
    "sg:province":"CA",
    "sg:tags":[
        "wholesaler"
    ],
    "wof:name":"Yachts & Things Trading Co",
    "wof:placetype":"venue"
},
  "geometry": {"coordinates":[-117.26518,33.573469],"type":"Point"}
}