{
  "type": "Feature",
  "properties": {
    "iso:country":"US",
    "sg:address":"55 Market St",
    "sg:city":"Colusa",
    "sg:classifiers":[
        {
            "category":"Retail",
            "subcategory":"Auto Repair",
            "type":"Services"
        }
    ],
    "sg:phone":"+1 530 458 7897",
    "sg:postcode":"95932",
    "sg:province":"CA",
    "sg:tags":[
        "repairing",
        "automobile"
    ],
    "wof:name":"Morrow's Automotive Repair",
    "wof:placetype":"venue"
},
  "geometry": {"coordinates":[-122.00203500000001,39.212588],"type":"Point"}
}