{
  "type": "Feature",
  "properties": {
    "addr:full":"1455 2nd Ave San Diego CA 92101",
    "addr:housenumber":"1455",
    "addr:postcode":"92101",
    "addr:street":"2Nd Ave",
    "iso:country":"US",
    "sg:address":"1455 2nd Ave",
    "sg:city":"San Diego",
    "sg:classifiers":[
        {
            "category":"Insurance",
            "subcategory":"Insurance Agent",
            "type":"Services"
        }
    ],
    "sg:phone":"+1 619 299 2210",
    "sg:postcode":"92101",
    "sg:province":"CA",
    "wof:name":"Hiegel Insurance",
    "wof:placetype":"venue"
},
  "geometry": {"coordinates":[-117.16286599999999,32.720358],"type":"Point"}
}