{
  "type": "Feature",
  "properties": {
    "addr:full":"1100 E Orangefair Ln Anaheim CA 92801",
    "addr:housenumber":"1100",
    "addr:postcode":"92801",
    "addr:street":"E Orangefair Ln",
    "iso:country":"US",
    "sg:address":"1100 E Orangefair Ln",
    "sg:city":"Anaheim",
    "sg:classifiers":[
        {
            "category":"Manufacturing",
            "subcategory":"Metals",
            "type":"Manufacturing & Wholesale Goods"
        }
    ],
    "sg:phone":"+1 714 738 5429",
    "sg:postcode":"92801",
    "sg:province":"CA",
    "sg:tags":[
        "engraver"
    ],
    "wof:name":"Affordable Memorials",
    "wof:placetype":"venue"
},
  "geometry": {"coordinates":[-117.906813,33.85579],"type":"Point"}
}