{
  "type": "Feature",
  "properties": {
    "iso:country":"US",
    "sg:address":"19528 Cohasset St",
    "sg:city":"Reseda",
    "sg:classifiers":[
        {
            "category":"Manufacturing",
            "subcategory":"Glass & Minerals",
            "type":"Manufacturing & Wholesale Goods"
        }
    ],
    "sg:phone":"+1 818 886 7675",
    "sg:postcode":"91335",
    "sg:province":"CA",
    "sg:tags":[
        "fountain",
        "mfg"
    ],
    "wof:name":"Fountains For Pools",
    "wof:placetype":"venue"
},
  "geometry": {"coordinates":[-118.558664,34.207228],"type":"Point"}
}