{
  "type": "Feature",
  "properties": {
    "addr:full":"2890 Aegean Pl Castro Valley CA 94546",
    "addr:housenumber":"2890",
    "addr:postcode":"94546",
    "addr:street":"Aegean Pl",
    "iso:country":"US",
    "sg:address":"2890 Aegean Pl",
    "sg:city":"Castro Valley",
    "sg:classifiers":[
        {
            "category":"Real Estate",
            "subcategory":"Real Estate Agent",
            "type":"Services"
        }
    ],
    "sg:phone":"+1 510 714 4297",
    "sg:postcode":"94546",
    "sg:province":"CA",
    "wof:name":"Glass Doctor The",
    "wof:placetype":"venue"
},
  "geometry": {"coordinates":[-122.09301600000001,37.703748],"type":"Point"}
}