{
  "type": "Feature",
  "properties": {
    "addr:full":"9000 Orr Springs Rd Ukiah CA 95482",
    "addr:housenumber":"9000",
    "addr:postcode":"ca 95482",
    "addr:street":"Orr Springs Rd",
    "iso:country":"US",
    "sg:address":"9000 Orr Springs Rd",
    "sg:city":"Ukiah",
    "sg:classifiers":[
        {
            "category":"Building & Trades",
            "subcategory":"Construction",
            "type":"Services"
        }
    ],
    "sg:phone":"+1 800 844 2338",
    "sg:postcode":"95482",
    "sg:province":"CA",
    "sg:tags":[
        "painting",
        "contractor"
    ],
    "wof:name":"McAfee Bill Painting & Decorating",
    "wof:placetype":"venue"
},
  "geometry": {"coordinates":[-123.326317,39.217593],"type":"Point"}
}