{
  "type": "Feature",
  "properties": {
    "addr:full":"617 W Orangethorpe Ave Placentia CA 92870",
    "addr:housenumber":"617",
    "addr:postcode":"ca 92870",
    "addr:street":"W Orangethorpe Ave",
    "iso:country":"US",
    "sg:address":"617 W Orangethorpe Ave",
    "sg:city":"Placentia",
    "sg:classifiers":[
        {
            "category":"Manufacturing",
            "subcategory":"Tools & Machinery",
            "type":"Manufacturing & Wholesale Goods"
        }
    ],
    "sg:phone":"+1 714 996 3261",
    "sg:postcode":"92870",
    "sg:province":"CA",
    "sg:tags":[
        "mfg",
        "apparatus",
        "welding"
    ],
    "wof:name":"Praxair",
    "wof:placetype":"venue"
},
  "geometry": {"coordinates":[-117.87946100000001,33.860767],"type":"Point"}
}