{
  "type": "Feature",
  "properties": {
    "addr:full":"840 B St Hollister CA 95023",
    "addr:housenumber":"840",
    "addr:postcode":"hollister ca 95023",
    "addr:street":"B St",
    "iso:country":"US",
    "sg:address":"840 B St",
    "sg:city":"Hollister",
    "sg:classifiers":[
        {
            "category":"Retail",
            "subcategory":"Car Wash",
            "type":"Services"
        }
    ],
    "sg:phone":"+1 831 634 0605",
    "sg:postcode":"95023",
    "sg:province":"CA",
    "sg:tags":[
        "automobile",
        "detail",
        "clean"
    ],
    "wof:name":"Reyes Auto Detailing",
    "wof:placetype":"venue"
},
  "geometry": {"coordinates":[-121.411772,36.843611],"type":"Point"}
}