{
  "type": "Feature",
  "properties": {
    "addr:full":"670 Palisade St Pasadena CA 91103",
    "addr:housenumber":"670",
    "addr:postcode":"91103",
    "addr:street":"Palisade St",
    "iso:country":"US",
    "sg:address":"670 Palisade St",
    "sg:city":"Pasadena",
    "sg:classifiers":[
        {
            "category":"Education",
            "subcategory":"Special Training",
            "type":"Public Place"
        }
    ],
    "sg:phone":"+1 626 347 6363",
    "sg:postcode":"91103",
    "sg:province":"CA",
    "sg:tags":[
        "school",
        "instruction",
        "art"
    ],
    "wof:name":"Creative Portfolio Ctr",
    "wof:placetype":"venue"
},
  "geometry": {"coordinates":[-118.16558999999999,34.171753],"type":"Point"}
}