{
  "type": "Feature",
  "properties": {
    "addr:full":"1050 State Rte 175 Hopland CA 95449",
    "addr:housenumber":"1050",
    "addr:postcode":"95449",
    "addr:street":"State Rte 175",
    "iso:country":"US",
    "sg:address":"1050 State Rte 175",
    "sg:city":"Hopland",
    "sg:classifiers":[
        {
            "category":"Farming",
            "subcategory":"Orchard",
            "type":"Manufacturing & Wholesale Goods"
        }
    ],
    "sg:phone":"+1 707 744 1734",
    "sg:postcode":"95449",
    "sg:province":"CA",
    "sg:tags":[
        "fruit",
        "tree"
    ],
    "wof:name":"Rosetti Bros",
    "wof:placetype":"venue"
},
  "geometry": {"coordinates":[-123.098913,38.97756],"type":"Point"}
}