{
  "type": "Feature",
  "properties": {
    "iso:country":"US",
    "sg:address":"3211 Broad St",
    "sg:city":"San Luis Obispo",
    "sg:classifiers":[
        {
            "category":"Restaurant",
            "type":"Food & Drink"
        }
    ],
    "sg:phone":"+1 805 783 2013",
    "sg:postcode":"93401",
    "sg:province":"CA",
    "wof:name":"Le Ciel Crepes Cafe",
    "wof:placetype":"venue"
},
  "geometry": {"coordinates":[-120.649991,35.261177],"type":"Point"}
}