{
  "type": "Feature",
  "properties": {
    "addr:full":"997 Catalina Blvd San Diego CA 92106",
    "addr:housenumber":"997",
    "addr:postcode":"92106",
    "addr:street":"Catalina Blvd",
    "iso:country":"US",
    "sg:address":"997 Catalina Blvd",
    "sg:city":"San Diego",
    "sg:classifiers":[
        {
            "category":"Professional",
            "type":"Services"
        }
    ],
    "sg:phone":"+1 619 223 7587",
    "sg:postcode":"92106",
    "sg:province":"CA",
    "wof:name":"Sound Planning",
    "wof:placetype":"venue"
},
  "geometry": {"coordinates":[-117.245389,32.722688],"type":"Point"}
}