{
  "type": "Feature",
  "properties": {
    "addr:full":"638 K St Los Banos CA 93635",
    "addr:housenumber":"638",
    "addr:postcode":"93635",
    "addr:street":"K St",
    "iso:country":"US",
    "sg:address":"638 K St",
    "sg:city":"Los Banos",
    "sg:classifiers":[
        {
            "category":"Home & Garden",
            "subcategory":"Household Appliances",
            "type":"Retail Goods"
        }
    ],
    "sg:phone":"+1 209 826 6659",
    "sg:postcode":"93635",
    "sg:province":"CA",
    "sg:tags":[
        "cleaners",
        "vacuum"
    ],
    "wof:name":"Ferry's Vacuum-Sewing Machine",
    "wof:placetype":"venue"
},
  "geometry": {"coordinates":[-120.84869500000001,37.058813],"type":"Point"}
}