{
  "type": "Feature",
  "properties": {
    "iso:country":"US",
    "sg:address":"6237 43rd St",
    "sg:city":"Sacramento",
    "sg:classifiers":[
        {
            "category":"Building & Trades",
            "subcategory":"Landscaping Services",
            "type":"Services"
        }
    ],
    "sg:phone":"+1 916 393 5166",
    "sg:postcode":"95824",
    "sg:province":"CA",
    "wof:name":"Dm Barron Gardening",
    "wof:placetype":"venue"
},
  "geometry": {"coordinates":[-121.457126,38.512042],"type":"Point"}
}