{
  "type": "Feature",
  "properties": {
    "addr:full":"1268 S Vanderbilt Cir Manteca CA 95337",
    "addr:housenumber":"1268",
    "addr:postcode":"95337",
    "addr:street":"S Vanderbilt Cir",
    "iso:country":"US",
    "sg:address":"1268 S Vanderbilt Cir",
    "sg:city":"Manteca",
    "sg:classifiers":[
        {
            "category":"Retail",
            "subcategory":"Repair Shop",
            "type":"Services"
        }
    ],
    "sg:phone":"+1 209 823 7184",
    "sg:postcode":"95337",
    "sg:province":"CA",
    "sg:tags":[
        "upholsterer"
    ],
    "wof:name":"Color-Glo Upholstery",
    "wof:placetype":"venue"
},
  "geometry": {"coordinates":[-121.21334299999999,37.787338],"type":"Point"}
}