{
  "type": "Feature",
  "properties": {
    "iso:country":"US",
    "sg:address":"4854 N Blackstone Ave",
    "sg:city":"Fresno",
    "sg:classifiers":[
        {
            "category":"Professional",
            "subcategory":"Detective & Security Services",
            "type":"Services"
        }
    ],
    "sg:phone":"+1 800 346 1411",
    "sg:postcode":"93726",
    "sg:province":"CA",
    "sg:tags":[
        "buyer",
        "information"
    ],
    "wof:name":"RCA Consumer Service",
    "wof:placetype":"venue"
},
  "geometry": {"coordinates":[-119.79039299999999,36.805619],"type":"Point"}
}