{
  "type": "Feature",
  "properties": {
    "addr:full":"828 Diablo Rd Danville CA 94526",
    "addr:housenumber":"828",
    "addr:postcode":"94526",
    "addr:street":"Diablo Rd",
    "iso:country":"US",
    "sg:address":"828 Diablo Rd",
    "sg:city":"Danville",
    "sg:classifiers":[
        {
            "category":"Building & Trades",
            "subcategory":"Landscaping Services",
            "type":"Services"
        }
    ],
    "sg:phone":"+1 925 743 0288",
    "sg:postcode":"94526",
    "sg:province":"CA",
    "sg:tags":[
        "topsoil"
    ],
    "wof:name":"Sloat Top Soil",
    "wof:placetype":"venue"
},
  "geometry": {"coordinates":[-121.987392,37.829316],"type":"Point"}
}