{
  "type": "Feature",
  "properties": {
    "iso:country":"US",
    "sg:address":"770 E Ventura Ave",
    "sg:city":"Tulare",
    "sg:classifiers":[
        {
            "category":"Professional",
            "type":"Services"
        }
    ],
    "sg:phone":"+1 559 686 5959",
    "sg:postcode":"93274",
    "sg:province":"CA",
    "wof:name":"Gary Rummerfield",
    "wof:placetype":"venue"
},
  "geometry": {"coordinates":[-119.337012,36.204646],"type":"Point"}
}