{
  "type": "Feature",
  "properties": {
    "iso:country":"US",
    "sg:address":"1305 Granite Ln",
    "sg:city":"Modesto",
    "sg:classifiers":[
        {
            "category":"Autos & Motor Vehicles",
            "subcategory":"Recreational Vehicle Sales",
            "type":"Retail Goods"
        }
    ],
    "sg:phone":"+1 209 523 1513",
    "sg:postcode":"95351",
    "sg:province":"CA",
    "sg:tags":[
        "parts",
        "trailer"
    ],
    "wof:name":"Sierra Trailer Co",
    "wof:placetype":"venue"
},
  "geometry": {"coordinates":[-121.028625,37.656441],"type":"Point"}
}