{
  "type": "Feature",
  "properties": {
    "iso:country":"US",
    "sg:address":"1518 Noriega St",
    "sg:city":"San Francisco",
    "sg:classifiers":[
        {
            "category":"Health Services",
            "subcategory":"Doctor",
            "type":"Services"
        }
    ],
    "sg:phone":"+1 415 221 7939",
    "sg:postcode":"94122",
    "sg:province":"CA",
    "sg:tags":[
        "physician",
        "surgeon"
    ],
    "wof:name":"Carol K Lee MD",
    "wof:placetype":"venue"
},
  "geometry": {"coordinates":[-122.480608,37.754135],"type":"Point"}
}