{
  "type": "Feature",
  "properties": {
    "iso:country":"US",
    "sg:address":"117 E Rialto Ave",
    "sg:city":"Rialto",
    "sg:classifiers":[
        {
            "category":"Personal",
            "subcategory":"Beauty Salon",
            "type":"Services"
        }
    ],
    "sg:phone":"+1 909 873 0280",
    "sg:postcode":"92376",
    "sg:province":"CA",
    "wof:name":"Sarah's Shear Joy Hair Salon",
    "wof:placetype":"venue"
},
  "geometry": {"coordinates":[-117.369624,34.098676],"type":"Point"}
}