{
  "type": "Feature",
  "properties": {
    "addr:full":"890 Sacramento Ave West Sacramento CA 95605",
    "addr:housenumber":"890",
    "addr:postcode":"95605",
    "addr:street":"Sacramento Ave",
    "iso:country":"US",
    "sg:address":"890 Sacramento Ave",
    "sg:city":"West Sacramento",
    "sg:classifiers":[
        {
            "category":"Manufacturing",
            "subcategory":"Chemicals & Compounds",
            "type":"Manufacturing & Wholesale Goods"
        }
    ],
    "sg:phone":"+1 916 376 1000",
    "sg:postcode":"95605",
    "sg:province":"CA",
    "sg:tags":[
        "mfg",
        "pharmaceutical",
        "substance",
        "diagnostic"
    ],
    "wof:name":"Affymetrix Inc",
    "wof:placetype":"venue"
},
  "geometry": {"coordinates":[-121.524592,38.589282],"type":"Point"}
}