{
  "type": "Feature",
  "properties": {
    "iso:country":"US",
    "sg:address":"1020 15th St Ste 8",
    "sg:city":"Modesto",
    "sg:classifiers":[
        {
            "category":"Professional",
            "subcategory":"Lawyer & Legal Services",
            "type":"Services"
        }
    ],
    "sg:phone":"+1 209 526 0006",
    "sg:postcode":"95354",
    "sg:province":"CA",
    "wof:name":"MOORAD CALVIN LAW OFFICES",
    "wof:placetype":"venue"
},
  "geometry": {"coordinates":[-120.995632,37.644385],"type":"Point"}
}