{
  "type": "Feature",
  "properties": {
    "addr:full":"14056 Burbank Blvd Sherman Oaks CA 91401",
    "addr:housenumber":"14056",
    "addr:postcode":"91401",
    "addr:street":"Burbank Blvd",
    "iso:country":"US",
    "sg:address":"14056 Burbank Blvd",
    "sg:city":"Sherman Oaks",
    "sg:classifiers":[
        {
            "category":"Restaurant",
            "type":"Food & Drink"
        }
    ],
    "sg:phone":"+1 818 787 7070",
    "sg:postcode":"91401",
    "sg:province":"CA",
    "sg:tags":[
        "pizza"
    ],
    "sg:website":"www.guidospizzaandpasta.com/",
    "wof:name":"Guido's Pizza & Pasta",
    "wof:placetype":"venue"
},
  "geometry": {"coordinates":[-118.439003,34.172298],"type":"Point"}
}