{
  "type": "Feature",
  "properties": {
    "addr:full":"2465 Florencita Ave Montrose CA 91020",
    "addr:housenumber":"2465",
    "addr:postcode":"91020",
    "addr:street":"Florencita Ave",
    "iso:country":"US",
    "sg:address":"2465 Florencita Ave",
    "sg:city":"Montrose",
    "sg:classifiers":[
        {
            "category":"Building & Trades",
            "subcategory":"Cleaning & Sanitation",
            "type":"Services"
        }
    ],
    "sg:phone":"+1 818 248 7377",
    "sg:postcode":"91020",
    "sg:province":"CA",
    "sg:tags":[
        "home"
    ],
    "wof:name":"Speedi-Maid Cleaning Service",
    "wof:placetype":"venue"
},
  "geometry": {"coordinates":[-118.23221100000001,34.210097],"type":"Point"}
}