{
  "type": "Feature",
  "properties": {
    "addr:full":"387 Zachary St Moorpark CA 93021",
    "addr:housenumber":"387",
    "addr:postcode":"ca 93021",
    "addr:street":"Zachary St",
    "iso:country":"US",
    "sg:address":"387 Zachary St",
    "sg:city":"Moorpark",
    "sg:classifiers":[
        {
            "category":"Autos & Motor Vehicles",
            "subcategory":"Motorcycle Sales",
            "type":"Retail Goods"
        }
    ],
    "sg:phone":"+1 805 532 2068",
    "sg:postcode":"93021",
    "sg:province":"CA",
    "sg:tags":[
        "scooter"
    ],
    "wof:name":"Comanche Parts Svc",
    "wof:placetype":"venue"
},
  "geometry": {"coordinates":[-118.87159,34.282992],"type":"Point"}
}