{
  "type": "Feature",
  "properties": {
    "iso:country":"US",
    "sg:address":"2181 Meyers Ave",
    "sg:city":"Escondido",
    "sg:classifiers":[
        {
            "category":"Professional",
            "type":"Services"
        }
    ],
    "sg:phone":"+1 760 739 8597",
    "sg:postcode":"92029",
    "sg:province":"CA",
    "sg:tags":[
        "establishment"
    ],
    "wof:name":"TDE Fund Inc",
    "wof:placetype":"venue"
},
  "geometry": {"coordinates":[-117.124424,33.129138],"type":"Point"}
}