{
  "type": "Feature",
  "properties": {
    "iso:country":"US",
    "sg:address":"9430 Topanga Canyon Blvd 204",
    "sg:city":"Chatsworth",
    "sg:classifiers":[
        {
            "category":"Insurance",
            "subcategory":"Insurance Agent",
            "type":"Services"
        },
        {
            "category":"Insurance",
            "subcategory":"Hazard Insurance",
            "type":"Services"
        },
        {
            "category":"Insurance",
            "subcategory":"Title Insurance",
            "type":"Services"
        },
        {
            "category":"Insurance",
            "subcategory":"Life Insurance",
            "type":"Services"
        }
    ],
    "sg:phone":"+1 818 517 9524",
    "sg:postcode":"91311",
    "sg:province":"CA",
    "sg:tags":[
        "auto",
        "commercial",
        "business",
        "homeowner"
    ],
    "sg:website":"http://www.farmersagent.com/dschilling/",
    "wof:name":"Dustin Schilling - Farmers Insurance",
    "wof:placetype":"venue"
},
  "geometry": {"coordinates":[-118.60619199999999,34.241536],"type":"Point"}
}