{
  "type": "Feature",
  "properties": {
    "iso:country":"US",
    "sg:address":"2302 Martin Ct",
    "sg:city":"Irvine",
    "sg:classifiers":[
        {
            "category":"Government",
            "subcategory":"Office",
            "type":"Public Place"
        }
    ],
    "sg:phone":"+1 714 261 0031",
    "sg:postcode":"92612",
    "sg:province":"CA",
    "sg:tags":[
        "affairs"
    ],
    "wof:name":"Public Affairs Mar Corps Off",
    "wof:placetype":"venue"
},
  "geometry": {"coordinates":[-117.860316,33.672688],"type":"Point"}
}