{
  "type": "Feature",
  "properties": {
    "iso:country":"US",
    "sg:address":"817 E Thompson Blvd",
    "sg:city":"Ventura",
    "sg:classifiers":[
        {
            "category":"Professional",
            "subcategory":"Accounting & Tax Preparation",
            "type":"Services"
        }
    ],
    "sg:phone":"+1 805 653 0325",
    "sg:postcode":"93001",
    "sg:province":"CA",
    "sg:tags":[
        "bookkeeping",
        "general"
    ],
    "wof:name":"Dee Franco Contract Bkpg",
    "wof:placetype":"venue"
},
  "geometry": {"coordinates":[-119.287164,34.278361],"type":"Point"}
}