{
  "type": "Feature",
  "properties": {
    "iso:country":"US",
    "sg:address":"1133 Foothill Blvd",
    "sg:city":"La Canada Flintridge",
    "sg:classifiers":[
        {
            "category":"Food & Beverages",
            "subcategory":"Candy",
            "type":"Retail Goods"
        }
    ],
    "sg:phone":"+1 818 790 7022",
    "sg:postcode":"91011",
    "sg:province":"CA",
    "sg:tags":[
        "confectionery",
        "store"
    ],
    "sg:website":"www.sees.com",
    "wof:name":"See's Candies",
    "wof:placetype":"venue"
},
  "geometry": {"coordinates":[-118.204002,34.2061],"type":"Point"}
}