{
  "type": "Feature",
  "properties": {
    "addr:full":"222 Keyes Street San Jose CA 95112",
    "addr:housenumber":"222",
    "addr:postcode":"95112",
    "addr:street":"Keyes Street",
    "iso:country":"US",
    "sg:address":"222 Keyes Street",
    "sg:city":"San Jose",
    "sg:classifiers":[
        {
            "category":"Retail",
            "subcategory":"Auto Repair",
            "type":"Services"
        }
    ],
    "sg:phone":"+1 408 287 2886",
    "sg:postcode":"95112",
    "sg:province":"CA",
    "wof:name":"All Made Auto Repair",
    "wof:placetype":"venue"
},
  "geometry": {"coordinates":[-121.873434,37.32192],"type":"Point"}
}