{
  "type": "Feature",
  "properties": {
    "iso:country":"US",
    "sg:address":"206 Washington Blvd",
    "sg:city":"Half Moon Bay",
    "sg:classifiers":[
        {
            "category":"Professional",
            "subcategory":"Management & Consulting",
            "type":"Services"
        }
    ],
    "sg:phone":"+1 650 726 9441",
    "sg:postcode":"94019",
    "sg:province":"CA",
    "sg:tags":[
        "consultant",
        "business"
    ],
    "wof:name":"Miramar Technologies",
    "wof:placetype":"venue"
},
  "geometry": {"coordinates":[-122.453385,37.489167],"type":"Point"}
}