{
  "type": "Feature",
  "properties": {
    "iso:country":"US",
    "sg:address":"7421 Woodside Dr",
    "sg:city":"Stockton",
    "sg:classifiers":[
        {
            "category":"Wholesale",
            "subcategory":"Sporting Goods",
            "type":"Manufacturing & Wholesale Goods"
        }
    ],
    "sg:phone":"+1 209 957 7518",
    "sg:postcode":"95207",
    "sg:province":"CA",
    "wof:name":"MACS",
    "wof:placetype":"venue"
},
  "geometry": {"coordinates":[-121.339105,38.018485],"type":"Point"}
}