{
  "type": "Feature",
  "properties": {
    "addr:full":"2143 W Gaylord St Long Beach CA 90813",
    "addr:housenumber":"2143",
    "addr:postcode":"90813",
    "addr:street":"W Gaylord St",
    "iso:country":"US",
    "sg:address":"2143 W Gaylord St",
    "sg:city":"Long Beach",
    "sg:classifiers":[
        {
            "category":"Retail",
            "subcategory":"Auto Repair",
            "type":"Services"
        }
    ],
    "sg:phone":"+1 562 951 3354",
    "sg:postcode":"90813",
    "sg:province":"CA",
    "sg:tags":[
        "body",
        "shop"
    ],
    "wof:name":"Escaner Warlito",
    "wof:placetype":"venue"
},
  "geometry": {"coordinates":[-118.221001,33.786301],"type":"Point"}
}