{
  "type": "Feature",
  "properties": {
    "iso:country":"US",
    "sg:address":"1016 Felicidad Dr",
    "sg:city":"Fallbrook",
    "sg:classifiers":[
        {
            "category":"Shopping",
            "subcategory":"Computers & Home Electronics",
            "type":"Retail Goods"
        }
    ],
    "sg:phone":"+1 760 728 1453",
    "sg:postcode":"92028",
    "sg:province":"CA",
    "sg:tags":[
        "high",
        "fidelity",
        "stereophonic"
    ],
    "wof:name":"Home Theater Experience",
    "wof:placetype":"venue"
},
  "geometry": {"coordinates":[-117.236936,33.37815],"type":"Point"}
}