{
  "type": "Feature",
  "properties": {
    "iso:country":"US",
    "sg:address":"4269 N 1st St",
    "sg:city":"Fresno",
    "sg:classifiers":[
        {
            "category":"Food & Beverages",
            "subcategory":"Meat & Fish",
            "type":"Retail Goods"
        }
    ],
    "sg:phone":"+1 559 221 1350",
    "sg:postcode":"93726",
    "sg:province":"CA",
    "wof:name":"Renna's Meat Market",
    "wof:placetype":"venue"
},
  "geometry": {"coordinates":[-119.77236000000001,36.7944],"type":"Point"}
}