{
  "type": "Feature",
  "properties": {
    "addr:full":"1777 Concord Ave Concord CA 94520",
    "addr:housenumber":"1777",
    "addr:postcode":"94520",
    "addr:street":"Concord Ave",
    "iso:country":"US",
    "sg:address":"1777 Concord Ave",
    "sg:city":"Concord",
    "sg:classifiers":[
        {
            "category":"Retail",
            "subcategory":"Auto Repair",
            "type":"Services"
        }
    ],
    "sg:phone":"+1 925 682 2345",
    "sg:postcode":"94520",
    "sg:province":"CA",
    "sg:tags":[
        "clutches"
    ],
    "wof:name":"Clutch Stop",
    "wof:placetype":"venue"
},
  "geometry": {"coordinates":[-122.03967799999999,37.978283],"type":"Point"}
}