{
  "type": "Feature",
  "properties": {
    "addr:full":"324 E Shaw Ave Fresno CA 93710",
    "addr:housenumber":"324",
    "addr:postcode":"93710",
    "addr:street":"E Shaw Ave",
    "iso:country":"US",
    "sg:address":"324 E Shaw Ave",
    "sg:city":"Fresno",
    "sg:classifiers":[
        {
            "category":"Travel",
            "subcategory":"Hotels & Motels",
            "type":"Entertainment"
        },
        {
            "category":"Restaurant",
            "type":"Food & Drink"
        },
        {
            "category":"Retail",
            "subcategory":"Event Space",
            "type":"Services"
        }
    ],
    "sg:phone":"+1 559 224 4040",
    "sg:postcode":"93710",
    "sg:province":"CA",
    "sg:tags":[
        "facility",
        "banquet",
        "reception",
        "lodging",
        "hall"
    ],
    "sg:website":"http://www.ramada.com/hotel/00206&cid=RANE",
    "wof:name":"Ramada-University",
    "wof:placetype":"venue"
},
  "geometry": {"coordinates":[-119.782053,36.808651],"type":"Point"}
}