{
  "type": "Feature",
  "properties": {
    "iso:country":"US",
    "sg:address":"402 Princeland Ct",
    "sg:city":"Corona",
    "sg:classifiers":[
        {
            "category":"Home & Garden",
            "subcategory":"Building Materials",
            "type":"Retail Goods"
        },
        {
            "category":"Building & Trades",
            "subcategory":"Construction",
            "type":"Services"
        }
    ],
    "sg:phone":"+1 877 483 9400",
    "sg:postcode":"92879",
    "sg:province":"CA",
    "sg:tags":[
        "awning",
        "canopy",
        "canopies-repair"
    ],
    "wof:name":"Affordable Awnings Co",
    "wof:placetype":"venue"
},
  "geometry": {"coordinates":[-117.562096,33.886384],"type":"Point"}
}