{
  "type": "Feature",
  "properties": {
    "iso:country":"US",
    "sg:address":"4315 E Lowell St",
    "sg:city":"Ontario",
    "sg:classifiers":[
        {
            "category":"Professional",
            "subcategory":"Computer Services",
            "type":"Services"
        }
    ],
    "sg:phone":"+1 909 974 4424",
    "sg:postcode":"91761",
    "sg:province":"CA",
    "sg:tags":[
        "repair"
    ],
    "wof:name":"Computeam",
    "wof:placetype":"venue"
},
  "geometry": {"coordinates":[-117.55619799999999,34.051911],"type":"Point"}
}