{
  "type": "Feature",
  "properties": {
    "addr:full":"2720 Arden Way Ste 200 Sacramento CA 95825",
    "addr:housenumber":"2720",
    "addr:postcode":"95825",
    "addr:street":"Arden Way Ste 200",
    "iso:country":"US",
    "sg:address":"2720 Arden Way Ste 200",
    "sg:city":"Sacramento",
    "sg:classifiers":[
        {
            "category":"Insurance",
            "subcategory":"Hazard Insurance",
            "type":"Services"
        }
    ],
    "sg:phone":"+1 916 485 9111",
    "sg:postcode":"95825",
    "sg:province":"CA",
    "sg:tags":[
        "commercial",
        "business"
    ],
    "wof:name":"Wst 1 Ins",
    "wof:placetype":"venue"
},
  "geometry": {"coordinates":[-121.397362,38.595956],"type":"Point"}
}