{
  "type": "Feature",
  "properties": {
    "iso:country":"US",
    "sg:address":"3304 Ave del Presidente",
    "sg:city":"San Clemente",
    "sg:classifiers":[
        {
            "category":"Shopping",
            "subcategory":"Bicycles & Sporting Goods",
            "type":"Retail Goods"
        }
    ],
    "sg:phone":"+1 949 874 4457",
    "sg:postcode":"92672",
    "sg:province":"CA",
    "sg:tags":[
        "equipment",
        "surfing"
    ],
    "wof:name":"Alves Surfboards",
    "wof:placetype":"venue"
},
  "geometry": {"coordinates":[-117.597956,33.403762],"type":"Point"}
}