{
  "type": "Feature",
  "properties": {
    "addr:full":"23327 8th St Newhall CA 91321",
    "addr:housenumber":"23327",
    "addr:postcode":"91321",
    "addr:street":"8Th St",
    "iso:country":"US",
    "sg:address":"23327 8th St",
    "sg:city":"Newhall",
    "sg:classifiers":[
        {
            "category":"Organizations",
            "subcategory":"Religious Organization",
            "type":"Services"
        }
    ],
    "sg:phone":"+1 661 254 8417",
    "sg:postcode":"91321",
    "sg:province":"CA",
    "wof:name":"Institute of Religion",
    "wof:placetype":"venue"
},
  "geometry": {"coordinates":[-118.537965,34.373557],"type":"Point"}
}