{
  "type": "Feature",
  "properties": {
    "iso:country":"US",
    "sg:address":"8901 S Gate Ave",
    "sg:city":"South Gate",
    "sg:classifiers":[
        {
            "category":"Autos & Motor Vehicles",
            "subcategory":"Fuel & Gas Station",
            "type":"Retail Goods"
        }
    ],
    "sg:phone":"+1 323 569 9636",
    "sg:postcode":"90280",
    "sg:province":"CA",
    "sg:tags":[
        "oil"
    ],
    "wof:name":"South Gate Shell",
    "wof:placetype":"venue"
},
  "geometry": {"coordinates":[-118.214845,33.952999],"type":"Point"}
}