{
  "type": "Feature",
  "properties": {
    "iso:country":"US",
    "sg:address":"13495 Beach Blvd",
    "sg:city":"La Mirada",
    "sg:classifiers":[
        {
            "category":"Fast Food",
            "type":"Food & Drink"
        }
    ],
    "sg:phone":"+1 562 902 2214",
    "sg:postcode":"90638",
    "sg:province":"CA",
    "sg:tags":[
        "burger"
    ],
    "sg:website":"www.jackinthebox.com",
    "wof:name":"Jack In The Box",
    "wof:placetype":"venue"
},
  "geometry": {"coordinates":[-117.977554,33.909035],"type":"Point"}
}