{
  "type": "Feature",
  "properties": {
    "iso:country":"US",
    "sg:address":"19727 7th Pl",
    "sg:city":"Escondido",
    "sg:classifiers":[
        {
            "category":"Real Estate",
            "subcategory":"Real Estate Agent",
            "type":"Services"
        }
    ],
    "sg:phone":"+1 760 741 5253",
    "sg:postcode":"92029",
    "sg:province":"CA",
    "sg:website":"www.lakehodgesrealty.com",
    "wof:name":"Lake Hodges Realty",
    "wof:placetype":"venue"
},
  "geometry": {"coordinates":[-117.121067,33.069853],"type":"Point"}
}