{
  "type": "Feature",
  "properties": {
    "addr:full":"3683 San Gabriel River Pkwy Pico Rivera CA 90660",
    "addr:housenumber":"3683",
    "addr:postcode":"90660",
    "addr:street":"San Gabriel River Pkwy",
    "iso:country":"US",
    "sg:address":"3683 San Gabriel River Pkwy",
    "sg:city":"Pico Rivera",
    "sg:classifiers":[
        {
            "category":"Wholesale",
            "subcategory":"Machinery & Supplies",
            "type":"Manufacturing & Wholesale Goods"
        },
        {
            "category":"Autos & Motor Vehicles",
            "subcategory":"Automobile Sales",
            "type":"Retail Goods"
        }
    ],
    "sg:phone":"+1 562 463 7600",
    "sg:postcode":"90660",
    "sg:province":"CA",
    "sg:tags":[
        "to",
        "asia",
        "equipment",
        "aircraft",
        "parts",
        "export"
    ],
    "wof:name":"Ground Solution Inc",
    "wof:placetype":"venue"
},
  "geometry": {"coordinates":[-118.05780799999999,34.014115],"type":"Point"}
}