{
  "type": "Feature",
  "properties": {
    "iso:country":"US",
    "sg:address":"3739 6th Ave",
    "sg:city":"San Diego",
    "sg:classifiers":[
        {
            "category":"Restaurant",
            "type":"Food & Drink"
        }
    ],
    "sg:phone":"+1 619 692 4189",
    "sg:postcode":"92103",
    "sg:province":"CA",
    "sg:tags":[
        "japanese"
    ],
    "sg:website":"www.yakyudori.us/",
    "wof:name":"Yakitori Yakyudori",
    "wof:placetype":"venue"
},
  "geometry": {"coordinates":[-117.158997,32.745701],"type":"Point"}
}