{
  "type": "Feature",
  "properties": {
    "addr:full":"23 Vernon Dr Frazier Park CA 93225",
    "addr:housenumber":"23",
    "addr:postcode":"93225",
    "addr:street":"Vernon Dr",
    "iso:country":"US",
    "sg:address":"23 Vernon Dr",
    "sg:city":"Frazier Park",
    "sg:classifiers":[
        {
            "category":"Recreation",
            "type":"Entertainment"
        }
    ],
    "sg:phone":"+1 661 245 4907",
    "sg:postcode":"93225",
    "sg:province":"CA",
    "sg:tags":[
        "aquarium"
    ],
    "wof:name":"Fish Care Unlimited",
    "wof:placetype":"venue"
},
  "geometry": {"coordinates":[-119.007336,34.812625],"type":"Point"}
}