{
  "type": "Feature",
  "properties": {
    "addr:full":"201 N Figueroa St Los Angeles CA 90012",
    "addr:housenumber":"201",
    "addr:postcode":"90012",
    "addr:street":"N Figueroa St",
    "iso:country":"US",
    "sg:address":"201 N Figueroa St",
    "sg:city":"Los Angeles",
    "sg:classifiers":[
        {
            "category":"Government",
            "subcategory":"Office",
            "type":"Public Place"
        }
    ],
    "sg:phone":"+1 213 977 6941",
    "sg:postcode":"90012",
    "sg:province":"CA",
    "sg:tags":[
        "village"
    ],
    "wof:name":"Los Angeles Building & Safety",
    "wof:placetype":"venue"
},
  "geometry": {"coordinates":[-118.248711,34.059801],"type":"Point"}
}