{
  "type": "Feature",
  "properties": {
    "iso:country":"US",
    "sg:address":"11439 Encino Ave",
    "sg:city":"Granada Hills",
    "sg:classifiers":[
        {
            "category":"Education",
            "subcategory":"School",
            "type":"Public Place"
        }
    ],
    "sg:phone":"+1 818 360 9423",
    "sg:postcode":"91344",
    "sg:province":"CA",
    "wof:name":"Iqra Elementary School",
    "wof:placetype":"venue"
},
  "geometry": {"coordinates":[-118.51535800000001,34.278911],"type":"Point"}
}