{
  "type": "Feature",
  "properties": {
    "addr:full":"1620 Gough St San Francisco CA 94109",
    "addr:housenumber":"1620",
    "addr:postcode":"94109",
    "addr:street":"Gough St",
    "iso:country":"US",
    "sg:address":"1620 Gough St",
    "sg:city":"San Francisco",
    "sg:classifiers":[
        {
            "category":"Arts & Performance",
            "subcategory":"Arts Center",
            "type":"Entertainment"
        }
    ],
    "sg:phone":"+1 415 333 6389",
    "sg:postcode":"94109",
    "sg:province":"CA",
    "sg:tags":[
        "performing"
    ],
    "wof:name":"Next Stage Theater",
    "wof:placetype":"venue"
},
  "geometry": {"coordinates":[-122.42529,37.788239],"type":"Point"}
}