{
  "type": "Feature",
  "properties": {
    "iso:country":"US",
    "sg:address":"18800 Main Street",
    "sg:city":"Huntington Beach",
    "sg:classifiers":[
        {
            "category":"Health Services",
            "subcategory":"Doctor",
            "type":"Services"
        }
    ],
    "sg:phone":"+1 714 375 1441",
    "sg:postcode":"92648",
    "sg:province":"CA",
    "wof:name":"Lee Lester L MD",
    "wof:placetype":"venue"
},
  "geometry": {"coordinates":[-117.994142,33.689614],"type":"Point"}
}