{
  "type": "Feature",
  "properties": {
    "addr:full":"505 S Virgil Ave Ste 130 Los Angeles CA 90020",
    "addr:housenumber":"505",
    "addr:postcode":"90020",
    "addr:street":"S Virgil Ave Ste 130",
    "iso:country":"US",
    "sg:address":"505 S Virgil Ave Ste 130",
    "sg:city":"Los Angeles",
    "sg:classifiers":[
        {
            "category":"Education",
            "subcategory":"University",
            "type":"Public Place"
        }
    ],
    "sg:phone":"+1 213 908 1500",
    "sg:postcode":"90020",
    "sg:province":"CA",
    "sg:tags":[
        "college"
    ],
    "sg:website":"www.uwcla.org",
    "wof:name":"University of Western California",
    "wof:placetype":"venue"
},
  "geometry": {"coordinates":[-118.287678,34.064829],"type":"Point"}
}