{
  "type": "Feature",
  "properties": {
    "iso:country":"US",
    "sg:address":"387 Grand Avenue",
    "sg:city":"South San Francisco",
    "sg:classifiers":[
        {
            "category":"Sports & Exercise",
            "subcategory":"Gym",
            "type":"Entertainment"
        },
        {
            "category":"Arena",
            "subcategory":"Sports Club",
            "type":"Entertainment"
        }
    ],
    "sg:phone":"+1 650 583 8648",
    "sg:postcode":"94080",
    "sg:province":"CA",
    "sg:tags":[
        "trainer",
        "martial art"
    ],
    "wof:name":"Physique Magnifique Fitness Training Academy",
    "wof:placetype":"venue"
},
  "geometry": {"coordinates":[-122.41231000000001,37.655546],"type":"Point"}
}