{
  "type": "Feature",
  "properties": {
    "addr:full":"520 W Mineral King Ave Visalia CA 93291",
    "addr:housenumber":"520",
    "addr:postcode":"93291",
    "addr:street":"W Mineral King Ave",
    "iso:country":"US",
    "sg:address":"520 W Mineral King Ave",
    "sg:city":"Visalia",
    "sg:classifiers":[
        {
            "category":"Building & Trades",
            "subcategory":"Electrical",
            "type":"Services"
        }
    ],
    "sg:phone":"+1 559 625 5223",
    "sg:postcode":"93291",
    "sg:province":"CA",
    "sg:tags":[
        "electric",
        "contractor"
    ],
    "wof:name":"Collins Electric Inc",
    "wof:placetype":"venue"
},
  "geometry": {"coordinates":[-119.296723,36.327423],"type":"Point"}
}