{
  "type": "Feature",
  "properties": {
    "iso:country":"US",
    "sg:address":"2916 Northgate Blvd",
    "sg:city":"Sacramento",
    "sg:classifiers":[
        {
            "category":"Retail",
            "subcategory":"Auto Repair",
            "type":"Services"
        }
    ],
    "sg:phone":"+1 916 978 1204",
    "sg:postcode":"95833",
    "sg:province":"CA",
    "sg:website":"www.topautorepair.net",
    "wof:name":"Top Auto Repair",
    "wof:placetype":"venue"
},
  "geometry": {"coordinates":[-121.47525,38.618169],"type":"Point"}
}