{
  "type": "Feature",
  "properties": {
    "iso:country":"US",
    "sg:address":"29750 Cll Palmas",
    "sg:city":"Temecula",
    "sg:classifiers":[
        {
            "category":"Freight",
            "type":"Transportation"
        }
    ],
    "sg:phone":"+1 951 506 0846",
    "sg:postcode":"92591",
    "sg:province":"CA",
    "wof:name":"AA Transportation",
    "wof:placetype":"venue"
},
  "geometry": {"coordinates":[-117.143685,33.515135],"type":"Point"}
}