{
  "type": "Feature",
  "properties": {
    "addr:full":"13600 Pawnee Rd Apple Valley CA 92308",
    "addr:housenumber":"13600",
    "addr:postcode":"92308",
    "addr:street":"Pawnee Rd",
    "iso:country":"US",
    "sg:address":"13600 Pawnee Rd",
    "sg:city":"Apple Valley",
    "sg:classifiers":[
        {
            "category":"Building & Trades",
            "subcategory":"Construction",
            "type":"Services"
        }
    ],
    "sg:phone":"+1 760 247 8533",
    "sg:postcode":"92308",
    "sg:province":"CA",
    "sg:tags":[
        "pipe",
        "line",
        "contractor"
    ],
    "wof:name":"Roland Engineering",
    "wof:placetype":"venue"
},
  "geometry": {"coordinates":[-117.186483,34.498607],"type":"Point"}
}