{
  "type": "Feature",
  "properties": {
    "iso:country":"US",
    "sg:address":"475 W Stetson Ave # T211",
    "sg:city":"Hemet",
    "sg:classifiers":[
        {
            "category":"Building & Trades",
            "subcategory":"Plumbing",
            "type":"Services"
        },
        {
            "category":"Wholesale",
            "subcategory":"Construction Materials",
            "type":"Manufacturing & Wholesale Goods"
        }
    ],
    "sg:phone":"+1 951 927 9939",
    "sg:postcode":"92543",
    "sg:province":"CA",
    "sg:tags":[
        "plumber",
        "supply",
        "part",
        "cleaning",
        "fixtures",
        "plumbing-drain",
        "sewer"
    ],
    "sg:website":"http://almostretiredplumber.com",
    "wof:name":"Almost Retired Plumber",
    "wof:placetype":"venue"
},
  "geometry": {"coordinates":[-116.975461,33.729389],"type":"Point"}
}