{
  "type": "Feature",
  "properties": {
    "iso:country":"US",
    "sg:address":"16900 Sherman Way",
    "sg:city":"Van Nuys",
    "sg:classifiers":[
        {
            "category":"Retail",
            "subcategory":"Laundry & Dry Cleaning",
            "type":"Services"
        }
    ],
    "sg:phone":"+1 818 988 9344",
    "sg:postcode":"91406",
    "sg:province":"CA",
    "sg:tags":[
        "cleaners"
    ],
    "wof:name":"Jasmin Cleaner",
    "wof:placetype":"venue"
},
  "geometry": {"coordinates":[-118.50330700000001,34.201035],"type":"Point"}
}