{
  "type": "Feature",
  "properties": {
    "addr:full":"3517 W St Eureka CA 95503",
    "addr:housenumber":"3517",
    "addr:postcode":"95503",
    "addr:street":"W St",
    "iso:country":"US",
    "sg:address":"3517 W St",
    "sg:city":"Eureka",
    "sg:classifiers":[
        {
            "category":"Retail",
            "subcategory":"Auto Repair",
            "type":"Services"
        }
    ],
    "sg:phone":"+1 707 445 6507",
    "sg:postcode":"95503",
    "sg:province":"CA",
    "sg:tags":[
        "automobile",
        "truck",
        "maintenance"
    ],
    "wof:name":"National Guard",
    "wof:placetype":"venue"
},
  "geometry": {"coordinates":[-124.144345,40.775689],"type":"Point"}
}