{
  "type": "Feature",
  "properties": {
    "iso:country":"US",
    "sg:address":"226 S Gilbert St",
    "sg:city":"Hemet",
    "sg:classifiers":[
        {
            "category":"Retail",
            "subcategory":"Auto Repair",
            "type":"Services"
        }
    ],
    "sg:phone":"+1 951 766 4891",
    "sg:postcode":"92544",
    "sg:province":"CA",
    "sg:tags":[
        "repairing",
        "automobile"
    ],
    "wof:name":"J & M Auto Repair",
    "wof:placetype":"venue"
},
  "geometry": {"coordinates":[-116.975906,33.744377],"type":"Point"}
}