{
  "type": "Feature",
  "properties": {
    "iso:country":"US",
    "sg:address":"7502 Warner Ave",
    "sg:city":"Huntington Beach",
    "sg:classifiers":[
        {
            "category":"Home & Garden",
            "subcategory":"Building Materials",
            "type":"Retail Goods"
        }
    ],
    "sg:phone":"+1 714 842 1500",
    "sg:postcode":"92647",
    "sg:province":"CA",
    "sg:tags":[
        "supply"
    ],
    "wof:name":"Quality Building Supply",
    "wof:placetype":"venue"
},
  "geometry": {"coordinates":[-117.99750299999999,33.714967],"type":"Point"}
}