{
  "type": "Feature",
  "properties": {
    "iso:country":"US",
    "sg:address":"6161 Alvarado Road",
    "sg:city":"San Diego",
    "sg:classifiers":[
        {
            "category":"Education",
            "subcategory":"Special Training",
            "type":"Public Place"
        },
        {
            "category":"Education",
            "subcategory":"University",
            "type":"Public Place"
        }
    ],
    "sg:phone":"+1 619 594 2747",
    "sg:postcode":"92120",
    "sg:province":"CA",
    "sg:tags":[
        "school",
        "college",
        "language"
    ],
    "wof:name":"San Diego State University",
    "wof:placetype":"venue"
},
  "geometry": {"coordinates":[-117.065258,32.779106],"type":"Point"}
}