{
  "type": "Feature",
  "properties": {
    "iso:country":"US",
    "sg:address":"42 Stockton St",
    "sg:city":"San Francisco",
    "sg:classifiers":[
        {
            "category":"Food & Beverages",
            "subcategory":"Chocolate",
            "type":"Retail Goods"
        }
    ],
    "sg:phone":"+1 415 397 3030",
    "sg:postcode":"94108",
    "sg:province":"CA",
    "sg:tags":[
        "shop",
        "chocolatiers"
    ],
    "sg:website":"www.ghirardelli.com",
    "wof:name":"Ghirardelli Chocolate",
    "wof:placetype":"venue"
},
  "geometry": {"coordinates":[-122.406325,37.786217],"type":"Point"}
}