{
  "type": "Feature",
  "properties": {
    "addr:full":"5218 Topanga Canyon Blvd Woodland Hills CA 91364",
    "addr:housenumber":"5218",
    "addr:postcode":"91364",
    "addr:street":"Topanga Canyon Blvd",
    "iso:country":"US",
    "sg:address":"5218 Topanga Canyon Blvd",
    "sg:city":"Woodland Hills",
    "sg:classifiers":[
        {
            "category":"Shopping",
            "type":"Retail Goods"
        }
    ],
    "sg:phone":"+1 818 992 5454",
    "sg:postcode":"91364",
    "sg:province":"CA",
    "sg:tags":[
        "mural"
    ],
    "wof:name":"Dolly Lilly Signs & Murals",
    "wof:placetype":"venue"
},
  "geometry": {"coordinates":[-118.60575799999999,34.164651],"type":"Point"}
}