{
  "type": "Feature",
  "properties": {
    "iso:country":"US",
    "sg:address":"5218 Topanga Canyon Blvd",
    "sg:city":"Woodland Hills",
    "sg:classifiers":[
        {
            "category":"Shopping",
            "type":"Retail Goods"
        }
    ],
    "sg:phone":"+1 818 992 5454",
    "sg:postcode":"91364",
    "sg:province":"CA",
    "sg:tags":[
        "mural"
    ],
    "wof:name":"Dolly Lilly Signs & Murals",
    "wof:placetype":"venue"
},
  "geometry": {"coordinates":[-118.605758,34.164651],"type":"Point"}
}