{
  "type": "Feature",
  "properties": {
    "addr:full":"3021 Airport Ave Santa Monica CA 90405",
    "addr:housenumber":"3021",
    "addr:postcode":"90405",
    "addr:street":"Airport Ave",
    "iso:country":"US",
    "sg:address":"3021 Airport Ave",
    "sg:city":"Santa Monica",
    "sg:classifiers":[
        {
            "category":"Shopping",
            "subcategory":"Hobbies, Toys, & Games",
            "type":"Retail Goods"
        },
        {
            "category":"Shopping",
            "subcategory":"Gifts & Souvenirs",
            "type":"Retail Goods"
        }
    ],
    "sg:phone":"+1 310 391 6877",
    "sg:postcode":"90405",
    "sg:province":"CA",
    "sg:tags":[
        "basket"
    ],
    "sg:website":"www.artfullbaskets.com",
    "wof:name":"Artfull Baskets",
    "wof:placetype":"venue"
},
  "geometry": {"coordinates":[-118.451348,34.012919],"type":"Point"}
}