{
  "type": "Feature",
  "properties": {
    "iso:country":"US",
    "sg:address":"1103 E Clark Ave",
    "sg:city":"Santa Maria",
    "sg:classifiers":[
        {
            "category":"Professional",
            "subcategory":"Accounting & Tax Preparation",
            "type":"Services"
        }
    ],
    "sg:phone":"+1 805 937 8880",
    "sg:postcode":"93455",
    "sg:province":"CA",
    "sg:tags":[
        "return",
        "filing"
    ],
    "wof:name":"H & R Block Tax Svc",
    "wof:placetype":"venue"
},
  "geometry": {"coordinates":[-120.414507,34.865124],"type":"Point"}
}