{
  "type": "Feature",
  "properties": {
    "iso:country":"US",
    "sg:address":"1600 S Main St",
    "sg:city":"Walnut Creek",
    "sg:classifiers":[
        {
            "category":"Professional",
            "subcategory":"Lawyer & Legal Services",
            "type":"Services"
        }
    ],
    "sg:phone":"+1 925 891 2345",
    "sg:postcode":"94596",
    "sg:province":"CA",
    "sg:tags":[
        "attorney"
    ],
    "wof:name":"Daniel P Beaver Law Offices",
    "wof:placetype":"venue"
},
  "geometry": {"coordinates":[-122.057364,37.890072],"type":"Point"}
}