{
  "type": "Feature",
  "properties": {
    "addr:full":"2594 Telegraph Ave Berkeley CA 94704",
    "addr:housenumber":"2594",
    "addr:postcode":"94704",
    "addr:street":"Telegraph Ave",
    "iso:country":"US",
    "sg:address":"2594 Telegraph Ave",
    "sg:city":"Berkeley",
    "sg:classifiers":[
        {
            "category":"Shopping",
            "subcategory":"Mobile Phones",
            "type":"Retail Goods"
        }
    ],
    "sg:phone":"+1 510 644 2277",
    "sg:postcode":"94704",
    "sg:province":"CA",
    "wof:name":"UniTech Electronics",
    "wof:placetype":"venue"
},
  "geometry": {"coordinates":[-122.25872200000001,37.863354],"type":"Point"}
}