{
  "type": "Feature",
  "properties": {
    "iso:country":"US",
    "sg:address":"3206 W 8th St",
    "sg:city":"Los Angeles",
    "sg:classifiers":[
        {
            "category":"Travel",
            "subcategory":"Hotels & Motels",
            "type":"Entertainment"
        }
    ],
    "sg:phone":"+1 213 389 6711",
    "sg:postcode":"90005",
    "sg:province":"CA",
    "wof:name":"East West Hotel",
    "wof:placetype":"venue"
},
  "geometry": {"coordinates":[-118.297997,34.0578],"type":"Point"}
}