{
  "type": "Feature",
  "properties": {
    "addr:full":"415 E Washington Blvd Los Angeles CA 90015",
    "addr:housenumber":"415",
    "addr:postcode":"90015",
    "addr:street":"E Washington Blvd",
    "iso:country":"US",
    "sg:address":"415 E Washington Blvd",
    "sg:city":"Los Angeles",
    "sg:classifiers":[
        {
            "category":"Manufacturing",
            "subcategory":"Apparel",
            "type":"Manufacturing & Wholesale Goods"
        }
    ],
    "sg:phone":"+1 213 749 5550",
    "sg:postcode":"90015",
    "sg:province":"CA",
    "sg:tags":[
        "sewing",
        "contractor"
    ],
    "wof:name":"Rebel Fabrics Inc",
    "wof:placetype":"venue"
},
  "geometry": {"coordinates":[-118.260352,34.029087],"type":"Point"}
}