{
  "type": "Feature",
  "properties": {
    "iso:country":"US",
    "sg:address":"10470 Foothill Blvd",
    "sg:city":"Rancho Cucamonga",
    "sg:classifiers":[
        {
            "category":"Professional",
            "subcategory":"Lawyer & Legal Services",
            "type":"Services"
        }
    ],
    "sg:phone":"+1 909 483 6540",
    "sg:postcode":"91730",
    "sg:province":"CA",
    "sg:tags":[
        "attorney"
    ],
    "wof:name":"Epsten Grinnell & Howell",
    "wof:placetype":"venue"
},
  "geometry": {"coordinates":[-117.578116,34.106648],"type":"Point"}
}