{
  "type": "Feature",
  "properties": {
    "iso:country":"US",
    "sg:address":"2542 Avalon St",
    "sg:city":"Riverside",
    "sg:classifiers":[
        {
            "category":"Building & Trades",
            "subcategory":"Electrical",
            "type":"Services"
        }
    ],
    "sg:phone":"+1 951 784 1410",
    "sg:postcode":"92509",
    "sg:province":"CA",
    "sg:tags":[
        "electrical",
        "contractor"
    ],
    "wof:name":"Sierra Pacific Elec Contg",
    "wof:placetype":"venue"
},
  "geometry": {"coordinates":[-117.394927,34.014247],"type":"Point"}
}