{
  "type": "Feature",
  "properties": {
    "addr:full":"1650 N Grove Ave Ontario CA 91764",
    "addr:housenumber":"1650",
    "addr:postcode":"91764",
    "addr:street":"N Grove Ave",
    "iso:country":"US",
    "sg:address":"1650 N Grove Ave",
    "sg:city":"Ontario",
    "sg:classifiers":[
        {
            "category":"Food & Beverages",
            "subcategory":"Dairy",
            "type":"Retail Goods"
        }
    ],
    "sg:phone":"+1 909 982 0211",
    "sg:postcode":"91764",
    "sg:province":"CA",
    "sg:tags":[
        "product"
    ],
    "wof:name":"Alta Dena Drive-In Dairy",
    "wof:placetype":"venue"
},
  "geometry": {"coordinates":[-117.628568,34.088073],"type":"Point"}
}