{
  "type": "Feature",
  "properties": {
    "addr:full":"21739 Ambar Dr Woodland Hills CA 91364",
    "addr:postcode":"21739;91364",
    "addr:street":"Ambar Dr",
    "iso:country":"US",
    "sg:address":"21739 Ambar Dr",
    "sg:city":"Woodland Hills",
    "sg:classifiers":[
        {
            "category":"Building & Trades",
            "subcategory":"Construction",
            "type":"Services"
        }
    ],
    "sg:phone":"+1 818 340 7978",
    "sg:postcode":"91364",
    "sg:province":"CA",
    "sg:tags":[
        "designer",
        "dealer",
        "pool",
        "swimming"
    ],
    "sg:website":"www.rockdesigns.com",
    "wof:name":"Rock Designs",
    "wof:placetype":"venue"
},
  "geometry": {"coordinates":[-118.603336,34.142952],"type":"Point"}
}