{
  "type": "Feature",
  "properties": {
    "iso:country":"US",
    "sg:address":"1555 Bayshore Hwy",
    "sg:city":"Burlingame",
    "sg:classifiers":[
        {
            "category":"Insurance",
            "subcategory":"Insurance Agent",
            "type":"Services"
        }
    ],
    "sg:phone":"+1 650 552 0880",
    "sg:postcode":"94010",
    "sg:province":"CA",
    "wof:name":"Euler American Credit",
    "wof:placetype":"venue"
},
  "geometry": {"coordinates":[-122.366644,37.598566],"type":"Point"}
}