{
  "type": "Feature",
  "properties": {
    "addr:full":"9530 Towne Centre Dr San Diego CA 92121",
    "addr:housenumber":"9530",
    "addr:postcode":"92121",
    "addr:street":"Towne Centre Dr",
    "iso:country":"US",
    "sg:address":"9530 Towne Centre Dr",
    "sg:city":"San Diego",
    "sg:classifiers":[
        {
            "category":"Organizations",
            "subcategory":"Non-profit Organization",
            "type":"Services"
        },
        {
            "category":"Utilities",
            "subcategory":"Telephone",
            "type":"Services"
        }
    ],
    "sg:phone":"+1 858 638 9290",
    "sg:postcode":"92121",
    "sg:province":"CA",
    "sg:tags":[
        "communications",
        "medical",
        "management"
    ],
    "wof:name":"Cpu Medical Management Systems",
    "wof:placetype":"venue"
},
  "geometry": {"coordinates":[-117.20847500000001,32.88079],"type":"Point"}
}