{
  "type": "Feature",
  "properties": {
    "iso:country":"US",
    "sg:address":"7239 Topanga Canyon Blvd",
    "sg:city":"Canoga Park",
    "sg:classifiers":[
        {
            "category":"Travel",
            "subcategory":"Travel Agent",
            "type":"Entertainment"
        }
    ],
    "sg:phone":"+1 818 594 0081",
    "sg:postcode":"91303",
    "sg:province":"CA",
    "sg:tags":[
        "agency",
        "bureau"
    ],
    "wof:name":"Invelj Travel Inc",
    "wof:placetype":"venue"
},
  "geometry": {"coordinates":[-118.605931,34.202732],"type":"Point"}
}