{
  "type": "Feature",
  "properties": {
    "addr:full":"320 Tesconi Cir Santa Rosa CA 95401",
    "addr:housenumber":"320",
    "addr:postcode":"95401",
    "addr:street":"Tesconi Cir",
    "iso:country":"US",
    "sg:address":"320 Tesconi Cir",
    "sg:city":"Santa Rosa",
    "sg:classifiers":[
        {
            "category":"Professional",
            "type":"Services"
        }
    ],
    "sg:phone":"+1 707 526 9204",
    "sg:postcode":"95401",
    "sg:province":"CA",
    "sg:tags":[
        "establishment"
    ],
    "wof:name":"Clarity Solutions",
    "wof:placetype":"venue"
},
  "geometry": {"coordinates":[-122.73256600000001,38.448106],"type":"Point"}
}