{
  "type": "Feature",
  "properties": {
    "iso:country":"US",
    "sg:address":"28682 Sea Pt",
    "sg:city":"Laguna Niguel",
    "sg:classifiers":[
        {
            "category":"Manufacturing",
            "subcategory":"Jewelry",
            "type":"Manufacturing & Wholesale Goods"
        }
    ],
    "sg:phone":"+1 949 831 2981",
    "sg:postcode":"92677",
    "sg:province":"CA",
    "sg:tags":[
        "precious",
        "metal",
        "mfg"
    ],
    "wof:name":"Uniquely U 14 Kt Jwl",
    "wof:placetype":"venue"
},
  "geometry": {"coordinates":[-117.71883200000001,33.546451],"type":"Point"}
}