{
  "type": "Feature",
  "properties": {
    "iso:country":"US",
    "sg:address":"27800 Medical Center Road Suite 351",
    "sg:city":"Mission Viejo",
    "sg:classifiers":[
        {
            "category":"Health Services",
            "subcategory":"Doctor",
            "type":"Services"
        }
    ],
    "sg:phone":"+1 949 364 9107",
    "sg:postcode":"92691",
    "sg:province":"CA",
    "wof:name":"Cosmetic & Reconstructive Plastic Surgery",
    "wof:placetype":"venue"
},
  "geometry": {"coordinates":[-117.66585000000001,33.560088],"type":"Point"}
}