{
  "type": "Feature",
  "properties": {
    "iso:country":"US",
    "sg:address":"13060 Glenoaks Blvd",
    "sg:city":"Sylmar",
    "sg:classifiers":[
        {
            "category":"Restaurant",
            "type":"Food & Drink"
        }
    ],
    "sg:phone":"+1 818 367 7153",
    "sg:postcode":"91342",
    "sg:province":"CA",
    "wof:name":"Carniceria Los Toritos",
    "wof:placetype":"venue"
},
  "geometry": {"coordinates":[-118.450408,34.308192],"type":"Point"}
}