{
  "type": "Feature",
  "properties": {
    "iso:country":"US",
    "sg:address":"12183 Firestone Blvd",
    "sg:city":"Norwalk",
    "sg:classifiers":[
        {
            "category":"Health Services",
            "subcategory":"Nursing And Care Facility",
            "type":"Services"
        }
    ],
    "sg:phone":"+1 562 651 1045",
    "sg:postcode":"90650",
    "sg:province":"CA",
    "sg:tags":[
        "skilled"
    ],
    "wof:name":"Faith Care Hospice Inc",
    "wof:placetype":"venue"
},
  "geometry": {"coordinates":[-118.073605,33.908508],"type":"Point"}
}