{
  "type": "Feature",
  "properties": {
    "addr:full":"5034 Darrah Rd Mariposa CA 95338",
    "addr:housenumber":"5034",
    "addr:postcode":"95338",
    "addr:street":"Darrah Rd",
    "iso:country":"US",
    "sg:address":"5034 Darrah Rd",
    "sg:city":"Mariposa",
    "sg:classifiers":[
        {
            "category":"Restaurant",
            "type":"Food & Drink"
        }
    ],
    "sg:phone":"+1 209 742 6936",
    "sg:postcode":"95338",
    "sg:province":"CA",
    "wof:name":"The White House",
    "wof:placetype":"venue"
},
  "geometry": {"coordinates":[-119.88647,37.465055],"type":"Point"}
}