{
  "type": "Feature",
  "properties": {
    "addr:full":"2241 E el Segundo Blvd Compton CA 90222",
    "addr:housenumber":"2241",
    "addr:postcode":"90222",
    "addr:street":"E El Segundo Blvd",
    "iso:country":"US",
    "sg:address":"2241 E el Segundo Blvd",
    "sg:city":"Compton",
    "sg:classifiers":[
        {
            "category":"Government",
            "subcategory":"Post Office",
            "type":"Public Place"
        }
    ],
    "sg:phone":"+1 310 638 1753",
    "sg:postcode":"90222",
    "sg:province":"CA",
    "wof:name":"US Post Office",
    "wof:placetype":"venue"
},
  "geometry": {"coordinates":[-118.23199,33.916236],"type":"Point"}
}