{
  "type": "Feature",
  "properties": {
    "addr:full":"185 Folsom Ave Hayward CA 94544",
    "addr:housenumber":"185",
    "addr:postcode":"94544",
    "addr:street":"Folsom Ave",
    "iso:country":"US",
    "sg:address":"185 Folsom Ave",
    "sg:city":"Hayward",
    "sg:classifiers":[
        {
            "category":"Organizations",
            "subcategory":"Religious Organization",
            "type":"Services"
        }
    ],
    "sg:phone":"+1 510 786 0357",
    "sg:postcode":"94544",
    "sg:province":"CA",
    "sg:tags":[
        "church"
    ],
    "wof:name":"Apostolic Faith Tabernacle",
    "wof:placetype":"venue"
},
  "geometry": {"coordinates":[-122.059214,37.627557],"type":"Point"}
}