{
  "type": "Feature",
  "properties": {
    "iso:country":"US",
    "sg:address":"7817 Shrader Cir",
    "sg:city":"Sacramento",
    "sg:classifiers":[
        {
            "category":"Building & Trades",
            "subcategory":"Landscaping Services",
            "type":"Services"
        }
    ],
    "sg:phone":"+1 916 427 9397",
    "sg:postcode":"95832",
    "sg:province":"CA",
    "sg:tags":[
        "tree"
    ],
    "wof:name":"Cn Tree Service",
    "wof:placetype":"venue"
},
  "geometry": {"coordinates":[-121.468384,38.472627],"type":"Point"}
}