{
  "type": "Feature",
  "properties": {
    "addr:full":"3961 Moore St Los Angeles CA 90066",
    "addr:housenumber":"3961",
    "addr:postcode":"90066",
    "addr:street":"Moore St",
    "iso:country":"US",
    "sg:address":"3961 Moore St",
    "sg:city":"Los Angeles",
    "sg:classifiers":[
        {
            "category":"Wholesale",
            "subcategory":"Durable Goods & Equipment",
            "type":"Manufacturing & Wholesale Goods"
        }
    ],
    "sg:phone":"+1 310 574 0806",
    "sg:postcode":"90066",
    "sg:province":"CA",
    "wof:name":"Faviola Andrade",
    "wof:placetype":"venue"
},
  "geometry": {"coordinates":[-118.437766,33.996227],"type":"Point"}
}