{
  "type": "Feature",
  "properties": {
    "addr:full":"2308 6th St Oakland CA 94710",
    "addr:housenumber":"2308",
    "addr:postcode":"94710",
    "addr:street":"6Th St",
    "iso:country":"US",
    "sg:address":"2308 6th St",
    "sg:city":"Oakland",
    "sg:classifiers":[
        {
            "category":"Health Services",
            "subcategory":"Doctor",
            "type":"Services"
        }
    ],
    "sg:phone":"+1 510 845 8800",
    "sg:postcode":"94710",
    "sg:province":"CA",
    "sg:tags":[
        "psychiatrist"
    ],
    "wof:name":"Alice A Jones MD",
    "wof:placetype":"venue"
},
  "geometry": {"coordinates":[-122.296133,37.863171],"type":"Point"}
}