{
  "type": "Feature",
  "properties": {
    "addr:full":"12955 El Camino Real San Diego CA 92130",
    "addr:housenumber":"12955",
    "addr:postcode":"92130",
    "addr:street":"El Camino Real",
    "iso:country":"US",
    "sg:address":"12955 El Camino Real",
    "sg:city":"San Diego",
    "sg:classifiers":[
        {
            "category":"Ice Cream",
            "type":"Food & Drink"
        }
    ],
    "sg:menulink":"http://www.allmenus.com/ca/san-diego/183966-cold-stone-creamery/menu/",
    "sg:phone":"+1 858 792 8533",
    "sg:postcode":"92130",
    "sg:province":"CA",
    "sg:tags":[
        "smoothy",
        "juice",
        "american"
    ],
    "wof:name":"Cold Stone Creamery",
    "wof:placetype":"venue"
},
  "geometry": {"coordinates":[-117.232033,32.952415],"type":"Point"}
}