{
  "type": "Feature",
  "properties": {
    "addr:full":"608 Santa Monica Blvd Santa Monica CA 90401",
    "addr:housenumber":"608",
    "addr:postcode":"90401",
    "addr:street":"Santa Monica Blvd",
    "iso:country":"US",
    "sg:address":"608 Santa Monica Blvd",
    "sg:city":"Santa Monica",
    "sg:classifiers":[
        {
            "category":"Communications",
            "subcategory":"Film & Video Production",
            "type":"Services"
        }
    ],
    "sg:phone":"+1 310 394 7600",
    "sg:postcode":"90401",
    "sg:province":"CA",
    "sg:tags":[
        "animated"
    ],
    "wof:name":"Charlie Co Corp",
    "wof:placetype":"venue"
},
  "geometry": {"coordinates":[-118.492789,34.018224],"type":"Point"}
}