{
  "type": "Feature",
  "properties": {
    "iso:country":"US",
    "sg:address":"1633 Staunton Ave",
    "sg:city":"Los Angeles",
    "sg:classifiers":[
        {
            "category":"Wholesale",
            "subcategory":"Durable Goods & Equipment",
            "type":"Manufacturing & Wholesale Goods"
        }
    ],
    "sg:phone":"+1 213 747 4547",
    "sg:postcode":"90021",
    "sg:province":"CA",
    "sg:tags":[
        "exporter"
    ],
    "wof:name":"Tamid Enterprises Inc",
    "wof:placetype":"venue"
},
  "geometry": {"coordinates":[-118.24165499999999,34.020681],"type":"Point"}
}