{
  "type": "Feature",
  "properties": {
    "iso:country":"US",
    "sg:address":"5855 Capistrano Ave",
    "sg:city":"Atascadero",
    "sg:classifiers":[
        {
            "category":"Professional",
            "subcategory":"Lawyer & Legal Services",
            "type":"Services"
        }
    ],
    "sg:phone":"+1 805 466 6644",
    "sg:postcode":"93422",
    "sg:province":"CA",
    "sg:tags":[
        "attorney"
    ],
    "wof:name":"Glen R Lewis A Pro Law Corp",
    "wof:placetype":"venue"
},
  "geometry": {"coordinates":[-120.664163,35.490094],"type":"Point"}
}