{
  "type": "Feature",
  "properties": {
    "iso:country":"US",
    "sg:address":"2401 Waterman Blvd",
    "sg:city":"Fairfield",
    "sg:classifiers":[
        {
            "category":"Professional",
            "subcategory":"Business Services",
            "type":"Services"
        }
    ],
    "sg:phone":"+1 707 580 6161",
    "sg:postcode":"94534",
    "sg:province":"CA",
    "sg:tags":[
        "inventory"
    ],
    "wof:name":"ICP",
    "wof:placetype":"venue"
},
  "geometry": {"coordinates":[-122.062799,38.269478],"type":"Point"}
}