{
  "type": "Feature",
  "properties": {
    "addr:full":"20750 Ventura Blvd Woodland Hills CA 91364",
    "addr:housenumber":"20750",
    "addr:postcode":"91364",
    "addr:street":"Ventura Blvd",
    "iso:country":"US",
    "sg:address":"20750 Ventura Blvd",
    "sg:city":"Woodland Hills",
    "sg:classifiers":[
        {
            "category":"Social Services",
            "type":"Services"
        }
    ],
    "sg:phone":"+1 818 888 1524",
    "sg:postcode":"91364",
    "sg:province":"CA",
    "sg:tags":[
        "counselor",
        "marriage",
        "family"
    ],
    "wof:name":"Diane S Smith",
    "wof:placetype":"venue"
},
  "geometry": {"coordinates":[-118.58420099999999,34.16682],"type":"Point"}
}