{
  "type": "Feature",
  "properties": {
    "addr:full":"411 Jessie Ave Hanford CA 93230",
    "addr:housenumber":"411",
    "addr:postcode":"ca 93230",
    "addr:street":"Jessie Ave",
    "iso:country":"US",
    "sg:address":"411 Jessie Ave",
    "sg:city":"Hanford",
    "sg:classifiers":[
        {
            "category":"Retail",
            "subcategory":"Auto Repair",
            "type":"Services"
        }
    ],
    "sg:phone":"+1 559 583 0484",
    "sg:postcode":"93230",
    "sg:province":"CA",
    "sg:tags":[
        "automobile",
        "customizing"
    ],
    "wof:name":"California Tint Co",
    "wof:placetype":"venue"
},
  "geometry": {"coordinates":[-119.634471,36.329789],"type":"Point"}
}