{
  "type": "Feature",
  "properties": {
    "addr:full":"2101 S Hellman Ave Ontario CA 91761",
    "addr:housenumber":"2101",
    "addr:postcode":"91761",
    "addr:street":"S Hellman Ave",
    "iso:country":"US",
    "sg:address":"2101 S Hellman Ave",
    "sg:city":"Ontario",
    "sg:classifiers":[
        {
            "category":"Manufacturing",
            "subcategory":"Tools & Machinery",
            "type":"Manufacturing & Wholesale Goods"
        }
    ],
    "sg:phone":"+1 909 947 0253",
    "sg:postcode":"91761",
    "sg:province":"CA",
    "sg:tags":[
        "chemical",
        "industrial",
        "milling",
        "mfg"
    ],
    "wof:name":"Powers Manufacturing",
    "wof:placetype":"venue"
},
  "geometry": {"coordinates":[-117.60202200000001,34.033915],"type":"Point"}
}