{
  "type": "Feature",
  "properties": {
    "iso:country":"US",
    "sg:address":"4391 Pell Dr",
    "sg:city":"Sacramento",
    "sg:classifiers":[
        {
            "category":"Freight",
            "type":"Transportation"
        }
    ],
    "sg:phone":"+1 916 641 5588",
    "sg:postcode":"95838",
    "sg:province":"CA",
    "sg:tags":[
        "repair",
        "rail",
        "car"
    ],
    "wof:name":"Progress Rail Services Corp",
    "wof:placetype":"venue"
},
  "geometry": {"coordinates":[-121.470958,38.648286],"type":"Point"}
}