{
  "type": "Feature",
  "properties": {
    "addr:full":"32300 Almaden Blvd Union City CA 94587",
    "addr:postcode":"32300;94587",
    "addr:street":"Almaden Blvd",
    "iso:country":"US",
    "sg:address":"32300 Almaden Blvd",
    "sg:city":"Union City",
    "sg:classifiers":[
        {
            "category":"Real Estate",
            "subcategory":"Real Estate Operator",
            "type":"Services"
        }
    ],
    "sg:phone":"+1 510 471 6001",
    "sg:postcode":"94587",
    "sg:province":"CA",
    "sg:tags":[
        "apartment"
    ],
    "wof:name":"Los Robles Apartments",
    "wof:placetype":"venue"
},
  "geometry": {"coordinates":[-122.05535500000001,37.593977],"type":"Point"}
}