{
  "type": "Feature",
  "properties": {
    "iso:country":"US",
    "sg:address":"2512 Coffee Rd",
    "sg:city":"Modesto",
    "sg:classifiers":[
        {
            "category":"Food & Beverages",
            "subcategory":"Liquor & Beverages",
            "type":"Retail Goods"
        }
    ],
    "sg:phone":"+1 209 522 0266",
    "sg:postcode":"95355",
    "sg:province":"CA",
    "sg:tags":[
        "beer",
        "spirit",
        "wine"
    ],
    "wof:name":"Vineyard 76 At Coffee",
    "wof:placetype":"venue"
},
  "geometry": {"coordinates":[-120.975998,37.676399],"type":"Point"}
}