{
  "type": "Feature",
  "properties": {
    "addr:full":"611 N A St Oxnard CA 93030",
    "addr:housenumber":"611",
    "addr:postcode":"93030",
    "addr:street":"N A St",
    "iso:country":"US",
    "sg:address":"611 N A St",
    "sg:city":"Oxnard",
    "sg:classifiers":[
        {
            "category":"Personal",
            "subcategory":"Beauty Salon",
            "type":"Services"
        }
    ],
    "sg:phone":"+1 805 485 6069",
    "sg:postcode":"93030",
    "sg:province":"CA",
    "wof:name":"611 Place Beauty Salon",
    "wof:placetype":"venue"
},
  "geometry": {"coordinates":[-119.178528,34.209235],"type":"Point"}
}