{
  "type": "Feature",
  "properties": {
    "iso:country":"US",
    "sg:address":"2929 Flood Ave",
    "sg:city":"Redwood City",
    "sg:classifiers":[
        {
            "category":"Home & Garden",
            "subcategory":"Building Materials",
            "type":"Retail Goods"
        }
    ],
    "sg:phone":"+1 650 367 7203",
    "sg:postcode":"94063",
    "sg:province":"CA",
    "sg:tags":[
        "lumber"
    ],
    "wof:name":"Palo Alto Lumber Co",
    "wof:placetype":"venue"
},
  "geometry": {"coordinates":[-122.207137,37.475766],"type":"Point"}
}