{
  "type": "Feature",
  "properties": {
    "iso:country":"US",
    "sg:address":"501 7th St",
    "sg:city":"Modesto",
    "sg:classifiers":[
        {
            "category":"Retail",
            "subcategory":"Auto Rental",
            "type":"Services"
        }
    ],
    "sg:phone":"+1 209 523 2037",
    "sg:postcode":"95354",
    "sg:province":"CA",
    "sg:tags":[
        "renting",
        "truck",
        "leasing"
    ],
    "wof:name":"U-Haul Co",
    "wof:placetype":"venue"
},
  "geometry": {"coordinates":[-120.998535,37.634506],"type":"Point"}
}