{
  "type": "Feature",
  "properties": {
    "addr:full":"411 Center St Los Angeles CA 90012",
    "addr:housenumber":"411",
    "addr:postcode":"90012",
    "addr:street":"Center St",
    "iso:country":"US",
    "sg:address":"411 Center St",
    "sg:city":"Los Angeles",
    "sg:classifiers":[
        {
            "category":"Manufacturing",
            "subcategory":"Food",
            "type":"Manufacturing & Wholesale Goods"
        }
    ],
    "sg:phone":"+1 213 625 0038",
    "sg:postcode":"90012",
    "sg:province":"CA",
    "sg:tags":[
        "fish",
        "packaged",
        "mfg"
    ],
    "wof:name":"Processers Fish King",
    "wof:placetype":"venue"
},
  "geometry": {"coordinates":[-118.23154,34.051678],"type":"Point"}
}