{
  "type": "Feature",
  "properties": {
    "addr:full":"1445 Harrison St Oakland CA 94612",
    "addr:housenumber":"1445",
    "addr:postcode":"94612",
    "addr:street":"Harrison St",
    "iso:country":"US",
    "sg:address":"1445 Harrison St",
    "sg:city":"Oakland",
    "sg:classifiers":[
        {
            "category":"Freight",
            "type":"Transportation"
        }
    ],
    "sg:phone":"+1 510 390 4155",
    "sg:postcode":"94612",
    "sg:province":"CA",
    "wof:name":"Ochgerel Shagdar Trnsprtn",
    "wof:placetype":"venue"
},
  "geometry": {"coordinates":[-122.26732,37.803509],"type":"Point"}
}