{
  "type": "Feature",
  "properties": {
    "iso:country":"US",
    "sg:address":"107 Center St",
    "sg:city":"Roseville",
    "sg:classifiers":[
        {
            "category":"Real Estate",
            "subcategory":"Developer",
            "type":"Services"
        }
    ],
    "sg:phone":"+1 916 788 9731",
    "sg:postcode":"95678",
    "sg:province":"CA",
    "wof:name":"Crossroad Ventures Group",
    "wof:placetype":"venue"
},
  "geometry": {"coordinates":[-121.273033,38.7556],"type":"Point"}
}