{
  "type": "Feature",
  "properties": {
    "iso:country":"US",
    "sg:address":"914 Cedar Pl",
    "sg:city":"Costa Mesa",
    "sg:classifiers":[
        {
            "category":"Building & Trades",
            "subcategory":"Landscaping Services",
            "type":"Services"
        }
    ],
    "sg:phone":"+1 949 548 7052",
    "sg:postcode":"92627",
    "sg:province":"CA",
    "wof:name":"Wallys Gardening Service",
    "wof:placetype":"venue"
},
  "geometry": {"coordinates":[-117.93822,33.644848],"type":"Point"}
}