{
  "type": "Feature",
  "properties": {
    "iso:country":"US",
    "sg:address":"6565 Romaine St Bldg 30",
    "sg:city":"Los Angeles",
    "sg:classifiers":[
        {
            "category":"Arts & Performance",
            "subcategory":"Arts Center",
            "type":"Entertainment"
        }
    ],
    "sg:postcode":"90038",
    "sg:province":"CA",
    "wof:name":"Lurssen Mastering",
    "wof:placetype":"venue"
},
  "geometry": {"coordinates":[-118.332407,34.088927],"type":"Point"}
}