{
  "type": "Feature",
  "properties": {
    "addr:full":"3580 W Temple Ave Pomona CA 91768",
    "addr:housenumber":"3580",
    "addr:postcode":"91768",
    "addr:street":"W Temple Ave",
    "iso:country":"US",
    "sg:address":"3580 W Temple Ave",
    "sg:city":"Pomona",
    "sg:classifiers":[
        {
            "category":"Education",
            "subcategory":"Vocational School",
            "type":"Public Place"
        }
    ],
    "sg:phone":"+1 909 869 8497",
    "sg:postcode":"91768",
    "sg:province":"CA",
    "sg:tags":[
        "training",
        "computer"
    ],
    "sg:website":"www.trinetnt.com",
    "wof:name":"Trinet Network & Training",
    "wof:placetype":"venue"
},
  "geometry": {"coordinates":[-117.815343,34.049789],"type":"Point"}
}