{
  "type": "Feature",
  "properties": {
    "iso:country":"US",
    "sg:address":"845 Hinckley Rd",
    "sg:city":"Burlingame",
    "sg:classifiers":[
        {
            "category":"Airport",
            "type":"Transportation"
        }
    ],
    "sg:phone":"+1 650 259 9100",
    "sg:postcode":"94010",
    "sg:province":"CA",
    "sg:tags":[
        "aircraft",
        "maintenance"
    ],
    "sg:website":"www.mcmeng.com",
    "wof:name":"MCM Engineering Inc",
    "wof:placetype":"venue"
},
  "geometry": {"coordinates":[-122.36907600000001,37.597704],"type":"Point"}
}