{
  "type": "Feature",
  "properties": {
    "addr:full":"105 Percy Ave Yuba City CA 95991",
    "addr:housenumber":"105",
    "addr:postcode":"95991",
    "addr:street":"Percy Ave",
    "iso:country":"US",
    "sg:address":"105 Percy Ave",
    "sg:city":"Yuba City",
    "sg:classifiers":[
        {
            "category":"Personal",
            "subcategory":"Beauty Salon",
            "type":"Services"
        }
    ],
    "sg:phone":"+1 530 673 7461",
    "sg:postcode":"95991",
    "sg:province":"CA",
    "wof:name":"Jo's House Of Hair Design",
    "wof:placetype":"venue"
},
  "geometry": {"coordinates":[-121.613676,39.123516],"type":"Point"}
}