{
  "type": "Feature",
  "properties": {
    "addr:full":"222 E Valley St San Bernardino CA 92408",
    "addr:housenumber":"222",
    "addr:postcode":"92408",
    "addr:street":"E Valley St",
    "iso:country":"US",
    "sg:address":"222 E Valley St",
    "sg:city":"San Bernardino",
    "sg:classifiers":[
        {
            "category":"Building & Trades",
            "subcategory":"Equipment Rental",
            "type":"Services"
        }
    ],
    "sg:phone":"+1 909 884 6333",
    "sg:postcode":"92408",
    "sg:province":"CA",
    "sg:tags":[
        "contractor"
    ],
    "sg:website":"www.neffrental.com",
    "wof:name":"Neff Rental",
    "wof:placetype":"venue"
},
  "geometry": {"coordinates":[-117.279459,34.095928],"type":"Point"}
}