{
  "type": "Feature",
  "properties": {
    "iso:country":"US",
    "sg:address":"11835 Carmel Mountain Rd",
    "sg:city":"San Diego",
    "sg:classifiers":[
        {
            "category":"Shopping",
            "subcategory":"Clothing, Apparel, & Fashions",
            "type":"Retail Goods"
        }
    ],
    "sg:phone":"+1 858 451 2044",
    "sg:postcode":"92129",
    "sg:province":"CA",
    "sg:tags":[
        "tailor"
    ],
    "wof:name":"Chic Tailoring & Alteration",
    "wof:placetype":"venue"
},
  "geometry": {"coordinates":[-117.076311,32.982562],"type":"Point"}
}