{
  "type": "Feature",
  "properties": {
    "iso:country":"US",
    "sg:address":"10100 Galaxy Way",
    "sg:city":"Los Angeles",
    "sg:classifiers":[
        {
            "category":"Real Estate",
            "subcategory":"Real Estate Operator",
            "type":"Services"
        }
    ],
    "sg:phone":"+1 310 557 9000",
    "sg:postcode":"90067",
    "sg:province":"CA",
    "sg:tags":[
        "condominium"
    ],
    "wof:name":"Century Hill Homeowners Assn",
    "wof:placetype":"venue"
},
  "geometry": {"coordinates":[-118.411152,34.055746],"type":"Point"}
}