{
  "type": "Feature",
  "properties": {
    "iso:country":"US",
    "sg:address":"3340 W Ball Rd Ste H",
    "sg:city":"Anaheim",
    "sg:classifiers":[
        {
            "category":"Health Services",
            "subcategory":"Doctor",
            "type":"Services"
        }
    ],
    "sg:phone":"+1 714 952 9413",
    "sg:postcode":"92804",
    "sg:province":"CA",
    "wof:name":"Kim Yong Ho MD",
    "wof:placetype":"venue"
},
  "geometry": {"coordinates":[-118.00700399999999,33.817299],"type":"Point"}
}