{
  "type": "Feature",
  "properties": {
    "iso:country":"US",
    "sg:address":"3714 Main St",
    "sg:city":"San Diego",
    "sg:classifiers":[
        {
            "category":"Retail",
            "subcategory":"Auto Repair",
            "type":"Services"
        }
    ],
    "sg:phone":"+1 619 238 4385",
    "sg:postcode":"92113",
    "sg:province":"CA",
    "sg:tags":[
        "repairing",
        "automobile"
    ],
    "wof:name":"Main Auto Repair",
    "wof:placetype":"venue"
},
  "geometry": {"coordinates":[-117.114227,32.684829],"type":"Point"}
}