{
  "type": "Feature",
  "properties": {
    "addr:full":"P.O. Box 18979 Irvine CA 92623",
    "addr:housenumber":"p.o. box",
    "addr:postcode":"92623",
    "addr:street":"18979",
    "iso:country":"US",
    "sg:address":"P.O. Box 18979",
    "sg:city":"Irvine",
    "sg:classifiers":[
        {
            "category":"Professional",
            "subcategory":"Computer Services",
            "type":"Services"
        }
    ],
    "sg:postcode":"92623",
    "sg:province":"CA",
    "sg:tags":[
        "mmo",
        "software",
        "video-games"
    ],
    "wof:name":"Blizzard Entertainment",
    "wof:placetype":"venue"
},
  "geometry": {"coordinates":[-117.830788,33.686519],"type":"Point"}
}