{
  "type": "Feature",
  "properties": {
    "iso:country":"US",
    "sg:address":"13931 Carroll Way",
    "sg:city":"Tustin",
    "sg:classifiers":[
        {
            "category":"Arts & Performance",
            "subcategory":"Arts Center",
            "type":"Entertainment"
        },
        {
            "category":"Education",
            "subcategory":"Dance Studio",
            "type":"Public Place"
        }
    ],
    "sg:phone":"+1 714 368 3424",
    "sg:postcode":"92780",
    "sg:province":"CA",
    "sg:tags":[
        "performing"
    ],
    "sg:website":"www.madbollywooddance.com",
    "wof:name":"MAD Bollywood Dance Company",
    "wof:placetype":"venue"
},
  "geometry": {"coordinates":[-117.829922,33.760998],"type":"Point"}
}