{
  "type": "Feature",
  "properties": {
    "iso:country":"US",
    "sg:address":"17335 Daimler Street",
    "sg:city":"Irvine",
    "sg:classifiers":[
        {
            "category":"Building & Trades",
            "subcategory":"Construction",
            "type":"Services"
        }
    ],
    "sg:phone":"+1 949 261 5885",
    "sg:postcode":"92614",
    "sg:province":"CA",
    "sg:tags":[
        "interior",
        "design"
    ],
    "wof:name":"San Diego Shutter Company",
    "wof:placetype":"venue"
},
  "geometry": {"coordinates":[-117.856876,33.699337],"type":"Point"}
}