{
  "type": "Feature",
  "properties": {
    "addr:full":"6109 Rushmore Dr Sacramento CA 95842",
    "addr:housenumber":"6109",
    "addr:postcode":"95842",
    "addr:street":"Rushmore Dr",
    "iso:country":"US",
    "sg:address":"6109 Rushmore Dr",
    "sg:city":"Sacramento",
    "sg:classifiers":[
        {
            "category":"Building & Trades",
            "subcategory":"Landscaping Services",
            "type":"Services"
        }
    ],
    "sg:phone":"+1 916 332 3814",
    "sg:postcode":"95842",
    "sg:province":"CA",
    "wof:name":"Mr Green Landscape & Maintenan",
    "wof:placetype":"venue"
},
  "geometry": {"coordinates":[-121.343425,38.677918],"type":"Point"}
}