{
  "type": "Feature",
  "properties": {
    "iso:country":"US",
    "sg:address":"1020 29th St Ste 270",
    "sg:city":"Sacramento",
    "sg:classifiers":[
        {
            "category":"Health Services",
            "subcategory":"Doctor",
            "type":"Services"
        }
    ],
    "sg:phone":"+1 916 455 3700",
    "sg:postcode":"95816",
    "sg:province":"CA",
    "wof:name":"Adams Sallie O MD FACS",
    "wof:placetype":"venue"
},
  "geometry": {"coordinates":[-121.468188,38.573307],"type":"Point"}
}