{
  "type": "Feature",
  "properties": {
    "addr:full":"725 N Fig St Escondido CA 92025",
    "addr:housenumber":"725",
    "addr:postcode":"92025",
    "addr:street":"N Fig St",
    "iso:country":"US",
    "sg:address":"725 N Fig St",
    "sg:city":"Escondido",
    "sg:classifiers":[
        {
            "category":"Real Estate",
            "subcategory":"Real Estate Operator",
            "type":"Services"
        }
    ],
    "sg:phone":"+1 760 747 2024",
    "sg:postcode":"92025",
    "sg:province":"CA",
    "sg:tags":[
        "apartment"
    ],
    "wof:name":"Malibu Terrace",
    "wof:placetype":"venue"
},
  "geometry": {"coordinates":[-117.075827,33.129605],"type":"Point"}
}