{
  "type": "Feature",
  "properties": {
    "addr:full":"9079 Green Rd Pinon Hills CA 92372",
    "addr:housenumber":"9079",
    "addr:postcode":"92372",
    "addr:street":"Green Rd",
    "iso:country":"US",
    "sg:address":"9079 Green Rd",
    "sg:city":"Pinon Hills",
    "sg:classifiers":[
        {
            "category":"Manufacturing",
            "subcategory":"Toys & Sporting Goods",
            "type":"Manufacturing & Wholesale Goods"
        }
    ],
    "sg:phone":"+1 760 868 4484",
    "sg:postcode":"92372",
    "sg:province":"CA",
    "sg:tags":[
        "product",
        "wood",
        "mfg"
    ],
    "wof:name":"Nord Design",
    "wof:placetype":"venue"
},
  "geometry": {"coordinates":[-117.631821,34.414529],"type":"Point"}
}