{
  "type": "Feature",
  "properties": {
    "addr:full":"801 Civic Center Dr E Santa Ana CA 92701",
    "addr:housenumber":"801",
    "addr:postcode":"92701",
    "addr:street":"Civic Center Dr E",
    "iso:country":"US",
    "sg:address":"801 Civic Center Dr E",
    "sg:city":"Santa Ana",
    "sg:classifiers":[
        {
            "category":"Government",
            "subcategory":"Office",
            "type":"Public Place"
        }
    ],
    "sg:phone":"+1 714 246 8330",
    "sg:postcode":"92701",
    "sg:province":"CA",
    "sg:tags":[
        "international",
        "naturalization",
        "immigration",
        "affairs"
    ],
    "wof:name":"Citiznship Immgration Svcs Bur",
    "wof:placetype":"venue"
},
  "geometry": {"coordinates":[-117.859067,33.75335],"type":"Point"}
}