{
  "type": "Feature",
  "properties": {
    "addr:full":"8624 Lodestone Cir Elk Grove CA 95624",
    "addr:housenumber":"8624",
    "addr:postcode":"95624",
    "addr:street":"Lodestone Cir",
    "iso:country":"US",
    "sg:address":"8624 Lodestone Cir",
    "sg:city":"Elk Grove",
    "sg:classifiers":[
        {
            "category":"Building & Trades",
            "subcategory":"Construction",
            "type":"Services"
        }
    ],
    "sg:phone":"+1 916 686 6604",
    "sg:postcode":"95624",
    "sg:province":"CA",
    "sg:tags":[
        "coping",
        "plastering",
        "tiling",
        "pool",
        "swimming"
    ],
    "wof:name":"Paradise Pool Care",
    "wof:placetype":"venue"
},
  "geometry": {"coordinates":[-121.378597,38.403172],"type":"Point"}
}