{
  "type": "Feature",
  "properties": {
    "iso:country":"US",
    "sg:address":"8787 Uphill Rd",
    "sg:city":"Joshua Tree",
    "sg:classifiers":[
        {
            "category":"Real Estate",
            "subcategory":"Real Estate Agent",
            "type":"Services"
        }
    ],
    "sg:phone":"+1 760 366 2847",
    "sg:postcode":"92252",
    "sg:province":"CA",
    "wof:name":"Desert Lilly",
    "wof:placetype":"venue"
},
  "geometry": {"coordinates":[-116.283221,34.093922],"type":"Point"}
}