{
  "type": "Feature",
  "properties": {
    "addr:full":"3805 W 8th St Los Angeles CA 90005",
    "addr:housenumber":"3805",
    "addr:postcode":"90005",
    "addr:street":"W 8Th St",
    "iso:country":"US",
    "sg:address":"3805 W 8th St",
    "sg:city":"Los Angeles",
    "sg:classifiers":[
        {
            "category":"Shopping",
            "subcategory":"Florist",
            "type":"Retail Goods"
        }
    ],
    "sg:phone":"+1 213 365 2626",
    "sg:postcode":"90005",
    "sg:province":"CA",
    "sg:website":"www.flowerworld4u.com",
    "wof:name":"Flower World",
    "wof:placetype":"venue"
},
  "geometry": {"coordinates":[-118.309444,34.058039],"type":"Point"}
}