{
  "type": "Feature",
  "properties": {
    "addr:full":"2251 Florin Rd Sacramento CA 95822",
    "addr:housenumber":"2251",
    "addr:postcode":"95822",
    "addr:street":"Florin Rd",
    "iso:country":"US",
    "sg:address":"2251 Florin Rd",
    "sg:city":"Sacramento",
    "sg:classifiers":[
        {
            "category":"Personal",
            "subcategory":"Beauty Salon",
            "type":"Services"
        }
    ],
    "sg:phone":"+1 916 422 1189",
    "sg:postcode":"95822",
    "sg:province":"CA",
    "wof:name":"Hair Design Studio",
    "wof:placetype":"venue"
},
  "geometry": {"coordinates":[-121.48903,38.495806],"type":"Point"}
}