{
  "type": "Feature",
  "properties": {
    "addr:full":"4240 Tompkins Ave Oakland CA 94619",
    "addr:housenumber":"4240",
    "addr:postcode":"94619",
    "addr:street":"Tompkins Ave",
    "iso:country":"US",
    "sg:address":"4240 Tompkins Ave",
    "sg:city":"Oakland",
    "sg:classifiers":[
        {
            "category":"Shopping",
            "subcategory":"Clothing, Apparel, & Fashions",
            "type":"Retail Goods"
        },
        {
            "category":"Personal",
            "type":"Services"
        }
    ],
    "sg:phone":"+1 510 482 2145",
    "sg:postcode":"94619",
    "sg:province":"CA",
    "sg:tags":[
        "tailoring",
        "tailor",
        "alteration",
        "wedding"
    ],
    "wof:name":"Rose Tailoring & Alterations",
    "wof:placetype":"venue"
},
  "geometry": {"coordinates":[-122.18859399999999,37.791098],"type":"Point"}
}