{
  "type": "Feature",
  "properties": {
    "iso:country":"US",
    "sg:address":"1722 S Western Avenue",
    "sg:city":"Los Angeles",
    "sg:classifiers":[
        {
            "category":"Restaurant",
            "type":"Food & Drink"
        }
    ],
    "sg:phone":"+1 323 735 5321",
    "sg:postcode":"90006",
    "sg:province":"CA",
    "sg:tags":[
        "chinese"
    ],
    "wof:name":"Kay Kay Chinese Food",
    "wof:placetype":"venue"
},
  "geometry": {"coordinates":[-118.309128,34.041195],"type":"Point"}
}