{
  "type": "Feature",
  "properties": {
    "iso:country":"US",
    "sg:address":"1603 Aviation Blvd",
    "sg:city":"Redondo Beach",
    "sg:classifiers":[
        {
            "category":"Shopping",
            "subcategory":"Bicycles & Sporting Goods",
            "type":"Retail Goods"
        }
    ],
    "sg:phone":"+1 310 540 4606",
    "sg:postcode":"90278",
    "sg:province":"CA",
    "sg:tags":[
        "surfboard"
    ],
    "wof:name":"Surf Concepts Inc",
    "wof:placetype":"venue"
},
  "geometry": {"coordinates":[-118.382616,33.869794],"type":"Point"}
}