{
  "type": "Feature",
  "properties": {
    "iso:country":"US",
    "sg:address":"2167 Waterside Cir",
    "sg:city":"Thousand Oaks",
    "sg:classifiers":[
        {
            "category":"Professional",
            "type":"Services"
        }
    ],
    "sg:phone":"+1 805 491 0102",
    "sg:postcode":"91362",
    "sg:province":"CA",
    "wof:name":"Silvia Goldstein",
    "wof:placetype":"venue"
},
  "geometry": {"coordinates":[-118.82689499999999,34.20743],"type":"Point"}
}