{
  "type": "Feature",
  "properties": {
    "iso:country":"US",
    "sg:address":"9171 Wilshire Blvd",
    "sg:city":"Beverly Hills",
    "sg:classifiers":[
        {
            "category":"Professional",
            "subcategory":"Accounting & Tax Preparation",
            "type":"Services"
        }
    ],
    "sg:phone":"+1 310 274 5847",
    "sg:postcode":"90210",
    "sg:province":"CA",
    "sg:tags":[
        "accountant"
    ],
    "wof:name":"Cohen Pivo & Co",
    "wof:placetype":"venue"
},
  "geometry": {"coordinates":[-118.392055,34.067132],"type":"Point"}
}