{
  "type": "Feature",
  "properties": {
    "iso:country":"US",
    "sg:address":"1705 Shoreline Dr",
    "sg:city":"Alameda",
    "sg:classifiers":[
        {
            "category":"Local Transit",
            "type":"Transportation"
        }
    ],
    "sg:phone":"+1 510 522 2233",
    "sg:postcode":"94501",
    "sg:province":"CA",
    "sg:tags":[
        "passenger",
        "airport"
    ],
    "wof:name":"Yaz Limousine",
    "wof:placetype":"venue"
},
  "geometry": {"coordinates":[-122.260986,37.758336],"type":"Point"}
}