{
  "type": "Feature",
  "properties": {
    "addr:full":"5980 Pacific Blvd Huntington Park CA 90255",
    "addr:housenumber":"5980",
    "addr:postcode":"90255",
    "addr:street":"Pacific Blvd;Park",
    "iso:country":"US",
    "sg:address":"5980 Pacific Blvd",
    "sg:city":"Huntington Park",
    "sg:classifiers":[
        {
            "category":"Restaurant",
            "type":"Food & Drink"
        }
    ],
    "sg:phone":"+1 323 826 3155",
    "sg:postcode":"90255",
    "sg:province":"CA",
    "wof:name":"Pollo Campero",
    "wof:placetype":"venue"
},
  "geometry": {"coordinates":[-118.225115,33.988849],"type":"Point"}
}