{
  "type": "Feature",
  "properties": {
    "addr:full":"6700 E Pacific Coast Hwy Long Beach CA 90803",
    "addr:housenumber":"6700",
    "addr:postcode":"90803",
    "addr:street":"E Pacific Coast Hwy",
    "iso:country":"US",
    "sg:address":"6700 E Pacific Coast Hwy",
    "sg:city":"Long Beach",
    "sg:classifiers":[
        {
            "category":"Professional",
            "subcategory":"Management & Consulting",
            "type":"Services"
        }
    ],
    "sg:phone":"+1 562 598 8351",
    "sg:postcode":"90803",
    "sg:province":"CA",
    "sg:tags":[
        "consultant",
        "medium"
    ],
    "wof:name":"Lone Star Radio",
    "wof:placetype":"venue"
},
  "geometry": {"coordinates":[-118.108086,33.754833],"type":"Point"}
}