{
  "type": "Feature",
  "properties": {
    "iso:country":"US",
    "sg:address":"3122 Niles St",
    "sg:city":"Bakersfield",
    "sg:classifiers":[
        {
            "category":"Professional",
            "type":"Services"
        }
    ],
    "sg:phone":"+1 661 872 2700",
    "sg:postcode":"93306",
    "sg:province":"CA",
    "wof:name":"H & E Lopez Income Tax Svc",
    "wof:placetype":"venue"
},
  "geometry": {"coordinates":[-118.947481,35.375904],"type":"Point"}
}