{
  "type": "Feature",
  "properties": {
    "iso:country":"US",
    "sg:address":"25741 Commercentre Dr",
    "sg:city":"Lake Forest",
    "sg:classifiers":[
        {
            "category":"Home & Garden",
            "subcategory":"Household Appliances",
            "type":"Retail Goods"
        }
    ],
    "sg:phone":"+1 949 586 3669",
    "sg:postcode":"92630",
    "sg:province":"CA",
    "sg:website":"renwessales.com",
    "wof:name":"Renwes Sales",
    "wof:placetype":"venue"
},
  "geometry": {"coordinates":[-117.680907,33.664973],"type":"Point"}
}