{
  "type": "Feature",
  "properties": {
    "addr:full":"2171 India St San Diego CA 92101",
    "addr:housenumber":"2171",
    "addr:postcode":"92101",
    "addr:street":"India St",
    "iso:country":"US",
    "sg:address":"2171 India St",
    "sg:city":"San Diego",
    "sg:classifiers":[
        {
            "category":"Real Estate",
            "subcategory":"Architect",
            "type":"Services"
        }
    ],
    "sg:phone":"+1 619 232 1680",
    "sg:postcode":"92101",
    "sg:province":"CA",
    "wof:name":"Shaputnic Skip Architect",
    "wof:placetype":"venue"
},
  "geometry": {"coordinates":[-117.16999800000001,32.7272],"type":"Point"}
}