{
  "type": "Feature",
  "properties": {
    "addr:full":"397 W Highland Ave San Bernardino CA 92405",
    "addr:housenumber":"397",
    "addr:postcode":"92405",
    "addr:street":"W Highland Ave",
    "iso:country":"US",
    "sg:address":"397 W Highland Ave",
    "sg:city":"San Bernardino",
    "sg:classifiers":[
        {
            "category":"Professional",
            "subcategory":"Accounting & Tax Preparation",
            "type":"Services"
        }
    ],
    "sg:phone":"+1 909 882 7411",
    "sg:postcode":"92405",
    "sg:province":"CA",
    "sg:tags":[
        "return",
        "filing"
    ],
    "wof:name":"H & R Block Tax Svc",
    "wof:placetype":"venue"
},
  "geometry": {"coordinates":[-117.28979099999999,34.135893],"type":"Point"}
}