{
  "type": "Feature",
  "properties": {
    "iso:country":"US",
    "sg:address":"Richmond St. Counseling Center 333 Richmond St",
    "sg:city":"El Segundo",
    "sg:classifiers":[
        {
            "category":"Health Services",
            "subcategory":"Clinic",
            "type":"Services"
        }
    ],
    "sg:phone":"+1 310 925 0607",
    "sg:postcode":"90245",
    "sg:province":"CA",
    "sg:tags":[
        "counseling",
        "mental"
    ],
    "sg:website":"www.rebeccakahanemft.com",
    "wof:name":"Rebecca Kahane, LMFT",
    "wof:placetype":"venue"
},
  "geometry": {"coordinates":[-118.416465,33.91918],"type":"Point"}
}