{
  "type": "Feature",
  "properties": {
    "iso:country":"US",
    "sg:address":"3101 W Beverly Blvd",
    "sg:city":"Montebello",
    "sg:classifiers":[
        {
            "category":"Banks & Credit Unions",
            "subcategory":"Bank",
            "type":"Services"
        }
    ],
    "sg:phone":"+1 323 724 2100",
    "sg:postcode":"90640",
    "sg:province":"CA",
    "sg:tags":[
        "loan",
        "real estate"
    ],
    "wof:name":"LPZ Financial Svc",
    "wof:placetype":"venue"
},
  "geometry": {"coordinates":[-118.135813,34.023248],"type":"Point"}
}