{
  "type": "Feature",
  "properties": {
    "iso:country":"US",
    "sg:address":"2416 Marina Ave",
    "sg:city":"Livermore",
    "sg:classifiers":[
        {
            "category":"Manufacturing",
            "subcategory":"Food",
            "type":"Manufacturing & Wholesale Goods"
        }
    ],
    "sg:phone":"+1 925 371 8606",
    "sg:postcode":"94550",
    "sg:province":"CA",
    "sg:tags":[
        "mfg"
    ],
    "wof:name":"Eckert Estate Winery",
    "wof:placetype":"venue"
},
  "geometry": {"coordinates":[-121.765632,37.656694],"type":"Point"}
}