{
  "type": "Feature",
  "properties": {
    "iso:country":"US",
    "sg:address":"4942 Royal Island Way",
    "sg:city":"San Diego",
    "sg:classifiers":[
        {
            "category":"Personal",
            "subcategory":"Tattoo Parlor",
            "type":"Services"
        }
    ],
    "sg:phone":"+1 858 366 3374",
    "sg:postcode":"92154",
    "sg:province":"CA",
    "sg:website":"hennatrendz.com",
    "wof:name":"HennaTrendz by Wardah",
    "wof:placetype":"venue"
},
  "geometry": {"coordinates":[-117.024142,32.589276],"type":"Point"}
}