{
  "type": "Feature",
  "properties": {
    "iso:country":"US",
    "sg:address":"870 San Antonio Ave",
    "sg:city":"Palo Alto",
    "sg:classifiers":[
        {
            "category":"Real Estate",
            "subcategory":"Architect",
            "type":"Services"
        }
    ],
    "sg:phone":"+1 650 320 8775",
    "sg:postcode":"94303",
    "sg:province":"CA",
    "sg:tags":[
        "home",
        "planning",
        "design"
    ],
    "sg:website":"www.onetwosixdesign.com",
    "wof:name":"One Two Six Design",
    "wof:placetype":"venue"
},
  "geometry": {"coordinates":[-122.10146400000001,37.42197],"type":"Point"}
}