{
  "type": "Feature",
  "properties": {
    "addr:full":"7387 Tulare Hill Dr San Jose CA 95139",
    "addr:housenumber":"7387",
    "addr:postcode":"95139",
    "addr:street":"Tulare Hill Dr",
    "iso:country":"US",
    "sg:address":"7387 Tulare Hill Dr",
    "sg:city":"San Jose",
    "sg:classifiers":[
        {
            "category":"Professional",
            "subcategory":"Secretarial Services",
            "type":"Services"
        }
    ],
    "sg:phone":"+1 408 281 1281",
    "sg:postcode":"95139",
    "sg:province":"CA",
    "sg:tags":[
        "resume"
    ],
    "wof:name":"Resumes While-U-Wait",
    "wof:placetype":"venue"
},
  "geometry": {"coordinates":[-121.761799,37.226927],"type":"Point"}
}