{
  "type": "Feature",
  "properties": {
    "iso:country":"US",
    "sg:address":"4122 W Delta Ave",
    "sg:city":"Visalia",
    "sg:classifiers":[
        {
            "category":"Building & Trades",
            "subcategory":"Construction",
            "type":"Services"
        }
    ],
    "sg:phone":"+1 559 738 1092",
    "sg:postcode":"93291",
    "sg:province":"CA",
    "sg:tags":[
        "handyman"
    ],
    "wof:name":"Tri County Service & Repair",
    "wof:placetype":"venue"
},
  "geometry": {"coordinates":[-119.336673,36.342394],"type":"Point"}
}