{
  "type": "Feature",
  "properties": {
    "addr:full":"1423 S Bradley Rd Santa Maria CA 93454",
    "addr:housenumber":"1423",
    "addr:postcode":"93454",
    "addr:street":"S Bradley Rd",
    "iso:country":"US",
    "sg:address":"1423 S Bradley Rd",
    "sg:city":"Santa Maria",
    "sg:classifiers":[
        {
            "category":"Restaurant",
            "type":"Food & Drink"
        }
    ],
    "sg:menulink":"http://www.allmenus.com/ca/santa-maria-valley/235982-original-roadhouse-grill/menu/",
    "sg:phone":"+1 805 614 0586",
    "sg:postcode":"93454",
    "sg:province":"CA",
    "sg:tags":[
        "american"
    ],
    "wof:name":"Original Roadhouse Grill",
    "wof:placetype":"venue"
},
  "geometry": {"coordinates":[-120.418852,34.93466],"type":"Point"}
}