{
  "type": "Feature",
  "properties": {
    "iso:country":"US",
    "sg:address":"5947 Geary Blvd",
    "sg:city":"San Francisco",
    "sg:classifiers":[
        {
            "category":"Shopping",
            "subcategory":"Clothing, Apparel, & Fashions",
            "type":"Retail Goods"
        }
    ],
    "sg:phone":"+1 415 750 3961",
    "sg:postcode":"94121",
    "sg:province":"CA",
    "sg:tags":[
        "sportswear"
    ],
    "wof:name":"Max Sports",
    "wof:placetype":"venue"
},
  "geometry": {"coordinates":[-122.483231,37.780018],"type":"Point"}
}