{
  "type": "Feature",
  "properties": {
    "addr:full":"1560 S Harbor Blvd Anaheim CA 92802",
    "addr:housenumber":"1560",
    "addr:postcode":"92802",
    "addr:street":"S Harbor Blvd",
    "iso:country":"US",
    "sg:address":"1560 S Harbor Blvd",
    "sg:city":"Anaheim",
    "sg:classifiers":[
        {
            "category":"Restaurant",
            "type":"Food & Drink"
        }
    ],
    "sg:phone":"+1 714 635 0933",
    "sg:postcode":"92802",
    "sg:province":"CA",
    "sg:tags":[
        "breakfast",
        "brunch",
        "diner"
    ],
    "sg:website":"www.ihop.com",
    "wof:name":"International House of Pancakes",
    "wof:placetype":"venue"
},
  "geometry": {"coordinates":[-117.915001,33.809898],"type":"Point"}
}