{
  "type": "Feature",
  "properties": {
    "iso:country":"US",
    "sg:address":"2561 Booksin Avenue",
    "sg:city":"San Jose",
    "sg:classifiers":[
        {
            "category":"Personal",
            "type":"Services"
        }
    ],
    "sg:phone":"+1 408 634 2622",
    "sg:postcode":"95125",
    "sg:province":"CA",
    "sg:tags":[
        "sewing",
        "alteration"
    ],
    "sg:website":"www.bobbinstobritches.com",
    "wof:name":"Bobbins to Britches",
    "wof:placetype":"venue"
},
  "geometry": {"coordinates":[-121.89946500000001,37.277524],"type":"Point"}
}