{
  "type": "Feature",
  "properties": {
    "addr:full":"430 1st Ave Gustine CA 95322",
    "addr:housenumber":"430",
    "addr:postcode":"95322",
    "addr:street":"1St Ave",
    "iso:country":"US",
    "sg:address":"430 1st Ave",
    "sg:city":"Gustine",
    "sg:classifiers":[
        {
            "category":"Autos & Motor Vehicles",
            "subcategory":"Fuel & Gas Station",
            "type":"Retail Goods"
        }
    ],
    "sg:phone":"+1 209 854 2223",
    "sg:postcode":"95322",
    "sg:province":"CA",
    "sg:tags":[
        "oil"
    ],
    "wof:name":"Cheveron",
    "wof:placetype":"venue"
},
  "geometry": {"coordinates":[-121.000038,37.259955],"type":"Point"}
}