{
  "type": "Feature",
  "properties": {
    "addr:full":"127 E 9th St Los Angeles CA 90015",
    "addr:housenumber":"127",
    "addr:postcode":"90015",
    "addr:street":"E 9Th St",
    "iso:country":"US",
    "sg:address":"127 E 9th St",
    "sg:city":"Los Angeles",
    "sg:classifiers":[
        {
            "category":"Shopping",
            "subcategory":"Clothing, Apparel, & Fashions",
            "type":"Retail Goods"
        }
    ],
    "sg:phone":"+1 213 622 6922",
    "sg:postcode":"90015",
    "sg:province":"CA",
    "wof:name":"Circle Size Showroom",
    "wof:placetype":"venue"
},
  "geometry": {"coordinates":[-118.25407300000001,34.040824],"type":"Point"}
}