{
  "type": "Feature",
  "properties": {
    "iso:country":"US",
    "sg:address":"1111 W 165th Pl",
    "sg:city":"Gardena",
    "sg:classifiers":[
        {
            "category":"Retail",
            "subcategory":"Repair Shop",
            "type":"Services"
        }
    ],
    "sg:phone":"+1 310 538 9262",
    "sg:postcode":"90247",
    "sg:province":"CA",
    "sg:tags":[
        "taxidermist"
    ],
    "wof:name":"Steve Taxidermy",
    "wof:placetype":"venue"
},
  "geometry": {"coordinates":[-118.294382,33.880705],"type":"Point"}
}