{
  "type": "Feature",
  "properties": {
    "addr:full":"1827 Atlanta Ave Riverside CA 92507",
    "addr:housenumber":"1827",
    "addr:postcode":"92507",
    "addr:street":"Atlanta Ave",
    "iso:country":"US",
    "sg:address":"1827 Atlanta Ave",
    "sg:city":"Riverside",
    "sg:classifiers":[
        {
            "category":"Government",
            "subcategory":"Office",
            "type":"Public Place"
        }
    ],
    "sg:phone":"+1 951 955 2100",
    "sg:postcode":"92507",
    "sg:province":"CA",
    "wof:name":"Drug Abuse Program",
    "wof:placetype":"venue"
},
  "geometry": {"coordinates":[-117.344252,33.993235],"type":"Point"}
}