{
  "type": "Feature",
  "properties": {
    "addr:full":"5875 Carolus Drive Los Angeles CA 90068",
    "addr:housenumber":"5875",
    "addr:postcode":"90068",
    "addr:street":"Carolus Drive",
    "iso:country":"US",
    "sg:address":"5875 Carolus Drive",
    "sg:city":"Los Angeles",
    "sg:classifiers":[
        {
            "category":"Personal",
            "type":"Services"
        }
    ],
    "sg:phone":"+1 323 462 2583",
    "sg:postcode":"90068",
    "sg:province":"CA",
    "sg:tags":[
        "party",
        "planning",
        "event"
    ],
    "sg:website":"www.premeditatedproductions.com",
    "wof:name":"Premeditated Productions",
    "wof:placetype":"venue"
},
  "geometry": {"coordinates":[-118.317117,34.119576],"type":"Point"}
}