{
  "type": "Feature",
  "properties": {
    "iso:country":"US",
    "sg:address":"1200 S St",
    "sg:city":"Sacramento",
    "sg:classifiers":[
        {
            "category":"Arts & Performance",
            "subcategory":"Art Gallery",
            "type":"Entertainment"
        }
    ],
    "sg:phone":"+1 916 397 8958",
    "sg:postcode":"95811",
    "sg:province":"CA",
    "sg:website":"www.s12studios.com/",
    "wof:name":"Capitol Art Center",
    "wof:placetype":"venue"
},
  "geometry": {"coordinates":[-121.49493,38.569409],"type":"Point"}
}