{
  "type": "Feature",
  "properties": {
    "iso:country":"US",
    "sg:address":"495 Monterey Ave",
    "sg:city":"Morro Bay",
    "sg:classifiers":[
        {
            "category":"Organizations",
            "subcategory":"Religious Organization",
            "type":"Services"
        }
    ],
    "sg:phone":"+1 805 772 8457",
    "sg:postcode":"93442",
    "sg:province":"CA",
    "sg:tags":[
        "church"
    ],
    "sg:website":"www.morrobaylutherans.org",
    "wof:name":"Calvary Lutheran Church",
    "wof:placetype":"venue"
},
  "geometry": {"coordinates":[-120.848906,35.361676],"type":"Point"}
}