{
  "type": "Feature",
  "properties": {
    "iso:country":"US",
    "sg:address":"8813 Donaker St",
    "sg:city":"San Diego",
    "sg:classifiers":[
        {
            "category":"Professional",
            "type":"Services"
        }
    ],
    "sg:phone":"+1 858 538 5842",
    "sg:postcode":"92129",
    "sg:province":"CA",
    "wof:name":"Shabk Inc",
    "wof:placetype":"venue"
},
  "geometry": {"coordinates":[-117.138395,32.977018],"type":"Point"}
}