{
  "type": "Feature",
  "properties": {
    "iso:country":"US",
    "sg:address":"110 Melba Rd",
    "sg:city":"Encinitas",
    "sg:classifiers":[
        {
            "category":"Building & Trades",
            "subcategory":"Construction",
            "type":"Services"
        }
    ],
    "sg:phone":"+1 760 942 8600",
    "sg:postcode":"92024",
    "sg:province":"CA",
    "sg:tags":[
        "contractor"
    ],
    "sg:website":"www.onlinebuilders.net",
    "wof:name":"Online Builders",
    "wof:placetype":"venue"
},
  "geometry": {"coordinates":[-117.28993800000001,33.039736],"type":"Point"}
}