{
  "type": "Feature",
  "properties": {
    "addr:full":"8829 National Blvd Culver City CA 90232",
    "addr:housenumber":"8829",
    "addr:postcode":"90232",
    "addr:street":"National Blvd",
    "iso:country":"US",
    "sg:address":"8829 National Blvd",
    "sg:city":"Culver City",
    "sg:classifiers":[
        {
            "category":"Retail",
            "subcategory":"Storage",
            "type":"Services"
        }
    ],
    "sg:phone":"+1 310 558 4561",
    "sg:postcode":"90232",
    "sg:province":"CA",
    "sg:tags":[
        "self"
    ],
    "wof:name":"U-Haul Co",
    "wof:placetype":"venue"
},
  "geometry": {"coordinates":[-118.386002,34.027699],"type":"Point"}
}