{
  "type": "Feature",
  "properties": {
    "iso:country":"US",
    "sg:address":"10619 Ashton Ave",
    "sg:city":"Los Angeles",
    "sg:classifiers":[
        {
            "category":"Health Services",
            "subcategory":"Clinic",
            "type":"Services"
        }
    ],
    "sg:phone":"+1 310 909 8470",
    "sg:postcode":"90024",
    "sg:province":"CA",
    "sg:tags":[
        "counseling",
        "mental"
    ],
    "sg:website":"soberlivingsearch.com",
    "wof:name":"Sober Living Halfway House Search",
    "wof:placetype":"venue"
},
  "geometry": {"coordinates":[-118.433864,34.060357],"type":"Point"}
}