{
  "type": "Feature",
  "properties": {
    "iso:country":"US",
    "sg:address":"2438 Seaman Ave",
    "sg:city":"South El Monte",
    "sg:classifiers":[
        {
            "category":"Professional",
            "subcategory":"Computer Services",
            "type":"Services"
        }
    ],
    "sg:phone":"+1 626 350 7848",
    "sg:postcode":"91733",
    "sg:province":"CA",
    "sg:tags":[
        "graphics"
    ],
    "wof:name":"101 Color Printing",
    "wof:placetype":"venue"
},
  "geometry": {"coordinates":[-118.0527,34.059029],"type":"Point"}
}