{
  "type": "Feature",
  "properties": {
    "addr:full":"1031 Junction Blvd Roseville CA 95678",
    "addr:housenumber":"1031",
    "addr:postcode":"95678",
    "addr:street":"Junction Blvd",
    "iso:country":"US",
    "sg:address":"1031 Junction Blvd",
    "sg:city":"Roseville",
    "sg:classifiers":[
        {
            "category":"Insurance",
            "subcategory":"Hazard Insurance",
            "type":"Services"
        }
    ],
    "sg:phone":"+1 916 782 2377",
    "sg:postcode":"95678",
    "sg:province":"CA",
    "sg:tags":[
        "bond"
    ],
    "wof:name":"Aallied Bail Bonds",
    "wof:placetype":"venue"
},
  "geometry": {"coordinates":[-121.296708,38.75968],"type":"Point"}
}