{
  "type": "Feature",
  "properties": {
    "addr:full":"2030 Samson Ave Simi Valley CA 93063",
    "addr:postcode":"2030;93063",
    "addr:street":"Samson Ave",
    "iso:country":"US",
    "sg:address":"2030 Samson Ave",
    "sg:city":"Simi Valley",
    "sg:classifiers":[
        {
            "category":"Local Transit",
            "type":"Transportation"
        }
    ],
    "sg:phone":"+1 805 581 5742",
    "sg:postcode":"93063",
    "sg:province":"CA",
    "sg:tags":[
        "airport"
    ],
    "wof:name":"Lloyd's Limousine & Van Svc",
    "wof:placetype":"venue"
},
  "geometry": {"coordinates":[-118.726365,34.27457],"type":"Point"}
}