{
  "type": "Feature",
  "properties": {
    "addr:full":"25 Omar Way San Francisco CA 94127",
    "addr:housenumber":"25",
    "addr:postcode":"94127",
    "addr:street":"Omar Way",
    "iso:country":"US",
    "sg:address":"25 Omar Way",
    "sg:city":"San Francisco",
    "sg:classifiers":[
        {
            "category":"Park",
            "type":"Public Place"
        },
        {
            "category":"Education",
            "subcategory":"School",
            "type":"Public Place"
        },
        {
            "category":"Recreation",
            "subcategory":"Playground",
            "type":"Entertainment"
        }
    ],
    "sg:phone":"+1 415 337 4704",
    "sg:postcode":"94127",
    "sg:province":"CA",
    "sg:tags":[
        "elementary"
    ],
    "sg:website":"parks.sfgov.org",
    "wof:name":"Miraloma Playground",
    "wof:placetype":"venue"
},
  "geometry": {"coordinates":[-122.44892299999999,37.739299],"type":"Point"}
}