{
  "type": "Feature",
  "properties": {
    "addr:full":"140 Brannan Island Rd Isleton CA 95641",
    "addr:housenumber":"140",
    "addr:postcode":"95641",
    "addr:street":"Brannan Island Rd",
    "iso:country":"US",
    "sg:address":"140 Brannan Island Rd",
    "sg:city":"Isleton",
    "sg:classifiers":[
        {
            "category":"Government",
            "subcategory":"Police Station",
            "type":"Public Place"
        }
    ],
    "sg:phone":"+1 916 777 4196",
    "sg:postcode":"95641",
    "sg:province":"CA",
    "sg:tags":[
        "protection"
    ],
    "wof:name":"Sheriffs Dept",
    "wof:placetype":"venue"
},
  "geometry": {"coordinates":[-121.572979,38.100203],"type":"Point"}
}