{
  "type": "Feature",
  "properties": {
    "iso:country":"US",
    "sg:address":"23355 Millerick Rd",
    "sg:city":"Sonoma",
    "sg:classifiers":[
        {
            "category":"Manufacturing",
            "subcategory":"Food",
            "type":"Manufacturing & Wholesale Goods"
        }
    ],
    "sg:phone":"+1 707 938 0966",
    "sg:postcode":"95476",
    "sg:province":"CA",
    "sg:tags":[
        "drink",
        "soft",
        "mfg"
    ],
    "wof:name":"Ultima Mobile Bottling Company",
    "wof:placetype":"venue"
},
  "geometry": {"coordinates":[-122.43725,38.223051],"type":"Point"}
}