{
  "type": "Feature",
  "properties": {
    "iso:country":"US",
    "sg:address":"4011 Clipper Ct",
    "sg:city":"Fremont",
    "sg:classifiers":[
        {
            "category":"Utilities",
            "subcategory":"Telephone",
            "type":"Services"
        }
    ],
    "sg:phone":"+1 510 252 9688",
    "sg:postcode":"94538",
    "sg:province":"CA",
    "sg:tags":[
        "telecommunication"
    ],
    "sg:website":"www.vicomptelusa.com",
    "wof:name":"Vicomptel Inc",
    "wof:placetype":"venue"
},
  "geometry": {"coordinates":[-121.94749,37.479204],"type":"Point"}
}