{
  "type": "Feature",
  "properties": {
    "iso:country":"US",
    "sg:address":"27570 Mission Blvd",
    "sg:city":"Hayward",
    "sg:classifiers":[
        {
            "category":"Autos & Motor Vehicles",
            "subcategory":"Automobile Sales",
            "type":"Retail Goods"
        }
    ],
    "sg:phone":"+1 510 727 9400",
    "sg:postcode":"94544",
    "sg:province":"CA",
    "sg:tags":[
        "car",
        "dealer"
    ],
    "wof:name":"K J Auto",
    "wof:placetype":"venue"
},
  "geometry": {"coordinates":[-122.059386,37.641855],"type":"Point"}
}