{
  "type": "Feature",
  "properties": {
    "addr:full":"805 Walnut St Red Bluff CA 96080",
    "addr:housenumber":"805",
    "addr:postcode":"96080",
    "addr:street":"Walnut St",
    "iso:country":"US",
    "sg:address":"805 Walnut St",
    "sg:city":"Red Bluff",
    "sg:classifiers":[
        {
            "category":"Shopping",
            "subcategory":"Clothing, Apparel, & Fashions",
            "type":"Retail Goods"
        }
    ],
    "sg:phone":"+1 530 529 0376",
    "sg:postcode":"96080",
    "sg:province":"CA",
    "sg:tags":[
        "alteration"
    ],
    "wof:name":"Nitz Alterations",
    "wof:placetype":"venue"
},
  "geometry": {"coordinates":[-122.240936,40.175651],"type":"Point"}
}