{
  "type": "Feature",
  "properties": {
    "addr:full":"9299 Thornton Rd Ste C Stockton CA 95209",
    "addr:housenumber":"9299",
    "addr:postcode":"95209",
    "addr:street":"Thornton Rd Ste C",
    "iso:country":"US",
    "sg:address":"9299 Thornton Rd Ste C",
    "sg:city":"Stockton",
    "sg:classifiers":[
        {
            "category":"Banks & Credit Unions",
            "subcategory":"Investment Brokerage",
            "type":"Services"
        },
        {
            "category":"Insurance",
            "subcategory":"Hazard Insurance",
            "type":"Services"
        }
    ],
    "sg:phone":"+1 209 955 0520",
    "sg:postcode":"95209",
    "sg:province":"CA",
    "sg:tags":[
        "agent",
        "resume"
    ],
    "wof:name":"Duchuan Multiservice Center",
    "wof:placetype":"venue"
},
  "geometry": {"coordinates":[-121.338672,38.035071],"type":"Point"}
}