{
  "type": "Feature",
  "properties": {
    "iso:country":"US",
    "sg:address":"2606 Coronet Blvd",
    "sg:city":"Belmont",
    "sg:classifiers":[
        {
            "category":"Shopping",
            "subcategory":"Crafts & Fabrics",
            "type":"Retail Goods"
        }
    ],
    "sg:phone":"+1 650 620 9580",
    "sg:postcode":"94002",
    "sg:province":"CA",
    "sg:tags":[
        "sewing",
        "machines-household"
    ],
    "wof:name":"Sylvia Sewing Studio",
    "wof:placetype":"venue"
},
  "geometry": {"coordinates":[-122.298958,37.51186],"type":"Point"}
}