{
  "type": "Feature",
  "properties": {
    "addr:full":"1667 Dominican Way Ste 234 Santa Cruz CA 95065",
    "addr:housenumber":"1667",
    "addr:postcode":"95065",
    "addr:street":"Dominican Way Ste 234",
    "iso:country":"US",
    "sg:address":"1667 Dominican Way Ste 234",
    "sg:city":"Santa Cruz",
    "sg:classifiers":[
        {
            "category":"Health Services",
            "subcategory":"Doctor",
            "type":"Services"
        }
    ],
    "sg:phone":"+1 831 476 3363",
    "sg:postcode":"95065",
    "sg:province":"CA",
    "sg:tags":[
        "obstetrician",
        "gynecologist"
    ],
    "wof:name":"Storz Elise Cnm",
    "wof:placetype":"venue"
},
  "geometry": {"coordinates":[-121.983002,36.990601],"type":"Point"}
}