{
  "type": "Feature",
  "properties": {
    "addr:full":"105 Leavesley Rd Gilroy CA 95020",
    "addr:housenumber":"105",
    "addr:postcode":"95020",
    "addr:street":"Leavesley Rd",
    "iso:country":"US",
    "sg:address":"105 Leavesley Rd",
    "sg:city":"Gilroy",
    "sg:classifiers":[
        {
            "category":"Manufacturing",
            "subcategory":"Wood Products",
            "type":"Manufacturing & Wholesale Goods"
        },
        {
            "category":"Home & Garden",
            "subcategory":"Furniture",
            "type":"Retail Goods"
        }
    ],
    "sg:phone":"+1 408 847 0241",
    "sg:postcode":"95020",
    "sg:province":"CA",
    "sg:tags":[
        "mfg",
        "cabinet"
    ],
    "wof:name":"Romero & Sons Cabinets",
    "wof:placetype":"venue"
},
  "geometry": {"coordinates":[-121.573781,37.019708],"type":"Point"}
}