{
  "type": "Feature",
  "properties": {
    "iso:country":"US",
    "sg:address":"9901 Indiana Ave",
    "sg:city":"Riverside",
    "sg:classifiers":[
        {
            "category":"Building & Trades",
            "subcategory":"Construction",
            "type":"Services"
        },
        {
            "category":"Manufacturing",
            "subcategory":"Tools & Machinery",
            "type":"Manufacturing & Wholesale Goods"
        }
    ],
    "sg:phone":"+1 951 637 0597",
    "sg:postcode":"92503",
    "sg:province":"CA",
    "sg:tags":[
        "deck",
        "mfg",
        "builder",
        "cooking",
        "equipment",
        "household",
        "patio"
    ],
    "wof:name":"Your Backyard",
    "wof:placetype":"venue"
},
  "geometry": {"coordinates":[-117.452398,33.907877],"type":"Point"}
}