{
  "type": "Feature",
  "properties": {
    "addr:full":"22838 Bear Valley Rd Apple Valley CA 92308",
    "addr:housenumber":"22838",
    "addr:postcode":"92308",
    "addr:street":"Bear Valley Rd",
    "iso:country":"US",
    "sg:address":"22838 Bear Valley Rd",
    "sg:city":"Apple Valley",
    "sg:classifiers":[
        {
            "category":"Real Estate",
            "subcategory":"Developer",
            "type":"Services"
        }
    ],
    "sg:phone":"+1 760 247 0992",
    "sg:postcode":"92308",
    "sg:province":"CA",
    "sg:tags":[
        "mobile",
        "home"
    ],
    "wof:name":"Bear Valley Mobile Home Park",
    "wof:placetype":"venue"
},
  "geometry": {"coordinates":[-117.164717,34.471765],"type":"Point"}
}