{
  "type": "Feature",
  "properties": {
    "iso:country":"US",
    "sg:address":"2221 American Ave",
    "sg:city":"Sacramento",
    "sg:classifiers":[
        {
            "category":"Real Estate",
            "subcategory":"Real Estate Services",
            "type":"Services"
        }
    ],
    "sg:phone":"+1 916 514 1144",
    "sg:postcode":"95833",
    "sg:province":"CA",
    "sg:tags":[
        "boarding",
        "house"
    ],
    "wof:name":"Bloom Room And Board",
    "wof:placetype":"venue"
},
  "geometry": {"coordinates":[-121.471767,38.607059],"type":"Point"}
}