{
  "type": "Feature",
  "properties": {
    "iso:country":"US",
    "sg:address":"12150 Ramona Ave",
    "sg:city":"Chino",
    "sg:classifiers":[
        {
            "category":"Banks & Credit Unions",
            "subcategory":"Bank",
            "type":"Services"
        }
    ],
    "sg:phone":"+1 909 590 5036",
    "sg:postcode":"91710",
    "sg:province":"CA",
    "sg:tags":[
        "loan",
        "real estate"
    ],
    "wof:name":"Golden Horizon Mortgage",
    "wof:placetype":"venue"
},
  "geometry": {"coordinates":[-117.706948,34.032832],"type":"Point"}
}