{
  "type": "Feature",
  "properties": {
    "addr:full":"3176 Pullman St Ste 104 Costa Mesa CA 92626",
    "addr:housenumber":"3176",
    "addr:postcode":"92626",
    "addr:street":"Pullman St Ste 104",
    "iso:country":"US",
    "sg:address":"3176 Pullman St Ste 104",
    "sg:city":"Costa Mesa",
    "sg:classifiers":[
        {
            "category":"Shopping",
            "subcategory":"Jewelry",
            "type":"Retail Goods"
        }
    ],
    "sg:phone":"+1 714 708 2500",
    "sg:postcode":"92626",
    "sg:province":"CA",
    "wof:name":"MOD Jewelry Inc",
    "wof:placetype":"venue"
},
  "geometry": {"coordinates":[-117.874617,33.683143],"type":"Point"}
}