{
  "type": "Feature",
  "properties": {
    "addr:full":"14920 Costa Mesa Dr La Mirada CA 90638",
    "addr:housenumber":"14920",
    "addr:postcode":"90638",
    "addr:street":"Costa Mesa Dr",
    "iso:country":"US",
    "sg:address":"14920 Costa Mesa Dr",
    "sg:city":"La Mirada",
    "sg:classifiers":[
        {
            "category":"Shopping",
            "subcategory":"Computers & Home Electronics",
            "type":"Retail Goods"
        }
    ],
    "sg:phone":"+1 714 522 2242",
    "sg:postcode":"90638",
    "sg:province":"CA",
    "sg:tags":[
        "equipment"
    ],
    "wof:name":"Computer Corner",
    "wof:placetype":"venue"
},
  "geometry": {"coordinates":[-117.999003,33.895518],"type":"Point"}
}