{
  "type": "Feature",
  "properties": {
    "iso:country":"US",
    "sg:address":"845 The Alameda",
    "sg:city":"Berkeley",
    "sg:classifiers":[
        {
            "category":"Shopping",
            "subcategory":"Bicycles & Sporting Goods",
            "type":"Retail Goods"
        },
        {
            "category":"Parking",
            "subcategory":"Bicycle",
            "type":"Transportation"
        }
    ],
    "sg:phone":"+1 617 308 3736",
    "sg:postcode":"94707",
    "sg:province":"CA",
    "sg:tags":[
        "shop",
        "security",
        "system",
        "rack"
    ],
    "sg:website":"http://www.monkeylectric.com",
    "wof:name":"Squid Consulting",
    "wof:placetype":"venue"
},
  "geometry": {"coordinates":[-122.27731300000001,37.892948],"type":"Point"}
}