{
  "type": "Feature",
  "properties": {
    "addr:full":"13123 Whistler Ave Granada Hills CA 91344",
    "addr:housenumber":"13123",
    "addr:postcode":"91344",
    "addr:street":"Whistler Ave",
    "iso:country":"US",
    "sg:address":"13123 Whistler Ave",
    "sg:city":"Granada Hills",
    "sg:classifiers":[
        {
            "category":"Professional",
            "subcategory":"Employment Agencies",
            "type":"Services"
        }
    ],
    "sg:phone":"+1 818 366 2738",
    "sg:postcode":"91344",
    "sg:province":"CA",
    "sg:tags":[
        "opportunity"
    ],
    "wof:name":"Advancement Personnel Agency",
    "wof:placetype":"venue"
},
  "geometry": {"coordinates":[-118.505351,34.308866],"type":"Point"}
}