{
  "type": "Feature",
  "properties": {
    "iso:country":"US",
    "sg:address":"670 N Fairoaks Ave",
    "sg:city":"Sunnyvale",
    "sg:classifiers":[
        {
            "category":"Restaurant",
            "type":"Food & Drink"
        }
    ],
    "sg:phone":"+1 408 735 8657",
    "sg:postcode":"94085",
    "sg:province":"CA",
    "wof:name":"Tres Potrillos Taqueria",
    "wof:placetype":"venue"
},
  "geometry": {"coordinates":[-122.014349,37.390397],"type":"Point"}
}