{
  "type": "Feature",
  "properties": {
    "addr:full":"839 Bright Star St Thousand Oaks CA 91360",
    "addr:housenumber":"839",
    "addr:postcode":"91360",
    "addr:street":"Bright Star St",
    "iso:country":"US",
    "sg:address":"839 Bright Star St",
    "sg:city":"Thousand Oaks",
    "sg:classifiers":[
        {
            "category":"Professional",
            "subcategory":"Research",
            "type":"Services"
        }
    ],
    "sg:phone":"+1 805 492 6790",
    "sg:postcode":"91360",
    "sg:province":"CA",
    "sg:tags":[
        "educational"
    ],
    "wof:name":"Calrichwell Corp Inc",
    "wof:placetype":"venue"
},
  "geometry": {"coordinates":[-118.902019,34.220626],"type":"Point"}
}