{
  "type": "Feature",
  "properties": {
    "iso:country":"US",
    "sg:address":"5023B Clayton Rd",
    "sg:city":"Concord",
    "sg:classifiers":[
        {
            "category":"Professional",
            "subcategory":"Accounting & Tax Preparation",
            "type":"Services"
        }
    ],
    "sg:phone":"+1 925 429 1040",
    "sg:postcode":"94521",
    "sg:province":"CA",
    "sg:tags":[
        "bookkeeping",
        "return",
        "representative",
        "preparation-business",
        "taxes-consultants"
    ],
    "sg:website":"http://www.jacksonhewitt.com/",
    "wof:name":"Jackson Hewitt Tax Service",
    "wof:placetype":"venue"
},
  "geometry": {"coordinates":[-121.972899,37.957746],"type":"Point"}
}