{
  "type": "Feature",
  "properties": {
    "addr:full":"600 Aviation Dr Camarillo CA 93010",
    "addr:housenumber":"600",
    "addr:postcode":"93010",
    "addr:street":"Aviation Dr",
    "iso:country":"US",
    "sg:address":"600 Aviation Dr",
    "sg:city":"Camarillo",
    "sg:classifiers":[
        {
            "category":"Government",
            "subcategory":"Office",
            "type":"Public Place"
        }
    ],
    "sg:phone":"+1 805 388 4341",
    "sg:postcode":"93010",
    "sg:province":"CA",
    "wof:name":"Ventura County Animal Rgltn",
    "wof:placetype":"venue"
},
  "geometry": {"coordinates":[-119.084551,34.209461],"type":"Point"}
}