{
  "type": "Feature",
  "properties": {
    "addr:full":"9081 Cade Ter San Diego CA 92126",
    "addr:housenumber":"9081",
    "addr:postcode":"92126",
    "addr:street":"Cade Ter",
    "iso:country":"US",
    "sg:address":"9081 Cade Ter",
    "sg:city":"San Diego",
    "sg:classifiers":[
        {
            "category":"Building & Trades",
            "subcategory":"Plumbing",
            "type":"Services"
        }
    ],
    "sg:phone":"+1 858 693 4299",
    "sg:postcode":"92126",
    "sg:province":"CA",
    "sg:tags":[
        "conditioning"
    ],
    "wof:name":"Cal-Cool Mechanical",
    "wof:placetype":"venue"
},
  "geometry": {"coordinates":[-117.12852599999999,32.930279],"type":"Point"}
}