{
  "type": "Feature",
  "properties": {
    "addr:full":"5192 Lakeview Ave Yorba Linda CA 92886",
    "addr:housenumber":"5192",
    "addr:postcode":"92886",
    "addr:street":"Lakeview Ave",
    "iso:country":"US",
    "sg:address":"5192 Lakeview Ave",
    "sg:city":"Yorba Linda",
    "sg:classifiers":[
        {
            "category":"Building & Trades",
            "subcategory":"Construction",
            "type":"Services"
        }
    ],
    "sg:phone":"+1 714 878 1140",
    "sg:postcode":"92886",
    "sg:province":"CA",
    "sg:tags":[
        "contractor"
    ],
    "wof:name":"Dain Concrete Breaking",
    "wof:placetype":"venue"
},
  "geometry": {"coordinates":[-117.81301999999999,33.88632],"type":"Point"}
}