{
  "type": "Feature",
  "properties": {
    "iso:country":"US",
    "sg:address":"1244 W Winton Ave",
    "sg:city":"Hayward",
    "sg:classifiers":[
        {
            "category":"Home & Garden",
            "subcategory":"Home Furnishings",
            "type":"Retail Goods"
        }
    ],
    "sg:phone":"+1 510 732 1555",
    "sg:postcode":"94545",
    "sg:province":"CA",
    "sg:tags":[
        "bath",
        "kitchen"
    ],
    "wof:name":"A1 Interiors Decoration Inc",
    "wof:placetype":"venue"
},
  "geometry": {"coordinates":[-122.115149,37.652904],"type":"Point"}
}