{
  "type": "Feature",
  "properties": {
    "iso:country":"US",
    "sg:address":"11101 Woodley Ave",
    "sg:city":"Granada Hills",
    "sg:classifiers":[
        {
            "category":"Restaurant",
            "type":"Food & Drink"
        }
    ],
    "sg:menulink":"http://www.allmenus.com/ca/san-fernando-valley/213391-taco-bell/menu/",
    "sg:phone":"+1 818 360 8417",
    "sg:postcode":"91344",
    "sg:province":"CA",
    "sg:tags":[
        "mexican"
    ],
    "wof:name":"Taco Bell",
    "wof:placetype":"venue"
},
  "geometry": {"coordinates":[-118.484712,34.271961],"type":"Point"}
}