{
  "type": "Feature",
  "properties": {
    "iso:country":"US",
    "sg:address":"3530 W Century Blvd",
    "sg:city":"Inglewood",
    "sg:classifiers":[
        {
            "category":"Professional",
            "subcategory":"Employment Agencies",
            "type":"Services"
        }
    ],
    "sg:phone":"+1 310 988 1538",
    "sg:postcode":"90303",
    "sg:province":"CA",
    "wof:name":"Quality Staffing Agency",
    "wof:placetype":"venue"
},
  "geometry": {"coordinates":[-118.333329,33.94527],"type":"Point"}
}