{
  "type": "Feature",
  "properties": {
    "iso:country":"US",
    "sg:address":"2800 Neilson Way",
    "sg:city":"Santa Monica",
    "sg:classifiers":[
        {
            "category":"Professional",
            "subcategory":"Computer Services",
            "type":"Services"
        }
    ],
    "sg:phone":"+1 310 392 4840",
    "sg:postcode":"90405",
    "sg:province":"CA",
    "sg:tags":[
        "consultant",
        "designer"
    ],
    "wof:name":"No Sweat Personalized Computer",
    "wof:placetype":"venue"
},
  "geometry": {"coordinates":[-118.481759,33.999216],"type":"Point"}
}