{
  "type": "Feature",
  "properties": {
    "addr:full":"929 Valencia Street San Francisco CA 94110",
    "addr:housenumber":"929",
    "addr:postcode":"94110",
    "addr:street":"Valencia Street",
    "iso:country":"US",
    "sg:address":"929 Valencia Street",
    "sg:city":"San Francisco",
    "sg:classifiers":[
        {
            "category":"Real Estate",
            "subcategory":"Architect",
            "type":"Services"
        }
    ],
    "sg:phone":"+1 415 285 0100",
    "sg:postcode":"94110",
    "sg:province":"CA",
    "wof:name":"Massey Architects",
    "wof:placetype":"venue"
},
  "geometry": {"coordinates":[-122.420998,37.758099],"type":"Point"}
}