{
  "type": "Feature",
  "properties": {
    "iso:country":"US",
    "sg:address":"5932 S Kings Rd",
    "sg:city":"Los Angeles",
    "sg:classifiers":[
        {
            "category":"Building & Trades",
            "subcategory":"Cleaning & Sanitation",
            "type":"Services"
        }
    ],
    "sg:phone":"+1 323 299 4600",
    "sg:postcode":"90056",
    "sg:province":"CA",
    "sg:tags":[
        "carpet"
    ],
    "sg:website":"web.me.com/digitalvideorecall/UL...",
    "wof:name":"Ultra-Brite Carpet and Upholstery Care",
    "wof:placetype":"venue"
},
  "geometry": {"coordinates":[-118.36776999999999,33.984767],"type":"Point"}
}