{
  "type": "Feature",
  "properties": {
    "iso:country":"US",
    "sg:address":"1527 E 4th St",
    "sg:city":"Santa Ana",
    "sg:classifiers":[
        {
            "category":"Professional",
            "subcategory":"Lawyer & Legal Services",
            "type":"Services"
        }
    ],
    "sg:phone":"+1 714 836 5700",
    "sg:postcode":"92701",
    "sg:province":"CA",
    "sg:tags":[
        "attorney"
    ],
    "wof:name":"Harker James Law Offices",
    "wof:placetype":"venue"
},
  "geometry": {"coordinates":[-117.84899900000001,33.748199],"type":"Point"}
}