{
  "type": "Feature",
  "properties": {
    "iso:country":"US",
    "sg:address":"2062 S Oaks Ave",
    "sg:city":"Ontario",
    "sg:classifiers":[
        {
            "category":"Building & Trades",
            "subcategory":"Construction",
            "type":"Services"
        }
    ],
    "sg:phone":"+1 909 702 5519",
    "sg:postcode":"91762",
    "sg:province":"CA",
    "sg:tags":[
        "masonry",
        "contractor"
    ],
    "wof:name":"Douma Masonry",
    "wof:placetype":"venue"
},
  "geometry": {"coordinates":[-117.67647700000001,34.035826],"type":"Point"}
}