{
  "type": "Feature",
  "properties": {
    "addr:full":"1313 N Milpitas Blvd Ste 235 San Jose CA 95138",
    "addr:housenumber":"1313",
    "addr:postcode":"95138",
    "addr:street":"N Milpitas Blvd Ste 235",
    "iso:country":"US",
    "sg:address":"1313 N Milpitas Blvd Ste 235",
    "sg:city":"San Jose",
    "sg:classifiers":[
        {
            "category":"Real Estate",
            "subcategory":"Real Estate Services",
            "type":"Services"
        },
        {
            "category":"Banks & Credit Unions",
            "subcategory":"Investment Brokerage",
            "type":"Services"
        },
        {
            "category":"Banks & Credit Unions",
            "subcategory":"Financial Services",
            "type":"Services"
        }
    ],
    "sg:phone":"+1 415 205 0255",
    "sg:postcode":"95138",
    "sg:province":"CA",
    "sg:tags":[
        "investing",
        "broker",
        "mortgage"
    ],
    "wof:name":"Royal Marc Financial",
    "wof:placetype":"venue"
},
  "geometry": {"coordinates":[-121.91081200000001,37.45023],"type":"Point"}
}