{
  "type": "Feature",
  "properties": {
    "addr:full":"388 9th St Ste 183 Oakland CA 94607",
    "addr:housenumber":"388",
    "addr:postcode":"94607",
    "addr:street":"9Th St Ste 183",
    "iso:country":"US",
    "sg:address":"388 9th St Ste 183",
    "sg:city":"Oakland",
    "sg:classifiers":[
        {
            "category":"Shopping",
            "subcategory":"Crafts & Fabrics",
            "type":"Retail Goods"
        }
    ],
    "sg:phone":"+1 510 839 6888",
    "sg:postcode":"94607",
    "sg:province":"CA",
    "sg:tags":[
        "art",
        "supply"
    ],
    "wof:name":"House of Fortune",
    "wof:placetype":"venue"
},
  "geometry": {"coordinates":[-122.272003,37.800301],"type":"Point"}
}