{
  "type": "Feature",
  "properties": {
    "iso:country":"US",
    "sg:address":"2204 Chris Ct",
    "sg:city":"Bakersfield",
    "sg:classifiers":[
        {
            "category":"Wholesale",
            "subcategory":"Vending Machines",
            "type":"Manufacturing & Wholesale Goods"
        }
    ],
    "sg:phone":"+1 661 871 1310",
    "sg:postcode":"93306",
    "sg:province":"CA",
    "wof:name":"Quality Vending",
    "wof:placetype":"venue"
},
  "geometry": {"coordinates":[-118.959454,35.38739],"type":"Point"}
}