{
  "type": "Feature",
  "properties": {
    "iso:country":"US",
    "sg:address":"127 N Madison Ave",
    "sg:city":"Pasadena",
    "sg:classifiers":[
        {
            "category":"Health Services",
            "subcategory":"Health Practitioner",
            "type":"Services"
        },
        {
            "category":"Communications",
            "type":"Services"
        }
    ],
    "sg:phone":"+1 626 795 5593",
    "sg:postcode":"91101",
    "sg:province":"CA",
    "sg:tags":[
        "pathologist",
        "speech-language",
        "audiologists",
        "therapy",
        "myofunctional"
    ],
    "wof:name":"Rosemary Scott",
    "wof:placetype":"venue"
},
  "geometry": {"coordinates":[-118.138418,34.148033],"type":"Point"}
}