{
  "type": "Feature",
  "properties": {
    "addr:full":"9337 Emerald Grove Ave Lakeside CA 92040",
    "addr:housenumber":"9337",
    "addr:postcode":"92040",
    "addr:street":"Emerald Grove Ave",
    "iso:country":"US",
    "sg:address":"9337 Emerald Grove Ave",
    "sg:city":"Lakeside",
    "sg:classifiers":[
        {
            "category":"Wholesale",
            "subcategory":"Home Furnishings",
            "type":"Manufacturing & Wholesale Goods"
        }
    ],
    "sg:phone":"+1 619 561 2542",
    "sg:postcode":"92040",
    "sg:province":"CA",
    "wof:name":"Carol-Joy Donohue",
    "wof:placetype":"venue"
},
  "geometry": {"coordinates":[-116.938186,32.847391],"type":"Point"}
}