{
  "type": "Feature",
  "properties": {
    "iso:country":"US",
    "sg:address":"5400 Thomas Ave",
    "sg:city":"Oakland",
    "sg:classifiers":[
        {
            "category":"Professional",
            "subcategory":"Detective & Security Services",
            "type":"Services"
        }
    ],
    "sg:phone":"+1 510 658 2040",
    "sg:postcode":"94618",
    "sg:province":"CA",
    "sg:tags":[
        "information",
        "bureau"
    ],
    "wof:name":"Healthstar Laser Services Inc",
    "wof:placetype":"venue"
},
  "geometry": {"coordinates":[-122.248497,37.838879],"type":"Point"}
}