{
  "type": "Feature",
  "properties": {
    "addr:full":"5031 N Figueroa St Los Angeles CA 90042",
    "addr:housenumber":"5031",
    "addr:postcode":"90042",
    "addr:street":"N Figueroa St",
    "iso:country":"US",
    "sg:address":"5031 N Figueroa St",
    "sg:city":"Los Angeles",
    "sg:classifiers":[
        {
            "category":"Arts & Performance",
            "subcategory":"Theater",
            "type":"Entertainment"
        }
    ],
    "sg:phone":"+1 323 259 5000",
    "sg:postcode":"90042",
    "sg:province":"CA",
    "sg:tags":[
        "bureau"
    ],
    "wof:name":"El Che Production",
    "wof:placetype":"venue"
},
  "geometry": {"coordinates":[-118.20121,34.10549],"type":"Point"}
}