{
  "type": "Feature",
  "properties": {
    "iso:country":"US",
    "sg:address":"6717 Fairwinds Ct",
    "sg:city":"Alta Loma",
    "sg:classifiers":[
        {
            "category":"Manufacturing",
            "subcategory":"Food",
            "type":"Manufacturing & Wholesale Goods"
        },
        {
            "category":"Restaurant",
            "type":"Food & Drink"
        }
    ],
    "sg:phone":"+1 909 948 7970",
    "sg:postcode":"91701",
    "sg:province":"CA",
    "sg:tags":[
        "preparation",
        "mfg",
        "caterer"
    ],
    "wof:name":"Gumbo Ya Ya",
    "wof:placetype":"venue"
},
  "geometry": {"coordinates":[-117.556862,34.133821],"type":"Point"}
}