{
  "type": "Feature",
  "properties": {
    "iso:country":"US",
    "sg:address":"951 Mariners Island Blvd Ste 150",
    "sg:city":"San Mateo",
    "sg:classifiers":[
        {
            "category":"Banks & Credit Unions",
            "subcategory":"Financial Services",
            "type":"Services"
        }
    ],
    "sg:phone":"+1 650 573 6888",
    "sg:postcode":"94404",
    "sg:province":"CA",
    "sg:tags":[
        "broker",
        "mortgage"
    ],
    "wof:name":"Cc Legacy Financial",
    "wof:placetype":"venue"
},
  "geometry": {"coordinates":[-122.28751800000001,37.558816],"type":"Point"}
}