{
  "type": "Feature",
  "properties": {
    "iso:country":"US",
    "sg:address":"1284 W Shaw Ave",
    "sg:city":"Fresno",
    "sg:classifiers":[
        {
            "category":"Health Services",
            "subcategory":"Optometrist",
            "type":"Services"
        }
    ],
    "sg:phone":"+1 559 244 6040",
    "sg:postcode":"93711",
    "sg:province":"CA",
    "wof:name":"Northwest Optometry Assoc Inc",
    "wof:placetype":"venue"
},
  "geometry": {"coordinates":[-119.81482,36.808412],"type":"Point"}
}