{
  "type": "Feature",
  "properties": {
    "addr:full":"224 Garnsey Ave Bakersfield CA 93309",
    "addr:housenumber":"224",
    "addr:postcode":"93309",
    "addr:street":"Garnsey Ave",
    "iso:country":"US",
    "sg:address":"224 Garnsey Ave",
    "sg:city":"Bakersfield",
    "sg:classifiers":[
        {
            "category":"Home & Garden",
            "subcategory":"Building Materials",
            "type":"Retail Goods"
        },
        {
            "category":"Building & Trades",
            "subcategory":"Construction",
            "type":"Services"
        },
        {
            "category":"Home & Garden",
            "subcategory":"Carpets & Floor Coverings",
            "type":"Retail Goods"
        }
    ],
    "sg:phone":"+1 661 549 9857",
    "sg:postcode":"93309",
    "sg:province":"CA",
    "sg:tags":[
        "concrete",
        "staining",
        "flooring",
        "contractor"
    ],
    "wof:name":"Concrete Connections",
    "wof:placetype":"venue"
},
  "geometry": {"coordinates":[-119.045868,35.356641],"type":"Point"}
}