{
  "type": "Feature",
  "properties": {
    "addr:full":"3000 Geer Rd Turlock CA 95382",
    "addr:housenumber":"3000",
    "addr:postcode":"95382",
    "addr:street":"Geer Rd",
    "iso:country":"US",
    "sg:address":"3000 Geer Rd",
    "sg:city":"Turlock",
    "sg:classifiers":[
        {
            "category":"Coffee & Tea",
            "type":"Food & Drink"
        }
    ],
    "sg:menulink":"http://www.allmenus.com/ca/turlock/118547-starbucks-coffee/menu/",
    "sg:phone":"+1 209 656 1460",
    "sg:postcode":"95382",
    "sg:province":"CA",
    "sg:tags":[
        "american"
    ],
    "wof:name":"Starbucks Coffee",
    "wof:placetype":"venue"
},
  "geometry": {"coordinates":[-120.848426,37.520226],"type":"Point"}
}