{
  "type": "Feature",
  "properties": {
    "iso:country":"US",
    "sg:address":"1318 Opal St",
    "sg:city":"San Diego",
    "sg:classifiers":[
        {
            "category":"Travel",
            "subcategory":"Travel Agent",
            "type":"Entertainment"
        }
    ],
    "sg:phone":"+1 858 488 2209",
    "sg:postcode":"92109",
    "sg:province":"CA",
    "sg:tags":[
        "operator",
        "tour"
    ],
    "wof:name":"Where Your Want To Be Tours",
    "wof:placetype":"venue"
},
  "geometry": {"coordinates":[-117.246948,32.808535],"type":"Point"}
}