{
  "type": "Feature",
  "properties": {
    "addr:full":"800 Howe Ave Ste 440 Sacramento CA 95825",
    "addr:housenumber":"800",
    "addr:postcode":"95825",
    "addr:street":"Howe Ave Ste 440",
    "iso:country":"US",
    "sg:address":"800 Howe Ave Ste 440",
    "sg:city":"Sacramento",
    "sg:classifiers":[
        {
            "category":"Professional",
            "subcategory":"Detective & Security Services",
            "type":"Services"
        }
    ],
    "sg:phone":"+1 916 614 9571",
    "sg:postcode":"95825",
    "sg:province":"CA",
    "sg:tags":[
        "control",
        "patrol",
        "consultant",
        "system",
        "equipment",
        "guard",
        "monitoring"
    ],
    "wof:name":"ABM Security",
    "wof:placetype":"venue"
},
  "geometry": {"coordinates":[-121.41538199999999,38.579281],"type":"Point"}
}