{
  "type": "Feature",
  "properties": {
    "addr:full":"2256 Main St Chula Vista CA 91911",
    "addr:housenumber":"2256",
    "addr:postcode":"91911",
    "addr:street":"Main St",
    "iso:country":"US",
    "sg:address":"2256 Main St",
    "sg:city":"Chula Vista",
    "sg:classifiers":[
        {
            "category":"Professional",
            "type":"Services"
        }
    ],
    "sg:phone":"+1 619 423 3203",
    "sg:postcode":"91911",
    "sg:province":"CA",
    "sg:tags":[
        "establishment"
    ],
    "wof:name":"Cipesa Corp",
    "wof:placetype":"venue"
},
  "geometry": {"coordinates":[-117.086699,32.594944],"type":"Point"}
}