{
  "type": "Feature",
  "properties": {
    "iso:country":"US",
    "sg:address":"20301 Ventura Blvd",
    "sg:city":"Woodland Hills",
    "sg:classifiers":[
        {
            "category":"Professional",
            "subcategory":"Lawyer & Legal Services",
            "type":"Services"
        }
    ],
    "sg:phone":"+1 818 703 7600",
    "sg:postcode":"91364",
    "sg:province":"CA",
    "wof:name":"Mendelson Law Group",
    "wof:placetype":"venue"
},
  "geometry": {"coordinates":[-118.574986,34.169628],"type":"Point"}
}