{
  "type": "Feature",
  "properties": {
    "addr:full":"2875 Mitchell Dr Walnut Creek CA 94598",
    "addr:housenumber":"2875",
    "addr:postcode":"94598",
    "addr:street":"Mitchell Dr",
    "iso:country":"US",
    "sg:address":"2875 Mitchell Dr",
    "sg:city":"Walnut Creek",
    "sg:classifiers":[
        {
            "category":"Social Services",
            "subcategory":"Child Care",
            "type":"Services"
        }
    ],
    "sg:phone":"+1 925 935 5562",
    "sg:postcode":"94598",
    "sg:province":"CA",
    "wof:name":"Children's World Learning Ctr",
    "wof:placetype":"venue"
},
  "geometry": {"coordinates":[-122.024647,37.929129],"type":"Point"}
}