{
  "type": "Feature",
  "properties": {
    "iso:country":"US",
    "sg:address":"6375 Creekview Ct",
    "sg:city":"Martinez",
    "sg:classifiers":[
        {
            "category":"Food & Beverages",
            "subcategory":"Liquor & Beverages",
            "type":"Retail Goods"
        },
        {
            "category":"Wholesale",
            "subcategory":"Wine & Distilled Alcoholic Beverages",
            "type":"Manufacturing & Wholesale Goods"
        }
    ],
    "sg:phone":"+1 925 370 6997",
    "sg:postcode":"94553",
    "sg:province":"CA",
    "sg:tags":[
        "broker"
    ],
    "wof:name":"Winecentives",
    "wof:placetype":"venue"
},
  "geometry": {"coordinates":[-122.10274099999999,37.9638],"type":"Point"}
}