{
  "type": "Feature",
  "properties": {
    "iso:country":"US",
    "sg:address":"118 Auto Center Dr. #45",
    "sg:city":"Foothill Ranch",
    "sg:classifiers":[
        {
            "category":"Personal",
            "subcategory":"Nail Salon",
            "type":"Services"
        }
    ],
    "sg:phone":"+1 949 454 0745",
    "sg:postcode":"92610",
    "sg:province":"CA",
    "wof:name":"Red Persimmon Nail & Spa",
    "wof:placetype":"venue"
},
  "geometry": {"coordinates":[-117.659802,33.67542],"type":"Point"}
}