{
  "type": "Feature",
  "properties": {
    "iso:country":"US",
    "sg:address":"147 N Santa Cruz Ave",
    "sg:city":"Los Gatos",
    "sg:classifiers":[
        {
            "category":"Shopping",
            "subcategory":"Optician",
            "type":"Retail Goods"
        }
    ],
    "sg:phone":"+1 408 395 3199",
    "sg:postcode":"95030",
    "sg:province":"CA",
    "sg:tags":[
        "eyewear"
    ],
    "wof:name":"U & I Eyeware & Sunglasses",
    "wof:placetype":"venue"
},
  "geometry": {"coordinates":[-121.98200199999999,37.225899],"type":"Point"}
}