{
  "type": "Feature",
  "properties": {
    "addr:full":"16440 Martincoit Rd Poway CA 92064",
    "addr:housenumber":"16440",
    "addr:postcode":"ca 92064",
    "addr:street":"Martincoit Rd",
    "iso:country":"US",
    "sg:address":"16440 Martincoit Rd",
    "sg:city":"Poway",
    "sg:classifiers":[
        {
            "category":"Real Estate",
            "subcategory":"Real Estate Agent",
            "type":"Services"
        }
    ],
    "sg:phone":"+1 858 676 1211",
    "sg:postcode":"92064",
    "sg:province":"CA",
    "wof:name":"Arrow Realty",
    "wof:placetype":"venue"
},
  "geometry": {"coordinates":[-117.038371,33.009687],"type":"Point"}
}