{
  "type": "Feature",
  "properties": {
    "addr:full":"12812 Arroyo St Sylmar CA 91342",
    "addr:housenumber":"12812",
    "addr:postcode":"91342",
    "addr:street":"Arroyo St",
    "iso:country":"US",
    "sg:address":"12812 Arroyo St",
    "sg:city":"Sylmar",
    "sg:classifiers":[
        {
            "category":"Wholesale",
            "subcategory":"Hardware",
            "type":"Manufacturing & Wholesale Goods"
        }
    ],
    "sg:phone":"+1 818 365 9451",
    "sg:postcode":"91342",
    "sg:province":"CA",
    "sg:tags":[
        "parts",
        "refrigerating"
    ],
    "wof:name":"Anthony International",
    "wof:placetype":"venue"
},
  "geometry": {"coordinates":[-118.411644,34.294759],"type":"Point"}
}