{
  "type": "Feature",
  "properties": {
    "addr:full":"1109 E Prosperity Ave Tulare CA 93274",
    "addr:housenumber":"1109",
    "addr:postcode":"93274",
    "addr:street":"E Prosperity Ave",
    "iso:country":"US",
    "sg:address":"1109 E Prosperity Ave",
    "sg:city":"Tulare",
    "sg:classifiers":[
        {
            "category":"Retail",
            "subcategory":"Laundry & Dry Cleaning",
            "type":"Services"
        }
    ],
    "sg:phone":"+1 559 687 1976",
    "sg:postcode":"93274",
    "sg:province":"CA",
    "sg:tags":[
        "cleaner"
    ],
    "sg:website":"http://www.quality-cleaners.com",
    "wof:name":"Quality Cleaners",
    "wof:placetype":"venue"
},
  "geometry": {"coordinates":[-119.330727,36.225815],"type":"Point"}
}