{
  "type": "Feature",
  "properties": {
    "iso:country":"US",
    "sg:address":"16200 Watson Rd",
    "sg:city":"Guerneville",
    "sg:classifiers":[
        {
            "category":"Building & Trades",
            "subcategory":"Construction",
            "type":"Services"
        }
    ],
    "sg:phone":"+1 707 869 3745",
    "sg:postcode":"95446",
    "sg:province":"CA",
    "sg:tags":[
        "fabricator",
        "metal"
    ],
    "wof:name":"Meuller Metals",
    "wof:placetype":"venue"
},
  "geometry": {"coordinates":[-122.998364,38.516557],"type":"Point"}
}