{
  "type": "Feature",
  "properties": {
    "iso:country":"US",
    "sg:address":"2604 E Cesar E Chavez Ave",
    "sg:city":"Los Angeles",
    "sg:classifiers":[
        {
            "category":"Personal",
            "subcategory":"Beauty Salon",
            "type":"Services"
        }
    ],
    "sg:phone":"+1 323 269 2706",
    "sg:postcode":"90033",
    "sg:province":"CA",
    "wof:name":"Crystal Hair Design",
    "wof:placetype":"venue"
},
  "geometry": {"coordinates":[-118.204124,34.045112],"type":"Point"}
}