{
  "type": "Feature",
  "properties": {
    "iso:country":"US",
    "sg:address":"3962 Sorrento Valley Blvd",
    "sg:city":"San Diego",
    "sg:classifiers":[
        {
            "category":"Personal",
            "type":"Services"
        }
    ],
    "sg:phone":"+1 949 366 1460",
    "sg:postcode":"92121",
    "sg:province":"CA",
    "sg:tags":[
        "organization",
        "consumer"
    ],
    "wof:name":"UCC Total Home Of San Diego",
    "wof:placetype":"venue"
},
  "geometry": {"coordinates":[-117.214151,32.905037],"type":"Point"}
}