{
  "type": "Feature",
  "properties": {
    "iso:country":"US",
    "sg:address":"8007 Somerset Blvd",
    "sg:city":"Paramount",
    "sg:classifiers":[
        {
            "category":"Food & Beverages",
            "subcategory":"Liquor & Beverages",
            "type":"Retail Goods"
        }
    ],
    "sg:phone":"+1 562 634 7087",
    "sg:postcode":"90723",
    "sg:province":"CA",
    "sg:tags":[
        "beer",
        "spirit",
        "wine"
    ],
    "wof:name":"Tequila Ranch Liquor Mart",
    "wof:placetype":"venue"
},
  "geometry": {"coordinates":[-118.159622,33.896604],"type":"Point"}
}