{
  "type": "Feature",
  "properties": {
    "addr:full":"257 S Kelly Rd American Canyon CA 94589",
    "addr:housenumber":"257",
    "addr:postcode":"94589",
    "addr:street":"S Kelly Rd American",
    "iso:country":"US",
    "sg:address":"257 S Kelly Rd",
    "sg:city":"American Canyon",
    "sg:phone":"+1 707 252 6888",
    "sg:postcode":"94589",
    "sg:province":"CA",
    "sg:tags":[
        "gas"
    ],
    "wof:name":"Napa Valley Petroleum",
    "wof:placetype":"venue"
},
  "geometry": {"coordinates":[-122.254541,38.209247],"type":"Point"}
}