{
  "type": "Feature",
  "properties": {
    "iso:country":"US",
    "sg:address":"939 Howard St",
    "sg:city":"San Francisco",
    "sg:classifiers":[
        {
            "category":"Shopping",
            "subcategory":"Stationery & Office Supplies",
            "type":"Retail Goods"
        }
    ],
    "sg:phone":"+1 415 777 0722",
    "sg:postcode":"94103",
    "sg:province":"CA",
    "wof:name":"Blue Bird Office Supply",
    "wof:placetype":"venue"
},
  "geometry": {"coordinates":[-122.405174,37.781317],"type":"Point"}
}