{
  "type": "Feature",
  "properties": {
    "addr:full":"24952 Ariella Dr Calabasas CA 91302",
    "addr:housenumber":"24952",
    "addr:postcode":"91302",
    "addr:street":"Ariella Dr",
    "iso:country":"US",
    "sg:address":"24952 Ariella Dr",
    "sg:city":"Calabasas",
    "sg:classifiers":[
        {
            "category":"Travel",
            "subcategory":"Travel Agent",
            "type":"Entertainment"
        }
    ],
    "sg:phone":"+1 818 884 8320",
    "sg:postcode":"91302",
    "sg:province":"CA",
    "sg:tags":[
        "agency",
        "bureau"
    ],
    "wof:name":"Westbrent Travel Svc",
    "wof:placetype":"venue"
},
  "geometry": {"coordinates":[-118.666068,34.139013],"type":"Point"}
}