{
  "type": "Feature",
  "properties": {
    "addr:full":"9164 Independence Ave Chatsworth CA 91311",
    "addr:housenumber":"9164",
    "addr:postcode":"91311",
    "addr:street":"Independence Ave",
    "iso:country":"US",
    "sg:address":"9164 Independence Ave",
    "sg:city":"Chatsworth",
    "sg:classifiers":[
        {
            "category":"Manufacturing",
            "subcategory":"Metals",
            "type":"Manufacturing & Wholesale Goods"
        }
    ],
    "sg:phone":"+1 818 341 2191",
    "sg:postcode":"91311",
    "sg:province":"CA",
    "sg:tags":[
        "plating"
    ],
    "sg:website":"www.plateronics.com",
    "wof:name":"Plateronics Processing Inc",
    "wof:placetype":"venue"
},
  "geometry": {"coordinates":[-118.59075300000001,34.23659],"type":"Point"}
}