{
  "type": "Feature",
  "properties": {
    "iso:country":"US",
    "sg:address":"4848 E Wasatch Dr",
    "sg:city":"Anaheim",
    "sg:classifiers":[
        {
            "category":"Shopping",
            "subcategory":"Gifts & Souvenirs",
            "type":"Retail Goods"
        }
    ],
    "sg:phone":"+1 714 998 4905",
    "sg:postcode":"92807",
    "sg:province":"CA",
    "sg:tags":[
        "flower"
    ],
    "wof:name":"Gifts In A Basket",
    "wof:placetype":"venue"
},
  "geometry": {"coordinates":[-117.81165300000001,33.851635],"type":"Point"}
}