{
  "type": "Feature",
  "properties": {
    "iso:country":"US",
    "sg:address":"2436 Loma Vista Dr",
    "sg:city":"Sacramento",
    "sg:classifiers":[
        {
            "category":"Health Services",
            "subcategory":"Health Practitioner",
            "type":"Services"
        }
    ],
    "sg:phone":"+1 916 482 6898",
    "sg:postcode":"95825",
    "sg:province":"CA",
    "sg:tags":[
        "hypnotist"
    ],
    "wof:name":"Inner Works",
    "wof:placetype":"venue"
},
  "geometry": {"coordinates":[-121.400622,38.609408],"type":"Point"}
}