{
  "type": "Feature",
  "properties": {
    "iso:country":"US",
    "sg:address":"6219 Imperial Ave",
    "sg:city":"San Diego",
    "sg:classifiers":[
        {
            "category":"Personal",
            "subcategory":"Beauty Salon",
            "type":"Services"
        }
    ],
    "sg:phone":"+1 619 266 9419",
    "sg:postcode":"92114",
    "sg:province":"CA",
    "wof:name":"Pat's Palace Of Beauty",
    "wof:placetype":"venue"
},
  "geometry": {"coordinates":[-117.062787,32.709884],"type":"Point"}
}