{
  "type": "Feature",
  "properties": {
    "iso:country":"US",
    "sg:address":"5159 Cmt Cachorro",
    "sg:city":"San Diego",
    "sg:classifiers":[
        {
            "category":"Shopping",
            "subcategory":"Computers & Home Electronics",
            "type":"Retail Goods"
        }
    ],
    "sg:phone":"+1 619 266 1790",
    "sg:postcode":"92105",
    "sg:province":"CA",
    "wof:name":"Inspire One Computer Services",
    "wof:placetype":"venue"
},
  "geometry": {"coordinates":[-117.086991,32.732723],"type":"Point"}
}