{
  "type": "Feature",
  "properties": {
    "addr:full":"12341 Carmenita Rd Whittier CA 90605",
    "addr:housenumber":"12341",
    "addr:postcode":"90605",
    "addr:street":"Carmenita Rd",
    "iso:country":"US",
    "sg:address":"12341 Carmenita Rd",
    "sg:city":"Whittier",
    "sg:classifiers":[
        {
            "category":"Autos & Motor Vehicles",
            "subcategory":"Automobile Sales",
            "type":"Retail Goods"
        }
    ],
    "sg:phone":"+1 562 941 1841",
    "sg:postcode":"90605",
    "sg:province":"CA",
    "wof:name":"Francisco Barajas",
    "wof:placetype":"venue"
},
  "geometry": {"coordinates":[-118.04656199999999,33.9194],"type":"Point"}
}