{
  "type": "Feature",
  "properties": {
    "addr:full":"31075 Quarry St Mentone CA 92359",
    "addr:housenumber":"31075",
    "addr:postcode":"92359",
    "addr:street":"Quarry St",
    "iso:country":"US",
    "sg:address":"31075 Quarry St",
    "sg:city":"Mentone",
    "sg:classifiers":[
        {
            "category":"Health Services",
            "subcategory":"Hospital",
            "type":"Services"
        }
    ],
    "sg:phone":"+1 909 794 6744",
    "sg:postcode":"92359",
    "sg:province":"CA",
    "sg:tags":[
        "sleep",
        "treatment",
        "disorders-information"
    ],
    "wof:name":"Omni Rehab & Therapy Center",
    "wof:placetype":"venue"
},
  "geometry": {"coordinates":[-117.126395,34.067188],"type":"Point"}
}