{
  "type": "Feature",
  "properties": {
    "addr:full":"5073 Federal Blvd San Diego CA 92102",
    "addr:housenumber":"5073",
    "addr:postcode":"92102",
    "addr:street":"Federal Blvd",
    "iso:country":"US",
    "sg:address":"5073 Federal Blvd",
    "sg:city":"San Diego",
    "sg:classifiers":[
        {
            "category":"Autos & Motor Vehicles",
            "subcategory":"Auto Supplies",
            "type":"Retail Goods"
        }
    ],
    "sg:phone":"+1 619 527 4101",
    "sg:postcode":"92102",
    "sg:province":"CA",
    "sg:tags":[
        "automobile",
        "parts"
    ],
    "sg:website":"www.autozone.com",
    "wof:name":"Autozone",
    "wof:placetype":"venue"
},
  "geometry": {"coordinates":[-117.08562999999999,32.721344],"type":"Point"}
}