{
  "type": "Feature",
  "properties": {
    "addr:full":"5571 W Adams Blvd Los Angeles CA 90016",
    "addr:housenumber":"5571",
    "addr:postcode":"90016",
    "addr:street":"W Adams Blvd",
    "iso:country":"US",
    "sg:address":"5571 W Adams Blvd",
    "sg:city":"Los Angeles",
    "sg:classifiers":[
        {
            "category":"Shopping",
            "subcategory":"Gifts & Souvenirs",
            "type":"Retail Goods"
        }
    ],
    "sg:phone":"+1 323 937 5057",
    "sg:postcode":"90016",
    "sg:province":"CA",
    "sg:tags":[
        "party",
        "supply"
    ],
    "wof:name":"Lupita's Party Supplies",
    "wof:placetype":"venue"
},
  "geometry": {"coordinates":[-118.364733,34.032465],"type":"Point"}
}