{
  "type": "Feature",
  "properties": {
    "iso:country":"US",
    "sg:address":"728 S Hill St Ste 705",
    "sg:city":"Los Angeles",
    "sg:classifiers":[
        {
            "category":"Shopping",
            "subcategory":"Jewelry",
            "type":"Retail Goods"
        }
    ],
    "sg:phone":"+1 213 622 4248",
    "sg:postcode":"90014",
    "sg:province":"CA",
    "wof:name":"Zig Zag Jewelry",
    "wof:placetype":"venue"
},
  "geometry": {"coordinates":[-118.254736,34.045041],"type":"Point"}
}