{
  "type": "Feature",
  "properties": {
    "iso:country":"US",
    "sg:address":"9709 Lurline Ave",
    "sg:city":"Chatsworth",
    "sg:classifiers":[
        {
            "category":"Manufacturing",
            "subcategory":"Tools & Machinery",
            "type":"Manufacturing & Wholesale Goods"
        }
    ],
    "sg:phone":"+1 818 882 2535",
    "sg:postcode":"91311",
    "sg:province":"CA",
    "sg:tags":[
        "machine",
        "shop"
    ],
    "wof:name":"Aero Technology Co",
    "wof:placetype":"venue"
},
  "geometry": {"coordinates":[-118.584254,34.247945],"type":"Point"}
}