{
  "type": "Feature",
  "properties": {
    "iso:country":"US",
    "sg:address":"187 E Wilbur Rd",
    "sg:city":"Thousand Oaks",
    "sg:classifiers":[
        {
            "category":"Health Services",
            "subcategory":"Health Practitioner",
            "type":"Services"
        }
    ],
    "sg:phone":"+1 805 494 8340",
    "sg:postcode":"91360",
    "sg:province":"CA",
    "sg:tags":[
        "homeopath"
    ],
    "wof:name":"Laurie Monteleone Classical",
    "wof:placetype":"venue"
},
  "geometry": {"coordinates":[-118.874589,34.186668],"type":"Point"}
}