{
  "type": "Feature",
  "properties": {
    "addr:full":"9065 Pajaro Ln Atascadero CA 93422",
    "addr:housenumber":"9065",
    "addr:postcode":"93422",
    "addr:street":"Pajaro Ln",
    "iso:country":"US",
    "sg:address":"9065 Pajaro Ln",
    "sg:city":"Atascadero",
    "sg:classifiers":[
        {
            "category":"Building & Trades",
            "subcategory":"Construction",
            "type":"Services"
        }
    ],
    "sg:phone":"+1 805 238 4270",
    "sg:postcode":"93422",
    "sg:province":"CA",
    "sg:tags":[
        "roofing",
        "contractor"
    ],
    "wof:name":"Paso Robles Roofing Co",
    "wof:placetype":"venue"
},
  "geometry": {"coordinates":[-120.657538,35.472467],"type":"Point"}
}