{
  "type": "Feature",
  "properties": {
    "iso:country":"US",
    "sg:address":"286 S 16th St",
    "sg:city":"Grover Beach",
    "sg:classifiers":[
        {
            "category":"Health Services",
            "subcategory":"Hospital",
            "type":"Services"
        }
    ],
    "sg:phone":"+1 805 473 7034",
    "sg:postcode":"93433",
    "sg:province":"CA",
    "sg:tags":[
        "general"
    ],
    "wof:name":"Slo Co HSP Grover Bch Pediatrc",
    "wof:placetype":"venue"
},
  "geometry": {"coordinates":[-120.611813,35.119113],"type":"Point"}
}