{
  "type": "Feature",
  "properties": {
    "addr:full":"11795 Education St Auburn CA 95602",
    "addr:housenumber":"11795",
    "addr:postcode":"ca 95602",
    "addr:street":"Education St",
    "iso:country":"US",
    "sg:address":"11795 Education St",
    "sg:city":"Auburn",
    "sg:classifiers":[
        {
            "category":"Government",
            "subcategory":"Office",
            "type":"Public Place"
        }
    ],
    "sg:phone":"+1 530 889 5700",
    "sg:postcode":"95602",
    "sg:province":"CA",
    "sg:tags":[
        "support",
        "child"
    ],
    "wof:name":"Children Support Services",
    "wof:placetype":"venue"
},
  "geometry": {"coordinates":[-121.09957799999999,38.944239],"type":"Point"}
}