{
  "type": "Feature",
  "properties": {
    "iso:country":"US",
    "sg:address":"12239 Santa Monica Blvd",
    "sg:city":"Los Angeles",
    "sg:classifiers":[
        {
            "category":"Restaurant",
            "type":"Food & Drink"
        }
    ],
    "sg:phone":"+1 310 207 5496",
    "sg:postcode":"90025",
    "sg:province":"CA",
    "wof:name":"Best Chinese Food",
    "wof:placetype":"venue"
},
  "geometry": {"coordinates":[-118.46516099999999,34.039852],"type":"Point"}
}