{
  "type": "Feature",
  "properties": {
    "addr:full":"6430 Franklin Blvd Sacramento CA 95823",
    "addr:housenumber":"6430",
    "addr:postcode":"95823",
    "addr:street":"Franklin Blvd",
    "iso:country":"US",
    "sg:address":"6430 Franklin Blvd",
    "sg:city":"Sacramento",
    "sg:classifiers":[
        {
            "category":"Shopping",
            "subcategory":"Computers & Home Electronics",
            "type":"Retail Goods"
        },
        {
            "category":"Professional",
            "subcategory":"Computer Services",
            "type":"Services"
        }
    ],
    "sg:phone":"+1 916 429 2293",
    "sg:postcode":"95823",
    "sg:province":"CA",
    "sg:tags":[
        "stereo",
        "installation"
    ],
    "sg:website":"www.acmetopsandtunes.com",
    "wof:name":"Acme Tops & Tunes",
    "wof:placetype":"venue"
},
  "geometry": {"coordinates":[-121.46684,38.509128],"type":"Point"}
}