{
  "type": "Feature",
  "properties": {
    "iso:country":"US",
    "sg:address":"24421 Jefferson Ave",
    "sg:city":"Murrieta",
    "sg:classifiers":[
        {
            "category":"Building & Trades",
            "subcategory":"Construction",
            "type":"Services"
        }
    ],
    "sg:phone":"+1 951 698 2556",
    "sg:postcode":"92562",
    "sg:province":"CA",
    "sg:tags":[
        "plastering",
        "contractor"
    ],
    "wof:name":"Best Plastering",
    "wof:placetype":"venue"
},
  "geometry": {"coordinates":[-117.215805,33.565943],"type":"Point"}
}