{
  "type": "Feature",
  "properties": {
    "addr:full":"540 N Court St Visalia CA 93291",
    "addr:housenumber":"540",
    "addr:postcode":"93291",
    "addr:street":"N Court St",
    "iso:country":"US",
    "sg:address":"540 N Court St",
    "sg:city":"Visalia",
    "sg:classifiers":[
        {
            "category":"Food & Beverages",
            "subcategory":"Groceries & Convenience Stores",
            "type":"Retail Goods"
        }
    ],
    "sg:phone":"+1 559 625 3569",
    "sg:postcode":"93291",
    "sg:province":"CA",
    "wof:name":"Lee Sarn",
    "wof:placetype":"venue"
},
  "geometry": {"coordinates":[-119.292294,36.334702],"type":"Point"}
}