{
  "type": "Feature",
  "properties": {
    "iso:country":"US",
    "sg:address":"2910 Jefferson St",
    "sg:city":"Carlsbad",
    "sg:classifiers":[
        {
            "category":"Organizations",
            "subcategory":"Professional Association",
            "type":"Services"
        }
    ],
    "sg:phone":"+1 760 730 1471",
    "sg:postcode":"92008",
    "sg:province":"CA",
    "wof:name":"Cardiovascular Disease Fndtn",
    "wof:placetype":"venue"
},
  "geometry": {"coordinates":[-117.34564,33.161509],"type":"Point"}
}