{
  "type": "Feature",
  "properties": {
    "iso:country":"US",
    "sg:address":"4059 26th St",
    "sg:city":"San Francisco",
    "sg:classifiers":[
        {
            "category":"Professional",
            "subcategory":"Management & Consulting",
            "type":"Services"
        }
    ],
    "sg:phone":"+1 415 641 7146",
    "sg:postcode":"94131",
    "sg:province":"CA",
    "wof:name":"HDA Consulting",
    "wof:placetype":"venue"
},
  "geometry": {"coordinates":[-122.43051699999999,37.748233],"type":"Point"}
}