{
  "type": "Feature",
  "properties": {
    "addr:full":"427 N Canon Dr Beverly Hills CA 90210",
    "addr:housenumber":"427",
    "addr:postcode":"90210",
    "addr:street":"N Canon Dr",
    "iso:country":"US",
    "sg:address":"427 N Canon Dr",
    "sg:city":"Beverly Hills",
    "sg:classifiers":[
        {
            "category":"Travel",
            "subcategory":"Hotels & Motels",
            "type":"Entertainment"
        }
    ],
    "sg:phone":"+1 310 205 9100",
    "sg:postcode":"90210",
    "sg:province":"CA",
    "wof:name":"Monarchy Hotel Group",
    "wof:placetype":"venue"
},
  "geometry": {"coordinates":[-118.401487,34.101381],"type":"Point"}
}