{
  "type": "Feature",
  "properties": {
    "iso:country":"US",
    "sg:address":"3661 N. Freeway Blvd # 105",
    "sg:city":"Sacramento",
    "sg:classifiers":[
        {
            "category":"Personal",
            "subcategory":"Beauty Salon",
            "type":"Services"
        }
    ],
    "sg:phone":"+1 916 928 9976",
    "sg:postcode":"95834",
    "sg:province":"CA",
    "sg:tags":[
        "spa"
    ],
    "sg:website":"www.topcoatsalon.com",
    "wof:name":"Top Coat Nail Salon",
    "wof:placetype":"venue"
},
  "geometry": {"coordinates":[-121.497001,38.639292],"type":"Point"}
}