{
  "type": "Feature",
  "properties": {
    "addr:full":"18916 Gale Ave La Puente CA 91748",
    "addr:housenumber":"18916",
    "addr:postcode":"91748",
    "addr:street":"Gale Ave",
    "iso:country":"US",
    "sg:address":"18916 Gale Ave",
    "sg:city":"La Puente",
    "sg:classifiers":[
        {
            "category":"Personal",
            "subcategory":"Beauty Salon",
            "type":"Services"
        }
    ],
    "sg:phone":"+1 626 965 6536",
    "sg:postcode":"91748",
    "sg:province":"CA",
    "wof:name":"Shinny Beauty Salon",
    "wof:placetype":"venue"
},
  "geometry": {"coordinates":[-117.89038600000001,33.995632],"type":"Point"}
}