{
  "type": "Feature",
  "properties": {
    "addr:full":"9550 Flair Dr El Monte CA 91731",
    "addr:housenumber":"9550",
    "addr:postcode":"91731",
    "addr:street":"Flair Dr",
    "iso:country":"US",
    "sg:address":"9550 Flair Dr",
    "sg:city":"El Monte",
    "sg:classifiers":[
        {
            "category":"Professional",
            "subcategory":"Lawyer & Legal Services",
            "type":"Services"
        }
    ],
    "sg:phone":"+1 626 442 2434",
    "sg:postcode":"91731",
    "sg:province":"CA",
    "wof:name":"Khuong-Atty",
    "wof:placetype":"venue"
},
  "geometry": {"coordinates":[-118.060997,34.071999],"type":"Point"}
}