{
  "type": "Feature",
  "properties": {
    "addr:full":"2235 W Middlefield Rd Mountain View CA 94043",
    "addr:housenumber":"2235",
    "addr:postcode":"94043",
    "addr:street":"W Middlefield Rd",
    "iso:country":"US",
    "sg:address":"2235 W Middlefield Rd",
    "sg:city":"Mountain View",
    "sg:classifiers":[
        {
            "category":"Retail",
            "subcategory":"Auto Repair",
            "type":"Services"
        }
    ],
    "sg:phone":"+1 650 962 0930",
    "sg:postcode":"94043",
    "sg:province":"CA",
    "sg:tags":[
        "repairing",
        "automobile"
    ],
    "wof:name":"Heyer Performance",
    "wof:placetype":"venue"
},
  "geometry": {"coordinates":[-122.09744499999999,37.411857],"type":"Point"}
}