{
  "type": "Feature",
  "properties": {
    "iso:country":"US",
    "sg:address":"114 N Coast Highway 101",
    "sg:city":"Encinitas",
    "sg:classifiers":[
        {
            "category":"Autos & Motor Vehicles",
            "subcategory":"Automobile Sales",
            "type":"Retail Goods"
        }
    ],
    "sg:phone":"+1 760 632 2500",
    "sg:postcode":"92024",
    "sg:province":"CA",
    "sg:tags":[
        "dealers-used",
        "car",
        "used",
        "cars-wholesale"
    ],
    "wof:name":"Marina Motors",
    "wof:placetype":"venue"
},
  "geometry": {"coordinates":[-117.294352,33.049978],"type":"Point"}
}