{
  "type": "Feature",
  "properties": {
    "iso:country":"US",
    "sg:address":"4319 Bidwell Dr",
    "sg:city":"Fremont",
    "sg:classifiers":[
        {
            "category":"Wholesale",
            "subcategory":"Computers",
            "type":"Manufacturing & Wholesale Goods"
        }
    ],
    "sg:phone":"+1 510 793 8845",
    "sg:postcode":"94538",
    "sg:province":"CA",
    "sg:tags":[
        "equipment",
        "peripheral",
        "software"
    ],
    "wof:name":"Global Import Sale",
    "wof:placetype":"venue"
},
  "geometry": {"coordinates":[-121.979187,37.538773],"type":"Point"}
}