{
  "type": "Feature",
  "properties": {
    "iso:country":"US",
    "sg:address":"1400 10th St",
    "sg:city":"Sacramento",
    "sg:classifiers":[
        {
            "category":"Education",
            "subcategory":"University",
            "type":"Public Place"
        }
    ],
    "sg:phone":"+1 916 558 2511",
    "sg:postcode":"95814",
    "sg:province":"CA",
    "sg:tags":[
        "college"
    ],
    "wof:name":"Sacramento City College",
    "wof:placetype":"venue"
},
  "geometry": {"coordinates":[-121.495541,38.575923],"type":"Point"}
}