{
  "type": "Feature",
  "properties": {
    "iso:country":"US",
    "sg:address":"14845 S Main Street",
    "sg:city":"Gardena",
    "sg:classifiers":[
        {
            "category":"Restaurant",
            "type":"Food & Drink"
        }
    ],
    "sg:phone":"+1 310 532 0277",
    "sg:postcode":"90248",
    "sg:province":"CA",
    "wof:name":"Fabulous Grill On Main Street",
    "wof:placetype":"venue"
},
  "geometry": {"coordinates":[-118.275436,33.897501],"type":"Point"}
}