{
  "type": "Feature",
  "properties": {
    "iso:country":"US",
    "sg:address":"207 Roma St",
    "sg:city":"Redlands",
    "sg:classifiers":[
        {
            "category":"Retail",
            "subcategory":"Animal Services",
            "type":"Services"
        }
    ],
    "sg:phone":"+1 909 792 8795",
    "sg:postcode":"92373",
    "sg:province":"CA",
    "wof:name":"Planeta Professional Dog Train",
    "wof:placetype":"venue"
},
  "geometry": {"coordinates":[-117.19117,34.046775],"type":"Point"}
}