{
  "type": "Feature",
  "properties": {
    "addr:full":"845 W Market St Salinas CA 93901",
    "addr:housenumber":"845",
    "addr:postcode":"93901",
    "addr:street":"W Market St",
    "iso:country":"US",
    "sg:address":"845 W Market St",
    "sg:city":"Salinas",
    "sg:classifiers":[
        {
            "category":"Wholesale",
            "subcategory":"Office Equipment",
            "type":"Manufacturing & Wholesale Goods"
        }
    ],
    "sg:phone":"+1 831 424 2153",
    "sg:postcode":"93901",
    "sg:province":"CA",
    "sg:tags":[
        "machine",
        "duplicating",
        "copying"
    ],
    "wof:name":"N P Office Machines",
    "wof:placetype":"venue"
},
  "geometry": {"coordinates":[-121.671577,36.683409],"type":"Point"}
}