{
  "type": "Feature",
  "properties": {
    "addr:full":"8022 Florence Avenue Downey CA 90240",
    "addr:housenumber":"8022",
    "addr:postcode":"90240",
    "addr:street":"Florence Avenue",
    "iso:country":"US",
    "sg:address":"8022 Florence Avenue",
    "sg:city":"Downey",
    "sg:classifiers":[
        {
            "category":"Shopping",
            "subcategory":"Shoes",
            "type":"Retail Goods"
        }
    ],
    "sg:phone":"+1 562 928 0854",
    "sg:postcode":"90240",
    "sg:province":"CA",
    "sg:tags":[
        "store"
    ],
    "sg:website":"www.shoecity.com",
    "wof:name":"Shoe City",
    "wof:placetype":"venue"
},
  "geometry": {"coordinates":[-118.12950499999999,33.953182],"type":"Point"}
}