{
  "type": "Feature",
  "properties": {
    "iso:country":"US",
    "sg:address":"1806 Flower Ave",
    "sg:city":"Duarte",
    "sg:classifiers":[
        {
            "category":"Home & Garden",
            "subcategory":"Building Materials",
            "type":"Retail Goods"
        }
    ],
    "sg:phone":"+1 626 599 9494",
    "sg:postcode":"91010",
    "sg:province":"CA",
    "sg:tags":[
        "door"
    ],
    "sg:website":"www.socaloverheaddoor.com",
    "wof:name":"Southern California Overhead",
    "wof:placetype":"venue"
},
  "geometry": {"coordinates":[-117.962153,34.133485],"type":"Point"}
}