{
  "type": "Feature",
  "properties": {
    "addr:full":"12437 Magnolia Ave Livingston CA 95334",
    "addr:housenumber":"12437",
    "addr:postcode":"95334",
    "addr:street":"Magnolia Ave",
    "iso:country":"US",
    "sg:address":"12437 Magnolia Ave",
    "sg:city":"Livingston",
    "sg:classifiers":[
        {
            "category":"Food & Beverages",
            "subcategory":"Fruits & Vegetables",
            "type":"Retail Goods"
        }
    ],
    "sg:phone":"+1 209 394 2777",
    "sg:postcode":"95334",
    "sg:province":"CA",
    "sg:tags":[
        "produce"
    ],
    "wof:name":"Doreva Produce",
    "wof:placetype":"venue"
},
  "geometry": {"coordinates":[-120.717033,37.367681],"type":"Point"}
}