{
  "type": "Feature",
  "properties": {
    "iso:country":"US",
    "sg:address":"429 Bauchet St",
    "sg:city":"Los Angeles",
    "sg:classifiers":[
        {
            "category":"Government",
            "subcategory":"Court House",
            "type":"Public Place"
        }
    ],
    "sg:phone":"+1 213 974 6068",
    "sg:postcode":"90012",
    "sg:province":"CA",
    "sg:tags":[
        "misdemeanor",
        "arraignment"
    ],
    "wof:name":"Los Angels Cnty Mncpl Court",
    "wof:placetype":"venue"
},
  "geometry": {"coordinates":[-118.23003,34.059815],"type":"Point"}
}