{
  "type": "Feature",
  "properties": {
    "addr:full":"388 E Valley Blvd Ste 120 Alhambra CA 91801",
    "addr:housenumber":"388",
    "addr:postcode":"91801",
    "addr:street":"E Valley Blvd Ste 120",
    "iso:country":"US",
    "sg:address":"388 E Valley Blvd Ste 120",
    "sg:city":"Alhambra",
    "sg:classifiers":[
        {
            "category":"Insurance",
            "subcategory":"Hazard Insurance",
            "type":"Services"
        }
    ],
    "sg:phone":"+1 626 437 6237",
    "sg:postcode":"91801",
    "sg:province":"CA",
    "sg:website":"www.libertymutual.com/ryanchou",
    "wof:name":"Ryan Chou - Liberty Mutual Insurance",
    "wof:placetype":"venue"
},
  "geometry": {"coordinates":[-118.11829899999999,34.078832],"type":"Point"}
}