{
  "type": "Feature",
  "properties": {
    "addr:full":"1401 N Tustin Ave Santa Ana CA 92705",
    "addr:housenumber":"1401",
    "addr:postcode":"92705",
    "addr:street":"N Tustin Ave",
    "iso:country":"US",
    "sg:address":"1401 N Tustin Ave",
    "sg:city":"Santa Ana",
    "sg:classifiers":[
        {
            "category":"Banks & Credit Unions",
            "subcategory":"Financial Services",
            "type":"Services"
        }
    ],
    "sg:phone":"+1 714 834 9907",
    "sg:postcode":"92705",
    "sg:province":"CA",
    "sg:tags":[
        "broker",
        "mortgage"
    ],
    "wof:name":"Citinet Mortgage",
    "wof:placetype":"venue"
},
  "geometry": {"coordinates":[-117.833975,33.756393],"type":"Point"}
}