{
  "type": "Feature",
  "properties": {
    "addr:full":"849 Almar Ave # B Santa Cruz CA 95060",
    "addr:housenumber":"849",
    "addr:postcode":"95060",
    "addr:street":"Almar Ave # B",
    "iso:country":"US",
    "sg:address":"849 Almar Ave # B",
    "sg:city":"Santa Cruz",
    "sg:classifiers":[
        {
            "category":"Shopping",
            "subcategory":"Pets & Pet Supplies",
            "type":"Retail Goods"
        }
    ],
    "sg:phone":"+1 831 429 1242",
    "sg:postcode":"95060",
    "sg:province":"CA",
    "sg:tags":[
        "store"
    ],
    "sg:website":"www.tropaquarium.net",
    "wof:name":"Trop-Aquarium & Pet Center-Santa Cruz",
    "wof:placetype":"venue"
},
  "geometry": {"coordinates":[-122.043999,36.960999],"type":"Point"}
}