{
  "type": "Feature",
  "properties": {
    "iso:country":"US",
    "sg:address":"924 E Main St",
    "sg:city":"Alhambra",
    "sg:classifiers":[
        {
            "category":"Food & Beverages",
            "subcategory":"Meat & Fish",
            "type":"Retail Goods"
        }
    ],
    "sg:phone":"+1 626 216 7983",
    "sg:postcode":"91801",
    "sg:province":"CA",
    "wof:name":"S & J Meat Enterprise Inc",
    "wof:placetype":"venue"
},
  "geometry": {"coordinates":[-118.115663,34.100482],"type":"Point"}
}