{
  "type": "Feature",
  "properties": {
    "iso:country":"US",
    "sg:address":"1990 3rd St",
    "sg:city":"Sacramento",
    "sg:classifiers":[
        {
            "category":"Social Services",
            "type":"Services"
        },
        {
            "category":"Personal",
            "type":"Services"
        }
    ],
    "sg:phone":"+1 916 455 8169",
    "sg:postcode":"95811",
    "sg:province":"CA",
    "sg:tags":[
        "individual",
        "family",
        "professional",
        "counselors-licensed",
        "therapist",
        "marriage",
        "child",
        "counseling",
        "counselor"
    ],
    "wof:name":"Miller, Nancy G MFCC",
    "wof:placetype":"venue"
},
  "geometry": {"coordinates":[-121.50749999999999,38.571889],"type":"Point"}
}