{
  "type": "Feature",
  "properties": {
    "addr:full":"765 Pennsylvania Ave San Francisco CA 94107",
    "addr:housenumber":"765",
    "addr:postcode":"94107",
    "addr:street":"Pennsylvania Ave",
    "iso:country":"US",
    "sg:address":"765 Pennsylvania Ave",
    "sg:city":"San Francisco",
    "sg:classifiers":[
        {
            "category":"Travel",
            "subcategory":"Travel Agent",
            "type":"Entertainment"
        },
        {
            "category":"Landmark",
            "subcategory":"Tourist Information",
            "type":"Public Place"
        }
    ],
    "sg:phone":"+1 415 642 7378",
    "sg:postcode":"94107",
    "sg:province":"CA",
    "sg:tags":[
        "tour"
    ],
    "sg:website":"www.incadventures.com/trips/sanf...",
    "wof:name":"Incredible Adventures",
    "wof:placetype":"venue"
},
  "geometry": {"coordinates":[-122.39275000000001,37.756408],"type":"Point"}
}