{
  "type": "Feature",
  "properties": {
    "addr:full":"460 State Hwy 49 Sutter Creek CA 95685",
    "addr:housenumber":"460",
    "addr:postcode":"95685",
    "addr:street":"State Hwy 49",
    "iso:country":"US",
    "sg:address":"460 State Hwy 49",
    "sg:city":"Sutter Creek",
    "sg:classifiers":[
        {
            "category":"Autos & Motor Vehicles",
            "subcategory":"Auto Supplies",
            "type":"Retail Goods"
        }
    ],
    "sg:phone":"+1 209 267 5241",
    "sg:postcode":"95685",
    "sg:province":"CA",
    "sg:tags":[
        "automobile",
        "parts"
    ],
    "wof:name":"ATI Parts",
    "wof:placetype":"venue"
},
  "geometry": {"coordinates":[-120.80825299999999,38.399098],"type":"Point"}
}