{
  "type": "Feature",
  "properties": {
    "iso:country":"US",
    "sg:address":"3196 de Forest Rd",
    "sg:city":"Marina",
    "sg:classifiers":[
        {
            "category":"Building & Trades",
            "subcategory":"Cleaning & Sanitation",
            "type":"Services"
        }
    ],
    "sg:phone":"+1 831 384 2222",
    "sg:postcode":"93933",
    "sg:province":"CA",
    "sg:tags":[
        "janitor"
    ],
    "wof:name":"Yang's Maintenance",
    "wof:placetype":"venue"
},
  "geometry": {"coordinates":[-121.79347799999999,36.684697],"type":"Point"}
}