{
  "type": "Feature",
  "properties": {
    "iso:country":"US",
    "sg:address":"12526 High Bluff Dr",
    "sg:city":"San Diego",
    "sg:classifiers":[
        {
            "category":"Real Estate",
            "subcategory":"Real Estate Services",
            "type":"Services"
        }
    ],
    "sg:phone":"+1 858 755 8222",
    "sg:postcode":"92130",
    "sg:province":"CA",
    "wof:name":"LTV Capital Inc",
    "wof:placetype":"venue"
},
  "geometry": {"coordinates":[-117.240853,32.945497],"type":"Point"}
}