{
  "type": "Feature",
  "properties": {
    "iso:country":"US",
    "sg:address":"40379 Rd 96",
    "sg:city":"Dinuba",
    "sg:classifiers":[
        {
            "category":"Manufacturing",
            "subcategory":"Metals",
            "type":"Manufacturing & Wholesale Goods"
        }
    ],
    "sg:phone":"+1 559 591 5299",
    "sg:postcode":"93618",
    "sg:province":"CA",
    "sg:tags":[
        "box",
        "mail"
    ],
    "wof:name":"Fisher Mail Houses",
    "wof:placetype":"venue"
},
  "geometry": {"coordinates":[-119.358654,36.516918],"type":"Point"}
}