{
  "type": "Feature",
  "properties": {
    "iso:country":"US",
    "sg:address":"2125 S el Camino Real",
    "sg:city":"Oceanside",
    "sg:classifiers":[
        {
            "category":"Health Services",
            "subcategory":"Health Practitioner",
            "type":"Services"
        }
    ],
    "sg:phone":"+1 760 722 6468",
    "sg:postcode":"92054",
    "sg:province":"CA",
    "sg:tags":[
        "psychologist"
    ],
    "wof:name":"Margot B Kopley",
    "wof:placetype":"venue"
},
  "geometry": {"coordinates":[-117.328428,33.187886],"type":"Point"}
}