{
  "type": "Feature",
  "properties": {
    "iso:country":"US",
    "sg:address":"3232 San Helena Dr",
    "sg:city":"Oceanside",
    "sg:classifiers":[
        {
            "category":"Professional",
            "subcategory":"Secretarial Services",
            "type":"Services"
        }
    ],
    "sg:phone":"+1 760 757 5233",
    "sg:postcode":"92056",
    "sg:province":"CA",
    "sg:tags":[
        "processing",
        "word"
    ],
    "wof:name":"A Diversified Svc Ctr",
    "wof:placetype":"venue"
},
  "geometry": {"coordinates":[-117.311527,33.19926],"type":"Point"}
}