{
  "type": "Feature",
  "properties": {
    "iso:country":"US",
    "sg:address":"7427 Woodley Ave",
    "sg:city":"Van Nuys",
    "sg:classifiers":[
        {
            "category":"Education",
            "subcategory":"Vocational School",
            "type":"Public Place"
        }
    ],
    "sg:phone":"+1 818 901 7168",
    "sg:postcode":"91406",
    "sg:province":"CA",
    "wof:name":"Pacific Security Training",
    "wof:placetype":"venue"
},
  "geometry": {"coordinates":[-118.483739,34.204871],"type":"Point"}
}