{
  "type": "Feature",
  "properties": {
    "addr:full":"2812 176th St Torrance CA 90504",
    "addr:housenumber":"2812",
    "addr:postcode":"90504",
    "addr:street":"176Th St",
    "iso:country":"US",
    "sg:address":"2812 176th St",
    "sg:city":"Torrance",
    "sg:classifiers":[
        {
            "category":"Building & Trades",
            "subcategory":"Construction",
            "type":"Services"
        }
    ],
    "sg:phone":"+1 310 329 5564",
    "sg:postcode":"90504",
    "sg:province":"CA",
    "sg:tags":[
        "carpenter"
    ],
    "wof:name":"Allpro Carpentry",
    "wof:placetype":"venue"
},
  "geometry": {"coordinates":[-118.32342800000001,33.871304],"type":"Point"}
}