{
  "type": "Feature",
  "properties": {
    "iso:country":"US",
    "sg:address":"225 S Milpas St",
    "sg:city":"Santa Barbara",
    "sg:classifiers":[
        {
            "category":"Retail",
            "subcategory":"Auto Repair",
            "type":"Services"
        }
    ],
    "sg:phone":"+1 805 965 8705",
    "sg:postcode":"93103",
    "sg:province":"CA",
    "sg:tags":[
        "transmission"
    ],
    "wof:name":"Alphonso's Transmission",
    "wof:placetype":"venue"
},
  "geometry": {"coordinates":[-119.674663,34.41861],"type":"Point"}
}