{
  "type": "Feature",
  "properties": {
    "iso:country":"US",
    "sg:address":"68685 Ramon Rd",
    "sg:city":"Cathedral City",
    "sg:classifiers":[
        {
            "category":"Personal",
            "subcategory":"Tanning Parlor",
            "type":"Services"
        },
        {
            "category":"Personal",
            "subcategory":"Day Spa",
            "type":"Services"
        }
    ],
    "sg:phone":"+1 760 324 4321",
    "sg:postcode":"92234",
    "sg:province":"CA",
    "sg:website":"www.guiltytans.com",
    "wof:name":"GUILTY TANS",
    "wof:placetype":"venue"
},
  "geometry": {"coordinates":[-116.463504,33.815742],"type":"Point"}
}