{
  "type": "Feature",
  "properties": {
    "iso:country":"US",
    "sg:address":"1420 4th St",
    "sg:city":"Santa Monica",
    "sg:classifiers":[
        {
            "category":"Personal",
            "subcategory":"Tattoo Parlor",
            "type":"Services"
        }
    ],
    "sg:phone":"+1 310 395 4663",
    "sg:postcode":"90401",
    "sg:province":"CA",
    "sg:tags":[
        "tattooing"
    ],
    "sg:website":"www.goodart.com",
    "wof:name":"Good Art Co Body Jewelry",
    "wof:placetype":"venue"
},
  "geometry": {"coordinates":[-118.493912,34.015299],"type":"Point"}
}