{
  "type": "Feature",
  "properties": {
    "iso:country":"US",
    "sg:address":"4067 Hardwick St",
    "sg:city":"Lakewood",
    "sg:classifiers":[
        {
            "category":"Professional",
            "subcategory":"Engineering",
            "type":"Services"
        }
    ],
    "sg:phone":"+1 562 377 1678",
    "sg:postcode":"90712",
    "sg:province":"CA",
    "sg:tags":[
        "engineer"
    ],
    "wof:name":"Hayer Consultants Inc",
    "wof:placetype":"venue"
},
  "geometry": {"coordinates":[-118.144853,33.850549],"type":"Point"}
}