{
  "type": "Feature",
  "properties": {
    "addr:full":"453 4th Ave Chula Vista CA 91910",
    "addr:housenumber":"453",
    "addr:postcode":"91910",
    "addr:street":"4Th Ave",
    "iso:country":"US",
    "sg:address":"453 4th Ave",
    "sg:city":"Chula Vista",
    "sg:classifiers":[
        {
            "category":"Shopping",
            "type":"Retail Goods"
        }
    ],
    "sg:phone":"+1 619 427 9900",
    "sg:postcode":"91910",
    "sg:province":"CA",
    "sg:tags":[
        "hearing",
        "equipment",
        "supply",
        "impaired"
    ],
    "wof:name":"South Bay Hearing & Balance",
    "wof:placetype":"venue"
},
  "geometry": {"coordinates":[-117.081281,32.633466],"type":"Point"}
}