{
  "type": "Feature",
  "properties": {
    "addr:full":"14615 Palmdale Rd Victorville CA 92392",
    "addr:housenumber":"14615",
    "addr:postcode":"92392",
    "addr:street":"Palmdale Rd",
    "iso:country":"US",
    "sg:address":"14615 Palmdale Rd",
    "sg:city":"Victorville",
    "sg:classifiers":[
        {
            "category":"Autos & Motor Vehicles",
            "subcategory":"Recreational Vehicle Sales",
            "type":"Retail Goods"
        }
    ],
    "sg:phone":"+1 760 955 9375",
    "sg:postcode":"92392",
    "sg:province":"CA",
    "wof:name":"Banning Discount Rv Ctr",
    "wof:placetype":"venue"
},
  "geometry": {"coordinates":[-117.344785,34.506668],"type":"Point"}
}