{
  "type": "Feature",
  "properties": {
    "iso:country":"US",
    "sg:address":"11100 Santa Monica Boulevard",
    "sg:city":"Los Angeles",
    "sg:classifiers":[
        {
            "category":"Banks & Credit Unions",
            "subcategory":"Bank",
            "type":"Services"
        }
    ],
    "sg:phone":"+1 310 996 6000",
    "sg:postcode":"90025",
    "sg:province":"CA",
    "wof:name":"Capital Research and Management Company",
    "wof:placetype":"venue"
},
  "geometry": {"coordinates":[-118.444294,34.047532],"type":"Point"}
}