{
  "type": "Feature",
  "properties": {
    "addr:full":"1555 Riverlake Rd Discovery Bay CA 94505",
    "addr:housenumber":"1555",
    "addr:postcode":"94505",
    "addr:street":"Riverlake Rd",
    "iso:country":"US",
    "sg:address":"1555 Riverlake Rd",
    "sg:city":"Discovery Bay",
    "sg:classifiers":[
        {
            "category":"Banks & Credit Unions",
            "subcategory":"Bank",
            "type":"Services"
        }
    ],
    "sg:phone":"+1 925 240 1636",
    "sg:postcode":"94505",
    "sg:province":"CA",
    "sg:tags":[
        "loan",
        "real estate"
    ],
    "wof:name":"Diversified Capitol",
    "wof:placetype":"venue"
},
  "geometry": {"coordinates":[-121.606297,37.902497],"type":"Point"}
}