{
  "type": "Feature",
  "properties": {
    "addr:full":"731 el Camino Real Redwood City CA 94063",
    "addr:housenumber":"731",
    "addr:postcode":"94063",
    "addr:street":"El Camino Real",
    "iso:country":"US",
    "sg:address":"731 el Camino Real",
    "sg:city":"Redwood City",
    "sg:classifiers":[
        {
            "category":"Shopping",
            "subcategory":"Tobacco",
            "type":"Retail Goods"
        }
    ],
    "sg:phone":"+1 650 364 8055",
    "sg:postcode":"94063",
    "sg:province":"CA",
    "sg:tags":[
        "cigarette",
        "cigar",
        "dealer"
    ],
    "wof:name":"Redwood Smoke Shop & Novelty",
    "wof:placetype":"venue"
},
  "geometry": {"coordinates":[-122.234996,37.486401],"type":"Point"}
}