{
  "type": "Feature",
  "properties": {
    "addr:full":"885 Laurel St San Carlos CA 94070",
    "addr:housenumber":"885",
    "addr:postcode":"94070",
    "addr:street":"Laurel St",
    "iso:country":"US",
    "sg:address":"885 Laurel St",
    "sg:city":"San Carlos",
    "sg:classifiers":[
        {
            "category":"Restaurant",
            "type":"Food & Drink"
        }
    ],
    "sg:menulink":"http://www.allmenus.com/ca/san-mateo/279451-yans-garden-chinese-restaurant/menu/",
    "sg:phone":"+1 650 593 9777",
    "sg:postcode":"94070",
    "sg:province":"CA",
    "sg:tags":[
        "asian",
        "chinese"
    ],
    "wof:name":"Yan's Garden Chinese Restaurant",
    "wof:placetype":"venue"
},
  "geometry": {"coordinates":[-122.256681,37.50273],"type":"Point"}
}