{
  "type": "Feature",
  "properties": {
    "addr:full":"1809 University Ave Berkeley CA 94703",
    "addr:housenumber":"1809",
    "addr:postcode":"94703",
    "addr:street":"University Ave",
    "iso:country":"US",
    "sg:address":"1809 University Ave",
    "sg:city":"Berkeley",
    "sg:classifiers":[
        {
            "category":"Education",
            "subcategory":"Music School",
            "type":"Public Place"
        }
    ],
    "sg:phone":"+1 510 665 5466",
    "sg:postcode":"94703",
    "sg:province":"CA",
    "sg:tags":[
        "instrument",
        "teacher",
        "musical"
    ],
    "sg:website":"www.goldenkeypianoschool.com",
    "wof:name":"Golden Key Piano School",
    "wof:placetype":"venue"
},
  "geometry": {"coordinates":[-122.274867,37.871474],"type":"Point"}
}