{
  "type": "Feature",
  "properties": {
    "addr:full":"Pier 38, Suite 208 The Embarcadero San Francisco CA 94107",
    "addr:housenumber":"suite 208",
    "addr:postcode":"94107",
    "addr:street":"The Embarcadero",
    "iso:country":"US",
    "sg:address":"Pier 38, Suite 208 The Embarcadero",
    "sg:city":"San Francisco",
    "sg:classifiers":[
        {
            "category":"Professional",
            "subcategory":"Computer Services",
            "type":"Services"
        }
    ],
    "sg:postcode":"94107",
    "sg:province":"CA",
    "sg:tags":[
        "social-discovery",
        "mobile",
        "lbs",
        "local-search",
        "trust-networks",
        "mobile-widgets",
        "iphone-apps",
        "personal-recommendations",
        "recommendation-engines",
        "gps"
    ],
    "sg:website":"http://www.rummble.com",
    "wof:name":"Rummble",
    "wof:placetype":"venue"
},
  "geometry": {"coordinates":[-122.39684099999999,37.782119],"type":"Point"}
}