{
  "type": "Feature",
  "properties": {
    "iso:country":"US",
    "sg:address":"7 Columbus Ave",
    "sg:city":"San Francisco",
    "sg:classifiers":[
        {
            "category":"Shopping",
            "subcategory":"Clothing, Apparel, & Fashions",
            "type":"Retail Goods"
        }
    ],
    "sg:phone":"+1 415 923 1263",
    "sg:postcode":"94111",
    "sg:province":"CA",
    "sg:tags":[
        "t"
    ],
    "sg:website":"www.promotionstore.com",
    "wof:name":"Promotion Store Inc",
    "wof:placetype":"venue"
},
  "geometry": {"coordinates":[-122.404057,37.795953],"type":"Point"}
}