{
  "type": "Feature",
  "properties": {
    "iso:country":"US",
    "sg:address":"128 Auburn Ct",
    "sg:city":"Westlake Village",
    "sg:classifiers":[
        {
            "category":"Social Services",
            "type":"Services"
        }
    ],
    "sg:phone":"+1 805 495 3355",
    "sg:postcode":"91362",
    "sg:province":"CA",
    "sg:tags":[
        "counseling",
        "disability",
        "learning"
    ],
    "wof:name":"Stacey Rogers",
    "wof:placetype":"venue"
},
  "geometry": {"coordinates":[-118.830612,34.1656],"type":"Point"}
}