{
  "type": "Feature",
  "properties": {
    "addr:full":"121 S Indian Hill Blvd Claremont CA 91711",
    "addr:housenumber":"121",
    "addr:postcode":"91711",
    "addr:street":"S Indian Hill Blvd",
    "iso:country":"US",
    "sg:address":"121 S Indian Hill Blvd",
    "sg:city":"Claremont",
    "sg:classifiers":[
        {
            "category":"Autos & Motor Vehicles",
            "subcategory":"Auto Supplies",
            "type":"Retail Goods"
        }
    ],
    "sg:phone":"+1 909 621 3843",
    "sg:postcode":"91711",
    "sg:province":"CA",
    "sg:tags":[
        "filter",
        "automobile",
        "part",
        "gas"
    ],
    "sg:website":"www.vortox.com",
    "wof:name":"Vortox Co",
    "wof:placetype":"venue"
},
  "geometry": {"coordinates":[-117.719306,34.09422],"type":"Point"}
}