{
  "type": "Feature",
  "properties": {
    "addr:full":"15050 Wild Way Los Gatos CA 95030",
    "addr:housenumber":"15050",
    "addr:postcode":"95030",
    "addr:street":"Wild Way",
    "iso:country":"US",
    "sg:address":"15050 Wild Way",
    "sg:city":"Los Gatos",
    "sg:classifiers":[
        {
            "category":"Insurance",
            "subcategory":"Insurance Agent",
            "type":"Services"
        }
    ],
    "sg:phone":"+1 408 395 9112",
    "sg:postcode":"95030",
    "sg:province":"CA",
    "sg:tags":[
        "real estate"
    ],
    "wof:name":"Patriot Financial",
    "wof:placetype":"venue"
},
  "geometry": {"coordinates":[-121.968022,37.24843],"type":"Point"}
}