{
  "type": "Feature",
  "properties": {
    "addr:full":"2194 Edison Avenue San Leandro CA 94577",
    "addr:housenumber":"2194",
    "addr:postcode":"94577",
    "addr:street":"Edison Avenue",
    "iso:country":"US",
    "sg:address":"2194 Edison Avenue",
    "sg:city":"San Leandro",
    "sg:classifiers":[
        {
            "category":"Restaurant",
            "type":"Food & Drink"
        }
    ],
    "sg:phone":"+1 510 632 1880",
    "sg:postcode":"94577",
    "sg:province":"CA",
    "sg:tags":[
        "new",
        "american"
    ],
    "wof:name":"The Big Cheese",
    "wof:placetype":"venue"
},
  "geometry": {"coordinates":[-122.189003,37.722599],"type":"Point"}
}