{
  "type": "Feature",
  "properties": {
    "iso:country":"US",
    "sg:address":"8555 Station Village Ln Suite B",
    "sg:city":"San Diego",
    "sg:classifiers":[
        {
            "category":"Personal",
            "subcategory":"Massage",
            "type":"Services"
        },
        {
            "category":"Health Services",
            "subcategory":"Health Practitioner",
            "type":"Services"
        },
        {
            "category":"Health Services",
            "subcategory":"Chiropractor",
            "type":"Services"
        }
    ],
    "sg:phone":"+1 619 284 3883",
    "sg:postcode":"92108",
    "sg:province":"CA",
    "sg:tags":[
        "therapy",
        "physical"
    ],
    "sg:website":"www.spencechiropractic.com",
    "wof:name":"Spence Chiropractic DC",
    "wof:placetype":"venue"
},
  "geometry": {"coordinates":[-117.14286199999999,32.77439],"type":"Point"}
}