{
  "type": "Feature",
  "properties": {
    "iso:country":"US",
    "sg:address":"1550 The Alameda Ste 300",
    "sg:city":"San Jose",
    "sg:classifiers":[
        {
            "category":"Professional",
            "subcategory":"Lawyer & Legal Services",
            "type":"Services"
        }
    ],
    "sg:phone":"+1 408 279 5040",
    "sg:postcode":"95126",
    "sg:province":"CA",
    "wof:name":"Law Office Of Jesse Jack",
    "wof:placetype":"venue"
},
  "geometry": {"coordinates":[-121.91574,37.334946],"type":"Point"}
}