{
  "type": "Feature",
  "properties": {
    "addr:full":"3800 W Wilson St Banning CA 92220",
    "addr:housenumber":"3800",
    "addr:postcode":"92220",
    "addr:street":"W Wilson St",
    "iso:country":"US",
    "sg:address":"3800 W Wilson St",
    "sg:city":"Banning",
    "sg:classifiers":[
        {
            "category":"Manufacturing",
            "subcategory":"Building Materials",
            "type":"Manufacturing & Wholesale Goods"
        }
    ],
    "sg:phone":"+1 951 849 4619",
    "sg:postcode":"92220",
    "sg:province":"CA",
    "sg:tags":[
        "mfg"
    ],
    "wof:name":"Woodworking Directions DOT Co",
    "wof:placetype":"venue"
},
  "geometry": {"coordinates":[-116.914501,33.932514],"type":"Point"}
}