{
  "type": "Feature",
  "properties": {
    "iso:country":"US",
    "sg:address":"1320 Industrial Ave",
    "sg:city":"Petaluma",
    "sg:classifiers":[
        {
            "category":"Building & Trades",
            "subcategory":"Construction",
            "type":"Services"
        }
    ],
    "sg:phone":"+1 707 769 8974",
    "sg:postcode":"94952",
    "sg:province":"CA",
    "sg:tags":[
        "contractor"
    ],
    "wof:name":"Construction Management Sltns",
    "wof:placetype":"venue"
},
  "geometry": {"coordinates":[-122.66974,38.268593],"type":"Point"}
}