{
  "type": "Feature",
  "properties": {
    "iso:country":"US",
    "sg:address":"93 W Main St",
    "sg:city":"Woodland",
    "sg:classifiers":[
        {
            "category":"Professional",
            "subcategory":"Computer Services",
            "type":"Services"
        }
    ],
    "sg:phone":"+1 530 666 5271",
    "sg:postcode":"95695",
    "sg:province":"CA",
    "sg:tags":[
        "repair"
    ],
    "wof:name":"INC Group",
    "wof:placetype":"venue"
},
  "geometry": {"coordinates":[-121.784424,38.677476],"type":"Point"}
}