{
  "type": "Feature",
  "properties": {
    "addr:full":"31491 Highview Dr Redlands CA 92373",
    "addr:postcode":"31491;92373",
    "addr:street":"Highview Dr",
    "iso:country":"US",
    "sg:address":"31491 Highview Dr",
    "sg:city":"Redlands",
    "sg:classifiers":[
        {
            "category":"Shopping",
            "subcategory":"Clothing, Apparel, & Fashions",
            "type":"Retail Goods"
        }
    ],
    "sg:phone":"+1 909 794 6094",
    "sg:postcode":"92373",
    "sg:province":"CA",
    "sg:tags":[
        "apparel",
        "women's"
    ],
    "wof:name":"Elc Design",
    "wof:placetype":"venue"
},
  "geometry": {"coordinates":[-117.117282,34.019741],"type":"Point"}
}