{
  "type": "Feature",
  "properties": {
    "iso:country":"US",
    "sg:address":"1786 N Reed Ave",
    "sg:city":"Reedley",
    "sg:classifiers":[
        {
            "category":"Education",
            "subcategory":"College",
            "type":"Public Place"
        }
    ],
    "sg:phone":"+1 559 637 1222",
    "sg:postcode":"93654",
    "sg:province":"CA",
    "wof:name":"Guidance and Learning Center",
    "wof:placetype":"venue"
},
  "geometry": {"coordinates":[-119.45760900000001,36.611486],"type":"Point"}
}