{
  "type": "Feature",
  "properties": {
    "iso:country":"US",
    "sg:address":"1449 W Jefferson Blvd",
    "sg:city":"Los Angeles",
    "sg:classifiers":[
        {
            "category":"Retail",
            "subcategory":"Auto Repair",
            "type":"Services"
        }
    ],
    "sg:phone":"+1 323 733 6896",
    "sg:postcode":"90007",
    "sg:province":"CA",
    "sg:tags":[
        "repairing",
        "automobile"
    ],
    "wof:name":"L A Auto Tech",
    "wof:placetype":"venue"
},
  "geometry": {"coordinates":[-118.29856700000001,34.025588],"type":"Point"}
}