{
  "type": "Feature",
  "properties": {
    "iso:country":"US",
    "sg:address":"42 Park Plaza Dr",
    "sg:city":"Daly City",
    "sg:classifiers":[
        {
            "category":"Wholesale",
            "subcategory":"Tobacco Products",
            "type":"Manufacturing & Wholesale Goods"
        }
    ],
    "sg:phone":"+1 650 991 3085",
    "sg:postcode":"94015",
    "sg:province":"CA",
    "wof:name":"Five Friends",
    "wof:placetype":"venue"
},
  "geometry": {"coordinates":[-122.481599,37.700849],"type":"Point"}
}