{
  "type": "Feature",
  "properties": {
    "addr:full":"6400 Brisa St Livermore CA 94550",
    "addr:postcode":"6400;94550",
    "addr:street":"Brisa St",
    "iso:country":"US",
    "sg:address":"6400 Brisa St",
    "sg:city":"Livermore",
    "sg:classifiers":[
        {
            "category":"Shopping",
            "subcategory":"Hobbies, Toys, & Games",
            "type":"Retail Goods"
        }
    ],
    "sg:phone":"+1 925 606 2600",
    "sg:postcode":"94550",
    "sg:province":"CA",
    "wof:name":"Discovery Toys Inc",
    "wof:placetype":"venue"
},
  "geometry": {"coordinates":[-121.718279,37.699581],"type":"Point"}
}