{
  "type": "Feature",
  "properties": {
    "addr:full":"1006 Stafford St Lodi CA 95242",
    "addr:housenumber":"1006",
    "addr:postcode":"95242",
    "addr:street":"Stafford St",
    "iso:country":"US",
    "sg:address":"1006 Stafford St",
    "sg:city":"Lodi",
    "sg:classifiers":[
        {
            "category":"Building & Trades",
            "subcategory":"Construction",
            "type":"Services"
        }
    ],
    "sg:phone":"+1 209 368 9357",
    "sg:postcode":"95242",
    "sg:province":"CA",
    "sg:tags":[
        "house"
    ],
    "wof:name":"Michael Stotts General Contr",
    "wof:placetype":"venue"
},
  "geometry": {"coordinates":[-121.295857,38.119748],"type":"Point"}
}