{
  "type": "Feature",
  "properties": {
    "addr:full":"855 E Portsmouth Dr Fresno CA 93720",
    "addr:housenumber":"855",
    "addr:postcode":"93720",
    "addr:street":"E Portsmouth Dr",
    "iso:country":"US",
    "sg:address":"855 E Portsmouth Dr",
    "sg:city":"Fresno",
    "sg:classifiers":[
        {
            "category":"Social Services",
            "subcategory":"Job Training",
            "type":"Services"
        }
    ],
    "sg:phone":"+1 559 433 1870",
    "sg:postcode":"93720",
    "sg:province":"CA",
    "sg:tags":[
        "rehabilitation"
    ],
    "wof:name":"Therapeutic Health Care Inc",
    "wof:placetype":"venue"
},
  "geometry": {"coordinates":[-119.76802499999999,36.892096],"type":"Point"}
}