{
  "type": "Feature",
  "properties": {
    "iso:country":"US",
    "sg:address":"931 San Bruno Ave W",
    "sg:city":"San Bruno",
    "sg:classifiers":[
        {
            "category":"Health Services",
            "subcategory":"Dentist",
            "type":"Services"
        }
    ],
    "sg:phone":"+1 650 583 3412",
    "sg:postcode":"94066",
    "sg:province":"CA",
    "wof:name":"Pulido Steven DDS",
    "wof:placetype":"venue"
},
  "geometry": {"coordinates":[-122.41916500000001,37.627619],"type":"Point"}
}