{
  "type": "Feature",
  "properties": {
    "iso:country":"US",
    "sg:address":"5770 Melrose Ave",
    "sg:city":"Los Angeles",
    "sg:classifiers":[
        {
            "category":"Personal",
            "subcategory":"Beauty Salon",
            "type":"Services"
        }
    ],
    "sg:phone":"+1 323 467 2471",
    "sg:postcode":"90038",
    "sg:province":"CA",
    "wof:name":"Natural Face Place",
    "wof:placetype":"venue"
},
  "geometry": {"coordinates":[-118.325372,34.083417],"type":"Point"}
}