{
  "type": "Feature",
  "properties": {
    "addr:full":"1138 W Church St Santa Maria CA 93458",
    "addr:housenumber":"1138",
    "addr:postcode":"93458",
    "addr:street":"W Church St",
    "iso:country":"US",
    "sg:address":"1138 W Church St",
    "sg:city":"Santa Maria",
    "sg:classifiers":[
        {
            "category":"Communications",
            "subcategory":"Television Station",
            "type":"Services"
        }
    ],
    "sg:phone":"+1 805 928 7700",
    "sg:postcode":"93458",
    "sg:province":"CA",
    "sg:tags":[
        "sales"
    ],
    "wof:name":"Wxtv",
    "wof:placetype":"venue"
},
  "geometry": {"coordinates":[-120.452235,34.951966],"type":"Point"}
}