{
  "type": "Feature",
  "properties": {
    "addr:full":"920 S La Brea Ave Los Angeles CA 90036",
    "addr:housenumber":"920",
    "addr:postcode":"90036",
    "addr:street":"S La Brea Ave",
    "iso:country":"US",
    "sg:address":"920 S La Brea Ave",
    "sg:city":"Los Angeles",
    "sg:classifiers":[
        {
            "category":"Retail",
            "subcategory":"Auto Rental",
            "type":"Services"
        }
    ],
    "sg:phone":"+1 323 932 9666",
    "sg:postcode":"90036",
    "sg:province":"CA",
    "sg:tags":[
        "car"
    ],
    "wof:name":"Aviv Rent A Car",
    "wof:placetype":"venue"
},
  "geometry": {"coordinates":[-118.34521100000001,34.058197],"type":"Point"}
}