{
  "type": "Feature",
  "properties": {
    "addr:full":"722 E Main St Santa Paula CA 93060",
    "addr:housenumber":"722",
    "addr:postcode":"93060",
    "addr:street":"E Main St",
    "iso:country":"US",
    "sg:address":"722 E Main St",
    "sg:city":"Santa Paula",
    "sg:classifiers":[
        {
            "category":"Health Services",
            "subcategory":"Doctor",
            "type":"Services"
        }
    ],
    "sg:phone":"+1 805 525 3001",
    "sg:postcode":"93060",
    "sg:province":"CA",
    "sg:tags":[
        "dentist"
    ],
    "wof:name":"A Dee Wayne Jones DDS",
    "wof:placetype":"venue"
},
  "geometry": {"coordinates":[-119.064871,34.352271],"type":"Point"}
}