{
  "type": "Feature",
  "properties": {
    "addr:full":"2425 Green St San Francisco CA 94123",
    "addr:housenumber":"2425",
    "addr:postcode":"94123",
    "addr:street":"Green St",
    "iso:country":"US",
    "sg:address":"2425 Green St",
    "sg:city":"San Francisco",
    "sg:classifiers":[
        {
            "category":"Banks & Credit Unions",
            "subcategory":"Investment Brokerage",
            "type":"Services"
        }
    ],
    "sg:phone":"+1 415 440 6744",
    "sg:postcode":"94123",
    "sg:province":"CA",
    "sg:tags":[
        "security"
    ],
    "wof:name":"Fulcrum Securities LLC",
    "wof:placetype":"venue"
},
  "geometry": {"coordinates":[-122.439904,37.79551],"type":"Point"}
}