{
  "type": "Feature",
  "properties": {
    "iso:country":"US",
    "sg:address":"1524 Steinbeck Dr",
    "sg:city":"Roseville",
    "sg:classifiers":[
        {
            "category":"Professional",
            "subcategory":"Computer Services",
            "type":"Services"
        }
    ],
    "sg:phone":"+1 916 771 5128",
    "sg:postcode":"95747",
    "sg:province":"CA",
    "sg:tags":[
        "graphics"
    ],
    "wof:name":"Bulldog Graphics",
    "wof:placetype":"venue"
},
  "geometry": {"coordinates":[-121.33650400000001,38.770872],"type":"Point"}
}