{
  "type": "Feature",
  "properties": {
    "iso:country":"US",
    "sg:address":"6918 Brighton Dr",
    "sg:city":"Dublin",
    "sg:classifiers":[
        {
            "category":"Retail",
            "subcategory":"Laundry & Dry Cleaning",
            "type":"Services"
        }
    ],
    "sg:phone":"+1 925 803 7641",
    "sg:postcode":"94568",
    "sg:province":"CA",
    "sg:tags":[
        "cleaners",
        "rug",
        "carpet"
    ],
    "wof:name":"Nichols Carpet Cleaning",
    "wof:placetype":"venue"
},
  "geometry": {"coordinates":[-121.921702,37.718146],"type":"Point"}
}