{
  "type": "Feature",
  "properties": {
    "iso:country":"US",
    "sg:address":"12540 Braddock Dr",
    "sg:city":"Los Angeles",
    "sg:classifiers":[
        {
            "category":"Building & Trades",
            "subcategory":"Construction",
            "type":"Services"
        }
    ],
    "sg:phone":"+1 310 577 2069",
    "sg:postcode":"90066",
    "sg:province":"CA",
    "sg:tags":[
        "contractor"
    ],
    "wof:name":"Dr Seal Good Co",
    "wof:placetype":"venue"
},
  "geometry": {"coordinates":[-118.423355,33.98679],"type":"Point"}
}