{
  "type": "Feature",
  "properties": {
    "addr:full":"11163 Sable River Ct Rancho Cordova CA 95670",
    "addr:housenumber":"11163",
    "addr:postcode":"95670",
    "addr:street":"Sable River Ct",
    "iso:country":"US",
    "sg:address":"11163 Sable River Ct",
    "sg:city":"Rancho Cordova",
    "sg:classifiers":[
        {
            "category":"Professional",
            "type":"Services"
        }
    ],
    "sg:phone":"+1 916 638 4336",
    "sg:postcode":"95670",
    "sg:province":"CA",
    "wof:name":"Cameo Dental Lab",
    "wof:placetype":"venue"
},
  "geometry": {"coordinates":[-121.269913,38.622679],"type":"Point"}
}