{
  "type": "Feature",
  "properties": {
    "addr:full":"1110 Santa Rosa Ave Santa Rosa CA 95404",
    "addr:housenumber":"1110",
    "addr:postcode":"95404",
    "addr:street":"Santa Rosa Ave",
    "iso:country":"US",
    "sg:address":"1110 Santa Rosa Ave",
    "sg:city":"Santa Rosa",
    "sg:classifiers":[
        {
            "category":"Wholesale",
            "subcategory":"Auto Parts",
            "type":"Manufacturing & Wholesale Goods"
        }
    ],
    "sg:phone":"+1 707 545 6700",
    "sg:postcode":"95404",
    "sg:province":"CA",
    "sg:tags":[
        "equipment",
        "truck"
    ],
    "sg:website":"www.santarosaauto.com",
    "wof:name":"Santa Rosa Auto Parts",
    "wof:placetype":"venue"
},
  "geometry": {"coordinates":[-122.713409,38.425834],"type":"Point"}
}