{
  "type": "Feature",
  "properties": {
    "addr:full":"503 W Whittier Blvd # 207 Montebello CA 90640",
    "addr:housenumber":"503",
    "addr:postcode":"90640",
    "addr:street":"W Whittier Blvd # 207",
    "iso:country":"US",
    "sg:address":"503 W Whittier Blvd # 207",
    "sg:city":"Montebello",
    "sg:classifiers":[
        {
            "category":"Social Services",
            "type":"Services"
        },
        {
            "category":"Professional",
            "subcategory":"Employment Agencies",
            "type":"Services"
        }
    ],
    "sg:phone":"+1 323 724 0758",
    "sg:postcode":"90640",
    "sg:province":"CA",
    "sg:tags":[
        "workers'",
        "placement",
        "volunteer"
    ],
    "wof:name":"Brigadas De Esperanza Internacional",
    "wof:placetype":"venue"
},
  "geometry": {"coordinates":[-118.104995,34.009385],"type":"Point"}
}