{
  "type": "Feature",
  "properties": {
    "addr:full":"120 W Elm Ct Burbank CA 91502",
    "addr:housenumber":"120",
    "addr:postcode":"91502",
    "addr:street":"W Elm Ct",
    "iso:country":"US",
    "sg:address":"120 W Elm Ct",
    "sg:city":"Burbank",
    "sg:classifiers":[
        {
            "category":"Retail",
            "subcategory":"Repair Shop",
            "type":"Services"
        }
    ],
    "sg:phone":"+1 818 845 2666",
    "sg:postcode":"91502",
    "sg:province":"CA",
    "sg:tags":[
        "repairing",
        "equipment",
        "electric"
    ],
    "wof:name":"Electro Energy Corp",
    "wof:placetype":"venue"
},
  "geometry": {"coordinates":[-118.30201,34.169505],"type":"Point"}
}