{
  "type": "Feature",
  "properties": {
    "addr:full":"984 Eureka Dr Turlock CA 95380",
    "addr:housenumber":"984",
    "addr:postcode":"95380",
    "addr:street":"Eureka Dr",
    "iso:country":"US",
    "sg:address":"984 Eureka Dr",
    "sg:city":"Turlock",
    "sg:classifiers":[
        {
            "category":"Freight",
            "type":"Transportation"
        }
    ],
    "sg:phone":"+1 209 656 1026",
    "sg:postcode":"95380",
    "sg:province":"CA",
    "sg:tags":[
        "operator",
        "local",
        "trucking"
    ],
    "wof:name":"Takhar Trucking",
    "wof:placetype":"venue"
},
  "geometry": {"coordinates":[-120.83885600000001,37.478555],"type":"Point"}
}