{
  "type": "Feature",
  "properties": {
    "addr:full":"1661 Soquel Dr Ste D Santa Cruz CA 95065",
    "addr:housenumber":"1661",
    "addr:postcode":"95065",
    "addr:street":"Soquel Dr Ste D",
    "iso:country":"US",
    "sg:address":"1661 Soquel Dr Ste D",
    "sg:city":"Santa Cruz",
    "sg:classifiers":[
        {
            "category":"Community Center",
            "type":"Public Place"
        }
    ],
    "sg:phone":"+1 831 460 6041",
    "sg:postcode":"95065",
    "sg:province":"CA",
    "sg:tags":[
        "medical"
    ],
    "sg:website":"www.pamf.org",
    "wof:name":"Soquel Drive Office - Palo Alto Medical Foundation",
    "wof:placetype":"venue"
},
  "geometry": {"coordinates":[-121.982095,36.989647],"type":"Point"}
}