{
  "type": "Feature",
  "properties": {
    "iso:country":"US",
    "sg:address":"1238 Woodrow Ave",
    "sg:city":"San Diego",
    "sg:classifiers":[
        {
            "category":"Farming",
            "subcategory":"Farm",
            "type":"Manufacturing & Wholesale Goods"
        }
    ],
    "sg:phone":"+1 619 466 2809",
    "sg:postcode":"92114",
    "sg:province":"CA",
    "sg:tags":[
        "crop",
        "general"
    ],
    "wof:name":"Docs Reptile Farms",
    "wof:placetype":"venue"
},
  "geometry": {"coordinates":[-117.03740500000001,32.718759],"type":"Point"}
}