{
  "type": "Feature",
  "properties": {
    "iso:country":"US",
    "sg:address":"592 W 9th St",
    "sg:city":"San Pedro",
    "sg:classifiers":[
        {
            "category":"Professional",
            "subcategory":"Management & Consulting",
            "type":"Services"
        }
    ],
    "sg:phone":"+1 310 833 5650",
    "sg:postcode":"90731",
    "sg:province":"CA",
    "sg:tags":[
        "food",
        "facility"
    ],
    "wof:name":"Plan Room",
    "wof:placetype":"venue"
},
  "geometry": {"coordinates":[-118.287915,33.736036],"type":"Point"}
}