{
  "type": "Feature",
  "properties": {
    "addr:full":"17505 Chatsworth St Granada Hills CA 91344",
    "addr:housenumber":"17505",
    "addr:postcode":"91344",
    "addr:street":"Chatsworth St",
    "iso:country":"US",
    "sg:address":"17505 Chatsworth St",
    "sg:city":"Granada Hills",
    "sg:classifiers":[
        {
            "category":"Home & Garden",
            "subcategory":"Carpets & Floor Coverings",
            "type":"Retail Goods"
        }
    ],
    "sg:phone":"+1 818 363 4030",
    "sg:postcode":"91344",
    "sg:province":"CA",
    "sg:tags":[
        "dealer",
        "rug"
    ],
    "wof:name":"Al & Bob's Carpets",
    "wof:placetype":"venue"
},
  "geometry": {"coordinates":[-118.517483,34.264943],"type":"Point"}
}