{
  "type": "Feature",
  "properties": {
    "iso:country":"US",
    "sg:address":"281 San Benancio Rd",
    "sg:city":"Salinas",
    "sg:classifiers":[
        {
            "category":"Building & Trades",
            "subcategory":"Construction",
            "type":"Services"
        }
    ],
    "sg:phone":"+1 831 484 2472",
    "sg:postcode":"93908",
    "sg:province":"CA",
    "sg:tags":[
        "home",
        "builder"
    ],
    "wof:name":"Marc Bordonaro Construction",
    "wof:placetype":"venue"
},
  "geometry": {"coordinates":[-121.687095,36.550605],"type":"Point"}
}