{
  "type": "Feature",
  "properties": {
    "iso:country":"US",
    "sg:address":"10622 Prospect Ave",
    "sg:city":"Santee",
    "sg:classifiers":[
        {
            "category":"Real Estate",
            "subcategory":"Real Estate Agent",
            "type":"Services"
        }
    ],
    "sg:phone":"+1 619 448 2097",
    "sg:postcode":"92071",
    "sg:province":"CA",
    "sg:tags":[
        "investment"
    ],
    "wof:name":"Bear Valley Land & Cattle Co",
    "wof:placetype":"venue"
},
  "geometry": {"coordinates":[-116.967182,32.831183],"type":"Point"}
}