{
  "type": "Feature",
  "properties": {
    "iso:country":"US",
    "sg:address":"850 S Via Lata",
    "sg:city":"Colton",
    "sg:classifiers":[
        {
            "category":"Wholesale",
            "subcategory":"Electrical",
            "type":"Manufacturing & Wholesale Goods"
        }
    ],
    "sg:phone":"+1 909 423 0425",
    "sg:postcode":"92324",
    "sg:province":"CA",
    "sg:tags":[
        "video",
        "disc",
        "tape"
    ],
    "wof:name":"Bilika Video Corp",
    "wof:placetype":"venue"
},
  "geometry": {"coordinates":[-117.306882,34.056181],"type":"Point"}
}