{
  "type": "Feature",
  "properties": {
    "iso:country":"US",
    "sg:address":"11300 Coloma Road",
    "sg:city":"Gold River",
    "sg:classifiers":[
        {
            "category":"Restaurant",
            "type":"Food & Drink"
        }
    ],
    "sg:phone":"+1 916 636 9400",
    "sg:postcode":"95670",
    "sg:province":"CA",
    "wof:name":"Wood'ys Admin Office",
    "wof:placetype":"venue"
},
  "geometry": {"coordinates":[-121.26210500000001,38.619924],"type":"Point"}
}