{
  "type": "Feature",
  "properties": {
    "addr:full":"1604 Haight St San Francisco CA 94117",
    "addr:housenumber":"1604",
    "addr:postcode":"94117",
    "addr:street":"Haight St",
    "iso:country":"US",
    "sg:address":"1604 Haight St",
    "sg:city":"San Francisco",
    "sg:classifiers":[
        {
            "category":"Shopping",
            "subcategory":"Clothing, Apparel, & Fashions",
            "type":"Retail Goods"
        }
    ],
    "sg:phone":"+1 415 864 4701",
    "sg:postcode":"94117",
    "sg:province":"CA",
    "wof:name":"Clobba",
    "wof:placetype":"venue"
},
  "geometry": {"coordinates":[-122.44958699999999,37.769747],"type":"Point"}
}