{
  "type": "Feature",
  "properties": {
    "iso:country":"US",
    "sg:address":"6672 Santa Susana Pass Rd",
    "sg:city":"Simi Valley",
    "sg:classifiers":[
        {
            "category":"Bars & Pubs",
            "type":"Food & Drink"
        }
    ],
    "sg:phone":"+1 805 955 0363",
    "sg:postcode":"93063",
    "sg:province":"CA",
    "wof:name":"Walli Hideout",
    "wof:placetype":"venue"
},
  "geometry": {"coordinates":[-118.65876799999999,34.259996],"type":"Point"}
}