{
  "type": "Feature",
  "properties": {
    "addr:full":"1145 Harbour Way S Richmond CA 94804",
    "addr:housenumber":"1145",
    "addr:postcode":"94804",
    "addr:street":"Harbour Way",
    "iso:country":"US",
    "sg:address":"1145 Harbour Way S",
    "sg:city":"Richmond",
    "sg:classifiers":[
        {
            "category":"Shopping",
            "subcategory":"Department Store",
            "type":"Retail Goods"
        }
    ],
    "sg:phone":"+1 800 858 6457",
    "sg:postcode":"94804",
    "sg:province":"CA",
    "sg:tags":[
        "oils-vegetable"
    ],
    "wof:name":"Premiere Foods",
    "wof:placetype":"venue"
},
  "geometry": {"coordinates":[-122.360107,37.916895],"type":"Point"}
}