{
  "type": "Feature",
  "properties": {
    "addr:full":"24 Orinda Way Orinda CA 94563",
    "addr:housenumber":"24",
    "addr:postcode":"94563",
    "addr:street":"Orinda Way",
    "iso:country":"US",
    "sg:address":"24 Orinda Way",
    "sg:city":"Orinda",
    "sg:classifiers":[
        {
            "category":"Organizations",
            "subcategory":"Membership Organization",
            "type":"Services"
        }
    ],
    "sg:phone":"+1 925 254 1353",
    "sg:postcode":"94563",
    "sg:province":"CA",
    "sg:tags":[
        "historical"
    ],
    "wof:name":"Orinda Historical Society Lib",
    "wof:placetype":"venue"
},
  "geometry": {"coordinates":[-122.187014,37.881682],"type":"Point"}
}