{
  "type": "Feature",
  "properties": {
    "iso:country":"US",
    "sg:address":"2759 Valencia Rd",
    "sg:city":"Aptos",
    "sg:classifiers":[
        {
            "category":"Professional",
            "subcategory":"Management & Consulting",
            "type":"Services"
        },
        {
            "category":"Professional",
            "subcategory":"Engineering",
            "type":"Services"
        }
    ],
    "sg:phone":"+1 831 688 2104",
    "sg:postcode":"95003",
    "sg:province":"CA",
    "sg:tags":[
        "environmental",
        "ecological",
        "engineer",
        "consultant"
    ],
    "wof:name":"Dana C Bland",
    "wof:placetype":"venue"
},
  "geometry": {"coordinates":[-121.865098,36.994754],"type":"Point"}
}