{
  "type": "Feature",
  "properties": {
    "addr:full":"10699 Hickson St El Monte CA 91731",
    "addr:housenumber":"10699",
    "addr:postcode":"91731",
    "addr:street":"Hickson St",
    "iso:country":"US",
    "sg:address":"10699 Hickson St",
    "sg:city":"El Monte",
    "sg:classifiers":[
        {
            "category":"Wholesale",
            "subcategory":"Hardware",
            "type":"Manufacturing & Wholesale Goods"
        }
    ],
    "sg:phone":"+1 626 582 8973",
    "sg:postcode":"91731",
    "sg:province":"CA",
    "sg:tags":[
        "distributor",
        "fastener",
        "threaded"
    ],
    "wof:name":"Rush Fasteners",
    "wof:placetype":"venue"
},
  "geometry": {"coordinates":[-118.041691,34.081261],"type":"Point"}
}