{
  "type": "Feature",
  "properties": {
    "iso:country":"US",
    "sg:address":"4363 N Madera Ave",
    "sg:city":"Kerman",
    "sg:classifiers":[
        {
            "category":"Real Estate",
            "subcategory":"Real Estate Operator",
            "type":"Services"
        }
    ],
    "sg:phone":"+1 559 846 9705",
    "sg:postcode":"93630",
    "sg:province":"CA",
    "sg:tags":[
        "property",
        "lessor"
    ],
    "wof:name":"Heeren Leila",
    "wof:placetype":"venue"
},
  "geometry": {"coordinates":[-120.060437,36.793823],"type":"Point"}
}