{
  "type": "Feature",
  "properties": {
    "iso:country":"US",
    "sg:address":"25332 Hillary Ln",
    "sg:city":"Laguna Hills",
    "sg:classifiers":[
        {
            "category":"Professional",
            "subcategory":"Computer Services",
            "type":"Services"
        }
    ],
    "sg:phone":"+1 949 462 0024",
    "sg:postcode":"92653",
    "sg:province":"CA",
    "sg:tags":[
        "repair"
    ],
    "wof:name":"Cyber Base Systems",
    "wof:placetype":"venue"
},
  "geometry": {"coordinates":[-117.695075,33.594859],"type":"Point"}
}