{
  "type": "Feature",
  "properties": {
    "iso:country":"US",
    "sg:address":"25333 Barton Rd",
    "sg:city":"Loma Linda",
    "sg:classifiers":[
        {
            "category":"Health Services",
            "subcategory":"Doctor",
            "type":"Services"
        }
    ],
    "sg:phone":"+1 909 558 2828",
    "sg:postcode":"92354",
    "sg:province":"CA",
    "sg:tags":[
        "physician",
        "surgeon"
    ],
    "wof:name":"Ravindra Rao MD",
    "wof:placetype":"venue"
},
  "geometry": {"coordinates":[-117.24860200000001,34.048302],"type":"Point"}
}