{
  "type": "Feature",
  "properties": {
    "addr:full":"14517 Ventura Blvd Sherman Oaks CA 91403",
    "addr:housenumber":"14517",
    "addr:postcode":"91403",
    "addr:street":"Ventura Blvd",
    "iso:country":"US",
    "sg:address":"14517 Ventura Blvd",
    "sg:city":"Sherman Oaks",
    "sg:classifiers":[
        {
            "category":"Shopping",
            "subcategory":"Mobile Phones",
            "type":"Retail Goods"
        },
        {
            "category":"Shopping",
            "subcategory":"Computers & Home Electronics",
            "type":"Retail Goods"
        }
    ],
    "sg:phone":"+1 818 784 1191",
    "sg:postcode":"91403",
    "sg:province":"CA",
    "sg:website":"www.wireless.att.com",
    "wof:name":"Pacific Bell Pcs Store",
    "wof:placetype":"venue"
},
  "geometry": {"coordinates":[-118.44899700000001,34.150902],"type":"Point"}
}