{
  "type": "Feature",
  "properties": {
    "iso:country":"US",
    "sg:address":"1352 4th Ave",
    "sg:city":"Napa",
    "sg:classifiers":[
        {
            "category":"Farming",
            "subcategory":"Vineyard",
            "type":"Manufacturing & Wholesale Goods"
        }
    ],
    "sg:phone":"+1 707 255 3692",
    "sg:postcode":"94559",
    "sg:province":"CA",
    "wof:name":"Black Cat Vineyard",
    "wof:placetype":"venue"
},
  "geometry": {"coordinates":[-122.248634,38.280828],"type":"Point"}
}