{
  "type": "Feature",
  "properties": {
    "addr:full":"27364 Echo Canyon Ct Corona CA 92883",
    "addr:housenumber":"27364",
    "addr:postcode":"92883",
    "addr:street":"Echo Canyon Ct",
    "iso:country":"US",
    "sg:address":"27364 Echo Canyon Ct",
    "sg:city":"Corona",
    "sg:classifiers":[
        {
            "category":"Professional",
            "subcategory":"Management & Consulting",
            "type":"Services"
        }
    ],
    "sg:phone":"+1 951 471 1847",
    "sg:postcode":"92883",
    "sg:province":"CA",
    "sg:tags":[
        "hardware",
        "supp",
        "computer",
        "paper"
    ],
    "wof:name":"AFA Enterprises",
    "wof:placetype":"venue"
},
  "geometry": {"coordinates":[-117.432811,33.722415],"type":"Point"}
}