{
  "type": "Feature",
  "properties": {
    "iso:country":"US",
    "sg:address":"1780 Oak St",
    "sg:city":"Torrance",
    "sg:classifiers":[
        {
            "category":"Real Estate",
            "subcategory":"Real Estate Agent",
            "type":"Services"
        }
    ],
    "sg:phone":"+1 310 216 4358",
    "sg:postcode":"90501",
    "sg:province":"CA",
    "sg:tags":[
        "appraiser"
    ],
    "wof:name":"Certified Appraisers Network",
    "wof:placetype":"venue"
},
  "geometry": {"coordinates":[-118.326703,33.831245],"type":"Point"}
}