{
  "type": "Feature",
  "properties": {
    "iso:country":"US",
    "sg:address":"7837 Stockton Blvd",
    "sg:city":"Sacramento",
    "sg:classifiers":[
        {
            "category":"Shopping",
            "subcategory":"Clothing, Apparel, & Fashions",
            "type":"Retail Goods"
        }
    ],
    "sg:phone":"+1 916 681 2100",
    "sg:postcode":"95823",
    "sg:province":"CA",
    "sg:tags":[
        "apparel",
        "women's"
    ],
    "wof:name":"Savitri Fashions",
    "wof:placetype":"venue"
},
  "geometry": {"coordinates":[-121.41836600000001,38.473024],"type":"Point"}
}