{
  "type": "Feature",
  "properties": {
    "iso:country":"US",
    "sg:address":"14756 Goldcone Dr",
    "sg:city":"Magalia",
    "sg:classifiers":[
        {
            "category":"Manufacturing",
            "subcategory":"Chemicals & Compounds",
            "type":"Manufacturing & Wholesale Goods"
        }
    ],
    "sg:phone":"+1 530 873 2259",
    "sg:postcode":"95954",
    "sg:province":"CA",
    "sg:tags":[
        "preparation",
        "pharmaceutical",
        "industry",
        "ma",
        "mfg"
    ],
    "wof:name":"Reekie Life Care Enterprises",
    "wof:placetype":"venue"
},
  "geometry": {"coordinates":[-121.58472,39.845305],"type":"Point"}
}