{
  "type": "Feature",
  "properties": {
    "iso:country":"US",
    "sg:address":"14201 Kentwood Blvd",
    "sg:city":"Victorville",
    "sg:classifiers":[
        {
            "category":"Social Services",
            "subcategory":"Job Training",
            "type":"Services"
        }
    ],
    "sg:phone":"+1 909 381 1089",
    "sg:postcode":"92392",
    "sg:province":"CA",
    "sg:tags":[
        "consultant",
        "c",
        "vocational",
        "business",
        "rehabilitation"
    ],
    "wof:name":"B P S Group Inc",
    "wof:placetype":"venue"
},
  "geometry": {"coordinates":[-117.327499,34.509955],"type":"Point"}
}