{
  "type": "Feature",
  "properties": {
    "addr:full":"5796 Corporate Ave Cypress CA 90630",
    "addr:housenumber":"5796",
    "addr:postcode":"90630",
    "addr:street":"Corporate Ave",
    "iso:country":"US",
    "sg:address":"5796 Corporate Ave",
    "sg:city":"Cypress",
    "sg:classifiers":[
        {
            "category":"Government",
            "subcategory":"Office",
            "type":"Public Place"
        }
    ],
    "sg:phone":"+1 714 484 5300",
    "sg:postcode":"90630",
    "sg:province":"CA",
    "wof:name":"Toxic Substances Control Dept",
    "wof:placetype":"venue"
},
  "geometry": {"coordinates":[-118.029826,33.807915],"type":"Point"}
}