{
  "type": "Feature",
  "properties": {
    "addr:full":"1290 Coast Village Rd Santa Barbara CA 93108",
    "addr:housenumber":"1290",
    "addr:postcode":"93108",
    "addr:street":"Coast Village Rd",
    "iso:country":"US",
    "sg:address":"1290 Coast Village Rd",
    "sg:city":"Santa Barbara",
    "sg:classifiers":[
        {
            "category":"Real Estate",
            "subcategory":"Real Estate Agent",
            "type":"Services"
        }
    ],
    "sg:phone":"+1 805 969 4755",
    "sg:postcode":"93108",
    "sg:province":"CA",
    "wof:name":"Coldwell Banker",
    "wof:placetype":"venue"
},
  "geometry": {"coordinates":[-119.64103299999999,34.421574],"type":"Point"}
}