{
  "type": "Feature",
  "properties": {
    "addr:full":"5927 Fallbrook Ave Woodland Hills CA 91367",
    "addr:housenumber":"5927",
    "addr:postcode":"91367",
    "addr:street":"Fallbrook Ave",
    "iso:country":"US",
    "sg:address":"5927 Fallbrook Ave",
    "sg:city":"Woodland Hills",
    "sg:classifiers":[
        {
            "category":"Real Estate",
            "subcategory":"Architect",
            "type":"Services"
        }
    ],
    "sg:phone":"+1 818 992 3344",
    "sg:postcode":"91367",
    "sg:province":"CA",
    "wof:name":"Le Duvand Architects-Engineers",
    "wof:placetype":"venue"
},
  "geometry": {"coordinates":[-118.62349500000001,34.177858],"type":"Point"}
}