{
  "type": "Feature",
  "properties": {
    "iso:country":"US",
    "sg:address":"46511 Mission Blvd",
    "sg:city":"Fremont",
    "sg:classifiers":[
        {
            "category":"Shopping",
            "type":"Retail Goods"
        }
    ],
    "sg:phone":"+1 510 353 0600",
    "sg:postcode":"94539",
    "sg:province":"CA",
    "sg:tags":[
        "telephone",
        "cellular"
    ],
    "wof:name":"Cellular Warehouse",
    "wof:placetype":"venue"
},
  "geometry": {"coordinates":[-121.925936,37.492993],"type":"Point"}
}