{
  "type": "Feature",
  "properties": {
    "iso:country":"US",
    "sg:address":"3672 San Pablo Dam Rd",
    "sg:city":"El Sobrante",
    "sg:classifiers":[
        {
            "category":"Personal",
            "subcategory":"Beauty Salon",
            "type":"Services"
        }
    ],
    "sg:phone":"+1 510 222 3014",
    "sg:postcode":"94803",
    "sg:province":"CA",
    "wof:name":"Afro Accent Hair Weaving",
    "wof:placetype":"venue"
},
  "geometry": {"coordinates":[-122.3191,37.963926],"type":"Point"}
}