{
  "type": "Feature",
  "properties": {
    "addr:full":"3672 San Pablo Dam Rd El Sobrante CA 94803",
    "addr:housenumber":"3672",
    "addr:postcode":"94803",
    "addr:street":"San Pablo Dam Rd",
    "iso:country":"US",
    "sg:address":"3672 San Pablo Dam Rd",
    "sg:city":"El Sobrante",
    "sg:classifiers":[
        {
            "category":"Personal",
            "subcategory":"Beauty Salon",
            "type":"Services"
        }
    ],
    "sg:phone":"+1 510 222 3014",
    "sg:postcode":"94803",
    "sg:province":"CA",
    "wof:name":"Afro Accent Hair Weaving",
    "wof:placetype":"venue"
},
  "geometry": {"coordinates":[-122.31910000000001,37.963926],"type":"Point"}
}