{
  "type": "Feature",
  "properties": {
    "iso:country":"US",
    "sg:address":"5146 3rd St",
    "sg:city":"San Francisco",
    "sg:classifiers":[
        {
            "category":"Building & Trades",
            "subcategory":"Plumbing",
            "type":"Services"
        }
    ],
    "sg:phone":"+1 415 822 5812",
    "sg:postcode":"94124",
    "sg:province":"CA",
    "sg:tags":[
        "mechanical",
        "contractor"
    ],
    "wof:name":"Scott-Norman Mechanical Inc",
    "wof:placetype":"venue"
},
  "geometry": {"coordinates":[-122.392088,37.731313],"type":"Point"}
}