{
  "type": "Feature",
  "properties": {
    "iso:country":"US",
    "sg:address":"827 7th St",
    "sg:city":"Sacramento",
    "sg:classifiers":[
        {
            "category":"Government",
            "subcategory":"Office",
            "type":"Public Place"
        }
    ],
    "sg:phone":"+1 916 874 6546",
    "sg:postcode":"95814",
    "sg:province":"CA",
    "wof:name":"Sacramento County Surveyor",
    "wof:placetype":"venue"
},
  "geometry": {"coordinates":[-121.496814,38.582732],"type":"Point"}
}