{
  "type": "Feature",
  "properties": {
    "addr:full":"1814 Judah St San Francisco CA 94122",
    "addr:housenumber":"1814",
    "addr:postcode":"94122",
    "addr:street":"Judah St",
    "iso:country":"US",
    "sg:address":"1814 Judah St",
    "sg:city":"San Francisco",
    "sg:classifiers":[
        {
            "category":"Building & Trades",
            "subcategory":"Landscaping Services",
            "type":"Services"
        }
    ],
    "sg:phone":"+1 415 504 8345",
    "sg:postcode":"94122",
    "sg:province":"CA",
    "sg:tags":[
        "landscape"
    ],
    "wof:name":"Sol Landscaping Service",
    "wof:placetype":"venue"
},
  "geometry": {"coordinates":[-122.48223400000001,37.761546],"type":"Point"}
}