{
  "type": "Feature",
  "properties": {
    "addr:full":"1210 E Houston Ave Visalia CA 93292",
    "addr:housenumber":"1210",
    "addr:postcode":"93292",
    "addr:street":"E Houston Ave",
    "iso:country":"US",
    "sg:address":"1210 E Houston Ave",
    "sg:city":"Visalia",
    "sg:classifiers":[
        {
            "category":"Shopping",
            "subcategory":"Tobacco",
            "type":"Retail Goods"
        }
    ],
    "sg:phone":"+1 559 624 0661",
    "sg:postcode":"93292",
    "sg:province":"CA",
    "sg:tags":[
        "cigarette",
        "cigar",
        "dealer"
    ],
    "wof:name":"Discount Cigarettes",
    "wof:placetype":"venue"
},
  "geometry": {"coordinates":[-119.27980700000001,36.341917],"type":"Point"}
}