{
  "type": "Feature",
  "properties": {
    "iso:country":"US",
    "sg:address":"6624 Stanford Ave",
    "sg:city":"Los Angeles",
    "sg:classifiers":[
        {
            "category":"Wholesale",
            "subcategory":"Painting Supplies",
            "type":"Manufacturing & Wholesale Goods"
        }
    ],
    "sg:phone":"+1 323 758 1147",
    "sg:postcode":"90001",
    "sg:province":"CA",
    "sg:tags":[
        "paint"
    ],
    "sg:website":"www.pervo.com",
    "wof:name":"Pervo Paint Co",
    "wof:placetype":"venue"
},
  "geometry": {"coordinates":[-118.262894,33.975002],"type":"Point"}
}