{
  "type": "Feature",
  "properties": {
    "addr:full":"231 Race St Grass Valley CA 95945",
    "addr:housenumber":"231",
    "addr:postcode":"95945",
    "addr:street":"Race St",
    "iso:country":"US",
    "sg:address":"231 Race St",
    "sg:city":"Grass Valley",
    "sg:classifiers":[
        {
            "category":"Real Estate",
            "subcategory":"Real Estate Agent",
            "type":"Services"
        }
    ],
    "sg:phone":"+1 925 634 3058",
    "sg:postcode":"95945",
    "sg:province":"CA",
    "wof:name":"Platinum Enterprise",
    "wof:placetype":"venue"
},
  "geometry": {"coordinates":[-121.05663300000001,39.213399],"type":"Point"}
}