{
  "type": "Feature",
  "properties": {
    "addr:full":"13400 Kitching St Moreno Valley CA 92553",
    "addr:housenumber":"13400",
    "addr:postcode":"92553",
    "addr:street":"Kitching St",
    "iso:country":"US",
    "sg:address":"13400 Kitching St",
    "sg:city":"Moreno Valley",
    "sg:classifiers":[
        {
            "category":"Sports & Exercise",
            "subcategory":"Gym",
            "type":"Entertainment"
        }
    ],
    "sg:phone":"+1 951 247 9236",
    "sg:postcode":"92553",
    "sg:province":"CA",
    "sg:tags":[
        "club",
        "health",
        "studio",
        "gymnasium"
    ],
    "wof:name":"YMCA",
    "wof:placetype":"venue"
},
  "geometry": {"coordinates":[-117.21756000000001,33.926769],"type":"Point"}
}