{
  "type": "Feature",
  "properties": {
    "iso:country":"US",
    "sg:address":"1712 Ocean Avenue",
    "sg:city":"San Francisco",
    "sg:classifiers":[
        {
            "category":"Personal",
            "subcategory":"Beauty Salon",
            "type":"Services"
        },
        {
            "category":"Personal",
            "subcategory":"Barber",
            "type":"Services"
        }
    ],
    "sg:phone":"+1 415 239 5156",
    "sg:postcode":"94112",
    "sg:province":"CA",
    "sg:tags":[
        "hair"
    ],
    "wof:name":"Mahogany House of Styles",
    "wof:placetype":"venue"
},
  "geometry": {"coordinates":[-122.459999,37.724899],"type":"Point"}
}