{
  "type": "Feature",
  "properties": {
    "iso:country":"US",
    "sg:address":"561 Broadway",
    "sg:city":"Sonoma",
    "sg:classifiers":[
        {
            "category":"Professional",
            "type":"Services"
        }
    ],
    "sg:phone":"+1 707 996 6864",
    "sg:postcode":"95476",
    "sg:province":"CA",
    "sg:tags":[
        "establishment"
    ],
    "wof:name":"Magnolia Capital Inc",
    "wof:placetype":"venue"
},
  "geometry": {"coordinates":[-122.45808100000001,38.290863],"type":"Point"}
}