{
  "type": "Feature",
  "properties": {
    "addr:full":"591 W 10th St Pittsburg CA 94565",
    "addr:housenumber":"591",
    "addr:postcode":"94565",
    "addr:street":"W 10Th St",
    "iso:country":"US",
    "sg:address":"591 W 10th St",
    "sg:city":"Pittsburg",
    "sg:classifiers":[
        {
            "category":"Building & Trades",
            "subcategory":"Landscaping Services",
            "type":"Services"
        }
    ],
    "sg:phone":"+1 925 432 2090",
    "sg:postcode":"94565",
    "sg:province":"CA",
    "sg:tags":[
        "landscape",
        "contractor"
    ],
    "wof:name":"Green Earth Development Inc",
    "wof:placetype":"venue"
},
  "geometry": {"coordinates":[-121.895855,38.029368],"type":"Point"}
}