{
  "type": "Feature",
  "properties": {
    "addr:full":"2610 Durfee Ave El Monte CA 91732",
    "addr:postcode":"2610;91732",
    "addr:street":"Durfee Ave",
    "iso:country":"US",
    "sg:address":"2610 Durfee Ave",
    "sg:city":"El Monte",
    "sg:classifiers":[
        {
            "category":"Food & Beverages",
            "subcategory":"Bakery",
            "type":"Retail Goods"
        }
    ],
    "sg:phone":"+1 626 452 1268",
    "sg:postcode":"91732",
    "sg:province":"CA",
    "sg:tags":[
        "doughnut"
    ],
    "wof:name":"Crispy Donuts",
    "wof:placetype":"venue"
},
  "geometry": {"coordinates":[-118.01905499999999,34.054443],"type":"Point"}
}