{
  "type": "Feature",
  "properties": {
    "iso:country":"US",
    "sg:address":"1729 Springs Rd",
    "sg:city":"Vallejo",
    "sg:classifiers":[
        {
            "category":"Personal",
            "subcategory":"Beauty Salon",
            "type":"Services"
        }
    ],
    "sg:phone":"+1 707 645 0864",
    "sg:postcode":"94591",
    "sg:province":"CA",
    "wof:name":"Any Hair",
    "wof:placetype":"venue"
},
  "geometry": {"coordinates":[-122.223022,38.105991],"type":"Point"}
}