{
  "type": "Feature",
  "properties": {
    "iso:country":"US",
    "sg:address":"12270 Oak Knoll Rd",
    "sg:city":"Poway",
    "sg:classifiers":[
        {
            "category":"Building & Trades",
            "subcategory":"Equipment Rental",
            "type":"Services"
        }
    ],
    "sg:phone":"+1 858 748 4848",
    "sg:postcode":"92064",
    "sg:province":"CA",
    "sg:tags":[
        "yard"
    ],
    "wof:name":"One Stop Rental & Supply Ctr",
    "wof:placetype":"venue"
},
  "geometry": {"coordinates":[-117.064256,32.94999],"type":"Point"}
}