{
  "type": "Feature",
  "properties": {
    "iso:country":"US",
    "sg:address":"15 Alice St",
    "sg:city":"Arcadia",
    "sg:classifiers":[
        {
            "category":"Health Services",
            "subcategory":"Dentist",
            "type":"Services"
        }
    ],
    "sg:phone":"+1 626 285 1199",
    "sg:postcode":"91006",
    "sg:province":"CA",
    "wof:name":"Yu David DDS",
    "wof:placetype":"venue"
},
  "geometry": {"coordinates":[-118.076878,34.131491],"type":"Point"}
}