{
  "type": "Feature",
  "properties": {
    "iso:country":"US",
    "sg:address":"13915 Paramount Blvd",
    "sg:city":"Paramount",
    "sg:classifiers":[
        {
            "category":"Shopping",
            "subcategory":"Computers & Home Electronics",
            "type":"Retail Goods"
        }
    ],
    "sg:phone":"+1 562 633 7135",
    "sg:postcode":"90723",
    "sg:province":"CA",
    "wof:name":"Paramount Electronics Inc",
    "wof:placetype":"venue"
},
  "geometry": {"coordinates":[-118.160004,33.908199],"type":"Point"}
}