{
  "type": "Feature",
  "properties": {
    "iso:country":"US",
    "sg:address":"800 W El Camino Real Suite 180",
    "sg:city":"Mountain View",
    "sg:classifiers":[
        {
            "category":"Building & Trades",
            "subcategory":"Cleaning & Sanitation",
            "type":"Services"
        }
    ],
    "sg:phone":"+1 408 988 8071",
    "sg:postcode":"94040",
    "sg:province":"CA",
    "sg:tags":[
        "home"
    ],
    "sg:website":"www.ableserv.com",
    "wof:name":"Able Building Maintenance Company.",
    "wof:placetype":"venue"
},
  "geometry": {"coordinates":[-122.083519,37.38421],"type":"Point"}
}