{
  "type": "Feature",
  "properties": {
    "addr:full":"2350 E Curry St Long Beach CA 90805",
    "addr:housenumber":"2350",
    "addr:postcode":"90805",
    "addr:street":"E Curry St",
    "iso:country":"US",
    "sg:address":"2350 E Curry St",
    "sg:city":"Long Beach",
    "sg:classifiers":[
        {
            "category":"Home & Garden",
            "subcategory":"Furniture",
            "type":"Retail Goods"
        }
    ],
    "sg:phone":"+1 562 428 8680",
    "sg:postcode":"90805",
    "sg:province":"CA",
    "sg:tags":[
        "builder",
        "custom"
    ],
    "wof:name":"Chacon Furniture",
    "wof:placetype":"venue"
},
  "geometry": {"coordinates":[-118.167494,33.866413],"type":"Point"}
}