{
  "type": "Feature",
  "properties": {
    "iso:country":"US",
    "sg:address":"7607 International Blvd",
    "sg:city":"Oakland",
    "sg:classifiers":[
        {
            "category":"Professional",
            "type":"Services"
        }
    ],
    "sg:phone":"+1 510 567 9782",
    "sg:postcode":"94621",
    "sg:province":"CA",
    "sg:tags":[
        "apartment"
    ],
    "wof:name":"Allen Temple Manor",
    "wof:placetype":"venue"
},
  "geometry": {"coordinates":[-122.18476200000001,37.758089],"type":"Point"}
}