{
  "type": "Feature",
  "properties": {
    "iso:country":"US",
    "sg:address":"12001 Hawthorne Way",
    "sg:city":"Hawthorne",
    "sg:classifiers":[
        {
            "category":"Autos & Motor Vehicles",
            "subcategory":"Automobile Sales",
            "type":"Retail Goods"
        }
    ],
    "sg:phone":"+1 310 679 4411",
    "sg:postcode":"90250",
    "sg:province":"CA",
    "sg:tags":[
        "limo"
    ],
    "wof:name":"Mayorlax Airport and Transportation Services",
    "wof:placetype":"venue"
},
  "geometry": {"coordinates":[-118.353565,33.923646],"type":"Point"}
}