{
  "type": "Feature",
  "properties": {
    "addr:full":"1807 E Olympic Blvd Los Angeles CA 90021",
    "addr:housenumber":"1807",
    "addr:postcode":"90021",
    "addr:street":"E Olympic Blvd",
    "iso:country":"US",
    "sg:address":"1807 E Olympic Blvd",
    "sg:city":"Los Angeles",
    "sg:classifiers":[
        {
            "category":"Shopping",
            "subcategory":"Clothing, Apparel, & Fashions",
            "type":"Retail Goods"
        }
    ],
    "sg:phone":"+1 213 624 6033",
    "sg:postcode":"90021",
    "sg:province":"CA",
    "wof:name":"Sesil Fashion",
    "wof:placetype":"venue"
},
  "geometry": {"coordinates":[-118.23800799999999,34.027391],"type":"Point"}
}