{
  "type": "Feature",
  "properties": {
    "iso:country":"US",
    "sg:address":"365 10th St",
    "sg:city":"San Francisco",
    "sg:classifiers":[
        {
            "category":"Shopping",
            "subcategory":"Beauty & Cosmetics",
            "type":"Retail Goods"
        }
    ],
    "sg:phone":"+1 415 255 4693",
    "sg:postcode":"94103",
    "sg:province":"CA",
    "sg:tags":[
        "supply"
    ],
    "sg:website":"www.sfmassagesupply.com",
    "wof:name":"San Francisco Massage Supply Co",
    "wof:placetype":"venue"
},
  "geometry": {"coordinates":[-122.411664,37.771936],"type":"Point"}
}