{
  "type": "Feature",
  "properties": {
    "addr:full":"631 Silver Lake Blvd Los Angeles CA 90026",
    "addr:housenumber":"631",
    "addr:postcode":"90026",
    "addr:street":"Silver Lake Blvd",
    "iso:country":"US",
    "sg:address":"631 Silver Lake Blvd",
    "sg:city":"Los Angeles",
    "sg:classifiers":[
        {
            "category":"Food & Beverages",
            "subcategory":"Liquor & Beverages",
            "type":"Retail Goods"
        }
    ],
    "sg:phone":"+1 323 660 1022",
    "sg:postcode":"90026",
    "sg:province":"CA",
    "sg:tags":[
        "beer",
        "spirit",
        "wine"
    ],
    "wof:name":"Mikron Liquor",
    "wof:placetype":"venue"
},
  "geometry": {"coordinates":[-118.278999,34.0788],"type":"Point"}
}