{
  "type": "Feature",
  "properties": {
    "addr:full":"26459 Ynez Rd Temecula CA 92591",
    "addr:housenumber":"26459",
    "addr:postcode":"92591",
    "addr:street":"Ynez Rd",
    "iso:country":"US",
    "sg:address":"26459 Ynez Rd",
    "sg:city":"Temecula",
    "sg:classifiers":[
        {
            "category":"Shopping",
            "subcategory":"Clothing, Apparel, & Fashions",
            "type":"Retail Goods"
        }
    ],
    "sg:phone":"+1 951 296 2100",
    "sg:postcode":"92591",
    "sg:province":"CA",
    "sg:tags":[
        "shop",
        "bridal"
    ],
    "wof:name":"Bridal Etc",
    "wof:placetype":"venue"
},
  "geometry": {"coordinates":[-117.157566,33.522093],"type":"Point"}
}