{
  "type": "Feature",
  "properties": {
    "iso:country":"US",
    "sg:address":"1350 Bennett Valley Rd",
    "sg:city":"Santa Rosa",
    "sg:classifiers":[
        {
            "category":"Government",
            "subcategory":"Office",
            "type":"Public Place"
        }
    ],
    "sg:phone":"+1 707 545 4200",
    "sg:postcode":"95404",
    "sg:province":"CA",
    "wof:name":"Sonoma County Fairgrounds",
    "wof:placetype":"venue"
},
  "geometry": {"coordinates":[-122.704014,38.432369],"type":"Point"}
}