{
  "type": "Feature",
  "properties": {
    "iso:country":"US",
    "sg:address":"Cedar & Curtis",
    "sg:city":"Berkeley",
    "sg:classifiers":[
        {
            "category":"Retail",
            "subcategory":"Pet Boarding",
            "type":"Services"
        }
    ],
    "sg:phone":"+1 510 527 1866",
    "sg:postcode":"94702",
    "sg:province":"CA",
    "sg:tags":[
        "boarding/pet",
        "sitting"
    ],
    "wof:name":"Well Loved Dogs",
    "wof:placetype":"venue"
},
  "geometry": {"coordinates":[-122.290612,37.875675],"type":"Point"}
}