{
  "type": "Feature",
  "properties": {
    "addr:full":"10014 Campo Rd Spring Valley CA 91977",
    "addr:housenumber":"10014",
    "addr:postcode":"91977",
    "addr:street":"Campo Rd",
    "iso:country":"US",
    "sg:address":"10014 Campo Rd",
    "sg:city":"Spring Valley",
    "sg:classifiers":[
        {
            "category":"Personal",
            "subcategory":"Barber",
            "type":"Services"
        }
    ],
    "sg:phone":"+1 619 670 5770",
    "sg:postcode":"91977",
    "sg:province":"CA",
    "wof:name":"Thompson Bill",
    "wof:placetype":"venue"
},
  "geometry": {"coordinates":[-116.97989200000001,32.748051],"type":"Point"}
}