{
  "type": "Feature",
  "properties": {
    "iso:country":"US",
    "sg:address":"7711 Woodwind Dr",
    "sg:city":"Huntington Beach",
    "sg:classifiers":[
        {
            "category":"Professional",
            "type":"Services"
        }
    ],
    "sg:phone":"+1 714 375 5850",
    "sg:postcode":"92647",
    "sg:province":"CA",
    "wof:name":"Valentino Collecione",
    "wof:placetype":"venue"
},
  "geometry": {"coordinates":[-117.994551,33.704302],"type":"Point"}
}