{
  "type": "Feature",
  "properties": {
    "iso:country":"US",
    "sg:address":"14616 S Bahama Ave",
    "sg:city":"Compton",
    "sg:classifiers":[
        {
            "category":"Professional",
            "subcategory":"Business Services",
            "type":"Services"
        }
    ],
    "sg:phone":"+1 310 639 9140",
    "sg:postcode":"90220",
    "sg:province":"CA",
    "wof:name":"DGO Construction Co",
    "wof:placetype":"venue"
},
  "geometry": {"coordinates":[-118.253575,33.90078],"type":"Point"}
}