{
  "type": "Feature",
  "properties": {
    "iso:country":"US",
    "sg:address":"50 Alessandro Pl",
    "sg:city":"Pasadena",
    "sg:classifiers":[
        {
            "category":"Health Services",
            "subcategory":"Doctor",
            "type":"Services"
        }
    ],
    "sg:phone":"+1 626 793 7114",
    "sg:postcode":"91105",
    "sg:province":"CA",
    "wof:name":"Rosenberg Peter M MD Gastroenterologist",
    "wof:placetype":"venue"
},
  "geometry": {"coordinates":[-118.152016,34.130479],"type":"Point"}
}