{
  "type": "Feature",
  "properties": {
    "addr:full":"995 Vintage Ave St Helena CA 94574",
    "addr:housenumber":"995",
    "addr:postcode":"94574",
    "addr:street":"Vintage Ave",
    "iso:country":"US",
    "sg:address":"995 Vintage Ave",
    "sg:city":"St Helena",
    "sg:classifiers":[
        {
            "category":"Professional",
            "subcategory":"Computer Services",
            "type":"Services"
        }
    ],
    "sg:phone":"+1 707 967 9290",
    "sg:postcode":"94574",
    "sg:province":"CA",
    "sg:tags":[
        "consultant",
        "designer"
    ],
    "sg:website":"www.syberlink.net",
    "wof:name":"Sieberlich Systems",
    "wof:placetype":"venue"
},
  "geometry": {"coordinates":[-122.457486,38.495894],"type":"Point"}
}