{
  "type": "Feature",
  "properties": {
    "iso:country":"US",
    "sg:address":"119 Broadway",
    "sg:city":"San Diego",
    "sg:classifiers":[
        {
            "category":"Restaurant",
            "type":"Food & Drink"
        }
    ],
    "sg:menulink":"http://www.allmenus.com/ca/san-diego/123279-quiznos-sub/menu/",
    "sg:phone":"+1 619 231 9430",
    "sg:postcode":"92101",
    "sg:province":"CA",
    "sg:tags":[
        "wrap",
        "american",
        "sandwich"
    ],
    "wof:name":"Quiznos Sub",
    "wof:placetype":"venue"
},
  "geometry": {"coordinates":[-117.163399,32.715652],"type":"Point"}
}