{
  "type": "Feature",
  "properties": {
    "iso:country":"US",
    "sg:address":"1204 Vicente St",
    "sg:city":"San Francisco",
    "sg:classifiers":[
        {
            "category":"Health Services",
            "subcategory":"Doctor",
            "type":"Services"
        }
    ],
    "sg:phone":"+1 415 731 5582",
    "sg:postcode":"94116",
    "sg:province":"CA",
    "sg:tags":[
        "psychiatrist"
    ],
    "wof:name":"Frank Van Orden, MD",
    "wof:placetype":"venue"
},
  "geometry": {"coordinates":[-122.47980800000001,37.739147],"type":"Point"}
}