{
  "type": "Feature",
  "properties": {
    "addr:full":"2111 E Howell Ave Anaheim CA 92806",
    "addr:housenumber":"2111",
    "addr:postcode":"92806",
    "addr:street":"E Howell Ave",
    "iso:country":"US",
    "sg:address":"2111 E Howell Ave",
    "sg:city":"Anaheim",
    "sg:classifiers":[
        {
            "category":"Wholesale",
            "subcategory":"Construction Materials",
            "type":"Manufacturing & Wholesale Goods"
        }
    ],
    "sg:phone":"+1 714 937 1930",
    "sg:postcode":"92806",
    "sg:province":"CA",
    "wof:name":"Sit Marble",
    "wof:placetype":"venue"
},
  "geometry": {"coordinates":[-117.888428,33.80705],"type":"Point"}
}