{
  "type": "Feature",
  "properties": {
    "iso:country":"US",
    "sg:address":"13302 San Antonio Dr",
    "sg:city":"Norwalk",
    "sg:classifiers":[
        {
            "category":"Personal",
            "subcategory":"Beauty Salon",
            "type":"Services"
        }
    ],
    "sg:phone":"+1 562 864 3669",
    "sg:postcode":"90650",
    "sg:province":"CA",
    "wof:name":"Princess Beauty Salon",
    "wof:placetype":"venue"
},
  "geometry": {"coordinates":[-118.075485,33.909414],"type":"Point"}
}