{
  "type": "Feature",
  "properties": {
    "iso:country":"US",
    "sg:address":"601 N Palm St",
    "sg:city":"La Habra",
    "sg:classifiers":[
        {
            "category":"Building & Trades",
            "subcategory":"Landscaping Services",
            "type":"Services"
        }
    ],
    "sg:phone":"+1 562 690 6424",
    "sg:postcode":"90631",
    "sg:province":"CA",
    "sg:tags":[
        "landscape",
        "contractor"
    ],
    "wof:name":"North Hills Landscaping",
    "wof:placetype":"venue"
},
  "geometry": {"coordinates":[-117.924412,33.937277],"type":"Point"}
}