{
  "type": "Feature",
  "properties": {
    "addr:full":"201 John St Salinas CA 93901",
    "addr:housenumber":"201",
    "addr:postcode":"93901",
    "addr:street":"John St",
    "iso:country":"US",
    "sg:address":"201 John St",
    "sg:city":"Salinas",
    "sg:classifiers":[
        {
            "category":"Professional",
            "subcategory":"Accounting & Tax Preparation",
            "type":"Services"
        }
    ],
    "sg:phone":"+1 831 424 0841",
    "sg:postcode":"93901",
    "sg:province":"CA",
    "sg:tags":[
        "accountant"
    ],
    "wof:name":"Timmins & Sorensen",
    "wof:placetype":"venue"
},
  "geometry": {"coordinates":[-121.648443,36.669639],"type":"Point"}
}