{
  "type": "Feature",
  "properties": {
    "addr:full":"6331 Florence Pl Bell Gardens CA 90201",
    "addr:housenumber":"6331",
    "addr:postcode":"90201",
    "addr:street":"Florence Pl",
    "iso:country":"US",
    "sg:address":"6331 Florence Pl",
    "sg:city":"Bell Gardens",
    "sg:classifiers":[
        {
            "category":"Retail",
            "subcategory":"Auto Repair",
            "type":"Services"
        }
    ],
    "sg:phone":"+1 562 287 2552",
    "sg:postcode":"90201",
    "sg:province":"CA",
    "wof:name":"1 Complete Auto Repair",
    "wof:placetype":"venue"
},
  "geometry": {"coordinates":[-118.152028,33.966834],"type":"Point"}
}