{
  "type": "Feature",
  "properties": {
    "iso:country":"US",
    "sg:address":"2704 E Thompson Blvd",
    "sg:city":"Ventura",
    "sg:classifiers":[
        {
            "category":"Banks & Credit Unions",
            "subcategory":"Bank",
            "type":"Services"
        }
    ],
    "sg:phone":"+1 805 653 0431",
    "sg:postcode":"93003",
    "sg:province":"CA",
    "sg:tags":[
        "loan",
        "real estate"
    ],
    "wof:name":"World Savings Home Loans",
    "wof:placetype":"venue"
},
  "geometry": {"coordinates":[-119.258615,34.271972],"type":"Point"}
}