{
  "type": "Feature",
  "properties": {
    "addr:full":"1704 W Highland Ave San Bernardino CA 92411",
    "addr:housenumber":"1704",
    "addr:postcode":"92411",
    "addr:street":"W Highland Ave",
    "iso:country":"US",
    "sg:address":"1704 W Highland Ave",
    "sg:city":"San Bernardino",
    "sg:classifiers":[
        {
            "category":"Shopping",
            "subcategory":"Gifts & Souvenirs",
            "type":"Retail Goods"
        }
    ],
    "sg:phone":"+1 909 473 9590",
    "sg:postcode":"92411",
    "sg:province":"CA",
    "wof:name":"Amys Party Supply",
    "wof:placetype":"venue"
},
  "geometry": {"coordinates":[-117.324652,34.13622],"type":"Point"}
}