{
  "type": "Feature",
  "properties": {
    "addr:full":"103 H St Petaluma CA 94952",
    "addr:housenumber":"103",
    "addr:postcode":"94952",
    "addr:street":"H St",
    "iso:country":"US",
    "sg:address":"103 H St",
    "sg:city":"Petaluma",
    "sg:classifiers":[
        {
            "category":"Professional",
            "subcategory":"Management & Consulting",
            "type":"Services"
        }
    ],
    "sg:phone":"+1 707 766 6391",
    "sg:postcode":"94952",
    "sg:province":"CA",
    "sg:tags":[
        "marketing",
        "consultant"
    ],
    "wof:name":"Mall Services Group",
    "wof:placetype":"venue"
},
  "geometry": {"coordinates":[-122.63141,38.231206],"type":"Point"}
}