{
  "type": "Feature",
  "properties": {
    "addr:full":"13146 Firestone Blvd Norwalk CA 90650",
    "addr:housenumber":"13146",
    "addr:postcode":"90650",
    "addr:street":"Firestone Blvd",
    "iso:country":"US",
    "sg:address":"13146 Firestone Blvd",
    "sg:city":"Norwalk",
    "sg:classifiers":[
        {
            "category":"Manufacturing",
            "subcategory":"Furniture",
            "type":"Manufacturing & Wholesale Goods"
        }
    ],
    "sg:phone":"+1 323 773 3451",
    "sg:postcode":"90650",
    "sg:province":"CA",
    "sg:tags":[
        "equipment"
    ],
    "wof:name":"McDowell-Craig Office Furniture",
    "wof:placetype":"venue"
},
  "geometry": {"coordinates":[-118.052415,33.897066],"type":"Point"}
}