{
  "type": "Feature",
  "properties": {
    "iso:country":"US",
    "sg:address":"880 Hazel St",
    "sg:city":"Gridley",
    "sg:classifiers":[
        {
            "category":"Real Estate",
            "subcategory":"Real Estate Operator",
            "type":"Services"
        }
    ],
    "sg:phone":"+1 530 846 7800",
    "sg:postcode":"95948",
    "sg:province":"CA",
    "sg:tags":[
        "building",
        "apartment"
    ],
    "wof:name":"Hazel Hotel Seniors Apartments",
    "wof:placetype":"venue"
},
  "geometry": {"coordinates":[-121.696673,39.364747],"type":"Point"}
}