{
  "type": "Feature",
  "properties": {
    "iso:country":"US",
    "sg:address":"17747 State Rte 120",
    "sg:city":"Ripon",
    "sg:classifiers":[
        {
            "category":"Farming",
            "subcategory":"Farm",
            "type":"Manufacturing & Wholesale Goods"
        }
    ],
    "sg:phone":"+1 209 982 4184",
    "sg:postcode":"95366",
    "sg:province":"CA",
    "wof:name":"C R Fisher Farm",
    "wof:placetype":"venue"
},
  "geometry": {"coordinates":[-121.088993,37.798204],"type":"Point"}
}