{
  "type": "Feature",
  "properties": {
    "addr:full":"27042 Calle Del Cid Mission Viejo CA 92691",
    "addr:housenumber":"27042",
    "addr:postcode":"92691",
    "addr:street":"Calle Del Cid",
    "iso:country":"US",
    "sg:address":"27042 Calle Del Cid",
    "sg:city":"Mission Viejo",
    "sg:classifiers":[
        {
            "category":"Home & Garden",
            "subcategory":"Carpets & Floor Coverings",
            "type":"Retail Goods"
        }
    ],
    "sg:phone":"+1 949 582 8866",
    "sg:postcode":"92691",
    "sg:province":"CA",
    "sg:tags":[
        "flooring"
    ],
    "wof:name":"Shelter Flooring & Construction",
    "wof:placetype":"venue"
},
  "geometry": {"coordinates":[-117.661069,33.569753],"type":"Point"}
}