{
  "type": "Feature",
  "properties": {
    "iso:country":"US",
    "sg:address":"830 S Hill St",
    "sg:city":"Los Angeles",
    "sg:classifiers":[
        {
            "category":"Shopping",
            "subcategory":"Clothing, Apparel, & Fashions",
            "type":"Retail Goods"
        }
    ],
    "sg:phone":"+1 213 622 3318",
    "sg:postcode":"90014",
    "sg:province":"CA",
    "sg:tags":[
        "garment"
    ],
    "wof:name":"SKC Apparel Inc",
    "wof:placetype":"venue"
},
  "geometry": {"coordinates":[-118.256726,34.04342],"type":"Point"}
}