{
  "type": "Feature",
  "properties": {
    "iso:country":"US",
    "sg:address":"6750 Central Ave",
    "sg:city":"Riverside",
    "sg:classifiers":[
        {
            "category":"Manufacturing",
            "subcategory":"Rubber & Plastics",
            "type":"Manufacturing & Wholesale Goods"
        }
    ],
    "sg:phone":"+1 951 688 5993",
    "sg:postcode":"92504",
    "sg:province":"CA",
    "wof:name":"Kel-Jac Engineering",
    "wof:placetype":"venue"
},
  "geometry": {"coordinates":[-117.44870299999999,33.956266],"type":"Point"}
}