{
  "type": "Feature",
  "properties": {
    "addr:full":"18101 Von Karman Ave Irvine CA 92612",
    "addr:housenumber":"18101",
    "addr:postcode":"92612",
    "addr:street":"Von Karman Ave",
    "iso:country":"US",
    "sg:address":"18101 Von Karman Ave",
    "sg:city":"Irvine",
    "sg:classifiers":[
        {
            "category":"Utilities",
            "subcategory":"Electric",
            "type":"Services"
        }
    ],
    "sg:phone":"+1 949 752 5588",
    "sg:postcode":"92612",
    "sg:province":"CA",
    "sg:tags":[
        "generation",
        "power"
    ],
    "wof:name":"Arrowhead Energy Company",
    "wof:placetype":"venue"
},
  "geometry": {"coordinates":[-117.853397,33.676465],"type":"Point"}
}