{
  "type": "Feature",
  "properties": {
    "addr:full":"18791 Park Tree Ln Sonoma CA 95476",
    "addr:housenumber":"18791",
    "addr:postcode":"95476",
    "addr:street":"Park Tree Ln",
    "iso:country":"US",
    "sg:address":"18791 Park Tree Ln",
    "sg:city":"Sonoma",
    "sg:classifiers":[
        {
            "category":"Professional",
            "subcategory":"Management & Consulting",
            "type":"Services"
        }
    ],
    "sg:phone":"+1 707 938 2828",
    "sg:postcode":"95476",
    "sg:province":"CA",
    "sg:tags":[
        "consultant",
        "telephone"
    ],
    "wof:name":"Tech Pro Solutions",
    "wof:placetype":"venue"
},
  "geometry": {"coordinates":[-122.48835800000001,38.302064],"type":"Point"}
}