{
  "type": "Feature",
  "properties": {
    "addr:full":"5031 La Palma Ave La Palma CA 90623",
    "addr:housenumber":"5031",
    "addr:postcode":"90623",
    "addr:street":"La Palma Ave",
    "iso:country":"US",
    "sg:address":"5031 La Palma Ave",
    "sg:city":"La Palma",
    "sg:classifiers":[
        {
            "category":"Arena",
            "subcategory":"Sports Club",
            "type":"Entertainment"
        }
    ],
    "sg:phone":"+1 714 615 5163",
    "sg:postcode":"90623",
    "sg:province":"CA",
    "sg:tags":[
        "martial art"
    ],
    "wof:name":"All American Jiu-Jitsu",
    "wof:placetype":"venue"
},
  "geometry": {"coordinates":[-118.04528000000001,33.846603],"type":"Point"}
}