{
  "type": "Feature",
  "properties": {
    "iso:country":"US",
    "sg:address":"711 Union Ave",
    "sg:city":"Bakersfield",
    "sg:classifiers":[
        {
            "category":"Travel",
            "subcategory":"Hotels & Motels",
            "type":"Entertainment"
        }
    ],
    "sg:phone":"+1 661 325 5831",
    "sg:postcode":"93307",
    "sg:province":"CA",
    "wof:name":"Plaza Motel",
    "wof:placetype":"venue"
},
  "geometry": {"coordinates":[-119.003028,35.363921],"type":"Point"}
}