{
  "type": "Feature",
  "properties": {
    "addr:full":"11591 Ridge Rd Nevada City CA 95959",
    "addr:housenumber":"11591",
    "addr:postcode":"95959",
    "addr:street":"Ridge Rd",
    "iso:country":"US",
    "sg:address":"11591 Ridge Rd",
    "sg:city":"Nevada City",
    "sg:classifiers":[
        {
            "category":"Social Services",
            "subcategory":"Child Care",
            "type":"Services"
        }
    ],
    "sg:phone":"+1 530 265 4757",
    "sg:postcode":"95959",
    "sg:province":"CA",
    "wof:name":"Mc Laughlin Learning Ctr",
    "wof:placetype":"venue"
},
  "geometry": {"coordinates":[-121.057677,39.239642],"type":"Point"}
}