{
  "type": "Feature",
  "properties": {
    "addr:full":"1221 E Main St Barstow CA 92311",
    "addr:housenumber":"1221",
    "addr:postcode":"92311",
    "addr:street":"E Main St",
    "iso:country":"US",
    "sg:address":"1221 E Main St",
    "sg:city":"Barstow",
    "sg:classifiers":[
        {
            "category":"Autos & Motor Vehicles",
            "subcategory":"Automobile Sales",
            "type":"Retail Goods"
        }
    ],
    "sg:phone":"+1 760 256 2438",
    "sg:postcode":"92311",
    "sg:province":"CA",
    "sg:tags":[
        "car",
        "dealer"
    ],
    "wof:name":"Ideal Auto Ctr",
    "wof:placetype":"venue"
},
  "geometry": {"coordinates":[-117.007893,34.896658],"type":"Point"}
}