{
  "type": "Feature",
  "properties": {
    "iso:country":"US",
    "sg:address":"9244 Piedmont St",
    "sg:city":"Spring Valley",
    "sg:classifiers":[
        {
            "category":"Social Services",
            "subcategory":"Job Training",
            "type":"Services"
        }
    ],
    "sg:phone":"+1 619 474 8794",
    "sg:postcode":"91977",
    "sg:province":"CA",
    "sg:tags":[
        "rehabilitation"
    ],
    "wof:name":"Counseling Resources Barcenas",
    "wof:placetype":"venue"
},
  "geometry": {"coordinates":[-116.999988,32.713571],"type":"Point"}
}