{
  "type": "Feature",
  "properties": {
    "iso:country":"US",
    "sg:address":"3401 W Lake Center Dr",
    "sg:city":"Santa Ana",
    "sg:classifiers":[
        {
            "category":"Manufacturing",
            "subcategory":"Tools & Machinery",
            "type":"Manufacturing & Wholesale Goods"
        }
    ],
    "sg:phone":"+1 714 979 4925",
    "sg:postcode":"92704",
    "sg:province":"CA",
    "sg:tags":[
        "machine",
        "shop"
    ],
    "wof:name":"Excel C & C Products",
    "wof:placetype":"venue"
},
  "geometry": {"coordinates":[-117.914856,33.699309],"type":"Point"}
}