{
  "type": "Feature",
  "properties": {
    "iso:country":"US",
    "sg:address":"7451 Warner Ave",
    "sg:city":"Huntington Beach",
    "sg:classifiers":[
        {
            "category":"Manufacturing",
            "subcategory":"Printing",
            "type":"Manufacturing & Wholesale Goods"
        }
    ],
    "sg:phone":"+1 714 596 8641",
    "sg:postcode":"92647",
    "sg:province":"CA",
    "sg:tags":[
        "printer"
    ],
    "wof:name":"All Forms Express",
    "wof:placetype":"venue"
},
  "geometry": {"coordinates":[-117.99831,33.715628],"type":"Point"}
}