{
  "type": "Feature",
  "properties": {
    "addr:full":"180 Montgomery Street Suite 900 San Francisco CA 94104",
    "addr:housenumber":"180",
    "addr:postcode":"94104",
    "addr:street":"Montgomery Street Suite 900",
    "iso:country":"US",
    "sg:address":"180 Montgomery Street Suite 900",
    "sg:city":"San Francisco",
    "sg:classifiers":[
        {
            "category":"Personal",
            "type":"Services"
        }
    ],
    "sg:phone":"+1 415 434 3388",
    "sg:postcode":"94104",
    "sg:province":"CA",
    "sg:tags":[
        "local"
    ],
    "sg:website":"www.caregiver.org",
    "wof:name":"Family Caregiver Alliance",
    "wof:placetype":"venue"
},
  "geometry": {"coordinates":[-122.40196899999999,37.790736],"type":"Point"}
}