{
  "type": "Feature",
  "properties": {
    "addr:full":"27652 Camino Capistrano Laguna Niguel CA 92677",
    "addr:housenumber":"27652",
    "addr:postcode":"92677",
    "addr:street":"Camino Capistrano",
    "iso:country":"US",
    "sg:address":"27652 Camino Capistrano",
    "sg:city":"Laguna Niguel",
    "sg:classifiers":[
        {
            "category":"Retail",
            "subcategory":"Auto Repair",
            "type":"Services"
        }
    ],
    "sg:phone":"+1 949 582 5303",
    "sg:postcode":"92677",
    "sg:province":"CA",
    "wof:name":"Bmw & Mercedes Service Center",
    "wof:placetype":"venue"
},
  "geometry": {"coordinates":[-117.674004,33.560902],"type":"Point"}
}