{
  "type": "Feature",
  "properties": {
    "addr:full":"3133 Ad Art Rd Stockton CA 95215",
    "addr:postcode":"3133;95215",
    "addr:street":"Art Rd",
    "iso:country":"US",
    "sg:address":"3133 Ad Art Rd",
    "sg:city":"Stockton",
    "sg:classifiers":[
        {
            "category":"Professional",
            "type":"Services"
        }
    ],
    "sg:phone":"+1 209 931 4377",
    "sg:postcode":"95215",
    "sg:province":"CA",
    "wof:name":"Classic Natural Granite",
    "wof:placetype":"venue"
},
  "geometry": {"coordinates":[-121.25140500000001,37.993216],"type":"Point"}
}