{
  "type": "Feature",
  "properties": {
    "addr:full":"30650 Pauba Rd Temecula CA 92592",
    "addr:postcode":"30650;92592",
    "addr:street":"Pauba Rd",
    "iso:country":"US",
    "sg:address":"30650 Pauba Rd",
    "sg:city":"Temecula",
    "sg:classifiers":[
        {
            "category":"Government",
            "subcategory":"Fire Station",
            "type":"Public Place"
        }
    ],
    "sg:phone":"+1 951 693 0683",
    "sg:postcode":"92592",
    "sg:province":"CA",
    "sg:tags":[
        "department"
    ],
    "wof:name":"Riverside County Fire Dept",
    "wof:placetype":"venue"
},
  "geometry": {"coordinates":[-117.126734,33.496456],"type":"Point"}
}