{
  "type": "Feature",
  "properties": {
    "iso:country":"US",
    "sg:address":"2716 Ocean Park Blvd",
    "sg:city":"Santa Monica",
    "sg:classifiers":[
        {
            "category":"Real Estate",
            "subcategory":"Developer",
            "type":"Services"
        }
    ],
    "sg:phone":"+1 310 314 2460",
    "sg:postcode":"90405",
    "sg:province":"CA",
    "sg:tags":[
        "land",
        "subdivider"
    ],
    "wof:name":"Watt Developers LLC",
    "wof:placetype":"venue"
},
  "geometry": {"coordinates":[-118.456295,34.018402],"type":"Point"}
}