{
  "type": "Feature",
  "properties": {
    "iso:country":"US",
    "sg:address":"4113 Scotts Valley Drive",
    "sg:city":"Scotts Valley",
    "sg:classifiers":[
        {
            "category":"Insurance",
            "subcategory":"Health Insurance",
            "type":"Services"
        }
    ],
    "sg:phone":"+1 831 440 9935",
    "sg:postcode":"95066",
    "sg:province":"CA",
    "sg:tags":[
        "market"
    ],
    "sg:website":"www.lifestylehealthy.com",
    "wof:name":"Healthy Lifestyle",
    "wof:placetype":"venue"
},
  "geometry": {"coordinates":[-122.022929,37.044762],"type":"Point"}
}