{
  "type": "Feature",
  "properties": {
    "addr:full":"35089 Yucaipa Blvd Yucaipa CA 92399",
    "addr:postcode":"35089;92399",
    "addr:street":"Yucaipa Blvd",
    "iso:country":"US",
    "sg:address":"35089 Yucaipa Blvd",
    "sg:city":"Yucaipa",
    "sg:classifiers":[
        {
            "category":"Banks & Credit Unions",
            "subcategory":"Bank",
            "type":"Services"
        }
    ],
    "sg:phone":"+1 909 790 7733",
    "sg:postcode":"92399",
    "sg:province":"CA",
    "sg:tags":[
        "money",
        "transfer"
    ],
    "wof:name":"Silvia's Gifts",
    "wof:placetype":"venue"
},
  "geometry": {"coordinates":[-117.040728,34.033801],"type":"Point"}
}