{
  "type": "Feature",
  "properties": {
    "iso:country":"US",
    "sg:address":"2275 E 37th St",
    "sg:city":"Los Angeles",
    "sg:classifiers":[
        {
            "category":"Manufacturing",
            "subcategory":"Apparel",
            "type":"Manufacturing & Wholesale Goods"
        }
    ],
    "sg:phone":"+1 323 588 0000",
    "sg:postcode":"90058",
    "sg:province":"CA",
    "sg:website":"www.karenkane.com",
    "wof:name":"Karen KANE Co",
    "wof:placetype":"venue"
},
  "geometry": {"coordinates":[-118.233656,34.009075],"type":"Point"}
}