{
  "type": "Feature",
  "properties": {
    "addr:full":"18420 S Laurel Park Rd Compton CA 90220",
    "addr:housenumber":"18420",
    "addr:postcode":"90220",
    "addr:street":"S Laurel Park Rd",
    "iso:country":"US",
    "sg:address":"18420 S Laurel Park Rd",
    "sg:city":"Compton",
    "sg:classifiers":[
        {
            "category":"Manufacturing",
            "subcategory":"Chemicals & Compounds",
            "type":"Manufacturing & Wholesale Goods"
        }
    ],
    "sg:phone":"+1 310 632 9211",
    "sg:postcode":"90220",
    "sg:province":"CA",
    "sg:tags":[
        "mfg",
        "cyclic"
    ],
    "wof:name":"Techmer PM LLC",
    "wof:placetype":"venue"
},
  "geometry": {"coordinates":[-118.21941099999999,33.858454],"type":"Point"}
}