{
  "type": "Feature",
  "properties": {
    "iso:country":"US",
    "sg:address":"1635 Taraval St",
    "sg:city":"San Francisco",
    "sg:classifiers":[
        {
            "category":"Communications",
            "type":"Services"
        }
    ],
    "sg:phone":"+1 415 665 6026",
    "sg:postcode":"94116",
    "sg:province":"CA",
    "sg:tags":[
        "communication"
    ],
    "wof:name":"Scientific Media Products",
    "wof:placetype":"venue"
},
  "geometry": {"coordinates":[-122.483966,37.742614],"type":"Point"}
}