{
  "type": "Feature",
  "properties": {
    "iso:country":"US",
    "sg:address":"99 N. La Cienega Blvd. Ste 206",
    "sg:city":"Beverly Hills",
    "sg:classifiers":[
        {
            "category":"Health Services",
            "subcategory":"Doctor",
            "type":"Services"
        }
    ],
    "sg:phone":"+1 310 385 3326",
    "sg:postcode":"90211",
    "sg:province":"CA",
    "sg:tags":[
        "medicine",
        "internal"
    ],
    "sg:website":"www.cedars-sinai.edu/Patients/Ph...",
    "wof:name":"Neil Goldberg, MD",
    "wof:placetype":"venue"
},
  "geometry": {"coordinates":[-118.376313,34.067081],"type":"Point"}
}