{
  "type": "Feature",
  "properties": {
    "addr:full":"220 E O'Keefe St Palo Alto CA 94303",
    "addr:housenumber":"220",
    "addr:postcode":"94303",
    "addr:street":"E O'Keefe St",
    "iso:country":"US",
    "sg:address":"220 E O'Keefe St",
    "sg:city":"Palo Alto",
    "sg:classifiers":[
        {
            "category":"Shopping",
            "subcategory":"Shoes",
            "type":"Retail Goods"
        }
    ],
    "sg:phone":"+1 650 326 3702",
    "sg:postcode":"94303",
    "sg:province":"CA",
    "wof:name":"AR Media Designs",
    "wof:placetype":"venue"
},
  "geometry": {"coordinates":[-122.14469200000001,37.461532],"type":"Point"}
}