{
  "type": "Feature",
  "properties": {
    "addr:full":"2267 N Rockridge Pl Orange CA 92867",
    "addr:housenumber":"2267",
    "addr:postcode":"92867",
    "addr:street":"N Rockridge Pl",
    "iso:country":"US",
    "sg:address":"2267 N Rockridge Pl",
    "sg:city":"Orange",
    "sg:classifiers":[
        {
            "category":"Professional",
            "subcategory":"Employment Agencies",
            "type":"Services"
        }
    ],
    "sg:phone":"+1 714 921 8008",
    "sg:postcode":"92867",
    "sg:province":"CA",
    "sg:website":"www.frankparillo.net",
    "wof:name":"Parillo Frank & Associates",
    "wof:placetype":"venue"
},
  "geometry": {"coordinates":[-117.813512,33.826683],"type":"Point"}
}