{
  "type": "Feature",
  "properties": {
    "addr:full":"1111 Broadway, 19th Fl Oakland CA 94620",
    "addr:housenumber":"1111",
    "addr:postcode":"94620",
    "addr:street":"Broadway 19Th Fl",
    "iso:country":"US",
    "sg:address":"1111 Broadway, 19th Fl",
    "sg:city":"Oakland",
    "sg:classifiers":[
        {
            "category":"Professional",
            "subcategory":"Lawyer & Legal Services",
            "type":"Services"
        }
    ],
    "sg:phone":"+1 510 834 6600",
    "sg:postcode":"94620",
    "sg:province":"CA",
    "sg:website":"www.wendel.com/",
    "wof:name":"Wendel, Rosen Black & Dean Law Firm",
    "wof:placetype":"venue"
},
  "geometry": {"coordinates":[-122.27261,37.80268],"type":"Point"}
}