{
  "type": "Feature",
  "properties": {
    "addr:full":"4900 Hopyard Rd Pleasanton CA 94588",
    "addr:housenumber":"4900",
    "addr:postcode":"94588",
    "addr:street":"Hopyard Rd",
    "iso:country":"US",
    "sg:address":"4900 Hopyard Rd",
    "sg:city":"Pleasanton",
    "sg:classifiers":[
        {
            "category":"Organizations",
            "subcategory":"Professional Association",
            "type":"Services"
        }
    ],
    "sg:phone":"+1 925 933 2121",
    "sg:postcode":"94588",
    "sg:province":"CA",
    "sg:tags":[
        "business",
        "trade"
    ],
    "sg:website":"www.vhawestcoast.com",
    "wof:name":"VHA West Coast",
    "wof:placetype":"venue"
},
  "geometry": {"coordinates":[-121.903582,37.694164],"type":"Point"}
}