{
  "type": "Feature",
  "properties": {
    "iso:country":"US",
    "sg:address":"3145 Santa Anita Ave",
    "sg:city":"El Monte",
    "sg:classifiers":[
        {
            "category":"Food & Beverages",
            "subcategory":"Specialty",
            "type":"Retail Goods"
        }
    ],
    "sg:phone":"+1 626 443 8370",
    "sg:postcode":"91733",
    "sg:province":"CA",
    "sg:tags":[
        "nutritionist",
        "health",
        "vitamin"
    ],
    "wof:name":"El Monte Nutrition Center",
    "wof:placetype":"venue"
},
  "geometry": {"coordinates":[-118.04299899999999,34.065399],"type":"Point"}
}