{
  "type": "Feature",
  "properties": {
    "iso:country":"US",
    "sg:address":"1950 Franklin St",
    "sg:city":"Oakland",
    "sg:classifiers":[
        {
            "category":"Health Services",
            "subcategory":"Hospital",
            "type":"Services"
        },
        {
            "category":"Building & Trades",
            "subcategory":"Construction",
            "type":"Services"
        },
        {
            "category":"Insurance",
            "subcategory":"Health Insurance",
            "type":"Services"
        }
    ],
    "sg:phone":"+1 510 987 3347",
    "sg:postcode":"94612",
    "sg:province":"CA",
    "sg:tags":[
        "surgical",
        "supply",
        "plan",
        "purchasing",
        "nonresidential"
    ],
    "sg:website":"www.kp.org",
    "wof:name":"Kaiser Permanente",
    "wof:placetype":"venue"
},
  "geometry": {"coordinates":[-122.267035,37.80843],"type":"Point"}
}