{
  "type": "Feature",
  "properties": {
    "addr:full":"1950 Franklin St Oakland CA 94612",
    "addr:housenumber":"1950",
    "addr:postcode":"94612",
    "addr:street":"Franklin St",
    "iso:country":"US",
    "sg:address":"1950 Franklin St",
    "sg:city":"Oakland",
    "sg:classifiers":[
        {
            "category":"Health Services",
            "subcategory":"Hospital",
            "type":"Services"
        },
        {
            "category":"Building & Trades",
            "subcategory":"Construction",
            "type":"Services"
        },
        {
            "category":"Insurance",
            "subcategory":"Health Insurance",
            "type":"Services"
        }
    ],
    "sg:phone":"+1 510 987 3347",
    "sg:postcode":"94612",
    "sg:province":"CA",
    "sg:tags":[
        "surgical",
        "supply",
        "plan",
        "purchasing",
        "nonresidential"
    ],
    "sg:website":"www.kp.org",
    "wof:name":"Kaiser Permanente",
    "wof:placetype":"venue"
},
  "geometry": {"coordinates":[-122.26703500000001,37.80843],"type":"Point"}
}