{
  "type": "Feature",
  "properties": {
    "iso:country":"US",
    "sg:address":"Main Street",
    "sg:city":"Morro Bay",
    "sg:classifiers":[
        {
            "category":"Food & Beverages",
            "subcategory":"Farmers Market",
            "type":"Retail Goods"
        }
    ],
    "sg:postcode":"93443",
    "sg:province":"CA",
    "wof:name":"Morro Bay Farmers Market",
    "wof:placetype":"venue"
},
  "geometry": {"coordinates":[-120.855497,35.381259],"type":"Point"}
}