{
  "type": "Feature",
  "properties": {
    "addr:full":"9295 Magnolia Ave Riverside CA 92503",
    "addr:housenumber":"9295",
    "addr:postcode":"92503",
    "addr:street":"Magnolia Ave",
    "iso:country":"US",
    "sg:address":"9295 Magnolia Ave",
    "sg:city":"Riverside",
    "sg:classifiers":[
        {
            "category":"Wholesale",
            "subcategory":"Hardware",
            "type":"Manufacturing & Wholesale Goods"
        },
        {
            "category":"Food & Beverages",
            "subcategory":"Specialty",
            "type":"Retail Goods"
        }
    ],
    "sg:phone":"+1 951 688 3032",
    "sg:postcode":"92503",
    "sg:province":"CA",
    "sg:tags":[
        "water",
        "sal",
        "company",
        "direct",
        "bulk",
        "refrigeration"
    ],
    "wof:name":"Gana Water",
    "wof:placetype":"venue"
},
  "geometry": {"coordinates":[-117.44205700000001,33.923015],"type":"Point"}
}