{
  "type": "Feature",
  "properties": {
    "addr:full":"2466 Butternut Dr Burlingame CA 94010",
    "addr:housenumber":"2466",
    "addr:postcode":"94010",
    "addr:street":"Butternut Dr",
    "iso:country":"US",
    "sg:address":"2466 Butternut Dr",
    "sg:city":"Burlingame",
    "sg:classifiers":[
        {
            "category":"Professional",
            "subcategory":"Management & Consulting",
            "type":"Services"
        }
    ],
    "sg:phone":"+1 650 401 6281",
    "sg:postcode":"94010",
    "sg:province":"CA",
    "wof:name":"Hr Ventures",
    "wof:placetype":"venue"
},
  "geometry": {"coordinates":[-122.380526,37.565713],"type":"Point"}
}