{
  "type": "Feature",
  "properties": {
    "iso:country":"US",
    "sg:address":"20320 SW Birch St",
    "sg:city":"Newport Beach",
    "sg:classifiers":[
        {
            "category":"Real Estate",
            "subcategory":"Real Estate Agent",
            "type":"Services"
        }
    ],
    "sg:phone":"+1 949 640 9881",
    "sg:postcode":"92660",
    "sg:province":"CA",
    "sg:tags":[
        "management"
    ],
    "wof:name":"JPC Properties",
    "wof:placetype":"venue"
},
  "geometry": {"coordinates":[-117.878148,33.656407],"type":"Point"}
}