{
  "type": "Feature",
  "properties": {
    "iso:country":"US",
    "sg:address":"6523 Mimus Ln",
    "sg:city":"Granite Bay",
    "sg:classifiers":[
        {
            "category":"Real Estate",
            "subcategory":"Real Estate Operator",
            "type":"Services"
        }
    ],
    "sg:phone":"+1 916 652 4626",
    "sg:postcode":"95746",
    "sg:province":"CA",
    "sg:tags":[
        "building",
        "apartment"
    ],
    "wof:name":"Pasa Robles Apts",
    "wof:placetype":"venue"
},
  "geometry": {"coordinates":[-121.144318,38.771523],"type":"Point"}
}