{
  "type": "Feature",
  "properties": {
    "addr:full":"2600 Capitol Avenue Sacramento CA 95816",
    "addr:housenumber":"2600",
    "addr:postcode":"95816",
    "addr:street":"Capitol Avenue",
    "iso:country":"US",
    "sg:address":"2600 Capitol Avenue",
    "sg:city":"Sacramento",
    "sg:classifiers":[
        {
            "category":"Health Services",
            "subcategory":"Doctor",
            "type":"Services"
        }
    ],
    "sg:phone":"+1 916 452 0513",
    "sg:postcode":"95816",
    "sg:province":"CA",
    "wof:name":"Dr David Taketa",
    "wof:placetype":"venue"
},
  "geometry": {"coordinates":[-121.473288,38.571343],"type":"Point"}
}