{
  "type": "Feature",
  "properties": {
    "iso:country":"US",
    "sg:address":"17775 Monterey St",
    "sg:city":"Morgan Hill",
    "sg:classifiers":[
        {
            "category":"Professional",
            "subcategory":"Lawyer & Legal Services",
            "type":"Services"
        }
    ],
    "sg:phone":"+1 408 779 9194",
    "sg:postcode":"95037",
    "sg:province":"CA",
    "sg:tags":[
        "attorney"
    ],
    "wof:name":"Bruce Tichinin Law Offices",
    "wof:placetype":"venue"
},
  "geometry": {"coordinates":[-121.655585,37.131381],"type":"Point"}
}