{
  "type": "Feature",
  "properties": {
    "addr:full":"604 C St Eureka CA 95501",
    "addr:housenumber":"604",
    "addr:postcode":"95501",
    "addr:street":"C St",
    "iso:country":"US",
    "sg:address":"604 C St",
    "sg:city":"Eureka",
    "sg:classifiers":[
        {
            "category":"Government",
            "subcategory":"Police Station",
            "type":"Public Place"
        }
    ],
    "sg:phone":"+1 707 441 4073",
    "sg:postcode":"95501",
    "sg:province":"CA",
    "sg:tags":[
        "department"
    ],
    "wof:name":"Eureka Parking Ticket Adm",
    "wof:placetype":"venue"
},
  "geometry": {"coordinates":[-124.16983999999999,40.803952],"type":"Point"}
}