{
  "type": "Feature",
  "properties": {
    "iso:country":"US",
    "sg:address":"1320 E Olympic Blvd",
    "sg:city":"Los Angeles",
    "sg:classifiers":[
        {
            "category":"Manufacturing",
            "subcategory":"Apparel",
            "type":"Manufacturing & Wholesale Goods"
        }
    ],
    "sg:phone":"+1 213 892 9990",
    "sg:postcode":"90021",
    "sg:province":"CA",
    "sg:tags":[
        "equipment",
        "commercial",
        "clothing"
    ],
    "wof:name":"All The Right Stuff",
    "wof:placetype":"venue"
},
  "geometry": {"coordinates":[-118.243393,34.031312],"type":"Point"}
}