{
  "type": "Feature",
  "properties": {
    "iso:country":"US",
    "sg:address":"2102 Bus Center Dr",
    "sg:city":"Irvine",
    "sg:classifiers":[
        {
            "category":"Retail",
            "subcategory":"Funeral Services",
            "type":"Services"
        }
    ],
    "sg:phone":"+1 714 638 1112",
    "sg:postcode":"92612",
    "sg:province":"CA",
    "sg:tags":[
        "director"
    ],
    "wof:name":"Coastal Funeral Svc",
    "wof:placetype":"venue"
},
  "geometry": {"coordinates":[-117.855876,33.679638],"type":"Point"}
}