{
  "type": "Feature",
  "properties": {
    "addr:full":"910 Lorne Way Sunnyvale CA 94087",
    "addr:housenumber":"910",
    "addr:postcode":"94087",
    "addr:street":"Lorne Way",
    "iso:country":"US",
    "sg:address":"910 Lorne Way",
    "sg:city":"Sunnyvale",
    "sg:classifiers":[
        {
            "category":"Building & Trades",
            "subcategory":"Electrical",
            "type":"Services"
        }
    ],
    "sg:phone":"+1 408 245 7677",
    "sg:postcode":"94087",
    "sg:province":"CA",
    "sg:tags":[
        "electric",
        "contractor"
    ],
    "wof:name":"Da Rosa Electric Co",
    "wof:placetype":"venue"
},
  "geometry": {"coordinates":[-122.01056,37.338519],"type":"Point"}
}