{
  "type": "Feature",
  "properties": {
    "addr:full":"94 Bonaventura Dr San Jose CA 95134",
    "addr:housenumber":"94",
    "addr:postcode":"95134",
    "addr:street":"Bonaventura Dr",
    "iso:country":"US",
    "sg:address":"94 Bonaventura Dr",
    "sg:city":"San Jose",
    "sg:classifiers":[
        {
            "category":"Manufacturing",
            "subcategory":"Electronics",
            "type":"Manufacturing & Wholesale Goods"
        }
    ],
    "sg:phone":"+1 408 428 9101",
    "sg:postcode":"95134",
    "sg:province":"CA",
    "sg:tags":[
        "development",
        "product",
        "optical"
    ],
    "wof:name":"Next Wave Optics Inc",
    "wof:placetype":"venue"
},
  "geometry": {"coordinates":[-121.926075,37.390595],"type":"Point"}
}