{
  "type": "Feature",
  "properties": {
    "addr:full":"17770 Old Summit Rd Los Gatos CA 95033",
    "addr:housenumber":"17770",
    "addr:postcode":"95033",
    "addr:street":"Old Summit Rd",
    "iso:country":"US",
    "sg:address":"17770 Old Summit Rd",
    "sg:city":"Los Gatos",
    "sg:classifiers":[
        {
            "category":"Manufacturing",
            "subcategory":"Apparel",
            "type":"Manufacturing & Wholesale Goods"
        }
    ],
    "sg:phone":"+1 408 353 2890",
    "sg:postcode":"95033",
    "sg:province":"CA",
    "sg:tags":[
        "household",
        "furnishing",
        "mfg"
    ],
    "wof:name":"Rush Design",
    "wof:placetype":"venue"
},
  "geometry": {"coordinates":[-121.983255,37.143282],"type":"Point"}
}