{
  "type": "Feature",
  "properties": {
    "addr:full":"874 4th St San Rafael CA 94901",
    "addr:housenumber":"874",
    "addr:postcode":"94901",
    "addr:street":"4Th St",
    "iso:country":"US",
    "sg:address":"874 4th St",
    "sg:city":"San Rafael",
    "sg:classifiers":[
        {
            "category":"Food & Beverages",
            "subcategory":"Specialty",
            "type":"Retail Goods"
        }
    ],
    "sg:phone":"+1 415 457 0132",
    "sg:postcode":"94901",
    "sg:province":"CA",
    "sg:tags":[
        "vitamin"
    ],
    "sg:website":"www.raphashoppe.com",
    "wof:name":"Rapha Natural Shoppe",
    "wof:placetype":"venue"
},
  "geometry": {"coordinates":[-122.525575,37.972935],"type":"Point"}
}