{
  "type": "Feature",
  "properties": {
    "addr:full":"4701 Franklin Blvd Sacramento CA 95820",
    "addr:housenumber":"4701",
    "addr:postcode":"95820",
    "addr:street":"Franklin Blvd",
    "iso:country":"US",
    "sg:address":"4701 Franklin Blvd",
    "sg:city":"Sacramento",
    "sg:classifiers":[
        {
            "category":"Professional",
            "subcategory":"Management & Consulting",
            "type":"Services"
        }
    ],
    "sg:phone":"+1 916 457 9000",
    "sg:postcode":"95820",
    "sg:province":"CA",
    "sg:tags":[
        "international",
        "consultant",
        "business",
        "trade"
    ],
    "wof:name":"Farhat Co. Import Export Inc.",
    "wof:placetype":"venue"
},
  "geometry": {"coordinates":[-121.473747,38.532749],"type":"Point"}
}