{
  "type": "Feature",
  "properties": {
    "iso:country":"US",
    "sg:address":"199 Leal Way",
    "sg:city":"Fremont",
    "sg:classifiers":[
        {
            "category":"Professional",
            "type":"Services"
        }
    ],
    "sg:phone":"+1 510 226 9338",
    "sg:postcode":"94539",
    "sg:province":"CA",
    "wof:name":"Infornia Inc",
    "wof:placetype":"venue"
},
  "geometry": {"coordinates":[-121.93726599999999,37.548956],"type":"Point"}
}