{
  "type": "Feature",
  "properties": {
    "addr:full":"2505 Miramar Ave Long Beach CA 90815",
    "addr:housenumber":"2505",
    "addr:postcode":"90815",
    "addr:street":"Miramar Ave",
    "iso:country":"US",
    "sg:address":"2505 Miramar Ave",
    "sg:city":"Long Beach",
    "sg:classifiers":[
        {
            "category":"Building & Trades",
            "subcategory":"Electrical",
            "type":"Services"
        },
        {
            "category":"Building & Trades",
            "subcategory":"Plumbing",
            "type":"Services"
        }
    ],
    "sg:phone":"+1 562 498 0130",
    "sg:postcode":"90815",
    "sg:province":"CA",
    "sg:tags":[
        "consulting",
        "installation",
        "sprinkler",
        "business",
        "fire",
        "system",
        "contractor",
        "electrical"
    ],
    "wof:name":"Cal Protection",
    "wof:placetype":"venue"
},
  "geometry": {"coordinates":[-118.146513,33.800868],"type":"Point"}
}