{
  "type": "Feature",
  "properties": {
    "iso:country":"US",
    "sg:address":"2185 Churn Creek Rd",
    "sg:city":"Redding",
    "sg:classifiers":[
        {
            "category":"Professional",
            "subcategory":"Business Services",
            "type":"Services"
        }
    ],
    "sg:phone":"+1 530 221 5560",
    "sg:postcode":"96002",
    "sg:province":"CA",
    "sg:tags":[
        "embroidery"
    ],
    "wof:name":"Heel Sew Quik",
    "wof:placetype":"venue"
},
  "geometry": {"coordinates":[-122.352901,40.575657],"type":"Point"}
}