{
  "type": "Feature",
  "properties": {
    "iso:country":"US",
    "sg:address":"920 N Amelia Ave",
    "sg:city":"San Dimas",
    "sg:classifiers":[
        {
            "category":"Wholesale",
            "subcategory":"Metals & Minerals",
            "type":"Manufacturing & Wholesale Goods"
        }
    ],
    "sg:phone":"+1 626 966 7960",
    "sg:postcode":"91773",
    "sg:province":"CA",
    "sg:tags":[
        "center"
    ],
    "wof:name":"Hawk Industry Products",
    "wof:placetype":"venue"
},
  "geometry": {"coordinates":[-117.820133,34.117993],"type":"Point"}
}