{
  "type": "Feature",
  "properties": {
    "addr:full":"3041 Cochran St Simi Valley CA 93065",
    "addr:housenumber":"3041",
    "addr:postcode":"93065",
    "addr:street":"Cochran St",
    "iso:country":"US",
    "sg:address":"3041 Cochran St",
    "sg:city":"Simi Valley",
    "sg:classifiers":[
        {
            "category":"Insurance",
            "subcategory":"Insurance Agent",
            "type":"Services"
        }
    ],
    "sg:phone":"+1 805 583 7400",
    "sg:postcode":"93065",
    "sg:province":"CA",
    "sg:website":"www.farmersinsurance.com",
    "wof:name":"Farmers Insurance Group",
    "wof:placetype":"venue"
},
  "geometry": {"coordinates":[-118.738489,34.279074],"type":"Point"}
}