{
  "type": "Feature",
  "properties": {
    "iso:country":"US",
    "sg:address":"3919 Clayton Ave",
    "sg:city":"Los Angeles",
    "sg:classifiers":[
        {
            "category":"Professional",
            "type":"Services"
        }
    ],
    "sg:phone":"+1 323 665 1940",
    "sg:postcode":"90027",
    "sg:province":"CA",
    "wof:name":"Patricia L Smith",
    "wof:placetype":"venue"
},
  "geometry": {"coordinates":[-118.276991,34.09922],"type":"Point"}
}