{
  "type": "Feature",
  "properties": {
    "iso:country":"US",
    "sg:address":"24725 Alessandro Blvd",
    "sg:city":"Moreno Valley",
    "sg:classifiers":[
        {
            "category":"Shopping",
            "subcategory":"Jewelry",
            "type":"Retail Goods"
        }
    ],
    "sg:phone":"+1 951 601 0954",
    "sg:postcode":"92553",
    "sg:province":"CA",
    "sg:tags":[
        "jeweler"
    ],
    "wof:name":"T & L Jewelry",
    "wof:placetype":"venue"
},
  "geometry": {"coordinates":[-117.22712199999999,33.917229],"type":"Point"}
}