{
  "type": "Feature",
  "properties": {
    "iso:country":"US",
    "sg:address":"82575 Amboy Rd",
    "sg:city":"Twentynine Palms",
    "sg:classifiers":[
        {
            "category":"Organizations",
            "subcategory":"Religious Organization",
            "type":"Services"
        }
    ],
    "sg:phone":"+1 760 367 0279",
    "sg:postcode":"92277",
    "sg:province":"CA",
    "sg:tags":[
        "church"
    ],
    "wof:name":"Wonder Valley Community",
    "wof:placetype":"venue"
},
  "geometry": {"coordinates":[-115.861165,34.165452],"type":"Point"}
}