{
  "type": "Feature",
  "properties": {
    "iso:country":"US",
    "sg:address":"9233 Twin Schools Rd",
    "sg:city":"Granite Bay",
    "sg:classifiers":[
        {
            "category":"Education",
            "subcategory":"School",
            "type":"Public Place"
        }
    ],
    "sg:phone":"+1 916 791 5391",
    "sg:postcode":"95746",
    "sg:province":"CA",
    "wof:name":"Oakhills School",
    "wof:placetype":"venue"
},
  "geometry": {"coordinates":[-121.206532,38.730341],"type":"Point"}
}