{
  "type": "Feature",
  "properties": {
    "iso:country":"US",
    "sg:address":"10905 Imperial Hwy",
    "sg:city":"Norwalk",
    "sg:classifiers":[
        {
            "category":"Restaurant",
            "type":"Food & Drink"
        }
    ],
    "sg:menulink":"http://www.allmenus.com/ca/downey-norwalk/198018-kfc---kentucky-fried-chicken/menu/",
    "sg:phone":"+1 562 929 1122",
    "sg:postcode":"90650",
    "sg:province":"CA",
    "sg:tags":[
        "american",
        "chicken"
    ],
    "wof:name":"KFC - Kentucky Fried Chicken",
    "wof:placetype":"venue"
},
  "geometry": {"coordinates":[-118.101296,33.917165],"type":"Point"}
}