{
  "type": "Feature",
  "properties": {
    "addr:full":"1801 N Chester Ave Bakersfield CA 93308",
    "addr:housenumber":"1801",
    "addr:postcode":"93308",
    "addr:street":"N Chester Ave",
    "iso:country":"US",
    "sg:address":"1801 N Chester Ave",
    "sg:city":"Bakersfield",
    "sg:classifiers":[
        {
            "category":"Retail",
            "subcategory":"Auto Repair",
            "type":"Services"
        }
    ],
    "sg:phone":"+1 661 393 2517",
    "sg:postcode":"93308",
    "sg:province":"CA",
    "sg:tags":[
        "repairing",
        "automobile"
    ],
    "wof:name":"North Chester Automotive Rpr",
    "wof:placetype":"venue"
},
  "geometry": {"coordinates":[-119.02120600000001,35.423207],"type":"Point"}
}