{
  "type": "Feature",
  "properties": {
    "addr:full":"1175 S 19th Ave Lemoore CA 93245",
    "addr:housenumber":"1175",
    "addr:postcode":"93245",
    "addr:street":"S 19Th Ave",
    "iso:country":"US",
    "sg:address":"1175 S 19th Ave",
    "sg:city":"Lemoore",
    "sg:classifiers":[
        {
            "category":"Farming",
            "subcategory":"Farm",
            "type":"Manufacturing & Wholesale Goods"
        }
    ],
    "sg:phone":"+1 559 924 6518",
    "sg:postcode":"93245",
    "sg:province":"CA",
    "wof:name":"S S Farms",
    "wof:placetype":"venue"
},
  "geometry": {"coordinates":[-119.798987,36.282221],"type":"Point"}
}