{
  "type": "Feature",
  "properties": {
    "iso:country":"US",
    "sg:address":"3575 Davis St",
    "sg:city":"Oakland",
    "sg:classifiers":[
        {
            "category":"Organizations",
            "subcategory":"Non-profit Organization",
            "type":"Services"
        }
    ],
    "sg:phone":"+1 510 534 9603",
    "sg:postcode":"94601",
    "sg:province":"CA",
    "wof:name":"Spirit Drumz",
    "wof:placetype":"venue"
},
  "geometry": {"coordinates":[-122.21340600000001,37.785553],"type":"Point"}
}