{
  "type": "Feature",
  "properties": {
    "addr:full":"9411 Brighton Way Beverly Hills CA 90210",
    "addr:housenumber":"9411",
    "addr:postcode":"90210",
    "addr:street":"Brighton Way",
    "iso:country":"US",
    "sg:address":"9411 Brighton Way",
    "sg:city":"Beverly Hills",
    "sg:classifiers":[
        {
            "category":"Shopping",
            "subcategory":"Clothing, Apparel, & Fashions",
            "type":"Retail Goods"
        }
    ],
    "sg:phone":"+1 310 273 6727",
    "sg:postcode":"90210",
    "sg:province":"CA",
    "wof:name":"Renee Bardot Boutique",
    "wof:placetype":"venue"
},
  "geometry": {"coordinates":[-118.40125399999999,34.07049],"type":"Point"}
}