{
  "type": "Feature",
  "properties": {
    "addr:full":"113 E Lake Ave Watsonville CA 95076",
    "addr:housenumber":"113",
    "addr:postcode":"95076",
    "addr:street":"E Lake Ave",
    "iso:country":"US",
    "sg:address":"113 E Lake Ave",
    "sg:city":"Watsonville",
    "sg:classifiers":[
        {
            "category":"Real Estate",
            "subcategory":"Real Estate Agent",
            "type":"Services"
        }
    ],
    "sg:phone":"+1 831 728 1444",
    "sg:postcode":"95076",
    "sg:province":"CA",
    "wof:name":"Ponderosa Realty",
    "wof:placetype":"venue"
},
  "geometry": {"coordinates":[-121.756095,36.91336],"type":"Point"}
}