{
  "type": "Feature",
  "properties": {
    "addr:full":"851 Fremont Avenue Suite 102 Los Altos CA 94024",
    "addr:housenumber":"851",
    "addr:postcode":"94024",
    "addr:street":"Fremont Avenue Suite 102",
    "iso:country":"US",
    "sg:address":"851 Fremont Avenue Suite 102",
    "sg:city":"Los Altos",
    "sg:classifiers":[
        {
            "category":"Professional",
            "subcategory":"Lawyer & Legal Services",
            "type":"Services"
        }
    ],
    "sg:phone":"+1 650 949 4117",
    "sg:postcode":"94024",
    "sg:province":"CA",
    "wof:name":"Hawks & Comfort Llp",
    "wof:placetype":"venue"
},
  "geometry": {"coordinates":[-122.09128800000001,37.355853],"type":"Point"}
}