{
  "type": "Feature",
  "properties": {
    "iso:country":"US",
    "sg:address":"1606 W Rosecrans Ave",
    "sg:city":"Compton",
    "sg:classifiers":[
        {
            "category":"Shopping",
            "subcategory":"Music",
            "type":"Retail Goods"
        }
    ],
    "sg:phone":"+1 310 537 0678",
    "sg:postcode":"90220",
    "sg:province":"CA",
    "sg:tags":[
        "used",
        "tapes",
        "vintage",
        "records",
        "cd's",
        "store"
    ],
    "wof:name":"V I P Music",
    "wof:placetype":"venue"
},
  "geometry": {"coordinates":[-118.250259,33.903009],"type":"Point"}
}