{
  "type": "Feature",
  "properties": {
    "iso:country":"US",
    "sg:address":"530 New Los Angeles Ave",
    "sg:city":"Moorpark",
    "sg:classifiers":[
        {
            "category":"Shopping",
            "subcategory":"Clothing, Apparel, & Fashions",
            "type":"Retail Goods"
        }
    ],
    "sg:phone":"+1 805 529 7953",
    "sg:postcode":"93021",
    "sg:province":"CA",
    "sg:tags":[
        "sporting",
        "sportswear"
    ],
    "wof:name":"Palanis",
    "wof:placetype":"venue"
},
  "geometry": {"coordinates":[-118.874065,34.278795],"type":"Point"}
}