{
  "type": "Feature",
  "properties": {
    "addr:full":"4675 Macarthur Ct Newport Beach CA 92660",
    "addr:housenumber":"4675",
    "addr:postcode":"92660",
    "addr:street":"Macarthur Ct",
    "iso:country":"US",
    "sg:address":"4675 Macarthur Ct",
    "sg:city":"Newport Beach",
    "sg:classifiers":[
        {
            "category":"Building & Trades",
            "subcategory":"Plumbing",
            "type":"Services"
        }
    ],
    "sg:phone":"+1 714 777 3200",
    "sg:postcode":"92660",
    "sg:province":"CA",
    "sg:tags":[
        "product",
        "management",
        "energy",
        "system"
    ],
    "wof:name":"Pacific Summit Energy LLC",
    "wof:placetype":"venue"
},
  "geometry": {"coordinates":[-117.86171,33.670483],"type":"Point"}
}