{
  "type": "Feature",
  "properties": {
    "iso:country":"US",
    "sg:address":"217 N Lemon St",
    "sg:city":"Anaheim",
    "sg:classifiers":[
        {
            "category":"Building & Trades",
            "subcategory":"Construction",
            "type":"Services"
        }
    ],
    "sg:phone":"+1 714 544 0405",
    "sg:postcode":"92805",
    "sg:province":"CA",
    "sg:tags":[
        "contractor"
    ],
    "wof:name":"John Laing Homes",
    "wof:placetype":"venue"
},
  "geometry": {"coordinates":[-117.917,33.8367],"type":"Point"}
}