{
  "type": "Feature",
  "properties": {
    "iso:country":"US",
    "sg:address":"2422 E Katella Ave Suite B",
    "sg:city":"Anaheim",
    "sg:classifiers":[
        {
            "category":"Food & Beverages",
            "subcategory":"Bakery",
            "type":"Retail Goods"
        }
    ],
    "sg:phone":"+1 714 940 9999",
    "sg:postcode":"92806",
    "sg:province":"CA",
    "sg:tags":[
        "sandwich"
    ],
    "sg:website":"www.subway.com",
    "wof:name":"Subway",
    "wof:placetype":"venue"
},
  "geometry": {"coordinates":[-117.882381,33.805788],"type":"Point"}
}