{
  "type": "Feature",
  "properties": {
    "addr:full":"716 6th St Corning CA 96021",
    "addr:housenumber":"716",
    "addr:postcode":"96021",
    "addr:street":"6Th St",
    "iso:country":"US",
    "sg:address":"716 6th St",
    "sg:city":"Corning",
    "sg:classifiers":[
        {
            "category":"Retail",
            "subcategory":"Auto Repair",
            "type":"Services"
        }
    ],
    "sg:phone":"+1 530 824 1119",
    "sg:postcode":"96021",
    "sg:province":"CA",
    "sg:tags":[
        "repairing",
        "automobile"
    ],
    "wof:name":"A Radiator Shop & General Auto",
    "wof:placetype":"venue"
},
  "geometry": {"coordinates":[-122.183536,39.928747],"type":"Point"}
}