{
  "type": "Feature",
  "properties": {
    "iso:country":"US",
    "sg:address":"325 Sharon Park Dr",
    "sg:city":"Menlo Park",
    "sg:classifiers":[
        {
            "category":"Shopping",
            "subcategory":"Clothing, Apparel, & Fashions",
            "type":"Retail Goods"
        }
    ],
    "sg:phone":"+1 650 854 8030",
    "sg:postcode":"94025",
    "sg:province":"CA",
    "sg:website":"www.finofino.com",
    "wof:name":"Fino Fino",
    "wof:placetype":"venue"
},
  "geometry": {"coordinates":[-122.195778,37.423991],"type":"Point"}
}