{
  "type": "Feature",
  "properties": {
    "addr:full":"10825 S Peach Ave Fresno CA 93725",
    "addr:housenumber":"10825",
    "addr:postcode":"93725",
    "addr:street":"S Peach Ave",
    "iso:country":"US",
    "sg:address":"10825 S Peach Ave",
    "sg:city":"Fresno",
    "sg:classifiers":[
        {
            "category":"Farming",
            "subcategory":"Vineyard",
            "type":"Manufacturing & Wholesale Goods"
        }
    ],
    "sg:phone":"+1 559 896 2436",
    "sg:postcode":"93725",
    "sg:province":"CA",
    "wof:name":"Dosanjh Vineyards",
    "wof:placetype":"venue"
},
  "geometry": {"coordinates":[-119.718538,36.5811],"type":"Point"}
}