{
  "type": "Feature",
  "properties": {
    "iso:country":"US",
    "sg:address":"545 L St",
    "sg:city":"Sacramento",
    "sg:classifiers":[
        {
            "category":"Wholesale",
            "subcategory":"Furniture",
            "type":"Manufacturing & Wholesale Goods"
        }
    ],
    "sg:phone":"+1 925 286 9705",
    "sg:postcode":"95814",
    "sg:province":"CA",
    "sg:tags":[
        "retail"
    ],
    "wof:name":"Piyassa Inc",
    "wof:placetype":"venue"
},
  "geometry": {"coordinates":[-121.50015500000001,38.579748],"type":"Point"}
}