{
  "type": "Feature",
  "properties": {
    "iso:country":"US",
    "sg:address":"74053 San Marino Cir",
    "sg:city":"Palm Desert",
    "sg:classifiers":[
        {
            "category":"Professional",
            "type":"Services"
        }
    ],
    "sg:phone":"+1 760 340 1781",
    "sg:postcode":"92260",
    "sg:province":"CA",
    "wof:name":"Sumida Orchids",
    "wof:placetype":"venue"
},
  "geometry": {"coordinates":[-116.373361,33.722792],"type":"Point"}
}