{
  "type": "Feature",
  "properties": {
    "iso:country":"US",
    "sg:address":"321 Hartz Ave",
    "sg:city":"Danville",
    "sg:classifiers":[
        {
            "category":"Real Estate",
            "subcategory":"Real Estate Agent",
            "type":"Services"
        }
    ],
    "sg:phone":"+1 925 552 7800",
    "sg:postcode":"94526",
    "sg:province":"CA",
    "wof:name":"Rassier Properties",
    "wof:placetype":"venue"
},
  "geometry": {"coordinates":[-122.000722,37.822343],"type":"Point"}
}