{
  "type": "Feature",
  "properties": {
    "iso:country":"US",
    "sg:address":"5750 Wilshire Blvd",
    "sg:city":"Los Angeles",
    "sg:classifiers":[
        {
            "category":"Real Estate",
            "subcategory":"Real Estate Agent",
            "type":"Services"
        }
    ],
    "sg:phone":"+1 323 930 3734",
    "sg:postcode":"90036",
    "sg:province":"CA",
    "sg:tags":[
        "property",
        "management"
    ],
    "sg:website":"www.maison140.com",
    "wof:name":"Kor Realty Group LLC",
    "wof:placetype":"venue"
},
  "geometry": {"coordinates":[-118.354606,34.06238],"type":"Point"}
}