{
  "type": "Feature",
  "properties": {
    "iso:country":"US",
    "sg:address":"155 S Washington St",
    "sg:city":"Sonora",
    "sg:classifiers":[
        {
            "category":"Bars & Pubs",
            "type":"Food & Drink"
        }
    ],
    "sg:phone":"+1 209 532 4344",
    "sg:postcode":"95370",
    "sg:province":"CA",
    "sg:tags":[
        "lounge",
        "cocktail"
    ],
    "wof:name":"Office",
    "wof:placetype":"venue"
},
  "geometry": {"coordinates":[-120.38202,37.983246],"type":"Point"}
}