{
  "type": "Feature",
  "properties": {
    "iso:country":"US",
    "sg:address":"74 Digital Dr",
    "sg:city":"Novato",
    "sg:classifiers":[
        {
            "category":"Professional",
            "subcategory":"Computer Services",
            "type":"Services"
        }
    ],
    "sg:phone":"+1 415 382 8115",
    "sg:postcode":"94949",
    "sg:province":"CA",
    "sg:tags":[
        "graphics"
    ],
    "wof:name":"Light Studio",
    "wof:placetype":"venue"
},
  "geometry": {"coordinates":[-122.52984,38.071175],"type":"Point"}
}