{
  "type": "Feature",
  "properties": {
    "addr:full":"11890 Scripps Creek Dr San Diego CA 92131",
    "addr:housenumber":"11890",
    "addr:postcode":"92131",
    "addr:street":"Scripps Creek Dr",
    "iso:country":"US",
    "sg:address":"11890 Scripps Creek Dr",
    "sg:city":"San Diego",
    "sg:classifiers":[
        {
            "category":"Professional",
            "subcategory":"Computer Services",
            "type":"Services"
        }
    ],
    "sg:phone":"+1 858 549 4649",
    "sg:postcode":"92131",
    "sg:province":"CA",
    "sg:website":"www.hallmarkinterfaces.com",
    "wof:name":"Hallmark Interfaces",
    "wof:placetype":"venue"
},
  "geometry": {"coordinates":[-117.089061,32.934795],"type":"Point"}
}