{
  "type": "Feature",
  "properties": {
    "addr:full":"18559 Sherman Way Reseda CA 91335",
    "addr:housenumber":"18559",
    "addr:postcode":"91335",
    "addr:street":"Sherman Way",
    "iso:country":"US",
    "sg:address":"18559 Sherman Way",
    "sg:city":"Reseda",
    "sg:classifiers":[
        {
            "category":"Professional",
            "type":"Services"
        }
    ],
    "sg:phone":"+1 818 342 2821",
    "sg:postcode":"91335",
    "sg:province":"CA",
    "sg:tags":[
        "establishment"
    ],
    "wof:name":"Best Performing Systems",
    "wof:placetype":"venue"
},
  "geometry": {"coordinates":[-118.53820399999999,34.201136],"type":"Point"}
}