{
  "type": "Feature",
  "properties": {
    "addr:full":"8323 de Soto Ave Canoga Park CA 91304",
    "addr:housenumber":"8323",
    "addr:postcode":"91304",
    "addr:street":"De Soto Ave",
    "iso:country":"US",
    "sg:address":"8323 de Soto Ave",
    "sg:city":"Canoga Park",
    "sg:classifiers":[
        {
            "category":"Travel",
            "subcategory":"Travel Agent",
            "type":"Entertainment"
        }
    ],
    "sg:phone":"+1 818 717 3909",
    "sg:postcode":"91304",
    "sg:province":"CA",
    "sg:tags":[
        "agency",
        "bureau"
    ],
    "wof:name":"Mexicali Travel Svc",
    "wof:placetype":"venue"
},
  "geometry": {"coordinates":[-118.588588,34.221654],"type":"Point"}
}