{
  "type": "Feature",
  "properties": {
    "addr:full":"3109 22nd St San Francisco CA 94110",
    "addr:housenumber":"3109",
    "addr:postcode":"94110",
    "addr:street":"22Nd St",
    "iso:country":"US",
    "sg:address":"3109 22nd St",
    "sg:city":"San Francisco",
    "sg:classifiers":[
        {
            "category":"Retail",
            "subcategory":"Repair Shop",
            "type":"Services"
        }
    ],
    "sg:phone":"+1 415 826 3209",
    "sg:postcode":"94110",
    "sg:province":"CA",
    "sg:tags":[
        "watch"
    ],
    "wof:name":"House Of Seiko",
    "wof:placetype":"venue"
},
  "geometry": {"coordinates":[-122.417472,37.755441],"type":"Point"}
}