{
  "type": "Feature",
  "properties": {
    "addr:full":"7820 Edendale Ct Elk Grove CA 95758",
    "addr:housenumber":"7820",
    "addr:postcode":"95758",
    "addr:street":"Edendale Ct",
    "iso:country":"US",
    "sg:address":"7820 Edendale Ct",
    "sg:city":"Elk Grove",
    "sg:classifiers":[
        {
            "category":"Communications",
            "type":"Services"
        }
    ],
    "sg:phone":"+1 916 691 4815",
    "sg:postcode":"95758",
    "sg:province":"CA",
    "sg:tags":[
        "communication"
    ],
    "wof:name":"Nwg Communications",
    "wof:placetype":"venue"
},
  "geometry": {"coordinates":[-121.41204399999999,38.422079],"type":"Point"}
}