{
  "type": "Feature",
  "properties": {
    "iso:country":"US",
    "sg:address":"200 Greenhorn Rd",
    "sg:city":"Yreka",
    "sg:classifiers":[
        {
            "category":"Organizations",
            "subcategory":"Religious Organization",
            "type":"Services"
        }
    ],
    "sg:phone":"+1 530 842 1852",
    "sg:postcode":"96097",
    "sg:province":"CA",
    "sg:tags":[
        "church"
    ],
    "wof:name":"Covenant Chapel",
    "wof:placetype":"venue"
},
  "geometry": {"coordinates":[-122.646511,41.711771],"type":"Point"}
}