{
  "type": "Feature",
  "properties": {
    "iso:country":"US",
    "sg:address":"913 Court St",
    "sg:city":"Woodland",
    "sg:classifiers":[
        {
            "category":"Professional",
            "subcategory":"Lawyer & Legal Services",
            "type":"Services"
        }
    ],
    "sg:phone":"+1 530 666 1935",
    "sg:postcode":"95695",
    "sg:province":"CA",
    "sg:tags":[
        "attorney"
    ],
    "wof:name":"Gilbert A Roque",
    "wof:placetype":"venue"
},
  "geometry": {"coordinates":[-121.76754800000001,38.67877],"type":"Point"}
}