{
  "type": "Feature",
  "properties": {
    "addr:full":"13353 Houston Ave Hanford CA 93230",
    "addr:housenumber":"13353",
    "addr:postcode":"ca 93230",
    "addr:street":"Houston Ave",
    "iso:country":"US",
    "sg:address":"13353 Houston Ave",
    "sg:city":"Hanford",
    "sg:classifiers":[
        {
            "category":"Retail",
            "subcategory":"Repair Shop",
            "type":"Services"
        }
    ],
    "sg:phone":"+1 559 582 2805",
    "sg:postcode":"93230",
    "sg:province":"CA",
    "sg:tags":[
        "welding"
    ],
    "wof:name":"Silva's Welding",
    "wof:placetype":"venue"
},
  "geometry": {"coordinates":[-119.698071,36.298404],"type":"Point"}
}