{
  "type": "Feature",
  "properties": {
    "addr:full":"299 N California Ave Palo Alto CA 94301",
    "addr:housenumber":"299",
    "addr:postcode":"94301",
    "addr:street":"N California Ave",
    "iso:country":"US",
    "sg:address":"299 N California Ave",
    "sg:city":"Palo Alto",
    "sg:classifiers":[
        {
            "category":"Education",
            "subcategory":"Special Training",
            "type":"Public Place"
        }
    ],
    "sg:phone":"+1 650 327 0841",
    "sg:postcode":"94301",
    "sg:province":"CA",
    "sg:tags":[
        "educational"
    ],
    "wof:name":"Kaplan Educational Ctr",
    "wof:placetype":"venue"
},
  "geometry": {"coordinates":[-122.14046,37.431589],"type":"Point"}
}