{
  "type": "Feature",
  "properties": {
    "addr:full":"1212 Broadway Oakland CA 94612",
    "addr:housenumber":"1212",
    "addr:postcode":"94612",
    "addr:street":"Broadway",
    "iso:country":"US",
    "sg:address":"1212 Broadway",
    "sg:city":"Oakland",
    "sg:classifiers":[
        {
            "category":"Professional",
            "subcategory":"Lawyer & Legal Services",
            "type":"Services"
        }
    ],
    "sg:phone":"+1 510 835 3730",
    "sg:postcode":"94612",
    "sg:province":"CA",
    "sg:tags":[
        "attorney"
    ],
    "wof:name":"Ronald Uy Law Offices",
    "wof:placetype":"venue"
},
  "geometry": {"coordinates":[-122.271657,37.803558],"type":"Point"}
}