{
  "type": "Feature",
  "properties": {
    "iso:country":"US",
    "sg:address":"13120 Brookhurst St",
    "sg:city":"Garden Grove",
    "sg:classifiers":[
        {
            "category":"Professional",
            "type":"Services"
        }
    ],
    "sg:phone":"+1 714 636 6150",
    "sg:postcode":"92840",
    "sg:province":"CA",
    "wof:name":"J KS Outlet",
    "wof:placetype":"venue"
},
  "geometry": {"coordinates":[-117.954944,33.771447],"type":"Point"}
}