{
  "type": "Feature",
  "properties": {
    "addr:full":"199 Martha St San Jose CA 95112",
    "addr:housenumber":"199",
    "addr:postcode":"95112",
    "addr:street":"Martha St",
    "iso:country":"US",
    "sg:address":"199 Martha St",
    "sg:city":"San Jose",
    "sg:classifiers":[
        {
            "category":"Professional",
            "type":"Services"
        }
    ],
    "sg:phone":"+1 408 998 0314",
    "sg:postcode":"95112",
    "sg:province":"CA",
    "sg:tags":[
        "arts",
        "artist"
    ],
    "wof:name":"Magpie Studios",
    "wof:placetype":"venue"
},
  "geometry": {"coordinates":[-121.87713599999999,37.324205],"type":"Point"}
}