{
  "type": "Feature",
  "properties": {
    "addr:full":"1828 Golden Gate Ave San Francisco CA 94115",
    "addr:housenumber":"1828",
    "addr:postcode":"94115",
    "addr:street":"Golden Gate Ave",
    "iso:country":"US",
    "sg:address":"1828 Golden Gate Ave",
    "sg:city":"San Francisco",
    "sg:classifiers":[
        {
            "category":"Personal",
            "subcategory":"Adult",
            "type":"Services"
        }
    ],
    "sg:phone":"+1 415 749 1972",
    "sg:postcode":"94115",
    "sg:province":"CA",
    "sg:tags":[
        "escort"
    ],
    "wof:name":"Above Average Escorts",
    "wof:placetype":"venue"
},
  "geometry": {"coordinates":[-122.44150500000001,37.778434],"type":"Point"}
}