{
  "type": "Feature",
  "properties": {
    "iso:country":"US",
    "sg:address":"2588 El Camino Real Ste B",
    "sg:city":"Carlsbad",
    "sg:classifiers":[
        {
            "category":"Professional",
            "type":"Services"
        },
        {
            "category":"Restaurant",
            "type":"Food & Drink"
        },
        {
            "category":"Fast Food",
            "type":"Food & Drink"
        }
    ],
    "sg:phone":"+1 760 720 9500",
    "sg:postcode":"92008",
    "sg:province":"CA",
    "sg:tags":[
        "delivery",
        "take",
        "pizza"
    ],
    "sg:website":"http://www.pizzahut.com",
    "wof:name":"Pizza Hut",
    "wof:placetype":"venue"
},
  "geometry": {"coordinates":[-117.327003,33.177799],"type":"Point"}
}