{
  "type": "Feature",
  "properties": {
    "iso:country":"US",
    "sg:address":"5837 Camden Ave",
    "sg:city":"San Jose",
    "sg:classifiers":[
        {
            "category":"Bars & Pubs",
            "subcategory":"Sports Bar",
            "type":"Food & Drink"
        }
    ],
    "sg:phone":"+1 408 266 1431",
    "sg:postcode":"95124",
    "sg:province":"CA",
    "wof:name":"Touchdown Tommy's",
    "wof:placetype":"venue"
},
  "geometry": {"coordinates":[-121.903999,37.2314],"type":"Point"}
}