{
  "type": "Feature",
  "properties": {
    "addr:full":"6911 Santa Monica Blvd Los Angeles CA 90038",
    "addr:housenumber":"6911",
    "addr:postcode":"90038",
    "addr:street":"Santa Monica Blvd",
    "iso:country":"US",
    "sg:address":"6911 Santa Monica Blvd",
    "sg:city":"Los Angeles",
    "sg:classifiers":[
        {
            "category":"Personal",
            "type":"Services"
        }
    ],
    "sg:phone":"+1 323 465 6555",
    "sg:postcode":"90038",
    "sg:province":"CA",
    "sg:tags":[
        "towing"
    ],
    "wof:name":"Melrose Tow Service",
    "wof:placetype":"venue"
},
  "geometry": {"coordinates":[-118.34060599999999,34.090695],"type":"Point"}
}