{
  "type": "Feature",
  "properties": {
    "iso:country":"US",
    "sg:address":"251 Castro",
    "sg:city":"Mountain View",
    "sg:classifiers":[
        {
            "category":"Sports & Exercise",
            "subcategory":"Playing Field",
            "type":"Entertainment"
        }
    ],
    "sg:phone":"+1 530 637 8262",
    "sg:postcode":"94041",
    "sg:province":"CA",
    "sg:tags":[
        "instruction",
        "fitness"
    ],
    "sg:website":"www.clubberscardio.com",
    "wof:name":"Clubbers Cardio",
    "wof:placetype":"venue"
},
  "geometry": {"coordinates":[-122.078986,37.393086],"type":"Point"}
}