{
  "type": "Feature",
  "properties": {
    "addr:full":"90 E Gish Road Suite A San Jose CA 95112",
    "addr:housenumber":"90",
    "addr:postcode":"95112",
    "addr:street":"E Gish Road Suite A",
    "iso:country":"US",
    "sg:address":"90 E Gish Road Suite A",
    "sg:city":"San Jose",
    "sg:classifiers":[
        {
            "category":"Professional",
            "subcategory":"Lawyer & Legal Services",
            "type":"Services"
        }
    ],
    "sg:phone":"+1 408 573 8489",
    "sg:postcode":"95112",
    "sg:province":"CA",
    "sg:tags":[
        "notary"
    ],
    "wof:name":"Heera & Associates",
    "wof:placetype":"venue"
},
  "geometry": {"coordinates":[-121.907591,37.362839],"type":"Point"}
}