{
  "type": "Feature",
  "properties": {
    "iso:country":"US",
    "sg:address":"131 Cam Alto",
    "sg:city":"Mill Valley",
    "sg:classifiers":[
        {
            "category":"Health Services",
            "subcategory":"Doctor",
            "type":"Services"
        }
    ],
    "sg:phone":"+1 415 381 4020",
    "sg:postcode":"94941",
    "sg:province":"CA",
    "sg:tags":[
        "physician",
        "surgeon"
    ],
    "wof:name":"Teresa Black MD",
    "wof:placetype":"venue"
},
  "geometry": {"coordinates":[-122.529601,37.898765],"type":"Point"}
}