{
  "type": "Feature",
  "properties": {
    "addr:full":"1524 10th Ave San Francisco CA 94122",
    "addr:housenumber":"1524",
    "addr:postcode":"94122",
    "addr:street":"10Th Ave",
    "iso:country":"US",
    "sg:address":"1524 10th Ave",
    "sg:city":"San Francisco",
    "sg:classifiers":[
        {
            "category":"Personal",
            "subcategory":"Beauty Salon",
            "type":"Services"
        }
    ],
    "sg:phone":"+1 415 753 8008",
    "sg:postcode":"94122",
    "sg:province":"CA",
    "wof:name":"Cora's Place",
    "wof:placetype":"venue"
},
  "geometry": {"coordinates":[-122.466943,37.758859],"type":"Point"}
}