{
  "type": "Feature",
  "properties": {
    "iso:country":"US",
    "sg:address":"8876 Vintage Park Dr",
    "sg:city":"Sacramento",
    "sg:classifiers":[
        {
            "category":"Sports & Exercise",
            "subcategory":"Gym",
            "type":"Entertainment"
        }
    ],
    "sg:phone":"+1 916 688 7288",
    "sg:postcode":"95828",
    "sg:province":"CA",
    "sg:tags":[
        "club",
        "health",
        "studio",
        "gymnasium"
    ],
    "wof:name":"Curves For Women",
    "wof:placetype":"venue"
},
  "geometry": {"coordinates":[-121.372855,38.46546],"type":"Point"}
}