{
  "type": "Feature",
  "properties": {
    "addr:full":"1534 Moraga Dr Santa Rosa CA 95404",
    "addr:housenumber":"1534",
    "addr:postcode":"95404",
    "addr:street":"Moraga Dr",
    "iso:country":"US",
    "sg:address":"1534 Moraga Dr",
    "sg:city":"Santa Rosa",
    "sg:classifiers":[
        {
            "category":"Shopping",
            "subcategory":"Used Merchandise",
            "type":"Retail Goods"
        }
    ],
    "sg:phone":"+1 707 528 7047",
    "sg:postcode":"95404",
    "sg:province":"CA",
    "sg:tags":[
        "appliance"
    ],
    "wof:name":"Lloyd's Appliance",
    "wof:placetype":"venue"
},
  "geometry": {"coordinates":[-122.69998200000001,38.423418],"type":"Point"}
}