{
  "type": "Feature",
  "properties": {
    "iso:country":"US",
    "sg:address":"150 N Santa Anita Ave",
    "sg:city":"Arcadia",
    "sg:classifiers":[
        {
            "category":"Shopping",
            "subcategory":"Gifts & Souvenirs",
            "type":"Retail Goods"
        }
    ],
    "sg:phone":"+1 626 821 1898",
    "sg:postcode":"91006",
    "sg:province":"CA",
    "sg:tags":[
        "legal"
    ],
    "wof:name":"Stelow Garry E Law Office of",
    "wof:placetype":"venue"
},
  "geometry": {"coordinates":[-118.03139,34.141801],"type":"Point"}
}