{
  "type": "Feature",
  "properties": {
    "iso:country":"US",
    "sg:address":"4850 Arlington Ave",
    "sg:city":"Riverside",
    "sg:classifiers":[
        {
            "category":"Insurance",
            "subcategory":"Insurance Agent",
            "type":"Services"
        }
    ],
    "sg:phone":"+1 951 343 0382",
    "sg:postcode":"92504",
    "sg:province":"CA",
    "wof:name":"Stong Insurance Svc",
    "wof:placetype":"venue"
},
  "geometry": {"coordinates":[-117.406792,33.946111],"type":"Point"}
}