{
  "type": "Feature",
  "properties": {
    "addr:full":"4402 Summer Glen Ct Moorpark CA 93021",
    "addr:housenumber":"4402",
    "addr:postcode":"ca 93021",
    "addr:street":"Summer Glen Ct",
    "iso:country":"US",
    "sg:address":"4402 Summer Glen Ct",
    "sg:city":"Moorpark",
    "sg:classifiers":[
        {
            "category":"Wholesale",
            "subcategory":"Machinery & Supplies",
            "type":"Manufacturing & Wholesale Goods"
        }
    ],
    "sg:phone":"+1 805 517 1346",
    "sg:postcode":"93021",
    "sg:province":"CA",
    "sg:tags":[
        "equipment",
        "industrial"
    ],
    "wof:name":"Denali & Assoc",
    "wof:placetype":"venue"
},
  "geometry": {"coordinates":[-118.89484400000001,34.271838],"type":"Point"}
}