{
  "type": "Feature",
  "properties": {
    "iso:country":"US",
    "sg:address":"2137 Wembley Ln",
    "sg:city":"Corona",
    "sg:classifiers":[
        {
            "category":"Professional",
            "type":"Services"
        }
    ],
    "sg:phone":"+1 951 371 5666",
    "sg:postcode":"92881",
    "sg:province":"CA",
    "wof:name":"Frankenfind Corp",
    "wof:placetype":"venue"
},
  "geometry": {"coordinates":[-117.550113,33.852214],"type":"Point"}
}