{
  "type": "Feature",
  "properties": {
    "iso:country":"US",
    "sg:address":"1624 E Main St",
    "sg:city":"Ventura",
    "sg:classifiers":[
        {
            "category":"Health Services",
            "subcategory":"Chiropractor",
            "type":"Services"
        }
    ],
    "sg:phone":"+1 805 641 2004",
    "sg:postcode":"93001",
    "sg:province":"CA",
    "sg:tags":[
        "chiropractic"
    ],
    "sg:website":"http://www.purechiro.com",
    "wof:name":"Pure Chiropractic",
    "wof:placetype":"venue"
},
  "geometry": {"coordinates":[-119.275791,34.279415],"type":"Point"}
}