{
  "type": "Feature",
  "properties": {
    "addr:full":"5125 Harbord Dr Oakland CA 94618",
    "addr:housenumber":"5125",
    "addr:postcode":"94618",
    "addr:street":"Harbord Dr",
    "iso:country":"US",
    "sg:address":"5125 Harbord Dr",
    "sg:city":"Oakland",
    "sg:classifiers":[
        {
            "category":"Retail",
            "subcategory":"Portrait Studio",
            "type":"Services"
        }
    ],
    "sg:phone":"+1 510 652 9782",
    "sg:postcode":"94618",
    "sg:province":"CA",
    "sg:tags":[
        "photographer"
    ],
    "wof:name":"Wedding Photography By Peter",
    "wof:placetype":"venue"
},
  "geometry": {"coordinates":[-122.23031,37.838412],"type":"Point"}
}