{
  "type": "Feature",
  "properties": {
    "iso:country":"US",
    "sg:address":"550 Silver Spur Rd Ste 230",
    "sg:city":"Rancho Palos Verdes",
    "sg:classifiers":[
        {
            "category":"Sports & Exercise",
            "subcategory":"Gym",
            "type":"Entertainment"
        },
        {
            "category":"Health Services",
            "subcategory":"Health Practitioner",
            "type":"Services"
        }
    ],
    "sg:phone":"+1 310 544 4575",
    "sg:postcode":"90275",
    "sg:province":"CA",
    "sg:tags":[
        "pilate",
        "therapy",
        "physical"
    ],
    "wof:name":"Evolve Rehabilitation and Pilates",
    "wof:placetype":"venue"
},
  "geometry": {"coordinates":[-118.36993,33.772222],"type":"Point"}
}