{
  "type": "Feature",
  "properties": {
    "addr:full":"23608 El Toro Rd Lake Forest CA 92630",
    "addr:housenumber":"23608",
    "addr:postcode":"92630",
    "addr:street":"El Toro Rd",
    "iso:country":"US",
    "sg:address":"23608 El Toro Rd",
    "sg:city":"Lake Forest",
    "sg:classifiers":[
        {
            "category":"Shopping",
            "subcategory":"Discount & Variety Stores",
            "type":"Retail Goods"
        }
    ],
    "sg:phone":"+1 949 588 9401",
    "sg:postcode":"92630",
    "sg:province":"CA",
    "sg:tags":[
        "outlet"
    ],
    "wof:name":"Buy Rite Outlet",
    "wof:placetype":"venue"
},
  "geometry": {"coordinates":[-117.701716,33.619201],"type":"Point"}
}