{
  "type": "Feature",
  "properties": {
    "iso:country":"US",
    "sg:address":"3207 Los Feliz Blvd",
    "sg:city":"Los Angeles",
    "sg:classifiers":[
        {
            "category":"Sports & Exercise",
            "subcategory":"Golf",
            "type":"Entertainment"
        }
    ],
    "sg:phone":"+1 323 663 7758",
    "sg:postcode":"90039",
    "sg:province":"CA",
    "sg:website":"www.golflink.com/golf-courses/go...",
    "wof:name":"Los Feliz Municipal Golf Course",
    "wof:placetype":"venue"
},
  "geometry": {"coordinates":[-118.269345,34.123056],"type":"Point"}
}