{
  "type": "Feature",
  "properties": {
    "addr:full":"6400 Canoga Ave Woodland Hills CA 91367",
    "addr:housenumber":"6400",
    "addr:postcode":"91367",
    "addr:street":"Canoga Ave",
    "iso:country":"US",
    "sg:address":"6400 Canoga Ave",
    "sg:city":"Woodland Hills",
    "sg:classifiers":[
        {
            "category":"Professional",
            "subcategory":"Lawyer & Legal Services",
            "type":"Services"
        }
    ],
    "sg:phone":"+1 818 222 2810",
    "sg:postcode":"91367",
    "sg:province":"CA",
    "wof:name":"Lyden C Christine Law Offices of",
    "wof:placetype":"venue"
},
  "geometry": {"coordinates":[-118.59733799999999,34.186565],"type":"Point"}
}