{
  "type": "Feature",
  "properties": {
    "iso:country":"US",
    "sg:address":"2738 W Ave M",
    "sg:city":"Palmdale",
    "sg:classifiers":[
        {
            "category":"Building & Trades",
            "subcategory":"Construction",
            "type":"Services"
        }
    ],
    "sg:phone":"+1 661 722 4477",
    "sg:postcode":"93551",
    "sg:province":"CA",
    "sg:tags":[
        "builder",
        "patio",
        "deck"
    ],
    "wof:name":"Bench Mark Builders",
    "wof:placetype":"venue"
},
  "geometry": {"coordinates":[-118.179136,34.645639],"type":"Point"}
}