{
  "type": "Feature",
  "properties": {
    "iso:country":"US",
    "sg:address":"7309 Hannum Ave",
    "sg:city":"Culver City",
    "sg:classifiers":[
        {
            "category":"Landmark",
            "subcategory":"Tourist Information",
            "type":"Public Place"
        }
    ],
    "sg:phone":"+1 310 842 8818",
    "sg:postcode":"90230",
    "sg:province":"CA",
    "sg:tags":[
        "tour"
    ],
    "wof:name":"City Tours U S A",
    "wof:placetype":"venue"
},
  "geometry": {"coordinates":[-118.389,33.987],"type":"Point"}
}