{
  "type": "Feature",
  "properties": {
    "iso:country":"US",
    "sg:address":"3250 E Gage Ave",
    "sg:city":"Huntington Park",
    "sg:classifiers":[
        {
            "category":"Autos & Motor Vehicles",
            "subcategory":"Motorcycle Sales",
            "type":"Retail Goods"
        }
    ],
    "sg:phone":"+1 323 581 7113",
    "sg:postcode":"90255",
    "sg:province":"CA",
    "sg:tags":[
        "industrial",
        "machinery",
        "mfg"
    ],
    "wof:name":"All Motorcycles",
    "wof:placetype":"venue"
},
  "geometry": {"coordinates":[-118.209309,33.980313],"type":"Point"}
}