{
  "type": "Feature",
  "properties": {
    "iso:country":"US",
    "sg:address":"17025 Condit Rd",
    "sg:city":"Morgan Hill",
    "sg:classifiers":[
        {
            "category":"Restaurant",
            "type":"Food & Drink"
        }
    ],
    "sg:menulink":"http://www.allmenus.com/ca/san-jose/216090-mcdonalds/menu/",
    "sg:postcode":"95037",
    "sg:province":"CA",
    "sg:tags":[
        "burger",
        "american"
    ],
    "wof:name":"McDonald's",
    "wof:placetype":"venue"
},
  "geometry": {"coordinates":[-121.631272,37.133225],"type":"Point"}
}