{
  "type": "Feature",
  "properties": {
    "iso:country":"US",
    "sg:address":"7139 Katella Ave",
    "sg:city":"Stanton",
    "sg:classifiers":[
        {
            "category":"Wholesale",
            "subcategory":"Home Furnishings",
            "type":"Manufacturing & Wholesale Goods"
        }
    ],
    "sg:phone":"+1 714 236 3660",
    "sg:postcode":"90680",
    "sg:province":"CA",
    "wof:name":"South Coast Installations",
    "wof:placetype":"venue"
},
  "geometry": {"coordinates":[-118.009947,33.803007],"type":"Point"}
}