{
  "type": "Feature",
  "properties": {
    "addr:full":"1439 W Chapman Ave Orange CA 92868",
    "addr:housenumber":"1439",
    "addr:postcode":"92868",
    "addr:street":"W Chapman Ave",
    "iso:country":"US",
    "sg:address":"1439 W Chapman Ave",
    "sg:city":"Orange",
    "sg:classifiers":[
        {
            "category":"Professional",
            "subcategory":"Lawyer & Legal Services",
            "type":"Services"
        }
    ],
    "sg:phone":"+1 714 634 0777",
    "sg:postcode":"92868",
    "sg:province":"CA",
    "sg:tags":[
        "notary"
    ],
    "wof:name":"The Ups Store",
    "wof:placetype":"venue"
},
  "geometry": {"coordinates":[-117.86693200000001,33.787907],"type":"Point"}
}