{
  "type": "Feature",
  "properties": {
    "addr:full":"103 Cabrillo St San Francisco CA 94118",
    "addr:housenumber":"103",
    "addr:postcode":"94118",
    "addr:street":"Cabrillo St",
    "iso:country":"US",
    "sg:address":"103 Cabrillo St",
    "sg:city":"San Francisco",
    "sg:classifiers":[
        {
            "category":"Building & Trades",
            "subcategory":"Plumbing",
            "type":"Services"
        }
    ],
    "sg:phone":"+1 415 668 6918",
    "sg:postcode":"94118",
    "sg:province":"CA",
    "sg:tags":[
        "contractor"
    ],
    "wof:name":"Yims Refrigeration San Fr",
    "wof:placetype":"venue"
},
  "geometry": {"coordinates":[-122.460639,37.775443],"type":"Point"}
}