{
  "type": "Feature",
  "properties": {
    "addr:full":"714 Otis Ave Corcoran CA 93212",
    "addr:housenumber":"714",
    "addr:postcode":"93212",
    "addr:street":"Otis Ave",
    "iso:country":"US",
    "sg:address":"714 Otis Ave",
    "sg:city":"Corcoran",
    "sg:classifiers":[
        {
            "category":"Manufacturing",
            "subcategory":"Glass & Minerals",
            "type":"Manufacturing & Wholesale Goods"
        }
    ],
    "sg:phone":"+1 559 992 4197",
    "sg:postcode":"93212",
    "sg:province":"CA",
    "sg:tags":[
        "product",
        "gypsum"
    ],
    "wof:name":"Gene Daniel",
    "wof:placetype":"venue"
},
  "geometry": {"coordinates":[-119.56083599999999,36.103216],"type":"Point"}
}