{
  "type": "Feature",
  "properties": {
    "addr:full":"130 N Santa Cruz Ave Los Gatos CA 95030",
    "addr:housenumber":"130",
    "addr:postcode":"95030",
    "addr:street":"N Santa Cruz Ave",
    "iso:country":"US",
    "sg:address":"130 N Santa Cruz Ave",
    "sg:city":"Los Gatos",
    "sg:classifiers":[
        {
            "category":"Shopping",
            "subcategory":"Clothing, Apparel, & Fashions",
            "type":"Retail Goods"
        }
    ],
    "sg:phone":"+1 408 354 0069",
    "sg:postcode":"95030",
    "sg:province":"CA",
    "sg:tags":[
        "accessory",
        "clothing",
        "women's"
    ],
    "wof:name":"Alta Fine Contemporary Clothing",
    "wof:placetype":"venue"
},
  "geometry": {"coordinates":[-121.982483,37.225167],"type":"Point"}
}