{
  "type": "Feature",
  "properties": {
    "iso:country":"US",
    "sg:address":"3416 Meadowview Dr",
    "sg:city":"Riverside",
    "sg:classifiers":[
        {
            "category":"Travel",
            "subcategory":"Travel Agent",
            "type":"Entertainment"
        }
    ],
    "sg:phone":"+1 951 737 4698",
    "sg:postcode":"92503",
    "sg:province":"CA",
    "sg:tags":[
        "operator",
        "tour"
    ],
    "wof:name":"Am PM Intl Shuttle Service",
    "wof:placetype":"venue"
},
  "geometry": {"coordinates":[-117.499674,33.883336],"type":"Point"}
}