{
  "type": "Feature",
  "properties": {
    "iso:country":"US",
    "sg:address":"625 S Bixel St",
    "sg:city":"Los Angeles",
    "sg:classifiers":[
        {
            "category":"Autos & Motor Vehicles",
            "subcategory":"Automobile Sales",
            "type":"Retail Goods"
        }
    ],
    "sg:phone":"+1 213 482 1900",
    "sg:postcode":"90017",
    "sg:province":"CA",
    "sg:tags":[
        "car",
        "dealer"
    ],
    "wof:name":"Car Rack Auto Sales",
    "wof:placetype":"venue"
},
  "geometry": {"coordinates":[-118.26298800000001,34.053089],"type":"Point"}
}