{
  "type": "Feature",
  "properties": {
    "addr:full":"9338 Reseda Blvd Northridge CA 91324",
    "addr:housenumber":"9338",
    "addr:postcode":"91324",
    "addr:street":"Reseda Blvd",
    "iso:country":"US",
    "sg:address":"9338 Reseda Blvd",
    "sg:city":"Northridge",
    "sg:classifiers":[
        {
            "category":"Real Estate",
            "subcategory":"Real Estate Agent",
            "type":"Services"
        }
    ],
    "sg:phone":"+1 818 886 4598",
    "sg:postcode":"91324",
    "sg:province":"CA",
    "wof:name":"Encore Escrow Corp",
    "wof:placetype":"venue"
},
  "geometry": {"coordinates":[-118.536013,34.240232],"type":"Point"}
}