{
  "type": "Feature",
  "properties": {
    "addr:full":"1524 W Chapman Ave Orange CA 92868",
    "addr:housenumber":"1524",
    "addr:postcode":"92868",
    "addr:street":"W Chapman Ave",
    "iso:country":"US",
    "sg:address":"1524 W Chapman Ave",
    "sg:city":"Orange",
    "sg:classifiers":[
        {
            "category":"Shopping",
            "subcategory":"Pets & Pet Supplies",
            "type":"Retail Goods"
        }
    ],
    "sg:phone":"+1 714 634 0666",
    "sg:postcode":"92868",
    "sg:province":"CA",
    "sg:tags":[
        "store"
    ],
    "wof:name":"Sircol Pets",
    "wof:placetype":"venue"
},
  "geometry": {"coordinates":[-117.86799600000001,33.787998],"type":"Point"}
}