{
  "type": "Feature",
  "properties": {
    "iso:country":"US",
    "sg:address":"9900 Lakewood Blvd",
    "sg:city":"Downey",
    "sg:classifiers":[
        {
            "category":"Professional",
            "type":"Services"
        }
    ],
    "sg:phone":"+1 562 622 7781",
    "sg:postcode":"90240",
    "sg:province":"CA",
    "wof:name":"Vallayta Finance & Reality Hom",
    "wof:placetype":"venue"
},
  "geometry": {"coordinates":[-118.115934,33.949544],"type":"Point"}
}