{
  "type": "Feature",
  "properties": {
    "iso:country":"US",
    "sg:address":"845 E State Hwy 88",
    "sg:city":"Jackson",
    "sg:classifiers":[
        {
            "category":"Education",
            "subcategory":"Special Training",
            "type":"Public Place"
        }
    ],
    "sg:phone":"+1 209 223 1924",
    "sg:postcode":"95642",
    "sg:province":"CA",
    "sg:tags":[
        "instruction",
        "driving"
    ],
    "wof:name":"Gold Country Driving School",
    "wof:placetype":"venue"
},
  "geometry": {"coordinates":[-120.766398,38.35206],"type":"Point"}
}