{
  "type": "Feature",
  "properties": {
    "iso:country":"US",
    "sg:address":"23431 Golden Springs Dr",
    "sg:city":"Diamond Bar",
    "sg:classifiers":[
        {
            "category":"Social Services",
            "subcategory":"Child Care",
            "type":"Services"
        }
    ],
    "sg:phone":"+1 909 860 4001",
    "sg:postcode":"91765",
    "sg:province":"CA",
    "sg:tags":[
        "kindergarten",
        "academic",
        "school"
    ],
    "wof:name":"Village Montessori Academy",
    "wof:placetype":"venue"
},
  "geometry": {"coordinates":[-117.810041,34.01817],"type":"Point"}
}