{
  "type": "Feature",
  "properties": {
    "iso:country":"US",
    "sg:address":"980 9th St",
    "sg:city":"Sacramento",
    "sg:classifiers":[
        {
            "category":"Government",
            "subcategory":"Office",
            "type":"Public Place"
        }
    ],
    "sg:phone":"+1 916 323 5400",
    "sg:postcode":"95814",
    "sg:province":"CA",
    "sg:tags":[
        "administration",
        "housing",
        "transportation",
        "pro",
        "business"
    ],
    "wof:name":"Business Trnsp Hsing Agcy SEC",
    "wof:placetype":"venue"
},
  "geometry": {"coordinates":[-121.494581,38.581584],"type":"Point"}
}