{
  "type": "Feature",
  "properties": {
    "addr:full":"509 E 16th St Los Angeles CA 90015",
    "addr:housenumber":"509",
    "addr:postcode":"90015",
    "addr:street":"E 16Th St",
    "iso:country":"US",
    "sg:address":"509 E 16th St",
    "sg:city":"Los Angeles",
    "sg:classifiers":[
        {
            "category":"Manufacturing",
            "subcategory":"Apparel",
            "type":"Manufacturing & Wholesale Goods"
        }
    ],
    "sg:phone":"+1 213 748 2985",
    "sg:postcode":"90015",
    "sg:province":"CA",
    "sg:tags":[
        "manufacturer"
    ],
    "wof:name":"Flamingo Fashion",
    "wof:placetype":"venue"
},
  "geometry": {"coordinates":[-118.257912,34.031127],"type":"Point"}
}