{
  "type": "Feature",
  "properties": {
    "addr:full":"600 S. San Vicente Bvd # D Los Angeles CA 90048",
    "addr:housenumber":"600",
    "addr:postcode":"90048",
    "addr:street":"S. San Vicente Bvd # D",
    "iso:country":"US",
    "sg:address":"600 S. San Vicente Bvd # D",
    "sg:city":"Los Angeles",
    "sg:classifiers":[
        {
            "category":"Health Services",
            "subcategory":"Clinic",
            "type":"Services"
        }
    ],
    "sg:phone":"+1 310 922 6822",
    "sg:postcode":"90048",
    "sg:province":"CA",
    "sg:tags":[
        "counseling",
        "mental"
    ],
    "wof:name":"Arlene Krantz Hypnotherapist",
    "wof:placetype":"venue"
},
  "geometry": {"coordinates":[-118.37298800000001,34.065734],"type":"Point"}
}