{
  "type": "Feature",
  "properties": {
    "iso:country":"US",
    "sg:address":"1 Caryl Dr",
    "sg:city":"Oxnard",
    "sg:classifiers":[
        {
            "category":"Farming",
            "subcategory":"Orchard",
            "type":"Manufacturing & Wholesale Goods"
        }
    ],
    "sg:phone":"+1 805 488 5333",
    "sg:postcode":"93033",
    "sg:province":"CA",
    "sg:tags":[
        "citrus",
        "vegetable",
        "ranch",
        "farm",
        "cattle"
    ],
    "wof:name":"Rancho Guadalasca",
    "wof:placetype":"venue"
},
  "geometry": {"coordinates":[-119.071938,34.126506],"type":"Point"}
}