{
  "type": "Feature",
  "properties": {
    "iso:country":"US",
    "sg:address":"2234 Babette Way",
    "sg:city":"Sacramento",
    "sg:classifiers":[
        {
            "category":"Building & Trades",
            "subcategory":"Landscaping Services",
            "type":"Services"
        }
    ],
    "sg:phone":"+1 916 665 2825",
    "sg:postcode":"95832",
    "sg:province":"CA",
    "wof:name":"Granados Gardener",
    "wof:placetype":"venue"
},
  "geometry": {"coordinates":[-121.48599900000001,38.480158],"type":"Point"}
}