{
  "type": "Feature",
  "properties": {
    "addr:full":"352 Main St Loleta CA 95551",
    "addr:housenumber":"352",
    "addr:postcode":"95551",
    "addr:street":"Main St",
    "iso:country":"US",
    "sg:address":"352 Main St",
    "sg:city":"Loleta",
    "sg:classifiers":[
        {
            "category":"Food & Beverages",
            "subcategory":"Groceries & Convenience Stores",
            "type":"Retail Goods"
        }
    ],
    "sg:phone":"+1 707 733 5776",
    "sg:postcode":"95551",
    "sg:province":"CA",
    "sg:tags":[
        "grocer"
    ],
    "wof:name":"Loleta Grocery",
    "wof:placetype":"venue"
},
  "geometry": {"coordinates":[-124.224887,40.640309],"type":"Point"}
}