{
  "type": "Feature",
  "properties": {
    "iso:country":"US",
    "sg:address":"1410 Park Ave",
    "sg:city":"Alameda",
    "sg:classifiers":[
        {
            "category":"Professional",
            "subcategory":"Art Services",
            "type":"Services"
        },
        {
            "category":"Communications",
            "type":"Services"
        }
    ],
    "sg:phone":"+1 510 865 9378",
    "sg:postcode":"94501",
    "sg:province":"CA",
    "sg:tags":[
        "web",
        "graphic",
        "design"
    ],
    "sg:website":"www.westadvertising.com",
    "wof:name":"West Advertising",
    "wof:placetype":"venue"
},
  "geometry": {"coordinates":[-122.24158799999999,37.764142],"type":"Point"}
}