{
  "type": "Feature",
  "properties": {
    "iso:country":"US",
    "sg:address":"15800 Hawthorne Boulevard Suite B",
    "sg:city":"Lawndale",
    "sg:classifiers":[
        {
            "category":"Professional",
            "subcategory":"Computer Services",
            "type":"Services"
        }
    ],
    "sg:phone":"+1 310 542 4741",
    "sg:postcode":"90260",
    "sg:province":"CA",
    "sg:tags":[
        "stereo",
        "installation"
    ],
    "wof:name":"New Wave Sound",
    "wof:placetype":"venue"
},
  "geometry": {"coordinates":[-118.352363,33.887309],"type":"Point"}
}