{
  "type": "Feature",
  "properties": {
    "iso:country":"US",
    "sg:address":"46 McKenzie Ct",
    "sg:city":"Auburn",
    "sg:classifiers":[
        {
            "category":"Professional",
            "subcategory":"Business Services",
            "type":"Services"
        }
    ],
    "sg:phone":"+1 530 823 8456",
    "sg:postcode":"95603",
    "sg:province":"CA",
    "wof:name":"First American Documents",
    "wof:placetype":"venue"
},
  "geometry": {"coordinates":[-121.075211,38.903354],"type":"Point"}
}