{
  "type": "Feature",
  "properties": {
    "addr:full":"20578 Crow Creek Rd Castro Valley CA 94552",
    "addr:housenumber":"20578",
    "addr:postcode":"94552",
    "addr:street":"Crow Creek Rd",
    "iso:country":"US",
    "sg:address":"20578 Crow Creek Rd",
    "sg:city":"Castro Valley",
    "sg:classifiers":[
        {
            "category":"Banks & Credit Unions",
            "subcategory":"Bank",
            "type":"Services"
        }
    ],
    "sg:phone":"+1 510 881 2706",
    "sg:postcode":"94552",
    "sg:province":"CA",
    "sg:tags":[
        "escrow"
    ],
    "wof:name":"J P James Inc",
    "wof:placetype":"venue"
},
  "geometry": {"coordinates":[-122.050206,37.70202],"type":"Point"}
}