{
  "type": "Feature",
  "properties": {
    "addr:full":"439 Broadway Millbrae CA 94030",
    "addr:housenumber":"439",
    "addr:postcode":"94030",
    "addr:street":"Broadway",
    "iso:country":"US",
    "sg:address":"439 Broadway",
    "sg:city":"Millbrae",
    "sg:classifiers":[
        {
            "category":"Professional",
            "subcategory":"Art Services",
            "type":"Services"
        }
    ],
    "sg:phone":"+1 650 259 9168",
    "sg:postcode":"94030",
    "sg:province":"CA",
    "sg:tags":[
        "photographer"
    ],
    "sg:website":"www.sftaipeiwedding.us",
    "wof:name":"San Francisco Taipei Wedding Gifts and Accessories",
    "wof:placetype":"venue"
},
  "geometry": {"coordinates":[-122.393342,37.602002],"type":"Point"}
}