{
  "type": "Feature",
  "properties": {
    "iso:country":"US",
    "sg:address":"2665 Clarendon Avenue",
    "sg:city":"Huntington Park",
    "sg:classifiers":[
        {
            "category":"Education",
            "subcategory":"School",
            "type":"Public Place"
        },
        {
            "category":"Organizations",
            "subcategory":"Religious Organization",
            "type":"Services"
        }
    ],
    "sg:phone":"+1 323 585 3167",
    "sg:postcode":"90255",
    "sg:province":"CA",
    "sg:tags":[
        "high",
        "middle",
        "elementary"
    ],
    "wof:name":"Maywood Christian School",
    "wof:placetype":"venue"
},
  "geometry": {"coordinates":[-118.22364899999999,33.983689],"type":"Point"}
}