{
  "type": "Feature",
  "properties": {
    "iso:country":"US",
    "sg:address":"33 Creek Rd Side",
    "sg:city":"Irvine",
    "sg:classifiers":[
        {
            "category":"Travel",
            "subcategory":"Hotels & Motels",
            "type":"Entertainment"
        }
    ],
    "sg:phone":"+1 949 786 5665",
    "sg:postcode":"92604",
    "sg:province":"CA",
    "wof:name":"Arv Golden Creek Inn",
    "wof:placetype":"venue"
},
  "geometry": {"coordinates":[-117.797997,33.6754],"type":"Point"}
}