{
  "type": "Feature",
  "properties": {
    "addr:full":"24721 1st St Weed CA 96094",
    "addr:housenumber":"24721",
    "addr:postcode":"96094",
    "addr:street":"1St St",
    "iso:country":"US",
    "sg:address":"24721 1st St",
    "sg:city":"Weed",
    "sg:classifiers":[
        {
            "category":"Manufacturing",
            "subcategory":"Signs",
            "type":"Manufacturing & Wholesale Goods"
        }
    ],
    "sg:phone":"+1 530 938 4591",
    "sg:postcode":"96094",
    "sg:province":"CA",
    "wof:name":"Signs Of Life",
    "wof:placetype":"venue"
},
  "geometry": {"coordinates":[-122.43093500000001,41.457086],"type":"Point"}
}