{
  "type": "Feature",
  "properties": {
    "iso:country":"US",
    "sg:address":"579 Orange Ave",
    "sg:city":"Coronado",
    "sg:classifiers":[
        {
            "category":"Travel",
            "subcategory":"Travel Agent",
            "type":"Entertainment"
        }
    ],
    "sg:phone":"+1 619 435 0011",
    "sg:postcode":"92118",
    "sg:province":"CA",
    "sg:tags":[
        "agency",
        "bureau"
    ],
    "wof:name":"Coronado Travel Group Inc",
    "wof:placetype":"venue"
},
  "geometry": {"coordinates":[-117.175852,32.692716],"type":"Point"}
}