{
  "type": "Feature",
  "properties": {
    "iso:country":"US",
    "sg:address":"1727 Buena Vista St",
    "sg:city":"Duarte",
    "sg:classifiers":[
        {
            "category":"Professional",
            "subcategory":"Business Services",
            "type":"Services"
        }
    ],
    "sg:phone":"+1 626 301 1433",
    "sg:postcode":"91010",
    "sg:province":"CA",
    "sg:website":"www.fiestaparadefloats.com",
    "wof:name":"Fiesta Parade Floats",
    "wof:placetype":"venue"
},
  "geometry": {"coordinates":[-117.97762400000001,34.132532],"type":"Point"}
}