{
  "type": "Feature",
  "properties": {
    "addr:full":"1616 Pacific Ave San Francisco CA 94109",
    "addr:housenumber":"1616",
    "addr:postcode":"94109",
    "addr:street":"Pacific Ave",
    "iso:country":"US",
    "sg:address":"1616 Pacific Ave",
    "sg:city":"San Francisco",
    "sg:classifiers":[
        {
            "category":"Personal",
            "type":"Services"
        },
        {
            "category":"Building & Trades",
            "subcategory":"Construction",
            "type":"Services"
        }
    ],
    "sg:phone":"+1 415 474 3652",
    "sg:postcode":"94109",
    "sg:province":"CA",
    "sg:tags":[
        "interior",
        "local",
        "design"
    ],
    "sg:website":"www.starglassco.net",
    "wof:name":"Star Glass Company",
    "wof:placetype":"venue"
},
  "geometry": {"coordinates":[-122.421955,37.795015],"type":"Point"}
}