{
  "type": "Feature",
  "properties": {
    "addr:full":"210 Calderon Avenue Mountain View CA 94041",
    "addr:housenumber":"210",
    "addr:postcode":"94041",
    "addr:street":"Calderon Avenue",
    "iso:country":"US",
    "sg:address":"210 Calderon Avenue",
    "sg:city":"Mountain View",
    "sg:classifiers":[
        {
            "category":"Real Estate",
            "subcategory":"Real Estate Operator",
            "type":"Services"
        }
    ],
    "sg:phone":"+1 650 961 3370",
    "sg:postcode":"94041",
    "sg:province":"CA",
    "sg:tags":[
        "apartment"
    ],
    "wof:name":"Glenwood Apartments",
    "wof:placetype":"venue"
},
  "geometry": {"coordinates":[-122.072356,37.390556],"type":"Point"}
}