{
  "type": "Feature",
  "properties": {
    "addr:full":"181 Sherland Ave Mountain View CA 94043",
    "addr:housenumber":"181",
    "addr:postcode":"94043",
    "addr:street":"Sherland Ave",
    "iso:country":"US",
    "sg:address":"181 Sherland Ave",
    "sg:city":"Mountain View",
    "sg:classifiers":[
        {
            "category":"Professional",
            "subcategory":"Management & Consulting",
            "type":"Services"
        }
    ],
    "sg:phone":"+1 650 938 8190",
    "sg:postcode":"94043",
    "sg:province":"CA",
    "wof:name":"View Point Solutions Inc",
    "wof:placetype":"venue"
},
  "geometry": {"coordinates":[-122.059822,37.399759],"type":"Point"}
}