{
  "type": "Feature",
  "properties": {
    "addr:full":"443 San Benito St Hollister CA 95023",
    "addr:housenumber":"443",
    "addr:postcode":"hollister ca 95023",
    "addr:street":"San Benito St",
    "iso:country":"US",
    "sg:address":"443 San Benito St",
    "sg:city":"Hollister",
    "sg:classifiers":[
        {
            "category":"Professional",
            "type":"Services"
        }
    ],
    "sg:phone":"+1 831 630 9098",
    "sg:postcode":"95023",
    "sg:province":"CA",
    "wof:name":"Big Secrets",
    "wof:placetype":"venue"
},
  "geometry": {"coordinates":[-121.40196,36.852124],"type":"Point"}
}