{
  "type": "Feature",
  "properties": {
    "addr:full":"14151 Summit Crst Escondido CA 92025",
    "addr:housenumber":"14151",
    "addr:postcode":"92025",
    "addr:street":"Summit Crst",
    "iso:country":"US",
    "sg:address":"14151 Summit Crst",
    "sg:city":"Escondido",
    "sg:classifiers":[
        {
            "category":"Professional",
            "type":"Services"
        }
    ],
    "sg:phone":"+1 760 839 2125",
    "sg:postcode":"92025",
    "sg:province":"CA",
    "wof:name":"Telling Corporation",
    "wof:placetype":"venue"
},
  "geometry": {"coordinates":[-117.028385,33.091099],"type":"Point"}
}