{
  "type": "Feature",
  "properties": {
    "iso:country":"US",
    "sg:address":"11605 Goldring Rd",
    "sg:city":"Arcadia",
    "sg:classifiers":[
        {
            "category":"Home & Garden",
            "subcategory":"Building Materials",
            "type":"Retail Goods"
        }
    ],
    "sg:phone":"+1 626 444 0343",
    "sg:postcode":"91006",
    "sg:province":"CA",
    "sg:tags":[
        "glass",
        "window",
        "plate"
    ],
    "wof:name":"Bourret Glass & Upholstery",
    "wof:placetype":"venue"
},
  "geometry": {"coordinates":[-118.005393,34.100556],"type":"Point"}
}