{
  "type": "Feature",
  "properties": {
    "addr:full":"11808 Greenstone Ave Santa Fe Springs CA 90670",
    "addr:housenumber":"11808",
    "addr:postcode":"90670",
    "addr:street":"Greenstone Ave",
    "iso:country":"US",
    "sg:address":"11808 Greenstone Ave",
    "sg:city":"Santa Fe Springs",
    "sg:classifiers":[
        {
            "category":"Building & Trades",
            "subcategory":"Plumbing",
            "type":"Services"
        }
    ],
    "sg:phone":"+1 562 941 9994",
    "sg:postcode":"90670",
    "sg:province":"CA",
    "sg:tags":[
        "plumbing",
        "contractor"
    ],
    "wof:name":"Chuck's Rooter & Plumbing Inc",
    "wof:placetype":"venue"
},
  "geometry": {"coordinates":[-118.057993,33.920774],"type":"Point"}
}