{
  "type": "Feature",
  "properties": {
    "addr:full":"2310 Byron Pl Carlsbad CA 92008",
    "addr:housenumber":"2310",
    "addr:postcode":"92008",
    "addr:street":"Byron Pl",
    "iso:country":"US",
    "sg:address":"2310 Byron Pl",
    "sg:city":"Carlsbad",
    "sg:classifiers":[
        {
            "category":"Professional",
            "subcategory":"Research",
            "type":"Services"
        }
    ],
    "sg:phone":"+1 760 438 3663",
    "sg:postcode":"92008",
    "sg:province":"CA",
    "sg:tags":[
        "development",
        "marketing",
        "product"
    ],
    "wof:name":"RNR Partners",
    "wof:placetype":"venue"
},
  "geometry": {"coordinates":[-117.29311800000001,33.143886],"type":"Point"}
}