{
  "type": "Feature",
  "properties": {
    "iso:country":"US",
    "sg:address":"334 Sunfish Ct",
    "sg:city":"Foster City",
    "sg:classifiers":[
        {
            "category":"Real Estate",
            "subcategory":"Real Estate Agent",
            "type":"Services"
        }
    ],
    "sg:phone":"+1 650 345 7027",
    "sg:postcode":"94404",
    "sg:province":"CA",
    "wof:name":"Reeve Realty Cashin Co",
    "wof:placetype":"venue"
},
  "geometry": {"coordinates":[-122.252863,37.55617],"type":"Point"}
}