{
  "type": "Feature",
  "properties": {
    "addr:full":"1626 Quincy St Delano CA 93215",
    "addr:housenumber":"1626",
    "addr:postcode":"93215",
    "addr:street":"Quincy St",
    "iso:country":"US",
    "sg:address":"1626 Quincy St",
    "sg:city":"Delano",
    "sg:classifiers":[
        {
            "category":"Professional",
            "subcategory":"Art Services",
            "type":"Services"
        }
    ],
    "sg:phone":"+1 661 839 2041",
    "sg:postcode":"93215",
    "sg:province":"CA",
    "sg:tags":[
        "designer",
        "display",
        "producer"
    ],
    "wof:name":"Sylvia's Designs",
    "wof:placetype":"venue"
},
  "geometry": {"coordinates":[-119.23426000000001,35.776758],"type":"Point"}
}