{
  "type": "Feature",
  "properties": {
    "iso:country":"US",
    "sg:address":"10120 Main St",
    "sg:city":"Lamont",
    "sg:classifiers":[
        {
            "category":"Shopping",
            "subcategory":"Clothing, Apparel, & Fashions",
            "type":"Retail Goods"
        }
    ],
    "sg:phone":"+1 661 845 9452",
    "sg:postcode":"93241",
    "sg:province":"CA",
    "wof:name":"Di Vas Fashion",
    "wof:placetype":"venue"
},
  "geometry": {"coordinates":[-118.91446999999999,35.263575],"type":"Point"}
}