{
  "type": "Feature",
  "properties": {
    "addr:full":"41619 Big Bear Blvd Big Bear Lake CA 92315",
    "addr:housenumber":"41619",
    "addr:postcode":"92315",
    "addr:street":"Big Bear Blvd",
    "iso:country":"US",
    "sg:address":"41619 Big Bear Blvd",
    "sg:city":"Big Bear Lake",
    "sg:classifiers":[
        {
            "category":"Health Services",
            "subcategory":"Clinic",
            "type":"Services"
        }
    ],
    "sg:phone":"+1 909 866 4323",
    "sg:postcode":"92315",
    "sg:province":"CA",
    "sg:tags":[
        "home",
        "care"
    ],
    "wof:name":"Rim Of The World Home Health",
    "wof:placetype":"venue"
},
  "geometry": {"coordinates":[-116.894141,34.243367],"type":"Point"}
}