{
  "type": "Feature",
  "properties": {
    "addr:full":"3717 Mt Diablo Blvd Lafayette CA 94549",
    "addr:housenumber":"3717",
    "addr:postcode":"94549",
    "addr:street":"Mt Diablo Blvd",
    "iso:country":"US",
    "sg:address":"3717 Mt Diablo Blvd",
    "sg:city":"Lafayette",
    "sg:classifiers":[
        {
            "category":"Professional",
            "subcategory":"Lawyer & Legal Services",
            "type":"Services"
        }
    ],
    "sg:phone":"+1 925 299 3000",
    "sg:postcode":"94549",
    "sg:province":"CA",
    "sg:tags":[
        "attorney"
    ],
    "wof:name":"J Gregg Riehl Law Offices",
    "wof:placetype":"venue"
},
  "geometry": {"coordinates":[-122.132698,37.888898],"type":"Point"}
}