{
  "type": "Feature",
  "properties": {
    "addr:full":"3560 J St Sacramento CA 95816",
    "addr:housenumber":"3560",
    "addr:postcode":"95816",
    "addr:street":"J St",
    "iso:country":"US",
    "sg:address":"3560 J St",
    "sg:city":"Sacramento",
    "sg:classifiers":[
        {
            "category":"Health Services",
            "subcategory":"Health Practitioner",
            "type":"Services"
        }
    ],
    "sg:phone":"+1 916 451 6678",
    "sg:postcode":"95816",
    "sg:province":"CA",
    "sg:tags":[
        "psychotherapist"
    ],
    "wof:name":"Sheila Hirsch",
    "wof:placetype":"venue"
},
  "geometry": {"coordinates":[-121.458491,38.570918],"type":"Point"}
}