{
  "type": "Feature",
  "properties": {
    "iso:country":"US",
    "sg:address":"2743 Mansfield Dr",
    "sg:city":"Burbank",
    "sg:classifiers":[
        {
            "category":"Communications",
            "subcategory":"Film & Video Production",
            "type":"Services"
        }
    ],
    "sg:phone":"+1 818 567 0483",
    "sg:postcode":"91504",
    "sg:province":"CA",
    "sg:tags":[
        "motion"
    ],
    "wof:name":"Grover Lee Productions",
    "wof:placetype":"venue"
},
  "geometry": {"coordinates":[-118.327598,34.205912],"type":"Point"}
}