{
  "type": "Feature",
  "properties": {
    "addr:full":"19170 Hidden Valley Rd Middletown CA 95467",
    "addr:housenumber":"19170",
    "addr:postcode":"95467",
    "addr:street":"Hidden Valley Rd",
    "iso:country":"US",
    "sg:address":"19170 Hidden Valley Rd",
    "sg:city":"Middletown",
    "sg:classifiers":[
        {
            "category":"Wholesale",
            "subcategory":"Electrical",
            "type":"Manufacturing & Wholesale Goods"
        }
    ],
    "sg:phone":"+1 707 987 9207",
    "sg:postcode":"95467",
    "sg:province":"CA",
    "sg:tags":[
        "development",
        "satellite",
        "system",
        "software"
    ],
    "wof:name":"J & S Engineering Enterprises",
    "wof:placetype":"venue"
},
  "geometry": {"coordinates":[-122.55503,38.798922],"type":"Point"}
}