{
  "type": "Feature",
  "properties": {
    "addr:full":"2099 Scott Boulevard Santa Clara CA 95050",
    "addr:housenumber":"2099",
    "addr:postcode":"95050",
    "addr:street":"Scott Boulevard",
    "iso:country":"US",
    "sg:address":"2099 Scott Boulevard",
    "sg:city":"Santa Clara",
    "sg:classifiers":[
        {
            "category":"Food & Beverages",
            "subcategory":"Liquor & Beverages",
            "type":"Retail Goods"
        }
    ],
    "sg:phone":"+1 408 241 2222",
    "sg:postcode":"95050",
    "sg:province":"CA",
    "sg:tags":[
        "beer",
        "spirit",
        "wine"
    ],
    "wof:name":"Mission Liquor",
    "wof:placetype":"venue"
},
  "geometry": {"coordinates":[-121.959717,37.359474],"type":"Point"}
}