{
  "type": "Feature",
  "properties": {
    "iso:country":"US",
    "sg:address":"2151 Oakland Road #540",
    "sg:city":"San Jose",
    "sg:classifiers":[
        {
            "category":"Building & Trades",
            "subcategory":"Construction",
            "type":"Services"
        }
    ],
    "sg:phone":"+1 408 435 8465",
    "sg:postcode":"95131",
    "sg:province":"CA",
    "sg:tags":[
        "contractor"
    ],
    "wof:name":"Paul Conte Tile",
    "wof:placetype":"venue"
},
  "geometry": {"coordinates":[-121.902306,37.396823],"type":"Point"}
}