{
  "type": "Feature",
  "properties": {
    "iso:country":"US",
    "sg:address":"70 Prado Rd",
    "sg:city":"San Luis Obispo",
    "sg:classifiers":[
        {
            "category":"Retail",
            "subcategory":"Auto Repair",
            "type":"Services"
        }
    ],
    "sg:phone":"+1 805 543 3528",
    "sg:postcode":"93401",
    "sg:province":"CA",
    "sg:tags":[
        "body",
        "automobile",
        "painting"
    ],
    "wof:name":"Hong's Quality Auto Metal Work",
    "wof:placetype":"venue"
},
  "geometry": {"coordinates":[-120.672068,35.255735],"type":"Point"}
}