{
  "type": "Feature",
  "properties": {
    "addr:full":"7777 Rosedale Hwy Bakersfield CA 93308",
    "addr:housenumber":"7777",
    "addr:postcode":"93308",
    "addr:street":"Rosedale Hwy",
    "iso:country":"US",
    "sg:address":"7777 Rosedale Hwy",
    "sg:city":"Bakersfield",
    "sg:classifiers":[
        {
            "category":"Restaurant",
            "type":"Food & Drink"
        }
    ],
    "sg:phone":"+1 661 588 1400",
    "sg:postcode":"93308",
    "sg:province":"CA",
    "wof:name":"Pizza Market",
    "wof:placetype":"venue"
},
  "geometry": {"coordinates":[-119.08866500000001,35.383322],"type":"Point"}
}