{
  "type": "Feature",
  "properties": {
    "iso:country":"US",
    "sg:address":"7777 Rosedale Hwy",
    "sg:city":"Bakersfield",
    "sg:classifiers":[
        {
            "category":"Restaurant",
            "type":"Food & Drink"
        }
    ],
    "sg:phone":"+1 661 588 1400",
    "sg:postcode":"93308",
    "sg:province":"CA",
    "wof:name":"Pizza Market",
    "wof:placetype":"venue"
},
  "geometry": {"coordinates":[-119.088665,35.383322],"type":"Point"}
}