{
  "type": "Feature",
  "properties": {
    "iso:country":"US",
    "sg:address":"920 Redbud Dr",
    "sg:city":"Redding",
    "sg:classifiers":[
        {
            "category":"Health Services",
            "subcategory":"Nursing And Care Facility",
            "type":"Services"
        }
    ],
    "sg:phone":"+1 530 241 8492",
    "sg:postcode":"96001",
    "sg:province":"CA",
    "sg:tags":[
        "home",
        "retirement",
        "community"
    ],
    "wof:name":"Redbud Care Home",
    "wof:placetype":"venue"
},
  "geometry": {"coordinates":[-122.42641999999999,40.588845],"type":"Point"}
}