{
  "type": "Feature",
  "properties": {
    "iso:country":"US",
    "sg:address":"818 S Broadway",
    "sg:city":"Los Angeles",
    "sg:classifiers":[
        {
            "category":"Shopping",
            "subcategory":"Clothing, Apparel, & Fashions",
            "type":"Retail Goods"
        }
    ],
    "sg:phone":"+1 213 489 9242",
    "sg:postcode":"90014",
    "sg:province":"CA",
    "sg:tags":[
        "designer"
    ],
    "wof:name":"Susana Mercedes",
    "wof:placetype":"venue"
},
  "geometry": {"coordinates":[-118.255796,34.042548],"type":"Point"}
}