{
  "type": "Feature",
  "properties": {
    "iso:country":"US",
    "sg:address":"3944 19th St",
    "sg:city":"San Francisco",
    "sg:classifiers":[
        {
            "category":"Social Services",
            "type":"Services"
        }
    ],
    "sg:phone":"+1 415 552 5523",
    "sg:postcode":"94114",
    "sg:province":"CA",
    "sg:tags":[
        "counselor",
        "marriage",
        "family"
    ],
    "wof:name":"Jacque Grillo",
    "wof:placetype":"venue"
},
  "geometry": {"coordinates":[-122.431856,37.759558],"type":"Point"}
}