{
  "type": "Feature",
  "properties": {
    "iso:country":"US",
    "sg:address":"24396 Stacey Ave",
    "sg:city":"Moreno Valley",
    "sg:classifiers":[
        {
            "category":"Local Transit",
            "type":"Transportation"
        }
    ],
    "sg:phone":"+1 951 924 4578",
    "sg:postcode":"92551",
    "sg:province":"CA",
    "sg:tags":[
        "limousine"
    ],
    "wof:name":"Guillermo's Limousine Svc",
    "wof:placetype":"venue"
},
  "geometry": {"coordinates":[-117.237902,33.898786],"type":"Point"}
}