{
  "type": "Feature",
  "properties": {
    "addr:full":"1312 W Guava Ave Lompoc CA 93436",
    "addr:housenumber":"1312",
    "addr:postcode":"93436",
    "addr:street":"W Guava Ave",
    "iso:country":"US",
    "sg:address":"1312 W Guava Ave",
    "sg:city":"Lompoc",
    "sg:classifiers":[
        {
            "category":"Professional",
            "subcategory":"Engineering",
            "type":"Services"
        }
    ],
    "sg:phone":"+1 858 609 1467",
    "sg:postcode":"93436",
    "sg:province":"CA",
    "sg:tags":[
        "system",
        "cad"
    ],
    "wof:name":"Glenn M. Cerny Drafting Service",
    "wof:placetype":"venue"
},
  "geometry": {"coordinates":[-120.47323400000001,34.641558],"type":"Point"}
}