{
  "type": "Feature",
  "properties": {
    "addr:full":"3161 Senter Rd San Jose CA 95111",
    "addr:housenumber":"3161",
    "addr:postcode":"95111",
    "addr:street":"Senter Rd",
    "iso:country":"US",
    "sg:address":"3161 Senter Rd",
    "sg:city":"San Jose",
    "sg:classifiers":[
        {
            "category":"Communications",
            "subcategory":"Radio Station",
            "type":"Services"
        }
    ],
    "sg:phone":"+1 408 362 2596",
    "sg:postcode":"95111",
    "sg:province":"CA",
    "sg:tags":[
        "broadcast"
    ],
    "wof:name":"Weekend Radio",
    "wof:placetype":"venue"
},
  "geometry": {"coordinates":[-121.83346400000001,37.293545],"type":"Point"}
}