{
  "type": "Feature",
  "properties": {
    "addr:full":"1921 E Clay Ave Fresno CA 93701",
    "addr:housenumber":"1921",
    "addr:postcode":"93701",
    "addr:street":"E Clay Ave",
    "iso:country":"US",
    "sg:address":"1921 E Clay Ave",
    "sg:city":"Fresno",
    "sg:classifiers":[
        {
            "category":"Retail",
            "subcategory":"Auto Repair",
            "type":"Services"
        }
    ],
    "sg:phone":"+1 559 497 8532",
    "sg:postcode":"93701",
    "sg:province":"CA",
    "sg:tags":[
        "repairing",
        "automobile"
    ],
    "wof:name":"Auto Repair Guerrero",
    "wof:placetype":"venue"
},
  "geometry": {"coordinates":[-119.787273,36.756424],"type":"Point"}
}