{
  "type": "Feature",
  "properties": {
    "iso:country":"US",
    "sg:address":"1750 Canby Rd",
    "sg:city":"Redding",
    "sg:classifiers":[
        {
            "category":"Organizations",
            "subcategory":"Religious Organization",
            "type":"Services"
        }
    ],
    "sg:phone":"+1 530 223 0513",
    "sg:postcode":"96002",
    "sg:province":"CA",
    "sg:tags":[
        "church"
    ],
    "wof:name":"St Luke's Anglican Church",
    "wof:placetype":"venue"
},
  "geometry": {"coordinates":[-122.353081,40.580663],"type":"Point"}
}