{
  "type": "Feature",
  "properties": {
    "addr:full":"1909 S Business Center Dr San Bernardino CA 92408",
    "addr:housenumber":"1909",
    "addr:postcode":"92408",
    "addr:street":"S Business Center Dr",
    "iso:country":"US",
    "sg:address":"1909 S Business Center Dr",
    "sg:city":"San Bernardino",
    "sg:classifiers":[
        {
            "category":"Travel",
            "subcategory":"Hotels & Motels",
            "type":"Entertainment"
        }
    ],
    "sg:phone":"+1 909 889 0090",
    "sg:postcode":"92408",
    "sg:province":"CA",
    "sg:website":"www.comfortinn.com",
    "wof:name":"Comfort Inn",
    "wof:placetype":"venue"
},
  "geometry": {"coordinates":[-117.280106,34.067604],"type":"Point"}
}