{
  "type": "Feature",
  "properties": {
    "addr:full":"6155 Almaden Expy San Jose CA 95120",
    "addr:housenumber":"6155",
    "addr:postcode":"95120",
    "addr:street":"Almaden Expy",
    "iso:country":"US",
    "sg:address":"6155 Almaden Expy",
    "sg:city":"San Jose",
    "sg:classifiers":[
        {
            "category":"Real Estate",
            "subcategory":"Real Estate Agent",
            "type":"Services"
        }
    ],
    "sg:phone":"+1 408 323 3145",
    "sg:postcode":"95120",
    "sg:province":"CA",
    "sg:website":"www.rwranchogrande.com",
    "wof:name":"Realty World Rancho Grande",
    "wof:placetype":"venue"
},
  "geometry": {"coordinates":[-121.87036999999999,37.229293],"type":"Point"}
}