{
  "type": "Feature",
  "properties": {
    "iso:country":"US",
    "sg:address":"12930 Saratoga Avenue, Suite B-8",
    "sg:city":"Saratoga",
    "sg:classifiers":[
        {
            "category":"Professional",
            "subcategory":"Computer Services",
            "type":"Services"
        }
    ],
    "sg:phone":"+1 866 435 2428",
    "sg:postcode":"95070",
    "sg:province":"CA",
    "sg:website":"http://www.ekahau.com",
    "wof:name":"Ekahau",
    "wof:placetype":"venue"
},
  "geometry": {"coordinates":[-122.00391999999999,37.280272],"type":"Point"}
}