{
  "type": "Feature",
  "properties": {
    "addr:full":"4644 Waterloo Rd Stockton CA 95215",
    "addr:housenumber":"4644",
    "addr:postcode":"95215",
    "addr:street":"Waterloo Rd",
    "iso:country":"US",
    "sg:address":"4644 Waterloo Rd",
    "sg:city":"Stockton",
    "sg:classifiers":[
        {
            "category":"Building & Trades",
            "subcategory":"Landscaping Services",
            "type":"Services"
        }
    ],
    "sg:phone":"+1 209 931 5892",
    "sg:postcode":"95215",
    "sg:province":"CA",
    "sg:tags":[
        "tree"
    ],
    "wof:name":"Asplundh Construction Corp",
    "wof:placetype":"venue"
},
  "geometry": {"coordinates":[-121.243509,37.988648],"type":"Point"}
}