{
  "type": "Feature",
  "properties": {
    "iso:country":"US",
    "sg:address":"25448 Narbonne Ave",
    "sg:city":"Lomita",
    "sg:classifiers":[
        {
            "category":"Health Services",
            "subcategory":"Chiropractor",
            "type":"Services"
        }
    ],
    "sg:phone":"+1 310 326 2804",
    "sg:postcode":"90717",
    "sg:province":"CA",
    "wof:name":"Jennewein 'BJ' Beiarano DC",
    "wof:placetype":"venue"
},
  "geometry": {"coordinates":[-118.319802,33.792957],"type":"Point"}
}