{
  "type": "Feature",
  "properties": {
    "addr:full":"1199 Dunsyre Dr Lafayette CA 94549",
    "addr:housenumber":"1199",
    "addr:postcode":"94549",
    "addr:street":"Dunsyre Dr",
    "iso:country":"US",
    "sg:address":"1199 Dunsyre Dr",
    "sg:city":"Lafayette",
    "sg:classifiers":[
        {
            "category":"Government",
            "subcategory":"Fire Station",
            "type":"Public Place"
        },
        {
            "category":"Retail",
            "subcategory":"Laundry & Dry Cleaning",
            "type":"Services"
        },
        {
            "category":"Building & Trades",
            "subcategory":"Cleaning & Sanitation",
            "type":"Services"
        }
    ],
    "sg:phone":"+1 925 945 6767",
    "sg:postcode":"94549",
    "sg:province":"CA",
    "sg:tags":[
        "cleaner",
        "disaster",
        "recovery",
        "damage",
        "rug",
        "water",
        "restoration",
        "relief",
        "carpet"
    ],
    "sg:website":"http://www.diablocarpetcare.com",
    "wof:name":"Diablo Carpet Care",
    "wof:placetype":"venue"
},
  "geometry": {"coordinates":[-122.08631099999999,37.900829],"type":"Point"}
}