{
  "type": "Feature",
  "properties": {
    "addr:full":"4765 Trojan Ave San Diego CA 92115",
    "addr:housenumber":"4765",
    "addr:postcode":"92115",
    "addr:street":"Trojan Ave",
    "iso:country":"US",
    "sg:address":"4765 Trojan Ave",
    "sg:city":"San Diego",
    "sg:classifiers":[
        {
            "category":"Retail",
            "subcategory":"Auto Repair",
            "type":"Services"
        }
    ],
    "sg:phone":"+1 619 528 8818",
    "sg:postcode":"92115",
    "sg:province":"CA",
    "sg:tags":[
        "repairing",
        "automobile"
    ],
    "wof:name":"Right Torque Auto Repair",
    "wof:placetype":"venue"
},
  "geometry": {"coordinates":[-117.091272,32.754859],"type":"Point"}
}