{
  "type": "Feature",
  "properties": {
    "addr:full":"2431 San Ramon Valley Blvd San Ramon CA 94583",
    "addr:housenumber":"2431",
    "addr:postcode":"94583",
    "addr:street":"San Ramon Valley Blvd",
    "iso:country":"US",
    "sg:address":"2431 San Ramon Valley Blvd",
    "sg:city":"San Ramon",
    "sg:classifiers":[
        {
            "category":"Restaurant",
            "type":"Food & Drink"
        }
    ],
    "sg:menulink":"http://www.allmenus.com/ca/central-contra-costa/221639-chipotle/menu/",
    "sg:phone":"+1 925 820 4110",
    "sg:postcode":"94583",
    "sg:province":"CA",
    "sg:tags":[
        "mexican"
    ],
    "wof:name":"Chipotle",
    "wof:placetype":"venue"
},
  "geometry": {"coordinates":[-121.977965,37.775401],"type":"Point"}
}