{
  "type": "Feature",
  "properties": {
    "addr:full":"10925 Olson Dr Rancho Cordova CA 95670",
    "addr:housenumber":"10925",
    "addr:postcode":"95670",
    "addr:street":"Olson Dr",
    "iso:country":"US",
    "sg:address":"10925 Olson Dr",
    "sg:city":"Rancho Cordova",
    "sg:classifiers":[
        {
            "category":"Banks & Credit Unions",
            "subcategory":"Bank",
            "type":"Services"
        }
    ],
    "sg:phone":"+1 916 858 1506",
    "sg:postcode":"95670",
    "sg:province":"CA",
    "sg:tags":[
        "cashing",
        "check"
    ],
    "wof:name":"Check Into Cash",
    "wof:placetype":"venue"
},
  "geometry": {"coordinates":[-121.28161299999999,38.595941],"type":"Point"}
}