{
  "type": "Feature",
  "properties": {
    "addr:full":"6258 W Olympic Blvd Los Angeles CA 90048",
    "addr:housenumber":"6258",
    "addr:postcode":"90048",
    "addr:street":"W Olympic Blvd",
    "iso:country":"US",
    "sg:address":"6258 W Olympic Blvd",
    "sg:city":"Los Angeles",
    "sg:classifiers":[
        {
            "category":"Shopping",
            "subcategory":"Clothing, Apparel, & Fashions",
            "type":"Retail Goods"
        }
    ],
    "sg:phone":"+1 323 769 0958",
    "sg:postcode":"90048",
    "sg:province":"CA",
    "sg:tags":[
        "sportswear"
    ],
    "wof:name":"West LA Sports & Play",
    "wof:placetype":"venue"
},
  "geometry": {"coordinates":[-118.36732600000001,34.058499],"type":"Point"}
}