{
  "type": "Feature",
  "properties": {
    "addr:full":"2521 N Grand Ave Santa Ana CA 92705",
    "addr:housenumber":"2521",
    "addr:postcode":"92705",
    "addr:street":"N Grand Ave",
    "iso:country":"US",
    "sg:address":"2521 N Grand Ave",
    "sg:city":"Santa Ana",
    "sg:classifiers":[
        {
            "category":"Personal",
            "subcategory":"Beauty Salon",
            "type":"Services"
        }
    ],
    "sg:phone":"+1 714 771 8408",
    "sg:postcode":"92705",
    "sg:province":"CA",
    "sg:tags":[
        "hair"
    ],
    "wof:name":"Affiliated Barbershop",
    "wof:placetype":"venue"
},
  "geometry": {"coordinates":[-117.852251,33.770806],"type":"Point"}
}