{
  "type": "Feature",
  "properties": {
    "addr:full":"1334 Sutter St San Diego CA 92103",
    "addr:housenumber":"1334",
    "addr:postcode":"92103",
    "addr:street":"Sutter St",
    "iso:country":"US",
    "sg:address":"1334 Sutter St",
    "sg:city":"San Diego",
    "sg:classifiers":[
        {
            "category":"Building & Trades",
            "subcategory":"Construction",
            "type":"Services"
        }
    ],
    "sg:phone":"+1 619 692 3375",
    "sg:postcode":"92103",
    "sg:province":"CA",
    "sg:tags":[
        "contractor"
    ],
    "wof:name":"William F Jones Contractor",
    "wof:placetype":"venue"
},
  "geometry": {"coordinates":[-117.17665100000001,32.746267],"type":"Point"}
}