{
  "type": "Feature",
  "properties": {
    "iso:country":"US",
    "sg:address":"2834 Monogram Ave",
    "sg:city":"Long Beach",
    "sg:classifiers":[
        {
            "category":"Professional",
            "subcategory":"Business Services",
            "type":"Services"
        }
    ],
    "sg:phone":"+1 562 420 1364",
    "sg:postcode":"90815",
    "sg:province":"CA",
    "sg:tags":[
        "embroidery"
    ],
    "wof:name":"STS",
    "wof:placetype":"venue"
},
  "geometry": {"coordinates":[-118.102657,33.809845],"type":"Point"}
}