{
  "type": "Feature",
  "properties": {
    "addr:full":"5495 Mission St San Francisco CA 94112",
    "addr:housenumber":"5495",
    "addr:postcode":"94112",
    "addr:street":"Mission St",
    "iso:country":"US",
    "sg:address":"5495 Mission St",
    "sg:city":"San Francisco",
    "sg:classifiers":[
        {
            "category":"Wholesale",
            "subcategory":"Non-durable Goods",
            "type":"Manufacturing & Wholesale Goods"
        }
    ],
    "sg:phone":"+1 415 469 8962",
    "sg:postcode":"94112",
    "sg:province":"CA",
    "wof:name":"Creg General Merchandise",
    "wof:placetype":"venue"
},
  "geometry": {"coordinates":[-122.44406499999999,37.713265],"type":"Point"}
}