{
  "type": "Feature",
  "properties": {
    "iso:country":"US",
    "sg:address":"26225 Columbia St",
    "sg:city":"Hemet",
    "sg:classifiers":[
        {
            "category":"Sports & Exercise",
            "subcategory":"Sports Center",
            "type":"Entertainment"
        }
    ],
    "sg:phone":"+1 951 537 0057",
    "sg:postcode":"92544",
    "sg:province":"CA",
    "wof:name":"Real Deal Boxing Club",
    "wof:placetype":"venue"
},
  "geometry": {"coordinates":[-116.945578,33.740988],"type":"Point"}
}