{
  "type": "Feature",
  "properties": {
    "addr:full":"3636 Castro Valley Blvd # 2 Castro Valley CA 94546",
    "addr:housenumber":"3636",
    "addr:postcode":"94546",
    "addr:street":"Castro Valley Blvd # 2",
    "iso:country":"US",
    "sg:address":"3636 Castro Valley Blvd # 2",
    "sg:city":"Castro Valley",
    "sg:classifiers":[
        {
            "category":"Health Services",
            "subcategory":"Health Practitioner",
            "type":"Services"
        }
    ],
    "sg:phone":"+1 510 754 3901",
    "sg:postcode":"94546",
    "sg:province":"CA",
    "sg:tags":[
        "acupuncture",
        "naturopathic/holistic"
    ],
    "sg:website":"www.dancinggrassmedicine.com/",
    "wof:name":"Dancing Grass Medicine",
    "wof:placetype":"venue"
},
  "geometry": {"coordinates":[-122.072096,37.696277],"type":"Point"}
}