{
  "type": "Feature",
  "properties": {
    "iso:country":"US",
    "sg:address":"9348 Narnia Dr",
    "sg:city":"Riverside",
    "sg:classifiers":[
        {
            "category":"Manufacturing",
            "subcategory":"Printing",
            "type":"Manufacturing & Wholesale Goods"
        }
    ],
    "sg:phone":"+1 951 353 1717",
    "sg:postcode":"92503",
    "sg:province":"CA",
    "sg:tags":[
        "lithographic",
        "commercial"
    ],
    "sg:website":"www.theprintingplus.com",
    "wof:name":"Printing Plus",
    "wof:placetype":"venue"
},
  "geometry": {"coordinates":[-117.437805,33.914924],"type":"Point"}
}