{
  "type": "Feature",
  "properties": {
    "iso:country":"US",
    "sg:address":"1340 Post Ave",
    "sg:city":"Torrance",
    "sg:classifiers":[
        {
            "category":"Fast Food",
            "type":"Food & Drink"
        },
        {
            "category":"Restaurant",
            "type":"Food & Drink"
        }
    ],
    "sg:phone":"+1 310 533 0752",
    "sg:postcode":"90501",
    "sg:province":"CA",
    "sg:tags":[
        "burger",
        "breakfast",
        "brunch",
        "diner"
    ],
    "wof:name":"Eat at Rudy's",
    "wof:placetype":"venue"
},
  "geometry": {"coordinates":[-118.318001,33.8353],"type":"Point"}
}