{
  "type": "Feature",
  "properties": {
    "addr:full":"8615 Miramar Pl San Diego CA 92121",
    "addr:housenumber":"8615",
    "addr:postcode":"92121",
    "addr:street":"Miramar Pl",
    "iso:country":"US",
    "sg:address":"8615 Miramar Pl",
    "sg:city":"San Diego",
    "sg:classifiers":[
        {
            "category":"Wholesale",
            "subcategory":"Machinery & Supplies",
            "type":"Manufacturing & Wholesale Goods"
        }
    ],
    "sg:phone":"+1 858 597 0275",
    "sg:postcode":"92121",
    "sg:province":"CA",
    "sg:tags":[
        "contractor"
    ],
    "wof:name":"Oes Spec 8 Openings",
    "wof:placetype":"venue"
},
  "geometry": {"coordinates":[-117.180263,32.881828],"type":"Point"}
}