{
  "type": "Feature",
  "properties": {
    "iso:country":"US",
    "sg:address":"45 N Hunter Square Plz",
    "sg:city":"Stockton",
    "sg:classifiers":[
        {
            "category":"Professional",
            "subcategory":"Lawyer & Legal Services",
            "type":"Services"
        }
    ],
    "sg:phone":"+1 209 943 5674",
    "sg:postcode":"95202",
    "sg:province":"CA",
    "sg:tags":[
        "attorney"
    ],
    "wof:name":"Judicare Inc",
    "wof:placetype":"venue"
},
  "geometry": {"coordinates":[-121.288738,37.953467],"type":"Point"}
}