{
  "type": "Feature",
  "properties": {
    "addr:full":"1620 62nd Ave Oakland CA 94621",
    "addr:housenumber":"1620",
    "addr:postcode":"94621",
    "addr:street":"62Nd Ave",
    "iso:country":"US",
    "sg:address":"1620 62nd Ave",
    "sg:city":"Oakland",
    "sg:classifiers":[
        {
            "category":"Social Services",
            "subcategory":"Child Care",
            "type":"Services"
        }
    ],
    "sg:phone":"+1 510 568 8849",
    "sg:postcode":"94621",
    "sg:province":"CA",
    "sg:tags":[
        "day"
    ],
    "wof:name":"St Bernard's School Extended Care",
    "wof:placetype":"venue"
},
  "geometry": {"coordinates":[-122.19593,37.764477],"type":"Point"}
}