{
  "type": "Feature",
  "properties": {
    "iso:country":"US",
    "sg:address":"1 Fluor Daniel Dr",
    "sg:city":"Aliso Viejo",
    "sg:classifiers":[
        {
            "category":"Banks & Credit Unions",
            "subcategory":"Bank",
            "type":"Services"
        }
    ],
    "sg:phone":"+1 949 716 5746",
    "sg:postcode":"92698",
    "sg:province":"CA",
    "wof:name":"Fluor Daniel Credit Union",
    "wof:placetype":"venue"
},
  "geometry": {"coordinates":[-117.83899700000001,33.671299],"type":"Point"}
}