{
  "type": "Feature",
  "properties": {
    "addr:full":"3600 American River Drive Sacramento CA 95864",
    "addr:housenumber":"3600",
    "addr:postcode":"95864",
    "addr:street":"American River Drive",
    "iso:country":"US",
    "sg:address":"3600 American River Drive",
    "sg:city":"Sacramento",
    "sg:classifiers":[
        {
            "category":"Professional",
            "subcategory":"Accounting & Tax Preparation",
            "type":"Services"
        }
    ],
    "sg:phone":"+1 916 971 2470",
    "sg:postcode":"95864",
    "sg:province":"CA",
    "sg:tags":[
        "accountant"
    ],
    "wof:name":"Rathkamp Douglas W CPA",
    "wof:placetype":"venue"
},
  "geometry": {"coordinates":[-121.380353,38.570023],"type":"Point"}
}