{
  "type": "Feature",
  "properties": {
    "iso:country":"US",
    "sg:address":"1082 Glendon Ave",
    "sg:city":"Los Angeles",
    "sg:classifiers":[
        {
            "category":"Community Center",
            "type":"Public Place"
        }
    ],
    "sg:phone":"+1 310 209 2011",
    "sg:postcode":"90024",
    "sg:province":"CA",
    "sg:tags":[
        "medical"
    ],
    "sg:website":"www.universityvascular.com",
    "wof:name":"University Vascular Associates",
    "wof:placetype":"venue"
},
  "geometry": {"coordinates":[-118.44439,34.061012],"type":"Point"}
}