{
  "type": "Feature",
  "properties": {
    "addr:full":"30011 Ahern Ave Union City CA 94587",
    "addr:housenumber":"30011",
    "addr:postcode":"94587",
    "addr:street":"Ahern Ave",
    "iso:country":"US",
    "sg:address":"30011 Ahern Ave",
    "sg:city":"Union City",
    "sg:classifiers":[
        {
            "category":"Professional",
            "subcategory":"Business Services",
            "type":"Services"
        }
    ],
    "sg:phone":"+1 510 429 7200",
    "sg:postcode":"94587",
    "sg:province":"CA",
    "wof:name":"Mobile High Tech",
    "wof:placetype":"venue"
},
  "geometry": {"coordinates":[-122.076633,37.608728],"type":"Point"}
}