{
  "type": "Feature",
  "properties": {
    "addr:full":"2787 W Bullard Ave Fresno CA 93711",
    "addr:housenumber":"2787",
    "addr:postcode":"93711",
    "addr:street":"W Bullard Ave",
    "iso:country":"US",
    "sg:address":"2787 W Bullard Ave",
    "sg:city":"Fresno",
    "sg:classifiers":[
        {
            "category":"Banks & Credit Unions",
            "subcategory":"Bank",
            "type":"Services"
        }
    ],
    "sg:phone":"+1 559 228 0600",
    "sg:postcode":"93711",
    "sg:province":"CA",
    "wof:name":"Mortgage Dynamics Group",
    "wof:placetype":"venue"
},
  "geometry": {"coordinates":[-119.84173,36.822656],"type":"Point"}
}