{
  "type": "Feature",
  "properties": {
    "iso:country":"US",
    "sg:address":"3 Southwind Cir",
    "sg:city":"Richmond",
    "sg:classifiers":[
        {
            "category":"Personal",
            "subcategory":"Skin Care",
            "type":"Services"
        }
    ],
    "sg:phone":"+1 510 235 1438",
    "sg:postcode":"94804",
    "sg:province":"CA",
    "sg:tags":[
        "cosmetic"
    ],
    "wof:name":"Jeannie Taylor",
    "wof:placetype":"venue"
},
  "geometry": {"coordinates":[-122.342069,37.90933],"type":"Point"}
}