{
  "type": "Feature",
  "properties": {
    "iso:country":"US",
    "sg:address":"1655 Mesa Verde Ave",
    "sg:city":"Ventura",
    "sg:classifiers":[
        {
            "category":"Professional",
            "subcategory":"Accounting & Tax Preparation",
            "type":"Services"
        }
    ],
    "sg:phone":"+1 805 656 2515",
    "sg:postcode":"93003",
    "sg:province":"CA",
    "sg:tags":[
        "accountant"
    ],
    "wof:name":"Mark L Goldenson CPA",
    "wof:placetype":"venue"
},
  "geometry": {"coordinates":[-119.216801,34.257777],"type":"Point"}
}