{
  "type": "Feature",
  "properties": {
    "addr:full":"2319 California St Berkeley CA 94703",
    "addr:housenumber":"2319",
    "addr:postcode":"94703",
    "addr:street":"California St",
    "iso:country":"US",
    "sg:address":"2319 California St",
    "sg:city":"Berkeley",
    "sg:classifiers":[
        {
            "category":"Professional",
            "subcategory":"Management & Consulting",
            "type":"Services"
        }
    ],
    "sg:phone":"+1 510 548 1098",
    "sg:postcode":"94703",
    "sg:province":"CA",
    "sg:tags":[
        "counselor",
        "public",
        "relations"
    ],
    "sg:website":"www.fortunepublicrelations.com",
    "wof:name":"Fortune Public Relations",
    "wof:placetype":"venue"
},
  "geometry": {"coordinates":[-122.279088,37.864646],"type":"Point"}
}