{
  "type": "Feature",
  "properties": {
    "addr:full":"2202 S Hoover St Ste B2 Los Angeles CA 90007",
    "addr:housenumber":"2202",
    "addr:postcode":"90007",
    "addr:street":"S Hoover St Ste B2",
    "iso:country":"US",
    "sg:address":"2202 S Hoover St Ste B2",
    "sg:city":"Los Angeles",
    "sg:classifiers":[
        {
            "category":"Bakery",
            "type":"Food & Drink"
        }
    ],
    "sg:phone":"+1 213 745 6042",
    "sg:postcode":"90007",
    "sg:province":"CA",
    "wof:name":"La Fresa Bakery",
    "wof:placetype":"venue"
},
  "geometry": {"coordinates":[-118.283997,34.035999],"type":"Point"}
}