{
  "type": "Feature",
  "properties": {
    "iso:country":"US",
    "sg:address":"2245 S El Camino Real",
    "sg:city":"Oceanside",
    "sg:classifiers":[
        {
            "category":"Health Services",
            "subcategory":"Health Practitioner",
            "type":"Services"
        },
        {
            "category":"Health Services",
            "subcategory":"Chiropractor",
            "type":"Services"
        }
    ],
    "sg:phone":"+1 760 754 2225",
    "sg:postcode":"92054",
    "sg:province":"CA",
    "sg:tags":[
        "nutritionist"
    ],
    "sg:website":"www.spinehealth.net",
    "wof:name":"Smith Scott K DC",
    "wof:placetype":"venue"
},
  "geometry": {"coordinates":[-117.328003,33.185101],"type":"Point"}
}