{
  "type": "Feature",
  "properties": {
    "addr:full":"12727-B Sherman Way Suite B-08 North Hollywood CA 91605",
    "addr:housenumber":"12727-b",
    "addr:postcode":"91605",
    "addr:street":"Sherman Way Suite B-08",
    "iso:country":"US",
    "sg:address":"12727-B Sherman Way Suite B-08",
    "sg:city":"North Hollywood",
    "sg:classifiers":[
        {
            "category":"Restaurant",
            "type":"Food & Drink"
        }
    ],
    "sg:phone":"+1 818 759 2040",
    "sg:postcode":"91605",
    "sg:province":"CA",
    "sg:tags":[
        "peruvian"
    ],
    "wof:name":"La Perla del Pacifico",
    "wof:placetype":"venue"
},
  "geometry": {"coordinates":[-118.409942,34.201219],"type":"Point"}
}