{
  "type": "Feature",
  "properties": {
    "iso:country":"US",
    "sg:address":"21361 White Rd",
    "sg:city":"Turlock",
    "sg:classifiers":[
        {
            "category":"Wholesale",
            "subcategory":"Vending Machines",
            "type":"Manufacturing & Wholesale Goods"
        }
    ],
    "sg:phone":"+1 209 632 4008",
    "sg:postcode":"95380",
    "sg:province":"CA",
    "sg:tags":[
        "merchandise"
    ],
    "wof:name":"Pombo Vending",
    "wof:placetype":"venue"
},
  "geometry": {"coordinates":[-120.876741,37.441671],"type":"Point"}
}