{
  "type": "Feature",
  "properties": {
    "addr:full":"409 Appaloosa Dr Paso Robles CA 93446",
    "addr:housenumber":"409",
    "addr:postcode":"93446",
    "addr:street":"Appaloosa Dr",
    "iso:country":"US",
    "sg:address":"409 Appaloosa Dr",
    "sg:city":"Paso Robles",
    "sg:classifiers":[
        {
            "category":"Shopping",
            "subcategory":"Clothing, Apparel, & Fashions",
            "type":"Retail Goods"
        }
    ],
    "sg:phone":"+1 805 237 0746",
    "sg:postcode":"93446",
    "sg:province":"CA",
    "sg:tags":[
        "alteration"
    ],
    "wof:name":"Carmen's Sewing & Alterations",
    "wof:placetype":"venue"
},
  "geometry": {"coordinates":[-120.673777,35.618172],"type":"Point"}
}