{
  "type": "Feature",
  "properties": {
    "addr:full":"11447 Tuxford St Sun Valley CA 91352",
    "addr:housenumber":"11447",
    "addr:postcode":"91352",
    "addr:street":"Tuxford St",
    "iso:country":"US",
    "sg:address":"11447 Tuxford St",
    "sg:city":"Sun Valley",
    "sg:classifiers":[
        {
            "category":"Mining & Drilling",
            "type":"Manufacturing & Wholesale Goods"
        }
    ],
    "sg:phone":"+1 818 767 7119",
    "sg:postcode":"91352",
    "sg:province":"CA",
    "sg:tags":[
        "construction"
    ],
    "wof:name":"Vulcan Materials Company",
    "wof:placetype":"venue"
},
  "geometry": {"coordinates":[-118.377549,34.230553],"type":"Point"}
}