{
  "type": "Feature",
  "properties": {
    "addr:full":"2818 W Ball Rd Anaheim CA 92804",
    "addr:housenumber":"2818",
    "addr:postcode":"92804",
    "addr:street":"W Ball Rd",
    "iso:country":"US",
    "sg:address":"2818 W Ball Rd",
    "sg:city":"Anaheim",
    "sg:classifiers":[
        {
            "category":"Professional",
            "subcategory":"Management & Consulting",
            "type":"Services"
        }
    ],
    "sg:phone":"+1 714 952 0100",
    "sg:postcode":"92804",
    "sg:province":"CA",
    "sg:tags":[
        "retail",
        "direct",
        "sales"
    ],
    "wof:name":"N I K Water",
    "wof:placetype":"venue"
},
  "geometry": {"coordinates":[-117.9883,33.817391],"type":"Point"}
}