{
  "type": "Feature",
  "properties": {
    "iso:country":"US",
    "sg:address":"15740 Paramount Blvd Ste C",
    "sg:city":"Paramount",
    "sg:classifiers":[
        {
            "category":"Real Estate",
            "subcategory":"Real Estate Services",
            "type":"Services"
        },
        {
            "category":"Real Estate",
            "subcategory":"Real Estate Agent",
            "type":"Services"
        }
    ],
    "sg:phone":"+1 562 531 1330",
    "sg:postcode":"90723",
    "sg:province":"CA",
    "sg:tags":[
        "buyer",
        "broker"
    ],
    "wof:name":"Win Win Realtors",
    "wof:placetype":"venue"
},
  "geometry": {"coordinates":[-118.160033,33.890127],"type":"Point"}
}