{
  "type": "Feature",
  "properties": {
    "iso:country":"US",
    "sg:address":"660 Baker St",
    "sg:city":"Costa Mesa",
    "sg:classifiers":[
        {
            "category":"Retail",
            "subcategory":"Auto Repair",
            "type":"Services"
        }
    ],
    "sg:phone":"+1 714 444 0849",
    "sg:postcode":"92626",
    "sg:province":"CA",
    "wof:name":"Trico Products",
    "wof:placetype":"venue"
},
  "geometry": {"coordinates":[-117.8837,33.680227],"type":"Point"}
}