{
  "type": "Feature",
  "properties": {
    "iso:country":"US",
    "sg:address":"3045 Rosecrans Street Suite 214",
    "sg:city":"San Diego",
    "sg:classifiers":[
        {
            "category":"Landmark",
            "subcategory":"Tourist Information",
            "type":"Public Place"
        }
    ],
    "sg:phone":"+1 619 224 0099",
    "sg:postcode":"92110",
    "sg:province":"CA",
    "sg:tags":[
        "tour"
    ],
    "sg:website":"www.brazilianpacifictimes.com",
    "wof:name":"Brazilian Pacific Times",
    "wof:placetype":"venue"
},
  "geometry": {"coordinates":[-117.21168900000001,32.745055],"type":"Point"}
}