{
  "type": "Feature",
  "properties": {
    "iso:country":"US",
    "sg:address":"9701 Enos Ln",
    "sg:city":"Bakersfield",
    "sg:classifiers":[
        {
            "category":"Wholesale",
            "subcategory":"Medical Equipment & Supplies",
            "type":"Manufacturing & Wholesale Goods"
        }
    ],
    "sg:phone":"+1 661 746 3945",
    "sg:postcode":"93314",
    "sg:province":"CA",
    "wof:name":"Page Environmental",
    "wof:placetype":"venue"
},
  "geometry": {"coordinates":[-119.25802,35.453323],"type":"Point"}
}