{
  "type": "Feature",
  "properties": {
    "addr:full":"6913 Owensmouth Ave Canoga Park CA 91303",
    "addr:housenumber":"6913",
    "addr:postcode":"91303",
    "addr:street":"Owensmouth Ave",
    "iso:country":"US",
    "sg:address":"6913 Owensmouth Ave",
    "sg:city":"Canoga Park",
    "sg:classifiers":[
        {
            "category":"Insurance",
            "subcategory":"Insurance Agent",
            "type":"Services"
        }
    ],
    "sg:phone":"+1 818 716 6708",
    "sg:postcode":"91303",
    "sg:province":"CA",
    "wof:name":"Western Alliance Insurance Svc",
    "wof:placetype":"venue"
},
  "geometry": {"coordinates":[-118.601625,34.195401],"type":"Point"}
}