{
  "type": "Feature",
  "properties": {
    "addr:full":"8200 N Laurelglen Blvd Bakersfield CA 93311",
    "addr:housenumber":"8200",
    "addr:postcode":"93311",
    "addr:street":"N Laurelglen Blvd",
    "iso:country":"US",
    "sg:address":"8200 N Laurelglen Blvd",
    "sg:city":"Bakersfield",
    "sg:classifiers":[
        {
            "category":"Real Estate",
            "subcategory":"Real Estate Operator",
            "type":"Services"
        }
    ],
    "sg:phone":"+1 661 664 6200",
    "sg:postcode":"93311",
    "sg:province":"CA",
    "sg:tags":[
        "apartment"
    ],
    "wof:name":"Cambridge Village Apartments",
    "wof:placetype":"venue"
},
  "geometry": {"coordinates":[-119.092175,35.333734],"type":"Point"}
}