{
  "type": "Feature",
  "properties": {
    "addr:full":"2211 1st St Napa CA 94559",
    "addr:housenumber":"2211",
    "addr:postcode":"94559",
    "addr:street":"1St St",
    "iso:country":"US",
    "sg:address":"2211 1st St",
    "sg:city":"Napa",
    "sg:classifiers":[
        {
            "category":"Social Services",
            "subcategory":"Child Care",
            "type":"Services"
        }
    ],
    "sg:phone":"+1 707 255 1124",
    "sg:postcode":"94559",
    "sg:province":"CA",
    "sg:tags":[
        "kindergarten",
        "academic",
        "school"
    ],
    "wof:name":"Yellow Brick Road Preschool",
    "wof:placetype":"venue"
},
  "geometry": {"coordinates":[-122.298475,38.297895],"type":"Point"}
}