{
  "type": "Feature",
  "properties": {
    "iso:country":"US",
    "sg:address":"1332 Mokelumne Dr",
    "sg:city":"Antioch",
    "sg:classifiers":[
        {
            "category":"Place Of Worship",
            "subcategory":"Church",
            "type":"Public Place"
        },
        {
            "category":"Place Of Worship",
            "type":"Public Place"
        },
        {
            "category":"Organizations",
            "subcategory":"Religious Organization",
            "type":"Services"
        }
    ],
    "sg:phone":"+1 925 756 2940",
    "sg:postcode":"94531",
    "sg:province":"CA",
    "sg:tags":[
        "god",
        "churches-church",
        "churches-pentecostal"
    ],
    "sg:website":"http://www.cindypacileo.com",
    "wof:name":"National Spiritual Assembly Of The Baha'is Of The United States, Inc",
    "wof:placetype":"venue"
},
  "geometry": {"coordinates":[-121.79915099999999,37.957043],"type":"Point"}
}