{
  "type": "Feature",
  "properties": {
    "iso:country":"US",
    "sg:address":"1080 N Indian Canyon Dr Ste 104",
    "sg:city":"Palm Springs",
    "sg:classifiers":[
        {
            "category":"Health Services",
            "subcategory":"Doctor",
            "type":"Services"
        },
        {
            "category":"Health Services",
            "subcategory":"Hospital",
            "type":"Services"
        }
    ],
    "sg:phone":"+1 760 969 1888",
    "sg:postcode":"92262",
    "sg:province":"CA",
    "wof:name":"Kelly William M MD",
    "wof:placetype":"venue"
},
  "geometry": {"coordinates":[-116.545438,33.837405],"type":"Point"}
}