{
  "type": "Feature",
  "properties": {
    "iso:country":"US",
    "sg:address":"2610 Marin Ave",
    "sg:city":"Berkeley",
    "sg:classifiers":[
        {
            "category":"Train Station",
            "subcategory":"Rail",
            "type":"Transportation"
        }
    ],
    "sg:phone":"+1 510 527 0759",
    "sg:postcode":"94708",
    "sg:province":"CA",
    "sg:tags":[
        "marine",
        "engineer"
    ],
    "wof:name":"Marine Innovation & Technology",
    "wof:placetype":"venue"
},
  "geometry": {"coordinates":[-122.26243599999999,37.896549],"type":"Point"}
}