{
  "type": "Feature",
  "properties": {
    "iso:country":"US",
    "sg:address":"272 W 2nd St",
    "sg:city":"Claremont",
    "sg:classifiers":[
        {
            "category":"Shopping",
            "subcategory":"Tobacco",
            "type":"Retail Goods"
        }
    ],
    "sg:phone":"+1 909 625 6321",
    "sg:postcode":"91711",
    "sg:province":"CA",
    "sg:tags":[
        "cigarette",
        "cigar",
        "dealer"
    ],
    "wof:name":"Claremont Tobacco House",
    "wof:placetype":"venue"
},
  "geometry": {"coordinates":[-117.717589,34.095562],"type":"Point"}
}