{
  "type": "Feature",
  "properties": {
    "addr:full":"20 Dormody Ct Monterey CA 93940",
    "addr:housenumber":"20",
    "addr:postcode":"93940",
    "addr:street":"Dormody Ct",
    "iso:country":"US",
    "sg:address":"20 Dormody Ct",
    "sg:city":"Monterey",
    "sg:classifiers":[
        {
            "category":"Health Services",
            "subcategory":"Doctor",
            "type":"Services"
        }
    ],
    "sg:phone":"+1 831 373 3703",
    "sg:postcode":"93940",
    "sg:province":"CA",
    "sg:tags":[
        "dentist"
    ],
    "wof:name":"Daniel J Green DDS",
    "wof:placetype":"venue"
},
  "geometry": {"coordinates":[-121.896315,36.594432],"type":"Point"}
}