{
  "type": "Feature",
  "properties": {
    "addr:full":"21600 Oxnard St Woodland Hills CA 91367",
    "addr:housenumber":"21600",
    "addr:postcode":"91367",
    "addr:street":"Oxnard St",
    "iso:country":"US",
    "sg:address":"21600 Oxnard St",
    "sg:city":"Woodland Hills",
    "sg:classifiers":[
        {
            "category":"Professional",
            "subcategory":"Lawyer & Legal Services",
            "type":"Services"
        }
    ],
    "sg:phone":"+1 818 348 0665",
    "sg:postcode":"91367",
    "sg:province":"CA",
    "wof:name":"Lee Hecht Harrison",
    "wof:placetype":"venue"
},
  "geometry": {"coordinates":[-118.600138,34.179042],"type":"Point"}
}