{
  "type": "Feature",
  "properties": {
    "addr:full":"2260 Rutherford Rd Ste 110 Carlsbad CA 92008",
    "addr:housenumber":"2260",
    "addr:postcode":"92008",
    "addr:street":"Rutherford Rd Ste 110",
    "iso:country":"US",
    "sg:address":"2260 Rutherford Rd Ste 110",
    "sg:city":"Carlsbad",
    "sg:classifiers":[
        {
            "category":"Professional",
            "subcategory":"Computer Services",
            "type":"Services"
        }
    ],
    "sg:phone":"+1 760 692 5200",
    "sg:postcode":"92008",
    "sg:province":"CA",
    "sg:tags":[
        "repair"
    ],
    "sg:website":"www.horizoncomputers.com",
    "wof:name":"Horizon Computer Resources",
    "wof:placetype":"venue"
},
  "geometry": {"coordinates":[-117.27721699999999,33.131903],"type":"Point"}
}