{
  "type": "Feature",
  "properties": {
    "iso:country":"US",
    "sg:address":"1147 S Beverly Dr",
    "sg:city":"Los Angeles",
    "sg:classifiers":[
        {
            "category":"Travel",
            "subcategory":"Travel Agent",
            "type":"Entertainment"
        }
    ],
    "sg:phone":"+1 310 277 0484",
    "sg:postcode":"90035",
    "sg:province":"CA",
    "sg:tags":[
        "agency",
        "bureau"
    ],
    "wof:name":"Maryland Travel",
    "wof:placetype":"venue"
},
  "geometry": {"coordinates":[-118.395809,34.055759],"type":"Point"}
}