{
  "type": "Feature",
  "properties": {
    "addr:full":"1600 Bryant St San Francisco CA 94103",
    "addr:housenumber":"1600",
    "addr:postcode":"94103",
    "addr:street":"Bryant St",
    "iso:country":"US",
    "sg:address":"1600 Bryant St",
    "sg:city":"San Francisco",
    "sg:classifiers":[
        {
            "category":"Government",
            "subcategory":"Post Office",
            "type":"Public Place"
        }
    ],
    "sg:phone":"+1 415 621 8646",
    "sg:postcode":"94103",
    "sg:province":"CA",
    "wof:name":"Mission Annex Station",
    "wof:placetype":"venue"
},
  "geometry": {"coordinates":[-122.410487,37.765606],"type":"Point"}
}