{
  "type": "Feature",
  "properties": {
    "addr:full":"6601 Owens Dr Pleasanton CA 94588",
    "addr:housenumber":"6601",
    "addr:postcode":"94588",
    "addr:street":"Owens Dr",
    "iso:country":"US",
    "sg:address":"6601 Owens Dr",
    "sg:city":"Pleasanton",
    "sg:classifiers":[
        {
            "category":"Wholesale",
            "subcategory":"Groceries",
            "type":"Manufacturing & Wholesale Goods"
        }
    ],
    "sg:phone":"+1 925 463 8154",
    "sg:postcode":"94588",
    "sg:province":"CA",
    "wof:name":"Coca-Cola",
    "wof:placetype":"venue"
},
  "geometry": {"coordinates":[-121.909469,37.697379],"type":"Point"}
}