{
  "type": "Feature",
  "properties": {
    "iso:country":"US",
    "sg:address":"1029 E Sequoia Dr",
    "sg:city":"Dinuba",
    "sg:classifiers":[
        {
            "category":"Professional",
            "subcategory":"Employment Agencies",
            "type":"Services"
        }
    ],
    "sg:phone":"+1 559 591 3855",
    "sg:postcode":"93618",
    "sg:province":"CA",
    "sg:tags":[
        "opportunity"
    ],
    "wof:name":"Healthcare Staffing",
    "wof:placetype":"venue"
},
  "geometry": {"coordinates":[-119.384802,36.554762],"type":"Point"}
}