{
  "type": "Feature",
  "properties": {
    "addr:full":"3922 Forni Rd Placerville CA 95667",
    "addr:housenumber":"3922",
    "addr:postcode":"95667",
    "addr:street":"Forni Rd",
    "iso:country":"US",
    "sg:address":"3922 Forni Rd",
    "sg:city":"Placerville",
    "sg:classifiers":[
        {
            "category":"Recreation",
            "type":"Entertainment"
        }
    ],
    "sg:phone":"+1 530 622 0977",
    "sg:postcode":"95667",
    "sg:province":"CA",
    "sg:tags":[
        "psychic",
        "medium"
    ],
    "wof:name":"Gold Rush Ghosts",
    "wof:placetype":"venue"
},
  "geometry": {"coordinates":[-120.831653,38.703747],"type":"Point"}
}