{
  "type": "Feature",
  "properties": {
    "addr:full":"108 S San Pedro St Los Angeles CA 90012",
    "addr:housenumber":"108",
    "addr:postcode":"90012",
    "addr:street":"S San Pedro St",
    "iso:country":"US",
    "sg:address":"108 S San Pedro St",
    "sg:city":"Los Angeles",
    "sg:classifiers":[
        {
            "category":"Professional",
            "subcategory":"Lawyer & Legal Services",
            "type":"Services"
        }
    ],
    "sg:phone":"+1 213 613 9941",
    "sg:postcode":"90012",
    "sg:province":"CA",
    "wof:name":"Get Legal Immagration",
    "wof:placetype":"venue"
},
  "geometry": {"coordinates":[-118.241997,34.061501],"type":"Point"}
}