{
  "type": "Feature",
  "properties": {
    "iso:country":"US",
    "sg:address":"121 Nu",
    "sg:city":"Lincoln",
    "sg:classifiers":[
        {
            "category":"Education",
            "subcategory":"University",
            "type":"Public Place"
        }
    ],
    "sg:phone":"+1 402 472 7331",
    "sg:postcode":"68502",
    "sg:province":"NE",
    "sg:tags":[
        "college"
    ],
    "wof:name":"University of Nebraska-Lincoln",
    "wof:placetype":"venue"
},
  "geometry": {"coordinates":[-118.327671,34.162341],"type":"Point"}
}