{
  "type": "Feature",
  "properties": {
    "addr:full":"1451 W Florence Avenue Los Angeles CA 90047",
    "addr:housenumber":"1451",
    "addr:postcode":"90047",
    "addr:street":"W Florence Avenue",
    "iso:country":"US",
    "sg:address":"1451 W Florence Avenue",
    "sg:city":"Los Angeles",
    "sg:classifiers":[
        {
            "category":"Home & Garden",
            "subcategory":"Furniture",
            "type":"Retail Goods"
        }
    ],
    "sg:phone":"+1 323 751 7336",
    "sg:postcode":"90047",
    "sg:province":"CA",
    "sg:tags":[
        "store"
    ],
    "wof:name":"Zuper Discount Furniture",
    "wof:placetype":"venue"
},
  "geometry": {"coordinates":[-118.30228200000001,33.974465],"type":"Point"}
}