{
  "type": "Feature",
  "properties": {
    "addr:full":"6610 Flanders Dr San Diego CA 92121",
    "addr:housenumber":"6610",
    "addr:postcode":"92121",
    "addr:street":"Flanders Dr",
    "iso:country":"US",
    "sg:address":"6610 Flanders Dr",
    "sg:city":"San Diego",
    "sg:classifiers":[
        {
            "category":"Professional",
            "subcategory":"Employment Agencies",
            "type":"Services"
        }
    ],
    "sg:phone":"+1 858 587 9400",
    "sg:postcode":"92121",
    "sg:province":"CA",
    "sg:tags":[
        "opportunity"
    ],
    "wof:name":"Culver Careers",
    "wof:placetype":"venue"
},
  "geometry": {"coordinates":[-117.17666699999999,32.904247],"type":"Point"}
}