{
  "type": "Feature",
  "properties": {
    "addr:full":"3033 Wabash Ave Los Angeles CA 90063",
    "addr:housenumber":"3033",
    "addr:postcode":"90063",
    "addr:street":"Wabash Ave",
    "iso:country":"US",
    "sg:address":"3033 Wabash Ave",
    "sg:city":"Los Angeles",
    "sg:classifiers":[
        {
            "category":"Food & Beverages",
            "subcategory":"Groceries & Convenience Stores",
            "type":"Retail Goods"
        }
    ],
    "sg:phone":"+1 323 261 6942",
    "sg:postcode":"90063",
    "sg:province":"CA",
    "sg:tags":[
        "grocer"
    ],
    "wof:name":"Serrano's Produce",
    "wof:placetype":"venue"
},
  "geometry": {"coordinates":[-118.195365,34.049447],"type":"Point"}
}