{
  "type": "Feature",
  "properties": {
    "addr:full":"5678 N Palm Ave Fresno CA 93704",
    "addr:housenumber":"5678",
    "addr:postcode":"93704",
    "addr:street":"N Palm Ave",
    "iso:country":"US",
    "sg:address":"5678 N Palm Ave",
    "sg:city":"Fresno",
    "sg:classifiers":[
        {
            "category":"Education",
            "subcategory":"Special Training",
            "type":"Public Place"
        }
    ],
    "sg:phone":"+1 559 432 4482",
    "sg:postcode":"93704",
    "sg:province":"CA",
    "sg:tags":[
        "tutoring"
    ],
    "wof:name":"Kumon Center Of Fresno",
    "wof:placetype":"venue"
},
  "geometry": {"coordinates":[-119.808273,36.819611],"type":"Point"}
}