{
  "type": "Feature",
  "properties": {
    "iso:country":"US",
    "sg:address":"5300 Katella Ave",
    "sg:city":"Los Alamitos",
    "sg:classifiers":[
        {
            "category":"Restaurant",
            "type":"Food & Drink"
        }
    ],
    "sg:phone":"+1 714 827 7443",
    "sg:postcode":"90720",
    "sg:province":"CA",
    "wof:name":"Winners's Circle",
    "wof:placetype":"venue"
},
  "geometry": {"coordinates":[-118.040001,33.802799],"type":"Point"}
}