{
  "type": "Feature",
  "properties": {
    "iso:country":"US",
    "sg:address":"784 Noriega Way",
    "sg:city":"Pacifica",
    "sg:classifiers":[
        {
            "category":"Shopping",
            "subcategory":"Florist",
            "type":"Retail Goods"
        }
    ],
    "sg:phone":"+1 650 589 4005",
    "sg:postcode":"94044",
    "sg:province":"CA",
    "wof:name":"Bella Cose Florist",
    "wof:placetype":"venue"
},
  "geometry": {"coordinates":[-122.500807,37.591346],"type":"Point"}
}