{
  "type": "Feature",
  "properties": {
    "iso:country":"US",
    "sg:address":"270 Bristol St Ste 112",
    "sg:city":"Costa Mesa",
    "sg:classifiers":[
        {
            "category":"Food & Beverages",
            "subcategory":"Bakery",
            "type":"Retail Goods"
        }
    ],
    "sg:phone":"+1 714 751 3566",
    "sg:postcode":"92626",
    "sg:province":"CA",
    "sg:tags":[
        "sandwich"
    ],
    "wof:name":"Tummy Stuffer",
    "wof:placetype":"venue"
},
  "geometry": {"coordinates":[-117.879997,33.6684],"type":"Point"}
}