{
  "type": "Feature",
  "properties": {
    "addr:full":"5001 E Commerce Center Dr Bakersfield CA 93309",
    "addr:housenumber":"5001",
    "addr:postcode":"93309",
    "addr:street":"E Commerce Center Dr",
    "iso:country":"US",
    "sg:address":"5001 E Commerce Center Dr",
    "sg:city":"Bakersfield",
    "sg:classifiers":[
        {
            "category":"Professional",
            "subcategory":"Accounting & Tax Preparation",
            "type":"Services"
        }
    ],
    "sg:phone":"+1 661 631 0811",
    "sg:postcode":"93309",
    "sg:province":"CA",
    "sg:tags":[
        "return",
        "filing"
    ],
    "wof:name":"Progressive Business Svc",
    "wof:placetype":"venue"
},
  "geometry": {"coordinates":[-119.059679,35.363344],"type":"Point"}
}