{
  "type": "Feature",
  "properties": {
    "iso:country":"US",
    "sg:address":"48 Elm Ave",
    "sg:city":"Galt",
    "sg:classifiers":[
        {
            "category":"Building & Trades",
            "subcategory":"Plumbing",
            "type":"Services"
        }
    ],
    "sg:phone":"+1 209 745 0478",
    "sg:postcode":"95632",
    "sg:province":"CA",
    "sg:tags":[
        "plumbing",
        "contractor"
    ],
    "wof:name":"Galt Plumbing & Drain Cleaning",
    "wof:placetype":"venue"
},
  "geometry": {"coordinates":[-121.306057,38.262037],"type":"Point"}
}