{
  "type": "Feature",
  "properties": {
    "iso:country":"US",
    "sg:address":"3130 W 6th Street",
    "sg:city":"Los Angeles",
    "sg:classifiers":[
        {
            "category":"Health Services",
            "subcategory":"Dentist",
            "type":"Services"
        }
    ],
    "sg:phone":"+1 213 382 5650",
    "sg:postcode":"90020",
    "sg:province":"CA",
    "wof:name":"Roxas M Leoncia DMD",
    "wof:placetype":"venue"
},
  "geometry": {"coordinates":[-118.28942000000001,34.063808],"type":"Point"}
}