{
  "type": "Feature",
  "properties": {
    "iso:country":"US",
    "sg:address":"1409 W Wrightwood Dr",
    "sg:city":"San Bernardino",
    "sg:classifiers":[
        {
            "category":"Professional",
            "type":"Services"
        }
    ],
    "sg:phone":"+1 909 880 3075",
    "sg:postcode":"92407",
    "sg:province":"CA",
    "sg:tags":[
        "establishment"
    ],
    "wof:name":"Geared Up",
    "wof:placetype":"venue"
},
  "geometry": {"coordinates":[-117.318228,34.17306],"type":"Point"}
}