{
  "type": "Feature",
  "properties": {
    "addr:full":"2381 E Main St Barstow CA 92311",
    "addr:housenumber":"2381",
    "addr:postcode":"92311",
    "addr:street":"E Main St",
    "iso:country":"US",
    "sg:address":"2381 E Main St",
    "sg:city":"Barstow",
    "sg:classifiers":[
        {
            "category":"Wholesale",
            "subcategory":"Auto Parts",
            "type":"Manufacturing & Wholesale Goods"
        }
    ],
    "sg:phone":"+1 760 256 6300",
    "sg:postcode":"92311",
    "sg:province":"CA",
    "sg:tags":[
        "automobile",
        "wrecking"
    ],
    "wof:name":"A-1 Auto Wreckers",
    "wof:placetype":"venue"
},
  "geometry": {"coordinates":[-116.99373799999999,34.885436],"type":"Point"}
}