{
  "type": "Feature",
  "properties": {
    "addr:full":"31548 Peterson Rd Mc Farland CA 93250",
    "addr:housenumber":"31548",
    "addr:postcode":"93250",
    "addr:street":"Peterson Rd",
    "iso:country":"US",
    "sg:address":"31548 Peterson Rd",
    "sg:city":"Mc Farland",
    "sg:classifiers":[
        {
            "category":"Farming",
            "subcategory":"Farm & Veterinary Services",
            "type":"Manufacturing & Wholesale Goods"
        }
    ],
    "sg:phone":"+1 661 792 6468",
    "sg:postcode":"93250",
    "sg:province":"CA",
    "sg:tags":[
        "crop",
        "harvesting"
    ],
    "wof:name":"Casa Cristal Nursery Inc",
    "wof:placetype":"venue"
},
  "geometry": {"coordinates":[-119.230003,35.703465],"type":"Point"}
}