{
  "type": "Feature",
  "properties": {
    "addr:full":"420 California St Suisun City CA 94585",
    "addr:housenumber":"420",
    "addr:postcode":"94585",
    "addr:street":"California St",
    "iso:country":"US",
    "sg:address":"420 California St",
    "sg:city":"Suisun City",
    "sg:phone":"+1 707 428 0409",
    "sg:postcode":"94585",
    "sg:province":"CA",
    "sg:tags":[
        "oil"
    ],
    "wof:name":"Pennzoil Products Co",
    "wof:placetype":"venue"
},
  "geometry": {"coordinates":[-122.04071399999999,38.237812],"type":"Point"}
}