{
  "type": "Feature",
  "properties": {
    "addr:full":"2610 Abedul St Carlsbad CA 92009",
    "addr:housenumber":"2610",
    "addr:postcode":"92009",
    "addr:street":"Abedul St",
    "iso:country":"US",
    "sg:address":"2610 Abedul St",
    "sg:city":"Carlsbad",
    "sg:classifiers":[
        {
            "category":"Manufacturing",
            "subcategory":"Toys & Sporting Goods",
            "type":"Manufacturing & Wholesale Goods"
        }
    ],
    "sg:phone":"+1 760 431 0762",
    "sg:postcode":"92009",
    "sg:province":"CA",
    "sg:tags":[
        "mfg"
    ],
    "wof:name":"Brooks Mini Crafts",
    "wof:placetype":"venue"
},
  "geometry": {"coordinates":[-117.249118,33.107324],"type":"Point"}
}