{
  "type": "Feature",
  "properties": {
    "iso:country":"US",
    "sg:address":"1615 Murray Canyon Rd",
    "sg:city":"San Diego",
    "sg:classifiers":[
        {
            "category":"Communications",
            "subcategory":"Television Station",
            "type":"Services"
        }
    ],
    "sg:phone":"+1 619 296 2949",
    "sg:postcode":"92108",
    "sg:province":"CA",
    "wof:name":"Jefferson-Pilot",
    "wof:placetype":"venue"
},
  "geometry": {"coordinates":[-117.15904500000001,32.774404],"type":"Point"}
}