{
  "type": "Feature",
  "properties": {
    "addr:full":"4533 Hidalgo Ave Atascadero CA 93422",
    "addr:housenumber":"4533",
    "addr:postcode":"93422",
    "addr:street":"Hidalgo Ave",
    "iso:country":"US",
    "sg:address":"4533 Hidalgo Ave",
    "sg:city":"Atascadero",
    "sg:classifiers":[
        {
            "category":"Manufacturing",
            "subcategory":"Metals",
            "type":"Manufacturing & Wholesale Goods"
        }
    ],
    "sg:phone":"+1 805 466 4503",
    "sg:postcode":"93422",
    "sg:province":"CA",
    "wof:name":"Chucks Metal Polishing",
    "wof:placetype":"venue"
},
  "geometry": {"coordinates":[-120.6661,35.508604],"type":"Point"}
}