{
  "type": "Feature",
  "properties": {
    "addr:full":"25502 Jeronimo Rd Mission Viejo CA 92691",
    "addr:housenumber":"25502",
    "addr:postcode":"92691",
    "addr:street":"Jeronimo Rd",
    "iso:country":"US",
    "sg:address":"25502 Jeronimo Rd",
    "sg:city":"Mission Viejo",
    "sg:classifiers":[
        {
            "category":"Fast Food",
            "type":"Food & Drink"
        }
    ],
    "sg:phone":"+1 949 472 4690",
    "sg:postcode":"92691",
    "sg:province":"CA",
    "sg:website":"www.sonicdrivein.com",
    "wof:name":"Sonic Drive-In",
    "wof:placetype":"venue"
},
  "geometry": {"coordinates":[-117.685112,33.622433],"type":"Point"}
}