{
  "type": "Feature",
  "properties": {
    "addr:full":"1784 Picasso Ave Ste D Davis CA 95618",
    "addr:housenumber":"1784",
    "addr:postcode":"95618",
    "addr:street":"Picasso Ave Ste D",
    "iso:country":"US",
    "sg:address":"1784 Picasso Ave Ste D",
    "sg:city":"Davis",
    "sg:classifiers":[
        {
            "category":"Professional",
            "subcategory":"Employment Agencies",
            "type":"Services"
        },
        {
            "category":"Organizations",
            "subcategory":"Community Association",
            "type":"Services"
        }
    ],
    "sg:phone":"+1 530 753 3142",
    "sg:postcode":"95618",
    "sg:province":"CA",
    "sg:tags":[
        "employer"
    ],
    "wof:name":"American Society For Enology & Viticulture",
    "wof:placetype":"venue"
},
  "geometry": {"coordinates":[-121.729671,38.564183],"type":"Point"}
}