{
  "type": "Feature",
  "properties": {
    "addr:full":"11961 el Encanto Ln Yucaipa CA 92399",
    "addr:housenumber":"11961",
    "addr:postcode":"92399",
    "addr:street":"El Encanto Ln",
    "iso:country":"US",
    "sg:address":"11961 el Encanto Ln",
    "sg:city":"Yucaipa",
    "sg:classifiers":[
        {
            "category":"Recreation",
            "type":"Entertainment"
        }
    ],
    "sg:phone":"+1 909 790 0352",
    "sg:postcode":"92399",
    "sg:province":"CA",
    "sg:tags":[
        "amusement"
    ],
    "wof:name":"Wristlock Racing Advancements",
    "wof:placetype":"venue"
},
  "geometry": {"coordinates":[-117.044083,34.036559],"type":"Point"}
}