{
  "type": "Feature",
  "properties": {
    "iso:country":"US",
    "sg:address":"10365 Baron Dr",
    "sg:city":"San Diego",
    "sg:classifiers":[
        {
            "category":"Professional",
            "subcategory":"Management & Consulting",
            "type":"Services"
        }
    ],
    "sg:phone":"+1 858 689 9956",
    "sg:postcode":"92126",
    "sg:province":"CA",
    "sg:tags":[
        "consultant",
        "business"
    ],
    "wof:name":"Analyzed Business Consultants",
    "wof:placetype":"venue"
},
  "geometry": {"coordinates":[-117.13757,32.906749],"type":"Point"}
}