{
  "type": "Feature",
  "properties": {
    "iso:country":"US",
    "sg:address":"1572 N Batavia St",
    "sg:city":"Orange",
    "sg:classifiers":[
        {
            "category":"Wholesale",
            "subcategory":"Motor Vehicles",
            "type":"Manufacturing & Wholesale Goods"
        }
    ],
    "sg:phone":"+1 714 685 3310",
    "sg:postcode":"92867",
    "sg:province":"CA",
    "sg:tags":[
        "establishment"
    ],
    "wof:name":"Johnson Equipment Company",
    "wof:placetype":"venue"
},
  "geometry": {"coordinates":[-117.862404,33.809252],"type":"Point"}
}