{
  "type": "Feature",
  "properties": {
    "iso:country":"US",
    "sg:address":"13658 Hawthorne Blvd",
    "sg:city":"Hawthorne",
    "sg:classifiers":[
        {
            "category":"Social Services",
            "type":"Services"
        }
    ],
    "sg:phone":"+1 310 675 2158",
    "sg:postcode":"90250",
    "sg:province":"CA",
    "sg:tags":[
        "worker"
    ],
    "wof:name":"Ahmad Kausar",
    "wof:placetype":"venue"
},
  "geometry": {"coordinates":[-118.352276,33.908507],"type":"Point"}
}