{
  "type": "Feature",
  "properties": {
    "addr:full":"3600 American River Dr Ste 100 Sacramento CA 95864",
    "addr:housenumber":"3600",
    "addr:postcode":"95864",
    "addr:street":"American River Dr Ste 100",
    "iso:country":"US",
    "sg:address":"3600 American River Dr Ste 100",
    "sg:city":"Sacramento",
    "sg:classifiers":[
        {
            "category":"Professional",
            "subcategory":"Lawyer & Legal Services",
            "type":"Services"
        }
    ],
    "sg:phone":"+1 916 979 1917",
    "sg:postcode":"95864",
    "sg:province":"CA",
    "wof:name":"Mark A. Doughty Accident Lawyers",
    "wof:placetype":"venue"
},
  "geometry": {"coordinates":[-121.380313,38.569905],"type":"Point"}
}