{
  "type": "Feature",
  "properties": {
    "iso:country":"US",
    "sg:address":"391 S Orange Grove Blvd",
    "sg:city":"Pasadena",
    "sg:classifiers":[
        {
            "category":"Organizations",
            "subcategory":"Non-profit Organization",
            "type":"Services"
        }
    ],
    "sg:phone":"+1 626 449 4100",
    "sg:postcode":"91105",
    "sg:province":"CA",
    "sg:website":"www.tournamentofroses.com",
    "wof:name":"Tournament Of Roses Associate",
    "wof:placetype":"venue"
},
  "geometry": {"coordinates":[-118.159254,34.138501],"type":"Point"}
}