{
  "type": "Feature",
  "properties": {
    "iso:country":"US",
    "sg:address":"25302 Jeronimo Rd",
    "sg:city":"Lake Forest",
    "sg:classifiers":[
        {
            "category":"Autos & Motor Vehicles",
            "subcategory":"Auto Supplies",
            "type":"Retail Goods"
        }
    ],
    "sg:phone":"+1 949 458 9111",
    "sg:postcode":"92630",
    "sg:province":"CA",
    "sg:tags":[
        "automobile",
        "parts"
    ],
    "wof:name":"Quigley Auto Parts",
    "wof:placetype":"venue"
},
  "geometry": {"coordinates":[-117.68911,33.627284],"type":"Point"}
}