{
  "type": "Feature",
  "properties": {
    "iso:country":"US",
    "sg:address":"11817 Wicks St",
    "sg:city":"Sun Valley",
    "sg:classifiers":[
        {
            "category":"Building & Trades",
            "subcategory":"Construction",
            "type":"Services"
        }
    ],
    "sg:phone":"+1 818 767 2700",
    "sg:postcode":"91352",
    "sg:province":"CA",
    "sg:tags":[
        "material",
        "contractor"
    ],
    "sg:website":"www.xsurfaces.com",
    "wof:name":"Exquisite Surfaces",
    "wof:placetype":"venue"
},
  "geometry": {"coordinates":[-118.39384200000001,34.234049],"type":"Point"}
}