{
  "type": "Feature",
  "properties": {
    "addr:full":"8735 Laurel Canyon Blvd Sun Valley CA 91352",
    "addr:housenumber":"8735",
    "addr:postcode":"91352",
    "addr:street":"Laurel Canyon Blvd",
    "iso:country":"US",
    "sg:address":"8735 Laurel Canyon Blvd",
    "sg:city":"Sun Valley",
    "sg:classifiers":[
        {
            "category":"Social Services",
            "subcategory":"Child Care",
            "type":"Services"
        }
    ],
    "sg:phone":"+1 818 504 7315",
    "sg:postcode":"91352",
    "sg:province":"CA",
    "wof:name":"L A Child Care & Dev Counsel",
    "wof:placetype":"venue"
},
  "geometry": {"coordinates":[-118.398872,34.226937],"type":"Point"}
}