{
  "type": "Feature",
  "properties": {
    "iso:country":"US",
    "sg:address":"2700 El Camino Real",
    "sg:city":"Santa Clara",
    "sg:classifiers":[
        {
            "category":"Home & Garden",
            "subcategory":"Household Appliances",
            "type":"Retail Goods"
        },
        {
            "category":"Personal",
            "type":"Services"
        }
    ],
    "sg:phone":"+1 408 241 2001",
    "sg:postcode":"95051",
    "sg:province":"CA",
    "sg:tags":[
        "repair",
        "sewing",
        "alteration"
    ],
    "wof:name":"Moonlite Vacuum & Sewing Center",
    "wof:placetype":"venue"
},
  "geometry": {"coordinates":[-121.975998,37.352402],"type":"Point"}
}