{
  "type": "Feature",
  "properties": {
    "addr:full":"13125 Ventura Blvd Studio City CA 91604",
    "addr:housenumber":"13125",
    "addr:postcode":"91604",
    "addr:street":"Ventura Blvd",
    "iso:country":"US",
    "sg:address":"13125 Ventura Blvd",
    "sg:city":"Studio City",
    "sg:classifiers":[
        {
            "category":"Retail",
            "subcategory":"Pet Boarding",
            "type":"Services"
        }
    ],
    "sg:phone":"+1 818 986 5700",
    "sg:postcode":"91604",
    "sg:province":"CA",
    "sg:tags":[
        "boarding/pet",
        "sitting"
    ],
    "wof:name":"Four Paws Day Care",
    "wof:placetype":"venue"
},
  "geometry": {"coordinates":[-118.418657,34.146082],"type":"Point"}
}