{
  "type": "Feature",
  "properties": {
    "addr:full":"1500 Wallace Ave San Francisco CA 94124",
    "addr:housenumber":"1500",
    "addr:postcode":"94124",
    "addr:street":"Wallace Ave",
    "iso:country":"US",
    "sg:address":"1500 Wallace Ave",
    "sg:city":"San Francisco",
    "sg:classifiers":[
        {
            "category":"Building & Trades",
            "subcategory":"Construction",
            "type":"Services"
        }
    ],
    "sg:phone":"+1 415 822 2259",
    "sg:postcode":"94124",
    "sg:province":"CA",
    "sg:tags":[
        "contractor"
    ],
    "wof:name":"Nayoung Sheet Metal",
    "wof:placetype":"venue"
},
  "geometry": {"coordinates":[-122.38925,37.726726],"type":"Point"}
}