{
  "type": "Feature",
  "properties": {
    "addr:full":"5030 Prairie Way Antioch CA 94531",
    "addr:housenumber":"5030",
    "addr:postcode":"ca 94531",
    "addr:street":"Prairie Way",
    "iso:country":"US",
    "sg:address":"5030 Prairie Way",
    "sg:city":"Antioch",
    "sg:classifiers":[
        {
            "category":"Building & Trades",
            "subcategory":"Construction",
            "type":"Services"
        }
    ],
    "sg:phone":"+1 925 776 7524",
    "sg:postcode":"94531",
    "sg:province":"CA",
    "sg:tags":[
        "concrete",
        "contractor"
    ],
    "wof:name":"Concrete Precast Products",
    "wof:placetype":"venue"
},
  "geometry": {"coordinates":[-121.765946,37.96017],"type":"Point"}
}