{
  "type": "Feature",
  "properties": {
    "iso:country":"US",
    "sg:address":"4401 E Kirkwood Ave",
    "sg:city":"Orange",
    "sg:classifiers":[
        {
            "category":"Building & Trades",
            "subcategory":"Construction",
            "type":"Services"
        }
    ],
    "sg:phone":"+1 714 289 9584",
    "sg:postcode":"92869",
    "sg:province":"CA",
    "sg:tags":[
        "contractor"
    ],
    "wof:name":"Alta General Contracting",
    "wof:placetype":"venue"
},
  "geometry": {"coordinates":[-117.806096,33.775102],"type":"Point"}
}