{
  "type": "Feature",
  "properties": {
    "iso:country":"US",
    "sg:address":"9050 Burke St",
    "sg:city":"Pico Rivera",
    "sg:classifiers":[
        {
            "category":"Real Estate",
            "subcategory":"Real Estate Operator",
            "type":"Services"
        }
    ],
    "sg:phone":"+1 562 948 4926",
    "sg:postcode":"90660",
    "sg:province":"CA",
    "sg:tags":[
        "apartment"
    ],
    "wof:name":"Collaro Apartments",
    "wof:placetype":"venue"
},
  "geometry": {"coordinates":[-118.103996,33.9697],"type":"Point"}
}