{
  "type": "Feature",
  "properties": {
    "addr:full":"37537 Glenmoor Dr Fremont CA 94536",
    "addr:housenumber":"37537",
    "addr:postcode":"94536",
    "addr:street":"Glenmoor Dr",
    "iso:country":"US",
    "sg:address":"37537 Glenmoor Dr",
    "sg:city":"Fremont",
    "sg:classifiers":[
        {
            "category":"Autos & Motor Vehicles",
            "subcategory":"Automobile Sales",
            "type":"Retail Goods"
        }
    ],
    "sg:phone":"+1 510 713 1001",
    "sg:postcode":"94536",
    "sg:province":"CA",
    "sg:tags":[
        "car",
        "dealer"
    ],
    "wof:name":"Advanced Auto Sales",
    "wof:placetype":"venue"
},
  "geometry": {"coordinates":[-122.010882,37.549394],"type":"Point"}
}