{
  "type": "Feature",
  "properties": {
    "iso:country":"US",
    "sg:address":"32 Littlecroft Ln",
    "sg:city":"Oroville",
    "sg:classifiers":[
        {
            "category":"Retail",
            "subcategory":"Auto Repair",
            "type":"Services"
        }
    ],
    "sg:phone":"+1 530 519 7329",
    "sg:postcode":"95966",
    "sg:province":"CA",
    "sg:tags":[
        "repairing",
        "automobile"
    ],
    "wof:name":"Mobile Auto Clinic",
    "wof:placetype":"venue"
},
  "geometry": {"coordinates":[-121.44680099999999,39.489723],"type":"Point"}
}