{
  "type": "Feature",
  "properties": {
    "addr:full":"3058 W San Gabriel Ave Fresno CA 93722",
    "addr:housenumber":"3058",
    "addr:postcode":"93722",
    "addr:street":"W San Gabriel Ave",
    "iso:country":"US",
    "sg:address":"3058 W San Gabriel Ave",
    "sg:city":"Fresno",
    "sg:classifiers":[
        {
            "category":"Freight",
            "type":"Transportation"
        }
    ],
    "sg:phone":"+1 559 351 3995",
    "sg:postcode":"93722",
    "sg:province":"CA",
    "sg:tags":[
        "trucking"
    ],
    "wof:name":"F & A Trucking",
    "wof:placetype":"venue"
},
  "geometry": {"coordinates":[-119.84521100000001,36.803599],"type":"Point"}
}