{
  "type": "Feature",
  "properties": {
    "iso:country":"US",
    "sg:address":"3058 W San Gabriel Ave",
    "sg:city":"Fresno",
    "sg:classifiers":[
        {
            "category":"Freight",
            "type":"Transportation"
        }
    ],
    "sg:phone":"+1 559 351 3995",
    "sg:postcode":"93722",
    "sg:province":"CA",
    "sg:tags":[
        "trucking"
    ],
    "wof:name":"F & A Trucking",
    "wof:placetype":"venue"
},
  "geometry": {"coordinates":[-119.845211,36.803599],"type":"Point"}
}