{
  "type": "Feature",
  "properties": {
    "iso:country":"US",
    "sg:address":"2808 Morningside Ter",
    "sg:city":"Escondido",
    "sg:classifiers":[
        {
            "category":"Wholesale",
            "subcategory":"Plants",
            "type":"Manufacturing & Wholesale Goods"
        }
    ],
    "sg:phone":"+1 760 745 9428",
    "sg:postcode":"92029",
    "sg:province":"CA",
    "sg:tags":[
        "supply"
    ],
    "wof:name":"Cottage Gardens",
    "wof:placetype":"venue"
},
  "geometry": {"coordinates":[-117.094903,33.078672],"type":"Point"}
}