{
  "type": "Feature",
  "properties": {
    "iso:country":"US",
    "sg:address":"752 College Ave",
    "sg:city":"Menlo Park",
    "sg:classifiers":[
        {
            "category":"Professional",
            "type":"Services"
        }
    ],
    "sg:phone":"+1 650 326 6192",
    "sg:postcode":"94025",
    "sg:province":"CA",
    "wof:name":"3d Audio Corporation",
    "wof:placetype":"venue"
},
  "geometry": {"coordinates":[-122.177143,37.448995],"type":"Point"}
}