{
  "type": "Feature",
  "properties": {
    "addr:full":"3364 Greenbrook Pl Marina CA 93933",
    "addr:housenumber":"3364",
    "addr:postcode":"93933",
    "addr:street":"Greenbrook Pl",
    "iso:country":"US",
    "sg:address":"3364 Greenbrook Pl",
    "sg:city":"Marina",
    "sg:classifiers":[
        {
            "category":"Building & Trades",
            "subcategory":"Construction",
            "type":"Services"
        }
    ],
    "sg:phone":"+1 831 384 0763",
    "sg:postcode":"93933",
    "sg:province":"CA",
    "sg:tags":[
        "roofing",
        "contractor"
    ],
    "wof:name":"Coastal Roof Systems",
    "wof:placetype":"venue"
},
  "geometry": {"coordinates":[-121.798813,36.701609],"type":"Point"}
}