{
  "type": "Feature",
  "properties": {
    "addr:full":"2337 Otay Center Dr San Diego CA 92154",
    "addr:housenumber":"2337",
    "addr:postcode":"92154",
    "addr:street":"Otay Center Dr",
    "iso:country":"US",
    "sg:address":"2337 Otay Center Dr",
    "sg:city":"San Diego",
    "sg:classifiers":[
        {
            "category":"Freight",
            "type":"Transportation"
        }
    ],
    "sg:phone":"+1 619 671 0588",
    "sg:postcode":"92154",
    "sg:province":"CA",
    "sg:tags":[
        "wood",
        "mfg"
    ],
    "wof:name":"MS Carriers Inc",
    "wof:placetype":"venue"
},
  "geometry": {"coordinates":[-116.94238199999999,32.554265],"type":"Point"}
}