{
  "type": "Feature",
  "properties": {
    "iso:country":"US",
    "sg:address":"4160 Saviers Rd",
    "sg:city":"Oxnard",
    "sg:classifiers":[
        {
            "category":"Retail",
            "subcategory":"Auto Repair",
            "type":"Services"
        }
    ],
    "sg:phone":"+1 805 488 1414",
    "sg:postcode":"93033",
    "sg:province":"CA",
    "sg:tags":[
        "wrecker"
    ],
    "wof:name":"Prime Towing",
    "wof:placetype":"venue"
},
  "geometry": {"coordinates":[-119.177598,34.161306],"type":"Point"}
}