{
  "type": "Feature",
  "properties": {
    "addr:full":"1112 Montana Ave Santa Monica CA 90403",
    "addr:housenumber":"1112",
    "addr:postcode":"90403",
    "addr:street":"Montana Ave",
    "iso:country":"US",
    "sg:address":"1112 Montana Ave",
    "sg:city":"Santa Monica",
    "sg:classifiers":[
        {
            "category":"Shopping",
            "subcategory":"Clothing, Apparel, & Fashions",
            "type":"Retail Goods"
        }
    ],
    "sg:phone":"+1 310 829 5075",
    "sg:postcode":"90403",
    "sg:province":"CA",
    "sg:tags":[
        "infant",
        "wear"
    ],
    "wof:name":"Daisy Mercantile",
    "wof:placetype":"venue"
},
  "geometry": {"coordinates":[-118.497556,34.030148],"type":"Point"}
}