{
  "type": "Feature",
  "properties": {
    "addr:full":"807 State St Santa Barbara CA 93101",
    "addr:housenumber":"807",
    "addr:postcode":"93101",
    "addr:street":"State St",
    "iso:country":"US",
    "sg:address":"807 State St",
    "sg:city":"Santa Barbara",
    "sg:classifiers":[
        {
            "category":"Shopping",
            "subcategory":"Clothing, Apparel, & Fashions",
            "type":"Retail Goods"
        }
    ],
    "sg:phone":"+1 805 899 8100",
    "sg:postcode":"93101",
    "sg:province":"CA",
    "wof:name":"Reference Clothing",
    "wof:placetype":"venue"
},
  "geometry": {"coordinates":[-119.69998699999999,34.419993],"type":"Point"}
}