{
  "type": "Feature",
  "properties": {
    "iso:country":"US",
    "sg:address":"51 Grant Ave",
    "sg:city":"San Francisco",
    "sg:classifiers":[
        {
            "category":"Shopping",
            "subcategory":"Gifts & Souvenirs",
            "type":"Retail Goods"
        }
    ],
    "sg:phone":"+1 415 248 5353",
    "sg:postcode":"94108",
    "sg:province":"CA",
    "sg:tags":[
        "stationery",
        "announcement",
        "card",
        "invitation"
    ],
    "sg:website":"www.paperwhirl.com/",
    "wof:name":"Paperwhirl",
    "wof:placetype":"venue"
},
  "geometry": {"coordinates":[-122.404999,37.7873],"type":"Point"}
}