{
  "type": "Feature",
  "properties": {
    "addr:full":"631 Giguere Ct San Jose CA 95133",
    "addr:housenumber":"631",
    "addr:postcode":"95133",
    "addr:street":"Giguere Ct",
    "iso:country":"US",
    "sg:address":"631 Giguere Ct",
    "sg:city":"San Jose",
    "sg:classifiers":[
        {
            "category":"Restaurant",
            "type":"Food & Drink"
        }
    ],
    "sg:phone":"+1 408 259 3101",
    "sg:postcode":"95133",
    "sg:province":"CA",
    "wof:name":"Ringer Hut Corporate Office",
    "wof:placetype":"venue"
},
  "geometry": {"coordinates":[-121.860629,37.366697],"type":"Point"}
}