{
  "type": "Feature",
  "properties": {
    "addr:full":"2376 Torrance Blvd Torrance CA 90501",
    "addr:housenumber":"2376",
    "addr:postcode":"90501",
    "addr:street":"Torrance Blvd",
    "iso:country":"US",
    "sg:address":"2376 Torrance Blvd",
    "sg:city":"Torrance",
    "sg:classifiers":[
        {
            "category":"Education",
            "subcategory":"Special Training",
            "type":"Public Place"
        }
    ],
    "sg:phone":"+1 310 856 3608",
    "sg:postcode":"90501",
    "sg:province":"CA",
    "sg:tags":[
        "tutoring"
    ],
    "wof:name":"PASS",
    "wof:placetype":"venue"
},
  "geometry": {"coordinates":[-118.325695,33.8363],"type":"Point"}
}