{
  "type": "Feature",
  "properties": {
    "addr:full":"747 W Katella Ave Ste 102 Orange CA 92867",
    "addr:housenumber":"747",
    "addr:postcode":"92867",
    "addr:street":"W Katella Ave Ste 102",
    "iso:country":"US",
    "sg:address":"747 W Katella Ave Ste 102",
    "sg:city":"Orange",
    "sg:classifiers":[
        {
            "category":"Real Estate",
            "subcategory":"Real Estate Services",
            "type":"Services"
        }
    ],
    "sg:phone":"+1 714 639 8100",
    "sg:postcode":"92867",
    "sg:province":"CA",
    "wof:name":"Noble Real Estate",
    "wof:placetype":"venue"
},
  "geometry": {"coordinates":[-117.861,33.809101],"type":"Point"}
}