{
  "type": "Feature",
  "properties": {
    "addr:full":"2105 Hilltop Dr Redding CA 96002",
    "addr:housenumber":"2105",
    "addr:postcode":"96002",
    "addr:street":"Hilltop Dr",
    "iso:country":"US",
    "sg:address":"2105 Hilltop Dr",
    "sg:city":"Redding",
    "sg:classifiers":[
        {
            "category":"Home & Garden",
            "subcategory":"Household Appliances",
            "type":"Retail Goods"
        }
    ],
    "sg:phone":"+1 530 222 4026",
    "sg:postcode":"96002",
    "sg:province":"CA",
    "sg:tags":[
        "machine",
        "sewing"
    ],
    "wof:name":"Perfect Stitch",
    "wof:placetype":"venue"
},
  "geometry": {"coordinates":[-122.35778999999999,40.575582],"type":"Point"}
}