{
  "type": "Feature",
  "properties": {
    "iso:country":"US",
    "sg:address":"12 S 1st St",
    "sg:city":"San Jose",
    "sg:classifiers":[
        {
            "category":"Utilities",
            "subcategory":"Telephone",
            "type":"Services"
        }
    ],
    "sg:phone":"+1 408 295 8825",
    "sg:postcode":"95113",
    "sg:province":"CA",
    "sg:tags":[
        "communication",
        "provider",
        "internet"
    ],
    "wof:name":"News I Cast",
    "wof:placetype":"venue"
},
  "geometry": {"coordinates":[-121.889999,37.335899],"type":"Point"}
}