{
  "type": "Feature",
  "properties": {
    "addr:full":"846 W Valley Blvd Alhambra CA 91803",
    "addr:housenumber":"846",
    "addr:postcode":"91803",
    "addr:street":"W Valley Blvd",
    "iso:country":"US",
    "sg:address":"846 W Valley Blvd",
    "sg:city":"Alhambra",
    "sg:classifiers":[
        {
            "category":"Wholesale",
            "subcategory":"Medical Equipment & Supplies",
            "type":"Manufacturing & Wholesale Goods"
        }
    ],
    "sg:phone":"+1 626 284 8188",
    "sg:postcode":"91803",
    "sg:province":"CA",
    "sg:tags":[
        "physician",
        "surgeon"
    ],
    "wof:name":"Health Care 21",
    "wof:placetype":"venue"
},
  "geometry": {"coordinates":[-118.13258,34.077955],"type":"Point"}
}