{
  "type": "Feature",
  "properties": {
    "iso:country":"US",
    "sg:address":"16620 Pioneer Blvd Ste A",
    "sg:city":"Artesia",
    "sg:classifiers":[
        {
            "category":"Retail",
            "subcategory":"Auto Repair",
            "type":"Services"
        }
    ],
    "sg:phone":"+1 562 926 9783",
    "sg:postcode":"90701",
    "sg:province":"CA",
    "wof:name":"S & H Auto Repair",
    "wof:placetype":"venue"
},
  "geometry": {"coordinates":[-118.08200100000001,33.879799],"type":"Point"}
}