{
  "type": "Feature",
  "properties": {
    "iso:country":"US",
    "sg:address":"633 W Katella Ave",
    "sg:city":"Orange",
    "sg:classifiers":[
        {
            "category":"Wholesale",
            "subcategory":"Durable Goods & Equipment",
            "type":"Manufacturing & Wholesale Goods"
        },
        {
            "category":"Retail",
            "subcategory":"Auto Repair",
            "type":"Services"
        }
    ],
    "sg:phone":"+1 714 633 5290",
    "sg:postcode":"92867",
    "sg:province":"CA",
    "sg:tags":[
        "body",
        "automobile",
        "customizing"
    ],
    "wof:name":"Barker Custom",
    "wof:placetype":"venue"
},
  "geometry": {"coordinates":[-117.85756600000001,33.809108],"type":"Point"}
}