{
  "type": "Feature",
  "properties": {
    "addr:full":"7575 Spy Glass Ave Fresno CA 93711",
    "addr:housenumber":"7575",
    "addr:postcode":"93711",
    "addr:street":"Spy Glass Ave",
    "iso:country":"US",
    "sg:address":"7575 Spy Glass Ave",
    "sg:city":"Fresno",
    "sg:classifiers":[
        {
            "category":"Building & Trades",
            "subcategory":"Construction",
            "type":"Services"
        }
    ],
    "sg:phone":"+1 559 261 1111",
    "sg:postcode":"93711",
    "sg:province":"CA",
    "sg:tags":[
        "home",
        "builder"
    ],
    "wof:name":"Mission Homes",
    "wof:placetype":"venue"
},
  "geometry": {"coordinates":[-119.84833399999999,36.845558],"type":"Point"}
}