{
  "type": "Feature",
  "properties": {
    "iso:country":"US",
    "sg:address":"2498 E Colorado Blvd",
    "sg:city":"Pasadena",
    "sg:classifiers":[
        {
            "category":"Retail",
            "subcategory":"Laundry & Dry Cleaning",
            "type":"Services"
        }
    ],
    "sg:phone":"+1 626 440 9003",
    "sg:postcode":"91107",
    "sg:province":"CA",
    "wof:name":"Bonded Cleaners and Laundry",
    "wof:placetype":"venue"
},
  "geometry": {"coordinates":[-118.09899900000001,34.146],"type":"Point"}
}