{
  "type": "Feature",
  "properties": {
    "addr:full":"715 E Arrow Hwy # C-1 Glendora CA 91740",
    "addr:housenumber":"715",
    "addr:postcode":"91740",
    "addr:street":"E Arrow Hwy # C-1",
    "iso:country":"US",
    "sg:address":"715 E Arrow Hwy # C-1",
    "sg:city":"Glendora",
    "sg:phone":"+1 626 852 0603",
    "sg:postcode":"91740",
    "sg:province":"CA",
    "wof:name":"Sweden Volvo Specialist",
    "wof:placetype":"venue"
},
  "geometry": {"coordinates":[-117.850258,34.106739],"type":"Point"}
}