{
  "type": "Feature",
  "properties": {
    "addr:full":"901 Moraga Rd Ste A Suite 200 Berkeley CA 94549",
    "addr:housenumber":"901",
    "addr:postcode":"94549",
    "addr:street":"Moraga Rd Ste A Suite 200",
    "iso:country":"US",
    "sg:address":"901 Moraga Rd Ste A Suite 200",
    "sg:city":"Berkeley",
    "sg:classifiers":[
        {
            "category":"Health Services",
            "subcategory":"Doctor",
            "type":"Services"
        }
    ],
    "sg:phone":"+1 510 845 8047",
    "sg:postcode":"94549",
    "sg:province":"CA",
    "sg:tags":[
        "obstetrician",
        "gynecologist"
    ],
    "wof:name":"OB-Gyn & Fertility Specialists Medical Group",
    "wof:placetype":"venue"
},
  "geometry": {"coordinates":[-122.228748,37.83064],"type":"Point"}
}