{
  "type": "Feature",
  "properties": {
    "iso:country":"US",
    "sg:address":"5330 College Ave #110",
    "sg:city":"Oakland",
    "sg:classifiers":[
        {
            "category":"Shopping",
            "subcategory":"Clothing, Apparel, & Fashions",
            "type":"Retail Goods"
        }
    ],
    "sg:phone":"+1 510 923 1516",
    "sg:postcode":"94618",
    "sg:province":"CA",
    "sg:tags":[
        "clothing",
        "women's"
    ],
    "sg:website":"www.multiplethreads.org",
    "wof:name":"Multiple Threads",
    "wof:placetype":"venue"
},
  "geometry": {"coordinates":[-122.251025,37.838767],"type":"Point"}
}