{
  "type": "Feature",
  "properties": {
    "addr:full":"72244 Varner Rd Thousand Palms CA 92276",
    "addr:housenumber":"72244",
    "addr:postcode":"92276",
    "addr:street":"Varner Rd",
    "iso:country":"US",
    "sg:address":"72244 Varner Rd",
    "sg:city":"Thousand Palms",
    "sg:classifiers":[
        {
            "category":"Restaurant",
            "type":"Food & Drink"
        }
    ],
    "sg:menulink":"http://www.allmenus.com/ca/desert-hot-springs/8496-dennys/menu/",
    "sg:phone":"+1 760 343 3739",
    "sg:postcode":"92276",
    "sg:province":"CA",
    "sg:tags":[
        "american",
        "diner"
    ],
    "wof:name":"Denny's",
    "wof:placetype":"venue"
},
  "geometry": {"coordinates":[-116.400171,33.815047],"type":"Point"}
}