{
  "type": "Feature",
  "properties": {
    "addr:full":"1244 Westwood Boulevard Los Angeles CA 90024",
    "addr:housenumber":"1244",
    "addr:postcode":"90024",
    "addr:street":"Westwood Boulevard",
    "iso:country":"US",
    "sg:address":"1244 Westwood Boulevard",
    "sg:city":"Los Angeles",
    "sg:classifiers":[
        {
            "category":"Wholesale",
            "subcategory":"Computers",
            "type":"Manufacturing & Wholesale Goods"
        }
    ],
    "sg:phone":"+1 310 201 9837",
    "sg:postcode":"90024",
    "sg:province":"CA",
    "wof:name":"Compurent",
    "wof:placetype":"venue"
},
  "geometry": {"coordinates":[-118.44349800000001,34.057923],"type":"Point"}
}