{
  "type": "Feature",
  "properties": {
    "iso:country":"US",
    "sg:address":"10139 Woodley Ave",
    "sg:city":"Sepulveda",
    "sg:classifiers":[
        {
            "category":"Real Estate",
            "subcategory":"Real Estate Operator",
            "type":"Services"
        }
    ],
    "sg:phone":"+1 818 894 0017",
    "sg:postcode":"91343",
    "sg:province":"CA",
    "sg:tags":[
        "apartment"
    ],
    "wof:name":"Woodley Plaza Apartments",
    "wof:placetype":"venue"
},
  "geometry": {"coordinates":[-118.48493999999999,34.256259],"type":"Point"}
}