{
  "type": "Feature",
  "properties": {
    "iso:country":"US",
    "sg:address":"1112 S Vine St",
    "sg:city":"Paso Robles",
    "sg:classifiers":[
        {
            "category":"Health Services",
            "subcategory":"Medical Lab",
            "type":"Services"
        }
    ],
    "sg:phone":"+1 805 238 2100",
    "sg:postcode":"93446",
    "sg:province":"CA",
    "sg:tags":[
        "laboratory"
    ],
    "wof:name":"Paso Robles Dental Lab",
    "wof:placetype":"venue"
},
  "geometry": {"coordinates":[-120.693882,35.599446],"type":"Point"}
}