{
  "type": "Feature",
  "properties": {
    "addr:full":"220 Mar Vista Dr Aptos CA 95003",
    "addr:housenumber":"220",
    "addr:postcode":"ca 95003",
    "addr:street":"Mar Vista Dr",
    "iso:country":"US",
    "sg:address":"220 Mar Vista Dr",
    "sg:city":"Aptos",
    "sg:classifiers":[
        {
            "category":"Building & Trades",
            "subcategory":"Plumbing",
            "type":"Services"
        }
    ],
    "sg:phone":"+1 831 227 9156",
    "sg:postcode":"95003",
    "sg:province":"CA",
    "sg:tags":[
        "plumber"
    ],
    "wof:name":"T's Plumbing & Drain Cleaning Service",
    "wof:placetype":"venue"
},
  "geometry": {"coordinates":[-121.916702,36.979729],"type":"Point"}
}