{
  "type": "Feature",
  "properties": {
    "addr:full":"3360 Adeline St Berkeley CA 94703",
    "addr:housenumber":"3360",
    "addr:postcode":"94703",
    "addr:street":"Adeline St",
    "iso:country":"US",
    "sg:address":"3360 Adeline St",
    "sg:city":"Berkeley",
    "sg:classifiers":[
        {
            "category":"Building & Trades",
            "subcategory":"Plumbing",
            "type":"Services"
        }
    ],
    "sg:phone":"+1 510 420 5899",
    "sg:postcode":"94703",
    "sg:province":"CA",
    "sg:tags":[
        "contractor"
    ],
    "wof:name":"Sternfeld Company Inc",
    "wof:placetype":"venue"
},
  "geometry": {"coordinates":[-122.272384,37.846902],"type":"Point"}
}