{
  "type": "Feature",
  "properties": {
    "iso:country":"US",
    "sg:address":"Grand Avenue",
    "sg:city":"Oakland",
    "sg:classifiers":[
        {
            "category":"Sports & Exercise",
            "subcategory":"Gym",
            "type":"Entertainment"
        }
    ],
    "sg:phone":"+1 510 395 5685",
    "sg:postcode":"94611",
    "sg:province":"CA",
    "sg:tags":[
        "trainer"
    ],
    "wof:name":"Saevio, Malvin Johnson",
    "wof:placetype":"venue"
},
  "geometry": {"coordinates":[-122.243106,37.823915],"type":"Point"}
}