{
  "type": "Feature",
  "properties": {
    "addr:full":"920 N Cll Loro Palm Springs CA 92262",
    "addr:housenumber":"920",
    "addr:postcode":"92262",
    "addr:street":"N Cll Loro",
    "iso:country":"US",
    "sg:address":"920 N Cll Loro",
    "sg:city":"Palm Springs",
    "sg:classifiers":[
        {
            "category":"Government",
            "subcategory":"Office",
            "type":"Public Place"
        }
    ],
    "sg:phone":"+1 760 416 3653",
    "sg:postcode":"92262",
    "sg:province":"CA",
    "sg:tags":[
        "agricultural",
        "regulation",
        "marketing"
    ],
    "wof:name":"Mainezing Company",
    "wof:placetype":"venue"
},
  "geometry": {"coordinates":[-116.52286700000001,33.836661],"type":"Point"}
}