{
  "type": "Feature",
  "properties": {
    "addr:full":"625 Broadway Ste 906 San Diego CA 92101",
    "addr:housenumber":"625",
    "addr:postcode":"92101",
    "addr:street":"Broadway Ste 906",
    "iso:country":"US",
    "sg:address":"625 Broadway Ste 906",
    "sg:city":"San Diego",
    "sg:classifiers":[
        {
            "category":"Professional",
            "subcategory":"Lawyer & Legal Services",
            "type":"Services"
        }
    ],
    "sg:phone":"+1 619 434 0024",
    "sg:postcode":"92101",
    "sg:province":"CA",
    "sg:tags":[
        "litigation"
    ],
    "sg:website":"www.zhlaw.com",
    "wof:name":"Zeldes & Haeggquist, LLP",
    "wof:placetype":"venue"
},
  "geometry": {"coordinates":[-117.158799,32.715458],"type":"Point"}
}