{
  "type": "Feature",
  "properties": {
    "addr:full":"2499 Homestead Road Santa Clara CA 95050",
    "addr:housenumber":"2499",
    "addr:postcode":"95050",
    "addr:street":"Homestead Road",
    "iso:country":"US",
    "sg:address":"2499 Homestead Road",
    "sg:city":"Santa Clara",
    "sg:classifiers":[
        {
            "category":"Education",
            "subcategory":"Preschool",
            "type":"Public Place"
        },
        {
            "category":"Education",
            "subcategory":"School",
            "type":"Public Place"
        }
    ],
    "sg:phone":"+1 408 244 9777",
    "sg:postcode":"95050",
    "sg:province":"CA",
    "sg:tags":[
        "elementary"
    ],
    "wof:name":"Jubilee Academy",
    "wof:placetype":"venue"
},
  "geometry": {"coordinates":[-121.96847200000001,37.340879],"type":"Point"}
}