{
  "type": "Feature",
  "properties": {
    "addr:full":"39812 Mission Blvd Fremont CA 94539",
    "addr:housenumber":"39812",
    "addr:postcode":"94539",
    "addr:street":"Mission Blvd",
    "iso:country":"US",
    "sg:address":"39812 Mission Blvd",
    "sg:city":"Fremont",
    "sg:classifiers":[
        {
            "category":"Real Estate",
            "subcategory":"Real Estate Agent",
            "type":"Services"
        }
    ],
    "sg:phone":"+1 510 888 3448",
    "sg:postcode":"94539",
    "sg:province":"CA",
    "wof:name":"Steve Dhillon Realtor",
    "wof:placetype":"venue"
},
  "geometry": {"coordinates":[-121.95411799999999,37.559067],"type":"Point"}
}