{
  "type": "Feature",
  "properties": {
    "addr:full":"200 H St Antioch CA 94509",
    "addr:housenumber":"200",
    "addr:postcode":"ca 94509",
    "addr:street":"H St",
    "iso:country":"US",
    "sg:address":"200 H St",
    "sg:city":"Antioch",
    "sg:classifiers":[
        {
            "category":"Government",
            "subcategory":"Office",
            "type":"Public Place"
        }
    ],
    "sg:phone":"+1 925 779 7055",
    "sg:postcode":"94509",
    "sg:province":"CA",
    "sg:tags":[
        "government-state"
    ],
    "sg:website":"http://www.ci.antioch.ca.us",
    "wof:name":"Finance Dept",
    "wof:placetype":"venue"
},
  "geometry": {"coordinates":[-121.81501799999999,38.016178],"type":"Point"}
}