{
  "type": "Feature",
  "properties": {
    "iso:country":"US",
    "sg:address":"1543 Retherford St",
    "sg:city":"Tulare",
    "sg:classifiers":[
        {
            "category":"Restaurant",
            "type":"Food & Drink"
        }
    ],
    "sg:menulink":"http://www.allmenus.com/ca/tulare/163855-togos-eatery/menu/",
    "sg:phone":"+1 559 688 6100",
    "sg:postcode":"93274",
    "sg:province":"CA",
    "sg:tags":[
        "wrap",
        "american",
        "sandwich"
    ],
    "wof:name":"Togo's Eatery",
    "wof:placetype":"venue"
},
  "geometry": {"coordinates":[-119.335442,36.232512],"type":"Point"}
}