{
  "type": "Feature",
  "properties": {
    "iso:country":"US",
    "sg:address":"4770 Von Karman Ave",
    "sg:city":"Newport Beach",
    "sg:classifiers":[
        {
            "category":"Professional",
            "subcategory":"Lawyer & Legal Services",
            "type":"Services"
        }
    ],
    "sg:phone":"+1 949 474 9088",
    "sg:postcode":"92660",
    "sg:province":"CA",
    "wof:name":"Vollmer Michael Law Offices of",
    "wof:placetype":"venue"
},
  "geometry": {"coordinates":[-117.859291,33.668847],"type":"Point"}
}