{
  "type": "Feature",
  "properties": {
    "iso:country":"US",
    "sg:address":"1140 Wall St",
    "sg:city":"La Jolla",
    "sg:classifiers":[
        {
            "category":"Government",
            "subcategory":"Post Office",
            "type":"Public Place"
        }
    ],
    "sg:phone":"+1 858 459 5476",
    "sg:postcode":"92037",
    "sg:province":"CA",
    "sg:website":"www.usps.com",
    "wof:name":"United States Post Office",
    "wof:placetype":"venue"
},
  "geometry": {"coordinates":[-117.27271,32.847081],"type":"Point"}
}