{
  "type": "Feature",
  "properties": {
    "addr:full":"16626 Allison Way Spc 34 Sonora CA 95370",
    "addr:housenumber":"16626;34",
    "addr:postcode":"95370",
    "addr:street":"Allison Way",
    "iso:country":"US",
    "sg:address":"16626 Allison Way Spc 34",
    "sg:city":"Sonora",
    "sg:classifiers":[
        {
            "category":"Personal",
            "subcategory":"Beauty Salon",
            "type":"Services"
        }
    ],
    "sg:phone":"+1 209 532 7501",
    "sg:postcode":"95370",
    "sg:province":"CA",
    "wof:name":"Azteca Pools And Spas",
    "wof:placetype":"venue"
},
  "geometry": {"coordinates":[-120.278761,37.990573],"type":"Point"}
}