{
  "type": "Feature",
  "properties": {
    "iso:country":"US",
    "sg:address":"105 Neal St",
    "sg:city":"Grass Valley",
    "sg:classifiers":[
        {
            "category":"Food & Beverages",
            "subcategory":"Groceries & Convenience Stores",
            "type":"Retail Goods"
        }
    ],
    "sg:phone":"+1 530 273 0115",
    "sg:postcode":"95945",
    "sg:province":"CA",
    "sg:tags":[
        "grocer"
    ],
    "wof:name":"Safeway",
    "wof:placetype":"venue"
},
  "geometry": {"coordinates":[-121.06202,39.216528],"type":"Point"}
}