{
  "type": "Feature",
  "properties": {
    "addr:full":"26900 Newport Rd Menifee CA 92584",
    "addr:housenumber":"26900",
    "addr:postcode":"92584",
    "addr:street":"Newport Rd",
    "iso:country":"US",
    "sg:address":"26900 Newport Rd",
    "sg:city":"Menifee",
    "sg:classifiers":[
        {
            "category":"Health Services",
            "subcategory":"Doctor",
            "type":"Services"
        }
    ],
    "sg:phone":"+1 951 301 5380",
    "sg:postcode":"92584",
    "sg:province":"CA",
    "sg:website":"www.pediatricpartners.net",
    "wof:name":"MCCHESNEY PAMELA MD",
    "wof:placetype":"venue"
},
  "geometry": {"coordinates":[-117.19091,33.685157],"type":"Point"}
}