{
  "type": "Feature",
  "properties": {
    "addr:full":"9710 Mission Gorge Rd Santee CA 92071",
    "addr:housenumber":"9710",
    "addr:postcode":"92071",
    "addr:street":"Mission Gorge Rd",
    "iso:country":"US",
    "sg:address":"9710 Mission Gorge Rd",
    "sg:city":"Santee",
    "sg:classifiers":[
        {
            "category":"Shopping",
            "subcategory":"Mobile Phones",
            "type":"Retail Goods"
        }
    ],
    "sg:phone":"+1 619 449 6352",
    "sg:postcode":"92071",
    "sg:province":"CA",
    "wof:name":"Radioshack",
    "wof:placetype":"venue"
},
  "geometry": {"coordinates":[-116.985001,32.8386],"type":"Point"}
}