{
  "type": "Feature",
  "properties": {
    "addr:full":"3407 El Camino Ave Sacramento CA 95821",
    "addr:housenumber":"3407",
    "addr:postcode":"95821",
    "addr:street":"El Camino Ave",
    "iso:country":"US",
    "sg:address":"3407 El Camino Ave",
    "sg:city":"Sacramento",
    "sg:classifiers":[
        {
            "category":"Food & Beverages",
            "subcategory":"Liquor & Beverages",
            "type":"Retail Goods"
        }
    ],
    "sg:phone":"+1 916 483 1130",
    "sg:postcode":"95821",
    "sg:province":"CA",
    "sg:tags":[
        "beer",
        "spirit",
        "wine"
    ],
    "wof:name":"Country Club Food & Liquor",
    "wof:placetype":"venue"
},
  "geometry": {"coordinates":[-121.385002,38.6106],"type":"Point"}
}