{
  "type": "Feature",
  "properties": {
    "addr:full":"56 W Santa Clara St San Jose CA 95113",
    "addr:housenumber":"56",
    "addr:postcode":"95113",
    "addr:street":"W Santa Clara St",
    "iso:country":"US",
    "sg:address":"56 W Santa Clara St",
    "sg:city":"San Jose",
    "sg:classifiers":[
        {
            "category":"Restaurant",
            "type":"Food & Drink"
        }
    ],
    "sg:phone":"+1 408 298 3854",
    "sg:postcode":"95113",
    "sg:province":"CA",
    "sg:tags":[
        "sushi",
        "bar",
        "japanese"
    ],
    "sg:website":"www.fujisushisj.com",
    "wof:name":"Fuji Sushi",
    "wof:placetype":"venue"
},
  "geometry": {"coordinates":[-121.891488,37.335728],"type":"Point"}
}