{
  "type": "Feature",
  "properties": {
    "iso:country":"US",
    "sg:address":"6727 Sylmar Ave",
    "sg:city":"Van Nuys",
    "sg:classifiers":[
        {
            "category":"Building & Trades",
            "subcategory":"Construction",
            "type":"Services"
        }
    ],
    "sg:phone":"+1 818 298 0287",
    "sg:postcode":"91405",
    "sg:province":"CA",
    "sg:tags":[
        "general",
        "contractor"
    ],
    "wof:name":"BEPD Co",
    "wof:placetype":"venue"
},
  "geometry": {"coordinates":[-118.44661,34.191857],"type":"Point"}
}