{
  "type": "Feature",
  "properties": {
    "addr:full":"4190 E Patero Way Long Beach CA 90815",
    "addr:housenumber":"4190",
    "addr:postcode":"90815",
    "addr:street":"E Patero Way",
    "iso:country":"US",
    "sg:address":"4190 E Patero Way",
    "sg:city":"Long Beach",
    "sg:classifiers":[
        {
            "category":"Building & Trades",
            "subcategory":"Plumbing",
            "type":"Services"
        }
    ],
    "sg:phone":"+1 562 498 4410",
    "sg:postcode":"90815",
    "sg:province":"CA",
    "sg:tags":[
        "contractor"
    ],
    "wof:name":"All Plumbing",
    "wof:placetype":"venue"
},
  "geometry": {"coordinates":[-118.14384,33.795213],"type":"Point"}
}