{
  "type": "Feature",
  "properties": {
    "iso:country":"US",
    "sg:address":"1218 Oak St",
    "sg:city":"Napa",
    "sg:classifiers":[
        {
            "category":"Banks & Credit Unions",
            "subcategory":"Bank",
            "type":"Services"
        }
    ],
    "sg:phone":"+1 707 226 9301",
    "sg:postcode":"94559",
    "sg:province":"CA",
    "sg:tags":[
        "loan",
        "real estate"
    ],
    "wof:name":"Omega Lending Inc",
    "wof:placetype":"venue"
},
  "geometry": {"coordinates":[-122.285945,38.293788],"type":"Point"}
}