{
  "type": "Feature",
  "properties": {
    "addr:full":"6401 Hollywood Blvd Los Angeles CA 90028",
    "addr:housenumber":"6401",
    "addr:postcode":"90028",
    "addr:street":"Hollywood Blvd",
    "iso:country":"US",
    "sg:address":"6401 Hollywood Blvd",
    "sg:city":"Los Angeles",
    "sg:classifiers":[
        {
            "category":"Banks & Credit Unions",
            "subcategory":"Bank",
            "type":"Services"
        }
    ],
    "sg:phone":"+1 323 466 6274",
    "sg:postcode":"90028",
    "sg:province":"CA",
    "sg:tags":[
        "cashing",
        "check"
    ],
    "wof:name":"Coumminty Check Cashing & Food",
    "wof:placetype":"venue"
},
  "geometry": {"coordinates":[-118.33103699999999,34.101594],"type":"Point"}
}