{
  "type": "Feature",
  "properties": {
    "addr:full":"1498 11th St Los Osos CA 93402",
    "addr:housenumber":"1498",
    "addr:postcode":"93402",
    "addr:street":"11Th St",
    "iso:country":"US",
    "sg:address":"1498 11th St",
    "sg:city":"Los Osos",
    "sg:classifiers":[
        {
            "category":"Building & Trades",
            "subcategory":"Construction",
            "type":"Services"
        }
    ],
    "sg:phone":"+1 805 528 5106",
    "sg:postcode":"93402",
    "sg:province":"CA",
    "sg:tags":[
        "home",
        "improvement"
    ],
    "wof:name":"Honest Mike's All Around Home",
    "wof:placetype":"venue"
},
  "geometry": {"coordinates":[-120.831002,35.324372],"type":"Point"}
}