{
  "type": "Feature",
  "properties": {
    "addr:full":"5750 Obata Way Gilroy CA 95020",
    "addr:postcode":"5750;95020",
    "addr:street":"Obata Way",
    "iso:country":"US",
    "sg:address":"5750 Obata Way",
    "sg:city":"Gilroy",
    "sg:classifiers":[
        {
            "category":"Building & Trades",
            "subcategory":"Construction",
            "type":"Services"
        }
    ],
    "sg:phone":"+1 408 848 4313",
    "sg:postcode":"95020",
    "sg:province":"CA",
    "sg:tags":[
        "drywall",
        "framing",
        "contractor"
    ],
    "wof:name":"Melos Plastering",
    "wof:placetype":"venue"
},
  "geometry": {"coordinates":[-121.549871,36.985016],"type":"Point"}
}