{
  "type": "Feature",
  "properties": {
    "iso:country":"US",
    "sg:address":"1759 S Claudina Way",
    "sg:city":"Anaheim",
    "sg:classifiers":[
        {
            "category":"Bars & Pubs",
            "type":"Food & Drink"
        },
        {
            "category":"Restaurant",
            "type":"Food & Drink"
        },
        {
            "category":"Bars & Pubs",
            "subcategory":"Sports Bar",
            "type":"Food & Drink"
        }
    ],
    "sg:phone":"+1 714 533 3813",
    "sg:postcode":"92805",
    "sg:province":"CA",
    "sg:tags":[
        "grill"
    ],
    "sg:website":"www.throwbackssportsbar.com",
    "wof:name":"Throwbacks Sports Bar",
    "wof:placetype":"venue"
},
  "geometry": {"coordinates":[-117.901454,33.80439],"type":"Point"}
}