{
  "type": "Feature",
  "properties": {
    "iso:country":"US",
    "sg:address":"1081 N Fair Oaks Ave",
    "sg:city":"Pasadena",
    "sg:classifiers":[
        {
            "category":"Education",
            "subcategory":"Special Training",
            "type":"Public Place"
        }
    ],
    "sg:phone":"+1 626 345 9266",
    "sg:postcode":"91103",
    "sg:province":"CA",
    "sg:tags":[
        "school",
        "interest"
    ],
    "wof:name":"Brite",
    "wof:placetype":"venue"
},
  "geometry": {"coordinates":[-118.150704,34.163404],"type":"Point"}
}