{
  "type": "Feature",
  "properties": {
    "iso:country":"US",
    "sg:address":"12691 Pala Dr",
    "sg:city":"Garden Grove",
    "sg:classifiers":[
        {
            "category":"Professional",
            "subcategory":"Business Services",
            "type":"Services"
        }
    ],
    "sg:phone":"+1 714 895 7500",
    "sg:postcode":"92841",
    "sg:province":"CA",
    "sg:tags":[
        "equipment",
        "microfilming"
    ],
    "sg:website":"www.acs-inc.com",
    "wof:name":"ACS Integrated Document",
    "wof:placetype":"venue"
},
  "geometry": {"coordinates":[-118.007637,33.776287],"type":"Point"}
}