{
  "type": "Feature",
  "properties": {
    "addr:full":"219 N Riverside Ave Rialto CA 92376",
    "addr:housenumber":"219",
    "addr:postcode":"92376",
    "addr:street":"N Riverside Ave",
    "iso:country":"US",
    "sg:address":"219 N Riverside Ave",
    "sg:city":"Rialto",
    "sg:classifiers":[
        {
            "category":"Organizations",
            "subcategory":"Community Association",
            "type":"Services"
        }
    ],
    "sg:phone":"+1 909 820 9242",
    "sg:postcode":"92376",
    "sg:province":"CA",
    "sg:tags":[
        "club"
    ],
    "wof:name":"Women's Club Of Rialto",
    "wof:placetype":"venue"
},
  "geometry": {"coordinates":[-117.370153,34.103911],"type":"Point"}
}