{
  "type": "Feature",
  "properties": {
    "iso:country":"US",
    "sg:address":"7355 Jones Rd",
    "sg:city":"Winton",
    "sg:classifiers":[
        {
            "category":"Farming",
            "subcategory":"Orchard",
            "type":"Manufacturing & Wholesale Goods"
        }
    ],
    "sg:phone":"+1 209 358 0759",
    "sg:postcode":"95388",
    "sg:province":"CA",
    "wof:name":"George Mobley",
    "wof:placetype":"venue"
},
  "geometry": {"coordinates":[-120.62245900000001,37.393631],"type":"Point"}
}