{
  "type": "Feature",
  "properties": {
    "addr:full":"800 N Eckhoff St Orange CA 92868",
    "addr:housenumber":"800",
    "addr:postcode":"92868",
    "addr:street":"N Eckhoff St",
    "iso:country":"US",
    "sg:address":"800 N Eckhoff St",
    "sg:city":"Orange",
    "sg:classifiers":[
        {
            "category":"Government",
            "subcategory":"Office",
            "type":"Public Place"
        }
    ],
    "sg:phone":"+1 714 704 8674",
    "sg:postcode":"92868",
    "sg:province":"CA",
    "sg:tags":[
        "development"
    ],
    "wof:name":"Department of Family Services",
    "wof:placetype":"venue"
},
  "geometry": {"coordinates":[-117.874081,33.801363],"type":"Point"}
}