{
  "type": "Feature",
  "properties": {
    "iso:country":"US",
    "sg:address":"1733 Shady Crest Pl",
    "sg:city":"El Cajon",
    "sg:classifiers":[
        {
            "category":"Shopping",
            "subcategory":"Computers & Home Electronics",
            "type":"Retail Goods"
        }
    ],
    "sg:phone":"+1 619 562 4058",
    "sg:postcode":"92020",
    "sg:province":"CA",
    "sg:tags":[
        "communications",
        "2",
        "radio"
    ],
    "wof:name":"Samco-Sams Radio",
    "wof:placetype":"venue"
},
  "geometry": {"coordinates":[-116.986922,32.817652],"type":"Point"}
}