{
  "type": "Feature",
  "properties": {
    "iso:country":"US",
    "sg:address":"12439 Otsego St",
    "sg:city":"Valley Village",
    "sg:classifiers":[
        {
            "category":"Professional",
            "subcategory":"Computer Services",
            "type":"Services"
        }
    ],
    "sg:phone":"+1 818 760 8342",
    "sg:postcode":"91607",
    "sg:province":"CA",
    "sg:tags":[
        "hardware",
        "provider",
        "internet",
        "software"
    ],
    "sg:website":"www.planetbids.com",
    "wof:name":"Planetbids Inc",
    "wof:placetype":"venue"
},
  "geometry": {"coordinates":[-118.40508800000001,34.163133],"type":"Point"}
}