{
  "type": "Feature",
  "properties": {
    "iso:country":"US",
    "sg:address":"3687 Las Posas Rd Ste 180",
    "sg:city":"Camarillo",
    "sg:classifiers":[
        {
            "category":"Health Services",
            "subcategory":"Dentist",
            "type":"Services"
        }
    ],
    "sg:phone":"+1 805 484 2705",
    "sg:postcode":"93010",
    "sg:province":"CA",
    "sg:tags":[
        "orthodontist",
        "pediatric"
    ],
    "wof:name":"Lisagor Mark S DDS Inc",
    "wof:placetype":"venue"
},
  "geometry": {"coordinates":[-119.01799800000001,34.2416],"type":"Point"}
}