{
  "type": "Feature",
  "properties": {
    "addr:full":"71 Stevenson St San Francisco CA 94105",
    "addr:housenumber":"71",
    "addr:postcode":"94105",
    "addr:street":"Stevenson St",
    "iso:country":"US",
    "sg:address":"71 Stevenson St",
    "sg:city":"San Francisco",
    "sg:classifiers":[
        {
            "category":"Government",
            "subcategory":"Office",
            "type":"Public Place"
        }
    ],
    "sg:phone":"+1 415 975 4310",
    "sg:postcode":"94105",
    "sg:province":"CA",
    "sg:tags":[
        "regulatory",
        "agency",
        "labor"
    ],
    "wof:name":"Osha Region 9 Office",
    "wof:placetype":"venue"
},
  "geometry": {"coordinates":[-122.39955500000001,37.789871],"type":"Point"}
}