{
  "type": "Feature",
  "properties": {
    "addr:full":"6201 Winnetka Ave Woodland Hills CA 91367",
    "addr:housenumber":"6201",
    "addr:postcode":"91367",
    "addr:street":"Winnetka Ave",
    "iso:country":"US",
    "sg:address":"6201 Winnetka Ave",
    "sg:city":"Woodland Hills",
    "sg:classifiers":[
        {
            "category":"Social Services",
            "subcategory":"Child Care",
            "type":"Services"
        },
        {
            "category":"Recreation",
            "type":"Entertainment"
        }
    ],
    "sg:phone":"+1 888 909 2822",
    "sg:postcode":"91367",
    "sg:province":"CA",
    "sg:tags":[
        "summer",
        "camp",
        "day"
    ],
    "sg:website":"www.destinationscience.org",
    "wof:name":"Destination Science",
    "wof:placetype":"venue"
},
  "geometry": {"coordinates":[-118.57092900000001,34.182343],"type":"Point"}
}