{
  "type": "Feature",
  "properties": {
    "iso:country":"US",
    "sg:address":"2302 Zanker Rd",
    "sg:city":"San Jose",
    "sg:classifiers":[
        {
            "category":"Organizations",
            "subcategory":"Non-profit Organization",
            "type":"Services"
        }
    ],
    "sg:phone":"+1 408 232 5655",
    "sg:postcode":"95134",
    "sg:province":"CA",
    "wof:name":"Pacific Island Ministries",
    "wof:placetype":"venue"
},
  "geometry": {"coordinates":[-121.921492,37.38586],"type":"Point"}
}