{
  "type": "Feature",
  "properties": {
    "iso:country":"US",
    "sg:address":"3701 Parkway Pl",
    "sg:city":"West Sacramento",
    "sg:classifiers":[
        {
            "category":"Utilities",
            "subcategory":"Telephone",
            "type":"Services"
        }
    ],
    "sg:phone":"+1 916 371 6341",
    "sg:postcode":"95691",
    "sg:province":"CA",
    "sg:tags":[
        "e",
        "telecommunication",
        "cellular"
    ],
    "wof:name":"MCI",
    "wof:placetype":"venue"
},
  "geometry": {"coordinates":[-121.565585,38.571105],"type":"Point"}
}