{
  "type": "Feature",
  "properties": {
    "iso:country":"US",
    "sg:address":"17655 Clark Ave",
    "sg:city":"Bellflower",
    "sg:classifiers":[
        {
            "category":"Autos & Motor Vehicles",
            "subcategory":"Auto Supplies",
            "type":"Retail Goods"
        }
    ],
    "sg:phone":"+1 562 925 4730",
    "sg:postcode":"90706",
    "sg:province":"CA",
    "sg:tags":[
        "tire"
    ],
    "wof:name":"Rancho Tires And Wheels",
    "wof:placetype":"venue"
},
  "geometry": {"coordinates":[-118.134042,33.872495],"type":"Point"}
}