{
  "type": "Feature",
  "properties": {
    "addr:full":"380 N Main St Ste F Lakeport CA 95453",
    "addr:housenumber":"380",
    "addr:postcode":"95453",
    "addr:street":"N Main St Ste F",
    "iso:country":"US",
    "sg:address":"380 N Main St Ste F",
    "sg:city":"Lakeport",
    "sg:classifiers":[
        {
            "category":"Professional",
            "subcategory":"Lawyer & Legal Services",
            "type":"Services"
        }
    ],
    "sg:phone":"+1 707 263 5000",
    "sg:postcode":"95453",
    "sg:province":"CA",
    "sg:tags":[
        "attorney",
        "practice"
    ],
    "wof:name":"Swanson Paul",
    "wof:placetype":"venue"
},
  "geometry": {"coordinates":[-122.915155,39.044493],"type":"Point"}
}