{
  "type": "Feature",
  "properties": {
    "addr:full":"2500 Mitchell Rd Ceres CA 95307",
    "addr:housenumber":"2500",
    "addr:postcode":"95307",
    "addr:street":"Mitchell Rd",
    "iso:country":"US",
    "sg:address":"2500 Mitchell Rd",
    "sg:city":"Ceres",
    "sg:classifiers":[
        {
            "category":"Restaurant",
            "type":"Food & Drink"
        }
    ],
    "sg:phone":"+1 209 537 3619",
    "sg:postcode":"95307",
    "sg:province":"CA",
    "wof:name":"Perkos Cafe",
    "wof:placetype":"venue"
},
  "geometry": {"coordinates":[-120.939003,37.5947],"type":"Point"}
}