{
  "type": "Feature",
  "properties": {
    "iso:country":"US",
    "sg:address":"1775 W Foothill Blvd",
    "sg:city":"Upland",
    "sg:classifiers":[
        {
            "category":"Retail",
            "subcategory":"Auto Repair",
            "type":"Services"
        }
    ],
    "sg:phone":"+1 909 920 6476",
    "sg:postcode":"91786",
    "sg:province":"CA",
    "sg:tags":[
        "repairing",
        "automobile"
    ],
    "wof:name":"Route 66 Auto Repair Ctr",
    "wof:placetype":"venue"
},
  "geometry": {"coordinates":[-117.68929300000001,34.10685],"type":"Point"}
}