{
  "type": "Feature",
  "properties": {
    "addr:full":"100 Minner Ave Bakersfield CA 93308",
    "addr:housenumber":"100",
    "addr:postcode":"93308",
    "addr:street":"Minner Ave",
    "iso:country":"US",
    "sg:address":"100 Minner Ave",
    "sg:city":"Bakersfield",
    "sg:classifiers":[
        {
            "category":"Professional",
            "type":"Services"
        }
    ],
    "sg:phone":"+1 661 399 0412",
    "sg:postcode":"93308",
    "sg:province":"CA",
    "wof:name":"About Caskaets",
    "wof:placetype":"venue"
},
  "geometry": {"coordinates":[-119.02348499999999,35.418825],"type":"Point"}
}