{
  "type": "Feature",
  "properties": {
    "addr:full":"431 10th St Modesto CA 95354",
    "addr:housenumber":"431",
    "addr:postcode":"ca 95354",
    "addr:street":"10Th St",
    "iso:country":"US",
    "sg:address":"431 10th St",
    "sg:city":"Modesto",
    "sg:classifiers":[
        {
            "category":"Retail",
            "subcategory":"Auto Repair",
            "type":"Services"
        }
    ],
    "sg:phone":"+1 209 524 6631",
    "sg:postcode":"95354",
    "sg:province":"CA",
    "sg:tags":[
        "body",
        "shop"
    ],
    "wof:name":"Ray Starn Auto Body Shop",
    "wof:placetype":"venue"
},
  "geometry": {"coordinates":[-120.99400300000001,37.634998],"type":"Point"}
}