{
  "type": "Feature",
  "properties": {
    "addr:full":"1736 Stockton St San Francisco CA 94133",
    "addr:housenumber":"1736",
    "addr:postcode":"94133",
    "addr:street":"Stockton St",
    "iso:country":"US",
    "sg:address":"1736 Stockton St",
    "sg:city":"San Francisco",
    "sg:classifiers":[
        {
            "category":"Building & Trades",
            "subcategory":"Landscaping Services",
            "type":"Services"
        }
    ],
    "sg:phone":"+1 415 421 4231",
    "sg:postcode":"94133",
    "sg:province":"CA",
    "sg:tags":[
        "designer",
        "landscape"
    ],
    "wof:name":"Craig Heckman Landscape Arch",
    "wof:placetype":"venue"
},
  "geometry": {"coordinates":[-122.40947300000001,37.802231],"type":"Point"}
}