{
  "type": "Feature",
  "properties": {
    "iso:country":"US",
    "sg:address":"27231 Burbank",
    "sg:city":"El Toro",
    "sg:classifiers":[
        {
            "category":"Building & Trades",
            "subcategory":"Construction",
            "type":"Services"
        }
    ],
    "sg:phone":"+1 949 461 7030",
    "sg:postcode":"92610",
    "sg:province":"CA",
    "sg:tags":[
        "contractor"
    ],
    "wof:name":"Arciero & Sons",
    "wof:placetype":"venue"
},
  "geometry": {"coordinates":[-117.655841,33.67835],"type":"Point"}
}