{
  "type": "Feature",
  "properties": {
    "iso:country":"US",
    "sg:address":"889 Leong Dr",
    "sg:city":"Mountain View",
    "sg:classifiers":[
        {
            "category":"Deli",
            "type":"Food & Drink"
        }
    ],
    "sg:phone":"+1 650 967 3728",
    "sg:postcode":"94043",
    "sg:province":"CA",
    "wof:name":"El Paisano Mercado Y Cari",
    "wof:placetype":"venue"
},
  "geometry": {"coordinates":[-122.06500200000001,37.4067],"type":"Point"}
}