{
  "type": "Feature",
  "properties": {
    "addr:full":"17915 Ventura Blvd Encino CA 91316",
    "addr:housenumber":"17915",
    "addr:postcode":"91316",
    "addr:street":"Ventura Blvd",
    "iso:country":"US",
    "sg:address":"17915 Ventura Blvd",
    "sg:city":"Encino",
    "sg:classifiers":[
        {
            "category":"Professional",
            "subcategory":"Engineering",
            "type":"Services"
        }
    ],
    "sg:phone":"+1 818 708 9900",
    "sg:postcode":"91316",
    "sg:province":"CA",
    "sg:tags":[
        "engineer"
    ],
    "wof:name":"Paul Bennett Partnership Inc",
    "wof:placetype":"venue"
},
  "geometry": {"coordinates":[-118.522445,34.163753],"type":"Point"}
}