{
  "type": "Feature",
  "properties": {
    "addr:full":"3279 D St Sacramento CA 95816",
    "addr:housenumber":"3279",
    "addr:postcode":"95816",
    "addr:street":"D St",
    "iso:country":"US",
    "sg:address":"3279 D St",
    "sg:city":"Sacramento",
    "sg:classifiers":[
        {
            "category":"Shopping",
            "subcategory":"Books",
            "type":"Retail Goods"
        }
    ],
    "sg:phone":"+1 916 447 3557",
    "sg:postcode":"95816",
    "sg:province":"CA",
    "sg:tags":[
        "store"
    ],
    "wof:name":"Stories And Music Live",
    "wof:placetype":"venue"
},
  "geometry": {"coordinates":[-121.45915599999999,38.578465],"type":"Point"}
}