{
  "type": "Feature",
  "properties": {
    "addr:full":"60 E 3rd Ave San Mateo CA 94401",
    "addr:housenumber":"60",
    "addr:postcode":"94401",
    "addr:street":"E 3Rd Ave",
    "iso:country":"US",
    "sg:address":"60 E 3rd Ave",
    "sg:city":"San Mateo",
    "sg:classifiers":[
        {
            "category":"Professional",
            "subcategory":"Employment Agencies",
            "type":"Services"
        }
    ],
    "sg:phone":"+1 650 345 7755",
    "sg:postcode":"94401",
    "sg:province":"CA",
    "sg:tags":[
        "consultant",
        "outplacement"
    ],
    "wof:name":"Executive Marketing",
    "wof:placetype":"venue"
},
  "geometry": {"coordinates":[-122.325057,37.56346],"type":"Point"}
}