{
  "type": "Feature",
  "properties": {
    "addr:full":"2541 S Rodeo Gulch Rd Soquel CA 95073",
    "addr:housenumber":"2541",
    "addr:postcode":"95073",
    "addr:street":"S Rodeo Gulch Rd",
    "iso:country":"US",
    "sg:address":"2541 S Rodeo Gulch Rd",
    "sg:city":"Soquel",
    "sg:classifiers":[
        {
            "category":"Building & Trades",
            "subcategory":"Plumbing",
            "type":"Services"
        }
    ],
    "sg:phone":"+1 831 477 7150",
    "sg:postcode":"95073",
    "sg:province":"CA",
    "sg:tags":[
        "plumbing",
        "contractor"
    ],
    "wof:name":"Greg Bellows Plumbing Inc",
    "wof:placetype":"venue"
},
  "geometry": {"coordinates":[-121.969593,36.983954],"type":"Point"}
}