{
  "type": "Feature",
  "properties": {
    "iso:country":"US",
    "sg:address":"1775 S Main St",
    "sg:city":"Corona",
    "sg:classifiers":[
        {
            "category":"Organizations",
            "subcategory":"Religious Organization",
            "type":"Services"
        }
    ],
    "sg:phone":"+1 951 737 4125",
    "sg:postcode":"92882",
    "sg:province":"CA",
    "sg:tags":[
        "church"
    ],
    "wof:name":"Shrine Of The Presentation",
    "wof:placetype":"venue"
},
  "geometry": {"coordinates":[-117.568097,33.863755],"type":"Point"}
}