{
  "type": "Feature",
  "properties": {
    "iso:country":"US",
    "sg:address":"1426 Shotwell St",
    "sg:city":"San Francisco",
    "sg:classifiers":[
        {
            "category":"Building & Trades",
            "subcategory":"Construction",
            "type":"Services"
        }
    ],
    "sg:phone":"+1 415 282 0720",
    "sg:postcode":"94110",
    "sg:province":"CA",
    "sg:tags":[
        "contractor"
    ],
    "wof:name":"Muriel Construction",
    "wof:placetype":"venue"
},
  "geometry": {"coordinates":[-122.415052,37.745649],"type":"Point"}
}