{
  "type": "Feature",
  "properties": {
    "addr:full":"5200 S Broadway Los Angeles CA 90037",
    "addr:housenumber":"5200",
    "addr:postcode":"90037",
    "addr:street":"S Broadway",
    "iso:country":"US",
    "sg:address":"5200 S Broadway",
    "sg:city":"Los Angeles",
    "sg:classifiers":[
        {
            "category":"Real Estate",
            "subcategory":"Real Estate Operator",
            "type":"Services"
        }
    ],
    "sg:phone":"+1 323 234 1322",
    "sg:postcode":"90037",
    "sg:province":"CA",
    "sg:tags":[
        "apartment"
    ],
    "wof:name":"Paradise Arms",
    "wof:placetype":"venue"
},
  "geometry": {"coordinates":[-118.27800000000001,33.9953],"type":"Point"}
}