{
  "type": "Feature",
  "properties": {
    "addr:full":"1433 18th St Oakland CA 94607",
    "addr:housenumber":"1433",
    "addr:postcode":"94607",
    "addr:street":"18Th St",
    "iso:country":"US",
    "sg:address":"1433 18th St",
    "sg:city":"Oakland",
    "sg:classifiers":[
        {
            "category":"Retail",
            "subcategory":"Auto Repair",
            "type":"Services"
        }
    ],
    "sg:phone":"+1 510 444 8400",
    "sg:postcode":"94607",
    "sg:province":"CA",
    "sg:tags":[
        "truck"
    ],
    "wof:name":"J B Truck Electrical Repair",
    "wof:placetype":"venue"
},
  "geometry": {"coordinates":[-122.290378,37.813684],"type":"Point"}
}