{
  "type": "Feature",
  "properties": {
    "addr:full":"5275 Dent Ave San Jose CA 95118",
    "addr:housenumber":"5275",
    "addr:postcode":"95118",
    "addr:street":"Dent Ave",
    "iso:country":"US",
    "sg:address":"5275 Dent Ave",
    "sg:city":"San Jose",
    "sg:classifiers":[
        {
            "category":"Professional",
            "subcategory":"Art Services",
            "type":"Services"
        },
        {
            "category":"Professional",
            "subcategory":"Printing & Photocopies",
            "type":"Services"
        }
    ],
    "sg:phone":"+1 408 265 9599",
    "sg:postcode":"95118",
    "sg:province":"CA",
    "sg:tags":[
        "graphic",
        "design"
    ],
    "sg:website":"www.rj3signs.com",
    "wof:name":"RJ3 Signs",
    "wof:placetype":"venue"
},
  "geometry": {"coordinates":[-121.89669600000001,37.246877],"type":"Point"}
}