{
  "type": "Feature",
  "properties": {
    "iso:country":"US",
    "sg:address":"1520 3rd Ave",
    "sg:city":"Walnut Creek",
    "sg:classifiers":[
        {
            "category":"Retail",
            "subcategory":"Auto Repair",
            "type":"Services"
        }
    ],
    "sg:phone":"+1 925 946 9040",
    "sg:postcode":"94597",
    "sg:province":"CA",
    "sg:tags":[
        "repairing",
        "automobile",
        "general",
        "supply"
    ],
    "wof:name":"Kirk's Motorsport",
    "wof:placetype":"venue"
},
  "geometry": {"coordinates":[-122.066069,37.919598],"type":"Point"}
}