{
  "type": "Feature",
  "properties": {
    "iso:country":"US",
    "sg:address":"3830 Valley Centre Dr Ste 708B",
    "sg:city":"San Diego",
    "sg:classifiers":[
        {
            "category":"Juice Bar",
            "subcategory":"None",
            "type":"Food & Drink"
        }
    ],
    "sg:phone":"+1 858 720 1026",
    "sg:postcode":"92130",
    "sg:province":"CA",
    "sg:tags":[
        "smoothy"
    ],
    "sg:website":"www.robeks.com",
    "wof:name":"Robeks Juice",
    "wof:placetype":"venue"
},
  "geometry": {"coordinates":[-117.231165,32.939214],"type":"Point"}
}