{
  "type": "Feature",
  "properties": {
    "iso:country":"US",
    "sg:address":"2239 S Pacific Ave",
    "sg:city":"San Pedro",
    "sg:classifiers":[
        {
            "category":"Personal",
            "subcategory":"Shoe Repair & Shine",
            "type":"Services"
        }
    ],
    "sg:phone":"+1 310 831 1733",
    "sg:postcode":"90731",
    "sg:province":"CA",
    "sg:tags":[
        "repairing",
        "boot"
    ],
    "wof:name":"San Pedro Shoe Repair",
    "wof:placetype":"venue"
},
  "geometry": {"coordinates":[-118.288044,33.725068],"type":"Point"}
}