{
  "type": "Feature",
  "properties": {
    "iso:country":"US",
    "sg:address":"5354 W Yale Ave",
    "sg:city":"Fresno",
    "sg:classifiers":[
        {
            "category":"Wholesale",
            "subcategory":"Machinery & Supplies",
            "type":"Manufacturing & Wholesale Goods"
        }
    ],
    "sg:phone":"+1 559 275 4894",
    "sg:postcode":"93722",
    "sg:province":"CA",
    "sg:tags":[
        "sprinkler"
    ],
    "wof:name":"Bud's Fire Protection",
    "wof:placetype":"venue"
},
  "geometry": {"coordinates":[-119.888468,36.769847],"type":"Point"}
}