{
  "type": "Feature",
  "properties": {
    "iso:country":"US",
    "sg:address":"5720 Labath Ave",
    "sg:city":"Rohnert Park",
    "sg:classifiers":[
        {
            "category":"Local Transit",
            "type":"Transportation"
        }
    ],
    "sg:phone":"+1 707 206 0371",
    "sg:postcode":"94928",
    "sg:province":"CA",
    "sg:tags":[
        "limousine"
    ],
    "wof:name":"Beau Wine Tours",
    "wof:placetype":"venue"
},
  "geometry": {"coordinates":[-122.722281,38.35591],"type":"Point"}
}