{
  "type": "Feature",
  "properties": {
    "addr:full":"2521 Myrtle Ave Merced CA 95340",
    "addr:housenumber":"2521",
    "addr:postcode":"95340",
    "addr:street":"Myrtle Ave",
    "iso:country":"US",
    "sg:address":"2521 Myrtle Ave",
    "sg:city":"Merced",
    "sg:classifiers":[
        {
            "category":"Building & Trades",
            "subcategory":"Electrical",
            "type":"Services"
        }
    ],
    "sg:phone":"+1 209 383 6338",
    "sg:postcode":"95340",
    "sg:province":"CA",
    "sg:tags":[
        "electrician"
    ],
    "wof:name":"Kramer's Electric",
    "wof:placetype":"venue"
},
  "geometry": {"coordinates":[-120.443398,37.302602],"type":"Point"}
}