{
  "type": "Feature",
  "properties": {
    "iso:country":"US",
    "sg:address":"2240 S el Camino Real",
    "sg:city":"San Mateo",
    "sg:classifiers":[
        {
            "category":"Home & Garden",
            "subcategory":"Household Appliances",
            "type":"Retail Goods"
        }
    ],
    "sg:phone":"+1 650 349 2913",
    "sg:postcode":"94403",
    "sg:province":"CA",
    "wof:name":"Davies Appliance Stores",
    "wof:placetype":"venue"
},
  "geometry": {"coordinates":[-122.307278,37.545875],"type":"Point"}
}