{
  "type": "Feature",
  "properties": {
    "iso:country":"US",
    "sg:address":"11029 Wilkie Ave",
    "sg:city":"Inglewood",
    "sg:classifiers":[
        {
            "category":"Professional",
            "subcategory":"Business Services",
            "type":"Services"
        }
    ],
    "sg:phone":"+1 323 777 9867",
    "sg:postcode":"90303",
    "sg:province":"CA",
    "wof:name":"G JS Fashions",
    "wof:placetype":"venue"
},
  "geometry": {"coordinates":[-118.32282,33.934072],"type":"Point"}
}