{
  "type": "Feature",
  "properties": {
    "iso:country":"US",
    "sg:address":"6040 Cazadero Hwy",
    "sg:city":"Cazadero",
    "sg:classifiers":[
        {
            "category":"Building & Trades",
            "subcategory":"Construction",
            "type":"Services"
        }
    ],
    "sg:phone":"+1 707 632 5610",
    "sg:postcode":"95421",
    "sg:province":"CA",
    "sg:tags":[
        "excavating",
        "contractor"
    ],
    "wof:name":"Parmeter Logging Excavation",
    "wof:placetype":"venue"
},
  "geometry": {"coordinates":[-123.085443,38.533449],"type":"Point"}
}