{
  "type": "Feature",
  "properties": {
    "addr:full":"25101 Southport St Laguna Hills CA 92653",
    "addr:housenumber":"25101",
    "addr:postcode":"92653",
    "addr:street":"Southport St",
    "iso:country":"US",
    "sg:address":"25101 Southport St",
    "sg:city":"Laguna Hills",
    "sg:classifiers":[
        {
            "category":"Freight",
            "type":"Transportation"
        }
    ],
    "sg:phone":"+1 949 697 3833",
    "sg:postcode":"92653",
    "sg:province":"CA",
    "sg:tags":[
        "operator",
        "local",
        "trucking"
    ],
    "wof:name":"Professional Delivery Service",
    "wof:placetype":"venue"
},
  "geometry": {"coordinates":[-117.69524,33.5972],"type":"Point"}
}