{
  "type": "Feature",
  "properties": {
    "iso:country":"US",
    "sg:address":"1802 Manor Dr",
    "sg:city":"Santa Rosa",
    "sg:classifiers":[
        {
            "category":"Building & Trades",
            "subcategory":"Construction",
            "type":"Services"
        }
    ],
    "sg:phone":"+1 707 528 4370",
    "sg:postcode":"95403",
    "sg:province":"CA",
    "sg:tags":[
        "carpentry",
        "contractor"
    ],
    "wof:name":"WC Ferrell Cabinetry",
    "wof:placetype":"venue"
},
  "geometry": {"coordinates":[-122.757893,38.45281],"type":"Point"}
}