{
  "type": "Feature",
  "properties": {
    "addr:full":"27160 Newport Rd Menifee CA 92584",
    "addr:housenumber":"27160",
    "addr:postcode":"92584",
    "addr:street":"Newport Rd",
    "iso:country":"US",
    "sg:address":"27160 Newport Rd",
    "sg:city":"Menifee",
    "sg:classifiers":[
        {
            "category":"Building & Trades",
            "subcategory":"Construction",
            "type":"Services"
        }
    ],
    "sg:phone":"+1 951 246 1416",
    "sg:postcode":"92584",
    "sg:province":"CA",
    "sg:tags":[
        "contractor"
    ],
    "wof:name":"Apco Construction",
    "wof:placetype":"venue"
},
  "geometry": {"coordinates":[-117.18542600000001,33.685113],"type":"Point"}
}