{
  "type": "Feature",
  "properties": {
    "iso:country":"US",
    "sg:address":"7022 Greenleaf Ave",
    "sg:city":"Whittier",
    "sg:classifiers":[
        {
            "category":"Restaurant",
            "type":"Food & Drink"
        }
    ],
    "sg:phone":"+1 562 698 4760",
    "sg:postcode":"90602",
    "sg:province":"CA",
    "sg:tags":[
        "mexican"
    ],
    "wof:name":"Sierra Verde",
    "wof:placetype":"venue"
},
  "geometry": {"coordinates":[-118.037376,33.978681],"type":"Point"}
}