{
  "type": "Feature",
  "properties": {
    "addr:full":"321 Jewell Ave Sebastopol CA 95472",
    "addr:housenumber":"321",
    "addr:postcode":"95472",
    "addr:street":"Jewell Ave",
    "iso:country":"US",
    "sg:address":"321 Jewell Ave",
    "sg:city":"Sebastopol",
    "sg:classifiers":[
        {
            "category":"Professional",
            "type":"Services"
        }
    ],
    "sg:phone":"+1 707 823 3335",
    "sg:postcode":"95472",
    "sg:province":"CA",
    "wof:name":"Forget You Not Designs",
    "wof:placetype":"venue"
},
  "geometry": {"coordinates":[-122.827389,38.39777],"type":"Point"}
}