{
  "type": "Feature",
  "properties": {
    "iso:country":"US",
    "sg:address":"410 Princeland Ct",
    "sg:city":"Corona",
    "sg:classifiers":[
        {
            "category":"Professional",
            "subcategory":"Detective & Security Services",
            "type":"Services"
        }
    ],
    "sg:phone":"+1 951 549 6925",
    "sg:postcode":"92879",
    "sg:province":"CA",
    "sg:tags":[
        "bodyguard",
        "patrol",
        "consultant",
        "system",
        "equipment",
        "guard"
    ],
    "wof:name":"Nordic Security Services",
    "wof:placetype":"venue"
},
  "geometry": {"coordinates":[-117.562099,33.88636],"type":"Point"}
}