{
  "type": "Feature",
  "properties": {
    "iso:country":"US",
    "sg:address":"1030 Larkin St",
    "sg:city":"San Francisco",
    "sg:classifiers":[
        {
            "category":"Freight",
            "type":"Transportation"
        }
    ],
    "sg:phone":"+1 415 424 7751",
    "sg:postcode":"94109",
    "sg:province":"CA",
    "wof:name":"Dujardin Leonel Transportation",
    "wof:placetype":"venue"
},
  "geometry": {"coordinates":[-122.418387,37.787952],"type":"Point"}
}