{
  "type": "Feature",
  "properties": {
    "iso:country":"US",
    "sg:address":"106 N 8th St",
    "sg:city":"Santa Paula",
    "sg:classifiers":[
        {
            "category":"Utilities",
            "subcategory":"Water",
            "type":"Services"
        }
    ],
    "sg:phone":"+1 805 525 4431",
    "sg:postcode":"93060",
    "sg:province":"CA",
    "sg:tags":[
        "conservation",
        "agency",
        "public",
        "ground"
    ],
    "sg:website":"www.unitedwater.org",
    "wof:name":"United Water Conservation Dist",
    "wof:placetype":"venue"
},
  "geometry": {"coordinates":[-119.06488,34.354213],"type":"Point"}
}