{
  "type": "Feature",
  "properties": {
    "iso:country":"US",
    "sg:address":"2040 S Hacienda Blvd",
    "sg:city":"Hacienda Heights",
    "sg:classifiers":[
        {
            "category":"Banks & Credit Unions",
            "subcategory":"Bank",
            "type":"Services"
        }
    ],
    "sg:phone":"+1 626 330 3361",
    "sg:postcode":"91745",
    "sg:province":"CA",
    "wof:name":"Pacific Century Bank",
    "wof:placetype":"venue"
},
  "geometry": {"coordinates":[-117.967793,33.996539],"type":"Point"}
}