{
  "type": "Feature",
  "properties": {
    "addr:full":"1510 11th St Santa Monica CA 90401",
    "addr:housenumber":"1510",
    "addr:postcode":"90401",
    "addr:street":"11Th St",
    "iso:country":"US",
    "sg:address":"1510 11th St",
    "sg:city":"Santa Monica",
    "sg:classifiers":[
        {
            "category":"Wholesale",
            "subcategory":"Groceries",
            "type":"Manufacturing & Wholesale Goods"
        }
    ],
    "sg:phone":"+1 310 451 4505",
    "sg:postcode":"90401",
    "sg:province":"CA",
    "sg:tags":[
        "food",
        "broker"
    ],
    "wof:name":"Trading West",
    "wof:placetype":"venue"
},
  "geometry": {"coordinates":[-118.485598,34.019225],"type":"Point"}
}