{
  "type": "Feature",
  "properties": {
    "addr:full":"12765 Van Nuys Blvd Pacoima CA 91331",
    "addr:housenumber":"12765",
    "addr:postcode":"91331",
    "addr:street":"Van Nuys Blvd",
    "iso:country":"US",
    "sg:address":"12765 Van Nuys Blvd",
    "sg:city":"Pacoima",
    "sg:classifiers":[
        {
            "category":"Food & Beverages",
            "subcategory":"Groceries & Convenience Stores",
            "type":"Retail Goods"
        }
    ],
    "sg:phone":"+1 818 890 1151",
    "sg:postcode":"91331",
    "sg:province":"CA",
    "wof:name":"Food 4 Less",
    "wof:placetype":"venue"
},
  "geometry": {"coordinates":[-118.409963,34.275306],"type":"Point"}
}