{
  "type": "Feature",
  "properties": {
    "iso:country":"US",
    "sg:address":"18727 Main St",
    "sg:city":"Groveland",
    "sg:classifiers":[
        {
            "category":"Real Estate",
            "subcategory":"Real Estate Agent",
            "type":"Services"
        }
    ],
    "sg:phone":"+1 209 962 7765",
    "sg:postcode":"95321",
    "sg:province":"CA",
    "sg:website":"www.sugarpinerealty.com",
    "wof:name":"Sugar Pine Realty",
    "wof:placetype":"venue"
},
  "geometry": {"coordinates":[-120.232919,37.837588],"type":"Point"}
}