{
  "type": "Feature",
  "properties": {
    "iso:country":"US",
    "sg:address":"6301 E Gage Ave",
    "sg:city":"Los Angeles",
    "sg:classifiers":[
        {
            "category":"Food & Beverages",
            "subcategory":"Groceries & Convenience Stores",
            "type":"Retail Goods"
        }
    ],
    "sg:phone":"+1 323 773 0446",
    "sg:postcode":"90040",
    "sg:province":"CA",
    "wof:name":"Merrymart",
    "wof:placetype":"venue"
},
  "geometry": {"coordinates":[-118.14857000000001,33.973973],"type":"Point"}
}