{
  "type": "Feature",
  "properties": {
    "iso:country":"US",
    "sg:address":"321 Webster St",
    "sg:city":"Monterey",
    "sg:classifiers":[
        {
            "category":"Banks & Credit Unions",
            "subcategory":"Bank",
            "type":"Services"
        }
    ],
    "sg:phone":"+1 831 642 6090",
    "sg:postcode":"93940",
    "sg:province":"CA",
    "wof:name":"Monterey County Bank",
    "wof:placetype":"venue"
},
  "geometry": {"coordinates":[-121.892439,36.596693],"type":"Point"}
}