{
  "type": "Feature",
  "properties": {
    "iso:country":"US",
    "sg:address":"2601 Oakdale Rd",
    "sg:city":"Modesto",
    "sg:classifiers":[
        {
            "category":"Personal",
            "subcategory":"Beauty Salon",
            "type":"Services"
        },
        {
            "category":"Personal",
            "subcategory":"Skin Care",
            "type":"Services"
        },
        {
            "category":"Personal",
            "subcategory":"Nail Salon",
            "type":"Services"
        }
    ],
    "sg:phone":"+1 209 575 1688",
    "sg:postcode":"95355",
    "sg:province":"CA",
    "wof:name":"Capital Nails",
    "wof:placetype":"venue"
},
  "geometry": {"coordinates":[-120.957748,37.678131],"type":"Point"}
}