{
  "type": "Feature",
  "properties": {
    "addr:full":"1390 Market Street San Francisco CA 94102",
    "addr:housenumber":"1390",
    "addr:postcode":"94102",
    "addr:street":"Market Street",
    "iso:country":"US",
    "sg:address":"1390 Market Street",
    "sg:city":"San Francisco",
    "sg:classifiers":[
        {
            "category":"Professional",
            "subcategory":"Lawyer & Legal Services",
            "type":"Services"
        }
    ],
    "sg:phone":"+1 415 626 5400",
    "sg:postcode":"94102",
    "sg:province":"CA",
    "sg:tags":[
        "personal",
        "injury"
    ],
    "sg:website":"www.mjmandel.com",
    "wof:name":"Greenberg Peter M Atty",
    "wof:placetype":"venue"
},
  "geometry": {"coordinates":[-122.41716099999999,37.776853],"type":"Point"}
}