{
  "type": "Feature",
  "properties": {
    "iso:country":"US",
    "sg:address":"591 Lake Tahoe Blvd",
    "sg:city":"South Lake Tahoe",
    "sg:classifiers":[
        {
            "category":"Health Services",
            "subcategory":"Doctor",
            "type":"Services"
        }
    ],
    "sg:phone":"+1 530 541 4042",
    "sg:postcode":"96158",
    "sg:province":"NV",
    "sg:tags":[
        "dentist"
    ],
    "wof:name":"Gary B Woodcock DDS",
    "wof:placetype":"venue"
},
  "geometry": {"coordinates":[-120.034077,38.877314],"type":"Point"}
}