{
  "type": "Feature",
  "properties": {
    "addr:full":"1105 W Columbia Way M Lancaster CA 93534",
    "addr:housenumber":"1105",
    "addr:postcode":"93534",
    "addr:street":"W Columbia Way M",
    "iso:country":"US",
    "sg:address":"1105 W Columbia Way M",
    "sg:city":"Lancaster",
    "sg:classifiers":[
        {
            "category":"Insurance",
            "subcategory":"Insurance Agent",
            "type":"Services"
        },
        {
            "category":"Insurance",
            "subcategory":"Hazard Insurance",
            "type":"Services"
        },
        {
            "category":"Insurance",
            "subcategory":"Title Insurance",
            "type":"Services"
        },
        {
            "category":"Insurance",
            "subcategory":"Life Insurance",
            "type":"Services"
        }
    ],
    "sg:phone":"+1 661 951 8900",
    "sg:postcode":"93534",
    "sg:province":"CA",
    "sg:tags":[
        "business",
        "auto",
        "commercial",
        "homeowner",
        "motorcycle",
        "renter"
    ],
    "wof:name":"Allstate Insurance Company - Mark Goldman",
    "wof:placetype":"venue"
},
  "geometry": {"coordinates":[-118.149912,34.645791],"type":"Point"}
}