{
  "type": "Feature",
  "properties": {
    "iso:country":"US",
    "sg:address":"4690 Victoria Ave",
    "sg:city":"Riverside",
    "sg:classifiers":[
        {
            "category":"Organizations",
            "subcategory":"Religious Organization",
            "type":"Services"
        }
    ],
    "sg:phone":"+1 951 684 7443",
    "sg:postcode":"92507",
    "sg:province":"CA",
    "sg:tags":[
        "church"
    ],
    "wof:name":"St James Church Of God-Christ",
    "wof:placetype":"venue"
},
  "geometry": {"coordinates":[-117.36823200000001,33.965811],"type":"Point"}
}