{
  "type": "Feature",
  "properties": {
    "addr:full":"3825 E Ventura Ave Fresno CA 93702",
    "addr:housenumber":"3825",
    "addr:postcode":"93702",
    "addr:street":"E Ventura Ave",
    "iso:country":"US",
    "sg:address":"3825 E Ventura Ave",
    "sg:city":"Fresno",
    "sg:classifiers":[
        {
            "category":"Autos & Motor Vehicles",
            "subcategory":"Automobile Sales",
            "type":"Retail Goods"
        }
    ],
    "sg:phone":"+1 559 255 5213",
    "sg:postcode":"93702",
    "sg:province":"CA",
    "sg:tags":[
        "dealers-used",
        "car",
        "used",
        "cars-wholesale"
    ],
    "wof:name":"Luxury Auto Imports",
    "wof:placetype":"venue"
},
  "geometry": {"coordinates":[-119.760217,36.735934],"type":"Point"}
}