{
  "type": "Feature",
  "properties": {
    "iso:country":"US",
    "sg:address":"5885 Downey Ave",
    "sg:city":"Long Beach",
    "sg:classifiers":[
        {
            "category":"Organizations",
            "subcategory":"Religious Organization",
            "type":"Services"
        }
    ],
    "sg:phone":"+1 562 634 1056",
    "sg:postcode":"90805",
    "sg:province":"CA",
    "sg:tags":[
        "church"
    ],
    "wof:name":"Community Grace Brethren Chr",
    "wof:placetype":"venue"
},
  "geometry": {"coordinates":[-118.151278,33.862236],"type":"Point"}
}