{
  "type": "Feature",
  "properties": {
    "addr:full":"22720 Roscoe Blvd West Hills CA 91304",
    "addr:housenumber":"22720",
    "addr:postcode":"91304",
    "addr:street":"Roscoe Blvd",
    "iso:country":"US",
    "sg:address":"22720 Roscoe Blvd",
    "sg:city":"West Hills",
    "sg:classifiers":[
        {
            "category":"Deli",
            "type":"Food & Drink"
        },
        {
            "category":"Food & Beverages",
            "subcategory":"Bakery",
            "type":"Retail Goods"
        }
    ],
    "sg:phone":"+1 818 884 5131",
    "sg:postcode":"91304",
    "sg:province":"CA",
    "sg:tags":[
        "sandwich"
    ],
    "sg:website":"www.bigmosubandgrill.com/",
    "wof:name":"Big Mo's Subs & Grill",
    "wof:placetype":"venue"
},
  "geometry": {"coordinates":[-118.621745,34.219424],"type":"Point"}
}