{
  "type": "Feature",
  "properties": {
    "addr:full":"3330 el Cajon Blvd San Diego CA 92104",
    "addr:housenumber":"3330",
    "addr:postcode":"92104",
    "addr:street":"El Cajon Blvd",
    "iso:country":"US",
    "sg:address":"3330 el Cajon Blvd",
    "sg:city":"San Diego",
    "sg:classifiers":[
        {
            "category":"Autos & Motor Vehicles",
            "subcategory":"Auto Supplies",
            "type":"Retail Goods"
        }
    ],
    "sg:phone":"+1 619 283 7381",
    "sg:postcode":"92104",
    "sg:province":"CA",
    "sg:tags":[
        "corvette",
        "repair",
        "parts",
        "used"
    ],
    "wof:name":"Corvette Spcalty By Dave Meyer",
    "wof:placetype":"venue"
},
  "geometry": {"coordinates":[-117.121205,32.755334],"type":"Point"}
}