{
  "type": "Feature",
  "properties": {
    "iso:country":"US",
    "sg:address":"164 N. Oak Knoll # 11",
    "sg:city":"Pasadena",
    "sg:classifiers":[
        {
            "category":"Personal",
            "subcategory":"Massage",
            "type":"Services"
        },
        {
            "category":"Health Services",
            "subcategory":"Health Practitioner",
            "type":"Services"
        }
    ],
    "sg:phone":"+1 626 390 0820",
    "sg:postcode":"91101",
    "sg:province":"CA",
    "sg:tags":[
        "therapy",
        "physical"
    ],
    "sg:website":"bodhi.massagetherapy.com",
    "wof:name":"Bodhi McLeod, LMT",
    "wof:placetype":"venue"
},
  "geometry": {"coordinates":[-118.13518999999999,34.14305],"type":"Point"}
}