{
  "type": "Feature",
  "properties": {
    "addr:full":"6067 Cahalan Ave San Jose CA 95123",
    "addr:housenumber":"6067",
    "addr:postcode":"95123",
    "addr:street":"Cahalan Ave",
    "iso:country":"US",
    "sg:address":"6067 Cahalan Ave",
    "sg:city":"San Jose",
    "sg:classifiers":[
        {
            "category":"Shopping",
            "type":"Retail Goods"
        }
    ],
    "sg:phone":"+1 408 224 8075",
    "sg:postcode":"95123",
    "sg:province":"CA",
    "sg:tags":[
        "art",
        "gallery",
        "dealer"
    ],
    "wof:name":"Artcraft Framing",
    "wof:placetype":"venue"
},
  "geometry": {"coordinates":[-121.85069300000001,37.23932],"type":"Point"}
}