{
  "type": "Feature",
  "properties": {
    "addr:full":"406 9th Ave Suite 212 San Diego CA 92101",
    "addr:housenumber":"406",
    "addr:postcode":"92101",
    "addr:street":"9Th Ave Suite 212",
    "iso:country":"US",
    "sg:address":"406 9th Ave Suite 212",
    "sg:city":"San Diego",
    "sg:classifiers":[
        {
            "category":"Professional",
            "subcategory":"Lawyer & Legal Services",
            "type":"Services"
        }
    ],
    "sg:phone":"+1 619 595 1655",
    "sg:postcode":"92101",
    "sg:province":"CA",
    "sg:website":"www.IRSsolution.com",
    "wof:name":"The Law Offices of Ronson Shamoun",
    "wof:placetype":"venue"
},
  "geometry": {"coordinates":[-117.156921,32.709641],"type":"Point"}
}