{
  "type": "Feature",
  "properties": {
    "addr:full":"7042 Drywood Way Orangevale CA 95662",
    "addr:housenumber":"7042",
    "addr:postcode":"95662",
    "addr:street":"Drywood Way",
    "iso:country":"US",
    "sg:address":"7042 Drywood Way",
    "sg:city":"Orangevale",
    "sg:classifiers":[
        {
            "category":"Wholesale",
            "subcategory":"Auto Parts",
            "type":"Manufacturing & Wholesale Goods"
        }
    ],
    "sg:phone":"+1 916 729 4372",
    "sg:postcode":"95662",
    "sg:province":"CA",
    "wof:name":"Trailer Hitch Inserts",
    "wof:placetype":"venue"
},
  "geometry": {"coordinates":[-121.25425199999999,38.693677],"type":"Point"}
}