{
  "type": "Feature",
  "properties": {
    "iso:country":"US",
    "sg:address":"220 S Linden Ave Ste B",
    "sg:city":"South San Francisco",
    "sg:classifiers":[
        {
            "category":"Professional",
            "subcategory":"Printing & Photocopies",
            "type":"Services"
        }
    ],
    "sg:phone":"+1 415 760 9227",
    "sg:postcode":"94080",
    "sg:province":"CA",
    "sg:website":"www.bayshred.com",
    "wof:name":"Bay Shred",
    "wof:placetype":"venue"
},
  "geometry": {"coordinates":[-122.41251200000001,37.64144],"type":"Point"}
}