{
  "type": "Feature",
  "properties": {
    "iso:country":"US",
    "sg:address":"7130 Engineer Rd",
    "sg:city":"San Diego",
    "sg:classifiers":[
        {
            "category":"Wholesale",
            "subcategory":"Computers",
            "type":"Manufacturing & Wholesale Goods"
        }
    ],
    "sg:phone":"+1 858 279 7400",
    "sg:postcode":"92111",
    "sg:province":"CA",
    "sg:website":"www.ocp.com",
    "wof:name":"Oasis Computer Products",
    "wof:placetype":"venue"
},
  "geometry": {"coordinates":[-117.158485,32.827259],"type":"Point"}
}