{
  "type": "Feature",
  "properties": {
    "iso:country":"US",
    "sg:address":"221 Tuxedo Ct",
    "sg:city":"Stockton",
    "sg:classifiers":[
        {
            "category":"Insurance",
            "subcategory":"Insurance Agent",
            "type":"Services"
        },
        {
            "category":"Insurance",
            "subcategory":"Hazard Insurance",
            "type":"Services"
        },
        {
            "category":"Insurance",
            "subcategory":"Title Insurance",
            "type":"Services"
        },
        {
            "category":"Insurance",
            "subcategory":"Life Insurance",
            "type":"Services"
        }
    ],
    "sg:phone":"+1 209 943 8344",
    "sg:postcode":"95204",
    "sg:province":"CA",
    "sg:tags":[
        "business",
        "auto",
        "commercial",
        "homeowner",
        "motorcycle",
        "renter"
    ],
    "wof:name":"Allstate Insurance Company - Tim Delaney",
    "wof:placetype":"venue"
},
  "geometry": {"coordinates":[-121.300731,37.971647],"type":"Point"}
}