{
  "type": "Feature",
  "properties": {
    "addr:full":"795 Folsom St San Francisco CA 94107",
    "addr:housenumber":"795",
    "addr:postcode":"94107",
    "addr:street":"Folsom St",
    "iso:country":"US",
    "sg:address":"795 Folsom St",
    "sg:city":"San Francisco",
    "sg:classifiers":[
        {
            "category":"Travel",
            "subcategory":"Hotels & Motels",
            "type":"Entertainment"
        }
    ],
    "sg:phone":"+1 415 540 8280",
    "sg:postcode":"94107",
    "sg:province":"CA",
    "sg:tags":[
        "operation"
    ],
    "wof:name":"Marriott",
    "wof:placetype":"venue"
},
  "geometry": {"coordinates":[-122.400589,37.782488],"type":"Point"}
}