{
  "type": "Feature",
  "properties": {
    "addr:full":"4120 Douglas Blvd Roseville CA 95746",
    "addr:housenumber":"4120",
    "addr:postcode":"95746",
    "addr:street":"Douglas Blvd",
    "iso:country":"US",
    "sg:address":"4120 Douglas Blvd",
    "sg:city":"Roseville",
    "sg:classifiers":[
        {
            "category":"Personal",
            "subcategory":"Beauty Salon",
            "type":"Services"
        }
    ],
    "sg:phone":"+1 916 791 4545",
    "sg:postcode":"95746",
    "sg:province":"CA",
    "wof:name":"Great Reflections",
    "wof:placetype":"venue"
},
  "geometry": {"coordinates":[-121.22578900000001,38.74374],"type":"Point"}
}