{
  "type": "Feature",
  "properties": {
    "iso:country":"US",
    "sg:address":"21770 Foster Rd",
    "sg:city":"Corona",
    "sg:classifiers":[
        {
            "category":"Retail",
            "subcategory":"Car Wash",
            "type":"Services"
        }
    ],
    "sg:phone":"+1 909 496 5772",
    "sg:postcode":"92883",
    "sg:province":"CA",
    "sg:tags":[
        "truck",
        "cleaning"
    ],
    "wof:name":"S L Svc",
    "wof:placetype":"venue"
},
  "geometry": {"coordinates":[-117.502748,33.803848],"type":"Point"}
}