{
  "type": "Feature",
  "properties": {
    "addr:full":"150 W Bonita Ave San Dimas CA 91773",
    "addr:housenumber":"150",
    "addr:postcode":"91773",
    "addr:street":"W Bonita Ave",
    "iso:country":"US",
    "sg:address":"150 W Bonita Ave",
    "sg:city":"San Dimas",
    "sg:classifiers":[
        {
            "category":"Real Estate",
            "subcategory":"Real Estate Agent",
            "type":"Services"
        }
    ],
    "sg:phone":"+1 626 966 8859",
    "sg:postcode":"91773",
    "sg:province":"CA",
    "sg:tags":[
        "brokerage"
    ],
    "wof:name":"Realestate By Walterscheid",
    "wof:placetype":"venue"
},
  "geometry": {"coordinates":[-117.809228,34.106583],"type":"Point"}
}