{
  "type": "Feature",
  "properties": {
    "iso:country":"US",
    "sg:address":"5249 1/2 Paramount Blvd",
    "sg:city":"Lakewood",
    "sg:classifiers":[
        {
            "category":"Shopping",
            "subcategory":"Florist",
            "type":"Retail Goods"
        }
    ],
    "sg:phone":"+1 562 630 3698",
    "sg:postcode":"90712",
    "sg:province":"CA",
    "wof:name":"Graceful Goods",
    "wof:placetype":"venue"
},
  "geometry": {"coordinates":[-118.160087,33.852804],"type":"Point"}
}