{
  "type": "Feature",
  "properties": {
    "addr:full":"19516 Quail Creek Pl Northridge CA 91326",
    "addr:housenumber":"19516",
    "addr:postcode":"91326",
    "addr:street":"Quail Creek Pl",
    "iso:country":"US",
    "sg:address":"19516 Quail Creek Pl",
    "sg:city":"Northridge",
    "sg:classifiers":[
        {
            "category":"Government",
            "subcategory":"Fire Station",
            "type":"Public Place"
        }
    ],
    "sg:phone":"+1 818 368 7387",
    "sg:postcode":"91326",
    "sg:province":"CA",
    "sg:tags":[
        "protection"
    ],
    "wof:name":"California Fire Station",
    "wof:placetype":"venue"
},
  "geometry": {"coordinates":[-118.558182,34.277747],"type":"Point"}
}