{
  "type": "Feature",
  "properties": {
    "iso:country":"US",
    "sg:address":"22872 Ave Empresa",
    "sg:city":"Rancho Santa Margarita",
    "sg:classifiers":[
        {
            "category":"Manufacturing",
            "subcategory":"Tools & Machinery",
            "type":"Manufacturing & Wholesale Goods"
        }
    ],
    "sg:phone":"+1 949 713 8000",
    "sg:postcode":"92688",
    "sg:province":"CA",
    "sg:tags":[
        "instrument",
        "medical",
        "mfg"
    ],
    "wof:name":"Applied Medical Dist Corp",
    "wof:placetype":"venue"
},
  "geometry": {"coordinates":[-117.6041,33.62817],"type":"Point"}
}