{
  "type": "Feature",
  "properties": {
    "iso:country":"US",
    "sg:address":"1191 7th St",
    "sg:city":"Mendota",
    "sg:classifiers":[
        {
            "category":"Food & Beverages",
            "subcategory":"Groceries & Convenience Stores",
            "type":"Retail Goods"
        }
    ],
    "sg:phone":"+1 559 655 3251",
    "sg:postcode":"93640",
    "sg:province":"CA",
    "wof:name":"Mendota Market",
    "wof:placetype":"venue"
},
  "geometry": {"coordinates":[-120.376825,36.75751],"type":"Point"}
}