{
  "type": "Feature",
  "properties": {
    "addr:full":"5167 Johnson Dr Pleasanton CA 94588",
    "addr:housenumber":"5167",
    "addr:postcode":"94588",
    "addr:street":"Johnson Dr",
    "iso:country":"US",
    "sg:address":"5167 Johnson Dr",
    "sg:city":"Pleasanton",
    "sg:classifiers":[
        {
            "category":"Building & Trades",
            "subcategory":"Electrical",
            "type":"Services"
        }
    ],
    "sg:phone":"+1 925 734 8757",
    "sg:postcode":"94588",
    "sg:province":"CA",
    "sg:tags":[
        "electrical",
        "electronic",
        "contractor"
    ],
    "wof:name":"Expanets of California Inc",
    "wof:placetype":"venue"
},
  "geometry": {"coordinates":[-121.907173,37.698409],"type":"Point"}
}