{
  "type": "Feature",
  "properties": {
    "addr:full":"83 Pope St San Francisco CA 94112",
    "addr:housenumber":"83",
    "addr:postcode":"94112",
    "addr:street":"Pope St",
    "iso:country":"US",
    "sg:address":"83 Pope St",
    "sg:city":"San Francisco",
    "sg:classifiers":[
        {
            "category":"Wholesale",
            "subcategory":"Toys & Hobbies",
            "type":"Manufacturing & Wholesale Goods"
        },
        {
            "category":"Wholesale",
            "subcategory":"Non-durable Goods",
            "type":"Manufacturing & Wholesale Goods"
        }
    ],
    "sg:phone":"+1 415 587 4060",
    "sg:postcode":"94112",
    "sg:province":"CA",
    "sg:tags":[
        "wholesaler"
    ],
    "wof:name":"Samuel Trading Import Export",
    "wof:placetype":"venue"
},
  "geometry": {"coordinates":[-122.44162,37.715333],"type":"Point"}
}