{
  "type": "Feature",
  "properties": {
    "iso:country":"US",
    "sg:address":"161 Alpine Way",
    "sg:city":"San Bruno",
    "sg:classifiers":[
        {
            "category":"Real Estate",
            "subcategory":"Real Estate Agent",
            "type":"Services"
        }
    ],
    "sg:phone":"+1 650 756 5120",
    "sg:postcode":"94066",
    "sg:province":"CA",
    "sg:tags":[
        "investment"
    ],
    "wof:name":"Lone Wolf Investments",
    "wof:placetype":"venue"
},
  "geometry": {"coordinates":[-122.43839199999999,37.619155],"type":"Point"}
}