{
  "type": "Feature",
  "properties": {
    "iso:country":"US",
    "sg:address":"312 S Catalina Ave",
    "sg:city":"Redondo Beach",
    "sg:classifiers":[
        {
            "category":"Home & Garden",
            "subcategory":"Furniture",
            "type":"Retail Goods"
        }
    ],
    "sg:phone":"+1 310 379 9800",
    "sg:postcode":"90277",
    "sg:province":"CA",
    "sg:tags":[
        "equipment",
        "kitchen",
        "cabinet"
    ],
    "wof:name":"Kitchen Studio South Bay",
    "wof:placetype":"venue"
},
  "geometry": {"coordinates":[-118.387857,33.83665],"type":"Point"}
}