{
  "type": "Feature",
  "properties": {
    "addr:full":"2420 Cam Ramon San Ramon CA 94583",
    "addr:housenumber":"2420",
    "addr:postcode":"ramon ca 94583",
    "addr:street":"Cam Ramon San",
    "iso:country":"US",
    "sg:address":"2420 Cam Ramon",
    "sg:city":"San Ramon",
    "sg:classifiers":[
        {
            "category":"Wholesale",
            "subcategory":"Durable Goods & Equipment",
            "type":"Manufacturing & Wholesale Goods"
        }
    ],
    "sg:phone":"+1 925 866 9988",
    "sg:postcode":"94583",
    "sg:province":"CA",
    "sg:tags":[
        "exporter"
    ],
    "wof:name":"Appollo International",
    "wof:placetype":"venue"
},
  "geometry": {"coordinates":[-121.96266199999999,37.770956],"type":"Point"}
}