{
  "type": "Feature",
  "properties": {
    "iso:country":"US",
    "sg:address":"3132 Lincoln Ave",
    "sg:city":"San Diego",
    "sg:classifiers":[
        {
            "category":"Health Services",
            "subcategory":"Health Practitioner",
            "type":"Services"
        }
    ],
    "sg:phone":"+1 619 281 1271",
    "sg:postcode":"92104",
    "sg:province":"CA",
    "sg:tags":[
        "nurse"
    ],
    "wof:name":"R E Health Clinic",
    "wof:placetype":"venue"
},
  "geometry": {"coordinates":[-117.126624,32.750429],"type":"Point"}
}