{
  "type": "Feature",
  "properties": {
    "iso:country":"US",
    "sg:address":"4959 Arlington Ave",
    "sg:city":"Riverside",
    "sg:classifiers":[
        {
            "category":"Health Services",
            "subcategory":"Doctor",
            "type":"Services"
        }
    ],
    "sg:phone":"+1 951 787 7150",
    "sg:postcode":"92504",
    "sg:province":"CA",
    "sg:tags":[
        "dentist"
    ],
    "wof:name":"Patrick W Schenk DDS",
    "wof:placetype":"venue"
},
  "geometry": {"coordinates":[-117.411924,33.946179],"type":"Point"}
}