{
  "type": "Feature",
  "properties": {
    "iso:country":"US",
    "sg:address":"5950 Serendipity Rd",
    "sg:city":"Riverside",
    "sg:classifiers":[
        {
            "category":"Place Of Worship",
            "subcategory":"Church",
            "type":"Public Place"
        },
        {
            "category":"Place Of Worship",
            "type":"Public Place"
        }
    ],
    "sg:phone":"+1 951 681 0211",
    "sg:postcode":"92509",
    "sg:province":"CA",
    "sg:tags":[
        "testament",
        "churches-church",
        "christ-new",
        "christ"
    ],
    "wof:name":"Norco Ward",
    "wof:placetype":"venue"
},
  "geometry": {"coordinates":[-117.50494500000001,33.980005],"type":"Point"}
}