{
  "type": "Feature",
  "properties": {
    "addr:full":"6921 El Cajon Boulevard San Diego CA 92115",
    "addr:housenumber":"6921",
    "addr:postcode":"92115",
    "addr:street":"El Cajon Boulevard",
    "iso:country":"US",
    "sg:address":"6921 El Cajon Boulevard",
    "sg:city":"San Diego",
    "sg:classifiers":[
        {
            "category":"Personal",
            "subcategory":"Nail Salon",
            "type":"Services"
        }
    ],
    "sg:phone":"+1 619 667 2016",
    "sg:postcode":"92115",
    "sg:province":"CA",
    "wof:name":"Levi Nails",
    "wof:placetype":"venue"
},
  "geometry": {"coordinates":[-117.048984,32.768716],"type":"Point"}
}