{
  "type": "Feature",
  "properties": {
    "addr:full":"3901 Landis St San Diego CA 92105",
    "addr:housenumber":"3901",
    "addr:postcode":"92105",
    "addr:street":"Landis St",
    "iso:country":"US",
    "sg:address":"3901 Landis St",
    "sg:city":"San Diego",
    "sg:classifiers":[
        {
            "category":"Social Services",
            "subcategory":"Child Care",
            "type":"Services"
        }
    ],
    "sg:phone":"+1 619 563 0162",
    "sg:postcode":"92105",
    "sg:province":"CA",
    "wof:name":"De LA Paz Head Start",
    "wof:placetype":"venue"
},
  "geometry": {"coordinates":[-117.110056,32.745954],"type":"Point"}
}