{
  "type": "Feature",
  "properties": {
    "addr:full":"1630 W 158th St Gardena CA 90247",
    "addr:housenumber":"1630",
    "addr:postcode":"90247",
    "addr:street":"W 158Th St",
    "iso:country":"US",
    "sg:address":"1630 W 158th St",
    "sg:city":"Gardena",
    "sg:classifiers":[
        {
            "category":"Organizations",
            "subcategory":"Religious Organization",
            "type":"Services"
        }
    ],
    "sg:phone":"+1 310 323 5683",
    "sg:postcode":"90247",
    "sg:province":"CA",
    "sg:tags":[
        "church"
    ],
    "sg:website":"www.gvbc.net",
    "wof:name":"Gardena Valley Baptist Church",
    "wof:placetype":"venue"
},
  "geometry": {"coordinates":[-118.30500000000001,33.887501],"type":"Point"}
}