{
  "type": "Feature",
  "properties": {
    "iso:country":"US",
    "sg:address":"9364 Ridgeside Ln",
    "sg:city":"Orangevale",
    "sg:classifiers":[
        {
            "category":"Real Estate",
            "subcategory":"Real Estate Operator",
            "type":"Services"
        }
    ],
    "sg:phone":"+1 916 988 0760",
    "sg:postcode":"95662",
    "sg:province":"CA",
    "sg:tags":[
        "apartment"
    ],
    "wof:name":"Rollingwood Duplex Homes",
    "wof:placetype":"venue"
},
  "geometry": {"coordinates":[-121.204523,38.672312],"type":"Point"}
}