{
  "type": "Feature",
  "properties": {
    "addr:full":"14842 Upland Rd Magalia CA 95954",
    "addr:housenumber":"14842",
    "addr:postcode":"95954",
    "addr:street":"Upland Rd",
    "iso:country":"US",
    "sg:address":"14842 Upland Rd",
    "sg:city":"Magalia",
    "sg:classifiers":[
        {
            "category":"Manufacturing",
            "subcategory":"Retail Goods",
            "type":"Manufacturing & Wholesale Goods"
        }
    ],
    "sg:phone":"+1 530 873 1540",
    "sg:postcode":"95954",
    "sg:province":"CA",
    "sg:tags":[
        "product",
        "mfg"
    ],
    "wof:name":"Houtman Beekeeping",
    "wof:placetype":"venue"
},
  "geometry": {"coordinates":[-121.594491,39.84845],"type":"Point"}
}