{
  "type": "Feature",
  "properties": {
    "addr:full":"660 3rd St San Francisco CA 94107",
    "addr:housenumber":"660",
    "addr:postcode":"94107",
    "addr:street":"3Rd St",
    "iso:country":"US",
    "sg:address":"660 3rd St",
    "sg:city":"San Francisco",
    "sg:classifiers":[
        {
            "category":"Shopping",
            "subcategory":"Musical Instruments",
            "type":"Retail Goods"
        }
    ],
    "sg:phone":"+1 415 543 9988",
    "sg:postcode":"94107",
    "sg:province":"CA",
    "sg:tags":[
        "equipment"
    ],
    "wof:name":"Piedmont Piano Co",
    "wof:placetype":"venue"
},
  "geometry": {"coordinates":[-122.393553,37.779557],"type":"Point"}
}