{
  "type": "Feature",
  "properties": {
    "iso:country":"US",
    "sg:address":"3675 E 3rd St",
    "sg:city":"Los Angeles",
    "sg:classifiers":[
        {
            "category":"Retail",
            "subcategory":"Auto Repair",
            "type":"Services"
        }
    ],
    "sg:phone":"+1 323 268 5420",
    "sg:postcode":"90063",
    "sg:province":"CA",
    "sg:tags":[
        "muffler",
        "exhaust",
        "system"
    ],
    "wof:name":"East LA Muffler Shop",
    "wof:placetype":"venue"
},
  "geometry": {"coordinates":[-118.189412,34.03338],"type":"Point"}
}