{
  "type": "Feature",
  "properties": {
    "addr:full":"6305 Morella Ave. North Hollywood CA 91606",
    "addr:housenumber":"6305",
    "addr:postcode":"91606",
    "addr:street":"Morella Ave.",
    "iso:country":"US",
    "sg:address":"6305 Morella Ave.",
    "sg:city":"North Hollywood",
    "sg:classifiers":[
        {
            "category":"Communications",
            "type":"Services"
        }
    ],
    "sg:phone":"+1 818 279 4414",
    "sg:postcode":"91606",
    "sg:province":"CA",
    "sg:tags":[
        "recording",
        "rehearsal",
        "studio"
    ],
    "sg:website":"www.myspace.com/deedeeomalley",
    "wof:name":"Size 7 Music Production",
    "wof:placetype":"venue"
},
  "geometry": {"coordinates":[-118.39028399999999,34.185012],"type":"Point"}
}