{
  "type": "Feature",
  "properties": {
    "addr:full":"498 Broadway San Francisco CA 94133",
    "addr:housenumber":"498",
    "addr:postcode":"94133",
    "addr:street":"Broadway",
    "iso:country":"US",
    "sg:address":"498 Broadway",
    "sg:city":"San Francisco",
    "sg:classifiers":[
        {
            "category":"Restaurant",
            "type":"Food & Drink"
        }
    ],
    "sg:phone":"+1 415 837 0228",
    "sg:postcode":"94133",
    "sg:province":"CA",
    "wof:name":"Sake Lab",
    "wof:placetype":"venue"
},
  "geometry": {"coordinates":[-122.40468,37.798117],"type":"Point"}
}