{
  "type": "Feature",
  "properties": {
    "iso:country":"US",
    "sg:address":"9660 Flair Dr",
    "sg:city":"El Monte",
    "sg:classifiers":[
        {
            "category":"Health Services",
            "subcategory":"Clinic",
            "type":"Services"
        }
    ],
    "sg:phone":"+1 626 279 1950",
    "sg:postcode":"91731",
    "sg:province":"CA",
    "sg:tags":[
        "home"
    ],
    "wof:name":"Intermed Home Care Svc",
    "wof:placetype":"venue"
},
  "geometry": {"coordinates":[-118.058907,34.071977],"type":"Point"}
}