{
  "type": "Feature",
  "properties": {
    "iso:country":"US",
    "sg:address":"319 N Taylor Ave",
    "sg:city":"Montebello",
    "sg:classifiers":[
        {
            "category":"Communications",
            "type":"Services"
        }
    ],
    "sg:phone":"+1 323 428 8910",
    "sg:postcode":"90640",
    "sg:province":"CA",
    "sg:tags":[
        "communication"
    ],
    "wof:name":"S & D Digital Communications",
    "wof:placetype":"venue"
},
  "geometry": {"coordinates":[-118.112471,34.016348],"type":"Point"}
}