{
  "type": "Feature",
  "properties": {
    "iso:country":"US",
    "sg:address":"1037 Star Park Cir",
    "sg:city":"Coronado",
    "sg:classifiers":[
        {
            "category":"Building & Trades",
            "subcategory":"Landscaping Services",
            "type":"Services"
        }
    ],
    "sg:phone":"+1 619 435 3895",
    "sg:postcode":"92118",
    "sg:province":"CA",
    "sg:tags":[
        "designer",
        "landscape"
    ],
    "wof:name":"Baby Bloomers",
    "wof:placetype":"venue"
},
  "geometry": {"coordinates":[-117.18052,32.684075],"type":"Point"}
}