{
  "type": "Feature",
  "properties": {
    "addr:full":"1225 W Dakota Ave Fresno CA 93705",
    "addr:housenumber":"1225",
    "addr:postcode":"93705",
    "addr:street":"W Dakota Ave",
    "iso:country":"US",
    "sg:address":"1225 W Dakota Ave",
    "sg:city":"Fresno",
    "sg:classifiers":[
        {
            "category":"Education",
            "subcategory":"School",
            "type":"Public Place"
        }
    ],
    "sg:phone":"+1 559 248 7250",
    "sg:postcode":"93705",
    "sg:province":"CA",
    "sg:tags":[
        "elementary"
    ],
    "sg:website":"http://www.fresno.k12.ca.us",
    "wof:name":"Roeding Elementary School",
    "wof:placetype":"venue"
},
  "geometry": {"coordinates":[-119.82565,36.786553],"type":"Point"}
}