{
  "type": "Feature",
  "properties": {
    "addr:full":"8284 Industrial Ave Roseville CA 95648",
    "addr:housenumber":"8284",
    "addr:postcode":"95648",
    "addr:street":"Industrial Ave",
    "iso:country":"US",
    "sg:address":"8284 Industrial Ave",
    "sg:city":"Roseville",
    "sg:classifiers":[
        {
            "category":"Manufacturing",
            "subcategory":"Food",
            "type":"Manufacturing & Wholesale Goods"
        }
    ],
    "sg:phone":"+1 916 781 2337",
    "sg:postcode":"95648",
    "sg:province":"CA",
    "sg:tags":[
        "malt",
        "beverage",
        "mfg"
    ],
    "wof:name":"Beermann Limited",
    "wof:placetype":"venue"
},
  "geometry": {"coordinates":[-121.30590599999999,38.778162],"type":"Point"}
}