{
  "type": "Feature",
  "properties": {
    "iso:country":"US",
    "sg:address":"2245 Eureka Way",
    "sg:city":"Redding",
    "sg:classifiers":[
        {
            "category":"Organizations",
            "subcategory":"Membership Organization",
            "type":"Services"
        }
    ],
    "sg:phone":"+1 530 244 3005",
    "sg:postcode":"96001",
    "sg:province":"CA",
    "sg:tags":[
        "society",
        "humane"
    ],
    "wof:name":"Forever Pets",
    "wof:placetype":"venue"
},
  "geometry": {"coordinates":[-122.40434399999999,40.586389],"type":"Point"}
}