{
  "type": "Feature",
  "properties": {
    "iso:country":"US",
    "sg:address":"225 Cabrillo Hwy S",
    "sg:city":"Half Moon Bay",
    "sg:classifiers":[
        {
            "category":"Organizations",
            "subcategory":"Religious Organization",
            "type":"Services"
        }
    ],
    "sg:phone":"+1 650 726 5959",
    "sg:postcode":"94019",
    "sg:province":"CA",
    "sg:tags":[
        "church"
    ],
    "sg:website":"www.marinerscc.org",
    "wof:name":"Mariner's Community Church",
    "wof:placetype":"venue"
},
  "geometry": {"coordinates":[-122.434335,37.462359],"type":"Point"}
}