{
  "type": "Feature",
  "properties": {
    "addr:full":"104 E 17th Street Los Angeles CA 90015",
    "addr:housenumber":"104",
    "addr:postcode":"90015",
    "addr:street":"E 17Th Street",
    "iso:country":"US",
    "sg:address":"104 E 17th Street",
    "sg:city":"Los Angeles",
    "sg:classifiers":[
        {
            "category":"Shopping",
            "subcategory":"Bicycles & Sporting Goods",
            "type":"Retail Goods"
        }
    ],
    "sg:phone":"+1 213 745 7711",
    "sg:postcode":"90015",
    "sg:province":"CA",
    "wof:name":"E-Z Sportswear",
    "wof:placetype":"venue"
},
  "geometry": {"coordinates":[-118.263193,34.032754],"type":"Point"}
}