{
  "type": "Feature",
  "properties": {
    "iso:country":"US",
    "sg:address":"289 S San Antonio Rd",
    "sg:city":"Los Altos",
    "sg:classifiers":[
        {
            "category":"Real Estate",
            "subcategory":"Real Estate Services",
            "type":"Services"
        }
    ],
    "sg:phone":"+1 650 947 1910",
    "sg:postcode":"94022",
    "sg:province":"CA",
    "sg:tags":[
        "company",
        "title"
    ],
    "wof:name":"Financial Title Co",
    "wof:placetype":"venue"
},
  "geometry": {"coordinates":[-122.113985,37.378547],"type":"Point"}
}