{
  "type": "Feature",
  "properties": {
    "iso:country":"US",
    "sg:address":"14647 Bonanza Rd",
    "sg:city":"Victorville",
    "sg:classifiers":[
        {
            "category":"Organizations",
            "subcategory":"Religious Organization",
            "type":"Services"
        }
    ],
    "sg:phone":"+1 760 241 6279",
    "sg:postcode":"92392",
    "sg:province":"CA",
    "sg:tags":[
        "church"
    ],
    "wof:name":"St Mary Coptic Orthodox Church",
    "wof:placetype":"venue"
},
  "geometry": {"coordinates":[-117.346751,34.503105],"type":"Point"}
}