{
  "type": "Feature",
  "properties": {
    "addr:full":"3400 Lomita Blvd Torrance CA 90505",
    "addr:housenumber":"3400",
    "addr:postcode":"90505",
    "addr:street":"Lomita Blvd",
    "iso:country":"US",
    "sg:address":"3400 Lomita Blvd",
    "sg:city":"Torrance",
    "sg:classifiers":[
        {
            "category":"Health Services",
            "subcategory":"Doctor",
            "type":"Services"
        }
    ],
    "sg:phone":"+1 310 326 8551",
    "sg:postcode":"90505",
    "sg:province":"CA",
    "sg:tags":[
        "podiatrist"
    ],
    "wof:name":"Serkin Arnold L DPM",
    "wof:placetype":"venue"
},
  "geometry": {"coordinates":[-118.345001,33.813099],"type":"Point"}
}