{
  "type": "Feature",
  "properties": {
    "iso:country":"US",
    "sg:address":"1111 E Cabrillo Blvd",
    "sg:city":"Santa Barbara",
    "sg:classifiers":[
        {
            "category":"Restaurant",
            "type":"Food & Drink"
        }
    ],
    "sg:phone":"+1 805 730 1111",
    "sg:postcode":"93103",
    "sg:province":"CA",
    "wof:name":"Bistro 11 11",
    "wof:placetype":"venue"
},
  "geometry": {"coordinates":[-119.669938,34.417258],"type":"Point"}
}