{
  "type": "Feature",
  "properties": {
    "iso:country":"US",
    "sg:address":"2429 Lomita Blvd",
    "sg:city":"Lomita",
    "sg:classifiers":[
        {
            "category":"Autos & Motor Vehicles",
            "subcategory":"Automobile Sales",
            "type":"Retail Goods"
        }
    ],
    "sg:phone":"+1 310 539 0100",
    "sg:postcode":"90717",
    "sg:province":"CA",
    "sg:tags":[
        "car",
        "dealer"
    ],
    "wof:name":"Run USA Auto Sales",
    "wof:placetype":"venue"
},
  "geometry": {"coordinates":[-118.32579800000001,33.804971],"type":"Point"}
}