{
  "type": "Feature",
  "properties": {
    "iso:country":"US",
    "sg:address":"190 Mendell",
    "sg:city":"San Mateo",
    "sg:classifiers":[
        {
            "category":"Building & Trades",
            "subcategory":"Cleaning & Sanitation",
            "type":"Services"
        }
    ],
    "sg:phone":"+1 650 558 9110",
    "sg:postcode":"94401",
    "sg:province":"CA",
    "sg:tags":[
        "carpet"
    ],
    "wof:name":"North America Chem Dry",
    "wof:placetype":"venue"
},
  "geometry": {"coordinates":[-122.321634,37.571445],"type":"Point"}
}