{
  "type": "Feature",
  "properties": {
    "addr:full":"20510 Big Springs Rd Ste E Weed CA 96094",
    "addr:housenumber":"20510",
    "addr:postcode":"96094",
    "addr:street":"Big Springs Rd Ste E",
    "iso:country":"US",
    "sg:address":"20510 Big Springs Rd Ste E",
    "sg:city":"Weed",
    "sg:classifiers":[
        {
            "category":"Professional",
            "subcategory":"Lawyer & Legal Services",
            "type":"Services"
        }
    ],
    "sg:phone":"+1 530 938 9906",
    "sg:postcode":"96094",
    "sg:province":"CA",
    "sg:tags":[
        "attorney",
        "practice"
    ],
    "wof:name":"Moore Rebecca E Attorney At Law",
    "wof:placetype":"venue"
},
  "geometry": {"coordinates":[-122.35297,41.473354],"type":"Point"}
}