{
  "type": "Feature",
  "properties": {
    "addr:full":"89 Tumble Weed Ct San Ramon CA 94583",
    "addr:housenumber":"89",
    "addr:postcode":"94583",
    "addr:street":"Tumble Weed Ct",
    "iso:country":"US",
    "sg:address":"89 Tumble Weed Ct",
    "sg:city":"San Ramon",
    "sg:classifiers":[
        {
            "category":"Professional",
            "subcategory":"Engineering",
            "type":"Services"
        }
    ],
    "sg:phone":"+1 925 828 4801",
    "sg:postcode":"94583",
    "sg:province":"CA",
    "sg:tags":[
        "engineer"
    ],
    "wof:name":"Synergyn Of Northern Ca",
    "wof:placetype":"venue"
},
  "geometry": {"coordinates":[-121.973777,37.754582],"type":"Point"}
}