{
  "type": "Feature",
  "properties": {
    "iso:country":"US",
    "sg:address":"98 Siena",
    "sg:city":"Laguna Niguel",
    "sg:classifiers":[
        {
            "category":"Professional",
            "type":"Services"
        }
    ],
    "sg:phone":"+1 949 363 9537",
    "sg:postcode":"92677",
    "sg:province":"CA",
    "sg:tags":[
        "arts",
        "artist"
    ],
    "wof:name":"Sound Image Art",
    "wof:placetype":"venue"
},
  "geometry": {"coordinates":[-117.705534,33.510852],"type":"Point"}
}