{
  "type": "Feature",
  "properties": {
    "addr:full":"23010 Cmt Lago Laguna Hills CA 92653",
    "addr:postcode":"23010;92653",
    "addr:street":"Cmt Lago",
    "iso:country":"US",
    "sg:address":"23010 Cmt Lago",
    "sg:city":"Laguna Hills",
    "sg:classifiers":[
        {
            "category":"Utilities",
            "subcategory":"Water",
            "type":"Services"
        }
    ],
    "sg:phone":"+1 949 951 0904",
    "sg:postcode":"92653",
    "sg:province":"CA",
    "sg:tags":[
        "company",
        "sewage"
    ],
    "wof:name":"Mass Air Systems",
    "wof:placetype":"venue"
},
  "geometry": {"coordinates":[-117.736986,33.631022],"type":"Point"}
}