{
  "type": "Feature",
  "properties": {
    "addr:full":"610 N San Antonio Ave Pomona CA 91767",
    "addr:housenumber":"610",
    "addr:postcode":"91767",
    "addr:street":"N San Antonio Ave",
    "iso:country":"US",
    "sg:address":"610 N San Antonio Ave",
    "sg:city":"Pomona",
    "sg:classifiers":[
        {
            "category":"Education",
            "subcategory":"Special Training",
            "type":"Public Place"
        }
    ],
    "sg:phone":"+1 909 622 4193",
    "sg:postcode":"91767",
    "sg:province":"CA",
    "sg:tags":[
        "information",
        "school",
        "college"
    ],
    "wof:name":"Soledad Enrichment Action",
    "wof:placetype":"venue"
},
  "geometry": {"coordinates":[-117.736558,34.064681],"type":"Point"}
}