{
  "type": "Feature",
  "properties": {
    "addr:full":"9090 Wilshire Blvd Ste 200 Beverly Hills CA 90210",
    "addr:housenumber":"9090",
    "addr:postcode":"90210",
    "addr:street":"Wilshire Blvd Ste 200;Hills Ca",
    "iso:country":"US",
    "sg:address":"9090 Wilshire Blvd Ste 200",
    "sg:city":"Beverly Hills",
    "sg:classifiers":[
        {
            "category":"Community Center",
            "type":"Public Place"
        }
    ],
    "sg:phone":"+1 310 888 8680",
    "sg:postcode":"90210",
    "sg:province":"CA",
    "sg:tags":[
        "medical"
    ],
    "sg:website":"www.toweroncology.com",
    "wof:name":"Tower Hematology Oncology Medical Group",
    "wof:placetype":"venue"
},
  "geometry": {"coordinates":[-118.38916500000001,34.066699],"type":"Point"}
}