{
  "type": "Feature",
  "properties": {
    "addr:full":"1124 W Winslow St Upland CA 91786",
    "addr:housenumber":"1124",
    "addr:postcode":"91786",
    "addr:street":"W Winslow St",
    "iso:country":"US",
    "sg:address":"1124 W Winslow St",
    "sg:city":"Upland",
    "sg:classifiers":[
        {
            "category":"Building & Trades",
            "subcategory":"Landscaping Services",
            "type":"Services"
        }
    ],
    "sg:phone":"+1 909 981 2811",
    "sg:postcode":"91786",
    "sg:province":"CA",
    "sg:tags":[
        "tree"
    ],
    "wof:name":"Quality Tree Svc.",
    "wof:placetype":"venue"
},
  "geometry": {"coordinates":[-117.668228,34.115689],"type":"Point"}
}