{
  "type": "Feature",
  "properties": {
    "iso:country":"US",
    "sg:address":"182 Hart Court",
    "sg:city":"Mountain View",
    "sg:classifiers":[
        {
            "category":"Professional",
            "subcategory":"Computer Services",
            "type":"Services"
        }
    ],
    "sg:phone":"+1 952 393 9333",
    "sg:postcode":"94043",
    "sg:province":"CA",
    "sg:tags":[
        "stocks",
        "e-learning",
        "investing"
    ],
    "sg:website":"http://www.tidalwavetrader.com",
    "wof:name":"Tidalwave Trader",
    "wof:placetype":"venue"
},
  "geometry": {"coordinates":[-122.057444,37.390225],"type":"Point"}
}