{
  "type": "Feature",
  "properties": {
    "iso:country":"US",
    "sg:address":"1157 Orange St",
    "sg:city":"Redlands",
    "sg:classifiers":[
        {
            "category":"Museum",
            "type":"Entertainment"
        }
    ],
    "sg:phone":"+1 909 798 0868",
    "sg:postcode":"92374",
    "sg:province":"CA",
    "wof:name":"Historical Glass Museum",
    "wof:placetype":"venue"
},
  "geometry": {"coordinates":[-117.182511,34.066404],"type":"Point"}
}