{
  "type": "Feature",
  "properties": {
    "addr:full":"6408 Independence Ave Woodland Hills CA 91367",
    "addr:housenumber":"6408",
    "addr:postcode":"91367",
    "addr:street":"Independence Ave",
    "iso:country":"US",
    "sg:address":"6408 Independence Ave",
    "sg:city":"Woodland Hills",
    "sg:classifiers":[
        {
            "category":"Shopping",
            "subcategory":"Beauty & Cosmetics",
            "type":"Retail Goods"
        }
    ],
    "sg:phone":"+1 818 703 8249",
    "sg:postcode":"91367",
    "sg:province":"CA",
    "sg:tags":[
        "supply"
    ],
    "wof:name":"Valerie Beverly Hills",
    "wof:placetype":"venue"
},
  "geometry": {"coordinates":[-118.59044299999999,34.187044],"type":"Point"}
}