{
  "type": "Feature",
  "properties": {
    "addr:full":"134 E Main St San Jacinto CA 92583",
    "addr:housenumber":"134",
    "addr:postcode":"92583",
    "addr:street":"E Main St",
    "iso:country":"US",
    "sg:address":"134 E Main St",
    "sg:city":"San Jacinto",
    "sg:classifiers":[
        {
            "category":"Retail",
            "subcategory":"Repair Shop",
            "type":"Services"
        }
    ],
    "sg:phone":"+1 951 654 8880",
    "sg:postcode":"92583",
    "sg:province":"CA",
    "sg:tags":[
        "watch"
    ],
    "wof:name":"Wayne's Jewelry & Watch World",
    "wof:placetype":"venue"
},
  "geometry": {"coordinates":[-116.958102,33.783831],"type":"Point"}
}