{
  "type": "Feature",
  "properties": {
    "addr:full":"240 Stockton Street 6th Floor San Francisco CA 94108",
    "addr:housenumber":"240;6th",
    "addr:postcode":"94108",
    "addr:street":"Stockton Street;Floor",
    "iso:country":"US",
    "sg:address":"240 Stockton Street 6th Floor",
    "sg:city":"San Francisco",
    "sg:classifiers":[
        {
            "category":"Professional",
            "subcategory":"Business Services",
            "type":"Services"
        }
    ],
    "sg:phone":"+1 415 513 1099",
    "sg:postcode":"94108",
    "sg:province":"CA",
    "sg:tags":[
        "integrated-sales-and-marketing-solutions",
        "consumer-acquisition",
        "demand-generation",
        "experiential-marketing",
        "cause-marketing",
        "direct-email",
        "social-media",
        "digital-advertising",
        "non-profit-organizations",
        "fund-raising-events",
        "charities",
        "invitations",
        "newsletter"
    ],
    "sg:website":"http://www.TheAList.org",
    "wof:name":"The A-List Inc.",
    "wof:placetype":"venue"
},
  "geometry": {"coordinates":[-122.40658999999999,37.787568],"type":"Point"}
}