{
  "type": "Feature",
  "properties": {
    "addr:full":"9 Rock Spring Irvine CA 92604",
    "addr:housenumber":"9",
    "addr:postcode":"92604",
    "addr:street":"Rock",
    "iso:country":"US",
    "sg:address":"9 Rock Spring",
    "sg:city":"Irvine",
    "sg:classifiers":[
        {
            "category":"Manufacturing",
            "subcategory":"Tools & Machinery",
            "type":"Manufacturing & Wholesale Goods"
        }
    ],
    "sg:phone":"+1 949 551 1477",
    "sg:postcode":"92604",
    "sg:province":"CA",
    "sg:tags":[
        "machine",
        "repair",
        "vending",
        "mfg"
    ],
    "wof:name":"SSS Vending Services",
    "wof:placetype":"venue"
},
  "geometry": {"coordinates":[-117.788107,33.693805],"type":"Point"}
}