{
  "type": "Feature",
  "properties": {
    "iso:country":"US",
    "sg:address":"65 N Beckwith St",
    "sg:city":"Portola",
    "sg:classifiers":[
        {
            "category":"Real Estate",
            "subcategory":"Surveying",
            "type":"Services"
        }
    ],
    "sg:phone":"+1 530 832 5571",
    "sg:postcode":"96122",
    "sg:province":"CA",
    "sg:tags":[
        "surveyor"
    ],
    "wof:name":"Hamby Surveying Inc",
    "wof:placetype":"venue"
},
  "geometry": {"coordinates":[-120.46701,39.811183],"type":"Point"}
}