{
  "type": "Feature",
  "properties": {
    "iso:country":"US",
    "sg:address":"7900 Vallecitos Rd",
    "sg:city":"Sunol",
    "sg:classifiers":[
        {
            "category":"Recreation",
            "type":"Entertainment"
        }
    ],
    "sg:phone":"+1 510 489 9499",
    "sg:postcode":"94586",
    "sg:province":"CA",
    "sg:tags":[
        "paint",
        "ball",
        "sport"
    ],
    "wof:name":"Sunol Paint Ball Field 2000",
    "wof:placetype":"venue"
},
  "geometry": {"coordinates":[-121.85657399999999,37.597535],"type":"Point"}
}