{
  "type": "Feature",
  "properties": {
    "addr:full":"2350 Mulberry St Riverside CA 92501",
    "addr:housenumber":"2350",
    "addr:postcode":"92501",
    "addr:street":"Mulberry St",
    "iso:country":"US",
    "sg:address":"2350 Mulberry St",
    "sg:city":"Riverside",
    "sg:classifiers":[
        {
            "category":"Wholesale",
            "subcategory":"Hardware",
            "type":"Manufacturing & Wholesale Goods"
        }
    ],
    "sg:phone":"+1 951 682 7474",
    "sg:postcode":"92501",
    "sg:province":"CA",
    "sg:tags":[
        "air",
        "parts",
        "conditioning",
        "supply"
    ],
    "wof:name":"Heating & Cooling Supply Inc",
    "wof:placetype":"venue"
},
  "geometry": {"coordinates":[-117.360737,33.992338],"type":"Point"}
}