{
  "type": "Feature",
  "properties": {
    "iso:country":"US",
    "sg:address":"5100 S Santa Fe Avenue",
    "sg:city":"Los Angeles",
    "sg:classifiers":[
        {
            "category":"Shopping",
            "type":"Retail Goods"
        }
    ],
    "sg:phone":"+1 323 587 1500",
    "sg:postcode":"90058",
    "sg:province":"CA",
    "sg:website":"www.lacarton.com",
    "wof:name":"Los Angeles Carton Company",
    "wof:placetype":"venue"
},
  "geometry": {"coordinates":[-118.230458,33.996166],"type":"Point"}
}