{
  "type": "Feature",
  "properties": {
    "addr:full":"2710 W Edinger Ave Santa Ana CA 92704",
    "addr:housenumber":"2710",
    "addr:postcode":"92704",
    "addr:street":"W Edinger Ave",
    "iso:country":"US",
    "sg:address":"2710 W Edinger Ave",
    "sg:city":"Santa Ana",
    "sg:classifiers":[
        {
            "category":"Shopping",
            "subcategory":"Shoes",
            "type":"Retail Goods"
        }
    ],
    "sg:phone":"+1 714 241 1495",
    "sg:postcode":"92704",
    "sg:province":"CA",
    "sg:tags":[
        "store"
    ],
    "wof:name":"Shoes For Less",
    "wof:placetype":"venue"
},
  "geometry": {"coordinates":[-117.90501500000001,33.727122],"type":"Point"}
}