{
  "type": "Feature",
  "properties": {
    "addr:full":"46 Sunnyside Ave Campbell CA 95008",
    "addr:housenumber":"46",
    "addr:postcode":"95008",
    "addr:street":"Sunnyside Ave",
    "iso:country":"US",
    "sg:address":"46 Sunnyside Ave",
    "sg:city":"Campbell",
    "sg:classifiers":[
        {
            "category":"Building & Trades",
            "subcategory":"Construction",
            "type":"Services"
        }
    ],
    "sg:phone":"+1 408 997 8700",
    "sg:postcode":"95008",
    "sg:province":"CA",
    "sg:tags":[
        "roofing",
        "contractor"
    ],
    "wof:name":"CNL Roofing",
    "wof:placetype":"venue"
},
  "geometry": {"coordinates":[-121.948454,37.282811],"type":"Point"}
}