{
  "type": "Feature",
  "properties": {
    "iso:country":"US",
    "sg:address":"1109 W 190th St",
    "sg:city":"Gardena",
    "sg:classifiers":[
        {
            "category":"Autos & Motor Vehicles",
            "subcategory":"Motorcycle Sales",
            "type":"Retail Goods"
        }
    ],
    "sg:phone":"+1 310 715 6249",
    "sg:postcode":"90248",
    "sg:province":"CA",
    "sg:tags":[
        "scooter"
    ],
    "wof:name":"Motorcycle Werks",
    "wof:placetype":"venue"
},
  "geometry": {"coordinates":[-118.296915,33.858392],"type":"Point"}
}