{
  "type": "Feature",
  "properties": {
    "iso:country":"US",
    "sg:address":"355 Kishimura Dr",
    "sg:city":"Gilroy",
    "sg:classifiers":[
        {
            "category":"Home & Garden",
            "subcategory":"Home Furnishings",
            "type":"Retail Goods"
        }
    ],
    "sg:phone":"+1 408 842 6570",
    "sg:postcode":"95020",
    "sg:province":"CA",
    "sg:tags":[
        "fireplace"
    ],
    "wof:name":"American Business Management",
    "wof:placetype":"venue"
},
  "geometry": {"coordinates":[-121.573735,37.027083],"type":"Point"}
}