{
  "type": "Feature",
  "properties": {
    "addr:full":"8219 La Mesa Blvd La Mesa CA 91942",
    "addr:housenumber":"8219",
    "addr:postcode":"91942",
    "addr:street":"La Mesa Blvd",
    "iso:country":"US",
    "sg:address":"8219 La Mesa Blvd",
    "sg:city":"La Mesa",
    "sg:classifiers":[
        {
            "category":"Shopping",
            "subcategory":"Books",
            "type":"Retail Goods"
        }
    ],
    "sg:phone":"+1 619 461 1400",
    "sg:postcode":"91942",
    "sg:province":"CA",
    "sg:tags":[
        "bookstore"
    ],
    "sg:website":"www.readersinconline.com",
    "wof:name":"Readers, Inc.",
    "wof:placetype":"venue"
},
  "geometry": {"coordinates":[-117.020984,32.764152],"type":"Point"}
}