{
  "type": "Feature",
  "properties": {
    "iso:country":"US",
    "sg:address":"24515 el Sorrento",
    "sg:city":"Laguna Niguel",
    "sg:classifiers":[
        {
            "category":"Wholesale",
            "subcategory":"Machinery & Supplies",
            "type":"Manufacturing & Wholesale Goods"
        }
    ],
    "sg:phone":"+1 949 389 9883",
    "sg:postcode":"92677",
    "sg:province":"CA",
    "sg:tags":[
        "equipment",
        "establishment"
    ],
    "wof:name":"Crown Beauty Supplies",
    "wof:placetype":"venue"
},
  "geometry": {"coordinates":[-117.702887,33.548081],"type":"Point"}
}