{
  "type": "Feature",
  "properties": {
    "addr:full":"1102 Saratoga Ave San Jose CA 95129",
    "addr:housenumber":"1102",
    "addr:postcode":"95129",
    "addr:street":"Saratoga Ave",
    "iso:country":"US",
    "sg:address":"1102 Saratoga Ave",
    "sg:city":"San Jose",
    "sg:classifiers":[
        {
            "category":"Restaurant",
            "type":"Food & Drink"
        }
    ],
    "sg:phone":"+1 408 296 0789",
    "sg:postcode":"95129",
    "sg:province":"CA",
    "sg:tags":[
        "sushi",
        "bar",
        "japanese"
    ],
    "wof:name":"Totoro Sushi Boat",
    "wof:placetype":"venue"
},
  "geometry": {"coordinates":[-121.978996,37.304901],"type":"Point"}
}