{
  "type": "Feature",
  "properties": {
    "addr:full":"1405 S Broadway Los Angeles CA 90015",
    "addr:housenumber":"1405",
    "addr:postcode":"90015",
    "addr:street":"S Broadway",
    "iso:country":"US",
    "sg:address":"1405 S Broadway",
    "sg:city":"Los Angeles",
    "sg:classifiers":[
        {
            "category":"Government",
            "subcategory":"Office",
            "type":"Public Place"
        }
    ],
    "sg:phone":"+1 213 744 2445",
    "sg:postcode":"90015",
    "sg:province":"CA",
    "sg:tags":[
        "employment"
    ],
    "wof:name":"Employment Development CA Dept",
    "wof:placetype":"venue"
},
  "geometry": {"coordinates":[-118.263052,34.034923],"type":"Point"}
}