{
  "type": "Feature",
  "properties": {
    "addr:full":"143 Glasgow Way Vacaville CA 95687",
    "addr:housenumber":"143",
    "addr:postcode":"95687",
    "addr:street":"Glasgow Way",
    "iso:country":"US",
    "sg:address":"143 Glasgow Way",
    "sg:city":"Vacaville",
    "sg:classifiers":[
        {
            "category":"Manufacturing",
            "subcategory":"Tools & Machinery",
            "type":"Manufacturing & Wholesale Goods"
        }
    ],
    "sg:phone":"+1 707 455 1749",
    "sg:postcode":"95687",
    "sg:province":"CA",
    "sg:tags":[
        "computer",
        "electronic",
        "mfg"
    ],
    "wof:name":"P C Family Co",
    "wof:placetype":"venue"
},
  "geometry": {"coordinates":[-121.94967,38.341749],"type":"Point"}
}