{
  "type": "Feature",
  "properties": {
    "addr:full":"441 S California Ave Palo Alto CA 94306",
    "addr:housenumber":"441",
    "addr:postcode":"94306",
    "addr:street":"S California Ave",
    "iso:country":"US",
    "sg:address":"441 S California Ave",
    "sg:city":"Palo Alto",
    "sg:classifiers":[
        {
            "category":"Professional",
            "subcategory":"Management & Consulting",
            "type":"Services"
        }
    ],
    "sg:phone":"+1 650 566 9000",
    "sg:postcode":"94306",
    "sg:province":"CA",
    "sg:tags":[
        "consultant",
        "training"
    ],
    "wof:name":"Compliance Media",
    "wof:placetype":"venue"
},
  "geometry": {"coordinates":[-122.145399,37.425597],"type":"Point"}
}