{
  "type": "Feature",
  "properties": {
    "addr:full":"1019 Via Sorella Diamond Bar CA 91789",
    "addr:housenumber":"1019",
    "addr:postcode":"91789",
    "addr:street":"Via Sorella",
    "iso:country":"US",
    "sg:address":"1019 Via Sorella",
    "sg:city":"Diamond Bar",
    "sg:classifiers":[
        {
            "category":"Education",
            "subcategory":"School",
            "type":"Public Place"
        }
    ],
    "sg:phone":"+1 909 869 6345",
    "sg:postcode":"91789",
    "sg:province":"CA",
    "wof:name":"Apple Learning Ctr Inc",
    "wof:placetype":"venue"
},
  "geometry": {"coordinates":[-117.840789,33.996613],"type":"Point"}
}