{
  "type": "Feature",
  "properties": {
    "addr:full":"42520 Buccaneer Ct Bermuda Dunes CA 92203",
    "addr:postcode":"42520;92203",
    "addr:street":"Buccaneer Ct",
    "iso:country":"US",
    "sg:address":"42520 Buccaneer Ct",
    "sg:city":"Bermuda Dunes",
    "sg:classifiers":[
        {
            "category":"Professional",
            "subcategory":"Lawyer & Legal Services",
            "type":"Services"
        }
    ],
    "sg:phone":"+1 760 341 9200",
    "sg:postcode":"92203",
    "sg:province":"CA",
    "sg:tags":[
        "attorney"
    ],
    "wof:name":"B Palmer Riedel Law Office",
    "wof:placetype":"venue"
},
  "geometry": {"coordinates":[-116.273393,33.73943],"type":"Point"}
}