{
  "type": "Feature",
  "properties": {
    "addr:full":"20969 Ventura Blvd Woodland Hills CA 91364",
    "addr:housenumber":"20969",
    "addr:postcode":"91364",
    "addr:street":"Ventura Blvd",
    "iso:country":"US",
    "sg:address":"20969 Ventura Blvd",
    "sg:city":"Woodland Hills",
    "sg:classifiers":[
        {
            "category":"Health Services",
            "subcategory":"Chiropractor",
            "type":"Services"
        }
    ],
    "sg:phone":"+1 818 999 0202",
    "sg:postcode":"91364",
    "sg:province":"CA",
    "wof:name":"Eliaspour Shadi DC",
    "wof:placetype":"venue"
},
  "geometry": {"coordinates":[-118.59001000000001,34.166714],"type":"Point"}
}