{
  "type": "Feature",
  "properties": {
    "addr:full":"1749 Bancroft Ave San Leandro CA 94577",
    "addr:housenumber":"1749",
    "addr:postcode":"94577",
    "addr:street":"Bancroft Ave",
    "iso:country":"US",
    "sg:address":"1749 Bancroft Ave",
    "sg:city":"San Leandro",
    "sg:classifiers":[
        {
            "category":"Building & Trades",
            "subcategory":"Construction",
            "type":"Services"
        }
    ],
    "sg:phone":"+1 510 483 7818",
    "sg:postcode":"94577",
    "sg:province":"CA",
    "sg:tags":[
        "residential"
    ],
    "wof:name":"Harrington & Grace",
    "wof:placetype":"venue"
},
  "geometry": {"coordinates":[-122.146176,37.723069],"type":"Point"}
}