{
  "type": "Feature",
  "properties": {
    "iso:country":"US",
    "sg:address":"4464 Convoy St",
    "sg:city":"San Diego",
    "sg:classifiers":[
        {
            "category":"Retail",
            "subcategory":"Auto Repair",
            "type":"Services"
        }
    ],
    "sg:phone":"+1 858 565 0524",
    "sg:postcode":"92111",
    "sg:province":"CA",
    "sg:tags":[
        "automotive"
    ],
    "wof:name":"Express Tire",
    "wof:placetype":"venue"
},
  "geometry": {"coordinates":[-117.155146,32.820579],"type":"Point"}
}