{
  "type": "Feature",
  "properties": {
    "iso:country":"US",
    "sg:address":"11471 Culver Park Dr",
    "sg:city":"Culver City",
    "sg:classifiers":[
        {
            "category":"Building & Trades",
            "subcategory":"Landscaping Services",
            "type":"Services"
        }
    ],
    "sg:phone":"+1 310 391 6105",
    "sg:postcode":"90230",
    "sg:province":"CA",
    "wof:name":"Mike",
    "wof:placetype":"venue"
},
  "geometry": {"coordinates":[-118.398336,33.990906],"type":"Point"}
}