{
  "type": "Feature",
  "properties": {
    "addr:full":"1219 Sunbright Drive Oceanside CA 92056",
    "addr:housenumber":"1219",
    "addr:postcode":"92056",
    "addr:street":"Sunbright Drive",
    "iso:country":"US",
    "sg:address":"1219 Sunbright Drive",
    "sg:city":"Oceanside",
    "sg:classifiers":[
        {
            "category":"Travel",
            "subcategory":"Hotels & Motels",
            "type":"Entertainment"
        },
        {
            "category":"Travel",
            "subcategory":"Travel Agent",
            "type":"Entertainment"
        }
    ],
    "sg:phone":"+1 760 559 0732",
    "sg:postcode":"92056",
    "sg:province":"CA",
    "sg:tags":[
        "house",
        "guest"
    ],
    "sg:website":"www.thebajaexperience.com",
    "wof:name":"The Baja Experience",
    "wof:placetype":"venue"
},
  "geometry": {"coordinates":[-117.264359,33.230092],"type":"Point"}
}