{
  "type": "Feature",
  "properties": {
    "addr:full":"3282 Main St Lemon Grove CA 91945",
    "addr:housenumber":"3282",
    "addr:postcode":"91945",
    "addr:street":"Main St",
    "iso:country":"US",
    "sg:address":"3282 Main St",
    "sg:city":"Lemon Grove",
    "sg:classifiers":[
        {
            "category":"Home & Garden",
            "subcategory":"Household Appliances",
            "type":"Retail Goods"
        }
    ],
    "sg:phone":"+1 619 469 2144",
    "sg:postcode":"91945",
    "sg:province":"CA",
    "sg:tags":[
        "repair"
    ],
    "wof:name":"Maytag Browne's Factory Authorized",
    "wof:placetype":"venue"
},
  "geometry": {"coordinates":[-117.030998,32.7416],"type":"Point"}
}