{
  "type": "Feature",
  "properties": {
    "addr:full":"603 F St Eureka CA 95501",
    "addr:housenumber":"603",
    "addr:postcode":"95501",
    "addr:street":"F St",
    "iso:country":"US",
    "sg:address":"603 F St",
    "sg:city":"Eureka",
    "sg:classifiers":[
        {
            "category":"Communications",
            "subcategory":"Radio Station",
            "type":"Services"
        }
    ],
    "sg:phone":"+1 707 445 8104",
    "sg:postcode":"95501",
    "sg:province":"CA",
    "sg:tags":[
        "company",
        "broadcasting"
    ],
    "sg:website":"www.theclassicrockexperience.com",
    "wof:name":"KXGO",
    "wof:placetype":"venue"
},
  "geometry": {"coordinates":[-124.165672,40.801063],"type":"Point"}
}