{
  "type": "Feature",
  "properties": {
    "addr:full":"901 Edgewater Blvd Foster City CA 94404",
    "addr:housenumber":"901",
    "addr:postcode":"94404",
    "addr:street":"Edgewater Blvd",
    "iso:country":"US",
    "sg:address":"901 Edgewater Blvd",
    "sg:city":"Foster City",
    "sg:classifiers":[
        {
            "category":"Retail",
            "subcategory":"Laundry & Dry Cleaning",
            "type":"Services"
        }
    ],
    "sg:phone":"+1 650 345 3994",
    "sg:postcode":"94404",
    "sg:province":"CA",
    "sg:tags":[
        "cleaner"
    ],
    "wof:name":"Edgewater Cleaners",
    "wof:placetype":"venue"
},
  "geometry": {"coordinates":[-122.272003,37.5457],"type":"Point"}
}