{
  "type": "Feature",
  "properties": {
    "addr:full":"44 Race St San Jose CA 95126",
    "addr:housenumber":"44",
    "addr:postcode":"95126",
    "addr:street":"Race St",
    "iso:country":"US",
    "sg:address":"44 Race St",
    "sg:city":"San Jose",
    "sg:classifiers":[
        {
            "category":"Building & Trades",
            "subcategory":"Construction",
            "type":"Services"
        }
    ],
    "sg:phone":"+1 408 279 8432",
    "sg:postcode":"95126",
    "sg:province":"CA",
    "sg:tags":[
        "maker",
        "cabinet"
    ],
    "wof:name":"Becher's Custom Fixtures",
    "wof:placetype":"venue"
},
  "geometry": {"coordinates":[-121.911844,37.329699],"type":"Point"}
}