{
  "type": "Feature",
  "properties": {
    "addr:full":"5990 14th Avenue Sacramento CA 95820",
    "addr:housenumber":"5990",
    "addr:postcode":"95820",
    "addr:street":"14Th Avenue",
    "iso:country":"US",
    "sg:address":"5990 14th Avenue",
    "sg:city":"Sacramento",
    "sg:classifiers":[
        {
            "category":"Personal",
            "subcategory":"Nail Salon",
            "type":"Services"
        }
    ],
    "sg:phone":"+1 916 451 4109",
    "sg:postcode":"95820",
    "sg:province":"CA",
    "wof:name":"The Nail Stop",
    "wof:placetype":"venue"
},
  "geometry": {"coordinates":[-121.44284,38.535356],"type":"Point"}
}