{
  "type": "Feature",
  "properties": {
    "addr:full":"3075 23rd St San Francisco CA 94110",
    "addr:housenumber":"3075",
    "addr:postcode":"94110",
    "addr:street":"23Rd St",
    "iso:country":"US",
    "sg:address":"3075 23rd St",
    "sg:city":"San Francisco",
    "sg:classifiers":[
        {
            "category":"Professional",
            "subcategory":"Computer Services",
            "type":"Services"
        }
    ],
    "sg:phone":"+1 415 642 2869",
    "sg:postcode":"94110",
    "sg:province":"CA",
    "sg:tags":[
        "website",
        "design"
    ],
    "wof:name":"Imageteq Technologies Inc",
    "wof:placetype":"venue"
},
  "geometry": {"coordinates":[-122.413796,37.754057],"type":"Point"}
}