{
  "type": "Feature",
  "properties": {
    "iso:country":"US",
    "sg:address":"1352 Apsley Rd",
    "sg:city":"Santa Ana",
    "sg:classifiers":[
        {
            "category":"Banks & Credit Unions",
            "subcategory":"Investment Brokerage",
            "type":"Services"
        }
    ],
    "sg:phone":"+1 714 832 7936",
    "sg:postcode":"92705",
    "sg:province":"CA",
    "sg:tags":[
        "security"
    ],
    "wof:name":"Heiskell Bblgraphic Foundation",
    "wof:placetype":"venue"
},
  "geometry": {"coordinates":[-117.781588,33.769808],"type":"Point"}
}