{
  "type": "Feature",
  "properties": {
    "iso:country":"US",
    "sg:address":"2421 W 205th St",
    "sg:city":"Torrance",
    "sg:classifiers":[
        {
            "category":"Retail",
            "subcategory":"Laundry & Dry Cleaning",
            "type":"Services"
        }
    ],
    "sg:phone":"+1 310 328 3870",
    "sg:postcode":"90501",
    "sg:province":"CA",
    "wof:name":"Marufo USA Inc",
    "wof:placetype":"venue"
},
  "geometry": {"coordinates":[-118.325996,33.845299],"type":"Point"}
}