{
  "type": "Feature",
  "properties": {
    "iso:country":"US",
    "sg:address":"9710 Klingerman St",
    "sg:city":"El Monte",
    "sg:classifiers":[
        {
            "category":"Manufacturing",
            "subcategory":"Aerospace",
            "type":"Manufacturing & Wholesale Goods"
        }
    ],
    "sg:phone":"+1 626 448 3897",
    "sg:postcode":"91733",
    "sg:province":"CA",
    "sg:tags":[
        "aircraft",
        "component"
    ],
    "wof:name":"Roc-Aire Corp",
    "wof:placetype":"venue"
},
  "geometry": {"coordinates":[-118.05748199999999,34.055461],"type":"Point"}
}