{
  "type": "Feature",
  "properties": {
    "addr:full":"2986 1st St La Verne CA 91750",
    "addr:housenumber":"2986",
    "addr:postcode":"91750",
    "addr:street":"1St St",
    "iso:country":"US",
    "sg:address":"2986 1st St",
    "sg:city":"La Verne",
    "sg:classifiers":[
        {
            "category":"Professional",
            "subcategory":"Art Services",
            "type":"Services"
        },
        {
            "category":"Manufacturing",
            "subcategory":"Printing",
            "type":"Manufacturing & Wholesale Goods"
        }
    ],
    "sg:phone":"+1 909 596 6624",
    "sg:postcode":"91750",
    "sg:province":"CA",
    "sg:tags":[
        "commercial",
        "printer",
        "design"
    ],
    "wof:name":"J C Printing & Graphics",
    "wof:placetype":"venue"
},
  "geometry": {"coordinates":[-117.76318499999999,34.096988],"type":"Point"}
}