{
  "type": "Feature",
  "properties": {
    "iso:country":"US",
    "sg:address":"724 N Lemoore Ave",
    "sg:city":"Lemoore",
    "sg:classifiers":[
        {
            "category":"Retail",
            "subcategory":"Auto Repair",
            "type":"Services"
        }
    ],
    "sg:phone":"+1 559 924 3889",
    "sg:postcode":"93245",
    "sg:province":"CA",
    "sg:tags":[
        "muffler",
        "exhaust",
        "system"
    ],
    "wof:name":"AAA Radiators & Mufflers",
    "wof:placetype":"venue"
},
  "geometry": {"coordinates":[-119.780796,36.306209],"type":"Point"}
}