{
  "type": "Feature",
  "properties": {
    "addr:full":"4221 Oslo Ct Antelope CA 95843",
    "addr:postcode":"4221;95843",
    "addr:street":"Ct",
    "iso:country":"US",
    "sg:address":"4221 Oslo Ct",
    "sg:city":"Antelope",
    "sg:classifiers":[
        {
            "category":"Manufacturing",
            "subcategory":"Metals",
            "type":"Manufacturing & Wholesale Goods"
        },
        {
            "category":"Shopping",
            "subcategory":"Hobbies, Toys, & Games",
            "type":"Retail Goods"
        }
    ],
    "sg:phone":"+1 916 363 1777",
    "sg:postcode":"95843",
    "sg:province":"CA",
    "sg:tags":[
        "product",
        "craft",
        "fabricated",
        "mfg"
    ],
    "wof:name":"La Grand Armoire",
    "wof:placetype":"venue"
},
  "geometry": {"coordinates":[-121.366367,38.724418],"type":"Point"}
}