{
  "type": "Feature",
  "properties": {
    "iso:country":"US",
    "sg:address":"5247 Melrose Avenue",
    "sg:city":"Los Angeles",
    "sg:classifiers":[
        {
            "category":"Shopping",
            "subcategory":"Clothing, Apparel, & Fashions",
            "type":"Retail Goods"
        }
    ],
    "sg:phone":"+1 323 464 7000",
    "sg:postcode":"90038",
    "sg:province":"CA",
    "sg:tags":[
        "men's",
        "clothing"
    ],
    "wof:name":"Marc Callo",
    "wof:placetype":"venue"
},
  "geometry": {"coordinates":[-118.314802,34.083396],"type":"Point"}
}