{
  "type": "Feature",
  "properties": {
    "addr:full":"10812 Jefferson Blvd Culver City CA 90230",
    "addr:housenumber":"10812",
    "addr:postcode":"90230",
    "addr:street":"Jefferson Blvd",
    "iso:country":"US",
    "sg:address":"10812 Jefferson Blvd",
    "sg:city":"Culver City",
    "sg:classifiers":[
        {
            "category":"Restaurant",
            "type":"Food & Drink"
        }
    ],
    "sg:phone":"+1 310 558 3202",
    "sg:postcode":"90230",
    "sg:province":"CA",
    "wof:name":"Burger King",
    "wof:placetype":"venue"
},
  "geometry": {"coordinates":[-118.394997,34.0019],"type":"Point"}
}