{
  "type": "Feature",
  "properties": {
    "iso:country":"US",
    "sg:address":"10356 Truckee Airport Rd",
    "sg:city":"Truckee",
    "sg:classifiers":[
        {
            "category":"Professional",
            "type":"Services"
        }
    ],
    "sg:phone":"+1 530 582 1339",
    "sg:postcode":"96161",
    "sg:province":"CA",
    "wof:name":"Biophoretics Inc",
    "wof:placetype":"venue"
},
  "geometry": {"coordinates":[-120.13603000000001,39.35223],"type":"Point"}
}