{
  "type": "Feature",
  "properties": {
    "addr:full":"8885 Venice Blvd Los Angeles CA 90034",
    "addr:housenumber":"8885",
    "addr:postcode":"90034",
    "addr:street":"Venice Blvd",
    "iso:country":"US",
    "sg:address":"8885 Venice Blvd",
    "sg:city":"Los Angeles",
    "sg:classifiers":[
        {
            "category":"Travel",
            "subcategory":"Travel Agent",
            "type":"Entertainment"
        }
    ],
    "sg:phone":"+1 310 202 4220",
    "sg:postcode":"90034",
    "sg:province":"CA",
    "sg:tags":[
        "passenger",
        "agency",
        "transportation",
        "arrangement"
    ],
    "wof:name":"Fiji Holliday",
    "wof:placetype":"venue"
},
  "geometry": {"coordinates":[-118.388246,34.02964],"type":"Point"}
}