{
  "type": "Feature",
  "properties": {
    "iso:country":"US",
    "sg:address":"2151 E Monte Vista Ave",
    "sg:city":"Vacaville",
    "sg:classifiers":[
        {
            "category":"Wholesale",
            "subcategory":"Home Furnishings",
            "type":"Manufacturing & Wholesale Goods"
        }
    ],
    "sg:phone":"+1 707 452 1052",
    "sg:postcode":"95688",
    "sg:province":"CA",
    "sg:tags":[
        "plumbing",
        "supplies-wholesale",
        "part",
        "fixture",
        "manufacturer"
    ],
    "sg:website":"http://www.aircold.com",
    "wof:name":"Ferguson Enterprises, Inc.",
    "wof:placetype":"venue"
},
  "geometry": {"coordinates":[-121.952151,38.386289],"type":"Point"}
}