{
  "type": "Feature",
  "properties": {
    "iso:country":"US",
    "sg:address":"3401 Dale Rd",
    "sg:city":"Modesto",
    "sg:classifiers":[
        {
            "category":"Restaurant",
            "type":"Food & Drink"
        }
    ],
    "sg:menulink":"http://www.allmenus.com/ca/modesto/104981-carinos-italian-grill/menu/",
    "sg:phone":"+1 209 578 9432",
    "sg:postcode":"95356",
    "sg:province":"CA",
    "sg:tags":[
        "american",
        "italian"
    ],
    "wof:name":"Carino's Italian Grill",
    "wof:placetype":"venue"
},
  "geometry": {"coordinates":[-121.05022,37.68864],"type":"Point"}
}