{
  "type": "Feature",
  "properties": {
    "addr:full":"3333 Wilshire Blvd Los Angeles CA 90010",
    "addr:housenumber":"3333",
    "addr:postcode":"90010",
    "addr:street":"Wilshire Blvd",
    "iso:country":"US",
    "sg:address":"3333 Wilshire Blvd",
    "sg:city":"Los Angeles",
    "sg:classifiers":[
        {
            "category":"Health Services",
            "subcategory":"Health Practitioner",
            "type":"Services"
        },
        {
            "category":"Professional",
            "subcategory":"Employment Agencies",
            "type":"Services"
        }
    ],
    "sg:phone":"+1 213 736 6771",
    "sg:postcode":"90010",
    "sg:province":"CA",
    "sg:tags":[
        "nurse",
        "registry"
    ],
    "wof:name":"Secure Nursing Service Inc",
    "wof:placetype":"venue"
},
  "geometry": {"coordinates":[-118.294465,34.061853],"type":"Point"}
}