{
  "type": "Feature",
  "properties": {
    "addr:full":"1747 Grand Pheasant Ln Lincoln CA 95648",
    "addr:housenumber":"1747",
    "addr:postcode":"95648",
    "addr:street":"Grand Pheasant Ln",
    "iso:country":"US",
    "sg:address":"1747 Grand Pheasant Ln",
    "sg:city":"Lincoln",
    "sg:classifiers":[
        {
            "category":"Real Estate",
            "subcategory":"Real Estate Services",
            "type":"Services"
        },
        {
            "category":"Banks & Credit Unions",
            "subcategory":"Financial Services",
            "type":"Services"
        }
    ],
    "sg:phone":"+1 916 408 5700",
    "sg:postcode":"95648",
    "sg:province":"CA",
    "sg:tags":[
        "loan",
        "processing"
    ],
    "wof:name":"Pacific Home Mortgage",
    "wof:placetype":"venue"
},
  "geometry": {"coordinates":[-121.25294700000001,38.857643],"type":"Point"}
}