{
  "type": "Feature",
  "properties": {
    "addr:full":"5436 Holt Blvd Montclair CA 91763",
    "addr:housenumber":"5436",
    "addr:postcode":"91763",
    "addr:street":"Holt Blvd",
    "iso:country":"US",
    "sg:address":"5436 Holt Blvd",
    "sg:city":"Montclair",
    "sg:classifiers":[
        {
            "category":"Shopping",
            "subcategory":"Computers & Home Electronics",
            "type":"Retail Goods"
        }
    ],
    "sg:phone":"+1 909 629 9129",
    "sg:postcode":"91763",
    "sg:province":"CA",
    "sg:tags":[
        "high",
        "fidelity",
        "stereophonic"
    ],
    "wof:name":"CBA Stereo",
    "wof:placetype":"venue"
},
  "geometry": {"coordinates":[-117.68605100000001,34.063335],"type":"Point"}
}