{
  "type": "Feature",
  "properties": {
    "iso:country":"US",
    "sg:address":"790 Beaumont Ave",
    "sg:city":"Beaumont",
    "sg:classifiers":[
        {
            "category":"Professional",
            "subcategory":"Lawyer & Legal Services",
            "type":"Services"
        }
    ],
    "sg:phone":"+1 951 769 3543",
    "sg:postcode":"92223",
    "sg:province":"CA",
    "wof:name":"Reilly Melissa",
    "wof:placetype":"venue"
},
  "geometry": {"coordinates":[-116.97699799999999,33.932342],"type":"Point"}
}