{
  "type": "Feature",
  "properties": {
    "iso:country":"US",
    "sg:address":"5485 E Atchison St",
    "sg:city":"Fresno",
    "sg:classifiers":[
        {
            "category":"Building & Trades",
            "subcategory":"Construction",
            "type":"Services"
        }
    ],
    "sg:phone":"+1 559 908 1991",
    "sg:postcode":"93727",
    "sg:province":"CA",
    "sg:tags":[
        "maker",
        "cabinet"
    ],
    "wof:name":"Artistic Furniture & Cabinets",
    "wof:placetype":"venue"
},
  "geometry": {"coordinates":[-119.708653,36.721389],"type":"Point"}
}