{
  "type": "Feature",
  "properties": {
    "addr:full":"1101 N Pacific Ave Ste 105 Glendale CA 91202",
    "addr:housenumber":"1101",
    "addr:postcode":"91202",
    "addr:street":"N Pacific Ave Ste 105",
    "iso:country":"US",
    "sg:address":"1101 N Pacific Ave Ste 105",
    "sg:city":"Glendale",
    "sg:classifiers":[
        {
            "category":"Health Services",
            "subcategory":"Optometrist",
            "type":"Services"
        }
    ],
    "sg:phone":"+1 818 243 1111",
    "sg:postcode":"91202",
    "sg:province":"CA",
    "wof:name":"Bagdassar Shakeh J OD",
    "wof:placetype":"venue"
},
  "geometry": {"coordinates":[-118.264999,34.163898],"type":"Point"}
}