{
  "type": "Feature",
  "properties": {
    "addr:full":"1001 S Hill St Los Angeles CA 90015",
    "addr:housenumber":"1001",
    "addr:postcode":"90015",
    "addr:street":"S Hill St",
    "iso:country":"US",
    "sg:address":"1001 S Hill St",
    "sg:city":"Los Angeles",
    "sg:classifiers":[
        {
            "category":"Professional",
            "subcategory":"Printing & Photocopies",
            "type":"Services"
        }
    ],
    "sg:phone":"+1 213 746 0222",
    "sg:postcode":"90015",
    "sg:province":"CA",
    "wof:name":"Ace Copy Center",
    "wof:placetype":"venue"
},
  "geometry": {"coordinates":[-118.25900300000001,34.041698],"type":"Point"}
}