{
  "type": "Feature",
  "properties": {
    "iso:country":"US",
    "sg:address":"322 W Honolulu St",
    "sg:city":"Lindsay",
    "sg:classifiers":[
        {
            "category":"Professional",
            "type":"Services"
        },
        {
            "category":"Restaurant",
            "type":"Food & Drink"
        },
        {
            "category":"Fast Food",
            "type":"Food & Drink"
        }
    ],
    "sg:phone":"+1 559 562 9838",
    "sg:postcode":"93247",
    "sg:province":"CA",
    "sg:tags":[
        "style",
        "take",
        "family",
        "caterer"
    ],
    "sg:website":"http://www.elmolcajeterestaurant2.com",
    "wof:name":"El Molcajete Restaurant 2",
    "wof:placetype":"venue"
},
  "geometry": {"coordinates":[-119.092951,36.201572],"type":"Point"}
}