{
  "type": "Feature",
  "properties": {
    "iso:country":"US",
    "sg:address":"2340 Sunrise Blvd",
    "sg:city":"Rancho Cordova",
    "sg:classifiers":[
        {
            "category":"Manufacturing",
            "subcategory":"Furniture",
            "type":"Manufacturing & Wholesale Goods"
        }
    ],
    "sg:phone":"+1 916 635 7070",
    "sg:postcode":"95670",
    "sg:province":"CA",
    "sg:tags":[
        "mfg",
        "cabinet"
    ],
    "wof:name":"Ronald J Bonanno",
    "wof:placetype":"venue"
},
  "geometry": {"coordinates":[-121.268512,38.617214],"type":"Point"}
}