{
  "type": "Feature",
  "properties": {
    "addr:full":"1909 Fillmore Street San Francisco CA 94115",
    "addr:housenumber":"1909",
    "addr:postcode":"94115",
    "addr:street":"Fillmore Street",
    "iso:country":"US",
    "sg:address":"1909 Fillmore Street",
    "sg:city":"San Francisco",
    "sg:classifiers":[
        {
            "category":"Retail",
            "subcategory":"Laundry & Dry Cleaning",
            "type":"Services"
        }
    ],
    "sg:phone":"+1 415 775 1638",
    "sg:postcode":"94115",
    "sg:province":"CA",
    "wof:name":"Perfect Cleaners",
    "wof:placetype":"venue"
},
  "geometry": {"coordinates":[-122.433998,37.7873],"type":"Point"}
}