{
  "type": "Feature",
  "properties": {
    "addr:full":"309 N Garden St Visalia CA 93291",
    "addr:housenumber":"309",
    "addr:postcode":"93291",
    "addr:street":"N Garden St",
    "iso:country":"US",
    "sg:address":"309 N Garden St",
    "sg:city":"Visalia",
    "sg:classifiers":[
        {
            "category":"Insurance",
            "subcategory":"Insurance Agent",
            "type":"Services"
        }
    ],
    "sg:phone":"+1 559 733 0221",
    "sg:postcode":"93291",
    "sg:province":"CA",
    "wof:name":"D G Insurance",
    "wof:placetype":"venue"
},
  "geometry": {"coordinates":[-119.290176,36.332355],"type":"Point"}
}