{
  "type": "Feature",
  "properties": {
    "addr:full":"2276 Arden Way Sacramento CA 95825",
    "addr:housenumber":"2276",
    "addr:postcode":"95825",
    "addr:street":"Arden Way",
    "iso:country":"US",
    "sg:address":"2276 Arden Way",
    "sg:city":"Sacramento",
    "sg:classifiers":[
        {
            "category":"Restaurant",
            "type":"Food & Drink"
        }
    ],
    "sg:phone":"+1 916 929 8889",
    "sg:postcode":"95825",
    "sg:province":"CA",
    "sg:tags":[
        "chinese"
    ],
    "wof:name":"Chinese Express Restaurants",
    "wof:placetype":"venue"
},
  "geometry": {"coordinates":[-121.41147100000001,38.595929],"type":"Point"}
}