{
  "type": "Feature",
  "properties": {
    "iso:country":"US",
    "sg:address":"24024 Humphries Rd",
    "sg:city":"Tecate",
    "sg:classifiers":[
        {
            "category":"Professional",
            "type":"Services"
        }
    ],
    "sg:phone":"+1 619 478 2300",
    "sg:postcode":"91980",
    "sg:province":"CA",
    "wof:name":"Sierra Products",
    "wof:placetype":"venue"
},
  "geometry": {"coordinates":[-116.633088,32.582486],"type":"Point"}
}