{
  "type": "Feature",
  "properties": {
    "addr:full":"21777 Ventura Blvd Woodland Hills CA 91364",
    "addr:housenumber":"21777",
    "addr:postcode":"91364",
    "addr:street":"Ventura Blvd",
    "iso:country":"US",
    "sg:address":"21777 Ventura Blvd",
    "sg:city":"Woodland Hills",
    "sg:classifiers":[
        {
            "category":"Manufacturing",
            "subcategory":"Printing",
            "type":"Manufacturing & Wholesale Goods"
        }
    ],
    "sg:phone":"+1 818 226 9991",
    "sg:postcode":"91364",
    "sg:province":"CA",
    "sg:tags":[
        "publisher",
        "music"
    ],
    "wof:name":"Jowcol Music",
    "wof:placetype":"venue"
},
  "geometry": {"coordinates":[-118.601192,34.168388],"type":"Point"}
}