{
  "type": "Feature",
  "properties": {
    "iso:country":"US",
    "sg:address":"2489 Mission St",
    "sg:city":"San Francisco",
    "sg:classifiers":[
        {
            "category":"Organizations",
            "subcategory":"Non-profit Organization",
            "type":"Services"
        }
    ],
    "sg:phone":"+1 415 821 6545",
    "sg:postcode":"94110",
    "sg:province":"CA",
    "wof:name":"All Peoples' Congress",
    "wof:placetype":"venue"
},
  "geometry": {"coordinates":[-122.418933,37.758475],"type":"Point"}
}