{
  "type": "Feature",
  "properties": {
    "addr:full":"5230 Pacific Concourse Dr Los Angeles CA 90045",
    "addr:housenumber":"5230",
    "addr:postcode":"90045",
    "addr:street":"Pacific Concourse Dr",
    "iso:country":"US",
    "sg:address":"5230 Pacific Concourse Dr",
    "sg:city":"Los Angeles",
    "sg:classifiers":[
        {
            "category":"Shopping",
            "subcategory":"Computers & Home Electronics",
            "type":"Retail Goods"
        }
    ],
    "sg:phone":"+1 310 643 4467",
    "sg:postcode":"90045",
    "sg:province":"CA",
    "sg:tags":[
        "software"
    ],
    "wof:name":"Hospital Service Assn",
    "wof:placetype":"venue"
},
  "geometry": {"coordinates":[-118.3706,33.926383],"type":"Point"}
}