{
  "type": "Feature",
  "properties": {
    "iso:country":"US",
    "sg:address":"7602 Murray Dr",
    "sg:city":"Stockton",
    "sg:classifiers":[
        {
            "category":"Retail",
            "subcategory":"Auto Repair",
            "type":"Services"
        }
    ],
    "sg:phone":"+1 209 477 6771",
    "sg:postcode":"95210",
    "sg:province":"CA",
    "sg:tags":[
        "glass",
        "coating",
        "tinting"
    ],
    "wof:name":"All Pro Window Tinting",
    "wof:placetype":"venue"
},
  "geometry": {"coordinates":[-121.301763,38.016805],"type":"Point"}
}