{
  "type": "Feature",
  "properties": {
    "addr:full":"Grand Central Market, Space A-5 317 S Broadway Los Angeles CA 90013",
    "addr:housenumber":"317",
    "addr:postcode":"90013",
    "addr:street":"Grand;A-5;S Broadway",
    "iso:country":"US",
    "sg:address":"Grand Central Market, Space A-5 317 S Broadway",
    "sg:city":"Los Angeles",
    "sg:classifiers":[
        {
            "category":"Restaurant",
            "type":"Food & Drink"
        }
    ],
    "sg:phone":"+1 213 620 1071",
    "sg:postcode":"90013",
    "sg:province":"CA",
    "sg:tags":[
        "mexican"
    ],
    "sg:website":"www.grandcentralsquare.com",
    "wof:name":"Tacos Tumbras a Tomas",
    "wof:placetype":"venue"
},
  "geometry": {"coordinates":[-118.248234,34.050702],"type":"Point"}
}