{
  "type": "Feature",
  "properties": {
    "addr:full":"7490 State Hwy 20 Smartville CA 95977",
    "addr:housenumber":"7490",
    "addr:postcode":"95977",
    "addr:street":"State Hwy 20",
    "iso:country":"US",
    "sg:address":"7490 State Hwy 20",
    "sg:city":"Smartville",
    "sg:classifiers":[
        {
            "category":"Farming",
            "subcategory":"Fish & Marine Products",
            "type":"Manufacturing & Wholesale Goods"
        }
    ],
    "sg:phone":"+1 530 639 2200",
    "sg:postcode":"95977",
    "sg:province":"CA",
    "sg:tags":[
        "preserves",
        "fishing",
        "hunting"
    ],
    "wof:name":"Timbuctoo Sporting Estate Inc",
    "wof:placetype":"venue"
},
  "geometry": {"coordinates":[-121.33439199999999,39.219354],"type":"Point"}
}