{
  "type": "Feature",
  "properties": {
    "iso:country":"US",
    "sg:address":"1489 N Fairvalley Ave",
    "sg:city":"Covina",
    "sg:classifiers":[
        {
            "category":"Shopping",
            "subcategory":"Catalog Store",
            "type":"Retail Goods"
        }
    ],
    "sg:phone":"+1 626 915 1187",
    "sg:postcode":"91722",
    "sg:province":"CA",
    "sg:tags":[
        "mail",
        "house"
    ],
    "wof:name":"Baldwin Naty",
    "wof:placetype":"venue"
},
  "geometry": {"coordinates":[-117.885503,34.104697],"type":"Point"}
}