{
  "type": "Feature",
  "properties": {
    "iso:country":"US",
    "sg:address":"2244 Lomita Blvd",
    "sg:city":"Lomita",
    "sg:classifiers":[
        {
            "category":"Wholesale",
            "subcategory":"Furniture",
            "type":"Manufacturing & Wholesale Goods"
        }
    ],
    "sg:phone":"+1 310 534 7101",
    "sg:postcode":"90717",
    "sg:province":"CA",
    "sg:tags":[
        "store"
    ],
    "wof:name":"Ezell Co",
    "wof:placetype":"venue"
},
  "geometry": {"coordinates":[-118.320999,33.803101],"type":"Point"}
}