{
  "type": "Feature",
  "properties": {
    "addr:full":"9353 Oviedo St San Diego CA 92129",
    "addr:housenumber":"9353",
    "addr:postcode":"92129",
    "addr:street":"Oviedo St",
    "iso:country":"US",
    "sg:address":"9353 Oviedo St",
    "sg:city":"San Diego",
    "sg:classifiers":[
        {
            "category":"Education",
            "subcategory":"School",
            "type":"Public Place"
        }
    ],
    "sg:phone":"+1 858 484 1300",
    "sg:postcode":"92129",
    "sg:province":"CA",
    "sg:website":"www.powayusd.com",
    "wof:name":"Black Mountain Middle School",
    "wof:placetype":"venue"
},
  "geometry": {"coordinates":[-117.128074,32.96862],"type":"Point"}
}