{
  "type": "Feature",
  "properties": {
    "iso:country":"US",
    "sg:address":"1650 Las Trampas Rd",
    "sg:city":"Alamo",
    "sg:classifiers":[
        {
            "category":"Banks & Credit Unions",
            "subcategory":"Investment Brokerage",
            "type":"Services"
        }
    ],
    "sg:phone":"+1 925 862 2353",
    "sg:postcode":"94507",
    "sg:province":"CA",
    "sg:tags":[
        "advisory",
        "financial"
    ],
    "wof:name":"DBT",
    "wof:placetype":"venue"
},
  "geometry": {"coordinates":[-122.036483,37.844823],"type":"Point"}
}