{
  "type": "Feature",
  "properties": {
    "addr:full":"1250 Coast Village Rd Montecito CA 93108",
    "addr:housenumber":"1250",
    "addr:postcode":"93108",
    "addr:street":"Coast Village Rd",
    "iso:country":"US",
    "sg:address":"1250 Coast Village Rd",
    "sg:city":"Montecito",
    "sg:classifiers":[
        {
            "category":"Real Estate",
            "subcategory":"Real Estate Agent",
            "type":"Services"
        }
    ],
    "sg:phone":"+1 805 969 8900",
    "sg:postcode":"93108",
    "sg:province":"CA",
    "sg:website":"www.villagesite.com",
    "wof:name":"Village Properties",
    "wof:placetype":"venue"
},
  "geometry": {"coordinates":[-119.64384,34.421079],"type":"Point"}
}