{
  "type": "Feature",
  "properties": {
    "iso:country":"US",
    "sg:address":"13611 Sherman Way",
    "sg:city":"Van Nuys",
    "sg:classifiers":[
        {
            "category":"Restaurant",
            "type":"Food & Drink"
        }
    ],
    "sg:phone":"+1 818 785 4138",
    "sg:postcode":"91405",
    "sg:province":"CA",
    "wof:name":"El Indio",
    "wof:placetype":"venue"
},
  "geometry": {"coordinates":[-118.43000000000001,34.201099],"type":"Point"}
}