{
  "type": "Feature",
  "properties": {
    "addr:full":"1200 Whalen Way Lakeport CA 95453",
    "addr:housenumber":"1200",
    "addr:postcode":"95453",
    "addr:street":"Whalen Way",
    "iso:country":"US",
    "sg:address":"1200 Whalen Way",
    "sg:city":"Lakeport",
    "sg:classifiers":[
        {
            "category":"Wholesale",
            "subcategory":"Electrical",
            "type":"Manufacturing & Wholesale Goods"
        }
    ],
    "sg:phone":"+1 707 263 1994",
    "sg:postcode":"95453",
    "sg:province":"CA",
    "sg:tags":[
        "alarm",
        "burglar",
        "system"
    ],
    "wof:name":"Clifton Security Systems",
    "wof:placetype":"venue"
},
  "geometry": {"coordinates":[-122.911587,39.11202],"type":"Point"}
}