{
  "type": "Feature",
  "properties": {
    "addr:full":"3995 Alton Parkway Irvine CA 92606",
    "addr:housenumber":"3995",
    "addr:postcode":"92606",
    "addr:street":"Alton Parkway",
    "iso:country":"US",
    "sg:address":"3995 Alton Parkway",
    "sg:city":"Irvine",
    "sg:classifiers":[
        {
            "category":"Shopping",
            "subcategory":"Mobile Phones",
            "type":"Retail Goods"
        }
    ],
    "sg:phone":"+1 949 251 1576",
    "sg:postcode":"92606",
    "sg:province":"CA",
    "wof:name":"T-Mobile",
    "wof:placetype":"venue"
},
  "geometry": {"coordinates":[-117.81552499999999,33.686942],"type":"Point"}
}