{
  "type": "Feature",
  "properties": {
    "iso:country":"US",
    "sg:address":"3501 Saviers Rd",
    "sg:city":"Oxnard",
    "sg:classifiers":[
        {
            "category":"Professional",
            "type":"Services"
        }
    ],
    "sg:phone":"+1 805 486 2466",
    "sg:postcode":"93033",
    "sg:province":"CA",
    "wof:name":"Angels Hosiery",
    "wof:placetype":"venue"
},
  "geometry": {"coordinates":[-119.177694,34.167854],"type":"Point"}
}