{
  "type": "Feature",
  "properties": {
    "addr:full":"15470 Bomberg Ln Forest Ranch CA 95942",
    "addr:postcode":"15470;95942",
    "addr:street":"Bomberg Ln",
    "iso:country":"US",
    "sg:address":"15470 Bomberg Ln",
    "sg:city":"Forest Ranch",
    "sg:classifiers":[
        {
            "category":"Professional",
            "subcategory":"Computer Services",
            "type":"Services"
        }
    ],
    "sg:phone":"+1 530 893 5111",
    "sg:postcode":"95942",
    "sg:province":"CA",
    "sg:tags":[
        "internet"
    ],
    "wof:name":"Netk2ne",
    "wof:placetype":"venue"
},
  "geometry": {"coordinates":[-121.670931,39.872342],"type":"Point"}
}