{
  "type": "Feature",
  "properties": {
    "iso:country":"US",
    "sg:address":"13059 Aerospace Dr",
    "sg:city":"Victorville",
    "sg:classifiers":[
        {
            "category":"Manufacturing",
            "subcategory":"Tools & Machinery",
            "type":"Manufacturing & Wholesale Goods"
        }
    ],
    "sg:phone":"+1 760 246 1669",
    "sg:postcode":"92394",
    "sg:province":"CA",
    "sg:tags":[
        "industry",
        "aerospace"
    ],
    "wof:name":"West Coast Aerospace",
    "wof:placetype":"venue"
},
  "geometry": {"coordinates":[-117.380087,34.579697],"type":"Point"}
}