{
  "type": "Feature",
  "properties": {
    "iso:country":"US",
    "sg:address":"3135 Woodmark Ct",
    "sg:city":"Sacramento",
    "sg:classifiers":[
        {
            "category":"Banks & Credit Unions",
            "subcategory":"Bank",
            "type":"Services"
        }
    ],
    "sg:phone":"+1 916 561 0955",
    "sg:postcode":"95821",
    "sg:province":"CA",
    "sg:tags":[
        "broker",
        "mortgage"
    ],
    "wof:name":"Premier Brokerage Group",
    "wof:placetype":"venue"
},
  "geometry": {"coordinates":[-121.36926800000001,38.622698],"type":"Point"}
}