{
  "type": "Feature",
  "properties": {
    "iso:country":"US",
    "sg:address":"351 W Robles Ave",
    "sg:city":"Santa Rosa",
    "sg:classifiers":[
        {
            "category":"Building & Trades",
            "subcategory":"Construction",
            "type":"Services"
        }
    ],
    "sg:phone":"+1 707 588 8604",
    "sg:postcode":"95407",
    "sg:province":"CA",
    "sg:tags":[
        "repairing",
        "remodeling",
        "contractor"
    ],
    "wof:name":"Rehbehn ML General Contractor",
    "wof:placetype":"venue"
},
  "geometry": {"coordinates":[-122.724172,38.394499],"type":"Point"}
}