{
  "type": "Feature",
  "properties": {
    "iso:country":"US",
    "sg:address":"650 Municipal Wharf",
    "sg:city":"Santa Cruz",
    "sg:classifiers":[
        {
            "category":"Restaurant",
            "type":"Food & Drink"
        }
    ],
    "sg:phone":"+1 831 458 9393",
    "sg:postcode":"95060",
    "sg:province":"CA",
    "sg:tags":[
        "seafood",
        "mexican"
    ],
    "sg:website":"www.olitassantacruz.com",
    "wof:name":"Las Olitas Cantina & Grill",
    "wof:placetype":"venue"
},
  "geometry": {"coordinates":[-122.017561,36.958474],"type":"Point"}
}