{
  "type": "Feature",
  "properties": {
    "iso:country":"US",
    "sg:address":"2626 Newport Blvd",
    "sg:city":"Costa Mesa",
    "sg:classifiers":[
        {
            "category":"Building & Trades",
            "subcategory":"Construction",
            "type":"Services"
        }
    ],
    "sg:phone":"+1 949 548 1645",
    "sg:postcode":"92627",
    "sg:province":"CA",
    "sg:tags":[
        "roofing",
        "siding",
        "contractor"
    ],
    "wof:name":"Petronella Roofing",
    "wof:placetype":"venue"
},
  "geometry": {"coordinates":[-117.89534,33.665143],"type":"Point"}
}