{
  "type": "Feature",
  "properties": {
    "iso:country":"US",
    "sg:address":"555 Meridian Ave",
    "sg:city":"San Jose",
    "sg:classifiers":[
        {
            "category":"Social Services",
            "subcategory":"Child Care",
            "type":"Services"
        }
    ],
    "sg:phone":"+1 408 275 0810",
    "sg:postcode":"95126",
    "sg:province":"CA",
    "sg:tags":[
        "center"
    ],
    "sg:website":"www.communityfamilyservices.org",
    "wof:name":"Community Family Svc",
    "wof:placetype":"venue"
},
  "geometry": {"coordinates":[-121.914739,37.316051],"type":"Point"}
}