{
  "type": "Feature",
  "properties": {
    "addr:full":"14152 Paramount Blvd Paramount CA 90723",
    "addr:housenumber":"14152",
    "addr:postcode":"90723",
    "addr:street":"Paramount Blvd",
    "iso:country":"US",
    "sg:address":"14152 Paramount Blvd",
    "sg:city":"Paramount",
    "sg:classifiers":[
        {
            "category":"Shopping",
            "subcategory":"Florist",
            "type":"Retail Goods"
        }
    ],
    "sg:phone":"+1 562 633 8984",
    "sg:postcode":"90723",
    "sg:province":"CA",
    "wof:name":"Cinderella Florist",
    "wof:placetype":"venue"
},
  "geometry": {"coordinates":[-118.160023,33.90533],"type":"Point"}
}