{
  "type": "Feature",
  "properties": {
    "iso:country":"US",
    "sg:address":"222 Meigs Rd",
    "sg:city":"Santa Barbara",
    "sg:classifiers":[
        {
            "category":"Professional",
            "type":"Services"
        }
    ],
    "sg:phone":"+1 805 899 2614",
    "sg:postcode":"93109",
    "sg:province":"CA",
    "wof:name":"Sbnetworkx",
    "wof:placetype":"venue"
},
  "geometry": {"coordinates":[-119.722387,34.39851],"type":"Point"}
}