{
  "type": "Feature",
  "properties": {
    "addr:full":"1820 W 11th St Upland CA 91786",
    "addr:housenumber":"1820",
    "addr:postcode":"91786",
    "addr:street":"W 11Th St",
    "iso:country":"US",
    "sg:address":"1820 W 11th St",
    "sg:city":"Upland",
    "sg:classifiers":[
        {
            "category":"Retail",
            "subcategory":"Auto Repair",
            "type":"Services"
        }
    ],
    "sg:phone":"+1 909 608 1700",
    "sg:postcode":"91786",
    "sg:province":"CA",
    "sg:tags":[
        "muffler",
        "exhaust",
        "system"
    ],
    "sg:website":"www.mufflercity.net",
    "wof:name":"Muffler City",
    "wof:placetype":"venue"
},
  "geometry": {"coordinates":[-117.689408,34.103131],"type":"Point"}
}