{
  "type": "Feature",
  "properties": {
    "addr:full":"11916 Aviation Blvd Inglewood CA 90304",
    "addr:housenumber":"11916",
    "addr:postcode":"90304",
    "addr:street":"Aviation Blvd",
    "iso:country":"US",
    "sg:address":"11916 Aviation Blvd",
    "sg:city":"Inglewood",
    "sg:classifiers":[
        {
            "category":"Restaurant",
            "type":"Food & Drink"
        }
    ],
    "sg:phone":"+1 310 643 9911",
    "sg:postcode":"90304",
    "sg:province":"CA",
    "wof:name":"Happy Garden Restaurant",
    "wof:placetype":"venue"
},
  "geometry": {"coordinates":[-118.378396,33.924888],"type":"Point"}
}