{
  "type": "Feature",
  "properties": {
    "addr:full":"6837 Rio Linda Blvd Rio Linda CA 95673",
    "addr:housenumber":"6837",
    "addr:postcode":"95673",
    "addr:street":"Rio Linda Blvd",
    "iso:country":"US",
    "sg:address":"6837 Rio Linda Blvd",
    "sg:city":"Rio Linda",
    "sg:classifiers":[
        {
            "category":"Real Estate",
            "subcategory":"Real Estate Agent",
            "type":"Services"
        }
    ],
    "sg:phone":"+1 916 991 9795",
    "sg:postcode":"95673",
    "sg:province":"CA",
    "wof:name":"McClendon & Co",
    "wof:placetype":"venue"
},
  "geometry": {"coordinates":[-121.456937,38.691623],"type":"Point"}
}