{
  "type": "Feature",
  "properties": {
    "addr:full":"9121 Glenoaks Blvd Sun Valley CA 91352",
    "addr:housenumber":"9121",
    "addr:postcode":"91352",
    "addr:street":"Glenoaks Blvd",
    "iso:country":"US",
    "sg:address":"9121 Glenoaks Blvd",
    "sg:city":"Sun Valley",
    "sg:classifiers":[
        {
            "category":"Manufacturing",
            "subcategory":"Printing",
            "type":"Manufacturing & Wholesale Goods"
        }
    ],
    "sg:phone":"+1 818 767 7007",
    "sg:postcode":"91352",
    "sg:province":"CA",
    "sg:tags":[
        "printer"
    ],
    "sg:website":"www.insua.com",
    "wof:name":"Insua Graphics",
    "wof:placetype":"venue"
},
  "geometry": {"coordinates":[-118.372704,34.235654],"type":"Point"}
}