{
  "type": "Feature",
  "properties": {
    "iso:country":"US",
    "sg:address":"1601 N Long Beach Boulevard",
    "sg:city":"Compton",
    "sg:classifiers":[
        {
            "category":"Health Services",
            "subcategory":"Dentist",
            "type":"Services"
        }
    ],
    "sg:phone":"+1 310 639 5000",
    "sg:postcode":"90221",
    "sg:province":"CA",
    "wof:name":"Golden State Dental",
    "wof:placetype":"venue"
},
  "geometry": {"coordinates":[-118.208646,33.906443],"type":"Point"}
}