{
  "type": "Feature",
  "properties": {
    "addr:full":"32573 Highway 18 Running Springs CA 92382",
    "addr:housenumber":"32573",
    "addr:postcode":"92382",
    "addr:street":"Highway 18",
    "iso:country":"US",
    "sg:address":"32573 Highway 18",
    "sg:city":"Running Springs",
    "sg:classifiers":[
        {
            "category":"Sports & Exercise",
            "subcategory":"Sports Center",
            "type":"Entertainment"
        }
    ],
    "sg:phone":"+1 909 867 5996",
    "sg:postcode":"92382",
    "sg:province":"CA",
    "sg:tags":[
        "amateur",
        "team"
    ],
    "wof:name":"Childrens Forest",
    "wof:placetype":"venue"
},
  "geometry": {"coordinates":[-117.197982,34.203182],"type":"Point"}
}