{
  "type": "Feature",
  "properties": {
    "addr:full":"2232 S California Ave Duarte CA 91010",
    "addr:housenumber":"2232",
    "addr:postcode":"91010",
    "addr:street":"S California Ave",
    "iso:country":"US",
    "sg:address":"2232 S California Ave",
    "sg:city":"Duarte",
    "sg:classifiers":[
        {
            "category":"Real Estate",
            "subcategory":"Real Estate Agent",
            "type":"Services"
        }
    ],
    "sg:phone":"+1 626 303 4225",
    "sg:postcode":"91010",
    "sg:province":"CA",
    "sg:website":"www.chateaubradbury.com",
    "wof:name":"Chateau Bradbury Estate",
    "wof:placetype":"venue"
},
  "geometry": {"coordinates":[-117.997086,34.123797],"type":"Point"}
}