{
  "type": "Feature",
  "properties": {
    "addr:full":"11300 Houston Ave Hanford CA 93230",
    "addr:housenumber":"11300",
    "addr:postcode":"ca 93230",
    "addr:street":"Houston Ave",
    "iso:country":"US",
    "sg:address":"11300 Houston Ave",
    "sg:city":"Hanford",
    "sg:classifiers":[
        {
            "category":"Farming",
            "subcategory":"Farm",
            "type":"Manufacturing & Wholesale Goods"
        }
    ],
    "sg:phone":"+1 559 584 3947",
    "sg:postcode":"93230",
    "sg:province":"CA",
    "sg:tags":[
        "general"
    ],
    "wof:name":"Sanchez Brothers A Partnership",
    "wof:placetype":"venue"
},
  "geometry": {"coordinates":[-119.659115,36.298369],"type":"Point"}
}