{
  "type": "Feature",
  "properties": {
    "iso:country":"US",
    "sg:address":"530 B St",
    "sg:city":"Davis",
    "sg:classifiers":[
        {
            "category":"Education",
            "subcategory":"School",
            "type":"Public Place"
        }
    ],
    "sg:phone":"+1 530 757 5340",
    "sg:postcode":"95616",
    "sg:province":"CA",
    "wof:name":"Children's Center",
    "wof:placetype":"venue"
},
  "geometry": {"coordinates":[-121.745622,38.547394],"type":"Point"}
}