{
  "type": "Feature",
  "properties": {
    "iso:country":"US",
    "sg:address":"15466 Los Gatos Blvd. #109-122",
    "sg:city":"Los Gatos",
    "sg:classifiers":[
        {
            "category":"Building & Trades",
            "subcategory":"Cleaning & Sanitation",
            "type":"Services"
        }
    ],
    "sg:phone":"+1 408 355 5678",
    "sg:postcode":"95032",
    "sg:province":"CA",
    "sg:tags":[
        "carpet"
    ],
    "sg:website":"www.heavensbest.com/bay_area",
    "wof:name":"Heaven's Best Carpet and Upholstery Cleaning",
    "wof:placetype":"venue"
},
  "geometry": {"coordinates":[-121.958735,37.244046],"type":"Point"}
}