{
  "type": "Feature",
  "properties": {
    "iso:country":"US",
    "sg:address":"50 N Calaveras St",
    "sg:city":"Fresno",
    "sg:classifiers":[
        {
            "category":"Social Services",
            "type":"Services"
        }
    ],
    "sg:phone":"+1 559 497 8552",
    "sg:postcode":"93701",
    "sg:province":"CA",
    "sg:tags":[
        "youth",
        "organization",
        "center"
    ],
    "wof:name":"Chicano Youth Ctr",
    "wof:placetype":"venue"
},
  "geometry": {"coordinates":[-119.791815,36.743784],"type":"Point"}
}