{
  "type": "Feature",
  "properties": {
    "iso:country":"US",
    "sg:address":"3940 Redondo Beach Blvd",
    "sg:city":"Torrance",
    "sg:classifiers":[
        {
            "category":"Restaurant",
            "type":"Food & Drink"
        }
    ],
    "sg:menulink":"http://www.allmenus.com/ca/inglewood/178068-jack-in-the-box/menu/",
    "sg:phone":"+1 310 715 6494",
    "sg:postcode":"90504",
    "sg:province":"CA",
    "sg:tags":[
        "burger",
        "american"
    ],
    "wof:name":"Jack in the Box",
    "wof:placetype":"venue"
},
  "geometry": {"coordinates":[-118.342595,33.877698],"type":"Point"}
}