{
  "type": "Feature",
  "properties": {
    "iso:country":"US",
    "sg:address":"3535 Lincoln Ave",
    "sg:city":"Altadena",
    "sg:classifiers":[
        {
            "category":"Building & Trades",
            "subcategory":"Construction",
            "type":"Services"
        }
    ],
    "sg:phone":"+1 626 798 4795",
    "sg:postcode":"91001",
    "sg:province":"CA",
    "sg:tags":[
        "contractor"
    ],
    "wof:name":"John W Hedrick Contracting",
    "wof:placetype":"venue"
},
  "geometry": {"coordinates":[-118.159465,34.206677],"type":"Point"}
}