{
  "type": "Feature",
  "properties": {
    "iso:country":"US",
    "sg:address":"28145 Harrison Pkwy",
    "sg:city":"Valencia",
    "sg:classifiers":[
        {
            "category":"Wholesale",
            "subcategory":"Machinery & Supplies",
            "type":"Manufacturing & Wholesale Goods"
        }
    ],
    "sg:phone":"+1 661 295 8317",
    "sg:postcode":"91355",
    "sg:province":"CA",
    "sg:tags":[
        "equipment",
        "establishment"
    ],
    "wof:name":"Malys",
    "wof:placetype":"venue"
},
  "geometry": {"coordinates":[-118.62578000000001,34.440641],"type":"Point"}
}