{
  "type": "Feature",
  "properties": {
    "addr:full":"9542 Hamilton Ave Huntington Beach CA 92646",
    "addr:housenumber":"9542",
    "addr:postcode":"92646",
    "addr:street":"Hamilton Ave",
    "iso:country":"US",
    "sg:address":"9542 Hamilton Ave",
    "sg:city":"Huntington Beach",
    "sg:classifiers":[
        {
            "category":"Home & Garden",
            "subcategory":"Building Materials",
            "type":"Retail Goods"
        },
        {
            "category":"Building & Trades",
            "subcategory":"Locksmith",
            "type":"Services"
        }
    ],
    "sg:phone":"+1 714 965 0018",
    "sg:postcode":"92646",
    "sg:province":"CA",
    "sg:tags":[
        "equipment",
        "lighting",
        "fixture",
        "key"
    ],
    "wof:name":"Aaaa Signs",
    "wof:placetype":"venue"
},
  "geometry": {"coordinates":[-117.96199799999999,33.650398],"type":"Point"}
}