{
  "type": "Feature",
  "properties": {
    "addr:full":"1924 Stafford St Redwood City CA 94063",
    "addr:housenumber":"1924",
    "addr:postcode":"94063",
    "addr:street":"Stafford St",
    "iso:country":"US",
    "sg:address":"1924 Stafford St",
    "sg:city":"Redwood City",
    "sg:classifiers":[
        {
            "category":"Building & Trades",
            "subcategory":"Construction",
            "type":"Services"
        }
    ],
    "sg:phone":"+1 650 367 8777",
    "sg:postcode":"94063",
    "sg:province":"CA",
    "wof:name":"Wash On Wheels",
    "wof:placetype":"venue"
},
  "geometry": {"coordinates":[-122.243635,37.493912],"type":"Point"}
}