{
  "type": "Feature",
  "properties": {
    "addr:full":"4022 Pacheco Blvd Martinez CA 94553",
    "addr:housenumber":"4022",
    "addr:postcode":"94553",
    "addr:street":"Pacheco Blvd",
    "iso:country":"US",
    "sg:address":"4022 Pacheco Blvd",
    "sg:city":"Martinez",
    "sg:classifiers":[
        {
            "category":"Building & Trades",
            "subcategory":"Landscaping Services",
            "type":"Services"
        }
    ],
    "sg:phone":"+1 925 686 0104",
    "sg:postcode":"94553",
    "sg:province":"CA",
    "sg:tags":[
        "landscape",
        "contractor"
    ],
    "wof:name":"Zabarte Garden Co",
    "wof:placetype":"venue"
},
  "geometry": {"coordinates":[-122.09519299999999,38.007992],"type":"Point"}
}