{
  "type": "Feature",
  "properties": {
    "iso:country":"US",
    "sg:address":"400 Riviera Cir",
    "sg:city":"Larkspur",
    "sg:classifiers":[
        {
            "category":"Building & Trades",
            "subcategory":"Construction",
            "type":"Services"
        }
    ],
    "sg:phone":"+1 415 924 5899",
    "sg:postcode":"94939",
    "sg:province":"CA",
    "sg:tags":[
        "system",
        "contractor",
        "air conditioning"
    ],
    "wof:name":"Mentis Ars",
    "wof:placetype":"venue"
},
  "geometry": {"coordinates":[-122.525848,37.94239],"type":"Point"}
}