{
  "type": "Feature",
  "properties": {
    "addr:full":"2517 Purdue Ave Los Angeles CA 90064",
    "addr:housenumber":"2517",
    "addr:postcode":"90064",
    "addr:street":"Purdue Ave",
    "iso:country":"US",
    "sg:address":"2517 Purdue Ave",
    "sg:city":"Los Angeles",
    "sg:classifiers":[
        {
            "category":"Wholesale",
            "subcategory":"Stationery",
            "type":"Manufacturing & Wholesale Goods"
        }
    ],
    "sg:phone":"+1 310 473 8952",
    "sg:postcode":"90064",
    "sg:province":"CA",
    "sg:tags":[
        "distributor",
        "business",
        "form"
    ],
    "sg:website":"www.versagraphics4u.com",
    "wof:name":"Versa Graphics",
    "wof:placetype":"venue"
},
  "geometry": {"coordinates":[-118.43831400000001,34.031267],"type":"Point"}
}