{
  "type": "Feature",
  "properties": {
    "iso:country":"US",
    "sg:address":"14751 Daphne Ave",
    "sg:city":"Gardena",
    "sg:classifiers":[
        {
            "category":"Social Services",
            "type":"Services"
        }
    ],
    "sg:phone":"+1 310 324 0514",
    "sg:postcode":"90249",
    "sg:province":"CA",
    "sg:tags":[
        "counselor",
        "marriage",
        "family"
    ],
    "wof:name":"Orpheus Artes Backgrounds",
    "wof:placetype":"venue"
},
  "geometry": {"coordinates":[-118.31965700000001,33.89707],"type":"Point"}
}