{
  "type": "Feature",
  "properties": {
    "iso:country":"US",
    "sg:address":"1564 American River Trl",
    "sg:city":"Cool",
    "sg:classifiers":[
        {
            "category":"Professional",
            "type":"Services"
        }
    ],
    "sg:phone":"+1 530 889 9439",
    "sg:postcode":"95614",
    "sg:province":"CA",
    "wof:name":"Hassler Products Online",
    "wof:placetype":"venue"
},
  "geometry": {"coordinates":[-121.000176,38.897279],"type":"Point"}
}