{
  "type": "Feature",
  "properties": {
    "iso:country":"US",
    "sg:address":"9621 Mission Gorge Rd Ste 107",
    "sg:city":"Santee",
    "sg:classifiers":[
        {
            "category":"Professional",
            "type":"Services"
        },
        {
            "category":"Restaurant",
            "type":"Food & Drink"
        }
    ],
    "sg:phone":"+1 619 562 1888",
    "sg:postcode":"92071",
    "sg:province":"CA",
    "sg:tags":[
        "barbeque",
        "hawaiian",
        "caterer"
    ],
    "sg:website":"www.llbarbecue.com",
    "wof:name":"L&L Hawaiian Barbecue",
    "wof:placetype":"venue"
},
  "geometry": {"coordinates":[-116.98788399999999,32.837948],"type":"Point"}
}