{
  "type": "Feature",
  "properties": {
    "addr:full":"705 B St San Rafael CA 94901",
    "addr:housenumber":"705",
    "addr:postcode":"94901",
    "addr:street":"B St",
    "iso:country":"US",
    "sg:address":"705 B St",
    "sg:city":"San Rafael",
    "sg:classifiers":[
        {
            "category":"Retail",
            "subcategory":"Laundry & Dry Cleaning",
            "type":"Services"
        }
    ],
    "sg:phone":"+1 415 485 1499",
    "sg:postcode":"94901",
    "sg:province":"CA",
    "sg:tags":[
        "cleaners"
    ],
    "wof:name":"Marshall Steel Full Svc Clnrs",
    "wof:placetype":"venue"
},
  "geometry": {"coordinates":[-122.530002,37.970451],"type":"Point"}
}