{
  "type": "Feature",
  "properties": {
    "iso:country":"US",
    "sg:address":"12304 Santa Monica Blvd",
    "sg:city":"Los Angeles",
    "sg:classifiers":[
        {
            "category":"Professional",
            "subcategory":"Employment Agencies",
            "type":"Services"
        }
    ],
    "sg:phone":"+1 310 207 0979",
    "sg:postcode":"90025",
    "sg:province":"CA",
    "sg:tags":[
        "medical"
    ],
    "sg:website":"www.doctorscornerpersonnel.com",
    "wof:name":"Doctors' Corner Personnel Svc",
    "wof:placetype":"venue"
},
  "geometry": {"coordinates":[-118.466526,34.03906],"type":"Point"}
}