{
  "type": "Feature",
  "properties": {
    "iso:country":"US",
    "sg:address":"6904 Miramar Rd",
    "sg:city":"San Diego",
    "sg:classifiers":[
        {
            "category":"Shopping",
            "subcategory":"Computers & Home Electronics",
            "type":"Retail Goods"
        }
    ],
    "sg:phone":"+1 858 578 6886",
    "sg:postcode":"92121",
    "sg:province":"CA",
    "sg:tags":[
        "television",
        "radio"
    ],
    "wof:name":"Blackwell Satellite System",
    "wof:placetype":"venue"
},
  "geometry": {"coordinates":[-117.167,32.878406],"type":"Point"}
}