{
  "type": "Feature",
  "properties": {
    "iso:country":"US",
    "sg:address":"7605 Sierra Ave",
    "sg:city":"Fontana",
    "sg:classifiers":[
        {
            "category":"Organizations",
            "subcategory":"Religious Organization",
            "type":"Services"
        }
    ],
    "sg:phone":"+1 909 427 0915",
    "sg:postcode":"92336",
    "sg:province":"CA",
    "sg:tags":[
        "church"
    ],
    "wof:name":"Come & See Baptist Church",
    "wof:placetype":"venue"
},
  "geometry": {"coordinates":[-117.435782,34.113989],"type":"Point"}
}