{
  "type": "Feature",
  "properties": {
    "addr:full":"2540 N 1st Street San Jose CA 95131",
    "addr:housenumber":"2540",
    "addr:postcode":"95131",
    "addr:street":"N 1St Street",
    "iso:country":"US",
    "sg:address":"2540 N 1st Street",
    "sg:city":"San Jose",
    "sg:classifiers":[
        {
            "category":"Banks & Credit Unions",
            "subcategory":"Financial Services",
            "type":"Services"
        }
    ],
    "sg:phone":"+1 408 240 8800",
    "sg:postcode":"95131",
    "sg:province":"CA",
    "sg:tags":[
        "broker",
        "mortgage"
    ],
    "wof:name":"Cipher Lending",
    "wof:placetype":"venue"
},
  "geometry": {"coordinates":[-121.92615000000001,37.384163],"type":"Point"}
}