{
  "type": "Feature",
  "properties": {
    "addr:full":"2901 State Hwy 88 Ione CA 95640",
    "addr:housenumber":"2901",
    "addr:postcode":"ca 95640",
    "addr:street":"State Hwy 88",
    "iso:country":"US",
    "sg:address":"2901 State Hwy 88",
    "sg:city":"Ione",
    "sg:classifiers":[
        {
            "category":"Farming",
            "subcategory":"Farm & Veterinary Services",
            "type":"Manufacturing & Wholesale Goods"
        }
    ],
    "sg:phone":"+1 209 274 4595",
    "sg:postcode":"95640",
    "sg:province":"CA",
    "sg:tags":[
        "livestock"
    ],
    "wof:name":"CJ Rauch",
    "wof:placetype":"venue"
},
  "geometry": {"coordinates":[-120.978893,38.306592],"type":"Point"}
}