{
  "type": "Feature",
  "properties": {
    "addr:full":"675 24th Ave Santa Cruz CA 95062",
    "addr:housenumber":"675",
    "addr:postcode":"95062",
    "addr:street":"24Th Ave",
    "iso:country":"US",
    "sg:address":"675 24th Ave",
    "sg:city":"Santa Cruz",
    "sg:classifiers":[
        {
            "category":"Social Services",
            "subcategory":"Adult Care",
            "type":"Services"
        }
    ],
    "sg:phone":"+1 831 475 6323",
    "sg:postcode":"95062",
    "sg:province":"CA",
    "sg:tags":[
        "home",
        "residential"
    ],
    "wof:name":"Driftwood Health Care Ctr",
    "wof:placetype":"venue"
},
  "geometry": {"coordinates":[-121.979782,36.964335],"type":"Point"}
}