{
  "type": "Feature",
  "properties": {
    "addr:full":"211 N Court St Visalia CA 93291",
    "addr:housenumber":"211",
    "addr:postcode":"93291",
    "addr:street":"N Court St",
    "iso:country":"US",
    "sg:address":"211 N Court St",
    "sg:city":"Visalia",
    "sg:classifiers":[
        {
            "category":"Professional",
            "subcategory":"Lawyer & Legal Services",
            "type":"Services"
        }
    ],
    "sg:phone":"+1 559 624 1234",
    "sg:postcode":"93291",
    "sg:province":"CA",
    "sg:tags":[
        "attorney"
    ],
    "wof:name":"Wolff & Kinsler",
    "wof:placetype":"venue"
},
  "geometry": {"coordinates":[-119.292406,36.331418],"type":"Point"}
}