{
  "type": "Feature",
  "properties": {
    "addr:full":"750 Mobil Ave Apt 78 Camarillo CA 93010",
    "addr:housenumber":"750;78",
    "addr:postcode":"93010",
    "addr:street":"Mobil Ave Apt",
    "iso:country":"US",
    "sg:address":"750 Mobil Ave Apt 78",
    "sg:city":"Camarillo",
    "sg:classifiers":[
        {
            "category":"Real Estate",
            "subcategory":"Real Estate Operator",
            "type":"Services"
        }
    ],
    "sg:phone":"+1 805 482 8800",
    "sg:postcode":"93010",
    "sg:province":"CA",
    "sg:tags":[
        "apartment"
    ],
    "sg:website":"www.villaponderosa.com",
    "wof:name":"Villa Ponderosa",
    "wof:placetype":"venue"
},
  "geometry": {"coordinates":[-119.04299899999999,34.2248],"type":"Point"}
}