{
  "type": "Feature",
  "properties": {
    "addr:full":"989 Mount Curve Ave Altadena CA 91001",
    "addr:housenumber":"989",
    "addr:postcode":"91001",
    "addr:street":"Mount Curve Ave",
    "iso:country":"US",
    "sg:address":"989 Mount Curve Ave",
    "sg:city":"Altadena",
    "sg:classifiers":[
        {
            "category":"Arts & Performance",
            "subcategory":"Theater",
            "type":"Entertainment"
        }
    ],
    "sg:phone":"+1 818 989 2565",
    "sg:postcode":"91001",
    "sg:province":"CA",
    "sg:tags":[
        "live",
        "music"
    ],
    "wof:name":"Sing Sing Enterprises",
    "wof:placetype":"venue"
},
  "geometry": {"coordinates":[-118.129121,34.200961],"type":"Point"}
}