{
  "type": "Feature",
  "properties": {
    "iso:country":"US",
    "sg:address":"423 2nd St",
    "sg:city":"Solvang",
    "sg:classifiers":[
        {
            "category":"Manufacturing",
            "subcategory":"Printing",
            "type":"Manufacturing & Wholesale Goods"
        }
    ],
    "sg:phone":"+1 805 688 5522",
    "sg:postcode":"93463",
    "sg:province":"CA",
    "sg:tags":[
        "dealers-wholesale",
        "news",
        "newspaper"
    ],
    "wof:name":"Santa Ynez Valley News",
    "wof:placetype":"venue"
},
  "geometry": {"coordinates":[-120.141436,34.594363],"type":"Point"}
}