{
  "type": "Feature",
  "properties": {
    "iso:country":"US",
    "sg:address":"1083 S 7th St",
    "sg:city":"San Jose",
    "sg:classifiers":[
        {
            "category":"Banks & Credit Unions",
            "subcategory":"Bank",
            "type":"Services"
        }
    ],
    "sg:phone":"+1 408 279 9333",
    "sg:postcode":"95112",
    "sg:province":"CA",
    "sg:tags":[
        "loan",
        "real estate"
    ],
    "sg:website":"www.homeloanstreet.com",
    "wof:name":"Excel Mortgage",
    "wof:placetype":"venue"
},
  "geometry": {"coordinates":[-121.872899,37.323921],"type":"Point"}
}