{
  "type": "Feature",
  "properties": {
    "iso:country":"US",
    "sg:address":"624 W 9th St",
    "sg:city":"San Pedro",
    "sg:classifiers":[
        {
            "category":"Professional",
            "subcategory":"Lawyer & Legal Services",
            "type":"Services"
        }
    ],
    "sg:phone":"+1 310 519 0425",
    "sg:postcode":"90731",
    "sg:province":"CA",
    "sg:tags":[
        "attorney"
    ],
    "wof:name":"Michael A Sokolich",
    "wof:placetype":"venue"
},
  "geometry": {"coordinates":[-118.291468,33.736121],"type":"Point"}
}