{
  "type": "Feature",
  "properties": {
    "addr:full":"816 H St Sacramento CA 95814",
    "addr:housenumber":"816",
    "addr:postcode":"95814",
    "addr:street":"H St",
    "iso:country":"US",
    "sg:address":"816 H St",
    "sg:city":"Sacramento",
    "sg:classifiers":[
        {
            "category":"Insurance",
            "subcategory":"Hazard Insurance",
            "type":"Services"
        }
    ],
    "sg:phone":"+1 916 444 8799",
    "sg:postcode":"95814",
    "sg:province":"CA",
    "sg:tags":[
        "bond"
    ],
    "wof:name":"Carolyn Lee Bail Bonds",
    "wof:placetype":"venue"
},
  "geometry": {"coordinates":[-121.49405899999999,38.582842],"type":"Point"}
}