{
  "type": "Feature",
  "properties": {
    "addr:full":"3941 J Street Sacramento CA 95819",
    "addr:housenumber":"3941",
    "addr:postcode":"95819",
    "addr:street":"J Street",
    "iso:country":"US",
    "sg:address":"3941 J Street",
    "sg:city":"Sacramento",
    "sg:classifiers":[
        {
            "category":"Shopping",
            "subcategory":"Pharmacy",
            "type":"Retail Goods"
        }
    ],
    "sg:phone":"+1 916 733 6970",
    "sg:postcode":"95819",
    "sg:province":"CA",
    "sg:tags":[
        "drugstore"
    ],
    "wof:name":"Mercy Pharmacy",
    "wof:placetype":"venue"
},
  "geometry": {"coordinates":[-121.454187,38.569728],"type":"Point"}
}