{
  "type": "Feature",
  "properties": {
    "addr:full":"508 Woodland Way Santa Cruz CA 95067",
    "addr:housenumber":"508",
    "addr:postcode":"95067",
    "addr:street":"Woodland Way",
    "iso:country":"US",
    "sg:address":"508 Woodland Way",
    "sg:city":"Santa Cruz",
    "sg:classifiers":[
        {
            "category":"Park",
            "type":"Public Place"
        }
    ],
    "sg:postcode":"95067",
    "sg:province":"CA",
    "sg:website":"www.ci.santa-cruz.ca.us/pr/parks...",
    "wof:name":"Derby Park",
    "wof:placetype":"venue"
},
  "geometry": {"coordinates":[-122.052548,36.953304],"type":"Point"}
}