{
  "type": "Feature",
  "properties": {
    "iso:country":"US",
    "sg:address":"5830 Oak House Ct",
    "sg:city":"Orangevale",
    "sg:classifiers":[
        {
            "category":"Building & Trades",
            "subcategory":"Construction",
            "type":"Services"
        }
    ],
    "sg:phone":"+1 916 837 6409",
    "sg:postcode":"95662",
    "sg:province":"CA",
    "sg:tags":[
        "contractor"
    ],
    "sg:website":"www.decksdotcom.com",
    "wof:name":"Roger Holme Construction",
    "wof:placetype":"venue"
},
  "geometry": {"coordinates":[-121.236608,38.672429],"type":"Point"}
}