{
  "type": "Feature",
  "properties": {
    "iso:country":"US",
    "sg:address":"3550 Wilshire Boulevard Suite 640",
    "sg:city":"Los Angeles",
    "sg:classifiers":[
        {
            "category":"Professional",
            "subcategory":"Lawyer & Legal Services",
            "type":"Services"
        }
    ],
    "sg:phone":"+1 213 384 8602",
    "sg:postcode":"90010",
    "sg:province":"CA",
    "wof:name":"David Kim Law Office of",
    "wof:placetype":"venue"
},
  "geometry": {"coordinates":[-118.302001,34.061728],"type":"Point"}
}