{
  "type": "Feature",
  "properties": {
    "addr:full":"46410 Fremont Boulevard Fremont CA 94538",
    "addr:housenumber":"46410",
    "addr:postcode":"94538",
    "addr:street":"Fremont Boulevard",
    "iso:country":"US",
    "sg:address":"46410 Fremont Boulevard",
    "sg:city":"Fremont",
    "sg:classifiers":[
        {
            "category":"Professional",
            "subcategory":"Computer Services",
            "type":"Services"
        }
    ],
    "sg:phone":"+1 510 668 0227",
    "sg:postcode":"94538",
    "sg:province":"CA",
    "sg:website":"http://www.intematix.com/",
    "wof:name":"Intematix",
    "wof:placetype":"venue"
},
  "geometry": {"coordinates":[-121.946027,37.484541],"type":"Point"}
}