{
  "type": "Feature",
  "properties": {
    "addr:full":"27457 Jefferson Ave Temecula CA 92590",
    "addr:housenumber":"27457",
    "addr:postcode":"92590",
    "addr:street":"Jefferson Ave",
    "iso:country":"US",
    "sg:address":"27457 Jefferson Ave",
    "sg:city":"Temecula",
    "sg:classifiers":[
        {
            "category":"Retail",
            "subcategory":"Auto Rental",
            "type":"Services"
        }
    ],
    "sg:phone":"+1 951 506 9696",
    "sg:postcode":"92590",
    "sg:province":"CA",
    "sg:tags":[
        "passenger",
        "truck",
        "car"
    ],
    "sg:website":"http://www.enterprise.com/car_rental/deeplinkmap.do?gpbr=32Y7&bid=004&cnty=US&arc=YPTRL01&cm_mmc=Yellowpages.com-_-IYP-_-Tradelisting-_-branch",
    "wof:name":"Enterprise Rent-A-Car",
    "wof:placetype":"venue"
},
  "geometry": {"coordinates":[-117.16380599999999,33.519577],"type":"Point"}
}