{
  "type": "Feature",
  "properties": {
    "iso:country":"US",
    "sg:address":"10953 Kinross Ave",
    "sg:city":"Los Angeles",
    "sg:classifiers":[
        {
            "category":"Shopping",
            "subcategory":"News",
            "type":"Retail Goods"
        }
    ],
    "sg:phone":"+1 310 824 8840",
    "sg:postcode":"90024",
    "sg:province":"CA",
    "sg:tags":[
        "shop",
        "newspaper",
        "magazine",
        "tobacco"
    ],
    "wof:name":"Smoke Spot & News",
    "wof:placetype":"venue"
},
  "geometry": {"coordinates":[-118.446634,34.060139],"type":"Point"}
}