{
  "type": "Feature",
  "properties": {
    "addr:full":"2334 10th St Berkeley CA 94710",
    "addr:housenumber":"2334",
    "addr:postcode":"94710",
    "addr:street":"10Th St",
    "iso:country":"US",
    "sg:address":"2334 10th St",
    "sg:city":"Berkeley",
    "sg:classifiers":[
        {
            "category":"Taxi",
            "type":"Transportation"
        }
    ],
    "sg:phone":"+1 800 666 2626",
    "sg:postcode":"94710",
    "sg:province":"CA",
    "wof:name":"Yellow Cab",
    "wof:placetype":"venue"
},
  "geometry": {"coordinates":[-122.291663,37.863775],"type":"Point"}
}