{
  "type": "Feature",
  "properties": {
    "addr:full":"23450 Lyons Ave Santa Clarita CA 91321",
    "addr:housenumber":"23450",
    "addr:postcode":"91321",
    "addr:street":"Lyons Ave",
    "iso:country":"US",
    "sg:address":"23450 Lyons Ave",
    "sg:city":"Santa Clarita",
    "sg:classifiers":[
        {
            "category":"Health Services",
            "subcategory":"Dentist",
            "type":"Services"
        }
    ],
    "sg:phone":"+1 661 254 5657",
    "sg:postcode":"91321",
    "sg:province":"CA",
    "wof:name":"Vir Kunwar DMD",
    "wof:placetype":"venue"
},
  "geometry": {"coordinates":[-118.544133,34.379183],"type":"Point"}
}