{
  "type": "Feature",
  "properties": {
    "addr:full":"549 S San Fernando Blvd Burbank CA 91502",
    "addr:housenumber":"549",
    "addr:postcode":"91502",
    "addr:street":"S San Fernando Blvd",
    "iso:country":"US",
    "sg:address":"549 S San Fernando Blvd",
    "sg:city":"Burbank",
    "sg:classifiers":[
        {
            "category":"Wholesale",
            "subcategory":"Hardware",
            "type":"Manufacturing & Wholesale Goods"
        }
    ],
    "sg:phone":"+1 818 845 6383",
    "sg:postcode":"91502",
    "sg:province":"CA",
    "sg:tags":[
        "equipment",
        "locksmith",
        "key",
        "supply"
    ],
    "wof:name":"L A Locksmith Supply",
    "wof:placetype":"venue"
},
  "geometry": {"coordinates":[-118.304001,34.177502],"type":"Point"}
}