{
  "type": "Feature",
  "properties": {
    "addr:full":"408 Los Gatos Almaden Rd Los Gatos CA 95032",
    "addr:housenumber":"408",
    "addr:postcode":"95032",
    "addr:street":"Los;Almaden Rd",
    "iso:country":"US",
    "sg:address":"408 Los Gatos Almaden Rd",
    "sg:city":"Los Gatos",
    "sg:classifiers":[
        {
            "category":"Travel",
            "subcategory":"Travel Agent",
            "type":"Entertainment"
        }
    ],
    "sg:phone":"+1 408 377 1058",
    "sg:postcode":"95032",
    "sg:province":"CA",
    "sg:tags":[
        "agency"
    ],
    "wof:name":"Esperanzas Travel Services",
    "wof:placetype":"venue"
},
  "geometry": {"coordinates":[-121.92496,37.243397],"type":"Point"}
}