{
  "type": "Feature",
  "properties": {
    "iso:country":"US",
    "sg:address":"3218 Heglis Ave",
    "sg:city":"Rosemead",
    "sg:classifiers":[
        {
            "category":"Social Services",
            "type":"Services"
        }
    ],
    "sg:phone":"+1 626 280 0061",
    "sg:postcode":"91770",
    "sg:province":"CA",
    "sg:tags":[
        "home",
        "bureau",
        "placement"
    ],
    "wof:name":"Heglis Care Home",
    "wof:placetype":"venue"
},
  "geometry": {"coordinates":[-118.070108,34.066521],"type":"Point"}
}