{
  "type": "Feature",
  "properties": {
    "addr:full":"NE Corner 4th & Junipero Ave Carmel-by-the-Sea CA 93923",
    "addr:postcode":"93923",
    "addr:street":"Ne;Junipero Ave",
    "iso:country":"US",
    "sg:address":"NE Corner 4th & Junipero Ave",
    "sg:city":"Carmel-by-the-Sea",
    "sg:classifiers":[
        {
            "category":"Autos & Motor Vehicles",
            "subcategory":"Automobile Sales",
            "type":"Retail Goods"
        }
    ],
    "sg:phone":"+1 831 626 0774",
    "sg:postcode":"93923",
    "sg:province":"CA",
    "sg:tags":[
        "automotive"
    ],
    "wof:name":"Carmel Garage",
    "wof:placetype":"venue"
},
  "geometry": {"coordinates":[-121.919966,36.558136],"type":"Point"}
}