{
  "type": "Feature",
  "properties": {
    "iso:country":"US",
    "sg:address":"11012 Magnolia St",
    "sg:city":"Garden Grove",
    "sg:classifiers":[
        {
            "category":"Restaurant",
            "type":"Food & Drink"
        }
    ],
    "sg:phone":"+1 714 539 8274",
    "sg:postcode":"92841",
    "sg:province":"CA",
    "sg:tags":[
        "mexican"
    ],
    "wof:name":"Tacos La Lagunilla",
    "wof:placetype":"venue"
},
  "geometry": {"coordinates":[-117.975998,33.802799],"type":"Point"}
}