{
  "type": "Feature",
  "properties": {
    "addr:full":"228 30th Ave San Francisco CA 94121",
    "addr:housenumber":"228",
    "addr:postcode":"94121",
    "addr:street":"30Th Ave",
    "iso:country":"US",
    "sg:address":"228 30th Ave",
    "sg:city":"San Francisco",
    "sg:classifiers":[
        {
            "category":"Wholesale",
            "subcategory":"Groceries",
            "type":"Manufacturing & Wholesale Goods"
        }
    ],
    "sg:phone":"+1 415 668 5437",
    "sg:postcode":"94121",
    "sg:province":"CA",
    "sg:tags":[
        "general"
    ],
    "wof:name":"CM Food Sales",
    "wof:placetype":"venue"
},
  "geometry": {"coordinates":[-122.490368,37.784803],"type":"Point"}
}