{
  "type": "Feature",
  "properties": {
    "iso:country":"US",
    "sg:address":"10632 Fulton Wells Ave",
    "sg:city":"Santa Fe Springs",
    "sg:classifiers":[
        {
            "category":"Freight",
            "type":"Transportation"
        }
    ],
    "sg:phone":"+1 562 944 2200",
    "sg:postcode":"90670",
    "sg:province":"CA",
    "sg:tags":[
        "warehouse",
        "self",
        "storage"
    ],
    "wof:name":"CAN Logistics Inc",
    "wof:placetype":"venue"
},
  "geometry": {"coordinates":[-118.075834,33.935641],"type":"Point"}
}