{
  "type": "Feature",
  "properties": {
    "iso:country":"US",
    "sg:address":"1995 E 20th St",
    "sg:city":"Los Angeles",
    "sg:classifiers":[
        {
            "category":"Wholesale",
            "subcategory":"Fruits & Vegetables",
            "type":"Manufacturing & Wholesale Goods"
        }
    ],
    "sg:phone":"+1 213 746 1940",
    "sg:postcode":"90058",
    "sg:province":"CA",
    "wof:name":"L A Consolidation Inc",
    "wof:placetype":"venue"
},
  "geometry": {"coordinates":[-118.236694,34.017705],"type":"Point"}
}