{
  "type": "Feature",
  "properties": {
    "addr:full":"1271 Los Viboras Rd Hollister CA 95023",
    "addr:housenumber":"1271",
    "addr:postcode":"hollister ca 95023",
    "addr:street":"Los Viboras Rd",
    "iso:country":"US",
    "sg:address":"1271 Los Viboras Rd",
    "sg:city":"Hollister",
    "sg:classifiers":[
        {
            "category":"Shopping",
            "type":"Retail Goods"
        }
    ],
    "sg:phone":"+1 831 636 1971",
    "sg:postcode":"95023",
    "sg:province":"CA",
    "sg:tags":[
        "outdoor",
        "lighting",
        "specialty"
    ],
    "wof:name":"Bourdet's Christmas Trees",
    "wof:placetype":"venue"
},
  "geometry": {"coordinates":[-121.358692,36.934122],"type":"Point"}
}