{
  "type": "Feature",
  "properties": {
    "iso:country":"US",
    "sg:address":"60 S Market Street Bsmt",
    "sg:city":"San Jose",
    "sg:classifiers":[
        {
            "category":"Professional",
            "subcategory":"Lawyer & Legal Services",
            "type":"Services"
        }
    ],
    "sg:phone":"+1 408 287 9501",
    "sg:postcode":"95113",
    "sg:province":"CA",
    "wof:name":"Green Christine B Attys",
    "wof:placetype":"venue"
},
  "geometry": {"coordinates":[-121.891143,37.33431],"type":"Point"}
}