{
  "type": "Feature",
  "properties": {
    "addr:full":"3055 Alvarado St San Leandro CA 94577",
    "addr:housenumber":"3055",
    "addr:postcode":"94577",
    "addr:street":"Alvarado St",
    "iso:country":"US",
    "sg:address":"3055 Alvarado St",
    "sg:city":"San Leandro",
    "sg:classifiers":[
        {
            "category":"Professional",
            "subcategory":"Accounting & Tax Preparation",
            "type":"Services"
        }
    ],
    "sg:phone":"+1 510 357 7560",
    "sg:postcode":"94577",
    "sg:province":"CA",
    "sg:tags":[
        "accountant"
    ],
    "wof:name":"Seiberlich Accountancy Corp",
    "wof:placetype":"venue"
},
  "geometry": {"coordinates":[-122.154363,37.7087],"type":"Point"}
}