{
  "type": "Feature",
  "properties": {
    "addr:full":"1287 Palomino Rd Fallbrook CA 92028",
    "addr:housenumber":"1287",
    "addr:postcode":"92028",
    "addr:street":"Palomino Rd",
    "iso:country":"US",
    "sg:address":"1287 Palomino Rd",
    "sg:city":"Fallbrook",
    "sg:classifiers":[
        {
            "category":"Shopping",
            "subcategory":"Hobbies, Toys, & Games",
            "type":"Retail Goods"
        }
    ],
    "sg:phone":"+1 760 451 0051",
    "sg:postcode":"92028",
    "sg:province":"CA",
    "wof:name":"Esthers Victorian Elegance",
    "wof:placetype":"venue"
},
  "geometry": {"coordinates":[-117.23088,33.365503],"type":"Point"}
}