{
  "type": "Feature",
  "properties": {
    "addr:full":"165 Niblick Rd Paso Robles CA 93446",
    "addr:housenumber":"165",
    "addr:postcode":"93446",
    "addr:street":"Niblick Rd",
    "iso:country":"US",
    "sg:address":"165 Niblick Rd",
    "sg:city":"Paso Robles",
    "sg:classifiers":[
        {
            "category":"Personal",
            "subcategory":"Beauty Salon",
            "type":"Services"
        }
    ],
    "sg:phone":"+1 805 238 2232",
    "sg:postcode":"93446",
    "sg:province":"CA",
    "sg:tags":[
        "manicuring"
    ],
    "wof:name":"Number 1 Nails",
    "wof:placetype":"venue"
},
  "geometry": {"coordinates":[-120.68517799999999,35.615247],"type":"Point"}
}