{
  "type": "Feature",
  "properties": {
    "addr:full":"9010 S Elm Ave Fresno CA 93706",
    "addr:housenumber":"9010",
    "addr:postcode":"93706",
    "addr:street":"S Elm Ave",
    "iso:country":"US",
    "sg:address":"9010 S Elm Ave",
    "sg:city":"Fresno",
    "sg:classifiers":[
        {
            "category":"Food & Beverages",
            "subcategory":"Groceries & Convenience Stores",
            "type":"Retail Goods"
        }
    ],
    "sg:phone":"+1 559 834 6757",
    "sg:postcode":"93706",
    "sg:province":"CA",
    "wof:name":"Adina Valley Market",
    "wof:placetype":"venue"
},
  "geometry": {"coordinates":[-119.791,36.604301],"type":"Point"}
}