{
  "type": "Feature",
  "properties": {
    "iso:country":"US",
    "sg:address":"4926 Newport Ave",
    "sg:city":"San Diego",
    "sg:classifiers":[
        {
            "category":"Shopping",
            "subcategory":"Used Merchandise",
            "type":"Retail Goods"
        }
    ],
    "sg:phone":"+1 619 222 2232",
    "sg:postcode":"92107",
    "sg:province":"CA",
    "sg:tags":[
        "antique"
    ],
    "wof:name":"Antiques & Stuff By Ruth",
    "wof:placetype":"venue"
},
  "geometry": {"coordinates":[-117.25057700000001,32.746631],"type":"Point"}
}