{
  "type": "Feature",
  "properties": {
    "addr:full":"1753 Hillhurst Ave Los Angeles CA 90027",
    "addr:housenumber":"1753",
    "addr:postcode":"90027",
    "addr:street":"Hillhurst Ave",
    "iso:country":"US",
    "sg:address":"1753 Hillhurst Ave",
    "sg:city":"Los Angeles",
    "sg:classifiers":[
        {
            "category":"Personal",
            "subcategory":"Barber",
            "type":"Services"
        }
    ],
    "sg:phone":"+1 323 660 0500",
    "sg:postcode":"90027",
    "sg:province":"CA",
    "wof:name":"Lecamus Beau",
    "wof:placetype":"venue"
},
  "geometry": {"coordinates":[-118.287548,34.102892],"type":"Point"}
}