{
  "type": "Feature",
  "properties": {
    "iso:country":"US",
    "sg:address":"1301 Georgia St",
    "sg:city":"Vallejo",
    "sg:classifiers":[
        {
            "category":"Autos & Motor Vehicles",
            "subcategory":"Auto Supplies",
            "type":"Retail Goods"
        },
        {
            "category":"Retail",
            "subcategory":"Auto Repair",
            "type":"Services"
        }
    ],
    "sg:phone":"+1 707 643 2090",
    "sg:postcode":"94590",
    "sg:province":"CA",
    "sg:tags":[
        "wheel",
        "tire",
        "automobile",
        "accessory",
        "part",
        "brake"
    ],
    "wof:name":"Tire Tech",
    "wof:placetype":"venue"
},
  "geometry": {"coordinates":[-122.241508,38.100899],"type":"Point"}
}