{
  "type": "Feature",
  "properties": {
    "iso:country":"US",
    "sg:address":"736 Salem St",
    "sg:city":"Glendale",
    "sg:classifiers":[
        {
            "category":"Manufacturing",
            "subcategory":"Tools & Machinery",
            "type":"Manufacturing & Wholesale Goods"
        }
    ],
    "sg:phone":"+1 818 240 3913",
    "sg:postcode":"91203",
    "sg:province":"CA",
    "sg:tags":[
        "lighting",
        "fixture"
    ],
    "wof:name":"Lighting Specialist Inc",
    "wof:placetype":"venue"
},
  "geometry": {"coordinates":[-118.272666,34.148769],"type":"Point"}
}