{
  "type": "Feature",
  "properties": {
    "addr:full":"213 Sandy Beach Rd Vallejo CA 94590",
    "addr:housenumber":"213",
    "addr:postcode":"94590",
    "addr:street":"Sandy Beach Rd",
    "iso:country":"US",
    "sg:address":"213 Sandy Beach Rd",
    "sg:city":"Vallejo",
    "sg:classifiers":[
        {
            "category":"Local Transit",
            "type":"Transportation"
        }
    ],
    "sg:phone":"+1 707 642 7129",
    "sg:postcode":"94590",
    "sg:province":"CA",
    "sg:tags":[
        "passenger"
    ],
    "wof:name":"All Seasons Limousine",
    "wof:placetype":"venue"
},
  "geometry": {"coordinates":[-122.23728199999999,38.078227],"type":"Point"}
}