{
  "type": "Feature",
  "properties": {
    "addr:full":"2708 N Broadway Los Angeles CA 90031",
    "addr:housenumber":"2708",
    "addr:postcode":"90031",
    "addr:street":"N Broadway",
    "iso:country":"US",
    "sg:address":"2708 N Broadway",
    "sg:city":"Los Angeles",
    "sg:classifiers":[
        {
            "category":"Bakery",
            "type":"Food & Drink"
        }
    ],
    "sg:phone":"+1 323 225 2569",
    "sg:postcode":"90031",
    "sg:province":"CA",
    "wof:name":"Palace Bakery",
    "wof:placetype":"venue"
},
  "geometry": {"coordinates":[-118.21399700000001,34.073502],"type":"Point"}
}