{
  "type": "Feature",
  "properties": {
    "addr:full":"14249 Inglewood Ave Hawthorne CA 90250",
    "addr:housenumber":"14249",
    "addr:postcode":"90250",
    "addr:street":"Inglewood Ave",
    "iso:country":"US",
    "sg:address":"14249 Inglewood Ave",
    "sg:city":"Hawthorne",
    "sg:classifiers":[
        {
            "category":"Shopping",
            "subcategory":"Computers & Home Electronics",
            "type":"Retail Goods"
        }
    ],
    "sg:phone":"+1 310 679 5526",
    "sg:postcode":"90250",
    "sg:province":"CA",
    "sg:tags":[
        "television",
        "radio"
    ],
    "wof:name":"Pacific Television & Video",
    "wof:placetype":"venue"
},
  "geometry": {"coordinates":[-118.36134,33.902381],"type":"Point"}
}