{
  "type": "Feature",
  "properties": {
    "addr:full":"3440 Wilshire Blvd Los Angeles CA 90010",
    "addr:housenumber":"3440",
    "addr:postcode":"90010",
    "addr:street":"Wilshire Blvd",
    "iso:country":"US",
    "sg:address":"3440 Wilshire Blvd",
    "sg:city":"Los Angeles",
    "sg:classifiers":[
        {
            "category":"Professional",
            "subcategory":"Lawyer & Legal Services",
            "type":"Services"
        }
    ],
    "sg:phone":"+1 213 383 3031",
    "sg:postcode":"90010",
    "sg:province":"CA",
    "wof:name":"Kim Myron M Attorney At Law",
    "wof:placetype":"venue"
},
  "geometry": {"coordinates":[-118.299004,34.061699],"type":"Point"}
}