{
  "type": "Feature",
  "properties": {
    "addr:full":"9626 Brighton Way Beverly Hills CA 90210",
    "addr:housenumber":"9626",
    "addr:postcode":"90210",
    "addr:street":"Brighton Way",
    "iso:country":"US",
    "sg:address":"9626 Brighton Way",
    "sg:city":"Beverly Hills",
    "sg:classifiers":[
        {
            "category":"Shopping",
            "subcategory":"Clothing, Apparel, & Fashions",
            "type":"Retail Goods"
        }
    ],
    "sg:phone":"+1 310 278 1288",
    "sg:postcode":"90210",
    "sg:province":"CA",
    "wof:name":"Ambrosia By Wei Wei",
    "wof:placetype":"venue"
},
  "geometry": {"coordinates":[-118.404402,34.06814],"type":"Point"}
}