{
  "type": "Feature",
  "properties": {
    "addr:full":"17310 Hendry Dr Morgan Hill CA 95037",
    "addr:housenumber":"17310",
    "addr:postcode":"95037",
    "addr:street":"Hendry Dr",
    "iso:country":"US",
    "sg:address":"17310 Hendry Dr",
    "sg:city":"Morgan Hill",
    "sg:classifiers":[
        {
            "category":"Building & Trades",
            "subcategory":"Construction",
            "type":"Services"
        }
    ],
    "sg:phone":"+1 408 779 0814",
    "sg:postcode":"95037",
    "sg:province":"CA",
    "sg:tags":[
        "contractor"
    ],
    "wof:name":"Villanova Estates Inc",
    "wof:placetype":"venue"
},
  "geometry": {"coordinates":[-121.619743,37.143544],"type":"Point"}
}