{
  "type": "Feature",
  "properties": {
    "iso:country":"US",
    "sg:address":"830 S Hill Street",
    "sg:city":"Los Angeles",
    "sg:classifiers":[
        {
            "category":"Shopping",
            "subcategory":"Clothing, Apparel, & Fashions",
            "type":"Retail Goods"
        }
    ],
    "sg:phone":"+1 213 488 3328",
    "sg:postcode":"90014",
    "sg:province":"CA",
    "sg:tags":[
        "clothing",
        "women's"
    ],
    "wof:name":"Best One Collection",
    "wof:placetype":"venue"
},
  "geometry": {"coordinates":[-118.256182,34.044012],"type":"Point"}
}