{
  "type": "Feature",
  "properties": {
    "addr:full":"3505 Cam del Rio S San Diego CA 92108",
    "addr:housenumber":"3505",
    "addr:postcode":"92108",
    "addr:street":"Cam Del Rio S",
    "iso:country":"US",
    "sg:address":"3505 Cam del Rio S",
    "sg:city":"San Diego",
    "sg:classifiers":[
        {
            "category":"Real Estate",
            "subcategory":"Real Estate Agent",
            "type":"Services"
        }
    ],
    "sg:phone":"+1 619 582 3078",
    "sg:postcode":"92108",
    "sg:province":"CA",
    "sg:website":"www.sandiegohomesandloans.com",
    "wof:name":"Rescom Investments",
    "wof:placetype":"venue"
},
  "geometry": {"coordinates":[-117.11765,32.777804],"type":"Point"}
}