{
  "type": "Feature",
  "properties": {
    "addr:full":"5680 San Pablo Ave Oakland CA 94608",
    "addr:housenumber":"5680",
    "addr:postcode":"94608",
    "addr:street":"San Pablo Ave",
    "iso:country":"US",
    "sg:address":"5680 San Pablo Ave",
    "sg:city":"Oakland",
    "sg:classifiers":[
        {
            "category":"Arena",
            "subcategory":"Sports Club",
            "type":"Entertainment"
        }
    ],
    "sg:phone":"+1 510 428 0502",
    "sg:postcode":"94608",
    "sg:province":"CA",
    "sg:tags":[
        "martial art"
    ],
    "sg:website":"www.handtohandkajukenbo.com",
    "wof:name":"Hand To Hand Kajukenbo Self Defense Center",
    "wof:placetype":"venue"
},
  "geometry": {"coordinates":[-122.282681,37.840084],"type":"Point"}
}