{
  "type": "Feature",
  "properties": {
    "iso:country":"US",
    "sg:address":"845 E California Blvd",
    "sg:city":"Pasadena",
    "sg:classifiers":[
        {
            "category":"Bakery",
            "type":"Food & Drink"
        },
        {
            "category":"Food & Beverages",
            "subcategory":"Groceries & Convenience Stores",
            "type":"Retail Goods"
        }
    ],
    "sg:phone":"+1 626 449 3968",
    "sg:postcode":"91106",
    "sg:province":"CA",
    "wof:name":"Vons",
    "wof:placetype":"venue"
},
  "geometry": {"coordinates":[-118.133003,34.136002],"type":"Point"}
}