{
  "type": "Feature",
  "properties": {
    "iso:country":"US",
    "sg:address":"125 Ave Buena Ventura",
    "sg:city":"San Clemente",
    "sg:classifiers":[
        {
            "category":"Professional",
            "subcategory":"Art Services",
            "type":"Services"
        }
    ],
    "sg:phone":"+1 949 369 5262",
    "sg:postcode":"92672",
    "sg:province":"CA",
    "sg:tags":[
        "photographer"
    ],
    "wof:name":"Blue Water Photography",
    "wof:placetype":"venue"
},
  "geometry": {"coordinates":[-117.593614,33.403056],"type":"Point"}
}