{
  "type": "Feature",
  "properties": {
    "addr:full":"3436 N Verdugo Rd Ste 230 Glendale CA 91208",
    "addr:housenumber":"3436",
    "addr:postcode":"91208",
    "addr:street":"N Verdugo Rd Ste 230",
    "iso:country":"US",
    "sg:address":"3436 N Verdugo Rd Ste 230",
    "sg:city":"Glendale",
    "sg:classifiers":[
        {
            "category":"Banks & Credit Unions",
            "subcategory":"Investment Brokerage",
            "type":"Services"
        }
    ],
    "sg:phone":"+1 818 248 8874",
    "sg:postcode":"91208",
    "sg:province":"CA",
    "sg:tags":[
        "investing"
    ],
    "wof:name":"Hurley Wealth Management Group",
    "wof:placetype":"venue"
},
  "geometry": {"coordinates":[-118.227552,34.201143],"type":"Point"}
}