{
  "type": "Feature",
  "properties": {
    "addr:full":"893 Cheltenham Rd Santa Barbara CA 93105",
    "addr:housenumber":"893",
    "addr:postcode":"93105",
    "addr:street":"Cheltenham Rd",
    "iso:country":"US",
    "sg:address":"893 Cheltenham Rd",
    "sg:city":"Santa Barbara",
    "sg:classifiers":[
        {
            "category":"Professional",
            "type":"Services"
        }
    ],
    "sg:phone":"+1 805 685 9262",
    "sg:postcode":"93105",
    "sg:province":"CA",
    "wof:name":"Gregg & Kinsey Svc",
    "wof:placetype":"venue"
},
  "geometry": {"coordinates":[-119.720516,34.44767],"type":"Point"}
}