{
  "type": "Feature",
  "properties": {
    "iso:country":"US",
    "sg:address":"4019 Sebastopol Rd",
    "sg:city":"Santa Rosa",
    "sg:classifiers":[
        {
            "category":"Wholesale",
            "subcategory":"Durable Goods & Equipment",
            "type":"Manufacturing & Wholesale Goods"
        }
    ],
    "sg:phone":"+1 707 541 7021",
    "sg:postcode":"95407",
    "sg:province":"CA",
    "sg:tags":[
        "importer"
    ],
    "wof:name":"Del Rio Import",
    "wof:placetype":"venue"
},
  "geometry": {"coordinates":[-122.768294,38.424906],"type":"Point"}
}