{
  "type": "Feature",
  "properties": {
    "iso:country":"US",
    "sg:address":"4605 Barranca Pkwy",
    "sg:city":"Irvine",
    "sg:classifiers":[
        {
            "category":"Professional",
            "type":"Services"
        }
    ],
    "sg:phone":"+1 949 262 0106",
    "sg:postcode":"92604",
    "sg:province":"CA",
    "wof:name":"Daniel Craig",
    "wof:placetype":"venue"
},
  "geometry": {"coordinates":[-117.800026,33.678945],"type":"Point"}
}