{
  "type": "Feature",
  "properties": {
    "iso:country":"US",
    "sg:address":"5350 Franklin Blvd",
    "sg:city":"Sacramento",
    "sg:classifiers":[
        {
            "category":"Autos & Motor Vehicles",
            "subcategory":"Auto Supplies",
            "type":"Retail Goods"
        }
    ],
    "sg:phone":"+1 916 452 3660",
    "sg:postcode":"95820",
    "sg:province":"CA",
    "sg:tags":[
        "tire"
    ],
    "wof:name":"Jose's Used Tires",
    "wof:placetype":"venue"
},
  "geometry": {"coordinates":[-121.47271499999999,38.528543],"type":"Point"}
}