{
  "type": "Feature",
  "properties": {
    "iso:country":"US",
    "sg:address":"1233 W Channel Islands Blvd",
    "sg:city":"Oxnard",
    "sg:classifiers":[
        {
            "category":"Building & Trades",
            "subcategory":"Construction",
            "type":"Services"
        }
    ],
    "sg:phone":"+1 805 240 1695",
    "sg:postcode":"93033",
    "sg:province":"CA",
    "sg:tags":[
        "repairing",
        "remodeling",
        "contractor"
    ],
    "wof:name":"California Home Remodeling",
    "wof:placetype":"venue"
},
  "geometry": {"coordinates":[-119.191981,34.175693],"type":"Point"}
}