{
  "type": "Feature",
  "properties": {
    "addr:full":"16600 Harbor Blvd Fountain Valley CA 92708",
    "addr:housenumber":"16600",
    "addr:postcode":"92708",
    "addr:street":"Harbor Blvd",
    "iso:country":"US",
    "sg:address":"16600 Harbor Blvd",
    "sg:city":"Fountain Valley",
    "sg:classifiers":[
        {
            "category":"Professional",
            "type":"Services"
        }
    ],
    "sg:phone":"+1 714 531 3292",
    "sg:postcode":"92708",
    "sg:province":"CA",
    "wof:name":"Zeeko Inc",
    "wof:placetype":"venue"
},
  "geometry": {"coordinates":[-117.92073600000001,33.719939],"type":"Point"}
}