{
  "type": "Feature",
  "properties": {
    "addr:full":"43 N Villa St Porterville CA 93257",
    "addr:housenumber":"43",
    "addr:postcode":"93257",
    "addr:street":"N Villa St",
    "iso:country":"US",
    "sg:address":"43 N Villa St",
    "sg:city":"Porterville",
    "sg:classifiers":[
        {
            "category":"Retail",
            "subcategory":"Auto Repair",
            "type":"Services"
        }
    ],
    "sg:phone":"+1 559 784 2036",
    "sg:postcode":"93257",
    "sg:province":"CA",
    "sg:tags":[
        "wrecker"
    ],
    "wof:name":"Shorty's Towing",
    "wof:placetype":"venue"
},
  "geometry": {"coordinates":[-119.030721,36.068834],"type":"Point"}
}