{
  "type": "Feature",
  "properties": {
    "iso:country":"US",
    "sg:address":"1250 Grand Ave",
    "sg:city":"Arroyo Grande",
    "sg:classifiers":[
        {
            "category":"Wholesale",
            "subcategory":"Groceries",
            "type":"Manufacturing & Wholesale Goods"
        }
    ],
    "sg:phone":"+1 805 748 3872",
    "sg:postcode":"93420",
    "sg:province":"CA",
    "sg:tags":[
        "food",
        "organic",
        "consulting",
        "quality"
    ],
    "wof:name":"Health By Organics Family LLC",
    "wof:placetype":"venue"
},
  "geometry": {"coordinates":[-120.602814,35.120708],"type":"Point"}
}