{
  "type": "Feature",
  "properties": {
    "addr:full":"17234 Main St Hesperia CA 92345",
    "addr:housenumber":"17234",
    "addr:postcode":"92345",
    "addr:street":"Main St",
    "iso:country":"US",
    "sg:address":"17234 Main St",
    "sg:city":"Hesperia",
    "sg:classifiers":[
        {
            "category":"Organizations",
            "subcategory":"Religious Organization",
            "type":"Services"
        }
    ],
    "sg:phone":"+1 760 947 6621",
    "sg:postcode":"92345",
    "sg:province":"CA",
    "sg:tags":[
        "church"
    ],
    "wof:name":"Living Water Faith Ctr II",
    "wof:placetype":"venue"
},
  "geometry": {"coordinates":[-117.286768,34.419439],"type":"Point"}
}