{
  "type": "Feature",
  "properties": {
    "iso:country":"US",
    "sg:address":"17251 Regulus Dr",
    "sg:city":"Yorba Linda",
    "sg:classifiers":[
        {
            "category":"Manufacturing",
            "subcategory":"Tools & Machinery",
            "type":"Manufacturing & Wholesale Goods"
        }
    ],
    "sg:phone":"+1 714 996 3875",
    "sg:postcode":"92886",
    "sg:province":"CA",
    "sg:tags":[
        "instrument",
        "mfg"
    ],
    "wof:name":"Pencil Pull",
    "wof:placetype":"venue"
},
  "geometry": {"coordinates":[-117.832951,33.889939],"type":"Point"}
}