{
  "type": "Feature",
  "properties": {
    "iso:country":"US",
    "sg:address":"7013 Melrose Ave",
    "sg:city":"Los Angeles",
    "sg:classifiers":[
        {
            "category":"Restaurant",
            "type":"Food & Drink"
        }
    ],
    "sg:phone":"+1 323 934 6488",
    "sg:postcode":"90038",
    "sg:province":"CA",
    "sg:tags":[
        "indian"
    ],
    "sg:website":"www.anarkaliindianrestaurant.com/",
    "wof:name":"Anarkali Indian Restaurant",
    "wof:placetype":"venue"
},
  "geometry": {"coordinates":[-118.343278,34.08367],"type":"Point"}
}