{
  "type": "Feature",
  "properties": {
    "iso:country":"US",
    "sg:address":"1901 E Gage Ave",
    "sg:city":"Los Angeles",
    "sg:classifiers":[
        {
            "category":"Restaurant",
            "type":"Food & Drink"
        }
    ],
    "sg:phone":"+1 323 585 5757",
    "sg:postcode":"90001",
    "sg:province":"CA",
    "wof:name":"Tom's Burgers",
    "wof:placetype":"venue"
},
  "geometry": {"coordinates":[-118.23620099999999,33.98169],"type":"Point"}
}