{
  "type": "Feature",
  "properties": {
    "iso:country":"US",
    "sg:address":"10362 Wateridge Cir",
    "sg:city":"San Diego",
    "sg:classifiers":[
        {
            "category":"Retail",
            "subcategory":"Auto Repair",
            "type":"Services"
        }
    ],
    "sg:phone":"+1 858 699 2054",
    "sg:postcode":"92121",
    "sg:province":"CA",
    "sg:tags":[
        "body",
        "automobile",
        "painting"
    ],
    "wof:name":"Denttime",
    "wof:placetype":"venue"
},
  "geometry": {"coordinates":[-117.205127,32.899447],"type":"Point"}
}