{
  "type": "Feature",
  "properties": {
    "addr:full":"10654 Cedar Ave Bloomington CA 92316",
    "addr:housenumber":"10654",
    "addr:postcode":"92316",
    "addr:street":"Cedar Ave",
    "iso:country":"US",
    "sg:address":"10654 Cedar Ave",
    "sg:city":"Bloomington",
    "sg:classifiers":[
        {
            "category":"Shopping",
            "subcategory":"Florist",
            "type":"Retail Goods"
        }
    ],
    "sg:phone":"+1 909 875 2677",
    "sg:postcode":"92316",
    "sg:province":"CA",
    "wof:name":"Yazzlees Florist & Party Supl",
    "wof:placetype":"venue"
},
  "geometry": {"coordinates":[-117.396494,34.056634],"type":"Point"}
}