{
  "type": "Feature",
  "properties": {
    "addr:full":"2025 California Dr Vacaville CA 95687",
    "addr:housenumber":"2025",
    "addr:postcode":"95687",
    "addr:street":"California Dr",
    "iso:country":"US",
    "sg:address":"2025 California Dr",
    "sg:city":"Vacaville",
    "sg:classifiers":[
        {
            "category":"Professional",
            "type":"Services"
        }
    ],
    "sg:phone":"+1 707 448 4802",
    "sg:postcode":"95687",
    "sg:province":"CA",
    "wof:name":"Martin Monarrez",
    "wof:placetype":"venue"
},
  "geometry": {"coordinates":[-121.96920900000001,38.333367],"type":"Point"}
}