{
  "type": "Feature",
  "properties": {
    "iso:country":"US",
    "sg:address":"260 H Ave",
    "sg:city":"Coronado",
    "sg:classifiers":[
        {
            "category":"Banks & Credit Unions",
            "subcategory":"Bank",
            "type":"Services"
        }
    ],
    "sg:phone":"+1 858 457 4366",
    "sg:postcode":"92118",
    "sg:province":"CA",
    "sg:tags":[
        "broker",
        "mortgage"
    ],
    "wof:name":"Palpacific Realty & Finance",
    "wof:placetype":"venue"
},
  "geometry": {"coordinates":[-117.179281,32.698793],"type":"Point"}
}