{
  "type": "Feature",
  "properties": {
    "addr:full":"51080 Hillside Dr Oakhurst CA 93644",
    "addr:housenumber":"51080",
    "addr:postcode":"93644",
    "addr:street":"Hillside Dr",
    "iso:country":"US",
    "sg:address":"51080 Hillside Dr",
    "sg:city":"Oakhurst",
    "sg:classifiers":[
        {
            "category":"Utilities",
            "subcategory":"Water",
            "type":"Services"
        },
        {
            "category":"Building & Trades",
            "subcategory":"Plumbing",
            "type":"Services"
        },
        {
            "category":"Home & Garden",
            "subcategory":"Hardware",
            "type":"Retail Goods"
        }
    ],
    "sg:phone":"+1 559 683 7876",
    "sg:postcode":"93644",
    "sg:province":"CA",
    "sg:tags":[
        "plumber",
        "industrial",
        "filtration",
        "softening",
        "supply",
        "work",
        "purification",
        "equipment",
        "conditioning",
        "contractors-commercial"
    ],
    "sg:website":"http://www.problemwater.com",
    "wof:name":"Joe Stern Water Conditioning",
    "wof:placetype":"venue"
},
  "geometry": {"coordinates":[-119.61515,37.367647],"type":"Point"}
}