{
  "type": "Feature",
  "properties": {
    "iso:country":"US",
    "sg:address":"15810 Boyle Ave",
    "sg:city":"Fontana",
    "sg:classifiers":[
        {
            "category":"Freight",
            "type":"Transportation"
        }
    ],
    "sg:phone":"+1 909 357 0233",
    "sg:postcode":"92337",
    "sg:province":"CA",
    "sg:tags":[
        "terminal",
        "truck",
        "facility"
    ],
    "wof:name":"Truckers Express Inc",
    "wof:placetype":"venue"
},
  "geometry": {"coordinates":[-117.466452,34.06489],"type":"Point"}
}