{
  "type": "Feature",
  "properties": {
    "iso:country":"US",
    "sg:address":"1631 S Walker Ave",
    "sg:city":"San Pedro",
    "sg:classifiers":[
        {
            "category":"Professional",
            "type":"Services"
        }
    ],
    "sg:phone":"+1 310 832 2220",
    "sg:postcode":"90731",
    "sg:province":"CA",
    "wof:name":"Coresurf LLC",
    "wof:placetype":"venue"
},
  "geometry": {"coordinates":[-118.303471,33.729111],"type":"Point"}
}