{
  "type": "Feature",
  "properties": {
    "addr:full":"Lanai and Tully San Jose CA 95122",
    "addr:postcode":"95122",
    "iso:country":"US",
    "sg:address":"Lanai and Tully",
    "sg:city":"San Jose",
    "sg:classifiers":[
        {
            "category":"Restaurant",
            "type":"Food & Drink"
        },
        {
            "category":"Food Court",
            "type":"Food & Drink"
        }
    ],
    "sg:postcode":"95122",
    "sg:province":"CA",
    "sg:tags":[
        "mexican",
        "stand"
    ],
    "wof:name":"Los Jarritos",
    "wof:placetype":"venue"
},
  "geometry": {"coordinates":[-121.82900100000001,37.320373],"type":"Point"}
}