{
  "type": "Feature",
  "properties": {
    "addr:full":"15725 Hawthorne Blvd Lawndale CA 90260",
    "addr:housenumber":"15725",
    "addr:postcode":"ca 90260",
    "addr:street":"Hawthorne Blvd",
    "iso:country":"US",
    "sg:address":"15725 Hawthorne Blvd",
    "sg:city":"Lawndale",
    "sg:classifiers":[
        {
            "category":"Manufacturing",
            "subcategory":"Signs",
            "type":"Manufacturing & Wholesale Goods"
        }
    ],
    "sg:phone":"+1 310 644 9800",
    "sg:postcode":"90260",
    "sg:province":"CA",
    "sg:tags":[
        "specialty",
        "mfg"
    ],
    "wof:name":"Sherleon Signs",
    "wof:placetype":"venue"
},
  "geometry": {"coordinates":[-118.35244400000001,33.888925],"type":"Point"}
}