{
  "type": "Feature",
  "properties": {
    "addr:full":"46743 Fremont Blvd Fremont CA 94538",
    "addr:housenumber":"46743",
    "addr:postcode":"94538",
    "addr:street":"Fremont Blvd",
    "iso:country":"US",
    "sg:address":"46743 Fremont Blvd",
    "sg:city":"Fremont",
    "sg:classifiers":[
        {
            "category":"Professional",
            "subcategory":"Advertising",
            "type":"Services"
        }
    ],
    "sg:phone":"+1 510 498 1540",
    "sg:postcode":"94538",
    "sg:province":"CA",
    "sg:tags":[
        "distribution"
    ],
    "wof:name":"IMC Intertech",
    "wof:placetype":"venue"
},
  "geometry": {"coordinates":[-121.9452,37.480201],"type":"Point"}
}