{
  "type": "Feature",
  "properties": {
    "addr:full":"820 Kiely Blvd Santa Clara CA 95051",
    "addr:housenumber":"820",
    "addr:postcode":"95051",
    "addr:street":"Kiely Blvd",
    "iso:country":"US",
    "sg:address":"820 Kiely Blvd",
    "sg:city":"Santa Clara",
    "sg:classifiers":[
        {
            "category":"Education",
            "subcategory":"Preschool",
            "type":"Public Place"
        },
        {
            "category":"Education",
            "subcategory":"School",
            "type":"Public Place"
        },
        {
            "category":"Organizations",
            "subcategory":"Religious Organization",
            "type":"Services"
        }
    ],
    "sg:phone":"+1 408 244 9403",
    "sg:postcode":"95051",
    "sg:province":"CA",
    "sg:tags":[
        "elementary"
    ],
    "wof:name":"Tomorrow's Promise Christian School",
    "wof:placetype":"venue"
},
  "geometry": {"coordinates":[-121.97729099999999,37.339069],"type":"Point"}
}