{
  "type": "Feature",
  "properties": {
    "iso:country":"US",
    "sg:address":"205 Meiss Lake Rd",
    "sg:city":"Macdoel",
    "sg:classifiers":[
        {
            "category":"Freight",
            "type":"Transportation"
        }
    ],
    "sg:phone":"+1 530 398 4574",
    "sg:postcode":"96058",
    "sg:province":"CA",
    "sg:tags":[
        "facility",
        "fixed",
        "scale",
        "motor",
        "mfg"
    ],
    "wof:name":"Macdoel Scales & Fuel",
    "wof:placetype":"venue"
},
  "geometry": {"coordinates":[-122.00581,41.822433],"type":"Point"}
}