{
  "type": "Feature",
  "properties": {
    "iso:country":"US",
    "sg:address":"3880 S Bascom Ave",
    "sg:city":"San Jose",
    "sg:classifiers":[
        {
            "category":"Health Services",
            "subcategory":"Clinic",
            "type":"Services"
        }
    ],
    "sg:phone":"+1 408 559 9088",
    "sg:postcode":"95124",
    "sg:province":"CA",
    "sg:tags":[
        "counseling",
        "mental"
    ],
    "sg:website":"www.anxietytreatmentservices.com",
    "wof:name":"Anxiety Treatment Services",
    "wof:placetype":"venue"
},
  "geometry": {"coordinates":[-121.949997,37.256401],"type":"Point"}
}