{
  "type": "Feature",
  "properties": {
    "addr:full":"31 Twin Leaf Ct Sacramento CA 95838",
    "addr:housenumber":"31",
    "addr:postcode":"95838",
    "addr:street":"Twin Leaf Ct",
    "iso:country":"US",
    "sg:address":"31 Twin Leaf Ct",
    "sg:city":"Sacramento",
    "sg:classifiers":[
        {
            "category":"Place Of Worship",
            "subcategory":"Church",
            "type":"Public Place"
        },
        {
            "category":"Place Of Worship",
            "type":"Public Place"
        }
    ],
    "sg:phone":"+1 916 929 2056",
    "sg:postcode":"95838",
    "sg:province":"CA",
    "sg:tags":[
        "churches-apostolic",
        "churches-pentecostal-apostolic"
    ],
    "wof:name":"Apostolic Faith Church",
    "wof:placetype":"venue"
},
  "geometry": {"coordinates":[-121.460058,38.65547],"type":"Point"}
}