{
  "type": "Feature",
  "properties": {
    "addr:full":"525 N Andreason Dr Escondido CA 92029",
    "addr:housenumber":"525",
    "addr:postcode":"92029",
    "addr:street":"N Andreason Dr",
    "iso:country":"US",
    "sg:address":"525 N Andreason Dr",
    "sg:city":"Escondido",
    "sg:classifiers":[
        {
            "category":"Manufacturing",
            "subcategory":"Printing",
            "type":"Manufacturing & Wholesale Goods"
        }
    ],
    "sg:phone":"+1 760 480 2768",
    "sg:postcode":"92029",
    "sg:province":"CA",
    "sg:tags":[
        "printer"
    ],
    "wof:name":"Michael Printing",
    "wof:placetype":"venue"
},
  "geometry": {"coordinates":[-117.108186,33.120968],"type":"Point"}
}