{
  "type": "Feature",
  "properties": {
    "addr:full":"7603 Pacific Blvd Huntington Park CA 90255",
    "addr:housenumber":"7603",
    "addr:postcode":"90255",
    "addr:street":"Pacific Blvd;Park",
    "iso:country":"US",
    "sg:address":"7603 Pacific Blvd",
    "sg:city":"Huntington Park",
    "sg:classifiers":[
        {
            "category":"Home & Garden",
            "subcategory":"Furniture",
            "type":"Retail Goods"
        }
    ],
    "sg:phone":"+1 323 587 3940",
    "sg:postcode":"90255",
    "sg:province":"CA",
    "sg:tags":[
        "store"
    ],
    "wof:name":"Muebles De Occidente",
    "wof:placetype":"venue"
},
  "geometry": {"coordinates":[-118.224998,33.9706],"type":"Point"}
}