{
  "type": "Feature",
  "properties": {
    "addr:full":"751 Laurel St San Carlos CA 94070",
    "addr:housenumber":"751",
    "addr:postcode":"94070",
    "addr:street":"Laurel St",
    "iso:country":"US",
    "sg:address":"751 Laurel St",
    "sg:city":"San Carlos",
    "sg:classifiers":[
        {
            "category":"Freight",
            "type":"Transportation"
        }
    ],
    "sg:phone":"+1 650 366 8040",
    "sg:postcode":"94070",
    "sg:province":"CA",
    "sg:tags":[
        "trucking"
    ],
    "sg:website":"www.shadeconstruction.com",
    "wof:name":"Shade Construction & Engrng",
    "wof:placetype":"venue"
},
  "geometry": {"coordinates":[-122.25863200000001,37.504555],"type":"Point"}
}