{
  "type": "Feature",
  "properties": {
    "iso:country":"US",
    "sg:address":"1936 State Rte 66",
    "sg:city":"Glendora",
    "sg:classifiers":[
        {
            "category":"Shopping",
            "subcategory":"Used Merchandise",
            "type":"Retail Goods"
        }
    ],
    "sg:phone":"+1 626 335 4468",
    "sg:postcode":"91740",
    "sg:province":"CA",
    "sg:tags":[
        "shop",
        "thrift"
    ],
    "wof:name":"Goodwill Store & Donations",
    "wof:placetype":"venue"
},
  "geometry": {"coordinates":[-117.827144,34.128086],"type":"Point"}
}