{
  "type": "Feature",
  "properties": {
    "addr:full":"5403 Canehill Ave Lakewood CA 90713",
    "addr:housenumber":"5403",
    "addr:postcode":"90713",
    "addr:street":"Canehill Ave",
    "iso:country":"US",
    "sg:address":"5403 Canehill Ave",
    "sg:city":"Lakewood",
    "sg:classifiers":[
        {
            "category":"Banks & Credit Unions",
            "subcategory":"Investment Brokerage",
            "type":"Services"
        }
    ],
    "sg:phone":"+1 562 867 1314",
    "sg:postcode":"90713",
    "sg:province":"CA",
    "sg:tags":[
        "trust"
    ],
    "wof:name":"Williams Trust",
    "wof:placetype":"venue"
},
  "geometry": {"coordinates":[-118.11103300000001,33.855709],"type":"Point"}
}