{
  "type": "Feature",
  "properties": {
    "iso:country":"US",
    "sg:address":"18403 Moss Rd",
    "sg:city":"Riverside",
    "sg:classifiers":[
        {
            "category":"Freight",
            "type":"Transportation"
        }
    ],
    "sg:phone":"+1 951 789 1063",
    "sg:postcode":"92508",
    "sg:province":"CA",
    "sg:tags":[
        "trucking"
    ],
    "wof:name":"Alvarado Trucking Inc",
    "wof:placetype":"venue"
},
  "geometry": {"coordinates":[-117.34411900000001,33.913802],"type":"Point"}
}