{
  "type": "Feature",
  "properties": {
    "addr:full":"1816 Belcroft Ave South El Monte CA 91733",
    "addr:housenumber":"1816",
    "addr:postcode":"91733",
    "addr:street":"Belcroft Ave",
    "iso:country":"US",
    "sg:address":"1816 Belcroft Ave",
    "sg:city":"South El Monte",
    "sg:classifiers":[
        {
            "category":"Home & Garden",
            "subcategory":"Building Materials",
            "type":"Retail Goods"
        }
    ],
    "sg:phone":"+1 626 453 3582",
    "sg:postcode":"91733",
    "sg:province":"CA",
    "wof:name":"JCH Enterprises Inc",
    "wof:placetype":"venue"
},
  "geometry": {"coordinates":[-118.032732,34.045136],"type":"Point"}
}