{
  "type": "Feature",
  "properties": {
    "addr:full":"4716 Ceasar Chavez Ave Los Angeles CA 90189",
    "addr:housenumber":"4716",
    "addr:postcode":"90189",
    "addr:street":"Ceasar Chavez Ave",
    "iso:country":"US",
    "sg:address":"4716 Ceasar Chavez Ave",
    "sg:city":"Los Angeles",
    "sg:classifiers":[
        {
            "category":"Government",
            "subcategory":"City Hall",
            "type":"Public Place"
        },
        {
            "category":"Professional",
            "type":"Services"
        }
    ],
    "sg:postcode":"90189",
    "sg:province":"CA",
    "sg:tags":[
        "planning",
        "event"
    ],
    "wof:name":"Hall of Records",
    "wof:placetype":"venue"
},
  "geometry": {"coordinates":[-118.164259,34.04059],"type":"Point"}
}