{
  "type": "Feature",
  "properties": {
    "addr:full":"2346 Westwood Blvd Ste 2 Los Angeles CA 90064",
    "addr:housenumber":"2346",
    "addr:postcode":"90064",
    "addr:street":"Westwood Blvd Ste 2",
    "iso:country":"US",
    "sg:address":"2346 Westwood Blvd Ste 2",
    "sg:city":"Los Angeles",
    "sg:classifiers":[
        {
            "category":"Personal",
            "subcategory":"Beauty Salon",
            "type":"Services"
        }
    ],
    "sg:phone":"+1 310 474 6777",
    "sg:postcode":"90064",
    "sg:province":"CA",
    "sg:tags":[
        "hair"
    ],
    "sg:website":"www.mdhairdesign.com",
    "wof:name":"MD Hair Design & Replacement",
    "wof:placetype":"venue"
},
  "geometry": {"coordinates":[-118.42931799999999,34.041586],"type":"Point"}
}