{
  "type": "Feature",
  "properties": {
    "addr:full":"1351 Pacheco Pass Hwy Gilroy CA 95020",
    "addr:housenumber":"1351",
    "addr:postcode":"95020",
    "addr:street":"Pacheco Pass Hwy",
    "iso:country":"US",
    "sg:address":"1351 Pacheco Pass Hwy",
    "sg:city":"Gilroy",
    "sg:classifiers":[
        {
            "category":"Professional",
            "type":"Services"
        }
    ],
    "sg:phone":"+1 408 842 4244",
    "sg:postcode":"95020",
    "sg:province":"CA",
    "sg:tags":[
        "establishment"
    ],
    "wof:name":"Ram Mobile Data",
    "wof:placetype":"venue"
},
  "geometry": {"coordinates":[-121.539458,37.003259],"type":"Point"}
}