{
  "type": "Feature",
  "properties": {
    "iso:country":"US",
    "sg:address":"205 S Broadway",
    "sg:city":"Los Angeles",
    "sg:classifiers":[
        {
            "category":"Building & Trades",
            "subcategory":"Construction",
            "type":"Services"
        }
    ],
    "sg:phone":"+1 213 972 0882",
    "sg:postcode":"90012",
    "sg:province":"CA",
    "sg:tags":[
        "contractor"
    ],
    "sg:website":"www.titlecourt.com",
    "wof:name":"Permits Etc",
    "wof:placetype":"venue"
},
  "geometry": {"coordinates":[-118.248031,34.051066],"type":"Point"}
}