{
  "type": "Feature",
  "properties": {
    "iso:country":"US",
    "sg:address":"5234 Frost Ave",
    "sg:city":"Carlsbad",
    "sg:classifiers":[
        {
            "category":"Professional",
            "subcategory":"Engineering",
            "type":"Services"
        }
    ],
    "sg:phone":"+1 760 931 6606",
    "sg:postcode":"92008",
    "sg:province":"CA",
    "sg:tags":[
        "engineer"
    ],
    "wof:name":"Perkin Elmer Inc",
    "wof:placetype":"venue"
},
  "geometry": {"coordinates":[-117.292404,33.145619],"type":"Point"}
}