{
  "type": "Feature",
  "properties": {
    "addr:full":"5993 Magnolia Ave Riverside CA 92506",
    "addr:housenumber":"5993",
    "addr:postcode":"92506",
    "addr:street":"Magnolia Ave",
    "iso:country":"US",
    "sg:address":"5993 Magnolia Ave",
    "sg:city":"Riverside",
    "sg:classifiers":[
        {
            "category":"Autos & Motor Vehicles",
            "subcategory":"Auto Supplies",
            "type":"Retail Goods"
        }
    ],
    "sg:phone":"+1 951 682 0310",
    "sg:postcode":"92506",
    "sg:province":"CA",
    "sg:tags":[
        "tire"
    ],
    "wof:name":"Bob's Auto Svc",
    "wof:placetype":"venue"
},
  "geometry": {"coordinates":[-117.391446,33.961549],"type":"Point"}
}