{
  "type": "Feature",
  "properties": {
    "iso:country":"US",
    "sg:address":"807 W Laurel Ave",
    "sg:city":"Lompoc",
    "sg:classifiers":[
        {
            "category":"Shopping",
            "subcategory":"Shoes",
            "type":"Retail Goods"
        }
    ],
    "sg:phone":"+1 805 735 7666",
    "sg:postcode":"93436",
    "sg:province":"CA",
    "sg:tags":[
        "boot"
    ],
    "wof:name":"O K Maguey",
    "wof:placetype":"venue"
},
  "geometry": {"coordinates":[-120.46686099999999,34.643968],"type":"Point"}
}