{
  "type": "Feature",
  "properties": {
    "addr:full":"1940 University Ave Berkeley CA 94705",
    "addr:housenumber":"1940",
    "addr:postcode":"94705",
    "addr:street":"University Ave",
    "iso:country":"US",
    "sg:address":"1940 University Ave",
    "sg:city":"Berkeley",
    "sg:classifiers":[
        {
            "category":"Sports & Exercise",
            "subcategory":"Gym",
            "type":"Entertainment"
        },
        {
            "category":"Health Services",
            "subcategory":"Health Practitioner",
            "type":"Services"
        }
    ],
    "sg:phone":"+1 510 965 5733",
    "sg:postcode":"94705",
    "sg:province":"CA",
    "sg:tags":[
        "pilate",
        "therapy",
        "physical"
    ],
    "sg:website":"www.reformyourbodypilates.com",
    "wof:name":"Reform Your Body Pilates",
    "wof:placetype":"venue"
},
  "geometry": {"coordinates":[-122.271914,37.871031],"type":"Point"}
}