{
  "type": "Feature",
  "properties": {
    "iso:country":"US",
    "sg:address":"500 N 1st Ave",
    "sg:city":"Arcadia",
    "sg:classifiers":[
        {
            "category":"Building & Trades",
            "subcategory":"Cleaning & Sanitation",
            "type":"Services"
        },
        {
            "category":"Personal",
            "type":"Services"
        }
    ],
    "sg:phone":"+1 626 821 8626",
    "sg:postcode":"91006",
    "sg:province":"CA",
    "sg:tags":[
        "maids'",
        "house",
        "contractor",
        "cleaning-industrial",
        "butlers'",
        "janitorial"
    ],
    "wof:name":"Dana's Housekeeping",
    "wof:placetype":"venue"
},
  "geometry": {"coordinates":[-118.028442,34.145538],"type":"Point"}
}