{
  "type": "Feature",
  "properties": {
    "addr:full":"31097 Wild Oak Dr Running Springs CA 92382",
    "addr:housenumber":"31097",
    "addr:postcode":"92382",
    "addr:street":"Wild Oak Dr",
    "iso:country":"US",
    "sg:address":"31097 Wild Oak Dr",
    "sg:city":"Running Springs",
    "sg:classifiers":[
        {
            "category":"Professional",
            "subcategory":"Art Services",
            "type":"Services"
        }
    ],
    "sg:phone":"+1 909 867 9274",
    "sg:postcode":"92382",
    "sg:province":"CA",
    "sg:tags":[
        "graphic",
        "designer"
    ],
    "wof:name":"Scullin Images",
    "wof:placetype":"venue"
},
  "geometry": {"coordinates":[-117.126074,34.214141],"type":"Point"}
}