{
  "type": "Feature",
  "properties": {
    "addr:full":"503 W Bardsley Ave Tulare CA 93274",
    "addr:housenumber":"503",
    "addr:postcode":"93274",
    "addr:street":"W Bardsley Ave",
    "iso:country":"US",
    "sg:address":"503 W Bardsley Ave",
    "sg:city":"Tulare",
    "sg:classifiers":[
        {
            "category":"Food & Beverages",
            "subcategory":"Groceries & Convenience Stores",
            "type":"Retail Goods"
        }
    ],
    "sg:phone":"+1 559 687 9293",
    "sg:postcode":"93274",
    "sg:province":"CA",
    "sg:tags":[
        "grocer"
    ],
    "wof:name":"Super Stop Foodmart",
    "wof:placetype":"venue"
},
  "geometry": {"coordinates":[-119.357777,36.196381],"type":"Point"}
}