{
  "type": "Feature",
  "properties": {
    "iso:country":"US",
    "sg:address":"6513 University Ave",
    "sg:city":"San Diego",
    "sg:classifiers":[
        {
            "category":"Restaurant",
            "type":"Food & Drink"
        }
    ],
    "sg:phone":"+1 619 286 3200",
    "sg:postcode":"92115",
    "sg:province":"CA",
    "sg:tags":[
        "mediterranean",
        "african"
    ],
    "wof:name":"Mim's Grill",
    "wof:placetype":"venue"
},
  "geometry": {"coordinates":[-117.055319,32.755319],"type":"Point"}
}