{
  "type": "Feature",
  "properties": {
    "addr:full":"222 Mason St San Francisco CA 94102",
    "addr:housenumber":"222",
    "addr:postcode":"94102",
    "addr:street":"Mason St",
    "iso:country":"US",
    "sg:address":"222 Mason St",
    "sg:city":"San Francisco",
    "sg:classifiers":[
        {
            "category":"Professional",
            "subcategory":"Management & Consulting",
            "type":"Services"
        }
    ],
    "sg:phone":"+1 415 398 0232",
    "sg:postcode":"94102",
    "sg:province":"CA",
    "sg:tags":[
        "development",
        "industrial"
    ],
    "wof:name":"Tak Development Inc",
    "wof:placetype":"venue"
},
  "geometry": {"coordinates":[-122.409576,37.786008],"type":"Point"}
}