{
  "type": "Feature",
  "properties": {
    "iso:country":"US",
    "sg:address":"3633 Seaport Blvd Ste A",
    "sg:city":"Sacramento",
    "sg:classifiers":[
        {
            "category":"Shopping",
            "subcategory":"Party Supplies",
            "type":"Retail Goods"
        },
        {
            "category":"Personal",
            "type":"Services"
        }
    ],
    "sg:phone":"+1 916 371 8500",
    "sg:postcode":"95814",
    "sg:province":"CA",
    "sg:tags":[
        "planning",
        "event"
    ],
    "sg:website":"www.madeshade.com",
    "wof:name":"Made In the Shade Tent Rentals",
    "wof:placetype":"venue"
},
  "geometry": {"coordinates":[-121.566148,38.566456],"type":"Point"}
}