{
  "type": "Feature",
  "properties": {
    "addr:full":"715 Hall Ave Corcoran CA 93212",
    "addr:housenumber":"715",
    "addr:postcode":"93212",
    "addr:street":"Hall Ave",
    "iso:country":"US",
    "sg:address":"715 Hall Ave",
    "sg:city":"Corcoran",
    "sg:classifiers":[
        {
            "category":"Building & Trades",
            "subcategory":"Plumbing",
            "type":"Services"
        }
    ],
    "sg:phone":"+1 559 992 2605",
    "sg:postcode":"93212",
    "sg:province":"CA",
    "sg:tags":[
        "plumbing",
        "contractor"
    ],
    "wof:name":"Nolan's Plumbing Repair",
    "wof:placetype":"venue"
},
  "geometry": {"coordinates":[-119.556853,36.095204],"type":"Point"}
}