{
  "type": "Feature",
  "properties": {
    "addr:full":"2135 Armory Dr Santa Rosa CA 95401",
    "addr:housenumber":"2135",
    "addr:postcode":"95401",
    "addr:street":"Armory Dr",
    "iso:country":"US",
    "sg:address":"2135 Armory Dr",
    "sg:city":"Santa Rosa",
    "sg:classifiers":[
        {
            "category":"Health Services",
            "subcategory":"Chiropractor",
            "type":"Services"
        }
    ],
    "sg:phone":"+1 707 575 1700",
    "sg:postcode":"95401",
    "sg:province":"CA",
    "wof:name":"Moore Chiropractic Offices",
    "wof:placetype":"venue"
},
  "geometry": {"coordinates":[-122.725696,38.458516],"type":"Point"}
}