{
  "type": "Feature",
  "properties": {
    "iso:country":"US",
    "sg:address":"12027 Ventura Blvd",
    "sg:city":"Studio City",
    "sg:classifiers":[
        {
            "category":"Personal",
            "subcategory":"Psychics & Astrologers",
            "type":"Services"
        }
    ],
    "sg:phone":"+1 818 508 6373",
    "sg:postcode":"91604",
    "sg:province":"CA",
    "sg:website":"www.thestudiocitypsychic.com/",
    "wof:name":"The Studio City Psychic",
    "wof:placetype":"venue"
},
  "geometry": {"coordinates":[-118.394291,34.143669],"type":"Point"}
}