{
  "type": "Feature",
  "properties": {
    "addr:full":"22777 Lyons Ave Ste 213D Newhall CA 91321",
    "addr:housenumber":"22777",
    "addr:postcode":"91321",
    "addr:street":"Lyons Ave Ste 213D",
    "iso:country":"US",
    "sg:address":"22777 Lyons Ave Ste 213D",
    "sg:city":"Newhall",
    "sg:classifiers":[
        {
            "category":"Building & Trades",
            "subcategory":"Pest Control",
            "type":"Services"
        }
    ],
    "sg:phone":"+1 818 700 1530",
    "sg:postcode":"91321",
    "sg:province":"CA",
    "wof:name":"Our Town Pest Control Co",
    "wof:placetype":"venue"
},
  "geometry": {"coordinates":[-118.519997,34.383598],"type":"Point"}
}