{
  "type": "Feature",
  "properties": {
    "addr:full":"100 S Citrus Ave West Covina CA 91791",
    "addr:housenumber":"100",
    "addr:postcode":"91791",
    "addr:street":"S Citrus Ave",
    "iso:country":"US",
    "sg:address":"100 S Citrus Ave",
    "sg:city":"West Covina",
    "sg:classifiers":[
        {
            "category":"Social Services",
            "subcategory":"Child Care",
            "type":"Services"
        }
    ],
    "sg:phone":"+1 626 967 7848",
    "sg:postcode":"91791",
    "sg:province":"CA",
    "sg:website":"www.optionscc.com",
    "wof:name":"Options",
    "wof:placetype":"venue"
},
  "geometry": {"coordinates":[-117.890085,34.071416],"type":"Point"}
}