{
  "type": "Feature",
  "properties": {
    "iso:country":"US",
    "sg:address":"1498 Solano Avenue",
    "sg:city":"Albany",
    "sg:classifiers":[
        {
            "category":"Health Services",
            "subcategory":"Doctor",
            "type":"Services"
        }
    ],
    "sg:phone":"+1 510 528 5400",
    "sg:postcode":"94706",
    "sg:province":"CA",
    "wof:name":"Bay Area Mental Health Associates",
    "wof:placetype":"venue"
},
  "geometry": {"coordinates":[-122.28800200000001,37.8908],"type":"Point"}
}