{
  "type": "Feature",
  "properties": {
    "addr:full":"535 Sebastopol Rd Santa Rosa CA 95407",
    "addr:housenumber":"535",
    "addr:postcode":"95407",
    "addr:street":"Sebastopol Rd",
    "iso:country":"US",
    "sg:address":"535 Sebastopol Rd",
    "sg:city":"Santa Rosa",
    "sg:classifiers":[
        {
            "category":"Building & Trades",
            "subcategory":"Construction",
            "type":"Services"
        }
    ],
    "sg:phone":"+1 707 573 4753",
    "sg:postcode":"95407",
    "sg:province":"CA",
    "sg:tags":[
        "windows",
        "shower",
        "door",
        "mirror"
    ],
    "wof:name":"Performance Glass",
    "wof:placetype":"venue"
},
  "geometry": {"coordinates":[-122.725469,38.430634],"type":"Point"}
}