{
  "type": "Feature",
  "properties": {
    "iso:country":"US",
    "sg:address":"336 Broadway",
    "sg:city":"El Cajon",
    "sg:classifiers":[
        {
            "category":"Banks & Credit Unions",
            "subcategory":"Bank",
            "type":"Services"
        }
    ],
    "sg:phone":"+1 619 593 4123",
    "sg:postcode":"92021",
    "sg:province":"CA",
    "sg:tags":[
        "cashing",
        "check"
    ],
    "wof:name":"Check 'n Go",
    "wof:placetype":"venue"
},
  "geometry": {"coordinates":[-116.959604,32.807756],"type":"Point"}
}