{
  "type": "Feature",
  "properties": {
    "addr:full":"4814 Firestone Boulevard South Gate CA 90280",
    "addr:housenumber":"4814",
    "addr:postcode":"90280",
    "addr:street":"Firestone Boulevard;Gate",
    "iso:country":"US",
    "sg:address":"4814 Firestone Boulevard",
    "sg:city":"South Gate",
    "sg:classifiers":[
        {
            "category":"Building & Trades",
            "subcategory":"Construction",
            "type":"Services"
        }
    ],
    "sg:phone":"+1 323 835 0510",
    "sg:postcode":"90280",
    "sg:province":"CA",
    "sg:tags":[
        "contractor"
    ],
    "wof:name":"Arce Martha",
    "wof:placetype":"venue"
},
  "geometry": {"coordinates":[-118.184465,33.951896],"type":"Point"}
}