{
  "type": "Feature",
  "properties": {
    "iso:country":"US",
    "sg:address":"1304 Castro St Suite C",
    "sg:city":"San Francisco",
    "sg:classifiers":[
        {
            "category":"Health Services",
            "subcategory":"Clinic",
            "type":"Services"
        }
    ],
    "sg:phone":"+1 415 265 3365",
    "sg:postcode":"94114",
    "sg:province":"CA",
    "sg:tags":[
        "counseling",
        "mental"
    ],
    "sg:website":"sharonrafferty.com",
    "wof:name":"Sharon Rafferty PhD Clinical Psychologist",
    "wof:placetype":"venue"
},
  "geometry": {"coordinates":[-122.434106,37.751218],"type":"Point"}
}