{
  "type": "Feature",
  "properties": {
    "iso:country":"US",
    "sg:address":"800 12th St",
    "sg:city":"Paso Robles",
    "sg:classifiers":[
        {
            "category":"Social Services",
            "type":"Services"
        }
    ],
    "sg:phone":"+1 805 238 4996",
    "sg:postcode":"93446",
    "sg:province":"CA",
    "sg:tags":[
        "organization",
        "welfare"
    ],
    "wof:name":"Pasa Robles Historical Society",
    "wof:placetype":"venue"
},
  "geometry": {"coordinates":[-120.688187,35.626858],"type":"Point"}
}