{
  "type": "Feature",
  "properties": {
    "iso:country":"US",
    "sg:address":"333 Ponoma St",
    "sg:city":"Port Hueneme",
    "sg:classifiers":[
        {
            "category":"Railroad",
            "type":"Transportation"
        }
    ],
    "sg:phone":"+1 805 488 6586",
    "sg:postcode":"93041",
    "sg:province":"CA",
    "sg:tags":[
        "operator",
        "line"
    ],
    "wof:name":"Ventura County Railroad Co",
    "wof:placetype":"venue"
},
  "geometry": {"coordinates":[-119.200115,34.151168],"type":"Point"}
}