{
  "type": "Feature",
  "properties": {
    "iso:country":"US",
    "sg:address":"753 S Spring St",
    "sg:city":"Los Angeles",
    "sg:classifiers":[
        {
            "category":"Recreation",
            "subcategory":"Dance Hall",
            "type":"Entertainment"
        }
    ],
    "sg:phone":"+1 213 627 6277",
    "sg:postcode":"90014",
    "sg:province":"CA",
    "sg:tags":[
        "club"
    ],
    "sg:website":"www.740LA.com",
    "wof:name":"Club 740",
    "wof:placetype":"venue"
},
  "geometry": {"coordinates":[-118.253832,34.043485],"type":"Point"}
}