{
  "type": "Feature",
  "properties": {
    "iso:country":"US",
    "sg:address":"1440 Camino Del Mar",
    "sg:city":"Del Mar",
    "sg:classifiers":[
        {
            "category":"Shopping",
            "subcategory":"Books",
            "type":"Retail Goods"
        }
    ],
    "sg:phone":"+1 858 755 4254",
    "sg:postcode":"92014",
    "sg:province":"CA",
    "sg:tags":[
        "bookstore"
    ],
    "wof:name":"Earthsong Book Store Inc",
    "wof:placetype":"venue"
},
  "geometry": {"coordinates":[-117.26532,32.959113],"type":"Point"}
}