{
  "type": "Feature",
  "properties": {
    "addr:full":"5655 College Ave Ste 312 Oakland CA 94618",
    "addr:housenumber":"5655",
    "addr:postcode":"94618",
    "addr:street":"College Ave Ste 312",
    "iso:country":"US",
    "sg:address":"5655 College Ave Ste 312",
    "sg:city":"Oakland",
    "sg:classifiers":[
        {
            "category":"Health Services",
            "subcategory":"Dentist",
            "type":"Services"
        }
    ],
    "sg:phone":"+1 510 653 6677",
    "sg:postcode":"94618",
    "sg:province":"CA",
    "sg:website":"www.rockdent.com",
    "wof:name":"Rockridge Dental",
    "wof:placetype":"venue"
},
  "geometry": {"coordinates":[-122.252827,37.84461],"type":"Point"}
}