{
  "type": "Feature",
  "properties": {
    "iso:country":"US",
    "sg:address":"8056 Telegraph Rd",
    "sg:city":"Downey",
    "sg:classifiers":[
        {
            "category":"Banks & Credit Unions",
            "subcategory":"Financial Services",
            "type":"Services"
        }
    ],
    "sg:phone":"+1 562 928 6160",
    "sg:postcode":"90240",
    "sg:province":"CA",
    "sg:tags":[
        "broker",
        "mortgage"
    ],
    "wof:name":"Infinity Mortgage",
    "wof:placetype":"venue"
},
  "geometry": {"coordinates":[-118.119046,33.970453],"type":"Point"}
}