{
  "type": "Feature",
  "properties": {
    "iso:country":"US",
    "sg:address":"1258 Stabler Ln",
    "sg:city":"Yuba City",
    "sg:classifiers":[
        {
            "category":"Travel",
            "subcategory":"Travel Agent",
            "type":"Entertainment"
        }
    ],
    "sg:phone":"+1 530 673 2929",
    "sg:postcode":"95993",
    "sg:province":"CA",
    "sg:tags":[
        "agency",
        "bureau"
    ],
    "wof:name":"Travel Network",
    "wof:placetype":"venue"
},
  "geometry": {"coordinates":[-121.644031,39.146077],"type":"Point"}
}