{
  "type": "Feature",
  "properties": {
    "addr:full":"13826 La Pat Place Westminster CA 92683",
    "addr:housenumber":"13826",
    "addr:postcode":"92683",
    "addr:street":"La Pat Place",
    "iso:country":"US",
    "sg:address":"13826 La Pat Place",
    "sg:city":"Westminster",
    "sg:classifiers":[
        {
            "category":"Real Estate",
            "subcategory":"Real Estate Operator",
            "type":"Services"
        }
    ],
    "sg:phone":"+1 714 903 5328",
    "sg:postcode":"92683",
    "sg:province":"CA",
    "sg:tags":[
        "apartment"
    ],
    "wof:name":"Tenant Services",
    "wof:placetype":"venue"
},
  "geometry": {"coordinates":[-118.014797,33.761404],"type":"Point"}
}