{
  "type": "Feature",
  "properties": {
    "iso:country":"US",
    "sg:address":"122 S Catalina Ave",
    "sg:city":"Redondo Beach",
    "sg:classifiers":[
        {
            "category":"Professional",
            "subcategory":"Computer Services",
            "type":"Services"
        }
    ],
    "sg:phone":"+1 310 406 8690",
    "sg:postcode":"90277",
    "sg:province":"CA",
    "sg:tags":[
        "website",
        "design"
    ],
    "sg:website":"www.bitsmediagroup.com",
    "wof:name":"Bits Media Group Inc",
    "wof:placetype":"venue"
},
  "geometry": {"coordinates":[-118.388143,33.840468],"type":"Point"}
}