{
  "type": "Feature",
  "properties": {
    "iso:country":"US",
    "sg:address":"1044 Revere Ave Ste B42",
    "sg:city":"San Francisco",
    "sg:classifiers":[
        {
            "category":"Retail",
            "subcategory":"Repair Shop",
            "type":"Services"
        }
    ],
    "sg:phone":"+1 415 595 2187",
    "sg:postcode":"94124",
    "sg:province":"CA",
    "sg:tags":[
        "reupholstery",
        "furniture"
    ],
    "wof:name":"Art-Tistic Interiors by Rene Caraballo",
    "wof:placetype":"venue"
},
  "geometry": {"coordinates":[-122.3798,37.725907],"type":"Point"}
}