{
  "type": "Feature",
  "properties": {
    "addr:full":"441 Irving St San Francisco CA 94122",
    "addr:housenumber":"441",
    "addr:postcode":"94122",
    "addr:street":"Irving St",
    "iso:country":"US",
    "sg:address":"441 Irving St",
    "sg:city":"San Francisco",
    "sg:classifiers":[
        {
            "category":"Travel",
            "subcategory":"Travel Agent",
            "type":"Entertainment"
        }
    ],
    "sg:phone":"+1 415 753 1400",
    "sg:postcode":"94122",
    "sg:province":"CA",
    "sg:tags":[
        "agency"
    ],
    "wof:name":"Assured Travel Services II",
    "wof:placetype":"venue"
},
  "geometry": {"coordinates":[-122.46275199999999,37.764122],"type":"Point"}
}