{
  "type": "Feature",
  "properties": {
    "iso:country":"US",
    "sg:address":"5257 Sierra St",
    "sg:city":"Riverside",
    "sg:classifiers":[
        {
            "category":"Organizations",
            "subcategory":"Non-profit Organization",
            "type":"Services"
        }
    ],
    "sg:phone":"+1 951 351 8800",
    "sg:postcode":"92504",
    "sg:province":"CA",
    "wof:name":"Janet Goeske Senior Ctr",
    "wof:placetype":"venue"
},
  "geometry": {"coordinates":[-117.417627,33.949808],"type":"Point"}
}