{
  "type": "Feature",
  "properties": {
    "addr:full":"819 W Broadway St Needles CA 92363",
    "addr:housenumber":"819",
    "addr:postcode":"92363",
    "addr:street":"W Broadway St",
    "iso:country":"US",
    "sg:address":"819 W Broadway St",
    "sg:city":"Needles",
    "sg:classifiers":[
        {
            "category":"Restaurant",
            "type":"Food & Drink"
        }
    ],
    "sg:phone":"+1 760 326 9191",
    "sg:postcode":"92363",
    "sg:province":"CA",
    "sg:tags":[
        "pizza"
    ],
    "wof:name":"Mudshark Pizza",
    "wof:placetype":"venue"
},
  "geometry": {"coordinates":[-114.60575,34.839099],"type":"Point"}
}