{
  "type": "Feature",
  "properties": {
    "addr:full":"204 2nd Ave San Mateo CA 94401",
    "addr:housenumber":"204",
    "addr:postcode":"94401",
    "addr:street":"2Nd Ave",
    "iso:country":"US",
    "sg:address":"204 2nd Ave",
    "sg:city":"San Mateo",
    "sg:classifiers":[
        {
            "category":"Building & Trades",
            "subcategory":"Construction",
            "type":"Services"
        }
    ],
    "sg:phone":"+1 650 328 8924",
    "sg:postcode":"94401",
    "sg:province":"CA",
    "sg:tags":[
        "contractor"
    ],
    "wof:name":"Gutter Doctors",
    "wof:placetype":"venue"
},
  "geometry": {"coordinates":[-122.323218,37.566197],"type":"Point"}
}