{
  "type": "Feature",
  "properties": {
    "addr:full":"1610 S Beverly Glen Boulevard Los Angeles CA 90024",
    "addr:housenumber":"1610",
    "addr:postcode":"90024",
    "addr:street":"S Beverly Glen Boulevard",
    "iso:country":"US",
    "sg:address":"1610 S Beverly Glen Boulevard",
    "sg:city":"Los Angeles",
    "sg:classifiers":[
        {
            "category":"Real Estate",
            "subcategory":"Real Estate Operator",
            "type":"Services"
        }
    ],
    "sg:phone":"+1 310 553 4434",
    "sg:postcode":"90024",
    "sg:province":"CA",
    "sg:tags":[
        "apartment"
    ],
    "wof:name":"Mickelson Oil & Gas Properties",
    "wof:placetype":"venue"
},
  "geometry": {"coordinates":[-118.42513,34.05956],"type":"Point"}
}