{
  "type": "Feature",
  "properties": {
    "addr:full":"10 W Pennsylvania Ave Redlands CA 92374",
    "addr:housenumber":"10",
    "addr:postcode":"92374",
    "addr:street":"W Pennsylvania Ave",
    "iso:country":"US",
    "sg:address":"10 W Pennsylvania Ave",
    "sg:city":"Redlands",
    "sg:classifiers":[
        {
            "category":"Government",
            "subcategory":"Fire Station",
            "type":"Public Place"
        }
    ],
    "sg:phone":"+1 909 798 7600",
    "sg:postcode":"92374",
    "sg:province":"CA",
    "sg:tags":[
        "department"
    ],
    "wof:name":"Redlands Fire Dept",
    "wof:placetype":"venue"
},
  "geometry": {"coordinates":[-117.183464,34.073744],"type":"Point"}
}