{
  "type": "Feature",
  "properties": {
    "iso:country":"US",
    "sg:address":"107 Sagamore St",
    "sg:city":"San Francisco",
    "sg:classifiers":[
        {
            "category":"Organizations",
            "subcategory":"Religious Organization",
            "type":"Services"
        }
    ],
    "sg:phone":"+1 415 587 8825",
    "sg:postcode":"94112",
    "sg:province":"CA",
    "sg:tags":[
        "church"
    ],
    "wof:name":"Bible Baptist Church",
    "wof:placetype":"venue"
},
  "geometry": {"coordinates":[-122.45593700000001,37.711193],"type":"Point"}
}