{
  "type": "Feature",
  "properties": {
    "addr:full":"592 South Ave Santa Rosa CA 95407",
    "addr:housenumber":"592",
    "addr:postcode":"95407",
    "addr:street":"South Ave",
    "iso:country":"US",
    "sg:address":"592 South Ave",
    "sg:city":"Santa Rosa",
    "sg:classifiers":[
        {
            "category":"Building & Trades",
            "subcategory":"Construction",
            "type":"Services"
        }
    ],
    "sg:phone":"+1 707 576 0789",
    "sg:postcode":"95407",
    "sg:province":"CA",
    "sg:tags":[
        "dry wall",
        "contractor"
    ],
    "wof:name":"Roy Drywall",
    "wof:placetype":"venue"
},
  "geometry": {"coordinates":[-122.727045,38.423663],"type":"Point"}
}