{
  "type": "Feature",
  "properties": {
    "iso:country":"US",
    "sg:address":"12930 Saratoga Ave",
    "sg:city":"Saratoga",
    "sg:classifiers":[
        {
            "category":"Shopping",
            "subcategory":"Computers & Home Electronics",
            "type":"Retail Goods"
        }
    ],
    "sg:phone":"+1 408 973 0332",
    "sg:postcode":"95070",
    "sg:province":"CA",
    "wof:name":"Videopropulsion Interactive Television Inc",
    "wof:placetype":"venue"
},
  "geometry": {"coordinates":[-122.05166199999999,37.280723],"type":"Point"}
}