{
  "type": "Feature",
  "properties": {
    "iso:country":"US",
    "sg:address":"1884 E Ave J",
    "sg:city":"Lancaster",
    "sg:classifiers":[
        {
            "category":"Food & Beverages",
            "subcategory":"Bakery",
            "type":"Retail Goods"
        }
    ],
    "sg:phone":"+1 661 723 9991",
    "sg:postcode":"93535",
    "sg:province":"CA",
    "sg:tags":[
        "doughnut"
    ],
    "wof:name":"Spudnuts",
    "wof:placetype":"venue"
},
  "geometry": {"coordinates":[-118.098275,34.68947],"type":"Point"}
}