{
  "type": "Feature",
  "properties": {
    "addr:full":"2108 Westwood Blvd Los Angeles CA 90025",
    "addr:housenumber":"2108",
    "addr:postcode":"90025",
    "addr:street":"Westwood Blvd",
    "iso:country":"US",
    "sg:address":"2108 Westwood Blvd",
    "sg:city":"Los Angeles",
    "sg:classifiers":[
        {
            "category":"Travel",
            "subcategory":"Travel Agent",
            "type":"Entertainment"
        }
    ],
    "sg:phone":"+1 310 234 3403",
    "sg:postcode":"90025",
    "sg:province":"CA",
    "sg:tags":[
        "agency"
    ],
    "wof:name":"Cruises By Rees",
    "wof:placetype":"venue"
},
  "geometry": {"coordinates":[-118.431753,34.044036],"type":"Point"}
}