{
  "type": "Feature",
  "properties": {
    "addr:full":"18310 Beach Boulevard Huntington Beach CA 92648",
    "addr:housenumber":"18310",
    "addr:postcode":"92648",
    "addr:street":"Beach Boulevard",
    "iso:country":"US",
    "sg:address":"18310 Beach Boulevard",
    "sg:city":"Huntington Beach",
    "sg:classifiers":[
        {
            "category":"Personal",
            "subcategory":"Shoe Repair & Shine",
            "type":"Services"
        }
    ],
    "sg:phone":"+1 714 842 0064",
    "sg:postcode":"92648",
    "sg:province":"CA",
    "wof:name":"Five Points Shoe Repair",
    "wof:placetype":"venue"
},
  "geometry": {"coordinates":[-117.989043,33.696981],"type":"Point"}
}