{
  "type": "Feature",
  "properties": {
    "addr:full":"9010 Reseda Blvd Northridge CA 91324",
    "addr:housenumber":"9010",
    "addr:postcode":"91324",
    "addr:street":"Reseda Blvd",
    "iso:country":"US",
    "sg:address":"9010 Reseda Blvd",
    "sg:city":"Northridge",
    "sg:classifiers":[
        {
            "category":"Travel",
            "subcategory":"Travel Agent",
            "type":"Entertainment"
        }
    ],
    "sg:phone":"+1 818 709 6885",
    "sg:postcode":"91324",
    "sg:province":"CA",
    "sg:tags":[
        "agency",
        "bureau"
    ],
    "wof:name":"Reserve4u",
    "wof:placetype":"venue"
},
  "geometry": {"coordinates":[-118.53601,34.233475],"type":"Point"}
}