{
  "type": "Feature",
  "properties": {
    "addr:full":"1280 Hacienda Dr Vista CA 92081",
    "addr:housenumber":"1280",
    "addr:postcode":"92081",
    "addr:street":"Hacienda Dr",
    "iso:country":"US",
    "sg:address":"1280 Hacienda Dr",
    "sg:city":"Vista",
    "sg:classifiers":[
        {
            "category":"Autos & Motor Vehicles",
            "subcategory":"Automobile Sales",
            "type":"Retail Goods"
        }
    ],
    "sg:phone":"+1 760 803 8786",
    "sg:postcode":"92081",
    "sg:province":"CA",
    "sg:tags":[
        "automotive"
    ],
    "sg:website":"www.renagadedetailing.com/",
    "wof:name":"Renagade Detailing",
    "wof:placetype":"venue"
},
  "geometry": {"coordinates":[-117.270422,33.190043],"type":"Point"}
}