{
  "type": "Feature",
  "properties": {
    "iso:country":"US",
    "sg:address":"17723 Vanowen St",
    "sg:city":"Reseda",
    "sg:classifiers":[
        {
            "category":"Manufacturing",
            "subcategory":"Signs",
            "type":"Manufacturing & Wholesale Goods"
        }
    ],
    "sg:phone":"+1 818 342 1811",
    "sg:postcode":"91335",
    "sg:province":"CA",
    "sg:tags":[
        "design",
        "mfg"
    ],
    "wof:name":"J V Graphic & Sign Productions",
    "wof:placetype":"venue"
},
  "geometry": {"coordinates":[-118.518965,34.193944],"type":"Point"}
}