{
  "type": "Feature",
  "properties": {
    "iso:country":"US",
    "sg:address":"2017 N. Hollywood Way",
    "sg:city":"Burbank",
    "sg:classifiers":[
        {
            "category":"Fast Food",
            "type":"Food & Drink"
        },
        {
            "category":"Food & Beverages",
            "subcategory":"Bakery",
            "type":"Retail Goods"
        }
    ],
    "sg:phone":"+1 818 843 5900",
    "sg:postcode":"91505",
    "sg:province":"CA",
    "sg:tags":[
        "sandwich"
    ],
    "sg:website":"subwayburbank.com",
    "wof:name":"Subway",
    "wof:placetype":"venue"
},
  "geometry": {"coordinates":[-118.34917,34.185722],"type":"Point"}
}