{
  "type": "Feature",
  "properties": {
    "iso:country":"US",
    "sg:address":"3285 Mission St",
    "sg:city":"San Francisco",
    "sg:classifiers":[
        {
            "category":"Personal",
            "subcategory":"Beauty Salon",
            "type":"Services"
        },
        {
            "category":"Personal",
            "subcategory":"Skin Care",
            "type":"Services"
        }
    ],
    "sg:phone":"+1 415 647 2475",
    "sg:postcode":"94110",
    "sg:province":"CA",
    "sg:tags":[
        "hair"
    ],
    "sg:website":"www.pepestudio.net",
    "wof:name":"Pepe Studio",
    "wof:placetype":"venue"
},
  "geometry": {"coordinates":[-122.42077399999999,37.74434],"type":"Point"}
}