{
  "type": "Feature",
  "properties": {
    "addr:full":"400 2nd St San Francisco CA 94107",
    "addr:housenumber":"400",
    "addr:postcode":"94107",
    "addr:street":"2Nd St",
    "iso:country":"US",
    "sg:address":"400 2nd St",
    "sg:city":"San Francisco",
    "sg:classifiers":[
        {
            "category":"Personal",
            "type":"Services"
        },
        {
            "category":"Retail",
            "subcategory":"Storage",
            "type":"Services"
        }
    ],
    "sg:phone":"+1 888 449 8999",
    "sg:postcode":"94107",
    "sg:province":"CA",
    "sg:tags":[
        "mover",
        "self"
    ],
    "sg:website":"www.betterwaytomove.com",
    "wof:name":"Better Way to Move",
    "wof:placetype":"venue"
},
  "geometry": {"coordinates":[-122.395261,37.784096],"type":"Point"}
}