{
  "type": "Feature",
  "properties": {
    "addr:full":"1311 E Philadelphia St Ontario CA 91761",
    "addr:housenumber":"1311 e",
    "addr:postcode":"91761",
    "addr:street":"Philadelphia St",
    "iso:country":"US",
    "sg:address":"1311 E Philadelphia St",
    "sg:city":"Ontario",
    "sg:classifiers":[
        {
            "category":"Manufacturing",
            "subcategory":"Motor Vehicles & Parts",
            "type":"Manufacturing & Wholesale Goods"
        }
    ],
    "sg:phone":"+1 909 923 3358",
    "sg:postcode":"91761",
    "sg:province":"CA",
    "sg:tags":[
        "automobile",
        "supply"
    ],
    "wof:name":"Premiere Power Products",
    "wof:placetype":"venue"
},
  "geometry": {"coordinates":[-117.62711299999999,34.034051],"type":"Point"}
}