{
  "type": "Feature",
  "properties": {
    "addr:full":"859 Terry St Monterey CA 93940",
    "addr:housenumber":"859",
    "addr:postcode":"93940",
    "addr:street":"Terry St",
    "iso:country":"US",
    "sg:address":"859 Terry St",
    "sg:city":"Monterey",
    "sg:classifiers":[
        {
            "category":"Building & Trades",
            "subcategory":"Cleaning & Sanitation",
            "type":"Services"
        }
    ],
    "sg:phone":"+1 831 375 1773",
    "sg:postcode":"93940",
    "sg:province":"CA",
    "sg:tags":[
        "janitor"
    ],
    "wof:name":"Allied Building Cleaners",
    "wof:placetype":"venue"
},
  "geometry": {"coordinates":[-121.913996,36.61055],"type":"Point"}
}