{
  "type": "Feature",
  "properties": {
    "iso:country":"US",
    "sg:address":"7213 Florin Mall Dr",
    "sg:city":"Sacramento",
    "sg:classifiers":[
        {
            "category":"Personal",
            "subcategory":"Beauty Salon",
            "type":"Services"
        }
    ],
    "sg:phone":"+1 916 391 6391",
    "sg:postcode":"95823",
    "sg:province":"CA",
    "wof:name":"Forum Hair Salon",
    "wof:placetype":"venue"
},
  "geometry": {"coordinates":[-121.434208,38.492864],"type":"Point"}
}