{
  "type": "Feature",
  "properties": {
    "iso:country":"US",
    "sg:address":"3463 Idlewild Way",
    "sg:city":"San Diego",
    "sg:classifiers":[
        {
            "category":"Autos & Motor Vehicles",
            "subcategory":"Boat Sales",
            "type":"Retail Goods"
        }
    ],
    "sg:phone":"+1 619 225 8500",
    "sg:postcode":"92117",
    "sg:province":"CA",
    "sg:tags":[
        "top",
        "upholstery",
        "cover"
    ],
    "wof:name":"Ken'z Custom Canvas & Uphlstry",
    "wof:placetype":"venue"
},
  "geometry": {"coordinates":[-117.211142,32.82622],"type":"Point"}
}