{
  "type": "Feature",
  "properties": {
    "iso:country":"US",
    "sg:address":"3094 Triunfo Canyon Rd",
    "sg:city":"Agoura Hills",
    "sg:classifiers":[
        {
            "category":"Recreation",
            "type":"Entertainment"
        }
    ],
    "sg:phone":"+1 818 597 1208",
    "sg:postcode":"91301",
    "sg:province":"CA",
    "sg:tags":[
        "stable"
    ],
    "wof:name":"Double T Enterprises",
    "wof:placetype":"venue"
},
  "geometry": {"coordinates":[-118.79431,34.123604],"type":"Point"}
}