{
  "type": "Feature",
  "properties": {
    "addr:full":"627 N Vermont Avenue Los Angeles CA 90004",
    "addr:housenumber":"627",
    "addr:postcode":"90004",
    "addr:street":"N Vermont Avenue",
    "iso:country":"US",
    "sg:address":"627 N Vermont Avenue",
    "sg:city":"Los Angeles",
    "sg:classifiers":[
        {
            "category":"Food & Beverages",
            "subcategory":"Groceries & Convenience Stores",
            "type":"Retail Goods"
        }
    ],
    "sg:phone":"+1 323 671 1020",
    "sg:postcode":"90004",
    "sg:province":"CA",
    "wof:name":"Island Pacific Supermarket",
    "wof:placetype":"venue"
},
  "geometry": {"coordinates":[-118.29184600000001,34.082689],"type":"Point"}
}