{
  "type": "Feature",
  "properties": {
    "addr:full":"1413 S Victoria Ave Ventura CA 93003",
    "addr:housenumber":"1413",
    "addr:postcode":"93003",
    "addr:street":"S Victoria Ave",
    "iso:country":"US",
    "sg:address":"1413 S Victoria Ave",
    "sg:city":"Ventura",
    "sg:classifiers":[
        {
            "category":"Professional",
            "type":"Services"
        }
    ],
    "sg:phone":"+1 805 658 1964",
    "sg:postcode":"93003",
    "sg:province":"CA",
    "wof:name":"Dream Dinners",
    "wof:placetype":"venue"
},
  "geometry": {"coordinates":[-119.21183499999999,34.262329],"type":"Point"}
}