{
  "type": "Feature",
  "properties": {
    "iso:country":"US",
    "sg:address":"1413 S Victoria Ave",
    "sg:city":"Ventura",
    "sg:classifiers":[
        {
            "category":"Professional",
            "type":"Services"
        }
    ],
    "sg:phone":"+1 805 658 1964",
    "sg:postcode":"93003",
    "sg:province":"CA",
    "wof:name":"Dream Dinners",
    "wof:placetype":"venue"
},
  "geometry": {"coordinates":[-119.211835,34.262329],"type":"Point"}
}