{
  "type": "Feature",
  "properties": {
    "iso:country":"US",
    "sg:address":"255 N el Cielo Rd",
    "sg:city":"Palm Springs",
    "sg:classifiers":[
        {
            "category":"Organizations",
            "subcategory":"Non-profit Organization",
            "type":"Services"
        }
    ],
    "sg:phone":"+1 760 325 7281",
    "sg:postcode":"92262",
    "sg:province":"CA",
    "wof:name":"Jewish Federation Palm Springs",
    "wof:placetype":"venue"
},
  "geometry": {"coordinates":[-116.510704,33.825721],"type":"Point"}
}