{
  "type": "Feature",
  "properties": {
    "iso:country":"US",
    "sg:address":"712 Jackson St",
    "sg:city":"Oakland",
    "sg:classifiers":[
        {
            "category":"Home & Garden",
            "subcategory":"Building Materials",
            "type":"Retail Goods"
        }
    ],
    "sg:phone":"+1 510 268 8117",
    "sg:postcode":"94607",
    "sg:province":"CA",
    "sg:tags":[
        "equipment",
        "fixture",
        "lighting"
    ],
    "sg:website":"www.solairco.com",
    "wof:name":"Solair Co",
    "wof:placetype":"venue"
},
  "geometry": {"coordinates":[-122.26799800000001,37.7976],"type":"Point"}
}