{
  "type": "Feature",
  "properties": {
    "iso:country":"US",
    "sg:address":"115 Alamo Plz Ste C",
    "sg:city":"Alamo",
    "sg:classifiers":[
        {
            "category":"Restaurant",
            "type":"Food & Drink"
        }
    ],
    "sg:phone":"+1 925 838 5583",
    "sg:postcode":"94507",
    "sg:province":"CA",
    "sg:tags":[
        "thai",
        "asian",
        "pan"
    ],
    "wof:name":"Star Of Thailand",
    "wof:placetype":"venue"
},
  "geometry": {"coordinates":[-122.033615,37.849918],"type":"Point"}
}