{
  "type": "Feature",
  "properties": {
    "iso:country":"US",
    "sg:address":"47900 Portola Ave",
    "sg:city":"Palm Desert",
    "sg:classifiers":[
        {
            "category":"Museum",
            "subcategory":"Botanical Garden",
            "type":"Entertainment"
        }
    ],
    "sg:phone":"+1 760 346 5694",
    "sg:postcode":"92260",
    "sg:province":"CA",
    "sg:tags":[
        "zoo",
        "venue",
        "event",
        "space"
    ],
    "sg:website":"www.livingdesert.org",
    "wof:name":"The Living Desert",
    "wof:placetype":"venue"
},
  "geometry": {"coordinates":[-116.375924,33.699942],"type":"Point"}
}