{
  "type": "Feature",
  "properties": {
    "addr:full":"608 S Hill St Los Angeles CA 90014",
    "addr:housenumber":"608",
    "addr:postcode":"90014",
    "addr:street":"S Hill St",
    "iso:country":"US",
    "sg:address":"608 S Hill St",
    "sg:city":"Los Angeles",
    "sg:classifiers":[
        {
            "category":"Wholesale",
            "subcategory":"Jewelry",
            "type":"Manufacturing & Wholesale Goods"
        }
    ],
    "sg:phone":"+1 213 627 7187",
    "sg:postcode":"90014",
    "sg:province":"CA",
    "sg:tags":[
        "stone"
    ],
    "wof:name":"H & A Mounting",
    "wof:placetype":"venue"
},
  "geometry": {"coordinates":[-118.25429800000001,34.04598],"type":"Point"}
}