{
  "type": "Feature",
  "properties": {
    "addr:full":"925 Gladys Way Shafter CA 93230",
    "addr:housenumber":"925",
    "addr:postcode":"93230",
    "addr:street":"Gladys Way",
    "iso:country":"US",
    "sg:address":"925 Gladys Way",
    "sg:city":"Shafter",
    "sg:classifiers":[
        {
            "category":"Wholesale",
            "subcategory":"Farm Supplies",
            "type":"Manufacturing & Wholesale Goods"
        }
    ],
    "sg:phone":"+1 661 399 2951",
    "sg:postcode":"93230",
    "sg:province":"CA",
    "sg:tags":[
        "fertilizer"
    ],
    "wof:name":"Wilbur-Ellis Co-KERN",
    "wof:placetype":"venue"
},
  "geometry": {"coordinates":[-119.632913,36.334028],"type":"Point"}
}