{
  "type": "Feature",
  "properties": {
    "addr:full":"3962 N Studebaker Rd Long Beach CA 90808",
    "addr:housenumber":"3962",
    "addr:postcode":"90808",
    "addr:street":"N Studebaker Rd",
    "iso:country":"US",
    "sg:address":"3962 N Studebaker Rd",
    "sg:city":"Long Beach",
    "sg:classifiers":[
        {
            "category":"Banks & Credit Unions",
            "subcategory":"Bank",
            "type":"Services"
        }
    ],
    "sg:phone":"+1 562 982 1444",
    "sg:postcode":"90808",
    "sg:province":"CA",
    "wof:name":"Johnson Del Ins",
    "wof:placetype":"venue"
},
  "geometry": {"coordinates":[-118.09899900000001,33.828899],"type":"Point"}
}