{
  "type": "Feature",
  "properties": {
    "iso:country":"US",
    "sg:address":"12482 Putnam Street",
    "sg:city":"Whittier",
    "sg:classifiers":[
        {
            "category":"Building & Trades",
            "subcategory":"Construction",
            "type":"Services"
        }
    ],
    "sg:phone":"+1 866 446 8873",
    "sg:postcode":"90602",
    "sg:province":"CA",
    "sg:tags":[
        "contractor"
    ],
    "sg:website":"www.sealtechpro.com",
    "wof:name":"SealTechPro",
    "wof:placetype":"venue"
},
  "geometry": {"coordinates":[-118.04599,33.969143],"type":"Point"}
}