{
  "type": "Feature",
  "properties": {
    "iso:country":"US",
    "sg:address":"128 Caribe Isle",
    "sg:city":"Novato",
    "sg:classifiers":[
        {
            "category":"Home & Garden",
            "subcategory":"Carpets & Floor Coverings",
            "type":"Retail Goods"
        }
    ],
    "sg:phone":"+1 415 265 0789",
    "sg:postcode":"94949",
    "sg:province":"CA",
    "wof:name":"Travis Kitchens",
    "wof:placetype":"venue"
},
  "geometry": {"coordinates":[-122.518723,38.084567],"type":"Point"}
}