{
  "type": "Feature",
  "properties": {
    "addr:full":"7049 Redwood Blvd Novato CA 94945",
    "addr:housenumber":"7049",
    "addr:postcode":"94945",
    "addr:street":"Redwood Blvd",
    "iso:country":"US",
    "sg:address":"7049 Redwood Blvd",
    "sg:city":"Novato",
    "sg:classifiers":[
        {
            "category":"Building & Trades",
            "subcategory":"Construction",
            "type":"Services"
        }
    ],
    "sg:phone":"+1 415 899 7475",
    "sg:postcode":"94945",
    "sg:province":"CA",
    "sg:tags":[
        "tile",
        "dealer"
    ],
    "wof:name":"Century Tile",
    "wof:placetype":"venue"
},
  "geometry": {"coordinates":[-122.566649,38.099078],"type":"Point"}
}