{
  "type": "Feature",
  "properties": {
    "addr:full":"539 Encinitas Blvd Encinitas CA 92024",
    "addr:housenumber":"539",
    "addr:postcode":"92024",
    "addr:street":"Encinitas Blvd",
    "iso:country":"US",
    "sg:address":"539 Encinitas Blvd",
    "sg:city":"Encinitas",
    "sg:classifiers":[
        {
            "category":"Health Services",
            "subcategory":"Chiropractor",
            "type":"Services"
        }
    ],
    "sg:phone":"+1 760 632 5200",
    "sg:postcode":"92024",
    "sg:province":"CA",
    "wof:name":"Optimal Wellness Ctr",
    "wof:placetype":"venue"
},
  "geometry": {"coordinates":[-117.280658,33.046772],"type":"Point"}
}