{
  "type": "Feature",
  "properties": {
    "iso:country":"US",
    "sg:address":"817 Sweetwater Rd",
    "sg:city":"Spring Valley",
    "sg:classifiers":[
        {
            "category":"Freight",
            "type":"Transportation"
        }
    ],
    "sg:phone":"+1 619 697 0217",
    "sg:postcode":"91977",
    "sg:province":"CA",
    "sg:website":"www.dot.ca.gov",
    "wof:name":"Ca Transportation Ventures",
    "wof:placetype":"venue"
},
  "geometry": {"coordinates":[-117.012116,32.710308],"type":"Point"}
}