{
  "type": "Feature",
  "properties": {
    "iso:country":"US",
    "sg:address":"976 Osos St",
    "sg:city":"San Luis Obispo",
    "sg:classifiers":[
        {
            "category":"Government",
            "subcategory":"Office",
            "type":"Public Place"
        }
    ],
    "sg:phone":"+1 805 781 5600",
    "sg:postcode":"93401",
    "sg:province":"CA",
    "sg:website":"www.slocoplanbldg.com",
    "wof:name":"San Luis Obispo Cnty Planning",
    "wof:placetype":"venue"
},
  "geometry": {"coordinates":[-120.661551,35.282021],"type":"Point"}
}