{
  "type": "Feature",
  "properties": {
    "iso:country":"US",
    "sg:address":"613 N Elizabeth St",
    "sg:city":"Santa Maria",
    "sg:classifiers":[
        {
            "category":"Social Services",
            "subcategory":"Child Care",
            "type":"Services"
        }
    ],
    "sg:phone":"+1 805 928 3544",
    "sg:postcode":"93454",
    "sg:province":"CA",
    "sg:tags":[
        "kindergarten",
        "academic",
        "school"
    ],
    "wof:name":"All About Kids Preschool",
    "wof:placetype":"venue"
},
  "geometry": {"coordinates":[-120.428647,34.959159],"type":"Point"}
}