{
  "type": "Feature",
  "properties": {
    "iso:country":"US",
    "sg:address":"9200 Oakdale Ave",
    "sg:city":"Chatsworth",
    "sg:classifiers":[
        {
            "category":"Banks & Credit Unions",
            "subcategory":"Bank",
            "type":"Services"
        }
    ],
    "sg:phone":"+1 818 775 7838",
    "sg:postcode":"91311",
    "sg:province":"CA",
    "sg:tags":[
        "savings",
        "loan"
    ],
    "wof:name":"Washington Mutual Bank",
    "wof:placetype":"venue"
},
  "geometry": {"coordinates":[-118.566805,34.237781],"type":"Point"}
}