{
  "type": "Feature",
  "properties": {
    "addr:full":"1925 E 1st St Los Angeles CA 90033",
    "addr:housenumber":"1925",
    "addr:postcode":"90033",
    "addr:street":"E 1St St",
    "iso:country":"US",
    "sg:address":"1925 E 1st St",
    "sg:city":"Los Angeles",
    "sg:classifiers":[
        {
            "category":"Organizations",
            "subcategory":"Religious Organization",
            "type":"Services"
        }
    ],
    "sg:phone":"+1 323 267 8579",
    "sg:postcode":"90033",
    "sg:province":"CA",
    "sg:tags":[
        "church"
    ],
    "wof:name":"Bethesda Tabernacle Church",
    "wof:placetype":"venue"
},
  "geometry": {"coordinates":[-118.216148,34.046106],"type":"Point"}
}