{
  "type": "Feature",
  "properties": {
    "addr:full":"297 E Stowell St Upland CA 91786",
    "addr:housenumber":"297",
    "addr:postcode":"91786",
    "addr:street":"E Stowell St",
    "iso:country":"US",
    "sg:address":"297 E Stowell St",
    "sg:city":"Upland",
    "sg:classifiers":[
        {
            "category":"Manufacturing",
            "subcategory":"Metals",
            "type":"Manufacturing & Wholesale Goods"
        }
    ],
    "sg:phone":"+1 909 982 9653",
    "sg:postcode":"91786",
    "sg:province":"CA",
    "sg:tags":[
        "shop",
        "plate",
        "work",
        "fabricated"
    ],
    "sg:website":"www.knightsafemfg.com",
    "wof:name":"Knight Safe Mfg",
    "wof:placetype":"venue"
},
  "geometry": {"coordinates":[-117.648475,34.094081],"type":"Point"}
}