{
  "type": "Feature",
  "properties": {
    "addr:full":"1900 S State College Blvd Ste 100 Anaheim CA 92806",
    "addr:housenumber":"1900",
    "addr:postcode":"92806",
    "addr:street":"S;Blvd Ste 100",
    "iso:country":"US",
    "sg:address":"1900 S State College Blvd Ste 100",
    "sg:city":"Anaheim",
    "sg:classifiers":[
        {
            "category":"Education",
            "subcategory":"Special Training",
            "type":"Public Place"
        }
    ],
    "sg:phone":"+1 714 221 3100",
    "sg:postcode":"92806",
    "sg:province":"CA",
    "sg:tags":[
        "school",
        "specialty"
    ],
    "sg:website":"www.newhorizons.com",
    "wof:name":"New Horizons Computer Learning Center of Santa Ana Inc",
    "wof:placetype":"venue"
},
  "geometry": {"coordinates":[-117.889015,33.801406],"type":"Point"}
}