{
  "type": "Feature",
  "properties": {
    "iso:country":"US",
    "sg:address":"37400 Mountain View Rd",
    "sg:city":"Burney",
    "sg:classifiers":[
        {
            "category":"Building & Trades",
            "subcategory":"Equipment Rental",
            "type":"Services"
        }
    ],
    "sg:phone":"+1 530 335 5545",
    "sg:postcode":"96013",
    "sg:province":"CA",
    "sg:tags":[
        "yard"
    ],
    "wof:name":"Burney Rental Ctr Sales & Svc",
    "wof:placetype":"venue"
},
  "geometry": {"coordinates":[-121.654539,40.885143],"type":"Point"}
}