{
  "type": "Feature",
  "properties": {
    "iso:country":"US",
    "sg:address":"3429 Bellevue Ave",
    "sg:city":"Los Angeles",
    "sg:classifiers":[
        {
            "category":"Shopping",
            "subcategory":"Gifts & Souvenirs",
            "type":"Retail Goods"
        }
    ],
    "sg:phone":"+1 323 663 4644",
    "sg:postcode":"90026",
    "sg:province":"CA",
    "sg:tags":[
        "novelty"
    ],
    "wof:name":"Rubber Chickens Cards",
    "wof:placetype":"venue"
},
  "geometry": {"coordinates":[-118.281872,34.079612],"type":"Point"}
}