{
  "type": "Feature",
  "properties": {
    "iso:country":"US",
    "sg:address":"534 S Murphy Ave",
    "sg:city":"Sunnyvale",
    "sg:classifiers":[
        {
            "category":"Wholesale",
            "subcategory":"Auto Parts",
            "type":"Manufacturing & Wholesale Goods"
        }
    ],
    "sg:phone":"+1 408 733 4521",
    "sg:postcode":"94086",
    "sg:province":"CA",
    "sg:tags":[
        "body",
        "automobile",
        "shop"
    ],
    "wof:name":"Don's Supply",
    "wof:placetype":"venue"
},
  "geometry": {"coordinates":[-122.03265399999999,37.36899],"type":"Point"}
}