{
  "type": "Feature",
  "properties": {
    "addr:full":"509 W 18th St Antioch CA 94509",
    "addr:housenumber":"509",
    "addr:postcode":"ca 94509",
    "addr:street":"W 18Th St",
    "iso:country":"US",
    "sg:address":"509 W 18th St",
    "sg:city":"Antioch",
    "sg:classifiers":[
        {
            "category":"Health Services",
            "subcategory":"Medical Lab",
            "type":"Services"
        }
    ],
    "sg:phone":"+1 925 586 8990",
    "sg:postcode":"94509",
    "sg:province":"CA",
    "sg:tags":[
        "detection",
        "equipment",
        "drug"
    ],
    "wof:name":"Antioch Occupational Health",
    "wof:placetype":"venue"
},
  "geometry": {"coordinates":[-121.814961,38.004913],"type":"Point"}
}