{
  "type": "Feature",
  "properties": {
    "addr:full":"6242 Santa Monica Blvd Los Angeles CA 90038",
    "addr:housenumber":"6242",
    "addr:postcode":"90038",
    "addr:street":"Santa Monica Blvd",
    "iso:country":"US",
    "sg:address":"6242 Santa Monica Blvd",
    "sg:city":"Los Angeles",
    "sg:classifiers":[
        {
            "category":"Restaurant",
            "type":"Food & Drink"
        },
        {
            "category":"Bakery",
            "type":"Food & Drink"
        }
    ],
    "sg:phone":"+1 323 962 3151",
    "sg:postcode":"90038",
    "sg:province":"CA",
    "sg:tags":[
        "american",
        "latin"
    ],
    "wof:name":"El Guanaquita Bakery & Pupuseria",
    "wof:placetype":"venue"
},
  "geometry": {"coordinates":[-118.326108,34.090696],"type":"Point"}
}