{
  "type": "Feature",
  "properties": {
    "addr:full":"661 Neilson St Berkeley CA 94707",
    "addr:housenumber":"661",
    "addr:postcode":"94707",
    "addr:street":"Neilson St",
    "iso:country":"US",
    "sg:address":"661 Neilson St",
    "sg:city":"Berkeley",
    "sg:classifiers":[
        {
            "category":"Building & Trades",
            "subcategory":"Plumbing",
            "type":"Services"
        },
        {
            "category":"Home & Garden",
            "subcategory":"Hardware",
            "type":"Retail Goods"
        }
    ],
    "sg:phone":"+1 510 525 7546",
    "sg:postcode":"94707",
    "sg:province":"CA",
    "sg:tags":[
        "filtration",
        "supply",
        "work",
        "purification",
        "water",
        "equipment"
    ],
    "wof:name":"Multi Pure James Baraz Independent Distributor",
    "wof:placetype":"venue"
},
  "geometry": {"coordinates":[-122.28639,37.895436],"type":"Point"}
}