{
  "type": "Feature",
  "properties": {
    "iso:country":"US",
    "sg:address":"5106 Zion Ave",
    "sg:city":"San Diego",
    "sg:classifiers":[
        {
            "category":"Social Services",
            "subcategory":"Child Care",
            "type":"Services"
        }
    ],
    "sg:phone":"+1 619 582 2699",
    "sg:postcode":"92120",
    "sg:province":"CA",
    "sg:tags":[
        "elementary",
        "kindergarten",
        "school",
        "academic"
    ],
    "wof:name":"Ascension Lutheran Preschool",
    "wof:placetype":"venue"
},
  "geometry": {"coordinates":[-117.083,32.792801],"type":"Point"}
}