{
  "type": "Feature",
  "properties": {
    "addr:full":"350 E Gobbi St Ukiah CA 95482",
    "addr:housenumber":"350",
    "addr:postcode":"ca 95482",
    "addr:street":"E Gobbi St",
    "iso:country":"US",
    "sg:address":"350 E Gobbi St",
    "sg:city":"Ukiah",
    "sg:classifiers":[
        {
            "category":"Organizations",
            "subcategory":"Community Association",
            "type":"Services"
        }
    ],
    "sg:phone":"+1 707 467 3674",
    "sg:postcode":"95482",
    "sg:province":"CA",
    "sg:tags":[
        "club"
    ],
    "wof:name":"Ukiah Rotary Club",
    "wof:placetype":"venue"
},
  "geometry": {"coordinates":[-123.20100499999999,39.14439],"type":"Point"}
}