{
  "type": "Feature",
  "properties": {
    "iso:country":"US",
    "sg:address":"1933 241st St",
    "sg:city":"Lomita",
    "sg:classifiers":[
        {
            "category":"Travel",
            "subcategory":"Travel Agent",
            "type":"Entertainment"
        }
    ],
    "sg:phone":"+1 310 792 0678",
    "sg:postcode":"90717",
    "sg:province":"CA",
    "sg:tags":[
        "conducted",
        "tours"
    ],
    "wof:name":"Healthcare Management Cons",
    "wof:placetype":"venue"
},
  "geometry": {"coordinates":[-118.31227,33.806352],"type":"Point"}
}