{
  "type": "Feature",
  "properties": {
    "iso:country":"US",
    "sg:address":"1004 W Foothill Blvd",
    "sg:city":"Upland",
    "sg:classifiers":[
        {
            "category":"Health Services",
            "subcategory":"Doctor",
            "type":"Services"
        }
    ],
    "sg:phone":"+1 909 981 2126",
    "sg:postcode":"91786",
    "sg:province":"CA",
    "sg:tags":[
        "physician",
        "surgeon"
    ],
    "wof:name":"California Surgical Institute",
    "wof:placetype":"venue"
},
  "geometry": {"coordinates":[-117.661702,34.106906],"type":"Point"}
}