{
  "type": "Feature",
  "properties": {
    "iso:country":"US",
    "sg:address":"7620 Copley Park Place",
    "sg:city":"San Diego",
    "sg:classifiers":[
        {
            "category":"Autos & Motor Vehicles",
            "subcategory":"Automobile Sales",
            "type":"Retail Goods"
        }
    ],
    "sg:phone":"+1 858 605 6668",
    "sg:postcode":"92111",
    "sg:province":"CA",
    "sg:tags":[
        "limo"
    ],
    "wof:name":"Gio Limo",
    "wof:placetype":"venue"
},
  "geometry": {"coordinates":[-117.154825,32.836632],"type":"Point"}
}