{
  "type": "Feature",
  "properties": {
    "addr:full":"18041 Magnolia St Fountain Valley CA 92708",
    "addr:housenumber":"18041",
    "addr:postcode":"92708",
    "addr:street":"Magnolia St",
    "iso:country":"US",
    "sg:address":"18041 Magnolia St",
    "sg:city":"Fountain Valley",
    "sg:classifiers":[
        {
            "category":"Restaurant",
            "type":"Food & Drink"
        }
    ],
    "sg:phone":"+1 714 593 2968",
    "sg:postcode":"92708",
    "sg:province":"CA",
    "wof:name":"Ashoka Cuisine Of India",
    "wof:placetype":"venue"
},
  "geometry": {"coordinates":[-117.971649,33.699709],"type":"Point"}
}