{
  "type": "Feature",
  "properties": {
    "addr:full":"13148 Saticoy St North Hollywood CA 91605",
    "addr:housenumber":"13148",
    "addr:postcode":"91605",
    "addr:street":"Saticoy St",
    "iso:country":"US",
    "sg:address":"13148 Saticoy St",
    "sg:city":"North Hollywood",
    "sg:classifiers":[
        {
            "category":"Professional",
            "subcategory":"Management & Consulting",
            "type":"Services"
        }
    ],
    "sg:phone":"+1 818 255 3771",
    "sg:postcode":"91605",
    "sg:province":"CA",
    "sg:tags":[
        "consultant",
        "construction"
    ],
    "wof:name":"Diamant Construction",
    "wof:placetype":"venue"
},
  "geometry": {"coordinates":[-118.420158,34.207637],"type":"Point"}
}