{
  "type": "Feature",
  "properties": {
    "iso:country":"US",
    "sg:address":"20917 Normandie Ave",
    "sg:city":"Torrance",
    "sg:classifiers":[
        {
            "category":"Shopping",
            "subcategory":"Hobbies, Toys, & Games",
            "type":"Retail Goods"
        }
    ],
    "sg:phone":"+1 585 201 6092",
    "sg:postcode":"90501",
    "sg:province":"CA",
    "sg:tags":[
        "toy",
        "store",
        "supply"
    ],
    "wof:name":"Animal Land",
    "wof:placetype":"venue"
},
  "geometry": {"coordinates":[-118.299599,33.839822],"type":"Point"}
}