{
  "type": "Feature",
  "properties": {
    "addr:full":"174 Emerald Forest Ln Santa Cruz CA 95060",
    "addr:housenumber":"174",
    "addr:postcode":"95060",
    "addr:street":"Emerald Forest Ln",
    "iso:country":"US",
    "sg:address":"174 Emerald Forest Ln",
    "sg:city":"Santa Cruz",
    "sg:classifiers":[
        {
            "category":"Wholesale",
            "subcategory":"Non-durable Goods",
            "type":"Manufacturing & Wholesale Goods"
        }
    ],
    "sg:phone":"+1 831 425 5279",
    "sg:postcode":"95060",
    "sg:province":"CA",
    "wof:name":"Kimbari Distrubuting",
    "wof:placetype":"venue"
},
  "geometry": {"coordinates":[-122.13462699999999,37.078082],"type":"Point"}
}