{
  "type": "Feature",
  "properties": {
    "iso:country":"US",
    "sg:address":"1049 Felspar St",
    "sg:city":"San Diego",
    "sg:classifiers":[
        {
            "category":"Building & Trades",
            "subcategory":"Construction",
            "type":"Services"
        }
    ],
    "sg:phone":"+1 858 483 8735",
    "sg:postcode":"92109",
    "sg:province":"CA",
    "sg:tags":[
        "general",
        "contractor"
    ],
    "wof:name":"RTO Construction",
    "wof:placetype":"venue"
},
  "geometry": {"coordinates":[-117.251086,32.798434],"type":"Point"}
}