{
  "type": "Feature",
  "properties": {
    "iso:country":"US",
    "sg:address":"6774 Mount Pakron Dr",
    "sg:city":"San Jose",
    "sg:classifiers":[
        {
            "category":"Professional",
            "subcategory":"Business Services",
            "type":"Services"
        }
    ],
    "sg:phone":"+1 408 997 9338",
    "sg:postcode":"95120",
    "sg:province":"CA",
    "sg:tags":[
        "interior",
        "consultant",
        "design",
        "decorator"
    ],
    "wof:name":"Quick Fix Designs",
    "wof:placetype":"venue"
},
  "geometry": {"coordinates":[-121.851141,37.215114],"type":"Point"}
}