{
  "type": "Feature",
  "properties": {
    "iso:country":"US",
    "sg:address":"424 S Mercey Springs Rd",
    "sg:city":"Los Banos",
    "sg:classifiers":[
        {
            "category":"Organizations",
            "subcategory":"Religious Organization",
            "type":"Services"
        }
    ],
    "sg:phone":"+1 209 826 5912",
    "sg:postcode":"93635",
    "sg:province":"CA",
    "sg:tags":[
        "church"
    ],
    "wof:name":"New Canaan Baptist Church",
    "wof:placetype":"venue"
},
  "geometry": {"coordinates":[-120.834993,37.07414],"type":"Point"}
}