{
  "type": "Feature",
  "properties": {
    "iso:country":"US",
    "sg:address":"40 Cam del Oro",
    "sg:city":"Rancho Santa Margarita",
    "sg:classifiers":[
        {
            "category":"Manufacturing",
            "subcategory":"Apparel",
            "type":"Manufacturing & Wholesale Goods"
        }
    ],
    "sg:phone":"+1 949 459 0998",
    "sg:postcode":"92688",
    "sg:province":"CA",
    "sg:tags":[
        "teaching",
        "design",
        "embroidery"
    ],
    "wof:name":"Dual Aspects",
    "wof:placetype":"venue"
},
  "geometry": {"coordinates":[-117.619547,33.655349],"type":"Point"}
}