{
  "type": "Feature",
  "properties": {
    "addr:full":"6935 Jellico Ave Van Nuys CA 91406",
    "addr:housenumber":"6935",
    "addr:postcode":"91406",
    "addr:street":"Jellico Ave",
    "iso:country":"US",
    "sg:address":"6935 Jellico Ave",
    "sg:city":"Van Nuys",
    "sg:classifiers":[
        {
            "category":"Retail",
            "subcategory":"Portrait Studio",
            "type":"Services"
        }
    ],
    "sg:phone":"+1 818 343 7592",
    "sg:postcode":"91406",
    "sg:province":"CA",
    "sg:tags":[
        "photographer"
    ],
    "wof:name":"Rafael Beer Photography",
    "wof:placetype":"venue"
},
  "geometry": {"coordinates":[-118.51746199999999,34.195044],"type":"Point"}
}