{
  "type": "Feature",
  "properties": {
    "addr:full":"2300 Walnut Ave Burbank CA 91501",
    "addr:housenumber":"2300",
    "addr:postcode":"91501",
    "addr:street":"Walnut Ave",
    "iso:country":"US",
    "sg:address":"2300 Walnut Ave",
    "sg:city":"Burbank",
    "sg:classifiers":[
        {
            "category":"Park",
            "type":"Public Place"
        },
        {
            "category":"Recreation",
            "type":"Entertainment"
        }
    ],
    "sg:phone":"+1 818 238 5440",
    "sg:postcode":"91501",
    "sg:province":"CA",
    "sg:tags":[
        "summer",
        "camp",
        "hiking"
    ],
    "sg:website":"www.lamountains.com",
    "wof:name":"Stough Canyon Nature Center",
    "wof:placetype":"venue"
},
  "geometry": {"coordinates":[-118.305396,34.205281],"type":"Point"}
}