{
  "type": "Feature",
  "properties": {
    "iso:country":"US",
    "sg:address":"435 E Napa St",
    "sg:city":"Sonoma",
    "sg:classifiers":[
        {
            "category":"Building & Trades",
            "subcategory":"Construction",
            "type":"Services"
        }
    ],
    "sg:phone":"+1 707 938 0232",
    "sg:postcode":"95476",
    "sg:province":"CA",
    "sg:tags":[
        "maker",
        "cabinet"
    ],
    "wof:name":"Greer Construction",
    "wof:placetype":"venue"
},
  "geometry": {"coordinates":[-122.4496,38.291043],"type":"Point"}
}