{
  "type": "Feature",
  "properties": {
    "addr:full":"401 Requeza St Suite F-6 Encinitas CA 92024",
    "addr:housenumber":"401",
    "addr:postcode":"92024",
    "addr:street":"Requeza St Suite F-6",
    "iso:country":"US",
    "sg:address":"401 Requeza St Suite F-6",
    "sg:city":"Encinitas",
    "sg:classifiers":[
        {
            "category":"Professional",
            "type":"Services"
        }
    ],
    "sg:phone":"+1 760 712 4664",
    "sg:postcode":"92024",
    "sg:province":"CA",
    "wof:name":"FM Solutions Pro",
    "wof:placetype":"venue"
},
  "geometry": {"coordinates":[-117.283452,33.04317],"type":"Point"}
}