{
  "type": "Feature",
  "properties": {
    "addr:full":"909 Broadway St Redwood City CA 94063",
    "addr:housenumber":"909",
    "addr:postcode":"94063",
    "addr:street":"Broadway St",
    "iso:country":"US",
    "sg:address":"909 Broadway St",
    "sg:city":"Redwood City",
    "sg:classifiers":[
        {
            "category":"Wholesale",
            "subcategory":"Machinery & Supplies",
            "type":"Manufacturing & Wholesale Goods"
        }
    ],
    "sg:phone":"+1 650 368 3311",
    "sg:postcode":"94063",
    "sg:province":"CA",
    "sg:tags":[
        "contractor"
    ],
    "wof:name":"Western Power & Equipment Corp",
    "wof:placetype":"venue"
},
  "geometry": {"coordinates":[-122.213684,37.486165],"type":"Point"}
}