{
  "type": "Feature",
  "properties": {
    "iso:country":"US",
    "sg:address":"11530 Simms Ave",
    "sg:city":"Inglewood",
    "sg:classifiers":[
        {
            "category":"Building & Trades",
            "subcategory":"Construction",
            "type":"Services"
        }
    ],
    "sg:phone":"+1 310 973 7520",
    "sg:postcode":"90303",
    "sg:province":"CA",
    "sg:tags":[
        "contractor"
    ],
    "wof:name":"Ing Cleaning Services",
    "wof:placetype":"venue"
},
  "geometry": {"coordinates":[-118.328165,33.929443],"type":"Point"}
}