{
  "type": "Feature",
  "properties": {
    "addr:full":"718 E Cypress Ave Lompoc CA 93436",
    "addr:housenumber":"718",
    "addr:postcode":"93436",
    "addr:street":"E Cypress Ave",
    "iso:country":"US",
    "sg:address":"718 E Cypress Ave",
    "sg:city":"Lompoc",
    "sg:classifiers":[
        {
            "category":"Home & Garden",
            "subcategory":"Building Materials",
            "type":"Retail Goods"
        }
    ],
    "sg:phone":"+1 805 736 9846",
    "sg:postcode":"93436",
    "sg:province":"CA",
    "sg:tags":[
        "type",
        "door"
    ],
    "wof:name":"All Star Garage Svc",
    "wof:placetype":"venue"
},
  "geometry": {"coordinates":[-120.449888,34.637189],"type":"Point"}
}