{
  "type": "Feature",
  "properties": {
    "addr:full":"9929 Hibert St San Diego CA 92131",
    "addr:housenumber":"9929",
    "addr:postcode":"92131",
    "addr:street":"Hibert St",
    "iso:country":"US",
    "sg:address":"9929 Hibert St",
    "sg:city":"San Diego",
    "sg:classifiers":[
        {
            "category":"Professional",
            "subcategory":"Secretarial Services",
            "type":"Services"
        }
    ],
    "sg:phone":"+1 858 271 0327",
    "sg:postcode":"92131",
    "sg:province":"CA",
    "sg:tags":[
        "reporting",
        "court"
    ],
    "wof:name":"AJC Enterprises",
    "wof:placetype":"venue"
},
  "geometry": {"coordinates":[-117.11212999999999,32.913759],"type":"Point"}
}