{
  "type": "Feature",
  "properties": {
    "addr:full":"1006 Shary Cir Concord CA 94518",
    "addr:housenumber":"1006",
    "addr:postcode":"94518",
    "addr:street":"Shary Cir",
    "iso:country":"US",
    "sg:address":"1006 Shary Cir",
    "sg:city":"Concord",
    "sg:classifiers":[
        {
            "category":"Wholesale",
            "subcategory":"Office Equipment",
            "type":"Manufacturing & Wholesale Goods"
        },
        {
            "category":"Professional",
            "subcategory":"Advertising",
            "type":"Services"
        },
        {
            "category":"Professional",
            "subcategory":"Printing & Photocopies",
            "type":"Services"
        },
        {
            "category":"Shopping",
            "subcategory":"Computers & Home Electronics",
            "type":"Retail Goods"
        }
    ],
    "sg:phone":"+1 925 827 0992",
    "sg:postcode":"94518",
    "sg:province":"CA",
    "sg:tags":[
        "scanning",
        "printer",
        "supply",
        "services-commercial",
        "direct",
        "mail",
        "plotting"
    ],
    "wof:name":"Payless Printing",
    "wof:placetype":"venue"
},
  "geometry": {"coordinates":[-122.029718,37.953365],"type":"Point"}
}