{
  "type": "Feature",
  "properties": {
    "addr:full":"1031 N Ventura Ave Farmersville CA 93223",
    "addr:housenumber":"1031",
    "addr:postcode":"93223",
    "addr:street":"N Ventura Ave",
    "iso:country":"US",
    "sg:address":"1031 N Ventura Ave",
    "sg:city":"Farmersville",
    "sg:classifiers":[
        {
            "category":"Shopping",
            "subcategory":"Clothing, Apparel, & Fashions",
            "type":"Retail Goods"
        }
    ],
    "sg:phone":"+1 559 747 5301",
    "sg:postcode":"93223",
    "sg:province":"CA",
    "sg:tags":[
        "alteration"
    ],
    "wof:name":"Alterations By Rosemary",
    "wof:placetype":"venue"
},
  "geometry": {"coordinates":[-119.211592,36.306877],"type":"Point"}
}