{
  "type": "Feature",
  "properties": {
    "addr:full":"239 8th street suite 12 San Francisco CA 94103",
    "addr:housenumber":"239;12",
    "addr:postcode":"94103",
    "addr:street":"8Th Street Suite",
    "iso:country":"US",
    "sg:address":"239 8th street suite 12",
    "sg:city":"San Francisco",
    "sg:classifiers":[
        {
            "category":"Professional",
            "subcategory":"Research",
            "type":"Services"
        }
    ],
    "sg:postcode":"94103",
    "sg:province":"CA",
    "sg:tags":[
        "heat-recovery"
    ],
    "sg:website":"http://www.alphabetenergy.com/",
    "wof:name":"Alphabet Energy",
    "wof:placetype":"venue"
},
  "geometry": {"coordinates":[-122.410768,37.775693],"type":"Point"}
}