{
  "type": "Feature",
  "properties": {
    "addr:full":"17921 Brighton Way Gardena CA 90248",
    "addr:housenumber":"17921",
    "addr:postcode":"90248",
    "addr:street":"Brighton Way",
    "iso:country":"US",
    "sg:address":"17921 Brighton Way",
    "sg:city":"Gardena",
    "sg:classifiers":[
        {
            "category":"Real Estate",
            "subcategory":"Real Estate Agent",
            "type":"Services"
        }
    ],
    "sg:phone":"+1 310 323 6502",
    "sg:postcode":"90248",
    "sg:province":"CA",
    "sg:tags":[
        "manager"
    ],
    "wof:name":"Westside Properties",
    "wof:placetype":"venue"
},
  "geometry": {"coordinates":[-118.29992900000001,33.86693],"type":"Point"}
}