{
  "type": "Feature",
  "properties": {
    "iso:country":"US",
    "sg:address":"1671 N Capitol Ave",
    "sg:city":"San Jose",
    "sg:classifiers":[
        {
            "category":"Shopping",
            "subcategory":"Music",
            "type":"Retail Goods"
        }
    ],
    "sg:phone":"+1 408 251 3258",
    "sg:postcode":"95132",
    "sg:province":"CA",
    "sg:tags":[
        "video",
        "disc",
        "tape",
        "cassette"
    ],
    "wof:name":"California Video",
    "wof:placetype":"venue"
},
  "geometry": {"coordinates":[-121.874364,37.398361],"type":"Point"}
}