{
  "type": "Feature",
  "properties": {
    "iso:country":"US",
    "sg:address":"1294 W Capitol Ave",
    "sg:city":"West Sacramento",
    "sg:classifiers":[
        {
            "category":"Recreation",
            "type":"Entertainment"
        }
    ],
    "sg:phone":"+1 916 374 1859",
    "sg:postcode":"95691",
    "sg:province":"CA",
    "sg:tags":[
        "martial",
        "arts",
        "instruction"
    ],
    "wof:name":"ATA Black Belt Academy",
    "wof:placetype":"venue"
},
  "geometry": {"coordinates":[-121.524018,38.581424],"type":"Point"}
}