{
  "type": "Feature",
  "properties": {
    "iso:country":"US",
    "sg:address":"2560 Lake Forest Rd",
    "sg:city":"Tahoe City",
    "sg:classifiers":[
        {
            "category":"Real Estate",
            "subcategory":"Real Estate Operator",
            "type":"Services"
        }
    ],
    "sg:phone":"+1 530 583 1808",
    "sg:postcode":"96145",
    "sg:province":"CA",
    "sg:tags":[
        "condominium"
    ],
    "wof:name":"St Francis Lakeside Condo",
    "wof:placetype":"venue"
},
  "geometry": {"coordinates":[-120.116968,39.184072],"type":"Point"}
}