{
  "type": "Feature",
  "properties": {
    "iso:country":"US",
    "sg:address":"4520 Enterprise St",
    "sg:city":"Fremont",
    "sg:classifiers":[
        {
            "category":"Manufacturing",
            "subcategory":"Printing",
            "type":"Manufacturing & Wholesale Goods"
        }
    ],
    "sg:phone":"+1 510 490 0798",
    "sg:postcode":"94538",
    "sg:province":"CA",
    "sg:tags":[
        "commercial"
    ],
    "wof:name":"Easy Color Printing",
    "wof:placetype":"venue"
},
  "geometry": {"coordinates":[-121.960218,37.504205],"type":"Point"}
}