{
  "type": "Feature",
  "properties": {
    "iso:country":"US",
    "sg:address":"25181 State Hwy 88",
    "sg:city":"Pioneer",
    "sg:classifiers":[
        {
            "category":"Building & Trades",
            "subcategory":"Construction",
            "type":"Services"
        }
    ],
    "sg:phone":"+1 209 295 3695",
    "sg:postcode":"95666",
    "sg:province":"CA",
    "sg:tags":[
        "general",
        "contractor"
    ],
    "wof:name":"D & M Enterprises",
    "wof:placetype":"venue"
},
  "geometry": {"coordinates":[-120.557323,38.435834],"type":"Point"}
}