{
  "type": "Feature",
  "properties": {
    "iso:country":"US",
    "sg:address":"544 W Katella Ave",
    "sg:city":"Orange",
    "sg:classifiers":[
        {
            "category":"Manufacturing",
            "subcategory":"Printing",
            "type":"Manufacturing & Wholesale Goods"
        }
    ],
    "sg:phone":"+1 714 633 2215",
    "sg:postcode":"92867",
    "sg:province":"CA",
    "sg:tags":[
        "printer"
    ],
    "wof:name":"Orbit Printing Co",
    "wof:placetype":"venue"
},
  "geometry": {"coordinates":[-117.856657,33.808967],"type":"Point"}
}