{
  "type": "Feature",
  "properties": {
    "iso:country":"US",
    "sg:address":"18440 Hart St",
    "sg:city":"Reseda",
    "sg:classifiers":[
        {
            "category":"Retail",
            "subcategory":"Auto Repair",
            "type":"Services"
        }
    ],
    "sg:phone":"+1 818 668 8190",
    "sg:postcode":"91335",
    "sg:province":"CA",
    "sg:tags":[
        "repairing",
        "automobile"
    ],
    "wof:name":"OND Auto Repair",
    "wof:placetype":"venue"
},
  "geometry": {"coordinates":[-118.535361,34.197407],"type":"Point"}
}