{
  "type": "Feature",
  "properties": {
    "iso:country":"US",
    "sg:address":"736 N Arthur Ave",
    "sg:city":"Fresno",
    "sg:classifiers":[
        {
            "category":"Shopping",
            "subcategory":"Gifts & Souvenirs",
            "type":"Retail Goods"
        }
    ],
    "sg:phone":"+1 559 233 2711",
    "sg:postcode":"93728",
    "sg:province":"CA",
    "wof:name":"Chepis Gifts",
    "wof:placetype":"venue"
},
  "geometry": {"coordinates":[-119.815264,36.753666],"type":"Point"}
}