{
  "type": "Feature",
  "properties": {
    "addr:full":"33 Hamilton Dr Novato CA 94949",
    "addr:housenumber":"33",
    "addr:postcode":"94949",
    "addr:street":"Hamilton Dr",
    "iso:country":"US",
    "sg:address":"33 Hamilton Dr",
    "sg:city":"Novato",
    "sg:classifiers":[
        {
            "category":"Home & Garden",
            "subcategory":"Furniture",
            "type":"Retail Goods"
        }
    ],
    "sg:phone":"+1 415 382 4022",
    "sg:postcode":"94949",
    "sg:province":"CA",
    "sg:tags":[
        "builder",
        "custom"
    ],
    "wof:name":"William August Studio",
    "wof:placetype":"venue"
},
  "geometry": {"coordinates":[-122.539552,38.073937],"type":"Point"}
}