{
  "type": "Feature",
  "properties": {
    "addr:full":"1950 N Texas St Fairfield CA 94533",
    "addr:housenumber":"1950",
    "addr:postcode":"94533",
    "addr:street":"N Texas St",
    "iso:country":"US",
    "sg:address":"1950 N Texas St",
    "sg:city":"Fairfield",
    "sg:classifiers":[
        {
            "category":"Food & Beverages",
            "subcategory":"Groceries & Convenience Stores",
            "type":"Retail Goods"
        },
        {
            "category":"Food & Beverages",
            "subcategory":"Meat & Fish",
            "type":"Retail Goods"
        }
    ],
    "sg:phone":"+1 707 427 8767",
    "sg:postcode":"94533",
    "sg:province":"CA",
    "sg:tags":[
        "market"
    ],
    "wof:name":"Mexico Taqueria 2",
    "wof:placetype":"venue"
},
  "geometry": {"coordinates":[-122.034198,38.264659],"type":"Point"}
}