{
  "type": "Feature",
  "properties": {
    "iso:country":"US",
    "sg:address":"3628 E Imperial Hwy",
    "sg:city":"Lynwood",
    "sg:classifiers":[
        {
            "category":"Health Services",
            "subcategory":"Doctor",
            "type":"Services"
        }
    ],
    "sg:phone":"+1 310 605 0048",
    "sg:postcode":"90262",
    "sg:province":"CA",
    "wof:name":"Monroe Benjamin F MD",
    "wof:placetype":"venue"
},
  "geometry": {"coordinates":[-118.204239,33.93084],"type":"Point"}
}