{
  "type": "Feature",
  "properties": {
    "iso:country":"US",
    "sg:address":"1787 Ellie Ct",
    "sg:city":"Benicia",
    "sg:classifiers":[
        {
            "category":"Manufacturing",
            "subcategory":"Furniture",
            "type":"Manufacturing & Wholesale Goods"
        }
    ],
    "sg:phone":"+1 707 745 1850",
    "sg:postcode":"94510",
    "sg:province":"CA",
    "sg:tags":[
        "household",
        "wood",
        "mfg"
    ],
    "wof:name":"Smock Family Heirlooms",
    "wof:placetype":"venue"
},
  "geometry": {"coordinates":[-122.158913,38.061356],"type":"Point"}
}