{
  "type": "Feature",
  "properties": {
    "addr:full":"641 E Monterey Ave Pomona CA 91767",
    "addr:housenumber":"641",
    "addr:postcode":"91767",
    "addr:street":"E Monterey Ave",
    "iso:country":"US",
    "sg:address":"641 E Monterey Ave",
    "sg:city":"Pomona",
    "sg:classifiers":[
        {
            "category":"Food & Beverages",
            "subcategory":"Bakery",
            "type":"Retail Goods"
        },
        {
            "category":"Bakery",
            "type":"Food & Drink"
        }
    ],
    "sg:phone":"+1 909 629 2424",
    "sg:postcode":"91767",
    "sg:province":"CA",
    "sg:tags":[
        "bakers-wholesale"
    ],
    "wof:name":"Pita Pit Bakery",
    "wof:placetype":"venue"
},
  "geometry": {"coordinates":[-117.738528,34.060815],"type":"Point"}
}