{
  "type": "Feature",
  "properties": {
    "iso:country":"US",
    "sg:address":"1450 Oro Dam Blvd E",
    "sg:city":"Oroville",
    "sg:classifiers":[
        {
            "category":"Retail",
            "subcategory":"Auto Repair",
            "type":"Services"
        }
    ],
    "sg:phone":"+1 530 532 4455",
    "sg:postcode":"95965",
    "sg:province":"CA",
    "sg:tags":[
        "muffler",
        "exhaust",
        "system"
    ],
    "wof:name":"King Muffler",
    "wof:placetype":"venue"
},
  "geometry": {"coordinates":[-121.559624,39.501678],"type":"Point"}
}