{
  "type": "Feature",
  "properties": {
    "iso:country":"US",
    "sg:address":"5701 Thornhill Dr",
    "sg:city":"Oakland",
    "sg:classifiers":[
        {
            "category":"Social Services",
            "subcategory":"Child Care",
            "type":"Services"
        }
    ],
    "sg:phone":"+1 510 339 3830",
    "sg:postcode":"94611",
    "sg:province":"CA",
    "sg:tags":[
        "elementary",
        "school"
    ],
    "wof:name":"Smile's Day School",
    "wof:placetype":"venue"
},
  "geometry": {"coordinates":[-122.212755,37.834112],"type":"Point"}
}