{
  "type": "Feature",
  "properties": {
    "iso:country":"US",
    "sg:address":"861 W. San Bruno Ave Suite #3",
    "sg:city":"San Bruno",
    "sg:classifiers":[
        {
            "category":"Health Services",
            "subcategory":"Health Practitioner",
            "type":"Services"
        }
    ],
    "sg:phone":"+1 650 866 3396",
    "sg:postcode":"94066",
    "sg:province":"CA",
    "sg:tags":[
        "acupuncture"
    ],
    "wof:name":"Sharlene X. Zhang",
    "wof:placetype":"venue"
},
  "geometry": {"coordinates":[-122.41836000000001,37.627879],"type":"Point"}
}