{
  "type": "Feature",
  "properties": {
    "addr:full":"1855 Hamilton Ave San Jose CA 95125",
    "addr:housenumber":"1855",
    "addr:postcode":"95125",
    "addr:street":"Hamilton Ave",
    "iso:country":"US",
    "sg:address":"1855 Hamilton Ave",
    "sg:city":"San Jose",
    "sg:classifiers":[
        {
            "category":"Freight",
            "type":"Transportation"
        }
    ],
    "sg:phone":"+1 408 369 8310",
    "sg:postcode":"95125",
    "sg:province":"CA",
    "wof:name":"In Motion Transportation",
    "wof:placetype":"venue"
},
  "geometry": {"coordinates":[-121.919014,37.294472],"type":"Point"}
}