{
  "type": "Feature",
  "properties": {
    "addr:full":"9161 Starr Rd Windsor CA 95492",
    "addr:housenumber":"9161",
    "addr:postcode":"95492",
    "addr:street":"Starr Rd",
    "iso:country":"US",
    "sg:address":"9161 Starr Rd",
    "sg:city":"Windsor",
    "sg:classifiers":[
        {
            "category":"Social Services",
            "subcategory":"Child Care",
            "type":"Services"
        }
    ],
    "sg:phone":"+1 707 838 9306",
    "sg:postcode":"95492",
    "sg:province":"CA",
    "sg:tags":[
        "kindergarten",
        "academic",
        "school"
    ],
    "wof:name":"Windsor Cooperative Nursery",
    "wof:placetype":"venue"
},
  "geometry": {"coordinates":[-122.826123,38.54577],"type":"Point"}
}