{
  "type": "Feature",
  "properties": {
    "iso:country":"US",
    "sg:address":"2440 4th Ave",
    "sg:city":"Sacramento",
    "sg:classifiers":[
        {
            "category":"Manufacturing",
            "subcategory":"Buildings",
            "type":"Manufacturing & Wholesale Goods"
        },
        {
            "category":"Building & Trades",
            "subcategory":"Construction",
            "type":"Services"
        }
    ],
    "sg:phone":"+1 916 736 2210",
    "sg:postcode":"95818",
    "sg:province":"CA",
    "sg:tags":[
        "home",
        "builder",
        "contractor"
    ],
    "wof:name":"Aging At Home-The Park Villages",
    "wof:placetype":"venue"
},
  "geometry": {"coordinates":[-121.48258199999999,38.55249],"type":"Point"}
}