{
  "type": "Feature",
  "properties": {
    "iso:country":"US",
    "sg:address":"512 E Virginia Way",
    "sg:city":"Barstow",
    "sg:classifiers":[
        {
            "category":"Shopping",
            "subcategory":"Shoes",
            "type":"Retail Goods"
        }
    ],
    "sg:phone":"+1 760 256 8411",
    "sg:postcode":"92311",
    "sg:province":"CA",
    "wof:name":"Payless Shoe Source",
    "wof:placetype":"venue"
},
  "geometry": {"coordinates":[-117.020425,34.88807],"type":"Point"}
}