{
  "type": "Feature",
  "properties": {
    "iso:country":"US",
    "sg:address":"1 Cyclotron Rd",
    "sg:city":"Berkeley",
    "sg:classifiers":[
        {
            "category":"Building & Trades",
            "subcategory":"Electrical",
            "type":"Services"
        }
    ],
    "sg:phone":"+1 510 486 0735",
    "sg:postcode":"94720",
    "sg:province":"CA",
    "sg:tags":[
        "electrician"
    ],
    "wof:name":"Contra Csta Electric",
    "wof:placetype":"venue"
},
  "geometry": {"coordinates":[-122.25205200000001,37.87764],"type":"Point"}
}