{
  "type": "Feature",
  "properties": {
    "addr:full":"1775 Monterey Hwy San Jose CA 95112",
    "addr:housenumber":"1775",
    "addr:postcode":"95112",
    "addr:street":"Monterey Hwy",
    "iso:country":"US",
    "sg:address":"1775 Monterey Hwy",
    "sg:city":"San Jose",
    "sg:classifiers":[
        {
            "category":"Professional",
            "subcategory":"Business Services",
            "type":"Services"
        }
    ],
    "sg:phone":"+1 408 292 1121",
    "sg:postcode":"95112",
    "sg:province":"CA",
    "sg:tags":[
        "embroidery"
    ],
    "wof:name":"Jiminy Stitch It",
    "wof:placetype":"venue"
},
  "geometry": {"coordinates":[-121.86615500000001,37.308546],"type":"Point"}
}