{
  "type": "Feature",
  "properties": {
    "addr:full":"2435 Fair Oaks Blvd Sacramento CA 95825",
    "addr:housenumber":"2435",
    "addr:postcode":"95825",
    "addr:street":"Fair Oaks Blvd",
    "iso:country":"US",
    "sg:address":"2435 Fair Oaks Blvd",
    "sg:city":"Sacramento",
    "sg:classifiers":[
        {
            "category":"Restaurant",
            "type":"Food & Drink"
        }
    ],
    "sg:phone":"+1 916 484 7250",
    "sg:postcode":"95825",
    "sg:province":"CA",
    "sg:tags":[
        "traditional",
        "american",
        "mediterranean",
        "fusion",
        "asian"
    ],
    "sg:website":"www.noodles.com",
    "wof:name":"Noodles & Company",
    "wof:placetype":"venue"
},
  "geometry": {"coordinates":[-121.405822,38.574356],"type":"Point"}
}