{
  "type": "Feature",
  "properties": {
    "addr:full":"1132 N Gower St Los Angeles CA 90038",
    "addr:housenumber":"1132",
    "addr:postcode":"90038",
    "addr:street":"N Gower St",
    "iso:country":"US",
    "sg:address":"1132 N Gower St",
    "sg:city":"Los Angeles",
    "sg:classifiers":[
        {
            "category":"Wholesale",
            "subcategory":"Apparel",
            "type":"Manufacturing & Wholesale Goods"
        }
    ],
    "sg:phone":"+1 323 463 3419",
    "sg:postcode":"90038",
    "sg:province":"CA",
    "sg:tags":[
        "clothing"
    ],
    "wof:name":"Sling Ting Inc",
    "wof:placetype":"venue"
},
  "geometry": {"coordinates":[-118.322197,34.09197],"type":"Point"}
}