{
  "type": "Feature",
  "properties": {
    "addr:full":"78536 Crystal Falls Rd Palm Desert CA 92211",
    "addr:housenumber":"78536",
    "addr:postcode":"92211",
    "addr:street":"Crystal Falls Rd",
    "iso:country":"US",
    "sg:address":"78536 Crystal Falls Rd",
    "sg:city":"Palm Desert",
    "sg:classifiers":[
        {
            "category":"Real Estate",
            "subcategory":"Real Estate Agent",
            "type":"Services"
        }
    ],
    "sg:phone":"+1 760 360 7954",
    "sg:postcode":"92211",
    "sg:province":"CA",
    "wof:name":"Joann Nelson",
    "wof:placetype":"venue"
},
  "geometry": {"coordinates":[-116.291573,33.778839],"type":"Point"}
}