{
  "type": "Feature",
  "properties": {
    "addr:full":"1133 Longfellow Ave Campbell CA 95008",
    "addr:housenumber":"1133",
    "addr:postcode":"95008",
    "addr:street":"Longfellow Ave",
    "iso:country":"US",
    "sg:address":"1133 Longfellow Ave",
    "sg:city":"Campbell",
    "sg:classifiers":[
        {
            "category":"Professional",
            "subcategory":"Engineering",
            "type":"Services"
        }
    ],
    "sg:phone":"+1 408 559 1072",
    "sg:postcode":"95008",
    "sg:province":"CA",
    "sg:tags":[
        "engineer"
    ],
    "wof:name":"Innovative Seminconductor Syst",
    "wof:placetype":"venue"
},
  "geometry": {"coordinates":[-121.95161,37.260543],"type":"Point"}
}