{
  "type": "Feature",
  "properties": {
    "addr:full":"16223 Devonshire St Granada Hills CA 91344",
    "addr:housenumber":"16223",
    "addr:postcode":"91344",
    "addr:street":"Devonshire St",
    "iso:country":"US",
    "sg:address":"16223 Devonshire St",
    "sg:city":"Granada Hills",
    "sg:classifiers":[
        {
            "category":"Wholesale",
            "subcategory":"Metals & Minerals",
            "type":"Manufacturing & Wholesale Goods"
        }
    ],
    "sg:phone":"+1 818 360 8386",
    "sg:postcode":"91344",
    "sg:province":"CA",
    "sg:tags":[
        "specialty"
    ],
    "wof:name":"All Metals Co",
    "wof:placetype":"venue"
},
  "geometry": {"coordinates":[-118.488761,34.257505],"type":"Point"}
}