{
  "type": "Feature",
  "properties": {
    "iso:country":"US",
    "sg:address":"22418 Bonita St",
    "sg:city":"Carson",
    "sg:classifiers":[
        {
            "category":"Education",
            "subcategory":"Music School",
            "type":"Public Place"
        }
    ],
    "sg:phone":"+1 310 834 4571",
    "sg:postcode":"90745",
    "sg:province":"CA",
    "sg:tags":[
        "barrel",
        "drum"
    ],
    "sg:website":"http://www.packageresource.com",
    "wof:name":"Hedwin Corporation",
    "wof:placetype":"venue"
},
  "geometry": {"coordinates":[-118.259249,33.823746],"type":"Point"}
}