{
  "type": "Feature",
  "properties": {
    "iso:country":"US",
    "sg:address":"120 W Channel Islands Blvd",
    "sg:city":"Oxnard",
    "sg:classifiers":[
        {
            "category":"Shopping",
            "subcategory":"Jewelry",
            "type":"Retail Goods"
        }
    ],
    "sg:phone":"+1 805 483 0019",
    "sg:postcode":"93033",
    "sg:province":"CA",
    "sg:tags":[
        "jeweler"
    ],
    "wof:name":"Joyeria 5 De Mayo",
    "wof:placetype":"venue"
},
  "geometry": {"coordinates":[-119.178656,34.173324],"type":"Point"}
}