{
  "type": "Feature",
  "properties": {
    "addr:full":"65 Via Brida Rancho Santa Margarita CA 92688",
    "addr:postcode":"92688",
    "addr:street":"Via Brida",
    "iso:country":"US",
    "sg:address":"65 Via Brida",
    "sg:city":"Rancho Santa Margarita",
    "sg:classifiers":[
        {
            "category":"Manufacturing",
            "subcategory":"Printing",
            "type":"Manufacturing & Wholesale Goods"
        }
    ],
    "sg:phone":"+1 949 766 1545",
    "sg:postcode":"92688",
    "sg:province":"CA",
    "sg:tags":[
        "book"
    ],
    "wof:name":"Permagrin Publishing",
    "wof:placetype":"venue"
},
  "geometry": {"coordinates":[-117.613373,33.65358],"type":"Point"}
}