{
  "type": "Feature",
  "properties": {
    "addr:full":"1760 Airline Hwy Hollister CA 95023",
    "addr:housenumber":"1760",
    "addr:postcode":"hollister ca 95023",
    "addr:street":"Airline Hwy",
    "iso:country":"US",
    "sg:address":"1760 Airline Hwy",
    "sg:city":"Hollister",
    "sg:classifiers":[
        {
            "category":"Shopping",
            "type":"Retail Goods"
        }
    ],
    "sg:phone":"+1 831 636 3737",
    "sg:postcode":"95023",
    "sg:province":"CA",
    "sg:tags":[
        "spa",
        "hot",
        "tub"
    ],
    "wof:name":"Hollister Spa & Stove",
    "wof:placetype":"venue"
},
  "geometry": {"coordinates":[-121.388757,36.836157],"type":"Point"}
}