{
  "type": "Feature",
  "properties": {
    "addr:full":"855 Sebastopol Rd Santa Rosa CA 95407",
    "addr:housenumber":"855",
    "addr:postcode":"95407",
    "addr:street":"Sebastopol Rd",
    "iso:country":"US",
    "sg:address":"855 Sebastopol Rd",
    "sg:city":"Santa Rosa",
    "sg:classifiers":[
        {
            "category":"Restaurant",
            "type":"Food & Drink"
        }
    ],
    "sg:phone":"+1 707 542 3212",
    "sg:postcode":"95407",
    "sg:province":"CA",
    "wof:name":"Foster's Freeze",
    "wof:placetype":"venue"
},
  "geometry": {"coordinates":[-122.731459,38.429222],"type":"Point"}
}