{
  "type": "Feature",
  "properties": {
    "addr:full":"15616 S Broadway St Gardena CA 90248",
    "addr:housenumber":"15616",
    "addr:postcode":"90248",
    "addr:street":"S Broadway St",
    "iso:country":"US",
    "sg:address":"15616 S Broadway St",
    "sg:city":"Gardena",
    "sg:classifiers":[
        {
            "category":"Manufacturing",
            "subcategory":"Apparel",
            "type":"Manufacturing & Wholesale Goods"
        }
    ],
    "sg:phone":"+1 310 217 8853",
    "sg:postcode":"90248",
    "sg:province":"CA",
    "sg:tags":[
        "blouse",
        "outerwear",
        "mfg"
    ],
    "wof:name":"Electric Designs",
    "wof:placetype":"venue"
},
  "geometry": {"coordinates":[-118.27851,33.890283],"type":"Point"}
}