{
  "type": "Feature",
  "properties": {
    "addr:full":"8687 Melrose Ave Los Angeles CA 90069",
    "addr:housenumber":"8687",
    "addr:postcode":"90069",
    "addr:street":"Melrose Ave",
    "iso:country":"US",
    "sg:address":"8687 Melrose Ave",
    "sg:city":"Los Angeles",
    "sg:classifiers":[
        {
            "category":"Manufacturing",
            "subcategory":"Metals",
            "type":"Manufacturing & Wholesale Goods"
        }
    ],
    "sg:phone":"+1 310 854 7262",
    "sg:postcode":"90069",
    "sg:province":"CA",
    "sg:tags":[
        "forging"
    ],
    "wof:name":"Naos Forge Co",
    "wof:placetype":"venue"
},
  "geometry": {"coordinates":[-118.38305800000001,34.081384],"type":"Point"}
}