{
  "type": "Feature",
  "properties": {
    "addr:full":"297 Grass Valley Hwy Auburn CA 95603",
    "addr:housenumber":"297",
    "addr:postcode":"ca 95603",
    "addr:street":"Grass Valley Hwy",
    "iso:country":"US",
    "sg:address":"297 Grass Valley Hwy",
    "sg:city":"Auburn",
    "sg:classifiers":[
        {
            "category":"Building & Trades",
            "subcategory":"Construction",
            "type":"Services"
        }
    ],
    "sg:phone":"+1 530 887 8677",
    "sg:postcode":"95603",
    "sg:province":"CA",
    "sg:tags":[
        "contractor"
    ],
    "wof:name":"AAA Construction",
    "wof:placetype":"venue"
},
  "geometry": {"coordinates":[-121.075965,38.902367],"type":"Point"}
}