{
  "type": "Feature",
  "properties": {
    "addr:full":"1505 Healdsburg Ave Healdsburg CA 95448",
    "addr:housenumber":"1505",
    "addr:postcode":"95448",
    "addr:street":"Healdsburg Ave",
    "iso:country":"US",
    "sg:address":"1505 Healdsburg Ave",
    "sg:city":"Healdsburg",
    "sg:classifiers":[
        {
            "category":"Wholesale",
            "subcategory":"Hardware",
            "type":"Manufacturing & Wholesale Goods"
        }
    ],
    "sg:phone":"+1 707 431 2323",
    "sg:postcode":"95448",
    "sg:province":"CA",
    "sg:tags":[
        "furnace"
    ],
    "wof:name":"Furia Heating & Air Cond",
    "wof:placetype":"venue"
},
  "geometry": {"coordinates":[-122.87267199999999,38.630411],"type":"Point"}
}