{
  "type": "Feature",
  "properties": {
    "iso:country":"US",
    "sg:address":"7126 Amethyst Ave",
    "sg:city":"Alta Loma",
    "sg:classifiers":[
        {
            "category":"Retail",
            "subcategory":"Auto Repair",
            "type":"Services"
        }
    ],
    "sg:phone":"+1 909 980 1766",
    "sg:postcode":"91701",
    "sg:province":"CA",
    "sg:tags":[
        "repairing",
        "automobile",
        "radiator"
    ],
    "wof:name":"Alta Loma Radiator",
    "wof:placetype":"venue"
},
  "geometry": {"coordinates":[-117.598259,34.124953],"type":"Point"}
}