{
  "type": "Feature",
  "properties": {
    "addr:full":"750 W Evelyn St Mountain View CA 94041",
    "addr:housenumber":"750",
    "addr:postcode":"94041",
    "addr:street":"W Evelyn St",
    "iso:country":"US",
    "sg:address":"750 W Evelyn St",
    "sg:city":"Mountain View",
    "sg:classifiers":[
        {
            "category":"Food & Beverages",
            "subcategory":"Liquor & Beverages",
            "type":"Retail Goods"
        },
        {
            "category":"Bars & Pubs",
            "subcategory":"Wine Bar",
            "type":"Food & Drink"
        }
    ],
    "sg:phone":"+1 650 969 3958",
    "sg:postcode":"94041",
    "sg:province":"CA",
    "sg:tags":[
        "beer",
        "spirit"
    ],
    "sg:website":"www.savvycellar.com",
    "wof:name":"Savvy Cellar Wine Bar & Wine Shop",
    "wof:placetype":"venue"
},
  "geometry": {"coordinates":[-122.077877,37.394893],"type":"Point"}
}