{
  "type": "Feature",
  "properties": {
    "iso:country":"US",
    "sg:address":"2534 Northrop Ave",
    "sg:city":"Sacramento",
    "sg:classifiers":[
        {
            "category":"Professional",
            "type":"Services"
        },
        {
            "category":"Food & Beverages",
            "subcategory":"Farmers Market",
            "type":"Retail Goods"
        }
    ],
    "sg:phone":"+1 916 972 1228",
    "sg:postcode":"95825",
    "sg:province":"CA",
    "sg:tags":[
        "field",
        "oil",
        "operator"
    ],
    "wof:name":"Tooley Oil Corporate",
    "wof:placetype":"venue"
},
  "geometry": {"coordinates":[-121.402764,38.5815],"type":"Point"}
}