{
  "type": "Feature",
  "properties": {
    "addr:full":"5770 Hollis St Emeryville CA 94608",
    "addr:housenumber":"5770",
    "addr:postcode":"94608",
    "addr:street":"Hollis St",
    "iso:country":"US",
    "sg:address":"5770 Hollis St",
    "sg:city":"Emeryville",
    "sg:classifiers":[
        {
            "category":"Wholesale",
            "subcategory":"Apparel",
            "type":"Manufacturing & Wholesale Goods"
        }
    ],
    "sg:phone":"+1 510 595 3555",
    "sg:postcode":"94608",
    "sg:province":"CA",
    "sg:tags":[
        "sportswear"
    ],
    "wof:name":"Cantebury Of New Zealand",
    "wof:placetype":"venue"
},
  "geometry": {"coordinates":[-122.289142,37.839529],"type":"Point"}
}