{
  "type": "Feature",
  "properties": {
    "addr:full":"7833 Greenback Ln Citrus Heights CA 95610",
    "addr:housenumber":"7833",
    "addr:postcode":"95610",
    "addr:street":"Greenback Ln",
    "iso:country":"US",
    "sg:address":"7833 Greenback Ln",
    "sg:city":"Citrus Heights",
    "sg:classifiers":[
        {
            "category":"Shopping",
            "subcategory":"Bicycles & Sporting Goods",
            "type":"Retail Goods"
        }
    ],
    "sg:phone":"+1 916 726 5566",
    "sg:postcode":"95610",
    "sg:province":"CA",
    "sg:website":"www.big5sportinggoods.com",
    "wof:name":"Big 5 Sporting Goods",
    "wof:placetype":"venue"
},
  "geometry": {"coordinates":[-121.274002,38.678501],"type":"Point"}
}