{
  "type": "Feature",
  "properties": {
    "iso:country":"US",
    "sg:address":"3 Altarinda Rd",
    "sg:city":"Orinda",
    "sg:classifiers":[
        {
            "category":"Health Services",
            "subcategory":"Doctor",
            "type":"Services"
        }
    ],
    "sg:phone":"+1 925 253 1990",
    "sg:postcode":"94563",
    "sg:province":"CA",
    "sg:tags":[
        "psychiatrist"
    ],
    "wof:name":"Rappaport Bernard MD",
    "wof:placetype":"venue"
},
  "geometry": {"coordinates":[-122.185587,37.882099],"type":"Point"}
}