{
  "type": "Feature",
  "properties": {
    "iso:country":"US",
    "sg:address":"1821 Christi Dr",
    "sg:city":"Vista",
    "sg:classifiers":[
        {
            "category":"Real Estate",
            "subcategory":"Real Estate Agent",
            "type":"Services"
        }
    ],
    "sg:phone":"+1 760 724 6744",
    "sg:postcode":"92084",
    "sg:province":"CA",
    "sg:tags":[
        "agency",
        "rental"
    ],
    "wof:name":"Nancy's Rentals",
    "wof:placetype":"venue"
},
  "geometry": {"coordinates":[-117.243229,33.228461],"type":"Point"}
}