{
  "type": "Feature",
  "properties": {
    "acgov:api":"948.0",
    "acgov:type":"HS",
    "addr:full":"41717 Palm Ave Fremont CA",
    "wof:categories":[
        "education_and_religion:education=school"
    ],
    "wof:name":"Mission San Jose High",
    "wof:placetype":"venue"
},
  "geometry": {"coordinates":[-121.93202073703799,37.54508746788193],"type":"Point"}
}