{
  "type": "Feature",
  "properties": {
    "iso:country":"US",
    "sg:address":"22025 Hawthorne Blvd",
    "sg:city":"Torrance",
    "sg:classifiers":[
        {
            "category":"Shopping",
            "subcategory":"Party Supplies",
            "type":"Retail Goods"
        }
    ],
    "sg:phone":"+1 310 542 7703",
    "sg:postcode":"90503",
    "sg:province":"CA",
    "wof:name":"Party City of Torrance",
    "wof:placetype":"venue"
},
  "geometry": {"coordinates":[-118.351997,33.8274],"type":"Point"}
}