{
  "type": "Feature",
  "properties": {
    "iso:country":"US",
    "sg:address":"1151 Galleria Blvd",
    "sg:city":"Roseville",
    "sg:classifiers":[
        {
            "category":"Restaurant",
            "type":"Food & Drink"
        }
    ],
    "sg:menulink":"http://www.allmenus.com/ca/roseville/229141-hibachi-san/menu/",
    "sg:phone":"+1 916 788 1882",
    "sg:postcode":"95678",
    "sg:province":"CA",
    "sg:tags":[
        "japanese",
        "asian"
    ],
    "wof:name":"Hibachi-San",
    "wof:placetype":"venue"
},
  "geometry": {"coordinates":[-121.265835,38.772203],"type":"Point"}
}