{
  "type": "Feature",
  "properties": {
    "addr:full":"2901 Atlas Ave Sacramento CA 95820",
    "addr:housenumber":"2901",
    "addr:postcode":"95820",
    "addr:street":"Atlas Ave",
    "iso:country":"US",
    "sg:address":"2901 Atlas Ave",
    "sg:city":"Sacramento",
    "sg:classifiers":[
        {
            "category":"Arts & Performance",
            "subcategory":"Music",
            "type":"Entertainment"
        }
    ],
    "sg:phone":"+1 916 952 2853",
    "sg:postcode":"95820",
    "sg:province":"CA",
    "sg:tags":[
        "venue"
    ],
    "sg:website":"www.mariachilosversatiles.com",
    "wof:name":"Mariachi Los Versatiles",
    "wof:placetype":"venue"
},
  "geometry": {"coordinates":[-121.475815,38.531662],"type":"Point"}
}