{
  "type": "Feature",
  "properties": {
    "iso:country":"US",
    "sg:address":"2381 W March Ln",
    "sg:city":"Stockton",
    "sg:classifiers":[
        {
            "category":"Restaurant",
            "type":"Food & Drink"
        }
    ],
    "sg:phone":"+1 209 472 1661",
    "sg:postcode":"95207",
    "sg:province":"CA",
    "wof:name":"Arroyo's Cafe",
    "wof:placetype":"venue"
},
  "geometry": {"coordinates":[-121.335849,37.985635],"type":"Point"}
}