{
  "type": "Feature",
  "properties": {
    "addr:full":"26312 Community Blvd Barstow CA 92311",
    "addr:housenumber":"26312",
    "addr:postcode":"92311",
    "addr:street":"Community Blvd",
    "iso:country":"US",
    "sg:address":"26312 Community Blvd",
    "sg:city":"Barstow",
    "sg:classifiers":[
        {
            "category":"Building & Trades",
            "subcategory":"Construction",
            "type":"Services"
        }
    ],
    "sg:phone":"+1 760 253 5528",
    "sg:postcode":"92311",
    "sg:province":"CA",
    "sg:tags":[
        "sandblasting"
    ],
    "wof:name":"Have A Blast Sandblasting",
    "wof:placetype":"venue"
},
  "geometry": {"coordinates":[-117.08296,34.906866],"type":"Point"}
}