{
  "type": "Feature",
  "properties": {
    "addr:full":"601 S Figueroa Street Los Angeles CA 90017",
    "addr:housenumber":"601",
    "addr:postcode":"90017",
    "addr:street":"S Figueroa Street",
    "iso:country":"US",
    "sg:address":"601 S Figueroa Street",
    "sg:city":"Los Angeles",
    "sg:classifiers":[
        {
            "category":"Professional",
            "subcategory":"Lawyer & Legal Services",
            "type":"Services"
        }
    ],
    "sg:phone":"+1 213 896 3100",
    "sg:postcode":"90017",
    "sg:province":"CA",
    "wof:name":"Higham Terry L Andrews Kurth Llp",
    "wof:placetype":"venue"
},
  "geometry": {"coordinates":[-118.25851299999999,34.050844],"type":"Point"}
}