{
  "type": "Feature",
  "properties": {
    "iso:country":"US",
    "sg:address":"11657 Adams St",
    "sg:city":"Yucaipa",
    "sg:classifiers":[
        {
            "category":"Health Services",
            "subcategory":"Clinic",
            "type":"Services"
        }
    ],
    "sg:phone":"+1 909 797 3923",
    "sg:postcode":"92399",
    "sg:province":"CA",
    "sg:tags":[
        "welfare"
    ],
    "wof:name":"Professional Medical Billing S",
    "wof:placetype":"venue"
},
  "geometry": {"coordinates":[-117.03550199999999,34.042276],"type":"Point"}
}