{
  "type": "Feature",
  "properties": {
    "addr:full":"1885 E Washington Blvd Pasadena CA 91104",
    "addr:housenumber":"1885",
    "addr:postcode":"91104",
    "addr:street":"E Washington Blvd",
    "iso:country":"US",
    "sg:address":"1885 E Washington Blvd",
    "sg:city":"Pasadena",
    "sg:classifiers":[
        {
            "category":"Shopping",
            "subcategory":"Florist",
            "type":"Retail Goods"
        }
    ],
    "sg:phone":"+1 626 794 7125",
    "sg:postcode":"91104",
    "sg:province":"CA",
    "sg:tags":[
        "nursery",
        "gardening"
    ],
    "wof:name":"Tropical Florist",
    "wof:placetype":"venue"
},
  "geometry": {"coordinates":[-118.111639,34.169141],"type":"Point"}
}