{
  "type": "Feature",
  "properties": {
    "addr:full":"7500 Imperial Hwy Downey CA 90242",
    "addr:housenumber":"7500",
    "addr:postcode":"90242",
    "addr:street":"Imperial Hwy",
    "iso:country":"US",
    "sg:address":"7500 Imperial Hwy",
    "sg:city":"Downey",
    "sg:classifiers":[
        {
            "category":"Government",
            "subcategory":"Office",
            "type":"Public Place"
        }
    ],
    "sg:phone":"+1 562 803 7130",
    "sg:postcode":"90242",
    "sg:province":"CA",
    "wof:name":"Los Angeles County Defender",
    "wof:placetype":"venue"
},
  "geometry": {"coordinates":[-118.156851,33.926439],"type":"Point"}
}