{
  "type": "Feature",
  "properties": {
    "addr:full":"1461 N Ranger Dr Covina CA 91722",
    "addr:housenumber":"1461",
    "addr:postcode":"91722",
    "addr:street":"N Ranger Dr",
    "iso:country":"US",
    "sg:address":"1461 N Ranger Dr",
    "sg:city":"Covina",
    "sg:classifiers":[
        {
            "category":"Retail",
            "subcategory":"Auto Repair",
            "type":"Services"
        }
    ],
    "sg:phone":"+1 626 339 5898",
    "sg:postcode":"91722",
    "sg:province":"CA",
    "sg:tags":[
        "repairing",
        "automobile"
    ],
    "wof:name":"Ranger Auto & Diesel",
    "wof:placetype":"venue"
},
  "geometry": {"coordinates":[-117.886428,34.103237],"type":"Point"}
}