{
  "type": "Feature",
  "properties": {
    "addr:full":"622 Osage St Spring Valley CA 91977",
    "addr:housenumber":"622",
    "addr:postcode":"91977",
    "addr:street":"Osage St",
    "iso:country":"US",
    "sg:address":"622 Osage St",
    "sg:city":"Spring Valley",
    "sg:classifiers":[
        {
            "category":"Manufacturing",
            "subcategory":"Furniture",
            "type":"Manufacturing & Wholesale Goods"
        }
    ],
    "sg:phone":"+1 619 470 4097",
    "sg:postcode":"91977",
    "sg:province":"CA",
    "sg:tags":[
        "mfg"
    ],
    "wof:name":"Star Display",
    "wof:placetype":"venue"
},
  "geometry": {"coordinates":[-117.019284,32.7075],"type":"Point"}
}