{
  "type": "Feature",
  "properties": {
    "addr:full":"301 H St Bakersfield CA 93304",
    "addr:housenumber":"301",
    "addr:postcode":"93304",
    "addr:street":"H St",
    "iso:country":"US",
    "sg:address":"301 H St",
    "sg:city":"Bakersfield",
    "sg:classifiers":[
        {
            "category":"Building & Trades",
            "subcategory":"Cleaning & Sanitation",
            "type":"Services"
        }
    ],
    "sg:phone":"+1 661 325 4906",
    "sg:postcode":"93304",
    "sg:province":"CA",
    "sg:tags":[
        "polishing",
        "waxing",
        "floor"
    ],
    "wof:name":"KERN Commercial Cleaning",
    "wof:placetype":"venue"
},
  "geometry": {"coordinates":[-119.021276,35.35985],"type":"Point"}
}