{
  "type": "Feature",
  "properties": {
    "iso:country":"US",
    "sg:address":"1131 Walnut Canyon Rd",
    "sg:city":"Moorpark",
    "sg:classifiers":[
        {
            "category":"Building & Trades",
            "subcategory":"Construction",
            "type":"Services"
        }
    ],
    "sg:phone":"+1 805 529 3036",
    "sg:postcode":"93021",
    "sg:province":"CA",
    "sg:tags":[
        "maker",
        "cabinet"
    ],
    "wof:name":"Carpenters A Printist",
    "wof:placetype":"venue"
},
  "geometry": {"coordinates":[-118.88010800000001,34.293347],"type":"Point"}
}