{
  "type": "Feature",
  "properties": {
    "addr:full":"1299 Columbia Ave Riverside CA 92507",
    "addr:housenumber":"1299",
    "addr:postcode":"92507",
    "addr:street":"Columbia Ave",
    "iso:country":"US",
    "sg:address":"1299 Columbia Ave",
    "sg:city":"Riverside",
    "sg:classifiers":[
        {
            "category":"Organizations",
            "subcategory":"Non-profit Organization",
            "type":"Services"
        }
    ],
    "sg:phone":"+1 951 787 9907",
    "sg:postcode":"92507",
    "sg:province":"CA",
    "wof:name":"Set Free Prison Ministries",
    "wof:placetype":"venue"
},
  "geometry": {"coordinates":[-117.33429599999999,34.001143],"type":"Point"}
}