{
  "type": "Feature",
  "properties": {
    "iso:country":"US",
    "sg:address":"751 Blossom Hill Rd Ste A-1",
    "sg:city":"Los Gatos",
    "sg:classifiers":[
        {
            "category":"Personal",
            "subcategory":"Massage",
            "type":"Services"
        }
    ],
    "sg:phone":"+1 408 839 4453",
    "sg:postcode":"95032",
    "sg:province":"CA",
    "wof:name":"Julia Foley, CMT",
    "wof:placetype":"venue"
},
  "geometry": {"coordinates":[-121.960795,37.235556],"type":"Point"}
}