{
  "type": "Feature",
  "properties": {
    "addr:full":"3120 Euclid Ave San Diego CA 92105",
    "addr:housenumber":"3120",
    "addr:postcode":"92105",
    "addr:street":"Euclid Ave",
    "iso:country":"US",
    "sg:address":"3120 Euclid Ave",
    "sg:city":"San Diego",
    "sg:classifiers":[
        {
            "category":"Coffee & Tea",
            "type":"Food & Drink"
        },
        {
            "category":"Restaurant",
            "type":"Food & Drink"
        }
    ],
    "sg:phone":"+1 619 284 0206",
    "sg:postcode":"92105",
    "sg:province":"CA",
    "sg:tags":[
        "traditional",
        "american"
    ],
    "sg:website":"www.natescafe.com",
    "wof:name":"Nate's Cafe",
    "wof:placetype":"venue"
},
  "geometry": {"coordinates":[-117.09223799999999,32.737684],"type":"Point"}
}