{
  "type": "Feature",
  "properties": {
    "addr:full":"4527 Montgomery Dr Santa Rosa CA 95409",
    "addr:housenumber":"4527",
    "addr:postcode":"95409",
    "addr:street":"Montgomery Dr",
    "iso:country":"US",
    "sg:address":"4527 Montgomery Dr",
    "sg:city":"Santa Rosa",
    "sg:classifiers":[
        {
            "category":"Health Services",
            "subcategory":"Health Practitioner",
            "type":"Services"
        }
    ],
    "sg:phone":"+1 707 546 0400",
    "sg:postcode":"95409",
    "sg:province":"CA",
    "sg:tags":[
        "psychologist"
    ],
    "wof:name":"Catherine Barnard PHD",
    "wof:placetype":"venue"
},
  "geometry": {"coordinates":[-122.671237,38.457469],"type":"Point"}
}