{
  "type": "Feature",
  "properties": {
    "iso:country":"US",
    "sg:address":"2060 S Hacienda Blvd",
    "sg:city":"Hacienda Heights",
    "sg:classifiers":[
        {
            "category":"Shopping",
            "subcategory":"Pharmacy",
            "type":"Retail Goods"
        }
    ],
    "sg:phone":"+1 626 333 5642",
    "sg:postcode":"91745",
    "sg:province":"CA",
    "wof:name":"Rite Aid Pharmacy",
    "wof:placetype":"venue"
},
  "geometry": {"coordinates":[-117.967677,33.996819],"type":"Point"}
}