{
  "type": "Feature",
  "properties": {
    "addr:full":"23210 del Lago Dr Laguna Hills CA 92653",
    "addr:housenumber":"23210",
    "addr:postcode":"92653",
    "addr:street":"Del Lago Dr",
    "iso:country":"US",
    "sg:address":"23210 del Lago Dr",
    "sg:city":"Laguna Hills",
    "sg:classifiers":[
        {
            "category":"Wholesale",
            "subcategory":"Medical Equipment & Supplies",
            "type":"Manufacturing & Wholesale Goods"
        }
    ],
    "sg:phone":"+1 949 770 9029",
    "sg:postcode":"92653",
    "sg:province":"CA",
    "sg:tags":[
        "hospital"
    ],
    "sg:website":"www.taggmed.com",
    "wof:name":"Tagg Industries",
    "wof:placetype":"venue"
},
  "geometry": {"coordinates":[-117.72677,33.626588],"type":"Point"}
}