{
  "type": "Feature",
  "properties": {
    "iso:country":"US",
    "sg:address":"5212 Katella Ave",
    "sg:city":"Los Alamitos",
    "sg:classifiers":[
        {
            "category":"Banks & Credit Unions",
            "subcategory":"Investment Brokerage",
            "type":"Services"
        }
    ],
    "sg:phone":"+1 562 594 4454",
    "sg:postcode":"90720",
    "sg:province":"CA",
    "sg:tags":[
        "consultant",
        "planning",
        "financial"
    ],
    "wof:name":"Fernandez Financial Advisory",
    "wof:placetype":"venue"
},
  "geometry": {"coordinates":[-118.043298,33.803021],"type":"Point"}
}