{
  "type": "Feature",
  "properties": {
    "addr:full":"619 N Broadway Santa Maria CA 93454",
    "addr:housenumber":"619",
    "addr:postcode":"93454",
    "addr:street":"N Broadway",
    "iso:country":"US",
    "sg:address":"619 N Broadway",
    "sg:city":"Santa Maria",
    "sg:classifiers":[
        {
            "category":"Autos & Motor Vehicles",
            "subcategory":"Automobile Sales",
            "type":"Retail Goods"
        }
    ],
    "sg:phone":"+1 805 928 4220",
    "sg:postcode":"93454",
    "sg:province":"CA",
    "sg:tags":[
        "passenger",
        "used",
        "rental",
        "dealer",
        "car"
    ],
    "wof:name":"Life Style Auto Rental & Sales",
    "wof:placetype":"venue"
},
  "geometry": {"coordinates":[-120.435897,34.959335],"type":"Point"}
}