{
  "type": "Feature",
  "properties": {
    "iso:country":"US",
    "sg:address":"850 E Jefferson Blvd",
    "sg:city":"Los Angeles",
    "sg:classifiers":[
        {
            "category":"Retail",
            "subcategory":"Auto Repair",
            "type":"Services"
        }
    ],
    "sg:phone":"+1 323 231 2787",
    "sg:postcode":"90011",
    "sg:province":"CA",
    "sg:tags":[
        "muffler",
        "exhaust",
        "system"
    ],
    "wof:name":"Mufflers Zone Sport",
    "wof:placetype":"venue"
},
  "geometry": {"coordinates":[-118.261449,34.013729],"type":"Point"}
}