{
  "type": "Feature",
  "properties": {
    "addr:full":"19319 Carmenita Rd Cerritos CA 90703",
    "addr:postcode":"19319;ca 90703",
    "addr:street":"Carmenita Rd",
    "iso:country":"US",
    "sg:address":"19319 Carmenita Rd",
    "sg:city":"Cerritos",
    "sg:classifiers":[
        {
            "category":"Education",
            "subcategory":"School",
            "type":"Public Place"
        }
    ],
    "sg:phone":"+1 562 865 2262",
    "sg:postcode":"90703",
    "sg:province":"CA",
    "wof:name":"Jaeneung Educational Institute",
    "wof:placetype":"venue"
},
  "geometry": {"coordinates":[-118.046216,33.855768],"type":"Point"}
}