{
  "type": "Feature",
  "properties": {
    "iso:country":"US",
    "sg:address":"1432 Cuernavaca Ct",
    "sg:city":"San Jose",
    "sg:classifiers":[
        {
            "category":"Wholesale",
            "subcategory":"Construction Materials",
            "type":"Manufacturing & Wholesale Goods"
        }
    ],
    "sg:phone":"+1 408 927 6682",
    "sg:postcode":"95120",
    "sg:province":"CA",
    "sg:tags":[
        "consulting",
        "business"
    ],
    "wof:name":"Nova Spectrum",
    "wof:placetype":"venue"
},
  "geometry": {"coordinates":[-121.892133,37.225539],"type":"Point"}
}