{
  "type": "Feature",
  "properties": {
    "iso:country":"US",
    "sg:address":"541 Jefferson Ave",
    "sg:city":"Redwood City",
    "sg:classifiers":[
        {
            "category":"Health Services",
            "subcategory":"Chiropractor",
            "type":"Services"
        }
    ],
    "sg:phone":"+1 650 365 2225",
    "sg:postcode":"94063",
    "sg:province":"CA",
    "wof:name":"Sport Tech Chiropractic",
    "wof:placetype":"venue"
},
  "geometry": {"coordinates":[-122.228272,37.4889],"type":"Point"}
}