{
  "type": "Feature",
  "properties": {
    "addr:full":"3427 Crenshaw Blvd Los Angeles CA 90016",
    "addr:housenumber":"3427",
    "addr:postcode":"90016",
    "addr:street":"Crenshaw Blvd",
    "iso:country":"US",
    "sg:address":"3427 Crenshaw Blvd",
    "sg:city":"Los Angeles",
    "sg:classifiers":[
        {
            "category":"Shopping",
            "subcategory":"Clothing, Apparel, & Fashions",
            "type":"Retail Goods"
        }
    ],
    "sg:phone":"+1 323 735 3947",
    "sg:postcode":"90016",
    "sg:province":"CA",
    "sg:tags":[
        "sportswear"
    ],
    "wof:name":"Baby Juniors",
    "wof:placetype":"venue"
},
  "geometry": {"coordinates":[-118.33517399999999,34.024238],"type":"Point"}
}