{
  "type": "Feature",
  "properties": {
    "addr:full":"970 Tennessee St San Francisco CA 94107",
    "addr:housenumber":"970",
    "addr:postcode":"94107",
    "addr:street":"Tennessee St",
    "iso:country":"US",
    "sg:address":"970 Tennessee St",
    "sg:city":"San Francisco",
    "sg:classifiers":[
        {
            "category":"Park",
            "type":"Public Place"
        }
    ],
    "sg:phone":"+1 415 826 1213",
    "sg:postcode":"94107",
    "sg:province":"CA",
    "wof:name":"Friends of Esprit Park",
    "wof:placetype":"venue"
},
  "geometry": {"coordinates":[-122.389416,37.759513],"type":"Point"}
}