{
  "type": "Feature",
  "properties": {
    "addr:full":"11400 Atwood Rd Auburn CA 95603",
    "addr:housenumber":"11400",
    "addr:postcode":"ca 95603",
    "addr:street":"Atwood Rd",
    "iso:country":"US",
    "sg:address":"11400 Atwood Rd",
    "sg:city":"Auburn",
    "sg:classifiers":[
        {
            "category":"Manufacturing",
            "subcategory":"Food",
            "type":"Manufacturing & Wholesale Goods"
        }
    ],
    "sg:phone":"+1 530 885 1298",
    "sg:postcode":"95603",
    "sg:province":"CA",
    "sg:tags":[
        "preparation",
        "mfg"
    ],
    "wof:name":"Judicial Flavors",
    "wof:placetype":"venue"
},
  "geometry": {"coordinates":[-121.10682799999999,38.934651],"type":"Point"}
}