{
  "type": "Feature",
  "properties": {
    "iso:country":"US",
    "sg:address":"6077 Van Nuys Blvd",
    "sg:city":"Van Nuys",
    "sg:classifiers":[
        {
            "category":"Insurance",
            "subcategory":"Hazard Insurance",
            "type":"Services"
        }
    ],
    "sg:phone":"+1 818 779 7774",
    "sg:postcode":"91401",
    "sg:province":"CA",
    "sg:tags":[
        "bond"
    ],
    "wof:name":"Bail Bond Girl-Garcia",
    "wof:placetype":"venue"
},
  "geometry": {"coordinates":[-118.448786,34.1808],"type":"Point"}
}