{
  "type": "Feature",
  "properties": {
    "iso:country":"US",
    "sg:address":"4201 Torrance Blvd Suite 360",
    "sg:city":"Torrance",
    "sg:classifiers":[
        {
            "category":"Health Services",
            "subcategory":"Doctor",
            "type":"Services"
        }
    ],
    "sg:phone":"+1 310 543 1050",
    "sg:postcode":"90503",
    "sg:province":"CA",
    "wof:name":"Chris Tsuneishi, MD",
    "wof:placetype":"venue"
},
  "geometry": {"coordinates":[-118.35873,33.838409],"type":"Point"}
}