{
  "type": "Feature",
  "properties": {
    "iso:country":"US",
    "sg:address":"1920 W 1st St",
    "sg:city":"Santa Ana",
    "sg:classifiers":[
        {
            "category":"Restaurant",
            "type":"Food & Drink"
        }
    ],
    "sg:phone":"+1 714 834 1310",
    "sg:postcode":"92703",
    "sg:province":"CA",
    "sg:tags":[
        "mexican"
    ],
    "wof:name":"El Bukanas",
    "wof:placetype":"venue"
},
  "geometry": {"coordinates":[-117.89564,33.745186],"type":"Point"}
}