{
  "type": "Feature",
  "properties": {
    "iso:country":"US",
    "sg:address":"8348 Eucalyptus Ave",
    "sg:city":"California City",
    "sg:classifiers":[
        {
            "category":"Shopping",
            "subcategory":"Hobbies, Toys, & Games",
            "type":"Retail Goods"
        }
    ],
    "sg:phone":"+1 760 373 8763",
    "sg:postcode":"93505",
    "sg:province":"CA",
    "wof:name":"Kim Cornelia",
    "wof:placetype":"venue"
},
  "geometry": {"coordinates":[-117.97562499999999,35.12148],"type":"Point"}
}