{
  "type": "Feature",
  "properties": {
    "addr:full":"2707 S Grand Ave Los Angeles CA 90007",
    "addr:housenumber":"2707",
    "addr:postcode":"90007",
    "addr:street":"S Grand Ave",
    "iso:country":"US",
    "sg:address":"2707 S Grand Ave",
    "sg:city":"Los Angeles",
    "sg:classifiers":[
        {
            "category":"Social Services",
            "type":"Services"
        }
    ],
    "sg:phone":"+1 213 744 5601",
    "sg:postcode":"90007",
    "sg:province":"CA",
    "sg:tags":[
        "administrative"
    ],
    "wof:name":"Public Social Services",
    "wof:placetype":"venue"
},
  "geometry": {"coordinates":[-118.27334,34.024937],"type":"Point"}
}