{
  "type": "Feature",
  "properties": {
    "iso:country":"US",
    "sg:address":"10061 Talbert Ave Ste 102",
    "sg:city":"Fountain Valley",
    "sg:classifiers":[
        {
            "category":"Banks & Credit Unions",
            "subcategory":"Financial Services",
            "type":"Services"
        }
    ],
    "sg:phone":"+1 714 594 1414",
    "sg:postcode":"92708",
    "sg:province":"CA",
    "sg:tags":[
        "broker",
        "mortgage"
    ],
    "wof:name":"Intercoastal Funding Corporation",
    "wof:placetype":"venue"
},
  "geometry": {"coordinates":[-117.953003,33.7019],"type":"Point"}
}