{
  "type": "Feature",
  "properties": {
    "iso:country":"US",
    "sg:address":"1610 Kathleen Ave",
    "sg:city":"Sacramento",
    "sg:classifiers":[
        {
            "category":"Autos & Motor Vehicles",
            "subcategory":"Auto Supplies",
            "type":"Retail Goods"
        },
        {
            "category":"Structure",
            "subcategory":"Warehouse",
            "type":"Public Place"
        }
    ],
    "sg:phone":"+1 916 374 9065",
    "sg:postcode":"95815",
    "sg:province":"CA",
    "sg:tags":[
        "warehouses-merchandise",
        "warehouses-public-commercial",
        "tire"
    ],
    "wof:name":"North State Bandag",
    "wof:placetype":"venue"
},
  "geometry": {"coordinates":[-121.429472,38.621832],"type":"Point"}
}