{
  "type": "Feature",
  "properties": {
    "iso:country":"US",
    "sg:address":"1604 Montebello Town Center",
    "sg:city":"Montebello",
    "sg:classifiers":[
        {
            "category":"Restaurant",
            "type":"Food & Drink"
        }
    ],
    "sg:phone":"+1 323 727 9946",
    "sg:postcode":"90640",
    "sg:province":"CA",
    "wof:name":"Great Khan's Mongolian",
    "wof:placetype":"venue"
},
  "geometry": {"coordinates":[-118.08248399999999,34.037558],"type":"Point"}
}