{
  "type": "Feature",
  "properties": {
    "iso:country":"US",
    "sg:address":"509 N Harbor Blvd",
    "sg:city":"Fullerton",
    "sg:classifiers":[
        {
            "category":"Professional",
            "type":"Services"
        }
    ],
    "sg:phone":"+1 714 773 5012",
    "sg:postcode":"92832",
    "sg:province":"CA",
    "wof:name":"Allan Proctor - State Farm Insurance",
    "wof:placetype":"venue"
},
  "geometry": {"coordinates":[-117.924352,33.874345],"type":"Point"}
}