{
  "type": "Feature",
  "properties": {
    "addr:full":"8233 Station Village Ln Ste 2111 San Diego CA 92108",
    "addr:housenumber":"8233",
    "addr:postcode":"92108",
    "addr:street":"Station Village Ln Ste 2111",
    "iso:country":"US",
    "sg:address":"8233 Station Village Ln Ste 2111",
    "sg:city":"San Diego",
    "sg:classifiers":[
        {
            "category":"Personal",
            "subcategory":"Beauty Salon",
            "type":"Services"
        }
    ],
    "sg:phone":"+1 619 846 5445",
    "sg:postcode":"92108",
    "sg:province":"CA",
    "sg:tags":[
        "hair"
    ],
    "sg:website":"www.lillysalon.com/",
    "wof:name":"Lilly Beauty Salon",
    "wof:placetype":"venue"
},
  "geometry": {"coordinates":[-117.14752,32.772853],"type":"Point"}
}