{
  "type": "Feature",
  "properties": {
    "addr:full":"1841 Lerner Ln Santa Ana CA 92705",
    "addr:housenumber":"1841",
    "addr:postcode":"92705",
    "addr:street":"Lerner Ln",
    "iso:country":"US",
    "sg:address":"1841 Lerner Ln",
    "sg:city":"Santa Ana",
    "sg:classifiers":[
        {
            "category":"Shopping",
            "subcategory":"Gifts & Souvenirs",
            "type":"Retail Goods"
        }
    ],
    "sg:phone":"+1 714 289 0324",
    "sg:postcode":"92705",
    "sg:province":"CA",
    "wof:name":"Copper West",
    "wof:placetype":"venue"
},
  "geometry": {"coordinates":[-117.788304,33.753843],"type":"Point"}
}