{
  "type": "Feature",
  "properties": {
    "iso:country":"US",
    "sg:address":"4 Starview Ct",
    "sg:city":"Sacramento",
    "sg:classifiers":[
        {
            "category":"Manufacturing",
            "subcategory":"Motor Vehicles & Parts",
            "type":"Manufacturing & Wholesale Goods"
        }
    ],
    "sg:phone":"+1 916 394 1913",
    "sg:postcode":"95823",
    "sg:province":"CA",
    "sg:tags":[
        "mfg"
    ],
    "wof:name":"N Jacks Jump",
    "wof:placetype":"venue"
},
  "geometry": {"coordinates":[-121.429276,38.446191],"type":"Point"}
}