{
  "type": "Feature",
  "properties": {
    "addr:full":"41 Maitland Dr Alameda CA 94502",
    "addr:housenumber":"41",
    "addr:postcode":"94502",
    "addr:street":"Maitland Dr",
    "iso:country":"US",
    "sg:address":"41 Maitland Dr",
    "sg:city":"Alameda",
    "sg:classifiers":[
        {
            "category":"Taxi",
            "type":"Transportation"
        }
    ],
    "sg:phone":"+1 510 865 1358",
    "sg:postcode":"94502",
    "sg:province":"CA",
    "sg:tags":[
        "taxicab"
    ],
    "wof:name":"Skyline Cab Co",
    "wof:placetype":"venue"
},
  "geometry": {"coordinates":[-122.238331,37.738721],"type":"Point"}
}