{
  "type": "Feature",
  "properties": {
    "addr:full":"214 John St Salinas CA 93901",
    "addr:housenumber":"214",
    "addr:postcode":"93901",
    "addr:street":"John St",
    "iso:country":"US",
    "sg:address":"214 John St",
    "sg:city":"Salinas",
    "sg:classifiers":[
        {
            "category":"Travel",
            "subcategory":"Hotels & Motels",
            "type":"Entertainment"
        }
    ],
    "sg:phone":"+1 831 424 6468",
    "sg:postcode":"93901",
    "sg:province":"CA",
    "wof:name":"Economy Inn",
    "wof:placetype":"venue"
},
  "geometry": {"coordinates":[-121.64894200000001,36.669702],"type":"Point"}
}