{
  "type": "Feature",
  "properties": {
    "iso:country":"US",
    "sg:address":"406 S Fern Hill Ln",
    "sg:city":"Anaheim",
    "sg:classifiers":[
        {
            "category":"Professional",
            "type":"Services"
        }
    ],
    "sg:phone":"+1 714 921 8992",
    "sg:postcode":"92807",
    "sg:province":"CA",
    "wof:name":"Davis Marlene Taylor Fmly Ltd",
    "wof:placetype":"venue"
},
  "geometry": {"coordinates":[-117.828615,33.83813],"type":"Point"}
}