{
  "type": "Feature",
  "properties": {
    "addr:full":"3645 San Fernando Rd Glendale CA 91204",
    "addr:housenumber":"3645",
    "addr:postcode":"91204",
    "addr:street":"San Fernando Rd",
    "iso:country":"US",
    "sg:address":"3645 San Fernando Rd",
    "sg:city":"Glendale",
    "sg:classifiers":[
        {
            "category":"Professional",
            "subcategory":"Business Services",
            "type":"Services"
        }
    ],
    "sg:phone":"+1 818 265 2880",
    "sg:postcode":"91204",
    "sg:province":"CA",
    "wof:name":"Action Demos",
    "wof:placetype":"venue"
},
  "geometry": {"coordinates":[-118.252746,34.12176],"type":"Point"}
}