{
  "type": "Feature",
  "properties": {
    "addr:full":"12449 Foothill Blvd Rancho Cucamonga CA 91730",
    "addr:housenumber":"12449",
    "addr:postcode":"91730",
    "addr:street":"Foothill Blvd",
    "iso:country":"US",
    "sg:address":"12449 Foothill Blvd",
    "sg:city":"Rancho Cucamonga",
    "sg:classifiers":[
        {
            "category":"Shopping",
            "subcategory":"Bicycles & Sporting Goods",
            "type":"Retail Goods"
        }
    ],
    "sg:phone":"+1 909 987 4321",
    "sg:postcode":"91730",
    "sg:province":"CA",
    "wof:name":"Sport Chalet Inc",
    "wof:placetype":"venue"
},
  "geometry": {"coordinates":[-117.534549,34.106249],"type":"Point"}
}