{
  "type": "Feature",
  "properties": {
    "iso:country":"US",
    "sg:address":"3026 Nebraska Ave",
    "sg:city":"Santa Monica",
    "sg:classifiers":[
        {
            "category":"Wholesale",
            "subcategory":"Apparel",
            "type":"Manufacturing & Wholesale Goods"
        }
    ],
    "sg:phone":"+1 310 998 5740",
    "sg:postcode":"90404",
    "sg:province":"CA",
    "wof:name":"Lounge Acts",
    "wof:placetype":"venue"
},
  "geometry": {"coordinates":[-118.463253,34.031685],"type":"Point"}
}