{
  "type": "Feature",
  "properties": {
    "addr:full":"3026 Nebraska Ave Santa Monica CA 90404",
    "addr:housenumber":"3026",
    "addr:postcode":"90404",
    "addr:street":"Nebraska Ave",
    "iso:country":"US",
    "sg:address":"3026 Nebraska Ave",
    "sg:city":"Santa Monica",
    "sg:classifiers":[
        {
            "category":"Wholesale",
            "subcategory":"Apparel",
            "type":"Manufacturing & Wholesale Goods"
        }
    ],
    "sg:phone":"+1 310 998 5740",
    "sg:postcode":"90404",
    "sg:province":"CA",
    "wof:name":"Lounge Acts",
    "wof:placetype":"venue"
},
  "geometry": {"coordinates":[-118.46325299999999,34.031685],"type":"Point"}
}