{
  "type": "Feature",
  "properties": {
    "addr:full":"4004 Fairwood St Bakersfield CA 93306",
    "addr:housenumber":"4004",
    "addr:postcode":"93306",
    "addr:street":"Fairwood St",
    "iso:country":"US",
    "sg:address":"4004 Fairwood St",
    "sg:city":"Bakersfield",
    "sg:classifiers":[
        {
            "category":"Manufacturing",
            "subcategory":"Furniture",
            "type":"Manufacturing & Wholesale Goods"
        }
    ],
    "sg:phone":"+1 661 871 0913",
    "sg:postcode":"93306",
    "sg:province":"CA",
    "sg:tags":[
        "upholstered",
        "household",
        "metal",
        "mfg"
    ],
    "sg:website":"www.jenniecompany.com",
    "wof:name":"Jennie Co",
    "wof:placetype":"venue"
},
  "geometry": {"coordinates":[-118.944087,35.410421],"type":"Point"}
}