{
  "type": "Feature",
  "properties": {
    "addr:full":"1308 Factory Pl Los Angeles CA 90013",
    "addr:housenumber":"1308",
    "addr:postcode":"90013",
    "addr:street":"Factory Pl",
    "iso:country":"US",
    "sg:address":"1308 Factory Pl",
    "sg:city":"Los Angeles",
    "sg:classifiers":[
        {
            "category":"Freight",
            "type":"Transportation"
        }
    ],
    "sg:phone":"+1 213 955 0062",
    "sg:postcode":"90013",
    "sg:province":"CA",
    "sg:tags":[
        "cargo",
        "loading",
        "unloading"
    ],
    "wof:name":"California Container Lifters",
    "wof:placetype":"venue"
},
  "geometry": {"coordinates":[-118.23606100000001,34.039077],"type":"Point"}
}