{
  "type": "Feature",
  "properties": {
    "iso:country":"US",
    "sg:address":"3230 N Golden Ave",
    "sg:city":"Long Beach",
    "sg:classifiers":[
        {
            "category":"Shopping",
            "subcategory":"Gifts & Souvenirs",
            "type":"Retail Goods"
        }
    ],
    "sg:phone":"+1 562 427 3968",
    "sg:postcode":"90806",
    "sg:province":"CA",
    "wof:name":"Greene & Co",
    "wof:placetype":"venue"
},
  "geometry": {"coordinates":[-118.202325,33.817812],"type":"Point"}
}