{
  "type": "Feature",
  "properties": {
    "iso:country":"US",
    "sg:address":"141 Duesenberg Dr",
    "sg:city":"Westlake Village",
    "sg:classifiers":[
        {
            "category":"Professional",
            "subcategory":"Lawyer & Legal Services",
            "type":"Services"
        }
    ],
    "sg:phone":"+1 805 496 5004",
    "sg:postcode":"91362",
    "sg:province":"CA",
    "sg:tags":[
        "attorney"
    ],
    "wof:name":"Robert D Rosso",
    "wof:placetype":"venue"
},
  "geometry": {"coordinates":[-118.832436,34.171108],"type":"Point"}
}