{
  "type": "Feature",
  "properties": {
    "iso:country":"US",
    "sg:address":"11070 White Rock Road",
    "sg:city":"Rancho Cordova",
    "sg:classifiers":[
        {
            "category":"Professional",
            "type":"Services"
        }
    ],
    "sg:phone":"+1 916 638 4363",
    "sg:postcode":"95670",
    "sg:province":"CA",
    "sg:tags":[
        "caterer"
    ],
    "wof:name":"Hannibals Restaurant",
    "wof:placetype":"venue"
},
  "geometry": {"coordinates":[-121.27392399999999,38.589597],"type":"Point"}
}