{
  "type": "Feature",
  "properties": {
    "iso:country":"US",
    "sg:address":"2063 E Foothill Blvd",
    "sg:city":"Pasadena",
    "sg:classifiers":[
        {
            "category":"Health Services",
            "subcategory":"Dentist",
            "type":"Services"
        }
    ],
    "sg:phone":"+1 626 449 1919",
    "sg:postcode":"91107",
    "sg:province":"CA",
    "wof:name":"Foothill Dental Group",
    "wof:placetype":"venue"
},
  "geometry": {"coordinates":[-118.107614,34.150095],"type":"Point"}
}