{
  "type": "Feature",
  "properties": {
    "iso:country":"US",
    "sg:address":"12747 Ventura Blvd",
    "sg:city":"Studio City",
    "sg:classifiers":[
        {
            "category":"Shopping",
            "subcategory":"Beauty & Cosmetics",
            "type":"Retail Goods"
        },
        {
            "category":"Personal",
            "subcategory":"Skin Care",
            "type":"Services"
        }
    ],
    "sg:phone":"+1 818 760 2200",
    "sg:postcode":"91604",
    "sg:province":"CA",
    "sg:tags":[
        "supply"
    ],
    "sg:website":"www.skinbodylounge.com/",
    "wof:name":"Skin Body Lounge",
    "wof:placetype":"venue"
},
  "geometry": {"coordinates":[-118.411018,34.144759],"type":"Point"}
}