{
  "type": "Feature",
  "properties": {
    "iso:country":"US",
    "sg:address":"4612 W Jefferson Blvd",
    "sg:city":"Los Angeles",
    "sg:classifiers":[
        {
            "category":"Building & Trades",
            "subcategory":"Construction",
            "type":"Services"
        }
    ],
    "sg:phone":"+1 323 730 1886",
    "sg:postcode":"90016",
    "sg:province":"CA",
    "sg:tags":[
        "maker",
        "cabinet"
    ],
    "wof:name":"Sawdust",
    "wof:placetype":"venue"
},
  "geometry": {"coordinates":[-118.34698299999999,34.025461],"type":"Point"}
}