{
  "type": "Feature",
  "properties": {
    "iso:country":"US",
    "sg:address":"42410 Bob Hope Dr",
    "sg:city":"Rancho Mirage",
    "sg:classifiers":[
        {
            "category":"Restaurant",
            "type":"Food & Drink"
        }
    ],
    "sg:phone":"+1 760 340 5311",
    "sg:postcode":"92270",
    "sg:province":"CA",
    "sg:tags":[
        "delicatessen"
    ],
    "wof:name":"Bouchee' Fine Foods",
    "wof:placetype":"venue"
},
  "geometry": {"coordinates":[-116.408253,33.738067],"type":"Point"}
}