{
  "type": "Feature",
  "properties": {
    "addr:full":"31880 Wrightwood Rd Bonsall CA 92003",
    "addr:postcode":"31880;92003",
    "addr:street":"Wrightwood Rd",
    "iso:country":"US",
    "sg:address":"31880 Wrightwood Rd",
    "sg:city":"Bonsall",
    "sg:classifiers":[
        {
            "category":"Personal",
            "subcategory":"Beauty Salon",
            "type":"Services"
        }
    ],
    "sg:phone":"+1 760 505 1416",
    "sg:postcode":"92003",
    "sg:province":"CA",
    "wof:name":"Distinctly Yours Event",
    "wof:placetype":"venue"
},
  "geometry": {"coordinates":[-117.193168,33.289532],"type":"Point"}
}