{
  "type": "Feature",
  "properties": {
    "iso:country":"US",
    "sg:address":"1565 Eureka Rd",
    "sg:city":"Roseville",
    "sg:classifiers":[
        {
            "category":"Coffee & Tea",
            "type":"Food & Drink"
        }
    ],
    "sg:menulink":"http://www.allmenus.com/ca/roseville/108240-starbucks-coffee/menu/",
    "sg:phone":"+1 916 797 3191",
    "sg:postcode":"95661",
    "sg:province":"CA",
    "sg:tags":[
        "american"
    ],
    "wof:name":"Starbucks Coffee",
    "wof:placetype":"venue"
},
  "geometry": {"coordinates":[-121.24897900000001,38.749947],"type":"Point"}
}