{
  "type": "Feature",
  "properties": {
    "addr:full":"23777 Madison St Torrance CA 90505",
    "addr:housenumber":"23777",
    "addr:postcode":"90505",
    "addr:street":"Madison St",
    "iso:country":"US",
    "sg:address":"23777 Madison St",
    "sg:city":"Torrance",
    "sg:classifiers":[
        {
            "category":"Professional",
            "subcategory":"Management & Consulting",
            "type":"Services"
        },
        {
            "category":"Professional",
            "subcategory":"Research",
            "type":"Services"
        },
        {
            "category":"Manufacturing",
            "subcategory":"Food",
            "type":"Manufacturing & Wholesale Goods"
        },
        {
            "category":"Science Facility",
            "type":"Public Place"
        }
    ],
    "sg:phone":"+1 310 378 2370",
    "sg:postcode":"90505",
    "sg:province":"CA",
    "sg:tags":[
        "development",
        "product",
        "consultant",
        "laboratories-research",
        "processing",
        "beverage"
    ],
    "wof:name":"Asta Food Research",
    "wof:placetype":"venue"
},
  "geometry": {"coordinates":[-118.348906,33.80945],"type":"Point"}
}