{
  "type": "Feature",
  "properties": {
    "iso:country":"US",
    "sg:address":"2270 Camino Vida Roble Suite C",
    "sg:city":"Carlsbad",
    "sg:classifiers":[
        {
            "category":"Home & Garden",
            "subcategory":"Furniture",
            "type":"Retail Goods"
        }
    ],
    "sg:phone":"+1 760 602 7818",
    "sg:postcode":"92011",
    "sg:province":"CA",
    "sg:tags":[
        "store"
    ],
    "sg:website":"www.tassajaradesigns.com",
    "wof:name":"Tassajara Designs, Inc.",
    "wof:placetype":"venue"
},
  "geometry": {"coordinates":[-117.271624,33.120124],"type":"Point"}
}