{
  "type": "Feature",
  "properties": {
    "addr:full":"19200 Von Karman Ave Ste 500 Irvine CA 92612",
    "addr:housenumber":"19200",
    "addr:postcode":"92612",
    "addr:street":"Von Karman Ave Ste 500",
    "iso:country":"US",
    "sg:address":"19200 Von Karman Ave Ste 500",
    "sg:city":"Irvine",
    "sg:classifiers":[
        {
            "category":"Banks & Credit Unions",
            "subcategory":"Investment Brokerage",
            "type":"Services"
        }
    ],
    "sg:phone":"+1 949 502 0050",
    "sg:postcode":"92612",
    "sg:province":"CA",
    "sg:tags":[
        "investing"
    ],
    "sg:website":"www.ifa.com",
    "wof:name":"Index Funds Advisors Inc",
    "wof:placetype":"venue"
},
  "geometry": {"coordinates":[-117.857681,33.670568],"type":"Point"}
}