{
  "type": "Feature",
  "properties": {
    "iso:country":"US",
    "sg:address":"160 W Garvey Ave",
    "sg:city":"Monterey Park",
    "sg:classifiers":[
        {
            "category":"Cinema",
            "subcategory":"Movie Rental",
            "type":"Entertainment"
        }
    ],
    "sg:phone":"+1 626 573 4765",
    "sg:postcode":"91754",
    "sg:province":"CA",
    "sg:tags":[
        "game",
        "video"
    ],
    "wof:name":"Nan Tian Video",
    "wof:placetype":"venue"
},
  "geometry": {"coordinates":[-118.124173,34.061861],"type":"Point"}
}