{
  "type": "Feature",
  "properties": {
    "addr:full":"1114 Lily Ave Sunnyvale CA 94086",
    "addr:housenumber":"1114",
    "addr:postcode":"94086",
    "addr:street":"Lily Ave",
    "iso:country":"US",
    "sg:address":"1114 Lily Ave",
    "sg:city":"Sunnyvale",
    "sg:classifiers":[
        {
            "category":"Social Services",
            "subcategory":"Child Care",
            "type":"Services"
        }
    ],
    "sg:phone":"+1 408 296 2805",
    "sg:postcode":"94086",
    "sg:province":"CA",
    "sg:tags":[
        "day"
    ],
    "sg:website":"asyasdaycare.com",
    "wof:name":"Asya's Daycare",
    "wof:placetype":"venue"
},
  "geometry": {"coordinates":[-122.000226,37.361545],"type":"Point"}
}