{
  "type": "Feature",
  "properties": {
    "iso:country":"US",
    "sg:address":"4636 Mission Gorge Pl",
    "sg:city":"San Diego",
    "sg:classifiers":[
        {
            "category":"Organizations",
            "subcategory":"Membership Organization",
            "type":"Services"
        }
    ],
    "sg:phone":"+1 626 798 0070",
    "sg:postcode":"92120",
    "sg:province":"CA",
    "wof:name":"NEIEP",
    "wof:placetype":"venue"
},
  "geometry": {"coordinates":[-117.093941,32.782921],"type":"Point"}
}