{
  "type": "Feature",
  "properties": {
    "addr:full":"171 N 13th St Grover Beach CA 93433",
    "addr:housenumber":"171",
    "addr:postcode":"93433",
    "addr:street":"N 13Th St",
    "iso:country":"US",
    "sg:address":"171 N 13th St",
    "sg:city":"Grover Beach",
    "sg:classifiers":[
        {
            "category":"Real Estate",
            "subcategory":"Real Estate Agent",
            "type":"Services"
        }
    ],
    "sg:phone":"+1 805 481 0325",
    "sg:postcode":"93433",
    "sg:province":"CA",
    "sg:tags":[
        "exchanger"
    ],
    "wof:name":"Central Coast Exch & Conslntg",
    "wof:placetype":"venue"
},
  "geometry": {"coordinates":[-120.615415,35.121577],"type":"Point"}
}