{
  "type": "Feature",
  "properties": {
    "addr:full":"11430 Laurel Canyon Blvd San Fernando CA 91340",
    "addr:housenumber":"11430",
    "addr:postcode":"91340",
    "addr:street":"Laurel Canyon Blvd",
    "iso:country":"US",
    "sg:address":"11430 Laurel Canyon Blvd",
    "sg:city":"San Fernando",
    "sg:classifiers":[
        {
            "category":"Insurance",
            "subcategory":"Insurance Agent",
            "type":"Services"
        }
    ],
    "sg:phone":"+1 818 365 6200",
    "sg:postcode":"91340",
    "sg:province":"CA",
    "wof:name":"Value Insurance Svc",
    "wof:placetype":"venue"
},
  "geometry": {"coordinates":[-118.451515,34.277013],"type":"Point"}
}