{
  "type": "Feature",
  "properties": {
    "addr:full":"7510 E Foppiano Ln Stockton CA 95212",
    "addr:housenumber":"7510",
    "addr:postcode":"95212",
    "addr:street":"E Foppiano Ln",
    "iso:country":"US",
    "sg:address":"7510 E Foppiano Ln",
    "sg:city":"Stockton",
    "sg:classifiers":[
        {
            "category":"Shopping",
            "subcategory":"Used Merchandise",
            "type":"Retail Goods"
        }
    ],
    "sg:phone":"+1 209 462 8934",
    "sg:postcode":"95212",
    "sg:province":"CA",
    "sg:tags":[
        "antique"
    ],
    "wof:name":"Put It All Together",
    "wof:placetype":"venue"
},
  "geometry": {"coordinates":[-121.217704,38.037202],"type":"Point"}
}