{
  "type": "Feature",
  "properties": {
    "addr:full":"1516 Gladstone Dr Sacramento CA 95864",
    "addr:housenumber":"1516",
    "addr:postcode":"95864",
    "addr:street":"Gladstone Dr",
    "iso:country":"US",
    "sg:address":"1516 Gladstone Dr",
    "sg:city":"Sacramento",
    "sg:classifiers":[
        {
            "category":"Freight",
            "type":"Transportation"
        }
    ],
    "sg:phone":"+1 916 480 0876",
    "sg:postcode":"95864",
    "sg:province":"CA",
    "sg:tags":[
        "hauling",
        "trucking"
    ],
    "wof:name":"Metro Transportation",
    "wof:placetype":"venue"
},
  "geometry": {"coordinates":[-121.384007,38.593637],"type":"Point"}
}