{
  "type": "Feature",
  "properties": {
    "iso:country":"US",
    "sg:address":"1820 N Broadway",
    "sg:city":"Walnut Creek",
    "sg:classifiers":[
        {
            "category":"Manufacturing",
            "subcategory":"Signs",
            "type":"Manufacturing & Wholesale Goods"
        }
    ],
    "sg:phone":"+1 925 930 6750",
    "sg:postcode":"94596",
    "sg:province":"CA",
    "wof:name":"Diablo Valley Signs",
    "wof:placetype":"venue"
},
  "geometry": {"coordinates":[-122.061167,37.904862],"type":"Point"}
}