{
  "type": "Feature",
  "properties": {
    "addr:full":"1920 Joe Crosson Dr El Cajon CA 92020",
    "addr:housenumber":"1920",
    "addr:postcode":"92020",
    "addr:street":"Joe Crosson Dr",
    "iso:country":"US",
    "sg:address":"1920 Joe Crosson Dr",
    "sg:city":"El Cajon",
    "sg:classifiers":[
        {
            "category":"Retail",
            "subcategory":"Auto Repair",
            "type":"Services"
        }
    ],
    "sg:phone":"+1 619 258 2922",
    "sg:postcode":"92020",
    "sg:province":"CA",
    "sg:tags":[
        "automobile",
        "customizing"
    ],
    "wof:name":"Brink Designs",
    "wof:placetype":"venue"
},
  "geometry": {"coordinates":[-116.969827,32.820838],"type":"Point"}
}