{
  "type": "Feature",
  "properties": {
    "iso:country":"US",
    "sg:address":"1301 L St",
    "sg:city":"Modesto",
    "sg:classifiers":[
        {
            "category":"Banks & Credit Unions",
            "subcategory":"Investment Brokerage",
            "type":"Services"
        }
    ],
    "sg:phone":"+1 209 571 2349",
    "sg:postcode":"95354",
    "sg:province":"CA",
    "sg:tags":[
        "consultant",
        "planning",
        "financial"
    ],
    "wof:name":"Herrick Newby",
    "wof:placetype":"venue"
},
  "geometry": {"coordinates":[-120.998753,37.645314],"type":"Point"}
}