{
  "type": "Feature",
  "properties": {
    "iso:country":"US",
    "sg:address":"2550 Britannia Blvd",
    "sg:city":"San Diego",
    "sg:classifiers":[
        {
            "category":"Manufacturing",
            "subcategory":"Rubber & Plastics",
            "type":"Manufacturing & Wholesale Goods"
        }
    ],
    "sg:phone":"+1 619 661 9506",
    "sg:postcode":"92154",
    "sg:province":"CA",
    "sg:tags":[
        "producer"
    ],
    "wof:name":"Poly-Ag Corp",
    "wof:placetype":"venue"
},
  "geometry": {"coordinates":[-116.979776,32.55254],"type":"Point"}
}