{
  "type": "Feature",
  "properties": {
    "iso:country":"US",
    "sg:address":"3465 S Chestnut Ave",
    "sg:city":"Fresno",
    "sg:classifiers":[
        {
            "category":"Shopping",
            "subcategory":"Used Merchandise",
            "type":"Retail Goods"
        }
    ],
    "sg:phone":"+1 559 268 4623",
    "sg:postcode":"93725",
    "sg:province":"CA",
    "sg:tags":[
        "a",
        "supply"
    ],
    "wof:name":"Continental Auto Dismantlers",
    "wof:placetype":"venue"
},
  "geometry": {"coordinates":[-119.736734,36.685],"type":"Point"}
}