{
  "type": "Feature",
  "properties": {
    "iso:country":"US",
    "sg:address":"445 W Freedom Ave",
    "sg:city":"Orange",
    "sg:classifiers":[
        {
            "category":"Cinema",
            "subcategory":"Movie Rental",
            "type":"Entertainment"
        }
    ],
    "sg:phone":"+1 714 282 1232",
    "sg:postcode":"92865",
    "sg:province":"CA",
    "sg:tags":[
        "game",
        "video"
    ],
    "sg:website":"www.ingramentertainment.com",
    "wof:name":"Ingram Entertainment",
    "wof:placetype":"venue"
},
  "geometry": {"coordinates":[-117.85700199999999,33.827301],"type":"Point"}
}