{
  "type": "Feature",
  "properties": {
    "iso:country":"US",
    "sg:address":"1225 Alpine Rd",
    "sg:city":"Walnut Creek",
    "sg:classifiers":[
        {
            "category":"Professional",
            "subcategory":"Management & Consulting",
            "type":"Services"
        }
    ],
    "sg:phone":"+1 925 932 7100",
    "sg:postcode":"94596",
    "sg:province":"CA",
    "sg:tags":[
        "association"
    ],
    "wof:name":"Miramonte Co",
    "wof:placetype":"venue"
},
  "geometry": {"coordinates":[-122.066659,37.896463],"type":"Point"}
}