{
  "type": "Feature",
  "properties": {
    "addr:full":"13737 Amarillo Ave Chino CA 91710",
    "addr:housenumber":"13737",
    "addr:postcode":"91710",
    "addr:street":"Amarillo Ave",
    "iso:country":"US",
    "sg:address":"13737 Amarillo Ave",
    "sg:city":"Chino",
    "sg:classifiers":[
        {
            "category":"Manufacturing",
            "subcategory":"Tools & Machinery",
            "type":"Manufacturing & Wholesale Goods"
        }
    ],
    "sg:phone":"+1 909 465 9652",
    "sg:postcode":"91710",
    "sg:province":"CA",
    "sg:tags":[
        "system",
        "power",
        "mfg"
    ],
    "wof:name":"W D C Inc",
    "wof:placetype":"venue"
},
  "geometry": {"coordinates":[-117.679434,34.004056],"type":"Point"}
}