{
  "type": "Feature",
  "properties": {
    "addr:full":"1340 Coffee Rd Modesto CA 95355",
    "addr:housenumber":"1340",
    "addr:postcode":"ca 95355",
    "addr:street":"Coffee Rd",
    "iso:country":"US",
    "sg:address":"1340 Coffee Rd",
    "sg:city":"Modesto",
    "sg:classifiers":[
        {
            "category":"Restaurant",
            "type":"Food & Drink"
        }
    ],
    "sg:phone":"+1 209 238 9212",
    "sg:postcode":"95355",
    "sg:province":"CA",
    "wof:name":"Maria's Taco Shop",
    "wof:placetype":"venue"
},
  "geometry": {"coordinates":[-120.97557500000001,37.662096],"type":"Point"}
}