{
  "type": "Feature",
  "properties": {
    "addr:full":"150 S Orchard Ave Vacaville CA 95688",
    "addr:housenumber":"150",
    "addr:postcode":"95688",
    "addr:street":"S Orchard Ave",
    "iso:country":"US",
    "sg:address":"150 S Orchard Ave",
    "sg:city":"Vacaville",
    "sg:classifiers":[
        {
            "category":"Building & Trades",
            "subcategory":"Electrical",
            "type":"Services"
        }
    ],
    "sg:phone":"+1 707 447 2377",
    "sg:postcode":"95688",
    "sg:province":"CA",
    "sg:tags":[
        "telecommunication",
        "contractor"
    ],
    "wof:name":"California Telephone",
    "wof:placetype":"venue"
},
  "geometry": {"coordinates":[-122.004778,38.357809],"type":"Point"}
}