{
  "type": "Feature",
  "properties": {
    "iso:country":"US",
    "sg:address":"3470 Wilshire Blvd",
    "sg:city":"Los Angeles",
    "sg:classifiers":[
        {
            "category":"Shopping",
            "subcategory":"Computers & Home Electronics",
            "type":"Retail Goods"
        }
    ],
    "sg:phone":"+1 213 383 7083",
    "sg:postcode":"90010",
    "sg:province":"CA",
    "sg:tags":[
        "software"
    ],
    "wof:name":"M & M Software & Hardware",
    "wof:placetype":"venue"
},
  "geometry": {"coordinates":[-118.299933,34.061671],"type":"Point"}
}