{
  "type": "Feature",
  "properties": {
    "addr:full":"850 E Ocean Blvd Long Beach CA 90802",
    "addr:housenumber":"850",
    "addr:postcode":"90802",
    "addr:street":"E Ocean Blvd",
    "iso:country":"US",
    "sg:address":"850 E Ocean Blvd",
    "sg:city":"Long Beach",
    "sg:classifiers":[
        {
            "category":"Professional",
            "type":"Services"
        }
    ],
    "sg:phone":"+1 562 439 7110",
    "sg:postcode":"90802",
    "sg:province":"CA",
    "wof:name":"Danes",
    "wof:placetype":"venue"
},
  "geometry": {"coordinates":[-118.18291600000001,33.766391],"type":"Point"}
}