{
  "type": "Feature",
  "properties": {
    "addr:full":"631 Draco Dr Petaluma CA 94954",
    "addr:housenumber":"631",
    "addr:postcode":"94954",
    "addr:street":"Draco Dr",
    "iso:country":"US",
    "sg:address":"631 Draco Dr",
    "sg:city":"Petaluma",
    "sg:classifiers":[
        {
            "category":"Recreation",
            "type":"Entertainment"
        }
    ],
    "sg:phone":"+1 707 778 9609",
    "sg:postcode":"94954",
    "sg:province":"CA",
    "sg:tags":[
        "pool",
        "swimming"
    ],
    "wof:name":"Morningstar Pool",
    "wof:placetype":"venue"
},
  "geometry": {"coordinates":[-122.637682,38.265094],"type":"Point"}
}