{
  "type": "Feature",
  "properties": {
    "addr:full":"241 Albertoni St. Carson CA 90746",
    "addr:housenumber":"241",
    "addr:postcode":"90746",
    "addr:street":"Albertoni St.",
    "iso:country":"US",
    "sg:address":"241 Albertoni St.",
    "sg:city":"Carson",
    "sg:classifiers":[
        {
            "category":"Autos & Motor Vehicles",
            "subcategory":"Fuel & Gas Station",
            "type":"Retail Goods"
        },
        {
            "category":"Food & Beverages",
            "subcategory":"Groceries & Convenience Stores",
            "type":"Retail Goods"
        }
    ],
    "sg:phone":"+1 310 538 5450",
    "sg:postcode":"90746",
    "sg:province":"CA",
    "wof:name":"AM/PM & Arco Station",
    "wof:placetype":"venue"
},
  "geometry": {"coordinates":[-118.271632,33.871753],"type":"Point"}
}