{
  "type": "Feature",
  "properties": {
    "addr:full":"2020 S East Ave Fresno CA 93721",
    "addr:housenumber":"2020",
    "addr:postcode":"93721",
    "addr:street":"S East",
    "iso:country":"US",
    "sg:address":"2020 S East Ave",
    "sg:city":"Fresno",
    "sg:classifiers":[
        {
            "category":"Manufacturing",
            "subcategory":"Food",
            "type":"Manufacturing & Wholesale Goods"
        }
    ],
    "sg:phone":"+1 559 486 2310",
    "sg:postcode":"93721",
    "sg:province":"CA",
    "sg:tags":[
        "product",
        "manufacturer"
    ],
    "wof:name":"Zacky Farms",
    "wof:placetype":"venue"
},
  "geometry": {"coordinates":[-119.772717,36.725039],"type":"Point"}
}