{
  "type": "Feature",
  "properties": {
    "iso:country":"US",
    "sg:address":"4356 N Bryan Ave",
    "sg:city":"Fresno",
    "sg:classifiers":[
        {
            "category":"Real Estate",
            "subcategory":"Real Estate Operator",
            "type":"Services"
        }
    ],
    "sg:phone":"+1 559 275 5135",
    "sg:postcode":"93723",
    "sg:province":"CA",
    "sg:tags":[
        "property",
        "lessor"
    ],
    "wof:name":"Scarabello Vinto",
    "wof:placetype":"venue"
},
  "geometry": {"coordinates":[-119.90734,36.797486],"type":"Point"}
}