{
  "type": "Feature",
  "properties": {
    "addr:full":"1611 E Main St Barstow CA 92311",
    "addr:housenumber":"1611",
    "addr:postcode":"92311",
    "addr:street":"E Main St",
    "iso:country":"US",
    "sg:address":"1611 E Main St",
    "sg:city":"Barstow",
    "sg:classifiers":[
        {
            "category":"Local Transit",
            "type":"Transportation"
        }
    ],
    "sg:phone":"+1 760 256 8757",
    "sg:postcode":"92311",
    "sg:province":"CA",
    "sg:tags":[
        "bus",
        "line"
    ],
    "wof:name":"Greyhound Bus Lines",
    "wof:placetype":"venue"
},
  "geometry": {"coordinates":[-117.00026,34.891548],"type":"Point"}
}