{
  "type": "Feature",
  "properties": {
    "addr:full":"701 Central Valley Hwy Shafter CA 93263",
    "addr:housenumber":"701",
    "addr:postcode":"93263",
    "addr:street":"Central Valley Hwy",
    "iso:country":"US",
    "sg:address":"701 Central Valley Hwy",
    "sg:city":"Shafter",
    "sg:classifiers":[
        {
            "category":"Restaurant",
            "type":"Food & Drink"
        }
    ],
    "sg:menulink":"http://www.allmenus.com/ca/shafter/87984-little-caesars-pizza/menu/",
    "sg:phone":"+1 661 746 4444",
    "sg:postcode":"93263",
    "sg:province":"CA",
    "sg:tags":[
        "american",
        "pizza"
    ],
    "wof:name":"Little Caesar's Pizza",
    "wof:placetype":"venue"
},
  "geometry": {"coordinates":[-119.28357200000001,35.510488],"type":"Point"}
}