{
  "type": "Feature",
  "properties": {
    "addr:full":"10423 Valley Blvd Ste C El Monte CA 91731",
    "addr:housenumber":"10423",
    "addr:postcode":"91731",
    "addr:street":"Valley Blvd Ste C",
    "iso:country":"US",
    "sg:address":"10423 Valley Blvd Ste C",
    "sg:city":"El Monte",
    "sg:classifiers":[
        {
            "category":"Personal",
            "subcategory":"Massage",
            "type":"Services"
        },
        {
            "category":"Health Services",
            "subcategory":"Clinic",
            "type":"Services"
        }
    ],
    "sg:phone":"+1 626 448 8516",
    "sg:postcode":"91731",
    "sg:province":"CA",
    "sg:tags":[
        "medical"
    ],
    "wof:name":"Well Spa & Massage",
    "wof:placetype":"venue"
},
  "geometry": {"coordinates":[-118.04534200000001,34.077158],"type":"Point"}
}