{
  "type": "Feature",
  "properties": {
    "iso:country":"US",
    "sg:address":"3265 India St",
    "sg:city":"San Diego",
    "sg:classifiers":[
        {
            "category":"Shopping",
            "subcategory":"Pets & Pet Supplies",
            "type":"Retail Goods"
        },
        {
            "category":"Retail",
            "subcategory":"Pet Boarding",
            "type":"Services"
        }
    ],
    "sg:phone":"+1 619 795 6421",
    "sg:postcode":"92103",
    "sg:province":"CA",
    "sg:tags":[
        "training",
        "boarding/pet",
        "sitting"
    ],
    "sg:website":"www.camprunamutt.com",
    "wof:name":"Camp Run-A-Mutt",
    "wof:placetype":"venue"
},
  "geometry": {"coordinates":[-117.175624,32.737278],"type":"Point"}
}