{
  "type": "Feature",
  "properties": {
    "iso:country":"US",
    "sg:address":"818 Coastal Ct",
    "sg:city":"Los Banos",
    "sg:classifiers":[
        {
            "category":"Farming",
            "subcategory":"Farm & Veterinary Services",
            "type":"Manufacturing & Wholesale Goods"
        }
    ],
    "sg:phone":"+1 209 826 8413",
    "sg:postcode":"93635",
    "sg:province":"CA",
    "sg:tags":[
        "livestock"
    ],
    "wof:name":"Pires I M T",
    "wof:placetype":"venue"
},
  "geometry": {"coordinates":[-120.84365099999999,37.0453],"type":"Point"}
}