{
  "type": "Feature",
  "properties": {
    "addr:full":"PO Box 79412 Los Angeles CA 90079",
    "addr:housenumber":"po box 79412",
    "addr:postcode":"90079",
    "iso:country":"US",
    "sg:address":"PO Box 79412",
    "sg:city":"Los Angeles",
    "sg:classifiers":[
        {
            "category":"Restaurant",
            "type":"Food & Drink"
        }
    ],
    "sg:phone":"+1 213 622 1702",
    "sg:postcode":"90079",
    "sg:province":"CA",
    "wof:name":"Broadway Snack Bar",
    "wof:placetype":"venue"
},
  "geometry": {"coordinates":[-118.254997,34.041302],"type":"Point"}
}