{
  "type": "Feature",
  "properties": {
    "iso:country":"US",
    "sg:address":"28210 N Ave Stanford",
    "sg:city":"Valencia",
    "sg:classifiers":[
        {
            "category":"Airline",
            "type":"Transportation"
        }
    ],
    "sg:phone":"+1 661 295 8719",
    "sg:postcode":"91355",
    "sg:province":"CA",
    "sg:tags":[
        "scheduled",
        "air"
    ],
    "wof:name":"Leufthansa German Airlines",
    "wof:placetype":"venue"
},
  "geometry": {"coordinates":[-118.598817,34.440385],"type":"Point"}
}