{
  "type": "Feature",
  "properties": {
    "iso:country":"US",
    "sg:address":"4368 Victoria Ave",
    "sg:city":"Union City",
    "sg:classifiers":[
        {
            "category":"Insurance",
            "subcategory":"Insurance Agent",
            "type":"Services"
        }
    ],
    "sg:phone":"+1 510 471 7228",
    "sg:postcode":"94587",
    "sg:province":"CA",
    "wof:name":"Automotive Consultants",
    "wof:placetype":"venue"
},
  "geometry": {"coordinates":[-122.07597199999999,37.59049],"type":"Point"}
}