{
  "type": "Feature",
  "properties": {
    "iso:country":"US",
    "sg:address":"3055 Badger Dr",
    "sg:city":"Pleasanton",
    "sg:classifiers":[
        {
            "category":"Wholesale",
            "subcategory":"Electrical",
            "type":"Manufacturing & Wholesale Goods"
        }
    ],
    "sg:phone":"+1 925 922 1448",
    "sg:postcode":"94566",
    "sg:province":"CA",
    "sg:tags":[
        "electronic"
    ],
    "wof:name":"Hdx International Inc",
    "wof:placetype":"venue"
},
  "geometry": {"coordinates":[-121.849177,37.667009],"type":"Point"}
}