{
  "type": "Feature",
  "properties": {
    "addr:full":"1580 Macarthur Blvd Oakland CA 94602",
    "addr:housenumber":"1580",
    "addr:postcode":"94602",
    "addr:street":"Macarthur Blvd",
    "iso:country":"US",
    "sg:address":"1580 Macarthur Blvd",
    "sg:city":"Oakland",
    "sg:classifiers":[
        {
            "category":"Shopping",
            "subcategory":"Gifts & Souvenirs",
            "type":"Retail Goods"
        }
    ],
    "sg:phone":"+1 510 482 4212",
    "sg:postcode":"94602",
    "sg:province":"CA",
    "wof:name":"Odds & Ends",
    "wof:placetype":"venue"
},
  "geometry": {"coordinates":[-122.224507,37.800792],"type":"Point"}
}