{
  "type": "Feature",
  "properties": {
    "iso:country":"US",
    "sg:address":"3150 Pio Pico Dr",
    "sg:city":"Carlsbad",
    "sg:classifiers":[
        {
            "category":"Health Services",
            "subcategory":"Doctor",
            "type":"Services"
        }
    ],
    "sg:phone":"+1 760 730 4540",
    "sg:postcode":"92008",
    "sg:province":"CA",
    "wof:name":"Essex Michael md",
    "wof:placetype":"venue"
},
  "geometry": {"coordinates":[-117.340744,33.161728],"type":"Point"}
}