{
  "type": "Feature",
  "properties": {
    "iso:country":"US",
    "sg:address":"1626 Valley High Ave",
    "sg:city":"Thousand Oaks",
    "sg:classifiers":[
        {
            "category":"Shopping",
            "subcategory":"Clothing, Apparel, & Fashions",
            "type":"Retail Goods"
        }
    ],
    "sg:phone":"+1 805 444 8839",
    "sg:postcode":"91362",
    "sg:province":"CA",
    "sg:tags":[
        "t"
    ],
    "wof:name":"Homeschool Rules",
    "wof:placetype":"venue"
},
  "geometry": {"coordinates":[-118.842997,34.198295],"type":"Point"}
}