{
  "type": "Feature",
  "properties": {
    "addr:full":"202 Main St Murphys CA 95247",
    "addr:housenumber":"202",
    "addr:postcode":"95247",
    "addr:street":"Main St",
    "iso:country":"US",
    "sg:address":"202 Main St",
    "sg:city":"Murphys",
    "sg:classifiers":[
        {
            "category":"Personal",
            "subcategory":"Barber",
            "type":"Services"
        }
    ],
    "sg:phone":"+1 209 728 2714",
    "sg:postcode":"95247",
    "sg:province":"CA",
    "wof:name":"Murphys Barber Shop",
    "wof:placetype":"venue"
},
  "geometry": {"coordinates":[-120.459917,38.137412],"type":"Point"}
}