{
  "type": "Feature",
  "properties": {
    "iso:country":"US",
    "sg:address":"848 Blossom Hill Road",
    "sg:city":"San Jose",
    "sg:classifiers":[
        {
            "category":"Banks & Credit Unions",
            "subcategory":"Bank",
            "type":"Services"
        }
    ],
    "sg:phone":"+1 408 281 7633",
    "sg:postcode":"95123",
    "sg:province":"CA",
    "sg:website":"www.wachovia.com",
    "wof:name":"World Savings",
    "wof:placetype":"venue"
},
  "geometry": {"coordinates":[-121.856724,37.250349],"type":"Point"}
}