{
  "type": "Feature",
  "properties": {
    "iso:country":"US",
    "sg:address":"88 Academy Ave",
    "sg:city":"Sanger",
    "sg:classifiers":[
        {
            "category":"Shopping",
            "subcategory":"Used Merchandise",
            "type":"Retail Goods"
        }
    ],
    "sg:phone":"+1 559 875 6297",
    "sg:postcode":"93657",
    "sg:province":"CA",
    "sg:tags":[
        "second",
        "store",
        "hand"
    ],
    "wof:name":"Apatchee Trading Post",
    "wof:placetype":"venue"
},
  "geometry": {"coordinates":[-119.556454,36.716745],"type":"Point"}
}