{
  "type": "Feature",
  "properties": {
    "iso:country":"US",
    "sg:address":"3235 4th Ave",
    "sg:city":"San Diego",
    "sg:classifiers":[
        {
            "category":"Social Services",
            "type":"Services"
        }
    ],
    "sg:phone":"+1 619 497 0990",
    "sg:postcode":"92103",
    "sg:province":"CA",
    "sg:tags":[
        "counseling"
    ],
    "wof:name":"Bankers Hill Counseling Ctr",
    "wof:placetype":"venue"
},
  "geometry": {"coordinates":[-117.161186,32.739391],"type":"Point"}
}