{
  "type": "Feature",
  "properties": {
    "addr:full":"1401 Irving Street San Francisco CA 94122",
    "addr:housenumber":"1401",
    "addr:postcode":"94122",
    "addr:street":"Irving Street",
    "iso:country":"US",
    "sg:address":"1401 Irving Street",
    "sg:city":"San Francisco",
    "sg:classifiers":[
        {
            "category":"Retail",
            "subcategory":"Laundry & Dry Cleaning",
            "type":"Services"
        }
    ],
    "sg:postcode":"94122",
    "sg:province":"CA",
    "wof:name":"Parkside Wash and Dry",
    "wof:placetype":"venue"
},
  "geometry": {"coordinates":[-122.472798,37.763745],"type":"Point"}
}