{
  "type": "Feature",
  "properties": {
    "addr:full":"1209 E Rosecrans Ave E Rancho Dmngz CA 90222",
    "addr:housenumber":"1209",
    "addr:postcode":"90222",
    "addr:street":"E Rosecrans Ave E",
    "iso:country":"US",
    "sg:address":"1209 E Rosecrans Ave",
    "sg:city":"E Rancho Dmngz",
    "sg:classifiers":[
        {
            "category":"Social Services",
            "type":"Services"
        }
    ],
    "sg:phone":"+1 310 608 1204",
    "sg:postcode":"90222",
    "sg:province":"CA",
    "sg:tags":[
        "organization",
        "welfare"
    ],
    "wof:name":"Corportation Club Acatlan",
    "wof:placetype":"venue"
},
  "geometry": {"coordinates":[-118.21091699999999,33.903441],"type":"Point"}
}