{
  "type": "Feature",
  "properties": {
    "iso:country":"US",
    "sg:address":"10 Nogales Ct",
    "sg:city":"Novato",
    "sg:classifiers":[
        {
            "category":"Professional",
            "subcategory":"Accounting & Tax Preparation",
            "type":"Services"
        }
    ],
    "sg:phone":"+1 415 892 2795",
    "sg:postcode":"94947",
    "sg:province":"CA",
    "sg:tags":[
        "bookkeeping",
        "billing"
    ],
    "wof:name":"Oasis",
    "wof:placetype":"venue"
},
  "geometry": {"coordinates":[-122.587856,38.108409],"type":"Point"}
}