{
  "type": "Feature",
  "properties": {
    "iso:country":"US",
    "sg:address":"28821 Silverado Canyon Rd",
    "sg:city":"Silverado",
    "sg:classifiers":[
        {
            "category":"Professional",
            "subcategory":"Computer Services",
            "type":"Services"
        },
        {
            "category":"Internet Cafe",
            "subcategory":"None",
            "type":"Food & Drink"
        }
    ],
    "sg:phone":"+1 714 649 2044",
    "sg:postcode":"92676",
    "sg:province":"CA",
    "sg:tags":[
        "product",
        "software"
    ],
    "wof:name":"James E Farr & Assoc",
    "wof:placetype":"venue"
},
  "geometry": {"coordinates":[-117.62766999999999,33.746124],"type":"Point"}
}