{
  "type": "Feature",
  "properties": {
    "iso:country":"US",
    "sg:address":"145 E Olive Ave",
    "sg:city":"Fresno",
    "sg:classifiers":[
        {
            "category":"Education",
            "subcategory":"Special Training",
            "type":"Public Place"
        },
        {
            "category":"Arena",
            "subcategory":"Sports Club",
            "type":"Entertainment"
        }
    ],
    "sg:phone":"+1 559 441 0402",
    "sg:postcode":"93728",
    "sg:province":"CA",
    "sg:tags":[
        "instruction",
        "equipment",
        "self defense",
        "martial art"
    ],
    "wof:name":"Red Dragon Martial Arts",
    "wof:placetype":"venue"
},
  "geometry": {"coordinates":[-119.809803,36.757621],"type":"Point"}
}