{
  "type": "Feature",
  "properties": {
    "addr:full":"3620 Arena Ave Atascadero CA 93422",
    "addr:housenumber":"3620",
    "addr:postcode":"93422",
    "addr:street":"Arena Ave",
    "iso:country":"US",
    "sg:address":"3620 Arena Ave",
    "sg:city":"Atascadero",
    "sg:classifiers":[
        {
            "category":"Health Services",
            "subcategory":"Health Practitioner",
            "type":"Services"
        }
    ],
    "sg:phone":"+1 805 462 8906",
    "sg:postcode":"93422",
    "sg:province":"CA",
    "sg:tags":[
        "therapist",
        "physical"
    ],
    "wof:name":"In Home Physical Therapy",
    "wof:placetype":"venue"
},
  "geometry": {"coordinates":[-120.682097,35.509954],"type":"Point"}
}