{
  "type": "Feature",
  "properties": {
    "iso:country":"US",
    "sg:address":"1424 N Batavia St",
    "sg:city":"Orange",
    "sg:classifiers":[
        {
            "category":"Professional",
            "subcategory":"Business Services",
            "type":"Services"
        }
    ],
    "sg:phone":"+1 714 639 2342",
    "sg:postcode":"92867",
    "sg:province":"CA",
    "sg:tags":[
        "paper",
        "lamination"
    ],
    "wof:name":"Vclad Laminates Inc",
    "wof:placetype":"venue"
},
  "geometry": {"coordinates":[-117.862503,33.810962],"type":"Point"}
}