{
  "type": "Feature",
  "properties": {
    "addr:full":"20855 Ventura Blvd Ste B Woodland Hills CA 91364",
    "addr:housenumber":"20855",
    "addr:postcode":"91364",
    "addr:street":"Ventura Blvd Ste B",
    "iso:country":"US",
    "sg:address":"20855 Ventura Blvd Ste B",
    "sg:city":"Woodland Hills",
    "sg:classifiers":[
        {
            "category":"Shopping",
            "subcategory":"Bridal",
            "type":"Retail Goods"
        }
    ],
    "sg:phone":"+1 818 999 0089",
    "sg:postcode":"91364",
    "sg:province":"CA",
    "sg:website":"www.pebblesbridal.com/",
    "wof:name":"Pebbles Bridal",
    "wof:placetype":"venue"
},
  "geometry": {"coordinates":[-118.58699799999999,34.166401],"type":"Point"}
}