{
  "type": "Feature",
  "properties": {
    "iso:country":"US",
    "sg:address":"171 E El Camino Real",
    "sg:city":"Mountain View",
    "sg:classifiers":[
        {
            "category":"Shopping",
            "subcategory":"Bicycles & Sporting Goods",
            "type":"Retail Goods"
        },
        {
            "category":"Sports & Exercise",
            "subcategory":"Bicycle Rental",
            "type":"Entertainment"
        }
    ],
    "sg:phone":"+1 650 968 1702",
    "sg:postcode":"94040",
    "sg:province":"CA",
    "sg:tags":[
        "outdoor",
        "gear",
        "wear"
    ],
    "wof:name":"Fairway Golf Shop",
    "wof:placetype":"venue"
},
  "geometry": {"coordinates":[-122.071742,37.379755],"type":"Point"}
}