{
  "type": "Feature",
  "properties": {
    "addr:full":"3519 W Magill Ave Fresno CA 93711",
    "addr:housenumber":"3519",
    "addr:postcode":"93711",
    "addr:street":"W Magill Ave",
    "iso:country":"US",
    "sg:address":"3519 W Magill Ave",
    "sg:city":"Fresno",
    "sg:classifiers":[
        {
            "category":"Banks & Credit Unions",
            "subcategory":"Investment Brokerage",
            "type":"Services"
        }
    ],
    "sg:phone":"+1 559 440 1816",
    "sg:postcode":"93711",
    "sg:province":"CA",
    "sg:tags":[
        "contract",
        "broker",
        "commodity",
        "cotton"
    ],
    "wof:name":"Kemble Cotton Services",
    "wof:placetype":"venue"
},
  "geometry": {"coordinates":[-119.856229,36.83531],"type":"Point"}
}