{
  "type": "Feature",
  "properties": {
    "iso:country":"US",
    "sg:address":"201 E Taylor St",
    "sg:city":"San Jose",
    "sg:classifiers":[
        {
            "category":"Insurance",
            "subcategory":"Insurance Agent",
            "type":"Services"
        }
    ],
    "sg:phone":"+1 408 287 8190",
    "sg:postcode":"95112",
    "sg:province":"CA",
    "wof:name":"State Farm Insurance",
    "wof:placetype":"venue"
},
  "geometry": {"coordinates":[-121.894874,37.351618],"type":"Point"}
}