{
  "type": "Feature",
  "properties": {
    "addr:full":"454 Los Cerritos Mall Cerritos CA 90703",
    "addr:housenumber":"454",
    "addr:postcode":"ca 90703",
    "addr:street":"Los Cerritos Mall",
    "iso:country":"US",
    "sg:address":"454 Los Cerritos Mall",
    "sg:city":"Cerritos",
    "sg:classifiers":[
        {
            "category":"Shopping",
            "subcategory":"Clothing, Apparel, & Fashions",
            "type":"Retail Goods"
        }
    ],
    "sg:phone":"+1 562 865 6310",
    "sg:postcode":"90703",
    "sg:province":"CA",
    "sg:tags":[
        "accessory",
        "clothing",
        "women's"
    ],
    "wof:name":"Limited the",
    "wof:placetype":"venue"
},
  "geometry": {"coordinates":[-118.095001,33.864201],"type":"Point"}
}