{
  "type": "Feature",
  "properties": {
    "iso:country":"US",
    "sg:address":"1491 E G St",
    "sg:city":"Oakdale",
    "sg:classifiers":[
        {
            "category":"Real Estate",
            "subcategory":"Real Estate Services",
            "type":"Services"
        }
    ],
    "sg:phone":"+1 209 848 1090",
    "sg:postcode":"95361",
    "sg:province":"CA",
    "sg:tags":[
        "company",
        "title"
    ],
    "wof:name":"Chicago Title Co",
    "wof:placetype":"venue"
},
  "geometry": {"coordinates":[-120.831225,37.769044],"type":"Point"}
}