{
  "type": "Feature",
  "properties": {
    "iso:country":"US",
    "sg:address":"8015 Kingston Ave",
    "sg:city":"Hesperia",
    "sg:classifiers":[
        {
            "category":"Retail",
            "subcategory":"Auto Repair",
            "type":"Services"
        }
    ],
    "sg:phone":"+1 760 948 0911",
    "sg:postcode":"92345",
    "sg:province":"CA",
    "sg:tags":[
        "wrecker"
    ],
    "wof:name":"MAD Towing & Recovery",
    "wof:placetype":"venue"
},
  "geometry": {"coordinates":[-117.278069,34.396014],"type":"Point"}
}