{
  "type": "Feature",
  "properties": {
    "iso:country":"US",
    "sg:address":"3131 Jay Street",
    "sg:city":"Santa Clara",
    "sg:classifiers":[
        {
            "category":"Professional",
            "subcategory":"Computer Services",
            "type":"Services"
        }
    ],
    "sg:phone":"+1 408 961 6100",
    "sg:postcode":"95054",
    "sg:province":"CA",
    "sg:tags":[
        "repair"
    ],
    "sg:website":"www.vormetric.com",
    "wof:name":"Vormetric",
    "wof:placetype":"venue"
},
  "geometry": {"coordinates":[-121.961702,37.377941],"type":"Point"}
}