{
  "type": "Feature",
  "properties": {
    "iso:country":"US",
    "sg:address":"550 Santa Rita Ave",
    "sg:city":"Palo Alto",
    "sg:classifiers":[
        {
            "category":"Professional",
            "type":"Services"
        }
    ],
    "sg:phone":"+1 650 328 2087",
    "sg:postcode":"94301",
    "sg:province":"CA",
    "wof:name":"Cabo Bound IA California",
    "wof:placetype":"venue"
},
  "geometry": {"coordinates":[-122.1382,37.43705],"type":"Point"}
}