{
  "type": "Feature",
  "properties": {
    "iso:country":"US",
    "sg:address":"3001 N Coolidge Avenue",
    "sg:city":"Los Angeles",
    "sg:classifiers":[
        {
            "category":"Building & Trades",
            "subcategory":"Construction",
            "type":"Services"
        }
    ],
    "sg:phone":"+1 323 666 5316",
    "sg:postcode":"90039",
    "sg:province":"CA",
    "sg:tags":[
        "contractor"
    ],
    "wof:name":"Pozzo Edw M Company",
    "wof:placetype":"venue"
},
  "geometry": {"coordinates":[-118.2449,34.104333],"type":"Point"}
}