{
  "type": "Feature",
  "properties": {
    "iso:country":"US",
    "sg:address":"6255 W Sunset Blvd",
    "sg:city":"Los Angeles",
    "sg:classifiers":[
        {
            "category":"Communications",
            "subcategory":"Film & Video Production",
            "type":"Services"
        }
    ],
    "sg:phone":"+1 323 957 9797",
    "sg:postcode":"90028",
    "sg:province":"CA",
    "sg:tags":[
        "duplication",
        "tape"
    ],
    "sg:website":"www.bitmax.net",
    "wof:name":"Bitmax",
    "wof:placetype":"venue"
},
  "geometry": {"coordinates":[-118.32638799999999,34.098071],"type":"Point"}
}