{
  "type": "Feature",
  "properties": {
    "iso:country":"US",
    "sg:address":"420 Acacia St",
    "sg:city":"Stockton",
    "sg:classifiers":[
        {
            "category":"Health Services",
            "subcategory":"Doctor",
            "type":"Services"
        }
    ],
    "sg:phone":"+1 209 461 7532",
    "sg:postcode":"95203",
    "sg:province":"CA",
    "sg:tags":[
        "clinic"
    ],
    "wof:name":"Sweet Success Clinic",
    "wof:placetype":"venue"
},
  "geometry": {"coordinates":[-121.300067,37.961244],"type":"Point"}
}