{
  "type": "Feature",
  "properties": {
    "iso:country":"US",
    "sg:address":"44830 Valley Central Way",
    "sg:city":"Lancaster",
    "sg:classifiers":[
        {
            "category":"Shopping",
            "subcategory":"Clothing, Apparel, & Fashions",
            "type":"Retail Goods"
        }
    ],
    "sg:phone":"+1 661 949 0586",
    "sg:postcode":"93536",
    "sg:province":"CA",
    "sg:tags":[
        "item",
        "boutique"
    ],
    "sg:website":"www.claires.com",
    "wof:name":"Claire's Boutique",
    "wof:placetype":"venue"
},
  "geometry": {"coordinates":[-118.17302,34.698004],"type":"Point"}
}