{
  "type": "Feature",
  "properties": {
    "addr:full":"9786 Edes Ave Oakland CA 94603",
    "addr:housenumber":"9786",
    "addr:postcode":"94603",
    "addr:street":"Edes Ave",
    "iso:country":"US",
    "sg:address":"9786 Edes Ave",
    "sg:city":"Oakland",
    "sg:classifiers":[
        {
            "category":"Food & Beverages",
            "subcategory":"Liquor & Beverages",
            "type":"Retail Goods"
        }
    ],
    "sg:phone":"+1 510 632 7076",
    "sg:postcode":"94603",
    "sg:province":"CA",
    "sg:tags":[
        "beer",
        "spirit",
        "wine"
    ],
    "wof:name":"Brookfield Discount Liquor",
    "wof:placetype":"venue"
},
  "geometry": {"coordinates":[-122.183998,37.736401],"type":"Point"}
}