{
  "type": "Feature",
  "properties": {
    "addr:full":"5229 Fillmore Ave Bakersfield CA 93306",
    "addr:housenumber":"5229",
    "addr:postcode":"93306",
    "addr:street":"Fillmore Ave",
    "iso:country":"US",
    "sg:address":"5229 Fillmore Ave",
    "sg:city":"Bakersfield",
    "sg:classifiers":[
        {
            "category":"Building & Trades",
            "subcategory":"Construction",
            "type":"Services"
        }
    ],
    "sg:phone":"+1 661 243 5011",
    "sg:postcode":"93306",
    "sg:province":"CA",
    "sg:tags":[
        "system",
        "contractor",
        "air conditioning"
    ],
    "wof:name":"Family Air",
    "wof:placetype":"venue"
},
  "geometry": {"coordinates":[-118.926109,35.369743],"type":"Point"}
}