{
  "type": "Feature",
  "properties": {
    "iso:country":"US",
    "sg:address":"2345 Paloma Ct",
    "sg:city":"Pinole",
    "sg:classifiers":[
        {
            "category":"Social Services",
            "subcategory":"Child Care",
            "type":"Services"
        }
    ],
    "sg:phone":"+1 510 758 1034",
    "sg:postcode":"94564",
    "sg:province":"CA",
    "wof:name":"Princilla's Day Care",
    "wof:placetype":"venue"
},
  "geometry": {"coordinates":[-122.283537,37.993008],"type":"Point"}
}