{
  "type": "Feature",
  "properties": {
    "addr:full":"945 Ward Dr Santa Barbara CA 93111",
    "addr:housenumber":"945",
    "addr:postcode":"93111",
    "addr:street":"Ward Dr",
    "iso:country":"US",
    "sg:address":"945 Ward Dr",
    "sg:city":"Santa Barbara",
    "sg:classifiers":[
        {
            "category":"Shopping",
            "type":"Retail Goods"
        }
    ],
    "sg:phone":"+1 805 683 1838",
    "sg:postcode":"93111",
    "sg:province":"CA",
    "sg:tags":[
        "cosmetic",
        "perfume"
    ],
    "wof:name":"Mary Kay Cosmetics",
    "wof:placetype":"venue"
},
  "geometry": {"coordinates":[-119.817824,34.434379],"type":"Point"}
}