{
  "type": "Feature",
  "properties": {
    "addr:full":"3021 Telegraph Ave Ste D Berkeley CA 94705",
    "addr:housenumber":"3021",
    "addr:postcode":"94705",
    "addr:street":"Telegraph Ave Ste D",
    "iso:country":"US",
    "sg:address":"3021 Telegraph Ave Ste D",
    "sg:city":"Berkeley",
    "sg:classifiers":[
        {
            "category":"Health Services",
            "subcategory":"Clinic",
            "type":"Services"
        },
        {
            "category":"Education",
            "subcategory":"School",
            "type":"Public Place"
        },
        {
            "category":"Communications",
            "type":"Services"
        }
    ],
    "sg:phone":"+1 925 945 1474",
    "sg:postcode":"94705",
    "sg:province":"CA",
    "sg:tags":[
        "pathologist",
        "speech-language",
        "medical"
    ],
    "sg:website":"www.speechpathologygroup.com",
    "wof:name":"The Speech Pathology Group",
    "wof:placetype":"venue"
},
  "geometry": {"coordinates":[-122.259445,37.855392],"type":"Point"}
}