{
  "type": "Feature",
  "properties": {
    "addr:full":"9101 S Normandie Ave Los Angeles CA 90044",
    "addr:housenumber":"9101",
    "addr:postcode":"90044",
    "addr:street":"S Normandie Ave",
    "iso:country":"US",
    "sg:address":"9101 S Normandie Ave",
    "sg:city":"Los Angeles",
    "sg:classifiers":[
        {
            "category":"Organizations",
            "subcategory":"Religious Organization",
            "type":"Services"
        }
    ],
    "sg:phone":"+1 323 756 4555",
    "sg:postcode":"90044",
    "sg:province":"CA",
    "sg:tags":[
        "church"
    ],
    "wof:name":"Church Of The Living God",
    "wof:placetype":"venue"
},
  "geometry": {"coordinates":[-118.30025500000001,33.954105],"type":"Point"}
}