{
  "type": "Feature",
  "properties": {
    "addr:full":"2123 A St La Verne CA 91750",
    "addr:housenumber":"2123",
    "addr:postcode":"91750",
    "addr:street":"A St",
    "iso:country":"US",
    "sg:address":"2123 A St",
    "sg:city":"La Verne",
    "sg:classifiers":[
        {
            "category":"Insurance",
            "subcategory":"Insurance Agent",
            "type":"Services"
        }
    ],
    "sg:phone":"+1 909 593 4665",
    "sg:postcode":"91750",
    "sg:province":"CA",
    "sg:website":"www.priamerica.com",
    "wof:name":"Harris & Harris",
    "wof:placetype":"venue"
},
  "geometry": {"coordinates":[-117.776819,34.100351],"type":"Point"}
}