{
  "type": "Feature",
  "properties": {
    "addr:full":"531 W Lockeford St Lodi CA 95240",
    "addr:housenumber":"531",
    "addr:postcode":"95240",
    "addr:street":"W Lockeford St",
    "iso:country":"US",
    "sg:address":"531 W Lockeford St",
    "sg:city":"Lodi",
    "sg:classifiers":[
        {
            "category":"Restaurant",
            "type":"Food & Drink"
        }
    ],
    "sg:phone":"+1 209 333 0299",
    "sg:postcode":"95240",
    "sg:province":"CA",
    "sg:tags":[
        "caterer"
    ],
    "wof:name":"Affair To Remember",
    "wof:placetype":"venue"
},
  "geometry": {"coordinates":[-121.280154,38.138141],"type":"Point"}
}