{
  "type": "Feature",
  "properties": {
    "addr:full":"3701 Wilshire Blvd Los Angeles CA 90010",
    "addr:housenumber":"3701",
    "addr:postcode":"90010",
    "addr:street":"Wilshire Blvd",
    "iso:country":"US",
    "sg:address":"3701 Wilshire Blvd",
    "sg:city":"Los Angeles",
    "sg:classifiers":[
        {
            "category":"Professional",
            "type":"Services"
        }
    ],
    "sg:phone":"+1 213 480 7790",
    "sg:postcode":"90010",
    "sg:province":"CA",
    "sg:tags":[
        "establishment"
    ],
    "wof:name":"Stc Corp",
    "wof:placetype":"venue"
},
  "geometry": {"coordinates":[-118.30783599999999,34.061699],"type":"Point"}
}