{
  "type": "Feature",
  "properties": {
    "addr:full":"112 Grand Ave Oroville CA 95965",
    "addr:housenumber":"112",
    "addr:postcode":"95965",
    "addr:street":"Grand Ave",
    "iso:country":"US",
    "sg:address":"112 Grand Ave",
    "sg:city":"Oroville",
    "sg:classifiers":[
        {
            "category":"Social Services",
            "subcategory":"Adult Care",
            "type":"Services"
        }
    ],
    "sg:phone":"+1 530 532 9354",
    "sg:postcode":"95965",
    "sg:province":"CA",
    "sg:tags":[
        "home",
        "residential"
    ],
    "wof:name":"C & C Care Home",
    "wof:placetype":"venue"
},
  "geometry": {"coordinates":[-121.564115,39.518648],"type":"Point"}
}