{
  "type": "Feature",
  "properties": {
    "addr:full":"3053 Rancho Vista Blvd Palmdale CA 93551",
    "addr:housenumber":"3053",
    "addr:postcode":"ca 93551",
    "addr:street":"Rancho Vista Blvd",
    "iso:country":"US",
    "sg:address":"3053 Rancho Vista Blvd",
    "sg:city":"Palmdale",
    "sg:classifiers":[
        {
            "category":"Shopping",
            "subcategory":"Hobbies, Toys, & Games",
            "type":"Retail Goods"
        }
    ],
    "sg:phone":"+1 661 538 1099",
    "sg:postcode":"93551",
    "sg:province":"CA",
    "wof:name":"Tots Service",
    "wof:placetype":"venue"
},
  "geometry": {"coordinates":[-118.18925,34.604709],"type":"Point"}
}