{
  "type": "Feature",
  "properties": {
    "iso:country":"US",
    "sg:address":"271 Lafayette Cir",
    "sg:city":"Lafayette",
    "sg:classifiers":[
        {
            "category":"Real Estate",
            "subcategory":"Real Estate Agent",
            "type":"Services"
        }
    ],
    "sg:phone":"+1 925 283 3488",
    "sg:postcode":"94549",
    "sg:province":"CA",
    "wof:name":"Kinnaird Properties",
    "wof:placetype":"venue"
},
  "geometry": {"coordinates":[-122.121918,37.890134],"type":"Point"}
}