{
  "type": "Feature",
  "properties": {
    "addr:full":"1735 Chester Ln Cambria CA 93428",
    "addr:housenumber":"1735",
    "addr:postcode":"93428",
    "addr:street":"Chester Ln",
    "iso:country":"US",
    "sg:address":"1735 Chester Ln",
    "sg:city":"Cambria",
    "sg:classifiers":[
        {
            "category":"Social Services",
            "subcategory":"Child Care",
            "type":"Services"
        }
    ],
    "sg:phone":"+1 805 927 4958",
    "sg:postcode":"93428",
    "sg:province":"CA",
    "sg:tags":[
        "kindergarten",
        "academic",
        "school"
    ],
    "wof:name":"New Dawn Montessori",
    "wof:placetype":"venue"
},
  "geometry": {"coordinates":[-121.083983,35.545858],"type":"Point"}
}