{
  "type": "Feature",
  "properties": {
    "addr:full":"146 Grissom Ct Hercules CA 94547",
    "addr:housenumber":"146",
    "addr:postcode":"94547",
    "addr:street":"Grissom Ct",
    "iso:country":"US",
    "sg:address":"146 Grissom Ct",
    "sg:city":"Hercules",
    "sg:classifiers":[
        {
            "category":"Building & Trades",
            "subcategory":"Plumbing",
            "type":"Services"
        }
    ],
    "sg:phone":"+1 510 799 1480",
    "sg:postcode":"94547",
    "sg:province":"CA",
    "sg:tags":[
        "contractor"
    ],
    "wof:name":"Denmuller Mechanical Inc",
    "wof:placetype":"venue"
},
  "geometry": {"coordinates":[-122.24095699999999,37.99851],"type":"Point"}
}