{
  "type": "Feature",
  "properties": {
    "iso:country":"US",
    "sg:address":"303 H St",
    "sg:city":"Chula Vista",
    "sg:classifiers":[
        {
            "category":"Recreation",
            "type":"Entertainment"
        }
    ],
    "sg:phone":"+1 619 426 4278",
    "sg:postcode":"91910",
    "sg:province":"CA",
    "sg:tags":[
        "martial",
        "arts",
        "instruction"
    ],
    "wof:name":"Family Fine Arts Academy",
    "wof:placetype":"venue"
},
  "geometry": {"coordinates":[-117.07918600000001,32.633913],"type":"Point"}
}