{
  "type": "Feature",
  "properties": {
    "iso:country":"US",
    "sg:address":"38339 Jeanette St",
    "sg:city":"Palmdale",
    "sg:classifiers":[
        {
            "category":"Home & Garden",
            "subcategory":"Building Materials",
            "type":"Retail Goods"
        },
        {
            "category":"Building & Trades",
            "subcategory":"Construction",
            "type":"Services"
        }
    ],
    "sg:phone":"+1 661 947 1868",
    "sg:postcode":"93550",
    "sg:province":"CA",
    "sg:tags":[
        "concrete",
        "staining",
        "contractor"
    ],
    "wof:name":"Shotcrete Advance",
    "wof:placetype":"venue"
},
  "geometry": {"coordinates":[-118.10016400000001,34.577456],"type":"Point"}
}