{
  "type": "Feature",
  "properties": {
    "iso:country":"US",
    "sg:address":"3505 Canfield Dr",
    "sg:city":"Danville",
    "sg:classifiers":[
        {
            "category":"Real Estate",
            "subcategory":"Real Estate Agent",
            "type":"Services"
        }
    ],
    "sg:phone":"+1 925 735 2079",
    "sg:postcode":"94526",
    "sg:province":"CA",
    "wof:name":"M George",
    "wof:placetype":"venue"
},
  "geometry": {"coordinates":[-121.969239,37.790049],"type":"Point"}
}