{
  "type": "Feature",
  "properties": {
    "addr:full":"2611 S Coast Highway 101 Ste 101 Cardiff by the Sea CA 92007",
    "addr:housenumber":"2611",
    "addr:postcode":"92007",
    "addr:street":"S Coast Highway 101 Ste 101",
    "iso:country":"US",
    "sg:address":"2611 S Coast Highway 101 Ste 101",
    "sg:city":"Cardiff by the Sea",
    "sg:classifiers":[
        {
            "category":"Real Estate",
            "subcategory":"Real Estate Services",
            "type":"Services"
        }
    ],
    "sg:phone":"+1 760 634 2076",
    "sg:postcode":"92007",
    "sg:province":"CA",
    "sg:tags":[
        "management",
        "property"
    ],
    "wof:name":"Djanogly Sidney",
    "wof:placetype":"venue"
},
  "geometry": {"coordinates":[-117.279039,33.011947],"type":"Point"}
}