{
  "type": "Feature",
  "properties": {
    "addr:full":"4091 Arena Way Atwater CA 95301",
    "addr:housenumber":"4091",
    "addr:postcode":"95301",
    "addr:street":"Arena Way",
    "iso:country":"US",
    "sg:address":"4091 Arena Way",
    "sg:city":"Atwater",
    "sg:classifiers":[
        {
            "category":"Farming",
            "subcategory":"Crops",
            "type":"Manufacturing & Wholesale Goods"
        }
    ],
    "sg:phone":"+1 209 394 7098",
    "sg:postcode":"95301",
    "sg:province":"CA",
    "sg:tags":[
        "grove",
        "nut",
        "tree"
    ],
    "wof:name":"Marvin Schmidt",
    "wof:placetype":"venue"
},
  "geometry": {"coordinates":[-120.677802,37.35175],"type":"Point"}
}