{
  "type": "Feature",
  "properties": {
    "addr:full":"1410 S McDowell Blvd Petaluma CA 94954",
    "addr:housenumber":"1410",
    "addr:postcode":"94954",
    "addr:street":"S Mcdowell Blvd",
    "iso:country":"US",
    "sg:address":"1410 S McDowell Blvd",
    "sg:city":"Petaluma",
    "sg:classifiers":[
        {
            "category":"Personal",
            "subcategory":"Beauty Salon",
            "type":"Services"
        }
    ],
    "sg:phone":"+1 707 765 0319",
    "sg:postcode":"94954",
    "sg:province":"CA",
    "sg:tags":[
        "manicuring"
    ],
    "wof:name":"M & M Nails",
    "wof:placetype":"venue"
},
  "geometry": {"coordinates":[-122.601308,38.23532],"type":"Point"}
}