{
  "type": "Feature",
  "properties": {
    "iso:country":"US",
    "sg:address":"9355 Bass Rd",
    "sg:city":"Kelseyville",
    "sg:classifiers":[
        {
            "category":"Professional",
            "type":"Services"
        }
    ],
    "sg:phone":"+1 707 279 0232",
    "sg:postcode":"95451",
    "sg:province":"CA",
    "sg:tags":[
        "establishment"
    ],
    "wof:name":"Ziebell & Ziebell",
    "wof:placetype":"venue"
},
  "geometry": {"coordinates":[-122.73390000000001,38.981297],"type":"Point"}
}