{
  "type": "Feature",
  "properties": {
    "iso:country":"US",
    "sg:address":"28181 Sorrento",
    "sg:city":"Laguna Niguel",
    "sg:classifiers":[
        {
            "category":"Professional",
            "subcategory":"Business Services",
            "type":"Services"
        }
    ],
    "sg:phone":"+1 949 683 6582",
    "sg:postcode":"92677",
    "sg:province":"CA",
    "sg:tags":[
        "notary"
    ],
    "wof:name":"H L Notary & Processing",
    "wof:placetype":"venue"
},
  "geometry": {"coordinates":[-117.678135,33.549833],"type":"Point"}
}