{
  "type": "Feature",
  "properties": {
    "addr:full":"14405 Prairie Ave Lawndale CA 90260",
    "addr:housenumber":"14405",
    "addr:postcode":"ca 90260",
    "addr:street":"Prairie Ave",
    "iso:country":"US",
    "sg:address":"14405 Prairie Ave",
    "sg:city":"Lawndale",
    "sg:classifiers":[
        {
            "category":"Personal",
            "subcategory":"Beauty Salon",
            "type":"Services"
        }
    ],
    "sg:phone":"+1 310 644 6900",
    "sg:postcode":"90260",
    "sg:province":"CA",
    "wof:name":"Camacho Beauty Salon",
    "wof:placetype":"venue"
},
  "geometry": {"coordinates":[-118.343912,33.900617],"type":"Point"}
}