{
  "type": "Feature",
  "properties": {
    "iso:country":"US",
    "sg:address":"4748 Olive Oak Way",
    "sg:city":"Carmichael",
    "sg:classifiers":[
        {
            "category":"Shopping",
            "subcategory":"Bicycles & Sporting Goods",
            "type":"Retail Goods"
        }
    ],
    "sg:phone":"+1 916 225 7557",
    "sg:postcode":"95608",
    "sg:province":"CA",
    "sg:tags":[
        "equipment",
        "golf",
        "supply"
    ],
    "wof:name":"Built 4U Golf Clubs",
    "wof:placetype":"venue"
},
  "geometry": {"coordinates":[-121.351703,38.597619],"type":"Point"}
}