{
  "type": "Feature",
  "properties": {
    "iso:country":"US",
    "sg:address":"16941 Beach Blvd",
    "sg:city":"Huntington Beach",
    "sg:classifiers":[
        {
            "category":"Personal",
            "type":"Services"
        },
        {
            "category":"Retail",
            "subcategory":"Storage",
            "type":"Services"
        }
    ],
    "sg:phone":"+1 714 847 2960",
    "sg:postcode":"92647",
    "sg:province":"CA",
    "sg:tags":[
        "mover",
        "self"
    ],
    "wof:name":"Budget Rent A Car System Inc",
    "wof:placetype":"venue"
},
  "geometry": {"coordinates":[-117.988998,33.7164],"type":"Point"}
}