{
  "type": "Feature",
  "properties": {
    "addr:full":"3003 Bunker Hill Lane Suite 220 Santa Clara CA 95054",
    "addr:housenumber":"3003",
    "addr:postcode":"95054",
    "addr:street":"Bunker Hill Lane Suite 220",
    "iso:country":"US",
    "sg:address":"3003 Bunker Hill Lane Suite 220",
    "sg:city":"Santa Clara",
    "sg:classifiers":[
        {
            "category":"Professional",
            "subcategory":"Computer Services",
            "type":"Services"
        }
    ],
    "sg:phone":"+1 408 343 8300",
    "sg:postcode":"95054",
    "sg:province":"CA",
    "sg:website":"http://www.whitehatsec.com",
    "wof:name":"WhiteHat Security",
    "wof:placetype":"venue"
},
  "geometry": {"coordinates":[-121.981998,37.405763],"type":"Point"}
}