{
  "type": "Feature",
  "properties": {
    "iso:country":"US",
    "sg:address":"19620 Moorshire Dr",
    "sg:city":"Cerritos",
    "sg:classifiers":[
        {
            "category":"Home & Garden",
            "subcategory":"Household Appliances",
            "type":"Retail Goods"
        }
    ],
    "sg:phone":"+1 562 924 5312",
    "sg:postcode":"90703",
    "sg:province":"CA",
    "sg:website":"www.vandlappliance.com",
    "wof:name":"V & L Appliance Service & Repair",
    "wof:placetype":"venue"
},
  "geometry": {"coordinates":[-118.056,33.8521],"type":"Point"}
}