{
  "type": "Feature",
  "properties": {
    "addr:full":"303 Blossom Hill Rd #365 San Jose CA 95123",
    "addr:housenumber":"303",
    "addr:postcode":"95123",
    "addr:street":"Blossom Hill Rd # 365",
    "iso:country":"US",
    "sg:address":"303 Blossom Hill Rd #365",
    "sg:city":"San Jose",
    "sg:classifiers":[
        {
            "category":"Health Services",
            "subcategory":"Clinic",
            "type":"Services"
        }
    ],
    "sg:postcode":"95123",
    "sg:province":"CA",
    "sg:tags":[
        "medical"
    ],
    "wof:name":"Dr. William O'Connor",
    "wof:placetype":"venue"
},
  "geometry": {"coordinates":[-121.821865,37.251528],"type":"Point"}
}