{
  "type": "Feature",
  "properties": {
    "addr:full":"14276 County Line Rd Delano CA 93215",
    "addr:housenumber":"14276",
    "addr:postcode":"93215",
    "addr:street":"County Line Rd",
    "iso:country":"US",
    "sg:address":"14276 County Line Rd",
    "sg:city":"Delano",
    "sg:classifiers":[
        {
            "category":"Farming",
            "subcategory":"Farm",
            "type":"Manufacturing & Wholesale Goods"
        }
    ],
    "sg:phone":"+1 661 720 9410",
    "sg:postcode":"93215",
    "sg:province":"CA",
    "wof:name":"Kovacevich 5 Farms",
    "wof:placetype":"venue"
},
  "geometry": {"coordinates":[-119.22582800000001,35.790478],"type":"Point"}
}