{
  "type": "Feature",
  "properties": {
    "iso:country":"US",
    "sg:address":"307 San Juan Grade Rd",
    "sg:city":"Salinas",
    "sg:classifiers":[
        {
            "category":"Autos & Motor Vehicles",
            "subcategory":"Fuel & Gas Station",
            "type":"Retail Goods"
        }
    ],
    "sg:phone":"+1 831 449 3470",
    "sg:postcode":"93906",
    "sg:province":"CA",
    "sg:tags":[
        "oil"
    ],
    "wof:name":"Chevron-Cecil's",
    "wof:placetype":"venue"
},
  "geometry": {"coordinates":[-121.64068,36.730949],"type":"Point"}
}