{
  "type": "Feature",
  "properties": {
    "addr:full":"673 Valencia St San Francisco CA 94110",
    "addr:housenumber":"673",
    "addr:postcode":"94110",
    "addr:street":"Valencia St",
    "iso:country":"US",
    "sg:address":"673 Valencia St",
    "sg:city":"San Francisco",
    "sg:classifiers":[
        {
            "category":"Social Services",
            "subcategory":"Child Care",
            "type":"Services"
        }
    ],
    "sg:phone":"+1 415 552 0169",
    "sg:postcode":"94110",
    "sg:province":"CA",
    "sg:tags":[
        "kindergarten",
        "academic",
        "school"
    ],
    "wof:name":"Mission Head Start",
    "wof:placetype":"venue"
},
  "geometry": {"coordinates":[-122.42154600000001,37.762267],"type":"Point"}
}