{
  "type": "Feature",
  "properties": {
    "addr:full":"1231 Gary Way Apt 31 Woodland CA 95695",
    "addr:housenumber":"1231;31",
    "addr:postcode":"95695",
    "addr:street":"Gary Way Apt",
    "iso:country":"US",
    "sg:address":"1231 Gary Way Apt 31",
    "sg:city":"Woodland",
    "sg:classifiers":[
        {
            "category":"Retail",
            "subcategory":"Repair Shop",
            "type":"Services"
        }
    ],
    "sg:phone":"+1 707 718 1576",
    "sg:postcode":"95695",
    "sg:province":"CA",
    "sg:tags":[
        "freezers-repair",
        "refrigerator"
    ],
    "wof:name":"Gambles Refrigeration & Air Conditioning",
    "wof:placetype":"venue"
},
  "geometry": {"coordinates":[-121.795697,38.6659],"type":"Point"}
}