{
  "type": "Feature",
  "properties": {
    "addr:full":"524 Main St Placerville CA 95667",
    "addr:housenumber":"524",
    "addr:postcode":"95667",
    "addr:street":"Main St",
    "iso:country":"US",
    "sg:address":"524 Main St",
    "sg:city":"Placerville",
    "sg:classifiers":[
        {
            "category":"Museum",
            "type":"Entertainment"
        }
    ],
    "sg:phone":"+1 530 626 0773",
    "sg:postcode":"95667",
    "sg:province":"CA",
    "wof:name":"El Dorado County Museum",
    "wof:placetype":"venue"
},
  "geometry": {"coordinates":[-120.798511,38.729481],"type":"Point"}
}