{
  "type": "Feature",
  "properties": {
    "iso:country":"US",
    "sg:address":"2610 San Juan Rd",
    "sg:city":"Hollister",
    "sg:classifiers":[
        {
            "category":"Building & Trades",
            "subcategory":"Equipment Rental",
            "type":"Services"
        }
    ],
    "sg:phone":"+1 831 638 1999",
    "sg:postcode":"95023",
    "sg:province":"CA",
    "sg:tags":[
        "contractor"
    ],
    "wof:name":"A Tool Shed Equip Rentals Inc",
    "wof:placetype":"venue"
},
  "geometry": {"coordinates":[-121.434405,36.850044],"type":"Point"}
}