{
  "type": "Feature",
  "properties": {
    "iso:country":"US",
    "sg:address":"327 N San Mateo Dr Ste 7",
    "sg:city":"San Mateo",
    "sg:classifiers":[
        {
            "category":"Health Services",
            "subcategory":"Doctor",
            "type":"Services"
        }
    ],
    "sg:phone":"+1 650 344 8335",
    "sg:postcode":"94401",
    "sg:province":"CA",
    "sg:tags":[
        "psychiatrist"
    ],
    "wof:name":"Marty Samuel C MD Inc",
    "wof:placetype":"venue"
},
  "geometry": {"coordinates":[-122.331001,37.570702],"type":"Point"}
}