{
  "type": "Feature",
  "properties": {
    "addr:full":"275 Centennial Way Ste 105 Tustin CA 92780",
    "addr:housenumber":"275",
    "addr:postcode":"92780",
    "addr:street":"Centennial Way Ste 105",
    "iso:country":"US",
    "sg:address":"275 Centennial Way Ste 105",
    "sg:city":"Tustin",
    "sg:classifiers":[
        {
            "category":"Professional",
            "subcategory":"Accounting & Tax Preparation",
            "type":"Services"
        }
    ],
    "sg:phone":"+1 714 730 1835",
    "sg:postcode":"92780",
    "sg:province":"CA",
    "sg:tags":[
        "accountant"
    ],
    "wof:name":"Cooper Colin CPA",
    "wof:placetype":"venue"
},
  "geometry": {"coordinates":[-117.819,33.743599],"type":"Point"}
}