{
  "type": "Feature",
  "properties": {
    "addr:full":"578 Tipperary Dr Vacaville CA 95688",
    "addr:housenumber":"578",
    "addr:postcode":"95688",
    "addr:street":"Tipperary Dr",
    "iso:country":"US",
    "sg:address":"578 Tipperary Dr",
    "sg:city":"Vacaville",
    "sg:classifiers":[
        {
            "category":"Wholesale",
            "subcategory":"Medical Equipment & Supplies",
            "type":"Manufacturing & Wholesale Goods"
        }
    ],
    "sg:phone":"+1 707 449 0378",
    "sg:postcode":"95688",
    "sg:province":"CA",
    "sg:tags":[
        "physician",
        "surgeon"
    ],
    "wof:name":"Broken Wing Slings",
    "wof:placetype":"venue"
},
  "geometry": {"coordinates":[-121.97542799999999,38.381536],"type":"Point"}
}