{
  "type": "Feature",
  "properties": {
    "addr:full":"3416 Silverbell Rd Chico CA 95973",
    "addr:housenumber":"3416",
    "addr:postcode":"95973",
    "addr:street":"Silverbell Rd",
    "iso:country":"US",
    "sg:address":"3416 Silverbell Rd",
    "sg:city":"Chico",
    "sg:classifiers":[
        {
            "category":"Communications",
            "subcategory":"Television Station",
            "type":"Services"
        }
    ],
    "sg:phone":"+1 530 345 7318",
    "sg:postcode":"95973",
    "sg:province":"CA",
    "sg:tags":[
        "broadcasting",
        "co"
    ],
    "wof:name":"KIWB TV",
    "wof:placetype":"venue"
},
  "geometry": {"coordinates":[-121.870282,39.773821],"type":"Point"}
}