{
  "type": "Feature",
  "properties": {
    "iso:country":"US",
    "sg:address":"4520 N River Rd Apt 29",
    "sg:city":"Oceanside",
    "sg:classifiers":[
        {
            "category":"Real Estate",
            "subcategory":"Real Estate Operator",
            "type":"Services"
        }
    ],
    "sg:phone":"+1 760 439 5612",
    "sg:postcode":"92057",
    "sg:province":"CA",
    "sg:tags":[
        "apartment"
    ],
    "wof:name":"North River Club Apartments",
    "wof:placetype":"venue"
},
  "geometry": {"coordinates":[-117.295998,33.237801],"type":"Point"}
}