{
  "type": "Feature",
  "properties": {
    "addr:full":"3801 3rd St Ste 116 San Francisco CA 94124",
    "addr:housenumber":"3801",
    "addr:postcode":"94124",
    "addr:street":"3Rd St Ste 116",
    "iso:country":"US",
    "sg:address":"3801 3rd St Ste 116",
    "sg:city":"San Francisco",
    "sg:classifiers":[
        {
            "category":"Banks & Credit Unions",
            "subcategory":"Bank",
            "type":"Services"
        }
    ],
    "sg:phone":"+1 415 401 1320",
    "sg:postcode":"94124",
    "sg:province":"CA",
    "sg:website":"www.wellsfargo.com",
    "wof:name":"Wells Fargo",
    "wof:placetype":"venue"
},
  "geometry": {"coordinates":[-122.387432,37.74194],"type":"Point"}
}