{
  "type": "Feature",
  "properties": {
    "addr:full":"2257 Stevens Creek Blvd San Jose CA 95128",
    "addr:housenumber":"2257",
    "addr:postcode":"95128",
    "addr:street":"Stevens Creek Blvd",
    "iso:country":"US",
    "sg:address":"2257 Stevens Creek Blvd",
    "sg:city":"San Jose",
    "sg:classifiers":[
        {
            "category":"Autos & Motor Vehicles",
            "subcategory":"Automobile Sales",
            "type":"Retail Goods"
        }
    ],
    "sg:phone":"+1 408 971 4975",
    "sg:postcode":"95128",
    "sg:province":"CA",
    "sg:tags":[
        "car"
    ],
    "wof:name":"H & K Auto Sales & Leasing",
    "wof:placetype":"venue"
},
  "geometry": {"coordinates":[-121.932999,37.323299],"type":"Point"}
}