{
  "type": "Feature",
  "properties": {
    "addr:full":"1365 Park St Alameda CA 94501",
    "addr:housenumber":"1365",
    "addr:postcode":"94501",
    "addr:street":"Park St",
    "iso:country":"US",
    "sg:address":"1365 Park St",
    "sg:city":"Alameda",
    "sg:classifiers":[
        {
            "category":"Restaurant",
            "type":"Food & Drink"
        }
    ],
    "sg:phone":"+1 510 473 0136",
    "sg:postcode":"94501",
    "sg:province":"CA",
    "sg:tags":[
        "shop",
        "tea",
        "coffee"
    ],
    "sg:website":"www.peets.com",
    "wof:name":"Peet's Coffee & Tea",
    "wof:placetype":"venue"
},
  "geometry": {"coordinates":[-122.243171,37.763764],"type":"Point"}
}