{
  "type": "Feature",
  "properties": {
    "addr:full":"1580 W San Bernardino Rd Covina CA 91791",
    "addr:housenumber":"1580",
    "addr:postcode":"91791",
    "addr:street":"W San Bernardino Rd",
    "iso:country":"US",
    "sg:address":"1580 W San Bernardino Rd",
    "sg:city":"Covina",
    "sg:classifiers":[
        {
            "category":"Wholesale",
            "subcategory":"Medical Equipment & Supplies",
            "type":"Manufacturing & Wholesale Goods"
        }
    ],
    "sg:phone":"+1 626 732 4545",
    "sg:postcode":"91791",
    "sg:province":"CA",
    "sg:tags":[
        "x",
        "apparatus"
    ],
    "wof:name":"Medical Processor Svc",
    "wof:placetype":"venue"
},
  "geometry": {"coordinates":[-117.921503,34.088869],"type":"Point"}
}