{
  "type": "Feature",
  "properties": {
    "addr:full":"1146 National City Blvd National City CA 91950",
    "addr:housenumber":"1146",
    "addr:postcode":"91950",
    "addr:street":"National City Blvd",
    "iso:country":"US",
    "sg:address":"1146 National City Blvd",
    "sg:city":"National City",
    "sg:classifiers":[
        {
            "category":"Retail",
            "subcategory":"Auto Repair",
            "type":"Services"
        }
    ],
    "sg:phone":"+1 619 474 3353",
    "sg:postcode":"91950",
    "sg:province":"CA",
    "sg:tags":[
        "body",
        "automobile",
        "painting"
    ],
    "wof:name":"One Day Paint & Body Ctr",
    "wof:placetype":"venue"
},
  "geometry": {"coordinates":[-117.105785,32.672756],"type":"Point"}
}