{
  "type": "Feature",
  "properties": {
    "addr:full":"5765 Antone Rd Fremont CA 94538",
    "addr:housenumber":"5765",
    "addr:postcode":"94538",
    "addr:street":"Antone Rd",
    "iso:country":"US",
    "sg:address":"5765 Antone Rd",
    "sg:city":"Fremont",
    "sg:classifiers":[
        {
            "category":"Professional",
            "type":"Services"
        }
    ],
    "sg:phone":"+1 510 490 2032",
    "sg:postcode":"94538",
    "sg:province":"CA",
    "sg:tags":[
        "establishment"
    ],
    "wof:name":"Sterling Care",
    "wof:placetype":"venue"
},
  "geometry": {"coordinates":[-121.973339,37.515066],"type":"Point"}
}