{
  "type": "Feature",
  "properties": {
    "iso:country":"US",
    "sg:address":"2255 G St",
    "sg:city":"Fresno",
    "sg:classifiers":[
        {
            "category":"Retail",
            "subcategory":"Auto Repair",
            "type":"Services"
        }
    ],
    "sg:phone":"+1 559 307 4194",
    "sg:postcode":"93706",
    "sg:province":"CA",
    "sg:tags":[
        "body",
        "automobile",
        "painting"
    ],
    "wof:name":"Maestro's Auto Body",
    "wof:placetype":"venue"
},
  "geometry": {"coordinates":[-119.805213,36.741324],"type":"Point"}
}