{
  "type": "Feature",
  "properties": {
    "addr:full":"1502 Glenn Ave Modesto CA 95358",
    "addr:housenumber":"1502",
    "addr:postcode":"ca 95358",
    "addr:street":"Glenn Ave",
    "iso:country":"US",
    "sg:address":"1502 Glenn Ave",
    "sg:city":"Modesto",
    "sg:classifiers":[
        {
            "category":"Professional",
            "subcategory":"Testing Lab",
            "type":"Services"
        }
    ],
    "sg:phone":"+1 209 581 9646",
    "sg:postcode":"95358",
    "sg:province":"CA",
    "sg:tags":[
        "asbestos"
    ],
    "wof:name":"J W Mack Consulting",
    "wof:placetype":"venue"
},
  "geometry": {"coordinates":[-121.015595,37.60164],"type":"Point"}
}