{
  "type": "Feature",
  "properties": {
    "addr:full":"6452 Stockton Boulevard Sacramento CA 95823",
    "addr:housenumber":"6452",
    "addr:postcode":"95823",
    "addr:street":"Stockton Boulevard",
    "iso:country":"US",
    "sg:address":"6452 Stockton Boulevard",
    "sg:city":"Sacramento",
    "sg:classifiers":[
        {
            "category":"Health Services",
            "subcategory":"Chiropractor",
            "type":"Services"
        }
    ],
    "sg:phone":"+1 916 395 9571",
    "sg:postcode":"95823",
    "sg:province":"CA",
    "wof:name":"Pain Injury Clinic",
    "wof:placetype":"venue"
},
  "geometry": {"coordinates":[-121.43523999999999,38.50885],"type":"Point"}
}