{
  "type": "Feature",
  "properties": {
    "addr:full":"433 McHenry Ave Modesto CA 95354",
    "addr:housenumber":"433",
    "addr:postcode":"ca 95354",
    "addr:street":"Mchenry Ave",
    "iso:country":"US",
    "sg:address":"433 McHenry Ave",
    "sg:city":"Modesto",
    "sg:classifiers":[
        {
            "category":"Shopping",
            "subcategory":"Tobacco",
            "type":"Retail Goods"
        }
    ],
    "sg:phone":"+1 209 575 2667",
    "sg:postcode":"95354",
    "sg:province":"CA",
    "sg:tags":[
        "cigarette",
        "cigar",
        "dealer"
    ],
    "wof:name":"Mc Henry Discount Cigarette",
    "wof:placetype":"venue"
},
  "geometry": {"coordinates":[-120.99383899999999,37.650803],"type":"Point"}
}