{
  "type": "Feature",
  "properties": {
    "iso:country":"US",
    "sg:address":"904 Lexington Dr",
    "sg:city":"Salinas",
    "sg:classifiers":[
        {
            "category":"Freight",
            "type":"Transportation"
        }
    ],
    "sg:phone":"+1 831 442 5963",
    "sg:postcode":"93906",
    "sg:province":"CA",
    "sg:tags":[
        "medical",
        "courier"
    ],
    "wof:name":"Rapid Medical Services",
    "wof:placetype":"venue"
},
  "geometry": {"coordinates":[-121.617577,36.706666],"type":"Point"}
}