{
  "type": "Feature",
  "properties": {
    "addr:full":"500 S Anaheim Hills Rd Anaheim CA 92807",
    "addr:housenumber":"500",
    "addr:postcode":"92807",
    "addr:street":"S Anaheim Hills Rd",
    "iso:country":"US",
    "sg:address":"500 S Anaheim Hills Rd",
    "sg:city":"Anaheim",
    "sg:classifiers":[
        {
            "category":"Health Services",
            "subcategory":"Doctor",
            "type":"Services"
        }
    ],
    "sg:phone":"+1 949 472 4244",
    "sg:postcode":"92807",
    "sg:province":"CA",
    "sg:tags":[
        "medicine",
        "physician",
        "surgeon",
        "internal",
        "surgeons"
    ],
    "wof:name":"Chen Caren H Md",
    "wof:placetype":"venue"
},
  "geometry": {"coordinates":[-117.777412,33.84428],"type":"Point"}
}