{
  "type": "Feature",
  "properties": {
    "addr:full":"611 Anton Blvd Costa Mesa CA 92626",
    "addr:housenumber":"611",
    "addr:postcode":"92626",
    "addr:street":"Anton Blvd Costa",
    "iso:country":"US",
    "sg:address":"611 Anton Blvd",
    "sg:city":"Costa Mesa",
    "sg:classifiers":[
        {
            "category":"Professional",
            "subcategory":"Lawyer & Legal Services",
            "type":"Services"
        }
    ],
    "sg:phone":"+1 714 662 7740",
    "sg:postcode":"92626",
    "sg:province":"CA",
    "sg:tags":[
        "divorce",
        "law",
        "family"
    ],
    "wof:name":"Gazin Michael H Atty",
    "wof:placetype":"venue"
},
  "geometry": {"coordinates":[-117.91100299999999,33.678699],"type":"Point"}
}