{
  "type": "Feature",
  "properties": {
    "iso:country":"US",
    "sg:address":"1585 Forbes Ave",
    "sg:city":"Edwards",
    "sg:classifiers":[
        {
            "category":"Education",
            "subcategory":"School",
            "type":"Public Place"
        }
    ],
    "sg:phone":"+1 661 258 4411",
    "sg:postcode":"93523",
    "sg:province":"CA",
    "wof:name":"Forbes Avenue Elementary Schl",
    "wof:placetype":"venue"
},
  "geometry": {"coordinates":[-117.890308,34.95037],"type":"Point"}
}