{
  "type": "Feature",
  "properties": {
    "addr:full":"3084 Cedar Ravine Rd Placerville CA 95667",
    "addr:housenumber":"3084",
    "addr:postcode":"95667",
    "addr:street":"Cedar Ravine Rd",
    "iso:country":"US",
    "sg:address":"3084 Cedar Ravine Rd",
    "sg:city":"Placerville",
    "sg:classifiers":[
        {
            "category":"Health Services",
            "subcategory":"Health Practitioner",
            "type":"Services"
        }
    ],
    "sg:phone":"+1 530 621 2773",
    "sg:postcode":"95667",
    "sg:province":"CA",
    "sg:tags":[
        "therapist",
        "physical"
    ],
    "wof:name":"Advanced Physical Therapy",
    "wof:placetype":"venue"
},
  "geometry": {"coordinates":[-120.794752,38.726769],"type":"Point"}
}