{
  "type": "Feature",
  "properties": {
    "iso:country":"US",
    "sg:address":"1026 McHenry Ave",
    "sg:city":"Modesto",
    "sg:classifiers":[
        {
            "category":"Shopping",
            "subcategory":"Jewelry",
            "type":"Retail Goods"
        }
    ],
    "sg:phone":"+1 209 521 7364",
    "sg:postcode":"95350",
    "sg:province":"CA",
    "sg:tags":[
        "jeweler"
    ],
    "wof:name":"Shingar Jewelers",
    "wof:placetype":"venue"
},
  "geometry": {"coordinates":[-120.99376700000001,37.657599],"type":"Point"}
}