{
  "type": "Feature",
  "properties": {
    "addr:full":"12474 Central Ave Ste A Chino CA 91710",
    "addr:postcode":"12474;91710",
    "addr:street":"Central Ave Ste A",
    "iso:country":"US",
    "sg:address":"12474 Central Ave Ste A",
    "sg:city":"Chino",
    "sg:classifiers":[
        {
            "category":"Banks & Credit Unions",
            "subcategory":"Bank",
            "type":"Services"
        }
    ],
    "sg:phone":"+1 909 591 6371",
    "sg:postcode":"91710",
    "sg:province":"CA",
    "sg:tags":[
        "saving",
        "commercial"
    ],
    "sg:website":"http://www.pacificwesternbank.com",
    "wof:name":"Pacific Western Bank",
    "wof:placetype":"venue"
},
  "geometry": {"coordinates":[-117.689486,34.026732],"type":"Point"}
}