{
  "type": "Feature",
  "properties": {
    "iso:country":"US",
    "sg:address":"969 6th St",
    "sg:city":"Norco",
    "sg:classifiers":[
        {
            "category":"Shopping",
            "subcategory":"Clothing, Apparel, & Fashions",
            "type":"Retail Goods"
        }
    ],
    "sg:phone":"+1 951 735 4130",
    "sg:postcode":"92860",
    "sg:province":"CA",
    "sg:tags":[
        "western"
    ],
    "wof:name":"Norco Ranch Outfitters",
    "wof:placetype":"venue"
},
  "geometry": {"coordinates":[-117.542297,33.938501],"type":"Point"}
}