{
  "type": "Feature",
  "properties": {
    "iso:country":"US",
    "sg:address":"9898 Trask Ave",
    "sg:city":"Garden Grove",
    "sg:classifiers":[
        {
            "category":"Autos & Motor Vehicles",
            "subcategory":"Automobile Sales",
            "type":"Retail Goods"
        }
    ],
    "sg:phone":"+1 714 539 5757",
    "sg:postcode":"92844",
    "sg:province":"CA",
    "sg:tags":[
        "car"
    ],
    "wof:name":"Union Dodge Inc",
    "wof:placetype":"venue"
},
  "geometry": {"coordinates":[-117.95700100000001,33.766701],"type":"Point"}
}