{
  "type": "Feature",
  "properties": {
    "addr:full":"1712 Berkeley St Santa Monica CA 90404",
    "addr:housenumber":"1712",
    "addr:postcode":"90404",
    "addr:street":"Berkeley St",
    "iso:country":"US",
    "sg:address":"1712 Berkeley St",
    "sg:city":"Santa Monica",
    "sg:classifiers":[
        {
            "category":"Professional",
            "type":"Services"
        }
    ],
    "sg:phone":"+1 310 998 8668",
    "sg:postcode":"90404",
    "sg:province":"CA",
    "wof:name":"Ntropic LLC",
    "wof:placetype":"venue"
},
  "geometry": {"coordinates":[-118.46337,34.032027],"type":"Point"}
}