{
  "type": "Feature",
  "properties": {
    "iso:country":"US",
    "sg:address":"18490 Santa Ana Ave",
    "sg:city":"Bloomington",
    "sg:classifiers":[
        {
            "category":"Organizations",
            "subcategory":"Religious Organization",
            "type":"Services"
        }
    ],
    "sg:phone":"+1 909 877 0341",
    "sg:postcode":"92316",
    "sg:province":"CA",
    "sg:tags":[
        "church"
    ],
    "wof:name":"Bloomington Congregational",
    "wof:placetype":"venue"
},
  "geometry": {"coordinates":[-117.40300499999999,34.055999],"type":"Point"}
}