{
  "type": "Feature",
  "properties": {
    "addr:full":"132 E Yorba Linda Blvd Placentia CA 92870",
    "addr:housenumber":"132",
    "addr:postcode":"ca 92870",
    "addr:street":"E Yorba Linda Blvd",
    "iso:country":"US",
    "sg:address":"132 E Yorba Linda Blvd",
    "sg:city":"Placentia",
    "sg:classifiers":[
        {
            "category":"Shopping",
            "subcategory":"Jewelry",
            "type":"Retail Goods"
        }
    ],
    "sg:phone":"+1 714 524 9888",
    "sg:postcode":"92870",
    "sg:province":"CA",
    "wof:name":"Jewels By Justin",
    "wof:placetype":"venue"
},
  "geometry": {"coordinates":[-117.86574899999999,33.886228],"type":"Point"}
}