{
  "type": "Feature",
  "properties": {
    "addr:full":"1600 Ardmore Ave Hermosa Beach CA 90254",
    "addr:housenumber":"1600",
    "addr:postcode":"90254",
    "addr:street":"Ardmore Ave",
    "iso:country":"US",
    "sg:address":"1600 Ardmore Ave",
    "sg:city":"Hermosa Beach",
    "sg:classifiers":[
        {
            "category":"Real Estate",
            "subcategory":"Real Estate Operator",
            "type":"Services"
        }
    ],
    "sg:phone":"+1 310 379 1600",
    "sg:postcode":"90254",
    "sg:province":"CA",
    "sg:tags":[
        "apartment"
    ],
    "wof:name":"Commodore Apartments",
    "wof:placetype":"venue"
},
  "geometry": {"coordinates":[-118.396473,33.868845],"type":"Point"}
}