{
  "type": "Feature",
  "properties": {
    "iso:country":"US",
    "sg:address":"1041 W 18th St",
    "sg:city":"Costa Mesa",
    "sg:classifiers":[
        {
            "category":"Wholesale",
            "subcategory":"Home Furnishings",
            "type":"Manufacturing & Wholesale Goods"
        }
    ],
    "sg:phone":"+1 949 548 0105",
    "sg:postcode":"92627",
    "sg:province":"CA",
    "sg:tags":[
        "pottery"
    ],
    "wof:name":"Patton Ceramics",
    "wof:placetype":"venue"
},
  "geometry": {"coordinates":[-117.942142,33.639579],"type":"Point"}
}