{
  "type": "Feature",
  "properties": {
    "iso:country":"US",
    "sg:address":"207 Ardennes Cir",
    "sg:city":"Seaside",
    "sg:classifiers":[
        {
            "category":"Professional",
            "type":"Services"
        }
    ],
    "sg:phone":"+1 831 393 9139",
    "sg:postcode":"93955",
    "sg:province":"CA",
    "wof:name":"Chee Bin Tay",
    "wof:placetype":"venue"
},
  "geometry": {"coordinates":[-121.809379,36.634439],"type":"Point"}
}