{
  "type": "Feature",
  "properties": {
    "iso:country":"US",
    "sg:address":"3616 W Pendleton Ave",
    "sg:city":"Santa Ana",
    "sg:classifiers":[
        {
            "category":"Wholesale",
            "subcategory":"Sporting Goods",
            "type":"Manufacturing & Wholesale Goods"
        }
    ],
    "sg:phone":"+1 714 436 0600",
    "sg:postcode":"92704",
    "sg:province":"CA",
    "wof:name":"Black Fly Clothing Company",
    "wof:placetype":"venue"
},
  "geometry": {"coordinates":[-117.917108,33.715955],"type":"Point"}
}