{
  "type": "Feature",
  "properties": {
    "iso:country":"US",
    "sg:address":"118 W Sycamore St",
    "sg:city":"Willows",
    "sg:classifiers":[
        {
            "category":"Communications",
            "subcategory":"Radio Station",
            "type":"Services"
        }
    ],
    "sg:phone":"+1 530 934 4654",
    "sg:postcode":"95988",
    "sg:province":"CA",
    "sg:tags":[
        "company",
        "broadcasting"
    ],
    "wof:name":"KIQS",
    "wof:placetype":"venue"
},
  "geometry": {"coordinates":[-122.194433,39.520458],"type":"Point"}
}