{
  "type": "Feature",
  "properties": {
    "iso:country":"US",
    "sg:address":"3355 Cochran St",
    "sg:city":"Simi Valley",
    "sg:classifiers":[
        {
            "category":"Professional",
            "subcategory":"Management & Consulting",
            "type":"Services"
        }
    ],
    "sg:phone":"+1 805 527 1300",
    "sg:postcode":"93063",
    "sg:province":"CA",
    "sg:tags":[
        "construction"
    ],
    "wof:name":"Continental Filing Svc",
    "wof:placetype":"venue"
},
  "geometry": {"coordinates":[-118.729167,34.279057],"type":"Point"}
}