{
  "type": "Feature",
  "properties": {
    "addr:full":"655 James Dr Placerville CA 95667",
    "addr:housenumber":"655",
    "addr:postcode":"95667",
    "addr:street":"James Dr",
    "iso:country":"US",
    "sg:address":"655 James Dr",
    "sg:city":"Placerville",
    "sg:classifiers":[
        {
            "category":"Farming",
            "subcategory":"Farm",
            "type":"Manufacturing & Wholesale Goods"
        }
    ],
    "sg:phone":"+1 530 622 5039",
    "sg:postcode":"95667",
    "sg:province":"CA",
    "sg:tags":[
        "crop",
        "general"
    ],
    "wof:name":"E Arambel",
    "wof:placetype":"venue"
},
  "geometry": {"coordinates":[-120.81403299999999,38.738974],"type":"Point"}
}