{
  "type": "Feature",
  "properties": {
    "addr:full":"6110 Graciosa Dr Los Angeles CA 90068",
    "addr:housenumber":"6110",
    "addr:postcode":"90068",
    "addr:street":"Graciosa Dr",
    "iso:country":"US",
    "sg:address":"6110 Graciosa Dr",
    "sg:city":"Los Angeles",
    "sg:classifiers":[
        {
            "category":"Wholesale",
            "subcategory":"Furniture",
            "type":"Manufacturing & Wholesale Goods"
        }
    ],
    "sg:phone":"+1 310 890 2387",
    "sg:postcode":"90068",
    "sg:province":"CA",
    "wof:name":"Red 9",
    "wof:placetype":"venue"
},
  "geometry": {"coordinates":[-118.322323,34.112536],"type":"Point"}
}