{
  "type": "Feature",
  "properties": {
    "iso:country":"US",
    "sg:address":"8131 Allport Ave",
    "sg:city":"Santa Fe Springs",
    "sg:classifiers":[
        {
            "category":"Manufacturing",
            "subcategory":"Metals",
            "type":"Manufacturing & Wholesale Goods"
        }
    ],
    "sg:phone":"+1 562 693 6372",
    "sg:postcode":"90670",
    "sg:province":"CA",
    "sg:tags":[
        "steel"
    ],
    "wof:name":"Richer Life",
    "wof:placetype":"venue"
},
  "geometry": {"coordinates":[-118.06457,33.968796],"type":"Point"}
}