{
  "type": "Feature",
  "properties": {
    "addr:full":"3904 Ellenboro Ave Modesto CA 95357",
    "addr:housenumber":"3904",
    "addr:postcode":"ca 95357",
    "addr:street":"Ellenboro Ave",
    "iso:country":"US",
    "sg:address":"3904 Ellenboro Ave",
    "sg:city":"Modesto",
    "sg:classifiers":[
        {
            "category":"Building & Trades",
            "subcategory":"Construction",
            "type":"Services"
        }
    ],
    "sg:phone":"+1 209 602 0426",
    "sg:postcode":"95357",
    "sg:province":"CA",
    "sg:tags":[
        "designer",
        "dealer",
        "pool",
        "swimming"
    ],
    "wof:name":"Blue Lagoon Pools",
    "wof:placetype":"venue"
},
  "geometry": {"coordinates":[-120.92429199999999,37.646746],"type":"Point"}
}