{
  "type": "Feature",
  "properties": {
    "addr:full":"8904 Locust Ave Fontana CA 92335",
    "addr:housenumber":"8904",
    "addr:postcode":"92335",
    "addr:street":"Locust Ave",
    "iso:country":"US",
    "sg:address":"8904 Locust Ave",
    "sg:city":"Fontana",
    "sg:classifiers":[
        {
            "category":"Organizations",
            "subcategory":"Community Association",
            "type":"Services"
        }
    ],
    "sg:phone":"+1 909 822 4801",
    "sg:postcode":"92335",
    "sg:province":"CA",
    "sg:tags":[
        "club"
    ],
    "wof:name":"Club Social Espanol",
    "wof:placetype":"venue"
},
  "geometry": {"coordinates":[-117.409678,34.09101],"type":"Point"}
}