{
  "type": "Feature",
  "properties": {
    "iso:country":"US",
    "sg:address":"4407 W Jefferson Blvd",
    "sg:city":"Los Angeles",
    "sg:classifiers":[
        {
            "category":"Food & Beverages",
            "subcategory":"Liquor & Beverages",
            "type":"Retail Goods"
        }
    ],
    "sg:phone":"+1 323 732 3383",
    "sg:postcode":"90016",
    "sg:province":"CA",
    "sg:tags":[
        "beer",
        "spirit",
        "wine"
    ],
    "wof:name":"Pg's Liquor",
    "wof:placetype":"venue"
},
  "geometry": {"coordinates":[-118.344002,34.025398],"type":"Point"}
}