{
  "type": "Feature",
  "properties": {
    "iso:country":"US",
    "sg:address":"9940 Cockle Bur Ct",
    "sg:city":"Salinas",
    "sg:classifiers":[
        {
            "category":"Building & Trades",
            "subcategory":"Electrical",
            "type":"Services"
        }
    ],
    "sg:phone":"+1 831 633 4435",
    "sg:postcode":"93907",
    "sg:province":"CA",
    "sg:tags":[
        "electrical",
        "contractor"
    ],
    "wof:name":"Lonestar Electric",
    "wof:placetype":"venue"
},
  "geometry": {"coordinates":[-121.730411,36.775469],"type":"Point"}
}