{
  "type": "Feature",
  "properties": {
    "iso:country":"US",
    "sg:address":"240 Pope St",
    "sg:city":"St Helena",
    "sg:classifiers":[
        {
            "category":"Building & Trades",
            "subcategory":"Construction",
            "type":"Services"
        }
    ],
    "sg:phone":"+1 707 963 9003",
    "sg:postcode":"94574",
    "sg:province":"CA",
    "sg:tags":[
        "company"
    ],
    "wof:name":"Binistar Inc",
    "wof:placetype":"venue"
},
  "geometry": {"coordinates":[-122.457731,38.509858],"type":"Point"}
}