{
  "type": "Feature",
  "properties": {
    "addr:full":"1695 Hillsdale Ave San Jose CA 95124",
    "addr:housenumber":"1695",
    "addr:postcode":"95124",
    "addr:street":"Hillsdale Ave",
    "iso:country":"US",
    "sg:address":"1695 Hillsdale Ave",
    "sg:city":"San Jose",
    "sg:classifiers":[
        {
            "category":"Sports & Exercise",
            "subcategory":"Swimming Pool",
            "type":"Entertainment"
        }
    ],
    "sg:phone":"+1 408 445 2264",
    "sg:postcode":"95124",
    "sg:province":"CA",
    "sg:website":"www.sjpools.com",
    "wof:name":"SJ Pools",
    "wof:placetype":"venue"
},
  "geometry": {"coordinates":[-121.909712,37.26654],"type":"Point"}
}