{
  "type": "Feature",
  "properties": {
    "addr:full":"1540 E El Monte Way Dinuba CA 93618",
    "addr:housenumber":"1540",
    "addr:postcode":"93618",
    "addr:street":"E El Monte Way",
    "iso:country":"US",
    "sg:address":"1540 E El Monte Way",
    "sg:city":"Dinuba",
    "sg:classifiers":[
        {
            "category":"Professional",
            "type":"Services"
        },
        {
            "category":"Restaurant",
            "type":"Food & Drink"
        },
        {
            "category":"Fast Food",
            "type":"Food & Drink"
        }
    ],
    "sg:phone":"+1 559 591 6110",
    "sg:postcode":"93618",
    "sg:province":"CA",
    "sg:tags":[
        "delivery",
        "style",
        "take",
        "family",
        "pizza"
    ],
    "sg:website":"http://www.pizzahut.com",
    "wof:name":"Pizza Hut",
    "wof:placetype":"venue"
},
  "geometry": {"coordinates":[-119.378486,36.545468],"type":"Point"}
}