{
  "type": "Feature",
  "properties": {
    "addr:full":"1800 Rollins Rd Burlingame CA 94010",
    "addr:housenumber":"1800",
    "addr:postcode":"94010",
    "addr:street":"Rollins Rd",
    "iso:country":"US",
    "sg:address":"1800 Rollins Rd",
    "sg:city":"Burlingame",
    "sg:classifiers":[
        {
            "category":"Education",
            "subcategory":"Special Training",
            "type":"Public Place"
        }
    ],
    "sg:phone":"+1 650 802 5400",
    "sg:postcode":"94010",
    "sg:province":"CA",
    "sg:tags":[
        "adult"
    ],
    "sg:website":"www.smcoe.k12.ca.us/apps/Comm.as...",
    "wof:name":"San Mateo County Office of Edu - Regional Occupational Program",
    "wof:placetype":"venue"
},
  "geometry": {"coordinates":[-122.379369,37.598134],"type":"Point"}
}