{
  "type": "Feature",
  "properties": {
    "iso:country":"US",
    "sg:address":"9301 Tampa Ave",
    "sg:city":"Northridge",
    "sg:classifiers":[
        {
            "category":"Shopping",
            "subcategory":"Clothing, Apparel, & Fashions",
            "type":"Retail Goods"
        }
    ],
    "sg:phone":"+1 818 349 0536",
    "sg:postcode":"91324",
    "sg:province":"CA",
    "sg:website":"www.anchorblue.com",
    "wof:name":"Anchor Blue",
    "wof:placetype":"venue"
},
  "geometry": {"coordinates":[-118.55357100000001,34.242742],"type":"Point"}
}