{
  "type": "Feature",
  "properties": {
    "addr:full":"1415 W Magnolia Blvd Burbank CA 91506",
    "addr:housenumber":"1415",
    "addr:postcode":"91506",
    "addr:street":"W Magnolia Blvd",
    "iso:country":"US",
    "sg:address":"1415 W Magnolia Blvd",
    "sg:city":"Burbank",
    "sg:classifiers":[
        {
            "category":"Arts & Performance",
            "subcategory":"Theater",
            "type":"Entertainment"
        }
    ],
    "sg:phone":"+1 818 840 9755",
    "sg:postcode":"91506",
    "sg:province":"CA",
    "sg:tags":[
        "entertainer",
        "adult"
    ],
    "wof:name":"Boulevard Entertainment the",
    "wof:placetype":"venue"
},
  "geometry": {"coordinates":[-118.32399700000001,34.1754],"type":"Point"}
}