{
  "type": "Feature",
  "properties": {
    "iso:country":"US",
    "sg:address":"3805 San Dimas St",
    "sg:city":"Bakersfield",
    "sg:classifiers":[
        {
            "category":"Health Services",
            "subcategory":"Doctor",
            "type":"Services"
        }
    ],
    "sg:phone":"+1 661 327 0843",
    "sg:postcode":"93301",
    "sg:province":"CA",
    "sg:tags":[
        "physician",
        "surgeon"
    ],
    "wof:name":"Mark L Nystrom MD",
    "wof:placetype":"venue"
},
  "geometry": {"coordinates":[-119.00825,35.396146],"type":"Point"}
}