{
  "type": "Feature",
  "properties": {
    "addr:full":"702 Gold Lake Dr Folsom CA 95630",
    "addr:housenumber":"702",
    "addr:postcode":"95630",
    "addr:street":"Gold Lake Dr",
    "iso:country":"US",
    "sg:address":"702 Gold Lake Dr",
    "sg:city":"Folsom",
    "sg:classifiers":[
        {
            "category":"Travel",
            "subcategory":"Hotels & Motels",
            "type":"Entertainment"
        }
    ],
    "sg:phone":"+1 916 351 1500",
    "sg:postcode":"95630",
    "sg:province":"CA",
    "sg:website":"www.lakenatomainn.com",
    "wof:name":"Lake Natoma Inn",
    "wof:placetype":"venue"
},
  "geometry": {"coordinates":[-121.179484,38.678172],"type":"Point"}
}