{
  "type": "Feature",
  "properties": {
    "addr:full":"8040 Lake Shore Dr Chowchilla CA 93610",
    "addr:housenumber":"8040",
    "addr:postcode":"93610",
    "addr:street":"Lake Shore Dr",
    "iso:country":"US",
    "sg:address":"8040 Lake Shore Dr",
    "sg:city":"Chowchilla",
    "sg:classifiers":[
        {
            "category":"Place Of Worship",
            "subcategory":"Church",
            "type":"Public Place"
        },
        {
            "category":"Place Of Worship",
            "type":"Public Place"
        },
        {
            "category":"Organizations",
            "subcategory":"Religious Organization",
            "type":"Services"
        }
    ],
    "sg:phone":"+1 559 665 3191",
    "sg:postcode":"93610",
    "sg:province":"CA",
    "sg:tags":[
        "god",
        "churches-church",
        "churches-pentecostal"
    ],
    "wof:name":"Passion Driven Minstries",
    "wof:placetype":"venue"
},
  "geometry": {"coordinates":[-120.23692200000001,37.116688],"type":"Point"}
}