{
  "type": "Feature",
  "properties": {
    "addr:full":"575 S San Jacinto St Hemet CA 92543",
    "addr:housenumber":"575",
    "addr:postcode":"92543",
    "addr:street":"S San Jacinto St",
    "iso:country":"US",
    "sg:address":"575 S San Jacinto St",
    "sg:city":"Hemet",
    "sg:classifiers":[
        {
            "category":"Organizations",
            "subcategory":"Religious Organization",
            "type":"Services"
        }
    ],
    "sg:phone":"+1 951 925 7317",
    "sg:postcode":"92543",
    "sg:province":"CA",
    "sg:tags":[
        "church"
    ],
    "sg:website":"www.hemet-centralcofc.com",
    "wof:name":"Church Of Christ",
    "wof:placetype":"venue"
},
  "geometry": {"coordinates":[-116.95865499999999,33.739494],"type":"Point"}
}