{
  "type": "Feature",
  "properties": {
    "iso:country":"US",
    "sg:address":"34147 Avenue E",
    "sg:city":"Yucaipa",
    "sg:classifiers":[
        {
            "category":"Building & Trades",
            "subcategory":"Construction",
            "type":"Services"
        }
    ],
    "sg:phone":"+1 909 797 6307",
    "sg:postcode":"92399",
    "sg:province":"CA",
    "sg:tags":[
        "concrete",
        "contractor"
    ],
    "wof:name":"Shoffeitt Construction",
    "wof:placetype":"venue"
},
  "geometry": {"coordinates":[-117.05722299999999,34.026566],"type":"Point"}
}