{
  "type": "Feature",
  "properties": {
    "addr:full":"15606 S Hacienda Blvd Hacienda Heights CA 91745",
    "addr:housenumber":"15606",
    "addr:postcode":"91745",
    "addr:street":"S Hacienda Blvd",
    "iso:country":"US",
    "sg:address":"15606 S Hacienda Blvd",
    "sg:city":"Hacienda Heights",
    "sg:classifiers":[
        {
            "category":"Shopping",
            "subcategory":"Gifts & Souvenirs",
            "type":"Retail Goods"
        }
    ],
    "sg:phone":"+1 626 330 1444",
    "sg:postcode":"91745",
    "sg:province":"CA",
    "sg:tags":[
        "cards"
    ],
    "wof:name":"Rays Sports Cards",
    "wof:placetype":"venue"
},
  "geometry": {"coordinates":[-117.971025,33.986613],"type":"Point"}
}