{
  "type": "Feature",
  "properties": {
    "iso:country":"US",
    "sg:address":"2055 Fox Way",
    "sg:city":"Concord",
    "sg:classifiers":[
        {
            "category":"Real Estate",
            "subcategory":"Real Estate Services",
            "type":"Services"
        },
        {
            "category":"Home & Garden",
            "subcategory":"Home Furnishings",
            "type":"Retail Goods"
        },
        {
            "category":"Real Estate",
            "subcategory":"Real Estate Operator",
            "type":"Services"
        }
    ],
    "sg:phone":"+1 925 676 9080",
    "sg:postcode":"94518",
    "sg:province":"CA",
    "sg:tags":[
        "apartments-furnished",
        "vacancy",
        "apartment",
        "rental",
        "listing"
    ],
    "sg:website":"http://www.rent-one.com",
    "wof:name":"Oakview Apartments",
    "wof:placetype":"venue"
},
  "geometry": {"coordinates":[-122.034763,37.950442],"type":"Point"}
}