{
  "type": "Feature",
  "properties": {
    "addr:full":"1605 W Carson St Torrance CA 90501",
    "addr:housenumber":"1605",
    "addr:postcode":"90501",
    "addr:street":"W Carson St",
    "iso:country":"US",
    "sg:address":"1605 W Carson St",
    "sg:city":"Torrance",
    "sg:classifiers":[
        {
            "category":"Autos & Motor Vehicles",
            "subcategory":"Fuel & Gas Station",
            "type":"Retail Goods"
        }
    ],
    "sg:phone":"+1 310 328 6605",
    "sg:postcode":"90501",
    "sg:province":"CA",
    "wof:name":"Allan's Arco",
    "wof:placetype":"venue"
},
  "geometry": {"coordinates":[-118.306999,33.831402],"type":"Point"}
}