{
  "type": "Feature",
  "properties": {
    "addr:full":"2332 5th St Berkeley CA 94710",
    "addr:housenumber":"2332",
    "addr:postcode":"94710",
    "addr:street":"5Th St",
    "iso:country":"US",
    "sg:address":"2332 5th St",
    "sg:city":"Berkeley",
    "sg:classifiers":[
        {
            "category":"Home & Garden",
            "subcategory":"Furniture",
            "type":"Retail Goods"
        }
    ],
    "sg:phone":"+1 510 644 1898",
    "sg:postcode":"94710",
    "sg:province":"CA",
    "sg:tags":[
        "builder",
        "custom"
    ],
    "sg:website":"www.swerveco.com",
    "wof:name":"Swerve Co",
    "wof:placetype":"venue"
},
  "geometry": {"coordinates":[-122.297102,37.862097],"type":"Point"}
}