{
  "type": "Feature",
  "properties": {
    "addr:full":"7342 Orangethorpe Ave Buena Park CA 90621",
    "addr:housenumber":"7342",
    "addr:postcode":"90621",
    "addr:street":"Orangethorpe Ave",
    "iso:country":"US",
    "sg:address":"7342 Orangethorpe Ave",
    "sg:city":"Buena Park",
    "sg:classifiers":[
        {
            "category":"Communications",
            "subcategory":"Newspaper",
            "type":"Services"
        }
    ],
    "sg:phone":"+1 714 739 1221",
    "sg:postcode":"90621",
    "sg:province":"CA",
    "sg:tags":[
        "print",
        "medium"
    ],
    "wof:name":"Kyocharo USA Inc",
    "wof:placetype":"venue"
},
  "geometry": {"coordinates":[-118.004997,33.859001],"type":"Point"}
}