{
  "type": "Feature",
  "properties": {
    "iso:country":"US",
    "sg:address":"14889 Pine Ave",
    "sg:city":"Fontana",
    "sg:classifiers":[
        {
            "category":"Freight",
            "type":"Transportation"
        }
    ],
    "sg:phone":"+1 909 823 3255",
    "sg:postcode":"92335",
    "sg:province":"CA",
    "sg:tags":[
        "operator",
        "local",
        "trucking"
    ],
    "wof:name":"Jose Trucking",
    "wof:placetype":"venue"
},
  "geometry": {"coordinates":[-117.48229600000001,34.086825],"type":"Point"}
}