{
  "type": "Feature",
  "properties": {
    "addr:full":"1027 60th St Oakland CA 94608",
    "addr:housenumber":"1027",
    "addr:postcode":"94608",
    "addr:street":"60Th St",
    "iso:country":"US",
    "sg:address":"1027 60th St",
    "sg:city":"Oakland",
    "sg:classifiers":[
        {
            "category":"Social Services",
            "subcategory":"Adult Care",
            "type":"Services"
        }
    ],
    "sg:phone":"+1 510 923 0744",
    "sg:postcode":"94608",
    "sg:province":"CA",
    "sg:tags":[
        "organization",
        "senior",
        "citizen"
    ],
    "wof:name":"Roy C Nichols Senior Housing",
    "wof:placetype":"venue"
},
  "geometry": {"coordinates":[-122.278991,37.843628],"type":"Point"}
}