{
  "type": "Feature",
  "properties": {
    "iso:country":"US",
    "sg:address":"22773 Islamare Ln",
    "sg:city":"Lake Forest",
    "sg:classifiers":[
        {
            "category":"Professional",
            "subcategory":"Business Services",
            "type":"Services"
        }
    ],
    "sg:phone":"+1 949 770 5511",
    "sg:postcode":"92630",
    "sg:province":"CA",
    "sg:tags":[
        "design"
    ],
    "wof:name":"Looney Bin The",
    "wof:placetype":"venue"
},
  "geometry": {"coordinates":[-117.703446,33.633175],"type":"Point"}
}