{
  "type": "Feature",
  "properties": {
    "iso:country":"US",
    "sg:address":"1028 W Avenue I",
    "sg:city":"Lancaster",
    "sg:classifiers":[
        {
            "category":"Restaurant",
            "type":"Food & Drink"
        }
    ],
    "sg:menulink":"http://www.allmenus.com/ca/north-antelope-valley/8438-dennys/menu/",
    "sg:phone":"+1 661 948 9630",
    "sg:postcode":"93534",
    "sg:province":"CA",
    "sg:tags":[
        "american",
        "diner"
    ],
    "wof:name":"Denny's",
    "wof:placetype":"venue"
},
  "geometry": {"coordinates":[-118.148565,34.703819],"type":"Point"}
}