{
  "type": "Feature",
  "properties": {
    "addr:full":"914 Lombard Dr Redlands CA 92374",
    "addr:housenumber":"914",
    "addr:postcode":"92374",
    "addr:street":"Lombard Dr",
    "iso:country":"US",
    "sg:address":"914 Lombard Dr",
    "sg:city":"Redlands",
    "sg:classifiers":[
        {
            "category":"Freight",
            "type":"Transportation"
        }
    ],
    "sg:phone":"+1 909 557 6031",
    "sg:postcode":"92374",
    "sg:province":"CA",
    "sg:tags":[
        "operator",
        "local",
        "trucking"
    ],
    "wof:name":"Haro Trucking",
    "wof:placetype":"venue"
},
  "geometry": {"coordinates":[-117.17483900000001,34.062885],"type":"Point"}
}