{
  "type": "Feature",
  "properties": {
    "addr:full":"386 S Burnside Ave Los Angeles CA 90036",
    "addr:housenumber":"386",
    "addr:postcode":"90036",
    "addr:street":"S Burnside Ave",
    "iso:country":"US",
    "sg:address":"386 S Burnside Ave",
    "sg:city":"Los Angeles",
    "sg:classifiers":[
        {
            "category":"Retail",
            "subcategory":"Laundry & Dry Cleaning",
            "type":"Services"
        }
    ],
    "sg:phone":"+1 323 935 7275",
    "sg:postcode":"90036",
    "sg:province":"CA",
    "wof:name":"Park La Brea Cleaners",
    "wof:placetype":"venue"
},
  "geometry": {"coordinates":[-118.351997,34.067101],"type":"Point"}
}