{
  "type": "Feature",
  "properties": {
    "addr:full":"202 N Marina Dr Long Beach CA 90803",
    "addr:housenumber":"202",
    "addr:postcode":"90803",
    "addr:street":"N Marina Dr",
    "iso:country":"US",
    "sg:address":"202 N Marina Dr",
    "sg:city":"Long Beach",
    "sg:classifiers":[
        {
            "category":"Building & Trades",
            "subcategory":"Construction",
            "type":"Services"
        }
    ],
    "sg:phone":"+1 562 431 1338",
    "sg:postcode":"90803",
    "sg:province":"CA",
    "sg:tags":[
        "residential"
    ],
    "wof:name":"Armorcraft Inc",
    "wof:placetype":"venue"
},
  "geometry": {"coordinates":[-118.108957,33.751068],"type":"Point"}
}