{
  "type": "Feature",
  "properties": {
    "iso:country":"US",
    "sg:address":"5120 Ave Encinas",
    "sg:city":"Carlsbad",
    "sg:classifiers":[
        {
            "category":"Banks & Credit Unions",
            "subcategory":"Bank",
            "type":"Services"
        }
    ],
    "sg:phone":"+1 760 804 8820",
    "sg:postcode":"92008",
    "sg:province":"CA",
    "sg:tags":[
        "escrow"
    ],
    "wof:name":"Land America Commonwealth",
    "wof:placetype":"venue"
},
  "geometry": {"coordinates":[-117.329396,33.131671],"type":"Point"}
}