{
  "type": "Feature",
  "properties": {
    "addr:full":"7040 Radford Ave North Hollywood CA 91605",
    "addr:housenumber":"7040",
    "addr:postcode":"91605",
    "addr:street":"Radford Ave",
    "iso:country":"US",
    "sg:address":"7040 Radford Ave",
    "sg:city":"North Hollywood",
    "sg:classifiers":[
        {
            "category":"Wholesale",
            "subcategory":"Non-durable Goods",
            "type":"Manufacturing & Wholesale Goods"
        }
    ],
    "sg:phone":"+1 818 982 8088",
    "sg:postcode":"91605",
    "sg:province":"CA",
    "wof:name":"Tj Trading",
    "wof:placetype":"venue"
},
  "geometry": {"coordinates":[-118.392072,34.199993],"type":"Point"}
}