{
  "type": "Feature",
  "properties": {
    "iso:country":"US",
    "sg:address":"14177 Kentwood Blvd",
    "sg:city":"Victorville",
    "sg:classifiers":[
        {
            "category":"Restaurant",
            "type":"Food & Drink"
        }
    ],
    "sg:phone":"+1 760 241 1960",
    "sg:postcode":"92392",
    "sg:province":"CA",
    "sg:tags":[
        "asian",
        "pan",
        "japanese"
    ],
    "wof:name":"Yoshi Sushi",
    "wof:placetype":"venue"
},
  "geometry": {"coordinates":[-117.32749200000001,34.508245],"type":"Point"}
}