{
  "type": "Feature",
  "properties": {
    "addr:full":"2980 Helen Ct Newbury Park CA 91320",
    "addr:housenumber":"2980",
    "addr:postcode":"91320",
    "addr:street":"Helen Ct",
    "iso:country":"US",
    "sg:address":"2980 Helen Ct",
    "sg:city":"Newbury Park",
    "sg:classifiers":[
        {
            "category":"Building & Trades",
            "subcategory":"Construction",
            "type":"Services"
        }
    ],
    "sg:phone":"+1 805 498 2089",
    "sg:postcode":"91320",
    "sg:province":"CA",
    "sg:tags":[
        "masonry",
        "contractor"
    ],
    "wof:name":"Majesky Masonry",
    "wof:placetype":"venue"
},
  "geometry": {"coordinates":[-118.939319,34.180311],"type":"Point"}
}