{
  "type": "Feature",
  "properties": {
    "iso:country":"US",
    "sg:address":"280 E Lincoln Ave",
    "sg:city":"Anaheim",
    "sg:classifiers":[
        {
            "category":"Education",
            "subcategory":"Dance Studio",
            "type":"Public Place"
        }
    ],
    "sg:phone":"+1 714 520 0904",
    "sg:postcode":"92805",
    "sg:province":"CA",
    "sg:tags":[
        "art",
        "performing",
        "instruction",
        "dancing"
    ],
    "sg:website":"www.anaheimballet.org",
    "wof:name":"Anaheim Ballet",
    "wof:placetype":"venue"
},
  "geometry": {"coordinates":[-117.912003,33.837002],"type":"Point"}
}