{
  "type": "Feature",
  "properties": {
    "addr:full":"4480 Camino De La Plaza San Ysidro CA 92173",
    "addr:housenumber":"4480",
    "addr:postcode":"92173",
    "addr:street":"Camino De La Plaza",
    "iso:country":"US",
    "sg:address":"4480 Camino De La Plaza",
    "sg:city":"San Ysidro",
    "sg:classifiers":[
        {
            "category":"Shopping",
            "subcategory":"Optician",
            "type":"Retail Goods"
        }
    ],
    "sg:phone":"+1 619 690 3792",
    "sg:postcode":"92173",
    "sg:province":"CA",
    "sg:tags":[
        "eyewear"
    ],
    "wof:name":"Sunglass Hut Internatl",
    "wof:placetype":"venue"
},
  "geometry": {"coordinates":[-117.03754600000001,32.544945],"type":"Point"}
}