{
  "type": "Feature",
  "properties": {
    "iso:country":"US",
    "sg:address":"22624 Normandie Ave # A",
    "sg:city":"Torrance",
    "sg:classifiers":[
        {
            "category":"Retail",
            "subcategory":"Auto Repair",
            "type":"Services"
        }
    ],
    "sg:phone":"+1 310 328 6481",
    "sg:postcode":"90502",
    "sg:province":"CA",
    "wof:name":"Best Mechanics",
    "wof:placetype":"venue"
},
  "geometry": {"coordinates":[-118.299004,33.820999],"type":"Point"}
}