{
  "type": "Feature",
  "properties": {
    "addr:full":"22988 Ventura Blvd Woodland Hills CA 91364",
    "addr:housenumber":"22988",
    "addr:postcode":"91364",
    "addr:street":"Ventura Blvd",
    "iso:country":"US",
    "sg:address":"22988 Ventura Blvd",
    "sg:city":"Woodland Hills",
    "sg:classifiers":[
        {
            "category":"Personal",
            "subcategory":"Beauty Salon",
            "type":"Services"
        }
    ],
    "sg:phone":"+1 818 224 4100",
    "sg:postcode":"91364",
    "sg:province":"CA",
    "sg:tags":[
        "hair"
    ],
    "wof:name":"Simas Beauty Salons",
    "wof:placetype":"venue"
},
  "geometry": {"coordinates":[-118.62677100000001,34.164907],"type":"Point"}
}