{
  "type": "Feature",
  "properties": {
    "iso:country":"US",
    "sg:address":"3456 Banyan St",
    "sg:city":"Santa Rosa",
    "sg:classifiers":[
        {
            "category":"Social Services",
            "subcategory":"Child Care",
            "type":"Services"
        }
    ],
    "sg:phone":"+1 707 578 9428",
    "sg:postcode":"95403",
    "sg:province":"CA",
    "wof:name":"Debbie's Day Care",
    "wof:placetype":"venue"
},
  "geometry": {"coordinates":[-122.742266,38.472926],"type":"Point"}
}