{
  "type": "Feature",
  "properties": {
    "iso:country":"US",
    "sg:address":"3333 California St Ste 282",
    "sg:city":"San Francisco",
    "sg:classifiers":[
        {
            "category":"Education",
            "subcategory":"Preschool",
            "type":"Public Place"
        },
        {
            "category":"Education",
            "subcategory":"School",
            "type":"Public Place"
        },
        {
            "category":"Education",
            "subcategory":"University",
            "type":"Public Place"
        }
    ],
    "sg:phone":"+1 415 476 4251",
    "sg:postcode":"94118",
    "sg:province":"CA",
    "sg:tags":[
        "elementary",
        "college"
    ],
    "wof:name":"University of California San Francisco",
    "wof:placetype":"venue"
},
  "geometry": {"coordinates":[-122.448982,37.786812],"type":"Point"}
}