{
  "type": "Feature",
  "properties": {
    "addr:full":"759 59th St Oakland CA 94609",
    "addr:housenumber":"759",
    "addr:postcode":"94609",
    "addr:street":"59Th St",
    "iso:country":"US",
    "sg:address":"759 59th St",
    "sg:city":"Oakland",
    "sg:classifiers":[
        {
            "category":"Personal",
            "type":"Services"
        }
    ],
    "sg:phone":"+1 510 601 0411",
    "sg:postcode":"94609",
    "sg:province":"CA",
    "sg:tags":[
        "assistant"
    ],
    "wof:name":"Susan Camper Personal Trainer",
    "wof:placetype":"venue"
},
  "geometry": {"coordinates":[-122.269547,37.844387],"type":"Point"}
}