{
  "type": "Feature",
  "properties": {
    "addr:full":"922 E Green St Pasadena CA 91106",
    "addr:housenumber":"922",
    "addr:postcode":"91106",
    "addr:street":"E Green St",
    "iso:country":"US",
    "sg:address":"922 E Green St",
    "sg:city":"Pasadena",
    "sg:classifiers":[
        {
            "category":"Real Estate",
            "subcategory":"Real Estate Services",
            "type":"Services"
        },
        {
            "category":"Real Estate",
            "subcategory":"Real Estate Agent",
            "type":"Services"
        }
    ],
    "sg:phone":"+1 818 284 6480",
    "sg:postcode":"91106",
    "sg:province":"CA",
    "sg:tags":[
        "buyer",
        "loan",
        "broker"
    ],
    "sg:website":"http://www.rateonefinancial.com",
    "wof:name":"Rate One Financial",
    "wof:placetype":"venue"
},
  "geometry": {"coordinates":[-118.131332,34.144547],"type":"Point"}
}