{
  "type": "Feature",
  "properties": {
    "addr:full":"1105 Towne Ave Los Angeles CA 90021",
    "addr:housenumber":"1105",
    "addr:postcode":"90021",
    "addr:street":"Towne Ave",
    "iso:country":"US",
    "sg:address":"1105 Towne Ave",
    "sg:city":"Los Angeles",
    "sg:classifiers":[
        {
            "category":"Professional",
            "type":"Services"
        }
    ],
    "sg:phone":"+1 213 741 0006",
    "sg:postcode":"90021",
    "sg:province":"CA",
    "sg:tags":[
        "establishment"
    ],
    "wof:name":"Catwalk LLC",
    "wof:placetype":"venue"
},
  "geometry": {"coordinates":[-118.250086,34.033813],"type":"Point"}
}