{
  "type": "Feature",
  "properties": {
    "addr:full":"4195 E Thousand Oaks Blvd Westlake Village CA 91362",
    "addr:housenumber":"4195",
    "addr:postcode":"91362",
    "addr:street":"E Thousand Oaks Blvd",
    "iso:country":"US",
    "sg:address":"4195 E Thousand Oaks Blvd",
    "sg:city":"Westlake Village",
    "sg:classifiers":[
        {
            "category":"Professional",
            "subcategory":"Lawyer & Legal Services",
            "type":"Services"
        }
    ],
    "sg:phone":"+1 805 379 6711",
    "sg:postcode":"91362",
    "sg:province":"CA",
    "sg:tags":[
        "attorney"
    ],
    "wof:name":"Drury Matisoff & Sale",
    "wof:placetype":"venue"
},
  "geometry": {"coordinates":[-118.82047300000001,34.159728],"type":"Point"}
}