{
  "type": "Feature",
  "properties": {
    "addr:full":"12333 S Manthey Rd Lathrop CA 95330",
    "addr:housenumber":"12333",
    "addr:postcode":"95330",
    "addr:street":"S Manthey Rd",
    "iso:country":"US",
    "sg:address":"12333 S Manthey Rd",
    "sg:city":"Lathrop",
    "sg:classifiers":[
        {
            "category":"Wholesale",
            "subcategory":"Farm Supplies",
            "type":"Manufacturing & Wholesale Goods"
        }
    ],
    "sg:phone":"+1 209 983 8278",
    "sg:postcode":"95330",
    "sg:province":"CA",
    "sg:tags":[
        "straw",
        "hay"
    ],
    "wof:name":"Giglis Hay Company",
    "wof:placetype":"venue"
},
  "geometry": {"coordinates":[-121.28466400000001,37.847065],"type":"Point"}
}