{
  "type": "Feature",
  "properties": {
    "addr:full":"23674 San Vicente Rd Ramona CA 92065",
    "addr:housenumber":"23674",
    "addr:postcode":"92065",
    "addr:street":"San Vicente Rd",
    "iso:country":"US",
    "sg:address":"23674 San Vicente Rd",
    "sg:city":"Ramona",
    "sg:classifiers":[
        {
            "category":"Restaurant",
            "type":"Food & Drink"
        }
    ],
    "sg:phone":"+1 760 789 5086",
    "sg:postcode":"92065",
    "sg:province":"CA",
    "wof:name":"Los Amigos Mexican Food",
    "wof:placetype":"venue"
},
  "geometry": {"coordinates":[-116.818966,33.005649],"type":"Point"}
}