{
  "type": "Feature",
  "properties": {
    "addr:full":"567 San Pablo Ave Albany CA 94706",
    "addr:housenumber":"567",
    "addr:postcode":"94706",
    "addr:street":"San Pablo Ave",
    "iso:country":"US",
    "sg:address":"567 San Pablo Ave",
    "sg:city":"Albany",
    "sg:classifiers":[
        {
            "category":"Professional",
            "type":"Services"
        }
    ],
    "sg:phone":"+1 510 524 4091",
    "sg:postcode":"94706",
    "sg:province":"CA",
    "wof:name":"Gardizi Gallery",
    "wof:placetype":"venue"
},
  "geometry": {"coordinates":[-122.300663,37.895577],"type":"Point"}
}