{
  "type": "Feature",
  "properties": {
    "addr:full":"717 Berryessa St Milpitas CA 95035",
    "addr:housenumber":"717",
    "addr:postcode":"95035",
    "addr:street":"Berryessa St",
    "iso:country":"US",
    "sg:address":"717 Berryessa St",
    "sg:city":"Milpitas",
    "sg:classifiers":[
        {
            "category":"Banks & Credit Unions",
            "subcategory":"Bank",
            "type":"Services"
        }
    ],
    "sg:phone":"+1 408 586 8129",
    "sg:postcode":"95035",
    "sg:province":"CA",
    "sg:tags":[
        "loan",
        "broker"
    ],
    "wof:name":"First Choice Brokers",
    "wof:placetype":"venue"
},
  "geometry": {"coordinates":[-121.909026,37.43919],"type":"Point"}
}