{
  "type": "Feature",
  "properties": {
    "iso:country":"US",
    "sg:address":"2562 Pine St",
    "sg:city":"San Francisco",
    "sg:classifiers":[
        {
            "category":"Manufacturing",
            "subcategory":"Electronics",
            "type":"Manufacturing & Wholesale Goods"
        }
    ],
    "sg:phone":"+1 415 931 8455",
    "sg:postcode":"94115",
    "sg:province":"CA",
    "sg:tags":[
        "devices",
        "mfg"
    ],
    "wof:name":"Sil-Pac",
    "wof:placetype":"venue"
},
  "geometry": {"coordinates":[-122.43777,37.78753],"type":"Point"}
}