{
  "type": "Feature",
  "properties": {
    "iso:country":"US",
    "sg:address":"8444 Crenshaw Boulevard",
    "sg:city":"Inglewood",
    "sg:classifiers":[
        {
            "category":"Health Services",
            "subcategory":"Chiropractor",
            "type":"Services"
        }
    ],
    "sg:phone":"+1 323 753 2488",
    "sg:postcode":"90305",
    "sg:province":"CA",
    "wof:name":"Martin Scott W DC Chirprctr",
    "wof:placetype":"venue"
},
  "geometry": {"coordinates":[-118.327162,33.961943],"type":"Point"}
}