{
  "type": "Feature",
  "properties": {
    "iso:country":"US",
    "sg:address":"17404 Ventura Blvd",
    "sg:city":"Encino",
    "sg:classifiers":[
        {
            "category":"Manufacturing",
            "subcategory":"Printing",
            "type":"Manufacturing & Wholesale Goods"
        }
    ],
    "sg:phone":"+1 818 783 8485",
    "sg:postcode":"91316",
    "sg:province":"CA",
    "sg:tags":[
        "publisher",
        "music"
    ],
    "sg:website":"www.weddingmusiccentral.com",
    "wof:name":"Musiconcepts",
    "wof:placetype":"venue"
},
  "geometry": {"coordinates":[-118.514095,34.161405],"type":"Point"}
}