{
  "type": "Feature",
  "properties": {
    "iso:country":"US",
    "sg:address":"1253 Dell Avenue",
    "sg:city":"Campbell",
    "sg:classifiers":[
        {
            "category":"Building & Trades",
            "subcategory":"Construction",
            "type":"Services"
        }
    ],
    "sg:phone":"+1 408 871 9830",
    "sg:postcode":"95008",
    "sg:province":"CA",
    "sg:tags":[
        "contractor"
    ],
    "wof:name":"Design Build Systems",
    "wof:placetype":"venue"
},
  "geometry": {"coordinates":[-121.952685,37.268981],"type":"Point"}
}