{
  "type": "Feature",
  "properties": {
    "addr:full":"775 Seaport Blvd Redwood City CA 94063",
    "addr:housenumber":"775",
    "addr:postcode":"94063",
    "addr:street":"Seaport Blvd",
    "iso:country":"US",
    "sg:address":"775 Seaport Blvd",
    "sg:city":"Redwood City",
    "sg:classifiers":[
        {
            "category":"Freight",
            "type":"Transportation"
        }
    ],
    "sg:phone":"+1 650 556 9912",
    "sg:postcode":"94063",
    "sg:province":"CA",
    "sg:tags":[
        "cargo",
        "handler",
        "marine"
    ],
    "wof:name":"Metropolitan Stevedore",
    "wof:placetype":"venue"
},
  "geometry": {"coordinates":[-122.209594,37.506106],"type":"Point"}
}