{
  "type": "Feature",
  "properties": {
    "iso:country":"US",
    "sg:address":"688 N Arrowhead Ave",
    "sg:city":"San Bernardino",
    "sg:classifiers":[
        {
            "category":"Banks & Credit Unions",
            "subcategory":"Bank",
            "type":"Services"
        }
    ],
    "sg:phone":"+1 909 383 7775",
    "sg:postcode":"92401",
    "sg:province":"CA",
    "sg:tags":[
        "loan",
        "real estate"
    ],
    "wof:name":"Mortgage One Financial",
    "wof:placetype":"venue"
},
  "geometry": {"coordinates":[-117.289754,34.110391],"type":"Point"}
}