{
  "type": "Feature",
  "properties": {
    "iso:country":"US",
    "sg:address":"169 W Brannan Island Rd",
    "sg:city":"Isleton",
    "sg:classifiers":[
        {
            "category":"Restaurant",
            "type":"Food & Drink"
        }
    ],
    "sg:phone":"+1 916 777 7797",
    "sg:postcode":"95641",
    "sg:province":"CA",
    "wof:name":"Shoals Cafe",
    "wof:placetype":"venue"
},
  "geometry": {"coordinates":[-121.593231,38.104896],"type":"Point"}
}