{
  "type": "Feature",
  "properties": {
    "iso:country":"US",
    "sg:address":"940 N Citrus Ave",
    "sg:city":"Covina",
    "sg:classifiers":[
        {
            "category":"Restaurant",
            "type":"Food & Drink"
        }
    ],
    "sg:phone":"+1 626 966 8750",
    "sg:postcode":"91722",
    "sg:province":"CA",
    "wof:name":"J R's Italian Pizza & Sports",
    "wof:placetype":"venue"
},
  "geometry": {"coordinates":[-117.890121,34.096553],"type":"Point"}
}