{
  "type": "Feature",
  "properties": {
    "iso:country":"US",
    "sg:address":"3657 Christensen Ln",
    "sg:city":"Castro Valley",
    "sg:classifiers":[
        {
            "category":"Education",
            "subcategory":"Preschool",
            "type":"Public Place"
        },
        {
            "category":"Education",
            "subcategory":"School",
            "type":"Public Place"
        }
    ],
    "sg:phone":"+1 510 582 7731",
    "sg:postcode":"94546",
    "sg:province":"CA",
    "sg:tags":[
        "elementary"
    ],
    "wof:name":"Castro Valley Parent Nursery School",
    "wof:placetype":"venue"
},
  "geometry": {"coordinates":[-122.084999,37.7066],"type":"Point"}
}