{
  "type": "Feature",
  "properties": {
    "addr:full":"5840 Traffic Way Atascadero CA 93422",
    "addr:housenumber":"5840",
    "addr:postcode":"93422",
    "addr:street":"Traffic Way",
    "iso:country":"US",
    "sg:address":"5840 Traffic Way",
    "sg:city":"Atascadero",
    "sg:classifiers":[
        {
            "category":"Personal",
            "subcategory":"Beauty Salon",
            "type":"Services"
        }
    ],
    "sg:phone":"+1 805 460 9493",
    "sg:postcode":"93422",
    "sg:province":"CA",
    "wof:name":"Accommodating You Hair & Nail Boutique",
    "wof:placetype":"venue"
},
  "geometry": {"coordinates":[-120.66973299999999,35.490384],"type":"Point"}
}