{
  "type": "Feature",
  "properties": {
    "addr:full":"3316 W 73rd Street Los Angeles CA 90043",
    "addr:housenumber":"3316",
    "addr:postcode":"90043",
    "addr:street":"W 73Rd Street",
    "iso:country":"US",
    "sg:address":"3316 W 73rd Street",
    "sg:city":"Los Angeles",
    "sg:classifiers":[
        {
            "category":"Real Estate",
            "subcategory":"Real Estate Operator",
            "type":"Services"
        }
    ],
    "sg:phone":"+1 323 759 9552",
    "sg:postcode":"90043",
    "sg:province":"CA",
    "sg:tags":[
        "apartment"
    ],
    "wof:name":"Crenshaw Terrace Apartments",
    "wof:placetype":"venue"
},
  "geometry": {"coordinates":[-118.32995099999999,33.973623],"type":"Point"}
}