{
  "type": "Feature",
  "properties": {
    "iso:country":"US",
    "sg:address":"4100 Irving Pl",
    "sg:city":"Culver City",
    "sg:classifiers":[
        {
            "category":"Government",
            "subcategory":"Office",
            "type":"Public Place"
        }
    ],
    "sg:phone":"+1 310 253 6650",
    "sg:postcode":"90232",
    "sg:province":"CA",
    "sg:tags":[
        "village"
    ],
    "wof:name":"Linwood E Howe Schl Playground",
    "wof:placetype":"venue"
},
  "geometry": {"coordinates":[-118.393742,34.022373],"type":"Point"}
}