{
  "type": "Feature",
  "properties": {
    "addr:full":"3021 Dana Street Berkeley CA 94705",
    "addr:housenumber":"3021",
    "addr:postcode":"94705",
    "addr:street":"Dana Street",
    "iso:country":"US",
    "sg:address":"3021 Dana Street",
    "sg:city":"Berkeley",
    "sg:classifiers":[
        {
            "category":"Health Services",
            "subcategory":"Doctor",
            "type":"Services"
        }
    ],
    "sg:phone":"+1 510 845 2422",
    "sg:postcode":"94705",
    "sg:province":"CA",
    "sg:tags":[
        "practice",
        "family"
    ],
    "wof:name":"Anderson Arlyss RN-C Fnp",
    "wof:placetype":"venue"
},
  "geometry": {"coordinates":[-122.258003,37.8545],"type":"Point"}
}