{
  "type": "Feature",
  "properties": {
    "iso:country":"US",
    "sg:address":"4100 Welltech Way",
    "sg:city":"Bakersfield",
    "sg:classifiers":[
        {
            "category":"Wholesale",
            "subcategory":"Electrical",
            "type":"Manufacturing & Wholesale Goods"
        }
    ],
    "sg:phone":"+1 661 589 4979",
    "sg:postcode":"93308",
    "sg:province":"CA",
    "sg:tags":[
        "meter"
    ],
    "wof:name":"Century Calibrating",
    "wof:placetype":"venue"
},
  "geometry": {"coordinates":[-119.07581999999999,35.397461],"type":"Point"}
}