{
  "type": "Feature",
  "properties": {
    "iso:country":"US",
    "sg:address":"7358 Turnford Dr",
    "sg:city":"San Diego",
    "sg:classifiers":[
        {
            "category":"Building & Trades",
            "subcategory":"Landscaping Services",
            "type":"Services"
        }
    ],
    "sg:phone":"+1 619 466 8008",
    "sg:postcode":"92119",
    "sg:province":"CA",
    "sg:tags":[
        "designer",
        "landscape"
    ],
    "wof:name":"Meadowbrook Landscape Co",
    "wof:placetype":"venue"
},
  "geometry": {"coordinates":[-117.01382599999999,32.814232],"type":"Point"}
}