{
  "type": "Feature",
  "properties": {
    "iso:country":"US",
    "sg:address":"3350 Fulton Rd",
    "sg:city":"Fulton",
    "sg:classifiers":[
        {
            "category":"Professional",
            "type":"Services"
        }
    ],
    "sg:phone":"+1 707 541 0153",
    "sg:postcode":"95439",
    "sg:province":"CA",
    "wof:name":"Pines Jeff",
    "wof:placetype":"venue"
},
  "geometry": {"coordinates":[-122.769982,38.495463],"type":"Point"}
}