{
  "type": "Feature",
  "properties": {
    "iso:country":"US",
    "sg:address":"1542 Highland Avenue",
    "sg:city":"National City",
    "sg:classifiers":[
        {
            "category":"Shopping",
            "subcategory":"Gifts & Souvenirs",
            "type":"Retail Goods"
        }
    ],
    "sg:phone":"+1 619 292 3111",
    "sg:postcode":"91950",
    "sg:province":"CA",
    "sg:tags":[
        "flower"
    ],
    "sg:website":"www.angelpetalsonline.com",
    "wof:name":"Angel Petals Flower Shop",
    "wof:placetype":"venue"
},
  "geometry": {"coordinates":[-117.09618,32.671421],"type":"Point"}
}