{
  "type": "Feature",
  "properties": {
    "addr:full":"14958 N Thornton Rd Lodi CA 95242",
    "addr:housenumber":"14958",
    "addr:postcode":"95242",
    "addr:street":"N Thornton Rd",
    "iso:country":"US",
    "sg:address":"14958 N Thornton Rd",
    "sg:city":"Lodi",
    "sg:classifiers":[
        {
            "category":"Restaurant",
            "type":"Food & Drink"
        }
    ],
    "sg:phone":"+1 209 366 2884",
    "sg:postcode":"95242",
    "sg:province":"CA",
    "wof:name":"Subway Sandwiches & Salads",
    "wof:placetype":"venue"
},
  "geometry": {"coordinates":[-121.39443799999999,38.113898],"type":"Point"}
}