{
  "type": "Feature",
  "properties": {
    "iso:country":"US",
    "sg:address":"548 S Kingsley Dr",
    "sg:city":"Los Angeles",
    "sg:classifiers":[
        {
            "category":"Organizations",
            "subcategory":"Religious Organization",
            "type":"Services"
        }
    ],
    "sg:phone":"+1 213 386 9191",
    "sg:postcode":"90020",
    "sg:province":"CA",
    "sg:tags":[
        "church"
    ],
    "wof:name":"L A Open Blessing Church",
    "wof:placetype":"venue"
},
  "geometry": {"coordinates":[-118.30277700000001,34.064441],"type":"Point"}
}