{
  "type": "Feature",
  "properties": {
    "iso:country":"US",
    "sg:address":"11527 Washington Blvd",
    "sg:city":"Whittier",
    "sg:classifiers":[
        {
            "category":"Shopping",
            "subcategory":"Books",
            "type":"Retail Goods"
        }
    ],
    "sg:phone":"+1 310 915 7188",
    "sg:postcode":"90606",
    "sg:province":"CA",
    "sg:tags":[
        "dealer"
    ],
    "wof:name":"Vagabond Books",
    "wof:placetype":"venue"
},
  "geometry": {"coordinates":[-118.065093,33.970547],"type":"Point"}
}