{
  "type": "Feature",
  "properties": {
    "iso:country":"US",
    "sg:address":"218 Carmen Ln",
    "sg:city":"Santa Maria",
    "sg:classifiers":[
        {
            "category":"Insurance",
            "subcategory":"Insurance Agent",
            "type":"Services"
        }
    ],
    "sg:phone":"+1 805 348 3121",
    "sg:postcode":"93458",
    "sg:province":"CA",
    "wof:name":"Barkley Insurance Agents",
    "wof:placetype":"venue"
},
  "geometry": {"coordinates":[-120.43669,34.924739],"type":"Point"}
}