{
  "type": "Feature",
  "properties": {
    "iso:country":"US",
    "sg:address":"2768 W Cardella Rd",
    "sg:city":"Merced",
    "sg:phone":"+1 209 383 2768",
    "sg:postcode":"95348",
    "sg:province":"CA",
    "sg:tags":[
        "farm"
    ],
    "wof:name":"Cardella Farms",
    "wof:placetype":"venue"
},
  "geometry": {"coordinates":[-120.53954400000001,37.3463],"type":"Point"}
}