{
  "type": "Feature",
  "properties": {
    "addr:full":"1704 Springs Rd # B Vallejo CA 94591",
    "addr:housenumber":"1704",
    "addr:postcode":"94591",
    "addr:street":"Springs Rd # B",
    "iso:country":"US",
    "sg:address":"1704 Springs Rd # B",
    "sg:city":"Vallejo",
    "sg:classifiers":[
        {
            "category":"Real Estate",
            "subcategory":"Real Estate Services",
            "type":"Services"
        },
        {
            "category":"Real Estate",
            "subcategory":"Real Estate Agent",
            "type":"Services"
        }
    ],
    "sg:phone":"+1 707 557 7328",
    "sg:postcode":"94591",
    "sg:province":"CA",
    "sg:tags":[
        "buyer",
        "broker"
    ],
    "wof:name":"Chandra Realty",
    "wof:placetype":"venue"
},
  "geometry": {"coordinates":[-122.223636,38.10606],"type":"Point"}
}