{
  "type": "Feature",
  "properties": {
    "addr:full":"1312 Kansas Ave Modesto CA 95351",
    "addr:housenumber":"1312",
    "addr:postcode":"ca 95351",
    "addr:street":"Kansas Ave",
    "iso:country":"US",
    "sg:address":"1312 Kansas Ave",
    "sg:city":"Modesto",
    "sg:classifiers":[
        {
            "category":"Retail",
            "subcategory":"Auto Repair",
            "type":"Services"
        }
    ],
    "sg:phone":"+1 209 492 9579",
    "sg:postcode":"95351",
    "sg:province":"CA",
    "sg:tags":[
        "glass",
        "coating",
        "tinting"
    ],
    "wof:name":"Shadz",
    "wof:placetype":"venue"
},
  "geometry": {"coordinates":[-121.024492,37.645919],"type":"Point"}
}