{
  "type": "Feature",
  "properties": {
    "iso:country":"US",
    "sg:address":"1301 Armstrong Rd",
    "sg:city":"Lodi",
    "sg:classifiers":[
        {
            "category":"Wholesale",
            "subcategory":"Metals & Minerals",
            "type":"Manufacturing & Wholesale Goods"
        }
    ],
    "sg:phone":"+1 707 933 0158",
    "sg:postcode":"95242",
    "sg:province":"CA",
    "sg:tags":[
        "pipe"
    ],
    "wof:name":"North Coast Irrigation",
    "wof:placetype":"venue"
},
  "geometry": {"coordinates":[-121.310481,38.086518],"type":"Point"}
}