{
  "type": "Feature",
  "properties": {
    "addr:full":"1152 Holly St San Carlos CA 94070",
    "addr:housenumber":"1152",
    "addr:postcode":"94070",
    "addr:street":"Holly St",
    "iso:country":"US",
    "sg:address":"1152 Holly St",
    "sg:city":"San Carlos",
    "sg:classifiers":[
        {
            "category":"Shopping",
            "subcategory":"Clothing, Apparel, & Fashions",
            "type":"Retail Goods"
        }
    ],
    "sg:phone":"+1 650 595 4056",
    "sg:postcode":"94070",
    "sg:province":"CA",
    "sg:tags":[
        "tailor"
    ],
    "wof:name":"Holly Cleaners & Alterations",
    "wof:placetype":"venue"
},
  "geometry": {"coordinates":[-122.262702,37.508023],"type":"Point"}
}