{
  "type": "Feature",
  "properties": {
    "addr:full":"1104 S Main St Los Angeles CA 90015",
    "addr:housenumber":"1104",
    "addr:postcode":"90015",
    "addr:street":"S Main St",
    "iso:country":"US",
    "sg:address":"1104 S Main St",
    "sg:city":"Los Angeles",
    "sg:classifiers":[
        {
            "category":"Wholesale",
            "subcategory":"Machinery & Supplies",
            "type":"Manufacturing & Wholesale Goods"
        }
    ],
    "sg:phone":"+1 213 748 6057",
    "sg:postcode":"90015",
    "sg:province":"CA",
    "sg:tags":[
        "equipment",
        "salon",
        "beauty"
    ],
    "wof:name":"Starus Trading Corp",
    "wof:placetype":"venue"
},
  "geometry": {"coordinates":[-118.259247,34.037608],"type":"Point"}
}