{
  "type": "Feature",
  "properties": {
    "addr:full":"1918 Camden Avenue San Jose CA 95124",
    "addr:housenumber":"1918",
    "addr:postcode":"95124",
    "addr:street":"Camden Avenue",
    "iso:country":"US",
    "sg:address":"1918 Camden Avenue",
    "sg:city":"San Jose",
    "sg:classifiers":[
        {
            "category":"Sports & Exercise",
            "subcategory":"Gym",
            "type":"Entertainment"
        }
    ],
    "sg:phone":"+1 408 559 9567",
    "sg:postcode":"95124",
    "sg:province":"CA",
    "sg:tags":[
        "trainer"
    ],
    "wof:name":"Max Wellness Personal Fitness Training",
    "wof:placetype":"venue"
},
  "geometry": {"coordinates":[-121.924775,37.261763],"type":"Point"}
}