{
  "type": "Feature",
  "properties": {
    "addr:full":"2300 Stockton Blvd Sacramento CA 95817",
    "addr:housenumber":"2300",
    "addr:postcode":"95817",
    "addr:street":"Stockton Blvd",
    "iso:country":"US",
    "sg:address":"2300 Stockton Blvd",
    "sg:city":"Sacramento",
    "sg:classifiers":[
        {
            "category":"Banks & Credit Unions",
            "subcategory":"Financial Services",
            "type":"Services"
        }
    ],
    "sg:phone":"+1 916 685 9376",
    "sg:postcode":"95817",
    "sg:province":"CA",
    "sg:tags":[
        "educational",
        "plan",
        "scholarship"
    ],
    "wof:name":"California Student Scholarship",
    "wof:placetype":"venue"
},
  "geometry": {"coordinates":[-121.457097,38.55393],"type":"Point"}
}