{
  "type": "Feature",
  "properties": {
    "iso:country":"US",
    "sg:address":"278 E Alexander Ave",
    "sg:city":"San Bernardino",
    "sg:classifiers":[
        {
            "category":"Retail",
            "subcategory":"Repair Shop",
            "type":"Services"
        }
    ],
    "sg:phone":"+1 909 886 3844",
    "sg:postcode":"92404",
    "sg:province":"CA",
    "sg:tags":[
        "door"
    ],
    "wof:name":"Lock-N-Door Mann",
    "wof:placetype":"venue"
},
  "geometry": {"coordinates":[-117.279923,34.141561],"type":"Point"}
}