{
  "type": "Feature",
  "properties": {
    "addr:full":"6192 Apache Rd Westminster CA 92683",
    "addr:housenumber":"6192",
    "addr:postcode":"92683",
    "addr:street":"Apache Rd",
    "iso:country":"US",
    "sg:address":"6192 Apache Rd",
    "sg:city":"Westminster",
    "sg:classifiers":[
        {
            "category":"Freight",
            "type":"Transportation"
        }
    ],
    "sg:phone":"+1 714 897 0092",
    "sg:postcode":"92683",
    "sg:province":"CA",
    "sg:tags":[
        "operator",
        "local",
        "trucking"
    ],
    "wof:name":"Vince Owen Trucking",
    "wof:placetype":"venue"
},
  "geometry": {"coordinates":[-118.020747,33.772626],"type":"Point"}
}