{
  "type": "Feature",
  "properties": {
    "iso:country":"US",
    "sg:address":"319 E 2nd St Ste 206",
    "sg:city":"Los Angeles",
    "sg:classifiers":[
        {
            "category":"Restaurant",
            "type":"Food & Drink"
        }
    ],
    "sg:phone":"+1 213 687 7780",
    "sg:postcode":"90012",
    "sg:province":"CA",
    "sg:tags":[
        "sushi",
        "bar"
    ],
    "sg:website":"www.zencu.com/",
    "wof:name":"Zencu Sushi & Grill",
    "wof:placetype":"venue"
},
  "geometry": {"coordinates":[-118.24121599999999,34.048958],"type":"Point"}
}