{
  "type": "Feature",
  "properties": {
    "iso:country":"US",
    "sg:address":"524 S Main St",
    "sg:city":"Los Angeles",
    "sg:classifiers":[
        {
            "category":"Food & Beverages",
            "subcategory":"Bakery",
            "type":"Retail Goods"
        }
    ],
    "sg:phone":"+1 213 683 9757",
    "sg:postcode":"90013",
    "sg:province":"CA",
    "sg:tags":[
        "baker"
    ],
    "wof:name":"National Bakery",
    "wof:placetype":"venue"
},
  "geometry": {"coordinates":[-118.249573,34.045562],"type":"Point"}
}