{
  "type": "Feature",
  "properties": {
    "iso:country":"US",
    "sg:address":"1441 E 16th St",
    "sg:city":"Los Angeles",
    "sg:classifiers":[
        {
            "category":"Shopping",
            "subcategory":"Clothing, Apparel, & Fashions",
            "type":"Retail Goods"
        }
    ],
    "sg:phone":"+1 213 435 4575",
    "sg:postcode":"90021",
    "sg:province":"CA",
    "sg:tags":[
        "clothing",
        "women's"
    ],
    "wof:name":"Off Price USA - Discounted Women's Plus Size Clothing",
    "wof:placetype":"venue"
},
  "geometry": {"coordinates":[-118.245542,34.024774],"type":"Point"}
}