{
  "type": "Feature",
  "properties": {
    "addr:full":"6009 Jurupa Ave Riverside CA 92504",
    "addr:housenumber":"6009",
    "addr:postcode":"92504",
    "addr:street":"Jurupa Ave",
    "iso:country":"US",
    "sg:address":"6009 Jurupa Ave",
    "sg:city":"Riverside",
    "sg:classifiers":[
        {
            "category":"Shopping",
            "subcategory":"Clothing, Apparel, & Fashions",
            "type":"Retail Goods"
        }
    ],
    "sg:phone":"+1 951 351 1193",
    "sg:postcode":"92504",
    "sg:province":"CA",
    "sg:tags":[
        "navy",
        "salvage",
        "surplus",
        "merchandise",
        "army"
    ],
    "wof:name":"J & T Military Surplus",
    "wof:placetype":"venue"
},
  "geometry": {"coordinates":[-117.434099,33.962978],"type":"Point"}
}