{
  "type": "Feature",
  "properties": {
    "addr:full":"101 Utah St San Francisco CA 94103",
    "addr:housenumber":"101",
    "addr:postcode":"94103",
    "addr:street":"Utah St",
    "iso:country":"US",
    "sg:address":"101 Utah St",
    "sg:city":"San Francisco",
    "sg:classifiers":[
        {
            "category":"Wholesale",
            "subcategory":"Jewelry",
            "type":"Manufacturing & Wholesale Goods"
        }
    ],
    "sg:phone":"+1 415 626 8288",
    "sg:postcode":"94103",
    "sg:province":"CA",
    "sg:tags":[
        "diamond"
    ],
    "wof:name":"Steve Padis Jewelry Plus Ents",
    "wof:placetype":"venue"
},
  "geometry": {"coordinates":[-122.406677,37.767142],"type":"Point"}
}