{
  "type": "Feature",
  "properties": {
    "addr:full":"1888 A St Antioch CA 94509",
    "addr:housenumber":"1888",
    "addr:postcode":"ca 94509",
    "addr:street":"A St",
    "iso:country":"US",
    "sg:address":"1888 A St",
    "sg:city":"Antioch",
    "sg:classifiers":[
        {
            "category":"Bars & Pubs",
            "type":"Food & Drink"
        }
    ],
    "sg:phone":"+1 925 753 5760",
    "sg:postcode":"94509",
    "sg:province":"CA",
    "sg:tags":[
        "lounge",
        "cocktail"
    ],
    "wof:name":"Cheers",
    "wof:placetype":"venue"
},
  "geometry": {"coordinates":[-121.80607999999999,38.004377],"type":"Point"}
}