{
  "type": "Feature",
  "properties": {
    "addr:full":"13400 Cherokee Ln Galt CA 95632",
    "addr:housenumber":"13400",
    "addr:postcode":"95632",
    "addr:street":"Cherokee Ln",
    "iso:country":"US",
    "sg:address":"13400 Cherokee Ln",
    "sg:city":"Galt",
    "sg:classifiers":[
        {
            "category":"Farming",
            "subcategory":"Livestock Farm",
            "type":"Manufacturing & Wholesale Goods"
        }
    ],
    "sg:phone":"+1 209 745 1942",
    "sg:postcode":"95632",
    "sg:province":"CA",
    "sg:tags":[
        "ranch"
    ],
    "wof:name":"Martin Ronayne",
    "wof:placetype":"venue"
},
  "geometry": {"coordinates":[-121.264089,38.269906],"type":"Point"}
}