{
  "type": "Feature",
  "properties": {
    "addr:full":"66 Hartnell Ave Redding CA 96002",
    "addr:housenumber":"66",
    "addr:postcode":"96002",
    "addr:street":"Hartnell Ave",
    "iso:country":"US",
    "sg:address":"66 Hartnell Ave",
    "sg:city":"Redding",
    "sg:classifiers":[
        {
            "category":"Restaurant",
            "type":"Food & Drink"
        }
    ],
    "sg:phone":"+1 530 222 6668",
    "sg:postcode":"96002",
    "sg:province":"CA",
    "wof:name":"Jimboy's Tacos",
    "wof:placetype":"venue"
},
  "geometry": {"coordinates":[-122.369197,40.568934],"type":"Point"}
}