{
  "type": "Feature",
  "properties": {
    "iso:country":"US",
    "sg:address":"10202 Washington Blvd",
    "sg:city":"Culver City",
    "sg:classifiers":[
        {
            "category":"Professional",
            "type":"Services"
        }
    ],
    "sg:phone":"+1 310 244 8080",
    "sg:postcode":"90232",
    "sg:province":"CA",
    "sg:tags":[
        "establishment"
    ],
    "wof:name":"Fountainbridge Films",
    "wof:placetype":"venue"
},
  "geometry": {"coordinates":[-118.401135,34.01941],"type":"Point"}
}