{
  "type": "Feature",
  "properties": {
    "addr:full":"1304 Dorothy Dr Glendale CA 91202",
    "addr:housenumber":"1304",
    "addr:postcode":"91202",
    "addr:street":"Dorothy Dr",
    "iso:country":"US",
    "sg:address":"1304 Dorothy Dr",
    "sg:city":"Glendale",
    "sg:classifiers":[
        {
            "category":"Home & Garden",
            "subcategory":"Building Materials",
            "type":"Retail Goods"
        },
        {
            "category":"Manufacturing",
            "subcategory":"Building Materials",
            "type":"Manufacturing & Wholesale Goods"
        }
    ],
    "sg:phone":"+1 323 843 5082",
    "sg:postcode":"91202",
    "sg:province":"CA",
    "sg:tags":[
        "frames",
        "window",
        "doors",
        "accessory"
    ],
    "wof:name":"A 1 Garage Doors And Gates",
    "wof:placetype":"venue"
},
  "geometry": {"coordinates":[-118.263851,34.165225],"type":"Point"}
}