{
  "type": "Feature",
  "properties": {
    "addr:full":"7848 Sepulveda Blvd Van Nuys CA 91405",
    "addr:housenumber":"7848",
    "addr:postcode":"91405",
    "addr:street":"Sepulveda Blvd",
    "iso:country":"US",
    "sg:address":"7848 Sepulveda Blvd",
    "sg:city":"Van Nuys",
    "sg:classifiers":[
        {
            "category":"Retail",
            "subcategory":"Auto Repair",
            "type":"Services"
        }
    ],
    "sg:phone":"+1 818 994 3353",
    "sg:postcode":"91405",
    "sg:province":"CA",
    "sg:tags":[
        "body",
        "automobile",
        "painting"
    ],
    "wof:name":"Super Auto Body",
    "wof:placetype":"venue"
},
  "geometry": {"coordinates":[-118.466128,34.212285],"type":"Point"}
}