{
  "type": "Feature",
  "properties": {
    "iso:country":"US",
    "sg:address":"350 Lorton Ave",
    "sg:city":"Burlingame",
    "sg:classifiers":[
        {
            "category":"Home & Garden",
            "subcategory":"Carpets & Floor Coverings",
            "type":"Retail Goods"
        }
    ],
    "sg:phone":"+1 650 344 5074",
    "sg:postcode":"94010",
    "sg:province":"CA",
    "sg:tags":[
        "dealer",
        "rug"
    ],
    "wof:name":"Black Sea Gallery",
    "wof:placetype":"venue"
},
  "geometry": {"coordinates":[-122.346998,37.580117],"type":"Point"}
}