{
  "type": "Feature",
  "properties": {
    "addr:full":"27714 Turnberry Mission Viejo CA 92692",
    "addr:housenumber":"27714",
    "addr:postcode":"92692",
    "addr:street":"Turnberry",
    "iso:country":"US",
    "sg:address":"27714 Turnberry",
    "sg:city":"Mission Viejo",
    "sg:classifiers":[
        {
            "category":"Shopping",
            "subcategory":"Clothing, Apparel, & Fashions",
            "type":"Retail Goods"
        }
    ],
    "sg:phone":"+1 949 262 1973",
    "sg:postcode":"92692",
    "sg:province":"CA",
    "wof:name":"Designer Details",
    "wof:placetype":"venue"
},
  "geometry": {"coordinates":[-117.646837,33.620639],"type":"Point"}
}