{
  "type": "Feature",
  "properties": {
    "addr:full":"113 Ave la Cuesta San Clemente CA 92672",
    "addr:housenumber":"113",
    "addr:postcode":"92672",
    "addr:street":"Ave",
    "iso:country":"US",
    "sg:address":"113 Ave la Cuesta",
    "sg:city":"San Clemente",
    "sg:classifiers":[
        {
            "category":"Building & Trades",
            "subcategory":"Electrical",
            "type":"Services"
        }
    ],
    "sg:phone":"+1 949 361 4877",
    "sg:postcode":"92672",
    "sg:province":"CA",
    "sg:tags":[
        "electrical",
        "contractor"
    ],
    "wof:name":"Two Bright Electric",
    "wof:placetype":"venue"
},
  "geometry": {"coordinates":[-117.61524900000001,33.4338],"type":"Point"}
}