{
  "type": "Feature",
  "properties": {
    "iso:country":"US",
    "sg:address":"570 Central Ave",
    "sg:city":"Lake Elsinore",
    "sg:classifiers":[
        {
            "category":"Professional",
            "subcategory":"Engineering",
            "type":"Services"
        }
    ],
    "sg:phone":"+1 951 245 2578",
    "sg:postcode":"92530",
    "sg:province":"CA",
    "sg:tags":[
        "engineer"
    ],
    "wof:name":"Lamda Engineering",
    "wof:placetype":"venue"
},
  "geometry": {"coordinates":[-117.340429,33.689386],"type":"Point"}
}