{
  "type": "Feature",
  "properties": {
    "addr:full":"4511 Logan Ave San Diego CA 92113",
    "addr:housenumber":"4511",
    "addr:postcode":"92113",
    "addr:street":"Logan Ave",
    "iso:country":"US",
    "sg:address":"4511 Logan Ave",
    "sg:city":"San Diego",
    "sg:classifiers":[
        {
            "category":"Manufacturing",
            "subcategory":"Printing",
            "type":"Manufacturing & Wholesale Goods"
        }
    ],
    "sg:phone":"+1 619 527 0344",
    "sg:postcode":"92113",
    "sg:province":"CA",
    "sg:tags":[
        "periodical"
    ],
    "wof:name":"Passport Magazine",
    "wof:placetype":"venue"
},
  "geometry": {"coordinates":[-117.097702,32.696743],"type":"Point"}
}