{
  "type": "Feature",
  "properties": {
    "iso:country":"US",
    "sg:address":"1996 Frankfort St",
    "sg:city":"San Diego",
    "sg:classifiers":[
        {
            "category":"Professional",
            "subcategory":"Research",
            "type":"Services"
        }
    ],
    "sg:phone":"+1 619 276 5335",
    "sg:postcode":"92110",
    "sg:province":"CA",
    "sg:tags":[
        "market",
        "analysis"
    ],
    "wof:name":"Meneses Research & Assoc",
    "wof:placetype":"venue"
},
  "geometry": {"coordinates":[-117.20291,32.78012],"type":"Point"}
}