{
  "type": "Feature",
  "properties": {
    "iso:country":"US",
    "sg:address":"3650 Verdugo Road",
    "sg:city":"Los Angeles",
    "sg:classifiers":[
        {
            "category":"Park",
            "type":"Public Place"
        },
        {
            "category":"Shopping Center",
            "type":"Public Place"
        },
        {
            "category":"Sports & Exercise",
            "subcategory":"Swimming Pool",
            "type":"Entertainment"
        }
    ],
    "sg:phone":"+1 323 257 1863",
    "sg:postcode":"90065",
    "sg:province":"CA",
    "sg:tags":[
        "soccer"
    ],
    "sg:website":"www.lacity.org/RAP/dos/reccenter...",
    "wof:name":"Glassell Park and Recreation Center",
    "wof:placetype":"venue"
},
  "geometry": {"coordinates":[-118.23357,34.11623],"type":"Point"}
}