{
  "type": "Feature",
  "properties": {
    "addr:full":"593 Toscanna Ct Brentwood CA 94513",
    "addr:housenumber":"593",
    "addr:postcode":"94513",
    "addr:street":"Toscanna Ct",
    "iso:country":"US",
    "sg:address":"593 Toscanna Ct",
    "sg:city":"Brentwood",
    "sg:classifiers":[
        {
            "category":"Shopping",
            "subcategory":"Party Supplies",
            "type":"Retail Goods"
        }
    ],
    "sg:phone":"+1 925 240 1403",
    "sg:postcode":"94513",
    "sg:province":"CA",
    "wof:name":"Cart Wheels Catering",
    "wof:placetype":"venue"
},
  "geometry": {"coordinates":[-121.708504,37.920927],"type":"Point"}
}