{
  "type": "Feature",
  "properties": {
    "addr:full":"1570 Melody Ln El Cajon CA 92019",
    "addr:housenumber":"1570",
    "addr:postcode":"92019",
    "addr:street":"Melody Ln",
    "iso:country":"US",
    "sg:address":"1570 Melody Ln",
    "sg:city":"El Cajon",
    "sg:classifiers":[
        {
            "category":"Social Services",
            "type":"Services"
        }
    ],
    "sg:phone":"+1 619 593 8885",
    "sg:postcode":"92019",
    "sg:province":"CA",
    "sg:tags":[
        "youth",
        "organization",
        "center"
    ],
    "sg:website":"www.eastcountyasa.com",
    "wof:name":"East County ASA",
    "wof:placetype":"venue"
},
  "geometry": {"coordinates":[-116.92100499999999,32.796461],"type":"Point"}
}