{
  "type": "Feature",
  "properties": {
    "iso:country":"US",
    "sg:address":"5521 Doyle St",
    "sg:city":"Emeryville",
    "sg:classifiers":[
        {
            "category":"Education",
            "subcategory":"Special Training",
            "type":"Public Place"
        },
        {
            "category":"Education",
            "subcategory":"Preschool",
            "type":"Public Place"
        },
        {
            "category":"Education",
            "subcategory":"School",
            "type":"Public Place"
        }
    ],
    "sg:phone":"+1 510 601 1500",
    "sg:postcode":"94608",
    "sg:province":"CA",
    "sg:tags":[
        "elementary",
        "language"
    ],
    "sg:website":"www.pacificriminternationalschoo...",
    "wof:name":"Pacific Rim International School",
    "wof:placetype":"venue"
},
  "geometry": {"coordinates":[-122.287003,37.8377],"type":"Point"}
}