{
  "type": "Feature",
  "properties": {
    "iso:country":"US",
    "sg:address":"218 Eastridge Mall",
    "sg:city":"San Jose",
    "sg:classifiers":[
        {
            "category":"Shopping",
            "subcategory":"Clothing, Apparel, & Fashions",
            "type":"Retail Goods"
        }
    ],
    "sg:phone":"+1 408 274 0232",
    "sg:postcode":"95122",
    "sg:province":"CA",
    "sg:tags":[
        "uniform"
    ],
    "wof:name":"Life Uniform Co",
    "wof:placetype":"venue"
},
  "geometry": {"coordinates":[-121.81076,37.324868],"type":"Point"}
}