{
  "type": "Feature",
  "properties": {
    "addr:full":"2000 S Alameda St Los Angeles CA 90013",
    "addr:housenumber":"2000",
    "addr:postcode":"90013",
    "addr:street":"S Alameda St",
    "iso:country":"US",
    "sg:address":"2000 S Alameda St",
    "sg:city":"Los Angeles",
    "sg:classifiers":[
        {
            "category":"Home & Garden",
            "subcategory":"Hardware",
            "type":"Retail Goods"
        }
    ],
    "sg:phone":"+1 213 748 7869",
    "sg:postcode":"90013",
    "sg:province":"CA",
    "wof:name":"Bobco Metals Co",
    "wof:placetype":"venue"
},
  "geometry": {"coordinates":[-118.239665,34.017224],"type":"Point"}
}