{
  "type": "Feature",
  "properties": {
    "addr:full":"2999 Alhambra Dr Cameron Park CA 95682",
    "addr:housenumber":"2999",
    "addr:postcode":"95682",
    "addr:street":"Alhambra Dr",
    "iso:country":"US",
    "sg:address":"2999 Alhambra Dr",
    "sg:city":"Cameron Park",
    "sg:classifiers":[
        {
            "category":"Retail",
            "subcategory":"Laundry & Dry Cleaning",
            "type":"Services"
        }
    ],
    "sg:phone":"+1 530 677 2448",
    "sg:postcode":"95682",
    "sg:province":"CA",
    "sg:tags":[
        "cleaners",
        "rug",
        "carpet"
    ],
    "wof:name":"Brite-Way Chem-Dry",
    "wof:placetype":"venue"
},
  "geometry": {"coordinates":[-120.990752,38.68838],"type":"Point"}
}