{
  "type": "Feature",
  "properties": {
    "iso:country":"US",
    "sg:address":"13031 San Antonio Dr Ste 118",
    "sg:city":"Norwalk",
    "sg:classifiers":[
        {
            "category":"Professional",
            "subcategory":"Lawyer & Legal Services",
            "type":"Services"
        }
    ],
    "sg:phone":"+1 562 864 0296",
    "sg:postcode":"90650",
    "sg:province":"CA",
    "sg:tags":[
        "notary"
    ],
    "wof:name":"A & A Community Service",
    "wof:placetype":"venue"
},
  "geometry": {"coordinates":[-118.07399700000001,33.912102],"type":"Point"}
}