{
  "type": "Feature",
  "properties": {
    "iso:country":"US",
    "sg:address":"20832 Roscoe Blvd",
    "sg:city":"Canoga Park",
    "sg:classifiers":[
        {
            "category":"Shopping",
            "subcategory":"Jewelry",
            "type":"Retail Goods"
        }
    ],
    "sg:phone":"+1 818 349 8162",
    "sg:postcode":"91306",
    "sg:province":"CA",
    "sg:tags":[
        "jeweler"
    ],
    "wof:name":"CMC",
    "wof:placetype":"venue"
},
  "geometry": {"coordinates":[-118.587642,34.21987],"type":"Point"}
}