{
  "type": "Feature",
  "properties": {
    "iso:country":"US",
    "sg:address":"1401 W 8th St",
    "sg:city":"Los Angeles",
    "sg:classifiers":[
        {
            "category":"Wholesale",
            "subcategory":"Apparel",
            "type":"Manufacturing & Wholesale Goods"
        }
    ],
    "sg:phone":"+1 213 741 9042",
    "sg:postcode":"90017",
    "sg:province":"CA",
    "wof:name":"Private Affaire",
    "wof:placetype":"venue"
},
  "geometry": {"coordinates":[-118.270678,34.051089],"type":"Point"}
}