{
  "type": "Feature",
  "properties": {
    "addr:full":"1919 Alameda de Las Pulgas San Mateo CA 94403",
    "addr:housenumber":"1919",
    "addr:postcode":"94403",
    "addr:street":"Alameda De Las Pulgas",
    "iso:country":"US",
    "sg:address":"1919 Alameda de Las Pulgas",
    "sg:city":"San Mateo",
    "sg:classifiers":[
        {
            "category":"Travel",
            "subcategory":"Travel Agent",
            "type":"Entertainment"
        }
    ],
    "sg:phone":"+1 650 525 9023",
    "sg:postcode":"94403",
    "sg:province":"CA",
    "sg:tags":[
        "agency",
        "bureau"
    ],
    "wof:name":"Coastyle Travel",
    "wof:placetype":"venue"
},
  "geometry": {"coordinates":[-122.321825,37.546496],"type":"Point"}
}