{
  "type": "Feature",
  "properties": {
    "addr:full":"1980 Oceanside Blvd Oceanside CA 92054",
    "addr:housenumber":"1980",
    "addr:postcode":"92054",
    "addr:street":"Oceanside Blvd",
    "iso:country":"US",
    "sg:address":"1980 Oceanside Blvd",
    "sg:city":"Oceanside",
    "sg:classifiers":[
        {
            "category":"Retail",
            "subcategory":"Car Wash",
            "type":"Services"
        }
    ],
    "sg:phone":"+1 760 966 0100",
    "sg:postcode":"92054",
    "sg:province":"CA",
    "wof:name":"VIP Carwash",
    "wof:placetype":"venue"
},
  "geometry": {"coordinates":[-117.353752,33.195054],"type":"Point"}
}