{
  "type": "Feature",
  "properties": {
    "addr:full":"120 W Wilshire Ave Fullerton CA 92832",
    "addr:housenumber":"120",
    "addr:postcode":"92832",
    "addr:street":"W Wilshire Ave",
    "iso:country":"US",
    "sg:address":"120 W Wilshire Ave",
    "sg:city":"Fullerton",
    "sg:classifiers":[
        {
            "category":"Arts & Performance",
            "subcategory":"Theater",
            "type":"Entertainment"
        }
    ],
    "sg:phone":"+1 714 526 8007",
    "sg:postcode":"92832",
    "sg:province":"CA",
    "wof:name":"A Vanguard Theatre Ensemble",
    "wof:placetype":"venue"
},
  "geometry": {"coordinates":[-117.926258,33.872296],"type":"Point"}
}