{
  "type": "Feature",
  "properties": {
    "addr:full":"5855 Green Valley Cir Culver City CA 90230",
    "addr:housenumber":"5855",
    "addr:postcode":"90230",
    "addr:street":"Green Valley Cir",
    "iso:country":"US",
    "sg:address":"5855 Green Valley Cir",
    "sg:city":"Culver City",
    "sg:classifiers":[
        {
            "category":"Insurance",
            "subcategory":"Insurance Agent",
            "type":"Services"
        }
    ],
    "sg:phone":"+1 310 649 1273",
    "sg:postcode":"90230",
    "sg:province":"CA",
    "sg:tags":[
        "adjuster"
    ],
    "sg:website":"www.kapilowandson.com",
    "wof:name":"Kapilow & Son Inc",
    "wof:placetype":"venue"
},
  "geometry": {"coordinates":[-118.39023899999999,33.983225],"type":"Point"}
}