{
  "type": "Feature",
  "properties": {
    "iso:country":"US",
    "sg:address":"3850 Wilcox Rd",
    "sg:city":"Stockton",
    "sg:classifiers":[
        {
            "category":"Building & Trades",
            "subcategory":"Electrical",
            "type":"Services"
        },
        {
            "category":"Professional",
            "subcategory":"Management & Consulting",
            "type":"Services"
        }
    ],
    "sg:phone":"+1 209 931 6646",
    "sg:postcode":"95215",
    "sg:province":"CA",
    "sg:tags":[
        "consultant",
        "electrical",
        "contractor"
    ],
    "wof:name":"Electrical Planning Service",
    "wof:placetype":"venue"
},
  "geometry": {"coordinates":[-121.252791,38.000459],"type":"Point"}
}