{
  "type": "Feature",
  "properties": {
    "iso:country":"US",
    "sg:address":"291 S State Hwy 173",
    "sg:city":"Lake Arrowhead",
    "sg:classifiers":[
        {
            "category":"Travel",
            "subcategory":"Hotels & Motels",
            "type":"Entertainment"
        }
    ],
    "sg:phone":"+1 909 337 2411",
    "sg:postcode":"92352",
    "sg:province":"CA",
    "sg:tags":[
        "resort"
    ],
    "wof:name":"Arrowhead Holiday Cabin Rental",
    "wof:placetype":"venue"
},
  "geometry": {"coordinates":[-117.178359,34.25014],"type":"Point"}
}