{
  "type": "Feature",
  "properties": {
    "addr:full":"4848 Tecolote Rd San Diego CA 92110",
    "addr:housenumber":"4848",
    "addr:postcode":"92110",
    "addr:street":"Tecolote Rd",
    "iso:country":"US",
    "sg:address":"4848 Tecolote Rd",
    "sg:city":"San Diego",
    "sg:classifiers":[
        {
            "category":"Recreation",
            "type":"Entertainment"
        }
    ],
    "sg:phone":"+1 619 275 3270",
    "sg:postcode":"92110",
    "sg:province":"CA",
    "sg:tags":[
        "tennis",
        "court"
    ],
    "sg:website":"www.sctrc.com",
    "wof:name":"San Diego Tennis Racquet Club",
    "wof:placetype":"venue"
},
  "geometry": {"coordinates":[-117.19954799999999,32.775653],"type":"Point"}
}