{
  "type": "Feature",
  "properties": {
    "iso:country":"US",
    "sg:address":"1121 Laurel St",
    "sg:city":"San Carlos",
    "sg:classifiers":[
        {
            "category":"Insurance",
            "subcategory":"Insurance Agent",
            "type":"Services"
        }
    ],
    "sg:phone":"+1 650 593 7601",
    "sg:postcode":"94070",
    "sg:province":"CA",
    "wof:name":"ISU Lovering Insurance",
    "wof:placetype":"venue"
},
  "geometry": {"coordinates":[-122.252126,37.499044],"type":"Point"}
}