{
  "type": "Feature",
  "properties": {
    "iso:country":"US",
    "sg:address":"4996 Stevens Creek Blvd",
    "sg:city":"San Jose",
    "sg:classifiers":[
        {
            "category":"Professional",
            "type":"Services"
        },
        {
            "category":"Restaurant",
            "type":"Food & Drink"
        }
    ],
    "sg:phone":"+1 408 248 7191",
    "sg:postcode":"95129",
    "sg:province":"CA",
    "sg:tags":[
        "thai",
        "caterer"
    ],
    "sg:website":"bluemangocuisine.com",
    "wof:name":"Blue Mango",
    "wof:placetype":"venue"
},
  "geometry": {"coordinates":[-121.989998,37.3232],"type":"Point"}
}