{
  "type": "Feature",
  "properties": {
    "addr:full":"4996 Stevens Creek Blvd San Jose CA 95129",
    "addr:housenumber":"4996",
    "addr:postcode":"95129",
    "addr:street":"Stevens Creek Blvd",
    "iso:country":"US",
    "sg:address":"4996 Stevens Creek Blvd",
    "sg:city":"San Jose",
    "sg:classifiers":[
        {
            "category":"Professional",
            "type":"Services"
        },
        {
            "category":"Restaurant",
            "type":"Food & Drink"
        }
    ],
    "sg:phone":"+1 408 248 7191",
    "sg:postcode":"95129",
    "sg:province":"CA",
    "sg:tags":[
        "thai",
        "caterer"
    ],
    "sg:website":"bluemangocuisine.com",
    "wof:name":"Blue Mango",
    "wof:placetype":"venue"
},
  "geometry": {"coordinates":[-121.989998,37.3232],"type":"Point"}
}