{
  "type": "Feature",
  "properties": {
    "addr:full":"6925 Canby Ave Reseda CA 91335",
    "addr:housenumber":"6925",
    "addr:postcode":"91335",
    "addr:street":"Canby Ave",
    "iso:country":"US",
    "sg:address":"6925 Canby Ave",
    "sg:city":"Reseda",
    "sg:classifiers":[
        {
            "category":"Professional",
            "subcategory":"Employment Agencies",
            "type":"Services"
        }
    ],
    "sg:phone":"+1 818 342 3204",
    "sg:postcode":"91335",
    "sg:province":"CA",
    "wof:name":"Plan Search",
    "wof:placetype":"venue"
},
  "geometry": {"coordinates":[-118.53462399999999,34.195653],"type":"Point"}
}