{
  "type": "Feature",
  "properties": {
    "addr:full":"891 Baker St Costa Mesa CA 92626",
    "addr:housenumber":"891",
    "addr:postcode":"92626",
    "addr:street":"Baker St",
    "iso:country":"US",
    "sg:address":"891 Baker St",
    "sg:city":"Costa Mesa",
    "sg:classifiers":[
        {
            "category":"Health Services",
            "subcategory":"Dentist",
            "type":"Services"
        }
    ],
    "sg:phone":"+1 714 641 0337",
    "sg:postcode":"92626",
    "sg:province":"CA",
    "wof:name":"Costa Mesa Cosmetic Dentistry",
    "wof:placetype":"venue"
},
  "geometry": {"coordinates":[-117.89353300000001,33.679575],"type":"Point"}
}