{
  "type": "Feature",
  "properties": {
    "iso:country":"US",
    "sg:address":"3250 Hwy 128",
    "sg:city":"Calistoga",
    "sg:classifiers":[
        {
            "category":"Travel",
            "subcategory":"Bed & Breakfast",
            "type":"Entertainment"
        }
    ],
    "sg:phone":"+1 877 558 2513",
    "sg:postcode":"94515",
    "sg:province":"CA",
    "sg:website":"www.cdvnapavalley.com",
    "wof:name":"Chateau de Vie",
    "wof:placetype":"venue"
},
  "geometry": {"coordinates":[-122.612595,38.593768],"type":"Point"}
}