{
  "type": "Feature",
  "properties": {
    "addr:full":"1323 E Houston Ave Visalia CA 93292",
    "addr:housenumber":"1323",
    "addr:postcode":"93292",
    "addr:street":"E Houston Ave",
    "iso:country":"US",
    "sg:address":"1323 E Houston Ave",
    "sg:city":"Visalia",
    "sg:classifiers":[
        {
            "category":"Home & Garden",
            "subcategory":"Furniture",
            "type":"Retail Goods"
        }
    ],
    "sg:phone":"+1 559 635 8182",
    "sg:postcode":"93292",
    "sg:province":"CA",
    "sg:tags":[
        "store"
    ],
    "wof:name":"Muebleria El Paisano",
    "wof:placetype":"venue"
},
  "geometry": {"coordinates":[-119.27958,36.341856],"type":"Point"}
}