{
  "type": "Feature",
  "properties": {
    "iso:country":"US",
    "sg:address":"756 Lakefield Rd",
    "sg:city":"Westlake Village",
    "sg:classifiers":[
        {
            "category":"Government",
            "subcategory":"Office",
            "type":"Public Place"
        }
    ],
    "sg:phone":"+1 805 495 8420",
    "sg:postcode":"91361",
    "sg:province":"CA",
    "sg:tags":[
        "management"
    ],
    "wof:name":"China American Import/Export C",
    "wof:placetype":"venue"
},
  "geometry": {"coordinates":[-118.830719,34.15746],"type":"Point"}
}