{
  "type": "Feature",
  "properties": {
    "addr:full":"3300 Lakeshore Ave Oakland CA 94610",
    "addr:housenumber":"3300",
    "addr:postcode":"94610",
    "addr:street":"Lakeshore Ave",
    "iso:country":"US",
    "sg:address":"3300 Lakeshore Ave",
    "sg:city":"Oakland",
    "sg:classifiers":[
        {
            "category":"Cinema",
            "subcategory":"Movie Rental",
            "type":"Entertainment"
        }
    ],
    "sg:phone":"+1 510 835 2294",
    "sg:postcode":"94610",
    "sg:province":"CA",
    "sg:tags":[
        "leasing",
        "video",
        "disc",
        "tape"
    ],
    "sg:website":"www.blockbuster.com",
    "wof:name":"Blockbuster Video",
    "wof:placetype":"venue"
},
  "geometry": {"coordinates":[-122.244507,37.81051],"type":"Point"}
}