{
  "type": "Feature",
  "properties": {
    "addr:full":"16225 Arrow Blvd Fontana CA 92335",
    "addr:housenumber":"16225",
    "addr:postcode":"92335",
    "addr:street":"Arrow Blvd",
    "iso:country":"US",
    "sg:address":"16225 Arrow Blvd",
    "sg:city":"Fontana",
    "sg:classifiers":[
        {
            "category":"Freight",
            "type":"Transportation"
        }
    ],
    "sg:phone":"+1 909 854 0360",
    "sg:postcode":"92335",
    "sg:province":"CA",
    "sg:tags":[
        "hauling",
        "trucking"
    ],
    "wof:name":"Bailey Hauling",
    "wof:placetype":"venue"
},
  "geometry": {"coordinates":[-117.45152400000001,34.099242],"type":"Point"}
}