{
  "type": "Feature",
  "properties": {
    "addr:full":"24053 Rd 212 Lindsay CA 93247",
    "addr:postcode":"24053;93247",
    "addr:street":"Rd 212",
    "iso:country":"US",
    "sg:address":"24053 Rd 212",
    "sg:city":"Lindsay",
    "sg:classifiers":[
        {
            "category":"Farming",
            "subcategory":"Orchard",
            "type":"Manufacturing & Wholesale Goods"
        }
    ],
    "sg:phone":"+1 559 562 3559",
    "sg:postcode":"93247",
    "sg:province":"CA",
    "sg:tags":[
        "citrus",
        "grove",
        "fruit"
    ],
    "wof:name":"Davis Merilyn",
    "wof:placetype":"venue"
},
  "geometry": {"coordinates":[-119.100661,36.232271],"type":"Point"}
}