{
  "type": "Feature",
  "properties": {
    "addr:full":"3319 Main St Cottonwood CA 96022",
    "addr:housenumber":"3319",
    "addr:postcode":"96022",
    "addr:street":"Main St",
    "iso:country":"US",
    "sg:address":"3319 Main St",
    "sg:city":"Cottonwood",
    "sg:classifiers":[
        {
            "category":"Real Estate",
            "subcategory":"Real Estate Agent",
            "type":"Services"
        }
    ],
    "sg:phone":"+1 530 347 6901",
    "sg:postcode":"96022",
    "sg:province":"CA",
    "wof:name":"Bar L Realty",
    "wof:placetype":"venue"
},
  "geometry": {"coordinates":[-122.28105100000001,40.385852],"type":"Point"}
}