{
  "type": "Feature",
  "properties": {
    "addr:full":"115 E Washington Blvd Los Angeles CA 90015",
    "addr:housenumber":"115",
    "addr:postcode":"90015",
    "addr:street":"E Washington Blvd",
    "iso:country":"US",
    "sg:address":"115 E Washington Blvd",
    "sg:city":"Los Angeles",
    "sg:classifiers":[
        {
            "category":"Health Services",
            "subcategory":"Doctor",
            "type":"Services"
        }
    ],
    "sg:phone":"+1 800 322 2222",
    "sg:postcode":"90015",
    "sg:province":"CA",
    "wof:name":"Clinica Medica San Miguel",
    "wof:placetype":"venue"
},
  "geometry": {"coordinates":[-118.264109,34.102363],"type":"Point"}
}