{
  "type": "Feature",
  "properties": {
    "addr:full":"225 Broadway Ste 450 San Diego CA 92101",
    "addr:housenumber":"225",
    "addr:postcode":"92101",
    "addr:street":"Broadway Ste 450",
    "iso:country":"US",
    "sg:address":"225 Broadway Ste 450",
    "sg:city":"San Diego",
    "sg:classifiers":[
        {
            "category":"Professional",
            "subcategory":"Employment Agencies",
            "type":"Services"
        }
    ],
    "sg:phone":"+1 619 230 7626",
    "sg:postcode":"92101",
    "sg:province":"CA",
    "sg:website":"www.davidsonstaffing.com",
    "wof:name":"Davidson Staffing",
    "wof:placetype":"venue"
},
  "geometry": {"coordinates":[-117.162644,32.715515],"type":"Point"}
}