{
  "type": "Feature",
  "properties": {
    "addr:full":"2100 Wylie Dr Apt 68 Modesto CA 95355",
    "addr:housenumber":"2100;68",
    "addr:postcode":"95355",
    "addr:street":"Wylie Dr Apt",
    "iso:country":"US",
    "sg:address":"2100 Wylie Dr Apt 68",
    "sg:city":"Modesto",
    "sg:classifiers":[
        {
            "category":"Real Estate",
            "subcategory":"Real Estate Services",
            "type":"Services"
        }
    ],
    "sg:phone":"+1 209 576 0878",
    "sg:postcode":"95355",
    "sg:province":"CA",
    "sg:tags":[
        "management",
        "property"
    ],
    "wof:name":"Marshall Perry Inc",
    "wof:placetype":"venue"
},
  "geometry": {"coordinates":[-120.959999,37.658001],"type":"Point"}
}