{
  "type": "Feature",
  "properties": {
    "iso:country":"US",
    "sg:address":"1060 E Colorado Blvd",
    "sg:city":"Pasadena",
    "sg:classifiers":[
        {
            "category":"Retail",
            "subcategory":"Auto Repair",
            "type":"Services"
        }
    ],
    "sg:phone":"+1 626 796 9592",
    "sg:postcode":"91106",
    "sg:province":"CA",
    "sg:tags":[
        "repairing",
        "automobile"
    ],
    "wof:name":"Gordons Auto Repair",
    "wof:placetype":"venue"
},
  "geometry": {"coordinates":[-118.128998,34.145802],"type":"Point"}
}