{
  "type": "Feature",
  "properties": {
    "addr:full":"519 S Oregon St Yreka CA 96097",
    "addr:housenumber":"519",
    "addr:postcode":"96097",
    "addr:street":"S Oregon St",
    "iso:country":"US",
    "sg:address":"519 S Oregon St",
    "sg:city":"Yreka",
    "sg:classifiers":[
        {
            "category":"Manufacturing",
            "subcategory":"Lumber",
            "type":"Manufacturing & Wholesale Goods"
        }
    ],
    "sg:phone":"+1 530 841 0394",
    "sg:postcode":"96097",
    "sg:province":"CA",
    "sg:tags":[
        "forestry"
    ],
    "wof:name":"Errol Giles",
    "wof:placetype":"venue"
},
  "geometry": {"coordinates":[-122.639692,41.728789],"type":"Point"}
}