{
  "type": "Feature",
  "properties": {
    "addr:full":"2115 Morrill Ave San Jose CA 95132",
    "addr:housenumber":"2115",
    "addr:postcode":"95132",
    "addr:street":"Morrill Ave",
    "iso:country":"US",
    "sg:address":"2115 Morrill Ave",
    "sg:city":"San Jose",
    "sg:classifiers":[
        {
            "category":"Food & Beverages",
            "subcategory":"Meat & Fish",
            "type":"Retail Goods"
        },
        {
            "category":"Food & Beverages",
            "subcategory":"Groceries & Convenience Stores",
            "type":"Retail Goods"
        }
    ],
    "sg:phone":"+1 408 263 3888",
    "sg:postcode":"95132",
    "sg:province":"CA",
    "sg:tags":[
        "seafood",
        "market"
    ],
    "wof:name":"California Ranch Supermarkets",
    "wof:placetype":"venue"
},
  "geometry": {"coordinates":[-121.875224,37.413811],"type":"Point"}
}