{
  "type": "Feature",
  "properties": {
    "addr:full":"10396 Bellegrave Ave Mira Loma CA 91752",
    "addr:housenumber":"10396",
    "addr:postcode":"91752",
    "addr:street":"Bellegrave Ave",
    "iso:country":"US",
    "sg:address":"10396 Bellegrave Ave",
    "sg:city":"Mira Loma",
    "sg:classifiers":[
        {
            "category":"Personal",
            "type":"Services"
        },
        {
            "category":"Retail",
            "subcategory":"Animal Services",
            "type":"Services"
        }
    ],
    "sg:phone":"+1 951 681 1438",
    "sg:postcode":"91752",
    "sg:province":"CA",
    "sg:tags":[
        "pet",
        "boarding",
        "sitting"
    ],
    "wof:name":"Golden Retreat Kennels",
    "wof:placetype":"venue"
},
  "geometry": {"coordinates":[-117.511613,34.003314],"type":"Point"}
}