{
  "type": "Feature",
  "properties": {
    "addr:full":"611 23rd St Richmond CA 94804",
    "addr:housenumber":"611",
    "addr:postcode":"94804",
    "addr:street":"23Rd St",
    "iso:country":"US",
    "sg:address":"611 23rd St",
    "sg:city":"Richmond",
    "sg:classifiers":[
        {
            "category":"Retail",
            "subcategory":"Auto Repair",
            "type":"Services"
        }
    ],
    "sg:phone":"+1 510 235 2800",
    "sg:postcode":"94804",
    "sg:province":"CA",
    "sg:tags":[
        "repairing",
        "automobile"
    ],
    "wof:name":"Express Automotive Svc",
    "wof:placetype":"venue"
},
  "geometry": {"coordinates":[-122.34758100000001,37.940076],"type":"Point"}
}