{
  "type": "Feature",
  "properties": {
    "iso:country":"US",
    "sg:address":"235 Main St",
    "sg:city":"Point Arena",
    "sg:classifiers":[
        {
            "category":"Shopping",
            "subcategory":"Pharmacy",
            "type":"Retail Goods"
        }
    ],
    "sg:phone":"+1 707 882 3025",
    "sg:postcode":"95468",
    "sg:province":"CA",
    "wof:name":"Arena Pharmacy",
    "wof:placetype":"venue"
},
  "geometry": {"coordinates":[-123.692487,38.909803],"type":"Point"}
}