{
  "type": "Feature",
  "properties": {
    "iso:country":"US",
    "sg:address":"9321 Melvin Ave",
    "sg:city":"Northridge",
    "sg:classifiers":[
        {
            "category":"Manufacturing",
            "subcategory":"Tools & Machinery",
            "type":"Manufacturing & Wholesale Goods"
        }
    ],
    "sg:phone":"+1 818 407 7577",
    "sg:postcode":"91324",
    "sg:province":"CA",
    "sg:tags":[
        "equipment",
        "pump",
        "pumping"
    ],
    "sg:website":"www.dynapumpinc.com",
    "wof:name":"Dynapump Inc",
    "wof:placetype":"venue"
},
  "geometry": {"coordinates":[-118.56019999999999,34.240215],"type":"Point"}
}