{
  "type": "Feature",
  "properties": {
    "iso:country":"US",
    "sg:address":"760 W 16th St",
    "sg:city":"Costa Mesa",
    "sg:classifiers":[
        {
            "category":"Professional",
            "type":"Services"
        }
    ],
    "sg:phone":"+1 949 261 3480",
    "sg:postcode":"92627",
    "sg:province":"CA",
    "sg:tags":[
        "establishment"
    ],
    "wof:name":"Pacifica",
    "wof:placetype":"venue"
},
  "geometry": {"coordinates":[-117.92999500000001,33.632577],"type":"Point"}
}