{
  "type": "Feature",
  "properties": {
    "iso:country":"US",
    "sg:address":"8345 Reseda Blvd",
    "sg:city":"Northridge",
    "sg:classifiers":[
        {
            "category":"Professional",
            "subcategory":"Advertising",
            "type":"Services"
        }
    ],
    "sg:phone":"+1 818 886 6668",
    "sg:postcode":"91324",
    "sg:province":"CA",
    "wof:name":"San Fernando Valley Cmnty News",
    "wof:placetype":"venue"
},
  "geometry": {"coordinates":[-118.536155,34.223746],"type":"Point"}
}