{
  "type": "Feature",
  "properties": {
    "addr:full":"5720 W Jefferson Blvd Los Angeles CA 90016",
    "addr:housenumber":"5720",
    "addr:postcode":"90016",
    "addr:street":"W Jefferson Blvd",
    "iso:country":"US",
    "sg:address":"5720 W Jefferson Blvd",
    "sg:city":"Los Angeles",
    "sg:classifiers":[
        {
            "category":"Building & Trades",
            "subcategory":"Cleaning & Sanitation",
            "type":"Services"
        }
    ],
    "sg:phone":"+1 323 549 9393",
    "sg:postcode":"90016",
    "sg:province":"CA",
    "sg:tags":[
        "janitor"
    ],
    "wof:name":"Commercial Cleaning",
    "wof:placetype":"venue"
},
  "geometry": {"coordinates":[-118.376369,34.025849],"type":"Point"}
}