{
  "type": "Feature",
  "properties": {
    "addr:full":"395 Peebles Ave Morgan Hill CA 95037",
    "addr:housenumber":"395",
    "addr:postcode":"95037",
    "addr:street":"Peebles Ave",
    "iso:country":"US",
    "sg:address":"395 Peebles Ave",
    "sg:city":"Morgan Hill",
    "sg:classifiers":[
        {
            "category":"Building & Trades",
            "subcategory":"Construction",
            "type":"Services"
        }
    ],
    "sg:phone":"+1 408 779 6455",
    "sg:postcode":"95037",
    "sg:province":"CA",
    "sg:tags":[
        "pipe",
        "line",
        "contractor"
    ],
    "wof:name":"G E Wolfe Construction Inc",
    "wof:placetype":"venue"
},
  "geometry": {"coordinates":[-121.66718899999999,37.153448],"type":"Point"}
}