{
  "type": "Feature",
  "properties": {
    "iso:country":"US",
    "sg:address":"395 Peebles Ave",
    "sg:city":"Morgan Hill",
    "sg:classifiers":[
        {
            "category":"Building & Trades",
            "subcategory":"Construction",
            "type":"Services"
        }
    ],
    "sg:phone":"+1 408 779 6455",
    "sg:postcode":"95037",
    "sg:province":"CA",
    "sg:tags":[
        "pipe",
        "line",
        "contractor"
    ],
    "wof:name":"G E Wolfe Construction Inc",
    "wof:placetype":"venue"
},
  "geometry": {"coordinates":[-121.667189,37.153448],"type":"Point"}
}