{
  "type": "Feature",
  "properties": {
    "addr:full":"900 Hyde St San Francisco CA 94109",
    "addr:housenumber":"900",
    "addr:postcode":"94109",
    "addr:street":"Hyde St",
    "iso:country":"US",
    "sg:address":"900 Hyde St",
    "sg:city":"San Francisco",
    "sg:classifiers":[
        {
            "category":"Health Services",
            "subcategory":"Doctor",
            "type":"Services"
        },
        {
            "category":"Sports & Exercise",
            "subcategory":"Gym",
            "type":"Entertainment"
        },
        {
            "category":"Health Services",
            "subcategory":"Health Practitioner",
            "type":"Services"
        }
    ],
    "sg:phone":"+1 415 353 6400",
    "sg:postcode":"94109",
    "sg:province":"CA",
    "sg:tags":[
        "orthopedist",
        "podiatrist",
        "therapy",
        "medicine",
        "pilate",
        "physical"
    ],
    "sg:website":"www.saintfrancismemorial.org",
    "wof:name":"Elizabeth O'toole, DPM",
    "wof:placetype":"venue"
},
  "geometry": {"coordinates":[-122.417064,37.789157],"type":"Point"}
}