{
  "type": "Feature",
  "properties": {
    "iso:country":"US",
    "sg:address":"2399 Westwood Blvd",
    "sg:city":"Los Angeles",
    "sg:classifiers":[
        {
            "category":"Professional",
            "subcategory":"Computer Services",
            "type":"Services"
        }
    ],
    "sg:phone":"+1 310 441 4130",
    "sg:postcode":"90064",
    "sg:province":"CA",
    "sg:tags":[
        "repair"
    ],
    "sg:website":"www.lacomp.net",
    "wof:name":"Landmark Computers",
    "wof:placetype":"venue"
},
  "geometry": {"coordinates":[-118.428569,34.040124],"type":"Point"}
}