{
  "type": "Feature",
  "properties": {
    "addr:full":"870 E Front St Ventura CA 93001",
    "addr:housenumber":"870",
    "addr:postcode":"93001",
    "addr:street":"E Front St",
    "iso:country":"US",
    "sg:address":"870 E Front St",
    "sg:city":"Ventura",
    "sg:classifiers":[
        {
            "category":"Professional",
            "subcategory":"Management & Consulting",
            "type":"Services"
        },
        {
            "category":"Manufacturing",
            "subcategory":"Printing",
            "type":"Manufacturing & Wholesale Goods"
        }
    ],
    "sg:phone":"+1 805 653 0532",
    "sg:postcode":"93001",
    "sg:province":"CA",
    "sg:tags":[
        "consultant",
        "publisher",
        "software"
    ],
    "wof:name":"Orange Consulting LLC",
    "wof:placetype":"venue"
},
  "geometry": {"coordinates":[-119.288,34.276936],"type":"Point"}
}