{
  "type": "Feature",
  "properties": {
    "addr:full":"28691 Via Las Flores Murrieta CA 92563",
    "addr:housenumber":"28691",
    "addr:postcode":"92563",
    "addr:street":"Via Las Flores",
    "iso:country":"US",
    "sg:address":"28691 Via Las Flores",
    "sg:city":"Murrieta",
    "sg:classifiers":[
        {
            "category":"Real Estate",
            "subcategory":"Real Estate Agent",
            "type":"Services"
        }
    ],
    "sg:phone":"+1 951 699 1002",
    "sg:postcode":"92563",
    "sg:province":"CA",
    "sg:tags":[
        "appraiser"
    ],
    "wof:name":"Cornerstone Appraisal",
    "wof:placetype":"venue"
},
  "geometry": {"coordinates":[-117.159333,33.557463],"type":"Point"}
}