{
  "type": "Feature",
  "properties": {
    "iso:country":"US",
    "sg:address":"423 Broadway",
    "sg:city":"Millbrae",
    "sg:classifiers":[
        {
            "category":"Wholesale",
            "subcategory":"Machinery & Supplies",
            "type":"Manufacturing & Wholesale Goods"
        }
    ],
    "sg:phone":"+1 650 697 4782",
    "sg:postcode":"94030",
    "sg:province":"CA",
    "sg:tags":[
        "processing",
        "representative"
    ],
    "wof:name":"Global Partners Inc",
    "wof:placetype":"venue"
},
  "geometry": {"coordinates":[-122.393669,37.60231],"type":"Point"}
}