{
  "type": "Feature",
  "properties": {
    "addr:full":"12300 Washington Blvd Whittier CA 90606",
    "addr:housenumber":"12300",
    "addr:postcode":"90606",
    "addr:street":"Washington Blvd",
    "iso:country":"US",
    "sg:address":"12300 Washington Blvd",
    "sg:city":"Whittier",
    "sg:classifiers":[
        {
            "category":"Communications",
            "subcategory":"Film & Video Production",
            "type":"Services"
        }
    ],
    "sg:phone":"+1 562 696 2324",
    "sg:postcode":"90606",
    "sg:province":"CA",
    "sg:tags":[
        "taping"
    ],
    "sg:website":"www.datavideo-tek.com",
    "wof:name":"Datavideo Corp",
    "wof:placetype":"venue"
},
  "geometry": {"coordinates":[-118.050151,33.967122],"type":"Point"}
}