{
  "type": "Feature",
  "properties": {
    "addr:full":"3735 Iowa Ave Riverside CA 92507",
    "addr:housenumber":"3735",
    "addr:postcode":"92507",
    "addr:street":"Iowa Ave",
    "iso:country":"US",
    "sg:address":"3735 Iowa Ave",
    "sg:city":"Riverside",
    "sg:classifiers":[
        {
            "category":"Travel",
            "subcategory":"Hotels & Motels",
            "type":"Entertainment"
        }
    ],
    "sg:phone":"+1 951 369 8200",
    "sg:postcode":"92507",
    "sg:province":"CA",
    "sg:website":"www.dynastysuites.com",
    "wof:name":"Dynasty Suites",
    "wof:placetype":"venue"
},
  "geometry": {"coordinates":[-117.339944,33.978572],"type":"Point"}
}