{
  "type": "Feature",
  "properties": {
    "addr:full":"15580 Gale Ave Hacienda Heights CA 91745",
    "addr:housenumber":"15580",
    "addr:postcode":"91745",
    "addr:street":"Gale Ave",
    "iso:country":"US",
    "sg:address":"15580 Gale Ave",
    "sg:city":"Hacienda Heights",
    "sg:classifiers":[
        {
            "category":"Travel",
            "subcategory":"Travel Agent",
            "type":"Entertainment"
        }
    ],
    "sg:phone":"+1 626 286 1278",
    "sg:postcode":"91745",
    "sg:province":"CA",
    "sg:tags":[
        "agency"
    ],
    "wof:name":"A & W Travel",
    "wof:placetype":"venue"
},
  "geometry": {"coordinates":[-117.96682699999999,34.012014],"type":"Point"}
}