{
  "type": "Feature",
  "properties": {
    "addr:full":"1390 Flynn Rd Camarillo CA 93012",
    "addr:housenumber":"1390",
    "addr:postcode":"93012",
    "addr:street":"Flynn Rd",
    "iso:country":"US",
    "sg:address":"1390 Flynn Rd",
    "sg:city":"Camarillo",
    "sg:classifiers":[
        {
            "category":"Manufacturing",
            "subcategory":"Tools & Machinery",
            "type":"Manufacturing & Wholesale Goods"
        }
    ],
    "sg:phone":"+1 805 482 1039",
    "sg:postcode":"93012",
    "sg:province":"CA",
    "sg:tags":[
        "machine",
        "shop"
    ],
    "sg:website":"www.aplusmach.com",
    "wof:name":"A Plus Precision Machining Inc",
    "wof:placetype":"venue"
},
  "geometry": {"coordinates":[-119.01388300000001,34.232279],"type":"Point"}
}