{
  "type": "Feature",
  "properties": {
    "addr:full":"31497 Outer Hwy 10 S Redlands CA 92373",
    "addr:housenumber":"31497",
    "addr:postcode":"92373",
    "addr:street":"Outer Hwy 10 S",
    "iso:country":"US",
    "sg:address":"31497 Outer Hwy 10 S",
    "sg:city":"Redlands",
    "sg:classifiers":[
        {
            "category":"Building & Trades",
            "subcategory":"Construction",
            "type":"Services"
        }
    ],
    "sg:phone":"+1 909 794 2514",
    "sg:postcode":"92373",
    "sg:province":"CA",
    "sg:tags":[
        "coping",
        "plastering",
        "tiling",
        "pool",
        "swimming"
    ],
    "wof:name":"A-1 Pools & Spas By Marglo Inc",
    "wof:placetype":"venue"
},
  "geometry": {"coordinates":[-117.117521,34.025582],"type":"Point"}
}