{
  "type": "Feature",
  "properties": {
    "addr:full":"34428 Yucaipa Blvd Yucaipa CA 92399",
    "addr:postcode":"34428;92399",
    "addr:street":"Yucaipa Blvd",
    "iso:country":"US",
    "sg:address":"34428 Yucaipa Blvd",
    "sg:city":"Yucaipa",
    "sg:classifiers":[
        {
            "category":"Professional",
            "subcategory":"Art Services",
            "type":"Services"
        }
    ],
    "sg:phone":"+1 909 446 0233",
    "sg:postcode":"92399",
    "sg:province":"CA",
    "sg:tags":[
        "artist"
    ],
    "wof:name":"Horse-Power Graphics",
    "wof:placetype":"venue"
},
  "geometry": {"coordinates":[-117.054354,34.033961],"type":"Point"}
}