{
  "type": "Feature",
  "properties": {
    "iso:country":"US",
    "sg:address":"931 Main St",
    "sg:city":"Fortuna",
    "sg:classifiers":[
        {
            "category":"Utilities",
            "subcategory":"Mobile Phone",
            "type":"Services"
        }
    ],
    "sg:phone":"+1 707 725 8800",
    "sg:postcode":"95540",
    "sg:province":"CA",
    "sg:tags":[
        "communication",
        "radiotelephone"
    ],
    "wof:name":"Lost Coast Wireless",
    "wof:placetype":"venue"
},
  "geometry": {"coordinates":[-124.157323,40.598088],"type":"Point"}
}