{
  "type": "Feature",
  "properties": {
    "iso:country":"US",
    "sg:address":"4041 Haviland Dr",
    "sg:city":"Granite Bay",
    "sg:classifiers":[
        {
            "category":"Building & Trades",
            "subcategory":"Landscaping Services",
            "type":"Services"
        }
    ],
    "sg:phone":"+1 510 339 1767",
    "sg:postcode":"95746",
    "sg:province":"CA",
    "wof:name":"Aspen Tree Care",
    "wof:placetype":"venue"
},
  "geometry": {"coordinates":[-121.22117299999999,38.717855],"type":"Point"}
}