{
  "type": "Feature",
  "properties": {
    "addr:full":"1777 Saratoga Ave San Jose CA 95129",
    "addr:housenumber":"1777",
    "addr:postcode":"95129",
    "addr:street":"Saratoga Ave",
    "iso:country":"US",
    "sg:address":"1777 Saratoga Ave",
    "sg:city":"San Jose",
    "sg:classifiers":[
        {
            "category":"Banks & Credit Unions",
            "subcategory":"Investment Brokerage",
            "type":"Services"
        }
    ],
    "sg:phone":"+1 408 996 7891",
    "sg:postcode":"95129",
    "sg:province":"CA",
    "wof:name":"Edward Jones Investments",
    "wof:placetype":"venue"
},
  "geometry": {"coordinates":[-121.99426200000001,37.289879],"type":"Point"}
}