{
  "type": "Feature",
  "properties": {
    "iso:country":"US",
    "sg:address":"23504 Lyons Ave",
    "sg:city":"Newhall",
    "sg:classifiers":[
        {
            "category":"Professional",
            "subcategory":"Lawyer & Legal Services",
            "type":"Services"
        }
    ],
    "sg:phone":"+1 661 253 3293",
    "sg:postcode":"91321",
    "sg:province":"CA",
    "sg:tags":[
        "attorney"
    ],
    "wof:name":"Charles R Hendricks",
    "wof:placetype":"venue"
},
  "geometry": {"coordinates":[-118.54588699999999,34.379323],"type":"Point"}
}