{
  "type": "Feature",
  "properties": {
    "addr:full":"901 Grant Ave San Francisco CA 94108",
    "addr:housenumber":"901",
    "addr:postcode":"94108",
    "addr:street":"Grant Ave",
    "iso:country":"US",
    "sg:address":"901 Grant Ave",
    "sg:city":"San Francisco",
    "sg:classifiers":[
        {
            "category":"Bars & Pubs",
            "type":"Food & Drink"
        }
    ],
    "sg:phone":"+1 415 362 1792",
    "sg:postcode":"94108",
    "sg:province":"CA",
    "sg:tags":[
        "lounge",
        "cocktail"
    ],
    "wof:name":"Buddha Lounge",
    "wof:placetype":"venue"
},
  "geometry": {"coordinates":[-122.406565,37.795592],"type":"Point"}
}