{
  "type": "Feature",
  "properties": {
    "iso:country":"US",
    "sg:address":"18003 Via la Cresta",
    "sg:city":"Chino Hills",
    "sg:classifiers":[
        {
            "category":"Building & Trades",
            "subcategory":"Landscaping Services",
            "type":"Services"
        }
    ],
    "sg:phone":"+1 909 606 9887",
    "sg:postcode":"91709",
    "sg:province":"CA",
    "wof:name":"Go Landscape Care",
    "wof:placetype":"venue"
},
  "geometry": {"coordinates":[-117.665651,33.928698],"type":"Point"}
}