{
  "type": "Feature",
  "properties": {
    "iso:country":"US",
    "sg:address":"52 Sunnybrae Center",
    "sg:city":"Arcata",
    "sg:classifiers":[
        {
            "category":"Personal",
            "subcategory":"Beauty Salon",
            "type":"Services"
        }
    ],
    "sg:phone":"+1 707 822 3884",
    "sg:postcode":"95521",
    "sg:province":"CA",
    "wof:name":"New Image Hair Salon",
    "wof:placetype":"venue"
},
  "geometry": {"coordinates":[-124.071883,40.857468],"type":"Point"}
}