{
  "type": "Feature",
  "properties": {
    "iso:country":"US",
    "sg:address":"2953 Loyola St",
    "sg:city":"Sacramento",
    "sg:classifiers":[
        {
            "category":"Home & Garden",
            "subcategory":"Furniture",
            "type":"Retail Goods"
        }
    ],
    "sg:phone":"+1 916 410 6836",
    "sg:postcode":"95826",
    "sg:province":"CA",
    "sg:tags":[
        "store"
    ],
    "wof:name":"Real Life Furniture",
    "wof:placetype":"venue"
},
  "geometry": {"coordinates":[-121.383352,38.552184],"type":"Point"}
}