{
  "type": "Feature",
  "properties": {
    "addr:full":"7835 Cll Juela La Jolla CA 92037",
    "addr:housenumber":"7835",
    "addr:postcode":"92037",
    "addr:street":"Cll Juela",
    "iso:country":"US",
    "sg:address":"7835 Cll Juela",
    "sg:city":"La Jolla",
    "sg:classifiers":[
        {
            "category":"Real Estate",
            "subcategory":"Real Estate Agent",
            "type":"Services"
        }
    ],
    "sg:phone":"+1 858 454 0101",
    "sg:postcode":"92037",
    "sg:province":"CA",
    "wof:name":"Robert J Harman Inc Realtors",
    "wof:placetype":"venue"
},
  "geometry": {"coordinates":[-117.25480399999999,32.849716],"type":"Point"}
}