{
  "type": "Feature",
  "properties": {
    "iso:country":"US",
    "sg:address":"124 N Sacramento St",
    "sg:city":"Lodi",
    "sg:classifiers":[
        {
            "category":"Autos & Motor Vehicles",
            "subcategory":"Fuel & Gas Station",
            "type":"Retail Goods"
        },
        {
            "category":"Building & Trades",
            "subcategory":"Plumbing",
            "type":"Services"
        },
        {
            "category":"Autos & Motor Vehicles",
            "subcategory":"Auto Supplies",
            "type":"Retail Goods"
        },
        {
            "category":"Retail",
            "subcategory":"Auto Repair",
            "type":"Services"
        }
    ],
    "sg:phone":"+1 209 333 6001",
    "sg:postcode":"95240",
    "sg:province":"CA",
    "sg:tags":[
        "radiators-repairing",
        "rebuilding",
        "radiator",
        "automotive",
        "sale",
        "accessory",
        "part",
        "automobile"
    ],
    "wof:name":"Alamo Radiator Service",
    "wof:placetype":"venue"
},
  "geometry": {"coordinates":[-121.272204,38.135644],"type":"Point"}
}