{
  "type": "Feature",
  "properties": {
    "iso:country":"US",
    "sg:address":"1190 S Main St",
    "sg:city":"Salinas",
    "sg:phone":"+1 831 758 0511",
    "sg:postcode":"93901",
    "sg:province":"CA",
    "sg:website":"http://www.smalleysroundup.com",
    "wof:name":"Smalley's Roundup",
    "wof:placetype":"venue"
},
  "geometry": {"coordinates":[-121.659431,36.657957],"type":"Point"}
}