{
  "type": "Feature",
  "properties": {
    "iso:country":"US",
    "sg:address":"3300 Webster St",
    "sg:city":"Oakland",
    "sg:classifiers":[
        {
            "category":"Health Services",
            "subcategory":"Doctor",
            "type":"Services"
        }
    ],
    "sg:phone":"+1 510 452 0060",
    "sg:postcode":"94609",
    "sg:province":"CA",
    "sg:tags":[
        "physician",
        "surgeon"
    ],
    "wof:name":"Webster Management",
    "wof:placetype":"venue"
},
  "geometry": {"coordinates":[-122.261953,37.822078],"type":"Point"}
}