{
  "type": "Feature",
  "properties": {
    "iso:country":"US",
    "sg:address":"5205 Traffic Way",
    "sg:city":"Atascadero",
    "sg:classifiers":[
        {
            "category":"Wholesale",
            "subcategory":"Farm Supplies",
            "type":"Manufacturing & Wholesale Goods"
        }
    ],
    "sg:phone":"+1 805 466 1166",
    "sg:postcode":"93422",
    "sg:province":"CA",
    "sg:tags":[
        "feed"
    ],
    "wof:name":"Cal Ag",
    "wof:placetype":"venue"
},
  "geometry": {"coordinates":[-120.665594,35.499867],"type":"Point"}
}