{
  "type": "Feature",
  "properties": {
    "addr:full":"1415 Stafford St San Luis Obispo CA 93405",
    "addr:housenumber":"1415",
    "addr:postcode":"93405",
    "addr:street":"Stafford St",
    "iso:country":"US",
    "sg:address":"1415 Stafford St",
    "sg:city":"San Luis Obispo",
    "sg:classifiers":[
        {
            "category":"Real Estate",
            "subcategory":"Real Estate Operator",
            "type":"Services"
        }
    ],
    "sg:phone":"+1 805 543 2032",
    "sg:postcode":"93405",
    "sg:province":"CA",
    "sg:tags":[
        "apartment"
    ],
    "wof:name":"Stafford Garden Apartments",
    "wof:placetype":"venue"
},
  "geometry": {"coordinates":[-120.658929,35.291962],"type":"Point"}
}