{
  "type": "Feature",
  "properties": {
    "iso:country":"US",
    "sg:address":"271 Posada del Sol",
    "sg:city":"Novato",
    "sg:classifiers":[
        {
            "category":"Retail",
            "subcategory":"Animal Services",
            "type":"Services"
        }
    ],
    "sg:phone":"+1 415 883 1699",
    "sg:postcode":"94949",
    "sg:province":"CA",
    "sg:tags":[
        "pet",
        "boarding",
        "sitting"
    ],
    "wof:name":"Kitty Sitting",
    "wof:placetype":"venue"
},
  "geometry": {"coordinates":[-122.532391,38.059238],"type":"Point"}
}