{
  "type": "Feature",
  "properties": {
    "addr:full":"3502 Hawkhaven Dr Rocklin CA 95765",
    "addr:housenumber":"3502",
    "addr:postcode":"95765",
    "addr:street":"Hawkhaven Dr",
    "iso:country":"US",
    "sg:address":"3502 Hawkhaven Dr",
    "sg:city":"Rocklin",
    "sg:classifiers":[
        {
            "category":"Personal",
            "type":"Services"
        }
    ],
    "sg:phone":"+1 916 435 8477",
    "sg:postcode":"95765",
    "sg:province":"CA",
    "sg:tags":[
        "consultant",
        "planning",
        "wedding"
    ],
    "wof:name":"Victorian Rose Of Biggs",
    "wof:placetype":"venue"
},
  "geometry": {"coordinates":[-121.247371,38.808581],"type":"Point"}
}