{
  "type": "Feature",
  "properties": {
    "addr:full":"1228 S Hayworth Ave. Los Angeles CA 90035",
    "addr:housenumber":"1228",
    "addr:postcode":"90035",
    "addr:street":"S Hayworth Ave.",
    "iso:country":"US",
    "sg:address":"1228 S Hayworth Ave.",
    "sg:city":"Los Angeles",
    "sg:classifiers":[
        {
            "category":"Professional",
            "subcategory":"Advertising",
            "type":"Services"
        }
    ],
    "sg:phone":"+1 510 457 8809",
    "sg:postcode":"90035",
    "sg:province":"CA",
    "sg:tags":[
        "marketing"
    ],
    "sg:website":"www.herenowcommunications.com",
    "wof:name":"Here Now Communications",
    "wof:placetype":"venue"
},
  "geometry": {"coordinates":[-118.36743300000001,34.052759],"type":"Point"}
}