{
  "type": "Feature",
  "properties": {
    "addr:full":"21115 E Benbow St Covina CA 91724",
    "addr:housenumber":"21115",
    "addr:postcode":"91724",
    "addr:street":"E Benbow St",
    "iso:country":"US",
    "sg:address":"21115 E Benbow St",
    "sg:city":"Covina",
    "sg:classifiers":[
        {
            "category":"Building & Trades",
            "subcategory":"Construction",
            "type":"Services"
        }
    ],
    "sg:phone":"+1 626 966 7640",
    "sg:postcode":"91724",
    "sg:province":"CA",
    "sg:tags":[
        "contractor",
        "mechanical"
    ],
    "wof:name":"Bonillas Mechanical Inc.",
    "wof:placetype":"venue"
},
  "geometry": {"coordinates":[-117.844116,34.09654],"type":"Point"}
}