{
  "type": "Feature",
  "properties": {
    "addr:full":"2343 Fillmore St San Francisco CA 94115",
    "addr:housenumber":"2343",
    "addr:postcode":"94115",
    "addr:street":"Fillmore St",
    "iso:country":"US",
    "sg:address":"2343 Fillmore St",
    "sg:city":"San Francisco",
    "sg:classifiers":[
        {
            "category":"Retail",
            "subcategory":"Veterinary Services",
            "type":"Services"
        }
    ],
    "sg:phone":"+1 415 563 6700",
    "sg:postcode":"94115",
    "sg:province":"CA",
    "sg:tags":[
        "animal",
        "sitting",
        "pet",
        "hospital",
        "membership",
        "boarding/pet"
    ],
    "sg:website":"www.petsunlimited.org",
    "wof:name":"Pets Unlimited",
    "wof:placetype":"venue"
},
  "geometry": {"coordinates":[-122.434625,37.791284],"type":"Point"}
}