{
  "type": "Feature",
  "properties": {
    "addr:full":"1253 Balboa Ct Sunnyvale CA 94086",
    "addr:housenumber":"1253",
    "addr:postcode":"94086",
    "addr:street":"Balboa Ct",
    "iso:country":"US",
    "sg:address":"1253 Balboa Ct",
    "sg:city":"Sunnyvale",
    "sg:classifiers":[
        {
            "category":"Health Services",
            "subcategory":"Clinic",
            "type":"Services"
        }
    ],
    "sg:phone":"+1 408 497 1672",
    "sg:postcode":"94086",
    "sg:province":"CA",
    "sg:tags":[
        "counseling",
        "mental"
    ],
    "sg:website":"www.hypnotherapyoasis.com",
    "wof:name":"Hypnotherapy Oasis",
    "wof:placetype":"venue"
},
  "geometry": {"coordinates":[-121.894037,37.255176],"type":"Point"}
}