{
  "type": "Feature",
  "properties": {
    "iso:country":"US",
    "sg:address":"833 G St",
    "sg:city":"San Diego",
    "sg:classifiers":[
        {
            "category":"Retail",
            "subcategory":"Photofinishing",
            "type":"Services"
        }
    ],
    "sg:phone":"+1 619 239 0311",
    "sg:postcode":"92101",
    "sg:province":"CA",
    "sg:tags":[
        "photo",
        "finishing"
    ],
    "wof:name":"Photosmith",
    "wof:placetype":"venue"
},
  "geometry": {"coordinates":[-117.156777,32.712517],"type":"Point"}
}