{
  "type": "Feature",
  "properties": {
    "addr:full":"1060 E Foothill Blvd Upland CA 91786",
    "addr:housenumber":"1060",
    "addr:postcode":"91786",
    "addr:street":"E Foothill Blvd",
    "iso:country":"US",
    "sg:address":"1060 E Foothill Blvd",
    "sg:city":"Upland",
    "sg:classifiers":[
        {
            "category":"Health Services",
            "subcategory":"Doctor",
            "type":"Services"
        }
    ],
    "sg:phone":"+1 909 985 0699",
    "sg:postcode":"91786",
    "sg:province":"CA",
    "sg:tags":[
        "physician",
        "surgeon"
    ],
    "wof:name":"Dr Lai's Medical Clinic",
    "wof:placetype":"venue"
},
  "geometry": {"coordinates":[-117.63776900000001,34.106982],"type":"Point"}
}