{
  "type": "Feature",
  "properties": {
    "iso:country":"US",
    "sg:address":"78 Paul Dr",
    "sg:city":"San Rafael",
    "sg:classifiers":[
        {
            "category":"Insurance",
            "subcategory":"Hazard Insurance",
            "type":"Services"
        }
    ],
    "sg:phone":"+1 415 472 6565",
    "sg:postcode":"94903",
    "sg:province":"CA",
    "sg:tags":[
        "profit",
        "sharing",
        "pension",
        "plan"
    ],
    "wof:name":"Social Profit Network",
    "wof:placetype":"venue"
},
  "geometry": {"coordinates":[-122.53751099999999,38.015504],"type":"Point"}
}