{
  "type": "Feature",
  "properties": {
    "addr:full":"774 36th St Richmond CA 94805",
    "addr:housenumber":"774",
    "addr:postcode":"94805",
    "addr:street":"36Th St",
    "iso:country":"US",
    "sg:address":"774 36th St",
    "sg:city":"Richmond",
    "sg:classifiers":[
        {
            "category":"Professional",
            "subcategory":"Accounting & Tax Preparation",
            "type":"Services"
        }
    ],
    "sg:phone":"+1 510 215 0128",
    "sg:postcode":"94805",
    "sg:province":"CA",
    "sg:tags":[
        "consultant"
    ],
    "wof:name":"Soriano Bookkeeping Tax Svc",
    "wof:placetype":"venue"
},
  "geometry": {"coordinates":[-122.33286,37.943379],"type":"Point"}
}