{
  "type": "Feature",
  "properties": {
    "iso:country":"US",
    "sg:address":"20709 Golden Springs Dr",
    "sg:city":"Walnut",
    "sg:classifiers":[
        {
            "category":"Shopping",
            "subcategory":"Pharmacy",
            "type":"Retail Goods"
        }
    ],
    "sg:phone":"+1 909 594 9555",
    "sg:postcode":"91765",
    "sg:province":"CA",
    "sg:tags":[
        "pharmaceutical",
        "consultant"
    ],
    "wof:name":"Pharmanalysis",
    "wof:placetype":"venue"
},
  "geometry": {"coordinates":[-117.85241499999999,33.997797],"type":"Point"}
}