{
  "type": "Feature",
  "properties": {
    "iso:country":"US",
    "sg:address":"12420 S Chestnut Ave",
    "sg:city":"Fresno",
    "sg:phone":"+1 559 834 5684",
    "sg:postcode":"93725",
    "sg:province":"CA",
    "sg:tags":[
        "vegetable",
        "farm"
    ],
    "wof:name":"Medina Growers",
    "wof:placetype":"venue"
},
  "geometry": {"coordinates":[-119.736921,36.560388],"type":"Point"}
}