{
  "type": "Feature",
  "properties": {
    "addr:full":"2400 Van Ness Ave San Francisco CA 94109",
    "addr:housenumber":"2400",
    "addr:postcode":"94109",
    "addr:street":"Van Ness Ave",
    "iso:country":"US",
    "sg:address":"2400 Van Ness Ave",
    "sg:city":"San Francisco",
    "sg:classifiers":[
        {
            "category":"Professional",
            "subcategory":"Art Services",
            "type":"Services"
        }
    ],
    "sg:phone":"+1 415 341 6531",
    "sg:postcode":"94109",
    "sg:province":"CA",
    "sg:tags":[
        "photographer"
    ],
    "sg:website":"www.xof711.com",
    "wof:name":"Xof711 Photography",
    "wof:placetype":"venue"
},
  "geometry": {"coordinates":[-122.42339800000001,37.797827],"type":"Point"}
}