{
  "type": "Feature",
  "properties": {
    "iso:country":"US",
    "sg:address":"5493 Carlson Dr Ste E",
    "sg:city":"Sacramento",
    "sg:classifiers":[
        {
            "category":"Shopping",
            "subcategory":"Hobbies, Toys, & Games",
            "type":"Retail Goods"
        },
        {
            "category":"Coffee & Tea",
            "type":"Food & Drink"
        }
    ],
    "sg:phone":"+1 916 476 3019",
    "sg:postcode":"95819",
    "sg:province":"CA",
    "sg:tags":[
        "toy",
        "store"
    ],
    "sg:website":"www.thewizardspond.com",
    "wof:name":"The Wizard's Pond",
    "wof:placetype":"venue"
},
  "geometry": {"coordinates":[-121.432373,38.572129],"type":"Point"}
}