{
  "type": "Feature",
  "properties": {
    "addr:full":"1711 S Broadway Santa Maria CA 93454",
    "addr:housenumber":"1711",
    "addr:postcode":"93454",
    "addr:street":"S Broadway",
    "iso:country":"US",
    "sg:address":"1711 S Broadway",
    "sg:city":"Santa Maria",
    "sg:classifiers":[
        {
            "category":"Shopping",
            "subcategory":"Clothing, Apparel, & Fashions",
            "type":"Retail Goods"
        }
    ],
    "sg:phone":"+1 805 922 9195",
    "sg:postcode":"93454",
    "sg:province":"CA",
    "sg:tags":[
        "infant",
        "wear"
    ],
    "wof:name":"Johnson For Children",
    "wof:placetype":"venue"
},
  "geometry": {"coordinates":[-120.436189,34.929448],"type":"Point"}
}