{
  "type": "Feature",
  "properties": {
    "addr:full":"1161 N Anaheim Blvd Anaheim CA 92801",
    "addr:housenumber":"1161",
    "addr:postcode":"92801",
    "addr:street":"N Anaheim Blvd",
    "iso:country":"US",
    "sg:address":"1161 N Anaheim Blvd",
    "sg:city":"Anaheim",
    "sg:classifiers":[
        {
            "category":"Building & Trades",
            "subcategory":"Plumbing",
            "type":"Services"
        }
    ],
    "sg:phone":"+1 714 808 8541",
    "sg:postcode":"92801",
    "sg:province":"CA",
    "wof:name":"Poes Quality Plumbing",
    "wof:placetype":"venue"
},
  "geometry": {"coordinates":[-117.91999800000001,33.8503],"type":"Point"}
}