{
  "type": "Feature",
  "properties": {
    "iso:country":"US",
    "sg:address":"1313 Cutting Blvd",
    "sg:city":"Richmond",
    "sg:classifiers":[
        {
            "category":"Health Services",
            "subcategory":"Doctor",
            "type":"Services"
        }
    ],
    "sg:phone":"+1 510 232 0874",
    "sg:postcode":"94804",
    "sg:province":"CA",
    "sg:tags":[
        "medicine",
        "physician",
        "addiction",
        "surgeons"
    ],
    "wof:name":"Cdp Primary Care",
    "wof:placetype":"venue"
},
  "geometry": {"coordinates":[-122.356804,37.925208],"type":"Point"}
}