{
  "type": "Feature",
  "properties": {
    "iso:country":"US",
    "sg:address":"4030 Welltech Way",
    "sg:city":"Bakersfield",
    "sg:classifiers":[
        {
            "category":"Building & Trades",
            "subcategory":"Construction",
            "type":"Services"
        }
    ],
    "sg:phone":"+1 661 587 8744",
    "sg:postcode":"93308",
    "sg:province":"CA",
    "sg:tags":[
        "general",
        "contractor"
    ],
    "wof:name":"Dennis Hyde Construction Inc",
    "wof:placetype":"venue"
},
  "geometry": {"coordinates":[-119.075822,35.396813],"type":"Point"}
}