{
  "type": "Feature",
  "properties": {
    "iso:country":"US",
    "sg:address":"2082 Walsh Ave",
    "sg:city":"Santa Clara",
    "sg:classifiers":[
        {
            "category":"Shopping",
            "subcategory":"Computers & Home Electronics",
            "type":"Retail Goods"
        }
    ],
    "sg:phone":"+1 408 982 9933",
    "sg:postcode":"95050",
    "sg:province":"CA",
    "sg:tags":[
        "software"
    ],
    "sg:website":"www.itdynamics.net",
    "wof:name":"I T Dynamics Inc",
    "wof:placetype":"venue"
},
  "geometry": {"coordinates":[-121.96088899999999,37.369392],"type":"Point"}
}