{
  "type": "Feature",
  "properties": {
    "iso:country":"US",
    "sg:address":"Kinross & Westwood Blvd",
    "sg:city":"Westwood",
    "sg:classifiers":[
        {
            "category":"Communications",
            "subcategory":"Newspaper",
            "type":"Services"
        }
    ],
    "sg:postcode":"96137",
    "sg:province":"CA",
    "sg:tags":[
        "magazine"
    ],
    "wof:name":"Westwood Village News Stand",
    "wof:placetype":"venue"
},
  "geometry": {"coordinates":[-118.445331,34.060749],"type":"Point"}
}