{
  "type": "Feature",
  "properties": {
    "addr:full":"1117 Stone Oak Dr Manteca CA 95336",
    "addr:housenumber":"1117",
    "addr:postcode":"95336",
    "addr:street":"Stone Oak Dr",
    "iso:country":"US",
    "sg:address":"1117 Stone Oak Dr",
    "sg:city":"Manteca",
    "sg:classifiers":[
        {
            "category":"Banks & Credit Unions",
            "subcategory":"Bank",
            "type":"Services"
        }
    ],
    "sg:phone":"+1 209 824 1586",
    "sg:postcode":"95336",
    "sg:province":"CA",
    "sg:tags":[
        "national",
        "commercial"
    ],
    "wof:name":"Guy Atm",
    "wof:placetype":"venue"
},
  "geometry": {"coordinates":[-121.189099,37.813033],"type":"Point"}
}