{
  "type": "Feature",
  "properties": {
    "iso:country":"US",
    "sg:address":"3075 Citrus Cir",
    "sg:city":"Walnut Creek",
    "sg:classifiers":[
        {
            "category":"Shopping",
            "subcategory":"Mobile Phones",
            "type":"Retail Goods"
        }
    ],
    "sg:phone":"+1 925 274 1075",
    "sg:postcode":"94598",
    "sg:province":"CA",
    "sg:website":"www.gowireless.net",
    "wof:name":"Go Wireless",
    "wof:placetype":"venue"
},
  "geometry": {"coordinates":[-122.356703,37.929534],"type":"Point"}
}