{
  "type": "Feature",
  "properties": {
    "addr:full":"2946 W 7th St Los Angeles CA 90005",
    "addr:housenumber":"2946",
    "addr:postcode":"90005",
    "addr:street":"W 7Th St",
    "iso:country":"US",
    "sg:address":"2946 W 7th St",
    "sg:city":"Los Angeles",
    "sg:classifiers":[
        {
            "category":"Shopping",
            "subcategory":"Gifts & Souvenirs",
            "type":"Retail Goods"
        }
    ],
    "sg:phone":"+1 213 386 7048",
    "sg:postcode":"90005",
    "sg:province":"CA",
    "sg:tags":[
        "shop"
    ],
    "wof:name":"Kimode USA",
    "wof:placetype":"venue"
},
  "geometry": {"coordinates":[-118.289046,34.059706],"type":"Point"}
}