{
  "type": "Feature",
  "properties": {
    "addr:full":"300 Richards Blvd Sacramento CA 95811",
    "addr:housenumber":"300",
    "addr:postcode":"95811",
    "addr:street":"Richards Blvd",
    "iso:country":"US",
    "sg:address":"300 Richards Blvd",
    "sg:city":"Sacramento",
    "sg:classifiers":[
        {
            "category":"Government",
            "subcategory":"Office",
            "type":"Public Place"
        }
    ],
    "sg:phone":"+1 916 808 4517",
    "sg:postcode":"95811",
    "sg:province":"CA",
    "sg:tags":[
        "township",
        "government-city",
        "village"
    ],
    "wof:name":"City of Sacramento Central Command Police Facility",
    "wof:placetype":"venue"
},
  "geometry": {"coordinates":[-121.50005299999999,38.597229],"type":"Point"}
}