{
  "type": "Feature",
  "properties": {
    "addr:full":"1819 W 6th St Los Angeles CA 90057",
    "addr:housenumber":"1819",
    "addr:postcode":"90057",
    "addr:street":"W 6Th St",
    "iso:country":"US",
    "sg:address":"1819 W 6th St",
    "sg:city":"Los Angeles",
    "sg:classifiers":[
        {
            "category":"Freight",
            "type":"Transportation"
        }
    ],
    "sg:phone":"+1 213 484 8440",
    "sg:postcode":"90057",
    "sg:province":"CA",
    "wof:name":"Jutiapa",
    "wof:placetype":"venue"
},
  "geometry": {"coordinates":[-118.272239,34.058438],"type":"Point"}
}