{
  "type": "Feature",
  "properties": {
    "iso:country":"US",
    "sg:address":"2310 Tienda Dr",
    "sg:city":"Lodi",
    "sg:classifiers":[
        {
            "category":"Shopping",
            "subcategory":"Gifts & Souvenirs",
            "type":"Retail Goods"
        }
    ],
    "sg:phone":"+1 209 333 1310",
    "sg:postcode":"95242",
    "sg:province":"CA",
    "sg:tags":[
        "party",
        "supply"
    ],
    "wof:name":"Arthur's Party World",
    "wof:placetype":"venue"
},
  "geometry": {"coordinates":[-121.301656,38.116932],"type":"Point"}
}