{
  "type": "Feature",
  "properties": {
    "iso:country":"US",
    "sg:address":"609 N Long Beach Blvd",
    "sg:city":"Compton",
    "sg:classifiers":[
        {
            "category":"Professional",
            "subcategory":"Management & Consulting",
            "type":"Services"
        }
    ],
    "sg:phone":"+1 310 886 0356",
    "sg:postcode":"90221",
    "sg:province":"CA",
    "sg:tags":[
        "retail",
        "direct",
        "sales"
    ],
    "wof:name":"K Beauty Supply & Water",
    "wof:placetype":"venue"
},
  "geometry": {"coordinates":[-118.208319,33.90028],"type":"Point"}
}