{
  "type": "Feature",
  "properties": {
    "iso:country":"US",
    "sg:address":"9333 Viking Pl Ste B",
    "sg:city":"Roseville",
    "sg:classifiers":[
        {
            "category":"Manufacturing",
            "subcategory":"Wood Products",
            "type":"Manufacturing & Wholesale Goods"
        },
        {
            "category":"Building & Trades",
            "subcategory":"Construction",
            "type":"Services"
        },
        {
            "category":"Manufacturing",
            "subcategory":"Building Materials",
            "type":"Manufacturing & Wholesale Goods"
        }
    ],
    "sg:phone":"+1 916 771 2006",
    "sg:postcode":"95747",
    "sg:province":"CA",
    "sg:tags":[
        "cabinetmakers-commercial",
        "industrial",
        "maker",
        "cabinet"
    ],
    "wof:name":"Pedersen Woodcraft",
    "wof:placetype":"venue"
},
  "geometry": {"coordinates":[-121.32110900000001,38.730343],"type":"Point"}
}