{
  "type": "Feature",
  "properties": {
    "addr:full":"2489 Gravenstein Hwy S Sebastopol CA 95472",
    "addr:housenumber":"2489",
    "addr:postcode":"95472",
    "addr:street":"Gravenstein Hwy S",
    "iso:country":"US",
    "sg:address":"2489 Gravenstein Hwy S",
    "sg:city":"Sebastopol",
    "sg:classifiers":[
        {
            "category":"Mining & Drilling",
            "type":"Manufacturing & Wholesale Goods"
        }
    ],
    "sg:phone":"+1 707 823 4447",
    "sg:postcode":"95472",
    "sg:province":"CA",
    "sg:tags":[
        "construction"
    ],
    "wof:name":"Connick Sand & Gravel Trucking",
    "wof:placetype":"venue"
},
  "geometry": {"coordinates":[-122.79680999999999,38.378486],"type":"Point"}
}