{
  "type": "Feature",
  "properties": {
    "addr:full":"11095 Flintkote Ave San Diego CA 92121",
    "addr:housenumber":"11095",
    "addr:postcode":"92121",
    "addr:street":"Flintkote Ave",
    "iso:country":"US",
    "sg:address":"11095 Flintkote Ave",
    "sg:city":"San Diego",
    "sg:classifiers":[
        {
            "category":"Wholesale",
            "subcategory":"Drugs",
            "type":"Manufacturing & Wholesale Goods"
        }
    ],
    "sg:phone":"+1 858 558 4880",
    "sg:postcode":"92121",
    "sg:province":"CA",
    "sg:tags":[
        "pharmaceutical",
        "product"
    ],
    "wof:name":"Priority Pharmaceuticals",
    "wof:placetype":"venue"
},
  "geometry": {"coordinates":[-117.230931,32.902939],"type":"Point"}
}