{
  "type": "Feature",
  "properties": {
    "addr:full":"1731 University Ave San Diego CA 92103",
    "addr:housenumber":"1731",
    "addr:postcode":"92103",
    "addr:street":"University Ave",
    "iso:country":"US",
    "sg:address":"1731 University Ave",
    "sg:city":"San Diego",
    "sg:classifiers":[
        {
            "category":"Restaurant",
            "type":"Food & Drink"
        }
    ],
    "sg:phone":"+1 619 269 8038",
    "sg:postcode":"92103",
    "sg:province":"CA",
    "sg:tags":[
        "traditional",
        "american",
        "creperies",
        "brunch",
        "breakfast"
    ],
    "sg:website":"www.babbogrande.com",
    "wof:name":"Babbo Grande",
    "wof:placetype":"venue"
},
  "geometry": {"coordinates":[-117.14761900000001,32.748121],"type":"Point"}
}