{
  "type": "Feature",
  "properties": {
    "addr:full":"6048 College Ave Oakland CA 94618",
    "addr:housenumber":"6048",
    "addr:postcode":"94618",
    "addr:street":"College Ave",
    "iso:country":"US",
    "sg:address":"6048 College Ave",
    "sg:city":"Oakland",
    "sg:classifiers":[
        {
            "category":"Personal",
            "type":"Services"
        },
        {
            "category":"Restaurant",
            "type":"Food & Drink"
        }
    ],
    "sg:phone":"+1 510 655 3298",
    "sg:postcode":"94618",
    "sg:province":"CA",
    "sg:tags":[
        "burmese",
        "chinese"
    ],
    "sg:website":"www.nanyangrockridge.com/",
    "wof:name":"Nan Yang",
    "wof:placetype":"venue"
},
  "geometry": {"coordinates":[-122.25188799999999,37.84905],"type":"Point"}
}