{
  "type": "Feature",
  "properties": {
    "iso:country":"US",
    "sg:address":"5962 S Vermont Ave",
    "sg:city":"Los Angeles",
    "sg:classifiers":[
        {
            "category":"Shopping",
            "type":"Retail Goods"
        }
    ],
    "sg:phone":"+1 323 758 4585",
    "sg:postcode":"90044",
    "sg:province":"CA",
    "sg:tags":[
        "merchandise"
    ],
    "wof:name":"R & M Cellular Accessories",
    "wof:placetype":"venue"
},
  "geometry": {"coordinates":[-118.291404,33.985939],"type":"Point"}
}