{
  "type": "Feature",
  "properties": {
    "addr:full":"1107 S Alvarado St Los Angeles CA 90006",
    "addr:housenumber":"1107",
    "addr:postcode":"90006",
    "addr:street":"S Alvarado St",
    "iso:country":"US",
    "sg:address":"1107 S Alvarado St",
    "sg:city":"Los Angeles",
    "sg:classifiers":[
        {
            "category":"Professional",
            "subcategory":"Detective & Security Services",
            "type":"Services"
        }
    ],
    "sg:phone":"+1 213 384 2018",
    "sg:postcode":"90006",
    "sg:province":"CA",
    "sg:tags":[
        "guard",
        "patrol"
    ],
    "wof:name":"Twins Security Co",
    "wof:placetype":"venue"
},
  "geometry": {"coordinates":[-118.281736,34.04891],"type":"Point"}
}