{
  "type": "Feature",
  "properties": {
    "iso:country":"US",
    "sg:address":"13020 Hadley St",
    "sg:city":"Whittier",
    "sg:classifiers":[
        {
            "category":"Social Services",
            "type":"Services"
        }
    ],
    "sg:phone":"+1 562 693 6559",
    "sg:postcode":"90601",
    "sg:province":"CA",
    "sg:tags":[
        "counselor",
        "marriage",
        "family"
    ],
    "wof:name":"Kelley Holtom & Assoc",
    "wof:placetype":"venue"
},
  "geometry": {"coordinates":[-118.036901,33.982658],"type":"Point"}
}