{
  "type": "Feature",
  "properties": {
    "iso:country":"US",
    "sg:address":"5705 Marconi Ave Ste A",
    "sg:city":"Carmichael",
    "sg:classifiers":[
        {
            "category":"Professional",
            "type":"Services"
        },
        {
            "category":"Professional",
            "subcategory":"Advertising",
            "type":"Services"
        },
        {
            "category":"Professional",
            "subcategory":"Printing & Photocopies",
            "type":"Services"
        }
    ],
    "sg:phone":"+1 916 488 7663",
    "sg:postcode":"95608",
    "sg:province":"CA",
    "sg:tags":[
        "sample",
        "product",
        "service-circular",
        "fair",
        "trophies",
        "trade",
        "distributing",
        "exposition",
        "advertising-promotional",
        "medal",
        "plaque",
        "shows"
    ],
    "sg:website":"http://www.justcallideas.com",
    "wof:name":"Just Call Inc",
    "wof:placetype":"venue"
},
  "geometry": {"coordinates":[-121.330753,38.61718],"type":"Point"}
}