{
  "type": "Feature",
  "properties": {
    "iso:country":"US",
    "sg:address":"24995 Ben Taylor Rd",
    "sg:city":"Colfax",
    "sg:classifiers":[
        {
            "category":"Education",
            "subcategory":"School",
            "type":"Public Place"
        }
    ],
    "sg:phone":"+1 530 346 7101",
    "sg:postcode":"95713",
    "sg:province":"CA",
    "wof:name":"49er ROP Auto Shop",
    "wof:placetype":"venue"
},
  "geometry": {"coordinates":[-120.963185,39.108355],"type":"Point"}
}