{
  "type": "Feature",
  "properties": {
    "addr:full":"2613 S Fairview St Santa Ana CA 92704",
    "addr:housenumber":"2613",
    "addr:postcode":"92704",
    "addr:street":"S Fairview St",
    "iso:country":"US",
    "sg:address":"2613 S Fairview St",
    "sg:city":"Santa Ana",
    "sg:classifiers":[
        {
            "category":"Real Estate",
            "subcategory":"Real Estate Operator",
            "type":"Services"
        }
    ],
    "sg:phone":"+1 714 556 0037",
    "sg:postcode":"92704",
    "sg:province":"CA",
    "sg:tags":[
        "apartment"
    ],
    "wof:name":"Fairview Green Apartments",
    "wof:placetype":"venue"
},
  "geometry": {"coordinates":[-117.90799699999999,33.712799],"type":"Point"}
}