{
  "type": "Feature",
  "properties": {
    "iso:country":"US",
    "sg:address":"1305 W Calle de Oro",
    "sg:city":"Calexico",
    "sg:classifiers":[
        {
            "category":"Shopping",
            "subcategory":"Shoes",
            "type":"Retail Goods"
        }
    ],
    "sg:phone":"+1 760 768 0221",
    "sg:postcode":"92231",
    "sg:province":"CA",
    "sg:tags":[
        "store"
    ],
    "wof:name":"Zapateria Isabel",
    "wof:placetype":"venue"
},
  "geometry": {"coordinates":[-115.49035600000001,32.68391],"type":"Point"}
}