{
  "type": "Feature",
  "properties": {
    "iso:country":"US",
    "sg:address":"408 Raymond Ave",
    "sg:city":"Glendale",
    "sg:classifiers":[
        {
            "category":"Personal",
            "subcategory":"Beauty Salon",
            "type":"Services"
        }
    ],
    "sg:phone":"+1 818 688 1834",
    "sg:postcode":"91201",
    "sg:province":"CA",
    "sg:tags":[
        "hair"
    ],
    "sg:website":"www.hairextensionsburbank.com",
    "wof:name":"Elaine's Hair Extensions",
    "wof:placetype":"venue"
},
  "geometry": {"coordinates":[-118.29937700000001,34.163103],"type":"Point"}
}