{
  "type": "Feature",
  "properties": {
    "addr:full":"191 Sutter St San Francisco CA 94104",
    "addr:housenumber":"191",
    "addr:postcode":"94104",
    "addr:street":"Sutter St",
    "iso:country":"US",
    "sg:address":"191 Sutter St",
    "sg:city":"San Francisco",
    "sg:classifiers":[
        {
            "category":"Travel",
            "subcategory":"Hotels & Motels",
            "type":"Entertainment"
        }
    ],
    "sg:phone":"+1 415 781 3060",
    "sg:postcode":"94104",
    "sg:province":"CA",
    "sg:tags":[
        "operation",
        "drinking"
    ],
    "sg:website":"www.jdvhotels.com/hotels/galleri...",
    "wof:name":"Galleria Park Hotel",
    "wof:placetype":"venue"
},
  "geometry": {"coordinates":[-122.403724,37.789849],"type":"Point"}
}