{
  "type": "Feature",
  "properties": {
    "iso:country":"US",
    "sg:address":"4103 Pioneer Dr",
    "sg:city":"Bakersfield",
    "sg:classifiers":[
        {
            "category":"Building & Trades",
            "subcategory":"Landscaping Services",
            "type":"Services"
        }
    ],
    "sg:phone":"+1 661 366 5103",
    "sg:postcode":"93306",
    "sg:province":"CA",
    "wof:name":"Villas Gardening",
    "wof:placetype":"venue"
},
  "geometry": {"coordinates":[-118.938658,35.368681],"type":"Point"}
}