{
  "type": "Feature",
  "properties": {
    "iso:country":"US",
    "sg:address":"317 Mcnab Ct",
    "sg:city":"Fillmore",
    "sg:classifiers":[
        {
            "category":"Building & Trades",
            "subcategory":"Equipment Rental",
            "type":"Services"
        }
    ],
    "sg:phone":"+1 805 524 0650",
    "sg:postcode":"93015",
    "sg:province":"CA",
    "sg:tags":[
        "yard",
        "leasing",
        "store"
    ],
    "wof:name":"Ernco Equipment Rental",
    "wof:placetype":"venue"
},
  "geometry": {"coordinates":[-118.930323,34.396314],"type":"Point"}
}