{
  "type": "Feature",
  "properties": {
    "iso:country":"US",
    "sg:address":"1875 Newport Blvd",
    "sg:city":"Costa Mesa",
    "sg:classifiers":[
        {
            "category":"Restaurant",
            "type":"Food & Drink"
        }
    ],
    "sg:phone":"+1 949 515 1617",
    "sg:postcode":"92627",
    "sg:province":"CA",
    "sg:tags":[
        "shop",
        "coffee"
    ],
    "wof:name":"Kelly's Coffee & Fudge",
    "wof:placetype":"venue"
},
  "geometry": {"coordinates":[-117.917827,33.642055],"type":"Point"}
}