{
  "type": "Feature",
  "properties": {
    "addr:full":"407 E Florence Avenue Los Angeles CA 90003",
    "addr:housenumber":"407",
    "addr:postcode":"90003",
    "addr:street":"E Florence Avenue",
    "iso:country":"US",
    "sg:address":"407 E Florence Avenue",
    "sg:city":"Los Angeles",
    "sg:classifiers":[
        {
            "category":"Taxi",
            "type":"Transportation"
        }
    ],
    "sg:phone":"+1 323 564 2020",
    "sg:postcode":"90003",
    "sg:province":"CA",
    "wof:name":"High Class Yellow Cab",
    "wof:placetype":"venue"
},
  "geometry": {"coordinates":[-118.266626,33.974829],"type":"Point"}
}