{
  "type": "Feature",
  "properties": {
    "iso:country":"US",
    "sg:address":"2781 S Diamond Bar Blvd",
    "sg:city":"Diamond Bar",
    "sg:classifiers":[
        {
            "category":"Food & Beverages",
            "subcategory":"Specialty",
            "type":"Retail Goods"
        }
    ],
    "sg:phone":"+1 909 468 1952",
    "sg:postcode":"91765",
    "sg:province":"CA",
    "sg:tags":[
        "health",
        "diet"
    ],
    "wof:name":"GNC",
    "wof:placetype":"venue"
},
  "geometry": {"coordinates":[-117.837744,33.974132],"type":"Point"}
}