{
  "type": "Feature",
  "properties": {
    "iso:country":"US",
    "sg:address":"9155 Corona Rd",
    "sg:city":"Atascadero",
    "sg:classifiers":[
        {
            "category":"Wholesale",
            "subcategory":"Hardware",
            "type":"Manufacturing & Wholesale Goods"
        }
    ],
    "sg:phone":"+1 805 461 5144",
    "sg:postcode":"93422",
    "sg:province":"CA",
    "sg:tags":[
        "equipment",
        "gas"
    ],
    "wof:name":"SGS Inc",
    "wof:placetype":"venue"
},
  "geometry": {"coordinates":[-120.724545,35.501044],"type":"Point"}
}