{
  "type": "Feature",
  "properties": {
    "iso:country":"US",
    "sg:address":"1319 3rd Ave",
    "sg:city":"Chula Vista",
    "sg:classifiers":[
        {
            "category":"Shopping",
            "subcategory":"Department Store",
            "type":"Retail Goods"
        }
    ],
    "sg:phone":"+1 619 422 2797",
    "sg:postcode":"91911",
    "sg:province":"CA",
    "wof:name":"Factory 2-U",
    "wof:placetype":"venue"
},
  "geometry": {"coordinates":[-117.065863,32.605637],"type":"Point"}
}