{
  "type": "Feature",
  "properties": {
    "addr:full":"180 3rd St Point Reyes Sta CA 94956",
    "addr:housenumber":"180",
    "addr:postcode":"94956",
    "addr:street":"3Rd St;Reyes Sta",
    "iso:country":"US",
    "sg:address":"180 3rd St",
    "sg:city":"Point Reyes Sta",
    "sg:classifiers":[
        {
            "category":"Travel",
            "subcategory":"Hotels & Motels",
            "type":"Entertainment"
        }
    ],
    "sg:phone":"+1 415 663 8143",
    "sg:postcode":"94956",
    "sg:province":"CA",
    "sg:tags":[
        "breakfast",
        "accommodation",
        "bed"
    ],
    "wof:name":"Annie's Garden Cottage",
    "wof:placetype":"venue"
},
  "geometry": {"coordinates":[-122.80698,38.067463],"type":"Point"}
}