{
  "type": "Feature",
  "properties": {
    "addr:full":"1701 Arnold Industrial Way Concord CA 94520",
    "addr:housenumber":"1701",
    "addr:postcode":"94520",
    "addr:street":"Arnold Industrial Way",
    "iso:country":"US",
    "sg:address":"1701 Arnold Industrial Way",
    "sg:city":"Concord",
    "sg:classifiers":[
        {
            "category":"Home & Garden",
            "subcategory":"Furniture",
            "type":"Retail Goods"
        }
    ],
    "sg:phone":"+1 925 827 4466",
    "sg:postcode":"94520",
    "sg:province":"CA",
    "wof:name":"Scandinavian Designs",
    "wof:placetype":"venue"
},
  "geometry": {"coordinates":[-122.053192,38.002336],"type":"Point"}
}