{
  "type": "Feature",
  "properties": {
    "addr:full":"4811 Madison Ave Sacramento CA 95841",
    "addr:housenumber":"4811",
    "addr:postcode":"95841",
    "addr:street":"Madison Ave",
    "iso:country":"US",
    "sg:address":"4811 Madison Ave",
    "sg:city":"Sacramento",
    "sg:classifiers":[
        {
            "category":"Professional",
            "subcategory":"Advertising",
            "type":"Services"
        }
    ],
    "sg:phone":"+1 916 334 6500",
    "sg:postcode":"95841",
    "sg:province":"CA",
    "sg:tags":[
        "counselor"
    ],
    "sg:website":"www.syner-g.com",
    "wof:name":"Syner G Inc",
    "wof:placetype":"venue"
},
  "geometry": {"coordinates":[-121.353713,38.660922],"type":"Point"}
}