{
  "type": "Feature",
  "properties": {
    "iso:country":"US",
    "sg:address":"333 E 8th St",
    "sg:city":"Oakland",
    "sg:classifiers":[
        {
            "category":"Government",
            "subcategory":"Police Station",
            "type":"Public Place"
        }
    ],
    "sg:phone":"+1 510 465 3514",
    "sg:postcode":"94606",
    "sg:province":"CA",
    "sg:tags":[
        "protection"
    ],
    "wof:name":"Sheriffs Dept",
    "wof:placetype":"venue"
},
  "geometry": {"coordinates":[-122.260054,37.793204],"type":"Point"}
}