{
  "type": "Feature",
  "properties": {
    "iso:country":"US",
    "sg:address":"3691 San Gabriel River Pkwy",
    "sg:city":"Pico Rivera",
    "sg:classifiers":[
        {
            "category":"Manufacturing",
            "subcategory":"Tools & Machinery",
            "type":"Manufacturing & Wholesale Goods"
        }
    ],
    "sg:phone":"+1 562 699 1811",
    "sg:postcode":"90660",
    "sg:province":"CA",
    "sg:tags":[
        "industrial",
        "mfg"
    ],
    "wof:name":"C & C Machining Services",
    "wof:placetype":"venue"
},
  "geometry": {"coordinates":[-118.057677,34.014228],"type":"Point"}
}