{
  "type": "Feature",
  "properties": {
    "addr:full":"7921 San Miguel Canyon Rd Salinas CA 93907",
    "addr:housenumber":"7921",
    "addr:postcode":"93907",
    "addr:street":"San Miguel Canyon Rd",
    "iso:country":"US",
    "sg:address":"7921 San Miguel Canyon Rd",
    "sg:city":"Salinas",
    "sg:classifiers":[
        {
            "category":"Personal",
            "subcategory":"Shoe Repair & Shine",
            "type":"Services"
        }
    ],
    "sg:phone":"+1 831 663 5660",
    "sg:postcode":"93907",
    "sg:province":"CA",
    "sg:tags":[
        "repairing",
        "boot"
    ],
    "wof:name":"Cortez Shoe Repair",
    "wof:placetype":"venue"
},
  "geometry": {"coordinates":[-121.664402,36.799621],"type":"Point"}
}