{
  "type": "Feature",
  "properties": {
    "iso:country":"US",
    "sg:address":"171 N Washington St",
    "sg:city":"Sonora",
    "sg:classifiers":[
        {
            "category":"Manufacturing",
            "subcategory":"Printing",
            "type":"Manufacturing & Wholesale Goods"
        },
        {
            "category":"Wholesale",
            "subcategory":"Books, Periodicals, & Newspapers",
            "type":"Manufacturing & Wholesale Goods"
        }
    ],
    "sg:phone":"+1 209 536 1755",
    "sg:postcode":"95370",
    "sg:province":"CA",
    "sg:tags":[
        "magazines-distributors",
        "publishers-periodical"
    ],
    "wof:name":"Friends And Neighbors Magazine",
    "wof:placetype":"venue"
},
  "geometry": {"coordinates":[-120.38458,37.987546],"type":"Point"}
}