{
  "type": "Feature",
  "properties": {
    "iso:country":"US",
    "sg:address":"439 E Harrison St",
    "sg:city":"Corona",
    "sg:classifiers":[
        {
            "category":"Building & Trades",
            "subcategory":"Construction",
            "type":"Services"
        }
    ],
    "sg:phone":"+1 951 279 6231",
    "sg:postcode":"92879",
    "sg:province":"CA",
    "sg:tags":[
        "contractor"
    ],
    "wof:name":"S & Q Construction",
    "wof:placetype":"venue"
},
  "geometry": {"coordinates":[-117.560785,33.883481],"type":"Point"}
}