{
  "type": "Feature",
  "properties": {
    "iso:country":"US",
    "sg:address":"4876 Santa Monica Ave",
    "sg:city":"San Diego",
    "sg:classifiers":[
        {
            "category":"Freight",
            "type":"Transportation"
        }
    ],
    "sg:phone":"+1 619 222 4876",
    "sg:postcode":"92107",
    "sg:province":"CA",
    "sg:tags":[
        "shipping"
    ],
    "sg:website":"www.saffranpackaging.com/",
    "wof:name":"Saffran Packaging & Shipping",
    "wof:placetype":"venue"
},
  "geometry": {"coordinates":[-117.247958,32.746665],"type":"Point"}
}