{
  "type": "Feature",
  "properties": {
    "iso:country":"US",
    "sg:address":"12118 Firestone Blvd",
    "sg:city":"Norwalk",
    "sg:classifiers":[
        {
            "category":"Manufacturing",
            "subcategory":"Printing",
            "type":"Manufacturing & Wholesale Goods"
        }
    ],
    "sg:phone":"+1 562 863 0368",
    "sg:postcode":"90650",
    "sg:province":"CA",
    "sg:tags":[
        "printer",
        "commercial"
    ],
    "wof:name":"Luna's Printing",
    "wof:placetype":"venue"
},
  "geometry": {"coordinates":[-118.07435599999999,33.90871],"type":"Point"}
}