{
  "type": "Feature",
  "properties": {
    "addr:full":"2101 Iroula Way Tracy CA 95377",
    "addr:housenumber":"2101",
    "addr:postcode":"95377",
    "addr:street":"Iroula Way",
    "iso:country":"US",
    "sg:address":"2101 Iroula Way",
    "sg:city":"Tracy",
    "sg:classifiers":[
        {
            "category":"Building & Trades",
            "subcategory":"Landscaping Services",
            "type":"Services"
        }
    ],
    "sg:phone":"+1 209 839 8756",
    "sg:postcode":"95377",
    "sg:province":"CA",
    "wof:name":"Dhillons Landscape Services",
    "wof:placetype":"venue"
},
  "geometry": {"coordinates":[-121.455325,37.746643],"type":"Point"}
}