{
  "type": "Feature",
  "properties": {
    "addr:full":"3901 Beverly Blvd Los Angeles CA 90004",
    "addr:housenumber":"3901",
    "addr:postcode":"90004",
    "addr:street":"Beverly Blvd",
    "iso:country":"US",
    "sg:address":"3901 Beverly Blvd",
    "sg:city":"Los Angeles",
    "sg:classifiers":[
        {
            "category":"Retail",
            "subcategory":"Auto Repair",
            "type":"Services"
        }
    ],
    "sg:phone":"+1 323 667 9776",
    "sg:postcode":"90004",
    "sg:province":"CA",
    "sg:tags":[
        "automotive",
        "product",
        "petroleum"
    ],
    "wof:name":"10 Minute Oil & Gen Mechanic",
    "wof:placetype":"venue"
},
  "geometry": {"coordinates":[-118.294179,34.076316],"type":"Point"}
}