{
  "type": "Feature",
  "properties": {
    "iso:country":"US",
    "sg:address":"5715 Alton Parkway",
    "sg:city":"Irvine",
    "sg:classifiers":[
        {
            "category":"Shopping",
            "subcategory":"Stationery & Office Supplies",
            "type":"Retail Goods"
        }
    ],
    "sg:phone":"+1 949 653 1928",
    "sg:postcode":"92618",
    "sg:province":"CA",
    "sg:tags":[
        "equipment"
    ],
    "wof:name":"Office Depot",
    "wof:placetype":"venue"
},
  "geometry": {"coordinates":[-117.785427,33.668287],"type":"Point"}
}