{
  "type": "Feature",
  "properties": {
    "addr:full":"409 N Camden Dr Beverly Hills CA 90210",
    "addr:housenumber":"409",
    "addr:postcode":"90210",
    "addr:street":"N Camden Dr",
    "iso:country":"US",
    "sg:address":"409 N Camden Dr",
    "sg:city":"Beverly Hills",
    "sg:classifiers":[
        {
            "category":"Health Services",
            "subcategory":"Doctor",
            "type":"Services"
        }
    ],
    "sg:phone":"+1 310 550 8949",
    "sg:postcode":"90210",
    "sg:province":"CA",
    "sg:tags":[
        "physician",
        "surgeon"
    ],
    "wof:name":"Norman J Lachman MD",
    "wof:placetype":"venue"
},
  "geometry": {"coordinates":[-118.405272,34.0697],"type":"Point"}
}