{
  "type": "Feature",
  "properties": {
    "iso:country":"US",
    "sg:address":"3915 Thornhill Dr",
    "sg:city":"Sacramento",
    "sg:classifiers":[
        {
            "category":"Banks & Credit Unions",
            "subcategory":"Bank",
            "type":"Services"
        }
    ],
    "sg:phone":"+1 916 363 5229",
    "sg:postcode":"95826",
    "sg:province":"CA",
    "sg:tags":[
        "financing"
    ],
    "wof:name":"Choiceone Funding",
    "wof:placetype":"venue"
},
  "geometry": {"coordinates":[-121.363908,38.543443],"type":"Point"}
}