{
  "type": "Feature",
  "properties": {
    "addr:full":"1400 Marsten Rd Burlingame CA 94010",
    "addr:housenumber":"1400",
    "addr:postcode":"94010",
    "addr:street":"Marsten Rd",
    "iso:country":"US",
    "sg:address":"1400 Marsten Rd",
    "sg:city":"Burlingame",
    "sg:classifiers":[
        {
            "category":"Professional",
            "type":"Services"
        }
    ],
    "sg:phone":"+1 650 558 1980",
    "sg:postcode":"94010",
    "sg:province":"CA",
    "sg:tags":[
        "arts",
        "artist"
    ],
    "wof:name":"Nancy Call Torres Art Studio",
    "wof:placetype":"venue"
},
  "geometry": {"coordinates":[-122.365689,37.591453],"type":"Point"}
}