{
  "type": "Feature",
  "properties": {
    "addr:full":"1100 Alma St Menlo Park CA 94025",
    "addr:housenumber":"1100",
    "addr:postcode":"94025",
    "addr:street":"Alma St",
    "iso:country":"US",
    "sg:address":"1100 Alma St",
    "sg:city":"Menlo Park",
    "sg:classifiers":[
        {
            "category":"Professional",
            "type":"Services"
        }
    ],
    "sg:phone":"+1 650 327 7200",
    "sg:postcode":"94025",
    "sg:province":"CA",
    "sg:tags":[
        "establishment"
    ],
    "wof:name":"Standard Allied Corp",
    "wof:placetype":"venue"
},
  "geometry": {"coordinates":[-122.181541,37.454506],"type":"Point"}
}