{
  "type": "Feature",
  "properties": {
    "addr:full":"2929 Fulton Ave Sacramento CA 95821",
    "addr:housenumber":"2929",
    "addr:postcode":"95821",
    "addr:street":"Fulton Ave",
    "iso:country":"US",
    "sg:address":"2929 Fulton Ave",
    "sg:city":"Sacramento",
    "sg:classifiers":[
        {
            "category":"Professional",
            "type":"Services"
        }
    ],
    "sg:phone":"+1 916 971 1788",
    "sg:postcode":"95821",
    "sg:province":"CA",
    "sg:tags":[
        "establishment"
    ],
    "wof:name":"Discovery Towers",
    "wof:placetype":"venue"
},
  "geometry": {"coordinates":[-121.40148499999999,38.618635],"type":"Point"}
}