{
  "type": "Feature",
  "properties": {
    "addr:full":"917 West Las Tunas Dr San Gabriel CA 91775",
    "addr:housenumber":"917",
    "addr:postcode":"91775",
    "addr:street":"West Las Tunas Dr",
    "iso:country":"US",
    "sg:address":"917 West Las Tunas Dr",
    "sg:city":"San Gabriel",
    "sg:classifiers":[
        {
            "category":"Health Services",
            "subcategory":"Health Practitioner",
            "type":"Services"
        }
    ],
    "sg:phone":"+1 626 588 1686",
    "sg:postcode":"91775",
    "sg:province":"CA",
    "sg:tags":[
        "home",
        "care"
    ],
    "wof:name":"Grace Home Health Care",
    "wof:placetype":"venue"
},
  "geometry": {"coordinates":[-118.110871,34.102412],"type":"Point"}
}