{
  "type": "Feature",
  "properties": {
    "iso:country":"US",
    "sg:address":"1046 W West Covina Pkwy",
    "sg:city":"West Covina",
    "sg:classifiers":[
        {
            "category":"Professional",
            "subcategory":"Employment Agencies",
            "type":"Services"
        }
    ],
    "sg:phone":"+1 626 480 9121",
    "sg:postcode":"91790",
    "sg:province":"CA",
    "sg:tags":[
        "opportunity"
    ],
    "wof:name":"Volt Services Group",
    "wof:placetype":"venue"
},
  "geometry": {"coordinates":[-117.928647,34.0682],"type":"Point"}
}