{
  "type": "Feature",
  "properties": {
    "addr:full":"15355 Brookhurst Street Westminster CA 92683",
    "addr:housenumber":"15355",
    "addr:postcode":"92683",
    "addr:street":"Brookhurst Street",
    "iso:country":"US",
    "sg:address":"15355 Brookhurst Street",
    "sg:city":"Westminster",
    "sg:classifiers":[
        {
            "category":"Health Services",
            "subcategory":"Dentist",
            "type":"Services"
        }
    ],
    "sg:phone":"+1 714 531 5175",
    "sg:postcode":"92683",
    "sg:province":"CA",
    "wof:name":"Nguyen Thanh Ngoc DMD",
    "wof:placetype":"venue"
},
  "geometry": {"coordinates":[-117.954814,33.739433],"type":"Point"}
}