{
  "type": "Feature",
  "properties": {
    "iso:country":"US",
    "sg:address":"2268 Quimby Rd",
    "sg:city":"San Jose",
    "sg:classifiers":[
        {
            "category":"Real Estate",
            "subcategory":"Real Estate Agent",
            "type":"Services"
        }
    ],
    "sg:phone":"+1 408 532 2100",
    "sg:postcode":"95122",
    "sg:province":"CA",
    "wof:name":"Mili Realty Group",
    "wof:placetype":"venue"
},
  "geometry": {"coordinates":[-121.80979600000001,37.323448],"type":"Point"}
}