{
  "type": "Feature",
  "properties": {
    "iso:country":"US",
    "sg:address":"8241 Foothill Blvd",
    "sg:city":"Rancho Cucamonga",
    "sg:classifiers":[
        {
            "category":"Restaurant",
            "type":"Food & Drink"
        }
    ],
    "sg:phone":"+1 909 981 1003",
    "sg:postcode":"91730",
    "sg:province":"CA",
    "sg:tags":[
        "eating"
    ],
    "wof:name":"Vince's Spaghetti",
    "wof:placetype":"venue"
},
  "geometry": {"coordinates":[-117.626024,34.105901],"type":"Point"}
}