{
  "type": "Feature",
  "properties": {
    "addr:full":"408 Via Media Palos Vrds Ests CA 90274",
    "addr:housenumber":"408",
    "addr:postcode":"90274",
    "addr:street":"Via Media Palos Vrds Ests",
    "iso:country":"US",
    "sg:address":"408 Via Media",
    "sg:city":"Palos Vrds Ests",
    "sg:classifiers":[
        {
            "category":"Shopping",
            "type":"Retail Goods"
        },
        {
            "category":"Professional",
            "subcategory":"Business Services",
            "type":"Services"
        }
    ],
    "sg:phone":"+1 310 375 8834",
    "sg:postcode":"90274",
    "sg:province":"CA",
    "sg:tags":[
        "interior",
        "consultant",
        "design",
        "decorator",
        "merchandise"
    ],
    "wof:name":"B E Designers",
    "wof:placetype":"venue"
},
  "geometry": {"coordinates":[-118.39959,33.800298],"type":"Point"}
}