{
  "type": "Feature",
  "properties": {
    "iso:country":"US",
    "sg:address":"10251 Mast Blvd Suite B",
    "sg:city":"Santee",
    "sg:classifiers":[
        {
            "category":"Restaurant",
            "type":"Food & Drink"
        }
    ],
    "sg:phone":"+1 619 596 4852",
    "sg:postcode":"92071",
    "sg:province":"CA",
    "sg:tags":[
        "thai",
        "sushi",
        "bar",
        "japanese"
    ],
    "sg:website":"www.oishiisantee.com/",
    "wof:name":"Oishii Japanese-Thai Cuisine",
    "wof:placetype":"venue"
},
  "geometry": {"coordinates":[-116.976099,32.855051],"type":"Point"}
}