{
  "type": "Feature",
  "properties": {
    "iso:country":"US",
    "sg:address":"4314 Bridge St",
    "sg:city":"Cambria",
    "sg:classifiers":[
        {
            "category":"Travel",
            "subcategory":"Bed & Breakfast",
            "type":"Entertainment"
        }
    ],
    "sg:phone":"+1 805 927 7653",
    "sg:postcode":"93428",
    "sg:province":"CA",
    "sg:tags":[
        "hotel",
        "hostel"
    ],
    "sg:website":"www.bridgestreetinncambria.com",
    "wof:name":"Bridge Street Inn",
    "wof:placetype":"venue"
},
  "geometry": {"coordinates":[-121.08200100000001,35.565201],"type":"Point"}
}