{
  "type": "Feature",
  "properties": {
    "iso:country":"US",
    "sg:address":"17150 S Park Ln",
    "sg:city":"Gardena",
    "sg:classifiers":[
        {
            "category":"Real Estate",
            "subcategory":"Real Estate Agent",
            "type":"Services"
        }
    ],
    "sg:phone":"+1 310 532 8310",
    "sg:postcode":"90247",
    "sg:province":"CA",
    "sg:tags":[
        "authorities",
        "housing"
    ],
    "wof:name":"Meadowlark Manor",
    "wof:placetype":"venue"
},
  "geometry": {"coordinates":[-118.296403,33.875267],"type":"Point"}
}