{
  "type": "Feature",
  "properties": {
    "addr:full":"1333 Balboa Street San Francisco CA 94118",
    "addr:housenumber":"1333",
    "addr:postcode":"94118",
    "addr:street":"Balboa Street",
    "iso:country":"US",
    "sg:address":"1333 Balboa Street",
    "sg:city":"San Francisco",
    "sg:classifiers":[
        {
            "category":"Professional",
            "subcategory":"Lawyer & Legal Services",
            "type":"Services"
        }
    ],
    "sg:phone":"+1 415 221 0134",
    "sg:postcode":"94118",
    "sg:province":"CA",
    "wof:name":"Donnelly James Stephen Atty",
    "wof:placetype":"venue"
},
  "geometry": {"coordinates":[-122.473,37.776798],"type":"Point"}
}