{
  "type": "Feature",
  "properties": {
    "addr:full":"109 W Mason St Santa Barbara CA 93101",
    "addr:housenumber":"109",
    "addr:postcode":"93101",
    "addr:street":"W Mason St",
    "iso:country":"US",
    "sg:address":"109 W Mason St",
    "sg:city":"Santa Barbara",
    "sg:classifiers":[
        {
            "category":"Professional",
            "type":"Services"
        }
    ],
    "sg:phone":"+1 805 966 6394",
    "sg:postcode":"93101",
    "sg:province":"CA",
    "wof:name":"Wendy L Carpenter",
    "wof:placetype":"venue"
},
  "geometry": {"coordinates":[-119.691861,34.411234],"type":"Point"}
}