{
  "type": "Feature",
  "properties": {
    "iso:country":"US",
    "sg:address":"1110 Harkins Rd",
    "sg:city":"Salinas",
    "sg:classifiers":[
        {
            "category":"Wholesale",
            "subcategory":"Machinery & Supplies",
            "type":"Manufacturing & Wholesale Goods"
        }
    ],
    "sg:phone":"+1 831 753 6101",
    "sg:postcode":"93901",
    "sg:province":"CA",
    "sg:tags":[
        "rubber",
        "product"
    ],
    "wof:name":"Green Rubber Kennedy Ag",
    "wof:placetype":"venue"
},
  "geometry": {"coordinates":[-121.630816,36.65014],"type":"Point"}
}