{
  "type": "Feature",
  "properties": {
    "iso:country":"US",
    "sg:address":"2348 Walsh Ave Building F, 2nd Floor",
    "sg:city":"Santa Clara",
    "sg:classifiers":[
        {
            "category":"Professional",
            "subcategory":"Lawyer & Legal Services",
            "type":"Services"
        }
    ],
    "sg:phone":"+1 408 966 9645",
    "sg:postcode":"95051",
    "sg:province":"CA",
    "sg:tags":[
        "notary"
    ],
    "wof:name":"Mobile Notary Made Easy",
    "wof:placetype":"venue"
},
  "geometry": {"coordinates":[-121.966308,37.367614],"type":"Point"}
}