{
  "type": "Feature",
  "properties": {
    "addr:full":"23 Orinda Way Orinda CA 94563",
    "addr:housenumber":"23",
    "addr:postcode":"94563",
    "addr:street":"Orinda Way",
    "iso:country":"US",
    "sg:address":"23 Orinda Way",
    "sg:city":"Orinda",
    "sg:classifiers":[
        {
            "category":"Health Services",
            "subcategory":"Doctor",
            "type":"Services"
        }
    ],
    "sg:phone":"+1 925 254 2360",
    "sg:postcode":"94563",
    "sg:province":"CA",
    "sg:tags":[
        "dentist"
    ],
    "wof:name":"Todd B Pearson DDS",
    "wof:placetype":"venue"
},
  "geometry": {"coordinates":[-122.189104,37.8832],"type":"Point"}
}