{
  "type": "Feature",
  "properties": {
    "addr:full":"7128 Miramar Rd San Diego CA 92121",
    "addr:housenumber":"7128",
    "addr:postcode":"92121",
    "addr:street":"Miramar Rd",
    "iso:country":"US",
    "sg:address":"7128 Miramar Rd",
    "sg:city":"San Diego",
    "sg:classifiers":[
        {
            "category":"Home & Garden",
            "subcategory":"Furniture",
            "type":"Retail Goods"
        }
    ],
    "sg:phone":"+1 858 578 7983",
    "sg:postcode":"92121",
    "sg:province":"CA",
    "sg:tags":[
        "store",
        "mattress"
    ],
    "sg:website":"www.futons4lesssd.com",
    "wof:name":"Futons 4 Less",
    "wof:placetype":"venue"
},
  "geometry": {"coordinates":[-117.16100299999999,32.879501],"type":"Point"}
}