{
  "type": "Feature",
  "properties": {
    "addr:full":"648 Yerington Ln Lincoln CA 95648",
    "addr:postcode":"95648",
    "addr:street":"648 Yerington Ln",
    "iso:country":"US",
    "sg:address":"648 Yerington Ln",
    "sg:city":"Lincoln",
    "sg:classifiers":[
        {
            "category":"Real Estate",
            "subcategory":"Real Estate Agent",
            "type":"Services"
        }
    ],
    "sg:phone":"+1 916 408 3825",
    "sg:postcode":"95648",
    "sg:province":"CA",
    "wof:name":"Re/Max",
    "wof:placetype":"venue"
},
  "geometry": {"coordinates":[-121.27402600000001,38.874228],"type":"Point"}
}