{
  "type": "Feature",
  "properties": {
    "iso:country":"US",
    "sg:address":"7990 San Fernando Rd",
    "sg:city":"Sun Valley",
    "sg:classifiers":[
        {
            "category":"Shopping",
            "subcategory":"Clothing, Apparel, & Fashions",
            "type":"Retail Goods"
        }
    ],
    "sg:phone":"+1 818 342 3900",
    "sg:postcode":"91352",
    "sg:province":"CA",
    "sg:tags":[
        "jean"
    ],
    "wof:name":"Jefri Jeans",
    "wof:placetype":"venue"
},
  "geometry": {"coordinates":[-118.362386,34.214928],"type":"Point"}
}