{
  "type": "Feature",
  "properties": {
    "addr:full":"4539 Graywood Ave Long Beach CA 90808",
    "addr:housenumber":"4539",
    "addr:postcode":"90808",
    "addr:street":"Graywood Ave",
    "iso:country":"US",
    "sg:address":"4539 Graywood Ave",
    "sg:city":"Long Beach",
    "sg:classifiers":[
        {
            "category":"Wholesale",
            "subcategory":"Non-durable Goods",
            "type":"Manufacturing & Wholesale Goods"
        }
    ],
    "sg:phone":"+1 562 429 7471",
    "sg:postcode":"90808",
    "sg:province":"CA",
    "wof:name":"Kor Recycled Packaging",
    "wof:placetype":"venue"
},
  "geometry": {"coordinates":[-118.138261,33.842396],"type":"Point"}
}