{
  "type": "Feature",
  "properties": {
    "iso:country":"US",
    "sg:address":"4005 Whirlwind Dr",
    "sg:city":"Bakersfield",
    "sg:classifiers":[
        {
            "category":"Organizations",
            "subcategory":"Religious Organization",
            "type":"Services"
        }
    ],
    "sg:phone":"+1 661 831 1380",
    "sg:postcode":"93313",
    "sg:province":"CA",
    "sg:tags":[
        "church"
    ],
    "sg:website":"www.ridgeviewfamily.com",
    "wof:name":"Ridge View Family Worship Ctr",
    "wof:placetype":"venue"
},
  "geometry": {"coordinates":[-119.046286,35.29527],"type":"Point"}
}