{
  "type": "Feature",
  "properties": {
    "addr:full":"1775 W Imola Ave Napa CA 94559",
    "addr:housenumber":"1775",
    "addr:postcode":"94559",
    "addr:street":"W Imola Ave",
    "iso:country":"US",
    "sg:address":"1775 W Imola Ave",
    "sg:city":"Napa",
    "sg:classifiers":[
        {
            "category":"Autos & Motor Vehicles",
            "subcategory":"Fuel & Gas Station",
            "type":"Retail Goods"
        }
    ],
    "sg:phone":"+1 707 265 6785",
    "sg:postcode":"94559",
    "sg:province":"CA",
    "sg:tags":[
        "oil"
    ],
    "wof:name":"Imola Chevron",
    "wof:placetype":"venue"
},
  "geometry": {"coordinates":[-122.292957,38.281899],"type":"Point"}
}