{
  "type": "Feature",
  "properties": {
    "addr:full":"31791 Hilltop Blvd Running Springs CA 92314",
    "addr:housenumber":"31791",
    "addr:postcode":"92314",
    "addr:street":"Hilltop Blvd",
    "iso:country":"US",
    "sg:address":"31791 Hilltop Blvd",
    "sg:city":"Running Springs",
    "sg:classifiers":[
        {
            "category":"Health Services",
            "subcategory":"Chiropractor",
            "type":"Services"
        }
    ],
    "sg:phone":"+1 909 867 7400",
    "sg:postcode":"92314",
    "sg:province":"CA",
    "wof:name":"Chase Chiropractic Non Force",
    "wof:placetype":"venue"
},
  "geometry": {"coordinates":[-117.10940600000001,34.20753],"type":"Point"}
}