{
  "type": "Feature",
  "properties": {
    "iso:country":"US",
    "sg:address":"39812 Mission Blvd",
    "sg:city":"Fremont",
    "sg:classifiers":[
        {
            "category":"Real Estate",
            "subcategory":"Real Estate Agent",
            "type":"Services"
        }
    ],
    "sg:phone":"+1 510 226 6338",
    "sg:postcode":"94539",
    "sg:province":"CA",
    "sg:tags":[
        "management"
    ],
    "wof:name":"Topline Properties",
    "wof:placetype":"venue"
},
  "geometry": {"coordinates":[-121.95411799999999,37.559067],"type":"Point"}
}