{
  "type": "Feature",
  "properties": {
    "iso:country":"US",
    "sg:address":"427 County View Dr",
    "sg:city":"Mill Valley",
    "sg:classifiers":[
        {
            "category":"Health Services",
            "subcategory":"Doctor",
            "type":"Services"
        }
    ],
    "sg:phone":"+1 415 388 5410",
    "sg:postcode":"94941",
    "sg:province":"CA",
    "sg:tags":[
        "physician",
        "surgeon"
    ],
    "wof:name":"Tennenhouse Pro Publicatons",
    "wof:placetype":"venue"
},
  "geometry": {"coordinates":[-122.535681,37.872606],"type":"Point"}
}