{
  "type": "Feature",
  "properties": {
    "addr:full":"555 University Ave Suite 137 Sacramento CA 95825",
    "addr:housenumber":"555",
    "addr:postcode":"95825",
    "addr:street":"University Ave Suite 137",
    "iso:country":"US",
    "sg:address":"555 University Ave Suite 137",
    "sg:city":"Sacramento",
    "sg:classifiers":[
        {
            "category":"Professional",
            "subcategory":"Lawyer & Legal Services",
            "type":"Services"
        }
    ],
    "sg:phone":"+1 916 925 2200",
    "sg:postcode":"95825",
    "sg:province":"CA",
    "sg:tags":[
        "attorney",
        "law",
        "business",
        "personal",
        "landlord",
        "real estate",
        "injury",
        "tenant"
    ],
    "wof:name":"Law Offices Of Robert M Merritt",
    "wof:placetype":"venue"
},
  "geometry": {"coordinates":[-121.418943,38.568072],"type":"Point"}
}