{
  "type": "Feature",
  "properties": {
    "iso:country":"US",
    "sg:address":"50 Old Courthouse Sq",
    "sg:city":"Santa Rosa",
    "sg:classifiers":[
        {
            "category":"Professional",
            "type":"Services"
        }
    ],
    "sg:phone":"+1 707 524 7000",
    "sg:postcode":"95404",
    "sg:province":"CA",
    "wof:name":"Rybicki & Blevans LLP",
    "wof:placetype":"venue"
},
  "geometry": {"coordinates":[-122.71350099999999,38.439183],"type":"Point"}
}