{
  "type": "Feature",
  "properties": {
    "addr:full":"6380 Riviera Cir Long Beach CA 90815",
    "addr:housenumber":"6380",
    "addr:postcode":"90815",
    "addr:street":"Riviera Cir",
    "iso:country":"US",
    "sg:address":"6380 Riviera Cir",
    "sg:city":"Long Beach",
    "sg:classifiers":[
        {
            "category":"Professional",
            "subcategory":"Detective & Security Services",
            "type":"Services"
        }
    ],
    "sg:phone":"+1 562 430 3103",
    "sg:postcode":"90815",
    "sg:province":"CA",
    "sg:tags":[
        "guard",
        "patrol"
    ],
    "wof:name":"Bixby Riviera Condominium",
    "wof:placetype":"venue"
},
  "geometry": {"coordinates":[-118.10897300000001,33.774624],"type":"Point"}
}