{
  "type": "Feature",
  "properties": {
    "iso:country":"US",
    "sg:address":"240 Hospital Cir",
    "sg:city":"Westminster",
    "sg:classifiers":[
        {
            "category":"Health Services",
            "subcategory":"Hospital",
            "type":"Services"
        }
    ],
    "sg:phone":"+1 714 892 6686",
    "sg:postcode":"92683",
    "sg:province":"CA",
    "wof:name":"Westminster Helping Hand of",
    "wof:placetype":"venue"
},
  "geometry": {"coordinates":[-117.99566799999999,33.764314],"type":"Point"}
}