{
  "type": "Feature",
  "properties": {
    "iso:country":"US",
    "sg:address":"351 West San Fernando Blvd",
    "sg:city":"Burbank",
    "sg:classifiers":[
        {
            "category":"Building & Trades",
            "subcategory":"Cleaning & Sanitation",
            "type":"Services"
        }
    ],
    "sg:phone":"+1 818 253 9051",
    "sg:postcode":"91502",
    "sg:province":"CA",
    "sg:tags":[
        "carpet"
    ],
    "wof:name":"Floodz Happen Restoration",
    "wof:placetype":"venue"
},
  "geometry": {"coordinates":[-118.306116,34.178936],"type":"Point"}
}