{
  "type": "Feature",
  "properties": {
    "iso:country":"US",
    "sfac:artist":"Noguchi, Isamu",
    "sfac:created_at":"01/01/1970 12:32:25 AM +0000",
    "sfac:credit_line":"Purchased by the San Francisco Art Commission for the San Francisco International Airport",
    "sfac:display_dimensions":"61\" H X 21 1/2\" W X 15 1/4\" D",
    "sfac:location_description":"Airport : T1 : Boarding Area C : Gate 45",
    "sfac:medium":"Cast bronze with black patina",
    "sfac:revision":"2-93b27476039afded6c595a3238889881",
    "sfac:title":"Figure",
    "wof:name":"Figure",
    "wof:placetype":"venue"
},
  "geometry": {"coordinates":[-122.38278200000001,37.615098],"type":"Point"}
}