{
  "type": "Feature",
  "properties": {
    "iso:country":"US",
    "sg:address":"29259 Arnold Dr",
    "sg:city":"Sonoma",
    "sg:classifiers":[
        {
            "category":"Wholesale",
            "subcategory":"Auto Parts",
            "type":"Manufacturing & Wholesale Goods"
        }
    ],
    "sg:phone":"+1 707 939 8000",
    "sg:postcode":"95476",
    "sg:province":"CA",
    "wof:name":"Road Rockets",
    "wof:placetype":"venue"
},
  "geometry": {"coordinates":[-122.45723599999999,38.170504],"type":"Point"}
}