{
  "type": "Feature",
  "properties": {
    "iso:country":"US",
    "sg:address":"2601 Nuestra Castillo Ct Ste 4206",
    "sg:city":"San Jose",
    "sg:classifiers":[
        {
            "category":"Home & Garden",
            "subcategory":"Household Appliances",
            "type":"Retail Goods"
        },
        {
            "category":"Building & Trades",
            "subcategory":"Construction",
            "type":"Services"
        }
    ],
    "sg:phone":"+1 408 396 1833",
    "sg:postcode":"95127",
    "sg:province":"CA",
    "sg:tags":[
        "repair",
        "contractor"
    ],
    "wof:name":"Appliance Doc",
    "wof:placetype":"venue"
},
  "geometry": {"coordinates":[-121.83257500000001,37.35752],"type":"Point"}
}