{
  "type": "Feature",
  "properties": {
    "addr:full":"555 The Shops At Mission Viejo Mission Viejo CA 92691",
    "addr:housenumber":"555",
    "addr:postcode":"92691",
    "addr:street":"The Shops At Mission",
    "iso:country":"US",
    "sg:address":"555 The Shops At Mission Viejo",
    "sg:city":"Mission Viejo",
    "sg:classifiers":[
        {
            "category":"Banks & Credit Unions",
            "subcategory":"Financial Services",
            "type":"Services"
        }
    ],
    "sg:phone":"+1 949 364 6289",
    "sg:postcode":"92691",
    "sg:province":"CA",
    "sg:tags":[
        "broker",
        "mortgage"
    ],
    "wof:name":"Anywhere Communications",
    "wof:placetype":"venue"
},
  "geometry": {"coordinates":[-117.66925500000001,33.561273],"type":"Point"}
}