{
  "type": "Feature",
  "properties": {
    "iso:country":"US",
    "sg:address":"43 W Santa Ana Ave Apt D",
    "sg:city":"Clovis",
    "sg:classifiers":[
        {
            "category":"Wholesale",
            "subcategory":"Non-durable Goods",
            "type":"Manufacturing & Wholesale Goods"
        }
    ],
    "sg:phone":"+1 559 433 9095",
    "sg:postcode":"93612",
    "sg:province":"CA",
    "sg:tags":[
        "dry",
        "goods-wholesale"
    ],
    "wof:name":"American Foreign Trade",
    "wof:placetype":"venue"
},
  "geometry": {"coordinates":[-119.71010800000001,36.804852],"type":"Point"}
}