{
  "type": "Feature",
  "properties": {
    "addr:full":"12759 Poway Rd Poway CA 92064",
    "addr:housenumber":"12759",
    "addr:postcode":"ca 92064",
    "addr:street":"Poway Rd",
    "iso:country":"US",
    "sg:address":"12759 Poway Rd",
    "sg:city":"Poway",
    "sg:classifiers":[
        {
            "category":"Banks & Credit Unions",
            "subcategory":"Bank",
            "type":"Services"
        }
    ],
    "sg:phone":"+1 858 486 8281",
    "sg:postcode":"92064",
    "sg:province":"CA",
    "sg:tags":[
        "cashing",
        "check"
    ],
    "wof:name":"Checks-N-Advance",
    "wof:placetype":"venue"
},
  "geometry": {"coordinates":[-117.053837,32.956384],"type":"Point"}
}