{
  "type": "Feature",
  "properties": {
    "addr:full":"34 Westgate Laguna Niguel CA 92677",
    "addr:housenumber":"34",
    "addr:postcode":"92677",
    "addr:street":"Westgate",
    "iso:country":"US",
    "sg:address":"34 Westgate",
    "sg:city":"Laguna Niguel",
    "sg:classifiers":[
        {
            "category":"Shopping",
            "subcategory":"Hobbies, Toys, & Games",
            "type":"Retail Goods"
        }
    ],
    "sg:phone":"+1 949 489 7852",
    "sg:postcode":"92677",
    "sg:province":"CA",
    "sg:tags":[
        "craft"
    ],
    "wof:name":"Shan's Originals",
    "wof:placetype":"venue"
},
  "geometry": {"coordinates":[-117.68996199999999,33.501681],"type":"Point"}
}