{
  "type": "Feature",
  "properties": {
    "iso:country":"US",
    "sg:address":"23451 Madison St Ste 340",
    "sg:city":"Torrance",
    "sg:classifiers":[
        {
            "category":"Health Services",
            "subcategory":"Doctor",
            "type":"Services"
        }
    ],
    "sg:phone":"+1 310 373 6864",
    "sg:postcode":"90505",
    "sg:province":"CA",
    "wof:name":"Fisher Steven D MD Facs",
    "wof:placetype":"venue"
},
  "geometry": {"coordinates":[-118.348,33.812801],"type":"Point"}
}