{
  "type": "Feature",
  "properties": {
    "addr:full":"200 Main St Huntington Beach CA 92648",
    "addr:housenumber":"200",
    "addr:postcode":"92648",
    "addr:street":"Main St",
    "iso:country":"US",
    "sg:address":"200 Main St",
    "sg:city":"Huntington Beach",
    "sg:classifiers":[
        {
            "category":"Restaurant",
            "type":"Food & Drink"
        }
    ],
    "sg:phone":"+1 714 374 2224",
    "sg:postcode":"92648",
    "sg:province":"CA",
    "sg:tags":[
        "italian"
    ],
    "wof:name":"B J's Pizza & Grill",
    "wof:placetype":"venue"
},
  "geometry": {"coordinates":[-118.00024000000001,33.65893],"type":"Point"}
}