{
  "type": "Feature",
  "properties": {
    "iso:country":"US",
    "sg:address":"1117 Maple Ave",
    "sg:city":"Los Angeles",
    "sg:classifiers":[
        {
            "category":"Wholesale",
            "subcategory":"Apparel",
            "type":"Manufacturing & Wholesale Goods"
        },
        {
            "category":"Shopping",
            "subcategory":"Clothing, Apparel, & Fashions",
            "type":"Retail Goods"
        }
    ],
    "sg:phone":"+1 213 742 6715",
    "sg:postcode":"90015",
    "sg:province":"CA",
    "wof:name":"Jeans For You",
    "wof:placetype":"venue"
},
  "geometry": {"coordinates":[-118.256235,34.03593],"type":"Point"}
}