{
  "type": "Feature",
  "properties": {
    "addr:full":"21372 Creekside Dr Red Bluff CA 96080",
    "addr:housenumber":"21372",
    "addr:postcode":"96080",
    "addr:street":"Creekside Dr",
    "iso:country":"US",
    "sg:address":"21372 Creekside Dr",
    "sg:city":"Red Bluff",
    "sg:classifiers":[
        {
            "category":"Shopping",
            "subcategory":"Gifts & Souvenirs",
            "type":"Retail Goods"
        }
    ],
    "sg:phone":"+1 530 529 3292",
    "sg:postcode":"96080",
    "sg:province":"CA",
    "wof:name":"Crystal Art & Apparel",
    "wof:placetype":"venue"
},
  "geometry": {"coordinates":[-122.241392,40.218777],"type":"Point"}
}