{
  "type": "Feature",
  "properties": {
    "iso:country":"US",
    "sg:address":"707 Natoma St",
    "sg:city":"Folsom",
    "sg:classifiers":[
        {
            "category":"Professional",
            "type":"Services"
        }
    ],
    "sg:phone":"+1 916 792 4253",
    "sg:postcode":"95630",
    "sg:province":"CA",
    "sg:tags":[
        "establishment"
    ],
    "wof:name":"Danielle Sherman & Monroe",
    "wof:placetype":"venue"
},
  "geometry": {"coordinates":[-121.175335,38.674563],"type":"Point"}
}