{
  "type": "Feature",
  "properties": {
    "iso:country":"US",
    "sg:address":"9655 Granite Ridge Dr Ste 400",
    "sg:city":"San Diego",
    "sg:classifiers":[
        {
            "category":"Real Estate",
            "subcategory":"Architect",
            "type":"Services"
        }
    ],
    "sg:phone":"+1 858 565 4440",
    "sg:postcode":"92123",
    "sg:province":"CA",
    "wof:name":"NTDArchitects",
    "wof:placetype":"venue"
},
  "geometry": {"coordinates":[-117.12033700000001,32.806315],"type":"Point"}
}