{
  "type": "Feature",
  "properties": {
    "addr:full":"1473 Live Oak Blvd Yuba City CA 95991",
    "addr:housenumber":"1473",
    "addr:postcode":"95991",
    "addr:street":"Live Oak Blvd",
    "iso:country":"US",
    "sg:address":"1473 Live Oak Blvd",
    "sg:city":"Yuba City",
    "sg:classifiers":[
        {
            "category":"Health Services",
            "subcategory":"Doctor",
            "type":"Services"
        }
    ],
    "sg:phone":"+1 530 751 0599",
    "sg:postcode":"95991",
    "sg:province":"CA",
    "sg:tags":[
        "dentist"
    ],
    "wof:name":"Robert Ripley Inc",
    "wof:placetype":"venue"
},
  "geometry": {"coordinates":[-121.620541,39.150925],"type":"Point"}
}