{
  "type": "Feature",
  "properties": {
    "iso:country":"US",
    "sg:address":"50 S San Mateo Dr Ste 320",
    "sg:city":"San Mateo",
    "sg:classifiers":[
        {
            "category":"Health Services",
            "subcategory":"Doctor",
            "type":"Services"
        }
    ],
    "sg:phone":"+1 650 340 7200",
    "sg:postcode":"94401",
    "sg:province":"CA",
    "sg:tags":[
        "throat",
        "surgeon",
        "ear",
        "cosmetic",
        "nose"
    ],
    "wof:name":"James Newman, MD",
    "wof:placetype":"venue"
},
  "geometry": {"coordinates":[-122.326106,37.566283],"type":"Point"}
}