{
  "type": "Feature",
  "properties": {
    "addr:full":"847 San Pablo Avenue Albany CA 94706",
    "addr:housenumber":"847",
    "addr:postcode":"94706",
    "addr:street":"San Pablo Avenue",
    "iso:country":"US",
    "sg:address":"847 San Pablo Avenue",
    "sg:city":"Albany",
    "sg:classifiers":[
        {
            "category":"Health Services",
            "subcategory":"Dentist",
            "type":"Services"
        }
    ],
    "sg:phone":"+1 510 527 1245",
    "sg:postcode":"94706",
    "sg:province":"CA",
    "wof:name":"Albany Family Dental Center",
    "wof:placetype":"venue"
},
  "geometry": {"coordinates":[-122.299004,37.890598],"type":"Point"}
}