{
  "type": "Feature",
  "properties": {
    "addr:full":"10722 Beverly Blvd Whittier CA 90601",
    "addr:housenumber":"10722",
    "addr:postcode":"90601",
    "addr:street":"Beverly Blvd",
    "iso:country":"US",
    "sg:address":"10722 Beverly Blvd",
    "sg:city":"Whittier",
    "sg:classifiers":[
        {
            "category":"Manufacturing",
            "subcategory":"Printing",
            "type":"Manufacturing & Wholesale Goods"
        }
    ],
    "sg:phone":"+1 818 558 5250",
    "sg:postcode":"90601",
    "sg:province":"CA",
    "sg:tags":[
        "cards",
        "financial",
        "greeting"
    ],
    "wof:name":"Edward J Enterprise Inc",
    "wof:placetype":"venue"
},
  "geometry": {"coordinates":[-118.055819,33.998792],"type":"Point"}
}