{
  "type": "Feature",
  "properties": {
    "iso:country":"US",
    "sg:address":"17270 Hawthorne Blvd",
    "sg:city":"Torrance",
    "sg:classifiers":[
        {
            "category":"Health Services",
            "subcategory":"Dentist",
            "type":"Services"
        }
    ],
    "sg:phone":"+1 310 542 7331",
    "sg:postcode":"90504",
    "sg:province":"CA",
    "sg:website":"bergersbraces.com",
    "wof:name":"Berger Jeffrey DMD",
    "wof:placetype":"venue"
},
  "geometry": {"coordinates":[-118.352997,33.8736],"type":"Point"}
}