{
  "type": "Feature",
  "properties": {
    "addr:full":"9666 Central Ave Montclair CA 91763",
    "addr:housenumber":"9666",
    "addr:postcode":"91763",
    "addr:street":"Central Ave",
    "iso:country":"US",
    "sg:address":"9666 Central Ave",
    "sg:city":"Montclair",
    "sg:classifiers":[
        {
            "category":"Food & Beverages",
            "subcategory":"Liquor & Beverages",
            "type":"Retail Goods"
        }
    ],
    "sg:phone":"+1 909 624 6328",
    "sg:postcode":"91763",
    "sg:province":"CA",
    "wof:name":"Lou's Liquor-Montclair",
    "wof:placetype":"venue"
},
  "geometry": {"coordinates":[-117.689627,34.080788],"type":"Point"}
}