{
  "type": "Feature",
  "properties": {
    "iso:country":"US",
    "sg:address":"2711 Alcatraz Ave",
    "sg:city":"Berkeley",
    "sg:classifiers":[
        {
            "category":"Real Estate",
            "subcategory":"Real Estate Agent",
            "type":"Services"
        }
    ],
    "sg:phone":"+1 510 658 8044",
    "sg:postcode":"94705",
    "sg:province":"CA",
    "wof:name":"Quest Real Estate",
    "wof:placetype":"venue"
},
  "geometry": {"coordinates":[-122.25179900000001,37.851508],"type":"Point"}
}