{
  "type": "Feature",
  "properties": {
    "addr:full":"575 Silver Avenue San Francisco CA 94112",
    "addr:housenumber":"575",
    "addr:postcode":"94112",
    "addr:street":"Silver Avenue",
    "iso:country":"US",
    "sg:address":"575 Silver Avenue",
    "sg:city":"San Francisco",
    "sg:classifiers":[
        {
            "category":"Building & Trades",
            "subcategory":"Construction",
            "type":"Services"
        }
    ],
    "sg:phone":"+1 415 333 9733",
    "sg:postcode":"94112",
    "sg:province":"CA",
    "sg:tags":[
        "contractor"
    ],
    "wof:name":"Gogol S J Construction",
    "wof:placetype":"venue"
},
  "geometry": {"coordinates":[-122.424004,37.728901],"type":"Point"}
}