{
  "type": "Feature",
  "properties": {
    "addr:full":"20863 Stevens Creek Blvd Suite 300 Cupertino CA 95014",
    "addr:housenumber":"20863",
    "addr:postcode":"95014",
    "addr:street":"Stevens Creek Blvd Suite 300",
    "iso:country":"US",
    "sg:address":"20863 Stevens Creek Blvd Suite 300",
    "sg:city":"Cupertino",
    "sg:classifiers":[
        {
            "category":"Manufacturing",
            "subcategory":"Electronics",
            "type":"Manufacturing & Wholesale Goods"
        }
    ],
    "sg:phone":"+1 408 861 1400",
    "sg:postcode":"95014",
    "sg:province":"CA",
    "sg:tags":[
        "iptv"
    ],
    "sg:website":"http://www.entone.com",
    "wof:name":"Entone Technologies",
    "wof:placetype":"venue"
},
  "geometry": {"coordinates":[-122.03791099999999,37.322875],"type":"Point"}
}