{
  "type": "Feature",
  "properties": {
    "addr:full":"2529 Santa Fe Ave Long Beach CA 90810",
    "addr:postcode":"2529;90810",
    "addr:street":"Santa Fe Ave",
    "iso:country":"US",
    "sg:address":"2529 Santa Fe Ave",
    "sg:city":"Long Beach",
    "sg:classifiers":[
        {
            "category":"Personal",
            "subcategory":"Beauty Salon",
            "type":"Services"
        }
    ],
    "sg:phone":"+1 562 989 0707",
    "sg:postcode":"90810",
    "sg:province":"CA",
    "wof:name":"Chel's Beauty Salon",
    "wof:placetype":"venue"
},
  "geometry": {"coordinates":[-118.21551700000001,33.803865],"type":"Point"}
}