{
  "type": "Feature",
  "properties": {
    "iso:country":"US",
    "sg:address":"2529 Santa Fe Ave",
    "sg:city":"Long Beach",
    "sg:classifiers":[
        {
            "category":"Personal",
            "subcategory":"Beauty Salon",
            "type":"Services"
        }
    ],
    "sg:phone":"+1 562 989 0707",
    "sg:postcode":"90810",
    "sg:province":"CA",
    "wof:name":"Chel's Beauty Salon",
    "wof:placetype":"venue"
},
  "geometry": {"coordinates":[-118.215517,33.803865],"type":"Point"}
}