{
  "type": "Feature",
  "properties": {
    "addr:full":"4611 E 2nd St Long Beach CA 90803",
    "addr:housenumber":"4611",
    "addr:postcode":"90803",
    "addr:street":"E 2Nd St",
    "iso:country":"US",
    "sg:address":"4611 E 2nd St",
    "sg:city":"Long Beach",
    "sg:classifiers":[
        {
            "category":"Restaurant",
            "type":"Food & Drink"
        }
    ],
    "sg:phone":"+1 562 434 4454",
    "sg:postcode":"90803",
    "sg:province":"CA",
    "wof:name":"Papalucci",
    "wof:placetype":"venue"
},
  "geometry": {"coordinates":[-118.138676,33.761984],"type":"Point"}
}