{
  "type": "Feature",
  "properties": {
    "iso:country":"US",
    "sg:address":"2080 Enterprise Blvd",
    "sg:city":"West Sacramento",
    "sg:classifiers":[
        {
            "category":"Freight",
            "type":"Transportation"
        }
    ],
    "sg:phone":"+1 916 372 3600",
    "sg:postcode":"95691",
    "sg:province":"CA",
    "sg:tags":[
        "trucking"
    ],
    "sg:website":"www.cdcmclaughlin.com",
    "wof:name":"California Distribution Ctr",
    "wof:placetype":"venue"
},
  "geometry": {"coordinates":[-121.576351,38.560782],"type":"Point"}
}