{
  "type": "Feature",
  "properties": {
    "addr:full":"8064 State Hwy 99 Los Molinos CA 96055",
    "addr:housenumber":"8064",
    "addr:postcode":"96055",
    "addr:street":"State Hwy 99",
    "iso:country":"US",
    "sg:address":"8064 State Hwy 99",
    "sg:city":"Los Molinos",
    "sg:classifiers":[
        {
            "category":"Freight",
            "type":"Transportation"
        }
    ],
    "sg:phone":"+1 530 384 0242",
    "sg:postcode":"96055",
    "sg:province":"CA",
    "sg:tags":[
        "commercial",
        "storage"
    ],
    "wof:name":"Los Molinos Mini Storage",
    "wof:placetype":"venue"
},
  "geometry": {"coordinates":[-122.099891,40.027991],"type":"Point"}
}