{
  "type": "Feature",
  "properties": {
    "addr:full":"13604 Newport Rd Turlock CA 95303",
    "addr:housenumber":"13604",
    "addr:postcode":"95303",
    "addr:street":"Newport Rd",
    "iso:country":"US",
    "sg:address":"13604 Newport Rd",
    "sg:city":"Turlock",
    "sg:classifiers":[
        {
            "category":"Airport",
            "type":"Transportation"
        }
    ],
    "sg:phone":"+1 209 632 3244",
    "sg:postcode":"95303",
    "sg:province":"CA",
    "sg:tags":[
        "aircraft",
        "maintenance"
    ],
    "wof:name":"Aero Vista Inc",
    "wof:placetype":"venue"
},
  "geometry": {"coordinates":[-120.703068,37.486583],"type":"Point"}
}