{
  "type": "Feature",
  "properties": {
    "iso:country":"US",
    "sg:address":"5020 El Cerrito Plaza",
    "sg:city":"El Cerrito",
    "sg:classifiers":[
        {
            "category":"Restaurant",
            "type":"Food & Drink"
        }
    ],
    "sg:phone":"+1 510 525 2152",
    "sg:postcode":"94530",
    "sg:province":"CA",
    "wof:name":"Panda Express Restaurant",
    "wof:placetype":"venue"
},
  "geometry": {"coordinates":[-122.300003,37.900902],"type":"Point"}
}