{
  "type": "Feature",
  "properties": {
    "addr:full":"624 E Bidwell St Folsom CA 95630",
    "addr:housenumber":"624",
    "addr:postcode":"95630",
    "addr:street":"E Bidwell St",
    "iso:country":"US",
    "sg:address":"624 E Bidwell St",
    "sg:city":"Folsom",
    "sg:classifiers":[
        {
            "category":"Personal",
            "subcategory":"Beauty Salon",
            "type":"Services"
        }
    ],
    "sg:phone":"+1 916 983 2906",
    "sg:postcode":"95630",
    "sg:province":"CA",
    "wof:name":"Elvira's Hair & Nail Salon",
    "wof:placetype":"venue"
},
  "geometry": {"coordinates":[-121.156954,38.670348],"type":"Point"}
}