{
  "type": "Feature",
  "properties": {
    "iso:country":"US",
    "sg:address":"7500 del Cielo Way",
    "sg:city":"Modesto",
    "sg:classifiers":[
        {
            "category":"Organizations",
            "subcategory":"Professional Association",
            "type":"Services"
        }
    ],
    "sg:phone":"+1 209 545 3224",
    "sg:postcode":"95356",
    "sg:province":"CA",
    "wof:name":"Del Rio Homeowners Assn",
    "wof:placetype":"venue"
},
  "geometry": {"coordinates":[-121.00312,37.749125],"type":"Point"}
}