{
  "type": "Feature",
  "properties": {
    "iso:country":"US",
    "sg:address":"885 N San Antonio Rd",
    "sg:city":"Los Altos",
    "sg:classifiers":[
        {
            "category":"Health Services",
            "subcategory":"Health Practitioner",
            "type":"Services"
        }
    ],
    "sg:phone":"+1 650 948 7139",
    "sg:postcode":"94022",
    "sg:province":"CA",
    "sg:tags":[
        "psychologist"
    ],
    "wof:name":"J Michael Priddy PHD",
    "wof:placetype":"venue"
},
  "geometry": {"coordinates":[-122.114125,37.39849],"type":"Point"}
}