{
  "type": "Feature",
  "properties": {
    "addr:full":"4444 Geary Blvd Ste 100 San Francisco CA 94118",
    "addr:housenumber":"4444",
    "addr:postcode":"94118",
    "addr:street":"Geary Blvd Ste 100",
    "iso:country":"US",
    "sg:address":"4444 Geary Blvd Ste 100",
    "sg:city":"San Francisco",
    "sg:classifiers":[
        {
            "category":"Real Estate",
            "subcategory":"Real Estate Services",
            "type":"Services"
        },
        {
            "category":"Real Estate",
            "subcategory":"Real Estate Agent",
            "type":"Services"
        },
        {
            "category":"Real Estate",
            "subcategory":"Real Estate Operator",
            "type":"Services"
        }
    ],
    "sg:phone":"+1 415 834 9829",
    "sg:postcode":"94118",
    "sg:province":"CA",
    "sg:tags":[
        "property",
        "management",
        "apartment"
    ],
    "sg:website":"www.gaetanirealestate.com",
    "wof:name":"Gaetani Real Estate",
    "wof:placetype":"venue"
},
  "geometry": {"coordinates":[-122.46691800000001,37.781104],"type":"Point"}
}