{
  "type": "Feature",
  "properties": {
    "iso:country":"US",
    "sg:address":"3962 Landmark St",
    "sg:city":"Culver City",
    "sg:classifiers":[
        {
            "category":"Wholesale",
            "subcategory":"Machinery & Supplies",
            "type":"Manufacturing & Wholesale Goods"
        }
    ],
    "sg:phone":"+1 310 204 6600",
    "sg:postcode":"90232",
    "sg:province":"CA",
    "sg:tags":[
        "printing"
    ],
    "wof:name":"Mytel International Inc",
    "wof:placetype":"venue"
},
  "geometry": {"coordinates":[-118.387805,34.026875],"type":"Point"}
}