{
  "type": "Feature",
  "properties": {
    "addr:full":"5330 Shirley Ave Tarzana CA 91356",
    "addr:housenumber":"5330",
    "addr:postcode":"91356",
    "addr:street":"Shirley Ave",
    "iso:country":"US",
    "sg:address":"5330 Shirley Ave",
    "sg:city":"Tarzana",
    "sg:classifiers":[
        {
            "category":"Professional",
            "type":"Services"
        }
    ],
    "sg:phone":"+1 818 345 9978",
    "sg:postcode":"91356",
    "sg:province":"CA",
    "wof:name":"Joyce Sindel",
    "wof:placetype":"venue"
},
  "geometry": {"coordinates":[-118.557745,34.169112],"type":"Point"}
}