{
  "type": "Feature",
  "properties": {
    "iso:country":"US",
    "sg:address":"4420 E Miraloma Ave",
    "sg:city":"Anaheim",
    "sg:classifiers":[
        {
            "category":"Building & Trades",
            "subcategory":"Construction",
            "type":"Services"
        }
    ],
    "sg:phone":"+1 714 693 0531",
    "sg:postcode":"92806",
    "sg:province":"CA",
    "sg:tags":[
        "contractor"
    ],
    "wof:name":"Brown Consulting & Constr",
    "wof:placetype":"venue"
},
  "geometry": {"coordinates":[-117.836304,33.862695],"type":"Point"}
}