{
  "type": "Feature",
  "properties": {
    "iso:country":"US",
    "sg:address":"20058 Ventura Blvd",
    "sg:city":"Los Angeles",
    "sg:classifiers":[
        {
            "category":"Professional",
            "subcategory":"Advertising",
            "type":"Services"
        }
    ],
    "sg:phone":"+1 310 980 7395",
    "sg:postcode":"91364",
    "sg:province":"CA",
    "sg:tags":[
        "marketing"
    ],
    "sg:website":"www.promoteseo.com",
    "wof:name":"Astral Web",
    "wof:placetype":"venue"
},
  "geometry": {"coordinates":[-118.5706,34.171059],"type":"Point"}
}