{
  "type": "Feature",
  "properties": {
    "iso:country":"US",
    "sg:address":"7000 Bancroft Ave",
    "sg:city":"Oakland",
    "sg:classifiers":[
        {
            "category":"Food & Beverages",
            "subcategory":"Groceries & Convenience Stores",
            "type":"Retail Goods"
        }
    ],
    "sg:phone":"+1 510 569 2920",
    "sg:postcode":"94605",
    "sg:province":"CA",
    "wof:name":"Gazzali's Supermarket",
    "wof:placetype":"venue"
},
  "geometry": {"coordinates":[-122.178403,37.767149],"type":"Point"}
}