{
  "type": "Feature",
  "properties": {
    "iso:country":"US",
    "sg:address":"10142 Artesia Pl",
    "sg:city":"Bellflower",
    "sg:classifiers":[
        {
            "category":"Building & Trades",
            "subcategory":"Construction",
            "type":"Services"
        }
    ],
    "sg:phone":"+1 562 920 4443",
    "sg:postcode":"90706",
    "sg:province":"CA",
    "sg:tags":[
        "contractor"
    ],
    "wof:name":"GPS Construction",
    "wof:placetype":"venue"
},
  "geometry": {"coordinates":[-118.119828,33.874775],"type":"Point"}
}