{
  "type": "Feature",
  "properties": {
    "addr:full":"1084 Sycamore Dr Antioch CA 94509",
    "addr:housenumber":"1084",
    "addr:postcode":"ca 94509",
    "addr:street":"Sycamore Dr",
    "iso:country":"US",
    "sg:address":"1084 Sycamore Dr",
    "sg:city":"Antioch",
    "sg:classifiers":[
        {
            "category":"Personal",
            "subcategory":"Beauty Salon",
            "type":"Services"
        }
    ],
    "sg:phone":"+1 925 753 1663",
    "sg:postcode":"94509",
    "sg:province":"CA",
    "wof:name":"Latinos Hair Salon",
    "wof:placetype":"venue"
},
  "geometry": {"coordinates":[-121.81965700000001,38.003772],"type":"Point"}
}