{
  "type": "Feature",
  "properties": {
    "iso:country":"US",
    "sg:address":"100 N Robertson Blvd",
    "sg:city":"Beverly Hills",
    "sg:classifiers":[
        {
            "category":"Shopping",
            "type":"Retail Goods"
        }
    ],
    "sg:postcode":"90211",
    "sg:province":"CA",
    "wof:name":"All Saints Spitalfield",
    "wof:placetype":"venue"
},
  "geometry": {"coordinates":[-118.383661,34.067085],"type":"Point"}
}