{
  "type": "Feature",
  "properties": {
    "iso:country":"US",
    "sg:address":"3467 W 8th Street",
    "sg:city":"Los Angeles",
    "sg:classifiers":[
        {
            "category":"Shopping",
            "subcategory":"Clothing, Apparel, & Fashions",
            "type":"Retail Goods"
        }
    ],
    "sg:phone":"+1 213 389 0039",
    "sg:postcode":"90005",
    "sg:province":"CA",
    "sg:tags":[
        "accessory",
        "clothing",
        "women's"
    ],
    "wof:name":"Pretty Mama",
    "wof:placetype":"venue"
},
  "geometry": {"coordinates":[-118.30587,34.057561],"type":"Point"}
}