{
  "type": "Feature",
  "properties": {
    "iso:country":"US",
    "sg:address":"368 N Hockett St",
    "sg:city":"Porterville",
    "sg:classifiers":[
        {
            "category":"Real Estate",
            "subcategory":"Real Estate Agent",
            "type":"Services"
        }
    ],
    "sg:phone":"+1 559 782 4608",
    "sg:postcode":"93257",
    "sg:province":"CA",
    "wof:name":"Shirley J Gemmell",
    "wof:placetype":"venue"
},
  "geometry": {"coordinates":[-119.017201,36.072698],"type":"Point"}
}