{
  "type": "Feature",
  "properties": {
    "addr:full":"5558 E Kings Canyon Rd Fresno CA 93727",
    "addr:housenumber":"5558",
    "addr:postcode":"93727",
    "addr:street":"E Kings Canyon Rd",
    "iso:country":"US",
    "sg:address":"5558 E Kings Canyon Rd",
    "sg:city":"Fresno",
    "sg:classifiers":[
        {
            "category":"Personal",
            "subcategory":"Beauty Salon",
            "type":"Services"
        }
    ],
    "sg:phone":"+1 559 255 4091",
    "sg:postcode":"93727",
    "sg:province":"CA",
    "sg:tags":[
        "manicuring"
    ],
    "wof:name":"Rubye's Nail Clinique",
    "wof:placetype":"venue"
},
  "geometry": {"coordinates":[-119.70089400000001,36.735737],"type":"Point"}
}