{
  "type": "Feature",
  "properties": {
    "iso:country":"US",
    "sg:address":"504 N Oak St",
    "sg:city":"Inglewood",
    "sg:classifiers":[
        {
            "category":"Manufacturing",
            "subcategory":"Retail Goods",
            "type":"Manufacturing & Wholesale Goods"
        }
    ],
    "sg:phone":"+1 310 677 6400",
    "sg:postcode":"90302",
    "sg:province":"CA",
    "sg:tags":[
        "pet",
        "mfg",
        "supply"
    ],
    "wof:name":"Petpro Products Inc",
    "wof:placetype":"venue"
},
  "geometry": {"coordinates":[-118.362717,33.968489],"type":"Point"}
}