{
  "type": "Feature",
  "properties": {
    "addr:full":"340 Victoria St Costa Mesa CA 92627",
    "addr:housenumber":"340",
    "addr:postcode":"92627",
    "addr:street":"Victoria St",
    "iso:country":"US",
    "sg:address":"340 Victoria St",
    "sg:city":"Costa Mesa",
    "sg:classifiers":[
        {
            "category":"Health Services",
            "subcategory":"Nursing And Care Facility",
            "type":"Services"
        }
    ],
    "sg:phone":"+1 949 642 0387",
    "sg:postcode":"92627",
    "sg:province":"CA",
    "sg:tags":[
        "home",
        "retirement",
        "community"
    ],
    "wof:name":"Costa Victoria Ctr",
    "wof:placetype":"venue"
},
  "geometry": {"coordinates":[-117.915918,33.652655],"type":"Point"}
}