{
  "type": "Feature",
  "properties": {
    "addr:full":"17554 Patricia Way Grass Valley CA 95949",
    "addr:housenumber":"17554",
    "addr:postcode":"95949",
    "addr:street":"Patricia Way",
    "iso:country":"US",
    "sg:address":"17554 Patricia Way",
    "sg:city":"Grass Valley",
    "sg:classifiers":[
        {
            "category":"Retail",
            "subcategory":"Veterinary Services",
            "type":"Services"
        }
    ],
    "sg:phone":"+1 530 273 0123",
    "sg:postcode":"95949",
    "sg:province":"CA",
    "sg:tags":[
        "veterinarian"
    ],
    "wof:name":"Wolf Creek Veterinary",
    "wof:placetype":"venue"
},
  "geometry": {"coordinates":[-121.053285,39.10628],"type":"Point"}
}