{
  "type": "Feature",
  "properties": {
    "iso:country":"US",
    "sg:address":"16830 Ventura Blvd",
    "sg:city":"Encino",
    "sg:classifiers":[
        {
            "category":"Education",
            "subcategory":"College",
            "type":"Public Place"
        }
    ],
    "sg:phone":"+1 818 501 1600",
    "sg:postcode":"91436",
    "sg:province":"CA",
    "sg:tags":[
        "academic",
        "school"
    ],
    "sg:website":"www.pepperdine.edu",
    "wof:name":"Pepperdine University",
    "wof:placetype":"venue"
},
  "geometry": {"coordinates":[-118.499932,34.158903],"type":"Point"}
}