{
  "type": "Feature",
  "properties": {
    "iso:country":"US",
    "sg:address":"2422 33rd Avenue",
    "sg:city":"San Francisco",
    "sg:classifiers":[
        {
            "category":"Building & Trades",
            "subcategory":"Cleaning & Sanitation",
            "type":"Services"
        },
        {
            "category":"Home & Garden",
            "subcategory":"Carpets & Floor Coverings",
            "type":"Retail Goods"
        }
    ],
    "sg:phone":"+1 415 681 0377",
    "sg:postcode":"94116",
    "sg:province":"CA",
    "sg:tags":[
        "carpeting"
    ],
    "wof:name":"Advanced Cleaning Systems",
    "wof:placetype":"venue"
},
  "geometry": {"coordinates":[-122.49099699999999,37.742298],"type":"Point"}
}