{
  "type": "Feature",
  "properties": {
    "iso:country":"US",
    "sg:address":"151 Gilbert Dr",
    "sg:city":"Applegate",
    "sg:classifiers":[
        {
            "category":"Building & Trades",
            "subcategory":"Construction",
            "type":"Services"
        }
    ],
    "sg:phone":"+1 530 878 2066",
    "sg:postcode":"95703",
    "sg:province":"CA",
    "sg:tags":[
        "house"
    ],
    "wof:name":"H&H Construction",
    "wof:placetype":"venue"
},
  "geometry": {"coordinates":[-121.000732,38.988349],"type":"Point"}
}