{
  "type": "Feature",
  "properties": {
    "addr:full":"526 S Lovers Ln Visalia CA 93292",
    "addr:housenumber":"526",
    "addr:postcode":"93292",
    "addr:street":"S Lovers Ln",
    "iso:country":"US",
    "sg:address":"526 S Lovers Ln",
    "sg:city":"Visalia",
    "sg:classifiers":[
        {
            "category":"Real Estate",
            "subcategory":"Real Estate Agent",
            "type":"Services"
        }
    ],
    "sg:phone":"+1 559 636 8100",
    "sg:postcode":"93292",
    "sg:province":"CA",
    "wof:name":"Ironwood Properties",
    "wof:placetype":"venue"
},
  "geometry": {"coordinates":[-119.26068600000001,36.32689],"type":"Point"}
}