{
  "type": "Feature",
  "properties": {
    "iso:country":"US",
    "sg:address":"14531 Lolly Ln",
    "sg:city":"Sonora",
    "sg:classifiers":[
        {
            "category":"Real Estate",
            "subcategory":"Real Estate Operator",
            "type":"Services"
        }
    ],
    "sg:phone":"+1 209 532 6520",
    "sg:postcode":"95370",
    "sg:province":"CA",
    "sg:tags":[
        "apartment"
    ],
    "wof:name":"Mono Village Apartments",
    "wof:placetype":"venue"
},
  "geometry": {"coordinates":[-120.326109,37.976168],"type":"Point"}
}