{
  "type": "Feature",
  "properties": {
    "addr:full":"7333 Lasaine Ave Van Nuys CA 91406",
    "addr:housenumber":"7333",
    "addr:postcode":"91406",
    "addr:street":"Lasaine Ave",
    "iso:country":"US",
    "sg:address":"7333 Lasaine Ave",
    "sg:city":"Van Nuys",
    "sg:classifiers":[
        {
            "category":"Shopping",
            "subcategory":"Gifts & Souvenirs",
            "type":"Retail Goods"
        }
    ],
    "sg:phone":"+1 818 760 6460",
    "sg:postcode":"91406",
    "sg:province":"CA",
    "sg:tags":[
        "party",
        "supply"
    ],
    "wof:name":"Cabrera's Balloons",
    "wof:placetype":"venue"
},
  "geometry": {"coordinates":[-118.510965,34.203409],"type":"Point"}
}