{
  "type": "Feature",
  "properties": {
    "addr:full":"195 Farnum St San Francisco CA 94131",
    "addr:housenumber":"195",
    "addr:postcode":"94131",
    "addr:street":"Farnum St",
    "iso:country":"US",
    "sg:address":"195 Farnum St",
    "sg:city":"San Francisco",
    "sg:classifiers":[
        {
            "category":"Professional",
            "type":"Services"
        }
    ],
    "sg:phone":"+1 415 333 1043",
    "sg:postcode":"94131",
    "sg:province":"CA",
    "wof:name":"Dave Minaksi",
    "wof:placetype":"venue"
},
  "geometry": {"coordinates":[-122.43419,37.739419],"type":"Point"}
}