{
  "type": "Feature",
  "properties": {
    "addr:full":"16100 Sand Canyon Ave Suite 270 Irvine CA 92618",
    "addr:housenumber":"16100",
    "addr:postcode":"92618",
    "addr:street":"Sand Canyon Ave Suite 270",
    "iso:country":"US",
    "sg:address":"16100 Sand Canyon Ave Suite 270",
    "sg:city":"Irvine",
    "sg:classifiers":[
        {
            "category":"Health Services",
            "subcategory":"Dentist",
            "type":"Services"
        }
    ],
    "sg:phone":"+1 949 727 9077",
    "sg:postcode":"92618",
    "sg:province":"CA",
    "sg:website":"www.sandcanyondentistry.com/page...",
    "wof:name":"Sand Canyon Dental",
    "wof:placetype":"venue"
},
  "geometry": {"coordinates":[-117.77179700000001,33.662862],"type":"Point"}
}