{
  "type": "Feature",
  "properties": {
    "addr:full":"305 S Brookhurst St Anaheim CA 92804",
    "addr:housenumber":"305",
    "addr:postcode":"92804",
    "addr:street":"S Brookhurst St",
    "iso:country":"US",
    "sg:address":"305 S Brookhurst St",
    "sg:city":"Anaheim",
    "sg:classifiers":[
        {
            "category":"Restaurant",
            "type":"Food & Drink"
        },
        {
            "category":"Food & Beverages",
            "subcategory":"Ethnic Foods",
            "type":"Retail Goods"
        }
    ],
    "sg:phone":"+1 714 520 7935",
    "sg:postcode":"92804",
    "sg:province":"CA",
    "sg:tags":[
        "mexican"
    ],
    "wof:name":"Taqueria Arandas",
    "wof:placetype":"venue"
},
  "geometry": {"coordinates":[-117.959,33.828701],"type":"Point"}
}