{
  "type": "Feature",
  "properties": {
    "iso:country":"US",
    "sg:address":"2060 E Ave de Los Arboles",
    "sg:city":"Thousand Oaks",
    "sg:classifiers":[
        {
            "category":"Retail",
            "subcategory":"Auto Rental",
            "type":"Services"
        }
    ],
    "sg:phone":"+1 805 532 2272",
    "sg:postcode":"91362",
    "sg:province":"CA",
    "sg:tags":[
        "automobile",
        "leasing"
    ],
    "wof:name":"New Car Consultants",
    "wof:placetype":"venue"
},
  "geometry": {"coordinates":[-118.84338,34.211186],"type":"Point"}
}