{
  "type": "Feature",
  "properties": {
    "iso:country":"US",
    "sg:address":"2749 E Broadway",
    "sg:city":"Long Beach",
    "sg:classifiers":[
        {
            "category":"Banks & Credit Unions",
            "subcategory":"Bank",
            "type":"Services"
        }
    ],
    "sg:phone":"+1 562 439 0288",
    "sg:postcode":"90803",
    "sg:province":"CA",
    "sg:tags":[
        "loan",
        "real estate"
    ],
    "wof:name":"Metro City Mortgage Corp",
    "wof:placetype":"venue"
},
  "geometry": {"coordinates":[-118.159003,33.765575],"type":"Point"}
}