{
  "type": "Feature",
  "properties": {
    "addr:full":"2045 Preisker Ln Santa Maria CA 93454",
    "addr:housenumber":"2045",
    "addr:postcode":"93454",
    "addr:street":"Preisker Ln",
    "iso:country":"US",
    "sg:address":"2045 Preisker Ln",
    "sg:city":"Santa Maria",
    "sg:classifiers":[
        {
            "category":"Professional",
            "subcategory":"Business Services",
            "type":"Services"
        }
    ],
    "sg:phone":"+1 805 928 6392",
    "sg:postcode":"93454",
    "sg:province":"CA",
    "sg:tags":[
        "inspection"
    ],
    "sg:website":"www.diversifiedts.com",
    "wof:name":"Diversified Technology",
    "wof:placetype":"venue"
},
  "geometry": {"coordinates":[-120.43280900000001,34.978821],"type":"Point"}
}