{
  "type": "Feature",
  "properties": {
    "addr:full":"7525 Metropolitan Dr San Diego CA 92108",
    "addr:housenumber":"7525",
    "addr:postcode":"92108",
    "addr:street":"Metropolitan Dr",
    "iso:country":"US",
    "sg:address":"7525 Metropolitan Dr",
    "sg:city":"San Diego",
    "sg:classifiers":[
        {
            "category":"Building & Trades",
            "subcategory":"Construction",
            "type":"Services"
        }
    ],
    "sg:phone":"+1 619 291 6958",
    "sg:postcode":"92108",
    "sg:province":"CA",
    "sg:tags":[
        "contractor"
    ],
    "wof:name":"Patriot Environmental Lab Serv",
    "wof:placetype":"venue"
},
  "geometry": {"coordinates":[-117.159249,32.77672],"type":"Point"}
}