{
  "type": "Feature",
  "properties": {
    "iso:country":"US",
    "sg:address":"1334 Brommer St",
    "sg:city":"Santa Cruz",
    "sg:classifiers":[
        {
            "category":"Banks & Credit Unions",
            "subcategory":"Bank",
            "type":"Services"
        }
    ],
    "sg:phone":"+1 831 476 1425",
    "sg:postcode":"95062",
    "sg:province":"CA",
    "sg:tags":[
        "loan"
    ],
    "wof:name":"Equity Freedom Group",
    "wof:placetype":"venue"
},
  "geometry": {"coordinates":[-121.987658,36.971641],"type":"Point"}
}