{
  "type": "Feature",
  "properties": {
    "addr:full":"25571 Jeronimo Rd Ste 8 Mission Viejo CA 92691",
    "addr:housenumber":"25571",
    "addr:postcode":"92691",
    "addr:street":"Jeronimo Rd Ste 8",
    "iso:country":"US",
    "sg:address":"25571 Jeronimo Rd Ste 8",
    "sg:city":"Mission Viejo",
    "sg:classifiers":[
        {
            "category":"Restaurant",
            "type":"Food & Drink"
        }
    ],
    "sg:phone":"+1 949 768 0401",
    "sg:postcode":"92691",
    "sg:province":"CA",
    "wof:name":"Maya Inn",
    "wof:placetype":"venue"
},
  "geometry": {"coordinates":[-117.68359599999999,33.622652],"type":"Point"}
}