{
  "type": "Feature",
  "properties": {
    "addr:full":"8880 Rio San Diego Dr San Diego CA 92108",
    "addr:housenumber":"8880",
    "addr:postcode":"92108",
    "addr:street":"Rio San Diego Dr",
    "iso:country":"US",
    "sg:address":"8880 Rio San Diego Dr",
    "sg:city":"San Diego",
    "sg:classifiers":[
        {
            "category":"Wholesale",
            "subcategory":"Scrap",
            "type":"Manufacturing & Wholesale Goods"
        }
    ],
    "sg:phone":"+1 619 392 2755",
    "sg:postcode":"92108",
    "sg:province":"CA",
    "sg:tags":[
        "junk",
        "hauling",
        "removal"
    ],
    "sg:website":"www.bubbamove.com",
    "wof:name":"Bubba's Moving Company",
    "wof:placetype":"venue"
},
  "geometry": {"coordinates":[-117.13849399999999,32.776263],"type":"Point"}
}