{
  "type": "Feature",
  "properties": {
    "addr:full":"199 N 11th St San Jose CA 95112",
    "addr:housenumber":"199",
    "addr:postcode":"95112",
    "addr:street":"N 11Th St",
    "iso:country":"US",
    "sg:address":"199 N 11th St",
    "sg:city":"San Jose",
    "sg:classifiers":[
        {
            "category":"Professional",
            "subcategory":"Advertising",
            "type":"Services"
        }
    ],
    "sg:phone":"+1 408 278 1188",
    "sg:postcode":"95112",
    "sg:province":"CA",
    "sg:tags":[
        "counselor"
    ],
    "wof:name":"Spanishmasters Inc",
    "wof:placetype":"venue"
},
  "geometry": {"coordinates":[-121.881096,37.342684],"type":"Point"}
}