{
  "type": "Feature",
  "properties": {
    "addr:full":"1632 Ocean View Ave Kensington CA 94707",
    "addr:housenumber":"1632",
    "addr:postcode":"94707",
    "addr:street":"Ocean View Ave",
    "iso:country":"US",
    "sg:address":"1632 Ocean View Ave",
    "sg:city":"Kensington",
    "sg:classifiers":[
        {
            "category":"Building & Trades",
            "subcategory":"Plumbing",
            "type":"Services"
        },
        {
            "category":"Building & Trades",
            "subcategory":"Construction",
            "type":"Services"
        }
    ],
    "sg:phone":"+1 510 593 3818",
    "sg:postcode":"94707",
    "sg:province":"CA",
    "sg:tags":[
        "contractor",
        "heating",
        "conditioning/hvac",
        "air"
    ],
    "wof:name":"Heating Experts",
    "wof:placetype":"venue"
},
  "geometry": {"coordinates":[-122.284961,37.899433],"type":"Point"}
}