{
  "type": "Feature",
  "properties": {
    "addr:full":"146 N 3rd Ave Oakdale CA 95361",
    "addr:housenumber":"146",
    "addr:postcode":"95361",
    "addr:street":"N 3Rd Ave",
    "iso:country":"US",
    "sg:address":"146 N 3rd Ave",
    "sg:city":"Oakdale",
    "sg:classifiers":[
        {
            "category":"Shopping",
            "subcategory":"Used Merchandise",
            "type":"Retail Goods"
        }
    ],
    "sg:phone":"+1 209 845 8151",
    "sg:postcode":"95361",
    "sg:province":"CA",
    "sg:tags":[
        "antique"
    ],
    "wof:name":"J & J Antiques & Collectibles",
    "wof:placetype":"venue"
},
  "geometry": {"coordinates":[-120.848426,37.766871],"type":"Point"}
}