{
  "type": "Feature",
  "properties": {
    "iso:country":"US",
    "sg:address":"2006 Winchester Blvd",
    "sg:city":"Campbell",
    "sg:classifiers":[
        {
            "category":"Restaurant",
            "type":"Food & Drink"
        }
    ],
    "sg:menulink":"http://www.allmenus.com/ca/san-jose/150146-subway/menu/",
    "sg:phone":"+1 408 370 9003",
    "sg:postcode":"95008",
    "sg:province":"CA",
    "sg:tags":[
        "american",
        "sandwich"
    ],
    "wof:name":"Subway",
    "wof:placetype":"venue"
},
  "geometry": {"coordinates":[-121.949499,37.28681],"type":"Point"}
}