{
  "type": "Feature",
  "properties": {
    "addr:full":"17700 Castleton St City Of Industry CA 91748",
    "addr:housenumber":"17700",
    "addr:postcode":"91748",
    "addr:street":"Castleton St",
    "iso:country":"US",
    "sg:address":"17700 Castleton St",
    "sg:city":"City Of Industry",
    "sg:classifiers":[
        {
            "category":"Professional",
            "subcategory":"Lawyer & Legal Services",
            "type":"Services"
        }
    ],
    "sg:phone":"+1 626 965 7070",
    "sg:postcode":"91748",
    "sg:province":"CA",
    "sg:tags":[
        "attorney"
    ],
    "wof:name":"GTH Law Group",
    "wof:placetype":"venue"
},
  "geometry": {"coordinates":[-117.917344,33.993027],"type":"Point"}
}