{
  "type": "Feature",
  "properties": {
    "addr:full":"3132 Clairemont Dr San Diego CA 92117",
    "addr:housenumber":"3132",
    "addr:postcode":"92117",
    "addr:street":"Clairemont Dr",
    "iso:country":"US",
    "sg:address":"3132 Clairemont Dr",
    "sg:city":"San Diego",
    "sg:classifiers":[
        {
            "category":"Wholesale",
            "subcategory":"Auto Parts",
            "type":"Manufacturing & Wholesale Goods"
        }
    ],
    "sg:phone":"+1 619 276 8613",
    "sg:postcode":"92117",
    "sg:province":"CA",
    "wof:name":"Larrys Auto Products",
    "wof:placetype":"venue"
},
  "geometry": {"coordinates":[-117.194772,32.798958],"type":"Point"}
}