{
  "type": "Feature",
  "properties": {
    "addr:full":"74841 42nd Ave Palm Desert CA 92260",
    "addr:housenumber":"74841",
    "addr:postcode":"ca 92260",
    "addr:street":"42Nd Ave",
    "iso:country":"US",
    "sg:address":"74841 42nd Ave",
    "sg:city":"Palm Desert",
    "sg:classifiers":[
        {
            "category":"Retail",
            "subcategory":"Auto Repair",
            "type":"Services"
        }
    ],
    "sg:phone":"+1 760 346 6606",
    "sg:postcode":"92260",
    "sg:province":"CA",
    "sg:tags":[
        "repairing",
        "automobile"
    ],
    "wof:name":"Autotechniques",
    "wof:placetype":"venue"
},
  "geometry": {"coordinates":[-116.36083600000001,33.74336],"type":"Point"}
}