{
  "type": "Feature",
  "properties": {
    "iso:country":"US",
    "sg:address":"677 Portola Dr",
    "sg:city":"San Francisco",
    "sg:classifiers":[
        {
            "category":"Real Estate",
            "subcategory":"Real Estate Agent",
            "type":"Services"
        }
    ],
    "sg:phone":"+1 415 664 9175",
    "sg:postcode":"94127",
    "sg:province":"CA",
    "sg:website":"www.devries4sfhomes.com",
    "wof:name":"Andrew de Vries, MBA - Realtor",
    "wof:placetype":"venue"
},
  "geometry": {"coordinates":[-122.453118,37.74474],"type":"Point"}
}