{
  "type": "Feature",
  "properties": {
    "addr:full":"One Market Street Spear Tower #3529 San Francisco CA 94105",
    "addr:postcode":"94105",
    "addr:street":"Market Street",
    "iso:country":"US",
    "sg:address":"One Market Street Spear Tower #3529",
    "sg:city":"San Francisco",
    "sg:classifiers":[
        {
            "category":"Professional",
            "subcategory":"Advertising",
            "type":"Services"
        }
    ],
    "sg:postcode":"94105",
    "sg:province":"CA",
    "sg:tags":[
        "mobile",
        "local",
        "search",
        "advertising",
        "click-to-call"
    ],
    "sg:website":"http://xad.com",
    "wof:name":"xAD",
    "wof:placetype":"venue"
},
  "geometry": {"coordinates":[-122.39630099999999,37.793256],"type":"Point"}
}