{
  "type": "Feature",
  "properties": {
    "addr:full":"5611 Sebastopol Ave Sebastopol CA 95472",
    "addr:housenumber":"5611",
    "addr:postcode":"95472",
    "addr:street":"Sebastopol Ave",
    "iso:country":"US",
    "sg:address":"5611 Sebastopol Ave",
    "sg:city":"Sebastopol",
    "sg:classifiers":[
        {
            "category":"Government",
            "subcategory":"Office",
            "type":"Public Place"
        }
    ],
    "sg:phone":"+1 707 823 3156",
    "sg:postcode":"95472",
    "sg:province":"CA",
    "sg:tags":[
        "state",
        "program",
        "transportation"
    ],
    "wof:name":"Transportation California Dept",
    "wof:placetype":"venue"
},
  "geometry": {"coordinates":[-122.800721,38.408973],"type":"Point"}
}