{
  "type": "Feature",
  "properties": {
    "addr:full":"2140 S el Camino Real San Mateo CA 94403",
    "addr:housenumber":"2140",
    "addr:postcode":"94403",
    "addr:street":"S El Camino Real",
    "iso:country":"US",
    "sg:address":"2140 S el Camino Real",
    "sg:city":"San Mateo",
    "sg:classifiers":[
        {
            "category":"Retail",
            "subcategory":"Repair Shop",
            "type":"Services"
        },
        {
            "category":"Wholesale",
            "subcategory":"Electrical",
            "type":"Manufacturing & Wholesale Goods"
        }
    ],
    "sg:phone":"+1 650 574 8499",
    "sg:postcode":"94403",
    "sg:province":"CA",
    "sg:tags":[
        "shaver",
        "merchandise"
    ],
    "wof:name":"San Mateo Electric Shavers Sls",
    "wof:placetype":"venue"
},
  "geometry": {"coordinates":[-122.307868,37.546408],"type":"Point"}
}