{
  "type": "Feature",
  "properties": {
    "iso:country":"US",
    "sfac:artist":"Piazzoni, Gottardo Fidele Ponziano",
    "sfac:created_at":"01/01/1970 12:32:12 AM +0000",
    "sfac:credit_line":"Purchased for the San Francisco Main Library",
    "sfac:location_description":"de Young Museum",
    "sfac:medium":"Oil",
    "sfac:revision":"2-8fcf1cadeb1aa51865f2a55bf0764020",
    "sfac:title":"The Land",
    "wof:name":"The Land",
    "wof:placetype":"venue"
},
  "geometry": {"coordinates":[-122.467646,37.771503],"type":"Point"}
}