{
  "type": "Feature",
  "properties": {
    "iso:country":"US",
    "sg:address":"7998 Miramar Road",
    "sg:city":"San Diego",
    "sg:classifiers":[
        {
            "category":"Shopping",
            "subcategory":"Clothing, Apparel, & Fashions",
            "type":"Retail Goods"
        },
        {
            "category":"Cinema",
            "subcategory":"Movie Rental",
            "type":"Entertainment"
        },
        {
            "category":"Shopping",
            "subcategory":"Books",
            "type":"Retail Goods"
        }
    ],
    "sg:phone":"+1 858 549 8014",
    "sg:postcode":"92126",
    "sg:province":"CA",
    "sg:tags":[
        "game",
        "lingerie",
        "video",
        "bookstore"
    ],
    "wof:name":"F Street Adult Video & Gifts",
    "wof:placetype":"venue"
},
  "geometry": {"coordinates":[-117.14672,32.887338],"type":"Point"}
}