{
  "type": "Feature",
  "properties": {
    "addr:full":"112 Robin Hill Rd Goleta CA 93117",
    "addr:housenumber":"112",
    "addr:postcode":"93117",
    "addr:street":"Robin Hill Rd",
    "iso:country":"US",
    "sg:address":"112 Robin Hill Rd",
    "sg:city":"Goleta",
    "sg:classifiers":[
        {
            "category":"Manufacturing",
            "subcategory":"Tools & Machinery",
            "type":"Manufacturing & Wholesale Goods"
        }
    ],
    "sg:phone":"+1 805 967 1400",
    "sg:postcode":"93117",
    "sg:province":"CA",
    "sg:tags":[
        "analytical",
        "instrument",
        "optical",
        "mfg"
    ],
    "wof:name":"Veeco Instruments Inc",
    "wof:placetype":"venue"
},
  "geometry": {"coordinates":[-119.844701,34.432578],"type":"Point"}
}