{
  "type": "Feature",
  "properties": {
    "addr:full":"4200 California St San Francisco CA 94118",
    "addr:housenumber":"4200",
    "addr:postcode":"94118",
    "addr:street":"California St",
    "iso:country":"US",
    "sg:address":"4200 California St",
    "sg:city":"San Francisco",
    "sg:classifiers":[
        {
            "category":"Personal",
            "type":"Services"
        }
    ],
    "sg:phone":"+1 415 305 8118",
    "sg:postcode":"94118",
    "sg:province":"CA",
    "sg:tags":[
        "therapist",
        "massage"
    ],
    "wof:name":"Hot Stone Therapy",
    "wof:placetype":"venue"
},
  "geometry": {"coordinates":[-122.463503,37.785131],"type":"Point"}
}