{
  "type": "Feature",
  "properties": {
    "addr:full":"3608 N Armstrong Ave Fresno CA 93727",
    "addr:housenumber":"3608",
    "addr:postcode":"93727",
    "addr:street":"N Armstrong Ave",
    "iso:country":"US",
    "sg:address":"3608 N Armstrong Ave",
    "sg:city":"Fresno",
    "sg:classifiers":[
        {
            "category":"Farming",
            "subcategory":"Vineyard",
            "type":"Manufacturing & Wholesale Goods"
        }
    ],
    "sg:phone":"+1 559 291 6414",
    "sg:postcode":"93727",
    "sg:province":"CA",
    "sg:tags":[
        "grape"
    ],
    "wof:name":"William Graham",
    "wof:placetype":"venue"
},
  "geometry": {"coordinates":[-119.672989,36.792168],"type":"Point"}
}