{
  "type": "Feature",
  "properties": {
    "addr:full":"4907 Topanga Canyon Blvd Woodland Hills CA 91364",
    "addr:housenumber":"4907",
    "addr:postcode":"91364",
    "addr:street":"Topanga Canyon Blvd",
    "iso:country":"US",
    "sg:address":"4907 Topanga Canyon Blvd",
    "sg:city":"Woodland Hills",
    "sg:classifiers":[
        {
            "category":"Health Services",
            "subcategory":"Health Practitioner",
            "type":"Services"
        }
    ],
    "sg:phone":"+1 818 292 4866",
    "sg:postcode":"91364",
    "sg:province":"CA",
    "sg:tags":[
        "nutritionist"
    ],
    "wof:name":"Le Desma N Gladys",
    "wof:placetype":"venue"
},
  "geometry": {"coordinates":[-118.605889,34.15752],"type":"Point"}
}