{
  "type": "Feature",
  "properties": {
    "addr:full":"630 N Gardner St Los Angeles CA 90036",
    "addr:housenumber":"630",
    "addr:postcode":"90036",
    "addr:street":"N Gardner St",
    "iso:country":"US",
    "sg:address":"630 N Gardner St",
    "sg:city":"Los Angeles",
    "sg:classifiers":[
        {
            "category":"Manufacturing",
            "subcategory":"Glass & Minerals",
            "type":"Manufacturing & Wholesale Goods"
        }
    ],
    "sg:phone":"+1 323 655 8321",
    "sg:postcode":"90036",
    "sg:province":"CA",
    "sg:tags":[
        "product",
        "nonmetallic",
        "mfg"
    ],
    "wof:name":"Stempel Sculpture Studio",
    "wof:placetype":"venue"
},
  "geometry": {"coordinates":[-118.35315,34.083078],"type":"Point"}
}