{
  "type": "Feature",
  "properties": {
    "addr:full":"17612 Beach Boulevard Huntington Beach CA 92647",
    "addr:housenumber":"17612",
    "addr:postcode":"92647",
    "addr:street":"Beach Boulevard",
    "iso:country":"US",
    "sg:address":"17612 Beach Boulevard",
    "sg:city":"Huntington Beach",
    "sg:classifiers":[
        {
            "category":"Health Services",
            "subcategory":"Dentist",
            "type":"Services"
        }
    ],
    "sg:phone":"+1 714 843 6288",
    "sg:postcode":"92647",
    "sg:province":"CA",
    "wof:name":"Guzman Ria M DDS",
    "wof:placetype":"venue"
},
  "geometry": {"coordinates":[-117.989108,33.70707],"type":"Point"}
}