{
  "type": "Feature",
  "properties": {
    "iso:country":"US",
    "sg:address":"1663 Branham Ln",
    "sg:city":"San Jose",
    "sg:classifiers":[
        {
            "category":"Building & Trades",
            "subcategory":"Landscaping Services",
            "type":"Services"
        }
    ],
    "sg:phone":"+1 408 445 9782",
    "sg:postcode":"95118",
    "sg:province":"CA",
    "sg:tags":[
        "tree"
    ],
    "wof:name":"Ed's Tree Svc",
    "wof:placetype":"venue"
},
  "geometry": {"coordinates":[-121.905141,37.252606],"type":"Point"}
}