{
  "type": "Feature",
  "properties": {
    "addr:full":"30980 Dyer St Union City CA 94587",
    "addr:housenumber":"30980",
    "addr:postcode":"94587",
    "addr:street":"Dyer St",
    "iso:country":"US",
    "sg:address":"30980 Dyer St",
    "sg:city":"Union City",
    "sg:classifiers":[
        {
            "category":"Restaurant",
            "type":"Food & Drink"
        }
    ],
    "sg:menulink":"http://www.allmenus.com/ca/fremont/89894-applebees/menu/",
    "sg:phone":"+1 510 324 6300",
    "sg:postcode":"94587",
    "sg:province":"CA",
    "sg:tags":[
        "burger",
        "american",
        "sandwich",
        "soup"
    ],
    "wof:name":"Applebee's",
    "wof:placetype":"venue"
},
  "geometry": {"coordinates":[-122.06988800000001,37.60149],"type":"Point"}
}