{
  "type": "Feature",
  "properties": {
    "iso:country":"US",
    "sg:address":"212 W 8th St",
    "sg:city":"Los Angeles",
    "sg:classifiers":[
        {
            "category":"Food & Beverages",
            "subcategory":"Bakery",
            "type":"Retail Goods"
        }
    ],
    "sg:phone":"+1 213 489 3195",
    "sg:postcode":"90014",
    "sg:province":"CA",
    "sg:tags":[
        "donut",
        "doughnut"
    ],
    "wof:name":"O & K Donuts",
    "wof:placetype":"venue"
},
  "geometry": {"coordinates":[-118.253998,34.043701],"type":"Point"}
}