{
  "type": "Feature",
  "properties": {
    "iso:country":"US",
    "sg:address":"3333 N Texas St",
    "sg:city":"Fairfield",
    "sg:classifiers":[
        {
            "category":"Bars & Pubs",
            "type":"Food & Drink"
        },
        {
            "category":"Restaurant",
            "type":"Food & Drink"
        }
    ],
    "sg:phone":"+1 707 422 2908",
    "sg:postcode":"94533",
    "sg:province":"CA",
    "sg:tags":[
        "brew",
        "style",
        "family"
    ],
    "wof:name":"Muffin Treat, Inc",
    "wof:placetype":"venue"
},
  "geometry": {"coordinates":[-122.034113,38.290091],"type":"Point"}
}