{
  "type": "Feature",
  "properties": {
    "addr:full":"2344 E 8th St National City CA 91950",
    "addr:housenumber":"2344",
    "addr:postcode":"91950",
    "addr:street":"E 8Th St",
    "iso:country":"US",
    "sg:address":"2344 E 8th St",
    "sg:city":"National City",
    "sg:classifiers":[
        {
            "category":"Restaurant",
            "type":"Food & Drink"
        }
    ],
    "sg:phone":"+1 619 479 8994",
    "sg:postcode":"91950",
    "sg:province":"CA",
    "sg:tags":[
        "vietnamese"
    ],
    "wof:name":"Pho Nam Cali",
    "wof:placetype":"venue"
},
  "geometry": {"coordinates":[-117.08251300000001,32.682434],"type":"Point"}
}