{
  "type": "Feature",
  "properties": {
    "iso:country":"US",
    "sg:address":"3744 Main St",
    "sg:city":"Riverside",
    "sg:classifiers":[
        {
            "category":"Personal",
            "subcategory":"Beauty Salon",
            "type":"Services"
        }
    ],
    "sg:phone":"+1 951 276 1116",
    "sg:postcode":"92501",
    "sg:province":"CA",
    "sg:tags":[
        "aromatherapy"
    ],
    "wof:name":"Dragonmarsh",
    "wof:placetype":"venue"
},
  "geometry": {"coordinates":[-117.374135,33.982374],"type":"Point"}
}