{
  "type": "Feature",
  "properties": {
    "addr:full":"24133 Baywood Lane Santa Clarita CA 91350",
    "addr:housenumber":"24133",
    "addr:postcode":"91350",
    "addr:street":"Baywood Lane",
    "iso:country":"US",
    "sg:address":"24133 Baywood Lane",
    "sg:city":"Santa Clarita",
    "sg:classifiers":[
        {
            "category":"Food & Beverages",
            "subcategory":"Bakery",
            "type":"Retail Goods"
        },
        {
            "category":"Bakery",
            "type":"Food & Drink"
        }
    ],
    "sg:phone":"+1 661 287 3900",
    "sg:postcode":"91350",
    "sg:province":"CA",
    "sg:tags":[
        "sandwich"
    ],
    "sg:website":"www.panera-sanfernandovalley.com/",
    "wof:name":"Panera Bread",
    "wof:placetype":"venue"
},
  "geometry": {"coordinates":[-118.560013,34.430279],"type":"Point"}
}