{
  "type": "Feature",
  "properties": {
    "iso:country":"US",
    "sg:address":"13079 Valley Blvd",
    "sg:city":"City Of Industry",
    "sg:classifiers":[
        {
            "category":"Bars & Pubs",
            "type":"Food & Drink"
        }
    ],
    "sg:phone":"+1 626 336 1453",
    "sg:postcode":"91746",
    "sg:province":"CA",
    "sg:tags":[
        "club",
        "night"
    ],
    "wof:name":"Miss Kitty's",
    "wof:placetype":"venue"
},
  "geometry": {"coordinates":[-118.001682,34.052959],"type":"Point"}
}