{
  "type": "Feature",
  "properties": {
    "addr:full":"25857 Singing Hills Dr Apt 101 Valencia CA 91355",
    "addr:housenumber":"25857;101",
    "addr:postcode":"91355",
    "addr:street":"Singing Hills Dr Apt",
    "iso:country":"US",
    "sg:address":"25857 Singing Hills Dr Apt 101",
    "sg:city":"Valencia",
    "sg:classifiers":[
        {
            "category":"Real Estate",
            "subcategory":"Real Estate Operator",
            "type":"Services"
        }
    ],
    "sg:phone":"+1 661 259 3921",
    "sg:postcode":"91355",
    "sg:province":"CA",
    "sg:tags":[
        "apartment"
    ],
    "wof:name":"Valencia Villa Apartments",
    "wof:placetype":"venue"
},
  "geometry": {"coordinates":[-118.560997,34.394402],"type":"Point"}
}