{
  "type": "Feature",
  "properties": {
    "addr:full":"1770 Evergreen St San Diego CA 92106",
    "addr:housenumber":"1770",
    "addr:postcode":"92106",
    "addr:street":"Evergreen St",
    "iso:country":"US",
    "sg:address":"1770 Evergreen St",
    "sg:city":"San Diego",
    "sg:classifiers":[
        {
            "category":"Professional",
            "subcategory":"Advertising",
            "type":"Services"
        }
    ],
    "sg:phone":"+1 619 758 0726",
    "sg:postcode":"92106",
    "sg:province":"CA",
    "sg:tags":[
        "counselor"
    ],
    "wof:name":"Presentation",
    "wof:placetype":"venue"
},
  "geometry": {"coordinates":[-117.22638999999999,32.731578],"type":"Point"}
}