{
  "type": "Feature",
  "properties": {
    "addr:full":"4566 de Celis Pl Encino CA 91436",
    "addr:housenumber":"4566",
    "addr:postcode":"91436",
    "addr:street":"De Celis Pl",
    "iso:country":"US",
    "sg:address":"4566 de Celis Pl",
    "sg:city":"Encino",
    "sg:classifiers":[
        {
            "category":"Building & Trades",
            "subcategory":"Electrical",
            "type":"Services"
        }
    ],
    "sg:phone":"+1 818 981 5989",
    "sg:postcode":"91436",
    "sg:province":"CA",
    "sg:tags":[
        "electric",
        "contractor"
    ],
    "wof:name":"Amp Electric",
    "wof:placetype":"venue"
},
  "geometry": {"coordinates":[-118.493938,34.15339],"type":"Point"}
}