{
  "type": "Feature",
  "properties": {
    "addr:full":"12530 Royal Rd El Cajon CA 92021",
    "addr:housenumber":"12530",
    "addr:postcode":"92021",
    "addr:street":"Royal Rd",
    "iso:country":"US",
    "sg:address":"12530 Royal Rd",
    "sg:city":"El Cajon",
    "sg:classifiers":[
        {
            "category":"Real Estate",
            "subcategory":"Real Estate Operator",
            "type":"Services"
        }
    ],
    "sg:phone":"+1 619 443 2858",
    "sg:postcode":"92021",
    "sg:province":"CA",
    "sg:tags":[
        "mobile",
        "home",
        "community"
    ],
    "wof:name":"Knolls Mobile Estates",
    "wof:placetype":"venue"
},
  "geometry": {"coordinates":[-116.921836,32.824159],"type":"Point"}
}