{
  "type": "Feature",
  "properties": {
    "addr:full":"12731 Towne Center Dr Cerritos CA 90703",
    "addr:housenumber":"12731",
    "addr:postcode":"ca 90703",
    "addr:street":"Towne Center Dr",
    "iso:country":"US",
    "sg:address":"12731 Towne Center Dr",
    "sg:city":"Cerritos",
    "sg:classifiers":[
        {
            "category":"Shopping",
            "type":"Retail Goods"
        }
    ],
    "sg:postcode":"90703",
    "sg:province":"CA",
    "wof:name":"Yankee Candle Company",
    "wof:placetype":"venue"
},
  "geometry": {"coordinates":[-118.06283500000001,33.870321],"type":"Point"}
}