{
  "type": "Feature",
  "properties": {
    "iso:country":"US",
    "sg:address":"3871 Peach Dr",
    "sg:city":"Loomis",
    "sg:classifiers":[
        {
            "category":"Building & Trades",
            "subcategory":"Plumbing",
            "type":"Services"
        }
    ],
    "sg:phone":"+1 916 652 5717",
    "sg:postcode":"95650",
    "sg:province":"CA",
    "sg:tags":[
        "plumbing",
        "contractor"
    ],
    "wof:name":"Mid-Valley Plumbing",
    "wof:placetype":"venue"
},
  "geometry": {"coordinates":[-121.12164,38.81387],"type":"Point"}
}