{
  "type": "Feature",
  "properties": {
    "iso:country":"US",
    "sg:address":"2801 San Pablo Ave",
    "sg:city":"Berkeley",
    "sg:classifiers":[
        {
            "category":"Wholesale",
            "subcategory":"Electrical",
            "type":"Manufacturing & Wholesale Goods"
        }
    ],
    "sg:phone":"+1 510 444 8888",
    "sg:postcode":"94702",
    "sg:province":"CA",
    "sg:tags":[
        "home",
        "alarm",
        "burglar",
        "system"
    ],
    "sg:website":"911alarm.com/",
    "wof:name":"911 Alarm Monitoring Service",
    "wof:placetype":"venue"
},
  "geometry": {"coordinates":[-122.287425,37.855643],"type":"Point"}
}