{
  "type": "Feature",
  "properties": {
    "addr:full":"13811 Bentley Pl Cerritos CA 90703",
    "addr:housenumber":"13811",
    "addr:postcode":"ca 90703",
    "addr:street":"Bentley Pl",
    "iso:country":"US",
    "sg:address":"13811 Bentley Pl",
    "sg:city":"Cerritos",
    "sg:classifiers":[
        {
            "category":"Manufacturing",
            "subcategory":"Retail Goods",
            "type":"Manufacturing & Wholesale Goods"
        }
    ],
    "sg:phone":"+1 562 404 2098",
    "sg:postcode":"90703",
    "sg:province":"CA",
    "sg:tags":[
        "manufacturer"
    ],
    "wof:name":"Sygma Industries Inc",
    "wof:placetype":"venue"
},
  "geometry": {"coordinates":[-118.036356,33.882858],"type":"Point"}
}