{
  "type": "Feature",
  "properties": {
    "iso:country":"US",
    "sg:address":"1551 4th Ave",
    "sg:city":"San Diego",
    "sg:classifiers":[
        {
            "category":"Professional",
            "subcategory":"Computer Services",
            "type":"Services"
        }
    ],
    "sg:phone":"+1 619 699 0767",
    "sg:postcode":"92101",
    "sg:province":"CA",
    "sg:tags":[
        "hardware",
        "provider",
        "internet",
        "software"
    ],
    "wof:name":"Business Ol Com",
    "wof:placetype":"venue"
},
  "geometry": {"coordinates":[-117.161059,32.72145],"type":"Point"}
}