{
  "type": "Feature",
  "properties": {
    "addr:full":"9197 Larga Vista Ct Spring Valley CA 91977",
    "addr:housenumber":"9197",
    "addr:postcode":"91977",
    "addr:street":"Larga Vista Ct",
    "iso:country":"US",
    "sg:address":"9197 Larga Vista Ct",
    "sg:city":"Spring Valley",
    "sg:classifiers":[
        {
            "category":"Shopping",
            "type":"Retail Goods"
        }
    ],
    "sg:phone":"+1 619 469 3538",
    "sg:postcode":"91977",
    "sg:province":"CA",
    "sg:tags":[
        "merchandise"
    ],
    "wof:name":"Harris Treasures",
    "wof:placetype":"venue"
},
  "geometry": {"coordinates":[-117.00290699999999,32.724772],"type":"Point"}
}