{
  "type": "Feature",
  "properties": {
    "addr:full":"713 E 61st St Los Angeles CA 90001",
    "addr:housenumber":"713",
    "addr:postcode":"90001",
    "addr:street":"E 61St St",
    "iso:country":"US",
    "sg:address":"713 E 61st St",
    "sg:city":"Los Angeles",
    "sg:classifiers":[
        {
            "category":"Home & Garden",
            "subcategory":"Furniture",
            "type":"Retail Goods"
        }
    ],
    "sg:phone":"+1 323 983 0121",
    "sg:postcode":"90001",
    "sg:province":"CA",
    "sg:tags":[
        "store"
    ],
    "wof:name":"Adrianas Furniture",
    "wof:placetype":"venue"
},
  "geometry": {"coordinates":[-118.262001,33.984501],"type":"Point"}
}