{
  "type": "Feature",
  "properties": {
    "addr:full":"1430 E Cooley Dr Colton CA 92324",
    "addr:housenumber":"1430",
    "addr:postcode":"92324",
    "addr:street":"E Cooley Dr",
    "iso:country":"US",
    "sg:address":"1430 E Cooley Dr",
    "sg:city":"Colton",
    "sg:classifiers":[
        {
            "category":"Professional",
            "subcategory":"Management & Consulting",
            "type":"Services"
        }
    ],
    "sg:phone":"+1 909 514 0200",
    "sg:postcode":"92324",
    "sg:province":"CA",
    "sg:tags":[
        "personnel",
        "consultant"
    ],
    "wof:name":"Courtesy Staffing",
    "wof:placetype":"venue"
},
  "geometry": {"coordinates":[-117.30050900000001,34.05991],"type":"Point"}
}