{
  "type": "Feature",
  "properties": {
    "addr:full":"7516 Shaffer Rd Winton CA 95388",
    "addr:housenumber":"7516",
    "addr:postcode":"95388",
    "addr:street":"Shaffer Rd",
    "iso:country":"US",
    "sg:address":"7516 Shaffer Rd",
    "sg:city":"Winton",
    "sg:classifiers":[
        {
            "category":"Food & Beverages",
            "subcategory":"Groceries & Convenience Stores",
            "type":"Retail Goods"
        }
    ],
    "sg:phone":"+1 209 358 4681",
    "sg:postcode":"95388",
    "sg:province":"CA",
    "sg:tags":[
        "grocer"
    ],
    "wof:name":"Dutra's Market",
    "wof:placetype":"venue"
},
  "geometry": {"coordinates":[-120.594989,37.397741],"type":"Point"}
}