{
  "type": "Feature",
  "properties": {
    "iso:country":"US",
    "sg:address":"1495 W 9th St",
    "sg:city":"Upland",
    "sg:classifiers":[
        {
            "category":"Manufacturing",
            "subcategory":"Retail Goods",
            "type":"Manufacturing & Wholesale Goods"
        },
        {
            "category":"Manufacturing",
            "subcategory":"Tools & Machinery",
            "type":"Manufacturing & Wholesale Goods"
        }
    ],
    "sg:phone":"+1 909 981 9181",
    "sg:postcode":"91786",
    "sg:province":"CA",
    "sg:tags":[
        "model",
        "product",
        "maker",
        "mfg"
    ],
    "wof:name":"J & G Models",
    "wof:placetype":"venue"
},
  "geometry": {"coordinates":[-117.67118000000001,34.0961],"type":"Point"}
}