{
  "type": "Feature",
  "properties": {
    "addr:full":"520 W Olive Ave Porterville CA 93257",
    "addr:housenumber":"520",
    "addr:postcode":"93257",
    "addr:street":"W Olive Ave",
    "iso:country":"US",
    "sg:address":"520 W Olive Ave",
    "sg:city":"Porterville",
    "sg:classifiers":[
        {
            "category":"Fast Food",
            "type":"Food & Drink"
        },
        {
            "category":"Restaurant",
            "type":"Food & Drink"
        }
    ],
    "sg:phone":"+1 559 782 8228",
    "sg:postcode":"93257",
    "sg:province":"CA",
    "sg:tags":[
        "mexican",
        "take"
    ],
    "wof:name":"Rico Taco",
    "wof:placetype":"venue"
},
  "geometry": {"coordinates":[-119.02928300000001,36.066029],"type":"Point"}
}