{
  "type": "Feature",
  "properties": {
    "iso:country":"US",
    "sg:address":"2314 W Kettleman Ln",
    "sg:city":"Lodi",
    "sg:classifiers":[
        {
            "category":"Food & Beverages",
            "subcategory":"Specialty",
            "type":"Retail Goods"
        }
    ],
    "sg:phone":"+1 209 333 9356",
    "sg:postcode":"95242",
    "sg:province":"CA",
    "sg:tags":[
        "health",
        "diet"
    ],
    "wof:name":"General Nutrition Ctr",
    "wof:placetype":"venue"
},
  "geometry": {"coordinates":[-121.302964,38.115351],"type":"Point"}
}