{
  "type": "Feature",
  "properties": {
    "iso:country":"US",
    "sg:address":"9522 Joyzelle Dr",
    "sg:city":"Garden Grove",
    "sg:classifiers":[
        {
            "category":"Manufacturing",
            "subcategory":"Signs",
            "type":"Manufacturing & Wholesale Goods"
        }
    ],
    "sg:phone":"+1 714 636 2387",
    "sg:postcode":"92841",
    "sg:province":"CA",
    "wof:name":"Grove Sign Co",
    "wof:placetype":"venue"
},
  "geometry": {"coordinates":[-117.964102,33.798098],"type":"Point"}
}