{
  "type": "Feature",
  "properties": {
    "iso:country":"US",
    "sg:address":"1624 Canyon Rd",
    "sg:city":"Spring Valley",
    "sg:classifiers":[
        {
            "category":"Real Estate",
            "subcategory":"Real Estate Operator",
            "type":"Services"
        }
    ],
    "sg:phone":"+1 619 698 5533",
    "sg:postcode":"91977",
    "sg:province":"CA",
    "sg:tags":[
        "apartment"
    ],
    "wof:name":"Hidden Meadows Apartments",
    "wof:placetype":"venue"
},
  "geometry": {"coordinates":[-117.003998,32.7197],"type":"Point"}
}