{
  "type": "Feature",
  "properties": {
    "iso:country":"US",
    "sg:address":"709 N Inglewood Ave",
    "sg:city":"Inglewood",
    "sg:classifiers":[
        {
            "category":"Manufacturing",
            "subcategory":"Printing",
            "type":"Manufacturing & Wholesale Goods"
        }
    ],
    "sg:phone":"+1 310 490 0212",
    "sg:postcode":"90302",
    "sg:province":"CA",
    "sg:tags":[
        "printer"
    ],
    "wof:name":"Datuti Smatgate",
    "wof:placetype":"venue"
},
  "geometry": {"coordinates":[-118.361199,33.971942],"type":"Point"}
}