{
  "type": "Feature",
  "properties": {
    "addr:full":"3400 S el Camino Real San Mateo CA 94403",
    "addr:housenumber":"3400",
    "addr:postcode":"94403",
    "addr:street":"S El Camino Real",
    "iso:country":"US",
    "sg:address":"3400 S el Camino Real",
    "sg:city":"San Mateo",
    "sg:classifiers":[
        {
            "category":"Food & Beverages",
            "subcategory":"Bakery",
            "type":"Retail Goods"
        }
    ],
    "sg:phone":"+1 650 571 5380",
    "sg:postcode":"94403",
    "sg:province":"CA",
    "sg:tags":[
        "baker"
    ],
    "wof:name":"Grain D'Ord",
    "wof:placetype":"venue"
},
  "geometry": {"coordinates":[-122.299347,37.538697],"type":"Point"}
}