{
  "type": "Feature",
  "properties": {
    "iso:country":"US",
    "sg:address":"925 Blossom Hill Road Ofc",
    "sg:city":"San Jose",
    "sg:classifiers":[
        {
            "category":"Shopping",
            "subcategory":"Shoes",
            "type":"Retail Goods"
        }
    ],
    "sg:phone":"+1 408 362 0600",
    "sg:postcode":"95123",
    "sg:province":"CA",
    "sg:tags":[
        "store"
    ],
    "wof:name":"Takken Shoes",
    "wof:placetype":"venue"
},
  "geometry": {"coordinates":[-121.862354,37.250476],"type":"Point"}
}