{
  "type": "Feature",
  "properties": {
    "iso:country":"US",
    "sg:address":"831 Sierra Vista Ave",
    "sg:city":"Mountain View",
    "sg:classifiers":[
        {
            "category":"Building & Trades",
            "subcategory":"Cleaning & Sanitation",
            "type":"Services"
        }
    ],
    "sg:phone":"+1 650 793 2200",
    "sg:postcode":"94024",
    "sg:province":"CA",
    "sg:tags":[
        "home"
    ],
    "sg:website":"www.heavenlymaids.com",
    "wof:name":"Heavenly Maids Cleaning Service",
    "wof:placetype":"venue"
},
  "geometry": {"coordinates":[-122.08880600000001,37.415342],"type":"Point"}
}