{
  "type": "Feature",
  "properties": {
    "iso:country":"US",
    "sg:address":"121 N Joanne Ave",
    "sg:city":"Ventura",
    "sg:classifiers":[
        {
            "category":"Organizations",
            "subcategory":"Non-profit Organization",
            "type":"Services"
        }
    ],
    "sg:phone":"+1 805 641 5800",
    "sg:postcode":"93003",
    "sg:province":"CA",
    "sg:tags":[
        "medical",
        "management"
    ],
    "wof:name":"Buena Vista Medical Management",
    "wof:placetype":"venue"
},
  "geometry": {"coordinates":[-119.256371,34.274606],"type":"Point"}
}