{
  "type": "Feature",
  "properties": {
    "addr:full":"6421 Watt Avenue North Highlands CA 95660",
    "addr:housenumber":"6421",
    "addr:postcode":"95660",
    "addr:street":"Watt Avenue",
    "iso:country":"US",
    "sg:address":"6421 Watt Avenue",
    "sg:city":"North Highlands",
    "sg:classifiers":[
        {
            "category":"Retail",
            "subcategory":"Auto Repair",
            "type":"Services"
        },
        {
            "category":"Government",
            "subcategory":"Office",
            "type":"Public Place"
        }
    ],
    "sg:phone":"+1 916 334 1748",
    "sg:postcode":"95660",
    "sg:province":"CA",
    "sg:tags":[
        "smog",
        "check"
    ],
    "sg:website":"www.innoutsmog.com",
    "wof:name":"In & Out Smog",
    "wof:placetype":"venue"
},
  "geometry": {"coordinates":[-121.38304599999999,38.684328],"type":"Point"}
}