{
  "type": "Feature",
  "properties": {
    "iso:country":"US",
    "sg:address":"562 Manzanita Ave",
    "sg:city":"Chico",
    "sg:classifiers":[
        {
            "category":"Social Services",
            "type":"Services"
        }
    ],
    "sg:phone":"+1 530 891 3667",
    "sg:postcode":"95926",
    "sg:province":"CA",
    "sg:tags":[
        "counselor",
        "marriage",
        "family"
    ],
    "wof:name":"Barbara J Voss-Schmidt",
    "wof:placetype":"venue"
},
  "geometry": {"coordinates":[-121.843284,39.755244],"type":"Point"}
}