{
  "type": "Feature",
  "properties": {
    "iso:country":"US",
    "sg:address":"1004 Dairy Ave",
    "sg:city":"Corcoran",
    "sg:classifiers":[
        {
            "category":"Food & Beverages",
            "subcategory":"Liquor & Beverages",
            "type":"Retail Goods"
        }
    ],
    "sg:phone":"+1 559 992 4344",
    "sg:postcode":"93212",
    "sg:province":"CA",
    "wof:name":"R S Liquor",
    "wof:placetype":"venue"
},
  "geometry": {"coordinates":[-119.572156,36.099817],"type":"Point"}
}