{
  "type": "Feature",
  "properties": {
    "iso:country":"US",
    "sg:address":"18774 Cox Ave",
    "sg:city":"Saratoga",
    "sg:classifiers":[
        {
            "category":"Real Estate",
            "subcategory":"Real Estate Services",
            "type":"Services"
        }
    ],
    "sg:phone":"+1 408 379 9100",
    "sg:postcode":"95070",
    "sg:province":"CA",
    "sg:tags":[
        "management",
        "property"
    ],
    "wof:name":"Sandhill Property Company",
    "wof:placetype":"venue"
},
  "geometry": {"coordinates":[-121.998052,37.280416],"type":"Point"}
}