{
  "type": "Feature",
  "properties": {
    "iso:country":"US",
    "sg:address":"1651 W Foothill Blvd",
    "sg:city":"Upland",
    "sg:classifiers":[
        {
            "category":"Restaurant",
            "type":"Food & Drink"
        }
    ],
    "sg:phone":"+1 909 985 1777",
    "sg:postcode":"91786",
    "sg:province":"CA",
    "wof:name":"Sushi Delight",
    "wof:placetype":"venue"
},
  "geometry": {"coordinates":[-117.685668,34.1069],"type":"Point"}
}