{
  "type": "Feature",
  "properties": {
    "addr:full":"579 W Channel Islands Blvd Port Hueneme CA 93041",
    "addr:housenumber":"579",
    "addr:postcode":"93041",
    "addr:street":"W Channel Islands Blvd",
    "iso:country":"US",
    "sg:address":"579 W Channel Islands Blvd",
    "sg:city":"Port Hueneme",
    "sg:classifiers":[
        {
            "category":"Restaurant",
            "type":"Food & Drink"
        }
    ],
    "sg:phone":"+1 805 985 9905",
    "sg:postcode":"93041",
    "sg:province":"CA",
    "sg:website":"www.subway.com",
    "wof:name":"Subway Sandwiches & Salads",
    "wof:placetype":"venue"
},
  "geometry": {"coordinates":[-119.21387799999999,34.175846],"type":"Point"}
}