{
  "type": "Feature",
  "properties": {
    "iso:country":"US",
    "sg:address":"1801 Main St",
    "sg:city":"Susanville",
    "sg:classifiers":[
        {
            "category":"Government",
            "subcategory":"Police Station",
            "type":"Public Place"
        }
    ],
    "sg:phone":"+1 530 257 2171",
    "sg:postcode":"96130",
    "sg:province":"CA",
    "sg:tags":[
        "department"
    ],
    "wof:name":"Susanville Police Dept",
    "wof:placetype":"venue"
},
  "geometry": {"coordinates":[-120.64744399999999,40.415126],"type":"Point"}
}