{
  "type": "Feature",
  "properties": {
    "addr:full":"22445 Gilmore St West Hills CA 91307",
    "addr:housenumber":"22445",
    "addr:postcode":"91307",
    "addr:street":"Gilmore St",
    "iso:country":"US",
    "sg:address":"22445 Gilmore St",
    "sg:city":"West Hills",
    "sg:classifiers":[
        {
            "category":"Professional",
            "type":"Services"
        }
    ],
    "sg:phone":"+1 310 516 6302",
    "sg:postcode":"91307",
    "sg:province":"CA",
    "wof:name":"World Class Interpreting Svc",
    "wof:placetype":"venue"
},
  "geometry": {"coordinates":[-118.618995,34.187746],"type":"Point"}
}