{
  "type": "Feature",
  "properties": {
    "addr:full":"1900 Central Ave Mckinleyville CA 95519",
    "addr:housenumber":"1900",
    "addr:postcode":"95519",
    "addr:street":"Central Ave",
    "iso:country":"US",
    "sg:address":"1900 Central Ave",
    "sg:city":"Mckinleyville",
    "sg:classifiers":[
        {
            "category":"Retail",
            "subcategory":"Auto Repair",
            "type":"Services"
        }
    ],
    "sg:phone":"+1 707 822 7714",
    "sg:postcode":"95519",
    "sg:province":"CA",
    "sg:tags":[
        "body",
        "automobile",
        "painting",
        "repairing"
    ],
    "wof:name":"Opie's Body Shop",
    "wof:placetype":"venue"
},
  "geometry": {"coordinates":[-124.10095200000001,40.939522],"type":"Point"}
}