{
  "type": "Feature",
  "properties": {
    "iso:country":"US",
    "sg:address":"928 S Western Ave",
    "sg:city":"Los Angeles",
    "sg:classifiers":[
        {
            "category":"Shopping",
            "type":"Retail Goods"
        }
    ],
    "sg:phone":"+1 213 427 0088",
    "sg:postcode":"90006",
    "sg:province":"CA",
    "sg:tags":[
        "merchandise"
    ],
    "wof:name":"Vibendi",
    "wof:placetype":"venue"
},
  "geometry": {"coordinates":[-118.308987,34.055475],"type":"Point"}
}