{
  "type": "Feature",
  "properties": {
    "iso:country":"US",
    "sg:address":"1424 Continental St",
    "sg:city":"San Diego",
    "sg:classifiers":[
        {
            "category":"Airport",
            "type":"Transportation"
        }
    ],
    "sg:phone":"+1 619 424 0455",
    "sg:postcode":"92154",
    "sg:province":"CA",
    "wof:name":"Brown Field Municipal Airport",
    "wof:placetype":"venue"
},
  "geometry": {"coordinates":[-116.984539,32.568262],"type":"Point"}
}