{
  "type": "Feature",
  "properties": {
    "iso:country":"US",
    "sg:address":"1220 Pennsylvania Ave",
    "sg:city":"San Francisco",
    "sg:classifiers":[
        {
            "category":"Retail",
            "subcategory":"Auto Repair",
            "type":"Services"
        }
    ],
    "sg:phone":"+1 415 643 7467",
    "sg:postcode":"94107",
    "sg:province":"CA",
    "sg:tags":[
        "motorcycle"
    ],
    "sg:website":"www.sfvintagecycle.com",
    "wof:name":"SF Vintage Cycle",
    "wof:placetype":"venue"
},
  "geometry": {"coordinates":[-122.39262600000001,37.751227],"type":"Point"}
}