{
  "type": "Feature",
  "properties": {
    "addr:full":"171 N 2nd St Grover Beach CA 93433",
    "addr:housenumber":"171",
    "addr:postcode":"93433",
    "addr:street":"N 2Nd St",
    "iso:country":"US",
    "sg:address":"171 N 2nd St",
    "sg:city":"Grover Beach",
    "sg:classifiers":[
        {
            "category":"Recreation",
            "type":"Entertainment"
        }
    ],
    "sg:phone":"+1 805 473 1610",
    "sg:postcode":"93433",
    "sg:province":"CA",
    "sg:tags":[
        "scooter",
        "motorcycle",
        "motor"
    ],
    "wof:name":"Arnie's ATV Rentals",
    "wof:placetype":"venue"
},
  "geometry": {"coordinates":[-120.628927,35.122231],"type":"Point"}
}