{
  "type": "Feature",
  "properties": {
    "iso:country":"US",
    "sg:address":"15231 Alton Pkwy",
    "sg:city":"Irvine",
    "sg:classifiers":[
        {
            "category":"Professional",
            "type":"Services"
        }
    ],
    "sg:phone":"+1 949 417 0750",
    "sg:postcode":"92618",
    "sg:province":"CA",
    "wof:name":"Genself Corp",
    "wof:placetype":"venue"
},
  "geometry": {"coordinates":[-117.729249,33.647499],"type":"Point"}
}