{
  "type": "Feature",
  "properties": {
    "addr:full":"1927 E 8th St Davis CA 95616",
    "addr:housenumber":"1927",
    "addr:postcode":"95616",
    "addr:street":"E 8Th St",
    "iso:country":"US",
    "sg:address":"1927 E 8th St",
    "sg:city":"Davis",
    "sg:classifiers":[
        {
            "category":"Building & Trades",
            "subcategory":"Landscaping Services",
            "type":"Services"
        }
    ],
    "sg:phone":"+1 530 757 1355",
    "sg:postcode":"95616",
    "sg:province":"CA",
    "sg:tags":[
        "horticultural",
        "complete"
    ],
    "wof:name":"Empire Landscaping",
    "wof:placetype":"venue"
},
  "geometry": {"coordinates":[-121.730259,38.55347],"type":"Point"}
}