{
  "type": "Feature",
  "properties": {
    "iso:country":"US",
    "sg:address":"840 Newport Center Drive",
    "sg:city":"Newport Beach",
    "sg:classifiers":[
        {
            "category":"Professional",
            "subcategory":"Lawyer & Legal Services",
            "type":"Services"
        }
    ],
    "sg:phone":"+1 949 760 0991",
    "sg:postcode":"92660",
    "sg:province":"CA",
    "wof:name":"Pierotti Anthony W",
    "wof:placetype":"venue"
},
  "geometry": {"coordinates":[-117.87830099999999,33.618064],"type":"Point"}
}