{
  "type": "Feature",
  "properties": {
    "iso:country":"US",
    "sg:address":"2200 W 3rd Street Suite 500",
    "sg:city":"Los Angeles",
    "sg:classifiers":[
        {
            "category":"Health Services",
            "subcategory":"Doctor",
            "type":"Services"
        }
    ],
    "sg:phone":"+1 213 480 8747",
    "sg:postcode":"90057",
    "sg:province":"CA",
    "wof:name":"Isis Urologic & Transplant Institue",
    "wof:placetype":"venue"
},
  "geometry": {"coordinates":[-118.273802,34.063338],"type":"Point"}
}