{
  "type": "Feature",
  "properties": {
    "iso:country":"US",
    "sg:address":"126 Union Ave",
    "sg:city":"Bakersfield",
    "sg:classifiers":[
        {
            "category":"Manufacturing",
            "subcategory":"Rubber & Plastics",
            "type":"Manufacturing & Wholesale Goods"
        },
        {
            "category":"Autos & Motor Vehicles",
            "subcategory":"Auto Supplies",
            "type":"Retail Goods"
        },
        {
            "category":"Retail",
            "subcategory":"Auto Repair",
            "type":"Services"
        }
    ],
    "sg:phone":"+1 661 324 4773",
    "sg:postcode":"93307",
    "sg:province":"CA",
    "sg:tags":[
        "tires-wholesale",
        "tire",
        "automobile",
        "accessory",
        "part",
        "manufacturer"
    ],
    "wof:name":"Hashim's Automotive M & H Racing Tires & Balancing",
    "wof:placetype":"venue"
},
  "geometry": {"coordinates":[-119.0029,35.356856],"type":"Point"}
}