{
  "type": "Feature",
  "properties": {
    "iso:country":"US",
    "sg:address":"6846 Adele Ln",
    "sg:city":"Riverside",
    "sg:classifiers":[
        {
            "category":"Manufacturing",
            "subcategory":"Electronics",
            "type":"Manufacturing & Wholesale Goods"
        },
        {
            "category":"Professional",
            "subcategory":"Printing & Photocopies",
            "type":"Services"
        }
    ],
    "sg:phone":"+1 909 685 7410",
    "sg:postcode":"92509",
    "sg:province":"CA",
    "sg:tags":[
        "printers-equipment",
        "typesetting",
        "supply"
    ],
    "wof:name":"Parent Company Typsg Svc Burea",
    "wof:placetype":"venue"
},
  "geometry": {"coordinates":[-117.421972,34.025276],"type":"Point"}
}