{
  "type": "Feature",
  "properties": {
    "addr:full":"3108 Cherryland Ave Stockton CA 95215",
    "addr:housenumber":"3108",
    "addr:postcode":"95215",
    "addr:street":"Cherryland Ave",
    "iso:country":"US",
    "sg:address":"3108 Cherryland Ave",
    "sg:city":"Stockton",
    "sg:classifiers":[
        {
            "category":"Professional",
            "subcategory":"Detective & Security Services",
            "type":"Services"
        }
    ],
    "sg:phone":"+1 209 462 7600",
    "sg:postcode":"95215",
    "sg:province":"CA",
    "sg:tags":[
        "equipment",
        "system",
        "consultant"
    ],
    "wof:name":"Vanguard Security Services, Inc.",
    "wof:placetype":"venue"
},
  "geometry": {"coordinates":[-121.243287,37.991964],"type":"Point"}
}