{
  "type": "Feature",
  "properties": {
    "iso:country":"US",
    "sg:address":"7 Palomino Rd",
    "sg:city":"Palm Springs",
    "sg:classifiers":[
        {
            "category":"Professional",
            "subcategory":"Management & Consulting",
            "type":"Services"
        }
    ],
    "sg:phone":"+1 760 327 2760",
    "sg:postcode":"92264",
    "sg:province":"CA",
    "sg:tags":[
        "communications",
        "consultant"
    ],
    "wof:name":"K Huskey Assoc",
    "wof:placetype":"venue"
},
  "geometry": {"coordinates":[-116.535887,33.804608],"type":"Point"}
}