{
  "type": "Feature",
  "properties": {
    "iso:country":"US",
    "sg:address":"2026 N Riverside Ave",
    "sg:city":"Rialto",
    "sg:classifiers":[
        {
            "category":"Professional",
            "subcategory":"Management & Consulting",
            "type":"Services"
        }
    ],
    "sg:phone":"+1 951 543 2151",
    "sg:postcode":"92377",
    "sg:province":"CA",
    "sg:tags":[
        "communications",
        "consultant"
    ],
    "wof:name":"Total Communications Solutions",
    "wof:placetype":"venue"
},
  "geometry": {"coordinates":[-117.37070799999999,34.137455],"type":"Point"}
}