{
  "type": "Feature",
  "properties": {
    "addr:full":"9532 W Lilac Rd Escondido CA 92026",
    "addr:housenumber":"9532",
    "addr:postcode":"92026",
    "addr:street":"W Lilac Rd",
    "iso:country":"US",
    "sg:address":"9532 W Lilac Rd",
    "sg:city":"Escondido",
    "sg:classifiers":[
        {
            "category":"Farming",
            "subcategory":"Orchard",
            "type":"Manufacturing & Wholesale Goods"
        }
    ],
    "sg:phone":"+1 760 731 3232",
    "sg:postcode":"92026",
    "sg:province":"CA",
    "wof:name":"R & D Growers",
    "wof:placetype":"venue"
},
  "geometry": {"coordinates":[-117.126862,33.295811],"type":"Point"}
}