{
  "type": "Feature",
  "properties": {
    "iso:country":"US",
    "sg:address":"500 Lake Blvd",
    "sg:city":"Redding",
    "sg:classifiers":[
        {
            "category":"Professional",
            "type":"Services"
        }
    ],
    "sg:phone":"+1 530 242 0231",
    "sg:postcode":"96003",
    "sg:province":"CA",
    "wof:name":"Erin Hennesy",
    "wof:placetype":"venue"
},
  "geometry": {"coordinates":[-122.392189,40.616275],"type":"Point"}
}