{
  "type": "Feature",
  "properties": {
    "addr:full":"1458 Portland Ave Albany CA 94706",
    "addr:housenumber":"1458",
    "addr:postcode":"94706",
    "addr:street":"Portland Ave",
    "iso:country":"US",
    "sg:address":"1458 Portland Ave",
    "sg:city":"Albany",
    "sg:classifiers":[
        {
            "category":"Health Services",
            "subcategory":"Health Practitioner",
            "type":"Services"
        }
    ],
    "sg:phone":"+1 510 525 2255",
    "sg:postcode":"94706",
    "sg:province":"CA",
    "sg:tags":[
        "psychologist"
    ],
    "wof:name":"James H Billings PHD",
    "wof:placetype":"venue"
},
  "geometry": {"coordinates":[-122.287626,37.894645],"type":"Point"}
}