{
  "type": "Feature",
  "properties": {
    "iso:country":"US",
    "sg:address":"3350 Scott Blvd Bldg 54",
    "sg:city":"Santa Clara",
    "sg:classifiers":[
        {
            "category":"Wholesale",
            "subcategory":"Computers",
            "type":"Manufacturing & Wholesale Goods"
        }
    ],
    "sg:phone":"+1 408 450 7881",
    "sg:postcode":"95054",
    "sg:province":"CA",
    "wof:name":"I -Bus Corp.",
    "wof:placetype":"venue"
},
  "geometry": {"coordinates":[-121.981925,37.380248],"type":"Point"}
}