{
  "type": "Feature",
  "properties": {
    "iso:country":"US",
    "sg:address":"613 W Grand Blvd",
    "sg:city":"Corona",
    "sg:classifiers":[
        {
            "category":"Personal",
            "subcategory":"Beauty Salon",
            "type":"Services"
        }
    ],
    "sg:phone":"+1 951 734 9804",
    "sg:postcode":"92882",
    "sg:province":"CA",
    "sg:tags":[
        "manicuring"
    ],
    "wof:name":"Nail Buff",
    "wof:placetype":"venue"
},
  "geometry": {"coordinates":[-117.57393999999999,33.87529],"type":"Point"}
}