{
  "type": "Feature",
  "properties": {
    "addr:full":"3701 S Higuera St San Luis Obispo CA 93401",
    "addr:housenumber":"3701",
    "addr:postcode":"93401",
    "addr:street":"S Higuera St",
    "iso:country":"US",
    "sg:address":"3701 S Higuera St",
    "sg:city":"San Luis Obispo",
    "sg:classifiers":[
        {
            "category":"Health Services",
            "subcategory":"Medical Lab",
            "type":"Services"
        }
    ],
    "sg:phone":"+1 805 541 6033",
    "sg:postcode":"93401",
    "sg:province":"CA",
    "sg:tags":[
        "laboratory"
    ],
    "sg:website":"www.ccpathology.com",
    "wof:name":"Central Coast Pathology Cnslnt",
    "wof:placetype":"venue"
},
  "geometry": {"coordinates":[-120.671437,35.250496],"type":"Point"}
}