{
  "type": "Feature",
  "properties": {
    "addr:full":"25251 Mount Bache Rd Los Gatos CA 95033",
    "addr:housenumber":"25251",
    "addr:postcode":"95033",
    "addr:street":"Mount Bache Rd",
    "iso:country":"US",
    "sg:address":"25251 Mount Bache Rd",
    "sg:city":"Los Gatos",
    "sg:classifiers":[
        {
            "category":"Shopping",
            "subcategory":"Hobbies, Toys, & Games",
            "type":"Retail Goods"
        }
    ],
    "sg:phone":"+1 408 353 1587",
    "sg:postcode":"95033",
    "sg:province":"CA",
    "sg:tags":[
        "supply"
    ],
    "wof:name":"Schocal",
    "wof:placetype":"venue"
},
  "geometry": {"coordinates":[-121.89579500000001,37.104616],"type":"Point"}
}