{
  "type": "Feature",
  "properties": {
    "addr:full":"85 Arthur Rd Martinez CA 94553",
    "addr:housenumber":"85",
    "addr:postcode":"94553",
    "addr:street":"Arthur Rd",
    "iso:country":"US",
    "sg:address":"85 Arthur Rd",
    "sg:city":"Martinez",
    "sg:classifiers":[
        {
            "category":"Building & Trades",
            "subcategory":"Construction",
            "type":"Services"
        }
    ],
    "sg:phone":"+1 925 228 2009",
    "sg:postcode":"94553",
    "sg:province":"CA",
    "sg:tags":[
        "contractor"
    ],
    "wof:name":"Rath Construction",
    "wof:placetype":"venue"
},
  "geometry": {"coordinates":[-122.09026799999999,38.006337],"type":"Point"}
}