{
  "type": "Feature",
  "properties": {
    "iso:country":"US",
    "sg:address":"2214 S Santa Fe Ave",
    "sg:city":"Visalia",
    "sg:classifiers":[
        {
            "category":"Building & Trades",
            "subcategory":"Construction",
            "type":"Services"
        }
    ],
    "sg:phone":"+1 559 635 2868",
    "sg:postcode":"93292",
    "sg:province":"CA",
    "sg:tags":[
        "contractor"
    ],
    "wof:name":"Golden Oaks Construction",
    "wof:placetype":"venue"
},
  "geometry": {"coordinates":[-119.28729800000001,36.310495],"type":"Point"}
}