{
  "type": "Feature",
  "properties": {
    "iso:country":"US",
    "sg:address":"15548 Skylark Ave",
    "sg:city":"Fontana",
    "sg:classifiers":[
        {
            "category":"Building & Trades",
            "subcategory":"Construction",
            "type":"Services"
        }
    ],
    "sg:phone":"+1 909 822 6490",
    "sg:postcode":"92336",
    "sg:province":"CA",
    "sg:tags":[
        "home",
        "builder"
    ],
    "wof:name":"Centex Homes",
    "wof:placetype":"venue"
},
  "geometry": {"coordinates":[-117.463931,34.133642],"type":"Point"}
}