{
  "type": "Feature",
  "properties": {
    "iso:country":"US",
    "sg:address":"140 S Lake Ave",
    "sg:city":"Pasadena",
    "sg:classifiers":[
        {
            "category":"Professional",
            "subcategory":"Lawyer & Legal Services",
            "type":"Services"
        }
    ],
    "sg:phone":"+1 626 585 4176",
    "sg:postcode":"91101",
    "sg:province":"CA",
    "wof:name":"Curtis Tom Attorney At Law",
    "wof:placetype":"venue"
},
  "geometry": {"coordinates":[-118.13200399999999,34.143398],"type":"Point"}
}