{
  "type": "Feature",
  "properties": {
    "iso:country":"US",
    "sg:address":"6050 California Spring Dr",
    "sg:city":"Bakersfield",
    "sg:classifiers":[
        {
            "category":"Professional",
            "subcategory":"Business Services",
            "type":"Services"
        }
    ],
    "sg:phone":"+1 661 869 3909",
    "sg:postcode":"93313",
    "sg:province":"CA",
    "sg:tags":[
        "commercial",
        "bank"
    ],
    "wof:name":"Bank of Sierra",
    "wof:placetype":"venue"
},
  "geometry": {"coordinates":[-119.067967,35.300764],"type":"Point"}
}