{
  "type": "Feature",
  "properties": {
    "addr:full":"1032 E Ave de Los Arboles Thousand Oaks CA 91360",
    "addr:housenumber":"1032",
    "addr:postcode":"91360",
    "addr:street":"E Ave De Los Arboles",
    "iso:country":"US",
    "sg:address":"1032 E Ave de Los Arboles",
    "sg:city":"Thousand Oaks",
    "sg:classifiers":[
        {
            "category":"Food & Beverages",
            "subcategory":"Bakery",
            "type":"Retail Goods"
        }
    ],
    "sg:phone":"+1 805 241 7761",
    "sg:postcode":"91360",
    "sg:province":"CA",
    "sg:tags":[
        "doughnut"
    ],
    "wof:name":"Fresh N Fancy Donuts",
    "wof:placetype":"venue"
},
  "geometry": {"coordinates":[-118.86188799999999,34.215578],"type":"Point"}
}