{
  "type": "Feature",
  "properties": {
    "addr:full":"100 Gregory Ln Concord CA 94523",
    "addr:housenumber":"100",
    "addr:postcode":"94523",
    "addr:street":"Gregory Ln",
    "iso:country":"US",
    "sg:address":"100 Gregory Ln",
    "sg:city":"Concord",
    "sg:classifiers":[
        {
            "category":"Government",
            "subcategory":"Office",
            "type":"Public Place"
        }
    ],
    "sg:phone":"+1 925 671 5209",
    "sg:postcode":"94523",
    "sg:province":"CA",
    "sg:tags":[
        "village"
    ],
    "wof:name":"Pleasant Hill Planning",
    "wof:placetype":"venue"
},
  "geometry": {"coordinates":[-122.064235,37.94795],"type":"Point"}
}