{
  "type": "Feature",
  "properties": {
    "addr:full":"200 E Duarte Rd Arcadia CA 91006",
    "addr:housenumber":"200",
    "addr:postcode":"91006",
    "addr:street":"E Duarte Rd",
    "iso:country":"US",
    "sg:address":"200 E Duarte Rd",
    "sg:city":"Arcadia",
    "sg:classifiers":[
        {
            "category":"Banks & Credit Unions",
            "subcategory":"Bank",
            "type":"Services"
        }
    ],
    "sg:phone":"+1 626 821 4988",
    "sg:postcode":"91006",
    "sg:province":"CA",
    "sg:tags":[
        "saving",
        "commercial"
    ],
    "sg:website":"http://www.eastwest.com",
    "wof:name":"East West Bank",
    "wof:placetype":"venue"
},
  "geometry": {"coordinates":[-118.025032,34.130421],"type":"Point"}
}