{
  "type": "Feature",
  "properties": {
    "addr:full":"699 Higuera St San Luis Obispo CA 93401",
    "addr:housenumber":"699",
    "addr:postcode":"93401",
    "addr:street":"Higuera St",
    "iso:country":"US",
    "sg:address":"699 Higuera St",
    "sg:city":"San Luis Obispo",
    "sg:classifiers":[
        {
            "category":"Shopping",
            "subcategory":"Clothing, Apparel, & Fashions",
            "type":"Retail Goods"
        }
    ],
    "sg:phone":"+1 805 595 3822",
    "sg:postcode":"93401",
    "sg:province":"CA",
    "wof:name":"Uptown Jean Co",
    "wof:placetype":"venue"
},
  "geometry": {"coordinates":[-120.665706,35.278152],"type":"Point"}
}