{
  "type": "Feature",
  "properties": {
    "addr:full":"20440 Rd 7 Chowchilla CA 93610",
    "addr:postcode":"20440;93610",
    "addr:street":"Rd 7",
    "iso:country":"US",
    "sg:address":"20440 Rd 7",
    "sg:city":"Chowchilla",
    "sg:phone":"+1 559 665 4165",
    "sg:postcode":"93610",
    "sg:province":"CA",
    "sg:tags":[
        "farm",
        "cotton"
    ],
    "wof:name":"David L Talley",
    "wof:placetype":"venue"
},
  "geometry": {"coordinates":[-120.419419,37.040765],"type":"Point"}
}