{
  "type": "Feature",
  "properties": {
    "iso:country":"US",
    "sg:address":"1301 Broadway",
    "sg:city":"Millbrae",
    "sg:classifiers":[
        {
            "category":"Professional",
            "subcategory":"Engineering",
            "type":"Services"
        }
    ],
    "sg:phone":"+1 650 616 8000",
    "sg:postcode":"94030",
    "sg:province":"CA",
    "sg:tags":[
        "engineer"
    ],
    "wof:name":"Manna Consultants Inc",
    "wof:placetype":"venue"
},
  "geometry": {"coordinates":[-122.401874,37.609493],"type":"Point"}
}