{
  "type": "Feature",
  "properties": {
    "addr:full":"6840 Edinger Ave Huntington Beach CA 92647",
    "addr:housenumber":"6840",
    "addr:postcode":"92647",
    "addr:street":"Edinger Ave",
    "iso:country":"US",
    "sg:address":"6840 Edinger Ave",
    "sg:city":"Huntington Beach",
    "sg:classifiers":[
        {
            "category":"Ice Cream",
            "type":"Food & Drink"
        }
    ],
    "sg:postcode":"92647",
    "sg:province":"CA",
    "sg:tags":[
        "frozen",
        "yogurt"
    ],
    "sg:website":"www.snoonthego.net",
    "wof:name":"sno ON THE go",
    "wof:placetype":"venue"
},
  "geometry": {"coordinates":[-118.009078,33.730046],"type":"Point"}
}