{
  "type": "Feature",
  "properties": {
    "iso:country":"US",
    "sg:address":"1444 University Avenue",
    "sg:city":"Berkeley",
    "sg:classifiers":[
        {
            "category":"Personal",
            "subcategory":"Beauty Salon",
            "type":"Services"
        }
    ],
    "sg:phone":"+1 510 845 6752",
    "sg:postcode":"94702",
    "sg:province":"CA",
    "sg:tags":[
        "hair"
    ],
    "wof:name":"University Hair Care",
    "wof:placetype":"venue"
},
  "geometry": {"coordinates":[-122.28299699999999,37.869999],"type":"Point"}
}