{
  "type": "Feature",
  "properties": {
    "addr:full":"3467 Sonoma Blvd Vallejo CA 94590",
    "addr:housenumber":"3467",
    "addr:postcode":"94590",
    "addr:street":"Sonoma Blvd",
    "iso:country":"US",
    "sg:address":"3467 Sonoma Blvd",
    "sg:city":"Vallejo",
    "sg:classifiers":[
        {
            "category":"Organizations",
            "subcategory":"Non-profit Organization",
            "type":"Services"
        }
    ],
    "sg:phone":"+1 707 642 2585",
    "sg:postcode":"94590",
    "sg:province":"CA",
    "wof:name":"AIDS Project Napa Valley",
    "wof:placetype":"venue"
},
  "geometry": {"coordinates":[-122.255397,38.122205],"type":"Point"}
}