{
  "type": "Feature",
  "properties": {
    "iso:country":"US",
    "sg:address":"5236 Glide Dr",
    "sg:city":"Davis",
    "sg:classifiers":[
        {
            "category":"Landmark",
            "subcategory":"Tourist Information",
            "type":"Public Place"
        }
    ],
    "sg:phone":"+1 530 756 9407",
    "sg:postcode":"95618",
    "sg:province":"CA",
    "sg:tags":[
        "promoter",
        "tours-operators"
    ],
    "wof:name":"California Presenters",
    "wof:placetype":"venue"
},
  "geometry": {"coordinates":[-121.68401,38.552288],"type":"Point"}
}