{
  "type": "Feature",
  "properties": {
    "iso:country":"US",
    "sg:address":"445 Espinosa Rd",
    "sg:city":"Salinas",
    "sg:classifiers":[
        {
            "category":"Personal",
            "type":"Services"
        }
    ],
    "sg:phone":"+1 831 449 7777",
    "sg:postcode":"93907",
    "sg:province":"CA",
    "sg:tags":[
        "towing"
    ],
    "wof:name":"Doc's Towing & Transport",
    "wof:placetype":"venue"
},
  "geometry": {"coordinates":[-121.681999,36.741699],"type":"Point"}
}