{
  "type": "Feature",
  "properties": {
    "iso:country":"US",
    "sg:address":"31964 Phillips Rd",
    "sg:city":"Mc Farland",
    "sg:classifiers":[
        {
            "category":"Freight",
            "type":"Transportation"
        }
    ],
    "sg:phone":"+1 661 792 2135",
    "sg:postcode":"93250",
    "sg:province":"CA",
    "sg:tags":[
        "warehouse",
        "self",
        "storage"
    ],
    "wof:name":"Calico Compress & Warehouse Co",
    "wof:placetype":"venue"
},
  "geometry": {"coordinates":[-119.19132,35.631022],"type":"Point"}
}