{
  "type": "Feature",
  "properties": {
    "iso:country":"US",
    "sg:address":"20683 Tumeric Way",
    "sg:city":"Jamul",
    "sg:classifiers":[
        {
            "category":"Shopping",
            "subcategory":"Gifts & Souvenirs",
            "type":"Retail Goods"
        }
    ],
    "sg:phone":"+1 619 468 9148",
    "sg:postcode":"91935",
    "sg:province":"CA",
    "sg:tags":[
        "shop"
    ],
    "wof:name":"Feather Way",
    "wof:placetype":"venue"
},
  "geometry": {"coordinates":[-116.704712,32.67577],"type":"Point"}
}