{
  "type": "Feature",
  "properties": {
    "addr:full":"2001 3rd St San Francisco CA 94107",
    "addr:housenumber":"2001",
    "addr:postcode":"94107",
    "addr:street":"3Rd St",
    "iso:country":"US",
    "sg:address":"2001 3rd St",
    "sg:city":"San Francisco",
    "sg:classifiers":[
        {
            "category":"Professional",
            "subcategory":"Printing & Photocopies",
            "type":"Services"
        }
    ],
    "sg:phone":"+1 415 647 3507",
    "sg:postcode":"94107",
    "sg:province":"CA",
    "sg:website":"www.copyworldinc.com",
    "wof:name":"Copyworld",
    "wof:placetype":"venue"
},
  "geometry": {"coordinates":[-122.388679,37.764066],"type":"Point"}
}