{
  "type": "Feature",
  "properties": {
    "iso:country":"US",
    "sg:address":"9921 Romandel Ave",
    "sg:city":"Santa Fe Springs",
    "sg:classifiers":[
        {
            "category":"Manufacturing",
            "subcategory":"Metals",
            "type":"Manufacturing & Wholesale Goods"
        }
    ],
    "sg:phone":"+1 562 946 1717",
    "sg:postcode":"90670",
    "sg:province":"CA",
    "sg:tags":[
        "treating",
        "heat"
    ],
    "wof:name":"H & H Heat Treating",
    "wof:placetype":"venue"
},
  "geometry": {"coordinates":[-118.059695,33.948228],"type":"Point"}
}