{
  "type": "Feature",
  "properties": {
    "iso:country":"US",
    "sg:address":"1927 Harbor Blvd",
    "sg:city":"Costa Mesa",
    "sg:classifiers":[
        {
            "category":"Home & Garden",
            "subcategory":"Building Materials",
            "type":"Retail Goods"
        }
    ],
    "sg:phone":"+1 714 444 0236",
    "sg:postcode":"92627",
    "sg:province":"CA",
    "sg:tags":[
        "wholesale",
        "radiation",
        "equipment"
    ],
    "wof:name":"I & O Trading Company Inc",
    "wof:placetype":"venue"
},
  "geometry": {"coordinates":[-117.919,33.645199],"type":"Point"}
}