{
  "type": "Feature",
  "properties": {
    "iso:country":"US",
    "sg:address":"2508 W Martin Luther King J",
    "sg:city":"Los Angeles",
    "sg:classifiers":[
        {
            "category":"Building & Trades",
            "subcategory":"Plumbing",
            "type":"Services"
        }
    ],
    "sg:phone":"+1 323 295 5487",
    "sg:postcode":"90008",
    "sg:province":"CA",
    "wof:name":"Chris' Professional Plumbing Services",
    "wof:placetype":"venue"
},
  "geometry": {"coordinates":[-118.32044,34.010894],"type":"Point"}
}