{
  "type": "Feature",
  "properties": {
    "iso:country":"US",
    "sg:address":"5555 N Fresno St",
    "sg:city":"Fresno",
    "sg:classifiers":[
        {
            "category":"Health Services",
            "subcategory":"Clinic",
            "type":"Services"
        }
    ],
    "sg:phone":"+1 559 222 5765",
    "sg:postcode":"93710",
    "sg:province":"CA",
    "wof:name":"Center For Continence Care",
    "wof:placetype":"venue"
},
  "geometry": {"coordinates":[-119.78139400000001,36.818367],"type":"Point"}
}