{
  "type": "Feature",
  "properties": {
    "addr:full":"100 S San Gabriel Blvd San Gabriel CA 91776",
    "addr:housenumber":"100",
    "addr:postcode":"91776",
    "addr:street":"S San Gabriel Blvd",
    "iso:country":"US",
    "sg:address":"100 S San Gabriel Blvd",
    "sg:city":"San Gabriel",
    "sg:classifiers":[
        {
            "category":"Retail",
            "subcategory":"Auto Repair",
            "type":"Services"
        }
    ],
    "sg:phone":"+1 626 285 3600",
    "sg:postcode":"91776",
    "sg:province":"CA",
    "sg:tags":[
        "body",
        "shop"
    ],
    "wof:name":"O'donnell Collision Center",
    "wof:placetype":"venue"
},
  "geometry": {"coordinates":[-118.090583,34.102871],"type":"Point"}
}