{
  "type": "Feature",
  "properties": {
    "addr:full":"250 W Main St Ste 101 Woodland CA 95695",
    "addr:housenumber":"250",
    "addr:postcode":"95695",
    "addr:street":"W Main St Ste 101",
    "iso:country":"US",
    "sg:address":"250 W Main St Ste 101",
    "sg:city":"Woodland",
    "sg:classifiers":[
        {
            "category":"Real Estate",
            "subcategory":"Real Estate Services",
            "type":"Services"
        }
    ],
    "sg:phone":"+1 530 666 3321",
    "sg:postcode":"95695",
    "sg:province":"CA",
    "sg:tags":[
        "commercial"
    ],
    "sg:website":"http://www.towerinvestments.com",
    "wof:name":"Tower Investments",
    "wof:placetype":"venue"
},
  "geometry": {"coordinates":[-121.794892,38.67762],"type":"Point"}
}