{
  "type": "Feature",
  "properties": {
    "addr:full":"10621 Calle Lee Los Alamitos CA 90720",
    "addr:housenumber":"10621",
    "addr:postcode":"90720",
    "addr:street":"Calle Lee",
    "iso:country":"US",
    "sg:address":"10621 Calle Lee",
    "sg:city":"Los Alamitos",
    "sg:classifiers":[
        {
            "category":"Professional",
            "subcategory":"Accounting & Tax Preparation",
            "type":"Services"
        }
    ],
    "sg:phone":"+1 562 596 3351",
    "sg:postcode":"90720",
    "sg:province":"CA",
    "sg:tags":[
        "accountant"
    ],
    "wof:name":"Ahlstrom & Baker Cpa's",
    "wof:placetype":"venue"
},
  "geometry": {"coordinates":[-118.056999,33.808701],"type":"Point"}
}