{
  "type": "Feature",
  "properties": {
    "addr:full":"3055 Wilshire Boulevard Los Angeles CA 90010",
    "addr:housenumber":"3055",
    "addr:postcode":"90010",
    "addr:street":"Wilshire Boulevard",
    "iso:country":"US",
    "sg:address":"3055 Wilshire Boulevard",
    "sg:city":"Los Angeles",
    "sg:classifiers":[
        {
            "category":"Education",
            "subcategory":"Kindergarten",
            "type":"Public Place"
        }
    ],
    "sg:phone":"+1 213 365 2378",
    "sg:postcode":"90010",
    "sg:province":"CA",
    "sg:tags":[
        "school",
        "driving"
    ],
    "sg:website":"www.masterdrivingschool.com",
    "wof:name":"Master Driving School",
    "wof:placetype":"venue"
},
  "geometry": {"coordinates":[-118.288248,34.061887],"type":"Point"}
}