{
  "type": "Feature",
  "properties": {
    "addr:full":"2472 Overland Ave Los Angeles CA 90064",
    "addr:housenumber":"2472",
    "addr:postcode":"90064",
    "addr:street":"Overland Ave",
    "iso:country":"US",
    "sg:address":"2472 Overland Ave",
    "sg:city":"Los Angeles",
    "sg:classifiers":[
        {
            "category":"Health Services",
            "subcategory":"Dentist",
            "type":"Services"
        }
    ],
    "sg:phone":"+1 310 838 0844",
    "sg:postcode":"90064",
    "sg:province":"CA",
    "sg:website":"www.carlstondds.com",
    "wof:name":"Dean Carlston, DDS",
    "wof:placetype":"venue"
},
  "geometry": {"coordinates":[-118.423771,34.040675],"type":"Point"}
}