{
  "type": "Feature",
  "properties": {
    "addr:full":"650 S Hill St Ste 408 Los Angeles CA 90014",
    "addr:housenumber":"650",
    "addr:postcode":"90014",
    "addr:street":"S Hill St Ste 408",
    "iso:country":"US",
    "sg:address":"650 S Hill St Ste 408",
    "sg:city":"Los Angeles",
    "sg:classifiers":[
        {
            "category":"Shopping",
            "subcategory":"Jewelry",
            "type":"Retail Goods"
        }
    ],
    "sg:phone":"+1 213 623 6370",
    "sg:postcode":"90014",
    "sg:province":"CA",
    "wof:name":"Siera Jewelry Inc",
    "wof:placetype":"venue"
},
  "geometry": {"coordinates":[-118.253998,34.0466],"type":"Point"}
}