{
  "type": "Feature",
  "properties": {
    "addr:full":"8124 Firestone Blvd Downey CA 90241",
    "addr:housenumber":"8124",
    "addr:postcode":"90241",
    "addr:street":"Firestone Blvd",
    "iso:country":"US",
    "sg:address":"8124 Firestone Blvd",
    "sg:city":"Downey",
    "sg:classifiers":[
        {
            "category":"Retail",
            "subcategory":"Portrait Studio",
            "type":"Services"
        }
    ],
    "sg:phone":"+1 562 861 9771",
    "sg:postcode":"90241",
    "sg:province":"CA",
    "sg:tags":[
        "photography",
        "store"
    ],
    "wof:name":"Art's Camera",
    "wof:placetype":"venue"
},
  "geometry": {"coordinates":[-118.136002,33.941601],"type":"Point"}
}