{
  "type": "Feature",
  "properties": {
    "iso:country":"US",
    "sg:address":"9975 Rue Chantemar",
    "sg:city":"San Diego",
    "sg:classifiers":[
        {
            "category":"Organizations",
            "subcategory":"Community Association",
            "type":"Services"
        }
    ],
    "sg:phone":"+1 858 549 3692",
    "sg:postcode":"92131",
    "sg:province":"CA",
    "sg:tags":[
        "club"
    ],
    "wof:name":"New Yorker & East Coaster Assn",
    "wof:placetype":"venue"
},
  "geometry": {"coordinates":[-117.071262,32.900852],"type":"Point"}
}