{
  "type": "Feature",
  "properties": {
    "addr:full":"2250 Palm Ave San Diego CA 92154",
    "addr:housenumber":"2250",
    "addr:postcode":"92154",
    "addr:street":"Palm Ave",
    "iso:country":"US",
    "sg:address":"2250 Palm Ave",
    "sg:city":"San Diego",
    "sg:classifiers":[
        {
            "category":"Insurance",
            "subcategory":"Insurance Agent",
            "type":"Services"
        }
    ],
    "sg:phone":"+1 619 429 9517",
    "sg:postcode":"92154",
    "sg:province":"CA",
    "wof:name":"Allstate Insurance",
    "wof:placetype":"venue"
},
  "geometry": {"coordinates":[-117.087079,32.583896],"type":"Point"}
}