{
  "type": "Feature",
  "properties": {
    "iso:country":"US",
    "sg:address":"10932 Telechron Ave",
    "sg:city":"Whittier",
    "sg:classifiers":[
        {
            "category":"Building & Trades",
            "subcategory":"Construction",
            "type":"Services"
        }
    ],
    "sg:phone":"+1 562 864 1879",
    "sg:postcode":"90605",
    "sg:province":"CA",
    "sg:tags":[
        "tile",
        "dealer"
    ],
    "wof:name":"John Vadurro Tile",
    "wof:placetype":"venue"
},
  "geometry": {"coordinates":[-118.039327,33.933333],"type":"Point"}
}