{
  "type": "Feature",
  "properties": {
    "addr:full":"2426 San Ramon Valley Blvd San Ramon CA 94583",
    "addr:housenumber":"2426",
    "addr:postcode":"94583",
    "addr:street":"San Ramon Valley Blvd",
    "iso:country":"US",
    "sg:address":"2426 San Ramon Valley Blvd",
    "sg:city":"San Ramon",
    "sg:classifiers":[
        {
            "category":"Restaurant",
            "type":"Food & Drink"
        }
    ],
    "sg:phone":"+1 925 831 8882",
    "sg:postcode":"94583",
    "sg:province":"CA",
    "wof:name":"Nation's Giant Hamburgers",
    "wof:placetype":"venue"
},
  "geometry": {"coordinates":[-121.97397599999999,37.772045],"type":"Point"}
}