{
  "type": "Feature",
  "properties": {
    "addr:full":"101 Ash Avenue Carpinteria CA 93013",
    "addr:housenumber":"101",
    "addr:postcode":"93013",
    "addr:street":"Ash Avenue",
    "iso:country":"US",
    "sg:address":"101 Ash Avenue",
    "sg:city":"Carpinteria",
    "sg:classifiers":[
        {
            "category":"Recreation",
            "subcategory":"Boat Charter",
            "type":"Entertainment"
        },
        {
            "category":"Recreation",
            "type":"Entertainment"
        }
    ],
    "sg:phone":"+1 805 684 5405",
    "sg:postcode":"93013",
    "sg:province":"CA",
    "sg:tags":[
        "rafting/kayaking",
        "camp",
        "summer"
    ],
    "wof:name":"Ocean Recreation",
    "wof:placetype":"venue"
},
  "geometry": {"coordinates":[-119.528628,34.395472],"type":"Point"}
}