{
  "type": "Feature",
  "properties": {
    "addr:full":"73375 El Paseo Palm Desert CA 92260",
    "addr:housenumber":"73375",
    "addr:postcode":"ca 92260",
    "addr:street":"El Paseo",
    "iso:country":"US",
    "sg:address":"73375 El Paseo",
    "sg:city":"Palm Desert",
    "sg:classifiers":[
        {
            "category":"Restaurant",
            "type":"Food & Drink"
        }
    ],
    "sg:phone":"+1 760 837 1999",
    "sg:postcode":"92260",
    "sg:province":"CA",
    "sg:tags":[
        "breakfast",
        "brunch"
    ],
    "wof:name":"Il Sogno",
    "wof:placetype":"venue"
},
  "geometry": {"coordinates":[-116.385949,33.719203],"type":"Point"}
}