{
  "type": "Feature",
  "properties": {
    "iso:country":"US",
    "sg:address":"2001 E Fork Rd",
    "sg:city":"Trinity Center",
    "sg:classifiers":[
        {
            "category":"Manufacturing",
            "subcategory":"Food",
            "type":"Manufacturing & Wholesale Goods"
        }
    ],
    "sg:phone":"+1 530 266 9513",
    "sg:postcode":"96091",
    "sg:province":"CA",
    "sg:tags":[
        "winery"
    ],
    "wof:name":"Alpen Cellars",
    "wof:placetype":"venue"
},
  "geometry": {"coordinates":[-122.603092,41.031892],"type":"Point"}
}