{
  "type": "Feature",
  "properties": {
    "iso:country":"US",
    "sg:address":"7525 Linda Vista Rd",
    "sg:city":"San Diego",
    "sg:classifiers":[
        {
            "category":"Health Services",
            "subcategory":"Doctor",
            "type":"Services"
        }
    ],
    "sg:phone":"+1 858 279 2360",
    "sg:postcode":"92111",
    "sg:province":"CA",
    "sg:tags":[
        "dentist"
    ],
    "wof:name":"Mark Bishop DDS",
    "wof:placetype":"venue"
},
  "geometry": {"coordinates":[-117.159305,32.79864],"type":"Point"}
}