{
  "type": "Feature",
  "properties": {
    "addr:full":"740 Story Rd San Jose CA 95122",
    "addr:housenumber":"740",
    "addr:postcode":"95122",
    "addr:street":"Story Rd",
    "iso:country":"US",
    "sg:address":"740 Story Rd",
    "sg:city":"San Jose",
    "sg:classifiers":[
        {
            "category":"Professional",
            "subcategory":"Lawyer & Legal Services",
            "type":"Services"
        }
    ],
    "sg:phone":"+1 408 275 1626",
    "sg:postcode":"95122",
    "sg:province":"CA",
    "wof:name":"The Law Office Of Teresa Thu Huong Nguyen Hung",
    "wof:placetype":"venue"
},
  "geometry": {"coordinates":[-121.859279,37.328642],"type":"Point"}
}