{
  "type": "Feature",
  "properties": {
    "addr:full":"3128 Panmure Court San Jose CA 95135",
    "addr:housenumber":"3128",
    "addr:postcode":"95135",
    "addr:street":"Panmure Court",
    "iso:country":"US",
    "sg:address":"3128 Panmure Court",
    "sg:city":"San Jose",
    "sg:classifiers":[
        {
            "category":"Building & Trades",
            "subcategory":"Construction",
            "type":"Services"
        }
    ],
    "sg:phone":"+1 408 270 4434",
    "sg:postcode":"95135",
    "sg:province":"CA",
    "sg:tags":[
        "contractor"
    ],
    "sg:website":"www.hchaidez.com",
    "wof:name":"H Chaidez General Building",
    "wof:placetype":"venue"
},
  "geometry": {"coordinates":[-121.77078,37.30924],"type":"Point"}
}