{
  "type": "Feature",
  "properties": {
    "iso:country":"US",
    "sg:address":"1721 Eastern Ave",
    "sg:city":"Sacramento",
    "sg:classifiers":[
        {
            "category":"Banks & Credit Unions",
            "subcategory":"Bank",
            "type":"Services"
        }
    ],
    "sg:phone":"+1 916 487 4207",
    "sg:postcode":"95864",
    "sg:province":"CA",
    "sg:tags":[
        "loan",
        "real estate"
    ],
    "wof:name":"Arden Mortgage",
    "wof:placetype":"venue"
},
  "geometry": {"coordinates":[-121.364661,38.59576],"type":"Point"}
}