{
  "type": "Feature",
  "properties": {
    "iso:country":"US",
    "sg:address":"1841 W 11th St",
    "sg:city":"Tracy",
    "sg:classifiers":[
        {
            "category":"Real Estate",
            "subcategory":"Real Estate Agent",
            "type":"Services"
        }
    ],
    "sg:phone":"+1 209 833 6651",
    "sg:postcode":"95376",
    "sg:province":"CA",
    "wof:name":"Marsha Reihl",
    "wof:placetype":"venue"
},
  "geometry": {"coordinates":[-121.446978,37.739607],"type":"Point"}
}