{
  "type": "Feature",
  "properties": {
    "iso:country":"US",
    "sg:address":"2345 5th St",
    "sg:city":"Norco",
    "sg:classifiers":[
        {
            "category":"Organizations",
            "subcategory":"Religious Organization",
            "type":"Services"
        }
    ],
    "sg:phone":"+1 951 734 3890",
    "sg:postcode":"92860",
    "sg:province":"CA",
    "sg:tags":[
        "church"
    ],
    "wof:name":"St Anthony & St Abanoub Coptic",
    "wof:placetype":"venue"
},
  "geometry": {"coordinates":[-117.57575799999999,33.931251],"type":"Point"}
}