{
  "type": "Feature",
  "properties": {
    "iso:country":"US",
    "sg:address":"4615 1st St",
    "sg:city":"Pleasanton",
    "sg:classifiers":[
        {
            "category":"Professional",
            "subcategory":"Art Services",
            "type":"Services"
        }
    ],
    "sg:phone":"+1 925 417 7377",
    "sg:postcode":"94566",
    "sg:province":"CA",
    "sg:tags":[
        "graphic",
        "designer"
    ],
    "wof:name":"Kassner Graphics",
    "wof:placetype":"venue"
},
  "geometry": {"coordinates":[-121.875626,37.658119],"type":"Point"}
}