{
  "type": "Feature",
  "properties": {
    "addr:full":"1723 Dell Ave Campbell CA 95008",
    "addr:housenumber":"1723",
    "addr:postcode":"95008",
    "addr:street":"Dell Ave",
    "iso:country":"US",
    "sg:address":"1723 Dell Ave",
    "sg:city":"Campbell",
    "sg:classifiers":[
        {
            "category":"Building & Trades",
            "subcategory":"Construction",
            "type":"Services"
        }
    ],
    "sg:phone":"+1 408 378 4485",
    "sg:postcode":"95008",
    "sg:province":"CA",
    "sg:tags":[
        "contractor"
    ],
    "wof:name":"West Coast Gutters",
    "wof:placetype":"venue"
},
  "geometry": {"coordinates":[-121.95652200000001,37.264118],"type":"Point"}
}