{
  "type": "Feature",
  "properties": {
    "iso:country":"US",
    "sg:address":"1440 Southgate Ave",
    "sg:city":"Daly City",
    "sg:classifiers":[
        {
            "category":"Health Services",
            "subcategory":"Doctor",
            "type":"Services"
        }
    ],
    "sg:phone":"+1 650 757 5100",
    "sg:postcode":"94015",
    "sg:province":"CA",
    "sg:tags":[
        "physician",
        "surgeon"
    ],
    "wof:name":"Apolinar Tiongson MD",
    "wof:placetype":"venue"
},
  "geometry": {"coordinates":[-122.478266,37.67553],"type":"Point"}
}