{
  "type": "Feature",
  "properties": {
    "iso:country":"US",
    "sg:address":"2308 California St",
    "sg:city":"Stockton",
    "sg:classifiers":[
        {
            "category":"Health Services",
            "subcategory":"Chiropractor",
            "type":"Services"
        }
    ],
    "sg:phone":"+1 209 462 5222",
    "sg:postcode":"95204",
    "sg:province":"CA",
    "wof:name":"Ca Accident & Injury Ctr",
    "wof:placetype":"venue"
},
  "geometry": {"coordinates":[-121.29096699999999,37.975471],"type":"Point"}
}