{
  "type": "Feature",
  "properties": {
    "addr:full":"10495 S de Anza Blvd Cupertino CA 95014",
    "addr:housenumber":"10495",
    "addr:postcode":"95014",
    "addr:street":"S De Anza Blvd",
    "iso:country":"US",
    "sg:address":"10495 S de Anza Blvd",
    "sg:city":"Cupertino",
    "sg:classifiers":[
        {
            "category":"Banks & Credit Unions",
            "subcategory":"Bank",
            "type":"Services"
        }
    ],
    "sg:phone":"+1 408 863 8000",
    "sg:postcode":"95014",
    "sg:province":"CA",
    "sg:tags":[
        "loan",
        "real estate"
    ],
    "wof:name":"Countrywide Home Loans",
    "wof:placetype":"venue"
},
  "geometry": {"coordinates":[-122.03234,37.315625],"type":"Point"}
}