{
  "type": "Feature",
  "properties": {
    "addr:full":"5401 Sunrise Boulevard Citrus Heights CA 95610",
    "addr:housenumber":"5401",
    "addr:postcode":"95610",
    "addr:street":"Sunrise Boulevard",
    "iso:country":"US",
    "sg:address":"5401 Sunrise Boulevard",
    "sg:city":"Citrus Heights",
    "sg:classifiers":[
        {
            "category":"Shopping",
            "subcategory":"Mobile Phones",
            "type":"Retail Goods"
        }
    ],
    "sg:phone":"+1 916 967 1644",
    "sg:postcode":"95610",
    "sg:province":"CA",
    "wof:name":"Metro Pcs",
    "wof:placetype":"venue"
},
  "geometry": {"coordinates":[-121.27234199999999,38.664091],"type":"Point"}
}