{
  "type": "Feature",
  "properties": {
    "iso:country":"US",
    "sg:address":"206 Juanita Way",
    "sg:city":"San Francisco",
    "sg:classifiers":[
        {
            "category":"Retail",
            "subcategory":"Photofinishing",
            "type":"Services"
        }
    ],
    "sg:phone":"+1 415 566 5232",
    "sg:postcode":"94127",
    "sg:province":"CA",
    "sg:tags":[
        "laboratory"
    ],
    "wof:name":"Chang Hao Photography",
    "wof:placetype":"venue"
},
  "geometry": {"coordinates":[-122.455415,37.741319],"type":"Point"}
}