{
  "type": "Feature",
  "properties": {
    "addr:full":"5501 Cedars Rd Redding CA 96001",
    "addr:postcode":"5501;96001",
    "addr:street":"Cedars Rd",
    "iso:country":"US",
    "sg:address":"5501 Cedars Rd",
    "sg:city":"Redding",
    "sg:classifiers":[
        {
            "category":"Manufacturing",
            "subcategory":"Rubber & Plastics",
            "type":"Manufacturing & Wholesale Goods"
        }
    ],
    "sg:phone":"+1 530 243 0181",
    "sg:postcode":"96001",
    "sg:province":"CA",
    "wof:name":"Northwest Plastics",
    "wof:placetype":"venue"
},
  "geometry": {"coordinates":[-122.388133,40.533746],"type":"Point"}
}