{
  "type": "Feature",
  "properties": {
    "addr:full":"7602 Occidental Rd Sebastopol CA 95472",
    "addr:housenumber":"7602",
    "addr:postcode":"95472",
    "addr:street":"Occidental Rd",
    "iso:country":"US",
    "sg:address":"7602 Occidental Rd",
    "sg:city":"Sebastopol",
    "sg:classifiers":[
        {
            "category":"Farming",
            "subcategory":"Farm & Veterinary Services",
            "type":"Manufacturing & Wholesale Goods"
        }
    ],
    "sg:phone":"+1 707 829 7340",
    "sg:postcode":"95472",
    "sg:province":"CA",
    "sg:tags":[
        "vineyard"
    ],
    "wof:name":"LAncien Verger",
    "wof:placetype":"venue"
},
  "geometry": {"coordinates":[-122.844945,38.425793],"type":"Point"}
}