{
  "type": "Feature",
  "properties": {
    "addr:full":"3036 Scott Rd Burbank CA 91504",
    "addr:housenumber":"3036",
    "addr:postcode":"91504",
    "addr:street":"Scott Rd",
    "iso:country":"US",
    "sg:address":"3036 Scott Rd",
    "sg:city":"Burbank",
    "sg:classifiers":[
        {
            "category":"Organizations",
            "subcategory":"Religious Organization",
            "type":"Services"
        }
    ],
    "sg:phone":"+1 818 848 4243",
    "sg:postcode":"91504",
    "sg:province":"CA",
    "sg:tags":[
        "service/non-profit",
        "community"
    ],
    "wof:name":"Baha'i Faith",
    "wof:placetype":"venue"
},
  "geometry": {"coordinates":[-118.329904,34.207047],"type":"Point"}
}