{
  "type": "Feature",
  "properties": {
    "iso:country":"US",
    "sg:address":"200 Ridgetop Dr",
    "sg:city":"Redding",
    "sg:classifiers":[
        {
            "category":"Professional",
            "subcategory":"Computer Services",
            "type":"Services"
        }
    ],
    "sg:phone":"+1 530 917 4991",
    "sg:postcode":"96003",
    "sg:province":"CA",
    "sg:tags":[
        "internet"
    ],
    "wof:name":"Vivid Business Enterprises",
    "wof:placetype":"venue"
},
  "geometry": {"coordinates":[-122.375519,40.603116],"type":"Point"}
}