{
  "type": "Feature",
  "properties": {
    "addr:full":"5943 W Birch Ave Fresno CA 93722",
    "addr:housenumber":"5943",
    "addr:postcode":"93722",
    "addr:street":"W Birch Ave",
    "iso:country":"US",
    "sg:address":"5943 W Birch Ave",
    "sg:city":"Fresno",
    "sg:classifiers":[
        {
            "category":"Professional",
            "subcategory":"Computer Services",
            "type":"Services"
        }
    ],
    "sg:phone":"+1 559 277 1182",
    "sg:postcode":"93722",
    "sg:province":"CA",
    "sg:tags":[
        "website",
        "design"
    ],
    "sg:website":"www.nsconsulting.com",
    "wof:name":"N S Consulting Inc",
    "wof:placetype":"venue"
},
  "geometry": {"coordinates":[-119.89944800000001,36.841041],"type":"Point"}
}