{
  "type": "Feature",
  "properties": {
    "iso:country":"US",
    "sg:address":"701 S Parker St",
    "sg:city":"Orange",
    "sg:classifiers":[
        {
            "category":"Insurance",
            "subcategory":"Insurance Agent",
            "type":"Services"
        }
    ],
    "sg:phone":"+1 714 263 0220",
    "sg:postcode":"92868",
    "sg:province":"CA",
    "wof:name":"Aflac Ca CS State Office",
    "wof:placetype":"venue"
},
  "geometry": {"coordinates":[-117.859589,33.776621],"type":"Point"}
}