{
  "type": "Feature",
  "properties": {
    "addr:full":"33 E Canon Perdido St Santa Barbara CA 93101",
    "addr:housenumber":"33",
    "addr:postcode":"93101",
    "addr:street":"E Canon Perdido St",
    "iso:country":"US",
    "sg:address":"33 E Canon Perdido St",
    "sg:city":"Santa Barbara",
    "sg:classifiers":[
        {
            "category":"Arts & Performance",
            "subcategory":"Theater",
            "type":"Entertainment"
        }
    ],
    "sg:phone":"+1 805 963 0761",
    "sg:postcode":"93101",
    "sg:province":"CA",
    "wof:name":"Lobero Theatre",
    "wof:placetype":"venue"
},
  "geometry": {"coordinates":[-119.699799,34.421292],"type":"Point"}
}