{
  "type": "Feature",
  "properties": {
    "iso:country":"US",
    "sg:address":"1811 W 108th Street",
    "sg:city":"Los Angeles",
    "sg:classifiers":[
        {
            "category":"Personal",
            "subcategory":"Beauty Salon",
            "type":"Services"
        }
    ],
    "sg:phone":"+1 323 757 1844",
    "sg:postcode":"90047",
    "sg:province":"CA",
    "sg:tags":[
        "hair"
    ],
    "wof:name":"Shear Image Beauty Salon",
    "wof:placetype":"venue"
},
  "geometry": {"coordinates":[-118.309409,33.938101],"type":"Point"}
}