{
  "type": "Feature",
  "properties": {
    "addr:full":"1923 Calle Barcelona Suite 136 Carlsbad CA 92009",
    "addr:housenumber":"1923",
    "addr:postcode":"92009",
    "addr:street":"Calle Barcelona Suite 136",
    "iso:country":"US",
    "sg:address":"1923 Calle Barcelona Suite 136",
    "sg:city":"Carlsbad",
    "sg:classifiers":[
        {
            "category":"Shopping",
            "subcategory":"Clothing, Apparel, & Fashions",
            "type":"Retail Goods"
        },
        {
            "category":"Sports & Exercise",
            "subcategory":"Bicycle Rental",
            "type":"Entertainment"
        },
        {
            "category":"Sports & Exercise",
            "subcategory":"Gym",
            "type":"Entertainment"
        }
    ],
    "sg:phone":"+1 760 479 0183",
    "sg:postcode":"92009",
    "sg:province":"CA",
    "sg:tags":[
        "yoga",
        "clothing",
        "wear",
        "women's"
    ],
    "sg:website":"www.lululemon.com",
    "wof:name":"lululemon athletica",
    "wof:placetype":"venue"
},
  "geometry": {"coordinates":[-117.265288,33.070987],"type":"Point"}
}