{
  "type": "Feature",
  "properties": {
    "addr:full":"83 N Washington St Sonora CA 95370",
    "addr:housenumber":"83",
    "addr:postcode":"95370",
    "addr:street":"N Washington St",
    "iso:country":"US",
    "sg:address":"83 N Washington St",
    "sg:city":"Sonora",
    "sg:classifiers":[
        {
            "category":"Bagels",
            "subcategory":"None",
            "type":"Food & Drink"
        }
    ],
    "sg:phone":"+1 209 533 1904",
    "sg:postcode":"95370",
    "sg:province":"CA",
    "wof:name":"Bagel Bin the",
    "wof:placetype":"venue"
},
  "geometry": {"coordinates":[-120.33000199999999,37.999401],"type":"Point"}
}