{
  "type": "Feature",
  "properties": {
    "addr:full":"20849 Sherman Way Winnetka CA 91306",
    "addr:housenumber":"20849",
    "addr:postcode":"91306",
    "addr:street":"Sherman Way",
    "iso:country":"US",
    "sg:address":"20849 Sherman Way",
    "sg:city":"Winnetka",
    "sg:classifiers":[
        {
            "category":"Restaurant",
            "type":"Food & Drink"
        }
    ],
    "sg:phone":"+1 818 348 4747",
    "sg:postcode":"91306",
    "sg:province":"CA",
    "sg:tags":[
        "italian"
    ],
    "wof:name":"Bruno's Italian Restaurant",
    "wof:placetype":"venue"
},
  "geometry": {"coordinates":[-118.58699799999999,34.201],"type":"Point"}
}