{
  "type": "Feature",
  "properties": {
    "iso:country":"US",
    "sg:address":"2128 N Glenoaks Blvd",
    "sg:city":"Burbank",
    "sg:classifiers":[
        {
            "category":"Autos & Motor Vehicles",
            "subcategory":"Fuel & Gas Station",
            "type":"Retail Goods"
        }
    ],
    "sg:phone":"+1 818 846 2624",
    "sg:postcode":"91504",
    "sg:province":"CA",
    "sg:tags":[
        "oil"
    ],
    "wof:name":"D & D Union 76",
    "wof:placetype":"venue"
},
  "geometry": {"coordinates":[-118.32703600000001,34.198443],"type":"Point"}
}