{
  "type": "Feature",
  "properties": {
    "addr:full":"424 Toyon Ave San Jose CA 95127",
    "addr:housenumber":"424",
    "addr:postcode":"95127",
    "addr:street":"Toyon Ave",
    "iso:country":"US",
    "sg:address":"424 Toyon Ave",
    "sg:city":"San Jose",
    "sg:classifiers":[
        {
            "category":"Personal",
            "subcategory":"Beauty Salon",
            "type":"Services"
        }
    ],
    "sg:phone":"+1 408 926 5688",
    "sg:postcode":"95127",
    "sg:province":"CA",
    "sg:tags":[
        "hair"
    ],
    "wof:name":"Hair Plus",
    "wof:placetype":"venue"
},
  "geometry": {"coordinates":[-121.828003,37.383202],"type":"Point"}
}