{
  "type": "Feature",
  "properties": {
    "addr:full":"1379 Old County Rd San Carlos CA 94070",
    "addr:housenumber":"1379",
    "addr:postcode":"94070",
    "addr:street":"Old County Rd",
    "iso:country":"US",
    "sg:address":"1379 Old County Rd",
    "sg:city":"San Carlos",
    "sg:classifiers":[
        {
            "category":"Manufacturing",
            "subcategory":"Textiles",
            "type":"Manufacturing & Wholesale Goods"
        }
    ],
    "sg:phone":"+1 650 592 1350",
    "sg:postcode":"94070",
    "sg:province":"CA",
    "sg:tags":[
        "mills"
    ],
    "wof:name":"A Sommer Textiles Co",
    "wof:placetype":"venue"
},
  "geometry": {"coordinates":[-122.249262,37.498865],"type":"Point"}
}