{
  "type": "Feature",
  "properties": {
    "iso:country":"US",
    "sg:address":"4879 E Kings Canyon Rd",
    "sg:city":"Fresno",
    "sg:classifiers":[
        {
            "category":"Organizations",
            "subcategory":"Non-profit Organization",
            "type":"Services"
        }
    ],
    "sg:phone":"+1 559 255 8395",
    "sg:postcode":"93727",
    "sg:province":"CA",
    "sg:website":"www.fresnocenter.com",
    "wof:name":"Fresno Center-New Americans",
    "wof:placetype":"venue"
},
  "geometry": {"coordinates":[-119.733046,36.735998],"type":"Point"}
}