{
  "type": "Feature",
  "properties": {
    "iso:country":"US",
    "sg:address":"1001 Gayley Ave.",
    "sg:city":"Westwood Village",
    "sg:classifiers":[
        {
            "category":"Personal",
            "subcategory":"Beauty Salon",
            "type":"Services"
        }
    ],
    "sg:phone":"+1 800 925 5145",
    "sg:postcode":"90024",
    "sg:province":"CA",
    "sg:tags":[
        "hair"
    ],
    "sg:website":"www.westwoodhair.com",
    "wof:name":"Melissa B",
    "wof:placetype":"venue"
},
  "geometry": {"coordinates":[-118.448082,34.061611],"type":"Point"}
}