{
  "type": "Feature",
  "properties": {
    "addr:full":"41190 Chaco Canyon Rd Murrieta CA 92562",
    "addr:housenumber":"41190",
    "addr:postcode":"92562",
    "addr:street":"Chaco Canyon Rd",
    "iso:country":"US",
    "sg:address":"41190 Chaco Canyon Rd",
    "sg:city":"Murrieta",
    "sg:classifiers":[
        {
            "category":"Professional",
            "subcategory":"Business Services",
            "type":"Services"
        }
    ],
    "sg:phone":"+1 951 696 7779",
    "sg:postcode":"92562",
    "sg:province":"CA",
    "sg:tags":[
        "transcribing",
        "disc"
    ],
    "wof:name":"L S Transcription Svc",
    "wof:placetype":"venue"
},
  "geometry": {"coordinates":[-117.218255,33.575662],"type":"Point"}
}