{
  "type": "Feature",
  "properties": {
    "iso:country":"US",
    "sg:address":"27708 Jefferson Ave",
    "sg:city":"Temecula",
    "sg:classifiers":[
        {
            "category":"Insurance",
            "subcategory":"Insurance Agent",
            "type":"Services"
        }
    ],
    "sg:phone":"+1 951 693 1252",
    "sg:postcode":"92590",
    "sg:province":"CA",
    "wof:name":"Fidelity National Title",
    "wof:placetype":"venue"
},
  "geometry": {"coordinates":[-117.15804300000001,33.511357],"type":"Point"}
}