{
  "type": "Feature",
  "properties": {
    "iso:country":"US",
    "sg:address":"1001 W Imperial Hwy",
    "sg:city":"La Habra",
    "sg:classifiers":[
        {
            "category":"Government",
            "subcategory":"Post Office",
            "type":"Public Place"
        }
    ],
    "sg:phone":"+1 714 992 0580",
    "sg:postcode":"90631",
    "sg:province":"CA",
    "sg:tags":[
        "postal",
        "us"
    ],
    "wof:name":"US Post Office",
    "wof:placetype":"venue"
},
  "geometry": {"coordinates":[-117.960817,33.917324],"type":"Point"}
}