{
  "type": "Feature",
  "properties": {
    "addr:full":"13930 Valley Blvd Fontana CA 92335",
    "addr:housenumber":"13930",
    "addr:postcode":"92335",
    "addr:street":"Valley Blvd",
    "iso:country":"US",
    "sg:address":"13930 Valley Blvd",
    "sg:city":"Fontana",
    "sg:classifiers":[
        {
            "category":"Wholesale",
            "subcategory":"Motor Vehicles",
            "type":"Manufacturing & Wholesale Goods"
        }
    ],
    "sg:phone":"+1 909 357 6000",
    "sg:postcode":"92335",
    "sg:province":"CA",
    "sg:tags":[
        "trailer"
    ],
    "wof:name":"Century Truck & Equipment",
    "wof:placetype":"venue"
},
  "geometry": {"coordinates":[-117.498625,34.070239],"type":"Point"}
}