{
  "type": "Feature",
  "properties": {
    "addr:full":"100 N Citrus Ave Covina CA 91723",
    "addr:housenumber":"100",
    "addr:postcode":"91723",
    "addr:street":"N Citrus Ave",
    "iso:country":"US",
    "sg:address":"100 N Citrus Ave",
    "sg:city":"Covina",
    "sg:classifiers":[
        {
            "category":"Insurance",
            "subcategory":"Insurance Agent",
            "type":"Services"
        }
    ],
    "sg:phone":"+1 626 331 1669",
    "sg:postcode":"91723",
    "sg:province":"CA",
    "wof:name":"Nase District Office",
    "wof:placetype":"venue"
},
  "geometry": {"coordinates":[-117.89014,34.086858],"type":"Point"}
}