{
  "type": "Feature",
  "properties": {
    "addr:full":"1804 S Ardmore Ave Los Angeles CA 90006",
    "addr:housenumber":"1804",
    "addr:postcode":"90006",
    "addr:street":"S Ardmore Ave",
    "iso:country":"US",
    "sg:address":"1804 S Ardmore Ave",
    "sg:city":"Los Angeles",
    "sg:classifiers":[
        {
            "category":"Organizations",
            "subcategory":"Non-profit Organization",
            "type":"Services"
        }
    ],
    "sg:phone":"+1 323 731 8904",
    "sg:postcode":"90006",
    "sg:province":"CA",
    "sg:tags":[
        "alternative",
        "abortion"
    ],
    "wof:name":"Chelsea's Home-Pregnant Teens",
    "wof:placetype":"venue"
},
  "geometry": {"coordinates":[-118.3027,34.042445],"type":"Point"}
}