{
  "type": "Feature",
  "properties": {
    "addr:full":"311 California Suite 600 San Francisco CA 94104",
    "addr:housenumber":"311",
    "addr:postcode":"94104",
    "addr:street":"California Suite 600",
    "iso:country":"US",
    "sg:address":"311 California Suite 600",
    "sg:city":"San Francisco",
    "sg:classifiers":[
        {
            "category":"Professional",
            "subcategory":"Computer Services",
            "type":"Services"
        }
    ],
    "sg:phone":"+1 415 887 7678",
    "sg:postcode":"94104",
    "sg:province":"CA",
    "sg:tags":[
        "repair"
    ],
    "sg:website":"oneclickfix.net",
    "wof:name":"OneClickFix",
    "wof:placetype":"venue"
},
  "geometry": {"coordinates":[-122.400294,37.793124],"type":"Point"}
}