{
  "type": "Feature",
  "properties": {
    "iso:country":"US",
    "sg:address":"9388 Santa Monica Blvd",
    "sg:city":"Beverly Hills",
    "sg:classifiers":[
        {
            "category":"Real Estate",
            "subcategory":"Real Estate Services",
            "type":"Services"
        }
    ],
    "sg:phone":"+1 310 205 0113",
    "sg:postcode":"90210",
    "sg:province":"CA",
    "sg:website":"www.westcoastescrow.com",
    "wof:name":"West Coast Escrow",
    "wof:placetype":"venue"
},
  "geometry": {"coordinates":[-118.402293,34.072589],"type":"Point"}
}