{
  "type": "Feature",
  "properties": {
    "addr:full":"19236 State Rte 140 Stevinson CA 95374",
    "addr:housenumber":"19236",
    "addr:postcode":"95374",
    "addr:street":"State Rte 140",
    "iso:country":"US",
    "sg:address":"19236 State Rte 140",
    "sg:city":"Stevinson",
    "sg:classifiers":[
        {
            "category":"Farming",
            "subcategory":"Livestock Farm",
            "type":"Manufacturing & Wholesale Goods"
        }
    ],
    "sg:phone":"+1 209 634 1461",
    "sg:postcode":"95374",
    "sg:province":"CA",
    "sg:tags":[
        "beef",
        "feedlot",
        "cattle"
    ],
    "wof:name":"Daniel Avilla",
    "wof:placetype":"venue"
},
  "geometry": {"coordinates":[-120.836472,37.313115],"type":"Point"}
}