{
  "type": "Feature",
  "properties": {
    "iso:country":"US",
    "sg:address":"870 Market St",
    "sg:city":"San Francisco",
    "sg:classifiers":[
        {
            "category":"Social Services",
            "type":"Services"
        }
    ],
    "sg:phone":"+1 415 989 4422",
    "sg:postcode":"94102",
    "sg:province":"CA",
    "sg:tags":[
        "organization",
        "welfare"
    ],
    "wof:name":"Older Women's League",
    "wof:placetype":"venue"
},
  "geometry": {"coordinates":[-122.406645,37.785415],"type":"Point"}
}