{
  "type": "Feature",
  "properties": {
    "addr:full":"1704 Drexel Dr Davis CA 95616",
    "addr:housenumber":"1704",
    "addr:postcode":"95616",
    "addr:street":"Drexel Dr",
    "iso:country":"US",
    "sg:address":"1704 Drexel Dr",
    "sg:city":"Davis",
    "sg:classifiers":[
        {
            "category":"Building & Trades",
            "subcategory":"Construction",
            "type":"Services"
        }
    ],
    "sg:phone":"+1 530 758 7719",
    "sg:postcode":"95616",
    "sg:province":"CA",
    "sg:tags":[
        "contractor"
    ],
    "wof:name":"Galvin Construction Svc",
    "wof:placetype":"venue"
},
  "geometry": {"coordinates":[-121.728433,38.557375],"type":"Point"}
}