{
  "type": "Feature",
  "properties": {
    "iso:country":"US",
    "sg:address":"12325 Mills Ave Ste 21",
    "sg:city":"Chino",
    "sg:classifiers":[
        {
            "category":"Taxi",
            "type":"Transportation"
        }
    ],
    "sg:phone":"+1 951 823 8870",
    "sg:postcode":"91710",
    "sg:province":"CA",
    "sg:tags":[
        "delivery"
    ],
    "wof:name":"Ads",
    "wof:placetype":"venue"
},
  "geometry": {"coordinates":[-117.72874,34.029381],"type":"Point"}
}