{
  "type": "Feature",
  "properties": {
    "iso:country":"US",
    "sg:address":"1622 Ocean Park Blvd",
    "sg:city":"Santa Monica",
    "sg:classifiers":[
        {
            "category":"Retail",
            "subcategory":"Repair Shop",
            "type":"Services"
        }
    ],
    "sg:phone":"+1 310 526 8160",
    "sg:postcode":"90405",
    "sg:province":"CA",
    "sg:tags":[
        "lock",
        "locksmith"
    ],
    "wof:name":"Locksmith Service",
    "wof:placetype":"venue"
},
  "geometry": {"coordinates":[-118.467127,34.012172],"type":"Point"}
}