{
  "type": "Feature",
  "properties": {
    "iso:country":"US",
    "sg:address":"400 E Commonwealth Ave Ste 3",
    "sg:city":"Fullerton",
    "sg:classifiers":[
        {
            "category":"Health Services",
            "subcategory":"Doctor",
            "type":"Services"
        }
    ],
    "sg:phone":"+1 714 449 0022",
    "sg:postcode":"92832",
    "sg:province":"CA",
    "sg:tags":[
        "surgeon",
        "oral"
    ],
    "wof:name":"Nguyen Dani DDS",
    "wof:placetype":"venue"
},
  "geometry": {"coordinates":[-117.91799899999999,33.870399],"type":"Point"}
}