{
  "type": "Feature",
  "properties": {
    "addr:full":"11301 W Olympic Blvd Los Angeles CA 90064",
    "addr:housenumber":"11301",
    "addr:postcode":"90064",
    "addr:street":"W Olympic Blvd",
    "iso:country":"US",
    "sg:address":"11301 W Olympic Blvd",
    "sg:city":"Los Angeles",
    "sg:classifiers":[
        {
            "category":"Restaurant",
            "type":"Food & Drink"
        }
    ],
    "sg:menulink":"http://www.allmenus.com/ca/los-angeles/278041-zip-fusion/menu/",
    "sg:phone":"+1 310 575 3636",
    "sg:postcode":"90064",
    "sg:province":"CA",
    "sg:tags":[
        "sushi",
        "asian"
    ],
    "wof:name":"Zip Fusion",
    "wof:placetype":"venue"
},
  "geometry": {"coordinates":[-118.44139199999999,34.038185],"type":"Point"}
}