{
  "type": "Feature",
  "properties": {
    "iso:country":"US",
    "sg:address":"4408 Hedge Ave",
    "sg:city":"Sacramento",
    "sg:classifiers":[
        {
            "category":"Building & Trades",
            "subcategory":"Construction",
            "type":"Services"
        }
    ],
    "sg:phone":"+1 916 997 9228",
    "sg:postcode":"95826",
    "sg:province":"CA",
    "sg:tags":[
        "repair",
        "air conditioning"
    ],
    "wof:name":"Airodynamic Inc",
    "wof:placetype":"venue"
},
  "geometry": {"coordinates":[-121.361526,38.53764],"type":"Point"}
}