{
  "type": "Feature",
  "properties": {
    "iso:country":"US",
    "sg:address":"2101 Webster St",
    "sg:city":"Oakland",
    "sg:classifiers":[
        {
            "category":"Building & Trades",
            "subcategory":"Construction",
            "type":"Services"
        }
    ],
    "sg:phone":"+1 510 893 8337",
    "sg:postcode":"94612",
    "sg:province":"CA",
    "sg:tags":[
        "contractor"
    ],
    "wof:name":"Pankow Special Projects Lp",
    "wof:placetype":"venue"
},
  "geometry": {"coordinates":[-122.26585300000001,37.810257],"type":"Point"}
}