{
  "type": "Feature",
  "properties": {
    "iso:country":"US",
    "sg:address":"7750 Palm Ave",
    "sg:city":"Highland",
    "sg:classifiers":[
        {
            "category":"Personal",
            "subcategory":"Massage",
            "type":"Services"
        }
    ],
    "sg:phone":"+1 909 862 9000",
    "sg:postcode":"92346",
    "sg:province":"CA",
    "wof:name":"Japanese Massage",
    "wof:placetype":"venue"
},
  "geometry": {"coordinates":[-117.208856,34.114675],"type":"Point"}
}