{
  "type": "Feature",
  "properties": {
    "addr:full":"41825 Royal Palm Dr Hemet CA 92544",
    "addr:housenumber":"41825",
    "addr:postcode":"92544",
    "addr:street":"Royal Palm Dr",
    "iso:country":"US",
    "sg:address":"41825 Royal Palm Dr",
    "sg:city":"Hemet",
    "sg:classifiers":[
        {
            "category":"Banks & Credit Unions",
            "subcategory":"Bank",
            "type":"Services"
        }
    ],
    "sg:phone":"+1 951 652 0727",
    "sg:postcode":"92544",
    "sg:province":"CA",
    "sg:tags":[
        "mortgage"
    ],
    "wof:name":"All Lenders",
    "wof:placetype":"venue"
},
  "geometry": {"coordinates":[-116.931549,33.73895],"type":"Point"}
}