{
  "type": "Feature",
  "properties": {
    "iso:country":"US",
    "sg:address":"9608 Las Tunas Dr",
    "sg:city":"Temple City",
    "sg:classifiers":[
        {
            "category":"Shopping",
            "subcategory":"Clothing, Apparel, & Fashions",
            "type":"Retail Goods"
        }
    ],
    "sg:phone":"+1 626 285 6668",
    "sg:postcode":"91780",
    "sg:province":"CA",
    "sg:tags":[
        "dressmaker"
    ],
    "wof:name":"Louis Dress",
    "wof:placetype":"venue"
},
  "geometry": {"coordinates":[-118.059682,34.10677],"type":"Point"}
}