{
  "type": "Feature",
  "properties": {
    "iso:country":"US",
    "sg:address":"2125 W 25th St",
    "sg:city":"San Pedro",
    "sg:classifiers":[
        {
            "category":"Education",
            "subcategory":"Special Training",
            "type":"Public Place"
        }
    ],
    "sg:phone":"+1 310 833 5431",
    "sg:postcode":"90732",
    "sg:province":"CA",
    "sg:tags":[
        "program"
    ],
    "wof:name":"Richard D Paul Consulting",
    "wof:placetype":"venue"
},
  "geometry": {"coordinates":[-118.32281399999999,33.726504],"type":"Point"}
}