{
  "type": "Feature",
  "properties": {
    "iso:country":"US",
    "sg:address":"12751 Silver Spur Way",
    "sg:city":"Victorville",
    "sg:classifiers":[
        {
            "category":"Restaurant",
            "type":"Food & Drink"
        }
    ],
    "sg:phone":"+1 760 244 3434",
    "sg:postcode":"92392",
    "sg:province":"CA",
    "wof:name":"Siam Village Restaurant",
    "wof:placetype":"venue"
},
  "geometry": {"coordinates":[-117.390159,34.482659],"type":"Point"}
}