{
  "type": "Feature",
  "properties": {
    "addr:full":"371 Calabasas Rd Unit Nursery Watsonville CA 95076",
    "addr:housenumber":"371",
    "addr:postcode":"95076",
    "addr:street":"Calabasas Rd Unit Nursery",
    "iso:country":"US",
    "sg:address":"371 Calabasas Rd Unit Nursery",
    "sg:city":"Watsonville",
    "sg:classifiers":[
        {
            "category":"Wholesale",
            "subcategory":"Plants",
            "type":"Manufacturing & Wholesale Goods"
        },
        {
            "category":"Shopping",
            "subcategory":"Crafts & Fabrics",
            "type":"Retail Goods"
        }
    ],
    "sg:phone":"+1 831 761 7754",
    "sg:postcode":"95076",
    "sg:province":"CA",
    "sg:tags":[
        "florists'",
        "supply",
        "florists-wholesale",
        "florist",
        "supplies-wholesale",
        "manufacturer"
    ],
    "sg:website":"http://www.katocutflowers.com",
    "wof:name":"Kato Cut Flowers Inc",
    "wof:placetype":"venue"
},
  "geometry": {"coordinates":[-121.800723,36.947602],"type":"Point"}
}