{
  "type": "Feature",
  "properties": {
    "addr:full":"3942 Horseshoe Cir Loomis CA 95650",
    "addr:housenumber":"3942",
    "addr:postcode":"95650",
    "addr:street":"Horseshoe Cir",
    "iso:country":"US",
    "sg:address":"3942 Horseshoe Cir",
    "sg:city":"Loomis",
    "sg:classifiers":[
        {
            "category":"Wholesale",
            "subcategory":"Construction Materials",
            "type":"Manufacturing & Wholesale Goods"
        }
    ],
    "sg:phone":"+1 916 652 9545",
    "sg:postcode":"95650",
    "sg:province":"CA",
    "wof:name":"Jenkins Forest Products",
    "wof:placetype":"venue"
},
  "geometry": {"coordinates":[-121.111025,38.812865],"type":"Point"}
}