{
  "type": "Feature",
  "properties": {
    "iso:country":"US",
    "sg:address":"14403 Pacific Ave",
    "sg:city":"Baldwin Park",
    "sg:classifiers":[
        {
            "category":"Government",
            "subcategory":"Office",
            "type":"Public Place"
        }
    ],
    "sg:phone":"+1 626 813 5277",
    "sg:postcode":"91706",
    "sg:province":"CA",
    "sg:tags":[
        "village"
    ],
    "wof:name":"Baldwin Park Data Proc Div",
    "wof:placetype":"venue"
},
  "geometry": {"coordinates":[-117.959615,34.084705],"type":"Point"}
}