{
  "type": "Feature",
  "properties": {
    "addr:full":"4077 Avalon Boulevard Los Angeles CA 90011",
    "addr:housenumber":"4077",
    "addr:postcode":"90011",
    "addr:street":"Avalon Boulevard",
    "iso:country":"US",
    "sg:address":"4077 Avalon Boulevard",
    "sg:city":"Los Angeles",
    "sg:classifiers":[
        {
            "category":"Food & Beverages",
            "subcategory":"Groceries & Convenience Stores",
            "type":"Retail Goods"
        }
    ],
    "sg:phone":"+1 323 232 1230",
    "sg:postcode":"90011",
    "sg:province":"CA",
    "wof:name":"Buddy Market",
    "wof:placetype":"venue"
},
  "geometry": {"coordinates":[-118.265114,34.009385],"type":"Point"}
}