{
  "type": "Feature",
  "properties": {
    "iso:country":"US",
    "sg:address":"342 Fenway Dr",
    "sg:city":"Walnut Creek",
    "sg:classifiers":[
        {
            "category":"Retail",
            "subcategory":"Portrait Studio",
            "type":"Services"
        }
    ],
    "sg:phone":"+1 925 933 9467",
    "sg:postcode":"94598",
    "sg:province":"CA",
    "sg:tags":[
        "photographer"
    ],
    "wof:name":"Robbin Kilgore Photography",
    "wof:placetype":"venue"
},
  "geometry": {"coordinates":[-122.029144,37.916083],"type":"Point"}
}