{
  "type": "Feature",
  "properties": {
    "addr:full":"1250 S Main St Los Angeles CA 90015",
    "addr:housenumber":"1250",
    "addr:postcode":"90015",
    "addr:street":"S Main St",
    "iso:country":"US",
    "sg:address":"1250 S Main St",
    "sg:city":"Los Angeles",
    "sg:classifiers":[
        {
            "category":"Wholesale",
            "subcategory":"Drugs",
            "type":"Manufacturing & Wholesale Goods"
        }
    ],
    "sg:phone":"+1 949 929 5214",
    "sg:postcode":"90015",
    "sg:province":"CA",
    "sg:tags":[
        "cosmetic"
    ],
    "wof:name":"American Research Laboratories",
    "wof:placetype":"venue"
},
  "geometry": {"coordinates":[-118.25969000000001,34.03716],"type":"Point"}
}