{
  "type": "Feature",
  "properties": {
    "iso:country":"US",
    "sg:address":"1402 Francis Ave",
    "sg:city":"Upland",
    "sg:classifiers":[
        {
            "category":"Home & Garden",
            "subcategory":"Home Furnishings",
            "type":"Retail Goods"
        }
    ],
    "sg:phone":"+1 909 985 6684",
    "sg:postcode":"91786",
    "sg:province":"CA",
    "sg:tags":[
        "bedding"
    ],
    "wof:name":"Blankets From The Heart",
    "wof:placetype":"venue"
},
  "geometry": {"coordinates":[-117.645684,34.114358],"type":"Point"}
}