{
  "type": "Feature",
  "properties": {
    "iso:country":"US",
    "sg:address":"5800 Hannum Avenue Suite A240",
    "sg:city":"Culver City",
    "sg:classifiers":[
        {
            "category":"Professional",
            "subcategory":"Employment Agencies",
            "type":"Services"
        }
    ],
    "sg:phone":"+1 310 642 0444",
    "sg:postcode":"90230",
    "sg:province":"CA",
    "wof:name":"Stan's Quick Groom Agency",
    "wof:placetype":"venue"
},
  "geometry": {"coordinates":[-118.384646,33.987278],"type":"Point"}
}