{
  "type": "Feature",
  "properties": {
    "addr:full":"5211 E Washington Blvd Commerce CA 90040",
    "addr:housenumber":"5211",
    "addr:postcode":"90040",
    "addr:street":"E Washington Blvd",
    "iso:country":"US",
    "sg:address":"5211 E Washington Blvd",
    "sg:city":"Commerce",
    "sg:classifiers":[
        {
            "category":"Personal",
            "subcategory":"Beauty Salon",
            "type":"Services"
        }
    ],
    "sg:phone":"+1 323 266 3316",
    "sg:postcode":"90040",
    "sg:province":"CA",
    "wof:name":"Angel Hair & Nails Spa",
    "wof:placetype":"venue"
},
  "geometry": {"coordinates":[-118.167436,34.002921],"type":"Point"}
}