{
  "type": "Feature",
  "properties": {
    "addr:full":"7822 Bellaire Ave North Hollywood CA 91605",
    "addr:housenumber":"7822",
    "addr:postcode":"91605",
    "addr:street":"Bellaire Ave",
    "iso:country":"US",
    "sg:address":"7822 Bellaire Ave",
    "sg:city":"North Hollywood",
    "sg:classifiers":[
        {
            "category":"Professional",
            "subcategory":"Art Services",
            "type":"Services"
        }
    ],
    "sg:phone":"+1 818 765 4469",
    "sg:postcode":"91605",
    "sg:province":"CA",
    "sg:tags":[
        "photographer"
    ],
    "wof:name":"Century Studios",
    "wof:placetype":"venue"
},
  "geometry": {"coordinates":[-118.41122900000001,34.212514],"type":"Point"}
}