{
  "type": "Feature",
  "properties": {
    "addr:full":"2191 San Elijo Ave Cardiff By Sea CA 92007",
    "addr:housenumber":"2191",
    "addr:postcode":"92007",
    "addr:street":"San Elijo Ave",
    "iso:country":"US",
    "sg:address":"2191 San Elijo Ave",
    "sg:city":"Cardiff By Sea",
    "sg:classifiers":[
        {
            "category":"Banks & Credit Unions",
            "subcategory":"Bank",
            "type":"Services"
        }
    ],
    "sg:phone":"+1 760 632 5412",
    "sg:postcode":"92007",
    "sg:province":"CA",
    "sg:tags":[
        "loan",
        "real estate"
    ],
    "wof:name":"Neptune Processing",
    "wof:placetype":"venue"
},
  "geometry": {"coordinates":[-117.28187699999999,33.02012],"type":"Point"}
}