{
  "type": "Feature",
  "properties": {
    "addr:full":"2818 N Kingsgate Dr Orange CA 92867",
    "addr:housenumber":"2818",
    "addr:postcode":"92867",
    "addr:street":"N Kingsgate Dr",
    "iso:country":"US",
    "sg:address":"2818 N Kingsgate Dr",
    "sg:city":"Orange",
    "sg:classifiers":[
        {
            "category":"Building & Trades",
            "subcategory":"Pest Control",
            "type":"Services"
        }
    ],
    "sg:phone":"+1 714 921 8225",
    "sg:postcode":"92867",
    "sg:province":"CA",
    "sg:website":"www.allstatetermitebusters.com",
    "wof:name":"AAA Allstate Termite Busters Inc",
    "wof:placetype":"venue"
},
  "geometry": {"coordinates":[-117.815167,33.836203],"type":"Point"}
}