{
  "type": "Feature",
  "properties": {
    "iso:country":"US",
    "sg:address":"310 W Los Angeles Ave",
    "sg:city":"Moorpark",
    "sg:classifiers":[
        {
            "category":"Banks & Credit Unions",
            "subcategory":"Bank",
            "type":"Services"
        }
    ],
    "sg:phone":"+1 805 523 1818",
    "sg:postcode":"93021",
    "sg:province":"CA",
    "sg:tags":[
        "loan"
    ],
    "wof:name":"Solaris Investments",
    "wof:placetype":"venue"
},
  "geometry": {"coordinates":[-118.804698,34.284063],"type":"Point"}
}