{
  "type": "Feature",
  "properties": {
    "iso:country":"US",
    "sg:address":"1601 Manhattan Beach Blvd",
    "sg:city":"Manhattan Beach",
    "sg:classifiers":[
        {
            "category":"Arts & Performance",
            "subcategory":"Arts Center",
            "type":"Entertainment"
        },
        {
            "category":"Park",
            "type":"Public Place"
        },
        {
            "category":"Recreation",
            "subcategory":"Playground",
            "type":"Entertainment"
        }
    ],
    "sg:phone":"+1 310 802 5408",
    "sg:postcode":"90266",
    "sg:province":"CA",
    "sg:website":"www.ci.manhattan-beach.ca.us/Ind...",
    "wof:name":"Polliwog Park",
    "wof:placetype":"venue"
},
  "geometry": {"coordinates":[-118.38506599999999,33.887442],"type":"Point"}
}