{
  "type": "Feature",
  "properties": {
    "addr:full":"881 S. Winchester Blvd, Unit 95 San Jose CA 95128",
    "addr:housenumber":"881;95",
    "addr:postcode":"95128",
    "addr:street":"S. Winchester Blvd Unit;Jose",
    "iso:country":"US",
    "sg:address":"881 S. Winchester Blvd, Unit 95",
    "sg:city":"San Jose",
    "sg:classifiers":[
        {
            "category":"Professional",
            "subcategory":"Computer Services",
            "type":"Services"
        }
    ],
    "sg:postcode":"95128",
    "sg:province":"CA",
    "sg:tags":[
        "web",
        "web-2-0",
        "drupal",
        "joomla",
        "ecommerce",
        "india",
        "tax",
        "fpga",
        "semiconductor",
        "php",
        "mysql"
    ],
    "sg:website":"http://www.lamingo.com",
    "wof:name":"Lamingo",
    "wof:placetype":"venue"
},
  "geometry": {"coordinates":[-121.95013299999999,37.310993],"type":"Point"}
}