{
  "type": "Feature",
  "properties": {
    "addr:full":"154 N Lassen St Willows CA 95988",
    "addr:housenumber":"154",
    "addr:postcode":"95988",
    "addr:street":"N Lassen St",
    "iso:country":"US",
    "sg:address":"154 N Lassen St",
    "sg:city":"Willows",
    "sg:classifiers":[
        {
            "category":"Organizations",
            "subcategory":"Religious Organization",
            "type":"Services"
        }
    ],
    "sg:phone":"+1 530 934 3923",
    "sg:postcode":"95988",
    "sg:province":"CA",
    "sg:tags":[
        "church"
    ],
    "wof:name":"First Baptist Church",
    "wof:placetype":"venue"
},
  "geometry": {"coordinates":[-122.199504,39.521095],"type":"Point"}
}