{
  "type": "Feature",
  "properties": {
    "addr:full":"44128 Heaton Ave Lancaster CA 93534",
    "addr:postcode":"44128;93534",
    "addr:street":"Heaton Ave",
    "iso:country":"US",
    "sg:address":"44128 Heaton Ave",
    "sg:city":"Lancaster",
    "sg:classifiers":[
        {
            "category":"Health Services",
            "subcategory":"Clinic",
            "type":"Services"
        }
    ],
    "sg:phone":"+1 661 945 5584",
    "sg:postcode":"93534",
    "sg:province":"CA",
    "sg:tags":[
        "colonic",
        "irrigation"
    ],
    "wof:name":"Linda Halliwill",
    "wof:placetype":"venue"
},
  "geometry": {"coordinates":[-118.145258,34.685264],"type":"Point"}
}