{
  "type": "Feature",
  "properties": {
    "addr:full":"10144 Rush St South El Monte CA 91733",
    "addr:housenumber":"10144",
    "addr:postcode":"91733",
    "addr:street":"Rush St",
    "iso:country":"US",
    "sg:address":"10144 Rush St",
    "sg:city":"South El Monte",
    "sg:classifiers":[
        {
            "category":"Manufacturing",
            "subcategory":"Tools & Machinery",
            "type":"Manufacturing & Wholesale Goods"
        }
    ],
    "sg:phone":"+1 626 448 9525",
    "sg:postcode":"91733",
    "sg:province":"CA",
    "sg:tags":[
        "mfg"
    ],
    "wof:name":"Die Cast Mfg Co",
    "wof:placetype":"venue"
},
  "geometry": {"coordinates":[-118.046972,34.051759],"type":"Point"}
}