{
  "type": "Feature",
  "properties": {
    "addr:full":"1667 Cota Ave Long Beach CA 90813",
    "addr:housenumber":"1667",
    "addr:postcode":"90813",
    "addr:street":"Cota Ave",
    "iso:country":"US",
    "sg:address":"1667 Cota Ave",
    "sg:city":"Long Beach",
    "sg:classifiers":[
        {
            "category":"Retail",
            "subcategory":"Auto Repair",
            "type":"Services"
        }
    ],
    "sg:phone":"+1 562 435 4098",
    "sg:postcode":"90813",
    "sg:province":"CA",
    "sg:tags":[
        "body",
        "automobile",
        "painting"
    ],
    "wof:name":"P & S Auto Body",
    "wof:placetype":"venue"
},
  "geometry": {"coordinates":[-118.216611,33.789],"type":"Point"}
}