{
  "type": "Feature",
  "properties": {
    "iso:country":"US",
    "sg:address":"553 Tangerine Cove Dr",
    "sg:city":"Vista",
    "sg:classifiers":[
        {
            "category":"Home & Garden",
            "subcategory":"Home Furnishings",
            "type":"Retail Goods"
        }
    ],
    "sg:phone":"+1 760 521 5667",
    "sg:postcode":"92083",
    "sg:province":"CA",
    "wof:name":"Eclipse Window Covering",
    "wof:placetype":"venue"
},
  "geometry": {"coordinates":[-117.252658,33.197763],"type":"Point"}
}