{
  "type": "Feature",
  "properties": {
    "addr:full":"170 C Avenue San Diego CA 92118",
    "addr:housenumber":"170 c",
    "addr:postcode":"92118",
    "addr:street":"Avenue",
    "iso:country":"US",
    "sg:address":"170 C Avenue",
    "sg:city":"San Diego",
    "sg:classifiers":[
        {
            "category":"Arts & Performance",
            "subcategory":"Music",
            "type":"Entertainment"
        }
    ],
    "sg:phone":"+1 619 435 1100",
    "sg:postcode":"92118",
    "sg:province":"CA",
    "sg:tags":[
        "dj"
    ],
    "wof:name":"Pelky Miles Dj",
    "wof:placetype":"venue"
},
  "geometry": {"coordinates":[-117.17173099999999,32.697472],"type":"Point"}
}