{
  "type": "Feature",
  "properties": {
    "addr:full":"6100 Stow Canyon Rd Goleta CA 93117",
    "addr:housenumber":"6100",
    "addr:postcode":"93117",
    "addr:street":"Stow Canyon Rd",
    "iso:country":"US",
    "sg:address":"6100 Stow Canyon Rd",
    "sg:city":"Goleta",
    "sg:classifiers":[
        {
            "category":"Education",
            "subcategory":"School",
            "type":"Public Place"
        }
    ],
    "sg:phone":"+1 805 967 6522",
    "sg:postcode":"93117",
    "sg:province":"CA",
    "sg:tags":[
        "elementary"
    ],
    "wof:name":"Santa Barbara Charter Elementary School",
    "wof:placetype":"venue"
},
  "geometry": {"coordinates":[-119.83496100000001,34.448978],"type":"Point"}
}