{
  "type": "Feature",
  "properties": {
    "iso:country":"US",
    "sg:address":"5591 W South Ave",
    "sg:city":"Fresno",
    "sg:classifiers":[
        {
            "category":"Farming",
            "subcategory":"Vineyard",
            "type":"Manufacturing & Wholesale Goods"
        }
    ],
    "sg:phone":"+1 559 264 7451",
    "sg:postcode":"93706",
    "sg:province":"CA",
    "sg:tags":[
        "grape"
    ],
    "wof:name":"Randall Lutz",
    "wof:placetype":"venue"
},
  "geometry": {"coordinates":[-119.89653199999999,36.619178],"type":"Point"}
}