{
  "type": "Feature",
  "properties": {
    "addr:full":"15501 Texaco Ave Paramount CA 90723",
    "addr:housenumber":"15501",
    "addr:postcode":"90723",
    "addr:street":"Texaco Ave",
    "iso:country":"US",
    "sg:address":"15501 Texaco Ave",
    "sg:city":"Paramount",
    "sg:classifiers":[
        {
            "category":"Freight",
            "type":"Transportation"
        }
    ],
    "sg:phone":"+1 562 408 6677",
    "sg:postcode":"90723",
    "sg:province":"CA",
    "sg:tags":[
        "mover"
    ],
    "sg:website":"www.marlogcargo.com",
    "wof:name":"Marlog Cargo USA",
    "wof:placetype":"venue"
},
  "geometry": {"coordinates":[-118.171854,33.890946],"type":"Point"}
}