{
  "type": "Feature",
  "properties": {
    "addr:full":"1226 Pacific Ave San Francisco CA 94109",
    "addr:housenumber":"1226",
    "addr:postcode":"94109",
    "addr:street":"Pacific Ave",
    "iso:country":"US",
    "sg:address":"1226 Pacific Ave",
    "sg:city":"San Francisco",
    "sg:classifiers":[
        {
            "category":"Manufacturing",
            "subcategory":"Chemicals & Compounds",
            "type":"Manufacturing & Wholesale Goods"
        }
    ],
    "sg:phone":"+1 415 351 2800",
    "sg:postcode":"94109",
    "sg:province":"CA",
    "sg:tags":[
        "cosmetic"
    ],
    "sg:website":"www.ewightman.com",
    "wof:name":"E Wightman & Co",
    "wof:placetype":"venue"
},
  "geometry": {"coordinates":[-122.416319,37.795799],"type":"Point"}
}