{
  "type": "Feature",
  "properties": {
    "iso:country":"US",
    "sg:address":"445 W Garfield Ave",
    "sg:city":"Glendale",
    "sg:classifiers":[
        {
            "category":"Shopping",
            "subcategory":"Pharmacy",
            "type":"Retail Goods"
        }
    ],
    "sg:phone":"+1 818 507 8811",
    "sg:postcode":"91204",
    "sg:province":"CA",
    "wof:name":"L P Drugs",
    "wof:placetype":"venue"
},
  "geometry": {"coordinates":[-118.262434,34.135412],"type":"Point"}
}