{
  "type": "Feature",
  "properties": {
    "iso:country":"US",
    "sg:address":"1427 Callens Rd",
    "sg:city":"Ventura",
    "sg:classifiers":[
        {
            "category":"Wholesale",
            "subcategory":"Durable Goods & Equipment",
            "type":"Manufacturing & Wholesale Goods"
        }
    ],
    "sg:phone":"+1 805 650 1425",
    "sg:postcode":"93003",
    "sg:province":"CA",
    "wof:name":"Infrared Filters Inc",
    "wof:placetype":"venue"
},
  "geometry": {"coordinates":[-119.239561,34.262585],"type":"Point"}
}