{
  "type": "Feature",
  "properties": {
    "addr:full":"1427 Callens Rd Ventura CA 93003",
    "addr:housenumber":"1427",
    "addr:postcode":"93003",
    "addr:street":"Callens Rd",
    "iso:country":"US",
    "sg:address":"1427 Callens Rd",
    "sg:city":"Ventura",
    "sg:classifiers":[
        {
            "category":"Wholesale",
            "subcategory":"Durable Goods & Equipment",
            "type":"Manufacturing & Wholesale Goods"
        }
    ],
    "sg:phone":"+1 805 650 1425",
    "sg:postcode":"93003",
    "sg:province":"CA",
    "wof:name":"Infrared Filters Inc",
    "wof:placetype":"venue"
},
  "geometry": {"coordinates":[-119.23956099999999,34.262585],"type":"Point"}
}