{
  "type": "Feature",
  "properties": {
    "addr:full":"3520 Adams St Riverside CA 92504",
    "addr:housenumber":"3520",
    "addr:postcode":"92504",
    "addr:street":"Adams St",
    "iso:country":"US",
    "sg:address":"3520 Adams St",
    "sg:city":"Riverside",
    "sg:classifiers":[
        {
            "category":"Shopping",
            "subcategory":"Clothing, Apparel, & Fashions",
            "type":"Retail Goods"
        }
    ],
    "sg:phone":"+1 951 343 1224",
    "sg:postcode":"92504",
    "sg:province":"CA",
    "wof:name":"Portrillito Blanco",
    "wof:placetype":"venue"
},
  "geometry": {"coordinates":[-117.420874,33.928662],"type":"Point"}
}