{
  "type": "Feature",
  "properties": {
    "addr:full":"17710 Woodruff Ave Bellflower CA 90706",
    "addr:housenumber":"17710",
    "addr:postcode":"90706",
    "addr:street":"Woodruff Ave",
    "iso:country":"US",
    "sg:address":"17710 Woodruff Ave",
    "sg:city":"Bellflower",
    "sg:classifiers":[
        {
            "category":"Real Estate",
            "subcategory":"Real Estate Operator",
            "type":"Services"
        }
    ],
    "sg:phone":"+1 562 925 1119",
    "sg:postcode":"90706",
    "sg:province":"CA",
    "sg:tags":[
        "apartment"
    ],
    "wof:name":"Laurels Apartments",
    "wof:placetype":"venue"
},
  "geometry": {"coordinates":[-118.11644200000001,33.871764],"type":"Point"}
}