{
  "type": "Feature",
  "properties": {
    "addr:full":"4755 York Blvd Los Angeles CA 90042",
    "addr:housenumber":"4755",
    "addr:postcode":"90042",
    "addr:street":"York Blvd",
    "iso:country":"US",
    "sg:address":"4755 York Blvd",
    "sg:city":"Los Angeles",
    "sg:classifiers":[
        {
            "category":"Shopping",
            "subcategory":"Computers & Home Electronics",
            "type":"Retail Goods"
        }
    ],
    "sg:phone":"+1 323 982 0246",
    "sg:postcode":"90042",
    "sg:province":"CA",
    "sg:tags":[
        "game",
        "video"
    ],
    "wof:name":"Family Video",
    "wof:placetype":"venue"
},
  "geometry": {"coordinates":[-118.21098600000001,34.122342],"type":"Point"}
}