{
  "type": "Feature",
  "properties": {
    "iso:country":"US",
    "sg:address":"2 Theatre Square, Suite 143",
    "sg:city":"Orinda",
    "sg:classifiers":[
        {
            "category":"Arts & Performance",
            "subcategory":"Art Gallery",
            "type":"Entertainment"
        },
        {
            "category":"Shopping",
            "subcategory":"Jewelry",
            "type":"Retail Goods"
        }
    ],
    "sg:phone":"+1 925 253 1471",
    "sg:postcode":"94563",
    "sg:province":"CA",
    "sg:website":"www.shopaesthetics.com",
    "wof:name":"Aesthetics",
    "wof:placetype":"venue"
},
  "geometry": {"coordinates":[-122.181999,37.878899],"type":"Point"}
}