{
  "type": "Feature",
  "properties": {
    "addr:full":"165 E High St Ste 102 Moorpark CA 93021",
    "addr:housenumber":"165",
    "addr:postcode":"ca 93021",
    "addr:street":"E High St Ste 102",
    "iso:country":"US",
    "sg:address":"165 E High St Ste 102",
    "sg:city":"Moorpark",
    "sg:classifiers":[
        {
            "category":"Personal",
            "type":"Services"
        }
    ],
    "sg:phone":"+1 805 341 3234",
    "sg:postcode":"93021",
    "sg:province":"CA",
    "sg:tags":[
        "counseling"
    ],
    "wof:name":"Meyer Sasada Dianne Mft",
    "wof:placetype":"venue"
},
  "geometry": {"coordinates":[-118.87985399999999,34.285397],"type":"Point"}
}