{
  "type": "Feature",
  "properties": {
    "iso:country":"US",
    "sg:address":"6848 Five Star Blvd",
    "sg:city":"Rocklin",
    "sg:classifiers":[
        {
            "category":"Health Services",
            "subcategory":"Chiropractor",
            "type":"Services"
        }
    ],
    "sg:phone":"+1 916 771 6848",
    "sg:postcode":"95677",
    "sg:province":"CA",
    "sg:website":"www.webb-chiropractic.com",
    "wof:name":"WEBB Chiropractic",
    "wof:placetype":"venue"
},
  "geometry": {"coordinates":[-121.26648299999999,38.78189],"type":"Point"}
}