{
  "type": "Feature",
  "properties": {
    "iso:country":"US",
    "sg:address":"2910 W Manchester Blvd",
    "sg:city":"Inglewood",
    "sg:classifiers":[
        {
            "category":"Personal",
            "subcategory":"Barber",
            "type":"Services"
        }
    ],
    "sg:phone":"+1 323 971 2826",
    "sg:postcode":"90305",
    "sg:province":"CA",
    "wof:name":"Soul Sister's Hair Styling",
    "wof:placetype":"venue"
},
  "geometry": {"coordinates":[-118.324997,33.959999],"type":"Point"}
}