{
  "type": "Feature",
  "properties": {
    "iso:country":"US",
    "sg:address":"23700 Western Ave",
    "sg:city":"Harbor City",
    "sg:classifiers":[
        {
            "category":"Wholesale",
            "subcategory":"Computers",
            "type":"Manufacturing & Wholesale Goods"
        }
    ],
    "sg:phone":"+1 310 530 9800",
    "sg:postcode":"90710",
    "sg:province":"CA",
    "wof:name":"Computers N L A",
    "wof:placetype":"venue"
},
  "geometry": {"coordinates":[-118.308998,33.810101],"type":"Point"}
}