{
  "type": "Feature",
  "properties": {
    "addr:full":"200 Sheridan Ave Palo Alto CA 94306",
    "addr:housenumber":"200",
    "addr:postcode":"94306",
    "addr:street":"Sheridan Ave",
    "iso:country":"US",
    "sg:address":"200 Sheridan Ave",
    "sg:city":"Palo Alto",
    "sg:classifiers":[
        {
            "category":"Restaurant",
            "type":"Food & Drink"
        }
    ],
    "sg:menulink":"http://www.allmenus.com/ca/san-jose/275307-caffe-riace-ristorante-italian/menu/",
    "sg:phone":"+1 650 328 0407",
    "sg:postcode":"94306",
    "sg:province":"CA",
    "sg:tags":[
        "italian"
    ],
    "wof:name":"Caffe Riace Ristorante Italian",
    "wof:placetype":"venue"
},
  "geometry": {"coordinates":[-122.140416,37.426828],"type":"Point"}
}