{
  "type": "Feature",
  "properties": {
    "addr:full":"3834 Wisconsin St Oakland CA 94619",
    "addr:housenumber":"3834",
    "addr:postcode":"94619",
    "addr:street":"Wisconsin St",
    "iso:country":"US",
    "sg:address":"3834 Wisconsin St",
    "sg:city":"Oakland",
    "sg:classifiers":[
        {
            "category":"Shopping",
            "subcategory":"Jewelry",
            "type":"Retail Goods"
        }
    ],
    "sg:phone":"+1 510 530 9010",
    "sg:postcode":"94619",
    "sg:province":"CA",
    "sg:tags":[
        "jeweler"
    ],
    "wof:name":"Lacy Metals",
    "wof:placetype":"venue"
},
  "geometry": {"coordinates":[-122.19340099999999,37.794647],"type":"Point"}
}