{
  "type": "Feature",
  "properties": {
    "addr:full":"1387 N Ventura Ave Ventura CA 93001",
    "addr:housenumber":"1387",
    "addr:postcode":"93001",
    "addr:street":"N Ventura Ave",
    "iso:country":"US",
    "sg:address":"1387 N Ventura Ave",
    "sg:city":"Ventura",
    "sg:classifiers":[
        {
            "category":"Wholesale",
            "subcategory":"Metals & Minerals",
            "type":"Manufacturing & Wholesale Goods"
        }
    ],
    "sg:phone":"+1 805 643 6691",
    "sg:postcode":"93001",
    "sg:province":"CA",
    "sg:tags":[
        "steel",
        "warehouse"
    ],
    "wof:name":"Benkat & Son Steel Co",
    "wof:placetype":"venue"
},
  "geometry": {"coordinates":[-119.29668100000001,34.295062],"type":"Point"}
}