{
  "type": "Feature",
  "properties": {
    "addr:full":"1092 N El Camino Real Encinitas CA 92024",
    "addr:housenumber":"1092",
    "addr:postcode":"92024",
    "addr:street":"N El Camino Real",
    "iso:country":"US",
    "sg:address":"1092 N El Camino Real",
    "sg:city":"Encinitas",
    "sg:classifiers":[
        {
            "category":"Home & Garden",
            "subcategory":"Carpets & Floor Coverings",
            "type":"Retail Goods"
        }
    ],
    "sg:phone":"+1 760 634 6936",
    "sg:postcode":"92024",
    "sg:province":"CA",
    "sg:tags":[
        "mattress"
    ],
    "wof:name":"Simmons Mattress Gallery",
    "wof:placetype":"venue"
},
  "geometry": {"coordinates":[-117.26300000000001,33.072201],"type":"Point"}
}