{
  "type": "Feature",
  "properties": {
    "addr:full":"7975 Greenback Ln # A Citrus Heights CA 95610",
    "addr:housenumber":"7975",
    "addr:postcode":"95610",
    "addr:street":"Greenback Ln # A",
    "iso:country":"US",
    "sg:address":"7975 Greenback Ln # A",
    "sg:city":"Citrus Heights",
    "sg:classifiers":[
        {
            "category":"Shopping",
            "subcategory":"Department Store",
            "type":"Retail Goods"
        }
    ],
    "sg:phone":"+1 916 723 3974",
    "sg:postcode":"95610",
    "sg:province":"CA",
    "wof:name":"Marshall's",
    "wof:placetype":"venue"
},
  "geometry": {"coordinates":[-121.266998,38.6786],"type":"Point"}
}