{
  "type": "Feature",
  "properties": {
    "addr:full":"3213 Piedmont Ave Napa CA 94558",
    "addr:housenumber":"3213",
    "addr:postcode":"94558",
    "addr:street":"Piedmont Ave",
    "iso:country":"US",
    "sg:address":"3213 Piedmont Ave",
    "sg:city":"Napa",
    "sg:classifiers":[
        {
            "category":"Shopping",
            "subcategory":"Gifts & Souvenirs",
            "type":"Retail Goods"
        }
    ],
    "sg:phone":"+1 707 226 2338",
    "sg:postcode":"94558",
    "sg:province":"CA",
    "sg:tags":[
        "shop"
    ],
    "wof:name":"J P Gifts & Collectibles",
    "wof:placetype":"venue"
},
  "geometry": {"coordinates":[-122.297461,38.322226],"type":"Point"}
}