{
  "type": "Feature",
  "properties": {
    "iso:country":"US",
    "sg:address":"2500 P St",
    "sg:city":"Sacramento",
    "sg:classifiers":[
        {
            "category":"Food & Beverages",
            "subcategory":"Groceries & Convenience Stores",
            "type":"Retail Goods"
        }
    ],
    "sg:phone":"+1 916 456 4275",
    "sg:postcode":"95816",
    "sg:province":"CA",
    "wof:name":"Pacific Market",
    "wof:placetype":"venue"
},
  "geometry": {"coordinates":[-121.475998,38.5681],"type":"Point"}
}