{
  "type": "Feature",
  "properties": {
    "addr:full":"1850 W Redondo Beach Blvd Gardena CA 90247",
    "addr:housenumber":"1850",
    "addr:postcode":"90247",
    "addr:street":"W Redondo Beach Blvd",
    "iso:country":"US",
    "sg:address":"1850 W Redondo Beach Blvd",
    "sg:city":"Gardena",
    "sg:classifiers":[
        {
            "category":"Restaurant",
            "type":"Food & Drink"
        }
    ],
    "sg:phone":"+1 310 516 7079",
    "sg:postcode":"90247",
    "sg:province":"CA",
    "sg:tags":[
        "korean"
    ],
    "wof:name":"Nakzi Village",
    "wof:placetype":"venue"
},
  "geometry": {"coordinates":[-118.310627,33.888041],"type":"Point"}
}