{
  "type": "Feature",
  "properties": {
    "addr:full":"1630 W Redlands Blvd Redlands CA 92373",
    "addr:housenumber":"1630",
    "addr:postcode":"92373",
    "addr:street":"W Redlands Blvd",
    "iso:country":"US",
    "sg:address":"1630 W Redlands Blvd",
    "sg:city":"Redlands",
    "sg:classifiers":[
        {
            "category":"Restaurant",
            "type":"Food & Drink"
        }
    ],
    "sg:phone":"+1 909 335 8677",
    "sg:postcode":"92373",
    "sg:province":"CA",
    "wof:name":"Shogun Japanese Restaurant",
    "wof:placetype":"venue"
},
  "geometry": {"coordinates":[-117.210087,34.062972],"type":"Point"}
}