{
  "type": "Feature",
  "properties": {
    "iso:country":"US",
    "sg:address":"1051 Harrison Ave",
    "sg:city":"Venice",
    "sg:classifiers":[
        {
            "category":"Health Services",
            "subcategory":"Clinic",
            "type":"Services"
        }
    ],
    "sg:phone":"+1 310 577 7822",
    "sg:postcode":"90291",
    "sg:province":"CA",
    "wof:name":"Convictions Of The Heart",
    "wof:placetype":"venue"
},
  "geometry": {"coordinates":[-118.448958,33.990503],"type":"Point"}
}