{
  "type": "Feature",
  "properties": {
    "addr:full":"1200 Arizona St Redlands CA 92374",
    "addr:housenumber":"1200",
    "addr:postcode":"92374",
    "addr:street":"Arizona St",
    "iso:country":"US",
    "sg:address":"1200 Arizona St",
    "sg:city":"Redlands",
    "sg:classifiers":[
        {
            "category":"Building & Trades",
            "subcategory":"Construction",
            "type":"Services"
        }
    ],
    "sg:phone":"+1 909 307 2320",
    "sg:postcode":"92374",
    "sg:province":"CA",
    "sg:tags":[
        "insulation",
        "heat",
        "contractor"
    ],
    "wof:name":"Southern California Energy Svc",
    "wof:placetype":"venue"
},
  "geometry": {"coordinates":[-117.207521,34.068445],"type":"Point"}
}