{
  "type": "Feature",
  "properties": {
    "addr:full":"8450 S Englehart Ave Reedley CA 93654",
    "addr:housenumber":"8450",
    "addr:postcode":"93654",
    "addr:street":"S Englehart Ave",
    "iso:country":"US",
    "sg:address":"8450 S Englehart Ave",
    "sg:city":"Reedley",
    "sg:classifiers":[
        {
            "category":"Farming",
            "subcategory":"Farm & Veterinary Services",
            "type":"Manufacturing & Wholesale Goods"
        }
    ],
    "sg:phone":"+1 559 638 4388",
    "sg:postcode":"93654",
    "sg:province":"CA",
    "sg:tags":[
        "labor",
        "contractor"
    ],
    "wof:name":"Mora Labor Contracting",
    "wof:placetype":"venue"
},
  "geometry": {"coordinates":[-119.412904,36.61785],"type":"Point"}
}