{
  "type": "Feature",
  "properties": {
    "addr:full":"5709 Stockton Blvd Sacramento CA 95824",
    "addr:housenumber":"5709",
    "addr:postcode":"95824",
    "addr:street":"Stockton Blvd",
    "iso:country":"US",
    "sg:address":"5709 Stockton Blvd",
    "sg:city":"Sacramento",
    "sg:classifiers":[
        {
            "category":"Education",
            "subcategory":"Special Training",
            "type":"Public Place"
        },
        {
            "category":"Social Services",
            "type":"Services"
        }
    ],
    "sg:phone":"+1 916 454 1892",
    "sg:postcode":"95824",
    "sg:province":"CA",
    "sg:tags":[
        "organization",
        "agency",
        "employment",
        "welfare"
    ],
    "sg:website":"www.asianresources.org",
    "wof:name":"Asian Resources Inc",
    "wof:placetype":"venue"
},
  "geometry": {"coordinates":[-121.441885,38.523658],"type":"Point"}
}