{
  "type": "Feature",
  "properties": {
    "addr:full":"1413 Foothill Blvd La Verne CA 91750",
    "addr:housenumber":"1413",
    "addr:postcode":"91750",
    "addr:street":"Foothill Blvd",
    "iso:country":"US",
    "sg:address":"1413 Foothill Blvd",
    "sg:city":"La Verne",
    "sg:classifiers":[
        {
            "category":"Organizations",
            "subcategory":"Non-profit Organization",
            "type":"Services"
        }
    ],
    "sg:phone":"+1 909 392 1111",
    "sg:postcode":"91750",
    "sg:province":"CA",
    "wof:name":"American Middle Eas",
    "wof:placetype":"venue"
},
  "geometry": {"coordinates":[-117.77591099999999,34.116964],"type":"Point"}
}