{
  "type": "Feature",
  "properties": {
    "iso:country":"US",
    "sg:address":"6700 Dougherty Rd",
    "sg:city":"Dublin",
    "sg:classifiers":[
        {
            "category":"Food & Beverages",
            "subcategory":"Specialty",
            "type":"Retail Goods"
        }
    ],
    "sg:phone":"+1 925 560 7643",
    "sg:postcode":"94568",
    "sg:province":"CA",
    "wof:name":"Independent Herbal Life Distr",
    "wof:placetype":"venue"
},
  "geometry": {"coordinates":[-121.91017,37.719242],"type":"Point"}
}