{
  "type": "Feature",
  "properties": {
    "iso:country":"US",
    "sg:address":"6550 Yucca St",
    "sg:city":"Los Angeles",
    "sg:classifiers":[
        {
            "category":"Real Estate",
            "subcategory":"Real Estate Operator",
            "type":"Services"
        }
    ],
    "sg:phone":"+1 323 469 5782",
    "sg:postcode":"90028",
    "sg:province":"CA",
    "sg:tags":[
        "apartment"
    ],
    "wof:name":"Hollywood Terrace Apartments",
    "wof:placetype":"venue"
},
  "geometry": {"coordinates":[-118.332001,34.103401],"type":"Point"}
}