{
  "type": "Feature",
  "properties": {
    "iso:country":"US",
    "sg:address":"275 N Clovis Ave",
    "sg:city":"Clovis",
    "sg:classifiers":[
        {
            "category":"Banks & Credit Unions",
            "subcategory":"Bank",
            "type":"Services"
        }
    ],
    "sg:phone":"+1 559 324 0210",
    "sg:postcode":"93612",
    "sg:province":"CA",
    "sg:tags":[
        "financing"
    ],
    "wof:name":"Household Finance",
    "wof:placetype":"venue"
},
  "geometry": {"coordinates":[-119.699979,36.833912],"type":"Point"}
}