{
  "type": "Feature",
  "properties": {
    "iso:country":"US",
    "sg:address":"4519 Castle Rd",
    "sg:city":"La Canada Fltrdg",
    "sg:classifiers":[
        {
            "category":"Professional",
            "subcategory":"Engineering",
            "type":"Services"
        }
    ],
    "sg:phone":"+1 818 542 3580",
    "sg:postcode":"91011",
    "sg:province":"CA",
    "sg:tags":[
        "engineer"
    ],
    "wof:name":"Mission Space",
    "wof:placetype":"venue"
},
  "geometry": {"coordinates":[-118.225123,34.216246],"type":"Point"}
}