{
  "type": "Feature",
  "properties": {
    "iso:country":"US",
    "sg:address":"728 Sixteenth Street",
    "sg:city":"Sacramento",
    "sg:classifiers":[
        {
            "category":"Travel",
            "subcategory":"Hotels & Motels",
            "type":"Entertainment"
        },
        {
            "category":"Retail",
            "subcategory":"Event Space",
            "type":"Services"
        }
    ],
    "sg:phone":"+1 916 444 4436",
    "sg:postcode":"95814",
    "sg:province":"CA",
    "sg:tags":[
        "venue"
    ],
    "sg:website":"www.holidayinnexpress.com",
    "wof:name":"Holiday Inn Express Hotel Sacramento Convention Center",
    "wof:placetype":"venue"
},
  "geometry": {"coordinates":[-121.48459200000001,38.581253],"type":"Point"}
}