{
  "type": "Feature",
  "properties": {
    "iso:country":"US",
    "sg:address":"605 Connor Ln",
    "sg:city":"Woodland",
    "sg:classifiers":[
        {
            "category":"Social Services",
            "subcategory":"Adult Care",
            "type":"Services"
        }
    ],
    "sg:phone":"+1 530 662 6055",
    "sg:postcode":"95695",
    "sg:province":"CA",
    "sg:tags":[
        "home",
        "residential"
    ],
    "wof:name":"Sacred Heart Care Home",
    "wof:placetype":"venue"
},
  "geometry": {"coordinates":[-121.796424,38.672252],"type":"Point"}
}