{
  "type": "Feature",
  "properties": {
    "iso:country":"US",
    "sg:address":"5205 Avenida Encinas Suite C",
    "sg:city":"Carlsbad",
    "sg:classifiers":[
        {
            "category":"Personal",
            "subcategory":"Beauty Salon",
            "type":"Services"
        },
        {
            "category":"Personal",
            "subcategory":"Skin Care",
            "type":"Services"
        }
    ],
    "sg:phone":"+1 760 602 5002",
    "sg:postcode":"92008",
    "sg:province":"CA",
    "sg:tags":[
        "hair"
    ],
    "wof:name":"Skin Care Heaven",
    "wof:placetype":"venue"
},
  "geometry": {"coordinates":[-117.330991,33.134008],"type":"Point"}
}