{
  "type": "Feature",
  "properties": {
    "addr:full":"510 1st Ave San Diego CA 92101",
    "addr:housenumber":"510",
    "addr:postcode":"92101",
    "addr:street":"1St Ave",
    "iso:country":"US",
    "sg:address":"510 1st Ave",
    "sg:city":"San Diego",
    "sg:classifiers":[
        {
            "category":"Shopping",
            "subcategory":"Pets & Pet Supplies",
            "type":"Retail Goods"
        },
        {
            "category":"Retail",
            "subcategory":"Pet Boarding",
            "type":"Services"
        }
    ],
    "sg:phone":"+1 619 546 9150",
    "sg:postcode":"92101",
    "sg:province":"CA",
    "sg:tags":[
        "walker",
        "dog",
        "boarding/pet",
        "sitting"
    ],
    "sg:website":"www.HighRisePetSitting.com",
    "wof:name":"High Rise Pet Sitting",
    "wof:placetype":"venue"
},
  "geometry": {"coordinates":[-117.16422,32.710921],"type":"Point"}
}