{
  "type": "Feature",
  "properties": {
    "iso:country":"US",
    "sg:address":"1180 Kenwood Ave",
    "sg:city":"Turlock",
    "sg:classifiers":[
        {
            "category":"Building & Trades",
            "subcategory":"Landscaping Services",
            "type":"Services"
        }
    ],
    "sg:phone":"+1 209 632 4681",
    "sg:postcode":"95380",
    "sg:province":"CA",
    "sg:tags":[
        "landscape"
    ],
    "wof:name":"Lopez Landscaping",
    "wof:placetype":"venue"
},
  "geometry": {"coordinates":[-120.840902,37.504082],"type":"Point"}
}