{
  "type": "Feature",
  "properties": {
    "iso:country":"US",
    "sg:address":"801 S. Grand Ave Suite 1020",
    "sg:city":"Los Angeles",
    "sg:classifiers":[
        {
            "category":"Professional",
            "subcategory":"Advertising",
            "type":"Services"
        }
    ],
    "sg:phone":"+1 213 623 4991",
    "sg:postcode":"90017",
    "sg:province":"CA",
    "sg:tags":[
        "advertising"
    ],
    "sg:website":"http://indieclick.com",
    "wof:name":"IndieClick Media Group",
    "wof:placetype":"venue"
},
  "geometry": {"coordinates":[-118.259276,34.044418],"type":"Point"}
}