{
  "type": "Feature",
  "properties": {
    "iso:country":"US",
    "sg:address":"432 Cll Arboleda",
    "sg:city":"Novato",
    "sg:classifiers":[
        {
            "category":"Professional",
            "subcategory":"Art Services",
            "type":"Services"
        }
    ],
    "sg:phone":"+1 415 883 8044",
    "sg:postcode":"94949",
    "sg:province":"CA",
    "sg:tags":[
        "graphic",
        "designer"
    ],
    "sg:website":"www.zram.com",
    "wof:name":"Zram Media",
    "wof:placetype":"venue"
},
  "geometry": {"coordinates":[-122.537638,38.062105],"type":"Point"}
}