{
  "type": "Feature",
  "properties": {
    "addr:full":"2072 Hatch Rd Novato CA 94947",
    "addr:housenumber":"2072",
    "addr:postcode":"94947",
    "addr:street":"Hatch Rd",
    "iso:country":"US",
    "sg:address":"2072 Hatch Rd",
    "sg:city":"Novato",
    "sg:classifiers":[
        {
            "category":"Farming",
            "subcategory":"Farm",
            "type":"Manufacturing & Wholesale Goods"
        }
    ],
    "sg:phone":"+1 415 897 3048",
    "sg:postcode":"94947",
    "sg:province":"CA",
    "sg:tags":[
        "crop",
        "general"
    ],
    "wof:name":"North Branch Farm",
    "wof:placetype":"venue"
},
  "geometry": {"coordinates":[-122.602868,38.09795],"type":"Point"}
}