{
  "type": "Feature",
  "properties": {
    "iso:country":"US",
    "sg:address":"1350 S Hollencrest Dr",
    "sg:city":"West Covina",
    "sg:classifiers":[
        {
            "category":"Social Services",
            "subcategory":"Adult Care",
            "type":"Services"
        }
    ],
    "sg:phone":"+1 626 919 1647",
    "sg:postcode":"91791",
    "sg:province":"CA",
    "sg:tags":[
        "residential"
    ],
    "wof:name":"Krockers Family Home",
    "wof:placetype":"venue"
},
  "geometry": {"coordinates":[-117.896727,34.050201],"type":"Point"}
}