{
  "type": "Feature",
  "properties": {
    "addr:full":"113 N Starflower St Brea CA 92821",
    "addr:housenumber":"113",
    "addr:postcode":"92821",
    "addr:street":"N Starflower St",
    "iso:country":"US",
    "sg:address":"113 N Starflower St",
    "sg:city":"Brea",
    "sg:classifiers":[
        {
            "category":"Utilities",
            "subcategory":"Telephone",
            "type":"Services"
        }
    ],
    "sg:phone":"+1 714 223 9725",
    "sg:postcode":"92821",
    "sg:province":"CA",
    "sg:tags":[
        "communications"
    ],
    "wof:name":"BDB & Assoc",
    "wof:placetype":"venue"
},
  "geometry": {"coordinates":[-117.85964800000001,33.92049],"type":"Point"}
}