{
  "type": "Feature",
  "properties": {
    "addr:full":"2081 Balls Ferry Rd Anderson CA 96007",
    "addr:housenumber":"2081",
    "addr:postcode":"96007",
    "addr:street":"Balls Ferry Rd",
    "iso:country":"US",
    "sg:address":"2081 Balls Ferry Rd",
    "sg:city":"Anderson",
    "sg:classifiers":[
        {
            "category":"Personal",
            "subcategory":"Beauty Salon",
            "type":"Services"
        }
    ],
    "sg:phone":"+1 530 365 3543",
    "sg:postcode":"96007",
    "sg:province":"CA",
    "wof:name":"Final Touch Hair & Nail Salon",
    "wof:placetype":"venue"
},
  "geometry": {"coordinates":[-122.27647,40.453685],"type":"Point"}
}