{
  "type": "Feature",
  "properties": {
    "addr:full":"2634 Carson St Lakewood CA 90712",
    "addr:housenumber":"2634",
    "addr:postcode":"90712",
    "addr:street":"Carson St",
    "iso:country":"US",
    "sg:address":"2634 Carson St",
    "sg:city":"Lakewood",
    "sg:classifiers":[
        {
            "category":"Restaurant",
            "type":"Food & Drink"
        }
    ],
    "sg:phone":"+1 562 425 8448",
    "sg:postcode":"90712",
    "sg:province":"CA",
    "wof:name":"Denny's Restaurant Carson At Paramount",
    "wof:placetype":"venue"
},
  "geometry": {"coordinates":[-118.16100299999999,33.832199],"type":"Point"}
}