{
  "type": "Feature",
  "properties": {
    "addr:full":"6108 Whittier Blvd Los Angeles CA 90022",
    "addr:housenumber":"6108",
    "addr:postcode":"90022",
    "addr:street":"Whittier Blvd",
    "iso:country":"US",
    "sg:address":"6108 Whittier Blvd",
    "sg:city":"Los Angeles",
    "sg:classifiers":[
        {
            "category":"Autos & Motor Vehicles",
            "subcategory":"Auto Supplies",
            "type":"Retail Goods"
        }
    ],
    "sg:phone":"+1 323 728 7472",
    "sg:postcode":"90022",
    "sg:province":"CA",
    "wof:name":"Gomez Tire",
    "wof:placetype":"venue"
},
  "geometry": {"coordinates":[-118.139324,34.016537],"type":"Point"}
}