{
  "type": "Feature",
  "properties": {
    "iso:country":"US",
    "sg:address":"2551 State St",
    "sg:city":"Carlsbad",
    "sg:classifiers":[
        {
            "category":"Professional",
            "type":"Services"
        },
        {
            "category":"Professional",
            "subcategory":"Management & Consulting",
            "type":"Services"
        }
    ],
    "sg:phone":"+1 760 434 0300",
    "sg:postcode":"92008",
    "sg:province":"CA",
    "sg:tags":[
        "consultant",
        "lighting"
    ],
    "wof:name":"Bright Impact",
    "wof:placetype":"venue"
},
  "geometry": {"coordinates":[-117.35431,33.165809],"type":"Point"}
}