{
  "type": "Feature",
  "properties": {
    "addr:full":"433 F St Davis CA 95616",
    "addr:housenumber":"433",
    "addr:postcode":"95616",
    "addr:street":"F St",
    "iso:country":"US",
    "sg:address":"433 F St",
    "sg:city":"Davis",
    "sg:classifiers":[
        {
            "category":"Health Services",
            "subcategory":"Doctor",
            "type":"Services"
        }
    ],
    "sg:phone":"+1 530 756 7050",
    "sg:postcode":"95616",
    "sg:province":"CA",
    "sg:tags":[
        "physician",
        "surgeon"
    ],
    "wof:name":"Helen Krell MD",
    "wof:placetype":"venue"
},
  "geometry": {"coordinates":[-121.741043,38.546872],"type":"Point"}
}