{
  "type": "Feature",
  "properties": {
    "iso:country":"US",
    "sg:address":"6236 Starview Dr",
    "sg:city":"Lancaster",
    "sg:classifiers":[
        {
            "category":"Professional",
            "type":"Services"
        }
    ],
    "sg:phone":"+1 661 722 4630",
    "sg:postcode":"93536",
    "sg:province":"CA",
    "sg:tags":[
        "forestry",
        "consulting"
    ],
    "wof:name":"Mts",
    "wof:placetype":"venue"
},
  "geometry": {"coordinates":[-118.242362,34.681553],"type":"Point"}
}