{
  "type": "Feature",
  "properties": {
    "addr:full":"2706 Harbor Boulevard Suite A Costa Mesa CA 92626",
    "addr:housenumber":"2706",
    "addr:postcode":"92626",
    "addr:street":"Harbor Boulevard Suite A Costa",
    "iso:country":"US",
    "sg:address":"2706 Harbor Boulevard Suite A",
    "sg:city":"Costa Mesa",
    "sg:classifiers":[
        {
            "category":"Retail",
            "subcategory":"Auto Rental",
            "type":"Services"
        }
    ],
    "sg:phone":"+1 714 556 4473",
    "sg:postcode":"92626",
    "sg:province":"CA",
    "sg:tags":[
        "car"
    ],
    "sg:website":"www.hertz.com",
    "wof:name":"Hertz Rent A Car",
    "wof:placetype":"venue"
},
  "geometry": {"coordinates":[-117.91914800000001,33.670598],"type":"Point"}
}