{
  "type": "Feature",
  "properties": {
    "iso:country":"US",
    "sg:address":"2525 Main St",
    "sg:city":"Oakley",
    "sg:classifiers":[
        {
            "category":"Restaurant",
            "type":"Food & Drink"
        }
    ],
    "sg:phone":"+1 925 679 9015",
    "sg:postcode":"94561",
    "sg:province":"CA",
    "wof:name":"Renee Asian Island",
    "wof:placetype":"venue"
},
  "geometry": {"coordinates":[-121.730394,37.997921],"type":"Point"}
}