{
  "type": "Feature",
  "properties": {
    "addr:full":"3331 San Leandro St Oakland CA 94601",
    "addr:housenumber":"3331",
    "addr:postcode":"94601",
    "addr:street":"San Leandro St",
    "iso:country":"US",
    "sg:address":"3331 San Leandro St",
    "sg:city":"Oakland",
    "sg:classifiers":[
        {
            "category":"Personal",
            "type":"Services"
        }
    ],
    "sg:phone":"+1 510 430 1957",
    "sg:postcode":"94601",
    "sg:province":"CA",
    "sg:tags":[
        "towing"
    ],
    "wof:name":"Oakland Tire Repair & Tow Service",
    "wof:placetype":"venue"
},
  "geometry": {"coordinates":[-122.225998,37.7747],"type":"Point"}
}