{
  "type": "Feature",
  "properties": {
    "addr:full":"1933 Broadway Oakland CA 94612",
    "addr:housenumber":"1933",
    "addr:postcode":"94612",
    "addr:street":"Broadway",
    "iso:country":"US",
    "sg:address":"1933 Broadway",
    "sg:city":"Oakland",
    "sg:classifiers":[
        {
            "category":"Professional",
            "type":"Services"
        }
    ],
    "sg:phone":"+1 510 893 3500",
    "sg:postcode":"94612",
    "sg:province":"CA",
    "sg:tags":[
        "establishment"
    ],
    "wof:name":"Friends Of Creation Spiritully",
    "wof:placetype":"venue"
},
  "geometry": {"coordinates":[-122.268647,37.808608],"type":"Point"}
}