{
  "type": "Feature",
  "properties": {
    "iso:country":"US",
    "sg:address":"7602 Hollywood Blvd",
    "sg:city":"West Hollywood",
    "sg:classifiers":[
        {
            "category":"Wholesale",
            "subcategory":"Non-durable Goods",
            "type":"Manufacturing & Wholesale Goods"
        }
    ],
    "sg:phone":"+1 310 659 8468",
    "sg:postcode":"90046",
    "sg:province":"CA",
    "sg:tags":[
        "interior"
    ],
    "wof:name":"Shao Design",
    "wof:placetype":"venue"
},
  "geometry": {"coordinates":[-118.35608,34.101594],"type":"Point"}
}