{
  "type": "Feature",
  "properties": {
    "iso:country":"US",
    "sg:address":"405 Galaxy Ave",
    "sg:city":"Bakersfield",
    "sg:classifiers":[
        {
            "category":"Arena",
            "subcategory":"Sports Club",
            "type":"Entertainment"
        }
    ],
    "sg:phone":"+1 661 399 2720",
    "sg:postcode":"93308",
    "sg:province":"CA",
    "sg:tags":[
        "manager",
        "recruiter",
        "promoter"
    ],
    "wof:name":"Bakersfield Bud Light Triathlon",
    "wof:placetype":"venue"
},
  "geometry": {"coordinates":[-119.028226,35.428046],"type":"Point"}
}