{
  "type": "Feature",
  "properties": {
    "iso:country":"US",
    "sg:address":"5936 Main Ave",
    "sg:city":"Orangevale",
    "sg:classifiers":[
        {
            "category":"Insurance",
            "subcategory":"Insurance Agent",
            "type":"Services"
        }
    ],
    "sg:phone":"+1 916 988 9146",
    "sg:postcode":"95662",
    "sg:province":"CA",
    "wof:name":"State Farm Insurance",
    "wof:placetype":"venue"
},
  "geometry": {"coordinates":[-121.202405,38.673248],"type":"Point"}
}