{
  "type": "Feature",
  "properties": {
    "iso:country":"US",
    "sg:address":"5 Hutton Centre Dr Ste 860",
    "sg:city":"Santa Ana",
    "sg:classifiers":[
        {
            "category":"Professional",
            "subcategory":"Lawyer & Legal Services",
            "type":"Services"
        }
    ],
    "sg:phone":"+1 213 624 0485",
    "sg:postcode":"92707",
    "sg:province":"CA",
    "wof:name":"Sotoodeh & Associates",
    "wof:placetype":"venue"
},
  "geometry": {"coordinates":[-117.86488900000001,33.696591],"type":"Point"}
}