{
  "type": "Feature",
  "properties": {
    "addr:full":"1815 N Orangethorpe Park Anaheim CA 92801",
    "addr:housenumber":"1815",
    "addr:postcode":"92801",
    "addr:street":"N Orangethorpe Park",
    "iso:country":"US",
    "sg:address":"1815 N Orangethorpe Park",
    "sg:city":"Anaheim",
    "sg:classifiers":[
        {
            "category":"Shopping",
            "type":"Retail Goods"
        }
    ],
    "sg:phone":"+1 714 879 2711",
    "sg:postcode":"92801",
    "sg:province":"CA",
    "sg:tags":[
        "awning",
        "canopy"
    ],
    "wof:name":"Action Awnings Inc",
    "wof:placetype":"venue"
},
  "geometry": {"coordinates":[-117.90977599999999,33.860081],"type":"Point"}
}