{
  "type": "Feature",
  "properties": {
    "iso:country":"US",
    "sg:address":"1459 Broadway St",
    "sg:city":"Eureka",
    "sg:classifiers":[
        {
            "category":"Autos & Motor Vehicles",
            "subcategory":"Auto Supplies",
            "type":"Retail Goods"
        }
    ],
    "sg:phone":"+1 707 445 3283",
    "sg:postcode":"95501",
    "sg:province":"CA",
    "sg:tags":[
        "automobile",
        "stereo",
        "radio"
    ],
    "sg:website":"www.eurekacarstereo.com",
    "wof:name":"Eureka Car Stereo",
    "wof:placetype":"venue"
},
  "geometry": {"coordinates":[-124.17724800000001,40.7934],"type":"Point"}
}