{
  "type": "Feature",
  "properties": {
    "addr:full":"1431 Yosemite Ave Manteca CA 95337",
    "addr:housenumber":"1431",
    "addr:postcode":"95337",
    "addr:street":"Yosemite Ave",
    "iso:country":"US",
    "sg:address":"1431 Yosemite Ave",
    "sg:city":"Manteca",
    "sg:classifiers":[
        {
            "category":"Food & Beverages",
            "subcategory":"Groceries & Convenience Stores",
            "type":"Retail Goods"
        }
    ],
    "sg:phone":"+1 209 823 9881",
    "sg:postcode":"95337",
    "sg:province":"CA",
    "sg:tags":[
        "grocer"
    ],
    "wof:name":"Save Mart Supermarkets",
    "wof:placetype":"venue"
},
  "geometry": {"coordinates":[-121.239464,37.797445],"type":"Point"}
}