{
  "type": "Feature",
  "properties": {
    "iso:country":"US",
    "sg:address":"501 Spruce Avenue",
    "sg:city":"South San Francisco",
    "sg:classifiers":[
        {
            "category":"Education",
            "subcategory":"School",
            "type":"Public Place"
        }
    ],
    "sg:phone":"+1 650 877 8780",
    "sg:postcode":"94080",
    "sg:province":"CA",
    "sg:tags":[
        "high",
        "middle",
        "elementary"
    ],
    "wof:name":"South San Francisco Unified School District",
    "wof:placetype":"venue"
},
  "geometry": {"coordinates":[-122.415431,37.658631],"type":"Point"}
}