{
  "type": "Feature",
  "properties": {
    "iso:country":"US",
    "sg:address":"831 Gilman St",
    "sg:city":"Berkeley",
    "sg:classifiers":[
        {
            "category":"Professional",
            "subcategory":"Computer Services",
            "type":"Services"
        }
    ],
    "sg:phone":"+1 510 526 0939",
    "sg:postcode":"94710",
    "sg:province":"CA",
    "sg:tags":[
        "repair"
    ],
    "sg:website":"www.world.com",
    "wof:name":"MCI",
    "wof:placetype":"venue"
},
  "geometry": {"coordinates":[-122.30136400000001,37.879494],"type":"Point"}
}