{
  "type": "Feature",
  "properties": {
    "addr:full":"4730 W Hacienda Ave Campbell CA 95008",
    "addr:housenumber":"4730",
    "addr:postcode":"95008",
    "addr:street":"W Hacienda Ave",
    "iso:country":"US",
    "sg:address":"4730 W Hacienda Ave",
    "sg:city":"Campbell",
    "sg:classifiers":[
        {
            "category":"Professional",
            "subcategory":"Engineering",
            "type":"Services"
        },
        {
            "category":"Professional",
            "type":"Services"
        }
    ],
    "sg:phone":"+1 408 370 1274",
    "sg:postcode":"95008",
    "sg:province":"CA",
    "sg:tags":[
        "engineer"
    ],
    "wof:name":"Lamoreaux Mc Lendon & Assoc",
    "wof:placetype":"venue"
},
  "geometry": {"coordinates":[-121.983744,37.267231],"type":"Point"}
}