{
  "type": "Feature",
  "properties": {
    "iso:country":"US",
    "sg:address":"1302 Ozone Ave",
    "sg:city":"Santa Monica",
    "sg:classifiers":[
        {
            "category":"Insurance",
            "subcategory":"Insurance Agent",
            "type":"Services"
        }
    ],
    "sg:phone":"+1 310 399 6644",
    "sg:postcode":"90405",
    "sg:province":"CA",
    "wof:name":"Long Term Care",
    "wof:placetype":"venue"
},
  "geometry": {"coordinates":[-118.469033,34.003397],"type":"Point"}
}