{
  "type": "Feature",
  "properties": {
    "iso:country":"US",
    "sg:address":"2 Mareblu Ln Ste 200",
    "sg:city":"Aliso Viejo",
    "sg:classifiers":[
        {
            "category":"Health Services",
            "subcategory":"Dentist",
            "type":"Services"
        }
    ],
    "sg:phone":"+1 949 831 8826",
    "sg:postcode":"92656",
    "sg:province":"CA",
    "sg:website":"www.clairechodds.com",
    "wof:name":"Claire Cho DDS",
    "wof:placetype":"venue"
},
  "geometry": {"coordinates":[-117.702808,33.57221],"type":"Point"}
}