{
  "type": "Feature",
  "properties": {
    "addr:full":"2959 Gravenstein Highway North Sebastopol CA 95472",
    "addr:housenumber":"2959",
    "addr:postcode":"95472",
    "addr:street":"Gravenstein Highway North",
    "iso:country":"US",
    "sg:address":"2959 Gravenstein Highway North",
    "sg:city":"Sebastopol",
    "sg:classifiers":[
        {
            "category":"Winery",
            "type":"Food & Drink"
        }
    ],
    "sg:phone":"+1 707 823 7466",
    "sg:postcode":"95472",
    "sg:province":"CA",
    "sg:website":"www.merryedwards.com",
    "wof:name":"Merry Edwards Winery",
    "wof:placetype":"venue"
},
  "geometry": {"coordinates":[-122.857055,38.435051],"type":"Point"}
}