{
  "type": "Feature",
  "properties": {
    "iso:country":"US",
    "sg:address":"44249 Old Warm Springs Blvd",
    "sg:city":"Fremont",
    "sg:classifiers":[
        {
            "category":"Wholesale",
            "subcategory":"Electrical",
            "type":"Manufacturing & Wholesale Goods"
        }
    ],
    "sg:phone":"+1 510 651 3434",
    "sg:postcode":"94538",
    "sg:province":"CA",
    "sg:tags":[
        "comm",
        "system",
        "microwave"
    ],
    "sg:website":"www.customwave.com",
    "wof:name":"Custom Microwave Components",
    "wof:placetype":"venue"
},
  "geometry": {"coordinates":[-121.946189,37.506593],"type":"Point"}
}