{
  "type": "Feature",
  "properties": {
    "addr:full":"686 Wilson Ave Novato CA 94947",
    "addr:housenumber":"686",
    "addr:postcode":"94947",
    "addr:street":"Wilson Ave",
    "iso:country":"US",
    "sg:address":"686 Wilson Ave",
    "sg:city":"Novato",
    "sg:classifiers":[
        {
            "category":"Real Estate",
            "subcategory":"Real Estate Agent",
            "type":"Services"
        }
    ],
    "sg:phone":"+1 415 898 7972",
    "sg:postcode":"94947",
    "sg:province":"CA",
    "wof:name":"Anderson Realty",
    "wof:placetype":"venue"
},
  "geometry": {"coordinates":[-122.596931,38.103272],"type":"Point"}
}