{
  "type": "Feature",
  "properties": {
    "addr:full":"5602 Las Virgenes Rd Unit 83 Calabasas CA 91302",
    "addr:housenumber":"5602;83",
    "addr:postcode":"91302",
    "addr:street":"Las Virgenes Rd Unit",
    "iso:country":"US",
    "sg:address":"5602 Las Virgenes Rd Unit 83",
    "sg:city":"Calabasas",
    "sg:classifiers":[
        {
            "category":"Home & Garden",
            "subcategory":"Household Appliances",
            "type":"Retail Goods"
        }
    ],
    "sg:phone":"+1 818 878 9018",
    "sg:postcode":"91302",
    "sg:province":"CA",
    "wof:name":"Appliance Service Factory",
    "wof:placetype":"venue"
},
  "geometry": {"coordinates":[-118.700953,34.158586],"type":"Point"}
}