{
  "type": "Feature",
  "properties": {
    "iso:country":"US",
    "sg:address":"1679 E Main St",
    "sg:city":"El Cajon",
    "sg:classifiers":[
        {
            "category":"Education",
            "subcategory":"School",
            "type":"Public Place"
        }
    ],
    "sg:phone":"+1 619 441 3787",
    "sg:postcode":"92021",
    "sg:province":"CA",
    "wof:name":"Christian Unified Schools",
    "wof:placetype":"venue"
},
  "geometry": {"coordinates":[-116.921105,32.808499],"type":"Point"}
}