{
  "type": "Feature",
  "properties": {
    "addr:full":"23 Agnell Ct Sacramento CA 95835",
    "addr:housenumber":"23",
    "addr:postcode":"95835",
    "addr:street":"Agnell Ct",
    "iso:country":"US",
    "sg:address":"23 Agnell Ct",
    "sg:city":"Sacramento",
    "sg:classifiers":[
        {
            "category":"Manufacturing",
            "subcategory":"Building Materials",
            "type":"Manufacturing & Wholesale Goods"
        }
    ],
    "sg:phone":"+1 916 419 9561",
    "sg:postcode":"95835",
    "sg:province":"CA",
    "sg:tags":[
        "mfg"
    ],
    "wof:name":"Sacramento Stair Co",
    "wof:placetype":"venue"
},
  "geometry": {"coordinates":[-121.55015299999999,38.660034],"type":"Point"}
}