{
  "type": "Feature",
  "properties": {
    "iso:country":"US",
    "sg:address":"20840 Inspiration Ln",
    "sg:city":"Grass Valley",
    "sg:classifiers":[
        {
            "category":"Wholesale",
            "subcategory":"Medical Equipment & Supplies",
            "type":"Manufacturing & Wholesale Goods"
        }
    ],
    "sg:phone":"+1 530 268 8882",
    "sg:postcode":"95949",
    "sg:province":"CA",
    "sg:tags":[
        "sun",
        "goggles",
        "sunglasses"
    ],
    "wof:name":"Body Specs Sports Eyewear",
    "wof:placetype":"venue"
},
  "geometry": {"coordinates":[-121.039422,39.070036],"type":"Point"}
}