{
  "type": "Feature",
  "properties": {
    "addr:full":"706 W Broadway Glendale CA 91204",
    "addr:housenumber":"706",
    "addr:postcode":"91204",
    "addr:street":"W Broadway",
    "iso:country":"US",
    "sg:address":"706 W Broadway",
    "sg:city":"Glendale",
    "sg:classifiers":[
        {
            "category":"Organizations",
            "subcategory":"Community Association",
            "type":"Services"
        }
    ],
    "sg:phone":"+1 818 367 2878",
    "sg:postcode":"91204",
    "sg:province":"CA",
    "wof:name":"Parkwood Sylmar Homeowners Association",
    "wof:placetype":"venue"
},
  "geometry": {"coordinates":[-118.27067,34.146763],"type":"Point"}
}