{
  "type": "Feature",
  "properties": {
    "iso:country":"US",
    "sg:address":"2200 Harbor Boulevard",
    "sg:city":"Costa Mesa",
    "sg:classifiers":[
        {
            "category":"Personal",
            "subcategory":"Nail Salon",
            "type":"Services"
        }
    ],
    "sg:phone":"+1 949 645 9901",
    "sg:postcode":"92627",
    "sg:province":"CA",
    "wof:name":"1 Top Nails",
    "wof:placetype":"venue"
},
  "geometry": {"coordinates":[-117.91908599999999,33.654324],"type":"Point"}
}