{
  "type": "Feature",
  "properties": {
    "iso:country":"US",
    "sg:address":"3020 El Cerrito Plaza",
    "sg:city":"El Cerrito",
    "sg:classifiers":[
        {
            "category":"Personal",
            "type":"Services"
        }
    ],
    "sg:phone":"+1 510 528 9444",
    "sg:postcode":"94530",
    "sg:province":"CA",
    "sg:tags":[
        "local"
    ],
    "sg:website":"www.certifixlivescan.com",
    "wof:name":"El Cerrito Live Scan Fingerprinting",
    "wof:placetype":"venue"
},
  "geometry": {"coordinates":[-122.299826,37.901096],"type":"Point"}
}