{
  "type": "Feature",
  "properties": {
    "iso:country":"US",
    "sg:address":"8248 Birchbark Ave",
    "sg:city":"Pico Rivera",
    "sg:classifiers":[
        {
            "category":"Freight",
            "type":"Transportation"
        },
        {
            "category":"Wholesale",
            "subcategory":"Scrap",
            "type":"Manufacturing & Wholesale Goods"
        }
    ],
    "sg:phone":"+1 562 869 1330",
    "sg:postcode":"90660",
    "sg:province":"CA",
    "sg:tags":[
        "recycling",
        "center",
        "trucking"
    ],
    "wof:name":"Marroco Trucking Inc",
    "wof:placetype":"venue"
},
  "geometry": {"coordinates":[-118.112327,33.966653],"type":"Point"}
}