{
  "type": "Feature",
  "properties": {
    "addr:full":"8720 Whittier Blvd Pico Rivera CA 90660",
    "addr:housenumber":"8720",
    "addr:postcode":"90660",
    "addr:street":"Whittier Blvd",
    "iso:country":"US",
    "sg:address":"8720 Whittier Blvd",
    "sg:city":"Pico Rivera",
    "sg:classifiers":[
        {
            "category":"Cinema",
            "subcategory":"Movie Rental",
            "type":"Entertainment"
        }
    ],
    "sg:phone":"+1 562 801 0458",
    "sg:postcode":"90660",
    "sg:province":"CA",
    "sg:tags":[
        "video",
        "game",
        "disc",
        "leasing",
        "tape"
    ],
    "sg:website":"www.hollywoodvideo.com",
    "wof:name":"Hollywood Video",
    "wof:placetype":"venue"
},
  "geometry": {"coordinates":[-118.08699799999999,34.002399],"type":"Point"}
}