{
  "type": "Feature",
  "properties": {
    "iso:country":"US",
    "sg:address":"1110 S Robertson Blvd",
    "sg:city":"Los Angeles",
    "sg:classifiers":[
        {
            "category":"Shopping",
            "type":"Retail Goods"
        }
    ],
    "sg:phone":"+1 310 859 1322",
    "sg:postcode":"90035",
    "sg:province":"CA",
    "sg:tags":[
        "wedding",
        "supply"
    ],
    "wof:name":"Premier Label Water Co",
    "wof:placetype":"venue"
},
  "geometry": {"coordinates":[-118.383631,34.055005],"type":"Point"}
}