{
  "type": "Feature",
  "properties": {
    "iso:country":"US",
    "sg:address":"2642 McCourtney Rd",
    "sg:city":"Lincoln",
    "sg:classifiers":[
        {
            "category":"Wholesale",
            "subcategory":"Farm Supplies",
            "type":"Manufacturing & Wholesale Goods"
        }
    ],
    "sg:phone":"+1 916 645 3510",
    "sg:postcode":"95648",
    "sg:province":"CA",
    "sg:tags":[
        "livestock"
    ],
    "wof:name":"Loren Johnson Livestock",
    "wof:placetype":"venue"
},
  "geometry": {"coordinates":[-121.274625,38.919842],"type":"Point"}
}