{
  "type": "Feature",
  "properties": {
    "addr:full":"6101 Washington Blvd Culver City CA 90232",
    "addr:housenumber":"6101",
    "addr:postcode":"90232",
    "addr:street":"Washington Blvd",
    "iso:country":"US",
    "sg:address":"6101 Washington Blvd",
    "sg:city":"Culver City",
    "sg:classifiers":[
        {
            "category":"Arts & Performance",
            "subcategory":"Art Gallery",
            "type":"Entertainment"
        }
    ],
    "sg:phone":"+1 310 836 4600",
    "sg:postcode":"90232",
    "sg:province":"CA",
    "sg:website":"www.thewhole9.com",
    "wof:name":"The Whole 9 Gallery",
    "wof:placetype":"venue"
},
  "geometry": {"coordinates":[-118.37759800000001,34.031494],"type":"Point"}
}