{
  "type": "Feature",
  "properties": {
    "addr:full":"17250 Valley Blvd Fontana CA 92335",
    "addr:housenumber":"17250",
    "addr:postcode":"92335",
    "addr:street":"Valley Blvd",
    "iso:country":"US",
    "sg:address":"17250 Valley Blvd",
    "sg:city":"Fontana",
    "sg:classifiers":[
        {
            "category":"Retail",
            "subcategory":"Auto Repair",
            "type":"Services"
        }
    ],
    "sg:phone":"+1 909 429 1202",
    "sg:postcode":"92335",
    "sg:province":"CA",
    "sg:tags":[
        "body",
        "automobile",
        "painting"
    ],
    "wof:name":"Fontana Auto Collision Body",
    "wof:placetype":"venue"
},
  "geometry": {"coordinates":[-117.43513,34.07043],"type":"Point"}
}