{
  "type": "Feature",
  "properties": {
    "addr:full":"5810 Gage Ave Bell Gardens CA 90201",
    "addr:housenumber":"5810",
    "addr:postcode":"90201",
    "addr:street":"Gage Ave",
    "iso:country":"US",
    "sg:address":"5810 Gage Ave",
    "sg:city":"Bell Gardens",
    "sg:classifiers":[
        {
            "category":"Retail",
            "subcategory":"Auto Repair",
            "type":"Services"
        }
    ],
    "sg:phone":"+1 323 773 3886",
    "sg:postcode":"90201",
    "sg:province":"CA",
    "wof:name":"Ajax Brake Service",
    "wof:placetype":"venue"
},
  "geometry": {"coordinates":[-118.162003,33.975201],"type":"Point"}
}