{
  "type": "Feature",
  "properties": {
    "iso:country":"US",
    "sg:address":"6621 Sarnia Ave",
    "sg:city":"Long Beach",
    "sg:classifiers":[
        {
            "category":"Manufacturing",
            "subcategory":"Metals",
            "type":"Manufacturing & Wholesale Goods"
        }
    ],
    "sg:phone":"+1 562 634 6878",
    "sg:postcode":"90805",
    "sg:province":"CA",
    "sg:tags":[
        "spinning"
    ],
    "wof:name":"Continental Metal Spinning",
    "wof:placetype":"venue"
},
  "geometry": {"coordinates":[-118.165565,33.875384],"type":"Point"}
}