{
  "type": "Feature",
  "properties": {
    "iso:country":"US",
    "sg:address":"1923 16th St",
    "sg:city":"San Pablo",
    "sg:classifiers":[
        {
            "category":"Building & Trades",
            "subcategory":"Cleaning & Sanitation",
            "type":"Services"
        }
    ],
    "sg:phone":"+1 510 236 4724",
    "sg:postcode":"94806",
    "sg:province":"CA",
    "sg:tags":[
        "janitor"
    ],
    "wof:name":"Edenfur Janitorial",
    "wof:placetype":"venue"
},
  "geometry": {"coordinates":[-122.353429,37.960763],"type":"Point"}
}