{
  "type": "Feature",
  "properties": {
    "addr:full":"43 Panoramic Way Walnut Creek CA 94595",
    "addr:housenumber":"43",
    "addr:postcode":"94595",
    "addr:street":"Panoramic Way",
    "iso:country":"US",
    "sg:address":"43 Panoramic Way",
    "sg:city":"Walnut Creek",
    "sg:classifiers":[
        {
            "category":"Real Estate",
            "subcategory":"Architect",
            "type":"Services"
        }
    ],
    "sg:phone":"+1 925 906 1957",
    "sg:postcode":"94595",
    "sg:province":"CA",
    "wof:name":"Thomas J Wilson",
    "wof:placetype":"venue"
},
  "geometry": {"coordinates":[-122.076142,37.884302],"type":"Point"}
}