{
  "type": "Feature",
  "properties": {
    "addr:full":"26778 Baseline St Highland CA 92346",
    "addr:housenumber":"26778",
    "addr:postcode":"92346",
    "addr:street":"Baseline St",
    "iso:country":"US",
    "sg:address":"26778 Baseline St",
    "sg:city":"Highland",
    "sg:classifiers":[
        {
            "category":"Wholesale",
            "subcategory":"Motor Vehicles",
            "type":"Manufacturing & Wholesale Goods"
        },
        {
            "category":"Wholesale",
            "subcategory":"Auto Parts",
            "type":"Manufacturing & Wholesale Goods"
        }
    ],
    "sg:phone":"+1 909 863 1321",
    "sg:postcode":"92346",
    "sg:province":"CA",
    "sg:tags":[
        "automobile",
        "supply"
    ],
    "wof:name":"J & T Auto Wholesale",
    "wof:placetype":"venue"
},
  "geometry": {"coordinates":[-117.221081,34.12134],"type":"Point"}
}