{
  "type": "Feature",
  "properties": {
    "addr:full":"542 Ramona St Palo Alto CA 94301",
    "addr:housenumber":"542",
    "addr:postcode":"94301",
    "addr:street":"Ramona St",
    "iso:country":"US",
    "sg:address":"542 Ramona St",
    "sg:city":"Palo Alto",
    "sg:classifiers":[
        {
            "category":"Organizations",
            "subcategory":"Religious Organization",
            "type":"Services"
        }
    ],
    "sg:phone":"+1 650 326 6371",
    "sg:postcode":"94301",
    "sg:province":"CA",
    "sg:tags":[
        "church"
    ],
    "wof:name":"First Ch Of Christ Scientist",
    "wof:placetype":"venue"
},
  "geometry": {"coordinates":[-122.161445,37.444763],"type":"Point"}
}