{
  "type": "Feature",
  "properties": {
    "addr:full":"1670 Shop St South Lake Tahoe CA 96150",
    "addr:housenumber":"1670",
    "addr:postcode":"96150",
    "addr:street":"Shop St",
    "iso:country":"US",
    "sg:address":"1670 Shop St",
    "sg:city":"South Lake Tahoe",
    "sg:classifiers":[
        {
            "category":"Retail",
            "subcategory":"Auto Repair",
            "type":"Services"
        }
    ],
    "sg:phone":"+1 530 544 7267",
    "sg:postcode":"96150",
    "sg:province":"CA",
    "sg:tags":[
        "repairing",
        "automobile"
    ],
    "wof:name":"Sam's Auto Care & Mobile Rpr",
    "wof:placetype":"venue"
},
  "geometry": {"coordinates":[-120.012156,38.905169],"type":"Point"}
}