{
  "type": "Feature",
  "properties": {
    "iso:country":"US",
    "sg:address":"9608 S Main St",
    "sg:city":"Los Angeles",
    "sg:classifiers":[
        {
            "category":"Organizations",
            "subcategory":"Religious Organization",
            "type":"Services"
        }
    ],
    "sg:phone":"+1 323 755 6746",
    "sg:postcode":"90003",
    "sg:province":"CA",
    "sg:tags":[
        "church"
    ],
    "wof:name":"To God Be The Glory",
    "wof:placetype":"venue"
},
  "geometry": {"coordinates":[-118.273798,33.948364],"type":"Point"}
}