{
  "type": "Feature",
  "properties": {
    "addr:full":"4280 Iowa St Benicia CA 94510",
    "addr:housenumber":"4280",
    "addr:postcode":"94510",
    "addr:street":"Iowa St",
    "iso:country":"US",
    "sg:address":"4280 Iowa St",
    "sg:city":"Benicia",
    "sg:classifiers":[
        {
            "category":"Autos & Motor Vehicles",
            "subcategory":"Auto Supplies",
            "type":"Retail Goods"
        }
    ],
    "sg:phone":"+1 707 552 6666",
    "sg:postcode":"94510",
    "sg:province":"CA",
    "sg:tags":[
        "tire"
    ],
    "wof:name":"Pioneer Tire Supply",
    "wof:placetype":"venue"
},
  "geometry": {"coordinates":[-122.128309,38.075351],"type":"Point"}
}