{
  "type": "Feature",
  "properties": {
    "addr:full":"101 Howard Street, Suite 310 San Francisco CA 94105",
    "addr:housenumber":"101",
    "addr:postcode":"94105",
    "addr:street":"Howard Street Suite 310",
    "iso:country":"US",
    "sg:address":"101 Howard Street, Suite 310",
    "sg:city":"San Francisco",
    "sg:classifiers":[
        {
            "category":"Professional",
            "subcategory":"Lawyer & Legal Services",
            "type":"Services"
        }
    ],
    "sg:phone":"+1 415 778 6337",
    "sg:postcode":"94105",
    "sg:province":"CA",
    "sg:website":"www.marsannelaw.com/",
    "wof:name":"Law Offices of Marsanne Weese",
    "wof:placetype":"venue"
},
  "geometry": {"coordinates":[-122.39260899999999,37.7911],"type":"Point"}
}