{
  "type": "Feature",
  "properties": {
    "addr:full":"23828 Crenshaw Blvd Torrance CA 90505",
    "addr:housenumber":"23828",
    "addr:postcode":"90505",
    "addr:street":"Crenshaw Blvd",
    "iso:country":"US",
    "sg:address":"23828 Crenshaw Blvd",
    "sg:city":"Torrance",
    "sg:classifiers":[
        {
            "category":"Personal",
            "subcategory":"Beauty Salon",
            "type":"Services"
        }
    ],
    "sg:phone":"+1 310 326 7722",
    "sg:postcode":"90505",
    "sg:province":"CA",
    "wof:name":"Mona's Hair Salon",
    "wof:placetype":"venue"
},
  "geometry": {"coordinates":[-118.327853,33.807909],"type":"Point"}
}