{
  "type": "Feature",
  "properties": {
    "addr:full":"710 Brookside Ave Redlands CA 92373",
    "addr:housenumber":"710",
    "addr:postcode":"92373",
    "addr:street":"Brookside Ave",
    "iso:country":"US",
    "sg:address":"710 Brookside Ave",
    "sg:city":"Redlands",
    "sg:classifiers":[
        {
            "category":"Shopping",
            "type":"Retail Goods"
        }
    ],
    "sg:phone":"+1 909 307 5646",
    "sg:postcode":"92373",
    "sg:province":"CA",
    "sg:tags":[
        "cosmetic",
        "perfume"
    ],
    "wof:name":"Permanent Cosmetics",
    "wof:placetype":"venue"
},
  "geometry": {"coordinates":[-117.193161,34.051324],"type":"Point"}
}