{
  "type": "Feature",
  "properties": {
    "iso:country":"US",
    "sg:address":"30 Hemingway Ct",
    "sg:city":"Trabuco Canyon",
    "sg:classifiers":[
        {
            "category":"Government",
            "subcategory":"Fire Station",
            "type":"Public Place"
        }
    ],
    "sg:phone":"+1 949 766 3226",
    "sg:postcode":"92679",
    "sg:province":"CA",
    "sg:tags":[
        "protection"
    ],
    "wof:name":"Fast Fire Pro",
    "wof:placetype":"venue"
},
  "geometry": {"coordinates":[-117.599261,33.686507],"type":"Point"}
}