{
  "type": "Feature",
  "properties": {
    "addr:full":"827 S Lawson St City Of Industry CA 91748",
    "addr:housenumber":"827",
    "addr:postcode":"91748",
    "addr:street":"S Lawson St",
    "iso:country":"US",
    "sg:address":"827 S Lawson St",
    "sg:city":"City Of Industry",
    "sg:classifiers":[
        {
            "category":"Wholesale",
            "subcategory":"Apparel",
            "type":"Manufacturing & Wholesale Goods"
        }
    ],
    "sg:phone":"+1 626 581 1808",
    "sg:postcode":"91748",
    "sg:province":"CA",
    "sg:tags":[
        "shoes"
    ],
    "sg:website":"www.new-creators.com",
    "wof:name":"New Creators",
    "wof:placetype":"venue"
},
  "geometry": {"coordinates":[-117.910774,34.003937],"type":"Point"}
}