{
  "type": "Feature",
  "properties": {
    "iso:country":"US",
    "sg:address":"2841 Meridian Ave",
    "sg:city":"San Jose",
    "sg:classifiers":[
        {
            "category":"Shopping",
            "type":"Retail Goods"
        }
    ],
    "sg:phone":"+1 408 265 1833",
    "sg:postcode":"95124",
    "sg:province":"CA",
    "sg:tags":[
        "church",
        "supply"
    ],
    "wof:name":"Berean Christian Stores",
    "wof:placetype":"venue"
},
  "geometry": {"coordinates":[-121.906108,37.271174],"type":"Point"}
}