{
  "type": "Feature",
  "properties": {
    "addr:full":"8088 Palm Ln San Bernardino CA 92410",
    "addr:housenumber":"8088",
    "addr:postcode":"92410",
    "addr:street":"Palm Ln",
    "iso:country":"US",
    "sg:address":"8088 Palm Ln",
    "sg:city":"San Bernardino",
    "sg:classifiers":[
        {
            "category":"Government",
            "subcategory":"Office",
            "type":"Public Place"
        }
    ],
    "sg:phone":"+1 909 381 7976",
    "sg:postcode":"92410",
    "sg:province":"CA",
    "sg:tags":[
        "county",
        "program",
        "health"
    ],
    "wof:name":"San Bernardino County Health",
    "wof:placetype":"venue"
},
  "geometry": {"coordinates":[-117.271714,34.107363],"type":"Point"}
}