{
  "type": "Feature",
  "properties": {
    "addr:full":"6520 Canoga Ave Ste D-2 San Fernando Valley CA 91303",
    "addr:housenumber":"6520",
    "addr:postcode":"91303",
    "addr:street":"Canoga Ave Ste D-2",
    "iso:country":"US",
    "sg:address":"6520 Canoga Ave Ste D-2",
    "sg:city":"San Fernando Valley",
    "sg:classifiers":[
        {
            "category":"Food & Beverages",
            "subcategory":"Liquor & Beverages",
            "type":"Retail Goods"
        }
    ],
    "sg:phone":"+1 818 340 1548",
    "sg:postcode":"91303",
    "sg:province":"CA",
    "sg:tags":[
        "beer",
        "spirit",
        "wine"
    ],
    "sg:website":"www.bevmo.com",
    "wof:name":"BevMo!",
    "wof:placetype":"venue"
},
  "geometry": {"coordinates":[-118.59744600000001,34.190389],"type":"Point"}
}