{
  "type": "Feature",
  "properties": {
    "iso:country":"US",
    "sg:address":"2335 E Valley Pkwy Ste E",
    "sg:city":"Escondido",
    "sg:classifiers":[
        {
            "category":"Restaurant",
            "type":"Food & Drink"
        }
    ],
    "sg:phone":"+1 760 743 8622",
    "sg:postcode":"92027",
    "sg:province":"CA",
    "sg:tags":[
        "chinese"
    ],
    "wof:name":"Yummy Express",
    "wof:placetype":"venue"
},
  "geometry": {"coordinates":[-117.045492,33.140421],"type":"Point"}
}