{
  "type": "Feature",
  "properties": {
    "addr:full":"5923 Cloverly Ave Temple City CA 91780",
    "addr:housenumber":"5923",
    "addr:postcode":"91780",
    "addr:street":"Cloverly Ave",
    "iso:country":"US",
    "sg:address":"5923 Cloverly Ave",
    "sg:city":"Temple City",
    "sg:classifiers":[
        {
            "category":"Banks & Credit Unions",
            "subcategory":"Bank",
            "type":"Services"
        }
    ],
    "sg:phone":"+1 626 291 5868",
    "sg:postcode":"91780",
    "sg:province":"CA",
    "sg:tags":[
        "loan",
        "real estate"
    ],
    "wof:name":"Mortgage Lending & Assoc",
    "wof:placetype":"venue"
},
  "geometry": {"coordinates":[-118.06382499999999,34.106321],"type":"Point"}
}