{
  "type": "Feature",
  "properties": {
    "addr:full":"7518 Pratt Ave Citrus Heights CA 95610",
    "addr:housenumber":"7518",
    "addr:postcode":"95610",
    "addr:street":"Pratt Ave",
    "iso:country":"US",
    "sg:address":"7518 Pratt Ave",
    "sg:city":"Citrus Heights",
    "sg:classifiers":[
        {
            "category":"Freight",
            "type":"Transportation"
        }
    ],
    "sg:phone":"+1 916 485 3222",
    "sg:postcode":"95610",
    "sg:province":"CA",
    "sg:tags":[
        "mover"
    ],
    "sg:website":"www.aaamovingsacto.com",
    "wof:name":"AAA Moving",
    "wof:placetype":"venue"
},
  "geometry": {"coordinates":[-121.28921699999999,38.703102],"type":"Point"}
}