{
  "type": "Feature",
  "properties": {
    "addr:full":"6191 N Figueroa St Los Angeles CA 90042",
    "addr:housenumber":"6191",
    "addr:postcode":"90042",
    "addr:street":"N Figueroa St",
    "iso:country":"US",
    "sg:address":"6191 N Figueroa St",
    "sg:city":"Los Angeles",
    "sg:classifiers":[
        {
            "category":"Personal",
            "subcategory":"Beauty Salon",
            "type":"Services"
        }
    ],
    "sg:phone":"+1 323 255 3491",
    "sg:postcode":"90042",
    "sg:province":"CA",
    "sg:tags":[
        "hair"
    ],
    "sg:website":"www.geocities.com/rocioshairstudio",
    "wof:name":"Rocio Hair Studio",
    "wof:placetype":"venue"
},
  "geometry": {"coordinates":[-118.18463800000001,34.1152],"type":"Point"}
}