{
  "type": "Feature",
  "properties": {
    "iso:country":"US",
    "sg:address":"3234 Freeman St",
    "sg:city":"San Diego",
    "sg:classifiers":[
        {
            "category":"Insurance",
            "subcategory":"Insurance Agent",
            "type":"Services"
        }
    ],
    "sg:phone":"+1 619 758 0857",
    "sg:postcode":"92106",
    "sg:province":"CA",
    "wof:name":"Chuck Lombardi",
    "wof:placetype":"venue"
},
  "geometry": {"coordinates":[-117.21818500000001,32.742292],"type":"Point"}
}