{
  "type": "Feature",
  "properties": {
    "addr:full":"213 W Elder St Fallbrook CA 92028",
    "addr:housenumber":"213",
    "addr:postcode":"92028",
    "addr:street":"W Elder St",
    "iso:country":"US",
    "sg:address":"213 W Elder St",
    "sg:city":"Fallbrook",
    "sg:classifiers":[
        {
            "category":"Autos & Motor Vehicles",
            "subcategory":"Automobile Sales",
            "type":"Retail Goods"
        },
        {
            "category":"Retail",
            "subcategory":"Auto Rental",
            "type":"Services"
        }
    ],
    "sg:phone":"+1 760 728 7100",
    "sg:postcode":"92028",
    "sg:province":"CA",
    "sg:tags":[
        "dealers-used",
        "car",
        "used",
        "cars-wholesale"
    ],
    "sg:website":"www.fallbrookmotors.net",
    "wof:name":"Fallbrook Motors",
    "wof:placetype":"venue"
},
  "geometry": {"coordinates":[-117.25299800000001,33.3801],"type":"Point"}
}