{
  "type": "Feature",
  "properties": {
    "iso:country":"US",
    "sg:address":"1421 Hemlock Ave",
    "sg:city":"Anderson",
    "sg:classifiers":[
        {
            "category":"Professional",
            "subcategory":"Advertising",
            "type":"Services"
        },
        {
            "category":"Manufacturing",
            "subcategory":"Signs",
            "type":"Manufacturing & Wholesale Goods"
        }
    ],
    "sg:phone":"+1 530 365 0537",
    "sg:postcode":"96007",
    "sg:province":"CA",
    "sg:tags":[
        "specialty"
    ],
    "wof:name":"Art Noahs Signs & Graphic",
    "wof:placetype":"venue"
},
  "geometry": {"coordinates":[-122.29662399999999,40.434496],"type":"Point"}
}