{
  "type": "Feature",
  "properties": {
    "addr:full":"675 E Campbell Ave Campbell CA 95008",
    "addr:housenumber":"675",
    "addr:postcode":"95008",
    "addr:street":"E Campbell Ave",
    "iso:country":"US",
    "sg:address":"675 E Campbell Ave",
    "sg:city":"Campbell",
    "sg:classifiers":[
        {
            "category":"Travel",
            "subcategory":"Hotels & Motels",
            "type":"Entertainment"
        }
    ],
    "sg:phone":"+1 408 374 4300",
    "sg:postcode":"95008",
    "sg:province":"CA",
    "sg:website":"www.campbell-inn.com",
    "wof:name":"Campbell Inn",
    "wof:placetype":"venue"
},
  "geometry": {"coordinates":[-121.93746,37.287297],"type":"Point"}
}