{
  "type": "Feature",
  "properties": {
    "iso:country":"US",
    "sg:address":"10049 Rubio Ave",
    "sg:city":"North Hills",
    "sg:classifiers":[
        {
            "category":"Retail",
            "subcategory":"Laundry & Dry Cleaning",
            "type":"Services"
        }
    ],
    "sg:phone":"+1 818 360 9943",
    "sg:postcode":"91343",
    "sg:province":"CA",
    "sg:tags":[
        "gown",
        "bridal",
        "preservation"
    ],
    "sg:website":"www.forevertreasured.com",
    "wof:name":"Forever Treasured",
    "wof:placetype":"venue"
},
  "geometry": {"coordinates":[-118.495903,34.253339],"type":"Point"}
}