{
  "type": "Feature",
  "properties": {
    "iso:country":"US",
    "sg:address":"2309 Downar Way",
    "sg:city":"Sacramento",
    "sg:classifiers":[
        {
            "category":"Building & Trades",
            "subcategory":"Electrical",
            "type":"Services"
        }
    ],
    "sg:phone":"+1 831 915 9679",
    "sg:postcode":"95838",
    "sg:province":"CA",
    "sg:tags":[
        "electrician"
    ],
    "wof:name":"Antonio M Ramirez",
    "wof:placetype":"venue"
},
  "geometry": {"coordinates":[-121.412761,38.645343],"type":"Point"}
}