{
  "type": "Feature",
  "properties": {
    "addr:full":"429 Nob Hill Dr Walnut Creek CA 94596",
    "addr:housenumber":"429",
    "addr:postcode":"94596",
    "addr:street":"Nob Hill Dr",
    "iso:country":"US",
    "sg:address":"429 Nob Hill Dr",
    "sg:city":"Walnut Creek",
    "sg:classifiers":[
        {
            "category":"Wholesale",
            "subcategory":"Drugs",
            "type":"Manufacturing & Wholesale Goods"
        }
    ],
    "sg:phone":"+1 925 938 2166",
    "sg:postcode":"94596",
    "sg:province":"CA",
    "sg:tags":[
        "cosmetic"
    ],
    "sg:website":"www.productsorganica.com",
    "wof:name":"Products Organica Inc",
    "wof:placetype":"venue"
},
  "geometry": {"coordinates":[-122.044113,37.896225],"type":"Point"}
}