{
  "type": "Feature",
  "properties": {
    "iso:country":"US",
    "sg:address":"226 S Ridgewood Rd",
    "sg:city":"Greenbrae",
    "sg:classifiers":[
        {
            "category":"Professional",
            "type":"Services"
        },
        {
            "category":"Professional",
            "subcategory":"Art Services",
            "type":"Services"
        }
    ],
    "sg:phone":"+1 415 721 7616",
    "sg:postcode":"94904",
    "sg:province":"CA",
    "sg:tags":[
        "graphic",
        "designer"
    ],
    "wof:name":"Pentalpha",
    "wof:placetype":"venue"
},
  "geometry": {"coordinates":[-122.556946,37.943222],"type":"Point"}
}