{
  "type": "Feature",
  "properties": {
    "addr:full":"190 Grace Ct Cloverdale CA 95425",
    "addr:housenumber":"190",
    "addr:postcode":"95425",
    "addr:street":"Grace Ct",
    "iso:country":"US",
    "sg:address":"190 Grace Ct",
    "sg:city":"Cloverdale",
    "sg:classifiers":[
        {
            "category":"Building & Trades",
            "subcategory":"Construction",
            "type":"Services"
        }
    ],
    "sg:phone":"+1 707 894 8689",
    "sg:postcode":"95425",
    "sg:province":"CA",
    "wof:name":"W M Linn Company",
    "wof:placetype":"venue"
},
  "geometry": {"coordinates":[-123.021794,38.814156],"type":"Point"}
}