{
  "type": "Feature",
  "properties": {
    "addr:full":"8621 Beech Ave Fontana CA 92335",
    "addr:housenumber":"8621",
    "addr:postcode":"92335",
    "addr:street":"Beech Ave",
    "iso:country":"US",
    "sg:address":"8621 Beech Ave",
    "sg:city":"Fontana",
    "sg:classifiers":[
        {
            "category":"Wholesale",
            "subcategory":"Construction Materials",
            "type":"Manufacturing & Wholesale Goods"
        }
    ],
    "sg:phone":"+1 909 355 1635",
    "sg:postcode":"92335",
    "sg:province":"CA",
    "sg:tags":[
        "pallet",
        "skid"
    ],
    "wof:name":"Garcia's Woodworks Corp",
    "wof:placetype":"venue"
},
  "geometry": {"coordinates":[-117.471143,34.098747],"type":"Point"}
}