{
  "type": "Feature",
  "properties": {
    "addr:full":"2920 W Temple St Los Angeles CA 90026",
    "addr:housenumber":"2920",
    "addr:postcode":"90026",
    "addr:street":"W Temple St",
    "iso:country":"US",
    "sg:address":"2920 W Temple St",
    "sg:city":"Los Angeles",
    "sg:classifiers":[
        {
            "category":"Restaurant",
            "type":"Food & Drink"
        }
    ],
    "sg:phone":"+1 213 487 0424",
    "sg:postcode":"90026",
    "sg:province":"CA",
    "sg:tags":[
        "thai"
    ],
    "sg:website":"www.quickythai.com",
    "wof:name":"Quickie Thai",
    "wof:placetype":"venue"
},
  "geometry": {"coordinates":[-118.279357,34.074156],"type":"Point"}
}