{
  "type": "Feature",
  "properties": {
    "addr:full":"874 N Batavia St Orange CA 92868",
    "addr:housenumber":"874",
    "addr:postcode":"92868",
    "addr:street":"N Batavia St",
    "iso:country":"US",
    "sg:address":"874 N Batavia St",
    "sg:city":"Orange",
    "sg:classifiers":[
        {
            "category":"Wholesale",
            "subcategory":"Construction Materials",
            "type":"Manufacturing & Wholesale Goods"
        }
    ],
    "sg:phone":"+1 714 532 3828",
    "sg:postcode":"92868",
    "sg:province":"CA",
    "sg:tags":[
        "hardware",
        "frame",
        "industrial",
        "door",
        "store"
    ],
    "wof:name":"Advantage Door And Hardware",
    "wof:placetype":"venue"
},
  "geometry": {"coordinates":[-117.86196700000001,33.801961],"type":"Point"}
}