{
  "type": "Feature",
  "properties": {
    "addr:full":"330 13th St Oakland CA 94612",
    "addr:housenumber":"330",
    "addr:postcode":"94612",
    "addr:street":"13Th St",
    "iso:country":"US",
    "sg:address":"330 13th St",
    "sg:city":"Oakland",
    "sg:classifiers":[
        {
            "category":"Real Estate",
            "subcategory":"Real Estate Services",
            "type":"Services"
        },
        {
            "category":"Real Estate",
            "subcategory":"Real Estate Operator",
            "type":"Services"
        }
    ],
    "sg:phone":"+1 510 452 0716",
    "sg:postcode":"94612",
    "sg:province":"CA",
    "sg:tags":[
        "vacancy",
        "apartment",
        "rental",
        "listing"
    ],
    "wof:name":"330 13th Street",
    "wof:placetype":"venue"
},
  "geometry": {"coordinates":[-122.268778,37.80252],"type":"Point"}
}