{
  "type": "Feature",
  "properties": {
    "addr:full":"7349 Coldwater Canyon Ave North Hollywood CA 91605",
    "addr:housenumber":"7349",
    "addr:postcode":"91605",
    "addr:street":"Coldwater Canyon Ave",
    "iso:country":"US",
    "sg:address":"7349 Coldwater Canyon Ave",
    "sg:city":"North Hollywood",
    "sg:classifiers":[
        {
            "category":"Building & Trades",
            "subcategory":"Construction",
            "type":"Services"
        }
    ],
    "sg:phone":"+1 818 255 5715",
    "sg:postcode":"91605",
    "sg:province":"CA",
    "sg:tags":[
        "maker",
        "cabinet"
    ],
    "wof:name":"Efi Cabinets",
    "wof:placetype":"venue"
},
  "geometry": {"coordinates":[-118.413791,34.204573],"type":"Point"}
}