{
  "type": "Feature",
  "properties": {
    "addr:full":"5050 Murphy Canyon Rd San Diego CA 92123",
    "addr:housenumber":"5050",
    "addr:postcode":"92123",
    "addr:street":"Murphy Canyon Rd",
    "iso:country":"US",
    "sg:address":"5050 Murphy Canyon Rd",
    "sg:city":"San Diego",
    "sg:classifiers":[
        {
            "category":"Real Estate",
            "subcategory":"Real Estate Services",
            "type":"Services"
        }
    ],
    "sg:phone":"+1 619 725 1200",
    "sg:postcode":"92123",
    "sg:province":"CA",
    "sg:tags":[
        "company",
        "title"
    ],
    "sg:website":"www.todiversified.com",
    "wof:name":"Diversified Title & Escrow Svc",
    "wof:placetype":"venue"
},
  "geometry": {"coordinates":[-117.11940800000001,32.825869],"type":"Point"}
}