{
  "type": "Feature",
  "properties": {
    "addr:full":"1571 W 8th Ave Chico CA 95926",
    "addr:housenumber":"1571",
    "addr:postcode":"95926",
    "addr:street":"W 8Th Ave",
    "iso:country":"US",
    "sg:address":"1571 W 8th Ave",
    "sg:city":"Chico",
    "sg:classifiers":[
        {
            "category":"Health Services",
            "subcategory":"Chiropractor",
            "type":"Services"
        }
    ],
    "sg:phone":"+1 530 879 9555",
    "sg:postcode":"95926",
    "sg:province":"CA",
    "wof:name":"Peter M Mallary DC",
    "wof:placetype":"venue"
},
  "geometry": {"coordinates":[-121.869946,39.732912],"type":"Point"}
}