{
  "type": "Feature",
  "properties": {
    "addr:full":"4456 Vandever Ave San Diego CA 92120",
    "addr:housenumber":"4456",
    "addr:postcode":"92120",
    "addr:street":"Vandever Ave",
    "iso:country":"US",
    "sg:address":"4456 Vandever Ave",
    "sg:city":"San Diego",
    "sg:classifiers":[
        {
            "category":"Professional",
            "subcategory":"Lawyer & Legal Services",
            "type":"Services"
        }
    ],
    "sg:phone":"+1 619 325 1499",
    "sg:postcode":"92120",
    "sg:province":"CA",
    "sg:tags":[
        "attorney"
    ],
    "wof:name":"Arlene Murphy Attorney At Law",
    "wof:placetype":"venue"
},
  "geometry": {"coordinates":[-117.099531,32.787785],"type":"Point"}
}