{
  "type": "Feature",
  "properties": {
    "iso:country":"US",
    "sg:address":"8218 Calmosa Ave",
    "sg:city":"Whittier",
    "sg:classifiers":[
        {
            "category":"Professional",
            "type":"Services"
        }
    ],
    "sg:phone":"+1 562 696 8202",
    "sg:postcode":"90602",
    "sg:province":"CA",
    "wof:name":"Alexandra Heinemann",
    "wof:placetype":"venue"
},
  "geometry": {"coordinates":[-118.015704,33.962498],"type":"Point"}
}