{
  "type": "Feature",
  "properties": {
    "addr:full":"14120 Firestone Blvd Santa Fe Springs CA 90670",
    "addr:housenumber":"14120",
    "addr:postcode":"90670",
    "addr:street":"Firestone Blvd",
    "iso:country":"US",
    "sg:address":"14120 Firestone Blvd",
    "sg:city":"Santa Fe Springs",
    "sg:classifiers":[
        {
            "category":"Building & Trades",
            "subcategory":"Construction",
            "type":"Services"
        }
    ],
    "sg:phone":"+1 562 926 7446",
    "sg:postcode":"90670",
    "sg:province":"CA",
    "sg:tags":[
        "painter"
    ],
    "wof:name":"Mako Co",
    "wof:placetype":"venue"
},
  "geometry": {"coordinates":[-118.03600299999999,33.887402],"type":"Point"}
}