{
  "type": "Feature",
  "properties": {
    "iso:country":"US",
    "sg:address":"17524 Lilac St",
    "sg:city":"Hesperia",
    "sg:classifiers":[
        {
            "category":"Retail",
            "subcategory":"Auto Repair",
            "type":"Services"
        }
    ],
    "sg:phone":"+1 760 956 8523",
    "sg:postcode":"92345",
    "sg:province":"CA",
    "sg:tags":[
        "truck"
    ],
    "wof:name":"Krejci Truck Repair",
    "wof:placetype":"venue"
},
  "geometry": {"coordinates":[-117.287852,34.45113],"type":"Point"}
}