{
  "type": "Feature",
  "properties": {
    "addr:full":"2135 N Bellflower Blvd Long Beach CA 90815",
    "addr:housenumber":"2135",
    "addr:postcode":"90815",
    "addr:street":"N Bellflower Blvd",
    "iso:country":"US",
    "sg:address":"2135 N Bellflower Blvd",
    "sg:city":"Long Beach",
    "sg:classifiers":[
        {
            "category":"Banks & Credit Unions",
            "subcategory":"Bank",
            "type":"Services"
        },
        {
            "category":"Banks & Credit Unions",
            "subcategory":"Financial Services",
            "type":"Services"
        }
    ],
    "sg:phone":"+1 562 597 0652",
    "sg:postcode":"90815",
    "sg:province":"CA",
    "sg:tags":[
        "broker",
        "mortgage"
    ],
    "sg:website":"www.bankofamerica.com",
    "wof:name":"Bank of America",
    "wof:placetype":"venue"
},
  "geometry": {"coordinates":[-118.12557,33.795121],"type":"Point"}
}