{
  "type": "Feature",
  "properties": {
    "addr:full":"2300 Crenshaw Blvd Torrance CA 90501",
    "addr:housenumber":"2300",
    "addr:postcode":"90501",
    "addr:street":"Crenshaw Blvd",
    "iso:country":"US",
    "sg:address":"2300 Crenshaw Blvd",
    "sg:city":"Torrance",
    "sg:classifiers":[
        {
            "category":"Building & Trades",
            "subcategory":"Construction",
            "type":"Services"
        }
    ],
    "sg:phone":"+1 310 787 7031",
    "sg:postcode":"90501",
    "sg:province":"CA",
    "sg:tags":[
        "contractor"
    ],
    "wof:name":"Construction Begl",
    "wof:placetype":"venue"
},
  "geometry": {"coordinates":[-118.329002,33.824501],"type":"Point"}
}