{
  "type": "Feature",
  "properties": {
    "addr:full":"8725 54th St Riverside CA 92509",
    "addr:housenumber":"8725",
    "addr:postcode":"92509",
    "addr:street":"54Th St",
    "iso:country":"US",
    "sg:address":"8725 54th St",
    "sg:city":"Riverside",
    "sg:classifiers":[
        {
            "category":"Manufacturing",
            "subcategory":"Tools & Machinery",
            "type":"Manufacturing & Wholesale Goods"
        }
    ],
    "sg:phone":"+1 951 817 0583",
    "sg:postcode":"92509",
    "sg:province":"CA",
    "sg:tags":[
        "machine",
        "shop"
    ],
    "wof:name":"Acuity Machine Co",
    "wof:placetype":"venue"
},
  "geometry": {"coordinates":[-117.471163,33.990061],"type":"Point"}
}