{
  "type": "Feature",
  "properties": {
    "addr:full":"1938 Junction Ave San Jose CA 95131",
    "addr:housenumber":"1938",
    "addr:postcode":"95131",
    "addr:street":"Junction Ave",
    "iso:country":"US",
    "sg:address":"1938 Junction Ave",
    "sg:city":"San Jose",
    "sg:classifiers":[
        {
            "category":"Shopping",
            "subcategory":"Computers & Home Electronics",
            "type":"Retail Goods"
        }
    ],
    "sg:phone":"+1 408 436 6505",
    "sg:postcode":"95131",
    "sg:province":"CA",
    "sg:tags":[
        "equipment",
        "electronic",
        "supply"
    ],
    "wof:name":"Req Inc",
    "wof:placetype":"venue"
},
  "geometry": {"coordinates":[-121.911704,37.383135],"type":"Point"}
}