{
  "type": "Feature",
  "properties": {
    "addr:full":"236 West Portal Ave #822 San Francisco CA 94127",
    "addr:housenumber":"236",
    "addr:postcode":"94127",
    "addr:street":"West Portal Ave # 822",
    "iso:country":"US",
    "sg:address":"236 West Portal Ave #822",
    "sg:city":"San Francisco",
    "sg:classifiers":[
        {
            "category":"Professional",
            "subcategory":"Art Services",
            "type":"Services"
        }
    ],
    "sg:phone":"+1 415 670 9777",
    "sg:postcode":"94127",
    "sg:province":"CA",
    "sg:tags":[
        "photographer"
    ],
    "sg:website":"bjmartinphotography.com",
    "wof:name":"BJ Martin Photography",
    "wof:placetype":"venue"
},
  "geometry": {"coordinates":[-122.468538,37.738504],"type":"Point"}
}