{
  "type": "Feature",
  "properties": {
    "iso:country":"US",
    "sg:address":"8840 Bellanca Ave",
    "sg:city":"Los Angeles",
    "sg:classifiers":[
        {
            "category":"Freight",
            "type":"Transportation"
        }
    ],
    "sg:phone":"+1 310 338 1210",
    "sg:postcode":"90045",
    "sg:province":"CA",
    "sg:tags":[
        "trucking"
    ],
    "sg:website":"www.dsdtrucking.com",
    "wof:name":"DSD Trucking Inc",
    "wof:placetype":"venue"
},
  "geometry": {"coordinates":[-118.38043399999999,33.955529],"type":"Point"}
}