{
  "type": "Feature",
  "properties": {
    "addr:full":"3309 Chenu Ave Sacramento CA 95821",
    "addr:housenumber":"3309",
    "addr:postcode":"95821",
    "addr:street":"Chenu Ave",
    "iso:country":"US",
    "sg:address":"3309 Chenu Ave",
    "sg:city":"Sacramento",
    "sg:classifiers":[
        {
            "category":"Manufacturing",
            "subcategory":"Furniture",
            "type":"Manufacturing & Wholesale Goods"
        }
    ],
    "sg:phone":"+1 916 482 8588",
    "sg:postcode":"95821",
    "sg:province":"CA",
    "sg:tags":[
        "builder",
        "designer",
        "custom"
    ],
    "wof:name":"Tony's Custom Shop",
    "wof:placetype":"venue"
},
  "geometry": {"coordinates":[-121.387028,38.614219],"type":"Point"}
}