{
  "type": "Feature",
  "properties": {
    "addr:full":"1500 W el Camino Ave Sacramento CA 95833",
    "addr:housenumber":"1500",
    "addr:postcode":"95833",
    "addr:street":"W El Camino Ave",
    "iso:country":"US",
    "sg:address":"1500 W el Camino Ave",
    "sg:city":"Sacramento",
    "sg:classifiers":[
        {
            "category":"Wholesale",
            "subcategory":"Jewelry",
            "type":"Manufacturing & Wholesale Goods"
        }
    ],
    "sg:phone":"+1 916 564 9138",
    "sg:postcode":"95833",
    "sg:province":"CA",
    "sg:tags":[
        "stone"
    ],
    "wof:name":"Gurpreet Inc",
    "wof:placetype":"venue"
},
  "geometry": {"coordinates":[-121.494568,38.612839],"type":"Point"}
}