{
  "type": "Feature",
  "properties": {
    "addr:full":"1440 Truxtun Ave Bakersfield CA 93301",
    "addr:housenumber":"1440",
    "addr:postcode":"93301",
    "addr:street":"Truxtun Ave",
    "iso:country":"US",
    "sg:address":"1440 Truxtun Ave",
    "sg:city":"Bakersfield",
    "sg:classifiers":[
        {
            "category":"Banks & Credit Unions",
            "subcategory":"Bank",
            "type":"Services"
        }
    ],
    "sg:phone":"+1 661 633 5380",
    "sg:postcode":"93301",
    "sg:province":"CA",
    "sg:tags":[
        "commercial",
        "saving"
    ],
    "sg:website":"http://locators.bankofamerica.com/a/BC-7579",
    "wof:name":"Bank Of America",
    "wof:placetype":"venue"
},
  "geometry": {"coordinates":[-119.018081,35.373426],"type":"Point"}
}