{
  "type": "Feature",
  "properties": {
    "addr:full":"1735 Pescadero Dr Salinas CA 93906",
    "addr:housenumber":"1735",
    "addr:postcode":"93906",
    "addr:street":"Pescadero Dr",
    "iso:country":"US",
    "sg:address":"1735 Pescadero Dr",
    "sg:city":"Salinas",
    "sg:classifiers":[
        {
            "category":"Shopping",
            "subcategory":"Gifts & Souvenirs",
            "type":"Retail Goods"
        }
    ],
    "sg:phone":"+1 831 449 3282",
    "sg:postcode":"93906",
    "sg:province":"CA",
    "sg:tags":[
        "party",
        "supply"
    ],
    "wof:name":"Gokono Jumping House",
    "wof:placetype":"venue"
},
  "geometry": {"coordinates":[-121.625839,36.707973],"type":"Point"}
}