{
  "type": "Feature",
  "properties": {
    "addr:full":"2652 Lobelia Rd Alpine CA 91901",
    "addr:housenumber":"2652",
    "addr:postcode":"91901",
    "addr:street":"Lobelia Rd",
    "iso:country":"US",
    "sg:address":"2652 Lobelia Rd",
    "sg:city":"Alpine",
    "sg:classifiers":[
        {
            "category":"Government",
            "subcategory":"Department Of Motor Vehicles",
            "type":"Public Place"
        }
    ],
    "sg:phone":"+1 619 818 5066",
    "sg:postcode":"91901",
    "sg:province":"CA",
    "sg:tags":[
        "truck",
        "trailer"
    ],
    "wof:name":"Aamaron Trailers",
    "wof:placetype":"venue"
},
  "geometry": {"coordinates":[-116.77517400000001,32.844972],"type":"Point"}
}