{
  "type": "Feature",
  "properties": {
    "iso:country":"US",
    "sg:address":"5555 Long Beach Blvd",
    "sg:city":"Long Beach",
    "sg:classifiers":[
        {
            "category":"Real Estate",
            "subcategory":"Real Estate Operator",
            "type":"Services"
        }
    ],
    "sg:phone":"+1 562 428 0107",
    "sg:postcode":"90805",
    "sg:province":"CA",
    "sg:tags":[
        "apartment"
    ],
    "wof:name":"Windmill Creek Apts",
    "wof:placetype":"venue"
},
  "geometry": {"coordinates":[-118.196999,33.856701],"type":"Point"}
}