{
  "type": "Feature",
  "properties": {
    "addr:full":"6601 Rugby Ave Huntington Park CA 90255",
    "addr:housenumber":"6601",
    "addr:postcode":"90255",
    "addr:street":"Rugby Ave;Park",
    "iso:country":"US",
    "sg:address":"6601 Rugby Ave",
    "sg:city":"Huntington Park",
    "sg:classifiers":[
        {
            "category":"Health Services",
            "subcategory":"Doctor",
            "type":"Services"
        }
    ],
    "sg:phone":"+1 323 583 2247",
    "sg:postcode":"90255",
    "sg:province":"CA",
    "sg:tags":[
        "physician",
        "surgeon"
    ],
    "wof:name":"Tahani B Soliman MD",
    "wof:placetype":"venue"
},
  "geometry": {"coordinates":[-118.226478,33.976894],"type":"Point"}
}