{
  "type": "Feature",
  "properties": {
    "iso:country":"US",
    "sg:address":"2816 N Blackstone Ave",
    "sg:city":"Fresno",
    "sg:classifiers":[
        {
            "category":"Health Services",
            "subcategory":"Medical Lab",
            "type":"Services"
        }
    ],
    "sg:phone":"+1 559 227 6365",
    "sg:postcode":"93704",
    "sg:province":"CA",
    "sg:tags":[
        "laboratory"
    ],
    "wof:name":"Domoto Dental Lab",
    "wof:placetype":"venue"
},
  "geometry": {"coordinates":[-119.790464,36.776656],"type":"Point"}
}