{
  "type": "Feature",
  "properties": {
    "addr:full":"4910 E Olympic Blvd Los Angeles CA 90022",
    "addr:housenumber":"4910",
    "addr:postcode":"90022",
    "addr:street":"E Olympic Blvd",
    "iso:country":"US",
    "sg:address":"4910 E Olympic Blvd",
    "sg:city":"Los Angeles",
    "sg:classifiers":[
        {
            "category":"Local Transit",
            "type":"Transportation"
        }
    ],
    "sg:phone":"+1 323 269 0992",
    "sg:postcode":"90022",
    "sg:province":"CA",
    "sg:tags":[
        "bus",
        "line"
    ],
    "wof:name":"Crucero USA LLC",
    "wof:placetype":"venue"
},
  "geometry": {"coordinates":[-118.16422300000001,34.017416],"type":"Point"}
}