{
  "type": "Feature",
  "properties": {
    "addr:full":"920 41st Ave Santa Cruz CA 95062",
    "addr:housenumber":"920",
    "addr:postcode":"95062",
    "addr:street":"41St Ave",
    "iso:country":"US",
    "sg:address":"920 41st Ave",
    "sg:city":"Santa Cruz",
    "sg:classifiers":[
        {
            "category":"Social Services",
            "type":"Services"
        }
    ],
    "sg:phone":"+1 831 475 4849",
    "sg:postcode":"95062",
    "sg:province":"CA",
    "sg:tags":[
        "counseling"
    ],
    "wof:name":"Capitola Counseling Svc",
    "wof:placetype":"venue"
},
  "geometry": {"coordinates":[-121.964822,36.963744],"type":"Point"}
}