{
  "type": "Feature",
  "properties": {
    "iso:country":"US",
    "sg:address":"21214 Ave 264",
    "sg:city":"Exeter",
    "sg:classifiers":[
        {
            "category":"Professional",
            "subcategory":"Management & Consulting",
            "type":"Services"
        }
    ],
    "sg:phone":"+1 559 592 4844",
    "sg:postcode":"93221",
    "sg:province":"CA",
    "sg:tags":[
        "agricultural",
        "consultant"
    ],
    "wof:name":"Agriculture Services Inc",
    "wof:placetype":"venue"
},
  "geometry": {"coordinates":[-119.09199599999999,36.268056],"type":"Point"}
}