{
  "type": "Feature",
  "properties": {
    "addr:full":"25041 Anza Dr Valencia CA 91355",
    "addr:housenumber":"25041",
    "addr:postcode":"91355",
    "addr:street":"Anza Dr",
    "iso:country":"US",
    "sg:address":"25041 Anza Dr",
    "sg:city":"Valencia",
    "sg:classifiers":[
        {
            "category":"Manufacturing",
            "subcategory":"Tools & Machinery",
            "type":"Manufacturing & Wholesale Goods"
        }
    ],
    "sg:phone":"+1 661 257 7773",
    "sg:postcode":"91355",
    "sg:province":"CA",
    "sg:tags":[
        "machine",
        "shop"
    ],
    "wof:name":"R L Industries Inc",
    "wof:placetype":"venue"
},
  "geometry": {"coordinates":[-118.572641,34.43256],"type":"Point"}
}