{
  "type": "Feature",
  "properties": {
    "addr:full":"1451 Grove St Healdsburg CA 95476",
    "addr:housenumber":"1451",
    "addr:postcode":"95476",
    "addr:street":"Grove St",
    "iso:country":"US",
    "sg:address":"1451 Grove St",
    "sg:city":"Healdsburg",
    "sg:classifiers":[
        {
            "category":"Manufacturing",
            "subcategory":"Food",
            "type":"Manufacturing & Wholesale Goods"
        }
    ],
    "sg:phone":"+1 707 433 0290",
    "sg:postcode":"95476",
    "sg:province":"CA",
    "sg:tags":[
        "winery"
    ],
    "sg:website":"www.grovestreetwinery.com",
    "wof:name":"Grove Street Winery",
    "wof:placetype":"venue"
},
  "geometry": {"coordinates":[-122.51310599999999,38.293247],"type":"Point"}
}