{
  "type": "Feature",
  "properties": {
    "addr:full":"1036 E Moreno Way Placentia CA 92870",
    "addr:housenumber":"1036",
    "addr:postcode":"ca 92870",
    "addr:street":"E Moreno Way",
    "iso:country":"US",
    "sg:address":"1036 E Moreno Way",
    "sg:city":"Placentia",
    "sg:classifiers":[
        {
            "category":"Manufacturing",
            "subcategory":"Food",
            "type":"Manufacturing & Wholesale Goods"
        }
    ],
    "sg:phone":"+1 714 792 2802",
    "sg:postcode":"92870",
    "sg:province":"CA",
    "sg:tags":[
        "flavor",
        "mfg"
    ],
    "wof:name":"Bee Valley Ingredients",
    "wof:placetype":"venue"
},
  "geometry": {"coordinates":[-117.846649,33.86901],"type":"Point"}
}