{
  "type": "Feature",
  "properties": {
    "addr:full":"1600 3rd St Atwater CA 95301",
    "addr:housenumber":"1600",
    "addr:postcode":"95301",
    "addr:street":"3Rd St",
    "iso:country":"US",
    "sg:address":"1600 3rd St",
    "sg:city":"Atwater",
    "sg:classifiers":[
        {
            "category":"Education",
            "subcategory":"Library",
            "type":"Public Place"
        }
    ],
    "sg:phone":"+1 209 358 6651",
    "sg:postcode":"95301",
    "sg:province":"CA",
    "wof:name":"Atwater Branch Library",
    "wof:placetype":"venue"
},
  "geometry": {"coordinates":[-120.606206,37.351512],"type":"Point"}
}