{
  "type": "Feature",
  "properties": {
    "addr:full":"16 N Marengo Ave Pasadena CA 91101",
    "addr:housenumber":"16",
    "addr:postcode":"91101",
    "addr:street":"N Marengo Ave",
    "iso:country":"US",
    "sg:address":"16 N Marengo Ave",
    "sg:city":"Pasadena",
    "sg:classifiers":[
        {
            "category":"Professional",
            "type":"Services"
        }
    ],
    "sg:phone":"+1 626 577 5090",
    "sg:postcode":"91101",
    "sg:province":"CA",
    "wof:name":"ARC Blue International",
    "wof:placetype":"venue"
},
  "geometry": {"coordinates":[-118.14591900000001,34.146521],"type":"Point"}
}