{
  "type": "Feature",
  "properties": {
    "iso:country":"US",
    "sg:address":"1875 Wharf Rd",
    "sg:city":"Capitola",
    "sg:classifiers":[
        {
            "category":"Manufacturing",
            "subcategory":"Printing",
            "type":"Manufacturing & Wholesale Goods"
        }
    ],
    "sg:phone":"+1 831 462 3370",
    "sg:postcode":"95010",
    "sg:province":"CA",
    "sg:tags":[
        "publishing"
    ],
    "wof:name":"Walkabout Publications",
    "wof:placetype":"venue"
},
  "geometry": {"coordinates":[-121.95717500000001,36.976958],"type":"Point"}
}