{
  "type": "Feature",
  "properties": {
    "addr:full":"783 S Madera Ave Kerman CA 93630",
    "addr:housenumber":"783",
    "addr:postcode":"93630",
    "addr:street":"S Madera Ave",
    "iso:country":"US",
    "sg:address":"783 S Madera Ave",
    "sg:city":"Kerman",
    "sg:classifiers":[
        {
            "category":"Organizations",
            "subcategory":"Professional Association",
            "type":"Services"
        }
    ],
    "sg:phone":"+1 559 846 6343",
    "sg:postcode":"93630",
    "sg:province":"CA",
    "sg:tags":[
        "chambers",
        "commerce"
    ],
    "sg:website":"www.kermanchamber.org",
    "wof:name":"Kerman Chamber Of Commerce",
    "wof:placetype":"venue"
},
  "geometry": {"coordinates":[-120.06034699999999,36.723019],"type":"Point"}
}