{
  "type": "Feature",
  "properties": {
    "addr:full":"520 I St Crescent City CA 95531",
    "addr:housenumber":"520",
    "addr:postcode":"95531",
    "addr:street":"I St Crescent",
    "iso:country":"US",
    "sg:address":"520 I St",
    "sg:city":"Crescent City",
    "sg:classifiers":[
        {
            "category":"Government",
            "subcategory":"Fire Station",
            "type":"Public Place"
        }
    ],
    "sg:phone":"+1 707 464 9113",
    "sg:postcode":"95531",
    "sg:province":"CA",
    "sg:tags":[
        "department",
        "protection"
    ],
    "wof:name":"Crescent City Vol Fire Dept",
    "wof:placetype":"venue"
},
  "geometry": {"coordinates":[-124.198858,41.7545],"type":"Point"}
}