{
  "type": "Feature",
  "properties": {
    "addr:full":"1011 E Walnut St Santa Ana CA 92701",
    "addr:housenumber":"1011",
    "addr:postcode":"92701",
    "addr:street":"E Walnut St",
    "iso:country":"US",
    "sg:address":"1011 E Walnut St",
    "sg:city":"Santa Ana",
    "sg:classifiers":[
        {
            "category":"Wholesale",
            "subcategory":"Construction Materials",
            "type":"Manufacturing & Wholesale Goods"
        }
    ],
    "sg:phone":"+1 714 647 9792",
    "sg:postcode":"92701",
    "sg:province":"CA",
    "sg:tags":[
        "roofing"
    ],
    "wof:name":"A L L Roofing Materials",
    "wof:placetype":"venue"
},
  "geometry": {"coordinates":[-117.854744,33.744615],"type":"Point"}
}