{
  "type": "Feature",
  "properties": {
    "addr:full":"12889 Osborne Hill Rd Grass Valley CA 95945",
    "addr:housenumber":"12889",
    "addr:postcode":"95945",
    "addr:street":"Osborne Hill Rd",
    "iso:country":"US",
    "sg:address":"12889 Osborne Hill Rd",
    "sg:city":"Grass Valley",
    "sg:classifiers":[
        {
            "category":"Organizations",
            "subcategory":"Religious Organization",
            "type":"Services"
        }
    ],
    "sg:phone":"+1 530 477 5017",
    "sg:postcode":"95945",
    "sg:province":"CA",
    "sg:tags":[
        "church"
    ],
    "sg:website":"www.gvadventist.com",
    "wof:name":"Seventh-Day Adventist Church",
    "wof:placetype":"venue"
},
  "geometry": {"coordinates":[-121.038707,39.200234],"type":"Point"}
}