{
  "type": "Feature",
  "properties": {
    "iso:country":"US",
    "sg:address":"9988 Arroyo Ave",
    "sg:city":"Hesperia",
    "sg:classifiers":[
        {
            "category":"Building & Trades",
            "subcategory":"Electrical",
            "type":"Services"
        }
    ],
    "sg:phone":"+1 760 947 7743",
    "sg:postcode":"92345",
    "sg:province":"CA",
    "sg:tags":[
        "installation"
    ],
    "wof:name":"Home Entertainment Pro's",
    "wof:placetype":"venue"
},
  "geometry": {"coordinates":[-117.331686,34.428903],"type":"Point"}
}