{
  "type": "Feature",
  "properties": {
    "addr:full":"1700 Airline Hwy Hollister CA 95023",
    "addr:housenumber":"1700",
    "addr:postcode":"hollister ca 95023",
    "addr:street":"Airline Hwy",
    "iso:country":"US",
    "sg:address":"1700 Airline Hwy",
    "sg:city":"Hollister",
    "sg:classifiers":[
        {
            "category":"Professional",
            "subcategory":"Accounting & Tax Preparation",
            "type":"Services"
        }
    ],
    "sg:phone":"+1 408 779 1410",
    "sg:postcode":"95023",
    "sg:province":"CA",
    "sg:tags":[
        "bookkeeping",
        "general"
    ],
    "wof:name":"Ann's Bookkeeping",
    "wof:placetype":"venue"
},
  "geometry": {"coordinates":[-121.38990800000001,36.837859],"type":"Point"}
}