{
  "type": "Feature",
  "properties": {
    "addr:full":"3280 Sonoma Blvd Vallejo CA 94590",
    "addr:housenumber":"3280",
    "addr:postcode":"94590",
    "addr:street":"Sonoma Blvd",
    "iso:country":"US",
    "sg:address":"3280 Sonoma Blvd",
    "sg:city":"Vallejo",
    "sg:classifiers":[
        {
            "category":"Home & Garden",
            "subcategory":"Building Materials",
            "type":"Retail Goods"
        }
    ],
    "sg:phone":"+1 707 557 3000",
    "sg:postcode":"94590",
    "sg:province":"CA",
    "sg:tags":[
        "lumber"
    ],
    "sg:website":"www.fosterlumber.com",
    "wof:name":"Foster Lumber Yard Inc",
    "wof:placetype":"venue"
},
  "geometry": {"coordinates":[-122.25469699999999,38.119139],"type":"Point"}
}