{
  "type": "Feature",
  "properties": {
    "addr:full":"3727 El Cajon Boulevard San Diego CA 92105",
    "addr:housenumber":"3727",
    "addr:postcode":"92105",
    "addr:street":"El Cajon Boulevard",
    "iso:country":"US",
    "sg:address":"3727 El Cajon Boulevard",
    "sg:city":"San Diego",
    "sg:classifiers":[
        {
            "category":"Retail",
            "subcategory":"Repair Shop",
            "type":"Services"
        }
    ],
    "sg:phone":"+1 619 280 3302",
    "sg:postcode":"92105",
    "sg:province":"CA",
    "sg:tags":[
        "reupholstery",
        "furniture"
    ],
    "wof:name":"Adolfo's Upholstery",
    "wof:placetype":"venue"
},
  "geometry": {"coordinates":[-117.112821,32.755225],"type":"Point"}
}