{
  "type": "Feature",
  "properties": {
    "iso:country":"US",
    "sg:address":"3103 Market St",
    "sg:city":"San Diego",
    "sg:classifiers":[
        {
            "category":"Building & Trades",
            "subcategory":"Construction",
            "type":"Services"
        }
    ],
    "sg:phone":"+1 619 325 5995",
    "sg:postcode":"92102",
    "sg:province":"CA",
    "sg:tags":[
        "contractor"
    ],
    "sg:website":"www.harconstruction.com",
    "wof:name":"Har Construction",
    "wof:placetype":"venue"
},
  "geometry": {"coordinates":[-117.125308,32.711597],"type":"Point"}
}