{
  "type": "Feature",
  "properties": {
    "addr:full":"21728 E River Rd Escalon CA 95320",
    "addr:housenumber":"21728",
    "addr:postcode":"95320",
    "addr:street":"E River Rd",
    "iso:country":"US",
    "sg:address":"21728 E River Rd",
    "sg:city":"Escalon",
    "sg:classifiers":[
        {
            "category":"Farming",
            "subcategory":"Vineyard",
            "type":"Manufacturing & Wholesale Goods"
        }
    ],
    "sg:phone":"+1 209 599 4492",
    "sg:postcode":"95320",
    "sg:province":"CA",
    "sg:tags":[
        "grape"
    ],
    "wof:name":"Zolezzi Ranch",
    "wof:placetype":"venue"
},
  "geometry": {"coordinates":[-121.03442099999999,37.754991],"type":"Point"}
}