{
  "type": "Feature",
  "properties": {
    "iso:country":"US",
    "sg:address":"4514 N Figueroa St",
    "sg:city":"Los Angeles",
    "sg:classifiers":[
        {
            "category":"Autos & Motor Vehicles",
            "subcategory":"Automobile Sales",
            "type":"Retail Goods"
        }
    ],
    "sg:phone":"+1 323 227 4704",
    "sg:postcode":"90065",
    "sg:province":"CA",
    "sg:tags":[
        "car",
        "dealer"
    ],
    "wof:name":"GLM Auto Sales",
    "wof:placetype":"venue"
},
  "geometry": {"coordinates":[-118.20645399999999,34.096872],"type":"Point"}
}