{
  "type": "Feature",
  "properties": {
    "iso:country":"US",
    "sg:address":"1919 S. Main St",
    "sg:city":"Santa Ana",
    "sg:classifiers":[
        {
            "category":"Banks & Credit Unions",
            "subcategory":"Financial Services",
            "type":"Services"
        }
    ],
    "sg:phone":"+1 714 549 1786",
    "sg:postcode":"92707",
    "sg:province":"CA",
    "wof:name":"Diaz Enterprises",
    "wof:placetype":"venue"
},
  "geometry": {"coordinates":[-117.867851,33.723394],"type":"Point"}
}