{
  "type": "Feature",
  "properties": {
    "iso:country":"US",
    "sg:address":"1000 E Via Wanda",
    "sg:city":"Long Beach",
    "sg:classifiers":[
        {
            "category":"Real Estate",
            "subcategory":"Real Estate Agent",
            "type":"Services"
        }
    ],
    "sg:phone":"+1 562 423 5464",
    "sg:postcode":"90805",
    "sg:province":"CA",
    "sg:tags":[
        "authorities",
        "housing"
    ],
    "sg:website":"www.lacdc.org",
    "wof:name":"Carmelitos Housing",
    "wof:placetype":"venue"
},
  "geometry": {"coordinates":[-118.18401299999999,33.851619],"type":"Point"}
}