{
  "type": "Feature",
  "properties": {
    "addr:full":"3870 Crenshaw Blvd Los Angeles CA 90008",
    "addr:housenumber":"3870",
    "addr:postcode":"90008",
    "addr:street":"Crenshaw Blvd",
    "iso:country":"US",
    "sg:address":"3870 Crenshaw Blvd",
    "sg:city":"Los Angeles",
    "sg:classifiers":[
        {
            "category":"Personal",
            "type":"Services"
        }
    ],
    "sg:phone":"+1 323 292 0108",
    "sg:postcode":"90008",
    "sg:province":"CA",
    "sg:tags":[
        "mail",
        "receiving"
    ],
    "wof:name":"Mail Bin",
    "wof:placetype":"venue"
},
  "geometry": {"coordinates":[-118.334807,34.015673],"type":"Point"}
}