{
  "type": "Feature",
  "properties": {
    "addr:full":"565 Explorer St Brea CA 92821",
    "addr:housenumber":"565",
    "addr:postcode":"92821",
    "addr:street":"Explorer St",
    "iso:country":"US",
    "sg:address":"565 Explorer St",
    "sg:city":"Brea",
    "sg:classifiers":[
        {
            "category":"Professional",
            "subcategory":"Business Services",
            "type":"Services"
        }
    ],
    "sg:phone":"+1 714 529 2020",
    "sg:postcode":"92821",
    "sg:province":"CA",
    "sg:tags":[
        "record",
        "document"
    ],
    "wof:name":"Brambles Information Mgmt Inc",
    "wof:placetype":"venue"
},
  "geometry": {"coordinates":[-117.90367000000001,33.928689],"type":"Point"}
}