{
  "type": "Feature",
  "properties": {
    "addr:full":"3396 Murphy Canyon Rd San Diego CA 92123",
    "addr:housenumber":"3396",
    "addr:postcode":"92123",
    "addr:street":"Murphy Canyon Rd",
    "iso:country":"US",
    "sg:address":"3396 Murphy Canyon Rd",
    "sg:city":"San Diego",
    "sg:classifiers":[
        {
            "category":"Shopping",
            "subcategory":"Pets & Pet Supplies",
            "type":"Retail Goods"
        }
    ],
    "sg:phone":"+1 858 571 0300",
    "sg:postcode":"92123",
    "sg:province":"CA",
    "sg:tags":[
        "training",
        "store"
    ],
    "wof:name":"Petsmart",
    "wof:placetype":"venue"
},
  "geometry": {"coordinates":[-117.113998,32.806],"type":"Point"}
}