{
  "type": "Feature",
  "properties": {
    "iso:country":"US",
    "sg:address":"127 Marine Ave",
    "sg:city":"Newport Beach",
    "sg:classifiers":[
        {
            "category":"Bars & Pubs",
            "type":"Food & Drink"
        },
        {
            "category":"Restaurant",
            "type":"Food & Drink"
        }
    ],
    "sg:phone":"+1 949 675 8300",
    "sg:postcode":"92662",
    "sg:province":"CA",
    "sg:tags":[
        "traditional",
        "american"
    ],
    "wof:name":"The Village Inn",
    "wof:placetype":"venue"
},
  "geometry": {"coordinates":[-117.890027,33.605509],"type":"Point"}
}