{
  "type": "Feature",
  "properties": {
    "addr:full":"100 Yale St Pasadena CA 91103",
    "addr:housenumber":"100",
    "addr:postcode":"91103",
    "addr:street":"Yale St",
    "iso:country":"US",
    "sg:address":"100 Yale St",
    "sg:city":"Pasadena",
    "sg:classifiers":[
        {
            "category":"Wholesale",
            "subcategory":"Non-durable Goods",
            "type":"Manufacturing & Wholesale Goods"
        }
    ],
    "sg:phone":"+1 626 356 0881",
    "sg:postcode":"91103",
    "sg:province":"CA",
    "sg:tags":[
        "merchandise-wholesale"
    ],
    "wof:name":"Trendline Imports",
    "wof:placetype":"venue"
},
  "geometry": {"coordinates":[-118.15278600000001,34.160191],"type":"Point"}
}