{
  "type": "Feature",
  "properties": {
    "addr:full":"101 H St Bakersfield CA 93304",
    "addr:housenumber":"101",
    "addr:postcode":"93304",
    "addr:street":"H St",
    "iso:country":"US",
    "sg:address":"101 H St",
    "sg:city":"Bakersfield",
    "sg:classifiers":[
        {
            "category":"Banks & Credit Unions",
            "subcategory":"Bank",
            "type":"Services"
        }
    ],
    "sg:phone":"+1 661 324 9955",
    "sg:postcode":"93304",
    "sg:province":"CA",
    "sg:tags":[
        "loan"
    ],
    "sg:website":"www.pacificcrestmtg.com",
    "wof:name":"Pacific Crest Mortgage",
    "wof:placetype":"venue"
},
  "geometry": {"coordinates":[-119.021305,35.355943],"type":"Point"}
}