{
  "type": "Feature",
  "properties": {
    "iso:country":"US",
    "sg:address":"2737 Woodberry Way Suite 103",
    "sg:city":"Rancho Cordova",
    "sg:classifiers":[
        {
            "category":"Health Services",
            "subcategory":"Doctor",
            "type":"Services"
        }
    ],
    "sg:phone":"+1 916 363 2229",
    "sg:postcode":"95670",
    "sg:province":"CA",
    "wof:name":"Sacramento Family Medical Clinic",
    "wof:placetype":"venue"
},
  "geometry": {"coordinates":[-121.298832,38.592192],"type":"Point"}
}