{
  "type": "Feature",
  "properties": {
    "iso:country":"US",
    "sg:address":"101 S Topanga Canyon Blvd",
    "sg:city":"Topanga",
    "sg:classifiers":[
        {
            "category":"Government",
            "subcategory":"Post Office",
            "type":"Public Place"
        }
    ],
    "sg:phone":"+1 310 455 0254",
    "sg:postcode":"90290",
    "sg:province":"CA",
    "wof:name":"Topanga Main Office",
    "wof:placetype":"venue"
},
  "geometry": {"coordinates":[-118.604306,34.089591],"type":"Point"}
}