{
  "type": "Feature",
  "properties": {
    "addr:full":"600 23rd St Richmond CA 94804",
    "addr:housenumber":"600",
    "addr:postcode":"94804",
    "addr:street":"23Rd St",
    "iso:country":"US",
    "sg:address":"600 23rd St",
    "sg:city":"Richmond",
    "sg:classifiers":[
        {
            "category":"Autos & Motor Vehicles",
            "subcategory":"Automobile Sales",
            "type":"Retail Goods"
        }
    ],
    "sg:phone":"+1 415 441 1600",
    "sg:postcode":"94804",
    "sg:province":"CA",
    "sg:tags":[
        "car"
    ],
    "sg:website":"www.mazda.com",
    "wof:name":"Richmond Mazda",
    "wof:placetype":"venue"
},
  "geometry": {"coordinates":[-122.34711299999999,37.940172],"type":"Point"}
}