{
  "type": "Feature",
  "properties": {
    "iso:country":"US",
    "sg:address":"625 E Arrow Hwy",
    "sg:city":"Glendora",
    "sg:classifiers":[
        {
            "category":"Personal",
            "subcategory":"Beauty Salon",
            "type":"Services"
        }
    ],
    "sg:phone":"+1 626 335 9747",
    "sg:postcode":"91740",
    "sg:province":"CA",
    "sg:tags":[
        "treatment",
        "skin"
    ],
    "wof:name":"Namaste Skin & Body Care",
    "wof:placetype":"venue"
},
  "geometry": {"coordinates":[-117.870535,34.106432],"type":"Point"}
}