{
  "type": "Feature",
  "properties": {
    "addr:full":"4549 W Washington Blvd Los Angeles CA 90016",
    "addr:housenumber":"4549",
    "addr:postcode":"90016",
    "addr:street":"W Washington Blvd",
    "iso:country":"US",
    "sg:address":"4549 W Washington Blvd",
    "sg:city":"Los Angeles",
    "sg:classifiers":[
        {
            "category":"Organizations",
            "subcategory":"Religious Organization",
            "type":"Services"
        }
    ],
    "sg:phone":"+1 323 935 3006",
    "sg:postcode":"90016",
    "sg:province":"CA",
    "sg:tags":[
        "church"
    ],
    "wof:name":"Church & Missionary",
    "wof:placetype":"venue"
},
  "geometry": {"coordinates":[-118.339679,34.039912],"type":"Point"}
}