{
  "type": "Feature",
  "properties": {
    "iso:country":"US",
    "sg:address":"7029 N Ingram Ave",
    "sg:city":"Pinedale",
    "sg:classifiers":[
        {
            "category":"Banks & Credit Unions",
            "subcategory":"Bank",
            "type":"Services"
        }
    ],
    "sg:phone":"+1 559 449 8145",
    "sg:postcode":"93650",
    "sg:province":"CA",
    "wof:name":"Bank Of The Sierra",
    "wof:placetype":"venue"
},
  "geometry": {"coordinates":[-119.80195500000001,36.837405],"type":"Point"}
}