{
  "type": "Feature",
  "properties": {
    "addr:full":"5339 Broadway Oakland CA 94618",
    "addr:housenumber":"5339",
    "addr:postcode":"94618",
    "addr:street":"Broadway",
    "iso:country":"US",
    "sg:address":"5339 Broadway",
    "sg:city":"Oakland",
    "sg:classifiers":[
        {
            "category":"Real Estate",
            "subcategory":"Real Estate Operator",
            "type":"Services"
        }
    ],
    "sg:phone":"+1 510 428 9111",
    "sg:postcode":"94618",
    "sg:province":"CA",
    "sg:tags":[
        "apartment"
    ],
    "sg:website":"www.lantzproperties.com",
    "wof:name":"Lantz Properties Llc",
    "wof:placetype":"venue"
},
  "geometry": {"coordinates":[-122.24099699999999,37.844799],"type":"Point"}
}