{
  "type": "Feature",
  "properties": {
    "addr:full":"3133 Sugar Beet Way Union City CA 94587",
    "addr:housenumber":"3133",
    "addr:postcode":"94587",
    "addr:street":"Sugar Beet Way",
    "iso:country":"US",
    "sg:address":"3133 Sugar Beet Way",
    "sg:city":"Union City",
    "sg:classifiers":[
        {
            "category":"Building & Trades",
            "subcategory":"Construction",
            "type":"Services"
        }
    ],
    "sg:phone":"+1 510 487 3019",
    "sg:postcode":"94587",
    "sg:province":"CA",
    "sg:tags":[
        "contractor"
    ],
    "wof:name":"Application S Contractors",
    "wof:placetype":"venue"
},
  "geometry": {"coordinates":[-122.071428,37.602262],"type":"Point"}
}