{
  "type": "Feature",
  "properties": {
    "iso:country":"US",
    "sg:address":"3823 W Sunset Blvd",
    "sg:city":"Los Angeles",
    "sg:classifiers":[
        {
            "category":"Restaurant",
            "type":"Food & Drink"
        }
    ],
    "sg:phone":"+1 323 667 3272",
    "sg:postcode":"90026",
    "sg:province":"CA",
    "wof:name":"Town & Country Bakery & Cafe",
    "wof:placetype":"venue"
},
  "geometry": {"coordinates":[-118.279429,34.091541],"type":"Point"}
}