{
  "type": "Feature",
  "properties": {
    "iso:country":"US",
    "sg:address":"1040 McNear Ave",
    "sg:city":"Petaluma",
    "sg:classifiers":[
        {
            "category":"Building & Trades",
            "subcategory":"Construction",
            "type":"Services"
        }
    ],
    "sg:phone":"+1 707 762 7573",
    "sg:postcode":"94952",
    "sg:province":"CA",
    "sg:tags":[
        "resurfacing",
        "laying",
        "refinishing",
        "floor"
    ],
    "wof:name":"Larry Carter Floor Install",
    "wof:placetype":"venue"
},
  "geometry": {"coordinates":[-122.623738,38.22114],"type":"Point"}
}