{
  "type": "Feature",
  "properties": {
    "addr:full":"2305 Otay Lakes Rd Chula Vista CA 91915",
    "addr:housenumber":"2305",
    "addr:postcode":"91915",
    "addr:street":"Otay Lakes Rd",
    "iso:country":"US",
    "sg:address":"2305 Otay Lakes Rd",
    "sg:city":"Chula Vista",
    "sg:classifiers":[
        {
            "category":"Shopping",
            "subcategory":"Mobile Phones",
            "type":"Retail Goods"
        }
    ],
    "sg:phone":"+1 619 482 7873",
    "sg:postcode":"91915",
    "sg:province":"CA",
    "sg:website":"www.t-mobile.com",
    "wof:name":"T-Mobile",
    "wof:placetype":"venue"
},
  "geometry": {"coordinates":[-116.965316,32.648509],"type":"Point"}
}