{
  "type": "Feature",
  "properties": {
    "addr:full":"8245 Remmet Ave Canoga Park CA 91304",
    "addr:housenumber":"8245",
    "addr:postcode":"91304",
    "addr:street":"Remmet Ave",
    "iso:country":"US",
    "sg:address":"8245 Remmet Ave",
    "sg:city":"Canoga Park",
    "sg:classifiers":[
        {
            "category":"Wholesale",
            "subcategory":"Construction Materials",
            "type":"Manufacturing & Wholesale Goods"
        },
        {
            "category":"Building & Trades",
            "subcategory":"Construction",
            "type":"Services"
        }
    ],
    "sg:phone":"+1 818 888 0050",
    "sg:postcode":"91304",
    "sg:province":"CA",
    "sg:tags":[
        "house",
        "waterproofing",
        "contractor"
    ],
    "wof:name":"A V M Industries",
    "wof:placetype":"venue"
},
  "geometry": {"coordinates":[-118.600387,34.216312],"type":"Point"}
}