{
  "type": "Feature",
  "properties": {
    "addr:full":"1304 E Main St Ventura CA 93001",
    "addr:housenumber":"1304",
    "addr:postcode":"93001",
    "addr:street":"E Main St",
    "iso:country":"US",
    "sg:address":"1304 E Main St",
    "sg:city":"Ventura",
    "sg:classifiers":[
        {
            "category":"Government",
            "subcategory":"Office",
            "type":"Public Place"
        }
    ],
    "sg:phone":"+1 805 648 9921",
    "sg:postcode":"93001",
    "sg:province":"CA",
    "sg:tags":[
        "health"
    ],
    "wof:name":"Rehabilitation California Dept",
    "wof:placetype":"venue"
},
  "geometry": {"coordinates":[-119.279113,34.280211],"type":"Point"}
}