{
  "type": "Feature",
  "properties": {
    "iso:country":"US",
    "sg:address":"5336 Highland View Pl",
    "sg:city":"Los Angeles",
    "sg:classifiers":[
        {
            "category":"Manufacturing",
            "subcategory":"Printing",
            "type":"Manufacturing & Wholesale Goods"
        }
    ],
    "sg:phone":"+1 323 547 4919",
    "sg:postcode":"90041",
    "sg:province":"CA",
    "sg:tags":[
        "press",
        "bindery",
        "book",
        "letter",
        "custom"
    ],
    "wof:name":"High Tower Press",
    "wof:placetype":"venue"
},
  "geometry": {"coordinates":[-118.209704,34.143699],"type":"Point"}
}