{
  "type": "Feature",
  "properties": {
    "iso:country":"US",
    "sg:address":"1 Wilder St",
    "sg:city":"San Francisco",
    "sg:classifiers":[
        {
            "category":"Professional",
            "type":"Services"
        }
    ],
    "sg:phone":"+1 415 469 7778",
    "sg:postcode":"94131",
    "sg:province":"CA",
    "sg:tags":[
        "establishment"
    ],
    "wof:name":"Carcure Com",
    "wof:placetype":"venue"
},
  "geometry": {"coordinates":[-122.432837,37.734027],"type":"Point"}
}