{
  "type": "Feature",
  "properties": {
    "addr:full":"30640 Via Las Palmas Thousand Palms CA 92276",
    "addr:housenumber":"30640",
    "addr:postcode":"92276",
    "addr:street":"Via Las Palmas;Palms",
    "iso:country":"US",
    "sg:address":"30640 Via Las Palmas",
    "sg:city":"Thousand Palms",
    "sg:classifiers":[
        {
            "category":"Retail",
            "subcategory":"Animal Services",
            "type":"Services"
        }
    ],
    "sg:phone":"+1 760 322 5652",
    "sg:postcode":"92276",
    "sg:province":"CA",
    "sg:tags":[
        "pet",
        "grooming",
        "washing"
    ],
    "sg:website":"www.thefroufrouroom.com",
    "wof:name":"Frou Frou Room",
    "wof:placetype":"venue"
},
  "geometry": {"coordinates":[-116.373349,33.828085],"type":"Point"}
}