{
  "type": "Feature",
  "properties": {
    "addr:full":"4676 Lakeview Ave Yorba Linda CA 92886",
    "addr:housenumber":"4676",
    "addr:postcode":"92886",
    "addr:street":"Lakeview Ave",
    "iso:country":"US",
    "sg:address":"4676 Lakeview Ave",
    "sg:city":"Yorba Linda",
    "sg:classifiers":[
        {
            "category":"Food & Beverages",
            "subcategory":"Bakery",
            "type":"Retail Goods"
        }
    ],
    "sg:phone":"+1 714 779 9092",
    "sg:postcode":"92886",
    "sg:province":"CA",
    "sg:tags":[
        "baker"
    ],
    "wof:name":"Auntie Anne's Hand Rolled Soft",
    "wof:placetype":"venue"
},
  "geometry": {"coordinates":[-117.81138,33.89178],"type":"Point"}
}