{
  "type": "Feature",
  "properties": {
    "iso:country":"US",
    "sg:address":"201 N San Gabriel Blvd",
    "sg:city":"San Gabriel",
    "sg:classifiers":[
        {
            "category":"Organizations",
            "subcategory":"Religious Organization",
            "type":"Services"
        }
    ],
    "sg:phone":"+1 626 286 3111",
    "sg:postcode":"91775",
    "sg:province":"CA",
    "sg:tags":[
        "church"
    ],
    "wof:name":"First United Methodist Church",
    "wof:placetype":"venue"
},
  "geometry": {"coordinates":[-118.091028,34.106207],"type":"Point"}
}