{
  "type": "Feature",
  "properties": {
    "iso:country":"US",
    "sg:address":"3525 2nd Ave",
    "sg:city":"Sacramento",
    "sg:classifiers":[
        {
            "category":"Home & Garden",
            "subcategory":"Home Furnishings",
            "type":"Retail Goods"
        }
    ],
    "sg:phone":"+1 916 451 6757",
    "sg:postcode":"95817",
    "sg:province":"CA",
    "sg:tags":[
        "draperies",
        "made",
        "window",
        "treatment",
        "curtain",
        "drapery"
    ],
    "wof:name":"Visions Window Coverings",
    "wof:placetype":"venue"
},
  "geometry": {"coordinates":[-121.467467,38.552545],"type":"Point"}
}