{
  "type": "Feature",
  "properties": {
    "iso:country":"US",
    "sg:address":"2380 Bluebell Dr",
    "sg:city":"Santa Rosa",
    "sg:classifiers":[
        {
            "category":"Wholesale",
            "subcategory":"Construction Materials",
            "type":"Manufacturing & Wholesale Goods"
        }
    ],
    "sg:phone":"+1 707 833 2069",
    "sg:postcode":"95403",
    "sg:province":"CA",
    "sg:tags":[
        "fence"
    ],
    "sg:website":"www.kenwoodfence.com",
    "wof:name":"Kenwood Fence Co",
    "wof:placetype":"venue"
},
  "geometry": {"coordinates":[-122.742986,38.465812],"type":"Point"}
}