{
  "type": "Feature",
  "properties": {
    "addr:full":"11526 Sorrento Valley Rd San Diego CA 92121",
    "addr:housenumber":"11526",
    "addr:postcode":"92121",
    "addr:street":"Sorrento Valley Rd",
    "iso:country":"US",
    "sg:address":"11526 Sorrento Valley Rd",
    "sg:city":"San Diego",
    "sg:classifiers":[
        {
            "category":"Wholesale",
            "subcategory":"Medical Equipment & Supplies",
            "type":"Manufacturing & Wholesale Goods"
        }
    ],
    "sg:phone":"+1 858 509 3726",
    "sg:postcode":"92121",
    "sg:province":"CA",
    "sg:tags":[
        "physician",
        "surgeon"
    ],
    "wof:name":"Pulse Metrics Inc",
    "wof:placetype":"venue"
},
  "geometry": {"coordinates":[-117.229798,32.909636],"type":"Point"}
}