{
  "type": "Feature",
  "properties": {
    "iso:country":"US",
    "sg:address":"1600 W Redondo Beach Blvd Ste 301",
    "sg:city":"Gardena",
    "sg:classifiers":[
        {
            "category":"Health Services",
            "subcategory":"Doctor",
            "type":"Services"
        },
        {
            "category":"Sports & Exercise",
            "subcategory":"Gym",
            "type":"Entertainment"
        }
    ],
    "sg:phone":"+1 310 532 6614",
    "sg:postcode":"90247",
    "sg:province":"CA",
    "sg:tags":[
        "trainer"
    ],
    "wof:name":"Customized Credentialing Service",
    "wof:placetype":"venue"
},
  "geometry": {"coordinates":[-118.304744,33.888716],"type":"Point"}
}