{
  "type": "Feature",
  "properties": {
    "addr:full":"2355 N Chain Dr Simi Valley CA 93065",
    "addr:housenumber":"2355",
    "addr:postcode":"93065",
    "addr:street":"N Chain Dr",
    "iso:country":"US",
    "sg:address":"2355 N Chain Dr",
    "sg:city":"Simi Valley",
    "sg:classifiers":[
        {
            "category":"Manufacturing",
            "subcategory":"Metals",
            "type":"Manufacturing & Wholesale Goods"
        },
        {
            "category":"Building & Trades",
            "subcategory":"Plumbing",
            "type":"Services"
        }
    ],
    "sg:phone":"+1 805 583 2725",
    "sg:postcode":"93065",
    "sg:province":"CA",
    "sg:tags":[
        "contractor",
        "work",
        "sheet",
        "metalwork",
        "mfg"
    ],
    "wof:name":"Mustang Precision Fabricators",
    "wof:placetype":"venue"
},
  "geometry": {"coordinates":[-118.793226,34.278516],"type":"Point"}
}