{
  "type": "Feature",
  "properties": {
    "iso:country":"US",
    "sg:address":"3002 W Manchester Blvd",
    "sg:city":"Inglewood",
    "sg:classifiers":[
        {
            "category":"Home & Garden",
            "subcategory":"Carpets & Floor Coverings",
            "type":"Retail Goods"
        }
    ],
    "sg:phone":"+1 323 750 6035",
    "sg:postcode":"90305",
    "sg:province":"CA",
    "sg:tags":[
        "carpeting"
    ],
    "wof:name":"House of Carpet",
    "wof:placetype":"venue"
},
  "geometry": {"coordinates":[-118.325996,33.959999],"type":"Point"}
}