{
  "type": "Feature",
  "properties": {
    "addr:full":"28639 S Western Ave Rancho Pls Vrds CA 90275",
    "addr:housenumber":"28639",
    "addr:postcode":"90275",
    "addr:street":"S Western Ave",
    "iso:country":"US",
    "sg:address":"28639 S Western Ave",
    "sg:city":"Rancho Pls Vrds",
    "sg:classifiers":[
        {
            "category":"Health Services",
            "subcategory":"Nursing And Care Facility",
            "type":"Services"
        }
    ],
    "sg:phone":"+1 310 548 4883",
    "sg:postcode":"90275",
    "sg:province":"CA",
    "sg:tags":[
        "hospice"
    ],
    "wof:name":"Peninsula Hospice",
    "wof:placetype":"venue"
},
  "geometry": {"coordinates":[-118.312533,33.759853],"type":"Point"}
}