{
  "type": "Feature",
  "properties": {
    "iso:country":"US",
    "sg:address":"2181 Fremont St",
    "sg:city":"Concord",
    "sg:classifiers":[
        {
            "category":"Organizations",
            "subcategory":"Membership Organization",
            "type":"Services"
        }
    ],
    "sg:phone":"+1 925 682 4975",
    "sg:postcode":"94520",
    "sg:province":"CA",
    "sg:tags":[
        "club",
        "private"
    ],
    "wof:name":"Iron Horsemen Inc",
    "wof:placetype":"venue"
},
  "geometry": {"coordinates":[-122.04096,37.978124],"type":"Point"}
}