{
  "type": "Feature",
  "properties": {
    "iso:country":"US",
    "sg:address":"1400 Valinda Ave",
    "sg:city":"La Puente",
    "sg:classifiers":[
        {
            "category":"Food & Beverages",
            "subcategory":"Liquor & Beverages",
            "type":"Retail Goods"
        }
    ],
    "sg:phone":"+1 626 917 7642",
    "sg:postcode":"91744",
    "sg:province":"CA",
    "wof:name":"Fast Trip Food Store",
    "wof:placetype":"venue"
},
  "geometry": {"coordinates":[-117.925656,34.045708],"type":"Point"}
}