{
  "type": "Feature",
  "properties": {
    "addr:full":"13382 Sayre St Sylmar CA 91342",
    "addr:housenumber":"13382",
    "addr:postcode":"91342",
    "addr:street":"Sayre St",
    "iso:country":"US",
    "sg:address":"13382 Sayre St",
    "sg:city":"Sylmar",
    "sg:classifiers":[
        {
            "category":"Food & Beverages",
            "subcategory":"Groceries & Convenience Stores",
            "type":"Retail Goods"
        }
    ],
    "sg:phone":"+1 818 367 1994",
    "sg:postcode":"91342",
    "sg:province":"CA",
    "sg:tags":[
        "market"
    ],
    "wof:name":"Ranchero's Meat Market",
    "wof:placetype":"venue"
},
  "geometry": {"coordinates":[-118.42437,34.318496],"type":"Point"}
}