{
  "type": "Feature",
  "properties": {
    "addr:full":"5663 Balboa Ave 487 San Diego CA 92111",
    "addr:housenumber":"5663;487",
    "addr:postcode":"92111",
    "addr:street":"Balboa Ave",
    "iso:country":"US",
    "sg:address":"5663 Balboa Ave 487",
    "sg:city":"San Diego",
    "sg:classifiers":[
        {
            "category":"Professional",
            "type":"Services"
        },
        {
            "category":"Personal",
            "type":"Services"
        }
    ],
    "sg:phone":"+1 619 871 6901",
    "sg:postcode":"92111",
    "sg:province":"CA",
    "sg:tags":[
        "chef",
        "caterer"
    ],
    "sg:website":"www.chefglenda.com",
    "wof:name":"No Place Like Home",
    "wof:placetype":"venue"
},
  "geometry": {"coordinates":[-117.178929,32.820096],"type":"Point"}
}