{
  "type": "Feature",
  "properties": {
    "iso:country":"US",
    "sg:address":"1400 65th St",
    "sg:city":"Emeryville",
    "sg:classifiers":[
        {
            "category":"Banks & Credit Unions",
            "subcategory":"Investment Brokerage",
            "type":"Services"
        }
    ],
    "sg:phone":"+1 510 655 0112",
    "sg:postcode":"94608",
    "sg:province":"CA",
    "sg:tags":[
        "advisory",
        "financial"
    ],
    "wof:name":"BJK Investments",
    "wof:placetype":"venue"
},
  "geometry": {"coordinates":[-122.294557,37.846205],"type":"Point"}
}