{
  "type": "Feature",
  "properties": {
    "addr:full":"14971 el Monte Rd Lakeside CA 92040",
    "addr:housenumber":"14971",
    "addr:postcode":"92040",
    "addr:street":"El Monte Rd",
    "iso:country":"US",
    "sg:address":"14971 el Monte Rd",
    "sg:city":"Lakeside",
    "sg:classifiers":[
        {
            "category":"Building & Trades",
            "subcategory":"Construction",
            "type":"Services"
        }
    ],
    "sg:phone":"+1 619 440 1788",
    "sg:postcode":"92040",
    "sg:province":"CA",
    "sg:tags":[
        "concrete",
        "contractor"
    ],
    "wof:name":"B & B Stamp Concrete",
    "wof:placetype":"venue"
},
  "geometry": {"coordinates":[-116.86022800000001,32.879118],"type":"Point"}
}