{
  "type": "Feature",
  "properties": {
    "iso:country":"US",
    "sg:address":"2975 Rockview Pl",
    "sg:city":"San Luis Obispo",
    "sg:classifiers":[
        {
            "category":"Health Services",
            "subcategory":"Doctor",
            "type":"Services"
        }
    ],
    "sg:phone":"+1 805 543 5415",
    "sg:postcode":"93401",
    "sg:province":"CA",
    "sg:tags":[
        "dentist"
    ],
    "wof:name":"Dental Boxes",
    "wof:placetype":"venue"
},
  "geometry": {"coordinates":[-120.652864,35.261972],"type":"Point"}
}