{
  "type": "Feature",
  "properties": {
    "iso:country":"US",
    "sg:address":"108 Water St",
    "sg:city":"Jackson",
    "sg:classifiers":[
        {
            "category":"Professional",
            "subcategory":"Lawyer & Legal Services",
            "type":"Services"
        }
    ],
    "sg:phone":"+1 209 223 0223",
    "sg:postcode":"95642",
    "sg:province":"CA",
    "sg:tags":[
        "attorney"
    ],
    "wof:name":"Patrick M Keene",
    "wof:placetype":"venue"
},
  "geometry": {"coordinates":[-120.772584,38.348565],"type":"Point"}
}