{
  "type": "Feature",
  "properties": {
    "iso:country":"US",
    "sg:address":"4344 E Morse Rd",
    "sg:city":"Lodi",
    "sg:classifiers":[
        {
            "category":"Restaurant",
            "type":"Food & Drink"
        }
    ],
    "sg:phone":"+1 209 601 2272",
    "sg:postcode":"95240",
    "sg:province":"CA",
    "sg:tags":[
        "caterer"
    ],
    "wof:name":"Mike's Texas Bar-B-Que",
    "wof:placetype":"venue"
},
  "geometry": {"coordinates":[-121.267301,38.068369],"type":"Point"}
}