{
  "type": "Feature",
  "properties": {
    "addr:full":"1800 Market St San Francisco CA 94102",
    "addr:housenumber":"1800",
    "addr:postcode":"94102",
    "addr:street":"Market St",
    "iso:country":"US",
    "sg:address":"1800 Market St",
    "sg:city":"San Francisco",
    "sg:classifiers":[
        {
            "category":"Organizations",
            "subcategory":"Non-profit Organization",
            "type":"Services"
        }
    ],
    "sg:phone":"+1 415 865 5555",
    "sg:postcode":"94102",
    "sg:province":"CA",
    "sg:tags":[
        "lesbian",
        "gay"
    ],
    "wof:name":"LGBT Community Ctr",
    "wof:placetype":"venue"
},
  "geometry": {"coordinates":[-122.424008,37.771474],"type":"Point"}
}