{
  "type": "Feature",
  "properties": {
    "addr:full":"15112 Sierra Hwy Santa Clarita CA 91390",
    "addr:housenumber":"15112",
    "addr:postcode":"91390",
    "addr:street":"Sierra Hwy",
    "iso:country":"US",
    "sg:address":"15112 Sierra Hwy",
    "sg:city":"Santa Clarita",
    "sg:classifiers":[
        {
            "category":"Recreation",
            "subcategory":"Amusement Park",
            "type":"Entertainment"
        },
        {
            "category":"Personal",
            "type":"Services"
        },
        {
            "category":"Arena",
            "subcategory":"Sports Club",
            "type":"Entertainment"
        }
    ],
    "sg:phone":"+1 661 255 5332",
    "sg:postcode":"91390",
    "sg:province":"CA",
    "sg:tags":[
        "local"
    ],
    "sg:website":"www.paintballusa.org",
    "wof:name":"Paintball USA",
    "wof:placetype":"venue"
},
  "geometry": {"coordinates":[-118.388184,34.471023],"type":"Point"}
}