{
  "type": "Feature",
  "properties": {
    "iso:country":"US",
    "sg:address":"711 Center Dr",
    "sg:city":"San Marcos",
    "sg:classifiers":[
        {
            "category":"Personal",
            "subcategory":"Beauty Salon",
            "type":"Services"
        }
    ],
    "sg:phone":"+1 760 233 4181",
    "sg:postcode":"92069",
    "sg:province":"CA",
    "sg:tags":[
        "manicuring"
    ],
    "wof:name":"Professionail",
    "wof:placetype":"venue"
},
  "geometry": {"coordinates":[-117.123088,33.133611],"type":"Point"}
}