{
  "type": "Feature",
  "properties": {
    "iso:country":"US",
    "sg:address":"972 Barstow Ave",
    "sg:city":"Clovis",
    "sg:classifiers":[
        {
            "category":"Retail",
            "subcategory":"Auto Repair",
            "type":"Services"
        }
    ],
    "sg:phone":"+1 559 299 5049",
    "sg:postcode":"93612",
    "sg:province":"CA",
    "sg:tags":[
        "repairing",
        "automobile"
    ],
    "wof:name":"Clovis Drop Shop",
    "wof:placetype":"venue"
},
  "geometry": {"coordinates":[-119.696005,36.815699],"type":"Point"}
}