{
  "type": "Feature",
  "properties": {
    "addr:full":"200 E Garvey Ave Ste 102 Monterey Park CA 91755",
    "addr:housenumber":"200",
    "addr:postcode":"91755",
    "addr:street":"E Garvey Ave Ste 102",
    "iso:country":"US",
    "sg:address":"200 E Garvey Ave Ste 102",
    "sg:city":"Monterey Park",
    "sg:classifiers":[
        {
            "category":"Shopping",
            "subcategory":"Clothing, Apparel, & Fashions",
            "type":"Retail Goods"
        }
    ],
    "sg:phone":"+1 626 573 5715",
    "sg:postcode":"91755",
    "sg:province":"CA",
    "sg:tags":[
        "accessory",
        "clothing",
        "women's"
    ],
    "wof:name":"Red Apple Co",
    "wof:placetype":"venue"
},
  "geometry": {"coordinates":[-118.121002,34.062401],"type":"Point"}
}