{
  "type": "Feature",
  "properties": {
    "addr:full":"2724 E Thompson Blvd Ventura CA 93003",
    "addr:housenumber":"2724",
    "addr:postcode":"93003",
    "addr:street":"E Thompson Blvd",
    "iso:country":"US",
    "sg:address":"2724 E Thompson Blvd",
    "sg:city":"Ventura",
    "sg:classifiers":[
        {
            "category":"Wholesale",
            "subcategory":"Machinery & Supplies",
            "type":"Manufacturing & Wholesale Goods"
        }
    ],
    "sg:phone":"+1 805 648 7600",
    "sg:postcode":"93003",
    "sg:province":"CA",
    "sg:tags":[
        "salon",
        "salons-equipment",
        "beauty"
    ],
    "wof:name":"Pro Beauty Of Ventura",
    "wof:placetype":"venue"
},
  "geometry": {"coordinates":[-119.25936400000001,34.272185],"type":"Point"}
}