{
  "type": "Feature",
  "properties": {
    "addr:full":"555 9th St San Francisco CA 94103",
    "addr:housenumber":"555",
    "addr:postcode":"94103",
    "addr:street":"9Th St",
    "iso:country":"US",
    "sg:address":"555 9th St",
    "sg:city":"San Francisco",
    "sg:classifiers":[
        {
            "category":"Home & Garden",
            "subcategory":"Furniture",
            "type":"Retail Goods"
        }
    ],
    "sg:phone":"+1 415 252 8618",
    "sg:postcode":"94103",
    "sg:province":"CA",
    "wof:name":"Black Sea Gallery",
    "wof:placetype":"venue"
},
  "geometry": {"coordinates":[-122.407614,37.770786],"type":"Point"}
}