{
  "type": "Feature",
  "properties": {
    "addr:full":"1619 S Main St Milpitas CA 95035",
    "addr:housenumber":"1619",
    "addr:postcode":"95035",
    "addr:street":"S Main St",
    "iso:country":"US",
    "sg:address":"1619 S Main St",
    "sg:city":"Milpitas",
    "sg:classifiers":[
        {
            "category":"Shopping",
            "subcategory":"Computers & Home Electronics",
            "type":"Retail Goods"
        }
    ],
    "sg:phone":"+1 408 941 0590",
    "sg:postcode":"95035",
    "sg:province":"CA",
    "sg:tags":[
        "software"
    ],
    "wof:name":"Green Tomato Software",
    "wof:placetype":"venue"
},
  "geometry": {"coordinates":[-121.902985,37.405767],"type":"Point"}
}