{
  "type": "Feature",
  "properties": {
    "iso:country":"US",
    "sg:address":"1802 E G St",
    "sg:city":"Ontario",
    "sg:classifiers":[
        {
            "category":"Health Services",
            "subcategory":"Clinic",
            "type":"Services"
        }
    ],
    "sg:phone":"+1 909 467 1950",
    "sg:postcode":"91764",
    "sg:province":"CA",
    "sg:tags":[
        "home"
    ],
    "wof:name":"Superior Home Health Care",
    "wof:placetype":"venue"
},
  "geometry": {"coordinates":[-117.611079,34.068743],"type":"Point"}
}