{
  "type": "Feature",
  "properties": {
    "addr:full":"686 Canterbury Pl Milpitas CA 95035",
    "addr:housenumber":"686",
    "addr:postcode":"95035",
    "addr:street":"Canterbury Pl",
    "iso:country":"US",
    "sg:address":"686 Canterbury Pl",
    "sg:city":"Milpitas",
    "sg:classifiers":[
        {
            "category":"Manufacturing",
            "subcategory":"Textiles",
            "type":"Manufacturing & Wholesale Goods"
        }
    ],
    "sg:phone":"+1 408 946 4720",
    "sg:postcode":"95035",
    "sg:province":"CA",
    "sg:tags":[
        "mill",
        "knit",
        "outerwear"
    ],
    "wof:name":"A Touch of Orient",
    "wof:placetype":"venue"
},
  "geometry": {"coordinates":[-121.896047,37.457022],"type":"Point"}
}