{
  "type": "Feature",
  "properties": {
    "iso:country":"US",
    "sg:address":"1543 W Olympic Boulevard Suite 100",
    "sg:city":"Los Angeles",
    "sg:classifiers":[
        {
            "category":"Communications",
            "subcategory":"Radio Station",
            "type":"Services"
        }
    ],
    "sg:phone":"+1 213 365 8515",
    "sg:postcode":"90015",
    "sg:province":"CA",
    "wof:name":"Jesus Satellite Tv",
    "wof:placetype":"venue"
},
  "geometry": {"coordinates":[-118.27344600000001,34.048878],"type":"Point"}
}