{
  "type": "Feature",
  "properties": {
    "addr:full":"1315 W Whittier Blvd La Habra CA 90631",
    "addr:housenumber":"1315",
    "addr:postcode":"90631",
    "addr:street":"W Whittier Blvd",
    "iso:country":"US",
    "sg:address":"1315 W Whittier Blvd",
    "sg:city":"La Habra",
    "sg:classifiers":[
        {
            "category":"Restaurant",
            "type":"Food & Drink"
        }
    ],
    "sg:phone":"+1 562 694 3681",
    "sg:postcode":"90631",
    "sg:province":"CA",
    "sg:website":"www.originaltommys.com",
    "wof:name":"Tommy's Hamburgers",
    "wof:placetype":"venue"
},
  "geometry": {"coordinates":[-117.96057,33.939297],"type":"Point"}
}