{
  "type": "Feature",
  "properties": {
    "addr:full":"7996 Armour Street San Diego CA 92111",
    "addr:housenumber":"7996",
    "addr:postcode":"92111",
    "addr:street":"Armour Street",
    "iso:country":"US",
    "sg:address":"7996 Armour Street",
    "sg:city":"San Diego",
    "sg:classifiers":[
        {
            "category":"Retail",
            "subcategory":"Repair Shop",
            "type":"Services"
        }
    ],
    "sg:phone":"+1 858 292 9009",
    "sg:postcode":"92111",
    "sg:province":"CA",
    "sg:tags":[
        "reupholstery",
        "furniture"
    ],
    "wof:name":"Canvas Complete",
    "wof:placetype":"venue"
},
  "geometry": {"coordinates":[-117.151037,32.820009],"type":"Point"}
}