{
  "type": "Feature",
  "properties": {
    "addr:full":"3024 Via del Robles Fallbrook CA 92028",
    "addr:housenumber":"3024",
    "addr:postcode":"92028",
    "addr:street":"Via Del Robles",
    "iso:country":"US",
    "sg:address":"3024 Via del Robles",
    "sg:city":"Fallbrook",
    "sg:classifiers":[
        {
            "category":"Wholesale",
            "subcategory":"Electrical",
            "type":"Manufacturing & Wholesale Goods"
        }
    ],
    "sg:phone":"+1 760 723 7262",
    "sg:postcode":"92028",
    "sg:province":"CA",
    "sg:tags":[
        "fire",
        "equipment",
        "protection"
    ],
    "wof:name":"Madden Fire Protection",
    "wof:placetype":"venue"
},
  "geometry": {"coordinates":[-117.196539,33.350859],"type":"Point"}
}