{
  "type": "Feature",
  "properties": {
    "addr:full":"2848 Morrill Rd Riverbank CA 95367",
    "addr:postcode":"2848;95367",
    "addr:street":"Morrill Rd",
    "iso:country":"US",
    "sg:address":"2848 Morrill Rd",
    "sg:city":"Riverbank",
    "sg:classifiers":[
        {
            "category":"Home & Garden",
            "subcategory":"Household Appliances",
            "type":"Retail Goods"
        }
    ],
    "sg:phone":"+1 209 869 3995",
    "sg:postcode":"95367",
    "sg:province":"CA",
    "wof:name":"Modesto Appliance",
    "wof:placetype":"venue"
},
  "geometry": {"coordinates":[-120.94493900000001,37.725362],"type":"Point"}
}