{
  "type": "Feature",
  "properties": {
    "iso:country":"US",
    "sg:address":"13740 Arnold Dr",
    "sg:city":"Glen Ellen",
    "sg:classifiers":[
        {
            "category":"Restaurant",
            "type":"Food & Drink"
        }
    ],
    "sg:menulink":"http://www.allmenus.com/ca/sonoma/22053-wolf-house/menu/",
    "sg:phone":"+1 707 996 4401",
    "sg:postcode":"95442",
    "sg:province":"CA",
    "sg:tags":[
        "american"
    ],
    "wof:name":"Wolf House",
    "wof:placetype":"venue"
},
  "geometry": {"coordinates":[-122.524348,38.363375],"type":"Point"}
}