{
  "type": "Feature",
  "properties": {
    "iso:country":"US",
    "sg:address":"8200 Slauson Ave",
    "sg:city":"Pico Rivera",
    "sg:classifiers":[
        {
            "category":"Wholesale",
            "subcategory":"Machinery & Supplies",
            "type":"Manufacturing & Wholesale Goods"
        },
        {
            "category":"Wholesale",
            "subcategory":"Chemicals & Plastics",
            "type":"Manufacturing & Wholesale Goods"
        }
    ],
    "sg:phone":"+1 562 949 0558",
    "sg:postcode":"90660",
    "sg:province":"CA",
    "sg:tags":[
        "glue",
        "adhesive",
        "industrial"
    ],
    "wof:name":"Hinckle Adhesives",
    "wof:placetype":"venue"
},
  "geometry": {"coordinates":[-118.118571,33.975088],"type":"Point"}
}