{
  "type": "Feature",
  "properties": {
    "iso:country":"US",
    "sg:address":"217 W Cerritos Ave",
    "sg:city":"Anaheim",
    "sg:classifiers":[
        {
            "category":"Health Services",
            "subcategory":"Clinic",
            "type":"Services"
        }
    ],
    "sg:phone":"+1 714 254 8473",
    "sg:postcode":"92805",
    "sg:province":"CA",
    "wof:name":"Aspen Community Svc",
    "wof:placetype":"venue"
},
  "geometry": {"coordinates":[-117.907305,33.809745],"type":"Point"}
}