{
  "type": "Feature",
  "properties": {
    "iso:country":"US",
    "sg:address":"5435 S Elm Ave",
    "sg:city":"Fresno",
    "sg:classifiers":[
        {
            "category":"Autos & Motor Vehicles",
            "subcategory":"Automobile Sales",
            "type":"Retail Goods"
        }
    ],
    "sg:phone":"+1 559 485 5882",
    "sg:postcode":"93706",
    "sg:province":"CA",
    "sg:tags":[
        "car",
        "dealer"
    ],
    "wof:name":"America Auto Sales",
    "wof:placetype":"venue"
},
  "geometry": {"coordinates":[-119.790865,36.662363],"type":"Point"}
}