{
  "type": "Feature",
  "properties": {
    "iso:country":"US",
    "sg:address":"2790 Harbor Blvd Ste 210",
    "sg:city":"Costa Mesa",
    "sg:classifiers":[
        {
            "category":"Sports & Exercise",
            "subcategory":"Playing Field",
            "type":"Entertainment"
        }
    ],
    "sg:phone":"+1 714 434 4991",
    "sg:postcode":"92626",
    "sg:province":"CA",
    "sg:tags":[
        "instruction",
        "fitness"
    ],
    "sg:website":"www.sfactor.com",
    "wof:name":"Sheila Kelley S Factor",
    "wof:placetype":"venue"
},
  "geometry": {"coordinates":[-117.91914,33.672971],"type":"Point"}
}