{
  "type": "Feature",
  "properties": {
    "iso:country":"US",
    "sg:address":"660 Cannery Row",
    "sg:city":"Monterey",
    "sg:classifiers":[
        {
            "category":"Restaurant",
            "type":"Food & Drink"
        }
    ],
    "sg:phone":"+1 831 648 8500",
    "sg:postcode":"93940",
    "sg:province":"CA",
    "wof:name":"Louie Linguini's Seafood Shack",
    "wof:placetype":"venue"
},
  "geometry": {"coordinates":[-121.899781,36.615359],"type":"Point"}
}