{
  "type": "Feature",
  "properties": {
    "iso:country":"US",
    "sg:address":"430 S 1st St",
    "sg:city":"Fresno",
    "sg:classifiers":[
        {
            "category":"Organizations",
            "subcategory":"Religious Organization",
            "type":"Services"
        }
    ],
    "sg:phone":"+1 559 237 6638",
    "sg:postcode":"93702",
    "sg:province":"CA",
    "sg:tags":[
        "churches-presbyterian-usa",
        "church"
    ],
    "sg:website":"www.fapc.net",
    "wof:name":"First Armenian Presbyterian Ch",
    "wof:placetype":"venue"
},
  "geometry": {"coordinates":[-119.772459,36.738904],"type":"Point"}
}