{
  "type": "Feature",
  "properties": {
    "iso:country":"US",
    "sg:address":"3501 Civic Center Dr",
    "sg:city":"San Rafael",
    "sg:classifiers":[
        {
            "category":"Government",
            "subcategory":"Office",
            "type":"Public Place"
        }
    ],
    "sg:phone":"+1 415 499 6549",
    "sg:postcode":"94903",
    "sg:province":"CA",
    "wof:name":"Marin County Land Development",
    "wof:placetype":"venue"
},
  "geometry": {"coordinates":[-122.528432,37.996741],"type":"Point"}
}