{
  "type": "Feature",
  "properties": {
    "addr:full":"520 Park View Ave Grover Beach CA 93433",
    "addr:housenumber":"520",
    "addr:postcode":"93433",
    "addr:street":"Park View Ave",
    "iso:country":"US",
    "sg:address":"520 Park View Ave",
    "sg:city":"Grover Beach",
    "sg:classifiers":[
        {
            "category":"Manufacturing",
            "subcategory":"Building Materials",
            "type":"Manufacturing & Wholesale Goods"
        }
    ],
    "sg:phone":"+1 805 481 1551",
    "sg:postcode":"93433",
    "sg:province":"CA",
    "sg:tags":[
        "mfg"
    ],
    "wof:name":"Traditional Woodwork",
    "wof:placetype":"venue"
},
  "geometry": {"coordinates":[-120.624498,35.128306],"type":"Point"}
}