{
  "type": "Feature",
  "properties": {
    "addr:full":"1265 Eureka Ave Los Altos CA 94024",
    "addr:housenumber":"1265",
    "addr:postcode":"94024",
    "addr:street":"Eureka Ave",
    "iso:country":"US",
    "sg:address":"1265 Eureka Ave",
    "sg:city":"Los Altos",
    "sg:classifiers":[
        {
            "category":"Building & Trades",
            "subcategory":"Construction",
            "type":"Services"
        }
    ],
    "sg:phone":"+1 650 969 0647",
    "sg:postcode":"94024",
    "sg:province":"CA",
    "sg:tags":[
        "contractor"
    ],
    "wof:name":"Proactive Building Svc",
    "wof:placetype":"venue"
},
  "geometry": {"coordinates":[-122.07784700000001,37.357745],"type":"Point"}
}