{
  "type": "Feature",
  "properties": {
    "addr:full":"449 34th St Manhattan Beach CA 90266",
    "addr:housenumber":"449",
    "addr:postcode":"90266",
    "addr:street":"34Th St",
    "iso:country":"US",
    "sg:address":"449 34th St",
    "sg:city":"Manhattan Beach",
    "sg:classifiers":[
        {
            "category":"Banks & Credit Unions",
            "subcategory":"Financial Services",
            "type":"Services"
        }
    ],
    "sg:phone":"+1 310 545 5656",
    "sg:postcode":"90266",
    "sg:province":"CA",
    "sg:tags":[
        "trust",
        "investment",
        "real estate"
    ],
    "wof:name":"Roese Development Group",
    "wof:placetype":"venue"
},
  "geometry": {"coordinates":[-118.41467299999999,33.899651],"type":"Point"}
}