{
  "type": "Feature",
  "properties": {
    "iso:country":"US",
    "sg:address":"11152 Rancho Carmel Dr",
    "sg:city":"San Diego",
    "sg:classifiers":[
        {
            "category":"Restaurant",
            "type":"Food & Drink"
        }
    ],
    "sg:menulink":"http://www.allmenus.com/ca/san-diego/174521-wendys/menu/",
    "sg:phone":"+1 858 674 6070",
    "sg:postcode":"92128",
    "sg:province":"CA",
    "sg:tags":[
        "burger",
        "american",
        "soup"
    ],
    "wof:name":"Wendy's",
    "wof:placetype":"venue"
},
  "geometry": {"coordinates":[-117.082421,32.980157],"type":"Point"}
}