{
  "type": "Feature",
  "properties": {
    "addr:full":"14715 Saticoy St Van Nuys CA 91405",
    "addr:postcode":"14715;91405",
    "addr:street":"Saticoy St",
    "iso:country":"US",
    "sg:address":"14715 Saticoy St",
    "sg:city":"Van Nuys",
    "sg:classifiers":[
        {
            "category":"Professional",
            "type":"Services"
        }
    ],
    "sg:phone":"+1 818 902 9203",
    "sg:postcode":"91405",
    "sg:province":"CA",
    "wof:name":"Visual Delight Effects",
    "wof:placetype":"venue"
},
  "geometry": {"coordinates":[-118.455248,34.208528],"type":"Point"}
}