{
  "type": "Feature",
  "properties": {
    "iso:country":"US",
    "sg:address":"10084 Branford Rd",
    "sg:city":"San Diego",
    "sg:classifiers":[
        {
            "category":"Professional",
            "type":"Services"
        }
    ],
    "sg:phone":"+1 858 484 1746",
    "sg:postcode":"92129",
    "sg:province":"CA",
    "wof:name":"Eden Alternative Region V",
    "wof:placetype":"venue"
},
  "geometry": {"coordinates":[-117.11380699999999,32.968651],"type":"Point"}
}