{
  "type": "Feature",
  "properties": {
    "iso:country":"US",
    "sg:address":"1937 E 20th St Ste 7",
    "sg:city":"Chico",
    "sg:phone":"+1 530 898 9160",
    "sg:postcode":"95928",
    "sg:province":"CA",
    "wof:name":"Nails Chu & Lee",
    "wof:placetype":"venue"
},
  "geometry": {"coordinates":[-121.80548400000001,39.72728],"type":"Point"}
}