{
  "type": "Feature",
  "properties": {
    "addr:full":"1870 Avondale Ave Sacramento CA 95825",
    "addr:housenumber":"1870",
    "addr:postcode":"95825",
    "addr:street":"Avondale Ave",
    "iso:country":"US",
    "sg:address":"1870 Avondale Ave",
    "sg:city":"Sacramento",
    "sg:classifiers":[
        {
            "category":"Health Services",
            "subcategory":"Doctor",
            "type":"Services"
        }
    ],
    "sg:phone":"+1 916 481 5990",
    "sg:postcode":"95825",
    "sg:province":"CA",
    "sg:tags":[
        "dentist"
    ],
    "wof:name":"Avondale Dental Office",
    "wof:placetype":"venue"
},
  "geometry": {"coordinates":[-121.394997,38.595886],"type":"Point"}
}