{
  "type": "Feature",
  "properties": {
    "addr:full":"10712 Gramercy Pl Riverside CA 92505",
    "addr:housenumber":"10712",
    "addr:postcode":"92505",
    "addr:street":"Gramercy Pl",
    "iso:country":"US",
    "sg:address":"10712 Gramercy Pl",
    "sg:city":"Riverside",
    "sg:classifiers":[
        {
            "category":"Banks & Credit Unions",
            "subcategory":"Investment Brokerage",
            "type":"Services"
        }
    ],
    "sg:phone":"+1 951 588 0787",
    "sg:postcode":"92505",
    "sg:province":"CA",
    "sg:tags":[
        "advisory",
        "financial"
    ],
    "wof:name":"C & H Financial",
    "wof:placetype":"venue"
},
  "geometry": {"coordinates":[-117.48890400000001,33.929052],"type":"Point"}
}