{
  "type": "Feature",
  "properties": {
    "addr:full":"8584 Rd 25 Madera CA 93637",
    "addr:housenumber":"8584",
    "addr:postcode":"93637",
    "addr:street":"Rd 25",
    "iso:country":"US",
    "sg:address":"8584 Rd 25",
    "sg:city":"Madera",
    "sg:classifiers":[
        {
            "category":"Farming",
            "subcategory":"Vineyard",
            "type":"Manufacturing & Wholesale Goods"
        }
    ],
    "sg:phone":"+1 559 661 4275",
    "sg:postcode":"93637",
    "sg:province":"CA",
    "sg:tags":[
        "grape"
    ],
    "wof:name":"Jim L Miller Farms",
    "wof:placetype":"venue"
},
  "geometry": {"coordinates":[-120.09231200000001,36.879022],"type":"Point"}
}