{
  "type": "Feature",
  "properties": {
    "iso:country":"US",
    "sg:address":"5321 Scotts Valley Dr",
    "sg:city":"Scotts Valley",
    "sg:classifiers":[
        {
            "category":"Professional",
            "subcategory":"Detective & Security Services",
            "type":"Services"
        }
    ],
    "sg:phone":"+1 831 438 2480",
    "sg:postcode":"95066",
    "sg:province":"CA",
    "sg:tags":[
        "investigator"
    ],
    "wof:name":"Cahill Investigations",
    "wof:placetype":"venue"
},
  "geometry": {"coordinates":[-122.010549,37.058279],"type":"Point"}
}