{
  "type": "Feature",
  "properties": {
    "iso:country":"US",
    "sg:address":"112 Ohio Ave",
    "sg:city":"Richmond",
    "sg:classifiers":[
        {
            "category":"Wholesale",
            "subcategory":"Scrap",
            "type":"Manufacturing & Wholesale Goods"
        }
    ],
    "sg:phone":"+1 510 236 3385",
    "sg:postcode":"94804",
    "sg:province":"CA",
    "sg:tags":[
        "recycling",
        "center"
    ],
    "wof:name":"Bay Area Biofuel",
    "wof:placetype":"venue"
},
  "geometry": {"coordinates":[-122.36792699999999,37.93077],"type":"Point"}
}