{
  "type": "Feature",
  "properties": {
    "addr:full":"1688 W Katella Ave Anaheim CA 92802",
    "addr:housenumber":"1688",
    "addr:postcode":"92802",
    "addr:street":"W Katella Ave",
    "iso:country":"US",
    "sg:address":"1688 W Katella Ave",
    "sg:city":"Anaheim",
    "sg:classifiers":[
        {
            "category":"Shopping",
            "subcategory":"Shoes",
            "type":"Retail Goods"
        }
    ],
    "sg:phone":"+1 714 636 8161",
    "sg:postcode":"92802",
    "sg:province":"CA",
    "sg:tags":[
        "store"
    ],
    "wof:name":"Payless Shoesource",
    "wof:placetype":"venue"
},
  "geometry": {"coordinates":[-117.941002,33.8032],"type":"Point"}
}