{
  "type": "Feature",
  "properties": {
    "iso:country":"US",
    "sg:address":"215 N Marengo Ave",
    "sg:city":"Pasadena",
    "sg:classifiers":[
        {
            "category":"Social Services",
            "type":"Services"
        }
    ],
    "sg:phone":"+1 626 564 0480",
    "sg:postcode":"91101",
    "sg:province":"CA",
    "sg:tags":[
        "counselor",
        "marriage",
        "family"
    ],
    "wof:name":"A Center For Singles",
    "wof:placetype":"venue"
},
  "geometry": {"coordinates":[-118.146067,34.150878],"type":"Point"}
}