{
  "type": "Feature",
  "properties": {
    "iso:country":"US",
    "sg:address":"4820 Mercury St Ste A",
    "sg:city":"San Diego",
    "sg:classifiers":[
        {
            "category":"Shopping",
            "subcategory":"Jewelry",
            "type":"Retail Goods"
        }
    ],
    "sg:phone":"+1 858 571 4554",
    "sg:postcode":"92111",
    "sg:province":"CA",
    "wof:name":"Digital & Beyond",
    "wof:placetype":"venue"
},
  "geometry": {"coordinates":[-117.149002,32.829399],"type":"Point"}
}