{
  "type": "Feature",
  "properties": {
    "addr:full":"26101 Ave Bonachon Mission Viejo CA 92691",
    "addr:housenumber":"26101",
    "addr:postcode":"92691",
    "addr:street":"Ave Bonachon",
    "iso:country":"US",
    "sg:address":"26101 Ave Bonachon",
    "sg:city":"Mission Viejo",
    "sg:classifiers":[
        {
            "category":"Freight",
            "type":"Transportation"
        }
    ],
    "sg:phone":"+1 949 859 1937",
    "sg:postcode":"92691",
    "sg:province":"CA",
    "wof:name":"Machado Brothers Trnsp",
    "wof:placetype":"venue"
},
  "geometry": {"coordinates":[-117.674032,33.615622],"type":"Point"}
}