{
  "type": "Feature",
  "properties": {
    "addr:full":"1014 Manhattan Ave Manhattan Beach CA 90266",
    "addr:housenumber":"1014",
    "addr:postcode":"90266",
    "addr:street":"Manhattan Ave",
    "iso:country":"US",
    "sg:address":"1014 Manhattan Ave",
    "sg:city":"Manhattan Beach",
    "sg:classifiers":[
        {
            "category":"Shopping",
            "subcategory":"Hobbies, Toys, & Games",
            "type":"Retail Goods"
        }
    ],
    "sg:phone":"+1 310 798 7744",
    "sg:postcode":"90266",
    "sg:province":"CA",
    "sg:tags":[
        "toy",
        "store"
    ],
    "wof:name":"Toy Jungle",
    "wof:placetype":"venue"
},
  "geometry": {"coordinates":[-118.410014,33.884029],"type":"Point"}
}