{
  "type": "Feature",
  "properties": {
    "iso:country":"US",
    "sg:address":"235 Eastridge Dr",
    "sg:city":"San Ramon",
    "sg:classifiers":[
        {
            "category":"Real Estate",
            "subcategory":"Real Estate Operator",
            "type":"Services"
        }
    ],
    "sg:phone":"+1 925 735 3330",
    "sg:postcode":"94582",
    "sg:province":"CA",
    "sg:tags":[
        "apartment",
        "complex"
    ],
    "wof:name":"Eastridge Apts",
    "wof:placetype":"venue"
},
  "geometry": {"coordinates":[-117.097613,33.15975],"type":"Point"}
}