{
  "type": "Feature",
  "properties": {
    "addr:full":"5636 Jackson Ranch Rd Weed CA 96094",
    "addr:housenumber":"5636",
    "addr:postcode":"96094",
    "addr:street":"Jackson Ranch Rd",
    "iso:country":"US",
    "sg:address":"5636 Jackson Ranch Rd",
    "sg:city":"Weed",
    "sg:classifiers":[
        {
            "category":"Building & Trades",
            "subcategory":"Plumbing",
            "type":"Services"
        }
    ],
    "sg:phone":"+1 530 938 2939",
    "sg:postcode":"96094",
    "sg:province":"CA",
    "sg:tags":[
        "plumbing",
        "contractor"
    ],
    "wof:name":"Vogel Plumbing",
    "wof:placetype":"venue"
},
  "geometry": {"coordinates":[-122.369291,41.493953],"type":"Point"}
}