{
  "type": "Feature",
  "properties": {
    "addr:full":"1834 Newport Boulevard Costa Mesa CA 92627",
    "addr:housenumber":"1834",
    "addr:postcode":"92627",
    "addr:street":"Newport Boulevard",
    "iso:country":"US",
    "sg:address":"1834 Newport Boulevard",
    "sg:city":"Costa Mesa",
    "sg:classifiers":[
        {
            "category":"Building & Trades",
            "subcategory":"Cleaning & Sanitation",
            "type":"Services"
        }
    ],
    "sg:phone":"+1 949 631 2913",
    "sg:postcode":"92627",
    "sg:province":"CA",
    "sg:tags":[
        "carpet"
    ],
    "wof:name":"Chem-Dry of Irvine-Newport",
    "wof:placetype":"venue"
},
  "geometry": {"coordinates":[-117.918254,33.641516],"type":"Point"}
}