{
  "type": "Feature",
  "properties": {
    "addr:full":"8041 Foothill Blvd Sunland CA 91040",
    "addr:housenumber":"8041",
    "addr:postcode":"91040",
    "addr:street":"Foothill Blvd",
    "iso:country":"US",
    "sg:address":"8041 Foothill Blvd",
    "sg:city":"Sunland",
    "sg:classifiers":[
        {
            "category":"Communications",
            "type":"Services"
        }
    ],
    "sg:phone":"+1 818 353 5857",
    "sg:postcode":"91040",
    "sg:province":"CA",
    "sg:tags":[
        "communication"
    ],
    "wof:name":"Superior Electronic Group",
    "wof:placetype":"venue"
},
  "geometry": {"coordinates":[-118.308323,34.259725],"type":"Point"}
}