{
  "type": "Feature",
  "properties": {
    "iso:country":"US",
    "sg:address":"15520 on Orbit Dr",
    "sg:city":"Saratoga",
    "sg:classifiers":[
        {
            "category":"Wholesale",
            "subcategory":"Electrical",
            "type":"Manufacturing & Wholesale Goods"
        },
        {
            "category":"Shopping",
            "subcategory":"Computers & Home Electronics",
            "type":"Retail Goods"
        }
    ],
    "sg:phone":"+1 408 741 1347",
    "sg:postcode":"95070",
    "sg:province":"CA",
    "sg:tags":[
        "product",
        "power",
        "mfg",
        "supply",
        "custom",
        "equipment",
        "electronic"
    ],
    "wof:name":"K D K Electronics Inc",
    "wof:placetype":"venue"
},
  "geometry": {"coordinates":[-122.045447,37.242198],"type":"Point"}
}