{
  "type": "Feature",
  "properties": {
    "iso:country":"US",
    "sg:address":"585 E Colorado Blvd",
    "sg:city":"Pasadena",
    "sg:classifiers":[
        {
            "category":"Organizations",
            "subcategory":"Religious Organization",
            "type":"Services"
        }
    ],
    "sg:phone":"+1 626 397 9004",
    "sg:postcode":"91101",
    "sg:province":"CA",
    "wof:name":"San Francisco Thoelogical Seminary",
    "wof:placetype":"venue"
},
  "geometry": {"coordinates":[-118.138381,34.146007],"type":"Point"}
}