{
  "type": "Feature",
  "properties": {
    "iso:country":"US",
    "sg:address":"454 E Alisal St",
    "sg:city":"Salinas",
    "sg:classifiers":[
        {
            "category":"Retail",
            "subcategory":"Repair Shop",
            "type":"Services"
        }
    ],
    "sg:phone":"+1 831 753 1281",
    "sg:postcode":"93905",
    "sg:province":"CA",
    "sg:tags":[
        "jewelry"
    ],
    "wof:name":"Reparacion De Jollas MGE",
    "wof:placetype":"venue"
},
  "geometry": {"coordinates":[-121.638746,36.673977],"type":"Point"}
}