{
  "type": "Feature",
  "properties": {
    "iso:country":"US",
    "sg:address":"7625 Rosecrans Ave",
    "sg:city":"Paramount",
    "sg:classifiers":[
        {
            "category":"Building & Trades",
            "subcategory":"Construction",
            "type":"Services"
        }
    ],
    "sg:phone":"+1 562 408 2031",
    "sg:postcode":"90723",
    "sg:province":"CA",
    "sg:tags":[
        "planning",
        "remodeling",
        "kitchen"
    ],
    "wof:name":"Simply Kitchen",
    "wof:placetype":"venue"
},
  "geometry": {"coordinates":[-118.166298,33.903722],"type":"Point"}
}