{
  "type": "Feature",
  "properties": {
    "iso:country":"US",
    "sg:address":"10910 Olson Dr",
    "sg:city":"Rancho Cordova",
    "sg:classifiers":[
        {
            "category":"Home & Garden",
            "subcategory":"Furniture",
            "type":"Retail Goods"
        }
    ],
    "sg:phone":"+1 916 852 2390",
    "sg:postcode":"95670",
    "sg:province":"CA",
    "wof:name":"Bauer Leather Galleries",
    "wof:placetype":"venue"
},
  "geometry": {"coordinates":[-121.281925,38.595499],"type":"Point"}
}