{
  "type": "Feature",
  "properties": {
    "iso:country":"US",
    "sg:address":"1360 Great Mall Dr",
    "sg:city":"Milpitas",
    "sg:classifiers":[
        {
            "category":"Shopping",
            "subcategory":"Department Store",
            "type":"Retail Goods"
        }
    ],
    "sg:phone":"+1 408 934 1821",
    "sg:postcode":"95035",
    "sg:province":"CA",
    "sg:website":"www.Marshallsonline.com",
    "wof:name":"Marshalls Department Store",
    "wof:placetype":"venue"
},
  "geometry": {"coordinates":[-121.900002,37.4189],"type":"Point"}
}