{
  "type": "Feature",
  "properties": {
    "iso:country":"US",
    "sg:address":"4400 Pacific Blvd",
    "sg:city":"Los Angeles",
    "sg:classifiers":[
        {
            "category":"Wholesale",
            "subcategory":"Non-durable Goods",
            "type":"Manufacturing & Wholesale Goods"
        }
    ],
    "sg:phone":"+1 323 263 3500",
    "sg:postcode":"90058",
    "sg:province":"CA",
    "wof:name":"Belair Distributing Company",
    "wof:placetype":"venue"
},
  "geometry": {"coordinates":[-118.227918,34.003945],"type":"Point"}
}