{
  "type": "Feature",
  "properties": {
    "addr:full":"227 Kelly Ave Half Moon Bay CA 94019",
    "addr:housenumber":"227",
    "addr:postcode":"94019",
    "addr:street":"Kelly Ave",
    "iso:country":"US",
    "sg:address":"227 Kelly Ave",
    "sg:city":"Half Moon Bay",
    "sg:classifiers":[
        {
            "category":"Food & Beverages",
            "subcategory":"Fruits & Vegetables",
            "type":"Retail Goods"
        }
    ],
    "sg:phone":"+1 650 726 9461",
    "sg:postcode":"94019",
    "sg:province":"CA",
    "wof:name":"Andreotti Family Farm",
    "wof:placetype":"venue"
},
  "geometry": {"coordinates":[-122.443215,37.465061],"type":"Point"}
}