{
  "type": "Feature",
  "properties": {
    "iso:country":"US",
    "sg:address":"1795 El Camino Real",
    "sg:city":"Millbrae",
    "sg:classifiers":[
        {
            "category":"Home & Garden",
            "subcategory":"Home Furnishings",
            "type":"Retail Goods"
        }
    ],
    "sg:phone":"+1 650 952 6323",
    "sg:postcode":"94030",
    "sg:province":"CA",
    "sg:tags":[
        "bath",
        "kitchen"
    ],
    "sg:website":"www.kbcabinets.com",
    "wof:name":"Kitchens, Baths & Cabinets",
    "wof:placetype":"venue"
},
  "geometry": {"coordinates":[-122.40632100000001,37.614723],"type":"Point"}
}