{
  "type": "Feature",
  "properties": {
    "addr:full":"4159 Margie Way Riverside CA 92509",
    "addr:housenumber":"4159",
    "addr:postcode":"92509",
    "addr:street":"Margie Way",
    "iso:country":"US",
    "sg:address":"4159 Margie Way",
    "sg:city":"Riverside",
    "sg:classifiers":[
        {
            "category":"Professional",
            "subcategory":"Advertising",
            "type":"Services"
        }
    ],
    "sg:phone":"+1 909 851 2159",
    "sg:postcode":"92509",
    "sg:province":"CA",
    "sg:tags":[
        "promotion",
        "sale"
    ],
    "wof:name":"Piluso Marketing",
    "wof:placetype":"venue"
},
  "geometry": {"coordinates":[-117.436317,34.000297],"type":"Point"}
}