{
  "type": "Feature",
  "properties": {
    "iso:country":"US",
    "sg:address":"5349 Shirley J Ln",
    "sg:city":"Wrightwood",
    "sg:classifiers":[
        {
            "category":"Restaurant",
            "type":"Food & Drink"
        }
    ],
    "sg:phone":"+1 760 249 5418",
    "sg:postcode":"92397",
    "sg:province":"CA",
    "wof:name":"Mc Donald's",
    "wof:placetype":"venue"
},
  "geometry": {"coordinates":[-117.620649,34.348791],"type":"Point"}
}