{
  "type": "Feature",
  "properties": {
    "iso:country":"US",
    "sg:address":"4783 W 133rd St",
    "sg:city":"Hawthorne",
    "sg:classifiers":[
        {
            "category":"Professional",
            "subcategory":"Business Services",
            "type":"Services"
        }
    ],
    "sg:phone":"+1 310 978 0893",
    "sg:postcode":"90250",
    "sg:province":"CA",
    "sg:tags":[
        "information",
        "referral"
    ],
    "wof:name":"Media Enterprises",
    "wof:placetype":"venue"
},
  "geometry": {"coordinates":[-118.360692,33.911722],"type":"Point"}
}