{
  "type": "Feature",
  "properties": {
    "addr:full":"28861 Via de Luna Laguna Niguel CA 92677",
    "addr:housenumber":"28861",
    "addr:postcode":"92677",
    "addr:street":"Via De Luna",
    "iso:country":"US",
    "sg:address":"28861 Via de Luna",
    "sg:city":"Laguna Niguel",
    "sg:classifiers":[
        {
            "category":"Wholesale",
            "subcategory":"Drugs",
            "type":"Manufacturing & Wholesale Goods"
        }
    ],
    "sg:phone":"+1 949 831 2093",
    "sg:postcode":"92677",
    "sg:province":"CA",
    "sg:tags":[
        "cosmetic"
    ],
    "wof:name":"Eurocare Products USA",
    "wof:placetype":"venue"
},
  "geometry": {"coordinates":[-117.69776299999999,33.544017],"type":"Point"}
}