{
  "type": "Feature",
  "properties": {
    "addr:full":"366 Golden Grove Ct Simi Valley CA 93065",
    "addr:housenumber":"366",
    "addr:postcode":"93065",
    "addr:street":"Golden Grove Ct",
    "iso:country":"US",
    "sg:address":"366 Golden Grove Ct",
    "sg:city":"Simi Valley",
    "sg:classifiers":[
        {
            "category":"Social Services",
            "type":"Services"
        }
    ],
    "sg:phone":"+1 805 522 9207",
    "sg:postcode":"93065",
    "sg:province":"CA",
    "sg:tags":[
        "crisis",
        "intervention"
    ],
    "sg:website":"www.wren.net",
    "wof:name":"Express Care",
    "wof:placetype":"venue"
},
  "geometry": {"coordinates":[-118.806207,34.247316],"type":"Point"}
}