{
  "type": "Feature",
  "properties": {
    "addr:full":"1606 Soquel Ave Santa Cruz CA 95062",
    "addr:housenumber":"1606",
    "addr:postcode":"95062",
    "addr:street":"Soquel Ave",
    "iso:country":"US",
    "sg:address":"1606 Soquel Ave",
    "sg:city":"Santa Cruz",
    "sg:classifiers":[
        {
            "category":"Building & Trades",
            "subcategory":"Landscaping Services",
            "type":"Services"
        }
    ],
    "sg:phone":"+1 831 454 0824",
    "sg:postcode":"95062",
    "sg:province":"CA",
    "sg:tags":[
        "landscape"
    ],
    "wof:name":"Clean Up Hauling Landscape",
    "wof:placetype":"venue"
},
  "geometry": {"coordinates":[-122.00302600000001,36.981394],"type":"Point"}
}