{
  "type": "Feature",
  "properties": {
    "addr:full":"1025 Tanklage Rd San Carlos CA 94070",
    "addr:housenumber":"1025",
    "addr:postcode":"94070",
    "addr:street":"Tanklage Rd",
    "iso:country":"US",
    "sg:address":"1025 Tanklage Rd",
    "sg:city":"San Carlos",
    "sg:classifiers":[
        {
            "category":"Building & Trades",
            "subcategory":"Construction",
            "type":"Services"
        }
    ],
    "sg:phone":"+1 650 591 7153",
    "sg:postcode":"94070",
    "sg:province":"CA",
    "sg:tags":[
        "contractor"
    ],
    "wof:name":"Tanklage Construction Co",
    "wof:placetype":"venue"
},
  "geometry": {"coordinates":[-122.25362199999999,37.507636],"type":"Point"}
}