{
  "type": "Feature",
  "properties": {
    "iso:country":"US",
    "sg:address":"9645 Arrow Rte",
    "sg:city":"Rancho Cucamonga",
    "sg:classifiers":[
        {
            "category":"Professional",
            "subcategory":"Lawyer & Legal Services",
            "type":"Services"
        }
    ],
    "sg:phone":"+1 909 581 1881",
    "sg:postcode":"91730",
    "sg:province":"CA",
    "sg:tags":[
        "attorney"
    ],
    "wof:name":"Ademola M Okusanya Law Offices",
    "wof:placetype":"venue"
},
  "geometry": {"coordinates":[-117.595795,34.099248],"type":"Point"}
}