{
  "type": "Feature",
  "properties": {
    "iso:country":"US",
    "sg:address":"1909 Santa Monica Blvd",
    "sg:city":"Santa Monica",
    "sg:classifiers":[
        {
            "category":"Manufacturing",
            "subcategory":"Printing",
            "type":"Manufacturing & Wholesale Goods"
        }
    ],
    "sg:phone":"+1 310 829 3022",
    "sg:postcode":"90404",
    "sg:province":"CA",
    "sg:tags":[
        "printer"
    ],
    "wof:name":"Sir Speedy Printing Ctr",
    "wof:placetype":"venue"
},
  "geometry": {"coordinates":[-118.480585,34.028297],"type":"Point"}
}