{
  "type": "Feature",
  "properties": {
    "addr:full":"308 S San Marino Ave San Gabriel CA 91776",
    "addr:housenumber":"308",
    "addr:postcode":"91776",
    "addr:street":"S San Marino Ave",
    "iso:country":"US",
    "sg:address":"308 S San Marino Ave",
    "sg:city":"San Gabriel",
    "sg:classifiers":[
        {
            "category":"Retail",
            "subcategory":"Repair Shop",
            "type":"Services"
        }
    ],
    "sg:phone":"+1 626 287 5563",
    "sg:postcode":"91776",
    "sg:province":"CA",
    "sg:tags":[
        "equipment",
        "printing"
    ],
    "wof:name":"Inc Graphic Arts Machinery",
    "wof:placetype":"venue"
},
  "geometry": {"coordinates":[-118.100521,34.097981],"type":"Point"}
}