{
  "type": "Feature",
  "properties": {
    "addr:full":"4917 Bellflower Blvd Lakewood CA 90713",
    "addr:housenumber":"4917",
    "addr:postcode":"90713",
    "addr:street":"Bellflower Blvd",
    "iso:country":"US",
    "sg:address":"4917 Bellflower Blvd",
    "sg:city":"Lakewood",
    "sg:classifiers":[
        {
            "category":"Fast Food",
            "type":"Food & Drink"
        }
    ],
    "sg:phone":"+1 562 925 1983",
    "sg:postcode":"90713",
    "sg:province":"CA",
    "sg:website":"www.kfc.com",
    "wof:name":"Kentucky Fried Chicken",
    "wof:placetype":"venue"
},
  "geometry": {"coordinates":[-118.12553,33.847676],"type":"Point"}
}