{
  "type": "Feature",
  "properties": {
    "addr:full":"1236 E Edinger Ave Santa Ana CA 92707",
    "addr:housenumber":"1236",
    "addr:postcode":"92707",
    "addr:street":"E Edinger Ave",
    "iso:country":"US",
    "sg:address":"1236 E Edinger Ave",
    "sg:city":"Santa Ana",
    "sg:classifiers":[
        {
            "category":"Shopping",
            "subcategory":"Mobile Phones",
            "type":"Retail Goods"
        }
    ],
    "sg:phone":"+1 714 547 3118",
    "sg:postcode":"92707",
    "sg:province":"CA",
    "wof:name":"Top Cellular",
    "wof:placetype":"venue"
},
  "geometry": {"coordinates":[-117.854833,33.726622],"type":"Point"}
}