{
  "type": "Feature",
  "properties": {
    "iso:country":"US",
    "sg:address":"990 Burnett Ave",
    "sg:city":"San Francisco",
    "sg:classifiers":[
        {
            "category":"Wholesale",
            "subcategory":"Durable Goods & Equipment",
            "type":"Manufacturing & Wholesale Goods"
        }
    ],
    "sg:phone":"+1 415 826 9524",
    "sg:postcode":"94131",
    "sg:province":"CA",
    "sg:tags":[
        "scientific"
    ],
    "wof:name":"Stecca Associates",
    "wof:placetype":"venue"
},
  "geometry": {"coordinates":[-122.44479,37.747124],"type":"Point"}
}