{
  "type": "Feature",
  "properties": {
    "iso:country":"US",
    "sg:address":"104 6th St",
    "sg:city":"West Sacramento",
    "sg:classifiers":[
        {
            "category":"Utilities",
            "subcategory":"Telephone",
            "type":"Services"
        }
    ],
    "sg:phone":"+1 916 373 0505",
    "sg:postcode":"95605",
    "sg:province":"CA",
    "sg:tags":[
        "communication",
        "medical",
        "health",
        "market"
    ],
    "wof:name":"Major Communications",
    "wof:placetype":"venue"
},
  "geometry": {"coordinates":[-121.514,38.5919],"type":"Point"}
}