{
  "type": "Feature",
  "properties": {
    "iso:country":"US",
    "sg:address":"1776 Arnold Industrial Way",
    "sg:city":"Concord",
    "sg:classifiers":[
        {
            "category":"Professional",
            "subcategory":"Employment Agencies",
            "type":"Services"
        }
    ],
    "sg:phone":"+1 925 689 3636",
    "sg:postcode":"94520",
    "sg:province":"CA",
    "sg:tags":[
        "opportunity"
    ],
    "wof:name":"Labor Connection",
    "wof:placetype":"venue"
},
  "geometry": {"coordinates":[-122.050239,38.003171],"type":"Point"}
}