{
  "type": "Feature",
  "properties": {
    "addr:full":"9876 White River Cir Fountain Valley CA 92708",
    "addr:housenumber":"9876",
    "addr:postcode":"92708",
    "addr:street":"White River Cir",
    "iso:country":"US",
    "sg:address":"9876 White River Cir",
    "sg:city":"Fountain Valley",
    "sg:classifiers":[
        {
            "category":"Real Estate",
            "subcategory":"Real Estate Agent",
            "type":"Services"
        }
    ],
    "sg:phone":"+1 714 964 1616",
    "sg:postcode":"92708",
    "sg:province":"CA",
    "wof:name":"Pappas & Hipp Realtors",
    "wof:placetype":"venue"
},
  "geometry": {"coordinates":[-117.956001,33.6884],"type":"Point"}
}