{
  "type": "Feature",
  "properties": {
    "iso:country":"US",
    "sg:address":"122 E Ivy St",
    "sg:city":"Hanford",
    "sg:classifiers":[
        {
            "category":"Organizations",
            "subcategory":"Religious Organization",
            "type":"Services"
        }
    ],
    "sg:phone":"+1 559 584 3268",
    "sg:postcode":"93230",
    "sg:province":"CA",
    "sg:tags":[
        "church"
    ],
    "wof:name":"Church Of The Nazarene",
    "wof:placetype":"venue"
},
  "geometry": {"coordinates":[-119.64573,36.332228],"type":"Point"}
}