{
  "type": "Feature",
  "properties": {
    "addr:full":"14533 Langhill Dr Hacienda Heights CA 91745",
    "addr:housenumber":"14533",
    "addr:postcode":"91745",
    "addr:street":"Langhill Dr",
    "iso:country":"US",
    "sg:address":"14533 Langhill Dr",
    "sg:city":"Hacienda Heights",
    "sg:classifiers":[
        {
            "category":"Real Estate",
            "subcategory":"Real Estate Agent",
            "type":"Services"
        }
    ],
    "sg:phone":"+1 626 330 9627",
    "sg:postcode":"91745",
    "sg:province":"CA",
    "wof:name":"Bejarano Family Partnership",
    "wof:placetype":"venue"
},
  "geometry": {"coordinates":[-117.997235,34.009266],"type":"Point"}
}