{
  "type": "Feature",
  "properties": {
    "iso:country":"US",
    "sg:address":"701 Acacia Ave",
    "sg:city":"Ripon",
    "sg:classifiers":[
        {
            "category":"Shopping",
            "subcategory":"Hobbies, Toys, & Games",
            "type":"Retail Goods"
        }
    ],
    "sg:phone":"+1 209 599 5160",
    "sg:postcode":"95366",
    "sg:province":"CA",
    "wof:name":"Ripon R C Speedway and Hobbies",
    "wof:placetype":"venue"
},
  "geometry": {"coordinates":[-121.128537,37.744311],"type":"Point"}
}