{
  "type": "Feature",
  "properties": {
    "addr:full":"3300 Orcutt Rd Santa Maria CA 93455",
    "addr:housenumber":"3300",
    "addr:postcode":"93455",
    "addr:street":"Orcutt Rd",
    "iso:country":"US",
    "sg:address":"3300 Orcutt Rd",
    "sg:city":"Santa Maria",
    "sg:classifiers":[
        {
            "category":"Retail",
            "subcategory":"Self-service Laundry",
            "type":"Services"
        }
    ],
    "sg:phone":"+1 805 938 9896",
    "sg:postcode":"93455",
    "sg:province":"CA",
    "wof:name":"Soap Opera",
    "wof:placetype":"venue"
},
  "geometry": {"coordinates":[-120.43652899999999,34.899494],"type":"Point"}
}