{
  "type": "Feature",
  "properties": {
    "iso:country":"US",
    "sg:address":"1005 Coombs St",
    "sg:city":"Napa",
    "sg:classifiers":[
        {
            "category":"Professional",
            "subcategory":"Lawyer & Legal Services",
            "type":"Services"
        }
    ],
    "sg:phone":"+1 707 226 9928",
    "sg:postcode":"94559",
    "sg:province":"CA",
    "sg:tags":[
        "attorney"
    ],
    "wof:name":"Lewis & Blevans LLP",
    "wof:placetype":"venue"
},
  "geometry": {"coordinates":[-122.288048,38.299805],"type":"Point"}
}