{
  "type": "Feature",
  "properties": {
    "addr:full":"34475 Date Palm Dr Cathedral City CA 92234",
    "addr:housenumber":"34475",
    "addr:postcode":"92234",
    "addr:street":"Date Palm Dr",
    "iso:country":"US",
    "sg:address":"34475 Date Palm Dr",
    "sg:city":"Cathedral City",
    "sg:classifiers":[
        {
            "category":"Building & Trades",
            "subcategory":"Equipment Rental",
            "type":"Services"
        }
    ],
    "sg:phone":"+1 760 324 5245",
    "sg:postcode":"92234",
    "sg:province":"CA",
    "sg:tags":[
        "yard"
    ],
    "wof:name":"Rent-A-Center",
    "wof:placetype":"venue"
},
  "geometry": {"coordinates":[-116.458119,33.801265],"type":"Point"}
}