{
  "type": "Feature",
  "properties": {
    "iso:country":"US",
    "sg:address":"660 Market St Ste 206",
    "sg:city":"San Francisco",
    "sg:classifiers":[
        {
            "category":"Personal",
            "subcategory":"Beauty Salon",
            "type":"Services"
        }
    ],
    "sg:phone":"+1 415 336 0947",
    "sg:postcode":"94104",
    "sg:province":"CA",
    "sg:tags":[
        "hair"
    ],
    "sg:website":"www.studioghb.com",
    "wof:name":"Gib Bolton - Studio GHB",
    "wof:placetype":"venue"
},
  "geometry": {"coordinates":[-122.40295,37.788457],"type":"Point"}
}