{
  "type": "Feature",
  "properties": {
    "addr:full":"403 E Bougainvillea Ln Glendora CA 91741",
    "addr:housenumber":"403",
    "addr:postcode":"91741",
    "addr:street":"E Bougainvillea Ln",
    "iso:country":"US",
    "sg:address":"403 E Bougainvillea Ln",
    "sg:city":"Glendora",
    "sg:classifiers":[
        {
            "category":"Shopping",
            "subcategory":"Used Merchandise",
            "type":"Retail Goods"
        }
    ],
    "sg:phone":"+1 909 620 1229",
    "sg:postcode":"91741",
    "sg:province":"CA",
    "wof:name":"Nothing Common Antiques",
    "wof:placetype":"venue"
},
  "geometry": {"coordinates":[-117.861446,34.140481],"type":"Point"}
}