{
  "type": "Feature",
  "properties": {
    "addr:full":"10960 Carrisa Hwy Santa Margarita CA 93453",
    "addr:housenumber":"10960",
    "addr:postcode":"93453",
    "addr:street":"Carrisa Hwy",
    "iso:country":"US",
    "sg:address":"10960 Carrisa Hwy",
    "sg:city":"Santa Margarita",
    "sg:classifiers":[
        {
            "category":"Wholesale",
            "subcategory":"Farm Supplies",
            "type":"Manufacturing & Wholesale Goods"
        }
    ],
    "sg:phone":"+1 805 475 2422",
    "sg:postcode":"93453",
    "sg:province":"CA",
    "wof:name":"Carrisa Country Store",
    "wof:placetype":"venue"
},
  "geometry": {"coordinates":[-119.986968,35.351321],"type":"Point"}
}