{
  "type": "Feature",
  "properties": {
    "addr:full":"7775 Healdsburg Ave Sebastopol CA 95472",
    "addr:housenumber":"7775",
    "addr:postcode":"95472",
    "addr:street":"Healdsburg Ave",
    "iso:country":"US",
    "sg:address":"7775 Healdsburg Ave",
    "sg:city":"Sebastopol",
    "sg:classifiers":[
        {
            "category":"Professional",
            "subcategory":"Advertising",
            "type":"Services"
        }
    ],
    "sg:phone":"+1 707 829 6070",
    "sg:postcode":"95472",
    "sg:province":"CA",
    "sg:website":"www.pdg1.com",
    "wof:name":"Performance Design Group",
    "wof:placetype":"venue"
},
  "geometry": {"coordinates":[-122.83528200000001,38.405197],"type":"Point"}
}