{
  "type": "Feature",
  "properties": {
    "iso:country":"US",
    "sg:address":"18543 Devonshire St",
    "sg:city":"Northridge",
    "sg:classifiers":[
        {
            "category":"Manufacturing",
            "subcategory":"Printing",
            "type":"Manufacturing & Wholesale Goods"
        }
    ],
    "sg:phone":"+1 818 831 0649",
    "sg:postcode":"91324",
    "sg:province":"CA",
    "sg:tags":[
        "publisher"
    ],
    "sg:website":"www.vpg.net",
    "wof:name":"Valentine Publishing Group",
    "wof:placetype":"venue"
},
  "geometry": {"coordinates":[-118.540363,34.25734],"type":"Point"}
}