{
  "type": "Feature",
  "properties": {
    "addr:full":"19 N Aviador St Camarillo CA 93010",
    "addr:housenumber":"19",
    "addr:postcode":"93010",
    "addr:street":"N Aviador St",
    "iso:country":"US",
    "sg:address":"19 N Aviador St",
    "sg:city":"Camarillo",
    "sg:classifiers":[
        {
            "category":"Home & Garden",
            "subcategory":"Building Materials",
            "type":"Retail Goods"
        }
    ],
    "sg:phone":"+1 805 987 3877",
    "sg:postcode":"93010",
    "sg:province":"CA",
    "sg:tags":[
        "hardwood"
    ],
    "wof:name":"H & M Hardwoods & Moldings",
    "wof:placetype":"venue"
},
  "geometry": {"coordinates":[-119.09404000000001,34.218423],"type":"Point"}
}