{
  "type": "Feature",
  "properties": {
    "addr:full":"1030 Donlon Ave Oxnard CA 93030",
    "addr:postcode":"1030;93030",
    "addr:street":"Donlon Ave",
    "iso:country":"US",
    "sg:address":"1030 Donlon Ave",
    "sg:city":"Oxnard",
    "sg:classifiers":[
        {
            "category":"Retail",
            "subcategory":"Auto Repair",
            "type":"Services"
        }
    ],
    "sg:phone":"+1 805 486 8780",
    "sg:postcode":"93030",
    "sg:province":"CA",
    "sg:tags":[
        "body",
        "automobile",
        "painting"
    ],
    "wof:name":"Jazz Auto Body",
    "wof:placetype":"venue"
},
  "geometry": {"coordinates":[-119.176568,34.191525],"type":"Point"}
}