{
  "type": "Feature",
  "properties": {
    "iso:country":"US",
    "sg:address":"340 N Camden Dr",
    "sg:city":"Beverly Hills",
    "sg:classifiers":[
        {
            "category":"Bus Charters",
            "type":"Transportation"
        }
    ],
    "sg:phone":"+1 323 233 1600",
    "sg:postcode":"90210",
    "sg:province":"CA",
    "sg:tags":[
        "local"
    ],
    "wof:name":"Super Scenic Tours",
    "wof:placetype":"venue"
},
  "geometry": {"coordinates":[-118.40342200000001,34.067974],"type":"Point"}
}