{
  "type": "Feature",
  "properties": {
    "iso:country":"US",
    "sg:address":"415 N Escondido Blvd",
    "sg:city":"Escondido",
    "sg:classifiers":[
        {
            "category":"Shopping",
            "subcategory":"Books",
            "type":"Retail Goods"
        }
    ],
    "sg:phone":"+1 619 203 4323",
    "sg:postcode":"92025",
    "sg:province":"CA",
    "sg:tags":[
        "dealers-used",
        "rare"
    ],
    "wof:name":"Crown Books Liquidation Ctr",
    "wof:placetype":"venue"
},
  "geometry": {"coordinates":[-117.086521,33.123585],"type":"Point"}
}