{
  "type": "Feature",
  "properties": {
    "addr:full":"6817 Elwood Rd Sanger CA 93657",
    "addr:housenumber":"6817",
    "addr:postcode":"ca 93657",
    "addr:street":"Elwood Rd",
    "iso:country":"US",
    "sg:address":"6817 Elwood Rd",
    "sg:city":"Sanger",
    "sg:classifiers":[
        {
            "category":"Government",
            "subcategory":"Fire Station",
            "type":"Public Place"
        }
    ],
    "sg:phone":"+1 559 787 3067",
    "sg:postcode":"93657",
    "sg:province":"CA",
    "sg:tags":[
        "department"
    ],
    "wof:name":"Wonder Valley Fire Station",
    "wof:placetype":"venue"
},
  "geometry": {"coordinates":[-119.310906,36.790744],"type":"Point"}
}