{
  "type": "Feature",
  "properties": {
    "addr:full":"26234 S Union Rd Manteca CA 95337",
    "addr:housenumber":"26234",
    "addr:postcode":"95337",
    "addr:street":"S Union Rd",
    "iso:country":"US",
    "sg:address":"26234 S Union Rd",
    "sg:city":"Manteca",
    "sg:classifiers":[
        {
            "category":"Farming",
            "subcategory":"Livestock Farm",
            "type":"Manufacturing & Wholesale Goods"
        }
    ],
    "sg:phone":"+1 209 823 4854",
    "sg:postcode":"95337",
    "sg:province":"CA",
    "sg:tags":[
        "beef",
        "feedlot",
        "cattle"
    ],
    "wof:name":"Double M Ranch",
    "wof:placetype":"venue"
},
  "geometry": {"coordinates":[-121.23351599999999,37.713732],"type":"Point"}
}