{
  "type": "Feature",
  "properties": {
    "iso:country":"US",
    "sg:address":"26640 Western Ave",
    "sg:city":"Harbor City",
    "sg:classifiers":[
        {
            "category":"Shopping",
            "subcategory":"Bicycles & Sporting Goods",
            "type":"Retail Goods"
        }
    ],
    "sg:phone":"+1 310 325 2700",
    "sg:postcode":"90710",
    "sg:province":"CA",
    "sg:tags":[
        "equipment",
        "exercise"
    ],
    "wof:name":"Fitness Guys",
    "wof:placetype":"venue"
},
  "geometry": {"coordinates":[-118.309691,33.78037],"type":"Point"}
}