{
  "type": "Feature",
  "properties": {
    "iso:country":"US",
    "sg:address":"1761 Bridge Creek Rd",
    "sg:city":"Scotts Valley",
    "sg:classifiers":[
        {
            "category":"Professional",
            "subcategory":"Management & Consulting",
            "type":"Services"
        }
    ],
    "sg:phone":"+1 831 335 4802",
    "sg:postcode":"95066",
    "sg:province":"CA",
    "sg:tags":[
        "consultant",
        "energy",
        "conservation"
    ],
    "wof:name":"Baer Title 24 Energy Clcltns",
    "wof:placetype":"venue"
},
  "geometry": {"coordinates":[-122.032141,37.072992],"type":"Point"}
}