{
  "type": "Feature",
  "properties": {
    "addr:full":"6433 Topanga Canyon Blvd Ste 811 Canoga Park CA 91303",
    "addr:housenumber":"6433",
    "addr:postcode":"91303",
    "addr:street":"Topanga Canyon Blvd Ste 811",
    "iso:country":"US",
    "sg:address":"6433 Topanga Canyon Blvd Ste 811",
    "sg:city":"Canoga Park",
    "sg:classifiers":[
        {
            "category":"Building & Trades",
            "subcategory":"Electrical",
            "type":"Services"
        }
    ],
    "sg:phone":"+1 323 257 2724",
    "sg:postcode":"91303",
    "sg:province":"CA",
    "sg:tags":[
        "electrician"
    ],
    "sg:website":"www.aperfectconnection.com/home",
    "wof:name":"A Perfect Connection, Inc.",
    "wof:placetype":"venue"
},
  "geometry": {"coordinates":[-118.60625899999999,34.187609],"type":"Point"}
}