{
  "type": "Feature",
  "properties": {
    "iso:country":"US",
    "sg:address":"1446 Foothill Blvd",
    "sg:city":"La Canada Flintridge",
    "sg:classifiers":[
        {
            "category":"Restaurant",
            "type":"Food & Drink"
        }
    ],
    "sg:phone":"+1 818 790 8950",
    "sg:postcode":"91011",
    "sg:province":"CA",
    "sg:tags":[
        "mexican"
    ],
    "wof:name":"Lupe's Place",
    "wof:placetype":"venue"
},
  "geometry": {"coordinates":[-118.20680299999999,34.207442],"type":"Point"}
}