{
  "type": "Feature",
  "properties": {
    "addr:full":"16070 Regency Ranch Rd Riverside CA 92504",
    "addr:housenumber":"16070",
    "addr:postcode":"92504",
    "addr:street":"Regency Ranch Rd",
    "iso:country":"US",
    "sg:address":"16070 Regency Ranch Rd",
    "sg:city":"Riverside",
    "sg:classifiers":[
        {
            "category":"Building & Trades",
            "subcategory":"Landscaping Services",
            "type":"Services"
        }
    ],
    "sg:phone":"+1 951 776 9487",
    "sg:postcode":"92504",
    "sg:province":"CA",
    "sg:tags":[
        "landscape"
    ],
    "wof:name":"Sam Landscape",
    "wof:placetype":"venue"
},
  "geometry": {"coordinates":[-117.399784,33.885299],"type":"Point"}
}