{
  "type": "Feature",
  "properties": {
    "addr:full":"2525 8th Street Berkeley CA 94710",
    "addr:housenumber":"2525",
    "addr:postcode":"94710",
    "addr:street":"8Th Street",
    "iso:country":"US",
    "sg:address":"2525 8th Street",
    "sg:city":"Berkeley",
    "sg:classifiers":[
        {
            "category":"Arts & Performance",
            "subcategory":"Arts Center",
            "type":"Entertainment"
        },
        {
            "category":"Sports & Exercise",
            "subcategory":"Gym",
            "type":"Entertainment"
        }
    ],
    "sg:phone":"+1 510 848 4878",
    "sg:postcode":"94710",
    "sg:province":"CA",
    "sg:tags":[
        "trainer",
        "performing"
    ],
    "sg:website":"www.berkeleymovingarts.com",
    "wof:name":"Berkeley Moving Arts",
    "wof:placetype":"venue"
},
  "geometry": {"coordinates":[-122.297997,37.872501],"type":"Point"}
}