{
  "type": "Feature",
  "properties": {
    "iso:country":"US",
    "sg:address":"6778 Julie Ln",
    "sg:city":"West Hills",
    "sg:classifiers":[
        {
            "category":"Wholesale",
            "subcategory":"Electrical",
            "type":"Manufacturing & Wholesale Goods"
        }
    ],
    "sg:phone":"+1 818 719 9287",
    "sg:postcode":"91307",
    "sg:province":"CA",
    "sg:tags":[
        "equipment",
        "system"
    ],
    "sg:website":"www.its-educational.com",
    "wof:name":"International Teaching Systems",
    "wof:placetype":"venue"
},
  "geometry": {"coordinates":[-118.659004,34.189751],"type":"Point"}
}