{
  "type": "Feature",
  "properties": {
    "iso:country":"US",
    "sg:address":"920 Darrell St",
    "sg:city":"Costa Mesa",
    "sg:classifiers":[
        {
            "category":"Building & Trades",
            "subcategory":"Cleaning & Sanitation",
            "type":"Services"
        }
    ],
    "sg:phone":"+1 949 650 2239",
    "sg:postcode":"92627",
    "sg:province":"CA",
    "sg:tags":[
        "janitor"
    ],
    "wof:name":"Max Clean",
    "wof:placetype":"venue"
},
  "geometry": {"coordinates":[-117.938367,33.6568],"type":"Point"}
}