{
  "type": "Feature",
  "properties": {
    "iso:country":"US",
    "sg:address":"6920 Fair Oaks Blvd",
    "sg:city":"Carmichael",
    "sg:classifiers":[
        {
            "category":"Professional",
            "subcategory":"Management & Consulting",
            "type":"Services"
        }
    ],
    "sg:phone":"+1 916 489 4271",
    "sg:postcode":"95608",
    "sg:province":"CA",
    "sg:tags":[
        "business"
    ],
    "wof:name":"Alisto Engineering Group Inc",
    "wof:placetype":"venue"
},
  "geometry": {"coordinates":[-121.328197,38.62842],"type":"Point"}
}