{
  "type": "Feature",
  "properties": {
    "iso:country":"US",
    "sg:address":"14427 S Western Ave",
    "sg:city":"Gardena",
    "sg:classifiers":[
        {
            "category":"Retail",
            "subcategory":"Auto Repair",
            "type":"Services"
        }
    ],
    "sg:phone":"+1 310 768 8760",
    "sg:postcode":"90249",
    "sg:province":"CA",
    "sg:tags":[
        "transmission"
    ],
    "wof:name":"Any Transmissions",
    "wof:placetype":"venue"
},
  "geometry": {"coordinates":[-118.30920500000001,33.900345],"type":"Point"}
}