{
  "type": "Feature",
  "properties": {
    "iso:country":"US",
    "sg:address":"16545 Gault St",
    "sg:city":"Van Nuys",
    "sg:classifiers":[
        {
            "category":"Building & Trades",
            "subcategory":"Plumbing",
            "type":"Services"
        }
    ],
    "sg:phone":"+1 818 901 0950",
    "sg:postcode":"91406",
    "sg:province":"CA",
    "sg:tags":[
        "plumbing",
        "contractor"
    ],
    "wof:name":"Oscar's Plumbing & Rooter Svc",
    "wof:placetype":"venue"
},
  "geometry": {"coordinates":[-118.494168,34.199412],"type":"Point"}
}