{
  "type": "Feature",
  "properties": {
    "addr:full":"2668 Monterey Hwy San Jose CA 95111",
    "addr:housenumber":"2668",
    "addr:postcode":"95111",
    "addr:street":"Monterey Hwy",
    "iso:country":"US",
    "sg:address":"2668 Monterey Hwy",
    "sg:city":"San Jose",
    "sg:classifiers":[
        {
            "category":"Personal",
            "subcategory":"Beauty Salon",
            "type":"Services"
        }
    ],
    "sg:phone":"+1 408 299 0814",
    "sg:postcode":"95111",
    "sg:province":"CA",
    "sg:tags":[
        "hair"
    ],
    "wof:name":"Melena's Barber Shop & Beauty Salon",
    "wof:placetype":"venue"
},
  "geometry": {"coordinates":[-121.853155,37.295843],"type":"Point"}
}