{
  "type": "Feature",
  "properties": {
    "addr:full":"1550 Bryant Street Suite 750 San Francisco CA 94107",
    "addr:housenumber":"1550",
    "addr:postcode":"94107",
    "addr:street":"Bryant Street Suite 750",
    "iso:country":"US",
    "sg:address":"1550 Bryant Street Suite 750",
    "sg:city":"San Francisco",
    "sg:classifiers":[
        {
            "category":"Professional",
            "subcategory":"Computer Services",
            "type":"Services"
        }
    ],
    "sg:phone":"+1 415 325 4905",
    "sg:postcode":"94107",
    "sg:province":"CA",
    "sg:tags":[
        "user-experience",
        "ui-design",
        "usability",
        "interaction-design",
        "information-architecture",
        "ux-design",
        "ux-strategy"
    ],
    "sg:website":"http://www.uevision.com",
    "wof:name":"UEVision",
    "wof:placetype":"venue"
},
  "geometry": {"coordinates":[-122.40363600000001,37.775161],"type":"Point"}
}