{
  "type": "Feature",
  "properties": {
    "addr:full":"10109 S Vermont Ave Los Angeles CA 90044",
    "addr:housenumber":"10109",
    "addr:postcode":"90044",
    "addr:street":"S Vermont Ave",
    "iso:country":"US",
    "sg:address":"10109 S Vermont Ave",
    "sg:city":"Los Angeles",
    "sg:classifiers":[
        {
            "category":"Organizations",
            "subcategory":"Religious Organization",
            "type":"Services"
        }
    ],
    "sg:phone":"+1 323 779 1051",
    "sg:postcode":"90044",
    "sg:province":"CA",
    "sg:tags":[
        "church"
    ],
    "wof:name":"St Michael's Redeeming United",
    "wof:placetype":"venue"
},
  "geometry": {"coordinates":[-118.2919,33.944156],"type":"Point"}
}