{
  "type": "Feature",
  "properties": {
    "addr:full":"10939 Victory Blvd North Hollywood CA 91606",
    "addr:housenumber":"10939",
    "addr:postcode":"91606",
    "addr:street":"Victory Blvd",
    "iso:country":"US",
    "sg:address":"10939 Victory Blvd",
    "sg:city":"North Hollywood",
    "sg:classifiers":[
        {
            "category":"Food & Beverages",
            "subcategory":"Liquor & Beverages",
            "type":"Retail Goods"
        }
    ],
    "sg:phone":"+1 818 508 5022",
    "sg:postcode":"91606",
    "sg:province":"CA",
    "sg:tags":[
        "beer",
        "spirit",
        "wine"
    ],
    "wof:name":"Viginia News Stand & Cigarettes",
    "wof:placetype":"venue"
},
  "geometry": {"coordinates":[-118.36934100000001,34.186819],"type":"Point"}
}