{
  "type": "Feature",
  "properties": {
    "addr:full":"13837 Ventura Blvd Sherman Oaks CA 91423",
    "addr:housenumber":"13837",
    "addr:postcode":"91423",
    "addr:street":"Ventura Blvd",
    "iso:country":"US",
    "sg:address":"13837 Ventura Blvd",
    "sg:city":"Sherman Oaks",
    "sg:classifiers":[
        {
            "category":"Professional",
            "subcategory":"Advertising",
            "type":"Services"
        }
    ],
    "sg:phone":"+1 818 205 1150",
    "sg:postcode":"91423",
    "sg:province":"CA",
    "sg:tags":[
        "distribution"
    ],
    "wof:name":"Euro Line Distribution",
    "wof:placetype":"venue"
},
  "geometry": {"coordinates":[-118.434558,34.148638],"type":"Point"}
}