{
  "type": "Feature",
  "properties": {
    "iso:country":"US",
    "sg:address":"10790 Coloma Road",
    "sg:city":"Rancho Cordova",
    "sg:classifiers":[
        {
            "category":"Real Estate",
            "subcategory":"Real Estate Operator",
            "type":"Services"
        }
    ],
    "sg:phone":"+1 916 858 1312",
    "sg:postcode":"95670",
    "sg:province":"CA",
    "sg:tags":[
        "apartment"
    ],
    "wof:name":"Mar Vista Apartment Complex",
    "wof:placetype":"venue"
},
  "geometry": {"coordinates":[-121.285539,38.614927],"type":"Point"}
}