{
  "type": "Feature",
  "properties": {
    "iso:country":"US",
    "sg:address":"2465 Foothill Blvd",
    "sg:city":"Oakland",
    "sg:classifiers":[
        {
            "category":"Manufacturing",
            "subcategory":"Buildings",
            "type":"Manufacturing & Wholesale Goods"
        },
        {
            "category":"Building & Trades",
            "subcategory":"Construction",
            "type":"Services"
        }
    ],
    "sg:phone":"+1 510 698 4239",
    "sg:postcode":"94601",
    "sg:province":"CA",
    "sg:tags":[
        "home",
        "builder",
        "contractor"
    ],
    "wof:name":"Abc",
    "wof:placetype":"venue"
},
  "geometry": {"coordinates":[-122.231302,37.784721],"type":"Point"}
}