{
  "type": "Feature",
  "properties": {
    "iso:country":"US",
    "sg:address":"1635 Centinela Ave",
    "sg:city":"Inglewood",
    "sg:classifiers":[
        {
            "category":"Retail",
            "subcategory":"Auto Repair",
            "type":"Services"
        }
    ],
    "sg:phone":"+1 310 348 8714",
    "sg:postcode":"90302",
    "sg:province":"CA",
    "sg:tags":[
        "automobile",
        "electric"
    ],
    "wof:name":"Soza's Auto Electric & Repair",
    "wof:placetype":"venue"
},
  "geometry": {"coordinates":[-118.36805200000001,33.977044],"type":"Point"}
}