{
  "type": "Feature",
  "properties": {
    "addr:full":"102 S Main St Cloverdale CA 95425",
    "addr:housenumber":"102",
    "addr:postcode":"95425",
    "addr:street":"S Main St",
    "iso:country":"US",
    "sg:address":"102 S Main St",
    "sg:city":"Cloverdale",
    "sg:classifiers":[
        {
            "category":"Health Services",
            "subcategory":"Doctor",
            "type":"Services"
        }
    ],
    "sg:phone":"+1 707 894 2464",
    "sg:postcode":"95425",
    "sg:province":"CA",
    "sg:tags":[
        "dentist"
    ],
    "wof:name":"James D Wood DDS",
    "wof:placetype":"venue"
},
  "geometry": {"coordinates":[-123.01569499999999,38.80576],"type":"Point"}
}