{
  "type": "Feature",
  "properties": {
    "addr:full":"1678 Broadway St Vallejo CA 94590",
    "addr:housenumber":"1678",
    "addr:postcode":"94590",
    "addr:street":"Broadway St",
    "iso:country":"US",
    "sg:address":"1678 Broadway St",
    "sg:city":"Vallejo",
    "sg:classifiers":[
        {
            "category":"Food & Beverages",
            "subcategory":"Meat & Fish",
            "type":"Retail Goods"
        }
    ],
    "sg:phone":"+1 707 643 3803",
    "sg:postcode":"94590",
    "sg:province":"CA",
    "wof:name":"Huff's Quality Meats",
    "wof:placetype":"venue"
},
  "geometry": {"coordinates":[-122.25147200000001,38.127763],"type":"Point"}
}