{
  "type": "Feature",
  "properties": {
    "iso:country":"US",
    "sg:address":"725 E Main St",
    "sg:city":"Santa Paula",
    "sg:classifiers":[
        {
            "category":"Social Services",
            "type":"Services"
        }
    ],
    "sg:phone":"+1 805 933 8450",
    "sg:postcode":"93060",
    "sg:province":"CA",
    "wof:name":"Family Planning Services",
    "wof:placetype":"venue"
},
  "geometry": {"coordinates":[-119.064959,34.352398],"type":"Point"}
}