{
  "type": "Feature",
  "properties": {
    "addr:full":"1220 H St Sacramento CA 95814",
    "addr:housenumber":"1220",
    "addr:postcode":"95814",
    "addr:street":"H St",
    "iso:country":"US",
    "sg:address":"1220 H St",
    "sg:city":"Sacramento",
    "sg:classifiers":[
        {
            "category":"Professional",
            "subcategory":"Lawyer & Legal Services",
            "type":"Services"
        }
    ],
    "sg:phone":"+1 916 441 5544",
    "sg:postcode":"95814",
    "sg:province":"CA",
    "sg:tags":[
        "attorney"
    ],
    "wof:name":"Solinsky & Assoc",
    "wof:placetype":"venue"
},
  "geometry": {"coordinates":[-121.48849,38.58136],"type":"Point"}
}