{
  "type": "Feature",
  "properties": {
    "iso:country":"US",
    "sg:address":"1851 Little Orchard St",
    "sg:city":"San Jose",
    "sg:classifiers":[
        {
            "category":"Manufacturing",
            "subcategory":"Printing",
            "type":"Manufacturing & Wholesale Goods"
        }
    ],
    "sg:phone":"+1 408 288 6886",
    "sg:postcode":"95125",
    "sg:province":"CA",
    "sg:tags":[
        "commercial"
    ],
    "wof:name":"Almaden Valley Printing Co Inc",
    "wof:placetype":"venue"
},
  "geometry": {"coordinates":[-121.87259899999999,37.306182],"type":"Point"}
}