{
  "type": "Feature",
  "properties": {
    "iso:country":"US",
    "sg:address":"833 E Denwall Dr",
    "sg:city":"Carson",
    "sg:classifiers":[
        {
            "category":"Professional",
            "subcategory":"Detective & Security Services",
            "type":"Services"
        }
    ],
    "sg:phone":"+1 310 538 1073",
    "sg:postcode":"90746",
    "sg:province":"CA",
    "sg:tags":[
        "information",
        "bureau"
    ],
    "wof:name":"Computer Tech Services",
    "wof:placetype":"venue"
},
  "geometry": {"coordinates":[-118.259758,33.847549],"type":"Point"}
}