{
  "type": "Feature",
  "properties": {
    "iso:country":"US",
    "sg:address":"1400 K St",
    "sg:city":"Modesto",
    "sg:classifiers":[
        {
            "category":"Professional",
            "type":"Services"
        }
    ],
    "sg:phone":"+1 209 522 2175",
    "sg:postcode":"95354",
    "sg:province":"CA",
    "sg:tags":[
        "establishment"
    ],
    "wof:name":"Charles D Reynolds Enterprises",
    "wof:placetype":"venue"
},
  "geometry": {"coordinates":[-120.996639,37.645039],"type":"Point"}
}