{
  "type": "Feature",
  "properties": {
    "iso:country":"US",
    "sg:address":"5000 Hopyard Rd",
    "sg:city":"Pleasanton",
    "sg:classifiers":[
        {
            "category":"Real Estate",
            "subcategory":"Developer",
            "type":"Services"
        },
        {
            "category":"Building & Trades",
            "subcategory":"Construction",
            "type":"Services"
        }
    ],
    "sg:phone":"+1 925 467 9900",
    "sg:postcode":"94588",
    "sg:province":"CA",
    "sg:tags":[
        "residential",
        "house"
    ],
    "wof:name":"Mission Valley Properties LLC",
    "wof:placetype":"venue"
},
  "geometry": {"coordinates":[-121.903597,37.693092],"type":"Point"}
}