{
  "type": "Feature",
  "properties": {
    "addr:full":"540 Ver Parque Goleta CA 93117",
    "addr:housenumber":"540",
    "addr:postcode":"93117",
    "addr:street":"Ver Parque",
    "iso:country":"US",
    "sg:address":"540 Ver Parque",
    "sg:city":"Goleta",
    "sg:classifiers":[
        {
            "category":"Building & Trades",
            "subcategory":"Electrical",
            "type":"Services"
        }
    ],
    "sg:phone":"+1 805 685 8225",
    "sg:postcode":"93117",
    "sg:province":"CA",
    "sg:tags":[
        "electric",
        "contractor"
    ],
    "wof:name":"Mc Gibbon Electric",
    "wof:placetype":"venue"
},
  "geometry": {"coordinates":[-119.91874799999999,34.446683],"type":"Point"}
}