{
  "type": "Feature",
  "properties": {
    "iso:country":"US",
    "sg:address":"14032 Enderle Center Dr",
    "sg:city":"Tustin",
    "sg:classifiers":[
        {
            "category":"Social Services",
            "type":"Services"
        }
    ],
    "sg:phone":"+1 714 669 9396",
    "sg:postcode":"92780",
    "sg:province":"CA",
    "sg:tags":[
        "counselor",
        "marriage",
        "family"
    ],
    "wof:name":"Associates In Counseling",
    "wof:placetype":"venue"
},
  "geometry": {"coordinates":[-117.827022,33.758174],"type":"Point"}
}