{
  "type": "Feature",
  "properties": {
    "addr:full":"3390 Keller Street, Ste. B Santa Clara CA 95050",
    "addr:housenumber":"3390",
    "addr:postcode":"95050",
    "addr:street":"Keller Street Ste. B",
    "iso:country":"US",
    "sg:address":"3390 Keller Street, Ste. B",
    "sg:city":"Santa Clara",
    "sg:classifiers":[
        {
            "category":"Building & Trades",
            "subcategory":"Plumbing",
            "type":"Services"
        }
    ],
    "sg:phone":"+1 800 869 6917",
    "sg:postcode":"95050",
    "sg:province":"CA",
    "sg:website":"ars.com/locations/Bay-South-CA.aspx",
    "wof:name":"Rescue Rooter of Bay Area South",
    "wof:placetype":"venue"
},
  "geometry": {"coordinates":[-121.949202,37.382196],"type":"Point"}
}