{
  "type": "Feature",
  "properties": {
    "addr:full":"3759 Bagley Ave Los Angeles CA 90034",
    "addr:housenumber":"3759",
    "addr:postcode":"90034",
    "addr:street":"Bagley Ave",
    "iso:country":"US",
    "sg:address":"3759 Bagley Ave",
    "sg:city":"Los Angeles",
    "sg:classifiers":[
        {
            "category":"Manufacturing",
            "subcategory":"Tools & Machinery",
            "type":"Manufacturing & Wholesale Goods"
        }
    ],
    "sg:phone":"+1 310 378 2244",
    "sg:postcode":"90034",
    "sg:province":"CA",
    "sg:tags":[
        "hardware",
        "rep",
        "computer",
        "reseller"
    ],
    "wof:name":"Innologix Solutions Inc",
    "wof:placetype":"venue"
},
  "geometry": {"coordinates":[-118.39634599999999,34.027214],"type":"Point"}
}