{
  "type": "Feature",
  "properties": {
    "iso:country":"US",
    "sg:address":"3242 W 8th St",
    "sg:city":"Los Angeles",
    "sg:classifiers":[
        {
            "category":"Building & Trades",
            "subcategory":"Plumbing",
            "type":"Services"
        }
    ],
    "sg:phone":"+1 213 387 5999",
    "sg:postcode":"90005",
    "sg:province":"CA",
    "sg:tags":[
        "plumbing",
        "contractor"
    ],
    "wof:name":"Hyundai Plumbing Co",
    "wof:placetype":"venue"
},
  "geometry": {"coordinates":[-118.299768,34.057632],"type":"Point"}
}