{
  "type": "Feature",
  "properties": {
    "iso:country":"US",
    "sg:address":"4876 Cass St",
    "sg:city":"San Diego",
    "sg:classifiers":[
        {
            "category":"Restaurant",
            "type":"Food & Drink"
        }
    ],
    "sg:phone":"+1 619 806 7040",
    "sg:postcode":"92109",
    "sg:province":"CA",
    "sg:tags":[
        "machine",
        "eating",
        "vending",
        "operator"
    ],
    "wof:name":"Beavers Treats",
    "wof:placetype":"venue"
},
  "geometry": {"coordinates":[-117.25387000000001,32.803721],"type":"Point"}
}