{
  "type": "Feature",
  "properties": {
    "addr:full":"1610 N Willowbrook Avenue Compton CA 90222",
    "addr:housenumber":"1610",
    "addr:postcode":"90222",
    "addr:street":"N Willowbrook Avenue",
    "iso:country":"US",
    "sg:address":"1610 N Willowbrook Avenue",
    "sg:city":"Compton",
    "sg:classifiers":[
        {
            "category":"Food & Beverages",
            "subcategory":"Groceries & Convenience Stores",
            "type":"Retail Goods"
        }
    ],
    "sg:phone":"+1 310 886 3175",
    "sg:postcode":"90222",
    "sg:province":"CA",
    "wof:name":"Duron Market",
    "wof:placetype":"venue"
},
  "geometry": {"coordinates":[-118.226231,33.906943],"type":"Point"}
}