{
  "type": "Feature",
  "properties": {
    "addr:full":"1008 E 12th St Oakland CA 94606",
    "addr:housenumber":"1008",
    "addr:postcode":"94606",
    "addr:street":"E 12Th St",
    "iso:country":"US",
    "sg:address":"1008 E 12th St",
    "sg:city":"Oakland",
    "sg:classifiers":[
        {
            "category":"Professional",
            "subcategory":"Computer Services",
            "type":"Services"
        }
    ],
    "sg:phone":"+1 415 641 1503",
    "sg:postcode":"94606",
    "sg:province":"CA",
    "sg:tags":[
        "isp",
        "provider",
        "internet"
    ],
    "wof:name":"Walkwire",
    "wof:placetype":"venue"
},
  "geometry": {"coordinates":[-122.25056499999999,37.791348],"type":"Point"}
}