{
  "type": "Feature",
  "properties": {
    "addr:full":"5879 W Ashlan Ave Fresno CA 93722",
    "addr:housenumber":"5879",
    "addr:postcode":"93722",
    "addr:street":"W Ashlan Ave",
    "iso:country":"US",
    "sg:address":"5879 W Ashlan Ave",
    "sg:city":"Fresno",
    "sg:classifiers":[
        {
            "category":"Building & Trades",
            "subcategory":"Landscaping Services",
            "type":"Services"
        }
    ],
    "sg:phone":"+1 559 277 5969",
    "sg:postcode":"93722",
    "sg:province":"CA",
    "sg:tags":[
        "landscape",
        "contractor"
    ],
    "wof:name":"Jerry Penn Landscaping",
    "wof:placetype":"venue"
},
  "geometry": {"coordinates":[-119.89645400000001,36.793446],"type":"Point"}
}