{
  "type": "Feature",
  "properties": {
    "addr:full":"300 Dairy Rd Auburn CA 95603",
    "addr:housenumber":"300",
    "addr:postcode":"ca 95603",
    "addr:street":"Dairy Rd",
    "iso:country":"US",
    "sg:address":"300 Dairy Rd",
    "sg:city":"Auburn",
    "sg:classifiers":[
        {
            "category":"Building & Trades",
            "subcategory":"Construction",
            "type":"Services"
        }
    ],
    "sg:phone":"+1 530 889 9511",
    "sg:postcode":"95603",
    "sg:province":"CA",
    "sg:tags":[
        "maker",
        "cabinet"
    ],
    "wof:name":"Cornerstone Cabinets & Bath",
    "wof:placetype":"venue"
},
  "geometry": {"coordinates":[-121.072365,38.918457],"type":"Point"}
}