{
  "type": "Feature",
  "properties": {
    "iso:country":"US",
    "sg:address":"2357 Northgate Boulevard",
    "sg:city":"Sacramento",
    "sg:classifiers":[
        {
            "category":"Shopping",
            "subcategory":"Music",
            "type":"Retail Goods"
        },
        {
            "category":"Arts & Performance",
            "subcategory":"Comedy Club",
            "type":"Entertainment"
        }
    ],
    "sg:phone":"+1 916 929 7710",
    "sg:postcode":"95833",
    "sg:province":"CA",
    "sg:tags":[
        "used",
        "tapes",
        "vintage",
        "records",
        "cd's",
        "store"
    ],
    "sg:website":"www.discotecamundolatino.com",
    "wof:name":"Discoteca Mundo Latino",
    "wof:placetype":"venue"
},
  "geometry": {"coordinates":[-121.475666,38.609305],"type":"Point"}
}