{
  "type": "Feature",
  "properties": {
    "addr:full":"2445 W Beverly Blvd Montebello CA 90640",
    "addr:housenumber":"2445",
    "addr:postcode":"90640",
    "addr:street":"W Beverly Blvd",
    "iso:country":"US",
    "sg:address":"2445 W Beverly Blvd",
    "sg:city":"Montebello",
    "sg:classifiers":[
        {
            "category":"Professional",
            "subcategory":"Accounting & Tax Preparation",
            "type":"Services"
        }
    ],
    "sg:phone":"+1 323 728 5000",
    "sg:postcode":"90640",
    "sg:province":"CA",
    "sg:tags":[
        "return",
        "filing"
    ],
    "wof:name":"AOS",
    "wof:placetype":"venue"
},
  "geometry": {"coordinates":[-118.125798,34.021305],"type":"Point"}
}