{
  "type": "Feature",
  "properties": {
    "addr:full":"2233 Santa Clara Ave Alameda CA 94501",
    "addr:housenumber":"2233",
    "addr:postcode":"94501",
    "addr:street":"Santa Clara Ave",
    "iso:country":"US",
    "sg:address":"2233 Santa Clara Ave",
    "sg:city":"Alameda",
    "sg:classifiers":[
        {
            "category":"Professional",
            "subcategory":"Art Services",
            "type":"Services"
        }
    ],
    "sg:phone":"+1 510 303 7129",
    "sg:postcode":"94501",
    "sg:province":"CA",
    "sg:tags":[
        "graphic",
        "designer"
    ],
    "wof:name":"Maddworldmedia",
    "wof:placetype":"venue"
},
  "geometry": {"coordinates":[-122.244191,37.766406],"type":"Point"}
}