{
  "type": "Feature",
  "properties": {
    "addr:full":"San Francisco International Airport International Terminal - Gate G91 San Francisco CA 94199",
    "addr:housenumber":"g91",
    "addr:postcode":"94199",
    "addr:street":"Gate",
    "iso:country":"US",
    "sg:address":"San Francisco International Airport International Terminal - Gate G91",
    "sg:city":"San Francisco",
    "sg:classifiers":[
        {
            "category":"Bars & Pubs",
            "type":"Food & Drink"
        },
        {
            "category":"Restaurant",
            "type":"Food & Drink"
        }
    ],
    "sg:phone":"+1 650 821 8201",
    "sg:postcode":"94199",
    "sg:province":"CA",
    "sg:tags":[
        "mexican"
    ],
    "sg:website":"www.andalemexican.com",
    "wof:name":"Andale Mexican Bar and Restaurant",
    "wof:placetype":"venue"
},
  "geometry": {"coordinates":[-122.38415500000001,37.616713],"type":"Point"}
}