{
  "type": "Feature",
  "properties": {
    "addr:full":"15333 Culver Drive Irvine CA 92604",
    "addr:housenumber":"15333",
    "addr:postcode":"92604",
    "addr:street":"Culver Drive",
    "iso:country":"US",
    "sg:address":"15333 Culver Drive",
    "sg:city":"Irvine",
    "sg:classifiers":[
        {
            "category":"Shopping",
            "subcategory":"Pharmacy",
            "type":"Retail Goods"
        }
    ],
    "sg:phone":"+1 949 654 2600",
    "sg:postcode":"92604",
    "sg:province":"CA",
    "sg:tags":[
        "drugstore"
    ],
    "wof:name":"CVS Pharmacy",
    "wof:placetype":"venue"
},
  "geometry": {"coordinates":[-117.79394499999999,33.691814],"type":"Point"}
}