{
  "type": "Feature",
  "properties": {
    "addr:full":"28946 Hook Creek Rd Cedar Glen CA 92321",
    "addr:housenumber":"28946",
    "addr:postcode":"92321",
    "addr:street":"Hook Creek Rd",
    "iso:country":"US",
    "sg:address":"28946 Hook Creek Rd",
    "sg:city":"Cedar Glen",
    "sg:classifiers":[
        {
            "category":"Home & Garden",
            "subcategory":"Hardware",
            "type":"Retail Goods"
        }
    ],
    "sg:phone":"+1 909 337 3310",
    "sg:postcode":"92321",
    "sg:province":"CA",
    "wof:name":"Cedar Glen Trading Post & Hdwr",
    "wof:placetype":"venue"
},
  "geometry": {"coordinates":[-117.17054899999999,34.253637],"type":"Point"}
}