{
  "type": "Feature",
  "properties": {
    "addr:full":"1368 N McDowell Blvd Petaluma CA 94954",
    "addr:housenumber":"1368",
    "addr:postcode":"94954",
    "addr:street":"N Mcdowell Blvd",
    "iso:country":"US",
    "sg:address":"1368 N McDowell Blvd",
    "sg:city":"Petaluma",
    "sg:classifiers":[
        {
            "category":"Travel",
            "subcategory":"Hotels & Motels",
            "type":"Entertainment"
        }
    ],
    "sg:phone":"+1 707 765 0333",
    "sg:postcode":"94954",
    "sg:province":"CA",
    "wof:name":"Motel 6",
    "wof:placetype":"venue"
},
  "geometry": {"coordinates":[-122.666466,38.274127],"type":"Point"}
}