{
  "type": "Feature",
  "properties": {
    "iso:country":"US",
    "sg:address":"1355 W 21st St",
    "sg:city":"San Bernardino",
    "sg:classifiers":[
        {
            "category":"Organizations",
            "subcategory":"Religious Organization",
            "type":"Services"
        }
    ],
    "sg:phone":"+1 909 887 1718",
    "sg:postcode":"92411",
    "sg:province":"CA",
    "sg:tags":[
        "church"
    ],
    "wof:name":"St Paul AME Church",
    "wof:placetype":"venue"
},
  "geometry": {"coordinates":[-117.314994,34.134602],"type":"Point"}
}