{
  "type": "Feature",
  "properties": {
    "addr:full":"2510 Daly St Los Angeles CA 90031",
    "addr:housenumber":"2510",
    "addr:postcode":"90031",
    "addr:street":"Daly St",
    "iso:country":"US",
    "sg:address":"2510 Daly St",
    "sg:city":"Los Angeles",
    "sg:classifiers":[
        {
            "category":"Building & Trades",
            "subcategory":"Construction",
            "type":"Services"
        }
    ],
    "sg:phone":"+1 323 221 1756",
    "sg:postcode":"90031",
    "sg:province":"CA",
    "sg:tags":[
        "contractor"
    ],
    "sg:website":"www.nationwideglass.net/",
    "wof:name":"Nationwide Glass & Glazing Contractors",
    "wof:placetype":"venue"
},
  "geometry": {"coordinates":[-118.215299,34.075813],"type":"Point"}
}