{
  "type": "Feature",
  "properties": {
    "iso:country":"US",
    "sg:address":"1530 N Poinsettia Pl",
    "sg:city":"Los Angeles",
    "sg:classifiers":[
        {
            "category":"Education",
            "subcategory":"Special Training",
            "type":"Public Place"
        }
    ],
    "sg:phone":"+1 323 969 9286",
    "sg:postcode":"90046",
    "sg:province":"CA",
    "sg:tags":[
        "program"
    ],
    "wof:name":"Rock Solid Achievements LLC",
    "wof:placetype":"venue"
},
  "geometry": {"coordinates":[-118.347787,34.099246],"type":"Point"}
}