{
  "type": "Feature",
  "properties": {
    "iso:country":"US",
    "sg:address":"3900 S Bristol St",
    "sg:city":"Santa Ana",
    "sg:classifiers":[
        {
            "category":"Shopping",
            "subcategory":"Hobbies, Toys, & Games",
            "type":"Retail Goods"
        }
    ],
    "sg:phone":"+1 714 540 0465",
    "sg:postcode":"92704",
    "sg:province":"CA",
    "sg:tags":[
        "merchandise"
    ],
    "wof:name":"Toys r US",
    "wof:placetype":"venue"
},
  "geometry": {"coordinates":[-117.885665,33.69577],"type":"Point"}
}