{
  "type": "Feature",
  "properties": {
    "addr:full":"1065 98th Ave Oakland CA 94603",
    "addr:housenumber":"1065",
    "addr:postcode":"94603",
    "addr:street":"98Th Ave",
    "iso:country":"US",
    "sg:address":"1065 98th Ave",
    "sg:city":"Oakland",
    "sg:classifiers":[
        {
            "category":"Food & Beverages",
            "subcategory":"Liquor & Beverages",
            "type":"Retail Goods"
        }
    ],
    "sg:phone":"+1 510 568 1799",
    "sg:postcode":"94603",
    "sg:province":"CA",
    "sg:tags":[
        "grocery",
        "store"
    ],
    "wof:name":"Four Bells Market & Liquor",
    "wof:placetype":"venue"
},
  "geometry": {"coordinates":[-122.17600299999999,37.741699],"type":"Point"}
}