{
  "type": "Feature",
  "properties": {
    "iso:country":"US",
    "sg:address":"333 Ofarrell St",
    "sg:city":"San Francisco",
    "sg:classifiers":[
        {
            "category":"Restaurant",
            "type":"Food & Drink"
        }
    ],
    "sg:phone":"+1 415 441 5458",
    "sg:postcode":"94102",
    "sg:province":"CA",
    "wof:name":"Kiku Of Tokyo",
    "wof:placetype":"venue"
},
  "geometry": {"coordinates":[-122.41088999999999,37.78599],"type":"Point"}
}