{
  "type": "Feature",
  "properties": {
    "addr:full":"38122 6th St E Palmdale CA 93550",
    "addr:housenumber":"38122",
    "addr:postcode":"ca 93550",
    "addr:street":"6Th St E",
    "iso:country":"US",
    "sg:address":"38122 6th St E",
    "sg:city":"Palmdale",
    "sg:classifiers":[
        {
            "category":"Retail",
            "subcategory":"Auto Repair",
            "type":"Services"
        }
    ],
    "sg:phone":"+1 661 947 1881",
    "sg:postcode":"93550",
    "sg:province":"CA",
    "sg:tags":[
        "body",
        "automobile",
        "painting",
        "repairing"
    ],
    "wof:name":"Dynamic Auto Body",
    "wof:placetype":"venue"
},
  "geometry": {"coordinates":[-118.11736500000001,34.574052],"type":"Point"}
}