{
  "type": "Feature",
  "properties": {
    "iso:country":"US",
    "sg:address":"1120 Bristol St",
    "sg:city":"Costa Mesa",
    "sg:classifiers":[
        {
            "category":"Insurance",
            "subcategory":"Hazard Insurance",
            "type":"Services"
        }
    ],
    "sg:phone":"+1 714 430 0035",
    "sg:postcode":"92626",
    "sg:province":"CA",
    "sg:website":"www.shorepointinsurance.com/",
    "wof:name":"Shorepoint Insurance Services",
    "wof:placetype":"venue"
},
  "geometry": {"coordinates":[-117.887252,33.669946],"type":"Point"}
}