{
  "type": "Feature",
  "properties": {
    "addr:full":"2295 Gateway Oaks Dr Ste 135 Sacramento CA 95833",
    "addr:housenumber":"2295",
    "addr:postcode":"95833",
    "addr:street":"Gateway Oaks Dr Ste 135",
    "iso:country":"US",
    "sg:address":"2295 Gateway Oaks Dr Ste 135",
    "sg:city":"Sacramento",
    "sg:classifiers":[
        {
            "category":"Insurance",
            "subcategory":"Hazard Insurance",
            "type":"Services"
        }
    ],
    "sg:phone":"+1 916 920 9375",
    "sg:postcode":"95833",
    "sg:province":"CA",
    "wof:name":"Colonial Supplemental Ins",
    "wof:placetype":"venue"
},
  "geometry": {"coordinates":[-121.51278499999999,38.607439],"type":"Point"}
}