{
  "type": "Feature",
  "properties": {
    "addr:full":"296 S California Ave Beaumont CA 92223",
    "addr:housenumber":"296",
    "addr:postcode":"92223",
    "addr:street":"S California Ave",
    "iso:country":"US",
    "sg:address":"296 S California Ave",
    "sg:city":"Beaumont",
    "sg:classifiers":[
        {
            "category":"Manufacturing",
            "subcategory":"Signs",
            "type":"Manufacturing & Wholesale Goods"
        }
    ],
    "sg:phone":"+1 951 769 0227",
    "sg:postcode":"92223",
    "sg:province":"CA",
    "wof:name":"A C Custom Graphics",
    "wof:placetype":"venue"
},
  "geometry": {"coordinates":[-116.982074,33.908729],"type":"Point"}
}