{
  "type": "Feature",
  "properties": {
    "iso:country":"US",
    "sg:address":"14880 Corralitos Ln",
    "sg:city":"San Jose",
    "sg:classifiers":[
        {
            "category":"Banks & Credit Unions",
            "subcategory":"Bank",
            "type":"Services"
        }
    ],
    "sg:phone":"+1 408 926 2100",
    "sg:postcode":"95127",
    "sg:province":"CA",
    "sg:tags":[
        "broker",
        "mortgage"
    ],
    "wof:name":"Tom Spehar Realtor",
    "wof:placetype":"venue"
},
  "geometry": {"coordinates":[-121.818668,37.375436],"type":"Point"}
}