{
  "type": "Feature",
  "properties": {
    "iso:country":"US",
    "sg:address":"10680 Treena St",
    "sg:city":"San Diego",
    "sg:classifiers":[
        {
            "category":"Manufacturing",
            "subcategory":"Chemicals & Compounds",
            "type":"Manufacturing & Wholesale Goods"
        },
        {
            "category":"Insurance",
            "subcategory":"Insurance Agent",
            "type":"Services"
        }
    ],
    "sg:phone":"+1 858 566 2727",
    "sg:postcode":"92131",
    "sg:province":"CA",
    "sg:tags":[
        "miller",
        "benefit",
        "management",
        "drug",
        "pharmacy"
    ],
    "sg:website":"www.medimpact.com",
    "wof:name":"Med Impact Healthcare Systems",
    "wof:placetype":"venue"
},
  "geometry": {"coordinates":[-117.113936,32.912414],"type":"Point"}
}