{
  "type": "Feature",
  "properties": {
    "addr:full":"2117 Vis Laredo Newport Beach CA 92660",
    "addr:housenumber":"2117",
    "addr:postcode":"92660",
    "addr:street":"Vis Laredo",
    "iso:country":"US",
    "sg:address":"2117 Vis Laredo",
    "sg:city":"Newport Beach",
    "sg:classifiers":[
        {
            "category":"Wholesale",
            "subcategory":"Non-durable Goods",
            "type":"Manufacturing & Wholesale Goods"
        }
    ],
    "sg:phone":"+1 949 720 1492",
    "sg:postcode":"92660",
    "sg:province":"CA",
    "wof:name":"All In A Basket",
    "wof:placetype":"venue"
},
  "geometry": {"coordinates":[-117.87969,33.636675],"type":"Point"}
}