{
  "type": "Feature",
  "properties": {
    "addr:full":"1939 107th Ave Oakland CA 94603",
    "addr:housenumber":"1939",
    "addr:postcode":"94603",
    "addr:street":"107Th Ave",
    "iso:country":"US",
    "sg:address":"1939 107th Ave",
    "sg:city":"Oakland",
    "sg:classifiers":[
        {
            "category":"Freight",
            "type":"Transportation"
        }
    ],
    "sg:phone":"+1 510 569 7952",
    "sg:postcode":"94603",
    "sg:province":"CA",
    "sg:tags":[
        "operator",
        "local",
        "trucking"
    ],
    "wof:name":"Tolefree Romey",
    "wof:placetype":"venue"
},
  "geometry": {"coordinates":[-122.160962,37.73966],"type":"Point"}
}