{
  "type": "Feature",
  "properties": {
    "addr:full":"15902 Fountain Ln Chino CA 91708",
    "addr:housenumber":"15902",
    "addr:postcode":"91708",
    "addr:street":"Fountain Ln",
    "iso:country":"US",
    "sg:address":"15902 Fountain Ln",
    "sg:city":"Chino",
    "sg:classifiers":[
        {
            "category":"Bakery",
            "type":"Food & Drink"
        }
    ],
    "sg:phone":"+1 909 614 1330",
    "sg:postcode":"91708",
    "sg:province":"CA",
    "sg:tags":[
        "cake",
        "pastry",
        "wedding"
    ],
    "wof:name":"Cakes By Tricia Faye",
    "wof:placetype":"venue"
},
  "geometry": {"coordinates":[-117.62664100000001,33.964967],"type":"Point"}
}