{
  "type": "Feature",
  "properties": {
    "addr:full":"366 E 58th St Los Angeles CA 90011",
    "addr:housenumber":"366",
    "addr:postcode":"90011",
    "addr:street":"E 58Th St",
    "iso:country":"US",
    "sg:address":"366 E 58th St",
    "sg:city":"Los Angeles",
    "sg:classifiers":[
        {
            "category":"Shopping",
            "type":"Retail Goods"
        }
    ],
    "sg:phone":"+1 323 234 9281",
    "sg:postcode":"90011",
    "sg:province":"CA",
    "sg:tags":[
        "miscellaneous",
        "store"
    ],
    "wof:name":"Metal Briquetting Co",
    "wof:placetype":"venue"
},
  "geometry": {"coordinates":[-118.268899,33.989749],"type":"Point"}
}