{
  "type": "Feature",
  "properties": {
    "addr:full":"5833 Clover Dr Oakland CA 94618",
    "addr:housenumber":"5833",
    "addr:postcode":"94618",
    "addr:street":"Clover Dr",
    "iso:country":"US",
    "sg:address":"5833 Clover Dr",
    "sg:city":"Oakland",
    "sg:classifiers":[
        {
            "category":"Professional",
            "subcategory":"Business Services",
            "type":"Services"
        }
    ],
    "sg:phone":"+1 510 654 4861",
    "sg:postcode":"94618",
    "sg:province":"CA",
    "sg:tags":[
        "interior",
        "designer",
        "decorator"
    ],
    "wof:name":"Design Associates",
    "wof:placetype":"venue"
},
  "geometry": {"coordinates":[-122.24555700000001,37.84912],"type":"Point"}
}