{
  "type": "Feature",
  "properties": {
    "addr:full":"375 W Apra St Compton CA 90220",
    "addr:housenumber":"375",
    "addr:postcode":"90220",
    "addr:street":"W Apra St",
    "iso:country":"US",
    "sg:address":"375 W Apra St",
    "sg:city":"Compton",
    "sg:classifiers":[
        {
            "category":"Shopping",
            "type":"Retail Goods"
        }
    ],
    "sg:phone":"+1 310 762 1742",
    "sg:postcode":"90220",
    "sg:province":"CA",
    "sg:tags":[
        "cosmetic",
        "perfume"
    ],
    "wof:name":"Amitee Cosmetics",
    "wof:placetype":"venue"
},
  "geometry": {"coordinates":[-118.226299,33.86821],"type":"Point"}
}