{
  "type": "Feature",
  "properties": {
    "iso:country":"US",
    "sg:address":"1229 Third Ave",
    "sg:city":"Chula Vista",
    "sg:classifiers":[
        {
            "category":"Professional",
            "subcategory":"Lawyer & Legal Services",
            "type":"Services"
        }
    ],
    "sg:phone":"+1 619 200 7677",
    "sg:postcode":"91911",
    "sg:province":"CA",
    "sg:tags":[
        "litigation",
        "injury",
        "family",
        "personal",
        "divorce",
        "law"
    ],
    "wof:name":"Law Office of Jesus F. Partida",
    "wof:placetype":"venue"
},
  "geometry": {"coordinates":[-117.067311,32.609168],"type":"Point"}
}