{
  "type": "Feature",
  "properties": {
    "addr:full":"15980 Alum Rock Ave. San Jose CA 95127",
    "addr:postcode":"15980;95127",
    "addr:street":"Alum Rock Ave.",
    "iso:country":"US",
    "sg:address":"15980 Alum Rock Ave.",
    "sg:city":"San Jose",
    "sg:classifiers":[
        {
            "category":"Building & Trades",
            "subcategory":"Landscaping Services",
            "type":"Services"
        }
    ],
    "sg:phone":"+1 408 923 3393",
    "sg:postcode":"95127",
    "sg:province":"CA",
    "sg:website":"www.lawnandrototillingservice.co...",
    "wof:name":"Lawn And Rototilling Services",
    "wof:placetype":"venue"
},
  "geometry": {"coordinates":[-121.816626,37.389054],"type":"Point"}
}