{
  "type": "Feature",
  "properties": {
    "addr:full":"2099 Westside Rd Bodega Bay CA 94923",
    "addr:housenumber":"2099",
    "addr:postcode":"94923",
    "addr:street":"Westside Rd",
    "iso:country":"US",
    "sg:address":"2099 Westside Rd",
    "sg:city":"Bodega Bay",
    "sg:classifiers":[
        {
            "category":"Professional",
            "subcategory":"Research",
            "type":"Services"
        }
    ],
    "sg:phone":"+1 707 875 2211",
    "sg:postcode":"94923",
    "sg:province":"CA",
    "sg:tags":[
        "development",
        "laboratory"
    ],
    "sg:website":"www.bml.ucdavis.edu",
    "wof:name":"University Of Ca Marine Lab",
    "wof:placetype":"venue"
},
  "geometry": {"coordinates":[-123.05549999999999,38.319064],"type":"Point"}
}