{
  "type": "Feature",
  "properties": {
    "iso:country":"US",
    "sg:address":"22934 1/2 Lyons Ave",
    "sg:city":"Newhall",
    "sg:classifiers":[
        {
            "category":"Insurance",
            "subcategory":"Hazard Insurance",
            "type":"Services"
        },
        {
            "category":"Insurance",
            "subcategory":"Insurance Agent",
            "type":"Services"
        },
        {
            "category":"Insurance",
            "subcategory":"Life Insurance",
            "type":"Services"
        },
        {
            "category":"Insurance",
            "subcategory":"Title Insurance",
            "type":"Services"
        }
    ],
    "sg:phone":"+1 661 295 8905",
    "sg:postcode":"91321",
    "sg:province":"CA",
    "sg:tags":[
        "auto",
        "commercial",
        "business",
        "homeowner"
    ],
    "sg:website":"http://www.farmersagent.com/mhodge/",
    "wof:name":"Michael Hodge - Farmers Insurance",
    "wof:placetype":"venue"
},
  "geometry": {"coordinates":[-118.53398,34.380114],"type":"Point"}
}