{
  "type": "Feature",
  "properties": {
    "iso:country":"US",
    "sg:address":"2882 Sand Hill Rd",
    "sg:city":"Menlo Park",
    "sg:classifiers":[
        {
            "category":"Real Estate",
            "subcategory":"Developer",
            "type":"Services"
        }
    ],
    "sg:phone":"+1 650 854 6300",
    "sg:postcode":"94025",
    "sg:province":"CA",
    "wof:name":"Courson Co",
    "wof:placetype":"venue"
},
  "geometry": {"coordinates":[-122.21445799999999,37.420574],"type":"Point"}
}