{
  "type": "Feature",
  "properties": {
    "iso:country":"US",
    "sg:address":"3025 Adams Ave",
    "sg:city":"San Diego",
    "sg:classifiers":[
        {
            "category":"Shopping",
            "subcategory":"Antiques",
            "type":"Retail Goods"
        }
    ],
    "sg:phone":"+1 619 282 9200",
    "sg:postcode":"92116",
    "sg:province":"CA",
    "wof:name":"Montecristo Art Gallery And Antiques",
    "wof:placetype":"venue"
},
  "geometry": {"coordinates":[-117.12958,32.762752],"type":"Point"}
}