{
  "type": "Feature",
  "properties": {
    "iso:country":"US",
    "sg:address":"350 S Grand Ave",
    "sg:city":"Los Angeles",
    "sg:classifiers":[
        {
            "category":"Professional",
            "subcategory":"Printing & Photocopies",
            "type":"Services"
        }
    ],
    "sg:phone":"+1 213 617 4040",
    "sg:postcode":"90071",
    "sg:province":"CA",
    "wof:name":"Copypage",
    "wof:placetype":"venue"
},
  "geometry": {"coordinates":[-118.251387,34.051662],"type":"Point"}
}