{
  "type": "Feature",
  "properties": {
    "addr:full":"350 S Grand Ave Los Angeles CA 90071",
    "addr:housenumber":"350",
    "addr:postcode":"90071",
    "addr:street":"S Grand Ave",
    "iso:country":"US",
    "sg:address":"350 S Grand Ave",
    "sg:city":"Los Angeles",
    "sg:classifiers":[
        {
            "category":"Professional",
            "subcategory":"Printing & Photocopies",
            "type":"Services"
        }
    ],
    "sg:phone":"+1 213 617 4040",
    "sg:postcode":"90071",
    "sg:province":"CA",
    "wof:name":"Copypage",
    "wof:placetype":"venue"
},
  "geometry": {"coordinates":[-118.25138699999999,34.051662],"type":"Point"}
}