{
  "type": "Feature",
  "properties": {
    "addr:full":"280 Newport Center Dr Newport Beach CA 92660",
    "addr:housenumber":"280",
    "addr:postcode":"92660",
    "addr:street":"Newport Center Dr",
    "iso:country":"US",
    "sg:address":"280 Newport Center Dr",
    "sg:city":"Newport Beach",
    "sg:classifiers":[
        {
            "category":"Health Services",
            "subcategory":"Medical Lab",
            "type":"Services"
        }
    ],
    "sg:phone":"+1 949 760 2554",
    "sg:postcode":"92660",
    "sg:province":"CA",
    "sg:tags":[
        "x",
        "laboratory"
    ],
    "wof:name":"Newport Radiographic Lab",
    "wof:placetype":"venue"
},
  "geometry": {"coordinates":[-117.87339799999999,33.613318],"type":"Point"}
}