{
  "type": "Feature",
  "properties": {
    "addr:full":"1011 19th St Santa Monica CA 90403",
    "addr:housenumber":"1011",
    "addr:postcode":"90403",
    "addr:street":"19Th St",
    "iso:country":"US",
    "sg:address":"1011 19th St",
    "sg:city":"Santa Monica",
    "sg:classifiers":[
        {
            "category":"Professional",
            "type":"Services"
        }
    ],
    "sg:phone":"+1 310 315 2606",
    "sg:postcode":"90403",
    "sg:province":"CA",
    "wof:name":"Ej & Sons Inc",
    "wof:placetype":"venue"
},
  "geometry": {"coordinates":[-118.485829,34.032184],"type":"Point"}
}