{
  "type": "Feature",
  "properties": {
    "addr:full":"421 Myrtle St Glendale CA 91203",
    "addr:housenumber":"421",
    "addr:postcode":"91203",
    "addr:street":"Myrtle St",
    "iso:country":"US",
    "sg:address":"421 Myrtle St",
    "sg:city":"Glendale",
    "sg:classifiers":[
        {
            "category":"Wholesale",
            "subcategory":"Machinery & Supplies",
            "type":"Manufacturing & Wholesale Goods"
        }
    ],
    "sg:phone":"+1 818 281 5745",
    "sg:postcode":"91203",
    "sg:province":"CA",
    "sg:tags":[
        "equipment",
        "establishment"
    ],
    "wof:name":"Vendorkay",
    "wof:placetype":"venue"
},
  "geometry": {"coordinates":[-118.26394500000001,34.150823],"type":"Point"}
}