{
  "type": "Feature",
  "properties": {
    "addr:full":"23 N Catalina Ave Pasadena CA 91106",
    "addr:housenumber":"23",
    "addr:postcode":"91106",
    "addr:street":"N Catalina Ave",
    "iso:country":"US",
    "sg:address":"23 N Catalina Ave",
    "sg:city":"Pasadena",
    "sg:classifiers":[
        {
            "category":"Personal",
            "type":"Services"
        }
    ],
    "sg:phone":"+1 626 578 1027",
    "sg:postcode":"91106",
    "sg:province":"CA",
    "sg:tags":[
        "sewing",
        "alteration"
    ],
    "wof:name":"Montoya Noe Academy Tailor Shop",
    "wof:placetype":"venue"
},
  "geometry": {"coordinates":[-118.129997,34.146198],"type":"Point"}
}