{
  "type": "Feature",
  "properties": {
    "addr:full":"1196 Mill St Selma CA 93662",
    "addr:housenumber":"1196",
    "addr:postcode":"93662",
    "addr:street":"Mill St",
    "iso:country":"US",
    "sg:address":"1196 Mill St",
    "sg:city":"Selma",
    "sg:classifiers":[
        {
            "category":"Government",
            "subcategory":"Office",
            "type":"Public Place"
        }
    ],
    "sg:phone":"+1 559 891 7001",
    "sg:postcode":"93662",
    "sg:province":"CA",
    "sg:tags":[
        "department",
        "planning"
    ],
    "wof:name":"Planning Commission",
    "wof:placetype":"venue"
},
  "geometry": {"coordinates":[-119.599293,36.566217],"type":"Point"}
}