{
  "type": "Feature",
  "properties": {
    "addr:full":"1111 Franklin St Oakland CA 94607",
    "addr:housenumber":"1111",
    "addr:postcode":"94607",
    "addr:street":"Franklin St",
    "iso:country":"US",
    "sg:address":"1111 Franklin St",
    "sg:city":"Oakland",
    "sg:classifiers":[
        {
            "category":"Government",
            "subcategory":"Office",
            "type":"Public Place"
        }
    ],
    "sg:phone":"+1 510 987 9000",
    "sg:postcode":"94607",
    "sg:province":"CA",
    "sg:tags":[
        "real estate"
    ],
    "wof:name":"Ucop RE MGT & Ln Program",
    "wof:placetype":"venue"
},
  "geometry": {"coordinates":[-122.270972,37.802432],"type":"Point"}
}