{
  "type": "Feature",
  "properties": {
    "addr:full":"14104 Lambert Rd Whittier CA 90605",
    "addr:housenumber":"14104",
    "addr:postcode":"90605",
    "addr:street":"Lambert Rd",
    "iso:country":"US",
    "sg:address":"14104 Lambert Rd",
    "sg:city":"Whittier",
    "sg:classifiers":[
        {
            "category":"Restaurant",
            "type":"Food & Drink"
        }
    ],
    "sg:phone":"+1 562 698 5899",
    "sg:postcode":"90605",
    "sg:province":"CA",
    "sg:tags":[
        "delicatessen"
    ],
    "wof:name":"Lascari's Deli & Bakery",
    "wof:placetype":"venue"
},
  "geometry": {"coordinates":[-118.025829,33.949779],"type":"Point"}
}