{
  "type": "Feature",
  "properties": {
    "addr:full":"28440 Plymouth Way Temecula CA 92591",
    "addr:housenumber":"28440",
    "addr:postcode":"92591",
    "addr:street":"Plymouth Way",
    "iso:country":"US",
    "sg:address":"28440 Plymouth Way",
    "sg:city":"Temecula",
    "sg:classifiers":[
        {
            "category":"Community Center",
            "subcategory":"Senior",
            "type":"Public Place"
        }
    ],
    "sg:phone":"+1 951 906 8829",
    "sg:postcode":"92591",
    "sg:province":"CA",
    "sg:tags":[
        "citizen"
    ],
    "wof:name":"Senior Solutions",
    "wof:placetype":"venue"
},
  "geometry": {"coordinates":[-117.16333299999999,33.535354],"type":"Point"}
}