{
  "type": "Feature",
  "properties": {
    "iso:country":"US",
    "sg:address":"2769 E Broadway",
    "sg:city":"Long Beach",
    "sg:classifiers":[
        {
            "category":"Shopping",
            "type":"Retail Goods"
        }
    ],
    "sg:phone":"+1 562 438 9375",
    "sg:postcode":"90803",
    "sg:province":"CA",
    "sg:tags":[
        "merchandise"
    ],
    "wof:name":"Vanguard Stamp & Coin",
    "wof:placetype":"venue"
},
  "geometry": {"coordinates":[-118.159167,33.765616],"type":"Point"}
}