{
  "type": "Feature",
  "properties": {
    "addr:full":"3600 W Burbank Blvd Burbank CA 91505",
    "addr:housenumber":"3600",
    "addr:postcode":"91505",
    "addr:street":"W Burbank Blvd",
    "iso:country":"US",
    "sg:address":"3600 W Burbank Blvd",
    "sg:city":"Burbank",
    "sg:classifiers":[
        {
            "category":"Retail",
            "subcategory":"Car Wash",
            "type":"Services"
        }
    ],
    "sg:phone":"+1 818 562 6959",
    "sg:postcode":"91505",
    "sg:province":"CA",
    "wof:name":"HWB",
    "wof:placetype":"venue"
},
  "geometry": {"coordinates":[-118.349262,34.174858],"type":"Point"}
}