{
  "type": "Feature",
  "properties": {
    "iso:country":"US",
    "sg:address":"8606 Garvey Ave",
    "sg:city":"Rosemead",
    "sg:classifiers":[
        {
            "category":"Food & Beverages",
            "subcategory":"Liquor & Beverages",
            "type":"Retail Goods"
        }
    ],
    "sg:phone":"+1 626 280 1598",
    "sg:postcode":"91770",
    "sg:province":"CA",
    "sg:tags":[
        "beer",
        "spirit",
        "wine"
    ],
    "wof:name":"AP Liquor",
    "wof:placetype":"venue"
},
  "geometry": {"coordinates":[-118.08200100000001,34.0625],"type":"Point"}
}