{
  "type": "Feature",
  "properties": {
    "addr:full":"909 Franklin St San Francisco CA 94109",
    "addr:housenumber":"909",
    "addr:postcode":"94109",
    "addr:street":"Franklin St",
    "iso:country":"US",
    "sg:address":"909 Franklin St",
    "sg:city":"San Francisco",
    "sg:classifiers":[
        {
            "category":"Local Transit",
            "type":"Transportation"
        }
    ],
    "sg:phone":"+1 415 440 6666",
    "sg:postcode":"94109",
    "sg:province":"CA",
    "sg:tags":[
        "limousine"
    ],
    "sg:website":"www.travellimo.com",
    "wof:name":"San Francisco Car Svc",
    "wof:placetype":"venue"
},
  "geometry": {"coordinates":[-122.42261999999999,37.783061],"type":"Point"}
}