{
  "type": "Feature",
  "properties": {
    "iso:country":"US",
    "sg:address":"1356 Lomita Blvd Apt 1",
    "sg:city":"Harbor City",
    "sg:classifiers":[
        {
            "category":"Real Estate",
            "subcategory":"Real Estate Operator",
            "type":"Services"
        }
    ],
    "sg:phone":"+1 310 530 1853",
    "sg:postcode":"90710",
    "sg:province":"CA",
    "sg:tags":[
        "apartment"
    ],
    "wof:name":"Lisa Apartments",
    "wof:placetype":"venue"
},
  "geometry": {"coordinates":[-118.30100299999999,33.797798],"type":"Point"}
}