{
  "type": "Feature",
  "properties": {
    "iso:country":"US",
    "sg:address":"1726 Ocean Way",
    "sg:city":"Laguna Beach",
    "sg:classifiers":[
        {
            "category":"Shopping",
            "subcategory":"Florist",
            "type":"Retail Goods"
        }
    ],
    "sg:phone":"+1 949 494 5654",
    "sg:postcode":"92651",
    "sg:province":"CA",
    "wof:name":"To Have & To Hold",
    "wof:placetype":"venue"
},
  "geometry": {"coordinates":[-117.772031,33.528538],"type":"Point"}
}