{
  "type": "Feature",
  "properties": {
    "addr:full":"3509 Cannon Rd Oceanside CA 92056",
    "addr:housenumber":"3509",
    "addr:postcode":"92056",
    "addr:street":"Cannon Rd",
    "iso:country":"US",
    "sg:address":"3509 Cannon Rd",
    "sg:city":"Oceanside",
    "sg:classifiers":[
        {
            "category":"Restaurant",
            "type":"Food & Drink"
        }
    ],
    "sg:phone":"+1 760 806 0095",
    "sg:postcode":"92056",
    "sg:province":"CA",
    "sg:tags":[
        "sandwich"
    ],
    "wof:name":"Icebox Too",
    "wof:placetype":"venue"
},
  "geometry": {"coordinates":[-117.265801,33.16763],"type":"Point"}
}