{
  "type": "Feature",
  "properties": {
    "addr:full":"632 Laguna Trl Frazier Park CA 93225",
    "addr:housenumber":"632",
    "addr:postcode":"93225",
    "addr:street":"Laguna Trl",
    "iso:country":"US",
    "sg:address":"632 Laguna Trl",
    "sg:city":"Frazier Park",
    "sg:classifiers":[
        {
            "category":"Food & Beverages",
            "subcategory":"Groceries & Convenience Stores",
            "type":"Retail Goods"
        }
    ],
    "sg:phone":"+1 661 245 3468",
    "sg:postcode":"93225",
    "sg:province":"CA",
    "sg:tags":[
        "grocer"
    ],
    "wof:name":"Frazier Park Market",
    "wof:placetype":"venue"
},
  "geometry": {"coordinates":[-118.946759,34.823523],"type":"Point"}
}