{
  "type": "Feature",
  "properties": {
    "addr:full":"5198 Arlington Ave Riverside CA 92504",
    "addr:housenumber":"5198",
    "addr:postcode":"92504",
    "addr:street":"Arlington Ave",
    "iso:country":"US",
    "sg:address":"5198 Arlington Ave",
    "sg:city":"Riverside",
    "sg:classifiers":[
        {
            "category":"Professional",
            "subcategory":"Computer Services",
            "type":"Services"
        }
    ],
    "sg:phone":"+1 951 352 3764",
    "sg:postcode":"92504",
    "sg:province":"CA",
    "sg:tags":[
        "website",
        "design"
    ],
    "wof:name":"Leap Frog Digital Design",
    "wof:placetype":"venue"
},
  "geometry": {"coordinates":[-117.41682900000001,33.945999],"type":"Point"}
}