{
  "type": "Feature",
  "properties": {
    "addr:full":"17735 Saticoy St Reseda CA 91335",
    "addr:postcode":"17735;91335",
    "addr:street":"Saticoy St",
    "iso:country":"US",
    "sg:address":"17735 Saticoy St",
    "sg:city":"Reseda",
    "sg:classifiers":[
        {
            "category":"Retail",
            "subcategory":"Car Wash",
            "type":"Services"
        }
    ],
    "sg:phone":"+1 818 996 6114",
    "sg:postcode":"91335",
    "sg:province":"CA",
    "sg:tags":[
        "polishing",
        "washing"
    ],
    "wof:name":"Balboa Car Wash",
    "wof:placetype":"venue"
},
  "geometry": {"coordinates":[-118.51940399999999,34.208475],"type":"Point"}
}