{
  "type": "Feature",
  "properties": {
    "addr:full":"2801 Main St Chula Vista CA 91912",
    "addr:housenumber":"2801",
    "addr:postcode":"91912",
    "addr:street":"Main St",
    "iso:country":"US",
    "sg:address":"2801 Main St",
    "sg:city":"Chula Vista",
    "sg:classifiers":[
        {
            "category":"Wholesale",
            "subcategory":"Sporting Goods",
            "type":"Manufacturing & Wholesale Goods"
        }
    ],
    "sg:phone":"+1 619 427 3627",
    "sg:postcode":"91912",
    "sg:province":"CA",
    "sg:tags":[
        "bike",
        "bicycle",
        "accessory"
    ],
    "wof:name":"Baja California Cycles Usa Inc",
    "wof:placetype":"venue"
},
  "geometry": {"coordinates":[-117.073205,32.594344],"type":"Point"}
}