{
  "type": "Feature",
  "properties": {
    "iso:country":"US",
    "sg:address":"11076 Coloma Rd",
    "sg:city":"Rancho Cordova",
    "sg:classifiers":[
        {
            "category":"Food & Beverages",
            "subcategory":"Groceries & Convenience Stores",
            "type":"Retail Goods"
        }
    ],
    "sg:phone":"+1 916 858 0224",
    "sg:postcode":"95670",
    "sg:province":"CA",
    "sg:tags":[
        "grocer"
    ],
    "wof:name":"Pavel's Deli & Bakerty",
    "wof:placetype":"venue"
},
  "geometry": {"coordinates":[-121.271111,38.617864],"type":"Point"}
}