{
  "type": "Feature",
  "properties": {
    "addr:full":"20860 Plummer St Chatsworth CA 91311",
    "addr:housenumber":"20860",
    "addr:postcode":"91311",
    "addr:street":"Plummer St",
    "iso:country":"US",
    "sg:address":"20860 Plummer St",
    "sg:city":"Chatsworth",
    "sg:classifiers":[
        {
            "category":"Sports & Exercise",
            "subcategory":"Gym",
            "type":"Entertainment"
        }
    ],
    "sg:phone":"+1 818 882 7874",
    "sg:postcode":"91311",
    "sg:province":"CA",
    "sg:tags":[
        "instruction",
        "gymnastics"
    ],
    "wof:name":"West Coast Rush",
    "wof:placetype":"venue"
},
  "geometry": {"coordinates":[-118.587278,34.242715],"type":"Point"}
}