{
  "type": "Feature",
  "properties": {
    "addr:full":"5902 Fallbrook Ave Woodland Hills CA 91367",
    "addr:housenumber":"5902",
    "addr:postcode":"91367",
    "addr:street":"Fallbrook Ave",
    "iso:country":"US",
    "sg:address":"5902 Fallbrook Ave",
    "sg:city":"Woodland Hills",
    "sg:classifiers":[
        {
            "category":"Building & Trades",
            "subcategory":"Electrical",
            "type":"Services"
        }
    ],
    "sg:phone":"+1 818 888 5467",
    "sg:postcode":"91367",
    "sg:province":"CA",
    "sg:tags":[
        "electrical",
        "contractor"
    ],
    "wof:name":"Tj Electric Service",
    "wof:placetype":"venue"
},
  "geometry": {"coordinates":[-118.623261,34.179141],"type":"Point"}
}