{
  "type": "Feature",
  "properties": {
    "iso:country":"US",
    "sg:address":"8920 Maryknoll Ave",
    "sg:city":"Whittier",
    "sg:classifiers":[
        {
            "category":"Wholesale",
            "subcategory":"Machinery & Supplies",
            "type":"Manufacturing & Wholesale Goods"
        }
    ],
    "sg:phone":"+1 562 690 0056",
    "sg:postcode":"90605",
    "sg:province":"CA",
    "sg:tags":[
        "equipment",
        "establishment"
    ],
    "wof:name":"Curtis Coin of Laundry",
    "wof:placetype":"venue"
},
  "geometry": {"coordinates":[-118.031144,33.955919],"type":"Point"}
}