{
  "type": "Feature",
  "properties": {
    "iso:country":"US",
    "sg:address":"26111 Ynez Rd",
    "sg:city":"Temecula",
    "sg:classifiers":[
        {
            "category":"Retail",
            "subcategory":"Animal Services",
            "type":"Services"
        }
    ],
    "sg:phone":"+1 951 296 1972",
    "sg:postcode":"92591",
    "sg:province":"CA",
    "wof:name":"Westcoast Animal Groomers Sply",
    "wof:placetype":"venue"
},
  "geometry": {"coordinates":[-117.162972,33.529678],"type":"Point"}
}