{
  "type": "Feature",
  "properties": {
    "addr:full":"31755 Date Palm Dr Cathedral City CA 92234",
    "addr:housenumber":"31755",
    "addr:postcode":"92234",
    "addr:street":"Date Palm Dr",
    "iso:country":"US",
    "sg:address":"31755 Date Palm Dr",
    "sg:city":"Cathedral City",
    "sg:classifiers":[
        {
            "category":"Food & Beverages",
            "subcategory":"Bakery",
            "type":"Retail Goods"
        }
    ],
    "sg:phone":"+1 760 770 8005",
    "sg:postcode":"92234",
    "sg:province":"CA",
    "sg:tags":[
        "doughnut"
    ],
    "wof:name":"Swiss Donuts",
    "wof:placetype":"venue"
},
  "geometry": {"coordinates":[-116.458494,33.843508],"type":"Point"}
}