{
  "type": "Feature",
  "properties": {
    "addr:full":"49774 Rd 426 Oakhurst CA 93644",
    "addr:postcode":"49774;93644",
    "addr:street":"Rd 426",
    "iso:country":"US",
    "sg:address":"49774 Rd 426",
    "sg:city":"Oakhurst",
    "sg:classifiers":[
        {
            "category":"Health Services",
            "subcategory":"Hospital",
            "type":"Services"
        }
    ],
    "sg:phone":"+1 559 683 4809",
    "sg:postcode":"93644",
    "sg:province":"CA",
    "sg:tags":[
        "mental"
    ],
    "wof:name":"Oakhurst Counseling Ctr",
    "wof:placetype":"venue"
},
  "geometry": {"coordinates":[-119.64017699999999,37.325539],"type":"Point"}
}