{
  "type": "Feature",
  "properties": {
    "addr:full":"135 Palamino Ct Watsonville CA 95076",
    "addr:housenumber":"135",
    "addr:postcode":"95076",
    "addr:street":"Palamino Ct",
    "iso:country":"US",
    "sg:address":"135 Palamino Ct",
    "sg:city":"Watsonville",
    "sg:classifiers":[
        {
            "category":"Farming",
            "subcategory":"Livestock Farm",
            "type":"Manufacturing & Wholesale Goods"
        }
    ],
    "sg:phone":"+1 831 722 1850",
    "sg:postcode":"95076",
    "sg:province":"CA",
    "sg:tags":[
        "equine"
    ],
    "wof:name":"Brint Boarding Stables",
    "wof:placetype":"venue"
},
  "geometry": {"coordinates":[-121.820125,36.959419],"type":"Point"}
}