{
  "type": "Feature",
  "properties": {
    "addr:full":"9851 W Chapman Ave Garden Grove CA 92841",
    "addr:housenumber":"9851",
    "addr:postcode":"92841",
    "addr:street":"W Chapman Ave",
    "iso:country":"US",
    "sg:address":"9851 W Chapman Ave",
    "sg:city":"Garden Grove",
    "sg:classifiers":[
        {
            "category":"Autos & Motor Vehicles",
            "subcategory":"Auto Supplies",
            "type":"Retail Goods"
        }
    ],
    "sg:phone":"+1 714 741 8030",
    "sg:postcode":"92841",
    "sg:province":"CA",
    "sg:tags":[
        "automobile",
        "parts"
    ],
    "wof:name":"Kragen Auto Parts",
    "wof:placetype":"venue"
},
  "geometry": {"coordinates":[-117.96217799999999,33.788635],"type":"Point"}
}