{
  "type": "Feature",
  "properties": {
    "iso:country":"US",
    "sg:address":"9 Soledad Dr",
    "sg:city":"Monterey",
    "sg:classifiers":[
        {
            "category":"Insurance",
            "subcategory":"Insurance Agent",
            "type":"Services"
        }
    ],
    "sg:phone":"+1 831 648 0130",
    "sg:postcode":"93940",
    "sg:province":"CA",
    "wof:name":"State Farm Insurance",
    "wof:placetype":"venue"
},
  "geometry": {"coordinates":[-121.902645,36.583912],"type":"Point"}
}