{
  "type": "Feature",
  "properties": {
    "addr:full":"2182 S el Camino Real Oceanside CA 92054",
    "addr:housenumber":"2182",
    "addr:postcode":"92054",
    "addr:street":"S El Camino Real",
    "iso:country":"US",
    "sg:address":"2182 S el Camino Real",
    "sg:city":"Oceanside",
    "sg:classifiers":[
        {
            "category":"Real Estate",
            "subcategory":"Real Estate Agent",
            "type":"Services"
        }
    ],
    "sg:phone":"+1 760 967 1133",
    "sg:postcode":"92054",
    "sg:province":"CA",
    "sg:tags":[
        "management"
    ],
    "wof:name":"L V Properties",
    "wof:placetype":"venue"
},
  "geometry": {"coordinates":[-117.328115,33.190796],"type":"Point"}
}