{
  "type": "Feature",
  "properties": {
    "addr:full":"407 N Normandie Avenue Los Angeles CA 90004",
    "addr:housenumber":"407",
    "addr:postcode":"90004",
    "addr:street":"N Normandie Avenue",
    "iso:country":"US",
    "sg:address":"407 N Normandie Avenue",
    "sg:city":"Los Angeles",
    "sg:classifiers":[
        {
            "category":"Professional",
            "subcategory":"Lawyer & Legal Services",
            "type":"Services"
        }
    ],
    "sg:phone":"+1 323 663 9814",
    "sg:postcode":"90004",
    "sg:province":"CA",
    "sg:tags":[
        "notary",
        "law",
        "family",
        "divorce"
    ],
    "wof:name":"Mayra's Notary Service",
    "wof:placetype":"venue"
},
  "geometry": {"coordinates":[-118.30055,34.077958],"type":"Point"}
}