{
  "type": "Feature",
  "properties": {
    "iso:country":"US",
    "sg:address":"42197 Margarita Rd",
    "sg:city":"Temecula",
    "sg:classifiers":[
        {
            "category":"Restaurant",
            "type":"Food & Drink"
        }
    ],
    "sg:menulink":"http://www.allmenus.com/ca/murrieta/198209-kfc---kentucky-fried-chicken/menu/",
    "sg:phone":"+1 951 506 6134",
    "sg:postcode":"92591",
    "sg:province":"CA",
    "sg:tags":[
        "american",
        "chicken"
    ],
    "wof:name":"KFC - Kentucky Fried Chicken",
    "wof:placetype":"venue"
},
  "geometry": {"coordinates":[-117.124804,33.509966],"type":"Point"}
}