{
  "type": "Feature",
  "properties": {
    "iso:country":"US",
    "sg:address":"2333 N Broadway",
    "sg:city":"Santa Ana",
    "sg:classifiers":[
        {
            "category":"Education",
            "subcategory":"University",
            "type":"Public Place"
        }
    ],
    "sg:phone":"+1 714 560 9555",
    "sg:postcode":"92706",
    "sg:province":"CA",
    "sg:tags":[
        "college"
    ],
    "wof:name":"Mti College English Language Center",
    "wof:placetype":"venue"
},
  "geometry": {"coordinates":[-117.870003,33.765999],"type":"Point"}
}