{
  "type": "Feature",
  "properties": {
    "addr:full":"17651 Brooklyn Ave Yorba Linda CA 92886",
    "addr:housenumber":"17651",
    "addr:postcode":"92886",
    "addr:street":"Brooklyn Ave",
    "iso:country":"US",
    "sg:address":"17651 Brooklyn Ave",
    "sg:city":"Yorba Linda",
    "sg:classifiers":[
        {
            "category":"Building & Trades",
            "subcategory":"Construction",
            "type":"Services"
        }
    ],
    "sg:phone":"+1 714 579 0749",
    "sg:postcode":"92886",
    "sg:province":"CA",
    "sg:tags":[
        "contractor"
    ],
    "wof:name":"Pacific Sandblasting Co",
    "wof:placetype":"venue"
},
  "geometry": {"coordinates":[-117.825445,33.902745],"type":"Point"}
}