{
  "type": "Feature",
  "properties": {
    "addr:full":"485 Monterey Avenue Los Gatos CA 95030",
    "addr:housenumber":"485",
    "addr:postcode":"95030",
    "addr:street":"Monterey Avenue",
    "iso:country":"US",
    "sg:address":"485 Monterey Avenue",
    "sg:city":"Los Gatos",
    "sg:classifiers":[
        {
            "category":"Health Services",
            "subcategory":"Doctor",
            "type":"Services"
        },
        {
            "category":"Professional",
            "subcategory":"Lawyer & Legal Services",
            "type":"Services"
        }
    ],
    "sg:phone":"+1 408 354 9200",
    "sg:postcode":"95030",
    "sg:province":"CA",
    "wof:name":"Rashkis Craig ESQ",
    "wof:placetype":"venue"
},
  "geometry": {"coordinates":[-121.980862,37.232133],"type":"Point"}
}