{
  "type": "Feature",
  "properties": {
    "iso:country":"US",
    "sg:address":"1021 3rd St",
    "sg:city":"Oakland",
    "sg:classifiers":[
        {
            "category":"Education",
            "subcategory":"School",
            "type":"Public Place"
        },
        {
            "category":"Recreation",
            "type":"Entertainment"
        }
    ],
    "sg:phone":"+1 510 595 7293",
    "sg:postcode":"94607",
    "sg:province":"CA",
    "sg:tags":[
        "summer",
        "camp"
    ],
    "sg:website":"www.galileo-learning.com/",
    "wof:name":"Galileo Learning",
    "wof:placetype":"venue"
},
  "geometry": {"coordinates":[-122.286468,37.800443],"type":"Point"}
}