{
  "type": "Feature",
  "properties": {
    "addr:full":"14515 Sabine Dr La Mirada CA 90638",
    "addr:housenumber":"14515",
    "addr:postcode":"90638",
    "addr:street":"Sabine Dr",
    "iso:country":"US",
    "sg:address":"14515 Sabine Dr",
    "sg:city":"La Mirada",
    "sg:classifiers":[
        {
            "category":"Professional",
            "type":"Services"
        }
    ],
    "sg:phone":"+1 562 941 1233",
    "sg:postcode":"90638",
    "sg:province":"CA",
    "sg:tags":[
        "establishment"
    ],
    "wof:name":"Kudco Diversified Inc",
    "wof:placetype":"venue"
},
  "geometry": {"coordinates":[-118.02091299999999,33.914318],"type":"Point"}
}