{
  "type": "Feature",
  "properties": {
    "addr:full":"199 Brannan St San Francisco CA 94107",
    "addr:housenumber":"199",
    "addr:postcode":"94107",
    "addr:street":"Brannan St",
    "iso:country":"US",
    "sg:address":"199 Brannan St",
    "sg:city":"San Francisco",
    "sg:classifiers":[
        {
            "category":"Food & Beverages",
            "subcategory":"Liquor & Beverages",
            "type":"Retail Goods"
        }
    ],
    "sg:phone":"+1 415 777 9403",
    "sg:postcode":"94107",
    "sg:province":"CA",
    "sg:tags":[
        "wine"
    ],
    "sg:website":"www.gourmetwines.com",
    "wof:name":"Hennessy's",
    "wof:placetype":"venue"
},
  "geometry": {"coordinates":[-122.388857,37.784388],"type":"Point"}
}