{
  "type": "Feature",
  "properties": {
    "addr:full":"9014 Garvey Ave Ste H Rosemead CA 91770",
    "addr:housenumber":"9014",
    "addr:postcode":"91770",
    "addr:street":"Garvey Ave Ste H",
    "iso:country":"US",
    "sg:address":"9014 Garvey Ave Ste H",
    "sg:city":"Rosemead",
    "sg:classifiers":[
        {
            "category":"Restaurant",
            "type":"Food & Drink"
        }
    ],
    "sg:phone":"+1 626 569 9511",
    "sg:postcode":"91770",
    "sg:province":"CA",
    "sg:tags":[
        "chinese"
    ],
    "wof:name":"Kim Ky Noodle House",
    "wof:placetype":"venue"
},
  "geometry": {"coordinates":[-118.072998,34.062599],"type":"Point"}
}