{
  "type": "Feature",
  "properties": {
    "iso:country":"US",
    "sg:address":"212 Technology Dr",
    "sg:city":"Irvine",
    "sg:classifiers":[
        {
            "category":"Wholesale",
            "subcategory":"Sporting Goods",
            "type":"Manufacturing & Wholesale Goods"
        }
    ],
    "sg:phone":"+1 949 753 9335",
    "sg:postcode":"92618",
    "sg:province":"CA",
    "wof:name":"S D G",
    "wof:placetype":"venue"
},
  "geometry": {"coordinates":[-117.74643500000001,33.665271],"type":"Point"}
}