{
  "type": "Feature",
  "properties": {
    "addr:full":"3110 Gold Canal Dr Rancho Cordova CA 95670",
    "addr:housenumber":"3110",
    "addr:postcode":"95670",
    "addr:street":"Gold Canal Dr",
    "iso:country":"US",
    "sg:address":"3110 Gold Canal Dr",
    "sg:city":"Rancho Cordova",
    "sg:classifiers":[
        {
            "category":"Home & Garden",
            "subcategory":"Building Materials",
            "type":"Retail Goods"
        }
    ],
    "sg:phone":"+1 916 852 8500",
    "sg:postcode":"95670",
    "sg:province":"CA",
    "wof:name":"Bma",
    "wof:placetype":"venue"
},
  "geometry": {"coordinates":[-121.268677,38.59258],"type":"Point"}
}