{
  "type": "Feature",
  "properties": {
    "iso:country":"US",
    "sg:address":"601 E Prosperity Ave",
    "sg:city":"Tulare",
    "sg:classifiers":[
        {
            "category":"Shopping",
            "subcategory":"Clothing, Apparel, & Fashions",
            "type":"Retail Goods"
        }
    ],
    "sg:phone":"+1 559 688 4629",
    "sg:postcode":"93274",
    "sg:province":"CA",
    "sg:tags":[
        "item",
        "boutique"
    ],
    "wof:name":"Mimosa",
    "wof:placetype":"venue"
},
  "geometry": {"coordinates":[-119.33817000000001,36.225678],"type":"Point"}
}