{
  "type": "Feature",
  "properties": {
    "addr:full":"459 Oro Dam Blvd E Oroville CA 95965",
    "addr:housenumber":"459",
    "addr:postcode":"95965",
    "addr:street":"Oro Dam Blvd E",
    "iso:country":"US",
    "sg:address":"459 Oro Dam Blvd E",
    "sg:city":"Oroville",
    "sg:classifiers":[
        {
            "category":"Real Estate",
            "subcategory":"Real Estate Agent",
            "type":"Services"
        }
    ],
    "sg:phone":"+1 530 534 9777",
    "sg:postcode":"95965",
    "sg:province":"CA",
    "wof:name":"Coldwell Banker",
    "wof:placetype":"venue"
},
  "geometry": {"coordinates":[-121.56954399999999,39.498215],"type":"Point"}
}