{
  "type": "Feature",
  "properties": {
    "addr:full":"14342 Ladd Canyon Rd Silverado CA 92676",
    "addr:housenumber":"14342",
    "addr:postcode":"92676",
    "addr:street":"Ladd Canyon Rd",
    "iso:country":"US",
    "sg:address":"14342 Ladd Canyon Rd",
    "sg:city":"Silverado",
    "sg:classifiers":[
        {
            "category":"Professional",
            "subcategory":"Lawyer & Legal Services",
            "type":"Services"
        }
    ],
    "sg:phone":"+1 714 649 0635",
    "sg:postcode":"92676",
    "sg:province":"CA",
    "wof:name":"Law of Peggy Oppedahl",
    "wof:placetype":"venue"
},
  "geometry": {"coordinates":[-117.644997,33.746601],"type":"Point"}
}