{
  "type": "Feature",
  "properties": {
    "addr:full":"1457 E Bermuda Dunes St Ontario CA 91761",
    "addr:housenumber":"1457",
    "addr:postcode":"91761",
    "addr:street":"E Bermuda Dunes St",
    "iso:country":"US",
    "sg:address":"1457 E Bermuda Dunes St",
    "sg:city":"Ontario",
    "sg:classifiers":[
        {
            "category":"Wholesale",
            "subcategory":"Vending Machines",
            "type":"Manufacturing & Wholesale Goods"
        }
    ],
    "sg:phone":"+1 909 923 2435",
    "sg:postcode":"91761",
    "sg:province":"CA",
    "sg:tags":[
        "operator"
    ],
    "wof:name":"Pilot Vending",
    "wof:placetype":"venue"
},
  "geometry": {"coordinates":[-117.621949,34.026282],"type":"Point"}
}