{
  "type": "Feature",
  "properties": {
    "iso:country":"US",
    "sg:address":"5066 N Fresno St",
    "sg:city":"Fresno",
    "sg:classifiers":[
        {
            "category":"Health Services",
            "subcategory":"Chiropractor",
            "type":"Services"
        }
    ],
    "sg:phone":"+1 559 221 6100",
    "sg:postcode":"93710",
    "sg:province":"CA",
    "wof:name":"Brenda Kattenhorn DC",
    "wof:placetype":"venue"
},
  "geometry": {"coordinates":[-119.781295,36.810037],"type":"Point"}
}