{
  "type": "Feature",
  "properties": {
    "acgov:api":"779.0",
    "acgov:type":"MS",
    "addr:full":"1781 Rose Street Berkeley CA",
    "wof:categories":[
        "education_and_religion:education=school"
    ],
    "wof:name":"Martin Luther King Middle",
    "wof:placetype":"venue"
},
  "geometry": {"coordinates":[-122.27702764713837,37.88119108989222],"type":"Point"}
}