{
  "type": "Feature",
  "properties": {
    "iso:country":"US",
    "sg:address":"2890 Geary Blvd",
    "sg:city":"San Francisco",
    "sg:classifiers":[
        {
            "category":"Professional",
            "subcategory":"Accounting & Tax Preparation",
            "type":"Services"
        },
        {
            "category":"Banks & Credit Unions",
            "subcategory":"Investment Brokerage",
            "type":"Services"
        },
        {
            "category":"Insurance",
            "subcategory":"Hazard Insurance",
            "type":"Services"
        }
    ],
    "sg:phone":"+1 415 896 4452",
    "sg:postcode":"94118",
    "sg:province":"CA",
    "sg:tags":[
        "investing",
        "accountant"
    ],
    "sg:website":"www.libertytax.com",
    "wof:name":"Liberty Tax Service",
    "wof:placetype":"venue"
},
  "geometry": {"coordinates":[-122.44986299999999,37.78238],"type":"Point"}
}