{
  "type": "Feature",
  "properties": {
    "addr:full":"2955 Chandler Dr Lompoc CA 93436",
    "addr:housenumber":"2955",
    "addr:postcode":"93436",
    "addr:street":"Chandler Dr",
    "iso:country":"US",
    "sg:address":"2955 Chandler Dr",
    "sg:city":"Lompoc",
    "sg:classifiers":[
        {
            "category":"Professional",
            "type":"Services"
        }
    ],
    "sg:phone":"+1 805 733 1421",
    "sg:postcode":"93436",
    "sg:province":"CA",
    "wof:name":"American Dream Foundation",
    "wof:placetype":"venue"
},
  "geometry": {"coordinates":[-120.440884,34.681155],"type":"Point"}
}