{
  "type": "Feature",
  "properties": {
    "addr:full":"4904 N Harbor Dr San Diego CA 92106",
    "addr:housenumber":"4904",
    "addr:postcode":"92106",
    "addr:street":"N Harbor Dr",
    "iso:country":"US",
    "sg:address":"4904 N Harbor Dr",
    "sg:city":"San Diego",
    "sg:classifiers":[
        {
            "category":"Marine",
            "type":"Transportation"
        }
    ],
    "sg:phone":"+1 619 223 2468",
    "sg:postcode":"92106",
    "sg:province":"CA",
    "sg:tags":[
        "construction",
        "towing"
    ],
    "wof:name":"Point Loma Maritime Services",
    "wof:placetype":"venue"
},
  "geometry": {"coordinates":[-117.22413,32.725492],"type":"Point"}
}