{
  "type": "Feature",
  "properties": {
    "iso:country":"US",
    "sg:address":"5700 Van Buren Blvd",
    "sg:city":"Riverside",
    "sg:classifiers":[
        {
            "category":"Shopping",
            "type":"Retail Goods"
        }
    ],
    "sg:phone":"+1 951 354 6411",
    "sg:postcode":"92503",
    "sg:province":"CA",
    "sg:tags":[
        "art",
        "gallery",
        "dealer"
    ],
    "wof:name":"Charming Art",
    "wof:placetype":"venue"
},
  "geometry": {"coordinates":[-117.454017,33.940269],"type":"Point"}
}