{
  "type": "Feature",
  "properties": {
    "addr:full":"1048 Irvine Ave Newport Beach CA 92660",
    "addr:housenumber":"1048",
    "addr:postcode":"92660",
    "addr:street":"Irvine Ave",
    "iso:country":"US",
    "sg:address":"1048 Irvine Ave",
    "sg:city":"Newport Beach",
    "sg:classifiers":[
        {
            "category":"Communications",
            "type":"Services"
        }
    ],
    "sg:phone":"+1 949 645 5444",
    "sg:postcode":"92660",
    "sg:province":"CA",
    "sg:tags":[
        "satellite",
        "video",
        "conferencing"
    ],
    "wof:name":"Star",
    "wof:placetype":"venue"
},
  "geometry": {"coordinates":[-117.907651,33.629481],"type":"Point"}
}