{
  "type": "Feature",
  "properties": {
    "iso:country":"US",
    "sg:address":"992 S. 8th Street",
    "sg:city":"San Jose",
    "sg:classifiers":[
        {
            "category":"Arts & Performance",
            "subcategory":"Arts Center",
            "type":"Entertainment"
        }
    ],
    "sg:phone":"+1 408 394 1093",
    "sg:postcode":"95112",
    "sg:province":"CA",
    "sg:website":"www.canvasghost.com/Home.html",
    "wof:name":"Canvas Ghost Productions",
    "wof:placetype":"venue"
},
  "geometry": {"coordinates":[-121.87182300000001,37.325073],"type":"Point"}
}