{
  "type": "Feature",
  "properties": {
    "addr:full":"271 S Market St San Jose CA 95113",
    "addr:housenumber":"271",
    "addr:postcode":"95113",
    "addr:street":"S Market St",
    "iso:country":"US",
    "sg:address":"271 S Market St",
    "sg:city":"San Jose",
    "sg:classifiers":[
        {
            "category":"Arts & Performance",
            "subcategory":"Arts Center",
            "type":"Entertainment"
        }
    ],
    "sg:phone":"+1 408 277 5277",
    "sg:postcode":"95113",
    "sg:province":"CA",
    "sg:tags":[
        "performing"
    ],
    "wof:name":"Montgomery Theater",
    "wof:placetype":"venue"
},
  "geometry": {"coordinates":[-121.889989,37.331081],"type":"Point"}
}