{
  "type": "Feature",
  "properties": {
    "addr:full":"1246 Lago Vista Dr Beverly Hills CA 90210",
    "addr:housenumber":"1246",
    "addr:postcode":"90210",
    "addr:street":"Lago Vista Dr",
    "iso:country":"US",
    "sg:address":"1246 Lago Vista Dr",
    "sg:city":"Beverly Hills",
    "sg:classifiers":[
        {
            "category":"Professional",
            "type":"Services"
        }
    ],
    "sg:phone":"+1 310 550 7009",
    "sg:postcode":"90210",
    "sg:province":"CA",
    "wof:name":"Malibu Beachfront Prpts LLC",
    "wof:placetype":"venue"
},
  "geometry": {"coordinates":[-118.406065,34.098093],"type":"Point"}
}