{
  "type": "Feature",
  "properties": {
    "iso:country":"US",
    "sg:address":"2525 E El Segundo Blvd",
    "sg:city":"El Segundo",
    "sg:classifiers":[
        {
            "category":"Shopping",
            "subcategory":"Bicycles & Sporting Goods",
            "type":"Retail Goods"
        }
    ],
    "sg:phone":"+1 310 536 0611",
    "sg:postcode":"90245",
    "sg:province":"CA",
    "sg:website":"www.big5sportinggoods.com",
    "wof:name":"Big 5 Sporting Goods",
    "wof:placetype":"venue"
},
  "geometry": {"coordinates":[-118.37573500000001,33.91685],"type":"Point"}
}