{
  "type": "Feature",
  "properties": {
    "iso:country":"US",
    "sg:address":"212 W F St",
    "sg:city":"Tehachapi",
    "sg:classifiers":[
        {
            "category":"Real Estate",
            "subcategory":"Real Estate Agent",
            "type":"Services"
        }
    ],
    "sg:phone":"+1 661 822 1095",
    "sg:postcode":"93561",
    "sg:province":"CA",
    "sg:tags":[
        "appraiser"
    ],
    "wof:name":"East KERN Appraisal",
    "wof:placetype":"venue"
},
  "geometry": {"coordinates":[-118.45077,35.13133],"type":"Point"}
}