{
  "type": "Feature",
  "properties": {
    "addr:full":"411 Broadway El Cajon CA 92021",
    "addr:housenumber":"411",
    "addr:postcode":"92021",
    "addr:street":"Broadway",
    "iso:country":"US",
    "sg:address":"411 Broadway",
    "sg:city":"El Cajon",
    "sg:classifiers":[
        {
            "category":"Restaurant",
            "type":"Food & Drink"
        }
    ],
    "sg:phone":"+1 619 444 4628",
    "sg:postcode":"92021",
    "sg:province":"CA",
    "sg:tags":[
        "mexican"
    ],
    "wof:name":"Santanas Mexican Food",
    "wof:placetype":"venue"
},
  "geometry": {"coordinates":[-116.958,32.807701],"type":"Point"}
}