{
  "type": "Feature",
  "properties": {
    "addr:full":"4041 Black Bird Way Calabasas CA 91302",
    "addr:housenumber":"4041",
    "addr:postcode":"91302",
    "addr:street":"Black Bird Way",
    "iso:country":"US",
    "sg:address":"4041 Black Bird Way",
    "sg:city":"Calabasas",
    "sg:classifiers":[
        {
            "category":"Real Estate",
            "subcategory":"Real Estate Services",
            "type":"Services"
        },
        {
            "category":"Real Estate",
            "subcategory":"Real Estate Agent",
            "type":"Services"
        }
    ],
    "sg:phone":"+1 818 591 0340",
    "sg:postcode":"91302",
    "sg:province":"CA",
    "sg:tags":[
        "buyer",
        "broker"
    ],
    "wof:name":"Ll Realty",
    "wof:placetype":"venue"
},
  "geometry": {"coordinates":[-118.629288,34.141709],"type":"Point"}
}