{
  "type": "Feature",
  "properties": {
    "acgov:api":"959.0",
    "acgov:type":"ES",
    "addr:full":"47100 Fernald St Fremont CA",
    "wof:categories":[
        "education_and_religion:education=school"
    ],
    "wof:name":"James Leitch Elementary",
    "wof:placetype":"venue"
},
  "geometry": {"coordinates":[-121.92319838793054,37.48653261055424],"type":"Point"}
}