{
  "type": "Feature",
  "properties": {
    "addr:full":"40 Cohansey Ave Gilroy CA 95020",
    "addr:housenumber":"40",
    "addr:postcode":"95020",
    "addr:street":"Cohansey Ave",
    "iso:country":"US",
    "sg:address":"40 Cohansey Ave",
    "sg:city":"Gilroy",
    "sg:classifiers":[
        {
            "category":"Manufacturing",
            "subcategory":"Pet Food",
            "type":"Manufacturing & Wholesale Goods"
        }
    ],
    "sg:phone":"+1 408 848 2174",
    "sg:postcode":"95020",
    "sg:province":"CA",
    "sg:tags":[
        "milling"
    ],
    "wof:name":"Double I Distributors",
    "wof:placetype":"venue"
},
  "geometry": {"coordinates":[-121.579588,37.035472],"type":"Point"}
}