{
  "type": "Feature",
  "properties": {
    "addr:full":"2930 N Fresno St Fresno CA 93703",
    "addr:housenumber":"2930",
    "addr:postcode":"93703",
    "addr:street":"N Fresno",
    "iso:country":"US",
    "sg:address":"2930 N Fresno St",
    "sg:city":"Fresno",
    "sg:classifiers":[
        {
            "category":"Professional",
            "subcategory":"Research",
            "type":"Services"
        }
    ],
    "sg:phone":"+1 559 243 1342",
    "sg:postcode":"93703",
    "sg:province":"CA",
    "sg:tags":[
        "laboratory"
    ],
    "wof:name":"Imperial Clinical",
    "wof:placetype":"venue"
},
  "geometry": {"coordinates":[-119.781463,36.779663],"type":"Point"}
}