{
  "type": "Feature",
  "properties": {
    "addr:full":"4153 24th St. San Francisco CA 94114",
    "addr:housenumber":"4153",
    "addr:postcode":"94114",
    "addr:street":"24Th St.",
    "iso:country":"US",
    "sg:address":"4153 24th St.",
    "sg:city":"San Francisco",
    "sg:classifiers":[
        {
            "category":"Real Estate",
            "subcategory":"Real Estate Services",
            "type":"Services"
        }
    ],
    "sg:phone":"+1 415 648 1200",
    "sg:postcode":"94114",
    "sg:province":"CA",
    "sg:tags":[
        "management",
        "property"
    ],
    "sg:website":"www.murphyobrienre.com",
    "wof:name":"Murphy & O'Brien Real Estate",
    "wof:placetype":"venue"
},
  "geometry": {"coordinates":[-122.43526900000001,37.751236],"type":"Point"}
}