{
  "type": "Feature",
  "properties": {
    "iso:country":"US",
    "sg:address":"1065 Brea Mall",
    "sg:city":"Brea",
    "sg:phone":"+1 714 671 1290",
    "sg:postcode":"92821",
    "sg:province":"CA",
    "sg:website":"http://www.surfcitysqueeze.com/",
    "wof:name":"Surf City Squeeze",
    "wof:placetype":"venue"
},
  "geometry": {"coordinates":[-117.886047,33.913392],"type":"Point"}
}