{
  "type": "Feature",
  "properties": {
    "addr:full":"4571 N Pershing Ave Stockton CA 95207",
    "addr:housenumber":"4571",
    "addr:postcode":"95207",
    "addr:street":"N Pershing Ave",
    "iso:country":"US",
    "sg:address":"4571 N Pershing Ave",
    "sg:city":"Stockton",
    "sg:classifiers":[
        {
            "category":"Restaurant",
            "type":"Food & Drink"
        }
    ],
    "sg:menulink":"http://www.allmenus.com/ca/stockton/171747-burger-king/menu/",
    "sg:phone":"+1 209 474 8007",
    "sg:postcode":"95207",
    "sg:province":"CA",
    "sg:tags":[
        "burger",
        "american"
    ],
    "wof:name":"Burger King",
    "wof:placetype":"venue"
},
  "geometry": {"coordinates":[-121.32194200000001,37.988244],"type":"Point"}
}