{
  "type": "Feature",
  "properties": {
    "iso:country":"US",
    "sg:address":"4323 Crenshaw Blvd",
    "sg:city":"Los Angeles",
    "sg:classifiers":[
        {
            "category":"Shopping",
            "subcategory":"Used Merchandise",
            "type":"Retail Goods"
        }
    ],
    "sg:phone":"+1 323 291 8457",
    "sg:postcode":"90008",
    "sg:province":"CA",
    "sg:tags":[
        "record",
        "rare"
    ],
    "wof:name":"Visjon Records",
    "wof:placetype":"venue"
},
  "geometry": {"coordinates":[-118.333325,34.004696],"type":"Point"}
}