{
  "type": "Feature",
  "properties": {
    "addr:full":"1942 S Court St Visalia CA 93277",
    "addr:housenumber":"1942",
    "addr:postcode":"93277",
    "addr:street":"S Court St",
    "iso:country":"US",
    "sg:address":"1942 S Court St",
    "sg:city":"Visalia",
    "sg:classifiers":[
        {
            "category":"Professional",
            "subcategory":"Management & Consulting",
            "type":"Services"
        }
    ],
    "sg:phone":"+1 559 627 1153",
    "sg:postcode":"93277",
    "sg:province":"CA",
    "sg:tags":[
        "agricultural",
        "consultant"
    ],
    "wof:name":"E S I",
    "wof:placetype":"venue"
},
  "geometry": {"coordinates":[-119.29201500000001,36.313367],"type":"Point"}
}