{
  "type": "Feature",
  "properties": {
    "addr:full":"6690 Amador Plaza Rd Dublin CA 94568",
    "addr:housenumber":"6690",
    "addr:postcode":"94568",
    "addr:street":"Amador Plaza Rd",
    "iso:country":"US",
    "sg:address":"6690 Amador Plaza Rd",
    "sg:city":"Dublin",
    "sg:classifiers":[
        {
            "category":"Building & Trades",
            "subcategory":"Construction",
            "type":"Services"
        }
    ],
    "sg:phone":"+1 925 875 0808",
    "sg:postcode":"94568",
    "sg:province":"CA",
    "sg:tags":[
        "fiber",
        "optics"
    ],
    "sg:website":"www.aoctech.com",
    "wof:name":"Aoc Technologies",
    "wof:placetype":"venue"
},
  "geometry": {"coordinates":[-121.926365,37.703558],"type":"Point"}
}