{
  "type": "Feature",
  "properties": {
    "addr:full":"119 E 12th Street Los Angeles CA 90015",
    "addr:housenumber":"119",
    "addr:postcode":"90015",
    "addr:street":"E 12Th Street",
    "iso:country":"US",
    "sg:address":"119 E 12th Street",
    "sg:city":"Los Angeles",
    "sg:classifiers":[
        {
            "category":"Shopping",
            "subcategory":"Optician",
            "type":"Retail Goods"
        }
    ],
    "sg:phone":"+1 213 748 9937",
    "sg:postcode":"90015",
    "sg:province":"CA",
    "sg:tags":[
        "eyewear"
    ],
    "wof:name":"James Shim International Eyewear",
    "wof:placetype":"venue"
},
  "geometry": {"coordinates":[-118.258568,34.037212],"type":"Point"}
}