{
  "type": "Feature",
  "properties": {
    "addr:full":"209 S McCarty Dr Beverly Hills CA 90212",
    "addr:housenumber":"209",
    "addr:postcode":"90212",
    "addr:street":"S Mccarty Dr",
    "iso:country":"US",
    "sg:address":"209 S McCarty Dr",
    "sg:city":"Beverly Hills",
    "sg:classifiers":[
        {
            "category":"Professional",
            "type":"Services"
        }
    ],
    "sg:phone":"+1 310 277 1185",
    "sg:postcode":"90212",
    "sg:province":"CA",
    "wof:name":"Richard B Wolf A Professional",
    "wof:placetype":"venue"
},
  "geometry": {"coordinates":[-118.406778,34.062451],"type":"Point"}
}