{
  "type": "Feature",
  "properties": {
    "addr:full":"1739 E Broadway Long Beach CA 90802",
    "addr:housenumber":"1739",
    "addr:postcode":"90802",
    "addr:street":"E Broadway",
    "iso:country":"US",
    "sg:address":"1739 E Broadway",
    "sg:city":"Long Beach",
    "sg:classifiers":[
        {
            "category":"Professional",
            "type":"Services"
        }
    ],
    "sg:phone":"+1 562 437 4080",
    "sg:postcode":"90802",
    "sg:province":"CA",
    "wof:name":"Flashnique",
    "wof:placetype":"venue"
},
  "geometry": {"coordinates":[-118.17024499999999,33.76768],"type":"Point"}
}