{
  "type": "Feature",
  "properties": {
    "addr:full":"133 3rd St Manhattan Beach CA 90266",
    "addr:housenumber":"133",
    "addr:postcode":"90266",
    "addr:street":"3Rd St",
    "iso:country":"US",
    "sg:address":"133 3rd St",
    "sg:city":"Manhattan Beach",
    "sg:classifiers":[
        {
            "category":"Organizations",
            "subcategory":"Community Association",
            "type":"Services"
        }
    ],
    "sg:phone":"+1 310 679 0127",
    "sg:postcode":"90266",
    "sg:province":"CA",
    "wof:name":"Kiwanis International Inc",
    "wof:placetype":"venue"
},
  "geometry": {"coordinates":[-118.407923,33.879047],"type":"Point"}
}