{
  "type": "Feature",
  "properties": {
    "addr:full":"919 N Mountain Ave Upland CA 91786",
    "addr:housenumber":"919",
    "addr:postcode":"91786",
    "addr:street":"N Mountain Ave",
    "iso:country":"US",
    "sg:address":"919 N Mountain Ave",
    "sg:city":"Upland",
    "sg:classifiers":[
        {
            "category":"Food & Beverages",
            "subcategory":"Groceries & Convenience Stores",
            "type":"Retail Goods"
        }
    ],
    "sg:phone":"+1 909 982 3514",
    "sg:postcode":"91786",
    "sg:province":"CA",
    "wof:name":"Stater Bros 45",
    "wof:placetype":"venue"
},
  "geometry": {"coordinates":[-117.67029100000001,34.105855],"type":"Point"}
}