{
  "type": "Feature",
  "properties": {
    "iso:country":"US",
    "sg:address":"412 Doulton Ct",
    "sg:city":"Pleasant Hill",
    "sg:classifiers":[
        {
            "category":"Local Transit",
            "type":"Transportation"
        }
    ],
    "sg:phone":"+1 925 943 1512",
    "sg:postcode":"94523",
    "sg:province":"CA",
    "sg:tags":[
        "airport"
    ],
    "wof:name":"Leisure Living Transportation",
    "wof:placetype":"venue"
},
  "geometry": {"coordinates":[-122.086285,37.935478],"type":"Point"}
}