{
  "type": "Feature",
  "properties": {
    "addr:full":"679 Monterey St San Luis Obispo CA 93401",
    "addr:housenumber":"679",
    "addr:postcode":"93401",
    "addr:street":"Monterey St",
    "iso:country":"US",
    "sg:address":"679 Monterey St",
    "sg:city":"San Luis Obispo",
    "sg:classifiers":[
        {
            "category":"Professional",
            "subcategory":"Lawyer & Legal Services",
            "type":"Services"
        }
    ],
    "sg:phone":"+1 805 541 6601",
    "sg:postcode":"93401",
    "sg:province":"CA",
    "sg:tags":[
        "attorney"
    ],
    "wof:name":"William S Walter A Pro Corp",
    "wof:placetype":"venue"
},
  "geometry": {"coordinates":[-120.666438,35.278967],"type":"Point"}
}