{
  "type": "Feature",
  "properties": {
    "addr:full":"3564 Central Ave Riverside CA 92506",
    "addr:housenumber":"3564",
    "addr:postcode":"92506",
    "addr:street":"Central Ave",
    "iso:country":"US",
    "sg:address":"3564 Central Ave",
    "sg:city":"Riverside",
    "sg:classifiers":[
        {
            "category":"Shopping",
            "subcategory":"Hobbies, Toys, & Games",
            "type":"Retail Goods"
        },
        {
            "category":"Shopping",
            "subcategory":"Pawn Shop",
            "type":"Retail Goods"
        },
        {
            "category":"Recreation",
            "subcategory":"Gun Range",
            "type":"Entertainment"
        }
    ],
    "sg:phone":"+1 951 781 6140",
    "sg:postcode":"92506",
    "sg:province":"CA",
    "sg:tags":[
        "pawnbroker",
        "safety",
        "instruction",
        "marksmanship",
        "gunsmith"
    ],
    "wof:name":"Centerfire Firearms",
    "wof:placetype":"venue"
},
  "geometry": {"coordinates":[-117.389931,33.953565],"type":"Point"}
}