{
  "type": "Feature",
  "properties": {
    "iso:country":"US",
    "sg:address":"1714 Acacia St",
    "sg:city":"Alhambra",
    "sg:classifiers":[
        {
            "category":"Wholesale",
            "subcategory":"Durable Goods & Equipment",
            "type":"Manufacturing & Wholesale Goods"
        }
    ],
    "sg:phone":"+1 626 284 5165",
    "sg:postcode":"91801",
    "sg:province":"CA",
    "sg:tags":[
        "fire",
        "extinguisher"
    ],
    "wof:name":"H I Fire Extinguishers",
    "wof:placetype":"venue"
},
  "geometry": {"coordinates":[-118.143315,34.090087],"type":"Point"}
}