{
  "type": "Feature",
  "properties": {
    "iso:country":"US",
    "sg:address":"2760 Tapo Canyon Rd",
    "sg:city":"Simi Valley",
    "sg:classifiers":[
        {
            "category":"Wholesale",
            "subcategory":"Machinery & Supplies",
            "type":"Manufacturing & Wholesale Goods"
        }
    ],
    "sg:phone":"+1 818 763 3900",
    "sg:postcode":"93063",
    "sg:province":"CA",
    "sg:tags":[
        "safety",
        "install",
        "devices"
    ],
    "wof:name":"Proof In Time",
    "wof:placetype":"venue"
},
  "geometry": {"coordinates":[-118.71767,34.285147],"type":"Point"}
}