{
  "type": "Feature",
  "properties": {
    "iso:country":"US",
    "sg:address":"1175 E Julian St #6",
    "sg:city":"San Jos?",
    "sg:classifiers":[
        {
            "category":"Retail",
            "subcategory":"Laundry & Dry Cleaning",
            "type":"Services"
        }
    ],
    "sg:phone":"+1 408 286 7534",
    "sg:postcode":"95116",
    "sg:province":"CA",
    "sg:website":"www.rainbowlaundrysj.com",
    "wof:name":"Rainbow Laundry & Water",
    "wof:placetype":"venue"
},
  "geometry": {"coordinates":[-121.871481,37.351321],"type":"Point"}
}