{
  "type": "Feature",
  "properties": {
    "iso:country":"US",
    "sg:address":"201 W Napa St Ste 8",
    "sg:city":"Sonoma",
    "sg:classifiers":[
        {
            "category":"Shopping",
            "subcategory":"Baby Store",
            "type":"Retail Goods"
        },
        {
            "category":"Shopping",
            "subcategory":"Used Merchandise",
            "type":"Retail Goods"
        }
    ],
    "sg:phone":"+1 707 938 2699",
    "sg:postcode":"95476",
    "sg:province":"CA",
    "sg:tags":[
        "shop",
        "resale",
        "infant",
        "wear",
        "children's"
    ],
    "wof:name":"Sandbox",
    "wof:placetype":"venue"
},
  "geometry": {"coordinates":[-122.46125000000001,38.292221],"type":"Point"}
}