{
  "type": "Feature",
  "properties": {
    "addr:full":"330 N. Atlantic Blvd Monterey Park CA 91754",
    "addr:housenumber":"330",
    "addr:postcode":"91754",
    "addr:street":"N. Atlantic Blvd",
    "iso:country":"US",
    "sg:address":"330 N. Atlantic Blvd",
    "sg:city":"Monterey Park",
    "sg:classifiers":[
        {
            "category":"Cinema",
            "subcategory":"Movie Rental",
            "type":"Entertainment"
        },
        {
            "category":"Shopping",
            "subcategory":"Music",
            "type":"Retail Goods"
        }
    ],
    "sg:phone":"+1 626 289 0261",
    "sg:postcode":"91754",
    "sg:province":"CA",
    "sg:tags":[
        "game",
        "video",
        "dvd's"
    ],
    "sg:website":"www.redbox.com/Titles/AvailableT...",
    "wof:name":"Redbox",
    "wof:placetype":"venue"
},
  "geometry": {"coordinates":[-118.13431799999999,34.067282],"type":"Point"}
}