{
  "type": "Feature",
  "properties": {
    "iso:country":"US",
    "sg:address":"5150 Collett Ave",
    "sg:city":"Encino",
    "sg:classifiers":[
        {
            "category":"Building & Trades",
            "subcategory":"Construction",
            "type":"Services"
        }
    ],
    "sg:phone":"+1 818 789 6295",
    "sg:postcode":"91436",
    "sg:province":"CA",
    "sg:tags":[
        "coping",
        "plastering",
        "tiling",
        "pool",
        "swimming"
    ],
    "wof:name":"Encino Pool & Spa Inc",
    "wof:placetype":"venue"
},
  "geometry": {"coordinates":[-118.482466,34.162697],"type":"Point"}
}