{
  "type": "Feature",
  "properties": {
    "addr:full":"1670 Zanker Road Suite A San Jose CA 95112",
    "addr:housenumber":"1670",
    "addr:postcode":"95112",
    "addr:street":"Zanker Road Suite A",
    "iso:country":"US",
    "sg:address":"1670 Zanker Road Suite A",
    "sg:city":"San Jose",
    "sg:classifiers":[
        {
            "category":"Building & Trades",
            "subcategory":"Construction",
            "type":"Services"
        }
    ],
    "sg:phone":"+1 408 467 1000",
    "sg:postcode":"95112",
    "sg:province":"CA",
    "sg:tags":[
        "contractor"
    ],
    "sg:website":"www.hillhouseconstruction.com",
    "wof:name":"Hillhouse Construction Company",
    "wof:placetype":"venue"
},
  "geometry": {"coordinates":[-121.88101,37.340699],"type":"Point"}
}