{
  "type": "Feature",
  "properties": {
    "addr:full":"2993 Corpus Christi St Simi Valley CA 93063",
    "addr:housenumber":"2993",
    "addr:postcode":"93063",
    "addr:street":"Corpus Christi St",
    "iso:country":"US",
    "sg:address":"2993 Corpus Christi St",
    "sg:city":"Simi Valley",
    "sg:classifiers":[
        {
            "category":"Shopping",
            "type":"Retail Goods"
        }
    ],
    "sg:phone":"+1 805 522 4699",
    "sg:postcode":"93063",
    "sg:province":"CA",
    "sg:tags":[
        "cosmetic",
        "perfume"
    ],
    "wof:name":"E M Cosmetics",
    "wof:placetype":"venue"
},
  "geometry": {"coordinates":[-118.699743,34.290023],"type":"Point"}
}