{
  "type": "Feature",
  "properties": {
    "addr:full":"1401 Mendell St San Francisco CA 94124",
    "addr:housenumber":"1401",
    "addr:postcode":"94124",
    "addr:street":"Mendell St",
    "iso:country":"US",
    "sg:address":"1401 Mendell St",
    "sg:city":"San Francisco",
    "sg:classifiers":[
        {
            "category":"Retail",
            "subcategory":"Auto Repair",
            "type":"Services"
        }
    ],
    "sg:phone":"+1 415 822 6333",
    "sg:postcode":"94124",
    "sg:province":"CA",
    "sg:tags":[
        "body",
        "automobile",
        "painting"
    ],
    "wof:name":"F F Auto Body & Muffler",
    "wof:placetype":"venue"
},
  "geometry": {"coordinates":[-122.390968,37.734013],"type":"Point"}
}