{
  "type": "Feature",
  "properties": {
    "addr:full":"2904 E. Hullett Street Long Beach CA 90805",
    "addr:housenumber":"2904",
    "addr:postcode":"90805",
    "addr:street":"E. Hullett Street",
    "iso:country":"US",
    "sg:address":"2904 E. Hullett Street",
    "sg:city":"Long Beach",
    "sg:classifiers":[
        {
            "category":"Personal",
            "type":"Services"
        }
    ],
    "sg:phone":"+1 310 303 8618",
    "sg:postcode":"90805",
    "sg:province":"CA",
    "sg:tags":[
        "home"
    ],
    "wof:name":"Central Metal Works",
    "wof:placetype":"venue"
},
  "geometry": {"coordinates":[-118.157538,33.860859],"type":"Point"}
}