{
  "type": "Feature",
  "properties": {
    "addr:full":"1752 S Victoria Ave Ventura CA 93003",
    "addr:housenumber":"1752",
    "addr:postcode":"93003",
    "addr:street":"S Victoria Ave",
    "iso:country":"US",
    "sg:address":"1752 S Victoria Ave",
    "sg:city":"Ventura",
    "sg:classifiers":[
        {
            "category":"Real Estate",
            "subcategory":"Real Estate Services",
            "type":"Services"
        }
    ],
    "sg:phone":"+1 805 339 0029",
    "sg:postcode":"93003",
    "sg:province":"CA",
    "sg:tags":[
        "company",
        "title"
    ],
    "wof:name":"Land America Southland Title",
    "wof:placetype":"venue"
},
  "geometry": {"coordinates":[-119.210579,34.256922],"type":"Point"}
}