{
  "type": "Feature",
  "properties": {
    "addr:full":"100 Shoreline Hwy Mill Valley CA 94941",
    "addr:housenumber":"100",
    "addr:postcode":"94941",
    "addr:street":"Shoreline Hwy",
    "iso:country":"US",
    "sg:address":"100 Shoreline Hwy",
    "sg:city":"Mill Valley",
    "sg:classifiers":[
        {
            "category":"Shopping",
            "subcategory":"Computers & Home Electronics",
            "type":"Retail Goods"
        }
    ],
    "sg:phone":"+1 415 332 4032",
    "sg:postcode":"94941",
    "sg:province":"CA",
    "sg:tags":[
        "software"
    ],
    "sg:website":"www.forerunnersystems.com",
    "wof:name":"Forerunner Systems Inc",
    "wof:placetype":"venue"
},
  "geometry": {"coordinates":[-122.517257,37.880284],"type":"Point"}
}