{
  "type": "Feature",
  "properties": {
    "iso:country":"US",
    "sg:address":"14520 Carmenita Rd",
    "sg:city":"Norwalk",
    "sg:classifiers":[
        {
            "category":"Manufacturing",
            "subcategory":"Tools & Machinery",
            "type":"Manufacturing & Wholesale Goods"
        }
    ],
    "sg:phone":"+1 562 404 0050",
    "sg:postcode":"90650",
    "sg:province":"CA",
    "sg:tags":[
        "industrial",
        "mfg"
    ],
    "wof:name":"J D Welding & Fabrication",
    "wof:placetype":"venue"
},
  "geometry": {"coordinates":[-118.046521,33.900113],"type":"Point"}
}