{
  "type": "Feature",
  "properties": {
    "addr:full":"1582 Lincoln Way Auburn CA 95603",
    "addr:housenumber":"1582",
    "addr:postcode":"ca 95603",
    "addr:street":"Lincoln Way",
    "iso:country":"US",
    "sg:address":"1582 Lincoln Way",
    "sg:city":"Auburn",
    "sg:classifiers":[
        {
            "category":"Shopping",
            "subcategory":"Used Merchandise",
            "type":"Retail Goods"
        }
    ],
    "sg:phone":"+1 530 885 0875",
    "sg:postcode":"95603",
    "sg:province":"CA",
    "sg:tags":[
        "antique"
    ],
    "wof:name":"Williams Antiques Collectibles",
    "wof:placetype":"venue"
},
  "geometry": {"coordinates":[-121.07854399999999,38.896444],"type":"Point"}
}