{
  "type": "Feature",
  "properties": {
    "iso:country":"US",
    "sg:address":"431 N Tustin Ave",
    "sg:city":"Santa Ana",
    "sg:classifiers":[
        {
            "category":"Health Services",
            "subcategory":"Health Practitioner",
            "type":"Services"
        }
    ],
    "sg:phone":"+1 714 285 1300",
    "sg:postcode":"92705",
    "sg:province":"CA",
    "sg:tags":[
        "nutritionist"
    ],
    "wof:name":"Body Smart Nutrition",
    "wof:placetype":"venue"
},
  "geometry": {"coordinates":[-117.834075,33.749056],"type":"Point"}
}