{
  "type": "Feature",
  "properties": {
    "addr:full":"6705 Greenleaf Ave Whittier CA 90601",
    "addr:housenumber":"6705",
    "addr:postcode":"90601",
    "addr:street":"Greenleaf Ave",
    "iso:country":"US",
    "sg:address":"6705 Greenleaf Ave",
    "sg:city":"Whittier",
    "sg:classifiers":[
        {
            "category":"Wholesale",
            "subcategory":"Machinery & Supplies",
            "type":"Manufacturing & Wholesale Goods"
        }
    ],
    "sg:phone":"+1 562 696 2639",
    "sg:postcode":"90601",
    "sg:province":"CA",
    "sg:tags":[
        "equipment",
        "establishment"
    ],
    "wof:name":"Janet Beauty Supply & Salon",
    "wof:placetype":"venue"
},
  "geometry": {"coordinates":[-118.037406,33.979124],"type":"Point"}
}