{
  "type": "Feature",
  "properties": {
    "iso:country":"US",
    "sg:address":"6831 Bender Ct",
    "sg:city":"Sacramento",
    "sg:classifiers":[
        {
            "category":"Retail",
            "subcategory":"Auto Repair",
            "type":"Services"
        }
    ],
    "sg:phone":"+1 916 452 1161",
    "sg:postcode":"95820",
    "sg:province":"CA",
    "sg:tags":[
        "wrecker"
    ],
    "wof:name":"Sierra Towing",
    "wof:placetype":"venue"
},
  "geometry": {"coordinates":[-121.424815,38.534291],"type":"Point"}
}