{
  "type": "Feature",
  "properties": {
    "addr:full":"621 S Prospect Ave Redondo Beach CA 90277",
    "addr:housenumber":"621",
    "addr:postcode":"90277",
    "addr:street":"S Prospect Ave",
    "iso:country":"US",
    "sg:address":"621 S Prospect Ave",
    "sg:city":"Redondo Beach",
    "sg:classifiers":[
        {
            "category":"Real Estate",
            "subcategory":"Real Estate Operator",
            "type":"Services"
        }
    ],
    "sg:phone":"+1 310 316 3272",
    "sg:postcode":"90277",
    "sg:province":"CA",
    "sg:tags":[
        "condominium"
    ],
    "wof:name":"Brookside Village Homeowners",
    "wof:placetype":"venue"
},
  "geometry": {"coordinates":[-118.376138,33.831246],"type":"Point"}
}