{
  "type": "Feature",
  "properties": {
    "iso:country":"US",
    "sg:address":"131 S Kilroy Rd",
    "sg:city":"Turlock",
    "sg:classifiers":[
        {
            "category":"Banks & Credit Unions",
            "subcategory":"Investment Brokerage",
            "type":"Services"
        }
    ],
    "sg:phone":"+1 209 668 1250",
    "sg:postcode":"95380",
    "sg:province":"CA",
    "sg:tags":[
        "advisory",
        "financial"
    ],
    "wof:name":"Real Equity Investment Group",
    "wof:placetype":"venue"
},
  "geometry": {"coordinates":[-120.876386,37.49019],"type":"Point"}
}