{
  "type": "Feature",
  "properties": {
    "iso:country":"US",
    "sg:address":"31844 Rancho Amigos Rd",
    "sg:city":"Bonsall",
    "sg:classifiers":[
        {
            "category":"Building & Trades",
            "subcategory":"Landscaping Services",
            "type":"Services"
        }
    ],
    "sg:phone":"+1 760 736 3096",
    "sg:postcode":"92003",
    "sg:province":"CA",
    "wof:name":"Daniels Landscape Inc",
    "wof:placetype":"venue"
},
  "geometry": {"coordinates":[-117.158829,33.28094],"type":"Point"}
}