{
  "type": "Feature",
  "properties": {
    "iso:country":"US",
    "sg:address":"502 Monterey Ave",
    "sg:city":"Morro Bay",
    "sg:classifiers":[
        {
            "category":"Professional",
            "subcategory":"Lawyer & Legal Services",
            "type":"Services"
        }
    ],
    "sg:phone":"+1 805 772 0151",
    "sg:postcode":"93442",
    "sg:province":"CA",
    "wof:name":"Mahan And David LLP",
    "wof:placetype":"venue"
},
  "geometry": {"coordinates":[-120.848662,35.362201],"type":"Point"}
}