{
  "type": "Feature",
  "properties": {
    "iso:country":"US",
    "sg:address":"21 N 5th St",
    "sg:city":"San Jose",
    "sg:classifiers":[
        {
            "category":"Retail",
            "subcategory":"Car Wash",
            "type":"Services"
        }
    ],
    "sg:phone":"+1 408 293 3128",
    "sg:postcode":"95112",
    "sg:province":"CA",
    "sg:website":"www.carwashpacific.com",
    "wof:name":"Pacific Hand Car Wash",
    "wof:placetype":"venue"
},
  "geometry": {"coordinates":[-121.887001,37.3382],"type":"Point"}
}