{
  "type": "Feature",
  "properties": {
    "iso:country":"US",
    "sg:address":"1216 S Main St",
    "sg:city":"Angels Camp",
    "sg:classifiers":[
        {
            "category":"Government",
            "subcategory":"Post Office",
            "type":"Public Place"
        }
    ],
    "sg:phone":"+1 209 736 2220",
    "sg:postcode":"95222",
    "sg:province":"CA",
    "wof:name":"US Post Office",
    "wof:placetype":"venue"
},
  "geometry": {"coordinates":[-120.540335,38.069579],"type":"Point"}
}