{
  "type": "Feature",
  "properties": {
    "iso:country":"US",
    "sg:address":"38660 Lexington St",
    "sg:city":"Fremont",
    "sg:classifiers":[
        {
            "category":"Local Transit",
            "type":"Transportation"
        }
    ],
    "sg:phone":"+1 510 547 0404",
    "sg:postcode":"94536",
    "sg:province":"CA",
    "sg:tags":[
        "airport"
    ],
    "wof:name":"Bay Area Express",
    "wof:placetype":"venue"
},
  "geometry": {"coordinates":[-121.990445,37.55172],"type":"Point"}
}