{
  "type": "Feature",
  "properties": {
    "addr:full":"635 California St Woodland CA 95695",
    "addr:housenumber":"635",
    "addr:postcode":"95695",
    "addr:street":"California St",
    "iso:country":"US",
    "sg:address":"635 California St",
    "sg:city":"Woodland",
    "sg:classifiers":[
        {
            "category":"Education",
            "subcategory":"Preschool",
            "type":"Public Place"
        }
    ],
    "sg:phone":"+1 530 668 2447",
    "sg:postcode":"95695",
    "sg:province":"CA",
    "sg:tags":[
        "kindergarten"
    ],
    "wof:name":"Holy Rosary Preschool",
    "wof:placetype":"venue"
},
  "geometry": {"coordinates":[-121.788681,38.673572],"type":"Point"}
}