{
  "type": "Feature",
  "properties": {
    "addr:full":"5662 Cll Real Goleta CA 93117",
    "addr:housenumber":"5662",
    "addr:postcode":"93117",
    "addr:street":"Cll Real",
    "iso:country":"US",
    "sg:address":"5662 Cll Real",
    "sg:city":"Goleta",
    "sg:classifiers":[
        {
            "category":"Professional",
            "subcategory":"Advertising",
            "type":"Services"
        }
    ],
    "sg:phone":"+1 805 967 2933",
    "sg:postcode":"93117",
    "sg:province":"CA",
    "sg:tags":[
        "mailing",
        "shipping"
    ],
    "wof:name":"UPS Store",
    "wof:placetype":"venue"
},
  "geometry": {"coordinates":[-119.81941500000001,34.441171],"type":"Point"}
}