{
  "type": "Feature",
  "properties": {
    "addr:full":"604 Galveston St West Sacramento CA 95691",
    "addr:housenumber":"604",
    "addr:postcode":"95691",
    "addr:street":"Galveston St",
    "iso:country":"US",
    "sg:address":"604 Galveston St",
    "sg:city":"West Sacramento",
    "sg:classifiers":[
        {
            "category":"Wholesale",
            "subcategory":"Auto Parts",
            "type":"Manufacturing & Wholesale Goods"
        }
    ],
    "sg:phone":"+1 916 371 5555",
    "sg:postcode":"95691",
    "sg:province":"CA",
    "sg:tags":[
        "automobile",
        "rebuilt"
    ],
    "wof:name":"Bumper Warehouse",
    "wof:placetype":"venue"
},
  "geometry": {"coordinates":[-121.55264,38.581589],"type":"Point"}
}