{
  "type": "Feature",
  "properties": {
    "addr:full":"4302 Overland Ave Culver City CA 90230",
    "addr:housenumber":"4302",
    "addr:postcode":"90230",
    "addr:street":"Overland Ave",
    "iso:country":"US",
    "sg:address":"4302 Overland Ave",
    "sg:city":"Culver City",
    "sg:classifiers":[
        {
            "category":"Insurance",
            "subcategory":"Insurance Agent",
            "type":"Services"
        }
    ],
    "sg:phone":"+1 310 559 0892",
    "sg:postcode":"90230",
    "sg:province":"CA",
    "wof:name":"Steve Libuser Insurance",
    "wof:placetype":"venue"
},
  "geometry": {"coordinates":[-118.399663,34.010983],"type":"Point"}
}