{
  "type": "Feature",
  "properties": {
    "addr:full":"3850 Charter Park Dr San Jose CA 95136",
    "addr:housenumber":"3850",
    "addr:postcode":"95136",
    "addr:street":"Charter Park Dr",
    "iso:country":"US",
    "sg:address":"3850 Charter Park Dr",
    "sg:city":"San Jose",
    "sg:phone":"+1 408 266 6690",
    "sg:postcode":"95136",
    "sg:province":"CA",
    "sg:tags":[
        "equipment",
        "station"
    ],
    "sg:website":"www.islandequipment.com",
    "wof:name":"Island Equipment Co Inc",
    "wof:placetype":"venue"
},
  "geometry": {"coordinates":[-121.851077,37.277779],"type":"Point"}
}