{
  "type": "Feature",
  "properties": {
    "addr:full":"10610 Visitar St Felton CA 95018",
    "addr:housenumber":"10610",
    "addr:postcode":"95018",
    "addr:street":"Visitar St",
    "iso:country":"US",
    "sg:address":"10610 Visitar St",
    "sg:city":"Felton",
    "sg:classifiers":[
        {
            "category":"Shopping",
            "type":"Retail Goods"
        }
    ],
    "sg:phone":"+1 831 335 9213",
    "sg:postcode":"95018",
    "sg:province":"CA",
    "sg:tags":[
        "cosmetic",
        "perfume"
    ],
    "wof:name":"Mary Kay Cosmetics",
    "wof:placetype":"venue"
},
  "geometry": {"coordinates":[-122.050842,37.10004],"type":"Point"}
}