{
  "type": "Feature",
  "properties": {
    "iso:country":"US",
    "sg:address":"117 Los Altos St",
    "sg:city":"Oxnard",
    "sg:classifiers":[
        {
            "category":"Restaurant",
            "type":"Food & Drink"
        }
    ],
    "sg:phone":"+1 805 985 9151",
    "sg:postcode":"93035",
    "sg:province":"CA",
    "wof:name":"Mrs Olson's Coffee Hut",
    "wof:placetype":"venue"
},
  "geometry": {"coordinates":[-119.23299,34.172355],"type":"Point"}
}