{
  "type": "Feature",
  "properties": {
    "iso:country":"US",
    "sg:address":"2333 Market St",
    "sg:city":"San Francisco",
    "sg:classifiers":[
        {
            "category":"Health Services",
            "subcategory":"Clinic",
            "type":"Services"
        },
        {
            "category":"Personal",
            "subcategory":"Psychics & Astrologers",
            "type":"Services"
        }
    ],
    "sg:phone":"+1 415 377 7533",
    "sg:postcode":"94114",
    "sg:province":"CA",
    "sg:tags":[
        "counseling",
        "mental"
    ],
    "sg:website":"www.matthewengel.com",
    "wof:name":"Matthew Engel, MSW, CHT",
    "wof:placetype":"venue"
},
  "geometry": {"coordinates":[-122.432992,37.7642],"type":"Point"}
}