{
  "type": "Feature",
  "properties": {
    "addr:full":"1631 N Bristol St Ste 202 Santa Ana CA 92706",
    "addr:housenumber":"1631",
    "addr:postcode":"92706",
    "addr:street":"N Bristol St Ste 202",
    "iso:country":"US",
    "sg:address":"1631 N Bristol St Ste 202",
    "sg:city":"Santa Ana",
    "sg:classifiers":[
        {
            "category":"Professional",
            "subcategory":"Lawyer & Legal Services",
            "type":"Services"
        }
    ],
    "sg:phone":"+1 714 542 9288",
    "sg:postcode":"92706",
    "sg:province":"CA",
    "wof:name":"Garcia Martin H & Associates",
    "wof:placetype":"venue"
},
  "geometry": {"coordinates":[-117.884612,33.759613],"type":"Point"}
}