{
  "type": "Feature",
  "properties": {
    "addr:full":"16 1/2 E Gabilan St Salinas CA 93901",
    "addr:housenumber":"1 / 2 e",
    "addr:postcode":"93901",
    "addr:street":"16;Gabilan St",
    "iso:country":"US",
    "sg:address":"16 1/2 E Gabilan St",
    "sg:city":"Salinas",
    "sg:classifiers":[
        {
            "category":"Travel",
            "subcategory":"Hotels & Motels",
            "type":"Entertainment"
        }
    ],
    "sg:phone":"+1 831 758 1198",
    "sg:postcode":"93901",
    "sg:province":"CA",
    "sg:tags":[
        "lodging"
    ],
    "wof:name":"Traveler's Hotel",
    "wof:placetype":"venue"
},
  "geometry": {"coordinates":[-121.654483,36.675751],"type":"Point"}
}