{
  "type": "Feature",
  "properties": {
    "addr:full":"316 Perkins Ct Suisun City CA 94585",
    "addr:housenumber":"316",
    "addr:postcode":"94585",
    "addr:street":"Perkins Ct",
    "iso:country":"US",
    "sg:address":"316 Perkins Ct",
    "sg:city":"Suisun City",
    "sg:classifiers":[
        {
            "category":"Building & Trades",
            "subcategory":"Construction",
            "type":"Services"
        }
    ],
    "sg:phone":"+1 707 372 2647",
    "sg:postcode":"94585",
    "sg:province":"CA",
    "sg:tags":[
        "home",
        "improvement"
    ],
    "wof:name":"Leave It To Biever Handyman",
    "wof:placetype":"venue"
},
  "geometry": {"coordinates":[-121.99328199999999,38.239365],"type":"Point"}
}