{
  "type": "Feature",
  "properties": {
    "iso:country":"US",
    "sg:address":"5770 Nicolle St",
    "sg:city":"Ventura",
    "sg:classifiers":[
        {
            "category":"Retail",
            "subcategory":"Auto Repair",
            "type":"Services"
        }
    ],
    "sg:phone":"+1 805 642 0530",
    "sg:postcode":"93003",
    "sg:province":"CA",
    "sg:tags":[
        "automobile",
        "top",
        "upholstery"
    ],
    "wof:name":"Quality Auto Upholstery",
    "wof:placetype":"venue"
},
  "geometry": {"coordinates":[-119.21066399999999,34.247403],"type":"Point"}
}