{
  "type": "Feature",
  "properties": {
    "iso:country":"US",
    "sg:address":"2600 Sacramento St",
    "sg:city":"San Francisco",
    "sg:classifiers":[
        {
            "category":"Personal",
            "subcategory":"Beauty Salon",
            "type":"Services"
        }
    ],
    "sg:phone":"+1 415 931 7091",
    "sg:postcode":"94115",
    "sg:province":"CA",
    "sg:tags":[
        "hair"
    ],
    "sg:website":"www.renaissancesalonsf.com",
    "wof:name":"Renaissance Salon",
    "wof:placetype":"venue"
},
  "geometry": {"coordinates":[-122.435695,37.789636],"type":"Point"}
}