{
  "type": "Feature",
  "properties": {
    "iso:country":"US",
    "sg:address":"505 S Flower St # B15",
    "sg:city":"Los Angeles",
    "sg:classifiers":[
        {
            "category":"Fast Food",
            "type":"Food & Drink"
        },
        {
            "category":"Restaurant",
            "type":"Food & Drink"
        }
    ],
    "sg:phone":"+1 213 488 0299",
    "sg:postcode":"90071",
    "sg:province":"CA",
    "sg:tags":[
        "japanese"
    ],
    "sg:website":"www.samuraisams.net/",
    "wof:name":"Samurai Sam's Terriyaki Grill",
    "wof:placetype":"venue"
},
  "geometry": {"coordinates":[-118.256156,34.051519],"type":"Point"}
}