{
  "type": "Feature",
  "properties": {
    "iso:country":"US",
    "sg:address":"4449 N Brawley Ave",
    "sg:city":"Fresno",
    "sg:classifiers":[
        {
            "category":"Building & Trades",
            "subcategory":"Construction",
            "type":"Services"
        }
    ],
    "sg:phone":"+1 559 275 6899",
    "sg:postcode":"93722",
    "sg:province":"CA",
    "sg:tags":[
        "designer",
        "dealer",
        "pool",
        "swimming"
    ],
    "sg:website":"www.valleypoolplastering.com",
    "wof:name":"Valley Pool Plastering",
    "wof:placetype":"venue"
},
  "geometry": {"coordinates":[-119.862543,36.801263],"type":"Point"}
}