{
  "type": "Feature",
  "properties": {
    "addr:full":"12716 Dorina Pl Granada Hills CA 91344",
    "addr:housenumber":"12716",
    "addr:postcode":"91344",
    "addr:street":"Dorina Pl",
    "iso:country":"US",
    "sg:address":"12716 Dorina Pl",
    "sg:city":"Granada Hills",
    "sg:classifiers":[
        {
            "category":"Manufacturing",
            "subcategory":"Retail Goods",
            "type":"Manufacturing & Wholesale Goods"
        }
    ],
    "sg:phone":"+1 818 368 7299",
    "sg:postcode":"91344",
    "sg:province":"CA",
    "sg:tags":[
        "manufacturer"
    ],
    "wof:name":"Findian Manufacturing Co",
    "wof:placetype":"venue"
},
  "geometry": {"coordinates":[-118.50514699999999,34.300339],"type":"Point"}
}