{
  "type": "Feature",
  "properties": {
    "addr:full":"4037 Market St Riverside CA 92501",
    "addr:housenumber":"4037",
    "addr:postcode":"92501",
    "addr:street":"Market St",
    "iso:country":"US",
    "sg:address":"4037 Market St",
    "sg:city":"Riverside",
    "sg:classifiers":[
        {
            "category":"Professional",
            "subcategory":"Lawyer & Legal Services",
            "type":"Services"
        },
        {
            "category":"Banks & Credit Unions",
            "subcategory":"Financial Services",
            "type":"Services"
        },
        {
            "category":"Social Services",
            "subcategory":"Adult Care",
            "type":"Services"
        }
    ],
    "sg:phone":"+1 951 784 1810",
    "sg:postcode":"92501",
    "sg:province":"CA",
    "sg:tags":[
        "bankruptcy",
        "attorney",
        "family",
        "divorce",
        "worker",
        "benefit",
        "compensation",
        "child",
        "employee",
        "law",
        "custody",
        "guardianship"
    ],
    "sg:website":"http://www.thomashamiltonattorney.com",
    "wof:name":"Hamilton Thomas H",
    "wof:placetype":"venue"
},
  "geometry": {"coordinates":[-117.37727,33.980181],"type":"Point"}
}