{
  "type": "Feature",
  "properties": {
    "addr:full":"8706 S Main Street Los Angeles CA 90003",
    "addr:housenumber":"8706",
    "addr:postcode":"90003",
    "addr:street":"S Main Street",
    "iso:country":"US",
    "sg:address":"8706 S Main Street",
    "sg:city":"Los Angeles",
    "sg:classifiers":[
        {
            "category":"Food & Beverages",
            "subcategory":"Groceries & Convenience Stores",
            "type":"Retail Goods"
        }
    ],
    "sg:phone":"+1 323 565 4038",
    "sg:postcode":"90003",
    "sg:province":"CA",
    "wof:name":"La Colmena Mini Market",
    "wof:placetype":"venue"
},
  "geometry": {"coordinates":[-118.274007,33.95877],"type":"Point"}
}