{
  "type": "Feature",
  "properties": {
    "iso:country":"US",
    "sg:address":"3798 Grand Ave Ste 3",
    "sg:city":"Oakland",
    "sg:classifiers":[
        {
            "category":"Personal",
            "subcategory":"Massage",
            "type":"Services"
        }
    ],
    "sg:phone":"+1 510 541 2715",
    "sg:postcode":"94610",
    "sg:province":"CA",
    "wof:name":"The Goose Sisters Healing Center",
    "wof:placetype":"venue"
},
  "geometry": {"coordinates":[-122.245152,37.817512],"type":"Point"}
}