{
  "type": "Feature",
  "properties": {
    "iso:country":"US",
    "sg:address":"1570 Gladding Ct",
    "sg:city":"Milpitas",
    "sg:classifiers":[
        {
            "category":"Building & Trades",
            "subcategory":"Construction",
            "type":"Services"
        }
    ],
    "sg:phone":"+1 408 263 1616",
    "sg:postcode":"95035",
    "sg:province":"CA",
    "sg:tags":[
        "drywall",
        "contractor"
    ],
    "wof:name":"Custom Drywall Inc",
    "wof:placetype":"venue"
},
  "geometry": {"coordinates":[-121.888903,37.411666],"type":"Point"}
}