{
  "type": "Feature",
  "properties": {
    "iso:country":"US",
    "sg:address":"1138 S de Anza Blvd",
    "sg:city":"San Jose",
    "sg:classifiers":[
        {
            "category":"Shopping",
            "subcategory":"Florist",
            "type":"Retail Goods"
        }
    ],
    "sg:phone":"+1 408 252 3560",
    "sg:postcode":"95129",
    "sg:province":"CA",
    "sg:website":"www.cupertinoflorist.com",
    "wof:name":"Cupertino Florist",
    "wof:placetype":"venue"
},
  "geometry": {"coordinates":[-122.032181,37.305991],"type":"Point"}
}