{
  "type": "Feature",
  "properties": {
    "addr:full":"1201 E Manning Ave Reedley CA 93654",
    "addr:housenumber":"1201",
    "addr:postcode":"93654",
    "addr:street":"E Manning Ave",
    "iso:country":"US",
    "sg:address":"1201 E Manning Ave",
    "sg:city":"Reedley",
    "sg:classifiers":[
        {
            "category":"Shopping",
            "subcategory":"Department Store",
            "type":"Retail Goods"
        }
    ],
    "sg:phone":"+1 559 638 6666",
    "sg:postcode":"93654",
    "sg:province":"CA",
    "wof:name":"Factory 2-U",
    "wof:placetype":"venue"
},
  "geometry": {"coordinates":[-119.435883,36.604124],"type":"Point"}
}