{
  "type": "Feature",
  "properties": {
    "addr:full":"2201 W 1st St Santa Ana CA 92703",
    "addr:housenumber":"2201",
    "addr:postcode":"92703",
    "addr:street":"W 1St St",
    "iso:country":"US",
    "sg:address":"2201 W 1st St",
    "sg:city":"Santa Ana",
    "sg:classifiers":[
        {
            "category":"Food & Beverages",
            "subcategory":"Groceries & Convenience Stores",
            "type":"Retail Goods"
        }
    ],
    "sg:phone":"+1 714 550 7203",
    "sg:postcode":"92703",
    "sg:province":"CA",
    "sg:tags":[
        "market"
    ],
    "wof:name":"Farmers Santa Ana",
    "wof:placetype":"venue"
},
  "geometry": {"coordinates":[-117.89821499999999,33.745311],"type":"Point"}
}