{
  "type": "Feature",
  "properties": {
    "addr:full":"3700 W Riego Rd Elverta CA 95626",
    "addr:housenumber":"3700",
    "addr:postcode":"ca 95626",
    "addr:street":"W Riego Rd",
    "iso:country":"US",
    "sg:address":"3700 W Riego Rd",
    "sg:city":"Elverta",
    "sg:classifiers":[
        {
            "category":"Manufacturing",
            "subcategory":"Building Materials",
            "type":"Manufacturing & Wholesale Goods"
        }
    ],
    "sg:phone":"+1 916 991 4400",
    "sg:postcode":"95626",
    "sg:province":"CA",
    "sg:tags":[
        "member",
        "mfg",
        "wood",
        "structural"
    ],
    "sg:website":"www.wwftruss.com",
    "wof:name":"Western Wood Fabricators",
    "wof:placetype":"venue"
},
  "geometry": {"coordinates":[-121.485527,38.751335],"type":"Point"}
}