{
  "type": "Feature",
  "properties": {
    "iso:country":"US",
    "sg:address":"336 S Spalding Dr",
    "sg:city":"Beverly Hills",
    "sg:classifiers":[
        {
            "category":"Professional",
            "subcategory":"Advertising",
            "type":"Services"
        }
    ],
    "sg:phone":"+1 310 657 4399",
    "sg:postcode":"90212",
    "sg:province":"CA",
    "wof:name":"Compass Advertising",
    "wof:placetype":"venue"
},
  "geometry": {"coordinates":[-118.408828,34.060306],"type":"Point"}
}