{
  "type": "Feature",
  "properties": {
    "addr:full":"41631 Lori Ln Hemet CA 92544",
    "addr:housenumber":"41631",
    "addr:postcode":"92544",
    "addr:street":"Lori Ln",
    "iso:country":"US",
    "sg:address":"41631 Lori Ln",
    "sg:city":"Hemet",
    "sg:classifiers":[
        {
            "category":"Health Services",
            "subcategory":"Nursing And Care Facility",
            "type":"Services"
        }
    ],
    "sg:phone":"+1 951 766 1402",
    "sg:postcode":"92544",
    "sg:province":"CA",
    "sg:tags":[
        "home",
        "convalescent"
    ],
    "wof:name":"A Quality Life Board & Care",
    "wof:placetype":"venue"
},
  "geometry": {"coordinates":[-116.935086,33.741837],"type":"Point"}
}