{
  "type": "Feature",
  "properties": {
    "iso:country":"US",
    "sg:address":"524 Myrtle St",
    "sg:city":"Glendale",
    "sg:classifiers":[
        {
            "category":"Freight",
            "type":"Transportation"
        }
    ],
    "sg:phone":"+1 818 244 2173",
    "sg:postcode":"91203",
    "sg:province":"CA",
    "sg:tags":[
        "distance",
        "long",
        "trucking"
    ],
    "wof:name":"Damco Transportation",
    "wof:placetype":"venue"
},
  "geometry": {"coordinates":[-118.26627,34.150719],"type":"Point"}
}