{
  "type": "Feature",
  "properties": {
    "iso:country":"US",
    "sg:address":"865 Battery St",
    "sg:city":"San Francisco",
    "sg:classifiers":[
        {
            "category":"Communications",
            "subcategory":"Radio Station",
            "type":"Services"
        }
    ],
    "sg:phone":"+1 415 765 4094",
    "sg:postcode":"94111",
    "sg:province":"CA",
    "sg:tags":[
        "broadcast"
    ],
    "wof:name":"Kcbs News Radio 74",
    "wof:placetype":"venue"
},
  "geometry": {"coordinates":[-122.401217,37.798898],"type":"Point"}
}