{
  "type": "Feature",
  "properties": {
    "iso:country":"US",
    "sg:address":"505 N Brand Blvd",
    "sg:city":"Glendale",
    "sg:classifiers":[
        {
            "category":"Food & Beverages",
            "subcategory":"Groceries & Convenience Stores",
            "type":"Retail Goods"
        }
    ],
    "sg:phone":"+1 818 409 0128",
    "sg:postcode":"91203",
    "sg:province":"CA",
    "wof:name":"Shoppe",
    "wof:placetype":"venue"
},
  "geometry": {"coordinates":[-118.255193,34.154604],"type":"Point"}
}