{
  "type": "Feature",
  "properties": {
    "addr:full":"7552 Fay Ave San Diego CA 92037",
    "addr:housenumber":"7552",
    "addr:postcode":"92037",
    "addr:street":"Fay Ave",
    "iso:country":"US",
    "sg:address":"7552 Fay Ave",
    "sg:city":"San Diego",
    "sg:classifiers":[
        {
            "category":"Personal",
            "subcategory":"Beauty Salon",
            "type":"Services"
        },
        {
            "category":"Personal",
            "type":"Services"
        }
    ],
    "sg:phone":"+1 858 353 8736",
    "sg:postcode":"92037",
    "sg:province":"CA",
    "sg:tags":[
        "hair",
        "planning",
        "makeup",
        "wedding",
        "artist"
    ],
    "sg:website":"www.threewaysbeautiful.com",
    "wof:name":"Three Ways Beautiful",
    "wof:placetype":"venue"
},
  "geometry": {"coordinates":[-117.27404,32.841163],"type":"Point"}
}