{
  "type": "Feature",
  "properties": {
    "iso:country":"US",
    "sg:address":"1107 Montana Ave",
    "sg:city":"Santa Monica",
    "sg:classifiers":[
        {
            "category":"Shopping",
            "type":"Retail Goods"
        }
    ],
    "sg:phone":"+1 310 276 9670",
    "sg:postcode":"90403",
    "sg:province":"CA",
    "sg:tags":[
        "cosmetic",
        "perfume"
    ],
    "wof:name":"Rescu-A Cosmetique",
    "wof:placetype":"venue"
},
  "geometry": {"coordinates":[-118.497612,34.030302],"type":"Point"}
}