{
  "type": "Feature",
  "properties": {
    "iso:country":"US",
    "sg:address":"7312 Scout Ave",
    "sg:city":"Bell Gardens",
    "sg:classifiers":[
        {
            "category":"Manufacturing",
            "subcategory":"Tools & Machinery",
            "type":"Manufacturing & Wholesale Goods"
        }
    ],
    "sg:phone":"+1 562 927 8424",
    "sg:postcode":"90201",
    "sg:province":"CA",
    "sg:tags":[
        "pattern",
        "industrial",
        "maker",
        "mfg"
    ],
    "wof:name":"Trinity Pattern Co",
    "wof:placetype":"venue"
},
  "geometry": {"coordinates":[-118.14162,33.963763],"type":"Point"}
}