{
  "type": "Feature",
  "properties": {
    "iso:country":"US",
    "sg:address":"1318 W Workman Ave",
    "sg:city":"West Covina",
    "sg:classifiers":[
        {
            "category":"Manufacturing",
            "subcategory":"Retail Goods",
            "type":"Manufacturing & Wholesale Goods"
        }
    ],
    "sg:phone":"+1 626 339 0555",
    "sg:postcode":"91790",
    "sg:province":"CA",
    "sg:tags":[
        "lead",
        "mfg"
    ],
    "wof:name":"Ann Cline Studio Inc",
    "wof:placetype":"venue"
},
  "geometry": {"coordinates":[-117.933634,34.075419],"type":"Point"}
}