{
  "type": "Feature",
  "properties": {
    "addr:full":"2000 S Main Street Los Angeles CA 90007",
    "addr:housenumber":"2000",
    "addr:postcode":"90007",
    "addr:street":"S Main Street",
    "iso:country":"US",
    "sg:address":"2000 S Main Street",
    "sg:city":"Los Angeles",
    "sg:classifiers":[
        {
            "category":"Shopping",
            "subcategory":"Clothing, Apparel, & Fashions",
            "type":"Retail Goods"
        }
    ],
    "sg:phone":"+1 213 741 0905",
    "sg:postcode":"90007",
    "sg:province":"CA",
    "sg:tags":[
        "lingerie"
    ],
    "sg:website":"www.trashylingerie.com",
    "wof:name":"Trashy Lingerie Internet Offices",
    "wof:placetype":"venue"
},
  "geometry": {"coordinates":[-118.26564,34.029797],"type":"Point"}
}