{
  "type": "Feature",
  "properties": {
    "iso:country":"US",
    "sg:address":"1800 23rd St",
    "sg:city":"San Francisco",
    "sg:classifiers":[
        {
            "category":"Food & Beverages",
            "subcategory":"Groceries & Convenience Stores",
            "type":"Retail Goods"
        }
    ],
    "sg:phone":"+1 415 282 9619",
    "sg:postcode":"94107",
    "sg:province":"CA",
    "sg:tags":[
        "grocer"
    ],
    "wof:name":"Four Way Market",
    "wof:placetype":"venue"
},
  "geometry": {"coordinates":[-122.39869299999999,37.754745],"type":"Point"}
}