{
  "type": "Feature",
  "properties": {
    "addr:full":"11500 W Eight Mile Rd Stockton CA 95219",
    "addr:housenumber":"11500",
    "addr:postcode":"95219",
    "addr:street":"W Eight Mile Rd",
    "iso:country":"US",
    "sg:address":"11500 W Eight Mile Rd",
    "sg:city":"Stockton",
    "sg:classifiers":[
        {
            "category":"Autos & Motor Vehicles",
            "subcategory":"Boat Sales",
            "type":"Retail Goods"
        }
    ],
    "sg:phone":"+1 209 476 0103",
    "sg:postcode":"95219",
    "sg:province":"CA",
    "sg:tags":[
        "dealer",
        "sales"
    ],
    "wof:name":"Honker Cut Marine",
    "wof:placetype":"venue"
},
  "geometry": {"coordinates":[-121.457943,38.059178],"type":"Point"}
}