{
  "type": "Feature",
  "properties": {
    "iso:country":"US",
    "sg:address":"520 Capitol Mall Ste 380",
    "sg:city":"Sacramento",
    "sg:classifiers":[
        {
            "category":"Professional",
            "subcategory":"Lawyer & Legal Services",
            "type":"Services"
        }
    ],
    "sg:phone":"+1 916 443 6461",
    "sg:postcode":"95814",
    "sg:province":"CA",
    "sg:tags":[
        "divorce",
        "law",
        "family"
    ],
    "wof:name":"Heather A Tattershall",
    "wof:placetype":"venue"
},
  "geometry": {"coordinates":[-121.50080699999999,38.578148],"type":"Point"}
}