{
  "type": "Feature",
  "properties": {
    "addr:full":"1883 London Ranch Rd Glen Ellen CA 95442",
    "addr:housenumber":"1883",
    "addr:postcode":"95442",
    "addr:street":"London Ranch Rd",
    "iso:country":"US",
    "sg:address":"1883 London Ranch Rd",
    "sg:city":"Glen Ellen",
    "sg:classifiers":[
        {
            "category":"Manufacturing",
            "subcategory":"Food",
            "type":"Manufacturing & Wholesale Goods"
        }
    ],
    "sg:phone":"+1 707 935 3000",
    "sg:postcode":"95442",
    "sg:province":"CA",
    "sg:tags":[
        "vineyard",
        "grape",
        "mfg"
    ],
    "sg:website":"www.benziger.com",
    "wof:name":"Benziger Family Winery",
    "wof:placetype":"venue"
},
  "geometry": {"coordinates":[-122.539535,38.358237],"type":"Point"}
}