{
  "type": "Feature",
  "properties": {
    "addr:full":"1639 W 252nd St Harbor City CA 90710",
    "addr:housenumber":"1639",
    "addr:postcode":"90710",
    "addr:street":"W 252Nd St",
    "iso:country":"US",
    "sg:address":"1639 W 252nd St",
    "sg:city":"Harbor City",
    "sg:classifiers":[
        {
            "category":"Building & Trades",
            "subcategory":"Landscaping Services",
            "type":"Services"
        }
    ],
    "sg:phone":"+1 310 530 6301",
    "sg:postcode":"90710",
    "sg:province":"CA",
    "wof:name":"Garden Builders",
    "wof:placetype":"venue"
},
  "geometry": {"coordinates":[-118.30646,33.795846],"type":"Point"}
}