{
  "type": "Feature",
  "properties": {
    "iso:country":"US",
    "sg:address":"303 Brookside Ave",
    "sg:city":"Redlands",
    "sg:classifiers":[
        {
            "category":"Professional",
            "subcategory":"Lawyer & Legal Services",
            "type":"Services"
        }
    ],
    "sg:phone":"+1 909 307 6282",
    "sg:postcode":"92373",
    "sg:province":"CA",
    "sg:tags":[
        "attorney"
    ],
    "wof:name":"Bethel Bishop & Co",
    "wof:placetype":"venue"
},
  "geometry": {"coordinates":[-117.187133,34.054483],"type":"Point"}
}