{
  "type": "Feature",
  "properties": {
    "iso:country":"US",
    "sg:address":"7980 Santa Monica Blvd",
    "sg:city":"West Hollywood",
    "sg:classifiers":[
        {
            "category":"Home & Garden",
            "subcategory":"Home Furnishings",
            "type":"Retail Goods"
        }
    ],
    "sg:phone":"+1 323 656 3900",
    "sg:postcode":"90046",
    "sg:province":"CA",
    "sg:tags":[
        "decor"
    ],
    "sg:website":"www.candledelirium.com",
    "wof:name":"Candle Delirium",
    "wof:placetype":"venue"
},
  "geometry": {"coordinates":[-118.364355,34.090789],"type":"Point"}
}