{
  "type": "Feature",
  "properties": {
    "iso:country":"US",
    "sg:address":"21650 Oxnard St",
    "sg:city":"Woodland Hills",
    "sg:classifiers":[
        {
            "category":"Professional",
            "subcategory":"Lawyer & Legal Services",
            "type":"Services"
        }
    ],
    "sg:phone":"+1 818 593 6355",
    "sg:postcode":"91367",
    "sg:province":"CA",
    "wof:name":"Stacey Sherman-Attorney At Law",
    "wof:placetype":"venue"
},
  "geometry": {"coordinates":[-118.600998,34.1791],"type":"Point"}
}