{
  "type": "Feature",
  "properties": {
    "iso:country":"US",
    "sg:address":"11380 Cmt Corriente",
    "sg:city":"San Diego",
    "sg:classifiers":[
        {
            "category":"Banks & Credit Unions",
            "subcategory":"Financial Services",
            "type":"Services"
        }
    ],
    "sg:phone":"+1 858 451 1308",
    "sg:postcode":"92128",
    "sg:province":"CA",
    "sg:tags":[
        "trust",
        "management"
    ],
    "wof:name":"Hassan Living Trust 04 10",
    "wof:placetype":"venue"
},
  "geometry": {"coordinates":[-117.076347,32.998573],"type":"Point"}
}