{
  "type": "Feature",
  "properties": {
    "iso:country":"US",
    "sg:address":"7708 Selkirk Dr",
    "sg:city":"Bakersfield",
    "sg:classifiers":[
        {
            "category":"Retail",
            "subcategory":"Laundry & Dry Cleaning",
            "type":"Services"
        }
    ],
    "sg:phone":"+1 661 831 7988",
    "sg:postcode":"93309",
    "sg:province":"CA",
    "sg:tags":[
        "cleaners",
        "rug",
        "carpet"
    ],
    "wof:name":"Perfection In Carpet Care",
    "wof:placetype":"venue"
},
  "geometry": {"coordinates":[-119.087833,35.334438],"type":"Point"}
}