{
  "type": "Feature",
  "properties": {
    "iso:country":"US",
    "sg:address":"2605 Mount Vernon Ave",
    "sg:city":"Bakersfield",
    "sg:classifiers":[
        {
            "category":"Real Estate",
            "subcategory":"Real Estate Operator",
            "type":"Services"
        }
    ],
    "sg:phone":"+1 661 872 0255",
    "sg:postcode":"93306",
    "sg:province":"CA",
    "sg:tags":[
        "apartment"
    ],
    "wof:name":"Manor Gardens",
    "wof:placetype":"venue"
},
  "geometry": {"coordinates":[-118.96747999999999,35.393885],"type":"Point"}
}