{
  "type": "Feature",
  "properties": {
    "addr:full":"1224 Village Way Santa Ana CA 92705",
    "addr:housenumber":"1224",
    "addr:postcode":"92705",
    "addr:street":"Village Way",
    "iso:country":"US",
    "sg:address":"1224 Village Way",
    "sg:city":"Santa Ana",
    "sg:classifiers":[
        {
            "category":"Real Estate",
            "subcategory":"Architect",
            "type":"Services"
        }
    ],
    "sg:phone":"+1 714 543 8352",
    "sg:postcode":"92705",
    "sg:province":"CA",
    "wof:name":"Beck Moffett & Assoc",
    "wof:placetype":"venue"
},
  "geometry": {"coordinates":[-117.835939,33.733474],"type":"Point"}
}