{
  "type": "Feature",
  "properties": {
    "addr:full":"2232 Sunshine Way Palm Springs CA 92264",
    "addr:housenumber":"2232",
    "addr:postcode":"92264",
    "addr:street":"Sunshine Way",
    "iso:country":"US",
    "sg:address":"2232 Sunshine Way",
    "sg:city":"Palm Springs",
    "sg:classifiers":[
        {
            "category":"Professional",
            "type":"Services"
        }
    ],
    "sg:phone":"+1 760 323 4643",
    "sg:postcode":"92264",
    "sg:province":"CA",
    "wof:name":"Samuel Perlmutter",
    "wof:placetype":"venue"
},
  "geometry": {"coordinates":[-116.52157699999999,33.814486],"type":"Point"}
}