{
  "type": "Feature",
  "properties": {
    "addr:full":"6170 Hamner Ave Mira Loma CA 91752",
    "addr:housenumber":"6170",
    "addr:postcode":"91752",
    "addr:street":"Hamner Ave",
    "iso:country":"US",
    "sg:address":"6170 Hamner Ave",
    "sg:city":"Mira Loma",
    "sg:classifiers":[
        {
            "category":"Food & Beverages",
            "subcategory":"Groceries & Convenience Stores",
            "type":"Retail Goods"
        }
    ],
    "sg:phone":"+1 951 360 1901",
    "sg:postcode":"91752",
    "sg:province":"CA",
    "sg:tags":[
        "grocer"
    ],
    "wof:name":"Vons Co",
    "wof:placetype":"venue"
},
  "geometry": {"coordinates":[-117.558255,33.981072],"type":"Point"}
}