{
  "type": "Feature",
  "properties": {
    "iso:country":"US",
    "sg:address":"2413 Harbor Blvd",
    "sg:city":"Ventura",
    "sg:classifiers":[
        {
            "category":"Retail",
            "subcategory":"Laundry & Dry Cleaning",
            "type":"Services"
        }
    ],
    "sg:phone":"+1 805 642 7355",
    "sg:postcode":"93001",
    "sg:province":"CA",
    "sg:tags":[
        "laundries-self",
        "operated",
        "washer",
        "dryer",
        "coin"
    ],
    "wof:name":"Marina Village Wash & Dry",
    "wof:placetype":"venue"
},
  "geometry": {"coordinates":[-119.270081,34.264497],"type":"Point"}
}