{
  "type": "Feature",
  "properties": {
    "iso:country":"US",
    "sg:address":"23632 El Toro Rd",
    "sg:city":"Lake Forest",
    "sg:classifiers":[
        {
            "category":"Restaurant",
            "type":"Food & Drink"
        }
    ],
    "sg:menulink":"http://www.allmenus.com/ca/el-toro/41535-johnny-rockets/menu/",
    "sg:phone":"+1 949 768 6042",
    "sg:postcode":"92630",
    "sg:province":"CA",
    "sg:tags":[
        "burger",
        "american"
    ],
    "wof:name":"Johnny Rockets",
    "wof:placetype":"venue"
},
  "geometry": {"coordinates":[-117.70149499999999,33.619674],"type":"Point"}
}