{
  "type": "Feature",
  "properties": {
    "addr:full":"9236 Beaver Ave Phelan CA 92371",
    "addr:housenumber":"9236",
    "addr:postcode":"92371",
    "addr:street":"Beaver Ave",
    "iso:country":"US",
    "sg:address":"9236 Beaver Ave",
    "sg:city":"Phelan",
    "sg:classifiers":[
        {
            "category":"Retail",
            "subcategory":"Laundry & Dry Cleaning",
            "type":"Services"
        }
    ],
    "sg:phone":"+1 760 949 4253",
    "sg:postcode":"92371",
    "sg:province":"CA",
    "sg:tags":[
        "cleaners",
        "rug",
        "carpet"
    ],
    "wof:name":"Hot On The Spot Carpet",
    "wof:placetype":"venue"
},
  "geometry": {"coordinates":[-117.459908,34.417977],"type":"Point"}
}