{
  "type": "Feature",
  "properties": {
    "iso:country":"US",
    "sg:address":"914 S Truro Ave",
    "sg:city":"Inglewood",
    "sg:classifiers":[
        {
            "category":"Personal",
            "subcategory":"Beauty Salon",
            "type":"Services"
        }
    ],
    "sg:phone":"+1 310 412 5081",
    "sg:postcode":"90301",
    "sg:province":"CA",
    "wof:name":"Super Class Beauty Salon",
    "wof:placetype":"venue"
},
  "geometry": {"coordinates":[-118.358261,33.95114],"type":"Point"}
}