{
  "type": "Feature",
  "properties": {
    "addr:full":"354 S Spring St Los Angeles CA 90013",
    "addr:housenumber":"354",
    "addr:postcode":"90013",
    "addr:street":"S Spring St",
    "iso:country":"US",
    "sg:address":"354 S Spring St",
    "sg:city":"Los Angeles",
    "sg:classifiers":[
        {
            "category":"Government",
            "subcategory":"Office",
            "type":"Public Place"
        }
    ],
    "sg:phone":"+1 213 680 1100",
    "sg:postcode":"90013",
    "sg:province":"CA",
    "sg:tags":[
        "development",
        "village"
    ],
    "wof:name":"Popular Center Management Off",
    "wof:placetype":"venue"
},
  "geometry": {"coordinates":[-118.247618,34.049571],"type":"Point"}
}