{
  "type": "Feature",
  "properties": {
    "addr:full":"17105 Terra Linda St Victorville CA 92395",
    "addr:housenumber":"17105",
    "addr:postcode":"92395",
    "addr:street":"Terra Linda St",
    "iso:country":"US",
    "sg:address":"17105 Terra Linda St",
    "sg:city":"Victorville",
    "sg:classifiers":[
        {
            "category":"Professional",
            "subcategory":"Management & Consulting",
            "type":"Services"
        }
    ],
    "sg:phone":"+1 760 951 9995",
    "sg:postcode":"92395",
    "sg:province":"CA",
    "sg:tags":[
        "consultant",
        "telecommunication"
    ],
    "wof:name":"HCI Inc",
    "wof:placetype":"venue"
},
  "geometry": {"coordinates":[-117.292061,34.495484],"type":"Point"}
}