{
  "type": "Feature",
  "properties": {
    "iso:country":"US",
    "sg:address":"4525 Ambrose Ave.",
    "sg:city":"Los Angeles",
    "sg:classifiers":[
        {
            "category":"Banks & Credit Unions",
            "subcategory":"Financial Services",
            "type":"Services"
        }
    ],
    "sg:phone":"+1 323 663 5727",
    "sg:postcode":"90027",
    "sg:province":"CA",
    "wof:name":"Pamela Price Ea Inc",
    "wof:placetype":"venue"
},
  "geometry": {"coordinates":[-118.288404,34.109961],"type":"Point"}
}