{
  "type": "Feature",
  "properties": {
    "iso:country":"US",
    "sg:address":"7020 N Marks Ave",
    "sg:city":"Fresno",
    "sg:classifiers":[
        {
            "category":"Banks & Credit Unions",
            "subcategory":"Bank",
            "type":"Services"
        }
    ],
    "sg:phone":"+1 559 449 7420",
    "sg:postcode":"93711",
    "sg:province":"CA",
    "sg:website":"www.tricountiesbank.com",
    "wof:name":"Tri Counties Bank",
    "wof:placetype":"venue"
},
  "geometry": {"coordinates":[-119.84742300000001,36.839118],"type":"Point"}
}