{
  "type": "Feature",
  "properties": {
    "addr:full":"23545 Crenshaw Blvd Torrance CA 90505",
    "addr:housenumber":"23545",
    "addr:postcode":"90505",
    "addr:street":"Crenshaw Blvd",
    "iso:country":"US",
    "sg:address":"23545 Crenshaw Blvd",
    "sg:city":"Torrance",
    "sg:classifiers":[
        {
            "category":"Health Services",
            "subcategory":"Chiropractor",
            "type":"Services"
        }
    ],
    "sg:phone":"+1 310 534 0098",
    "sg:postcode":"90505",
    "sg:province":"CA",
    "wof:name":"Rendo Chiropractic",
    "wof:placetype":"venue"
},
  "geometry": {"coordinates":[-118.328003,33.812099],"type":"Point"}
}