{
  "type": "Feature",
  "properties": {
    "iso:country":"US",
    "sg:address":"7601 Timberlake Way",
    "sg:city":"Sacramento",
    "sg:classifiers":[
        {
            "category":"Health Services",
            "subcategory":"Medical Lab",
            "type":"Services"
        }
    ],
    "sg:phone":"+1 916 423 3000",
    "sg:postcode":"95823",
    "sg:province":"CA",
    "sg:tags":[
        "laboratory"
    ],
    "wof:name":"Diagnostic Center",
    "wof:placetype":"venue"
},
  "geometry": {"coordinates":[-121.414773,38.465251],"type":"Point"}
}