{
  "type": "Feature",
  "properties": {
    "addr:full":"211 Los Cerritos Mall Cerritos CA 90703",
    "addr:housenumber":"211",
    "addr:postcode":"ca 90703",
    "addr:street":"Los Cerritos Mall",
    "iso:country":"US",
    "sg:address":"211 Los Cerritos Mall",
    "sg:city":"Cerritos",
    "sg:classifiers":[
        {
            "category":"Restaurant",
            "type":"Food & Drink"
        }
    ],
    "sg:phone":"+1 562 860 7022",
    "sg:postcode":"90703",
    "sg:province":"CA",
    "sg:tags":[
        "traditional",
        "american"
    ],
    "wof:name":"Johnny Rockets",
    "wof:placetype":"venue"
},
  "geometry": {"coordinates":[-118.095001,33.8652],"type":"Point"}
}