{
  "type": "Feature",
  "properties": {
    "addr:full":"9047 Arrow Rte Rancho Cucamonga CA 91730",
    "addr:housenumber":"9047",
    "addr:postcode":"91730",
    "addr:street":"Arrow Rte",
    "iso:country":"US",
    "sg:address":"9047 Arrow Rte",
    "sg:city":"Rancho Cucamonga",
    "sg:classifiers":[
        {
            "category":"Restaurant",
            "type":"Food & Drink"
        }
    ],
    "sg:phone":"+1 909 989 3025",
    "sg:postcode":"91730",
    "sg:province":"CA",
    "sg:tags":[
        "delicatessen"
    ],
    "wof:name":"Jersey Deli II",
    "wof:placetype":"venue"
},
  "geometry": {"coordinates":[-117.607591,34.099269],"type":"Point"}
}