{
  "type": "Feature",
  "properties": {
    "addr:full":"20870 Saratoga Rd Sonora CA 95370",
    "addr:housenumber":"20870",
    "addr:postcode":"95370",
    "addr:street":"Saratoga Rd",
    "iso:country":"US",
    "sg:address":"20870 Saratoga Rd",
    "sg:city":"Sonora",
    "sg:classifiers":[
        {
            "category":"Building & Trades",
            "subcategory":"Construction",
            "type":"Services"
        }
    ],
    "sg:phone":"+1 209 532 6392",
    "sg:postcode":"95370",
    "sg:province":"CA",
    "sg:tags":[
        "wallcoverings-installation",
        "wallpaper",
        "painting",
        "contractor"
    ],
    "wof:name":"Strozier Painting",
    "wof:placetype":"venue"
},
  "geometry": {"coordinates":[-120.39462899999999,38.000542],"type":"Point"}
}