{
  "type": "Feature",
  "properties": {
    "iso:country":"US",
    "sg:address":"14411 Brookhurst St",
    "sg:city":"Garden Grove",
    "sg:classifiers":[
        {
            "category":"Real Estate",
            "subcategory":"Real Estate Services",
            "type":"Services"
        }
    ],
    "sg:phone":"+1 714 531 7936",
    "sg:postcode":"92843",
    "sg:province":"CA",
    "wof:name":"Golden Real Estate",
    "wof:placetype":"venue"
},
  "geometry": {"coordinates":[-117.95500199999999,33.753799],"type":"Point"}
}