{
  "type": "Feature",
  "properties": {
    "iso:country":"US",
    "sg:address":"1800 Trousdale Dr",
    "sg:city":"Burlingame",
    "sg:classifiers":[
        {
            "category":"Professional",
            "subcategory":"Lawyer & Legal Services",
            "type":"Services"
        }
    ],
    "sg:phone":"+1 650 692 7481",
    "sg:postcode":"94010",
    "sg:province":"CA",
    "wof:name":"Holt Douglas W Atty",
    "wof:placetype":"venue"
},
  "geometry": {"coordinates":[-122.386002,37.591999],"type":"Point"}
}