{
  "type": "Feature",
  "properties": {
    "addr:full":"1063 Monroe St Santa Clara CA 95050",
    "addr:housenumber":"1063",
    "addr:postcode":"95050",
    "addr:street":"Monroe St",
    "iso:country":"US",
    "sg:address":"1063 Monroe St",
    "sg:city":"Santa Clara",
    "sg:classifiers":[
        {
            "category":"Health Services",
            "subcategory":"Health Practitioner",
            "type":"Services"
        }
    ],
    "sg:phone":"+1 408 248 4303",
    "sg:postcode":"95050",
    "sg:province":"CA",
    "sg:tags":[
        "acupuncture"
    ],
    "wof:name":"Chan's Acupuncture Center",
    "wof:placetype":"venue"
},
  "geometry": {"coordinates":[-121.94899700000001,37.348999],"type":"Point"}
}