{
  "type": "Feature",
  "properties": {
    "addr:full":"1419 Broadway Alameda CA 94501",
    "addr:housenumber":"1419",
    "addr:postcode":"94501",
    "addr:street":"Broadway",
    "iso:country":"US",
    "sg:address":"1419 Broadway",
    "sg:city":"Alameda",
    "sg:classifiers":[
        {
            "category":"Professional",
            "subcategory":"Art Services",
            "type":"Services"
        }
    ],
    "sg:phone":"+1 510 865 5555",
    "sg:postcode":"94501",
    "sg:province":"CA",
    "sg:tags":[
        "photographers-portrait"
    ],
    "wof:name":"Passport Action Photo Svc",
    "wof:placetype":"venue"
},
  "geometry": {"coordinates":[-122.23892499999999,37.762748],"type":"Point"}
}