{
  "type": "Feature",
  "properties": {
    "iso:country":"US",
    "sg:address":"6500 Belleau Wood Ln",
    "sg:city":"Sacramento",
    "sg:classifiers":[
        {
            "category":"Manufacturing",
            "subcategory":"Tools & Machinery",
            "type":"Manufacturing & Wholesale Goods"
        }
    ],
    "sg:phone":"+1 408 422 6712",
    "sg:postcode":"95822",
    "sg:province":"CA",
    "sg:tags":[
        "spraying",
        "equipment"
    ],
    "sg:website":"www.eaglespraybooths.com",
    "wof:name":"G & D Enterprises",
    "wof:placetype":"venue"
},
  "geometry": {"coordinates":[-121.505226,38.505519],"type":"Point"}
}