{
  "type": "Feature",
  "properties": {
    "iso:country":"US",
    "sg:address":"33 Hazelwood Ave",
    "sg:city":"San Francisco",
    "sg:classifiers":[
        {
            "category":"Building & Trades",
            "subcategory":"Plumbing",
            "type":"Services"
        }
    ],
    "sg:phone":"+1 415 337 2109",
    "sg:postcode":"94112",
    "sg:province":"CA",
    "sg:tags":[
        "plumbing",
        "contractor"
    ],
    "wof:name":"Cai Plumbing Co",
    "wof:placetype":"venue"
},
  "geometry": {"coordinates":[-122.454074,37.728906],"type":"Point"}
}