{
  "type": "Feature",
  "properties": {
    "iso:country":"US",
    "sg:address":"1225 E Latham Ave",
    "sg:city":"Hemet",
    "sg:classifiers":[
        {
            "category":"Health Services",
            "subcategory":"Doctor",
            "type":"Services"
        }
    ],
    "sg:phone":"+1 951 929 2800",
    "sg:postcode":"92543",
    "sg:province":"CA",
    "sg:tags":[
        "physician",
        "surgeon",
        "nephrology",
        "kidneys",
        "surgeons"
    ],
    "sg:website":"http://www.hemetvalleyurology.com",
    "wof:name":"Hemet Valley Urology Center",
    "wof:placetype":"venue"
},
  "geometry": {"coordinates":[-116.95946000000001,33.749409],"type":"Point"}
}