{
  "type": "Feature",
  "properties": {
    "iso:country":"US",
    "sg:address":"1015 Market Ave",
    "sg:city":"San Pablo",
    "sg:classifiers":[
        {
            "category":"Retail",
            "subcategory":"Repair Shop",
            "type":"Services"
        }
    ],
    "sg:phone":"+1 510 235 2598",
    "sg:postcode":"94806",
    "sg:province":"CA",
    "sg:tags":[
        "lock",
        "locksmith"
    ],
    "wof:name":"Pick A Lock",
    "wof:placetype":"venue"
},
  "geometry": {"coordinates":[-122.357552,37.958776],"type":"Point"}
}