{
  "type": "Feature",
  "properties": {
    "addr:full":"10279 Field Ln Forestville CA 95436",
    "addr:housenumber":"10279",
    "addr:postcode":"95436",
    "addr:street":"Field Ln",
    "iso:country":"US",
    "sg:address":"10279 Field Ln",
    "sg:city":"Forestville",
    "sg:classifiers":[
        {
            "category":"Professional",
            "subcategory":"Art Services",
            "type":"Services"
        }
    ],
    "sg:phone":"+1 707 887 2825",
    "sg:postcode":"95436",
    "sg:province":"CA",
    "sg:tags":[
        "graphic",
        "designer"
    ],
    "sg:website":"http://www.alacartejewelry.com",
    "wof:name":"Alacarte Jewelry",
    "wof:placetype":"venue"
},
  "geometry": {"coordinates":[-122.918843,38.508217],"type":"Point"}
}