{
  "type": "Feature",
  "properties": {
    "iso:country":"US",
    "sg:address":"14108 Doty Ave",
    "sg:city":"Hawthorne",
    "sg:classifiers":[
        {
            "category":"Professional",
            "subcategory":"Art Services",
            "type":"Services"
        }
    ],
    "sg:phone":"+1 310 973 0475",
    "sg:postcode":"90250",
    "sg:province":"CA",
    "sg:tags":[
        "graphic",
        "designer"
    ],
    "wof:name":"East West Design",
    "wof:placetype":"venue"
},
  "geometry": {"coordinates":[-118.33942399999999,33.903405],"type":"Point"}
}