{
  "type": "Feature",
  "properties": {
    "addr:full":"2232 E 7th St Long Beach CA 90804",
    "addr:housenumber":"2232",
    "addr:postcode":"90804",
    "addr:street":"E 7Th St",
    "iso:country":"US",
    "sg:address":"2232 E 7th St",
    "sg:city":"Long Beach",
    "sg:classifiers":[
        {
            "category":"Shopping",
            "subcategory":"Discount & Variety Stores",
            "type":"Retail Goods"
        }
    ],
    "sg:phone":"+1 562 438 3940",
    "sg:postcode":"90804",
    "sg:province":"CA",
    "wof:name":"Ninety Nine Cents & Bargain",
    "wof:placetype":"venue"
},
  "geometry": {"coordinates":[-118.16463299999999,33.775264],"type":"Point"}
}