{
  "type": "Feature",
  "properties": {
    "addr:full":"12306 Hatteras St North Hollywood CA 91607",
    "addr:housenumber":"12306",
    "addr:postcode":"91607",
    "addr:street":"Hatteras St",
    "iso:country":"US",
    "sg:address":"12306 Hatteras St",
    "sg:city":"North Hollywood",
    "sg:classifiers":[
        {
            "category":"Building & Trades",
            "subcategory":"Plumbing",
            "type":"Services"
        }
    ],
    "sg:phone":"+1 818 980 7342",
    "sg:postcode":"91607",
    "sg:province":"CA",
    "sg:tags":[
        "conditioning",
        "air",
        "system",
        "contractor"
    ],
    "wof:name":"Air Design",
    "wof:placetype":"venue"
},
  "geometry": {"coordinates":[-118.401121,34.175244],"type":"Point"}
}