{
  "type": "Feature",
  "properties": {
    "iso:country":"US",
    "sg:address":"1255 Reamwood Ave",
    "sg:city":"Sunnyvale",
    "sg:classifiers":[
        {
            "category":"Health Services",
            "subcategory":"Health Practitioner",
            "type":"Services"
        }
    ],
    "sg:phone":"+1 800 481 4662",
    "sg:postcode":"94086",
    "sg:province":"CA",
    "sg:tags":[
        "home",
        "care"
    ],
    "sg:website":"www.advantacare.net",
    "wof:name":"AdvantaCare",
    "wof:placetype":"venue"
},
  "geometry": {"coordinates":[-121.988575,37.406091],"type":"Point"}
}