{
  "type": "Feature",
  "properties": {
    "addr:full":"1843 Campesino Pl Oceanside CA 92054",
    "addr:housenumber":"1843",
    "addr:postcode":"92054",
    "addr:street":"Campesino Pl",
    "iso:country":"US",
    "sg:address":"1843 Campesino Pl",
    "sg:city":"Oceanside",
    "sg:classifiers":[
        {
            "category":"Professional",
            "subcategory":"Engineering",
            "type":"Services"
        }
    ],
    "sg:phone":"+1 760 439 2802",
    "sg:postcode":"92054",
    "sg:province":"CA",
    "sg:tags":[
        "engineer"
    ],
    "wof:name":"Aquaterra Engineering Inc",
    "wof:placetype":"venue"
},
  "geometry": {"coordinates":[-117.337913,33.187495],"type":"Point"}
}