{
  "type": "Feature",
  "properties": {
    "addr:full":"1188 S Livermore Ave Livermore CA 94550",
    "addr:housenumber":"1188",
    "addr:postcode":"94550",
    "addr:street":"S Livermore Ave",
    "iso:country":"US",
    "sg:address":"1188 S Livermore Ave",
    "sg:city":"Livermore",
    "sg:classifiers":[
        {
            "category":"Education",
            "subcategory":"Library",
            "type":"Public Place"
        }
    ],
    "sg:phone":"+1 925 373 5500",
    "sg:postcode":"94550",
    "sg:province":"CA",
    "sg:tags":[
        "executive"
    ],
    "wof:name":"Livermore Public Library",
    "wof:placetype":"venue"
},
  "geometry": {"coordinates":[-121.75474800000001,37.673378],"type":"Point"}
}