{
  "type": "Feature",
  "properties": {
    "iso:country":"US",
    "sg:address":"11700 Mc Bean Dr",
    "sg:city":"El Monte",
    "sg:classifiers":[
        {
            "category":"Building & Trades",
            "subcategory":"Plumbing",
            "type":"Services"
        }
    ],
    "sg:phone":"+1 909 946 4874",
    "sg:postcode":"91732",
    "sg:province":"CA",
    "sg:tags":[
        "plumbing",
        "contractor"
    ],
    "wof:name":"Drain Now Rooter Svc",
    "wof:placetype":"venue"
},
  "geometry": {"coordinates":[-118.007941,34.099741],"type":"Point"}
}