{
  "type": "Feature",
  "properties": {
    "addr:full":"915 Wilshire Blvd Los Angeles CA 90017",
    "addr:housenumber":"915",
    "addr:postcode":"90017",
    "addr:street":"Wilshire Blvd",
    "iso:country":"US",
    "sg:address":"915 Wilshire Blvd",
    "sg:city":"Los Angeles",
    "sg:classifiers":[
        {
            "category":"Organizations",
            "subcategory":"Professional Association",
            "type":"Services"
        }
    ],
    "sg:phone":"+1 213 624 2274",
    "sg:postcode":"90017",
    "sg:province":"CA",
    "wof:name":"California Assn-Physician Grps",
    "wof:placetype":"venue"
},
  "geometry": {"coordinates":[-118.26015200000001,34.050694],"type":"Point"}
}