{
  "type": "Feature",
  "properties": {
    "addr:full":"24206 Crenshaw Blvd Torrance CA 90505",
    "addr:housenumber":"24206",
    "addr:postcode":"90505",
    "addr:street":"Crenshaw Blvd",
    "iso:country":"US",
    "sg:address":"24206 Crenshaw Blvd",
    "sg:city":"Torrance",
    "sg:classifiers":[
        {
            "category":"Shopping",
            "subcategory":"Florist",
            "type":"Retail Goods"
        }
    ],
    "sg:phone":"+1 310 530 8128",
    "sg:postcode":"90505",
    "sg:province":"CA",
    "sg:website":"www.jennysflowershop.com/",
    "wof:name":"Jenny's Flowers & Gifts",
    "wof:placetype":"venue"
},
  "geometry": {"coordinates":[-118.328003,33.804798],"type":"Point"}
}