{
  "type": "Feature",
  "properties": {
    "addr:full":"150 Jackson St Hayward CA 94544",
    "addr:housenumber":"150",
    "addr:postcode":"94544",
    "addr:street":"Jackson St",
    "iso:country":"US",
    "sg:address":"150 Jackson St",
    "sg:city":"Hayward",
    "sg:classifiers":[
        {
            "category":"Government",
            "subcategory":"Office",
            "type":"Public Place"
        }
    ],
    "sg:phone":"+1 510 537 7761",
    "sg:postcode":"94544",
    "sg:province":"CA",
    "sg:tags":[
        "transportation"
    ],
    "wof:name":"Hayward DMV Office",
    "wof:placetype":"venue"
},
  "geometry": {"coordinates":[-122.086541,37.658594],"type":"Point"}
}