{
  "type": "Feature",
  "properties": {
    "addr:full":"6501 Cam Tassajara Pleasanton CA 94588",
    "addr:housenumber":"6501",
    "addr:postcode":"94588",
    "addr:street":"Cam Tassajara",
    "iso:country":"US",
    "sg:address":"6501 Cam Tassajara",
    "sg:city":"Pleasanton",
    "sg:classifiers":[
        {
            "category":"Building & Trades",
            "subcategory":"Construction",
            "type":"Services"
        }
    ],
    "sg:phone":"+1 925 248 0128",
    "sg:postcode":"94588",
    "sg:province":"CA",
    "sg:tags":[
        "tile",
        "dealer"
    ],
    "wof:name":"Tile One",
    "wof:placetype":"venue"
},
  "geometry": {"coordinates":[-121.871938,37.716713],"type":"Point"}
}