{
  "type": "Feature",
  "properties": {
    "iso:country":"US",
    "sg:address":"8997 California Avenue",
    "sg:city":"South Gate",
    "sg:classifiers":[
        {
            "category":"Shopping",
            "subcategory":"Party Supplies",
            "type":"Retail Goods"
        }
    ],
    "sg:phone":"+1 323 566 7929",
    "sg:postcode":"90280",
    "sg:province":"CA",
    "wof:name":"Fabrica De Pinatas Party Supply",
    "wof:placetype":"venue"
},
  "geometry": {"coordinates":[-118.206623,33.951025],"type":"Point"}
}