{
  "type": "Feature",
  "properties": {
    "iso:country":"US",
    "sg:address":"39000 Bob Hope Dr",
    "sg:city":"Rancho Mirage",
    "sg:classifiers":[
        {
            "category":"Health Services",
            "subcategory":"Hospital",
            "type":"Services"
        }
    ],
    "sg:phone":"+1 760 341 0546",
    "sg:postcode":"92270",
    "sg:province":"CA",
    "wof:name":"M S J Corporation",
    "wof:placetype":"venue"
},
  "geometry": {"coordinates":[-116.40799699999999,33.7686],"type":"Point"}
}