{
  "type": "Feature",
  "properties": {
    "iso:country":"US",
    "sg:address":"6745 Washington Ave",
    "sg:city":"Whittier",
    "sg:classifiers":[
        {
            "category":"Freight",
            "type":"Transportation"
        }
    ],
    "sg:phone":"+1 562 695 4606",
    "sg:postcode":"90601",
    "sg:province":"CA",
    "sg:tags":[
        "local",
        "trucking"
    ],
    "wof:name":"Best West Carrier Inc",
    "wof:placetype":"venue"
},
  "geometry": {"coordinates":[-118.035087,33.979355],"type":"Point"}
}