{
  "type": "Feature",
  "properties": {
    "addr:full":"2560 Junction Avenue San Jose CA 95134",
    "addr:housenumber":"2560",
    "addr:postcode":"95134",
    "addr:street":"Junction Avenue",
    "iso:country":"US",
    "sg:address":"2560 Junction Avenue",
    "sg:city":"San Jose",
    "sg:classifiers":[
        {
            "category":"Wholesale",
            "subcategory":"Computers",
            "type":"Manufacturing & Wholesale Goods"
        }
    ],
    "sg:phone":"+1 408 327 9800",
    "sg:postcode":"95134",
    "sg:province":"CA",
    "wof:name":"Central Design Systems",
    "wof:placetype":"venue"
},
  "geometry": {"coordinates":[-121.92314500000001,37.392992],"type":"Point"}
}