{
  "type": "Feature",
  "properties": {
    "addr:full":"420 S Mountain Ave Upland CA 91786",
    "addr:housenumber":"420",
    "addr:postcode":"91786",
    "addr:street":"S Mountain Ave",
    "iso:country":"US",
    "sg:address":"420 S Mountain Ave",
    "sg:city":"Upland",
    "sg:classifiers":[
        {
            "category":"Food & Beverages",
            "subcategory":"Groceries & Convenience Stores",
            "type":"Retail Goods"
        }
    ],
    "sg:phone":"+1 909 946 3465",
    "sg:postcode":"91786",
    "sg:province":"CA",
    "sg:tags":[
        "grocer"
    ],
    "wof:name":"Pavilions",
    "wof:placetype":"venue"
},
  "geometry": {"coordinates":[-117.670058,34.087975],"type":"Point"}
}