{
  "type": "Feature",
  "properties": {
    "iso:country":"US",
    "sg:address":"4175 E La Palma Ave Ste 205",
    "sg:city":"Anaheim",
    "sg:classifiers":[
        {
            "category":"Organizations",
            "subcategory":"Religious Organization",
            "type":"Services"
        }
    ],
    "sg:phone":"+1 714 985 9925",
    "sg:postcode":"92807",
    "sg:province":"CA",
    "wof:name":"The Foursquare Church",
    "wof:placetype":"venue"
},
  "geometry": {"coordinates":[-117.82655699999999,33.859587],"type":"Point"}
}