{
  "type": "Feature",
  "properties": {
    "iso:country":"US",
    "sg:address":"5000 Farnsworth Dr",
    "sg:city":"San Jose",
    "sg:classifiers":[
        {
            "category":"Education",
            "subcategory":"School",
            "type":"Public Place"
        }
    ],
    "sg:phone":"+1 408 223 4515",
    "sg:postcode":"95138",
    "sg:province":"CA",
    "wof:name":"Silver Oak Elementary School",
    "wof:placetype":"venue"
},
  "geometry": {"coordinates":[-121.758736,37.281248],"type":"Point"}
}