{
  "type": "Feature",
  "properties": {
    "iso:country":"US",
    "sg:address":"8801 Piedra Way",
    "sg:city":"Fair Oaks",
    "sg:classifiers":[
        {
            "category":"Building & Trades",
            "subcategory":"Construction",
            "type":"Services"
        }
    ],
    "sg:phone":"+1 916 961 2110",
    "sg:postcode":"95628",
    "sg:province":"CA",
    "sg:tags":[
        "roofing",
        "contractor"
    ],
    "wof:name":"Jeff Irwin Roofing Co",
    "wof:placetype":"venue"
},
  "geometry": {"coordinates":[-121.227194,38.665084],"type":"Point"}
}