{
  "type": "Feature",
  "properties": {
    "iso:country":"US",
    "sg:address":"1 Annabel Ln",
    "sg:city":"San Ramon",
    "sg:classifiers":[
        {
            "category":"Professional",
            "subcategory":"Engineering",
            "type":"Services"
        }
    ],
    "sg:phone":"+1 925 867 3339",
    "sg:postcode":"94583",
    "sg:province":"CA",
    "sg:tags":[
        "engineer"
    ],
    "sg:website":"www.eddyassociates.com",
    "wof:name":"James D Eddy Assoc",
    "wof:placetype":"venue"
},
  "geometry": {"coordinates":[-121.97061100000001,37.772166],"type":"Point"}
}