{
  "type": "Feature",
  "properties": {
    "iso:country":"US",
    "sg:address":"245 Saint Marys Dr",
    "sg:city":"Oxnard",
    "sg:classifiers":[
        {
            "category":"Marine",
            "type":"Transportation"
        }
    ],
    "sg:phone":"+1 805 276 5788",
    "sg:postcode":"93036",
    "sg:province":"CA",
    "sg:tags":[
        "cleaning",
        "boat"
    ],
    "wof:name":"C G Henning Yacht Svc",
    "wof:placetype":"venue"
},
  "geometry": {"coordinates":[-119.173198,34.22699],"type":"Point"}
}