{
  "type": "Feature",
  "properties": {
    "addr:full":"247 Mt Hermon Rd. Scotts Valley CA 95066",
    "addr:housenumber":"247",
    "addr:postcode":"95066",
    "addr:street":"Mt Hermon Rd.",
    "iso:country":"US",
    "sg:address":"247 Mt Hermon Rd.",
    "sg:city":"Scotts Valley",
    "sg:classifiers":[
        {
            "category":"Banks & Credit Unions",
            "subcategory":"Bank",
            "type":"Services"
        }
    ],
    "sg:phone":"+1 831 438 1715",
    "sg:postcode":"95066",
    "sg:province":"CA",
    "sg:website":"www.chase.com",
    "wof:name":"Chase",
    "wof:placetype":"venue"
},
  "geometry": {"coordinates":[-122.02857299999999,37.046174],"type":"Point"}
}