{
  "type": "Feature",
  "properties": {
    "addr:full":"1614 20th St Bakersfield CA 93301",
    "addr:housenumber":"1614",
    "addr:postcode":"93301",
    "addr:street":"20Th St",
    "iso:country":"US",
    "sg:address":"1614 20th St",
    "sg:city":"Bakersfield",
    "sg:classifiers":[
        {
            "category":"Personal",
            "type":"Services"
        },
        {
            "category":"Sports & Exercise",
            "subcategory":"Gym",
            "type":"Entertainment"
        },
        {
            "category":"Arena",
            "subcategory":"Sports Club",
            "type":"Entertainment"
        }
    ],
    "sg:phone":"+1 661 324 1808",
    "sg:postcode":"93301",
    "sg:province":"CA",
    "sg:tags":[
        "trainer",
        "yoga",
        "consultant",
        "instruction",
        "program",
        "health",
        "fitness",
        "physical"
    ],
    "sg:website":"http://www.innerbodyworks.com",
    "wof:name":"Inner Bodyworks Studio",
    "wof:placetype":"venue"
},
  "geometry": {"coordinates":[-119.020185,35.37718],"type":"Point"}
}