{
  "type": "Feature",
  "properties": {
    "addr:full":"934 W 15th St Merced CA 95340",
    "addr:housenumber":"934",
    "addr:postcode":"95340",
    "addr:street":"W 15Th St",
    "iso:country":"US",
    "sg:address":"934 W 15th St",
    "sg:city":"Merced",
    "sg:classifiers":[
        {
            "category":"Autos & Motor Vehicles",
            "subcategory":"Auto Supplies",
            "type":"Retail Goods"
        }
    ],
    "sg:phone":"+1 209 383 2222",
    "sg:postcode":"95340",
    "sg:province":"CA",
    "sg:tags":[
        "automobile",
        "parts"
    ],
    "wof:name":"Tba Auto Parts",
    "wof:placetype":"venue"
},
  "geometry": {"coordinates":[-120.49184099999999,37.301642],"type":"Point"}
}