{
  "type": "Feature",
  "properties": {
    "addr:full":"150 S Beverly Dr Beverly Hills CA 90212",
    "addr:housenumber":"150",
    "addr:postcode":"90212",
    "addr:street":"S Beverly Dr",
    "iso:country":"US",
    "sg:address":"150 S Beverly Dr",
    "sg:city":"Beverly Hills",
    "sg:classifiers":[
        {
            "category":"Restaurant",
            "type":"Food & Drink"
        }
    ],
    "sg:menulink":"http://www.allmenus.com/ca/los-angeles/22652-piccolo-paradiso/menu/",
    "sg:phone":"+1 310 271 0030",
    "sg:postcode":"90212",
    "sg:province":"CA",
    "sg:tags":[
        "italian"
    ],
    "wof:name":"Piccolo Paradiso",
    "wof:placetype":"venue"
},
  "geometry": {"coordinates":[-118.399135,34.065867],"type":"Point"}
}