{
  "type": "Feature",
  "properties": {
    "iso:country":"US",
    "sg:address":"1136 Garnet Avenue",
    "sg:city":"Pacific Beach",
    "sg:classifiers":[
        {
            "category":"Shopping",
            "subcategory":"Jewelry",
            "type":"Retail Goods"
        }
    ],
    "sg:phone":"+1 619 855 6032",
    "sg:postcode":"92109",
    "sg:province":"CA",
    "wof:name":"Mundi",
    "wof:placetype":"venue"
},
  "geometry": {"coordinates":[-117.24900100000001,32.798],"type":"Point"}
}