{
  "type": "Feature",
  "properties": {
    "iso:country":"US",
    "sg:address":"11 Lakepines",
    "sg:city":"Irvine",
    "sg:classifiers":[
        {
            "category":"Manufacturing",
            "subcategory":"Retail Goods",
            "type":"Manufacturing & Wholesale Goods"
        }
    ],
    "sg:phone":"+1 714 573 1448",
    "sg:postcode":"92620",
    "sg:province":"CA",
    "sg:tags":[
        "product",
        "mfg"
    ],
    "wof:name":"Rich Lampley",
    "wof:placetype":"venue"
},
  "geometry": {"coordinates":[-117.757656,33.716426],"type":"Point"}
}