{
  "type": "Feature",
  "properties": {
    "addr:full":"608 University Ave Sacramento CA 95825",
    "addr:housenumber":"608",
    "addr:postcode":"95825",
    "addr:street":"University Ave",
    "iso:country":"US",
    "sg:address":"608 University Ave",
    "sg:city":"Sacramento",
    "sg:classifiers":[
        {
            "category":"Professional",
            "subcategory":"Lawyer & Legal Services",
            "type":"Services"
        }
    ],
    "sg:phone":"+1 916 649 2214",
    "sg:postcode":"95825",
    "sg:province":"CA",
    "sg:tags":[
        "attorney"
    ],
    "wof:name":"Raley Michele",
    "wof:placetype":"venue"
},
  "geometry": {"coordinates":[-121.419139,38.567661],"type":"Point"}
}