{
  "type": "Feature",
  "properties": {
    "iso:country":"US",
    "sg:address":"318 Lincoln Blvd",
    "sg:city":"Venice",
    "sg:classifiers":[
        {
            "category":"Real Estate",
            "subcategory":"Real Estate Agent",
            "type":"Services"
        }
    ],
    "sg:phone":"+1 310 396 8821",
    "sg:postcode":"90291",
    "sg:province":"CA",
    "sg:tags":[
        "management"
    ],
    "wof:name":"D W Properties",
    "wof:placetype":"venue"
},
  "geometry": {"coordinates":[-118.46666500000001,34.000851],"type":"Point"}
}