{
  "type": "Feature",
  "properties": {
    "addr:full":"1920 E Maple Avenue El Segundo CA 90245",
    "addr:housenumber":"1920",
    "addr:postcode":"90245",
    "addr:street":"E Maple Avenue",
    "iso:country":"US",
    "sg:address":"1920 E Maple Avenue",
    "sg:city":"El Segundo",
    "sg:classifiers":[
        {
            "category":"Communications",
            "type":"Services"
        }
    ],
    "sg:phone":"+1 310 726 0939",
    "sg:postcode":"90245",
    "sg:province":"CA",
    "sg:tags":[
        "web",
        "design"
    ],
    "wof:name":"Fc2",
    "wof:placetype":"venue"
},
  "geometry": {"coordinates":[-118.393297,33.926824],"type":"Point"}
}