{
  "type": "Feature",
  "properties": {
    "iso:country":"US",
    "sg:address":"531 S State Hwy 59",
    "sg:city":"Merced",
    "sg:classifiers":[
        {
            "category":"Wholesale",
            "subcategory":"Machinery & Supplies",
            "type":"Manufacturing & Wholesale Goods"
        }
    ],
    "sg:phone":"+1 209 722 4145",
    "sg:postcode":"95340",
    "sg:province":"CA",
    "sg:tags":[
        "equipment",
        "dairy"
    ],
    "wof:name":"Laird Manufacturing",
    "wof:placetype":"venue"
},
  "geometry": {"coordinates":[-120.487742,37.280629],"type":"Point"}
}