{
  "type": "Feature",
  "properties": {
    "addr:full":"8502 Telegraph Road Downey CA 90240",
    "addr:housenumber":"8502",
    "addr:postcode":"90240",
    "addr:street":"Telegraph Road",
    "iso:country":"US",
    "sg:address":"8502 Telegraph Road",
    "sg:city":"Downey",
    "sg:classifiers":[
        {
            "category":"Restaurant",
            "type":"Food & Drink"
        }
    ],
    "sg:phone":"+1 562 923 1455",
    "sg:postcode":"90240",
    "sg:province":"CA",
    "wof:name":"Jose's Taco Delight",
    "wof:placetype":"venue"
},
  "geometry": {"coordinates":[-118.11098800000001,33.961423],"type":"Point"}
}