{
  "type": "Feature",
  "properties": {
    "addr:full":"1188 Industrial Ave Escondido CA 92029",
    "addr:housenumber":"1188",
    "addr:postcode":"92029",
    "addr:street":"Industrial Ave",
    "iso:country":"US",
    "sg:address":"1188 Industrial Ave",
    "sg:city":"Escondido",
    "sg:classifiers":[
        {
            "category":"Building & Trades",
            "subcategory":"Construction",
            "type":"Services"
        }
    ],
    "sg:phone":"+1 760 233 0111",
    "sg:postcode":"92029",
    "sg:province":"CA",
    "sg:tags":[
        "contractor"
    ],
    "wof:name":"Unlimited Motorsports",
    "wof:placetype":"venue"
},
  "geometry": {"coordinates":[-117.10464,33.118748],"type":"Point"}
}