{
  "type": "Feature",
  "properties": {
    "addr:full":"4628 Deerfield Dr Antioch CA 94531",
    "addr:housenumber":"4628",
    "addr:postcode":"ca 94531",
    "addr:street":"Deerfield Dr",
    "iso:country":"US",
    "sg:address":"4628 Deerfield Dr",
    "sg:city":"Antioch",
    "sg:classifiers":[
        {
            "category":"Professional",
            "subcategory":"Art Services",
            "type":"Services"
        }
    ],
    "sg:phone":"+1 925 706 8008",
    "sg:postcode":"94531",
    "sg:province":"CA",
    "sg:tags":[
        "interior",
        "designer",
        "decorator"
    ],
    "wof:name":"Cherie's Interior Professionals",
    "wof:placetype":"venue"
},
  "geometry": {"coordinates":[-121.766245,37.97339],"type":"Point"}
}