{
  "type": "Feature",
  "properties": {
    "iso:country":"US",
    "sg:address":"8585 Thys Ct",
    "sg:city":"Sacramento",
    "sg:classifiers":[
        {
            "category":"Professional",
            "subcategory":"Business Services",
            "type":"Services"
        }
    ],
    "sg:phone":"+1 916 387 9733",
    "sg:postcode":"95828",
    "sg:province":"CA",
    "sg:tags":[
        "barricade"
    ],
    "wof:name":"Traffic Control Svc",
    "wof:placetype":"venue"
},
  "geometry": {"coordinates":[-121.389287,38.518868],"type":"Point"}
}