{
  "type": "Feature",
  "properties": {
    "iso:country":"US",
    "sg:address":"3600 Wilshire Blvd",
    "sg:city":"Los Angeles",
    "sg:classifiers":[
        {
            "category":"Banks & Credit Unions",
            "subcategory":"Investment Brokerage",
            "type":"Services"
        }
    ],
    "sg:phone":"+1 213 252 9190",
    "sg:postcode":"90010",
    "sg:province":"CA",
    "sg:tags":[
        "consultant",
        "financing"
    ],
    "wof:name":"Sung Il Cho",
    "wof:placetype":"venue"
},
  "geometry": {"coordinates":[-118.304174,34.061721],"type":"Point"}
}