{
  "type": "Feature",
  "properties": {
    "addr:full":"4004 Regan Dr San Mateo CA 94403",
    "addr:housenumber":"4004",
    "addr:postcode":"94403",
    "addr:street":"Regan Dr",
    "iso:country":"US",
    "sg:address":"4004 Regan Dr",
    "sg:city":"San Mateo",
    "sg:classifiers":[
        {
            "category":"Building & Trades",
            "subcategory":"Landscaping Services",
            "type":"Services"
        }
    ],
    "sg:phone":"+1 650 574 3039",
    "sg:postcode":"94403",
    "sg:province":"CA",
    "wof:name":"Raymond Bidondo",
    "wof:placetype":"venue"
},
  "geometry": {"coordinates":[-122.284965,37.533886],"type":"Point"}
}