{
  "type": "Feature",
  "properties": {
    "addr:full":"2425 J St Sacramento CA 95816",
    "addr:housenumber":"2425",
    "addr:postcode":"95816",
    "addr:street":"J St",
    "iso:country":"US",
    "sg:address":"2425 J St",
    "sg:city":"Sacramento",
    "sg:classifiers":[
        {
            "category":"Shopping",
            "subcategory":"Clothing, Apparel, & Fashions",
            "type":"Retail Goods"
        }
    ],
    "sg:phone":"+1 916 447 4435",
    "sg:postcode":"95816",
    "sg:province":"CA",
    "sg:tags":[
        "clothing",
        "women's"
    ],
    "sg:website":"www.sugarshackboutique.com",
    "wof:name":"Sugar Shack Boutique",
    "wof:placetype":"venue"
},
  "geometry": {"coordinates":[-121.47399900000001,38.5751],"type":"Point"}
}