{
  "type": "Feature",
  "properties": {
    "addr:full":"11875 Pigeon Pass Rd Moreno Valley CA 92557",
    "addr:housenumber":"11875",
    "addr:postcode":"92557",
    "addr:street":"Pigeon Pass Rd",
    "iso:country":"US",
    "sg:address":"11875 Pigeon Pass Rd",
    "sg:city":"Moreno Valley",
    "sg:classifiers":[
        {
            "category":"Shopping",
            "subcategory":"Discount & Variety Stores",
            "type":"Retail Goods"
        }
    ],
    "sg:phone":"+1 951 485 0938",
    "sg:postcode":"92557",
    "sg:province":"CA",
    "wof:name":"J & M 99c",
    "wof:placetype":"venue"
},
  "geometry": {"coordinates":[-117.26148000000001,33.948078],"type":"Point"}
}