{
  "type": "Feature",
  "properties": {
    "iso:country":"US",
    "sg:address":"28802 Marguerite Pkwy",
    "sg:city":"Mission Viejo",
    "sg:classifiers":[
        {
            "category":"Autos & Motor Vehicles",
            "subcategory":"Automobile Sales",
            "type":"Retail Goods"
        }
    ],
    "sg:phone":"+1 949 347 0500",
    "sg:postcode":"92692",
    "sg:province":"CA",
    "sg:tags":[
        "car",
        "dealer"
    ],
    "sg:website":"www.4acura.com",
    "wof:name":"Acura Of Mission Viejo",
    "wof:placetype":"venue"
},
  "geometry": {"coordinates":[-117.671868,33.545569],"type":"Point"}
}