{
  "type": "Feature",
  "properties": {
    "addr:full":"6767 Forest Lawn Drive Los Angeles CA 90068",
    "addr:housenumber":"6767",
    "addr:postcode":"90068",
    "addr:street":"Forest Lawn Drive",
    "iso:country":"US",
    "sg:address":"6767 Forest Lawn Drive",
    "sg:city":"Los Angeles",
    "sg:classifiers":[
        {
            "category":"Arts & Performance",
            "subcategory":"Arts Center",
            "type":"Entertainment"
        }
    ],
    "sg:phone":"+1 323 850 9866",
    "sg:postcode":"90068",
    "sg:province":"CA",
    "sg:tags":[
        "performing"
    ],
    "wof:name":"Rafter H Entertainment",
    "wof:placetype":"venue"
},
  "geometry": {"coordinates":[-118.339983,34.144112],"type":"Point"}
}