{
  "type": "Feature",
  "properties": {
    "addr:full":"1231 A Park Ave Alameda CA 94501",
    "addr:housenumber":"1231 a",
    "addr:postcode":"94501",
    "addr:street":"Park Ave",
    "iso:country":"US",
    "sg:address":"1231 A Park Ave",
    "sg:city":"Alameda",
    "sg:classifiers":[
        {
            "category":"Communications",
            "subcategory":"Film & Video Production",
            "type":"Services"
        },
        {
            "category":"Professional",
            "subcategory":"Art Services",
            "type":"Services"
        }
    ],
    "sg:phone":"+1 617 285 4350",
    "sg:postcode":"94501",
    "sg:province":"CA",
    "sg:tags":[
        "photographer",
        "video/film"
    ],
    "sg:website":"heliosimagesblog.com/",
    "wof:name":"Helios Images",
    "wof:placetype":"venue"
},
  "geometry": {"coordinates":[-122.244265,37.761391],"type":"Point"}
}