{
  "type": "Feature",
  "properties": {
    "iso:country":"US",
    "sg:address":"8500 Melrose Avenue",
    "sg:city":"West Hollywood",
    "sg:classifiers":[
        {
            "category":"Home & Garden",
            "subcategory":"Home Furnishings",
            "type":"Retail Goods"
        }
    ],
    "sg:phone":"+1 310 657 2800",
    "sg:postcode":"90069",
    "sg:province":"CA",
    "sg:tags":[
        "bath",
        "kitchen"
    ],
    "wof:name":"Geoula Collection Kitchen and Bath",
    "wof:placetype":"venue"
},
  "geometry": {"coordinates":[-118.376502,34.081964],"type":"Point"}
}