{
  "type": "Feature",
  "properties": {
    "iso:country":"US",
    "sg:address":"11171 Venture Dr",
    "sg:city":"Mira Loma",
    "sg:classifiers":[
        {
            "category":"Autos & Motor Vehicles",
            "subcategory":"Recreational Vehicle Sales",
            "type":"Retail Goods"
        }
    ],
    "sg:phone":"+1 951 685 8384",
    "sg:postcode":"91752",
    "sg:province":"CA",
    "sg:tags":[
        "parts",
        "trailer"
    ],
    "wof:name":"Redneck Trailer Supplies",
    "wof:placetype":"venue"
},
  "geometry": {"coordinates":[-117.52947399999999,34.033108],"type":"Point"}
}