{
  "type": "Feature",
  "properties": {
    "addr:full":"8949 Complex Dr San Diego CA 92123",
    "addr:housenumber":"8949",
    "addr:postcode":"92123",
    "addr:street":"Complex Dr",
    "iso:country":"US",
    "sg:address":"8949 Complex Dr",
    "sg:city":"San Diego",
    "sg:classifiers":[
        {
            "category":"Manufacturing",
            "subcategory":"Printing",
            "type":"Manufacturing & Wholesale Goods"
        }
    ],
    "sg:phone":"+1 858 495 3102",
    "sg:postcode":"92123",
    "sg:province":"CA",
    "sg:tags":[
        "broker"
    ],
    "wof:name":"International Printing",
    "wof:placetype":"venue"
},
  "geometry": {"coordinates":[-117.13878,32.830036],"type":"Point"}
}