{
  "type": "Feature",
  "properties": {
    "addr:full":"12 Red Cedar Ct San Rafael CA 94903",
    "addr:housenumber":"12",
    "addr:postcode":"94903",
    "addr:street":"Red Cedar Ct",
    "iso:country":"US",
    "sg:address":"12 Red Cedar Ct",
    "sg:city":"San Rafael",
    "sg:classifiers":[
        {
            "category":"Professional",
            "subcategory":"Lawyer & Legal Services",
            "type":"Services"
        }
    ],
    "sg:phone":"+1 415 491 1040",
    "sg:postcode":"94903",
    "sg:province":"CA",
    "sg:tags":[
        "attorney"
    ],
    "wof:name":"Martin A Schainbaum",
    "wof:placetype":"venue"
},
  "geometry": {"coordinates":[-122.590092,38.03754],"type":"Point"}
}