{
  "type": "Feature",
  "properties": {
    "addr:full":"257 Newport Center Dr Newport Beach CA 92660",
    "addr:housenumber":"257",
    "addr:postcode":"92660",
    "addr:street":"Newport Center Dr",
    "iso:country":"US",
    "sg:address":"257 Newport Center Dr",
    "sg:city":"Newport Beach",
    "sg:classifiers":[
        {
            "category":"Shopping",
            "subcategory":"Clothing, Apparel, & Fashions",
            "type":"Retail Goods"
        }
    ],
    "sg:phone":"+1 949 640 5477",
    "sg:postcode":"92660",
    "sg:province":"CA",
    "wof:name":"Modern Romance",
    "wof:placetype":"venue"
},
  "geometry": {"coordinates":[-117.87312799999999,33.613858],"type":"Point"}
}