{
  "type": "Feature",
  "properties": {
    "addr:full":"371 Windsor River Rd Windsor CA 95492",
    "addr:housenumber":"371",
    "addr:postcode":"95492",
    "addr:street":"Windsor River Rd",
    "iso:country":"US",
    "sg:address":"371 Windsor River Rd",
    "sg:city":"Windsor",
    "sg:classifiers":[
        {
            "category":"Social Services",
            "type":"Services"
        }
    ],
    "sg:phone":"+1 707 838 8259",
    "sg:postcode":"95492",
    "sg:province":"CA",
    "sg:tags":[
        "organization",
        "welfare"
    ],
    "wof:name":"Masonic Lodge",
    "wof:placetype":"venue"
},
  "geometry": {"coordinates":[-122.816598,38.547328],"type":"Point"}
}