{
  "type": "Feature",
  "properties": {
    "iso:country":"US",
    "sg:address":"4617 Freeport Blvd",
    "sg:city":"Sacramento",
    "sg:classifiers":[
        {
            "category":"Health Services",
            "subcategory":"Optometrist",
            "type":"Services"
        }
    ],
    "sg:phone":"+1 916 452 4439",
    "sg:postcode":"95822",
    "sg:province":"CA",
    "wof:name":"Ronald B Mori OD",
    "wof:placetype":"venue"
},
  "geometry": {"coordinates":[-121.494556,38.532485],"type":"Point"}
}