{
  "type": "Feature",
  "properties": {
    "addr:full":"2431 5th St Berkeley CA 94710",
    "addr:housenumber":"2431",
    "addr:postcode":"94710",
    "addr:street":"5Th St",
    "iso:country":"US",
    "sg:address":"2431 5th St",
    "sg:city":"Berkeley",
    "sg:classifiers":[
        {
            "category":"Cinema",
            "subcategory":"Movie Theater",
            "type":"Entertainment"
        }
    ],
    "sg:phone":"+1 510 843 4500",
    "sg:postcode":"94710",
    "sg:province":"CA",
    "wof:name":"Wolf Cinema",
    "wof:placetype":"venue"
},
  "geometry": {"coordinates":[-122.296631,37.860975],"type":"Point"}
}