{
  "type": "Feature",
  "properties": {
    "addr:full":"1524 Catalina Ct Livermore CA 94550",
    "addr:housenumber":"1524",
    "addr:postcode":"94550",
    "addr:street":"Catalina Ct",
    "iso:country":"US",
    "sg:address":"1524 Catalina Ct",
    "sg:city":"Livermore",
    "sg:classifiers":[
        {
            "category":"Education",
            "subcategory":"School",
            "type":"Public Place"
        }
    ],
    "sg:phone":"+1 925 443 1690",
    "sg:postcode":"94550",
    "sg:province":"CA",
    "wof:name":"Livermore Valley Charter Sch",
    "wof:placetype":"venue"
},
  "geometry": {"coordinates":[-121.783067,37.661755],"type":"Point"}
}