{
  "type": "Feature",
  "properties": {
    "addr:full":"8750 el Camino Real Atascadero CA 93422",
    "addr:housenumber":"8750",
    "addr:postcode":"93422",
    "addr:street":"El Camino Real",
    "iso:country":"US",
    "sg:address":"8750 el Camino Real",
    "sg:city":"Atascadero",
    "sg:classifiers":[
        {
            "category":"Retail",
            "subcategory":"Auto Repair",
            "type":"Services"
        }
    ],
    "sg:phone":"+1 805 466 3121",
    "sg:postcode":"93422",
    "sg:province":"CA",
    "sg:tags":[
        "brake"
    ],
    "sg:website":"www.americanwesttire.com",
    "wof:name":"American West Tire & Auto",
    "wof:placetype":"venue"
},
  "geometry": {"coordinates":[-120.653637,35.472247],"type":"Point"}
}