{
  "type": "Feature",
  "properties": {
    "iso:country":"US",
    "sg:address":"3311 W Manchester Blvd",
    "sg:city":"Inglewood",
    "sg:classifiers":[
        {
            "category":"Insurance",
            "subcategory":"Insurance Agent",
            "type":"Services"
        }
    ],
    "sg:phone":"+1 323 751 6760",
    "sg:postcode":"90305",
    "sg:province":"CA",
    "wof:name":"Nationwide Mutual Insurance",
    "wof:placetype":"venue"
},
  "geometry": {"coordinates":[-118.329684,33.96013],"type":"Point"}
}