{
  "type": "Feature",
  "properties": {
    "iso:country":"US",
    "sg:address":"12056 Mount Vernon Ave",
    "sg:city":"Grand Terrace",
    "sg:classifiers":[
        {
            "category":"Professional",
            "subcategory":"Business Services",
            "type":"Services"
        },
        {
            "category":"Building & Trades",
            "subcategory":"Plumbing",
            "type":"Services"
        }
    ],
    "sg:phone":"+1 909 783 3817",
    "sg:postcode":"92313",
    "sg:province":"CA",
    "sg:tags":[
        "fire",
        "protection",
        "contractor"
    ],
    "wof:name":"Ornnell Fire Sprinkler Co",
    "wof:placetype":"venue"
},
  "geometry": {"coordinates":[-117.313725,34.034186],"type":"Point"}
}