{
  "type": "Feature",
  "properties": {
    "iso:country":"US",
    "sg:address":"6512 Covert Rd",
    "sg:city":"Modesto",
    "sg:classifiers":[
        {
            "category":"Manufacturing",
            "subcategory":"Food",
            "type":"Manufacturing & Wholesale Goods"
        }
    ],
    "sg:phone":"+1 209 545 4857",
    "sg:postcode":"95358",
    "sg:province":"CA",
    "sg:tags":[
        "mfg"
    ],
    "wof:name":"Heinrich Walnut Hulling",
    "wof:placetype":"venue"
},
  "geometry": {"coordinates":[-121.132028,37.703057],"type":"Point"}
}