{
  "type": "Feature",
  "properties": {
    "iso:country":"US",
    "sg:address":"821 13th St",
    "sg:city":"Modesto",
    "sg:classifiers":[
        {
            "category":"Professional",
            "subcategory":"Management & Consulting",
            "type":"Services"
        }
    ],
    "sg:phone":"+1 209 527 2677",
    "sg:postcode":"95354",
    "sg:province":"CA",
    "sg:tags":[
        "consultants-referral",
        "consultant",
        "security",
        "system"
    ],
    "wof:name":"Entrepid Inc.",
    "wof:placetype":"venue"
},
  "geometry": {"coordinates":[-120.995412,37.640913],"type":"Point"}
}