{
  "type": "Feature",
  "properties": {
    "addr:full":"26302 La Paz Rd Ste 101 Mission Viejo CA 92691",
    "addr:housenumber":"26302",
    "addr:postcode":"92691",
    "addr:street":"La Paz Rd Ste 101",
    "iso:country":"US",
    "sg:address":"26302 La Paz Rd Ste 101",
    "sg:city":"Mission Viejo",
    "sg:classifiers":[
        {
            "category":"Health Services",
            "subcategory":"Doctor",
            "type":"Services"
        }
    ],
    "sg:phone":"+1 949 586 8000",
    "sg:postcode":"92691",
    "sg:province":"CA",
    "wof:name":"Andrea Roberson, DO",
    "wof:placetype":"venue"
},
  "geometry": {"coordinates":[-117.6712,33.599511],"type":"Point"}
}