{
  "type": "Feature",
  "properties": {
    "addr:full":"311 4th Ave San Diego CA 92101",
    "addr:housenumber":"311",
    "addr:postcode":"92101",
    "addr:street":"4Th Ave",
    "iso:country":"US",
    "sg:address":"311 4th Ave",
    "sg:city":"San Diego",
    "sg:classifiers":[
        {
            "category":"Professional",
            "subcategory":"Lawyer & Legal Services",
            "type":"Services"
        }
    ],
    "sg:phone":"+1 619 235 4529",
    "sg:postcode":"92101",
    "sg:province":"CA",
    "wof:name":"Rockwell Ron Law Office of",
    "wof:placetype":"venue"
},
  "geometry": {"coordinates":[-117.16100299999999,32.708401],"type":"Point"}
}