{
  "type": "Feature",
  "properties": {
    "addr:full":"8251 Westminster Blvd Ste 203 Westminster CA 92683",
    "addr:housenumber":"8251",
    "addr:postcode":"92683",
    "addr:street":"Westminster Blvd Ste 203",
    "iso:country":"US",
    "sg:address":"8251 Westminster Blvd Ste 203",
    "sg:city":"Westminster",
    "sg:classifiers":[
        {
            "category":"Professional",
            "subcategory":"Lawyer & Legal Services",
            "type":"Services"
        }
    ],
    "sg:phone":"+1 714 892 3320",
    "sg:postcode":"92683",
    "sg:province":"CA",
    "wof:name":"Feirstein Norman Law Offices of",
    "wof:placetype":"venue"
},
  "geometry": {"coordinates":[-117.985275,33.759498],"type":"Point"}
}