{
  "type": "Feature",
  "properties": {
    "iso:country":"US",
    "sg:address":"30604 E Loma Linda Rd",
    "sg:city":"Temecula",
    "sg:classifiers":[
        {
            "category":"Professional",
            "type":"Services"
        }
    ],
    "sg:phone":"+1 951 693 5293",
    "sg:postcode":"92592",
    "sg:province":"CA",
    "wof:name":"Can Man",
    "wof:placetype":"venue"
},
  "geometry": {"coordinates":[-117.11976300000001,33.463581],"type":"Point"}
}