{
  "type": "Feature",
  "properties": {
    "iso:country":"US",
    "sg:address":"77931 Skypark Crk",
    "sg:city":"Irvine",
    "sg:classifiers":[
        {
            "category":"Home & Garden",
            "subcategory":"Household Appliances",
            "type":"Retail Goods"
        }
    ],
    "sg:phone":"+1 714 799 7275",
    "sg:postcode":"92602",
    "sg:province":"CA",
    "sg:tags":[
        "repair"
    ],
    "wof:name":"Allen & Son Appliance Repair",
    "wof:placetype":"venue"
},
  "geometry": {"coordinates":[-117.772003,33.729599],"type":"Point"}
}