{
  "type": "Feature",
  "properties": {
    "addr:full":"300 S Buena Vista Ave Corona CA 92882",
    "addr:housenumber":"300",
    "addr:postcode":"92882",
    "addr:street":"S Buena Vista Ave",
    "iso:country":"US",
    "sg:address":"300 S Buena Vista Ave",
    "sg:city":"Corona",
    "sg:classifiers":[
        {
            "category":"Education",
            "subcategory":"School",
            "type":"Public Place"
        }
    ],
    "sg:phone":"+1 951 736 3367",
    "sg:postcode":"92882",
    "sg:province":"CA",
    "wof:name":"Buena Vista High School",
    "wof:placetype":"venue"
},
  "geometry": {"coordinates":[-117.57757100000001,33.876633],"type":"Point"}
}