{
  "type": "Feature",
  "properties": {
    "addr:full":"1155 Deer Park Rd Deer Park CA 94576",
    "addr:housenumber":"1155",
    "addr:postcode":"94576",
    "addr:street":"Deer Park Rd",
    "iso:country":"US",
    "sg:address":"1155 Deer Park Rd",
    "sg:city":"Deer Park",
    "sg:classifiers":[
        {
            "category":"Manufacturing",
            "subcategory":"Food",
            "type":"Manufacturing & Wholesale Goods"
        }
    ],
    "sg:phone":"+1 707 942 4811",
    "sg:postcode":"94576",
    "sg:province":"CA",
    "sg:tags":[
        "winery"
    ],
    "wof:name":"Azalea Springs Vineyards",
    "wof:placetype":"venue"
},
  "geometry": {"coordinates":[-122.467191,38.556298],"type":"Point"}
}