{
  "type": "Feature",
  "properties": {
    "addr:full":"618 E 1st St Santa Ana CA 92701",
    "addr:housenumber":"618",
    "addr:postcode":"92701",
    "addr:street":"E 1St St",
    "iso:country":"US",
    "sg:address":"618 E 1st St",
    "sg:city":"Santa Ana",
    "sg:classifiers":[
        {
            "category":"Retail",
            "subcategory":"Auto Repair",
            "type":"Services"
        }
    ],
    "sg:phone":"+1 714 547 8256",
    "sg:postcode":"92701",
    "sg:province":"CA",
    "sg:tags":[
        "body",
        "shop",
        "painting",
        "automobile"
    ],
    "wof:name":"Gonzalez Paint and Body Shop",
    "wof:placetype":"venue"
},
  "geometry": {"coordinates":[-117.861,33.7453],"type":"Point"}
}