{
  "type": "Feature",
  "properties": {
    "iso:country":"US",
    "sg:address":"266 W Rincon Ave",
    "sg:city":"Campbell",
    "sg:classifiers":[
        {
            "category":"Wholesale",
            "subcategory":"Computers",
            "type":"Manufacturing & Wholesale Goods"
        }
    ],
    "sg:phone":"+1 408 370 0202",
    "sg:postcode":"95008",
    "sg:province":"CA",
    "wof:name":"Zenith Data Systems",
    "wof:placetype":"venue"
},
  "geometry": {"coordinates":[-121.95478900000001,37.284784],"type":"Point"}
}