{
  "type": "Feature",
  "properties": {
    "iso:country":"US",
    "sg:address":"9356 Alondra Blvd",
    "sg:city":"Bellflower",
    "sg:classifiers":[
        {
            "category":"Retail",
            "subcategory":"Auto Repair",
            "type":"Services"
        }
    ],
    "sg:phone":"+1 562 925 9930",
    "sg:postcode":"90706",
    "sg:province":"CA",
    "wof:name":"Ace Auto Repair",
    "wof:placetype":"venue"
},
  "geometry": {"coordinates":[-118.134003,33.889099],"type":"Point"}
}