{
  "type": "Feature",
  "properties": {
    "iso:country":"US",
    "sg:address":"1947 Camino Vida Roble",
    "sg:city":"Carlsbad",
    "sg:classifiers":[
        {
            "category":"Professional",
            "subcategory":"Employment Agencies",
            "type":"Services"
        }
    ],
    "sg:phone":"+1 760 438 4405",
    "sg:postcode":"92008",
    "sg:province":"CA",
    "sg:website":"www.marqueestaffing.com",
    "wof:name":"Marquee Staffing",
    "wof:placetype":"venue"
},
  "geometry": {"coordinates":[-117.284639,33.122229],"type":"Point"}
}