{
  "type": "Feature",
  "properties": {
    "iso:country":"US",
    "sg:address":"26012 Marguerite Parkway",
    "sg:city":"Mission Viejo",
    "sg:classifiers":[
        {
            "category":"Retail",
            "subcategory":"Laundry & Dry Cleaning",
            "type":"Services"
        }
    ],
    "sg:phone":"+1 949 582 5305",
    "sg:postcode":"92692",
    "sg:province":"CA",
    "wof:name":"One Day Cleaners",
    "wof:placetype":"venue"
},
  "geometry": {"coordinates":[-117.66010900000001,33.585238],"type":"Point"}
}