{
  "type": "Feature",
  "properties": {
    "addr:full":"5000 Highway 75 Coronado CA 92118",
    "addr:housenumber":"5000",
    "addr:postcode":"92118",
    "addr:street":"Highway 75",
    "iso:country":"US",
    "sg:address":"5000 Highway 75",
    "sg:city":"Coronado",
    "sg:classifiers":[
        {
            "category":"Education",
            "subcategory":"University",
            "type":"Public Place"
        }
    ],
    "sg:phone":"+1 619 575 6176",
    "sg:postcode":"92118",
    "sg:province":"CA",
    "sg:tags":[
        "college"
    ],
    "wof:name":"Southwestern Community College",
    "wof:placetype":"venue"
},
  "geometry": {"coordinates":[-117.139543,32.629553],"type":"Point"}
}