{
  "type": "Feature",
  "properties": {
    "iso:country":"US",
    "sg:address":"2271 Alpine Blvd",
    "sg:city":"Alpine",
    "sg:classifiers":[
        {
            "category":"Building & Trades",
            "subcategory":"Construction",
            "type":"Services"
        }
    ],
    "sg:phone":"+1 619 445 0265",
    "sg:postcode":"91901",
    "sg:province":"CA",
    "sg:tags":[
        "water",
        "well",
        "drilling"
    ],
    "wof:name":"Morrison Drilling Inc",
    "wof:placetype":"venue"
},
  "geometry": {"coordinates":[-116.765388,32.835398],"type":"Point"}
}