{
  "type": "Feature",
  "properties": {
    "addr:full":"23251 Antonio Pkwy Rancho Santa Margarita CA 92688",
    "addr:housenumber":"23251",
    "addr:postcode":"92688",
    "addr:street":"Antonio Pkwy",
    "iso:country":"US",
    "sg:address":"23251 Antonio Pkwy",
    "sg:city":"Rancho Santa Margarita",
    "sg:classifiers":[
        {
            "category":"Retail",
            "subcategory":"Auto Repair",
            "type":"Services"
        }
    ],
    "sg:phone":"+1 949 888 8260",
    "sg:postcode":"92688",
    "sg:province":"CA",
    "sg:tags":[
        "body"
    ],
    "wof:name":"M2 Collision Centers Inc",
    "wof:placetype":"venue"
},
  "geometry": {"coordinates":[-117.60807800000001,33.623994],"type":"Point"}
}