{
  "type": "Feature",
  "properties": {
    "addr:full":"1935 Ocean Ave San Francisco CA 94127",
    "addr:housenumber":"1935",
    "addr:postcode":"94127",
    "addr:street":"Ocean Ave",
    "iso:country":"US",
    "sg:address":"1935 Ocean Ave",
    "sg:city":"San Francisco",
    "sg:classifiers":[
        {
            "category":"Shopping",
            "subcategory":"Bicycles & Sporting Goods",
            "type":"Retail Goods"
        }
    ],
    "sg:phone":"+1 415 239 5004",
    "sg:postcode":"94127",
    "sg:province":"CA",
    "wof:name":"Ocean Cyclery",
    "wof:placetype":"venue"
},
  "geometry": {"coordinates":[-122.462288,37.72519],"type":"Point"}
}