{
  "type": "Feature",
  "properties": {
    "addr:full":"1333 N Main St Walnut Creek CA 94596",
    "addr:housenumber":"1333",
    "addr:postcode":"94596",
    "addr:street":"N Main St",
    "iso:country":"US",
    "sg:address":"1333 N Main St",
    "sg:city":"Walnut Creek",
    "sg:classifiers":[
        {
            "category":"Shopping",
            "subcategory":"Jewelry",
            "type":"Retail Goods"
        }
    ],
    "sg:phone":"+1 925 932 8877",
    "sg:postcode":"94596",
    "sg:province":"CA",
    "sg:tags":[
        "jeweler"
    ],
    "wof:name":"Spitz Jewelers",
    "wof:placetype":"venue"
},
  "geometry": {"coordinates":[-122.060108,37.897457],"type":"Point"}
}