{
  "type": "Feature",
  "properties": {
    "addr:full":"4271 McClung Dr Los Angeles CA 90008",
    "addr:housenumber":"4271",
    "addr:postcode":"90008",
    "addr:street":"Mcclung Dr",
    "iso:country":"US",
    "sg:address":"4271 McClung Dr",
    "sg:city":"Los Angeles",
    "sg:classifiers":[
        {
            "category":"Manufacturing",
            "subcategory":"Printing",
            "type":"Manufacturing & Wholesale Goods"
        }
    ],
    "sg:phone":"+1 323 294 2717",
    "sg:postcode":"90008",
    "sg:province":"CA",
    "sg:tags":[
        "periodical"
    ],
    "wof:name":"Woam Publishing",
    "wof:placetype":"venue"
},
  "geometry": {"coordinates":[-118.33377299999999,34.006893],"type":"Point"}
}