{
  "type": "Feature",
  "properties": {
    "iso:country":"US",
    "sg:address":"570 Renato Way",
    "sg:city":"Paradise",
    "sg:classifiers":[
        {
            "category":"Home & Garden",
            "subcategory":"Home Furnishings",
            "type":"Retail Goods"
        }
    ],
    "sg:phone":"+1 530 877 9299",
    "sg:postcode":"95969",
    "sg:province":"CA",
    "sg:tags":[
        "window",
        "covering"
    ],
    "wof:name":"Allan's Custom Blinds",
    "wof:placetype":"venue"
},
  "geometry": {"coordinates":[-121.62741800000001,39.774261],"type":"Point"}
}