{
  "type": "Feature",
  "properties": {
    "iso:country":"US",
    "sg:address":"520 5th St",
    "sg:city":"Marysville",
    "sg:classifiers":[
        {
            "category":"Autos & Motor Vehicles",
            "subcategory":"Automobile Sales",
            "type":"Retail Goods"
        }
    ],
    "sg:phone":"+1 530 743 4766",
    "sg:postcode":"95901",
    "sg:province":"CA",
    "wof:name":"Chavez Auto",
    "wof:placetype":"venue"
},
  "geometry": {"coordinates":[-121.592033,39.140021],"type":"Point"}
}