{
  "type": "Feature",
  "properties": {
    "addr:full":"409 Burney St Modesto CA 95354",
    "addr:housenumber":"409",
    "addr:postcode":"ca 95354",
    "addr:street":"Burney St",
    "iso:country":"US",
    "sg:address":"409 Burney St",
    "sg:city":"Modesto",
    "sg:classifiers":[
        {
            "category":"Shopping",
            "subcategory":"Bicycles & Sporting Goods",
            "type":"Retail Goods"
        }
    ],
    "sg:phone":"+1 209 575 2837",
    "sg:postcode":"95354",
    "sg:province":"CA",
    "sg:tags":[
        "equipment",
        "skateboard"
    ],
    "wof:name":"Mandatory Grind",
    "wof:placetype":"venue"
},
  "geometry": {"coordinates":[-120.98897700000001,37.644475],"type":"Point"}
}