{
  "type": "Feature",
  "properties": {
    "iso:country":"US",
    "sg:address":"8039 Beach Blvd",
    "sg:city":"Buena Park",
    "sg:classifiers":[
        {
            "category":"Recreation",
            "subcategory":"Amusement Park",
            "type":"Entertainment"
        },
        {
            "category":"Recreation",
            "subcategory":"Water Park",
            "type":"Entertainment"
        },
        {
            "category":"Sports & Exercise",
            "subcategory":"Swimming Pool",
            "type":"Entertainment"
        }
    ],
    "sg:phone":"+1 714 220 5200",
    "sg:postcode":"90620",
    "sg:province":"CA",
    "sg:tags":[
        "beach"
    ],
    "sg:website":"www.knotts.com",
    "wof:name":"Knott's Soak City Water Park",
    "wof:placetype":"venue"
},
  "geometry": {"coordinates":[-117.997163,33.841072],"type":"Point"}
}