{
  "type": "Feature",
  "properties": {
    "addr:full":"South Carlsbad State Beach Carlsbad CA 92011",
    "addr:postcode":"92011",
    "addr:street":"South Carlsbad State Beach",
    "iso:country":"US",
    "sg:address":"South Carlsbad State Beach",
    "sg:city":"Carlsbad",
    "sg:classifiers":[
        {
            "category":"Personal",
            "type":"Services"
        },
        {
            "category":"Sports & Exercise",
            "subcategory":"Playing Field",
            "type":"Entertainment"
        }
    ],
    "sg:phone":"+1 800 447 7873",
    "sg:postcode":"92011",
    "sg:province":"CA",
    "sg:tags":[
        "planning",
        "party",
        "instruction",
        "event",
        "fitness"
    ],
    "sg:website":"www.surfingacademy.com/",
    "wof:name":"San Diego Surfing Academy",
    "wof:placetype":"venue"
},
  "geometry": {"coordinates":[-117.31975,33.103958],"type":"Point"}
}