{
  "type": "Feature",
  "properties": {
    "iso:country":"US",
    "sg:address":"5901 Rosebud Lane Suite 320",
    "sg:city":"Sacramento",
    "sg:classifiers":[
        {
            "category":"Building & Trades",
            "subcategory":"Plumbing",
            "type":"Services"
        }
    ],
    "sg:phone":"+1 916 332 7473",
    "sg:postcode":"95841",
    "sg:province":"CA",
    "wof:name":"D & D Plumbing",
    "wof:placetype":"venue"
},
  "geometry": {"coordinates":[-121.34587999999999,38.66499],"type":"Point"}
}