{
  "type": "Feature",
  "properties": {
    "iso:country":"US",
    "sg:address":"Castro Theatre 429 Castro St",
    "sg:city":"San Francisco",
    "sg:classifiers":[
        {
            "category":"Cinema",
            "subcategory":"Movie Theater",
            "type":"Entertainment"
        }
    ],
    "sg:postcode":"94114",
    "sg:province":"CA",
    "sg:website":"www.noircity.com",
    "wof:name":"Noir City Film Festival",
    "wof:placetype":"venue"
},
  "geometry": {"coordinates":[-122.420863,37.779598],"type":"Point"}
}