{
  "type": "Feature",
  "properties": {
    "iso:country":"US",
    "sg:address":"484 N 14th St",
    "sg:city":"San Jose",
    "sg:classifiers":[
        {
            "category":"Freight",
            "type":"Transportation"
        }
    ],
    "sg:phone":"+1 408 280 5453",
    "sg:postcode":"95112",
    "sg:province":"CA",
    "sg:tags":[
        "operator",
        "local",
        "trucking"
    ],
    "wof:name":"Ralph Castro Trucking",
    "wof:placetype":"venue"
},
  "geometry": {"coordinates":[-121.882203,37.349366],"type":"Point"}
}