{
  "type": "Feature",
  "properties": {
    "addr:full":"7929 Valley Green Dr Sacramento CA 95823",
    "addr:housenumber":"7929",
    "addr:postcode":"95823",
    "addr:street":"Valley Green Dr",
    "iso:country":"US",
    "sg:address":"7929 Valley Green Dr",
    "sg:city":"Sacramento",
    "sg:classifiers":[
        {
            "category":"Personal",
            "type":"Services"
        }
    ],
    "sg:phone":"+1 916 730 9383",
    "sg:postcode":"95823",
    "sg:province":"CA",
    "sg:tags":[
        "therapist",
        "massage"
    ],
    "wof:name":"Comforting Hands",
    "wof:placetype":"venue"
},
  "geometry": {"coordinates":[-121.43495,38.465429],"type":"Point"}
}