{
  "type": "Feature",
  "properties": {
    "addr:full":"148 Nestles Rd Soledad CA 93960",
    "addr:housenumber":"148",
    "addr:postcode":"93960",
    "addr:street":"Nestles Rd",
    "iso:country":"US",
    "sg:address":"148 Nestles Rd",
    "sg:city":"Soledad",
    "sg:classifiers":[
        {
            "category":"Retail",
            "subcategory":"Auto Repair",
            "type":"Services"
        }
    ],
    "sg:phone":"+1 831 675 2227",
    "sg:postcode":"93960",
    "sg:province":"CA",
    "sg:tags":[
        "wrecker"
    ],
    "wof:name":"Pete's Shell Towing",
    "wof:placetype":"venue"
},
  "geometry": {"coordinates":[-121.322411,36.42024],"type":"Point"}
}