{
  "type": "Feature",
  "properties": {
    "addr:full":"2824 Normington Dr Sacramento CA 95833",
    "addr:housenumber":"2824",
    "addr:postcode":"95833",
    "addr:street":"Normington Dr",
    "iso:country":"US",
    "sg:address":"2824 Normington Dr",
    "sg:city":"Sacramento",
    "sg:classifiers":[
        {
            "category":"Building & Trades",
            "subcategory":"Landscaping Services",
            "type":"Services"
        }
    ],
    "sg:phone":"+1 916 716 3919",
    "sg:postcode":"95833",
    "sg:province":"CA",
    "sg:tags":[
        "lawn"
    ],
    "wof:name":"Salvador's Landscaping",
    "wof:placetype":"venue"
},
  "geometry": {"coordinates":[-121.480369,38.616387],"type":"Point"}
}