{
  "type": "Feature",
  "properties": {
    "addr:full":"1401 San Juan Rd Hollister CA 95023",
    "addr:housenumber":"1401",
    "addr:postcode":"hollister ca 95023",
    "addr:street":"San Juan Rd",
    "iso:country":"US",
    "sg:address":"1401 San Juan Rd",
    "sg:city":"Hollister",
    "sg:classifiers":[
        {
            "category":"Real Estate",
            "subcategory":"Real Estate Operator",
            "type":"Services"
        }
    ],
    "sg:phone":"+1 831 637 6311",
    "sg:postcode":"95023",
    "sg:province":"CA",
    "sg:tags":[
        "mobile",
        "home",
        "community"
    ],
    "wof:name":"Mission Oaks Mobile Home Park",
    "wof:placetype":"venue"
},
  "geometry": {"coordinates":[-121.4226,36.853054],"type":"Point"}
}