{
  "type": "Feature",
  "properties": {
    "addr:full":"1811 Trailwood Ct Redding CA 96003",
    "addr:housenumber":"1811",
    "addr:postcode":"96003",
    "addr:street":"Trailwood Ct",
    "iso:country":"US",
    "sg:address":"1811 Trailwood Ct",
    "sg:city":"Redding",
    "sg:classifiers":[
        {
            "category":"Building & Trades",
            "subcategory":"Landscaping Services",
            "type":"Services"
        }
    ],
    "sg:phone":"+1 530 246 8931",
    "sg:postcode":"96003",
    "sg:province":"CA",
    "sg:tags":[
        "landscape"
    ],
    "wof:name":"Cs Design Shop",
    "wof:placetype":"venue"
},
  "geometry": {"coordinates":[-122.393946,40.604488],"type":"Point"}
}