{
  "type": "Feature",
  "properties": {
    "iso:country":"US",
    "sg:address":"26875 Emerett Ln",
    "sg:city":"Perris",
    "sg:classifiers":[
        {
            "category":"Building & Trades",
            "subcategory":"Electrical",
            "type":"Services"
        }
    ],
    "sg:phone":"+1 951 940 1080",
    "sg:postcode":"92571",
    "sg:province":"CA",
    "sg:tags":[
        "electrical",
        "contractor"
    ],
    "wof:name":"Jerrys Electric",
    "wof:placetype":"venue"
},
  "geometry": {"coordinates":[-117.19314799999999,33.817463],"type":"Point"}
}