{
  "type": "Feature",
  "properties": {
    "addr:full":"154 Jordan Ave San Anselmo CA 94960",
    "addr:housenumber":"154",
    "addr:postcode":"94960",
    "addr:street":"Jordan Ave",
    "iso:country":"US",
    "sg:address":"154 Jordan Ave",
    "sg:city":"San Anselmo",
    "sg:classifiers":[
        {
            "category":"Professional",
            "type":"Services"
        }
    ],
    "sg:phone":"+1 415 456 2104",
    "sg:postcode":"94960",
    "sg:province":"CA",
    "wof:name":"Detweiler Family Ltd Partnr Th",
    "wof:placetype":"venue"
},
  "geometry": {"coordinates":[-122.554655,37.981369],"type":"Point"}
}