{
  "type": "Feature",
  "properties": {
    "iso:country":"US",
    "sg:address":"911 Central Ave",
    "sg:city":"Tracy",
    "sg:classifiers":[
        {
            "category":"Wholesale",
            "subcategory":"Durable Goods & Equipment",
            "type":"Manufacturing & Wholesale Goods"
        }
    ],
    "sg:phone":"+1 209 830 1373",
    "sg:postcode":"95376",
    "sg:province":"CA",
    "sg:tags":[
        "retail",
        "cassette",
        "jewelry"
    ],
    "wof:name":"Discoteca Toral",
    "wof:placetype":"venue"
},
  "geometry": {"coordinates":[-121.42600899999999,37.737814],"type":"Point"}
}