{
  "type": "Feature",
  "properties": {
    "addr:full":"8808 W Pico Blvd Los Angeles CA 90035",
    "addr:housenumber":"8808",
    "addr:postcode":"90035",
    "addr:street":"W Pico Blvd",
    "iso:country":"US",
    "sg:address":"8808 W Pico Blvd",
    "sg:city":"Los Angeles",
    "sg:classifiers":[
        {
            "category":"Shopping",
            "subcategory":"Clothing, Apparel, & Fashions",
            "type":"Retail Goods"
        }
    ],
    "sg:phone":"+1 310 276 7809",
    "sg:postcode":"90035",
    "sg:province":"CA",
    "sg:tags":[
        "costume",
        "jewelry"
    ],
    "wof:name":"International Jewelry Import",
    "wof:placetype":"venue"
},
  "geometry": {"coordinates":[-118.38450899999999,34.054832],"type":"Point"}
}