{
  "type": "Feature",
  "properties": {
    "iso:country":"US",
    "sg:address":"588 N Sunrise Ave Ste 150",
    "sg:city":"Roseville",
    "sg:classifiers":[
        {
            "category":"Health Services",
            "subcategory":"Clinic",
            "type":"Services"
        },
        {
            "category":"Health Services",
            "subcategory":"Medical Lab",
            "type":"Services"
        },
        {
            "category":"Professional",
            "subcategory":"Business Services",
            "type":"Services"
        }
    ],
    "sg:phone":"+1 877 312 7315",
    "sg:postcode":"95661",
    "sg:province":"CA",
    "sg:tags":[
        "information",
        "testing",
        "aid",
        "welfare"
    ],
    "sg:website":"http://sacramento.citysearch.com/profile/external/603804512/roseville_ca/std_test_express_roseville.html?publisher=yellowpages&reference_id=1&placement=ypwebsitemip",
    "wof:name":"STD Test Express Roseville",
    "wof:placetype":"venue"
},
  "geometry": {"coordinates":[-121.251597,38.760638],"type":"Point"}
}