{
  "type": "Feature",
  "properties": {
    "iso:country":"US",
    "sg:address":"7060 Hollywood Blvd",
    "sg:city":"Los Angeles",
    "sg:classifiers":[
        {
            "category":"Health Services",
            "subcategory":"Medical Lab",
            "type":"Services"
        }
    ],
    "sg:phone":"+1 323 469 7506",
    "sg:postcode":"90028",
    "sg:province":"CA",
    "sg:tags":[
        "laboratory"
    ],
    "wof:name":"Hollywood Imaging & Dgnstcs",
    "wof:placetype":"venue"
},
  "geometry": {"coordinates":[-118.344147,34.101526],"type":"Point"}
}