{
  "type": "Feature",
  "properties": {
    "iso:country":"US",
    "sg:address":"670 11th St",
    "sg:city":"Arcata",
    "sg:classifiers":[
        {
            "category":"Organizations",
            "subcategory":"Religious Organization",
            "type":"Services"
        }
    ],
    "sg:phone":"+1 707 822 1321",
    "sg:postcode":"95521",
    "sg:province":"CA",
    "sg:tags":[
        "counseling",
        "pastoral",
        "clergy"
    ],
    "wof:name":"First Presbyterian Church",
    "wof:placetype":"venue"
},
  "geometry": {"coordinates":[-124.08457799999999,40.870287],"type":"Point"}
}