{
  "type": "Feature",
  "properties": {
    "addr:full":"718 N Fries Ave Wilmington CA 90744",
    "addr:housenumber":"718",
    "addr:postcode":"90744",
    "addr:street":"N Fries Ave",
    "iso:country":"US",
    "sg:address":"718 N Fries Ave",
    "sg:city":"Wilmington",
    "sg:classifiers":[
        {
            "category":"Wholesale",
            "subcategory":"Durable Goods & Equipment",
            "type":"Manufacturing & Wholesale Goods"
        }
    ],
    "sg:phone":"+1 310 830 6601",
    "sg:postcode":"90744",
    "sg:province":"CA",
    "sg:tags":[
        "laboratory",
        "supply"
    ],
    "wof:name":"Sepor Inc",
    "wof:placetype":"venue"
},
  "geometry": {"coordinates":[-118.26494099999999,33.779572],"type":"Point"}
}