{
  "type": "Feature",
  "properties": {
    "iso:country":"US",
    "sg:address":"266 Plumosa Ave",
    "sg:city":"Vista",
    "sg:classifiers":[
        {
            "category":"Freight",
            "type":"Transportation"
        }
    ],
    "sg:phone":"+1 760 727 2004",
    "sg:postcode":"92083",
    "sg:province":"CA",
    "sg:tags":[
        "operator",
        "local",
        "trucking"
    ],
    "wof:name":"Reeds Transport",
    "wof:placetype":"venue"
},
  "geometry": {"coordinates":[-117.206363,33.164584],"type":"Point"}
}