{
  "type": "Feature",
  "properties": {
    "iso:country":"US",
    "sg:address":"4043 W 162nd St",
    "sg:city":"Lawndale",
    "sg:classifiers":[
        {
            "category":"Building & Trades",
            "subcategory":"Construction",
            "type":"Services"
        }
    ],
    "sg:phone":"+1 310 371 5603",
    "sg:postcode":"90260",
    "sg:province":"CA",
    "sg:tags":[
        "roofing",
        "industrial",
        "contractors-commercial",
        "contractor"
    ],
    "wof:name":"Weather Proof Roofing",
    "wof:placetype":"venue"
},
  "geometry": {"coordinates":[-118.344824,33.883572],"type":"Point"}
}