{
  "type": "Feature",
  "properties": {
    "addr:full":"298 Lakemuir Dr Sunnyvale CA 94089",
    "addr:housenumber":"298",
    "addr:postcode":"94089",
    "addr:street":"Lakemuir Dr",
    "iso:country":"US",
    "sg:address":"298 Lakemuir Dr",
    "sg:city":"Sunnyvale",
    "sg:classifiers":[
        {
            "category":"Autos & Motor Vehicles",
            "subcategory":"Automobile Sales",
            "type":"Retail Goods"
        }
    ],
    "sg:phone":"+1 408 830 0357",
    "sg:postcode":"94089",
    "sg:province":"CA",
    "sg:tags":[
        "limo"
    ],
    "wof:name":"Black Limousine & Sedan Service",
    "wof:placetype":"venue"
},
  "geometry": {"coordinates":[-121.998001,37.395802],"type":"Point"}
}