{
  "type": "Feature",
  "properties": {
    "addr:full":"619 E Gutierrez St Santa Barbara CA 93103",
    "addr:housenumber":"619",
    "addr:postcode":"93103",
    "addr:street":"E Gutierrez St",
    "iso:country":"US",
    "sg:address":"619 E Gutierrez St",
    "sg:city":"Santa Barbara",
    "sg:classifiers":[
        {
            "category":"Manufacturing",
            "subcategory":"Toys & Sporting Goods",
            "type":"Manufacturing & Wholesale Goods"
        }
    ],
    "sg:phone":"+1 805 966 3730",
    "sg:postcode":"93103",
    "sg:province":"CA",
    "sg:tags":[
        "athletic"
    ],
    "wof:name":"South Col",
    "wof:placetype":"venue"
},
  "geometry": {"coordinates":[-119.687129,34.422489],"type":"Point"}
}