{
  "type": "Feature",
  "properties": {
    "iso:country":"US",
    "sg:address":"15615 Alton Parkway",
    "sg:city":"Irvine",
    "sg:classifiers":[
        {
            "category":"Banks & Credit Unions",
            "subcategory":"Financial Services",
            "type":"Services"
        }
    ],
    "sg:phone":"+1 949 608 4900",
    "sg:postcode":"92618",
    "sg:province":"CA",
    "sg:tags":[
        "broker",
        "mortgage"
    ],
    "wof:name":"Equity Financial Group",
    "wof:placetype":"venue"
},
  "geometry": {"coordinates":[-117.75309,33.655438],"type":"Point"}
}