{
  "type": "Feature",
  "properties": {
    "addr:full":"769 Pacific St Monterey CA 93940",
    "addr:housenumber":"769",
    "addr:postcode":"93940",
    "addr:street":"Pacific St",
    "iso:country":"US",
    "sg:address":"769 Pacific St",
    "sg:city":"Monterey",
    "sg:classifiers":[
        {
            "category":"Professional",
            "subcategory":"Lawyer & Legal Services",
            "type":"Services"
        }
    ],
    "sg:phone":"+1 831 373 7636",
    "sg:postcode":"93940",
    "sg:province":"CA",
    "sg:tags":[
        "attorney"
    ],
    "wof:name":"Geoffrey C Fors",
    "wof:placetype":"venue"
},
  "geometry": {"coordinates":[-121.89812499999999,36.593724],"type":"Point"}
}