{
  "type": "Feature",
  "properties": {
    "iso:country":"US",
    "sg:address":"1359 Tea Rose Cir",
    "sg:city":"San Jose",
    "sg:classifiers":[
        {
            "category":"Professional",
            "subcategory":"Computer Services",
            "type":"Services"
        }
    ],
    "sg:phone":"+1 408 437 8870",
    "sg:postcode":"95131",
    "sg:province":"CA",
    "sg:tags":[
        "internet"
    ],
    "wof:name":"Dorm Deals",
    "wof:placetype":"venue"
},
  "geometry": {"coordinates":[-121.89434799999999,37.387828],"type":"Point"}
}