{
  "type": "Feature",
  "properties": {
    "addr:full":"3775 Alameda Avenue Oakland CA 94601",
    "addr:housenumber":"3775",
    "addr:postcode":"94601",
    "addr:street":"Alameda Avenue",
    "iso:country":"US",
    "sg:address":"3775 Alameda Avenue",
    "sg:city":"Oakland",
    "sg:classifiers":[
        {
            "category":"Sports & Exercise",
            "subcategory":"Gym",
            "type":"Entertainment"
        },
        {
            "category":"Sports & Exercise",
            "subcategory":"Sports Center",
            "type":"Entertainment"
        }
    ],
    "sg:phone":"+1 510 533 3939",
    "sg:postcode":"94601",
    "sg:province":"CA",
    "sg:tags":[
        "amateur",
        "team"
    ],
    "sg:website":"www.bayislandgymnastics.com",
    "wof:name":"Bay Island Gymnastics",
    "wof:placetype":"venue"
},
  "geometry": {"coordinates":[-122.229687,37.769536],"type":"Point"}
}