{
  "type": "Feature",
  "properties": {
    "addr:full":"7025 N Pleasant Ave Fresno CA 93711",
    "addr:housenumber":"7025",
    "addr:postcode":"93711",
    "addr:street":"N Pleasant Ave",
    "iso:country":"US",
    "sg:address":"7025 N Pleasant Ave",
    "sg:city":"Fresno",
    "sg:classifiers":[
        {
            "category":"Insurance",
            "subcategory":"Insurance Agent",
            "type":"Services"
        }
    ],
    "sg:phone":"+1 559 438 7235",
    "sg:postcode":"93711",
    "sg:province":"CA",
    "wof:name":"San Joaquin Actuarial Svc",
    "wof:placetype":"venue"
},
  "geometry": {"coordinates":[-119.83998200000001,36.837778],"type":"Point"}
}