{
  "type": "Feature",
  "properties": {
    "addr:full":"200 Old County Rd Belmont CA 94002",
    "addr:housenumber":"200",
    "addr:postcode":"94002",
    "addr:street":"Old County Rd",
    "iso:country":"US",
    "sg:address":"200 Old County Rd",
    "sg:city":"Belmont",
    "sg:classifiers":[
        {
            "category":"Professional",
            "type":"Services"
        },
        {
            "category":"Personal",
            "type":"Services"
        }
    ],
    "sg:phone":"+1 650 654 3663",
    "sg:postcode":"94002",
    "sg:province":"CA",
    "sg:tags":[
        "wedding",
        "planning",
        "caterer"
    ],
    "sg:website":"www.cuisinestyle.com/",
    "wof:name":"CuisineStyle by Pamela Keith",
    "wof:placetype":"venue"
},
  "geometry": {"coordinates":[-122.267881,37.514878],"type":"Point"}
}