{
  "type": "Feature",
  "properties": {
    "iso:country":"US",
    "sg:address":"8580 Sierra Ave",
    "sg:city":"Fontana",
    "sg:classifiers":[
        {
            "category":"Shopping",
            "subcategory":"Discount & Variety Stores",
            "type":"Retail Goods"
        }
    ],
    "sg:phone":"+1 909 822 0536",
    "sg:postcode":"92335",
    "sg:province":"CA",
    "wof:name":"Got A Dollar",
    "wof:placetype":"venue"
},
  "geometry": {"coordinates":[-117.43569599999999,34.098981],"type":"Point"}
}