{
  "type": "Feature",
  "properties": {
    "iso:country":"US",
    "sg:address":"350 N 18th St",
    "sg:city":"San Jose",
    "sg:classifiers":[
        {
            "category":"Building & Trades",
            "subcategory":"Construction",
            "type":"Services"
        }
    ],
    "sg:phone":"+1 408 279 4919",
    "sg:postcode":"95112",
    "sg:province":"CA",
    "sg:tags":[
        "house"
    ],
    "wof:name":"Rick Cruz Construction Inc",
    "wof:placetype":"venue"
},
  "geometry": {"coordinates":[-121.877521,37.349747],"type":"Point"}
}