{
  "type": "Feature",
  "properties": {
    "addr:full":"574 S Rancho Santa Fe Rd San Marcos CA 92078",
    "addr:housenumber":"574",
    "addr:postcode":"92078",
    "addr:street":"S Rancho Santa Fe Rd",
    "iso:country":"US",
    "sg:address":"574 S Rancho Santa Fe Rd",
    "sg:city":"San Marcos",
    "sg:classifiers":[
        {
            "category":"Professional",
            "subcategory":"Lawyer & Legal Services",
            "type":"Services"
        }
    ],
    "sg:phone":"+1 760 724 4800",
    "sg:postcode":"92078",
    "sg:province":"CA",
    "sg:tags":[
        "attorney"
    ],
    "wof:name":"Louis N Milstein",
    "wof:placetype":"venue"
},
  "geometry": {"coordinates":[-117.205202,33.136434],"type":"Point"}
}