{
  "type": "Feature",
  "properties": {
    "addr:full":"13150 E 166th Street. Cerritos CA 90703",
    "addr:housenumber":"13150",
    "addr:postcode":"ca 90703",
    "addr:street":"E 166Th Street.",
    "iso:country":"US",
    "sg:address":"13150 E 166th Street.",
    "sg:city":"Cerritos",
    "sg:classifiers":[
        {
            "category":"Sports & Exercise",
            "subcategory":"Gym",
            "type":"Entertainment"
        },
        {
            "category":"Sports & Exercise",
            "subcategory":"Swimming Pool",
            "type":"Entertainment"
        }
    ],
    "sg:phone":"+1 562 407 2600",
    "sg:postcode":"90703",
    "sg:province":"CA",
    "sg:website":"www.ci.cerritos.ca.us/cityserv/r...",
    "wof:name":"Cerritos Olympic Swim and Fitness Center",
    "wof:placetype":"venue"
},
  "geometry": {"coordinates":[-118.05073899999999,33.880485],"type":"Point"}
}