{
  "type": "Feature",
  "properties": {
    "iso:country":"US",
    "sg:address":"12325 Kerran St",
    "sg:city":"Poway",
    "sg:classifiers":[
        {
            "category":"Building & Trades",
            "subcategory":"Construction",
            "type":"Services"
        }
    ],
    "sg:phone":"+1 858 748 5011",
    "sg:postcode":"92064",
    "sg:province":"CA",
    "sg:tags":[
        "concrete",
        "contractor"
    ],
    "wof:name":"D & D Concrete Construction",
    "wof:placetype":"venue"
},
  "geometry": {"coordinates":[-117.053727,32.940032],"type":"Point"}
}