{
  "type": "Feature",
  "properties": {
    "addr:full":"1480 Edgewater Dr Turlock CA 95380",
    "addr:housenumber":"1480",
    "addr:postcode":"95380",
    "addr:street":"Edgewater Dr",
    "iso:country":"US",
    "sg:address":"1480 Edgewater Dr",
    "sg:city":"Turlock",
    "sg:classifiers":[
        {
            "category":"Building & Trades",
            "subcategory":"Cleaning & Sanitation",
            "type":"Services"
        }
    ],
    "sg:phone":"+1 209 669 1885",
    "sg:postcode":"95380",
    "sg:province":"CA",
    "sg:tags":[
        "janitor"
    ],
    "wof:name":"SST & C Cleaning",
    "wof:placetype":"venue"
},
  "geometry": {"coordinates":[-120.867107,37.506418],"type":"Point"}
}