{
  "type": "Feature",
  "properties": {
    "iso:country":"US",
    "sg:address":"4710 E Hoxie Ave",
    "sg:city":"Fresno",
    "sg:classifiers":[
        {
            "category":"Building & Trades",
            "subcategory":"Construction",
            "type":"Services"
        }
    ],
    "sg:phone":"+1 559 233 4707",
    "sg:postcode":"93725",
    "sg:province":"CA",
    "sg:tags":[
        "marking",
        "maintenance",
        "parking"
    ],
    "wof:name":"Romano & Sons Blacktop Sealing",
    "wof:placetype":"venue"
},
  "geometry": {"coordinates":[-119.739957,36.707311],"type":"Point"}
}