{
  "type": "Feature",
  "properties": {
    "iso:country":"US",
    "sg:address":"13050 2nd St",
    "sg:city":"Chino",
    "sg:classifiers":[
        {
            "category":"Organizations",
            "subcategory":"Religious Organization",
            "type":"Services"
        }
    ],
    "sg:phone":"+1 909 628 6512",
    "sg:postcode":"91710",
    "sg:province":"CA",
    "sg:tags":[
        "church"
    ],
    "wof:name":"Latin American Free Methodist",
    "wof:placetype":"venue"
},
  "geometry": {"coordinates":[-117.696932,34.016408],"type":"Point"}
}