{
  "type": "Feature",
  "properties": {
    "iso:country":"US",
    "sg:address":"12326 Riverside Dr",
    "sg:city":"North Hollywood",
    "sg:classifiers":[
        {
            "category":"Social Services",
            "type":"Services"
        }
    ],
    "sg:phone":"+1 818 762 4817",
    "sg:postcode":"91607",
    "sg:province":"CA",
    "sg:tags":[
        "crisis",
        "intervention"
    ],
    "wof:name":"Community Counseling Ctr",
    "wof:placetype":"venue"
},
  "geometry": {"coordinates":[-118.40261099999999,34.157542],"type":"Point"}
}