{
  "type": "Feature",
  "properties": {
    "addr:full":"1138 Wall St Los Angeles CA 90015",
    "addr:housenumber":"1138",
    "addr:postcode":"90015",
    "addr:street":"Wall St",
    "iso:country":"US",
    "sg:address":"1138 Wall St",
    "sg:city":"Los Angeles",
    "sg:classifiers":[
        {
            "category":"Shopping",
            "subcategory":"Clothing, Apparel, & Fashions",
            "type":"Retail Goods"
        }
    ],
    "sg:phone":"+1 213 747 1838",
    "sg:postcode":"90015",
    "sg:province":"CA",
    "sg:tags":[
        "clothing",
        "women's"
    ],
    "wof:name":"Clash Jeans & Sportswear",
    "wof:placetype":"venue"
},
  "geometry": {"coordinates":[-118.254997,34.035999],"type":"Point"}
}