{
  "type": "Feature",
  "properties": {
    "addr:full":"10879 N Wolfe Rd Cupertino CA 95014",
    "addr:housenumber":"10879",
    "addr:postcode":"95014",
    "addr:street":"N Wolfe Rd",
    "iso:country":"US",
    "sg:address":"10879 N Wolfe Rd",
    "sg:city":"Cupertino",
    "sg:classifiers":[
        {
            "category":"Personal",
            "subcategory":"Beauty Salon",
            "type":"Services"
        }
    ],
    "sg:phone":"+1 408 873 7662",
    "sg:postcode":"95014",
    "sg:province":"CA",
    "sg:tags":[
        "hair"
    ],
    "wof:name":"Calihair",
    "wof:placetype":"venue"
},
  "geometry": {"coordinates":[-122.014,37.3358],"type":"Point"}
}