{
  "type": "Feature",
  "properties": {
    "addr:full":"411 Rancho Rio Ave Ben Lomond CA 95005",
    "addr:housenumber":"411",
    "addr:postcode":"95005",
    "addr:street":"Rancho Rio Ave",
    "iso:country":"US",
    "sg:address":"411 Rancho Rio Ave",
    "sg:city":"Ben Lomond",
    "sg:classifiers":[
        {
            "category":"Retail",
            "subcategory":"Repair Shop",
            "type":"Services"
        }
    ],
    "sg:phone":"+1 831 336 8646",
    "sg:postcode":"95005",
    "sg:province":"CA",
    "sg:tags":[
        "spa",
        "hot",
        "tub"
    ],
    "wof:name":"Les Woolley Pool Svc",
    "wof:placetype":"venue"
},
  "geometry": {"coordinates":[-122.074347,37.090451],"type":"Point"}
}