{
  "type": "Feature",
  "properties": {
    "addr:full":"12125 Riverside Drive Suite 100 North Hollywood CA 91607",
    "addr:housenumber":"12125",
    "addr:postcode":"91607",
    "addr:street":"Riverside Drive Suite 100",
    "iso:country":"US",
    "sg:address":"12125 Riverside Drive Suite 100",
    "sg:city":"North Hollywood",
    "sg:classifiers":[
        {
            "category":"Real Estate",
            "subcategory":"Real Estate Agent",
            "type":"Services"
        }
    ],
    "sg:phone":"+1 818 755 1144",
    "sg:postcode":"91607",
    "sg:province":"CA",
    "sg:website":"www.findyourhomeinsanfernandoval...",
    "wof:name":"Erwin Residential Group",
    "wof:placetype":"venue"
},
  "geometry": {"coordinates":[-118.397451,34.157629],"type":"Point"}
}