{
  "type": "Feature",
  "properties": {
    "addr:full":"4315 Pacific Coast Hwy Torrance CA 90505",
    "addr:housenumber":"4315",
    "addr:postcode":"90505",
    "addr:street":"Pacific Coast Hwy",
    "iso:country":"US",
    "sg:address":"4315 Pacific Coast Hwy",
    "sg:city":"Torrance",
    "sg:classifiers":[
        {
            "category":"Shopping",
            "subcategory":"Department Store",
            "type":"Retail Goods"
        }
    ],
    "sg:phone":"+1 310 373 0784",
    "sg:postcode":"90505",
    "sg:province":"CA",
    "wof:name":"Ross Stores Inc",
    "wof:placetype":"venue"
},
  "geometry": {"coordinates":[-118.360001,33.808201],"type":"Point"}
}