{
  "type": "Feature",
  "properties": {
    "addr:full":"478 W Douglas Ave El Cajon CA 92020",
    "addr:housenumber":"478",
    "addr:postcode":"92020",
    "addr:street":"W Douglas Ave",
    "iso:country":"US",
    "sg:address":"478 W Douglas Ave",
    "sg:city":"El Cajon",
    "sg:classifiers":[
        {
            "category":"Manufacturing",
            "subcategory":"Building Materials",
            "type":"Manufacturing & Wholesale Goods"
        }
    ],
    "sg:phone":"+1 619 401 6878",
    "sg:postcode":"92020",
    "sg:province":"CA",
    "sg:tags":[
        "mfg",
        "wood",
        "kitchen",
        "cabinet"
    ],
    "wof:name":"Italian Cabinets",
    "wof:placetype":"venue"
},
  "geometry": {"coordinates":[-116.967879,32.794828],"type":"Point"}
}