{
  "type": "Feature",
  "properties": {
    "iso:country":"US",
    "sg:address":"15838 Arminta St",
    "sg:city":"Van Nuys",
    "sg:classifiers":[
        {
            "category":"Manufacturing",
            "subcategory":"Glass & Minerals",
            "type":"Manufacturing & Wholesale Goods"
        },
        {
            "category":"Professional",
            "subcategory":"Research",
            "type":"Services"
        }
    ],
    "sg:phone":"+1 818 785 9702",
    "sg:postcode":"91406",
    "sg:province":"CA",
    "sg:tags":[
        "mfg"
    ],
    "wof:name":"California Graphite Research",
    "wof:placetype":"venue"
},
  "geometry": {"coordinates":[-118.478091,34.21381],"type":"Point"}
}