{
  "type": "Feature",
  "properties": {
    "addr:full":"8951 Walker St Cypress CA 90630",
    "addr:housenumber":"8951",
    "addr:postcode":"90630",
    "addr:street":"Walker St",
    "iso:country":"US",
    "sg:address":"8951 Walker St",
    "sg:city":"Cypress",
    "sg:classifiers":[
        {
            "category":"Restaurant",
            "type":"Food & Drink"
        }
    ],
    "sg:phone":"+1 714 527 7849",
    "sg:postcode":"90630",
    "sg:province":"CA",
    "wof:name":"Cheng's Kitchen",
    "wof:placetype":"venue"
},
  "geometry": {"coordinates":[-118.037085,33.831971],"type":"Point"}
}