{
  "type": "Feature",
  "properties": {
    "addr:full":"9954 Macarthur Blvd Oakland CA 94605",
    "addr:housenumber":"9954",
    "addr:postcode":"94605",
    "addr:street":"Macarthur Blvd",
    "iso:country":"US",
    "sg:address":"9954 Macarthur Blvd",
    "sg:city":"Oakland",
    "sg:classifiers":[
        {
            "category":"Professional",
            "subcategory":"Management & Consulting",
            "type":"Services"
        }
    ],
    "sg:phone":"+1 510 638 8395",
    "sg:postcode":"94605",
    "sg:province":"CA",
    "sg:tags":[
        "consultant",
        "training"
    ],
    "wof:name":"Certified Trainers Inc",
    "wof:placetype":"venue"
},
  "geometry": {"coordinates":[-122.15639299999999,37.746232],"type":"Point"}
}