{
  "type": "Feature",
  "properties": {
    "iso:country":"US",
    "sg:address":"3747 Convoy St",
    "sg:city":"San Diego",
    "sg:classifiers":[
        {
            "category":"Autos & Motor Vehicles",
            "subcategory":"Auto Supplies",
            "type":"Retail Goods"
        }
    ],
    "sg:phone":"+1 858 576 0054",
    "sg:postcode":"92111",
    "sg:province":"CA",
    "sg:tags":[
        "tire"
    ],
    "wof:name":"Evans Tire & Svc Ctr",
    "wof:placetype":"venue"
},
  "geometry": {"coordinates":[-117.152609,32.812925],"type":"Point"}
}