{
  "type": "Feature",
  "properties": {
    "iso:country":"US",
    "sg:address":"17767 Santiago Blvd Ste 602",
    "sg:city":"Villa Park",
    "sg:classifiers":[
        {
            "category":"Shopping",
            "subcategory":"Jewelry",
            "type":"Retail Goods"
        }
    ],
    "sg:phone":"+1 714 974 3500",
    "sg:postcode":"92861",
    "sg:province":"CA",
    "wof:name":"Jewelry Designs by Steven",
    "wof:placetype":"venue"
},
  "geometry": {"coordinates":[-117.820999,33.814098],"type":"Point"}
}