{
  "type": "Feature",
  "properties": {
    "iso:country":"US",
    "sg:address":"5530 Buffwood Pl",
    "sg:city":"Agoura Hills",
    "sg:classifiers":[
        {
            "category":"Banks & Credit Unions",
            "subcategory":"Bank",
            "type":"Services"
        }
    ],
    "sg:phone":"+1 818 991 0023",
    "sg:postcode":"91301",
    "sg:province":"CA",
    "sg:tags":[
        "loan",
        "real estate"
    ],
    "wof:name":"Picture Perfect Properties",
    "wof:placetype":"venue"
},
  "geometry": {"coordinates":[-118.75995399999999,34.152202],"type":"Point"}
}