{
  "type": "Feature",
  "properties": {
    "iso:country":"US",
    "sg:address":"74818 Velie Dr",
    "sg:city":"Palm Desert",
    "sg:classifiers":[
        {
            "category":"Building & Trades",
            "subcategory":"Construction",
            "type":"Services"
        }
    ],
    "sg:phone":"+1 760 341 9333",
    "sg:postcode":"92260",
    "sg:province":"CA",
    "sg:tags":[
        "home",
        "builder"
    ],
    "wof:name":"Centennial Homes",
    "wof:placetype":"venue"
},
  "geometry": {"coordinates":[-116.358655,33.742619],"type":"Point"}
}