{
  "type": "Feature",
  "properties": {
    "addr:full":"5772 Angela Ave Riverside CA 92509",
    "addr:housenumber":"5772",
    "addr:postcode":"92509",
    "addr:street":"Angela Ave",
    "iso:country":"US",
    "sg:address":"5772 Angela Ave",
    "sg:city":"Riverside",
    "sg:classifiers":[
        {
            "category":"Home & Garden",
            "subcategory":"Building Materials",
            "type":"Retail Goods"
        },
        {
            "category":"Home & Garden",
            "subcategory":"Furniture",
            "type":"Retail Goods"
        }
    ],
    "sg:phone":"+1 951 681 2887",
    "sg:postcode":"92509",
    "sg:province":"CA",
    "sg:tags":[
        "equipment",
        "kitchen",
        "cabinet"
    ],
    "wof:name":"Darryn's Custom Cabinets",
    "wof:placetype":"venue"
},
  "geometry": {"coordinates":[-117.48115799999999,33.983288],"type":"Point"}
}