{
  "type": "Feature",
  "properties": {
    "addr:full":"10 Washington St Oakland CA 94607",
    "addr:housenumber":"10",
    "addr:postcode":"94607",
    "addr:street":"Washington St",
    "iso:country":"US",
    "sg:address":"10 Washington St",
    "sg:city":"Oakland",
    "sg:classifiers":[
        {
            "category":"Professional",
            "subcategory":"Management & Consulting",
            "type":"Services"
        },
        {
            "category":"Travel",
            "subcategory":"Hotels & Motels",
            "type":"Entertainment"
        }
    ],
    "sg:phone":"+1 510 836 2072",
    "sg:postcode":"94607",
    "sg:province":"CA",
    "sg:tags":[
        "consultant"
    ],
    "sg:website":"http://www.creativehospitality.com",
    "wof:name":"Creative Hospitality Corp",
    "wof:placetype":"venue"
},
  "geometry": {"coordinates":[-122.278999,37.794899],"type":"Point"}
}