{
  "type": "Feature",
  "properties": {
    "addr:full":"2602 N Broadway Los Angeles CA 90031",
    "addr:housenumber":"2602",
    "addr:postcode":"90031",
    "addr:street":"N Broadway",
    "iso:country":"US",
    "sg:address":"2602 N Broadway",
    "sg:city":"Los Angeles",
    "sg:classifiers":[
        {
            "category":"Shopping",
            "subcategory":"Shoes",
            "type":"Retail Goods"
        }
    ],
    "sg:phone":"+1 323 222 6839",
    "sg:postcode":"90031",
    "sg:province":"CA",
    "wof:name":"Payless",
    "wof:placetype":"venue"
},
  "geometry": {"coordinates":[-118.214381,34.073584],"type":"Point"}
}