{
  "type": "Feature",
  "properties": {
    "addr:full":"15712 Wilder Ave Norwalk CA 90650",
    "addr:housenumber":"15712",
    "addr:postcode":"90650",
    "addr:street":"Wilder Ave",
    "iso:country":"US",
    "sg:address":"15712 Wilder Ave",
    "sg:city":"Norwalk",
    "sg:classifiers":[
        {
            "category":"Manufacturing",
            "subcategory":"Retail Goods",
            "type":"Manufacturing & Wholesale Goods"
        }
    ],
    "sg:phone":"+1 562 883 0490",
    "sg:postcode":"90650",
    "sg:province":"CA",
    "sg:tags":[
        "product",
        "mfg"
    ],
    "wof:name":"Hypnos",
    "wof:placetype":"venue"
},
  "geometry": {"coordinates":[-118.06174900000001,33.890426],"type":"Point"}
}