{
  "type": "Feature",
  "properties": {
    "addr:full":"2810 S Bristol St Santa Ana CA 92704",
    "addr:housenumber":"2810",
    "addr:postcode":"92704",
    "addr:street":"S Bristol St",
    "iso:country":"US",
    "sg:address":"2810 S Bristol St",
    "sg:city":"Santa Ana",
    "sg:classifiers":[
        {
            "category":"Health Services",
            "subcategory":"Doctor",
            "type":"Services"
        }
    ],
    "sg:phone":"+1 714 754 0887",
    "sg:postcode":"92704",
    "sg:province":"CA",
    "wof:name":"Ludmir Jamie MD",
    "wof:placetype":"venue"
},
  "geometry": {"coordinates":[-117.886002,33.7094],"type":"Point"}
}