{
  "type": "Feature",
  "properties": {
    "addr:full":"2512 Russell St Berkeley CA 94705",
    "addr:housenumber":"2512",
    "addr:postcode":"94705",
    "addr:street":"Russell St",
    "iso:country":"US",
    "sg:address":"2512 Russell St",
    "sg:city":"Berkeley",
    "sg:classifiers":[
        {
            "category":"Professional",
            "type":"Services"
        }
    ],
    "sg:phone":"+1 510 847 1447",
    "sg:postcode":"94705",
    "sg:province":"CA",
    "wof:name":"AG Consulting Negotiations Coaching",
    "wof:placetype":"venue"
},
  "geometry": {"coordinates":[-122.25631799999999,37.857855],"type":"Point"}
}