{
  "type": "Feature",
  "properties": {
    "addr:full":"14078 Washington Ave San Leandro CA 94578",
    "addr:housenumber":"14078",
    "addr:postcode":"94578",
    "addr:street":"Washington Ave",
    "iso:country":"US",
    "sg:address":"14078 Washington Ave",
    "sg:city":"San Leandro",
    "sg:classifiers":[
        {
            "category":"Retail",
            "subcategory":"Auto Repair",
            "type":"Services"
        }
    ],
    "sg:phone":"+1 510 351 0467",
    "sg:postcode":"94578",
    "sg:province":"CA",
    "sg:tags":[
        "repairing",
        "automobile"
    ],
    "wof:name":"Union Auto Repair",
    "wof:placetype":"venue"
},
  "geometry": {"coordinates":[-122.147003,37.710499],"type":"Point"}
}