{
  "type": "Feature",
  "properties": {
    "iso:country":"US",
    "sg:address":"9281 Sheep Creek Rd",
    "sg:city":"Phelan",
    "sg:classifiers":[
        {
            "category":"Organizations",
            "subcategory":"Religious Organization",
            "type":"Services"
        }
    ],
    "sg:phone":"+1 760 868 1519",
    "sg:postcode":"92371",
    "sg:province":"CA",
    "sg:tags":[
        "church"
    ],
    "wof:name":"Cornerstone Baptist Church",
    "wof:placetype":"venue"
},
  "geometry": {"coordinates":[-117.572422,34.417187],"type":"Point"}
}