{
  "type": "Feature",
  "properties": {
    "iso:country":"US",
    "sg:address":"16055 Ventura Blvd",
    "sg:city":"Encino",
    "sg:classifiers":[
        {
            "category":"Health Services",
            "subcategory":"Doctor",
            "type":"Services"
        }
    ],
    "sg:phone":"+1 818 990 5240",
    "sg:postcode":"91436",
    "sg:province":"CA",
    "sg:tags":[
        "dentist"
    ],
    "wof:name":"Gary Tobin DDS",
    "wof:placetype":"venue"
},
  "geometry": {"coordinates":[-118.482609,34.156279],"type":"Point"}
}