{
  "type": "Feature",
  "properties": {
    "addr:full":"295 N Front St Rio Vista CA 94571",
    "addr:housenumber":"295",
    "addr:postcode":"94571",
    "addr:street":"N Front St",
    "iso:country":"US",
    "sg:address":"295 N Front St",
    "sg:city":"Rio Vista",
    "sg:classifiers":[
        {
            "category":"Retail",
            "subcategory":"Auto Repair",
            "type":"Services"
        }
    ],
    "sg:phone":"+1 707 374 5630",
    "sg:postcode":"94571",
    "sg:province":"CA",
    "sg:tags":[
        "tire",
        "supply"
    ],
    "wof:name":"Js Rio Vista Tire Service",
    "wof:placetype":"venue"
},
  "geometry": {"coordinates":[-121.688064,38.159511],"type":"Point"}
}