{
  "type": "Feature",
  "properties": {
    "iso:country":"US",
    "sg:address":"1565 W Arrow Hwy",
    "sg:city":"Upland",
    "sg:classifiers":[
        {
            "category":"Local Transit",
            "type":"Transportation"
        }
    ],
    "sg:phone":"+1 909 949 8349",
    "sg:postcode":"91786",
    "sg:province":"CA",
    "sg:tags":[
        "passenger"
    ],
    "wof:name":"Custom Class Limousines",
    "wof:placetype":"venue"
},
  "geometry": {"coordinates":[-117.67911100000001,34.099706],"type":"Point"}
}