{
  "type": "Feature",
  "properties": {
    "iso:country":"US",
    "sg:address":"9167 Kiefer Blvd",
    "sg:city":"Sacramento",
    "sg:classifiers":[
        {
            "category":"Shopping",
            "subcategory":"Computers & Home Electronics",
            "type":"Retail Goods"
        }
    ],
    "sg:phone":"+1 916 362 1855",
    "sg:postcode":"95826",
    "sg:province":"CA",
    "sg:tags":[
        "hardware",
        "supply"
    ],
    "wof:name":"Aritech Computer",
    "wof:placetype":"venue"
},
  "geometry": {"coordinates":[-121.359427,38.547282],"type":"Point"}
}