{
  "type": "Feature",
  "properties": {
    "addr:full":"3807 5th Ave San Diego CA 92103",
    "addr:housenumber":"3807",
    "addr:postcode":"92103",
    "addr:street":"5Th Ave",
    "iso:country":"US",
    "sg:address":"3807 5th Ave",
    "sg:city":"San Diego",
    "sg:classifiers":[
        {
            "category":"Shopping",
            "subcategory":"Florist",
            "type":"Retail Goods"
        }
    ],
    "sg:phone":"+1 619 299 9092",
    "sg:postcode":"92103",
    "sg:province":"CA",
    "wof:name":"Flora Style",
    "wof:placetype":"venue"
},
  "geometry": {"coordinates":[-117.160359,32.748189],"type":"Point"}
}