{
  "type": "Feature",
  "properties": {
    "addr:full":"9851 Acampo Rd Acampo CA 95220",
    "addr:housenumber":"9851",
    "addr:postcode":"95220",
    "addr:street":"Acampo Rd",
    "iso:country":"US",
    "sg:address":"9851 Acampo Rd",
    "sg:city":"Acampo",
    "sg:classifiers":[
        {
            "category":"Farming",
            "subcategory":"Vineyard",
            "type":"Manufacturing & Wholesale Goods"
        }
    ],
    "sg:phone":"+1 209 369 0864",
    "sg:postcode":"95220",
    "sg:province":"CA",
    "sg:tags":[
        "farm",
        "management",
        "grape"
    ],
    "wof:name":"Fuso Anthony & David",
    "wof:placetype":"venue"
},
  "geometry": {"coordinates":[-121.188354,38.175581],"type":"Point"}
}