{
  "type": "Feature",
  "properties": {
    "addr:full":"3030 Foothill Blvd La Crescenta CA 91214",
    "addr:housenumber":"3030",
    "addr:postcode":"91214",
    "addr:street":"Foothill Blvd",
    "iso:country":"US",
    "sg:address":"3030 Foothill Blvd",
    "sg:city":"La Crescenta",
    "sg:classifiers":[
        {
            "category":"Shopping",
            "subcategory":"Stationery & Office Supplies",
            "type":"Retail Goods"
        }
    ],
    "sg:phone":"+1 818 236 2121",
    "sg:postcode":"91214",
    "sg:province":"CA",
    "sg:website":"www.officedepot.com",
    "wof:name":"Office Depot",
    "wof:placetype":"venue"
},
  "geometry": {"coordinates":[-118.24489800000001,34.227119],"type":"Point"}
}