{
  "type": "Feature",
  "properties": {
    "addr:full":"22805 Macfarlane Dr Woodland Hills CA 91364",
    "addr:housenumber":"22805",
    "addr:postcode":"91364",
    "addr:street":"Macfarlane Dr",
    "iso:country":"US",
    "sg:address":"22805 Macfarlane Dr",
    "sg:city":"Woodland Hills",
    "sg:classifiers":[
        {
            "category":"Building & Trades",
            "subcategory":"Electrical",
            "type":"Services"
        }
    ],
    "sg:phone":"+1 805 494 7814",
    "sg:postcode":"91364",
    "sg:province":"CA",
    "sg:tags":[
        "electrical",
        "contractor"
    ],
    "wof:name":"Nottingham Electric",
    "wof:placetype":"venue"
},
  "geometry": {"coordinates":[-118.625175,34.161446],"type":"Point"}
}