{
  "type": "Feature",
  "properties": {
    "addr:full":"800 Heinz Ave Ste 11 Berkeley CA 94710",
    "addr:housenumber":"800;11",
    "addr:postcode":"94710",
    "addr:street":"Heinz Ave Ste",
    "iso:country":"US",
    "sg:address":"800 Heinz Ave Ste 11",
    "sg:city":"Berkeley",
    "sg:classifiers":[
        {
            "category":"Parking",
            "type":"Transportation"
        },
        {
            "category":"Shopping",
            "subcategory":"Bicycles & Sporting Goods",
            "type":"Retail Goods"
        }
    ],
    "sg:phone":"+1 510 549 2853",
    "sg:postcode":"94710",
    "sg:province":"CA",
    "sg:tags":[
        "bike"
    ],
    "sg:website":"www.bikelink.org",
    "wof:name":"BikeLink",
    "wof:placetype":"venue"
},
  "geometry": {"coordinates":[-122.293269,37.853215],"type":"Point"}
}