{
  "type": "Feature",
  "properties": {
    "addr:full":"256 S Robertson Blvd Beverly Hills CA 90211",
    "addr:housenumber":"256",
    "addr:postcode":"90211",
    "addr:street":"S Robertson Blvd",
    "iso:country":"US",
    "sg:address":"256 S Robertson Blvd",
    "sg:city":"Beverly Hills",
    "sg:classifiers":[
        {
            "category":"Professional",
            "type":"Services"
        }
    ],
    "sg:phone":"+1 310 657 1900",
    "sg:postcode":"90211",
    "sg:province":"CA",
    "wof:name":"Roddy Vaillancourt LP",
    "wof:placetype":"venue"
},
  "geometry": {"coordinates":[-118.383483,34.06411],"type":"Point"}
}