{
  "type": "Feature",
  "properties": {
    "iso:country":"US",
    "sg:address":"8052 Melrose Avenue",
    "sg:city":"Los Angeles",
    "sg:classifiers":[
        {
            "category":"Banks & Credit Unions",
            "subcategory":"Investment Brokerage",
            "type":"Services"
        }
    ],
    "sg:phone":"+1 323 658 7773",
    "sg:postcode":"90046",
    "sg:province":"CA",
    "sg:tags":[
        "investing"
    ],
    "wof:name":"Gordon Bill",
    "wof:placetype":"venue"
},
  "geometry": {"coordinates":[-118.365092,34.083867],"type":"Point"}
}