{
  "type": "Feature",
  "properties": {
    "addr:full":"9155 Las Tunas Dr Temple City CA 91780",
    "addr:housenumber":"9155",
    "addr:postcode":"91780",
    "addr:street":"Las Tunas Dr",
    "iso:country":"US",
    "sg:address":"9155 Las Tunas Dr",
    "sg:city":"Temple City",
    "sg:classifiers":[
        {
            "category":"Education",
            "subcategory":"Library",
            "type":"Public Place"
        }
    ],
    "sg:phone":"+1 323 283 5801",
    "sg:postcode":"91780",
    "sg:province":"CA",
    "wof:name":"Loose Leaf Filing Service",
    "wof:placetype":"venue"
},
  "geometry": {"coordinates":[-118.069,34.105598],"type":"Point"}
}