{
  "type": "Feature",
  "properties": {
    "iso:country":"US",
    "sg:address":"1577 Meadowlark Dr",
    "sg:city":"Fairfield",
    "sg:classifiers":[
        {
            "category":"Organizations",
            "subcategory":"Religious Organization",
            "type":"Services"
        }
    ],
    "sg:phone":"+1 925 427 9372",
    "sg:postcode":"94533",
    "sg:province":"CA",
    "sg:tags":[
        "church"
    ],
    "wof:name":"Shiloh Christian Ctr",
    "wof:placetype":"venue"
},
  "geometry": {"coordinates":[-121.998565,38.269326],"type":"Point"}
}