{
  "type": "Feature",
  "properties": {
    "addr:full":"1441 Gisler Avenue Costa Mesa CA 92626",
    "addr:housenumber":"1441",
    "addr:postcode":"92626",
    "addr:street":"Gisler Avenue",
    "iso:country":"US",
    "sg:address":"1441 Gisler Avenue",
    "sg:city":"Costa Mesa",
    "sg:classifiers":[
        {
            "category":"Travel",
            "subcategory":"Hotels & Motels",
            "type":"Entertainment"
        }
    ],
    "sg:phone":"+1 714 957 3063",
    "sg:postcode":"92626",
    "sg:province":"CA",
    "wof:name":"Motel 6",
    "wof:placetype":"venue"
},
  "geometry": {"coordinates":[-117.917805,33.686895],"type":"Point"}
}