{
  "type": "Feature",
  "properties": {
    "addr:full":"4144 Lankershim Blvd North Hollywood CA 91602",
    "addr:housenumber":"4144",
    "addr:postcode":"91602",
    "addr:street":"Lankershim Blvd",
    "iso:country":"US",
    "sg:address":"4144 Lankershim Blvd",
    "sg:city":"North Hollywood",
    "sg:classifiers":[
        {
            "category":"Professional",
            "subcategory":"Art Services",
            "type":"Services"
        }
    ],
    "sg:phone":"+1 323 845 0040",
    "sg:postcode":"91602",
    "sg:province":"CA",
    "sg:tags":[
        "graphic",
        "designer"
    ],
    "wof:name":"1 K Studios",
    "wof:placetype":"venue"
},
  "geometry": {"coordinates":[-118.363061,34.145907],"type":"Point"}
}