{
  "type": "Feature",
  "properties": {
    "addr:full":"5280 Yorkshire Dr Cypress CA 90630",
    "addr:housenumber":"5280",
    "addr:postcode":"90630",
    "addr:street":"Yorkshire Dr",
    "iso:country":"US",
    "sg:address":"5280 Yorkshire Dr",
    "sg:city":"Cypress",
    "sg:classifiers":[
        {
            "category":"Professional",
            "subcategory":"Advertising",
            "type":"Services"
        }
    ],
    "sg:phone":"+1 714 527 6340",
    "sg:postcode":"90630",
    "sg:province":"CA",
    "sg:website":"www.xy.com",
    "wof:name":"XY.COM",
    "wof:placetype":"venue"
},
  "geometry": {"coordinates":[-118.04026500000001,33.820881],"type":"Point"}
}