{
  "type": "Feature",
  "properties": {
    "addr:full":"14535 Stage Rd La Mirada CA 90638",
    "addr:housenumber":"14535",
    "addr:postcode":"90638",
    "addr:street":"Stage Rd",
    "iso:country":"US",
    "sg:address":"14535 Stage Rd",
    "sg:city":"La Mirada",
    "sg:classifiers":[
        {
            "category":"Real Estate",
            "subcategory":"Real Estate Operator",
            "type":"Services"
        }
    ],
    "sg:phone":"+1 714 521 7558",
    "sg:postcode":"90638",
    "sg:province":"CA",
    "sg:tags":[
        "apartment"
    ],
    "wof:name":"Ranch Apartments the",
    "wof:placetype":"venue"
},
  "geometry": {"coordinates":[-118.023003,33.894901],"type":"Point"}
}