{
  "type": "Feature",
  "properties": {
    "addr:full":"4039 Lyman Rd Oakland CA 94602",
    "addr:housenumber":"4039",
    "addr:postcode":"94602",
    "addr:street":"Lyman Rd",
    "iso:country":"US",
    "sg:address":"4039 Lyman Rd",
    "sg:city":"Oakland",
    "sg:classifiers":[
        {
            "category":"Professional",
            "subcategory":"Computer Services",
            "type":"Services"
        }
    ],
    "sg:phone":"+1 510 531 4837",
    "sg:postcode":"94602",
    "sg:province":"CA",
    "sg:tags":[
        "information",
        "technology"
    ],
    "wof:name":"Oakmore Resources",
    "wof:placetype":"venue"
},
  "geometry": {"coordinates":[-122.212279,37.807693],"type":"Point"}
}