{
  "type": "Feature",
  "properties": {
    "addr:full":"8620 Spectrum Center Blvd San Diego CA 92123",
    "addr:housenumber":"8620",
    "addr:postcode":"92123",
    "addr:street":"Spectrum Center Blvd",
    "iso:country":"US",
    "sg:address":"8620 Spectrum Center Blvd",
    "sg:city":"San Diego",
    "sg:classifiers":[
        {
            "category":"Education",
            "subcategory":"Special Training",
            "type":"Public Place"
        }
    ],
    "sg:phone":"+1 858 874 0743",
    "sg:postcode":"92123",
    "sg:province":"CA",
    "sg:tags":[
        "school",
        "specialty"
    ],
    "wof:name":"Bridgepoint Education",
    "wof:placetype":"venue"
},
  "geometry": {"coordinates":[-117.14251299999999,32.82732],"type":"Point"}
}