{
  "type": "Feature",
  "properties": {
    "addr:full":"7771 Foothill Blvd Tujunga CA 91042",
    "addr:housenumber":"7771",
    "addr:postcode":"91042",
    "addr:street":"Foothill Blvd",
    "iso:country":"US",
    "sg:address":"7771 Foothill Blvd",
    "sg:city":"Tujunga",
    "sg:classifiers":[
        {
            "category":"Education",
            "subcategory":"Library",
            "type":"Public Place"
        }
    ],
    "sg:phone":"+1 818 352 4481",
    "sg:postcode":"91042",
    "sg:province":"CA",
    "sg:website":"www.lapl.org",
    "wof:name":"Sunland-Tujunga Branch Library",
    "wof:placetype":"venue"
},
  "geometry": {"coordinates":[-118.30154899999999,34.257953],"type":"Point"}
}