{
  "type": "Feature",
  "properties": {
    "iso:country":"US",
    "sg:address":"6313 Shiloh Way",
    "sg:city":"Sacramento",
    "sg:classifiers":[
        {
            "category":"Retail",
            "subcategory":"Repair Shop",
            "type":"Services"
        }
    ],
    "sg:phone":"+1 916 765 8975",
    "sg:postcode":"95841",
    "sg:province":"CA",
    "sg:tags":[
        "television",
        "radio-service"
    ],
    "wof:name":"Expert Installations",
    "wof:placetype":"venue"
},
  "geometry": {"coordinates":[-121.337484,38.680448],"type":"Point"}
}