{
  "type": "Feature",
  "properties": {
    "addr:full":"505 Pole Line Rd Davis CA 95618",
    "addr:housenumber":"505",
    "addr:postcode":"95618",
    "addr:street":"Pole Line Rd",
    "iso:country":"US",
    "sg:address":"505 Pole Line Rd",
    "sg:city":"Davis",
    "sg:classifiers":[
        {
            "category":"Government",
            "subcategory":"Office",
            "type":"Public Place"
        }
    ],
    "sg:phone":"+1 530 753 6813",
    "sg:postcode":"95618",
    "sg:province":"CA",
    "sg:tags":[
        "transportation"
    ],
    "wof:name":"Davis DMV Office",
    "wof:placetype":"venue"
},
  "geometry": {"coordinates":[-121.72679599999999,38.549919],"type":"Point"}
}