{
  "type": "Feature",
  "properties": {
    "addr:full":"3295A El Camino Real Santa Clara CA 95051",
    "addr:housenumber":"3295a",
    "addr:postcode":"95051",
    "addr:street":"El Camino Real",
    "iso:country":"US",
    "sg:address":"3295A El Camino Real",
    "sg:city":"Santa Clara",
    "sg:classifiers":[
        {
            "category":"Retail",
            "subcategory":"Auto Repair",
            "type":"Services"
        }
    ],
    "sg:phone":"+1 408 554 9210",
    "sg:postcode":"95051",
    "sg:province":"CA",
    "sg:website":"actrepairca.com",
    "wof:name":"Auto Clutch & Transmission Auto Repair",
    "wof:placetype":"venue"
},
  "geometry": {"coordinates":[-121.986515,37.352946],"type":"Point"}
}