{
  "type": "Feature",
  "properties": {
    "iso:country":"US",
    "sg:address":"210 N Aviation Blvd",
    "sg:city":"Manhattan Beach",
    "sg:classifiers":[
        {
            "category":"Personal",
            "type":"Services"
        }
    ],
    "sg:phone":"+1 310 374 6924",
    "sg:postcode":"90266",
    "sg:province":"CA",
    "sg:tags":[
        "control",
        "weight"
    ],
    "wof:name":"Ladies Workout Express",
    "wof:placetype":"venue"
},
  "geometry": {"coordinates":[-118.379778,33.88057],"type":"Point"}
}