{
  "type": "Feature",
  "properties": {
    "addr:full":"990 Villa St Mountain View CA 94041",
    "addr:housenumber":"990",
    "addr:postcode":"94041",
    "addr:street":"Villa St",
    "iso:country":"US",
    "sg:address":"990 Villa St",
    "sg:city":"Mountain View",
    "sg:classifiers":[
        {
            "category":"Professional",
            "subcategory":"Computer Services",
            "type":"Services"
        }
    ],
    "sg:phone":"+1 650 625 1130",
    "sg:postcode":"94041",
    "sg:province":"CA",
    "sg:tags":[
        "internet"
    ],
    "wof:name":"Etheric Networks",
    "wof:placetype":"venue"
},
  "geometry": {"coordinates":[-122.080125,37.394344],"type":"Point"}
}