{
  "type": "Feature",
  "properties": {
    "addr:full":"4873 Watseka Way Sacramento CA 95835",
    "addr:postcode":"4873;95835",
    "addr:street":"Watseka Way",
    "iso:country":"US",
    "sg:address":"4873 Watseka Way",
    "sg:city":"Sacramento",
    "sg:classifiers":[
        {
            "category":"Professional",
            "subcategory":"Detective & Security Services",
            "type":"Services"
        }
    ],
    "sg:phone":"+1 916 419 3761",
    "sg:postcode":"95835",
    "sg:province":"CA",
    "sg:tags":[
        "private",
        "investigator"
    ],
    "wof:name":"Pruitt Investigative Services",
    "wof:placetype":"venue"
},
  "geometry": {"coordinates":[-121.525711,38.662223],"type":"Point"}
}