{
  "type": "Feature",
  "properties": {
    "iso:country":"US",
    "sg:address":"1536 Sonoma Ave",
    "sg:city":"Sacramento",
    "sg:classifiers":[
        {
            "category":"Building & Trades",
            "subcategory":"Landscaping Services",
            "type":"Services"
        }
    ],
    "sg:phone":"+1 916 486 9875",
    "sg:postcode":"95815",
    "sg:province":"CA",
    "sg:tags":[
        "tree"
    ],
    "wof:name":"All Arbor Care",
    "wof:placetype":"venue"
},
  "geometry": {"coordinates":[-121.432453,38.623717],"type":"Point"}
}