{
  "type": "Feature",
  "properties": {
    "addr:full":"27862 Camino Capistrano Laguna Niguel CA 92677",
    "addr:housenumber":"27862",
    "addr:postcode":"92677",
    "addr:street":"Camino Capistrano",
    "iso:country":"US",
    "sg:address":"27862 Camino Capistrano",
    "sg:city":"Laguna Niguel",
    "sg:classifiers":[
        {
            "category":"Building & Trades",
            "subcategory":"Construction",
            "type":"Services"
        }
    ],
    "sg:phone":"+1 949 364 6240",
    "sg:postcode":"92677",
    "sg:province":"CA",
    "sg:tags":[
        "contractor"
    ],
    "wof:name":"Mission Viejo Glass",
    "wof:placetype":"venue"
},
  "geometry": {"coordinates":[-117.67451699999999,33.558157],"type":"Point"}
}