{
  "type": "Feature",
  "properties": {
    "iso:country":"US",
    "sg:address":"177 Van Buren St",
    "sg:city":"Monterey",
    "sg:classifiers":[
        {
            "category":"Professional",
            "subcategory":"Art Services",
            "type":"Services"
        }
    ],
    "sg:phone":"+1 831 373 1947",
    "sg:postcode":"93940",
    "sg:province":"CA",
    "sg:tags":[
        "photographer"
    ],
    "wof:name":"Batista Moon Studio",
    "wof:placetype":"venue"
},
  "geometry": {"coordinates":[-121.896261,36.603778],"type":"Point"}
}