{
  "type": "Feature",
  "properties": {
    "addr:full":"8453 Beverly Boulevard Los Angeles CA 90048",
    "addr:housenumber":"8453",
    "addr:postcode":"90048",
    "addr:street":"Beverly Boulevard",
    "iso:country":"US",
    "sg:address":"8453 Beverly Boulevard",
    "sg:city":"Los Angeles",
    "sg:classifiers":[
        {
            "category":"Food & Beverages",
            "subcategory":"Specialty",
            "type":"Retail Goods"
        }
    ],
    "sg:phone":"+1 323 651 2233",
    "sg:postcode":"90048",
    "sg:province":"CA",
    "sg:website":"ediblearrangements.com",
    "wof:name":"Edible Arrangements",
    "wof:placetype":"venue"
},
  "geometry": {"coordinates":[-118.37478299999999,34.075943],"type":"Point"}
}