{
  "type": "Feature",
  "properties": {
    "addr:full":"116 New Montgomery Street San Francisco CA 94105",
    "addr:housenumber":"116",
    "addr:postcode":"94105",
    "addr:street":"New Montgomery Street",
    "iso:country":"US",
    "sg:address":"116 New Montgomery Street",
    "sg:city":"San Francisco",
    "sg:classifiers":[
        {
            "category":"Banks & Credit Unions",
            "subcategory":"Financial Services",
            "type":"Services"
        }
    ],
    "sg:phone":"+1 415 614 4602",
    "sg:postcode":"94105",
    "sg:province":"CA",
    "sg:tags":[
        "broker",
        "mortgage"
    ],
    "wof:name":"A & B Lending",
    "wof:placetype":"venue"
},
  "geometry": {"coordinates":[-122.400002,37.787102],"type":"Point"}
}