{
  "type": "Feature",
  "properties": {
    "addr:full":"5901 W Olympic Blvd Los Angeles CA 90036",
    "addr:housenumber":"5901",
    "addr:postcode":"90036",
    "addr:street":"W Olympic Blvd",
    "iso:country":"US",
    "sg:address":"5901 W Olympic Blvd",
    "sg:city":"Los Angeles",
    "sg:classifiers":[
        {
            "category":"Building & Trades",
            "subcategory":"Construction",
            "type":"Services"
        }
    ],
    "sg:phone":"+1 323 771 6671",
    "sg:postcode":"90036",
    "sg:province":"CA",
    "sg:tags":[
        "interior",
        "design",
        "contractor"
    ],
    "wof:name":"Licensed Remodeling Contractor Kitchen - Bathroom",
    "wof:placetype":"venue"
},
  "geometry": {"coordinates":[-118.360236,34.057925],"type":"Point"}
}