{
  "type": "Feature",
  "properties": {
    "addr:full":"236 S Chester Ave Pasadena CA 91106",
    "addr:housenumber":"236",
    "addr:postcode":"91106",
    "addr:street":"S Chester Ave",
    "iso:country":"US",
    "sg:address":"236 S Chester Ave",
    "sg:city":"Pasadena",
    "sg:classifiers":[
        {
            "category":"Banks & Credit Unions",
            "subcategory":"Financial Services",
            "type":"Services"
        }
    ],
    "sg:phone":"+1 626 584 9824",
    "sg:postcode":"91106",
    "sg:province":"CA",
    "sg:tags":[
        "broker",
        "mortgage"
    ],
    "wof:name":"Rmc Funding",
    "wof:placetype":"venue"
},
  "geometry": {"coordinates":[-118.124476,34.141986],"type":"Point"}
}