{
  "type": "Feature",
  "properties": {
    "addr:full":"4737 Toomes Rd Salida CA 95358",
    "addr:housenumber":"4737",
    "addr:postcode":"95358",
    "addr:street":"Toomes Rd",
    "iso:country":"US",
    "sg:address":"4737 Toomes Rd",
    "sg:city":"Salida",
    "sg:classifiers":[
        {
            "category":"Manufacturing",
            "subcategory":"Tools & Machinery",
            "type":"Manufacturing & Wholesale Goods"
        }
    ],
    "sg:phone":"+1 209 545 1167",
    "sg:postcode":"95358",
    "sg:province":"CA",
    "sg:tags":[
        "farm",
        "equipment"
    ],
    "wof:name":"Flory Industries",
    "wof:placetype":"venue"
},
  "geometry": {"coordinates":[-121.09573899999999,37.707026],"type":"Point"}
}