{
  "type": "Feature",
  "properties": {
    "addr:full":"1641 E 17th St Santa Ana CA 92705",
    "addr:housenumber":"1641",
    "addr:postcode":"92705",
    "addr:street":"E 17Th St",
    "iso:country":"US",
    "sg:address":"1641 E 17th St",
    "sg:city":"Santa Ana",
    "sg:classifiers":[
        {
            "category":"Health Services",
            "subcategory":"Dentist",
            "type":"Services"
        }
    ],
    "sg:phone":"+1 714 542 7400",
    "sg:postcode":"92705",
    "sg:province":"CA",
    "sg:website":"www.123smiledentalcare.com",
    "wof:name":"1-2-3 Smile Dental Care",
    "wof:placetype":"venue"
},
  "geometry": {"coordinates":[-117.84492,33.760107],"type":"Point"}
}