{
  "type": "Feature",
  "properties": {
    "addr:full":"655 Park Ct Rohnert Park CA 94928",
    "addr:housenumber":"655",
    "addr:postcode":"94928",
    "addr:street":"Park Ct",
    "iso:country":"US",
    "sg:address":"655 Park Ct",
    "sg:city":"Rohnert Park",
    "sg:classifiers":[
        {
            "category":"Manufacturing",
            "subcategory":"Printing",
            "type":"Manufacturing & Wholesale Goods"
        }
    ],
    "sg:phone":"+1 707 588 8028",
    "sg:postcode":"94928",
    "sg:province":"CA",
    "sg:tags":[
        "printer"
    ],
    "sg:website":"www.printing-mailing.com",
    "wof:name":"Goode Printing & Mailing",
    "wof:placetype":"venue"
},
  "geometry": {"coordinates":[-122.72336,38.356616],"type":"Point"}
}