{
  "type": "Feature",
  "properties": {
    "addr:full":"74075 Catalina Way Palm Desert CA 92260",
    "addr:housenumber":"74075",
    "addr:postcode":"ca 92260",
    "addr:street":"Catalina Way",
    "iso:country":"US",
    "sg:address":"74075 Catalina Way",
    "sg:city":"Palm Desert",
    "sg:classifiers":[
        {
            "category":"Building & Trades",
            "subcategory":"Cleaning & Sanitation",
            "type":"Services"
        }
    ],
    "sg:phone":"+1 760 340 3048",
    "sg:postcode":"92260",
    "sg:province":"CA",
    "sg:tags":[
        "home"
    ],
    "sg:website":"www.tcleaningservice.com",
    "wof:name":"T & S Cleaning Service",
    "wof:placetype":"venue"
},
  "geometry": {"coordinates":[-116.373001,33.726299],"type":"Point"}
}