{
  "type": "Feature",
  "properties": {
    "iso:country":"US",
    "sg:address":"2940 Leonis Blvd",
    "sg:city":"Vernon",
    "sg:classifiers":[
        {
            "category":"Wholesale",
            "subcategory":"Apparel",
            "type":"Manufacturing & Wholesale Goods"
        }
    ],
    "sg:phone":"+1 323 589 5999",
    "sg:postcode":"90058",
    "sg:province":"CA",
    "sg:tags":[
        "textiles-manufacturers",
        "sportswear"
    ],
    "wof:name":"Rotax Inc.",
    "wof:placetype":"venue"
},
  "geometry": {"coordinates":[-118.21601699999999,34.000098],"type":"Point"}
}