{
  "type": "Feature",
  "properties": {
    "addr:full":"2500 Broadway St Santa Monica CA 90404",
    "addr:housenumber":"2500",
    "addr:postcode":"90404",
    "addr:street":"Broadway St",
    "iso:country":"US",
    "sg:address":"2500 Broadway St",
    "sg:city":"Santa Monica",
    "sg:classifiers":[
        {
            "category":"Real Estate",
            "subcategory":"Architect",
            "type":"Services"
        }
    ],
    "sg:phone":"+1 310 449 5600",
    "sg:postcode":"90404",
    "sg:province":"CA",
    "sg:tags":[
        "architectural",
        "business"
    ],
    "sg:website":"www.gensler.com",
    "wof:name":"Gensler and Associates",
    "wof:placetype":"venue"
},
  "geometry": {"coordinates":[-118.473136,34.031622],"type":"Point"}
}