{
  "type": "Feature",
  "properties": {
    "iso:country":"US",
    "sg:address":"2661 Yard St",
    "sg:city":"Oroville",
    "sg:classifiers":[
        {
            "category":"Place Of Worship",
            "subcategory":"Church",
            "type":"Public Place"
        },
        {
            "category":"Place Of Worship",
            "type":"Public Place"
        }
    ],
    "sg:phone":"+1 530 533 6197",
    "sg:postcode":"95966",
    "sg:province":"CA",
    "sg:tags":[
        "churches-baptist-general",
        "churches-baptist"
    ],
    "sg:website":"http://www.abc-usa.org",
    "wof:name":"First Baptist Church",
    "wof:placetype":"venue"
},
  "geometry": {"coordinates":[-121.547451,39.51321],"type":"Point"}
}