{
  "type": "Feature",
  "properties": {
    "addr:full":"2089 Avy Ave Menlo Park CA 94025",
    "addr:housenumber":"2089",
    "addr:postcode":"94025",
    "addr:street":"Avy Ave",
    "iso:country":"US",
    "sg:address":"2089 Avy Ave",
    "sg:city":"Menlo Park",
    "sg:classifiers":[
        {
            "category":"Communications",
            "subcategory":"Film & Video Production",
            "type":"Services"
        }
    ],
    "sg:phone":"+1 650 854 7799",
    "sg:postcode":"94025",
    "sg:province":"CA",
    "sg:tags":[
        "duplication",
        "tape"
    ],
    "wof:name":"Copymasters",
    "wof:placetype":"venue"
},
  "geometry": {"coordinates":[-122.20106800000001,37.432267],"type":"Point"}
}