{
  "type": "Feature",
  "properties": {
    "addr:full":"1410 Bonair Rd Vista CA 92084",
    "addr:housenumber":"1410",
    "addr:postcode":"92084",
    "addr:street":"Bonair Rd",
    "iso:country":"US",
    "sg:address":"1410 Bonair Rd",
    "sg:city":"Vista",
    "sg:classifiers":[
        {
            "category":"Real Estate",
            "subcategory":"Real Estate Operator",
            "type":"Services"
        }
    ],
    "sg:phone":"+1 760 726 9633",
    "sg:postcode":"92084",
    "sg:province":"CA",
    "sg:tags":[
        "apartment"
    ],
    "wof:name":"Rancho Villas",
    "wof:placetype":"venue"
},
  "geometry": {"coordinates":[-117.219725,33.218015],"type":"Point"}
}