{
  "type": "Feature",
  "properties": {
    "iso:country":"US",
    "sg:address":"8342 Garden Grove Blvd",
    "sg:city":"Garden Grove",
    "sg:classifiers":[
        {
            "category":"Wholesale",
            "subcategory":"Non-durable Goods",
            "type":"Manufacturing & Wholesale Goods"
        }
    ],
    "sg:phone":"+1 714 638 8922",
    "sg:postcode":"92844",
    "sg:province":"CA",
    "wof:name":"Gog Trading Inc",
    "wof:placetype":"venue"
},
  "geometry": {"coordinates":[-117.98661300000001,33.773755],"type":"Point"}
}