{
  "type": "Feature",
  "properties": {
    "addr:full":"2048 Hurst Rd Eureka CA 95503",
    "addr:housenumber":"2048",
    "addr:postcode":"95503",
    "addr:street":"Hurst Rd",
    "iso:country":"US",
    "sg:address":"2048 Hurst Rd",
    "sg:city":"Eureka",
    "sg:classifiers":[
        {
            "category":"Building & Trades",
            "subcategory":"Pest Control",
            "type":"Services"
        }
    ],
    "sg:phone":"+1 707 442 2071",
    "sg:postcode":"95503",
    "sg:province":"CA",
    "wof:name":"Home Network Pest Control",
    "wof:placetype":"venue"
},
  "geometry": {"coordinates":[-124.14635199999999,40.747731],"type":"Point"}
}