{
  "type": "Feature",
  "properties": {
    "iso:country":"US",
    "sg:address":"552 Abrego St",
    "sg:city":"Monterey",
    "sg:classifiers":[
        {
            "category":"Professional",
            "subcategory":"Lawyer & Legal Services",
            "type":"Services"
        }
    ],
    "sg:phone":"+1 831 655 3114",
    "sg:postcode":"93940",
    "sg:province":"CA",
    "wof:name":"One Legal Inc",
    "wof:placetype":"venue"
},
  "geometry": {"coordinates":[-121.892421,36.596829],"type":"Point"}
}