{
  "type": "Feature",
  "properties": {
    "iso:country":"US",
    "sg:address":"3014 W Lincoln Ave",
    "sg:city":"Anaheim",
    "sg:classifiers":[
        {
            "category":"Food & Beverages",
            "subcategory":"Specialty",
            "type":"Retail Goods"
        },
        {
            "category":"Food & Beverages",
            "subcategory":"Bakery",
            "type":"Retail Goods"
        }
    ],
    "sg:phone":"+1 866 981 0971",
    "sg:postcode":"92804",
    "sg:province":"CA",
    "sg:tags":[
        "sandwich"
    ],
    "wof:name":"Zeros Subs",
    "wof:placetype":"venue"
},
  "geometry": {"coordinates":[-117.994153,33.831965],"type":"Point"}
}