{
  "type": "Feature",
  "properties": {
    "addr:full":"3620 E Shallow Brook Ln Orange CA 92867",
    "addr:housenumber":"3620",
    "addr:postcode":"92867",
    "addr:street":"E Shallow Brook Ln",
    "iso:country":"US",
    "sg:address":"3620 E Shallow Brook Ln",
    "sg:city":"Orange",
    "sg:classifiers":[
        {
            "category":"Building & Trades",
            "subcategory":"Cleaning & Sanitation",
            "type":"Services"
        }
    ],
    "sg:phone":"+1 714 998 2250",
    "sg:postcode":"92867",
    "sg:province":"CA",
    "sg:tags":[
        "carpet"
    ],
    "sg:website":"www.fab-pro.com",
    "wof:name":"Fab -Pro",
    "wof:placetype":"venue"
},
  "geometry": {"coordinates":[-117.815274,33.830271],"type":"Point"}
}