{
  "type": "Feature",
  "properties": {
    "iso:country":"US",
    "sg:address":"7028 Greenleaf Ave",
    "sg:city":"Whittier",
    "sg:classifiers":[
        {
            "category":"Shopping",
            "subcategory":"Gifts & Souvenirs",
            "type":"Retail Goods"
        }
    ],
    "sg:phone":"+1 562 464 5254",
    "sg:postcode":"90602",
    "sg:province":"CA",
    "sg:tags":[
        "shop"
    ],
    "wof:name":"Prissy Themes Boutique",
    "wof:placetype":"venue"
},
  "geometry": {"coordinates":[-118.037246,33.977521],"type":"Point"}
}