{
  "type": "Feature",
  "properties": {
    "iso:country":"US",
    "sg:address":"1861 Knoll Dr",
    "sg:city":"Ventura",
    "sg:classifiers":[
        {
            "category":"Professional",
            "subcategory":"Research",
            "type":"Services"
        }
    ],
    "sg:phone":"+1 805 644 2220",
    "sg:postcode":"93003",
    "sg:province":"CA",
    "sg:tags":[
        "environmental",
        "ecological"
    ],
    "sg:website":"www.padreinc.com",
    "wof:name":"Padre Associates Inc",
    "wof:placetype":"venue"
},
  "geometry": {"coordinates":[-119.220226,34.255957],"type":"Point"}
}