{
  "type": "Feature",
  "properties": {
    "iso:country":"US",
    "sg:address":"1775 Union St",
    "sg:city":"San Francisco",
    "sg:classifiers":[
        {
            "category":"Home & Garden",
            "subcategory":"Furniture",
            "type":"Retail Goods"
        }
    ],
    "sg:phone":"+1 415 922 9544",
    "sg:postcode":"94123",
    "sg:province":"CA",
    "wof:name":"Decor Furnishings",
    "wof:placetype":"venue"
},
  "geometry": {"coordinates":[-122.42792,37.798009],"type":"Point"}
}