{
  "type": "Feature",
  "properties": {
    "addr:full":"7104 Perry Rd Bell Gardens CA 90201",
    "addr:housenumber":"7104",
    "addr:postcode":"90201",
    "addr:street":"Perry Rd;Gardens",
    "iso:country":"US",
    "sg:address":"7104 Perry Rd",
    "sg:city":"Bell Gardens",
    "sg:classifiers":[
        {
            "category":"Organizations",
            "subcategory":"Community Association",
            "type":"Services"
        }
    ],
    "sg:phone":"+1 562 927 2677",
    "sg:postcode":"90201",
    "sg:province":"CA",
    "sg:tags":[
        "club"
    ],
    "wof:name":"Rio Hondo Boys & Girls Club",
    "wof:placetype":"venue"
},
  "geometry": {"coordinates":[-118.146725,33.968669],"type":"Point"}
}