{
  "type": "Feature",
  "properties": {
    "iso:country":"US",
    "sg:address":"32162 Corte Gardano",
    "sg:city":"Temecula",
    "sg:classifiers":[
        {
            "category":"Building & Trades",
            "subcategory":"Construction",
            "type":"Services"
        }
    ],
    "sg:phone":"+1 951 506 5662",
    "sg:postcode":"92592",
    "sg:province":"CA",
    "sg:tags":[
        "contractor"
    ],
    "wof:name":"Coppess Construction",
    "wof:placetype":"venue"
},
  "geometry": {"coordinates":[-117.096832,33.500002],"type":"Point"}
}