{
  "type": "Feature",
  "properties": {
    "addr:full":"465 34th St Oakland CA 94609",
    "addr:housenumber":"465",
    "addr:postcode":"94609",
    "addr:street":"34Th St",
    "iso:country":"US",
    "sg:address":"465 34th St",
    "sg:city":"Oakland",
    "sg:classifiers":[
        {
            "category":"Social Services",
            "type":"Services"
        }
    ],
    "sg:phone":"+1 510 658 1966",
    "sg:postcode":"94609",
    "sg:province":"CA",
    "sg:tags":[
        "worker"
    ],
    "wof:name":"Joy L Johnson",
    "wof:placetype":"venue"
},
  "geometry": {"coordinates":[-122.262134,37.822022],"type":"Point"}
}