{
  "type": "Feature",
  "properties": {
    "iso:country":"US",
    "sg:address":"20832 Roscoe Blvd",
    "sg:city":"Winnetka",
    "sg:classifiers":[
        {
            "category":"Real Estate",
            "subcategory":"Real Estate Services",
            "type":"Services"
        },
        {
            "category":"Real Estate",
            "subcategory":"Real Estate Agent",
            "type":"Services"
        }
    ],
    "sg:phone":"+1 818 721 0190",
    "sg:postcode":"91306",
    "sg:province":"CA",
    "sg:tags":[
        "buyer",
        "management",
        "broker"
    ],
    "wof:name":"America Estate Properties",
    "wof:placetype":"venue"
},
  "geometry": {"coordinates":[-118.587631,34.219971],"type":"Point"}
}