{
  "type": "Feature",
  "properties": {
    "iso:country":"US",
    "sg:address":"1118 Grant Ave #103",
    "sg:city":"San Francisco",
    "sg:classifiers":[
        {
            "category":"Travel",
            "subcategory":"Travel Agent",
            "type":"Entertainment"
        }
    ],
    "sg:phone":"+1 415 989 7733",
    "sg:postcode":"94133",
    "sg:province":"CA",
    "wof:name":"Windy's Travel Agency",
    "wof:placetype":"venue"
},
  "geometry": {"coordinates":[-122.406705,37.797159],"type":"Point"}
}