{
  "type": "Feature",
  "properties": {
    "addr:full":"1087 E Willow St Manteca CA 95337",
    "addr:housenumber":"1087",
    "addr:postcode":"95337",
    "addr:street":"E Willow St",
    "iso:country":"US",
    "sg:address":"1087 E Willow St",
    "sg:city":"Manteca",
    "sg:classifiers":[
        {
            "category":"Building & Trades",
            "subcategory":"Construction",
            "type":"Services"
        }
    ],
    "sg:phone":"+1 209 825 8787",
    "sg:postcode":"95337",
    "sg:province":"CA",
    "sg:tags":[
        "paving",
        "contractor"
    ],
    "wof:name":"D Willson Construction Co",
    "wof:placetype":"venue"
},
  "geometry": {"coordinates":[-121.297624,37.773736],"type":"Point"}
}