{
  "type": "Feature",
  "properties": {
    "addr:full":"233 Mark Twain Ct Santa Clara CA 95050",
    "addr:housenumber":"233",
    "addr:postcode":"95050",
    "addr:street":"Mark Twain Ct",
    "iso:country":"US",
    "sg:address":"233 Mark Twain Ct",
    "sg:city":"Santa Clara",
    "sg:classifiers":[
        {
            "category":"Professional",
            "subcategory":"Computer Services",
            "type":"Services"
        }
    ],
    "sg:phone":"+1 408 985 5397",
    "sg:postcode":"95050",
    "sg:province":"CA",
    "sg:tags":[
        "consultant",
        "designer"
    ],
    "wof:name":"Intel Corp",
    "wof:placetype":"venue"
},
  "geometry": {"coordinates":[-121.958123,37.329091],"type":"Point"}
}