{
  "type": "Feature",
  "properties": {
    "addr:full":"1941 Lundy Ave San Jose CA 95131",
    "addr:housenumber":"1941",
    "addr:postcode":"95131",
    "addr:street":"Lundy Ave",
    "iso:country":"US",
    "sg:address":"1941 Lundy Ave",
    "sg:city":"San Jose",
    "sg:classifiers":[
        {
            "category":"Wholesale",
            "subcategory":"Machinery & Supplies",
            "type":"Manufacturing & Wholesale Goods"
        }
    ],
    "sg:phone":"+1 408 435 1905",
    "sg:postcode":"95131",
    "sg:province":"CA",
    "sg:tags":[
        "printer",
        "cartridge"
    ],
    "wof:name":"Primesource Corp",
    "wof:placetype":"venue"
},
  "geometry": {"coordinates":[-121.890252,37.392218],"type":"Point"}
}