{
  "type": "Feature",
  "properties": {
    "addr:full":"25341 Campina Dr Mission Viejo CA 92691",
    "addr:postcode":"25341;92691",
    "addr:street":"Campina Dr",
    "iso:country":"US",
    "sg:address":"25341 Campina Dr",
    "sg:city":"Mission Viejo",
    "sg:classifiers":[
        {
            "category":"Professional",
            "subcategory":"Business Services",
            "type":"Services"
        }
    ],
    "sg:phone":"+1 949 770 5429",
    "sg:postcode":"92691",
    "sg:province":"CA",
    "sg:tags":[
        "operator",
        "local",
        "trucking"
    ],
    "wof:name":"Acme Courier Service Inc",
    "wof:placetype":"venue"
},
  "geometry": {"coordinates":[-117.661717,33.594423],"type":"Point"}
}