{
  "type": "Feature",
  "properties": {
    "addr:full":"1300 E Truxtun Ave Bakersfield CA 93305",
    "addr:housenumber":"1300",
    "addr:postcode":"93305",
    "addr:street":"E Truxtun Ave",
    "iso:country":"US",
    "sg:address":"1300 E Truxtun Ave",
    "sg:city":"Bakersfield",
    "sg:classifiers":[
        {
            "category":"Restaurant",
            "type":"Food & Drink"
        }
    ],
    "sg:phone":"+1 661 322 1146",
    "sg:postcode":"93305",
    "sg:province":"CA",
    "sg:tags":[
        "out"
    ],
    "wof:name":"Super Taco",
    "wof:placetype":"venue"
},
  "geometry": {"coordinates":[-118.98251500000001,35.373224],"type":"Point"}
}