{
  "type": "Feature",
  "properties": {
    "iso:country":"US",
    "sg:address":"4246 S Victoria Ave",
    "sg:city":"Los Angeles",
    "sg:classifiers":[
        {
            "category":"Social Services",
            "subcategory":"Child Care",
            "type":"Services"
        }
    ],
    "sg:phone":"+1 323 292 5273",
    "sg:postcode":"90008",
    "sg:province":"CA",
    "wof:name":"Mathis Family Day Care",
    "wof:placetype":"venue"
},
  "geometry": {"coordinates":[-118.335949,34.007179],"type":"Point"}
}