{
  "type": "Feature",
  "properties": {
    "iso:country":"US",
    "sg:address":"1559B Sloat Blvd. Ste 487",
    "sg:city":"San Francisco",
    "sg:classifiers":[
        {
            "category":"Professional",
            "subcategory":"Accounting & Tax Preparation",
            "type":"Services"
        }
    ],
    "sg:phone":"+1 800 730 0596",
    "sg:postcode":"94132",
    "sg:province":"CA",
    "sg:tags":[
        "accountant"
    ],
    "sg:website":"www.simkeina.com",
    "wof:name":"Kei Accounting & Management Services",
    "wof:placetype":"venue"
},
  "geometry": {"coordinates":[-122.48886299999999,37.734023],"type":"Point"}
}