{
  "type": "Feature",
  "properties": {
    "addr:full":"200 N Imperial Ave El Centro CA 92243",
    "addr:housenumber":"200",
    "addr:postcode":"92243",
    "addr:street":"N Imperial Ave",
    "iso:country":"US",
    "sg:address":"200 N Imperial Ave",
    "sg:city":"El Centro",
    "sg:classifiers":[
        {
            "category":"Shopping",
            "type":"Retail Goods"
        }
    ],
    "sg:phone":"+1 760 339 4900",
    "sg:postcode":"92243",
    "sg:province":"CA",
    "sg:tags":[
        "telephone",
        "cellular"
    ],
    "wof:name":"Cellular Unlimited",
    "wof:placetype":"venue"
},
  "geometry": {"coordinates":[-115.56989799999999,32.793324],"type":"Point"}
}