{
  "type": "Feature",
  "properties": {
    "addr:full":"2214B W Magnolia Blvd Burbank CA 91506",
    "addr:housenumber":"2214b",
    "addr:postcode":"91506",
    "addr:street":"W Magnolia Blvd",
    "iso:country":"US",
    "sg:address":"2214B W Magnolia Blvd",
    "sg:city":"Burbank",
    "sg:classifiers":[
        {
            "category":"Home & Garden",
            "subcategory":"Furniture",
            "type":"Retail Goods"
        }
    ],
    "sg:phone":"+1 818 720 5720",
    "sg:postcode":"91506",
    "sg:province":"CA",
    "sg:tags":[
        "store"
    ],
    "wof:name":"Gallery H Custom Furniture & Woodwork",
    "wof:placetype":"venue"
},
  "geometry": {"coordinates":[-118.33224199999999,34.17276],"type":"Point"}
}