{
  "type": "Feature",
  "properties": {
    "iso:country":"US",
    "sg:address":"13972 Doolittle Dr",
    "sg:city":"San Leandro",
    "sg:classifiers":[
        {
            "category":"Insurance",
            "subcategory":"Insurance Agent",
            "type":"Services"
        }
    ],
    "sg:phone":"+1 510 614 0288",
    "sg:postcode":"94577",
    "sg:province":"CA",
    "wof:name":"Delu Insurance",
    "wof:placetype":"venue"
},
  "geometry": {"coordinates":[-122.175487,37.698113],"type":"Point"}
}