{
  "type": "Feature",
  "properties": {
    "addr:full":"3110 Commerce Way Turlock CA 95380",
    "addr:housenumber":"3110",
    "addr:postcode":"95380",
    "addr:street":"Commerce Way",
    "iso:country":"US",
    "sg:address":"3110 Commerce Way",
    "sg:city":"Turlock",
    "sg:classifiers":[
        {
            "category":"Wholesale",
            "subcategory":"Machinery & Supplies",
            "type":"Manufacturing & Wholesale Goods"
        }
    ],
    "sg:phone":"+1 209 668 9050",
    "sg:postcode":"95380",
    "sg:province":"CA",
    "wof:name":"Nelson-Jameson Inc",
    "wof:placetype":"venue"
},
  "geometry": {"coordinates":[-120.883236,37.486295],"type":"Point"}
}