{
  "type": "Feature",
  "properties": {
    "addr:full":"12365 Lewis St Ste 101 Garden Grove CA 92840",
    "addr:housenumber":"12365",
    "addr:postcode":"92840",
    "addr:street":"Lewis St Ste 101",
    "iso:country":"US",
    "sg:address":"12365 Lewis St Ste 101",
    "sg:city":"Garden Grove",
    "sg:classifiers":[
        {
            "category":"Professional",
            "subcategory":"Accounting & Tax Preparation",
            "type":"Services"
        }
    ],
    "sg:phone":"+1 714 750 3303",
    "sg:postcode":"92840",
    "sg:province":"CA",
    "sg:tags":[
        "accountant"
    ],
    "wof:name":"Kinsel William K & Accountancy Corp",
    "wof:placetype":"venue"
},
  "geometry": {"coordinates":[-117.898003,33.784401],"type":"Point"}
}