{
  "type": "Feature",
  "properties": {
    "iso:country":"US",
    "sg:address":"146 W Gardena Blvd",
    "sg:city":"Gardena",
    "sg:classifiers":[
        {
            "category":"Building & Trades",
            "subcategory":"Construction",
            "type":"Services"
        }
    ],
    "sg:phone":"+1 310 768 2744",
    "sg:postcode":"90248",
    "sg:province":"CA",
    "sg:tags":[
        "contractor"
    ],
    "wof:name":"Andy Howard General Contractor",
    "wof:placetype":"venue"
},
  "geometry": {"coordinates":[-118.277715,33.881894],"type":"Point"}
}