{
  "type": "Feature",
  "properties": {
    "iso:country":"US",
    "sg:address":"947 Brookwood Ave",
    "sg:city":"Vallejo",
    "sg:classifiers":[
        {
            "category":"Wholesale",
            "subcategory":"Hardware",
            "type":"Manufacturing & Wholesale Goods"
        }
    ],
    "sg:phone":"+1 707 644 6721",
    "sg:postcode":"94591",
    "sg:province":"CA",
    "sg:tags":[
        "prevention",
        "flow",
        "back",
        "devices"
    ],
    "wof:name":"Best Choice USA",
    "wof:placetype":"venue"
},
  "geometry": {"coordinates":[-122.210767,38.103843],"type":"Point"}
}