{
  "type": "Feature",
  "properties": {
    "addr:full":"19173 New York Flat Rd Forbestown CA 95930",
    "addr:housenumber":"19173",
    "addr:postcode":"95930",
    "addr:street":"New;Flat Rd",
    "iso:country":"US",
    "sg:address":"19173 New York Flat Rd",
    "sg:city":"Forbestown",
    "sg:classifiers":[
        {
            "category":"Government",
            "subcategory":"Post Office",
            "type":"Public Place"
        }
    ],
    "sg:phone":"+1 530 675 2664",
    "sg:postcode":"95930",
    "sg:province":"CA",
    "wof:name":"US Post Office",
    "wof:placetype":"venue"
},
  "geometry": {"coordinates":[-121.275687,39.518738],"type":"Point"}
}