{
  "type": "Feature",
  "properties": {
    "iso:country":"US",
    "sg:address":"870 Santa Dorotea Cir",
    "sg:city":"Rohnert Park",
    "sg:classifiers":[
        {
            "category":"Retail",
            "subcategory":"Laundry & Dry Cleaning",
            "type":"Services"
        }
    ],
    "sg:phone":"+1 707 795 8306",
    "sg:postcode":"94928",
    "sg:province":"CA",
    "sg:tags":[
        "cleaners",
        "rug",
        "carpet"
    ],
    "wof:name":"Chem-Dry",
    "wof:placetype":"venue"
},
  "geometry": {"coordinates":[-122.700677,38.355669],"type":"Point"}
}