{
  "type": "Feature",
  "properties": {
    "addr:full":"9600 Bolsa Avenue Westminster CA 92683",
    "addr:housenumber":"9600",
    "addr:postcode":"92683",
    "addr:street":"Bolsa Avenue",
    "iso:country":"US",
    "sg:address":"9600 Bolsa Avenue",
    "sg:city":"Westminster",
    "sg:classifiers":[
        {
            "category":"Shopping",
            "subcategory":"Clothing, Apparel, & Fashions",
            "type":"Retail Goods"
        }
    ],
    "sg:phone":"+1 714 775 2769",
    "sg:postcode":"92683",
    "sg:province":"CA",
    "sg:tags":[
        "accessory",
        "clothing",
        "women's"
    ],
    "wof:name":"Mindy",
    "wof:placetype":"venue"
},
  "geometry": {"coordinates":[-117.96237000000001,33.744884],"type":"Point"}
}