{
  "type": "Feature",
  "properties": {
    "addr:full":"12000 Berryessa Road San Jose CA 95101",
    "addr:housenumber":"12000",
    "addr:postcode":"95101",
    "addr:street":"Berryessa Road",
    "iso:country":"US",
    "sg:address":"12000 Berryessa Road",
    "sg:city":"San Jose",
    "sg:classifiers":[
        {
            "category":"Wholesale",
            "subcategory":"Fruits & Vegetables",
            "type":"Manufacturing & Wholesale Goods"
        }
    ],
    "sg:phone":"+1 408 452 5768",
    "sg:postcode":"95101",
    "sg:province":"CA",
    "sg:tags":[
        "veggie"
    ],
    "wof:name":"El Dreco",
    "wof:placetype":"venue"
},
  "geometry": {"coordinates":[-121.88705,37.388254],"type":"Point"}
}