{
  "type": "Feature",
  "properties": {
    "addr:full":"404 Nebraska St Vallejo CA 94590",
    "addr:housenumber":"404",
    "addr:postcode":"94590",
    "addr:street":"Nebraska St",
    "iso:country":"US",
    "sg:address":"404 Nebraska St",
    "sg:city":"Vallejo",
    "sg:classifiers":[
        {
            "category":"Organizations",
            "subcategory":"Labor Organization",
            "type":"Services"
        }
    ],
    "sg:phone":"+1 707 644 8423",
    "sg:postcode":"94590",
    "sg:province":"CA",
    "wof:name":"Plasterers & Cement Masons",
    "wof:placetype":"venue"
},
  "geometry": {"coordinates":[-122.25392100000001,38.113987],"type":"Point"}
}