{
  "type": "Feature",
  "properties": {
    "addr:full":"7417 el Manor Ave Los Angeles CA 90045",
    "addr:housenumber":"7417",
    "addr:postcode":"90045",
    "addr:street":"El Manor Ave",
    "iso:country":"US",
    "sg:address":"7417 el Manor Ave",
    "sg:city":"Los Angeles",
    "sg:classifiers":[
        {
            "category":"Home & Garden",
            "subcategory":"Home Furnishings",
            "type":"Retail Goods"
        }
    ],
    "sg:phone":"+1 310 645 0521",
    "sg:postcode":"90045",
    "sg:province":"CA",
    "sg:tags":[
        "curtain",
        "made",
        "drapery"
    ],
    "wof:name":"LA Tijera Draperies",
    "wof:placetype":"venue"
},
  "geometry": {"coordinates":[-118.399079,33.974725],"type":"Point"}
}