{
  "type": "Feature",
  "properties": {
    "iso:country":"US",
    "sg:address":"2112 Calavera Cir",
    "sg:city":"Tustin",
    "sg:classifiers":[
        {
            "category":"Real Estate",
            "subcategory":"Real Estate Agent",
            "type":"Services"
        }
    ],
    "sg:phone":"+1 714 832 9283",
    "sg:postcode":"92782",
    "sg:province":"CA",
    "wof:name":"Midtown Realty & Investment Co",
    "wof:placetype":"venue"
},
  "geometry": {"coordinates":[-117.800221,33.73521],"type":"Point"}
}