{
  "type": "Feature",
  "properties": {
    "addr:full":"9320 Manteca Ave Hesperia CA 92345",
    "addr:postcode":"9320;92345",
    "addr:street":"Manteca Ave",
    "iso:country":"US",
    "sg:address":"9320 Manteca Ave",
    "sg:city":"Hesperia",
    "sg:classifiers":[
        {
            "category":"Retail",
            "subcategory":"Auto Repair",
            "type":"Services"
        }
    ],
    "sg:phone":"+1 760 910 1144",
    "sg:postcode":"92345",
    "sg:province":"CA",
    "sg:tags":[
        "repairing",
        "automobile"
    ],
    "wof:name":"Superior Fleet Svc",
    "wof:placetype":"venue"
},
  "geometry": {"coordinates":[-117.25393800000001,34.419126],"type":"Point"}
}