{
  "type": "Feature",
  "properties": {
    "addr:full":"1 Sand Oaks Rd Laguna Niguel CA 92677",
    "addr:housenumber":"1",
    "addr:postcode":"92677",
    "addr:street":"Sand Oaks Rd",
    "iso:country":"US",
    "sg:address":"1 Sand Oaks Rd",
    "sg:city":"Laguna Niguel",
    "sg:classifiers":[
        {
            "category":"Building & Trades",
            "subcategory":"Electrical",
            "type":"Services"
        }
    ],
    "sg:phone":"+1 949 495 7003",
    "sg:postcode":"92677",
    "sg:province":"CA",
    "sg:tags":[
        "electrical",
        "contractor"
    ],
    "wof:name":"Harman Electric",
    "wof:placetype":"venue"
},
  "geometry": {"coordinates":[-117.690558,33.516633],"type":"Point"}
}