{
  "type": "Feature",
  "properties": {
    "addr:full":"500 S Winchester Blvd San Jose CA 95128",
    "addr:housenumber":"500",
    "addr:postcode":"95128",
    "addr:street":"S Winchester Blvd",
    "iso:country":"US",
    "sg:address":"500 S Winchester Blvd",
    "sg:city":"San Jose",
    "sg:classifiers":[
        {
            "category":"Health Services",
            "subcategory":"Doctor",
            "type":"Services"
        }
    ],
    "sg:phone":"+1 408 247 4900",
    "sg:postcode":"95128",
    "sg:province":"CA",
    "sg:tags":[
        "physician",
        "surgeon"
    ],
    "wof:name":"Soar",
    "wof:placetype":"venue"
},
  "geometry": {"coordinates":[-121.95005399999999,37.318565],"type":"Point"}
}