{
  "type": "Feature",
  "properties": {
    "addr:full":"7912 Deer Creek Dr Sacramento CA 95823",
    "addr:housenumber":"7912",
    "addr:postcode":"95823",
    "addr:street":"Deer Creek Dr",
    "iso:country":"US",
    "sg:address":"7912 Deer Creek Dr",
    "sg:city":"Sacramento",
    "sg:classifiers":[
        {
            "category":"Building & Trades",
            "subcategory":"Electrical",
            "type":"Services"
        }
    ],
    "sg:phone":"+1 916 395 4296",
    "sg:postcode":"95823",
    "sg:province":"CA",
    "sg:tags":[
        "electrician"
    ],
    "wof:name":"Tellez Electrician",
    "wof:placetype":"venue"
},
  "geometry": {"coordinates":[-121.452448,38.472204],"type":"Point"}
}