{
  "type": "Feature",
  "properties": {
    "addr:full":"555 E Tachevah Dr Palm Springs CA 92262",
    "addr:housenumber":"555",
    "addr:postcode":"92262",
    "addr:street":"E Tachevah Dr",
    "iso:country":"US",
    "sg:address":"555 E Tachevah Dr",
    "sg:city":"Palm Springs",
    "sg:classifiers":[
        {
            "category":"Health Services",
            "subcategory":"Doctor",
            "type":"Services"
        }
    ],
    "sg:phone":"+1 760 323 9309",
    "sg:postcode":"92262",
    "sg:province":"CA",
    "wof:name":"GARZA EDURADO MD",
    "wof:placetype":"venue"
},
  "geometry": {"coordinates":[-116.541775,33.837482],"type":"Point"}
}