{
  "type": "Feature",
  "properties": {
    "iso:country":"US",
    "sg:address":"44601 Valley Central Way",
    "sg:city":"Lancaster",
    "sg:classifiers":[
        {
            "category":"Building & Trades",
            "subcategory":"Construction",
            "type":"Services"
        }
    ],
    "sg:phone":"+1 661 940 4339",
    "sg:postcode":"93536",
    "sg:province":"CA",
    "sg:tags":[
        "general",
        "contractor"
    ],
    "wof:name":"Big D Construction",
    "wof:placetype":"venue"
},
  "geometry": {"coordinates":[-118.172328,34.691866],"type":"Point"}
}