{
  "type": "Feature",
  "properties": {
    "iso:country":"US",
    "sg:address":"100 Park Pl",
    "sg:city":"San Ramon",
    "sg:classifiers":[
        {
            "category":"Wholesale",
            "subcategory":"Chemicals & Plastics",
            "type":"Manufacturing & Wholesale Goods"
        },
        {
            "category":"Manufacturing",
            "subcategory":"Rubber & Plastics",
            "type":"Manufacturing & Wholesale Goods"
        }
    ],
    "sg:phone":"+1 925 838 5541",
    "sg:postcode":"94583",
    "sg:province":"CA",
    "sg:tags":[
        "product",
        "mfg"
    ],
    "sg:website":"www.mytronics.com",
    "wof:name":"Mytronics",
    "wof:placetype":"venue"
},
  "geometry": {"coordinates":[-121.988382,37.772898],"type":"Point"}
}