{
  "type": "Feature",
  "properties": {
    "addr:full":"255 Kansas St Ste 302 San Francisco CA 94103",
    "addr:postcode":"94103",
    "addr:street":"255 Kansas St Ste 302",
    "iso:country":"US",
    "sg:address":"255 Kansas St Ste 302",
    "sg:city":"San Francisco",
    "sg:classifiers":[
        {
            "category":"Home & Garden",
            "subcategory":"Building Materials",
            "type":"Retail Goods"
        }
    ],
    "sg:phone":"+1 415 626 5262",
    "sg:postcode":"94103",
    "sg:province":"CA",
    "sg:tags":[
        "equipment",
        "fixture",
        "lighting"
    ],
    "sg:website":"www.store.shinelabs.com",
    "wof:name":"Shine Labs",
    "wof:placetype":"venue"
},
  "geometry": {"coordinates":[-122.403599,37.766507],"type":"Point"}
}