{
  "type": "Feature",
  "properties": {
    "addr:full":"1000 E Santa Ana Blvd Santa Ana CA 92701",
    "addr:housenumber":"1000",
    "addr:postcode":"92701",
    "addr:street":"E Santa Ana Blvd",
    "iso:country":"US",
    "sg:address":"1000 E Santa Ana Blvd",
    "sg:city":"Santa Ana",
    "sg:classifiers":[
        {
            "category":"Shopping",
            "subcategory":"Gifts & Souvenirs",
            "type":"Retail Goods"
        }
    ],
    "sg:phone":"+1 714 547 5574",
    "sg:postcode":"92701",
    "sg:province":"CA",
    "sg:tags":[
        "shop"
    ],
    "wof:name":"K Lee Gifts",
    "wof:placetype":"venue"
},
  "geometry": {"coordinates":[-117.85609599999999,33.753182],"type":"Point"}
}