{
  "type": "Feature",
  "properties": {
    "addr:full":"472 Canyon Crest Dr Simi Valley CA 93065",
    "addr:housenumber":"472",
    "addr:postcode":"93065",
    "addr:street":"Canyon Crest Dr",
    "iso:country":"US",
    "sg:address":"472 Canyon Crest Dr",
    "sg:city":"Simi Valley",
    "sg:classifiers":[
        {
            "category":"Insurance",
            "subcategory":"Insurance Agent",
            "type":"Services"
        }
    ],
    "sg:phone":"+1 805 583 1313",
    "sg:postcode":"93065",
    "sg:province":"CA",
    "wof:name":"Diprima Insurance Specialists",
    "wof:placetype":"venue"
},
  "geometry": {"coordinates":[-118.7975,34.23435],"type":"Point"}
}