{
  "type": "Feature",
  "properties": {
    "addr:full":"768 Brannan St San Francisco CA 94107",
    "addr:housenumber":"768",
    "addr:postcode":"94107",
    "addr:street":"Brannan St",
    "iso:country":"US",
    "sg:address":"768 Brannan St",
    "sg:city":"San Francisco",
    "sg:classifiers":[
        {
            "category":"Building & Trades",
            "subcategory":"Construction",
            "type":"Services"
        }
    ],
    "sg:phone":"+1 415 865 0510",
    "sg:postcode":"94107",
    "sg:province":"CA",
    "sg:tags":[
        "repairing",
        "remodeling",
        "contractor"
    ],
    "wof:name":"Pacific Coast Restoration",
    "wof:placetype":"venue"
},
  "geometry": {"coordinates":[-122.40261700000001,37.773632],"type":"Point"}
}