{
  "type": "Feature",
  "properties": {
    "iso:country":"US",
    "sg:address":"8824 Sepulveda Blvd.",
    "sg:city":"Los Angeles",
    "sg:classifiers":[
        {
            "category":"Food & Beverages",
            "subcategory":"Groceries & Convenience Stores",
            "type":"Retail Goods"
        }
    ],
    "sg:phone":"+1 310 645 2035",
    "sg:postcode":"90045",
    "sg:province":"CA",
    "sg:website":"services.ralphs.com/mapquest/sto...",
    "wof:name":"Ralphs Grocery Company",
    "wof:placetype":"venue"
},
  "geometry": {"coordinates":[-118.396201,33.956357],"type":"Point"}
}