{
  "type": "Feature",
  "properties": {
    "iso:country":"US",
    "sg:address":"2525 Bell Rd",
    "sg:city":"Auburn",
    "sg:classifiers":[
        {
            "category":"Personal",
            "subcategory":"Beauty Salon",
            "type":"Services"
        }
    ],
    "sg:phone":"+1 530 889 1142",
    "sg:postcode":"95603",
    "sg:province":"CA",
    "wof:name":"Magic Nails",
    "wof:placetype":"venue"
},
  "geometry": {"coordinates":[-121.097916,38.941925],"type":"Point"}
}