{
  "type": "Feature",
  "properties": {
    "addr:full":"6907 Melrose Ave Los Angeles CA 90038",
    "addr:housenumber":"6907",
    "addr:postcode":"90038",
    "addr:street":"Melrose Ave",
    "iso:country":"US",
    "sg:address":"6907 Melrose Ave",
    "sg:city":"Los Angeles",
    "sg:classifiers":[
        {
            "category":"Personal",
            "subcategory":"Barber",
            "type":"Services"
        }
    ],
    "sg:phone":"+1 323 939 4247",
    "sg:postcode":"90038",
    "sg:province":"CA",
    "sg:website":"www.rudysbarbershop.com",
    "wof:name":"Rudy's Barber Shop",
    "wof:placetype":"venue"
},
  "geometry": {"coordinates":[-118.341919,34.083675],"type":"Point"}
}