{
  "type": "Feature",
  "properties": {
    "iso:country":"US",
    "sg:address":"3528 Grant Park Drive",
    "sg:city":"Carmichael",
    "sg:classifiers":[
        {
            "category":"Professional",
            "type":"Services"
        }
    ],
    "sg:phone":"+1 866 369 4727",
    "sg:postcode":"95608",
    "sg:province":"CA",
    "sg:website":"www.fieldofgreen.com/",
    "wof:name":"Field of Green Synthetic Grass Solutions",
    "wof:placetype":"venue"
},
  "geometry": {"coordinates":[-121.325762,38.628986],"type":"Point"}
}