{
  "type": "Feature",
  "properties": {
    "iso:country":"US",
    "sg:address":"1194 N Mathilda Ave Building 2",
    "sg:city":"Sunnyvale",
    "sg:classifiers":[
        {
            "category":"Restaurant",
            "type":"Food & Drink"
        }
    ],
    "sg:postcode":"94085",
    "sg:province":"CA",
    "wof:name":"JUNOS Cafe",
    "wof:placetype":"venue"
},
  "geometry": {"coordinates":[-122.02648000000001,37.410187],"type":"Point"}
}