{
  "type": "Feature",
  "properties": {
    "iso:country":"US",
    "sg:address":"3 Meadow Rd",
    "sg:city":"Woodside",
    "sg:classifiers":[
        {
            "category":"Building & Trades",
            "subcategory":"Construction",
            "type":"Services"
        }
    ],
    "sg:phone":"+1 650 529 9321",
    "sg:postcode":"94062",
    "sg:province":"CA",
    "sg:tags":[
        "designer"
    ],
    "wof:name":"Toby Design",
    "wof:placetype":"venue"
},
  "geometry": {"coordinates":[-122.242485,37.386832],"type":"Point"}
}