{
  "type": "Feature",
  "properties": {
    "iso:country":"US",
    "sg:address":"1055 S C St",
    "sg:city":"Oxnard",
    "sg:classifiers":[
        {
            "category":"Education",
            "subcategory":"School",
            "type":"Public Place"
        }
    ],
    "sg:phone":"+1 805 486 4435",
    "sg:postcode":"93030",
    "sg:province":"CA",
    "wof:name":"Oxnard School District",
    "wof:placetype":"venue"
},
  "geometry": {"coordinates":[-119.181256,34.190789],"type":"Point"}
}