{
  "type": "Feature",
  "properties": {
    "addr:full":"3180 Imjin Rd Marina CA 93933",
    "addr:postcode":"3180;93933",
    "addr:street":"Imjin Rd",
    "iso:country":"US",
    "sg:address":"3180 Imjin Rd",
    "sg:city":"Marina",
    "sg:classifiers":[
        {
            "category":"Professional",
            "subcategory":"Research",
            "type":"Services"
        }
    ],
    "sg:phone":"+1 831 883 8187",
    "sg:postcode":"93933",
    "sg:province":"CA",
    "sg:tags":[
        "environmental",
        "ecological"
    ],
    "wof:name":"RBF Consulting",
    "wof:placetype":"venue"
},
  "geometry": {"coordinates":[-121.795543,36.659172],"type":"Point"}
}