{
  "type": "Feature",
  "properties": {
    "iso:country":"US",
    "sg:address":"279 E 17th St",
    "sg:city":"Costa Mesa",
    "sg:classifiers":[
        {
            "category":"Restaurant",
            "type":"Food & Drink"
        }
    ],
    "sg:menulink":"http://www.allmenus.com/ca/central-coast/35573-la-salsa/menu/",
    "sg:phone":"+1 949 574 1315",
    "sg:postcode":"92627",
    "sg:province":"CA",
    "sg:tags":[
        "mexican"
    ],
    "wof:name":"La Salsa",
    "wof:placetype":"venue"
},
  "geometry": {"coordinates":[-117.916049,33.633525],"type":"Point"}
}