{
  "type": "Feature",
  "properties": {
    "iso:country":"US",
    "sg:address":"12520 Magnolia Blvd",
    "sg:city":"Valley Village",
    "sg:classifiers":[
        {
            "category":"Health Services",
            "subcategory":"Dentist",
            "type":"Services"
        }
    ],
    "sg:phone":"+1 818 762 2621",
    "sg:postcode":"91607",
    "sg:province":"CA",
    "wof:name":"Alan R Brody, DDS",
    "wof:placetype":"venue"
},
  "geometry": {"coordinates":[-118.40610700000001,34.164589],"type":"Point"}
}