{
  "type": "Feature",
  "properties": {
    "iso:country":"US",
    "sg:address":"2383 E Mountain St",
    "sg:city":"Pasadena",
    "sg:phone":"+1 626 791 4440",
    "sg:postcode":"91104",
    "sg:province":"CA",
    "sg:tags":[
        "equipment",
        "commercial",
        "special",
        "mfg"
    ],
    "wof:name":"R and M Signs",
    "wof:placetype":"venue"
},
  "geometry": {"coordinates":[-118.099857,34.161615],"type":"Point"}
}