{
  "type": "Feature",
  "properties": {
    "iso:country":"US",
    "sg:address":"1221 S Oaks Ave",
    "sg:city":"Ontario",
    "sg:classifiers":[
        {
            "category":"Education",
            "subcategory":"School",
            "type":"Public Place"
        }
    ],
    "sg:phone":"+1 909 988 2050",
    "sg:postcode":"91762",
    "sg:province":"CA",
    "sg:website":"www.omsd.k12.ca.us",
    "wof:name":"Oaks Middle School",
    "wof:placetype":"venue"
},
  "geometry": {"coordinates":[-117.676282,34.051264],"type":"Point"}
}