{
  "type": "Feature",
  "properties": {
    "iso:country":"US",
    "sg:address":"2900 Acacia Ave",
    "sg:city":"Sutter",
    "sg:classifiers":[
        {
            "category":"Organizations",
            "subcategory":"Religious Organization",
            "type":"Services"
        }
    ],
    "sg:phone":"+1 530 755 0408",
    "sg:postcode":"95982",
    "sg:province":"CA",
    "sg:tags":[
        "church"
    ],
    "wof:name":"Sutter Community Church",
    "wof:placetype":"venue"
},
  "geometry": {"coordinates":[-121.753384,39.171341],"type":"Point"}
}