{
  "type": "Feature",
  "properties": {
    "iso:country":"US",
    "sg:address":"2875 Glascock St",
    "sg:city":"Oakland",
    "sg:classifiers":[
        {
            "category":"Education",
            "subcategory":"Special Training",
            "type":"Public Place"
        }
    ],
    "sg:phone":"+1 510 533 6300",
    "sg:postcode":"94601",
    "sg:province":"CA",
    "sg:tags":[
        "self",
        "motivational",
        "improvement"
    ],
    "wof:name":"Institute For Global Listening",
    "wof:placetype":"venue"
},
  "geometry": {"coordinates":[-122.23492,37.772573],"type":"Point"}
}