{
  "type": "Feature",
  "properties": {
    "addr:full":"2444 Wilshire Blvd Santa Monica CA 90403",
    "addr:housenumber":"2444",
    "addr:postcode":"90403",
    "addr:street":"Wilshire Blvd",
    "iso:country":"US",
    "sg:address":"2444 Wilshire Blvd",
    "sg:city":"Santa Monica",
    "sg:classifiers":[
        {
            "category":"Health Services",
            "subcategory":"Health Practitioner",
            "type":"Services"
        }
    ],
    "sg:phone":"+1 310 403 9198",
    "sg:postcode":"90403",
    "sg:province":"CA",
    "sg:tags":[
        "homeopath"
    ],
    "wof:name":"California Homeopathic Clinic",
    "wof:placetype":"venue"
},
  "geometry": {"coordinates":[-118.479657,34.034007],"type":"Point"}
}