{
  "type": "Feature",
  "properties": {
    "iso:country":"US",
    "sg:address":"1533 Waterloo Rd",
    "sg:city":"Stockton",
    "sg:classifiers":[
        {
            "category":"Utilities",
            "subcategory":"Refuse",
            "type":"Services"
        },
        {
            "category":"Wholesale",
            "subcategory":"Scrap",
            "type":"Manufacturing & Wholesale Goods"
        }
    ],
    "sg:phone":"+1 209 942 2267",
    "sg:postcode":"95205",
    "sg:province":"CA",
    "sg:tags":[
        "recycling",
        "transfer",
        "station",
        "center"
    ],
    "wof:name":"Stockton Recycling Center",
    "wof:placetype":"venue"
},
  "geometry": {"coordinates":[-121.267922,37.973169],"type":"Point"}
}