{
  "type": "Feature",
  "properties": {
    "iso:country":"US",
    "sg:address":"1916 Diamond Ct",
    "sg:city":"Santa Rosa",
    "sg:classifiers":[
        {
            "category":"Real Estate",
            "subcategory":"Developer",
            "type":"Services"
        }
    ],
    "sg:phone":"+1 707 526 6336",
    "sg:postcode":"95404",
    "sg:province":"CA",
    "wof:name":"Craig Meltzner & Assoc",
    "wof:placetype":"venue"
},
  "geometry": {"coordinates":[-122.694696,38.451513],"type":"Point"}
}