{
  "type": "Feature",
  "properties": {
    "iso:country":"US",
    "sg:address":"555 Saturn Blvd Ste B",
    "sg:city":"San Diego",
    "sg:classifiers":[
        {
            "category":"Freight",
            "type":"Transportation"
        }
    ],
    "sg:phone":"+1 619 424 9800",
    "sg:postcode":"92154",
    "sg:province":"CA",
    "sg:tags":[
        "shipping"
    ],
    "wof:name":"Postal Annex",
    "wof:placetype":"venue"
},
  "geometry": {"coordinates":[-117.09106800000001,32.585968],"type":"Point"}
}