{
  "type": "Feature",
  "properties": {
    "iso:country":"US",
    "sg:address":"39557 Kona Ct",
    "sg:city":"Fremont",
    "sg:classifiers":[
        {
            "category":"Building & Trades",
            "subcategory":"Plumbing",
            "type":"Services"
        }
    ],
    "sg:phone":"+1 510 490 8799",
    "sg:postcode":"94538",
    "sg:province":"CA",
    "sg:tags":[
        "contractor"
    ],
    "wof:name":"Faith Furnace & Duct Cleaning",
    "wof:placetype":"venue"
},
  "geometry": {"coordinates":[-121.99217299999999,37.53062],"type":"Point"}
}