{
  "type": "Feature",
  "properties": {
    "addr:full":"827 60th St Emeryville CA 94608",
    "addr:housenumber":"827",
    "addr:postcode":"94608",
    "addr:street":"60Th St",
    "iso:country":"US",
    "sg:address":"827 60th St",
    "sg:city":"Emeryville",
    "sg:classifiers":[
        {
            "category":"Bakery",
            "type":"Food & Drink"
        }
    ],
    "sg:phone":"+1 510 326 2086",
    "sg:postcode":"94608",
    "sg:province":"CA",
    "wof:name":"Chef Ron's Pastries",
    "wof:placetype":"venue"
},
  "geometry": {"coordinates":[-122.27195500000001,37.844982],"type":"Point"}
}