{
  "type": "Feature",
  "properties": {
    "addr:full":"8353 Laurel Canyon Blvd Sun Valley CA 91352",
    "addr:housenumber":"8353",
    "addr:postcode":"91352",
    "addr:street":"Laurel Canyon Blvd",
    "iso:country":"US",
    "sg:address":"8353 Laurel Canyon Blvd",
    "sg:city":"Sun Valley",
    "sg:classifiers":[
        {
            "category":"Shopping",
            "subcategory":"Clothing, Apparel, & Fashions",
            "type":"Retail Goods"
        }
    ],
    "sg:phone":"+1 818 767 0134",
    "sg:postcode":"91352",
    "sg:province":"CA",
    "sg:tags":[
        "accessory",
        "clothing",
        "women's"
    ],
    "wof:name":"Fashion Joy",
    "wof:placetype":"venue"
},
  "geometry": {"coordinates":[-118.396631,34.222608],"type":"Point"}
}