{
  "type": "Feature",
  "properties": {
    "iso:country":"US",
    "sg:address":"1040 Sylvan Dr",
    "sg:city":"San Carlos",
    "sg:classifiers":[
        {
            "category":"Professional",
            "type":"Services"
        }
    ],
    "sg:phone":"+1 650 508 1571",
    "sg:postcode":"94070",
    "sg:province":"CA",
    "wof:name":"Dobrudi Inc",
    "wof:placetype":"venue"
},
  "geometry": {"coordinates":[-122.260739,37.511837],"type":"Point"}
}