{
  "type": "Feature",
  "properties": {
    "addr:full":"7716 Locke Rd Vacaville CA 95688",
    "addr:housenumber":"7716",
    "addr:postcode":"95688",
    "addr:street":"Locke Rd",
    "iso:country":"US",
    "sg:address":"7716 Locke Rd",
    "sg:city":"Vacaville",
    "sg:classifiers":[
        {
            "category":"Wholesale",
            "subcategory":"Electrical",
            "type":"Manufacturing & Wholesale Goods"
        }
    ],
    "sg:phone":"+1 707 447 0473",
    "sg:postcode":"95688",
    "sg:province":"CA",
    "wof:name":"Dons Custom Service",
    "wof:placetype":"venue"
},
  "geometry": {"coordinates":[-121.948049,38.441642],"type":"Point"}
}