{
  "type": "Feature",
  "properties": {
    "addr:full":"735 Escobar St Martinez CA 94553",
    "addr:housenumber":"735",
    "addr:postcode":"94553",
    "addr:street":"Escobar St",
    "iso:country":"US",
    "sg:address":"735 Escobar St",
    "sg:city":"Martinez",
    "sg:classifiers":[
        {
            "category":"Manufacturing",
            "subcategory":"Printing",
            "type":"Manufacturing & Wholesale Goods"
        }
    ],
    "sg:phone":"+1 925 228 0197",
    "sg:postcode":"94553",
    "sg:province":"CA",
    "sg:tags":[
        "cards",
        "greeting",
        "mfg"
    ],
    "wof:name":"Garden Greetings",
    "wof:placetype":"venue"
},
  "geometry": {"coordinates":[-122.136459,38.018258],"type":"Point"}
}