{
  "type": "Feature",
  "properties": {
    "iso:country":"US",
    "sg:address":"1626 Oregon St",
    "sg:city":"Berkeley",
    "sg:classifiers":[
        {
            "category":"Building & Trades",
            "subcategory":"Construction",
            "type":"Services"
        }
    ],
    "sg:phone":"+1 510 384 6592",
    "sg:postcode":"94703",
    "sg:province":"CA",
    "sg:tags":[
        "contractor"
    ],
    "wof:name":"Flying Dutcman General Contractor",
    "wof:placetype":"venue"
},
  "geometry": {"coordinates":[-122.27617499999999,37.856448],"type":"Point"}
}