{
  "type": "Feature",
  "properties": {
    "iso:country":"US",
    "sg:address":"4924 Westminster Ter",
    "sg:city":"San Diego",
    "sg:classifiers":[
        {
            "category":"Health Services",
            "subcategory":"Chiropractor",
            "type":"Services"
        }
    ],
    "sg:phone":"+1 510 481 2377",
    "sg:postcode":"92116",
    "sg:province":"CA",
    "wof:name":"Lifestyle Chiropractic",
    "wof:placetype":"venue"
},
  "geometry": {"coordinates":[-117.108124,32.767882],"type":"Point"}
}