{
  "type": "Feature",
  "properties": {
    "addr:full":"1640 Rd D Redwood Valley CA 95470",
    "addr:housenumber":"1640",
    "addr:postcode":"95470",
    "addr:street":"Rd",
    "iso:country":"US",
    "sg:address":"1640 Rd D",
    "sg:city":"Redwood Valley",
    "sg:classifiers":[
        {
            "category":"Manufacturing",
            "subcategory":"Food",
            "type":"Manufacturing & Wholesale Goods"
        }
    ],
    "sg:phone":"+1 707 485 5656",
    "sg:postcode":"95470",
    "sg:province":"CA",
    "sg:tags":[
        "mfg"
    ],
    "wof:name":"Oracle Oaks Winery",
    "wof:placetype":"venue"
},
  "geometry": {"coordinates":[-123.194318,39.269002],"type":"Point"}
}