{
  "type": "Feature",
  "properties": {
    "iso:country":"US",
    "sg:address":"20317 Main St",
    "sg:city":"Stratford",
    "sg:classifiers":[
        {
            "category":"Autos & Motor Vehicles",
            "subcategory":"Auto Supplies",
            "type":"Retail Goods"
        }
    ],
    "sg:phone":"+1 559 947 3050",
    "sg:postcode":"93266",
    "sg:province":"CA",
    "sg:tags":[
        "automobile",
        "parts"
    ],
    "wof:name":"Stratford Auto Supply",
    "wof:placetype":"venue"
},
  "geometry": {"coordinates":[-119.824132,36.189173],"type":"Point"}
}