{
  "type": "Feature",
  "properties": {
    "iso:country":"US",
    "sg:address":"5420 Clark Ave",
    "sg:city":"Lakewood",
    "sg:classifiers":[
        {
            "category":"Organizations",
            "subcategory":"Religious Organization",
            "type":"Services"
        }
    ],
    "sg:phone":"+1 562 744 5424",
    "sg:postcode":"90712",
    "sg:province":"CA",
    "sg:tags":[
        "church"
    ],
    "wof:name":"Catholic Church-Holy Trinity",
    "wof:placetype":"venue"
},
  "geometry": {"coordinates":[-118.133683,33.855908],"type":"Point"}
}