{
  "type": "Feature",
  "properties": {
    "iso:country":"US",
    "sg:address":"10861 Morning Ridge Dr",
    "sg:city":"Moreno Valley",
    "sg:classifiers":[
        {
            "category":"Professional",
            "subcategory":"Advertising",
            "type":"Services"
        }
    ],
    "sg:phone":"+1 951 247 5855",
    "sg:postcode":"92557",
    "sg:province":"CA",
    "sg:tags":[
        "mail"
    ],
    "wof:name":"Oxford Data & Mail Svc",
    "wof:placetype":"venue"
},
  "geometry": {"coordinates":[-117.228589,33.962773],"type":"Point"}
}