{
  "type": "Feature",
  "properties": {
    "iso:country":"US",
    "sg:address":"3529 Cannon Rd",
    "sg:city":"Oceanside",
    "sg:classifiers":[
        {
            "category":"Personal",
            "subcategory":"Beauty Salon",
            "type":"Services"
        }
    ],
    "sg:phone":"+1 760 630 1332",
    "sg:postcode":"92056",
    "sg:province":"CA",
    "wof:name":"Perfect Cut",
    "wof:placetype":"venue"
},
  "geometry": {"coordinates":[-117.266054,33.16744],"type":"Point"}
}