{
  "type": "Feature",
  "properties": {
    "iso:country":"US",
    "sg:address":"7135 Hughson Ave",
    "sg:city":"Hughson",
    "sg:classifiers":[
        {
            "category":"Building & Trades",
            "subcategory":"Construction",
            "type":"Services"
        }
    ],
    "sg:phone":"+1 209 883 0446",
    "sg:postcode":"95326",
    "sg:province":"CA",
    "sg:tags":[
        "contractor"
    ],
    "wof:name":"Martin Allen Construction",
    "wof:placetype":"venue"
},
  "geometry": {"coordinates":[-120.858002,37.5979],"type":"Point"}
}