{
  "type": "Feature",
  "properties": {
    "addr:full":"5219 Mchenry Ave Modesto CA 95356",
    "addr:housenumber":"5219",
    "addr:postcode":"ca 95356",
    "addr:street":"Mchenry Ave",
    "iso:country":"US",
    "sg:address":"5219 Mchenry Ave",
    "sg:city":"Modesto",
    "sg:phone":"+1 209 544 2050",
    "sg:postcode":"95356",
    "sg:province":"CA",
    "wof:name":"Nino's Place",
    "wof:placetype":"venue"
},
  "geometry": {"coordinates":[-120.994941,37.713302],"type":"Point"}
}