{
  "type": "Feature",
  "properties": {
    "iso:country":"US",
    "sg:address":"14617 Prairie Ave",
    "sg:city":"Lawndale",
    "sg:classifiers":[
        {
            "category":"Personal",
            "type":"Services"
        }
    ],
    "sg:phone":"+1 310 970 7884",
    "sg:postcode":"90260",
    "sg:province":"CA",
    "sg:tags":[
        "control",
        "weight"
    ],
    "wof:name":"ESS-Emm Group",
    "wof:placetype":"venue"
},
  "geometry": {"coordinates":[-118.343885,33.898389],"type":"Point"}
}