{
  "type": "Feature",
  "properties": {
    "iso:country":"US",
    "sg:address":"1167 S Main St",
    "sg:city":"Manteca",
    "sg:classifiers":[
        {
            "category":"Shopping",
            "subcategory":"Jewelry",
            "type":"Retail Goods"
        }
    ],
    "sg:phone":"+1 209 824 2300",
    "sg:postcode":"95337",
    "sg:province":"CA",
    "sg:tags":[
        "jeweler"
    ],
    "wof:name":"New York Diamonds",
    "wof:placetype":"venue"
},
  "geometry": {"coordinates":[-121.216143,37.787277],"type":"Point"}
}