{
  "type": "Feature",
  "properties": {
    "addr:full":"12455 Branford St Pacoima CA 91331",
    "addr:housenumber":"12455",
    "addr:postcode":"91331",
    "addr:street":"Branford St",
    "iso:country":"US",
    "sg:address":"12455 Branford St",
    "sg:city":"Pacoima",
    "sg:classifiers":[
        {
            "category":"Manufacturing",
            "subcategory":"Printing",
            "type":"Manufacturing & Wholesale Goods"
        }
    ],
    "sg:phone":"+1 818 890 2444",
    "sg:postcode":"91331",
    "sg:province":"CA",
    "sg:tags":[
        "commercial"
    ],
    "wof:name":"Lightning Bolt Graphics",
    "wof:placetype":"venue"
},
  "geometry": {"coordinates":[-118.405654,34.246667],"type":"Point"}
}