{
  "type": "Feature",
  "properties": {
    "iso:country":"US",
    "sg:address":"3985 Tomales-Petaluma Hwy",
    "sg:city":"Tomales",
    "sg:classifiers":[
        {
            "category":"Real Estate",
            "subcategory":"Real Estate Services",
            "type":"Services"
        }
    ],
    "sg:phone":"+1 707 878 2204",
    "sg:postcode":"94971",
    "sg:province":"CA",
    "sg:tags":[
        "management"
    ],
    "sg:website":"http://www.dillonbeach.com",
    "wof:name":"Dillon Beach Property Management",
    "wof:placetype":"venue"
},
  "geometry": {"coordinates":[-122.904876,38.241989],"type":"Point"}
}