{
  "type": "Feature",
  "properties": {
    "iso:country":"US",
    "sg:address":"4901 W Rosecrans Ave",
    "sg:city":"Hawthorne",
    "sg:classifiers":[
        {
            "category":"Professional",
            "subcategory":"Detective & Security Services",
            "type":"Services"
        }
    ],
    "sg:phone":"+1 310 219 3286",
    "sg:postcode":"90250",
    "sg:province":"CA",
    "sg:tags":[
        "car"
    ],
    "wof:name":"Command Guard Services",
    "wof:placetype":"venue"
},
  "geometry": {"coordinates":[-118.367057,33.901733],"type":"Point"}
}