{
  "type": "Feature",
  "properties": {
    "addr:full":"19762 Yorba Linda Blvd Yorba Linda CA 92886",
    "addr:housenumber":"19762",
    "addr:postcode":"92886",
    "addr:street":"Yorba Linda Blvd",
    "iso:country":"US",
    "sg:address":"19762 Yorba Linda Blvd",
    "sg:city":"Yorba Linda",
    "sg:classifiers":[
        {
            "category":"Retail",
            "subcategory":"Veterinary Services",
            "type":"Services"
        }
    ],
    "sg:phone":"+1 714 693 3800",
    "sg:postcode":"92886",
    "sg:province":"CA",
    "wof:name":"Glen S Pyne Dvm",
    "wof:placetype":"venue"
},
  "geometry": {"coordinates":[-117.788782,33.889241],"type":"Point"}
}