{
  "type": "Feature",
  "properties": {
    "iso:country":"US",
    "sg:address":"954 San Pablo Ave",
    "sg:city":"Albany",
    "sg:classifiers":[
        {
            "category":"Retail",
            "subcategory":"Veterinary Services",
            "type":"Services"
        }
    ],
    "sg:phone":"+1 510 524 3072",
    "sg:postcode":"94706",
    "sg:province":"CA",
    "sg:tags":[
        "clinic",
        "hospital"
    ],
    "wof:name":"Codornices Cat Clinic",
    "wof:placetype":"venue"
},
  "geometry": {"coordinates":[-122.298483,37.88878],"type":"Point"}
}