{
  "type": "Feature",
  "properties": {
    "iso:country":"US",
    "sg:address":"23624-B El Toro Rd",
    "sg:city":"Lake Forest",
    "sg:classifiers":[
        {
            "category":"Restaurant",
            "type":"Food & Drink"
        }
    ],
    "sg:phone":"+1 949 855 4300",
    "sg:postcode":"92630",
    "sg:province":"CA",
    "sg:tags":[
        "pizza"
    ],
    "sg:website":"www.nysuppercrustpizza.com",
    "wof:name":"NY's Upper Crust Pizza",
    "wof:placetype":"venue"
},
  "geometry": {"coordinates":[-117.70229399999999,33.618929],"type":"Point"}
}