{
  "type": "Feature",
  "properties": {
    "addr:full":"2893 W Lincoln Ave Anaheim CA 92801",
    "addr:housenumber":"2893",
    "addr:postcode":"92801",
    "addr:street":"W Lincoln Ave",
    "iso:country":"US",
    "sg:address":"2893 W Lincoln Ave",
    "sg:city":"Anaheim",
    "sg:classifiers":[
        {
            "category":"Restaurant",
            "type":"Food & Drink"
        }
    ],
    "sg:phone":"+1 714 827 7820",
    "sg:postcode":"92801",
    "sg:province":"CA",
    "sg:tags":[
        "sushi",
        "bar"
    ],
    "wof:name":"Osaka Japanese Restaurant",
    "wof:placetype":"venue"
},
  "geometry": {"coordinates":[-117.98871699999999,33.832164],"type":"Point"}
}