{
  "type": "Feature",
  "properties": {
    "addr:full":"13502 Whittier Blvd Ste E Whittier CA 90605",
    "addr:housenumber":"13502",
    "addr:postcode":"90605",
    "addr:street":"Whittier Blvd Ste E",
    "iso:country":"US",
    "sg:address":"13502 Whittier Blvd Ste E",
    "sg:city":"Whittier",
    "sg:classifiers":[
        {
            "category":"Retail",
            "subcategory":"Portrait Studio",
            "type":"Services"
        }
    ],
    "sg:phone":"+1 562 696 2400",
    "sg:postcode":"90605",
    "sg:province":"CA",
    "sg:tags":[
        "photography",
        "store"
    ],
    "sg:website":"www.1hrfotocity.com",
    "wof:name":"1HRFOTOCITY",
    "wof:placetype":"venue"
},
  "geometry": {"coordinates":[-118.098553,33.961868],"type":"Point"}
}