{
  "type": "Feature",
  "properties": {
    "addr:full":"14614 Crenshaw Blvd Gardena CA 90249",
    "addr:housenumber":"14614",
    "addr:postcode":"90249",
    "addr:street":"Crenshaw Blvd",
    "iso:country":"US",
    "sg:address":"14614 Crenshaw Blvd",
    "sg:city":"Gardena",
    "sg:classifiers":[
        {
            "category":"Retail",
            "subcategory":"Laundry & Dry Cleaning",
            "type":"Services"
        }
    ],
    "sg:phone":"+1 310 324 8268",
    "sg:postcode":"90249",
    "sg:province":"CA",
    "sg:tags":[
        "cleaners",
        "rug",
        "carpet"
    ],
    "wof:name":"Carl's Carpet & Upholstery",
    "wof:placetype":"venue"
},
  "geometry": {"coordinates":[-118.326435,33.898886],"type":"Point"}
}