{
  "type": "Feature",
  "properties": {
    "addr:full":"298 Barnard Ave Ste A San Jose CA 95125",
    "addr:housenumber":"298",
    "addr:postcode":"95125",
    "addr:street":"Barnard Ave Ste A",
    "iso:country":"US",
    "sg:address":"298 Barnard Ave Ste A",
    "sg:city":"San Jose",
    "sg:classifiers":[
        {
            "category":"Health Services",
            "subcategory":"Clinic",
            "type":"Services"
        }
    ],
    "sg:phone":"+1 408 288 7990",
    "sg:postcode":"95125",
    "sg:province":"CA",
    "sg:tags":[
        "cannabis"
    ],
    "wof:name":"California Naturopathic Agricultural Association #2",
    "wof:placetype":"venue"
},
  "geometry": {"coordinates":[-121.876058,37.306273],"type":"Point"}
}