{
  "type": "Feature",
  "properties": {
    "iso:country":"US",
    "sg:address":"11442 Baden Rd",
    "sg:city":"Truckee",
    "sg:classifiers":[
        {
            "category":"Building & Trades",
            "subcategory":"Construction",
            "type":"Services"
        }
    ],
    "sg:phone":"+1 530 582 4355",
    "sg:postcode":"96161",
    "sg:province":"CA",
    "sg:tags":[
        "general",
        "contractor"
    ],
    "wof:name":"C M White Construction",
    "wof:placetype":"venue"
},
  "geometry": {"coordinates":[-120.22912100000001,39.344587],"type":"Point"}
}