{
  "type": "Feature",
  "properties": {
    "addr:full":"9605 Canoga Ave Chatsworth CA 91311",
    "addr:housenumber":"9605",
    "addr:postcode":"91311",
    "addr:street":"Canoga Ave",
    "iso:country":"US",
    "sg:address":"9605 Canoga Ave",
    "sg:city":"Chatsworth",
    "sg:classifiers":[
        {
            "category":"Shopping",
            "subcategory":"Pharmacy",
            "type":"Retail Goods"
        }
    ],
    "sg:phone":"+1 818 678 2660",
    "sg:postcode":"91311",
    "sg:province":"CA",
    "wof:name":"Neighbor Care Pharmacy",
    "wof:placetype":"venue"
},
  "geometry": {"coordinates":[-118.599025,34.245871],"type":"Point"}
}