{
  "type": "Feature",
  "properties": {
    "addr:full":"650 Eubanks Ct Vacaville CA 95688",
    "addr:housenumber":"650",
    "addr:postcode":"95688",
    "addr:street":"Eubanks Ct",
    "iso:country":"US",
    "sg:address":"650 Eubanks Ct",
    "sg:city":"Vacaville",
    "sg:classifiers":[
        {
            "category":"Government",
            "subcategory":"Fire Station",
            "type":"Public Place"
        }
    ],
    "sg:phone":"+1 707 449 6116",
    "sg:postcode":"95688",
    "sg:province":"CA",
    "sg:tags":[
        "department"
    ],
    "wof:name":"Vacaville Fire Dept",
    "wof:placetype":"venue"
},
  "geometry": {"coordinates":[-121.960657,38.395865],"type":"Point"}
}