{
  "type": "Feature",
  "properties": {
    "addr:full":"19885 Temescal Canyon Rd Corona CA 92881",
    "addr:housenumber":"19885",
    "addr:postcode":"92881",
    "addr:street":"Temescal Canyon Rd",
    "iso:country":"US",
    "sg:address":"19885 Temescal Canyon Rd",
    "sg:city":"Corona",
    "sg:classifiers":[
        {
            "category":"Freight",
            "type":"Transportation"
        }
    ],
    "sg:phone":"+1 951 735 9350",
    "sg:postcode":"92881",
    "sg:province":"CA",
    "sg:tags":[
        "trucking"
    ],
    "wof:name":"Best Transport",
    "wof:placetype":"venue"
},
  "geometry": {"coordinates":[-117.518754,33.832599],"type":"Point"}
}