{
  "type": "Feature",
  "properties": {
    "iso:country":"US",
    "sg:address":"700 S Hill St Ste 1",
    "sg:city":"Los Angeles",
    "sg:classifiers":[
        {
            "category":"Shopping",
            "subcategory":"Jewelry",
            "type":"Retail Goods"
        }
    ],
    "sg:phone":"+1 213 622 9270",
    "sg:postcode":"90014",
    "sg:province":"CA",
    "sg:website":"www.foxjewelry.com",
    "wof:name":"Fox Jewelry",
    "wof:placetype":"venue"
},
  "geometry": {"coordinates":[-118.253998,34.045898],"type":"Point"}
}