{
  "type": "Feature",
  "properties": {
    "addr:full":"7239 Topanga Canyon Blvd Canoga Park CA 91303",
    "addr:housenumber":"7239",
    "addr:postcode":"91303",
    "addr:street":"Topanga Canyon Blvd",
    "iso:country":"US",
    "sg:address":"7239 Topanga Canyon Blvd",
    "sg:city":"Canoga Park",
    "sg:classifiers":[
        {
            "category":"Banks & Credit Unions",
            "subcategory":"Bank",
            "type":"Services"
        }
    ],
    "sg:phone":"+1 818 594 0057",
    "sg:postcode":"91303",
    "sg:province":"CA",
    "sg:tags":[
        "cashing",
        "notary",
        "check"
    ],
    "wof:name":"Topanga Check Cashing Service",
    "wof:placetype":"venue"
},
  "geometry": {"coordinates":[-118.606003,34.202301],"type":"Point"}
}