{
  "type": "Feature",
  "properties": {
    "addr:full":"1936 Quivira Way San Diego CA 92109",
    "addr:housenumber":"1936",
    "addr:postcode":"92109",
    "addr:street":"Quivira Way",
    "iso:country":"US",
    "sg:address":"1936 Quivira Way",
    "sg:city":"San Diego",
    "sg:classifiers":[
        {
            "category":"Government",
            "subcategory":"City Hall",
            "type":"Public Place"
        }
    ],
    "sg:phone":"+1 800 925 1707",
    "sg:postcode":"92109",
    "sg:province":"CA",
    "sg:website":"www.greattrafficschool.net/index...",
    "wof:name":"Great Comedians Traffic School",
    "wof:placetype":"venue"
},
  "geometry": {"coordinates":[-117.235485,32.760038],"type":"Point"}
}