{
  "type": "Feature",
  "properties": {
    "addr:full":"211 W Huntington Dr Arcadia CA 91007",
    "addr:housenumber":"211",
    "addr:postcode":"91007",
    "addr:street":"W Huntington Dr",
    "iso:country":"US",
    "sg:address":"211 W Huntington Dr",
    "sg:city":"Arcadia",
    "sg:classifiers":[
        {
            "category":"Restaurant",
            "type":"Food & Drink"
        }
    ],
    "sg:menulink":"http://www.allmenus.com/ca/upper-san-gabriel-valley/22038-capistranos-restaurant/menu/",
    "sg:phone":"+1 626 294 0034",
    "sg:postcode":"91007",
    "sg:province":"CA",
    "sg:tags":[
        "american"
    ],
    "wof:name":"Capistrano's Restaurant",
    "wof:placetype":"venue"
},
  "geometry": {"coordinates":[-118.038776,34.138823],"type":"Point"}
}