{
  "type": "Feature",
  "properties": {
    "addr:full":"107 Palm St Newport Beach CA 92661",
    "addr:housenumber":"107",
    "addr:postcode":"92661",
    "addr:street":"Palm St",
    "iso:country":"US",
    "sg:address":"107 Palm St",
    "sg:city":"Newport Beach",
    "sg:classifiers":[
        {
            "category":"Shopping",
            "subcategory":"Tobacco",
            "type":"Retail Goods"
        },
        {
            "category":"Bars & Pubs",
            "subcategory":"Hookah Bar",
            "type":"Food & Drink"
        }
    ],
    "sg:phone":"+1 949 475 2992",
    "sg:postcode":"92661",
    "sg:province":"CA",
    "sg:tags":[
        "shop"
    ],
    "sg:website":"www.lahabanacigar.com",
    "wof:name":"La Habana Cigar Co",
    "wof:placetype":"venue"
},
  "geometry": {"coordinates":[-117.901319,33.601927],"type":"Point"}
}