{
  "type": "Feature",
  "properties": {
    "iso:country":"US",
    "sg:address":"1250 Parkview Ave",
    "sg:city":"Redding",
    "sg:classifiers":[
        {
            "category":"Recreation",
            "type":"Entertainment"
        }
    ],
    "sg:phone":"+1 530 225 4095",
    "sg:postcode":"96001",
    "sg:province":"CA",
    "sg:tags":[
        "parks"
    ],
    "wof:name":"Redding Recreation",
    "wof:placetype":"venue"
},
  "geometry": {"coordinates":[-122.386769,40.573658],"type":"Point"}
}