{
  "type": "Feature",
  "properties": {
    "iso:country":"US",
    "sg:address":"760 Vella Rd",
    "sg:city":"Palm Springs",
    "sg:classifiers":[
        {
            "category":"Manufacturing",
            "subcategory":"Printing",
            "type":"Manufacturing & Wholesale Goods"
        }
    ],
    "sg:phone":"+1 760 325 8515",
    "sg:postcode":"92264",
    "sg:province":"CA",
    "sg:tags":[
        "screen"
    ],
    "wof:name":"Drive Music Group",
    "wof:placetype":"venue"
},
  "geometry": {"coordinates":[-116.497322,33.808714],"type":"Point"}
}