{
  "type": "Feature",
  "properties": {
    "iso:country":"US",
    "sg:address":"15555 Jimmy Durante Blvd",
    "sg:city":"Del Mar",
    "sg:classifiers":[
        {
            "category":"Sports & Exercise",
            "subcategory":"Tennis Court",
            "type":"Entertainment"
        }
    ],
    "sg:phone":"+1 858 755 5293",
    "sg:postcode":"92014",
    "sg:province":"CA",
    "wof:name":"Surf & Turf Tennis Club",
    "wof:placetype":"venue"
},
  "geometry": {"coordinates":[-117.25599699999999,32.978001],"type":"Point"}
}