{
  "type": "Feature",
  "properties": {
    "addr:full":"130 Eastgate Rd Barstow CA 92311",
    "addr:housenumber":"130",
    "addr:postcode":"92311",
    "addr:street":"Eastgate Rd",
    "iso:country":"US",
    "sg:address":"130 Eastgate Rd",
    "sg:city":"Barstow",
    "sg:classifiers":[
        {
            "category":"Retail",
            "subcategory":"Auto Rental",
            "type":"Services"
        }
    ],
    "sg:phone":"+1 760 255 4111",
    "sg:postcode":"92311",
    "sg:province":"CA",
    "sg:tags":[
        "renting",
        "automobile"
    ],
    "wof:name":"Oasis Auto Rental",
    "wof:placetype":"venue"
},
  "geometry": {"coordinates":[-117.00256,34.894922],"type":"Point"}
}