{
  "type": "Feature",
  "properties": {
    "addr:full":"12930 Ventura Blvd Studio City CA 91604",
    "addr:housenumber":"12930",
    "addr:postcode":"91604",
    "addr:street":"Ventura Blvd",
    "iso:country":"US",
    "sg:address":"12930 Ventura Blvd",
    "sg:city":"Studio City",
    "sg:classifiers":[
        {
            "category":"Real Estate",
            "subcategory":"Real Estate Agent",
            "type":"Services"
        }
    ],
    "sg:phone":"+1 818 506 3030",
    "sg:postcode":"91604",
    "sg:province":"CA",
    "wof:name":"Progressive Title Company Inc",
    "wof:placetype":"venue"
},
  "geometry": {"coordinates":[-118.414978,34.145235],"type":"Point"}
}