{
  "type": "Feature",
  "properties": {
    "addr:full":"40960 California Oaks Rd Murrieta CA 92562",
    "addr:housenumber":"40960",
    "addr:postcode":"92562",
    "addr:street":"California Oaks Rd",
    "iso:country":"US",
    "sg:address":"40960 California Oaks Rd",
    "sg:city":"Murrieta",
    "sg:classifiers":[
        {
            "category":"Manufacturing",
            "subcategory":"Apparel",
            "type":"Manufacturing & Wholesale Goods"
        }
    ],
    "sg:phone":"+1 951 674 3442",
    "sg:postcode":"92562",
    "sg:province":"CA",
    "sg:tags":[
        "drapery",
        "contractor"
    ],
    "wof:name":"New Creations",
    "wof:placetype":"venue"
},
  "geometry": {"coordinates":[-117.205733,33.567911],"type":"Point"}
}