{
  "type": "Feature",
  "properties": {
    "addr:full":"5672 Almaden Expy Ste B San Jose CA 95118",
    "addr:housenumber":"5672",
    "addr:postcode":"95118",
    "addr:street":"Almaden Expy Ste B",
    "iso:country":"US",
    "sg:address":"5672 Almaden Expy Ste B",
    "sg:city":"San Jose",
    "sg:classifiers":[
        {
            "category":"Arts & Performance",
            "subcategory":"Art Gallery",
            "type":"Entertainment"
        },
        {
            "category":"Education",
            "subcategory":"Special Training",
            "type":"Public Place"
        }
    ],
    "sg:phone":"+1 408 978 9118",
    "sg:postcode":"95118",
    "sg:province":"CA",
    "sg:tags":[
        "school"
    ],
    "sg:website":"www.cindyartstudio.net",
    "wof:name":"Cindy Art Studio",
    "wof:placetype":"venue"
},
  "geometry": {"coordinates":[-121.87850299999999,37.270268],"type":"Point"}
}