{
  "type": "Feature",
  "properties": {
    "iso:country":"US",
    "sg:address":"Beachmont Plaza 10111 Adams Avenue",
    "sg:city":"Huntington Beach",
    "sg:classifiers":[
        {
            "category":"Personal",
            "subcategory":"Nail Salon",
            "type":"Services"
        }
    ],
    "sg:phone":"+1 714 968 2023",
    "sg:postcode":"92646",
    "sg:province":"CA",
    "wof:name":"Happy Nails",
    "wof:placetype":"venue"
},
  "geometry": {"coordinates":[-117.952994,33.673096],"type":"Point"}
}