{
  "type": "Feature",
  "properties": {
    "iso:country":"US",
    "sg:address":"547 W Commonwealth Ave",
    "sg:city":"Fullerton",
    "sg:classifiers":[
        {
            "category":"Building & Trades",
            "subcategory":"Construction",
            "type":"Services"
        }
    ],
    "sg:phone":"+1 714 447 0898",
    "sg:postcode":"92832",
    "sg:province":"CA",
    "sg:tags":[
        "contractor"
    ],
    "wof:name":"Super Seal Roofing",
    "wof:placetype":"venue"
},
  "geometry": {"coordinates":[-117.933965,33.870345],"type":"Point"}
}