{
  "type": "Feature",
  "properties": {
    "iso:country":"US",
    "sg:address":"1024 J St",
    "sg:city":"Modesto",
    "sg:classifiers":[
        {
            "category":"Professional",
            "subcategory":"Management & Consulting",
            "type":"Services"
        }
    ],
    "sg:phone":"+1 209 341 0525",
    "sg:postcode":"95354",
    "sg:province":"CA",
    "sg:tags":[
        "construction"
    ],
    "wof:name":"C M Pros",
    "wof:placetype":"venue"
},
  "geometry": {"coordinates":[-120.9995,37.641005],"type":"Point"}
}