{
  "type": "Feature",
  "properties": {
    "addr:full":"1313 Trieste Ln Carpinteria CA 93013",
    "addr:housenumber":"1313",
    "addr:postcode":"93013",
    "addr:street":"Trieste Ln",
    "iso:country":"US",
    "sg:address":"1313 Trieste Ln",
    "sg:city":"Carpinteria",
    "sg:classifiers":[
        {
            "category":"Professional",
            "type":"Services"
        }
    ],
    "sg:phone":"+1 805 684 8333",
    "sg:postcode":"93013",
    "sg:province":"CA",
    "wof:name":"Bill Dayka",
    "wof:placetype":"venue"
},
  "geometry": {"coordinates":[-119.533455,34.405869],"type":"Point"}
}