{
  "type": "Feature",
  "properties": {
    "iso:country":"US",
    "sg:address":"8826 Burton Way",
    "sg:city":"Beverly Hills",
    "sg:classifiers":[
        {
            "category":"Professional",
            "subcategory":"Employment Agencies",
            "type":"Services"
        }
    ],
    "sg:phone":"+1 310 276 8100",
    "sg:postcode":"90211",
    "sg:province":"CA",
    "sg:tags":[
        "modeling"
    ],
    "wof:name":"Ford Models Inc",
    "wof:placetype":"venue"
},
  "geometry": {"coordinates":[-118.383764,34.072122],"type":"Point"}
}