{
  "type": "Feature",
  "properties": {
    "iso:country":"US",
    "sg:address":"420 E Arrow Hwy",
    "sg:city":"San Dimas",
    "sg:classifiers":[
        {
            "category":"Wholesale",
            "subcategory":"Hardware",
            "type":"Manufacturing & Wholesale Goods"
        },
        {
            "category":"Manufacturing",
            "subcategory":"Tools & Machinery",
            "type":"Manufacturing & Wholesale Goods"
        }
    ],
    "sg:phone":"+1 909 592 8830",
    "sg:postcode":"91773",
    "sg:province":"CA",
    "sg:tags":[
        "equipment",
        "parts",
        "refrigeration",
        "refrigerating",
        "mfg"
    ],
    "sg:website":"www.hillphoenix.com",
    "wof:name":"National Cooler Corp",
    "wof:placetype":"venue"
},
  "geometry": {"coordinates":[-117.801506,34.102886],"type":"Point"}
}