{
  "type": "Feature",
  "properties": {
    "addr:full":"1555 S 10th St San Jose CA 95112",
    "addr:housenumber":"1555",
    "addr:postcode":"95112",
    "addr:street":"S 10Th St",
    "iso:country":"US",
    "sg:address":"1555 S 10th St",
    "sg:city":"San Jose",
    "sg:classifiers":[
        {
            "category":"Retail",
            "subcategory":"Auto Repair",
            "type":"Services"
        }
    ],
    "sg:phone":"+1 408 280 7002",
    "sg:postcode":"95112",
    "sg:province":"CA",
    "wof:name":"Star Auto Service",
    "wof:placetype":"venue"
},
  "geometry": {"coordinates":[-121.86471299999999,37.317861],"type":"Point"}
}