{
  "type": "Feature",
  "properties": {
    "iso:country":"US",
    "sg:address":"433 Airport Blvd",
    "sg:city":"Burlingame",
    "sg:classifiers":[
        {
            "category":"Wholesale",
            "subcategory":"Durable Goods & Equipment",
            "type":"Manufacturing & Wholesale Goods"
        }
    ],
    "sg:phone":"+1 650 685 5410",
    "sg:postcode":"94010",
    "sg:province":"CA",
    "sg:tags":[
        "exporter"
    ],
    "wof:name":"Cypress International Trading",
    "wof:placetype":"venue"
},
  "geometry": {"coordinates":[-122.349542,37.590135],"type":"Point"}
}