{
  "type": "Feature",
  "properties": {
    "addr:full":"8025 Lincoln St Lemon Grove CA 91945",
    "addr:housenumber":"8025",
    "addr:postcode":"91945",
    "addr:street":"Lincoln St",
    "iso:country":"US",
    "sg:address":"8025 Lincoln St",
    "sg:city":"Lemon Grove",
    "sg:classifiers":[
        {
            "category":"Education",
            "subcategory":"School",
            "type":"Public Place"
        }
    ],
    "sg:phone":"+1 619 825 5817",
    "sg:postcode":"91945",
    "sg:province":"CA",
    "sg:tags":[
        "elementary",
        "district"
    ],
    "wof:name":"Grove Lemon School District",
    "wof:placetype":"venue"
},
  "geometry": {"coordinates":[-117.02636699999999,32.738218],"type":"Point"}
}