{
  "type": "Feature",
  "properties": {
    "addr:full":"4 Chrysler Irvine CA 92618",
    "addr:housenumber":"4",
    "addr:postcode":"92618",
    "addr:street":"Chrysler",
    "iso:country":"US",
    "sg:address":"4 Chrysler",
    "sg:city":"Irvine",
    "sg:classifiers":[
        {
            "category":"Real Estate",
            "subcategory":"Real Estate Agent",
            "type":"Services"
        }
    ],
    "sg:phone":"+1 949 413 2240",
    "sg:postcode":"92618",
    "sg:province":"CA",
    "sg:tags":[
        "broker"
    ],
    "wof:name":"Pacific First Financial Realty",
    "wof:placetype":"venue"
},
  "geometry": {"coordinates":[-117.712569,33.64899],"type":"Point"}
}