{
  "type": "Feature",
  "properties": {
    "addr:full":"1700 Halford Ave Ofc Santa Clara CA 95051",
    "addr:housenumber":"1700",
    "addr:postcode":"95051",
    "addr:street":"Halford Ave",
    "iso:country":"US",
    "sg:address":"1700 Halford Ave Ofc",
    "sg:city":"Santa Clara",
    "sg:classifiers":[
        {
            "category":"Real Estate",
            "subcategory":"Real Estate Operator",
            "type":"Services"
        }
    ],
    "sg:phone":"+1 408 296 7500",
    "sg:postcode":"95051",
    "sg:province":"CA",
    "sg:tags":[
        "apartment"
    ],
    "wof:name":"Mission West Apartments",
    "wof:placetype":"venue"
},
  "geometry": {"coordinates":[-121.998001,37.3549],"type":"Point"}
}