{
  "type": "Feature",
  "properties": {
    "addr:full":"128 S Cross Creek Rd Orange CA 92869",
    "addr:housenumber":"128",
    "addr:postcode":"92869",
    "addr:street":"S Cross Creek Rd",
    "iso:country":"US",
    "sg:address":"128 S Cross Creek Rd",
    "sg:city":"Orange",
    "sg:classifiers":[
        {
            "category":"Real Estate",
            "subcategory":"Real Estate Services",
            "type":"Services"
        }
    ],
    "sg:phone":"+1 714 744 0617",
    "sg:postcode":"92869",
    "sg:province":"CA",
    "sg:tags":[
        "management",
        "property"
    ],
    "wof:name":"Real Estate Professionals",
    "wof:placetype":"venue"
},
  "geometry": {"coordinates":[-117.760266,33.786474],"type":"Point"}
}