{
  "type": "Feature",
  "properties": {
    "iso:country":"US",
    "sg:address":"199 Park Pl",
    "sg:city":"Richmond",
    "sg:classifiers":[
        {
            "category":"Restaurant",
            "type":"Food & Drink"
        }
    ],
    "sg:phone":"+1 510 236 2118",
    "sg:postcode":"94801",
    "sg:province":"CA",
    "wof:name":"Suzhou Chinese Rstrnt & Sushi",
    "wof:placetype":"venue"
},
  "geometry": {"coordinates":[-122.38481,37.927077],"type":"Point"}
}