{
  "type": "Feature",
  "properties": {
    "addr:full":"8731 de Soto Ave Canoga Park CA 91304",
    "addr:housenumber":"8731",
    "addr:postcode":"91304",
    "addr:street":"De Soto Ave",
    "iso:country":"US",
    "sg:address":"8731 de Soto Ave",
    "sg:city":"Canoga Park",
    "sg:classifiers":[
        {
            "category":"Real Estate",
            "subcategory":"Real Estate Operator",
            "type":"Services"
        }
    ],
    "sg:phone":"+1 818 709 6933",
    "sg:postcode":"91304",
    "sg:province":"CA",
    "sg:tags":[
        "apartment"
    ],
    "wof:name":"Desoto Pines Apartment",
    "wof:placetype":"venue"
},
  "geometry": {"coordinates":[-118.5886,34.230006],"type":"Point"}
}