{
  "type": "Feature",
  "properties": {
    "addr:full":"615 N Lemon St Orange CA 92867",
    "addr:housenumber":"615",
    "addr:postcode":"92867",
    "addr:street":"N Lemon St",
    "iso:country":"US",
    "sg:address":"615 N Lemon St",
    "sg:city":"Orange",
    "sg:classifiers":[
        {
            "category":"Education",
            "subcategory":"School",
            "type":"Public Place"
        }
    ],
    "sg:phone":"+1 714 997 6167",
    "sg:postcode":"92867",
    "sg:province":"CA",
    "sg:tags":[
        "high",
        "middle",
        "elementary"
    ],
    "wof:name":"Richland High School",
    "wof:placetype":"venue"
},
  "geometry": {"coordinates":[-117.855003,33.797298],"type":"Point"}
}