{
  "type": "Feature",
  "properties": {
    "iso:country":"US",
    "sg:address":"5027 Irwindale Ave",
    "sg:city":"Baldwin Park",
    "sg:classifiers":[
        {
            "category":"Freight",
            "type":"Transportation"
        }
    ],
    "sg:phone":"+1 626 214 3000",
    "sg:postcode":"91706",
    "sg:province":"CA",
    "sg:tags":[
        "arrangement"
    ],
    "wof:name":"International Frt Trnspt Inc",
    "wof:placetype":"venue"
},
  "geometry": {"coordinates":[-117.93423199999999,34.10306],"type":"Point"}
}