{
  "type": "Feature",
  "properties": {
    "addr:full":"1590 N Waterman Ave San Bernardino CA 92404",
    "addr:housenumber":"1590",
    "addr:postcode":"92404",
    "addr:street":"N Waterman Ave",
    "iso:country":"US",
    "sg:address":"1590 N Waterman Ave",
    "sg:city":"San Bernardino",
    "sg:classifiers":[
        {
            "category":"Professional",
            "subcategory":"Management & Consulting",
            "type":"Services"
        }
    ],
    "sg:phone":"+1 909 885 2029",
    "sg:postcode":"92404",
    "sg:province":"CA",
    "sg:tags":[
        "consultant",
        "educational"
    ],
    "wof:name":"BLU Educational Svc",
    "wof:placetype":"venue"
},
  "geometry": {"coordinates":[-117.278942,34.128763],"type":"Point"}
}