{
  "type": "Feature",
  "properties": {
    "iso:country":"US",
    "sg:address":"416 Rancho Santa Fe Rd",
    "sg:city":"Encinitas",
    "sg:classifiers":[
        {
            "category":"Organizations",
            "subcategory":"Religious Organization",
            "type":"Services"
        }
    ],
    "sg:phone":"+1 760 436 0045",
    "sg:postcode":"92024",
    "sg:province":"CA",
    "sg:tags":[
        "church"
    ],
    "wof:name":"Ranch View Baptist Church",
    "wof:placetype":"venue"
},
  "geometry": {"coordinates":[-117.23483,33.045425],"type":"Point"}
}