{
  "type": "Feature",
  "properties": {
    "iso:country":"US",
    "sg:address":"31225 Felecita Rd",
    "sg:city":"Temecula",
    "sg:classifiers":[
        {
            "category":"Freight",
            "type":"Transportation"
        }
    ],
    "sg:phone":"+1 951 694 1711",
    "sg:postcode":"92591",
    "sg:province":"CA",
    "sg:tags":[
        "operator",
        "trucking"
    ],
    "wof:name":"T & R Traffic Consulting Inc",
    "wof:placetype":"venue"
},
  "geometry": {"coordinates":[-117.11443,33.529346],"type":"Point"}
}