{
  "type": "Feature",
  "properties": {
    "addr:full":"4488 Don Milagro Dr Los Angeles CA 90008",
    "addr:housenumber":"4488",
    "addr:postcode":"90008",
    "addr:street":"Don Milagro Dr",
    "iso:country":"US",
    "sg:address":"4488 Don Milagro Dr",
    "sg:city":"Los Angeles",
    "sg:classifiers":[
        {
            "category":"Organizations",
            "subcategory":"Non-profit Organization",
            "type":"Services"
        }
    ],
    "sg:phone":"+1 323 290 0726",
    "sg:postcode":"90008",
    "sg:province":"CA",
    "sg:tags":[
        "medical",
        "management"
    ],
    "wof:name":"Safe Anesthesia Group",
    "wof:placetype":"venue"
},
  "geometry": {"coordinates":[-118.352492,34.008957],"type":"Point"}
}