{
  "type": "Feature",
  "properties": {
    "addr:full":"6399 Wilshire Blvd Ste 810 Los Angeles CA 90048",
    "addr:housenumber":"6399",
    "addr:postcode":"90048",
    "addr:street":"Wilshire Blvd Ste 810",
    "iso:country":"US",
    "sg:address":"6399 Wilshire Blvd Ste 810",
    "sg:city":"Los Angeles",
    "sg:classifiers":[
        {
            "category":"Professional",
            "subcategory":"Lawyer & Legal Services",
            "type":"Services"
        }
    ],
    "sg:phone":"+1 323 944 0993",
    "sg:postcode":"90048",
    "sg:province":"CA",
    "sg:tags":[
        "personal",
        "injury"
    ],
    "sg:website":"www.victimslawyer.com/",
    "wof:name":"The Law offices of Steven M. Sweat, APC",
    "wof:placetype":"venue"
},
  "geometry": {"coordinates":[-118.368002,34.064121],"type":"Point"}
}