{
  "type": "Feature",
  "properties": {
    "addr:full":"1710 N Milpitas Boulevard Milpitas CA 95035",
    "addr:housenumber":"1710",
    "addr:postcode":"95035",
    "addr:street":"N Milpitas Boulevard",
    "iso:country":"US",
    "sg:address":"1710 N Milpitas Boulevard",
    "sg:city":"Milpitas",
    "sg:classifiers":[
        {
            "category":"Coffee & Tea",
            "type":"Food & Drink"
        }
    ],
    "sg:phone":"+1 408 946 7280",
    "sg:postcode":"95035",
    "sg:province":"CA",
    "wof:name":"Bo Ba",
    "wof:placetype":"venue"
},
  "geometry": {"coordinates":[-121.910689,37.454823],"type":"Point"}
}