{
  "type": "Feature",
  "properties": {
    "addr:full":"1940 Embarcadero Oakland CA 94606",
    "addr:housenumber":"1940",
    "addr:postcode":"94606",
    "addr:street":"Embarcadero",
    "iso:country":"US",
    "sg:address":"1940 Embarcadero",
    "sg:city":"Oakland",
    "sg:classifiers":[
        {
            "category":"Professional",
            "subcategory":"Lawyer & Legal Services",
            "type":"Services"
        }
    ],
    "sg:phone":"+1 510 434 0140",
    "sg:postcode":"94606",
    "sg:province":"CA",
    "sg:tags":[
        "attorney"
    ],
    "wof:name":"Harrison Taylor & Brazile",
    "wof:placetype":"venue"
},
  "geometry": {"coordinates":[-122.242752,37.780654],"type":"Point"}
}