{
  "type": "Feature",
  "properties": {
    "addr:full":"23659 Calabasas Rd Calabasas CA 91302",
    "addr:housenumber":"23659",
    "addr:postcode":"91302",
    "addr:street":"Calabasas Rd",
    "iso:country":"US",
    "sg:address":"23659 Calabasas Rd",
    "sg:city":"Calabasas",
    "sg:classifiers":[
        {
            "category":"Health Services",
            "subcategory":"Optometrist",
            "type":"Services"
        }
    ],
    "sg:phone":"+1 818 222 4393",
    "sg:postcode":"91302",
    "sg:province":"CA",
    "wof:name":"Optometrics",
    "wof:placetype":"venue"
},
  "geometry": {"coordinates":[-118.643789,34.155614],"type":"Point"}
}