{
  "type": "Feature",
  "properties": {
    "addr:full":"890 Hillcrest Dr Laguna Beach CA 92651",
    "addr:housenumber":"890",
    "addr:postcode":"92651",
    "addr:street":"Hillcrest Dr",
    "iso:country":"US",
    "sg:address":"890 Hillcrest Dr",
    "sg:city":"Laguna Beach",
    "sg:classifiers":[
        {
            "category":"Professional",
            "type":"Services"
        }
    ],
    "sg:phone":"+1 949 376 8764",
    "sg:postcode":"92651",
    "sg:province":"CA",
    "wof:name":"Marilyn B Romano",
    "wof:placetype":"venue"
},
  "geometry": {"coordinates":[-117.795681,33.548697],"type":"Point"}
}