{
  "type": "Feature",
  "properties": {
    "addr:full":"5719 Holmes Ave Vernon CA 90058",
    "addr:housenumber":"5719",
    "addr:postcode":"90058",
    "addr:street":"Holmes Ave",
    "iso:country":"US",
    "sg:address":"5719 Holmes Ave",
    "sg:city":"Vernon",
    "sg:classifiers":[
        {
            "category":"Wholesale",
            "subcategory":"Electrical",
            "type":"Manufacturing & Wholesale Goods"
        }
    ],
    "sg:phone":"+1 323 581 7835",
    "sg:postcode":"90058",
    "sg:province":"CA",
    "sg:tags":[
        "equipment",
        "lighting",
        "system"
    ],
    "wof:name":"Montanez Custom Lighting",
    "wof:placetype":"venue"
},
  "geometry": {"coordinates":[-118.24118799999999,33.990465],"type":"Point"}
}