{
  "type": "Feature",
  "properties": {
    "addr:full":"2601 S Figueroa St Los Angeles CA 90007",
    "addr:housenumber":"2601",
    "addr:postcode":"90007",
    "addr:street":"S Figueroa St",
    "iso:country":"US",
    "sg:address":"2601 S Figueroa St",
    "sg:city":"Los Angeles",
    "sg:classifiers":[
        {
            "category":"Government",
            "subcategory":"Police Station",
            "type":"Public Place"
        }
    ],
    "sg:phone":"+1 213 763 5100",
    "sg:postcode":"90007",
    "sg:province":"CA",
    "sg:tags":[
        "protection"
    ],
    "wof:name":"Police Dept",
    "wof:placetype":"venue"
},
  "geometry": {"coordinates":[-118.276523,34.027336],"type":"Point"}
}