{
  "type": "Feature",
  "properties": {
    "addr:full":"736 Monterey Pass Rd Monterey Park CA 91754",
    "addr:housenumber":"736",
    "addr:postcode":"91754",
    "addr:street":"Monterey Pass Rd",
    "iso:country":"US",
    "sg:address":"736 Monterey Pass Rd",
    "sg:city":"Monterey Park",
    "sg:classifiers":[
        {
            "category":"Professional",
            "subcategory":"Business Services",
            "type":"Services"
        }
    ],
    "sg:phone":"+1 323 267 3217",
    "sg:postcode":"91754",
    "sg:province":"CA",
    "sg:tags":[
        "embroidery"
    ],
    "wof:name":"Designers Touch",
    "wof:placetype":"venue"
},
  "geometry": {"coordinates":[-118.160546,34.048876],"type":"Point"}
}