{
  "type": "Feature",
  "properties": {
    "addr:full":"12 Geary St San Francisco CA 94108",
    "addr:housenumber":"12",
    "addr:postcode":"94108",
    "addr:street":"Geary St",
    "iso:country":"US",
    "sg:address":"12 Geary St",
    "sg:city":"San Francisco",
    "sg:classifiers":[
        {
            "category":"Professional",
            "subcategory":"Business Services",
            "type":"Services"
        }
    ],
    "sg:phone":"+1 415 291 0273",
    "sg:postcode":"94108",
    "sg:province":"CA",
    "sg:tags":[
        "interior",
        "consultant",
        "design",
        "decorator"
    ],
    "sg:website":"www.clementmac.com",
    "wof:name":"Clement Mac",
    "wof:placetype":"venue"
},
  "geometry": {"coordinates":[-122.405041,37.787765],"type":"Point"}
}