{
  "type": "Feature",
  "properties": {
    "iso:country":"US",
    "sg:address":"4090 Broad St",
    "sg:city":"San Luis Obispo",
    "sg:classifiers":[
        {
            "category":"Retail",
            "subcategory":"Auto Repair",
            "type":"Services"
        }
    ],
    "sg:phone":"+1 805 541 2407",
    "sg:postcode":"93401",
    "sg:province":"CA",
    "sg:tags":[
        "repairing",
        "automobile"
    ],
    "wof:name":"Morin Brothers Foreign Auto",
    "wof:placetype":"venue"
},
  "geometry": {"coordinates":[-120.641508,35.245431],"type":"Point"}
}