{
  "type": "Feature",
  "properties": {
    "addr:full":"841 W Whittier Blvd La Habra CA 90631",
    "addr:housenumber":"841",
    "addr:postcode":"90631",
    "addr:street":"W Whittier Blvd",
    "iso:country":"US",
    "sg:address":"841 W Whittier Blvd",
    "sg:city":"La Habra",
    "sg:classifiers":[
        {
            "category":"Shopping",
            "subcategory":"Computers & Home Electronics",
            "type":"Retail Goods"
        }
    ],
    "sg:phone":"+1 562 697 6977",
    "sg:postcode":"90631",
    "sg:province":"CA",
    "sg:tags":[
        "equipment",
        "dealer"
    ],
    "wof:name":"Century Computer Systems",
    "wof:placetype":"venue"
},
  "geometry": {"coordinates":[-117.95242,33.939187],"type":"Point"}
}