{
  "type": "Feature",
  "properties": {
    "addr:full":"110 Biggs Ct Folsom CA 95630",
    "addr:housenumber":"110",
    "addr:postcode":"95630",
    "addr:street":"Biggs Ct",
    "iso:country":"US",
    "sg:address":"110 Biggs Ct",
    "sg:city":"Folsom",
    "sg:classifiers":[
        {
            "category":"Banks & Credit Unions",
            "subcategory":"Investment Brokerage",
            "type":"Services"
        }
    ],
    "sg:phone":"+1 916 984 9974",
    "sg:postcode":"95630",
    "sg:province":"CA",
    "sg:tags":[
        "consultant",
        "planning",
        "financial"
    ],
    "wof:name":"Smart Investor",
    "wof:placetype":"venue"
},
  "geometry": {"coordinates":[-121.144587,38.660796],"type":"Point"}
}