{
  "type": "Feature",
  "properties": {
    "iso:country":"US",
    "sg:address":"5610 Edgeview Dr",
    "sg:city":"Discovery Bay",
    "sg:classifiers":[
        {
            "category":"Building & Trades",
            "subcategory":"Construction",
            "type":"Services"
        }
    ],
    "sg:phone":"+1 925 516 2939",
    "sg:postcode":"94505",
    "sg:province":"CA",
    "sg:tags":[
        "concrete",
        "cutting",
        "breaking",
        "sawing"
    ],
    "wof:name":"T & A Asphalt Grinding",
    "wof:placetype":"venue"
},
  "geometry": {"coordinates":[-121.593626,37.902311],"type":"Point"}
}