{
  "type": "Feature",
  "properties": {
    "iso:country":"US",
    "sg:address":"3639 Midway Dr",
    "sg:city":"San Diego",
    "sg:classifiers":[
        {
            "category":"Personal",
            "subcategory":"Beauty Salon",
            "type":"Services"
        }
    ],
    "sg:phone":"+1 619 222 1169",
    "sg:postcode":"92110",
    "sg:province":"CA",
    "wof:name":"Shearpros Salon",
    "wof:placetype":"venue"
},
  "geometry": {"coordinates":[-117.217678,32.753581],"type":"Point"}
}