{
  "type": "Feature",
  "properties": {
    "iso:country":"US",
    "sg:address":"4114 Noriega St",
    "sg:city":"San Francisco",
    "sg:classifiers":[
        {
            "category":"Real Estate",
            "subcategory":"Real Estate Services",
            "type":"Services"
        },
        {
            "category":"Building & Trades",
            "subcategory":"Construction",
            "type":"Services"
        }
    ],
    "sg:phone":"+1 408 718 5070",
    "sg:postcode":"94122",
    "sg:province":"CA",
    "sg:tags":[
        "interior",
        "home",
        "design",
        "staging"
    ],
    "sg:website":"www.raquelinteriors.com",
    "wof:name":"Raquel Nayak Interiors",
    "wof:placetype":"venue"
},
  "geometry": {"coordinates":[-122.507921,37.753066],"type":"Point"}
}