{
  "type": "Feature",
  "properties": {
    "addr:full":"9828 Business Park Drive Sacramento CA 95827",
    "addr:housenumber":"9828",
    "addr:postcode":"95827",
    "addr:street":"Business Park Drive",
    "iso:country":"US",
    "sg:address":"9828 Business Park Drive",
    "sg:city":"Sacramento",
    "sg:classifiers":[
        {
            "category":"Education",
            "subcategory":"Special Training",
            "type":"Public Place"
        },
        {
            "category":"Education",
            "subcategory":"Vocational School",
            "type":"Public Place"
        }
    ],
    "sg:phone":"+1 916 366 1717",
    "sg:postcode":"95827",
    "sg:province":"CA",
    "sg:tags":[
        "educational",
        "business"
    ],
    "sg:website":"http://www.contractorschools.com",
    "wof:name":"License Instruction Schools",
    "wof:placetype":"venue"
},
  "geometry": {"coordinates":[-121.32879200000001,38.571194],"type":"Point"}
}