{
  "type": "Feature",
  "properties": {
    "iso:country":"US",
    "sg:address":"1835 W Steele Ln",
    "sg:city":"Santa Rosa",
    "sg:classifiers":[
        {
            "category":"Organizations",
            "subcategory":"Religious Organization",
            "type":"Services"
        }
    ],
    "sg:phone":"+1 707 571 1748",
    "sg:postcode":"95403",
    "sg:province":"CA",
    "sg:tags":[
        "church"
    ],
    "wof:name":"Santa Rosa Chinese Christian",
    "wof:placetype":"venue"
},
  "geometry": {"coordinates":[-122.735803,38.460057],"type":"Point"}
}