{
  "type": "Feature",
  "properties": {
    "addr:full":"2354 Andrade Ave Richmond CA 94804",
    "addr:housenumber":"2354",
    "addr:postcode":"94804",
    "addr:street":"Andrade Ave",
    "iso:country":"US",
    "sg:address":"2354 Andrade Ave",
    "sg:city":"Richmond",
    "sg:classifiers":[
        {
            "category":"Organizations",
            "subcategory":"Religious Organization",
            "type":"Services"
        }
    ],
    "sg:phone":"+1 510 243 9935",
    "sg:postcode":"94804",
    "sg:province":"CA",
    "sg:tags":[
        "church"
    ],
    "sg:website":"www.homechapel.com",
    "wof:name":"Harvest Chapel",
    "wof:placetype":"venue"
},
  "geometry": {"coordinates":[-122.346345,37.947692],"type":"Point"}
}