{
  "type": "Feature",
  "properties": {
    "iso:country":"US",
    "sg:address":"721 Oswell St",
    "sg:city":"Bakersfield",
    "sg:classifiers":[
        {
            "category":"Real Estate",
            "subcategory":"Real Estate Operator",
            "type":"Services"
        }
    ],
    "sg:phone":"+1 661 366 6331",
    "sg:postcode":"93306",
    "sg:province":"CA",
    "sg:tags":[
        "mobile",
        "home",
        "site",
        "community"
    ],
    "wof:name":"Black & White Mobile HM Lodge",
    "wof:placetype":"venue"
},
  "geometry": {"coordinates":[-118.949665,35.367329],"type":"Point"}
}