{
  "type": "Feature",
  "properties": {
    "iso:country":"US",
    "sg:address":"855 W Victoria St",
    "sg:city":"Compton",
    "sg:classifiers":[
        {
            "category":"Building & Trades",
            "subcategory":"Construction",
            "type":"Services"
        }
    ],
    "sg:phone":"+1 310 764 1500",
    "sg:postcode":"90220",
    "sg:province":"CA",
    "sg:tags":[
        "resurfacing",
        "laying",
        "refinishing",
        "floor"
    ],
    "wof:name":"Cvetko Installations",
    "wof:placetype":"venue"
},
  "geometry": {"coordinates":[-118.23794100000001,33.867934],"type":"Point"}
}