{
  "type": "Feature",
  "properties": {
    "iso:country":"US",
    "sg:address":"799 E El Camino Real",
    "sg:city":"Sunnyvale",
    "sg:classifiers":[
        {
            "category":"Personal",
            "subcategory":"Massage",
            "type":"Services"
        }
    ],
    "sg:phone":"+1 408 830 9000",
    "sg:postcode":"94087",
    "sg:province":"CA",
    "sg:website":"lavidamassage.com",
    "wof:name":"LaVida Massage",
    "wof:placetype":"venue"
},
  "geometry": {"coordinates":[-122.017758,37.355948],"type":"Point"}
}