{
  "type": "Feature",
  "properties": {
    "addr:full":"11221 Long Beach Boulevard Lynwood CA 90262",
    "addr:housenumber":"11221",
    "addr:postcode":"90262",
    "addr:street":"Long Beach Boulevard",
    "iso:country":"US",
    "sg:address":"11221 Long Beach Boulevard",
    "sg:city":"Lynwood",
    "sg:classifiers":[
        {
            "category":"Shopping",
            "subcategory":"Clothing, Apparel, & Fashions",
            "type":"Retail Goods"
        }
    ],
    "sg:phone":"+1 310 631 5625",
    "sg:postcode":"90262",
    "sg:province":"CA",
    "sg:tags":[
        "clothing",
        "store",
        "women's"
    ],
    "sg:website":"www.facebook.com/gstageclothing",
    "wof:name":"G Stage",
    "wof:placetype":"venue"
},
  "geometry": {"coordinates":[-118.211142,33.92934],"type":"Point"}
}