{
  "type": "Feature",
  "properties": {
    "addr:full":"2006 E el Segundo Blvd El Segundo CA 90245",
    "addr:housenumber":"2006",
    "addr:postcode":"90245",
    "addr:street":"E El Segundo Blvd",
    "iso:country":"US",
    "sg:address":"2006 E el Segundo Blvd",
    "sg:city":"El Segundo",
    "sg:classifiers":[
        {
            "category":"Retail",
            "subcategory":"Repair Shop",
            "type":"Services"
        }
    ],
    "sg:phone":"+1 310 616 1375",
    "sg:postcode":"90245",
    "sg:province":"CA",
    "sg:tags":[
        "technical",
        "support"
    ],
    "wof:name":"Raytheon",
    "wof:placetype":"venue"
},
  "geometry": {"coordinates":[-118.391108,33.916255],"type":"Point"}
}