{
  "type": "Feature",
  "properties": {
    "iso:country":"US",
    "sg:address":"7911 State St",
    "sg:city":"Huntington Park",
    "sg:classifiers":[
        {
            "category":"Shopping",
            "subcategory":"Computers & Home Electronics",
            "type":"Retail Goods"
        }
    ],
    "sg:phone":"+1 323 588 7762",
    "sg:postcode":"90255",
    "sg:province":"CA",
    "sg:tags":[
        "equipment",
        "dealer"
    ],
    "wof:name":"MYPC.COM",
    "wof:placetype":"venue"
},
  "geometry": {"coordinates":[-118.210794,33.964441],"type":"Point"}
}