{
  "type": "Feature",
  "properties": {
    "iso:country":"US",
    "sg:address":"8209 Melrose Ave",
    "sg:city":"Los Angeles",
    "sg:classifiers":[
        {
            "category":"Real Estate",
            "subcategory":"Architect",
            "type":"Services"
        }
    ],
    "sg:phone":"+1 323 651 3900",
    "sg:postcode":"90046",
    "sg:province":"CA",
    "wof:name":"OML Consultants Inc",
    "wof:placetype":"venue"
},
  "geometry": {"coordinates":[-118.368917,34.083776],"type":"Point"}
}