{
  "type": "Feature",
  "properties": {
    "addr:full":"3080 Stevens Creek Blvd San Jose CA 95128",
    "addr:housenumber":"3080",
    "addr:postcode":"95128",
    "addr:street":"Stevens Creek Blvd",
    "iso:country":"US",
    "sg:address":"3080 Stevens Creek Blvd",
    "sg:city":"San Jose",
    "sg:classifiers":[
        {
            "category":"Home & Garden",
            "subcategory":"Furniture",
            "type":"Retail Goods"
        }
    ],
    "sg:phone":"+1 408 261 8875",
    "sg:postcode":"95128",
    "sg:province":"CA",
    "wof:name":"Design With In Reach",
    "wof:placetype":"venue"
},
  "geometry": {"coordinates":[-121.94725699999999,37.323288],"type":"Point"}
}