{
  "type": "Feature",
  "properties": {
    "addr:full":"1700 Montgomery St San Francisco CA 94111",
    "addr:housenumber":"1700",
    "addr:postcode":"94111",
    "addr:street":"Montgomery St",
    "iso:country":"US",
    "sg:address":"1700 Montgomery St",
    "sg:city":"San Francisco",
    "sg:classifiers":[
        {
            "category":"Professional",
            "type":"Services"
        }
    ],
    "sg:phone":"+1 415 835 9466",
    "sg:postcode":"94111",
    "sg:province":"CA",
    "sg:tags":[
        "establishment"
    ],
    "wof:name":"Working Options",
    "wof:placetype":"venue"
},
  "geometry": {"coordinates":[-122.405357,37.805696],"type":"Point"}
}