{
  "type": "Feature",
  "properties": {
    "addr:full":"4071 Ave Sevilla Cypress CA 90630",
    "addr:housenumber":"4071",
    "addr:postcode":"90630",
    "addr:street":"Ave Sevilla",
    "iso:country":"US",
    "sg:address":"4071 Ave Sevilla",
    "sg:city":"Cypress",
    "sg:classifiers":[
        {
            "category":"Professional",
            "subcategory":"Employment Agencies",
            "type":"Services"
        }
    ],
    "sg:phone":"+1 714 816 0286",
    "sg:postcode":"90630",
    "sg:province":"CA",
    "sg:tags":[
        "opportunity"
    ],
    "wof:name":"O'Toole & O'Crowley",
    "wof:placetype":"venue"
},
  "geometry": {"coordinates":[-118.06199100000001,33.822695],"type":"Point"}
}