{
  "type": "Feature",
  "properties": {
    "iso:country":"US",
    "sg:address":"460 W 9th St",
    "sg:city":"San Bernardino",
    "sg:classifiers":[
        {
            "category":"Retail",
            "subcategory":"Auto Repair",
            "type":"Services"
        }
    ],
    "sg:phone":"+1 909 884 2803",
    "sg:postcode":"92401",
    "sg:province":"CA",
    "sg:tags":[
        "body",
        "automobile",
        "painting"
    ],
    "sg:website":"www.downtownautocenter.net",
    "wof:name":"Downtown Auto Ctr",
    "wof:placetype":"venue"
},
  "geometry": {"coordinates":[-117.292959,34.115875],"type":"Point"}
}