{
  "type": "Feature",
  "properties": {
    "addr:full":"2780 Tapo Canyon Rd Simi Valley CA 93063",
    "addr:housenumber":"2780",
    "addr:postcode":"93063",
    "addr:street":"Tapo Canyon Rd",
    "iso:country":"US",
    "sg:address":"2780 Tapo Canyon Rd",
    "sg:city":"Simi Valley",
    "sg:classifiers":[
        {
            "category":"Bars & Pubs",
            "type":"Food & Drink"
        }
    ],
    "sg:phone":"+1 805 526 0806",
    "sg:postcode":"93063",
    "sg:province":"CA",
    "sg:tags":[
        "lounge",
        "cocktail"
    ],
    "wof:name":"Judge Roy Bean's",
    "wof:placetype":"venue"
},
  "geometry": {"coordinates":[-118.71767,34.284784],"type":"Point"}
}