{
  "type": "Feature",
  "properties": {
    "iso:country":"US",
    "sg:address":"242 E Hospitality Ln",
    "sg:city":"San Bernardino",
    "sg:classifiers":[
        {
            "category":"Bakery",
            "type":"Food & Drink"
        }
    ],
    "sg:menulink":"http://www.allmenus.com/ca/san-bernardino/218713-cocos-bakery-restaurant/menu/",
    "sg:phone":"+1 909 381 3513",
    "sg:postcode":"92408",
    "sg:province":"CA",
    "sg:tags":[
        "sandwich",
        "salad",
        "soup",
        "american",
        "pastry",
        "wrap",
        "wing"
    ],
    "wof:name":"Coco's Bakery Restaurant",
    "wof:placetype":"venue"
},
  "geometry": {"coordinates":[-117.282736,34.066233],"type":"Point"}
}