{
  "type": "Feature",
  "properties": {
    "iso:country":"US",
    "sg:address":"7733 Starward Dr",
    "sg:city":"Dublin",
    "sg:classifiers":[
        {
            "category":"Manufacturing",
            "subcategory":"Retail Goods",
            "type":"Manufacturing & Wholesale Goods"
        }
    ],
    "sg:phone":"+1 925 828 2904",
    "sg:postcode":"94568",
    "sg:province":"CA",
    "sg:tags":[
        "product",
        "mfg"
    ],
    "wof:name":"Drums 2 Industries",
    "wof:placetype":"venue"
},
  "geometry": {"coordinates":[-121.936881,37.710123],"type":"Point"}
}