{
  "type": "Feature",
  "properties": {
    "iso:country":"US",
    "sg:address":"23704 el Toro Rd",
    "sg:city":"Lake Forest",
    "sg:classifiers":[
        {
            "category":"Professional",
            "subcategory":"Secretarial Services",
            "type":"Services"
        }
    ],
    "sg:phone":"+1 949 215 7290",
    "sg:postcode":"92630",
    "sg:province":"CA",
    "sg:tags":[
        "processing",
        "word"
    ],
    "wof:name":"Virtual Office Solutions",
    "wof:placetype":"venue"
},
  "geometry": {"coordinates":[-117.70313299999999,33.6183],"type":"Point"}
}