{
  "type": "Feature",
  "properties": {
    "iso:country":"US",
    "sg:address":"3299 Swetzer Rd",
    "sg:city":"Loomis",
    "sg:classifiers":[
        {
            "category":"Building & Trades",
            "subcategory":"Electrical",
            "type":"Services"
        }
    ],
    "sg:phone":"+1 916 652 3300",
    "sg:postcode":"95650",
    "sg:province":"CA",
    "sg:tags":[
        "electrician"
    ],
    "wof:name":"Sierra Foothills Electric Inc.",
    "wof:placetype":"venue"
},
  "geometry": {"coordinates":[-121.191742,38.831161],"type":"Point"}
}