{
  "type": "Feature",
  "properties": {
    "iso:country":"US",
    "sg:address":"25 Healdsburg Ave",
    "sg:city":"Healdsburg",
    "sg:classifiers":[
        {
            "category":"Retail",
            "subcategory":"Auto Rental",
            "type":"Services"
        }
    ],
    "sg:phone":"+1 707 431 7833",
    "sg:postcode":"95448",
    "sg:province":"CA",
    "sg:tags":[
        "renting",
        "truck",
        "leasing"
    ],
    "wof:name":"U-Haul Co",
    "wof:placetype":"venue"
},
  "geometry": {"coordinates":[-122.863034,38.603909],"type":"Point"}
}