{
  "type": "Feature",
  "properties": {
    "iso:country":"US",
    "sg:address":"5060 Hessel Ave",
    "sg:city":"Sebastopol",
    "sg:classifiers":[
        {
            "category":"Organizations",
            "subcategory":"Religious Organization",
            "type":"Services"
        }
    ],
    "sg:phone":"+1 707 823 8556",
    "sg:postcode":"95472",
    "sg:province":"CA",
    "sg:tags":[
        "church"
    ],
    "sg:website":"www.hessel.org",
    "wof:name":"Hessel Church",
    "wof:placetype":"venue"
},
  "geometry": {"coordinates":[-122.77972800000001,38.34746],"type":"Point"}
}