{
  "type": "Feature",
  "properties": {
    "addr:full":"14506 Olde Highway 80 El Cajon CA 92021",
    "addr:housenumber":"14506",
    "addr:postcode":"92021",
    "addr:street":"Olde Highway 80",
    "iso:country":"US",
    "sg:address":"14506 Olde Highway 80",
    "sg:city":"El Cajon",
    "sg:classifiers":[
        {
            "category":"Building & Trades",
            "subcategory":"Plumbing",
            "type":"Services"
        }
    ],
    "sg:phone":"+1 619 561 3055",
    "sg:postcode":"92021",
    "sg:province":"CA",
    "sg:tags":[
        "plumbing",
        "contractor"
    ],
    "wof:name":"Alexander Plumbing Co",
    "wof:placetype":"venue"
},
  "geometry": {"coordinates":[-116.866561,32.847881],"type":"Point"}
}