{
  "type": "Feature",
  "properties": {
    "addr:full":"401 Parnassus Ave San Francisco CA 94143",
    "addr:housenumber":"401",
    "addr:postcode":"94143",
    "addr:street":"Parnassus Ave",
    "iso:country":"US",
    "sg:address":"401 Parnassus Ave",
    "sg:city":"San Francisco",
    "sg:classifiers":[
        {
            "category":"Professional",
            "type":"Services"
        },
        {
            "category":"Community Center",
            "type":"Public Place"
        }
    ],
    "sg:phone":"+1 415 502 1576",
    "sg:postcode":"94143",
    "sg:province":"CA",
    "sg:tags":[
        "medical"
    ],
    "sg:website":"www.gcf.ucsf.edu/",
    "wof:name":"UCSF Genomics Core Facility",
    "wof:placetype":"venue"
},
  "geometry": {"coordinates":[-122.456655,37.763824],"type":"Point"}
}