{
  "type": "Feature",
  "properties": {
    "iso:country":"US",
    "sg:address":"1616 E Rock Creek Dr",
    "sg:city":"Orange",
    "sg:classifiers":[
        {
            "category":"Real Estate",
            "subcategory":"Real Estate Services",
            "type":"Services"
        },
        {
            "category":"Real Estate",
            "subcategory":"Real Estate Operator",
            "type":"Services"
        }
    ],
    "sg:phone":"+1 714 516 1900",
    "sg:postcode":"92866",
    "sg:province":"CA",
    "sg:tags":[
        "vacancy",
        "apartment",
        "rental",
        "listing"
    ],
    "sg:website":"http://www.tualatinview.com",
    "wof:name":"Harmony Creek Senior Apartments",
    "wof:placetype":"venue"
},
  "geometry": {"coordinates":[-117.83699799999999,33.779301],"type":"Point"}
}