{
  "type": "Feature",
  "properties": {
    "addr:full":"11668 Erwin St North Hollywood CA 91606",
    "addr:housenumber":"11668",
    "addr:postcode":"91606",
    "addr:street":"Erwin St",
    "iso:country":"US",
    "sg:address":"11668 Erwin St",
    "sg:city":"North Hollywood",
    "sg:classifiers":[
        {
            "category":"Manufacturing",
            "subcategory":"Printing",
            "type":"Manufacturing & Wholesale Goods"
        }
    ],
    "sg:phone":"+1 818 985 7871",
    "sg:postcode":"91606",
    "sg:province":"CA",
    "sg:tags":[
        "publishing"
    ],
    "wof:name":"Bendan Music",
    "wof:placetype":"venue"
},
  "geometry": {"coordinates":[-118.38690200000001,34.182966],"type":"Point"}
}