{
  "type": "Feature",
  "properties": {
    "addr:full":"2119 S 11th St Los Banos CA 93635",
    "addr:housenumber":"2119",
    "addr:postcode":"93635",
    "addr:street":"S 11Th St",
    "iso:country":"US",
    "sg:address":"2119 S 11th St",
    "sg:city":"Los Banos",
    "sg:classifiers":[
        {
            "category":"Shopping",
            "subcategory":"Catalog Store",
            "type":"Retail Goods"
        }
    ],
    "sg:phone":"+1 209 827 6366",
    "sg:postcode":"93635",
    "sg:province":"CA",
    "sg:tags":[
        "e"
    ],
    "wof:name":"EZSHOP-Site.Com",
    "wof:placetype":"venue"
},
  "geometry": {"coordinates":[-120.839479,37.04369],"type":"Point"}
}