{
  "type": "Feature",
  "properties": {
    "iso:country":"US",
    "sg:address":"500 E Esplanade Dr Fl 2",
    "sg:city":"Oxnard",
    "sg:classifiers":[
        {
            "category":"Banks & Credit Unions",
            "subcategory":"Bank",
            "type":"Services"
        }
    ],
    "sg:phone":"+1 805 981 2700",
    "sg:postcode":"93036",
    "sg:province":"CA",
    "sg:tags":[
        "saving",
        "commercial"
    ],
    "sg:website":"http://www.citynational.com",
    "wof:name":"City National Bank",
    "wof:placetype":"venue"
},
  "geometry": {"coordinates":[-119.17415,34.229648],"type":"Point"}
}