{
  "type": "Feature",
  "properties": {
    "addr:full":"515 W Kimball Ave Visalia CA 93277",
    "addr:housenumber":"515",
    "addr:postcode":"93277",
    "addr:street":"W Kimball Ave",
    "iso:country":"US",
    "sg:address":"515 W Kimball Ave",
    "sg:city":"Visalia",
    "sg:classifiers":[
        {
            "category":"Building & Trades",
            "subcategory":"Construction",
            "type":"Services"
        }
    ],
    "sg:phone":"+1 559 625 8500",
    "sg:postcode":"93277",
    "sg:province":"CA",
    "sg:tags":[
        "residential"
    ],
    "wof:name":"Machado & Pippin Development",
    "wof:placetype":"venue"
},
  "geometry": {"coordinates":[-119.298914,36.296921],"type":"Point"}
}