{
  "type": "Feature",
  "properties": {
    "addr:full":"852 5th Ave San Diego CA 92101",
    "addr:housenumber":"852",
    "addr:postcode":"92101",
    "addr:street":"5Th Ave",
    "iso:country":"US",
    "sg:address":"852 5th Ave",
    "sg:city":"San Diego",
    "sg:classifiers":[
        {
            "category":"Professional",
            "subcategory":"Advertising",
            "type":"Services"
        }
    ],
    "sg:phone":"+1 619 358 9829",
    "sg:postcode":"92101",
    "sg:province":"CA",
    "sg:tags":[
        "marketing"
    ],
    "sg:website":"constantmotioncm.com",
    "wof:name":"Constant Motion Creative Media",
    "wof:placetype":"venue"
},
  "geometry": {"coordinates":[-117.16029399999999,32.714408],"type":"Point"}
}