{
  "type": "Feature",
  "properties": {
    "iso:country":"US",
    "sg:address":"643 Chestnut Ave",
    "sg:city":"S San Francisco",
    "sg:classifiers":[
        {
            "category":"Local Transit",
            "type":"Transportation"
        }
    ],
    "sg:phone":"+1 650 327 1115",
    "sg:postcode":"94080",
    "sg:province":"CA",
    "sg:tags":[
        "airport"
    ],
    "sg:website":"www.legacylimousine.com",
    "wof:name":"Legacy Limousine & Sedan Svc",
    "wof:placetype":"venue"
},
  "geometry": {"coordinates":[-122.427759,37.666457],"type":"Point"}
}