{
  "type": "Feature",
  "properties": {
    "addr:full":"1646 Samar Pl Costa Mesa CA 92626",
    "addr:postcode":"1646;92626",
    "addr:street":"Samar Pl",
    "iso:country":"US",
    "sg:address":"1646 Samar Pl",
    "sg:city":"Costa Mesa",
    "sg:classifiers":[
        {
            "category":"Building & Trades",
            "subcategory":"Plumbing",
            "type":"Services"
        }
    ],
    "sg:phone":"+1 714 546 3792",
    "sg:postcode":"92626",
    "sg:province":"CA",
    "sg:tags":[
        "contractor"
    ],
    "wof:name":"All Seasons Sprinkler Service",
    "wof:placetype":"venue"
},
  "geometry": {"coordinates":[-117.92685299999999,33.676366],"type":"Point"}
}