{
  "type": "Feature",
  "properties": {
    "addr:full":"410 J St Marysville CA 95901",
    "addr:housenumber":"410",
    "addr:postcode":"95901",
    "addr:street":"J St",
    "iso:country":"US",
    "sg:address":"410 J St",
    "sg:city":"Marysville",
    "sg:classifiers":[
        {
            "category":"Social Services",
            "type":"Services"
        }
    ],
    "sg:phone":"+1 530 634 6060",
    "sg:postcode":"95901",
    "sg:province":"CA",
    "sg:tags":[
        "organization",
        "welfare"
    ],
    "wof:name":"Salvation Army Family Svc",
    "wof:placetype":"venue"
},
  "geometry": {"coordinates":[-121.596366,39.137406],"type":"Point"}
}