{
  "type": "Feature",
  "properties": {
    "iso:country":"US",
    "sg:address":"5801 S Hwy 1",
    "sg:city":"Elk",
    "sg:classifiers":[
        {
            "category":"Building & Trades",
            "subcategory":"Construction",
            "type":"Services"
        }
    ],
    "sg:phone":"+1 707 877 3296",
    "sg:postcode":"95432",
    "sg:province":"CA",
    "sg:tags":[
        "general",
        "contractor"
    ],
    "wof:name":"Mitchell Construction",
    "wof:placetype":"venue"
},
  "geometry": {"coordinates":[-123.717223,39.130239],"type":"Point"}
}