{
  "type": "Feature",
  "properties": {
    "addr:full":"340 Commerce Ste 200 Irvine CA 92602",
    "addr:housenumber":"340",
    "addr:postcode":"92602",
    "addr:street":"Commerce Ste 200",
    "iso:country":"US",
    "sg:address":"340 Commerce Ste 200",
    "sg:city":"Irvine",
    "sg:classifiers":[
        {
            "category":"Banks & Credit Unions",
            "subcategory":"Financial Services",
            "type":"Services"
        }
    ],
    "sg:phone":"+1 949 743 7210",
    "sg:postcode":"92602",
    "sg:province":"CA",
    "sg:tags":[
        "broker",
        "mortgage"
    ],
    "wof:name":"New Century Mortgage",
    "wof:placetype":"venue"
},
  "geometry": {"coordinates":[-117.786141,33.717155],"type":"Point"}
}