{
  "type": "Feature",
  "properties": {
    "iso:country":"US",
    "sg:address":"2340 Firestone Blvd",
    "sg:city":"South Gate",
    "sg:classifiers":[
        {
            "category":"Education",
            "subcategory":"University",
            "type":"Public Place"
        }
    ],
    "sg:phone":"+1 323 357 6200",
    "sg:postcode":"90280",
    "sg:province":"CA",
    "sg:tags":[
        "college"
    ],
    "wof:name":"East Los Angeles College",
    "wof:placetype":"venue"
},
  "geometry": {"coordinates":[-118.230003,33.957298],"type":"Point"}
}