{
  "type": "Feature",
  "properties": {
    "iso:country":"US",
    "sg:address":"3349 Sacramento St",
    "sg:city":"San Francisco",
    "sg:classifiers":[
        {
            "category":"Home & Garden",
            "subcategory":"Furniture",
            "type":"Retail Goods"
        }
    ],
    "sg:phone":"+1 415 922 3622",
    "sg:postcode":"94118",
    "sg:province":"CA",
    "wof:name":"Harvest Home Stores",
    "wof:placetype":"venue"
},
  "geometry": {"coordinates":[-122.447993,37.788005],"type":"Point"}
}