{
  "type": "Feature",
  "properties": {
    "iso:country":"US",
    "sg:address":"620 Moulton Ave Studio 104",
    "sg:city":"Los Angeles",
    "sg:classifiers":[
        {
            "category":"Arts & Performance",
            "subcategory":"Arts Center",
            "type":"Entertainment"
        },
        {
            "category":"Professional",
            "subcategory":"Art Services",
            "type":"Services"
        }
    ],
    "sg:phone":"+1 323 222 3238",
    "sg:postcode":"90031",
    "sg:province":"CA",
    "sg:tags":[
        "photographer"
    ],
    "sg:website":"www.taekphoto.com",
    "wof:name":"Taek Photography",
    "wof:placetype":"venue"
},
  "geometry": {"coordinates":[-118.217815,34.06489],"type":"Point"}
}