{
  "type": "Feature",
  "properties": {
    "addr:full":"2761 Mission St San Francisco CA 94110",
    "addr:housenumber":"2761",
    "addr:postcode":"94110",
    "addr:street":"Mission St",
    "iso:country":"US",
    "sg:address":"2761 Mission St",
    "sg:city":"San Francisco",
    "sg:classifiers":[
        {
            "category":"Retail",
            "subcategory":"Photofinishing",
            "type":"Services"
        }
    ],
    "sg:phone":"+1 415 285 8678",
    "sg:postcode":"94110",
    "sg:province":"CA",
    "sg:tags":[
        "photo",
        "finishing"
    ],
    "wof:name":"Sapphire Photo Inc",
    "wof:placetype":"venue"
},
  "geometry": {"coordinates":[-122.418442,37.753223],"type":"Point"}
}