{
  "type": "Feature",
  "properties": {
    "iso:country":"US",
    "sg:address":"23251 Cypress Pt Ct",
    "sg:city":"Auburn",
    "sg:classifiers":[
        {
            "category":"Building & Trades",
            "subcategory":"Construction",
            "type":"Services"
        }
    ],
    "sg:phone":"+1 530 268 9093",
    "sg:postcode":"95602",
    "sg:province":"CA",
    "sg:tags":[
        "project"
    ],
    "wof:name":"Sierra Monte Development Co",
    "wof:placetype":"venue"
},
  "geometry": {"coordinates":[-121.067115,39.044793],"type":"Point"}
}