{
  "type": "Feature",
  "properties": {
    "addr:full":"5401 W Sunset Blvd Los Angeles CA 90027",
    "addr:housenumber":"5401",
    "addr:postcode":"90027",
    "addr:street":"W Sunset Blvd",
    "iso:country":"US",
    "sg:address":"5401 W Sunset Blvd",
    "sg:city":"Los Angeles",
    "sg:classifiers":[
        {
            "category":"Shopping",
            "subcategory":"Clothing, Apparel, & Fashions",
            "type":"Retail Goods"
        }
    ],
    "sg:phone":"+1 323 467 4437",
    "sg:postcode":"90027",
    "sg:province":"CA",
    "sg:tags":[
        "men's",
        "clothing",
        "accessory",
        "women's"
    ],
    "wof:name":"Sunset T-Shirts Warehouse",
    "wof:placetype":"venue"
},
  "geometry": {"coordinates":[-118.307095,34.098096],"type":"Point"}
}