{
  "type": "Feature",
  "properties": {
    "addr:full":"603 North La Brea Avenue Los Angeles CA 90036",
    "addr:housenumber":"603",
    "addr:postcode":"90036",
    "addr:street":"North La Brea Avenue",
    "iso:country":"US",
    "sg:address":"603 North La Brea Avenue",
    "sg:city":"Los Angeles",
    "sg:classifiers":[
        {
            "category":"Arts & Performance",
            "subcategory":"Art Gallery",
            "type":"Entertainment"
        }
    ],
    "sg:postcode":"90036",
    "sg:province":"CA",
    "wof:name":"Project Space",
    "wof:placetype":"venue"
},
  "geometry": {"coordinates":[-118.344066,34.081915],"type":"Point"}
}