{
  "type": "Feature",
  "properties": {
    "addr:full":"1523 W Struck Ave Orange CA 92867",
    "addr:housenumber":"1523",
    "addr:postcode":"92867",
    "addr:street":"W Struck Ave",
    "iso:country":"US",
    "sg:address":"1523 W Struck Ave",
    "sg:city":"Orange",
    "sg:classifiers":[
        {
            "category":"Shopping",
            "subcategory":"Antiques",
            "type":"Retail Goods"
        }
    ],
    "sg:phone":"+1 714 516 1200",
    "sg:postcode":"92867",
    "sg:province":"CA",
    "wof:name":"Master Mechanic",
    "wof:placetype":"venue"
},
  "geometry": {"coordinates":[-117.86833,33.806177],"type":"Point"}
}