{
  "type": "Feature",
  "properties": {
    "addr:full":"135 Vermont St San Francisco CA 94103",
    "addr:housenumber":"135",
    "addr:postcode":"94103",
    "addr:street":"Vermont St",
    "iso:country":"US",
    "sg:address":"135 Vermont St",
    "sg:city":"San Francisco",
    "sg:classifiers":[
        {
            "category":"Home & Garden",
            "subcategory":"Carpets & Floor Coverings",
            "type":"Retail Goods"
        }
    ],
    "sg:phone":"+1 415 553 8504",
    "sg:postcode":"94103",
    "sg:province":"CA",
    "sg:tags":[
        "dealer",
        "rug"
    ],
    "wof:name":"Aga John Oriental Rugs",
    "wof:placetype":"venue"
},
  "geometry": {"coordinates":[-122.40470999999999,37.767704],"type":"Point"}
}