{
  "type": "Feature",
  "properties": {
    "iso:country":"US",
    "sg:address":"810 Winslow St",
    "sg:city":"Redwood City",
    "sg:classifiers":[
        {
            "category":"Government",
            "subcategory":"Office",
            "type":"Public Place"
        }
    ],
    "sg:phone":"+1 650 000 1111",
    "sg:postcode":"94063",
    "sg:province":"CA",
    "sg:tags":[
        "federal",
        "human"
    ],
    "wof:name":"US Social Security Adm",
    "wof:placetype":"venue"
},
  "geometry": {"coordinates":[-122.230908,37.485638],"type":"Point"}
}