{
  "type": "Feature",
  "properties": {
    "iso:country":"US",
    "sg:address":"3631 Broadway St",
    "sg:city":"American Canyon",
    "sg:classifiers":[
        {
            "category":"Wholesale",
            "subcategory":"Construction Materials",
            "type":"Manufacturing & Wholesale Goods"
        }
    ],
    "sg:phone":"+1 707 643 6321",
    "sg:postcode":"94503",
    "sg:province":"CA",
    "sg:tags":[
        "rock"
    ],
    "wof:name":"Broadway Landscape Material",
    "wof:placetype":"venue"
},
  "geometry": {"coordinates":[-122.25448,38.176978],"type":"Point"}
}