{
  "type": "Feature",
  "properties": {
    "addr:full":"3330 Main St Oakley CA 94561",
    "addr:housenumber":"3330",
    "addr:postcode":"94561",
    "addr:street":"Main St",
    "iso:country":"US",
    "sg:address":"3330 Main St",
    "sg:city":"Oakley",
    "sg:classifiers":[
        {
            "category":"Shopping",
            "subcategory":"Tobacco",
            "type":"Retail Goods"
        }
    ],
    "sg:phone":"+1 925 679 8311",
    "sg:postcode":"94561",
    "sg:province":"CA",
    "sg:tags":[
        "cigarette",
        "cigar",
        "dealer"
    ],
    "wof:name":"Cigarettes For Less",
    "wof:placetype":"venue"
},
  "geometry": {"coordinates":[-121.71588,37.997878],"type":"Point"}
}