{
  "type": "Feature",
  "properties": {
    "iso:country":"US",
    "sg:address":"1639 S China Lake Blvd",
    "sg:city":"Ridgecrest",
    "sg:classifiers":[
        {
            "category":"Wholesale",
            "subcategory":"Auto Parts",
            "type":"Manufacturing & Wholesale Goods"
        }
    ],
    "sg:phone":"+1 760 371 4026",
    "sg:postcode":"93555",
    "sg:province":"CA",
    "sg:tags":[
        "truck",
        "accessory"
    ],
    "wof:name":"Check Point Truck & Auto",
    "wof:placetype":"venue"
},
  "geometry": {"coordinates":[-117.687682,35.595796],"type":"Point"}
}