{
  "type": "Feature",
  "properties": {
    "addr:full":"1231 Cabrillo Ave Ste 201 Torrance CA 90501",
    "addr:housenumber":"1231",
    "addr:postcode":"90501",
    "addr:street":"Cabrillo Ave Ste 201",
    "iso:country":"US",
    "sg:address":"1231 Cabrillo Ave Ste 201",
    "sg:city":"Torrance",
    "sg:classifiers":[
        {
            "category":"Education",
            "subcategory":"University",
            "type":"Public Place"
        }
    ],
    "sg:phone":"+1 310 320 3200",
    "sg:postcode":"90501",
    "sg:province":"CA",
    "sg:tags":[
        "college"
    ],
    "wof:name":"Bryman College",
    "wof:placetype":"venue"
},
  "geometry": {"coordinates":[-118.31500200000001,33.835899],"type":"Point"}
}