{
  "type": "Feature",
  "properties": {
    "iso:country":"US",
    "sg:address":"750 Casserly Rd",
    "sg:city":"Watsonville",
    "sg:classifiers":[
        {
            "category":"Wholesale",
            "subcategory":"Farm Supplies",
            "type":"Manufacturing & Wholesale Goods"
        }
    ],
    "sg:phone":"+1 831 768 3830",
    "sg:postcode":"95076",
    "sg:province":"CA",
    "wof:name":"Reed Mariculture Inc",
    "wof:placetype":"venue"
},
  "geometry": {"coordinates":[-121.75115599999999,36.975418],"type":"Point"}
}