{
  "type": "Feature",
  "properties": {
    "iso:country":"US",
    "sg:address":"39 Linda Isle",
    "sg:city":"Newport Beach",
    "sg:classifiers":[
        {
            "category":"Banks & Credit Unions",
            "subcategory":"Investment Brokerage",
            "type":"Services"
        }
    ],
    "sg:phone":"+1 949 955 9213",
    "sg:postcode":"92660",
    "sg:province":"CA",
    "sg:tags":[
        "advisory"
    ],
    "wof:name":"Elliott Investment Co Inc",
    "wof:placetype":"venue"
},
  "geometry": {"coordinates":[-117.903727,33.612653],"type":"Point"}
}