{
  "type": "Feature",
  "properties": {
    "iso:country":"US",
    "sg:address":"3066 Lake Tahoe Blvd",
    "sg:city":"South Lake Tahoe",
    "sg:classifiers":[
        {
            "category":"Social Services",
            "type":"Services"
        }
    ],
    "sg:phone":"+1 530 544 5560",
    "sg:postcode":"96150",
    "sg:province":"CA",
    "sg:tags":[
        "employee",
        "assistance",
        "program"
    ],
    "wof:name":"Tahoe Employee Assistance",
    "wof:placetype":"venue"
},
  "geometry": {"coordinates":[-119.977137,38.939571],"type":"Point"}
}