{
  "type": "Feature",
  "properties": {
    "addr:full":"97 Fox Holw Irvine CA 92614",
    "addr:housenumber":"97",
    "addr:postcode":"92614",
    "addr:street":"Fox Holw",
    "iso:country":"US",
    "sg:address":"97 Fox Holw",
    "sg:city":"Irvine",
    "sg:classifiers":[
        {
            "category":"Shopping",
            "subcategory":"Pets & Pet Supplies",
            "type":"Retail Goods"
        },
        {
            "category":"Retail",
            "subcategory":"Pet Boarding",
            "type":"Services"
        }
    ],
    "sg:phone":"+1 714 541 3647",
    "sg:postcode":"92614",
    "sg:province":"CA",
    "sg:tags":[
        "boarding/pet",
        "groomers",
        "sitting"
    ],
    "wof:name":"Uptown Paw Resort & Spa",
    "wof:placetype":"venue"
},
  "geometry": {"coordinates":[-117.815119,33.674369],"type":"Point"}
}