{
  "type": "Feature",
  "properties": {
    "iso:country":"US",
    "sg:address":"555 E Evelyn Ave edgar at simplecarz.com",
    "sg:city":"Mountain View",
    "sg:classifiers":[
        {
            "category":"Autos & Motor Vehicles",
            "subcategory":"Automobile Sales",
            "type":"Retail Goods"
        },
        {
            "category":"Autos & Motor Vehicles",
            "subcategory":"Auto Supplies",
            "type":"Retail Goods"
        },
        {
            "category":"Retail",
            "subcategory":"Auto Repair",
            "type":"Services"
        }
    ],
    "sg:phone":"+1 888 588 2279",
    "sg:postcode":"94041",
    "sg:province":"CA",
    "sg:tags":[
        "glass",
        "detailing",
        "car"
    ],
    "wof:name":"SimpleCarz",
    "wof:placetype":"venue"
},
  "geometry": {"coordinates":[-122.056534,37.386832],"type":"Point"}
}