{
  "type": "Feature",
  "properties": {
    "addr:full":"110 Sutter St San Francisco CA 94104",
    "addr:housenumber":"110",
    "addr:postcode":"94104",
    "addr:street":"Sutter St",
    "iso:country":"US",
    "sg:address":"110 Sutter St",
    "sg:city":"San Francisco",
    "sg:classifiers":[
        {
            "category":"Professional",
            "type":"Services"
        }
    ],
    "sg:phone":"+1 415 296 8265",
    "sg:postcode":"94104",
    "sg:province":"CA",
    "sg:tags":[
        "establishment"
    ],
    "wof:name":"Zev Enterprises",
    "wof:placetype":"venue"
},
  "geometry": {"coordinates":[-122.40276900000001,37.789966],"type":"Point"}
}