{
  "type": "Feature",
  "properties": {
    "addr:full":"2341 W Sandy Ave Caruthers CA 93609",
    "addr:housenumber":"2341",
    "addr:postcode":"93609",
    "addr:street":"W Sandy Ave",
    "iso:country":"US",
    "sg:address":"2341 W Sandy Ave",
    "sg:city":"Caruthers",
    "sg:classifiers":[
        {
            "category":"Organizations",
            "subcategory":"Religious Organization",
            "type":"Services"
        }
    ],
    "sg:phone":"+1 559 864 3129",
    "sg:postcode":"93609",
    "sg:province":"CA",
    "sg:tags":[
        "church"
    ],
    "wof:name":"Church Of Christ",
    "wof:placetype":"venue"
},
  "geometry": {"coordinates":[-119.83249600000001,36.539002],"type":"Point"}
}