{
  "type": "Feature",
  "properties": {
    "iso:country":"US",
    "sg:address":"709 S K St",
    "sg:city":"Tulare",
    "sg:classifiers":[
        {
            "category":"Travel",
            "subcategory":"Hotels & Motels",
            "type":"Entertainment"
        }
    ],
    "sg:phone":"+1 559 686 6409",
    "sg:postcode":"93274",
    "sg:province":"CA",
    "wof:name":"Virginia Motor Lodge",
    "wof:placetype":"venue"
},
  "geometry": {"coordinates":[-119.344419,36.200316],"type":"Point"}
}