{
  "type": "Feature",
  "properties": {
    "iso:country":"US",
    "sg:address":"10936 Strathern St",
    "sg:city":"Sun Valley",
    "sg:classifiers":[
        {
            "category":"Professional",
            "subcategory":"Computer Services",
            "type":"Services"
        }
    ],
    "sg:phone":"+1 818 503 5994",
    "sg:postcode":"91352",
    "sg:province":"CA",
    "sg:tags":[
        "repair"
    ],
    "wof:name":"Cyber PC Repair",
    "wof:placetype":"venue"
},
  "geometry": {"coordinates":[-118.36933399999999,34.215555],"type":"Point"}
}