{
  "type": "Feature",
  "properties": {
    "addr:full":"9337 Telegraph Rd Pico Rivera CA 90660",
    "addr:housenumber":"9337",
    "addr:postcode":"90660",
    "addr:street":"Telegraph Rd",
    "iso:country":"US",
    "sg:address":"9337 Telegraph Rd",
    "sg:city":"Pico Rivera",
    "sg:classifiers":[
        {
            "category":"Travel",
            "subcategory":"Hotels & Motels",
            "type":"Entertainment"
        }
    ],
    "sg:phone":"+1 562 949 7390",
    "sg:postcode":"90660",
    "sg:province":"CA",
    "wof:name":"Tampico Motel",
    "wof:placetype":"venue"
},
  "geometry": {"coordinates":[-118.103996,33.956902],"type":"Point"}
}