{
  "type": "Feature",
  "properties": {
    "iso:country":"US",
    "sg:address":"1361 Titan Way",
    "sg:city":"Brea",
    "sg:classifiers":[
        {
            "category":"Manufacturing",
            "subcategory":"Metals",
            "type":"Manufacturing & Wholesale Goods"
        }
    ],
    "sg:phone":"+1 714 871 6110",
    "sg:postcode":"92821",
    "sg:province":"CA",
    "sg:tags":[
        "shop",
        "die",
        "tool",
        "stamping"
    ],
    "wof:name":"Jamar Tool Inc",
    "wof:placetype":"venue"
},
  "geometry": {"coordinates":[-117.920313,33.9196],"type":"Point"}
}