{
  "type": "Feature",
  "properties": {
    "iso:country":"US",
    "sg:address":"5911 Ostrander Rd",
    "sg:city":"Oakland",
    "sg:classifiers":[
        {
            "category":"Shopping",
            "subcategory":"Clothing, Apparel, & Fashions",
            "type":"Retail Goods"
        }
    ],
    "sg:phone":"+1 510 655 7294",
    "sg:postcode":"94618",
    "sg:province":"CA",
    "sg:tags":[
        "designer"
    ],
    "wof:name":"Gloria Walsh",
    "wof:placetype":"venue"
},
  "geometry": {"coordinates":[-122.23635400000001,37.842082],"type":"Point"}
}