{
  "type": "Feature",
  "properties": {
    "iso:country":"US",
    "sg:address":"4225 Spencer St",
    "sg:city":"Torrance",
    "sg:classifiers":[
        {
            "category":"Building & Trades",
            "subcategory":"Construction",
            "type":"Services"
        }
    ],
    "sg:phone":"+1 310 370 8100",
    "sg:postcode":"90503",
    "sg:province":"CA",
    "sg:tags":[
        "carpentry",
        "contractor",
        "furniture"
    ],
    "wof:name":"Conlaz Woodworking",
    "wof:placetype":"venue"
},
  "geometry": {"coordinates":[-118.35937300000001,33.845062],"type":"Point"}
}