{
  "type": "Feature",
  "properties": {
    "addr:full":"81778 Ave 46 Indio CA 92201",
    "addr:housenumber":"81778",
    "addr:postcode":"92201",
    "addr:street":"Ave 46",
    "iso:country":"US",
    "sg:address":"81778 Ave 46",
    "sg:city":"Indio",
    "sg:classifiers":[
        {
            "category":"Retail",
            "subcategory":"Laundry & Dry Cleaning",
            "type":"Services"
        }
    ],
    "sg:phone":"+1 760 347 2303",
    "sg:postcode":"92201",
    "sg:province":"CA",
    "sg:tags":[
        "cleaners"
    ],
    "wof:name":"Marshall's Fashion Cleaners",
    "wof:placetype":"venue"
},
  "geometry": {"coordinates":[-116.237585,33.714849],"type":"Point"}
}