{
  "type": "Feature",
  "properties": {
    "iso:country":"US",
    "sg:address":"841 N Branciforte Ave",
    "sg:city":"Santa Cruz",
    "sg:classifiers":[
        {
            "category":"Restaurant",
            "type":"Food & Drink"
        }
    ],
    "sg:phone":"+1 831 426 5955",
    "sg:postcode":"95062",
    "sg:province":"CA",
    "sg:tags":[
        "pizza"
    ],
    "wof:name":"Joe's Pizza and Subs",
    "wof:placetype":"venue"
},
  "geometry": {"coordinates":[-122.014,36.980499],"type":"Point"}
}