{
  "type": "Feature",
  "properties": {
    "addr:full":"18151 Vintage St Northridge CA 91325",
    "addr:housenumber":"18151",
    "addr:postcode":"91325",
    "addr:street":"Vintage St",
    "iso:country":"US",
    "sg:address":"18151 Vintage St",
    "sg:city":"Northridge",
    "sg:classifiers":[
        {
            "category":"Banks & Credit Unions",
            "subcategory":"Investment Brokerage",
            "type":"Services"
        }
    ],
    "sg:phone":"+1 818 885 9100",
    "sg:postcode":"91325",
    "sg:province":"CA",
    "sg:tags":[
        "advisory",
        "financial"
    ],
    "wof:name":"Patterson Financial",
    "wof:placetype":"venue"
},
  "geometry": {"coordinates":[-118.528721,34.2519],"type":"Point"}
}