{
  "type": "Feature",
  "properties": {
    "iso:country":"US",
    "sg:address":"7779 Garvey Ave",
    "sg:city":"Rosemead",
    "sg:classifiers":[
        {
            "category":"Restaurant",
            "type":"Food & Drink"
        }
    ],
    "sg:menulink":"http://www.allmenus.com/ca/southwest-san-gabriel-valley/78706-pizza-hut/menu/",
    "sg:phone":"+1 626 307 5533",
    "sg:postcode":"91770",
    "sg:province":"CA",
    "sg:tags":[
        "american",
        "pizza"
    ],
    "wof:name":"Pizza Hut",
    "wof:placetype":"venue"
},
  "geometry": {"coordinates":[-118.09969700000001,34.062919],"type":"Point"}
}