{
  "type": "Feature",
  "properties": {
    "addr:full":"222 Front St San Francisco CA 94111",
    "addr:housenumber":"222",
    "addr:postcode":"94111",
    "addr:street":"Front St",
    "iso:country":"US",
    "sg:address":"222 Front St",
    "sg:city":"San Francisco",
    "sg:classifiers":[
        {
            "category":"Real Estate",
            "subcategory":"Real Estate Agent",
            "type":"Services"
        }
    ],
    "sg:phone":"+1 415 658 0830",
    "sg:postcode":"94111",
    "sg:province":"CA",
    "sg:tags":[
        "relocation"
    ],
    "wof:name":"Oakwood Corporate Housing",
    "wof:placetype":"venue"
},
  "geometry": {"coordinates":[-122.39877,37.793633],"type":"Point"}
}