{
  "type": "Feature",
  "properties": {
    "iso:country":"US",
    "sg:address":"296 Great Mall Dr",
    "sg:city":"Milpitas",
    "sg:classifiers":[
        {
            "category":"Restaurant",
            "type":"Food & Drink"
        }
    ],
    "sg:phone":"+1 408 263 0582",
    "sg:postcode":"95035",
    "sg:province":"CA",
    "sg:tags":[
        "yogurt",
        "frozen",
        "parlor",
        "ice",
        "cream"
    ],
    "wof:name":"Dreyer's Grand Ice Cream",
    "wof:placetype":"venue"
},
  "geometry": {"coordinates":[-121.898101,37.419335],"type":"Point"}
}