{
  "type": "Feature",
  "properties": {
    "addr:full":"1345 S Harbor Blvd Fullerton CA 92832",
    "addr:housenumber":"1345",
    "addr:postcode":"92832",
    "addr:street":"S Harbor Blvd",
    "iso:country":"US",
    "sg:address":"1345 S Harbor Blvd",
    "sg:city":"Fullerton",
    "sg:classifiers":[
        {
            "category":"Utilities",
            "subcategory":"Mobile Phone",
            "type":"Services"
        },
        {
            "category":"Shopping",
            "subcategory":"Mobile Phones",
            "type":"Retail Goods"
        },
        {
            "category":"Communications",
            "type":"Services"
        },
        {
            "category":"Internet Cafe",
            "subcategory":"None",
            "type":"Food & Drink"
        }
    ],
    "sg:phone":"+1 714 870 9912",
    "sg:postcode":"92832",
    "sg:province":"CA",
    "sg:tags":[
        "supply",
        "telephone",
        "wireless",
        "equipment",
        "paging",
        "signaling",
        "cellular",
        "provider"
    ],
    "sg:website":"www.wireless.att.com",
    "wof:name":"AT&T",
    "wof:placetype":"venue"
},
  "geometry": {"coordinates":[-117.924525,33.858365],"type":"Point"}
}