{
  "type": "Feature",
  "properties": {
    "addr:full":"815 Tilden Dr Lodi CA 95242",
    "addr:housenumber":"815",
    "addr:postcode":"95242",
    "addr:street":"Tilden Dr",
    "iso:country":"US",
    "sg:address":"815 Tilden Dr",
    "sg:city":"Lodi",
    "sg:classifiers":[
        {
            "category":"Real Estate",
            "subcategory":"Developer",
            "type":"Services"
        }
    ],
    "sg:phone":"+1 209 334 3881",
    "sg:postcode":"95242",
    "sg:province":"CA",
    "wof:name":"K J Development & Design",
    "wof:placetype":"venue"
},
  "geometry": {"coordinates":[-121.29993,38.124767],"type":"Point"}
}