{
  "type": "Feature",
  "properties": {
    "addr:full":"8916 Quail Brook Ct Bakersfield CA 93312",
    "addr:housenumber":"8916",
    "addr:postcode":"93312",
    "addr:street":"Quail Brook Ct",
    "iso:country":"US",
    "sg:address":"8916 Quail Brook Ct",
    "sg:city":"Bakersfield",
    "sg:classifiers":[
        {
            "category":"Professional",
            "subcategory":"Management & Consulting",
            "type":"Services"
        },
        {
            "category":"Professional",
            "subcategory":"Engineering",
            "type":"Services"
        }
    ],
    "sg:phone":"+1 661 589 8046",
    "sg:postcode":"93312",
    "sg:province":"CA",
    "sg:tags":[
        "environmental",
        "ecological",
        "engineer",
        "consultant"
    ],
    "wof:name":"Matrix Process Systems Inc",
    "wof:placetype":"venue"
},
  "geometry": {"coordinates":[-119.10189099999999,35.426351],"type":"Point"}
}