{
  "type": "Feature",
  "properties": {
    "addr:full":"1540 W Glenoaks Blvd Glendale CA 91201",
    "addr:housenumber":"1540",
    "addr:postcode":"91201",
    "addr:street":"W Glenoaks Blvd",
    "iso:country":"US",
    "sg:address":"1540 W Glenoaks Blvd",
    "sg:city":"Glendale",
    "sg:classifiers":[
        {
            "category":"Banks & Credit Unions",
            "subcategory":"Financial Services",
            "type":"Services"
        }
    ],
    "sg:phone":"+1 818 247 8001",
    "sg:postcode":"91201",
    "sg:province":"CA",
    "sg:tags":[
        "broker",
        "mortgage"
    ],
    "wof:name":"Milbank Mortgage Corporation",
    "wof:placetype":"venue"
},
  "geometry": {"coordinates":[-118.287003,34.1688],"type":"Point"}
}