{
  "type": "Feature",
  "properties": {
    "addr:full":"11514 Humber Dr Mira Loma CA 91752",
    "addr:housenumber":"11514",
    "addr:postcode":"91752",
    "addr:street":"Humber Dr",
    "iso:country":"US",
    "sg:address":"11514 Humber Dr",
    "sg:city":"Mira Loma",
    "sg:classifiers":[
        {
            "category":"Building & Trades",
            "subcategory":"Construction",
            "type":"Services"
        }
    ],
    "sg:phone":"+1 951 361 2244",
    "sg:postcode":"91752",
    "sg:province":"CA",
    "sg:tags":[
        "contractor"
    ],
    "wof:name":"Jr Sign Service",
    "wof:placetype":"venue"
},
  "geometry": {"coordinates":[-117.534443,33.991642],"type":"Point"}
}