{
  "type": "Feature",
  "properties": {
    "addr:full":"1340 E Olympic Boulevard Los Angeles CA 90021",
    "addr:housenumber":"1340",
    "addr:postcode":"90021",
    "addr:street":"E Olympic Boulevard",
    "iso:country":"US",
    "sg:address":"1340 E Olympic Boulevard",
    "sg:city":"Los Angeles",
    "sg:classifiers":[
        {
            "category":"Wholesale",
            "subcategory":"Fruits & Vegetables",
            "type":"Manufacturing & Wholesale Goods"
        }
    ],
    "sg:phone":"+1 213 622 7619",
    "sg:postcode":"90021",
    "sg:province":"CA",
    "sg:tags":[
        "veggie"
    ],
    "wof:name":"Casa Lupe Produce Corporation",
    "wof:placetype":"venue"
},
  "geometry": {"coordinates":[-118.24370500000001,34.031514],"type":"Point"}
}