{
  "type": "Feature",
  "properties": {
    "addr:full":"1091 el Camino Real Menlo Park CA 94025",
    "addr:housenumber":"1091",
    "addr:postcode":"94025",
    "addr:street":"El Camino Real",
    "iso:country":"US",
    "sg:address":"1091 el Camino Real",
    "sg:city":"Menlo Park",
    "sg:classifiers":[
        {
            "category":"Shopping",
            "subcategory":"Music",
            "type":"Retail Goods"
        }
    ],
    "sg:phone":"+1 650 365 7468",
    "sg:postcode":"94025",
    "sg:province":"CA",
    "sg:tags":[
        "compact",
        "record",
        "disc",
        "tape"
    ],
    "wof:name":"Wherehouse Music",
    "wof:placetype":"venue"
},
  "geometry": {"coordinates":[-122.181907,37.452926],"type":"Point"}
}