{
  "type": "Feature",
  "properties": {
    "iso:country":"US",
    "sg:address":"1221 E 4th St",
    "sg:city":"Ontario",
    "sg:classifiers":[
        {
            "category":"Utilities",
            "subcategory":"Telephone",
            "type":"Services"
        }
    ],
    "sg:phone":"+1 909 635 1919",
    "sg:postcode":"91764",
    "sg:province":"CA",
    "sg:tags":[
        "telecommunication"
    ],
    "wof:name":"Leon Telecom",
    "wof:placetype":"venue"
},
  "geometry": {"coordinates":[-117.629688,34.078059],"type":"Point"}
}