{
  "type": "Feature",
  "properties": {
    "iso:country":"US",
    "sg:address":"5050 York Blvd",
    "sg:city":"Los Angeles",
    "sg:classifiers":[
        {
            "category":"Shopping",
            "type":"Retail Goods"
        }
    ],
    "sg:phone":"+1 323 957 3340",
    "sg:postcode":"90042",
    "sg:province":"CA",
    "sg:tags":[
        "cosmetic",
        "perfume"
    ],
    "wof:name":"Laboratorios MALLO",
    "wof:placetype":"venue"
},
  "geometry": {"coordinates":[-118.205673,34.121204],"type":"Point"}
}