{
  "type": "Feature",
  "properties": {
    "iso:country":"US",
    "sg:address":"17230 Norwalk Blvd",
    "sg:city":"Cerritos",
    "sg:classifiers":[
        {
            "category":"Shopping",
            "subcategory":"Tobacco",
            "type":"Retail Goods"
        }
    ],
    "sg:phone":"+1 562 860 2477",
    "sg:postcode":"90703",
    "sg:province":"CA",
    "sg:tags":[
        "shop",
        "cigarette",
        "cigar"
    ],
    "wof:name":"A 1 Tobacco",
    "wof:placetype":"venue"
},
  "geometry": {"coordinates":[-118.072998,33.874199],"type":"Point"}
}