{
  "type": "Feature",
  "properties": {
    "addr:full":"502 S Palmetto Ave Ontario CA 91762",
    "addr:housenumber":"502",
    "addr:postcode":"91762",
    "addr:street":"S Palmetto Ave",
    "iso:country":"US",
    "sg:address":"502 S Palmetto Ave",
    "sg:city":"Ontario",
    "sg:classifiers":[
        {
            "category":"Professional",
            "type":"Services"
        }
    ],
    "sg:phone":"+1 909 986 1566",
    "sg:postcode":"91762",
    "sg:province":"CA",
    "sg:tags":[
        "good"
    ],
    "wof:name":"Ceramic Services",
    "wof:placetype":"venue"
},
  "geometry": {"coordinates":[-117.66776400000001,34.057015],"type":"Point"}
}