{
  "type": "Feature",
  "properties": {
    "iso:country":"US",
    "sg:address":"23848 Hawthorne Blvd",
    "sg:city":"Torrance",
    "sg:classifiers":[
        {
            "category":"Building & Trades",
            "subcategory":"Construction",
            "type":"Services"
        }
    ],
    "sg:phone":"+1 310 320 1800",
    "sg:postcode":"90505",
    "sg:province":"CA",
    "sg:tags":[
        "roofing",
        "contractor"
    ],
    "wof:name":"K Moyer Roofing Co",
    "wof:placetype":"venue"
},
  "geometry": {"coordinates":[-118.350956,33.807006],"type":"Point"}
}