{
  "type": "Feature",
  "properties": {
    "iso:country":"US",
    "sg:address":"500 E Olive Ave",
    "sg:city":"Burbank",
    "sg:classifiers":[
        {
            "category":"Personal",
            "subcategory":"Hair Removal",
            "type":"Services"
        }
    ],
    "sg:phone":"+1 818 239 1366",
    "sg:postcode":"91501",
    "sg:province":"CA",
    "wof:name":"Sunamerica",
    "wof:placetype":"venue"
},
  "geometry": {"coordinates":[-118.303783,34.185513],"type":"Point"}
}