{
  "type": "Feature",
  "properties": {
    "addr:full":"9313 Bolsa Ave Westminster CA 92683",
    "addr:housenumber":"9313",
    "addr:postcode":"92683",
    "addr:street":"Bolsa Ave",
    "iso:country":"US",
    "sg:address":"9313 Bolsa Ave",
    "sg:city":"Westminster",
    "sg:classifiers":[
        {
            "category":"Food & Beverages",
            "subcategory":"Specialty",
            "type":"Retail Goods"
        }
    ],
    "sg:phone":"+1 714 897 9895",
    "sg:postcode":"92683",
    "sg:province":"CA",
    "sg:tags":[
        "water",
        "bulk",
        "company"
    ],
    "wof:name":"Aquafresh Pure Water",
    "wof:placetype":"venue"
},
  "geometry": {"coordinates":[-117.966409,33.744865],"type":"Point"}
}