{
  "type": "Feature",
  "properties": {
    "iso:country":"US",
    "sg:address":"1585 San Rafael Dr",
    "sg:city":"Corona",
    "sg:classifiers":[
        {
            "category":"Manufacturing",
            "subcategory":"Textiles",
            "type":"Manufacturing & Wholesale Goods"
        }
    ],
    "sg:phone":"+1 951 371 5988",
    "sg:postcode":"92882",
    "sg:province":"CA",
    "sg:tags":[
        "mill",
        "thread"
    ],
    "wof:name":"Thread Wear",
    "wof:placetype":"venue"
},
  "geometry": {"coordinates":[-117.61367300000001,33.865071],"type":"Point"}
}