{
  "type": "Feature",
  "properties": {
    "addr:full":"3830 Auburn Boulevard Suite E Sacramento CA 95821",
    "addr:housenumber":"3830",
    "addr:postcode":"95821",
    "addr:street":"Auburn Boulevard Suite E",
    "iso:country":"US",
    "sg:address":"3830 Auburn Boulevard Suite E",
    "sg:city":"Sacramento",
    "sg:classifiers":[
        {
            "category":"Shopping",
            "subcategory":"Beauty & Cosmetics",
            "type":"Retail Goods"
        }
    ],
    "sg:phone":"+1 916 482 8122",
    "sg:postcode":"95821",
    "sg:province":"CA",
    "sg:tags":[
        "supply"
    ],
    "wof:name":"Abs Beauty Supply",
    "wof:placetype":"venue"
},
  "geometry": {"coordinates":[-121.375282,38.639963],"type":"Point"}
}