{
  "type": "Feature",
  "properties": {
    "iso:country":"US",
    "sg:address":"17241 Murphy Ave",
    "sg:city":"Irvine",
    "sg:classifiers":[
        {
            "category":"Real Estate",
            "subcategory":"Real Estate Agent",
            "type":"Services"
        }
    ],
    "sg:phone":"+1 949 250 9103",
    "sg:postcode":"92614",
    "sg:province":"CA",
    "wof:name":"DSA Commercial Realty Inc",
    "wof:placetype":"venue"
},
  "geometry": {"coordinates":[-117.830341,33.687087],"type":"Point"}
}