{
  "type": "Feature",
  "properties": {
    "iso:country":"US",
    "sg:address":"1970 Broadway Suite 1200",
    "sg:city":"Oakland",
    "sg:classifiers":[
        {
            "category":"Professional",
            "subcategory":"Lawyer & Legal Services",
            "type":"Services"
        }
    ],
    "sg:phone":"+1 510 922 9400",
    "sg:postcode":"94612",
    "sg:province":"CA",
    "sg:website":"www.the1031attorney.com",
    "wof:name":"Richard A. Goodman, Atty",
    "wof:placetype":"venue"
},
  "geometry": {"coordinates":[-122.26837500000001,37.80879],"type":"Point"}
}