{
  "type": "Feature",
  "properties": {
    "addr:full":"123 Eddy Street San Francisco CA 94102",
    "addr:housenumber":"123",
    "addr:postcode":"94102",
    "addr:street":"Eddy Street",
    "iso:country":"US",
    "sg:address":"123 Eddy Street",
    "sg:city":"San Francisco",
    "sg:classifiers":[
        {
            "category":"Food & Beverages",
            "subcategory":"Groceries & Convenience Stores",
            "type":"Retail Goods"
        }
    ],
    "sg:phone":"+1 415 440 8688",
    "sg:postcode":"94102",
    "sg:province":"CA",
    "wof:name":"California Grocery",
    "wof:placetype":"venue"
},
  "geometry": {"coordinates":[-122.410004,37.784199],"type":"Point"}
}