{
  "type": "Feature",
  "properties": {
    "addr:full":"1370 Brea Blvd Ste 212 Fullerton CA 92835",
    "addr:housenumber":"1370",
    "addr:postcode":"92835",
    "addr:street":"Brea Blvd Ste 212",
    "iso:country":"US",
    "sg:address":"1370 Brea Blvd Ste 212",
    "sg:city":"Fullerton",
    "sg:classifiers":[
        {
            "category":"Insurance",
            "subcategory":"Health Insurance",
            "type":"Services"
        }
    ],
    "sg:phone":"+1 714 992 4545",
    "sg:postcode":"92835",
    "sg:province":"CA",
    "sg:tags":[
        "market"
    ],
    "wof:name":"Ayurvedic Herbal Power",
    "wof:placetype":"venue"
},
  "geometry": {"coordinates":[-117.924004,33.884399],"type":"Point"}
}