{
  "type": "Feature",
  "properties": {
    "addr:full":"20 Wayfarer Irvine CA 92614",
    "addr:housenumber":"20",
    "addr:postcode":"92614",
    "addr:street":"Wayfarer",
    "iso:country":"US",
    "sg:address":"20 Wayfarer",
    "sg:city":"Irvine",
    "sg:classifiers":[
        {
            "category":"Professional",
            "subcategory":"Management & Consulting",
            "type":"Services"
        }
    ],
    "sg:phone":"+1 949 551 1690",
    "sg:postcode":"92614",
    "sg:province":"CA",
    "sg:tags":[
        "party",
        "planning"
    ],
    "wof:name":"Traveling Tea Pot",
    "wof:placetype":"venue"
},
  "geometry": {"coordinates":[-117.808271,33.677399],"type":"Point"}
}