{
  "type": "Feature",
  "properties": {
    "iso:country":"US",
    "sg:address":"16250 Main St",
    "sg:city":"Lower Lake",
    "sg:classifiers":[
        {
            "category":"Shopping",
            "type":"Retail Goods"
        }
    ],
    "sg:phone":"+1 707 994 8420",
    "sg:postcode":"95457",
    "sg:province":"CA",
    "sg:tags":[
        "art",
        "gallery",
        "dealer"
    ],
    "wof:name":"Magoon's West",
    "wof:placetype":"venue"
},
  "geometry": {"coordinates":[-122.608402,38.910401],"type":"Point"}
}