{
  "type": "Feature",
  "properties": {
    "iso:country":"US",
    "sg:address":"3758 Grand Ave",
    "sg:city":"Oakland",
    "sg:classifiers":[
        {
            "category":"Building & Trades",
            "subcategory":"Construction",
            "type":"Services"
        }
    ],
    "sg:phone":"+1 510 821 6666",
    "sg:postcode":"94610",
    "sg:province":"CA",
    "sg:tags":[
        "road",
        "contractor"
    ],
    "wof:name":"Beresford-Howe Construction",
    "wof:placetype":"venue"
},
  "geometry": {"coordinates":[-122.245271,37.817034],"type":"Point"}
}