{
  "type": "Feature",
  "properties": {
    "addr:full":"2420 E 28th St Long Beach CA 90755",
    "addr:housenumber":"2420",
    "addr:postcode":"90755",
    "addr:street":"E 28Th St",
    "iso:country":"US",
    "sg:address":"2420 E 28th St",
    "sg:city":"Long Beach",
    "sg:classifiers":[
        {
            "category":"Education",
            "subcategory":"School",
            "type":"Public Place"
        },
        {
            "category":"Education",
            "subcategory":"Vocational School",
            "type":"Public Place"
        }
    ],
    "sg:phone":"+1 562 595 6190",
    "sg:postcode":"90755",
    "sg:province":"CA",
    "wof:name":"New World Licensing Seminars",
    "wof:placetype":"venue"
},
  "geometry": {"coordinates":[-118.16236499999999,33.807947],"type":"Point"}
}