{
  "type": "Feature",
  "properties": {
    "iso:country":"US",
    "sg:address":"5048 Calmview Ave",
    "sg:city":"Baldwin Park",
    "sg:classifiers":[
        {
            "category":"Building & Trades",
            "subcategory":"Construction",
            "type":"Services"
        }
    ],
    "sg:phone":"+1 626 338 0055",
    "sg:postcode":"91706",
    "sg:province":"CA",
    "sg:tags":[
        "maker",
        "cabinet"
    ],
    "wof:name":"Antique Restoration & Fine",
    "wof:placetype":"venue"
},
  "geometry": {"coordinates":[-117.94784,34.105816],"type":"Point"}
}