{
  "type": "Feature",
  "properties": {
    "addr:full":"800 W 6th St Ste 1420 Los Angeles CA 90017",
    "addr:housenumber":"800",
    "addr:postcode":"90017",
    "addr:street":"W 6Th St Ste 1420",
    "iso:country":"US",
    "sg:address":"800 W 6th St Ste 1420",
    "sg:city":"Los Angeles",
    "sg:classifiers":[
        {
            "category":"Professional",
            "subcategory":"Lawyer & Legal Services",
            "type":"Services"
        }
    ],
    "sg:phone":"+1 213 627 5200",
    "sg:postcode":"90017",
    "sg:province":"CA",
    "wof:name":"Law Office of Jeffrey H Kim",
    "wof:placetype":"venue"
},
  "geometry": {"coordinates":[-118.257783,34.050365],"type":"Point"}
}