{
  "type": "Feature",
  "properties": {
    "addr:full":"7930 Hwy 9 Ben Lomond CA 95005",
    "addr:housenumber":"7930",
    "addr:postcode":"95005",
    "addr:street":"Hwy 9",
    "iso:country":"US",
    "sg:address":"7930 Hwy 9",
    "sg:city":"Ben Lomond",
    "sg:classifiers":[
        {
            "category":"Retail",
            "subcategory":"Auto Repair",
            "type":"Services"
        }
    ],
    "sg:phone":"+1 831 336 9456",
    "sg:postcode":"95005",
    "sg:province":"CA",
    "sg:tags":[
        "repairing",
        "automobile"
    ],
    "wof:name":"Valley Lube N Tune",
    "wof:placetype":"venue"
},
  "geometry": {"coordinates":[-122.08414399999999,37.071978],"type":"Point"}
}