{
  "type": "Feature",
  "properties": {
    "iso:country":"US",
    "sg:address":"755 Broadway Cir",
    "sg:city":"San Diego",
    "sg:classifiers":[
        {
            "category":"Professional",
            "subcategory":"Lawyer & Legal Services",
            "type":"Services"
        }
    ],
    "sg:phone":"+1 619 231 0877",
    "sg:postcode":"92101",
    "sg:province":"CA",
    "wof:name":"Herring Margaret K",
    "wof:placetype":"venue"
},
  "geometry": {"coordinates":[-117.162003,32.7155],"type":"Point"}
}