{
  "type": "Feature",
  "properties": {
    "iso:country":"US",
    "sg:address":"1505 E Rose Ave",
    "sg:city":"Orange",
    "sg:classifiers":[
        {
            "category":"Professional",
            "subcategory":"Computer Services",
            "type":"Services"
        }
    ],
    "sg:phone":"+1 714 478 5578",
    "sg:postcode":"92867",
    "sg:province":"CA",
    "wof:name":"High Capacity Network",
    "wof:placetype":"venue"
},
  "geometry": {"coordinates":[-117.836926,33.797407],"type":"Point"}
}