{
  "type": "Feature",
  "properties": {
    "addr:full":"13574 6th Ave Victorville CA 92392",
    "addr:housenumber":"13574",
    "addr:postcode":"92392",
    "addr:street":"6Th Ave",
    "iso:country":"US",
    "sg:address":"13574 6th Ave",
    "sg:city":"Victorville",
    "sg:classifiers":[
        {
            "category":"Retail",
            "subcategory":"Auto Rental",
            "type":"Services"
        }
    ],
    "sg:phone":"+1 760 955 6232",
    "sg:postcode":"92392",
    "sg:province":"CA",
    "sg:tags":[
        "renting",
        "truck",
        "leasing"
    ],
    "wof:name":"U-Haul Co",
    "wof:placetype":"venue"
},
  "geometry": {"coordinates":[-117.308171,34.499455],"type":"Point"}
}