{
  "type": "Feature",
  "properties": {
    "iso:country":"US",
    "sg:address":"9955 Marconi Dr",
    "sg:city":"San Diego",
    "sg:classifiers":[
        {
            "category":"Wholesale",
            "subcategory":"Construction Materials",
            "type":"Manufacturing & Wholesale Goods"
        }
    ],
    "sg:phone":"+1 619 671 9355",
    "sg:postcode":"92154",
    "sg:province":"CA",
    "sg:tags":[
        "lumber"
    ],
    "wof:name":"Conmat Inc",
    "wof:placetype":"venue"
},
  "geometry": {"coordinates":[-116.930076,32.554223],"type":"Point"}
}