{
  "type": "Feature",
  "properties": {
    "iso:country":"US",
    "sg:address":"978 Lundy Ave",
    "sg:city":"San Jose",
    "sg:classifiers":[
        {
            "category":"Personal",
            "subcategory":"Beauty Salon",
            "type":"Services"
        },
        {
            "category":"Personal",
            "subcategory":"Nail Salon",
            "type":"Services"
        }
    ],
    "sg:phone":"+1 408 272 7777",
    "sg:postcode":"95133",
    "sg:province":"CA",
    "sg:tags":[
        "hair"
    ],
    "wof:name":"Stephanie's Hair & Nails",
    "wof:placetype":"venue"
},
  "geometry": {"coordinates":[-121.87279599999999,37.373635],"type":"Point"}
}