{
  "type": "Feature",
  "properties": {
    "iso:country":"US",
    "sg:address":"510 Alahmar St",
    "sg:city":"Alhambra",
    "sg:classifiers":[
        {
            "category":"Building & Trades",
            "subcategory":"Plumbing",
            "type":"Services"
        }
    ],
    "sg:phone":"+1 626 284 6544",
    "sg:postcode":"91801",
    "sg:province":"CA",
    "sg:tags":[
        "contractor"
    ],
    "wof:name":"Comfort Breeze AC",
    "wof:placetype":"venue"
},
  "geometry": {"coordinates":[-118.117295,34.106969],"type":"Point"}
}