{
  "type": "Feature",
  "properties": {
    "addr:full":"8493 W Sunset Blvd West Hollywood CA 90069",
    "addr:housenumber":"8493",
    "addr:postcode":"90069",
    "addr:street":"W Sunset Blvd",
    "iso:country":"US",
    "sg:address":"8493 W Sunset Blvd",
    "sg:city":"West Hollywood",
    "sg:classifiers":[
        {
            "category":"Shopping",
            "subcategory":"Shoes",
            "type":"Retail Goods"
        }
    ],
    "sg:phone":"+1 323 650 0475",
    "sg:postcode":"90069",
    "sg:province":"CA",
    "sg:tags":[
        "store"
    ],
    "wof:name":"Boot Star",
    "wof:placetype":"venue"
},
  "geometry": {"coordinates":[-118.376149,34.094502],"type":"Point"}
}