{
  "type": "Feature",
  "properties": {
    "addr:full":"1840 Green Street San Francisco CA 94123",
    "addr:housenumber":"1840",
    "addr:postcode":"94123",
    "addr:street":"Green Street",
    "iso:country":"US",
    "sg:address":"1840 Green Street",
    "sg:city":"San Francisco",
    "sg:classifiers":[
        {
            "category":"Utilities",
            "type":"Services"
        }
    ],
    "sg:phone":"+1 415 928 1500",
    "sg:postcode":"94123",
    "sg:province":"CA",
    "sg:tags":[
        "provider",
        "internet"
    ],
    "wof:name":"Perrine Jvince",
    "wof:placetype":"venue"
},
  "geometry": {"coordinates":[-122.42944900000001,37.796969],"type":"Point"}
}