{
  "type": "Feature",
  "properties": {
    "iso:country":"US",
    "sg:address":"7001 Highway 116",
    "sg:city":"Forestville",
    "sg:classifiers":[
        {
            "category":"Autos & Motor Vehicles",
            "subcategory":"Fuel & Gas Station",
            "type":"Retail Goods"
        }
    ],
    "sg:phone":"+1 707 887 7665",
    "sg:postcode":"95436",
    "sg:province":"CA",
    "wof:name":"Rotten Robbie",
    "wof:placetype":"venue"
},
  "geometry": {"coordinates":[-122.902,38.488201],"type":"Point"}
}