{
  "type": "Feature",
  "properties": {
    "addr:full":"3830 Oceanic Dr Oceanside CA 92056",
    "addr:housenumber":"3830",
    "addr:postcode":"92056",
    "addr:street":"Oceanic Dr",
    "iso:country":"US",
    "sg:address":"3830 Oceanic Dr",
    "sg:city":"Oceanside",
    "sg:classifiers":[
        {
            "category":"Shopping",
            "subcategory":"Computers & Home Electronics",
            "type":"Retail Goods"
        }
    ],
    "sg:phone":"+1 760 754 9880",
    "sg:postcode":"92056",
    "sg:province":"CA",
    "wof:name":"Viewtech Inc",
    "wof:placetype":"venue"
},
  "geometry": {"coordinates":[-117.30434099999999,33.20552],"type":"Point"}
}