{
  "type": "Feature",
  "properties": {
    "addr:full":"1484 S Beverly Dr Apt 101 Los Angeles CA 90035",
    "addr:housenumber":"1484;101",
    "addr:postcode":"90035",
    "addr:street":"S Beverly Dr Apt",
    "iso:country":"US",
    "sg:address":"1484 S Beverly Dr Apt 101",
    "sg:city":"Los Angeles",
    "sg:classifiers":[
        {
            "category":"Real Estate",
            "subcategory":"Real Estate Operator",
            "type":"Services"
        }
    ],
    "sg:phone":"+1 310 556 2606",
    "sg:postcode":"90035",
    "sg:province":"CA",
    "sg:tags":[
        "apartment"
    ],
    "wof:name":"Courtyard Apartments",
    "wof:placetype":"venue"
},
  "geometry": {"coordinates":[-118.394997,34.0527],"type":"Point"}
}