{
  "type": "Feature",
  "properties": {
    "addr:full":"437 San Pablo Ave Albany CA 94706",
    "addr:housenumber":"437",
    "addr:postcode":"94706",
    "addr:street":"San Pablo Ave",
    "iso:country":"US",
    "sg:address":"437 San Pablo Ave",
    "sg:city":"Albany",
    "sg:classifiers":[
        {
            "category":"Restaurant",
            "type":"Food & Drink"
        }
    ],
    "sg:phone":"+1 510 527 1523",
    "sg:postcode":"94706",
    "sg:province":"CA",
    "sg:tags":[
        "burger"
    ],
    "wof:name":"Al's Big Burger",
    "wof:placetype":"venue"
},
  "geometry": {"coordinates":[-122.301267,37.897698],"type":"Point"}
}