{
  "type": "Feature",
  "properties": {
    "iso:country":"US",
    "sg:address":"9611 Garvey Ave Ste 213",
    "sg:city":"South El Monte",
    "sg:classifiers":[
        {
            "category":"Shopping",
            "subcategory":"Jewelry",
            "type":"Retail Goods"
        }
    ],
    "sg:phone":"+1 626 443 9909",
    "sg:postcode":"91733",
    "sg:province":"CA",
    "wof:name":"P & T Jewelry Inc",
    "wof:placetype":"venue"
},
  "geometry": {"coordinates":[-118.05999799999999,34.062801],"type":"Point"}
}