{
  "type": "Feature",
  "properties": {
    "addr:full":"514 Community Ln Woodland CA 95695",
    "addr:housenumber":"514",
    "addr:postcode":"95695",
    "addr:street":"Community Ln",
    "iso:country":"US",
    "sg:address":"514 Community Ln",
    "sg:city":"Woodland",
    "sg:classifiers":[
        {
            "category":"Real Estate",
            "subcategory":"Real Estate Operator",
            "type":"Services"
        }
    ],
    "sg:phone":"+1 530 661 6418",
    "sg:postcode":"95695",
    "sg:province":"CA",
    "sg:tags":[
        "apartment"
    ],
    "wof:name":"Walnut Wood Apartments",
    "wof:placetype":"venue"
},
  "geometry": {"coordinates":[-121.79183500000001,38.673784],"type":"Point"}
}