{
  "type": "Feature",
  "properties": {
    "iso:country":"US",
    "sg:address":"333 N Lantana St",
    "sg:city":"Camarillo",
    "sg:classifiers":[
        {
            "category":"Health Services",
            "subcategory":"Health Practitioner",
            "type":"Services"
        }
    ],
    "sg:phone":"+1 805 389 4770",
    "sg:postcode":"93010",
    "sg:province":"CA",
    "sg:tags":[
        "psychologist"
    ],
    "wof:name":"Katherine Hamilton",
    "wof:placetype":"venue"
},
  "geometry": {"coordinates":[-119.055104,34.219118],"type":"Point"}
}