{
  "type": "Feature",
  "properties": {
    "addr:full":"8716 Imperial Hwy Downey CA 90242",
    "addr:housenumber":"8716",
    "addr:postcode":"90242",
    "addr:street":"Imperial Hwy",
    "iso:country":"US",
    "sg:address":"8716 Imperial Hwy",
    "sg:city":"Downey",
    "sg:classifiers":[
        {
            "category":"Restaurant",
            "type":"Food & Drink"
        }
    ],
    "sg:phone":"+1 562 923 8412",
    "sg:postcode":"90242",
    "sg:province":"CA",
    "sg:tags":[
        "chinese"
    ],
    "wof:name":"Lucky Star Chinese",
    "wof:placetype":"venue"
},
  "geometry": {"coordinates":[-118.140773,33.917937],"type":"Point"}
}