{
  "type": "Feature",
  "properties": {
    "iso:country":"US",
    "sg:address":"5519 W 123rd St",
    "sg:city":"Hawthorne",
    "sg:classifiers":[
        {
            "category":"Building & Trades",
            "subcategory":"Construction",
            "type":"Services"
        }
    ],
    "sg:phone":"+1 310 643 7105",
    "sg:postcode":"90250",
    "sg:province":"CA",
    "sg:tags":[
        "lift",
        "aerial",
        "scaffolding"
    ],
    "wof:name":"Bason Scaffolding Co Inc",
    "wof:placetype":"venue"
},
  "geometry": {"coordinates":[-118.376698,33.921638],"type":"Point"}
}