{
  "type": "Feature",
  "properties": {
    "addr:full":"68342 Kieley Rd Cathedral City CA 92234",
    "addr:postcode":"68342;92234",
    "addr:street":"Kieley Rd",
    "iso:country":"US",
    "sg:address":"68342 Kieley Rd",
    "sg:city":"Cathedral City",
    "sg:classifiers":[
        {
            "category":"Building & Trades",
            "subcategory":"Electrical",
            "type":"Services"
        }
    ],
    "sg:phone":"+1 760 328 1088",
    "sg:postcode":"92234",
    "sg:province":"CA",
    "sg:tags":[
        "electrician"
    ],
    "wof:name":"La Salle A M Electric",
    "wof:placetype":"venue"
},
  "geometry": {"coordinates":[-116.470001,33.786201],"type":"Point"}
}