{
  "type": "Feature",
  "properties": {
    "iso:country":"US",
    "sg:address":"12229 Norwalk Blvd",
    "sg:city":"Norwalk",
    "sg:classifiers":[
        {
            "category":"Cinema",
            "subcategory":"Movie Rental",
            "type":"Entertainment"
        }
    ],
    "sg:phone":"+1 562 864 8937",
    "sg:postcode":"90650",
    "sg:province":"CA",
    "sg:tags":[
        "video",
        "game",
        "disc",
        "leasing",
        "tape"
    ],
    "wof:name":"Omni Video",
    "wof:placetype":"venue"
},
  "geometry": {"coordinates":[-118.072998,33.920502],"type":"Point"}
}