{
  "type": "Feature",
  "properties": {
    "addr:full":"25092 Farthing St Lake Forest CA 92630",
    "addr:housenumber":"25092",
    "addr:postcode":"92630",
    "addr:street":"Farthing St",
    "iso:country":"US",
    "sg:address":"25092 Farthing St",
    "sg:city":"Lake Forest",
    "sg:classifiers":[
        {
            "category":"Real Estate",
            "subcategory":"Real Estate Operator",
            "type":"Services"
        }
    ],
    "sg:phone":"+1 949 768 9451",
    "sg:postcode":"92630",
    "sg:province":"CA",
    "sg:tags":[
        "apartment"
    ],
    "wof:name":"Forest Glen Apartment Homes",
    "wof:placetype":"venue"
},
  "geometry": {"coordinates":[-117.693001,33.628601],"type":"Point"}
}