{
  "type": "Feature",
  "properties": {
    "iso:country":"US",
    "sg:address":"198 Wool St",
    "sg:city":"Folsom",
    "sg:classifiers":[
        {
            "category":"Museum",
            "type":"Entertainment"
        }
    ],
    "sg:phone":"+1 916 985 6031",
    "sg:postcode":"95630",
    "sg:province":"CA",
    "wof:name":"Folsom Railroad Museum",
    "wof:placetype":"venue"
},
  "geometry": {"coordinates":[-121.178298,38.677613],"type":"Point"}
}