{
  "type": "Feature",
  "properties": {
    "addr:full":"2181 S El Camino Real Oceanside CA 92054",
    "addr:housenumber":"2181",
    "addr:postcode":"92054",
    "addr:street":"S El Camino Real",
    "iso:country":"US",
    "sg:address":"2181 S El Camino Real",
    "sg:city":"Oceanside",
    "sg:classifiers":[
        {
            "category":"Building & Trades",
            "subcategory":"Construction",
            "type":"Services"
        }
    ],
    "sg:phone":"+1 760 433 7557",
    "sg:postcode":"92054",
    "sg:province":"CA",
    "sg:tags":[
        "contractor"
    ],
    "wof:name":"American Mechanical Contractor",
    "wof:placetype":"venue"
},
  "geometry": {"coordinates":[-117.36199999999999,33.210701],"type":"Point"}
}