{
  "type": "Feature",
  "properties": {
    "addr:full":"1213 E Yorba Linda Blvd Placentia CA 92870",
    "addr:housenumber":"1213",
    "addr:postcode":"ca 92870",
    "addr:street":"E Yorba Linda Blvd",
    "iso:country":"US",
    "sg:address":"1213 E Yorba Linda Blvd",
    "sg:city":"Placentia",
    "sg:classifiers":[
        {
            "category":"Shopping",
            "subcategory":"Jewelry",
            "type":"Retail Goods"
        }
    ],
    "sg:phone":"+1 714 996 4490",
    "sg:postcode":"92870",
    "sg:province":"CA",
    "wof:name":"Marquis Jewelers",
    "wof:placetype":"venue"
},
  "geometry": {"coordinates":[-117.843002,33.8853],"type":"Point"}
}