{
  "type": "Feature",
  "properties": {
    "iso:country":"US",
    "sg:address":"333 Valencia St",
    "sg:city":"San Francisco",
    "sg:classifiers":[
        {
            "category":"Travel",
            "subcategory":"Travel Agent",
            "type":"Entertainment"
        }
    ],
    "sg:phone":"+1 415 431 4480",
    "sg:postcode":"94103",
    "sg:province":"CA",
    "sg:tags":[
        "operator",
        "tour"
    ],
    "wof:name":"Bike Aid",
    "wof:placetype":"venue"
},
  "geometry": {"coordinates":[-122.422085,37.767839],"type":"Point"}
}