{
  "type": "Feature",
  "properties": {
    "addr:full":"4127 W Shaw Ave Fresno CA 93722",
    "addr:housenumber":"4127",
    "addr:postcode":"93722",
    "addr:street":"W Shaw Ave",
    "iso:country":"US",
    "sg:address":"4127 W Shaw Ave",
    "sg:city":"Fresno",
    "sg:classifiers":[
        {
            "category":"Retail",
            "subcategory":"Auto Repair",
            "type":"Services"
        }
    ],
    "sg:phone":"+1 559 275 8795",
    "sg:postcode":"93722",
    "sg:province":"CA",
    "sg:tags":[
        "repairing",
        "automobile"
    ],
    "wof:name":"Econo Lube N' Tune",
    "wof:placetype":"venue"
},
  "geometry": {"coordinates":[-119.86414000000001,36.80818],"type":"Point"}
}