{
  "type": "Feature",
  "properties": {
    "addr:full":"20611 Reef Lane Huntington Beach CA 92646",
    "addr:housenumber":"20611",
    "addr:postcode":"92646",
    "addr:street":"Reef Lane",
    "iso:country":"US",
    "sg:address":"20611 Reef Lane",
    "sg:city":"Huntington Beach",
    "sg:classifiers":[
        {
            "category":"Building & Trades",
            "subcategory":"Electrical",
            "type":"Services"
        }
    ],
    "sg:phone":"+1 714 715 0521",
    "sg:postcode":"92646",
    "sg:province":"CA",
    "sg:tags":[
        "electrician"
    ],
    "wof:name":"HB Electric",
    "wof:placetype":"venue"
},
  "geometry": {"coordinates":[-117.957914,33.66335],"type":"Point"}
}