{
  "type": "Feature",
  "properties": {
    "addr:full":"15315 Cholame Rd Victorville CA 92392",
    "addr:housenumber":"15315",
    "addr:postcode":"92392",
    "addr:street":"Cholame Rd",
    "iso:country":"US",
    "sg:address":"15315 Cholame Rd",
    "sg:city":"Victorville",
    "sg:classifiers":[
        {
            "category":"Manufacturing",
            "subcategory":"Tools & Machinery",
            "type":"Manufacturing & Wholesale Goods"
        },
        {
            "category":"Manufacturing",
            "subcategory":"Electronics",
            "type":"Manufacturing & Wholesale Goods"
        },
        {
            "category":"Wholesale",
            "subcategory":"Electrical",
            "type":"Manufacturing & Wholesale Goods"
        }
    ],
    "sg:phone":"+1 562 988 3100",
    "sg:postcode":"92392",
    "sg:province":"CA",
    "sg:tags":[
        "electric",
        "supply",
        "equipment-testing",
        "equipment",
        "supplies-wholesale",
        "manufacturer"
    ],
    "sg:website":"http://www.walterswholesale.com",
    "wof:name":"Walters Wholesale Electric Co.",
    "wof:placetype":"venue"
},
  "geometry": {"coordinates":[-117.32983400000001,34.502152],"type":"Point"}
}