{
  "type": "Feature",
  "properties": {
    "addr:full":"8787 Cleburn Dr La Mesa CA 91942",
    "addr:housenumber":"8787",
    "addr:postcode":"91942",
    "addr:street":"Cleburn Dr",
    "iso:country":"US",
    "sg:address":"8787 Cleburn Dr",
    "sg:city":"La Mesa",
    "sg:classifiers":[
        {
            "category":"Building & Trades",
            "subcategory":"Cleaning & Sanitation",
            "type":"Services"
        }
    ],
    "sg:phone":"+1 619 469 2605",
    "sg:postcode":"91942",
    "sg:province":"CA",
    "sg:tags":[
        "window"
    ],
    "wof:name":"Radiant Window Cleaning",
    "wof:placetype":"venue"
},
  "geometry": {"coordinates":[-117.00815,32.78748],"type":"Point"}
}