{
  "type": "Feature",
  "properties": {
    "iso:country":"US",
    "sg:address":"1520 Sunshine Dr",
    "sg:city":"Glendale",
    "sg:classifiers":[
        {
            "category":"Professional",
            "type":"Services"
        }
    ],
    "sg:phone":"+1 818 662 0273",
    "sg:postcode":"91208",
    "sg:province":"CA",
    "wof:name":"SMA Second Family LP",
    "wof:placetype":"venue"
},
  "geometry": {"coordinates":[-118.232412,34.174004],"type":"Point"}
}