{
  "type": "Feature",
  "properties": {
    "addr:full":"17014 Calahan St Northridge CA 91325",
    "addr:postcode":"17014;91325",
    "addr:street":"Calahan St",
    "iso:country":"US",
    "sg:address":"17014 Calahan St",
    "sg:city":"Northridge",
    "sg:classifiers":[
        {
            "category":"Professional",
            "type":"Services"
        }
    ],
    "sg:phone":"+1 818 886 7627",
    "sg:postcode":"91325",
    "sg:province":"CA",
    "wof:name":"Carolina Manlapaz",
    "wof:placetype":"venue"
},
  "geometry": {"coordinates":[-118.504081,34.236329],"type":"Point"}
}