{
  "type": "Feature",
  "properties": {
    "iso:country":"US",
    "sg:address":"586 Coolidge Ave",
    "sg:city":"Hemet",
    "sg:classifiers":[
        {
            "category":"Freight",
            "type":"Transportation"
        }
    ],
    "sg:phone":"+1 951 658 9105",
    "sg:postcode":"92543",
    "sg:province":"CA",
    "sg:tags":[
        "operator",
        "local",
        "trucking"
    ],
    "wof:name":"Duran Trucking",
    "wof:placetype":"venue"
},
  "geometry": {"coordinates":[-116.977349,33.759744],"type":"Point"}
}