{
  "type": "Feature",
  "properties": {
    "addr:full":"12650 Baker Rd Stockton CA 95215",
    "addr:housenumber":"12650",
    "addr:postcode":"95215",
    "addr:street":"Baker Rd",
    "iso:country":"US",
    "sg:address":"12650 Baker Rd",
    "sg:city":"Stockton",
    "sg:classifiers":[
        {
            "category":"Farming",
            "subcategory":"Crops",
            "type":"Manufacturing & Wholesale Goods"
        }
    ],
    "sg:phone":"+1 209 931 5406",
    "sg:postcode":"95215",
    "sg:province":"CA",
    "sg:tags":[
        "fr",
        "grove",
        "nut",
        "tree",
        "cash",
        "farm",
        "grain"
    ],
    "wof:name":"Jon Brandstad Farms",
    "wof:placetype":"venue"
},
  "geometry": {"coordinates":[-121.15848699999999,38.029122],"type":"Point"}
}