{
  "type": "Feature",
  "properties": {
    "addr:full":"14273 Washington Ave San Leandro CA 94578",
    "addr:housenumber":"14273",
    "addr:postcode":"94578",
    "addr:street":"Washington Ave",
    "iso:country":"US",
    "sg:address":"14273 Washington Ave",
    "sg:city":"San Leandro",
    "sg:classifiers":[
        {
            "category":"Building & Trades",
            "subcategory":"Equipment Rental",
            "type":"Services"
        }
    ],
    "sg:phone":"+1 510 357 5900",
    "sg:postcode":"94578",
    "sg:province":"CA",
    "sg:tags":[
        "yard"
    ],
    "sg:website":"www.unitedrentals.com",
    "wof:name":"United Rentals",
    "wof:placetype":"venue"
},
  "geometry": {"coordinates":[-122.145391,37.708065],"type":"Point"}
}