{
  "type": "Feature",
  "properties": {
    "iso:country":"US",
    "sg:address":"4421 Clark Dr",
    "sg:city":"Stockton",
    "sg:classifiers":[
        {
            "category":"Wholesale",
            "subcategory":"Auto Parts",
            "type":"Manufacturing & Wholesale Goods"
        }
    ],
    "sg:phone":"+1 209 466 4987",
    "sg:postcode":"95215",
    "sg:province":"CA",
    "sg:tags":[
        "automobile"
    ],
    "wof:name":"Kennedy Auto Co",
    "wof:placetype":"venue"
},
  "geometry": {"coordinates":[-121.226055,37.919668],"type":"Point"}
}