{
  "type": "Feature",
  "properties": {
    "iso:country":"US",
    "sg:address":"1629 Date St",
    "sg:city":"Montebello",
    "sg:classifiers":[
        {
            "category":"Home & Garden",
            "subcategory":"Home Furnishings",
            "type":"Retail Goods"
        }
    ],
    "sg:phone":"+1 323 724 7957",
    "sg:postcode":"90640",
    "sg:province":"CA",
    "sg:tags":[
        "pillow"
    ],
    "sg:website":"www.lapillow.com",
    "wof:name":"LA Pillow & Fiber Inc",
    "wof:placetype":"venue"
},
  "geometry": {"coordinates":[-118.12734500000001,33.993206],"type":"Point"}
}