{
  "type": "Feature",
  "properties": {
    "iso:country":"US",
    "sg:address":"3825 Mission Ave",
    "sg:city":"Oceanside",
    "sg:classifiers":[
        {
            "category":"Fast Food",
            "type":"Food & Drink"
        },
        {
            "category":"Restaurant",
            "type":"Food & Drink"
        },
        {
            "category":"Food & Beverages",
            "subcategory":"Bakery",
            "type":"Retail Goods"
        }
    ],
    "sg:phone":"+1 760 901 4299",
    "sg:postcode":"92058",
    "sg:province":"CA",
    "sg:tags":[
        "burger",
        "sandwich",
        "diner"
    ],
    "wof:name":"Pit Stop Diner",
    "wof:placetype":"venue"
},
  "geometry": {"coordinates":[-117.32967600000001,33.22644],"type":"Point"}
}