{
  "type": "Feature",
  "properties": {
    "addr:full":"9808 Wilshire Boulevard Beverly Hills CA 90212",
    "addr:housenumber":"9808",
    "addr:postcode":"90212",
    "addr:street":"Wilshire Boulevard",
    "iso:country":"US",
    "sg:address":"9808 Wilshire Boulevard",
    "sg:city":"Beverly Hills",
    "sg:classifiers":[
        {
            "category":"Professional",
            "subcategory":"Accounting & Tax Preparation",
            "type":"Services"
        }
    ],
    "sg:phone":"+1 310 273 4550",
    "sg:postcode":"90212",
    "sg:province":"CA",
    "sg:tags":[
        "accountant"
    ],
    "wof:name":"Steinhauser Warren",
    "wof:placetype":"venue"
},
  "geometry": {"coordinates":[-118.409041,34.067003],"type":"Point"}
}