{
  "type": "Feature",
  "properties": {
    "addr:full":"1835 E 4th St Long Beach CA 90802",
    "addr:housenumber":"1835",
    "addr:postcode":"90802",
    "addr:street":"E 4Th St",
    "iso:country":"US",
    "sg:address":"1835 E 4th St",
    "sg:city":"Long Beach",
    "sg:classifiers":[
        {
            "category":"Real Estate",
            "subcategory":"Real Estate Operator",
            "type":"Services"
        }
    ],
    "sg:phone":"+1 562 491 5590",
    "sg:postcode":"90802",
    "sg:province":"CA",
    "sg:tags":[
        "apartment"
    ],
    "wof:name":"Fourth Street Apartments",
    "wof:placetype":"venue"
},
  "geometry": {"coordinates":[-118.16866400000001,33.771782],"type":"Point"}
}