{
  "type": "Feature",
  "properties": {
    "addr:full":"35246 Maple St Barstow CA 92311",
    "addr:housenumber":"35246",
    "addr:postcode":"92311",
    "addr:street":"Maple St",
    "iso:country":"US",
    "sg:address":"35246 Maple St",
    "sg:city":"Barstow",
    "sg:classifiers":[
        {
            "category":"Shopping",
            "subcategory":"Pets & Pet Supplies",
            "type":"Retail Goods"
        },
        {
            "category":"Retail",
            "subcategory":"Animal Services",
            "type":"Services"
        }
    ],
    "sg:phone":"+1 760 253 4500",
    "sg:postcode":"92311",
    "sg:province":"CA",
    "sg:tags":[
        "grooming",
        "dog",
        "cat"
    ],
    "wof:name":"Tammie's Critter Grooming",
    "wof:placetype":"venue"
},
  "geometry": {"coordinates":[-117.109837,34.891987],"type":"Point"}
}