{
  "type": "Feature",
  "properties": {
    "addr:full":"3450 3rd St San Francisco CA 94124",
    "addr:housenumber":"3450",
    "addr:postcode":"94124",
    "addr:street":"3Rd St",
    "iso:country":"US",
    "sg:address":"3450 3rd St",
    "sg:city":"San Francisco",
    "sg:classifiers":[
        {
            "category":"Manufacturing",
            "subcategory":"Printing",
            "type":"Manufacturing & Wholesale Goods"
        }
    ],
    "sg:phone":"+1 415 777 1777",
    "sg:postcode":"94124",
    "sg:province":"CA",
    "sg:tags":[
        "certificate",
        "stock"
    ],
    "sg:website":"www.oneshare.com",
    "wof:name":"One Share",
    "wof:placetype":"venue"
},
  "geometry": {"coordinates":[-122.387266,37.74562],"type":"Point"}
}