{
  "type": "Feature",
  "properties": {
    "iso:country":"US",
    "sg:address":"38 Discovery Ste 200",
    "sg:city":"Irvine",
    "sg:classifiers":[
        {
            "category":"Building & Trades",
            "subcategory":"Construction",
            "type":"Services"
        }
    ],
    "sg:phone":"+1 949 585 0100",
    "sg:postcode":"92618",
    "sg:province":"CA",
    "sg:tags":[
        "contractor"
    ],
    "sg:website":"www.suffolkconstruction.com",
    "wof:name":"Suffolk Construction",
    "wof:placetype":"venue"
},
  "geometry": {"coordinates":[-117.755636,33.66589],"type":"Point"}
}