{
  "type": "Feature",
  "properties": {
    "addr:full":"19936 Lorne St Winnetka CA 91306",
    "addr:housenumber":"19936",
    "addr:postcode":"91306",
    "addr:street":"Lorne St",
    "iso:country":"US",
    "sg:address":"19936 Lorne St",
    "sg:city":"Winnetka",
    "sg:classifiers":[
        {
            "category":"Professional",
            "type":"Services"
        }
    ],
    "sg:phone":"+1 818 998 6300",
    "sg:postcode":"91306",
    "sg:province":"CA",
    "sg:tags":[
        "establishment"
    ],
    "wof:name":"Gia Enterprises",
    "wof:placetype":"venue"
},
  "geometry": {"coordinates":[-118.56894200000001,34.217121],"type":"Point"}
}