{
  "type": "Feature",
  "properties": {
    "iso:country":"US",
    "sg:address":"1950 Compton Ave",
    "sg:city":"Corona",
    "sg:classifiers":[
        {
            "category":"Building & Trades",
            "subcategory":"Plumbing",
            "type":"Services"
        }
    ],
    "sg:phone":"+1 951 280 1870",
    "sg:postcode":"92881",
    "sg:province":"CA",
    "sg:tags":[
        "conditioning",
        "air",
        "system",
        "contractor"
    ],
    "wof:name":"Service Experts Htg & AC",
    "wof:placetype":"venue"
},
  "geometry": {"coordinates":[-117.536368,33.856876],"type":"Point"}
}