{
  "type": "Feature",
  "properties": {
    "addr:full":"1528 Ysrella Ave Simi Valley CA 93065",
    "addr:housenumber":"1528",
    "addr:postcode":"93065",
    "addr:street":"Ysrella Ave",
    "iso:country":"US",
    "sg:address":"1528 Ysrella Ave",
    "sg:city":"Simi Valley",
    "sg:classifiers":[
        {
            "category":"Building & Trades",
            "subcategory":"Landscaping Services",
            "type":"Services"
        }
    ],
    "sg:phone":"+1 805 494 9524",
    "sg:postcode":"93065",
    "sg:province":"CA",
    "sg:tags":[
        "designer",
        "landscape"
    ],
    "wof:name":"Thomas F Kaye",
    "wof:placetype":"venue"
},
  "geometry": {"coordinates":[-118.75495600000001,34.266438],"type":"Point"}
}