{
  "type": "Feature",
  "properties": {
    "iso:country":"US",
    "sg:address":"7122 McComber St",
    "sg:city":"Sacramento",
    "sg:classifiers":[
        {
            "category":"Retail",
            "subcategory":"Auto Repair",
            "type":"Services"
        }
    ],
    "sg:phone":"+1 916 381 8125",
    "sg:postcode":"95828",
    "sg:province":"CA",
    "sg:tags":[
        "wrecker"
    ],
    "wof:name":"H & N Towing",
    "wof:placetype":"venue"
},
  "geometry": {"coordinates":[-121.396019,38.49658],"type":"Point"}
}