{
  "type": "Feature",
  "properties": {
    "addr:full":"2380 NISSEN DR LIVERMORE CA 94551",
    "addr:postcode":"2380;94551",
    "addr:street":"Nissen Dr",
    "iso:country":"US",
    "sg:address":"2380 NISSEN DR",
    "sg:city":"LIVERMORE",
    "sg:classifiers":[
        {
            "category":"Travel",
            "subcategory":"Hotels & Motels",
            "type":"Entertainment"
        }
    ],
    "sg:phone":"+1 925 373 1700",
    "sg:postcode":"94551",
    "sg:province":"CA",
    "sg:tags":[
        "corporate",
        "lodging"
    ],
    "sg:website":"http://redirect.searchignite.com/si/cm/tracking/DGTrackingRedirect.aspx?siclientid=2918&siredirect=http%3A%2F%2Fwww%2Eextendedstayamerica%2Ecom%2FLVM&sisearchengine=155&siproduct=ESA+Livermore+%2D+Airway+Blvd%2E&clearppc=1",
    "wof:name":"Extended Stay America Livermore - Airway Blvd.",
    "wof:placetype":"venue"
},
  "geometry": {"coordinates":[-121.81522200000001,37.698036],"type":"Point"}
}