{
  "type": "Feature",
  "properties": {
    "iso:country":"US",
    "sg:address":"418 3rd St",
    "sg:city":"Oakland",
    "sg:classifiers":[
        {
            "category":"Manufacturing",
            "subcategory":"Paper Products",
            "type":"Manufacturing & Wholesale Goods"
        }
    ],
    "sg:phone":"+1 510 834 3000",
    "sg:postcode":"94607",
    "sg:province":"CA",
    "sg:tags":[
        "greeting",
        "cards-wholesale",
        "manufacturer"
    ],
    "wof:name":"Gotta Get Up",
    "wof:placetype":"venue"
},
  "geometry": {"coordinates":[-122.27516,37.796444],"type":"Point"}
}