{
  "type": "Feature",
  "properties": {
    "iso:country":"US",
    "sg:address":"31284 San Antonio St",
    "sg:city":"Hayward",
    "sg:classifiers":[
        {
            "category":"Manufacturing",
            "subcategory":"Printing",
            "type":"Manufacturing & Wholesale Goods"
        }
    ],
    "sg:phone":"+1 510 489 1744",
    "sg:postcode":"94544",
    "sg:province":"CA",
    "sg:tags":[
        "commercial",
        "label"
    ],
    "wof:name":"AAA Label Co",
    "wof:placetype":"venue"
},
  "geometry": {"coordinates":[-122.048287,37.611297],"type":"Point"}
}