{
  "type": "Feature",
  "properties": {
    "addr:full":"9034 Huntington Dr San Gabriel CA 91775",
    "addr:housenumber":"9034",
    "addr:postcode":"91775",
    "addr:street":"Huntington Dr",
    "iso:country":"US",
    "sg:address":"9034 Huntington Dr",
    "sg:city":"San Gabriel",
    "sg:classifiers":[
        {
            "category":"Shopping",
            "subcategory":"Bicycles & Sporting Goods",
            "type":"Retail Goods"
        }
    ],
    "sg:phone":"+1 626 287 0736",
    "sg:postcode":"91775",
    "sg:province":"CA",
    "sg:tags":[
        "equipment",
        "skiing"
    ],
    "wof:name":"Ski & Snowboard Liquidation",
    "wof:placetype":"venue"
},
  "geometry": {"coordinates":[-118.072602,34.130356],"type":"Point"}
}