{
  "type": "Feature",
  "properties": {
    "addr:full":"6921 Linda Vista Rd San Diego CA 92111",
    "addr:housenumber":"6921",
    "addr:postcode":"92111",
    "addr:street":"Linda Vista Rd",
    "iso:country":"US",
    "sg:address":"6921 Linda Vista Rd",
    "sg:city":"San Diego",
    "sg:classifiers":[
        {
            "category":"Restaurant",
            "type":"Food & Drink"
        }
    ],
    "sg:phone":"+1 858 492 9108",
    "sg:postcode":"92111",
    "sg:province":"CA",
    "sg:tags":[
        "vietnamese"
    ],
    "wof:name":"Pho Hoa Linda Vista",
    "wof:placetype":"venue"
},
  "geometry": {"coordinates":[-117.170998,32.7854],"type":"Point"}
}