{
  "type": "Feature",
  "properties": {
    "addr:full":"5123 W Walnut Ave Visalia CA 93277",
    "addr:housenumber":"5123",
    "addr:postcode":"93277",
    "addr:street":"W Walnut Ave",
    "iso:country":"US",
    "sg:address":"5123 W Walnut Ave",
    "sg:city":"Visalia",
    "sg:classifiers":[
        {
            "category":"Banks & Credit Unions",
            "subcategory":"Bank",
            "type":"Services"
        }
    ],
    "sg:phone":"+1 559 625 0270",
    "sg:postcode":"93277",
    "sg:province":"CA",
    "sg:tags":[
        "financing"
    ],
    "wof:name":"American General Finance Inc",
    "wof:placetype":"venue"
},
  "geometry": {"coordinates":[-119.346435,36.312705],"type":"Point"}
}