{
  "type": "Feature",
  "properties": {
    "iso:country":"US",
    "sg:address":"1000 S Union Ave",
    "sg:city":"Avenal",
    "sg:classifiers":[
        {
            "category":"Education",
            "subcategory":"School",
            "type":"Public Place"
        }
    ],
    "sg:phone":"+1 559 386 4051",
    "sg:postcode":"93204",
    "sg:province":"CA",
    "wof:name":"Tamarack Elementary School",
    "wof:placetype":"venue"
},
  "geometry": {"coordinates":[-120.124482,35.999937],"type":"Point"}
}