{
  "type": "Feature",
  "properties": {
    "addr:full":"7020 N West Ave Fresno CA 93711",
    "addr:housenumber":"7020",
    "addr:postcode":"93711",
    "addr:street":"N West Ave",
    "iso:country":"US",
    "sg:address":"7020 N West Ave",
    "sg:city":"Fresno",
    "sg:classifiers":[
        {
            "category":"Personal",
            "subcategory":"Beauty Salon",
            "type":"Services"
        }
    ],
    "sg:phone":"+1 559 434 8073",
    "sg:postcode":"93711",
    "sg:province":"CA",
    "wof:name":"Vito Marziliano Intl",
    "wof:placetype":"venue"
},
  "geometry": {"coordinates":[-119.826261,36.837419],"type":"Point"}
}