{
  "type": "Feature",
  "properties": {
    "iso:country":"US",
    "sg:address":"125 E F St",
    "sg:city":"Tehachapi",
    "sg:classifiers":[
        {
            "category":"Government",
            "subcategory":"Office",
            "type":"Public Place"
        }
    ],
    "sg:phone":"+1 661 384 5885",
    "sg:postcode":"93561",
    "sg:province":"CA",
    "sg:tags":[
        "general"
    ],
    "wof:name":"Resource Management Agency",
    "wof:placetype":"venue"
},
  "geometry": {"coordinates":[-118.447412,35.131015],"type":"Point"}
}