{
  "type": "Feature",
  "properties": {
    "iso:country":"US",
    "sg:address":"830 Highpoint Dr",
    "sg:city":"Claremont",
    "sg:classifiers":[
        {
            "category":"Freight",
            "type":"Transportation"
        }
    ],
    "sg:phone":"+1 909 625 9294",
    "sg:postcode":"91711",
    "sg:province":"CA",
    "sg:tags":[
        "for",
        "company",
        "sales",
        "agent",
        "trucking",
        "commission"
    ],
    "wof:name":"Transport Sales",
    "wof:placetype":"venue"
},
  "geometry": {"coordinates":[-117.73267800000001,34.135918],"type":"Point"}
}