{
  "type": "Feature",
  "properties": {
    "iso:country":"US",
    "sg:address":"1733 Stratford Cir",
    "sg:city":"Redlands",
    "sg:classifiers":[
        {
            "category":"Wholesale",
            "subcategory":"Jewelry",
            "type":"Manufacturing & Wholesale Goods"
        }
    ],
    "sg:phone":"+1 951 659 9502",
    "sg:postcode":"92374",
    "sg:province":"CA",
    "wof:name":"Gemking Co",
    "wof:placetype":"venue"
},
  "geometry": {"coordinates":[-117.141773,34.058737],"type":"Point"}
}