{
  "type": "Feature",
  "properties": {
    "addr:full":"14208 Tiara St Van Nuys CA 91401",
    "addr:housenumber":"14208",
    "addr:postcode":"91401",
    "addr:street":"Tiara St",
    "iso:country":"US",
    "sg:address":"14208 Tiara St",
    "sg:city":"Van Nuys",
    "sg:classifiers":[
        {
            "category":"Arts & Performance",
            "subcategory":"Theater",
            "type":"Entertainment"
        }
    ],
    "sg:phone":"+1 818 989 2079",
    "sg:postcode":"91401",
    "sg:province":"CA",
    "sg:tags":[
        "program",
        "radio",
        "producer"
    ],
    "wof:name":"JTC Productions",
    "wof:placetype":"venue"
},
  "geometry": {"coordinates":[-118.44419600000001,34.178392],"type":"Point"}
}