{
  "type": "Feature",
  "properties": {
    "addr:full":"3220 Kurtz St San Diego CA 92110",
    "addr:housenumber":"3220",
    "addr:postcode":"92110",
    "addr:street":"Kurtz St",
    "iso:country":"US",
    "sg:address":"3220 Kurtz St",
    "sg:city":"San Diego",
    "sg:classifiers":[
        {
            "category":"Communications",
            "subcategory":"Newspaper",
            "type":"Services"
        }
    ],
    "sg:phone":"+1 619 291 5571",
    "sg:postcode":"92110",
    "sg:province":"CA",
    "sg:tags":[
        "print",
        "medium"
    ],
    "wof:name":"Vanard Lithographers Inc",
    "wof:placetype":"venue"
},
  "geometry": {"coordinates":[-117.206001,32.7537],"type":"Point"}
}