{
  "type": "Feature",
  "properties": {
    "addr:full":"535 N Brand Blvd Ste 270 Glendale CA 91203",
    "addr:housenumber":"535",
    "addr:postcode":"91203",
    "addr:street":"N Brand Blvd Ste 270",
    "iso:country":"US",
    "sg:address":"535 N Brand Blvd Ste 270",
    "sg:city":"Glendale",
    "sg:classifiers":[
        {
            "category":"Professional",
            "subcategory":"Lawyer & Legal Services",
            "type":"Services"
        }
    ],
    "sg:phone":"+1 818 552 6030",
    "sg:postcode":"91203",
    "sg:province":"CA",
    "wof:name":"Yeghiayan Vartkes Atty",
    "wof:placetype":"venue"
},
  "geometry": {"coordinates":[-118.254997,34.1535],"type":"Point"}
}