{
  "type": "Feature",
  "properties": {
    "addr:full":"2897 W Olympic Blvd Los Angeles CA 90006",
    "addr:housenumber":"2897",
    "addr:postcode":"90006",
    "addr:street":"W Olympic Blvd",
    "iso:country":"US",
    "sg:address":"2897 W Olympic Blvd",
    "sg:city":"Los Angeles",
    "sg:classifiers":[
        {
            "category":"Restaurant",
            "type":"Food & Drink"
        }
    ],
    "sg:menulink":"http://www.allmenus.com/ca/los-angeles/238772-yoshinoya/menu/",
    "sg:phone":"+1 213 382 0184",
    "sg:postcode":"90006",
    "sg:province":"CA",
    "sg:tags":[
        "korean",
        "noodle",
        "bar",
        "japanese",
        "asian"
    ],
    "wof:name":"Yoshinoya",
    "wof:placetype":"venue"
},
  "geometry": {"coordinates":[-118.297511,34.053003],"type":"Point"}
}