{
  "type": "Feature",
  "properties": {
    "addr:full":"1520 San Pablo St Los Angeles CA 90033",
    "addr:housenumber":"1520",
    "addr:postcode":"90033",
    "addr:street":"San Pablo St",
    "iso:country":"US",
    "sg:address":"1520 San Pablo St",
    "sg:city":"Los Angeles",
    "sg:classifiers":[
        {
            "category":"Health Services",
            "subcategory":"Doctor",
            "type":"Services"
        }
    ],
    "sg:phone":"+1 323 442 5860",
    "sg:postcode":"90033",
    "sg:province":"CA",
    "sg:tags":[
        "physician",
        "surgeon"
    ],
    "wof:name":"Michael J Patzakis MD",
    "wof:placetype":"venue"
},
  "geometry": {"coordinates":[-118.20348799999999,34.061302],"type":"Point"}
}