{
  "type": "Feature",
  "properties": {
    "addr:full":"524 Giuffrida Ave San Jose CA 95123",
    "addr:housenumber":"524",
    "addr:postcode":"95123",
    "addr:street":"Giuffrida Ave",
    "iso:country":"US",
    "sg:address":"524 Giuffrida Ave",
    "sg:city":"San Jose",
    "sg:classifiers":[
        {
            "category":"Retail",
            "subcategory":"Car Wash",
            "type":"Services"
        }
    ],
    "sg:phone":"+1 408 226 5120",
    "sg:postcode":"95123",
    "sg:province":"CA",
    "sg:tags":[
        "polishing",
        "washing"
    ],
    "wof:name":"Blossom Self Svc Car Wash",
    "wof:placetype":"venue"
},
  "geometry": {"coordinates":[-121.831142,37.253076],"type":"Point"}
}