{
  "type": "Feature",
  "properties": {
    "iso:country":"US",
    "sg:address":"43032 Christy St",
    "sg:city":"Fremont",
    "sg:classifiers":[
        {
            "category":"Professional",
            "subcategory":"Computer Services",
            "type":"Services"
        }
    ],
    "sg:phone":"+1 510 657 8666",
    "sg:postcode":"94538",
    "sg:province":"CA",
    "sg:tags":[
        "communications",
        "datum",
        "system"
    ],
    "sg:website":"www.nmnc.com",
    "wof:name":"Newmedia Networking Corp",
    "wof:placetype":"venue"
},
  "geometry": {"coordinates":[-121.971479,37.50578],"type":"Point"}
}