{
  "type": "Feature",
  "properties": {
    "addr:full":"28587 Country Rose Ln Menifee CA 92584",
    "addr:housenumber":"28587",
    "addr:postcode":"92584",
    "addr:street":"Country Rose Ln",
    "iso:country":"US",
    "sg:address":"28587 Country Rose Ln",
    "sg:city":"Menifee",
    "sg:classifiers":[
        {
            "category":"Wholesale",
            "subcategory":"Electrical",
            "type":"Manufacturing & Wholesale Goods"
        }
    ],
    "sg:phone":"+1 951 679 6702",
    "sg:postcode":"92584",
    "sg:province":"CA",
    "sg:tags":[
        "equipment"
    ],
    "wof:name":"Saddleback Lighting",
    "wof:placetype":"venue"
},
  "geometry": {"coordinates":[-117.161534,33.669896],"type":"Point"}
}