{
  "type": "Feature",
  "properties": {
    "addr:full":"3000 Danville Blvd Alamo CA 94507",
    "addr:housenumber":"3000",
    "addr:postcode":"94507",
    "addr:street":"Danville Blvd",
    "iso:country":"US",
    "sg:address":"3000 Danville Blvd",
    "sg:city":"Alamo",
    "sg:classifiers":[
        {
            "category":"Personal",
            "subcategory":"Beauty Salon",
            "type":"Services"
        }
    ],
    "sg:phone":"+1 925 362 4362",
    "sg:postcode":"94507",
    "sg:province":"CA",
    "wof:name":"Laura Collings Hair Design",
    "wof:placetype":"venue"
},
  "geometry": {"coordinates":[-122.045165,37.870523],"type":"Point"}
}