{
  "type": "Feature",
  "properties": {
    "iso:country":"US",
    "sg:address":"2114 W Chalet Ave",
    "sg:city":"Anaheim",
    "sg:classifiers":[
        {
            "category":"Building & Trades",
            "subcategory":"Plumbing",
            "type":"Services"
        }
    ],
    "sg:phone":"+1 714 776 2812",
    "sg:postcode":"92804",
    "sg:province":"CA",
    "sg:tags":[
        "contractor"
    ],
    "wof:name":"Mans Air Cond & Heating",
    "wof:placetype":"venue"
},
  "geometry": {"coordinates":[-117.956879,33.814785],"type":"Point"}
}