{
  "type": "Feature",
  "properties": {
    "addr:full":"4114 Cricket Trail Rd Vacaville CA 95688",
    "addr:housenumber":"4114",
    "addr:postcode":"95688",
    "addr:street":"Cricket Trail Rd",
    "iso:country":"US",
    "sg:address":"4114 Cricket Trail Rd",
    "sg:city":"Vacaville",
    "sg:classifiers":[
        {
            "category":"Building & Trades",
            "subcategory":"Construction",
            "type":"Services"
        }
    ],
    "sg:phone":"+1 707 455 8851",
    "sg:postcode":"95688",
    "sg:province":"CA",
    "sg:tags":[
        "handyman"
    ],
    "wof:name":"Joel Danforth Handyman Repair",
    "wof:placetype":"venue"
},
  "geometry": {"coordinates":[-121.99879,38.442336],"type":"Point"}
}