{
  "type": "Feature",
  "properties": {
    "addr:full":"727 N Wendy Dr Newbury Park CA 91320",
    "addr:housenumber":"727",
    "addr:postcode":"91320",
    "addr:street":"N Wendy Dr",
    "iso:country":"US",
    "sg:address":"727 N Wendy Dr",
    "sg:city":"Newbury Park",
    "sg:classifiers":[
        {
            "category":"Home & Garden",
            "subcategory":"Hardware",
            "type":"Retail Goods"
        }
    ],
    "sg:phone":"+1 805 498 3218",
    "sg:postcode":"91320",
    "sg:province":"CA",
    "wof:name":"Newbury Park Hardware",
    "wof:placetype":"venue"
},
  "geometry": {"coordinates":[-118.940229,34.188836],"type":"Point"}
}