{
  "type": "Feature",
  "properties": {
    "iso:country":"US",
    "sg:address":"1957 Eastman Ave",
    "sg:city":"Ventura",
    "sg:classifiers":[
        {
            "category":"Professional",
            "subcategory":"Research",
            "type":"Services"
        }
    ],
    "sg:phone":"+1 805 639 0000",
    "sg:postcode":"93003",
    "sg:province":"CA",
    "wof:name":"Barna Research Group LTD",
    "wof:placetype":"venue"
},
  "geometry": {"coordinates":[-119.229902,34.25149],"type":"Point"}
}