{
  "type": "Feature",
  "properties": {
    "addr:full":"39473 Fremont Blvd Fremont CA 94538",
    "addr:housenumber":"39473",
    "addr:postcode":"94538",
    "addr:street":"Fremont Blvd",
    "iso:country":"US",
    "sg:address":"39473 Fremont Blvd",
    "sg:city":"Fremont",
    "sg:classifiers":[
        {
            "category":"Restaurant",
            "type":"Food & Drink"
        }
    ],
    "sg:phone":"+1 510 623 9393",
    "sg:postcode":"94538",
    "sg:province":"CA",
    "wof:name":"China Express Restaurant",
    "wof:placetype":"venue"
},
  "geometry": {"coordinates":[-121.981185,37.544776],"type":"Point"}
}