{
  "type": "Feature",
  "properties": {
    "addr:full":"8015 Deering Ave Canoga Park CA 91303",
    "addr:housenumber":"8015",
    "addr:postcode":"91303",
    "addr:street":"Deering Ave",
    "iso:country":"US",
    "sg:address":"8015 Deering Ave",
    "sg:city":"Canoga Park",
    "sg:classifiers":[
        {
            "category":"Shopping",
            "type":"Retail Goods"
        }
    ],
    "sg:phone":"+1 951 343 7900",
    "sg:postcode":"91303",
    "sg:province":"CA",
    "sg:tags":[
        "equipment",
        "supply"
    ],
    "wof:name":"Lo-Car Inland Empire",
    "wof:placetype":"venue"
},
  "geometry": {"coordinates":[-118.59512599999999,34.215947],"type":"Point"}
}