{
  "type": "Feature",
  "properties": {
    "iso:country":"US",
    "sg:address":"539 Broadway Ste D",
    "sg:city":"Sonoma",
    "sg:classifiers":[
        {
            "category":"Health Services",
            "subcategory":"Doctor",
            "type":"Services"
        }
    ],
    "sg:phone":"+1 707 996 5724",
    "sg:postcode":"95476",
    "sg:province":"CA",
    "sg:tags":[
        "psychiatry",
        "physician",
        "surgeon",
        "surgeons"
    ],
    "wof:name":"Mavis, Nancy A Md Psychiatrist",
    "wof:placetype":"venue"
},
  "geometry": {"coordinates":[-122.457902,38.291308],"type":"Point"}
}