{
  "type": "Feature",
  "properties": {
    "iso:country":"US",
    "sg:address":"1634 Taraval St",
    "sg:city":"San Francisco",
    "sg:classifiers":[
        {
            "category":"Retail",
            "subcategory":"Auto Repair",
            "type":"Services"
        }
    ],
    "sg:phone":"+1 415 731 8144",
    "sg:postcode":"94116",
    "sg:province":"CA",
    "sg:tags":[
        "body",
        "shop"
    ],
    "sg:website":"www.andresfcs.com/",
    "wof:name":"Andre's Foreign Car Service",
    "wof:placetype":"venue"
},
  "geometry": {"coordinates":[-122.483879,37.742766],"type":"Point"}
}