{
  "type": "Feature",
  "properties": {
    "addr:full":"305 S Maple St Corona CA 92880",
    "addr:housenumber":"305",
    "addr:postcode":"92880",
    "addr:street":"S Maple St",
    "iso:country":"US",
    "sg:address":"305 S Maple St",
    "sg:city":"Corona",
    "sg:classifiers":[
        {
            "category":"Professional",
            "subcategory":"Engineering",
            "type":"Services"
        }
    ],
    "sg:phone":"+1 951 736 3056",
    "sg:postcode":"92880",
    "sg:province":"CA",
    "sg:tags":[
        "engineer"
    ],
    "wof:name":"Madison Engineering",
    "wof:placetype":"venue"
},
  "geometry": {"coordinates":[-117.603449,33.881952],"type":"Point"}
}