{
  "type": "Feature",
  "properties": {
    "addr:full":"2200 County Center Dr Santa Rosa CA 95403",
    "addr:housenumber":"2200",
    "addr:postcode":"95403",
    "addr:street":"County Center Dr",
    "iso:country":"US",
    "sg:address":"2200 County Center Dr",
    "sg:city":"Santa Rosa",
    "sg:classifiers":[
        {
            "category":"Professional",
            "type":"Services"
        }
    ],
    "sg:phone":"+1 707 578 1700",
    "sg:postcode":"95403",
    "sg:province":"CA",
    "sg:tags":[
        "establishment"
    ],
    "wof:name":"Abortion Birth Control",
    "wof:placetype":"venue"
},
  "geometry": {"coordinates":[-122.726101,38.463102],"type":"Point"}
}