{
  "type": "Feature",
  "properties": {
    "addr:full":"7556 Fay Avenue La Jolla CA 92037",
    "addr:housenumber":"7556",
    "addr:postcode":"92037",
    "addr:street":"Fay Avenue",
    "iso:country":"US",
    "sg:address":"7556 Fay Avenue",
    "sg:city":"La Jolla",
    "sg:classifiers":[
        {
            "category":"Restaurant",
            "type":"Food & Drink"
        }
    ],
    "sg:phone":"+1 858 875 7737",
    "sg:postcode":"92037",
    "sg:province":"CA",
    "sg:tags":[
        "new",
        "american"
    ],
    "sg:website":"www.prepkitchen.com",
    "wof:name":"Prepkitchen",
    "wof:placetype":"venue"
},
  "geometry": {"coordinates":[-117.274452,32.841324],"type":"Point"}
}