{
  "type": "Feature",
  "properties": {
    "addr:full":"164 Maple St., Ste. 1 Auburn CA 95603",
    "addr:housenumber":"164",
    "addr:postcode":"ca 95603",
    "addr:street":"Maple St. Ste. 1",
    "iso:country":"US",
    "sg:address":"164 Maple St., Ste. 1",
    "sg:city":"Auburn",
    "sg:classifiers":[
        {
            "category":"Banks & Credit Unions",
            "subcategory":"Investment Brokerage",
            "type":"Services"
        },
        {
            "category":"Banks & Credit Unions",
            "subcategory":"Financial Services",
            "type":"Services"
        }
    ],
    "sg:phone":"+1 530 823 2792",
    "sg:postcode":"95603",
    "sg:province":"CA",
    "sg:tags":[
        "management"
    ],
    "sg:website":"http://www.mkbfinancial.com",
    "wof:name":"MKB Financial Services, Inc.",
    "wof:placetype":"venue"
},
  "geometry": {"coordinates":[-121.077696,38.896945],"type":"Point"}
}