{
  "type": "Feature",
  "properties": {
    "iso:country":"US",
    "sg:address":"19328 Drycliff St",
    "sg:city":"Canyon Country",
    "sg:classifiers":[
        {
            "category":"Real Estate",
            "subcategory":"Real Estate Agent",
            "type":"Services"
        }
    ],
    "sg:phone":"+1 661 250 4522",
    "sg:postcode":"91351",
    "sg:province":"CA",
    "wof:name":"National 50 Real Estate Inspec",
    "wof:placetype":"venue"
},
  "geometry": {"coordinates":[-118.472707,34.421478],"type":"Point"}
}