{
  "type": "Feature",
  "properties": {
    "addr:full":"236 Shops At Mission Viejo Mission Viejo CA 92692",
    "addr:housenumber":"236",
    "addr:postcode":"92692",
    "addr:street":"Shops At Mission",
    "iso:country":"US",
    "sg:address":"236 Shops At Mission Viejo",
    "sg:city":"Mission Viejo",
    "sg:classifiers":[
        {
            "category":"Cinema",
            "subcategory":"Movie Rental",
            "type":"Entertainment"
        },
        {
            "category":"Shopping",
            "subcategory":"Music",
            "type":"Retail Goods"
        }
    ],
    "sg:phone":"+1 949 347 8692",
    "sg:postcode":"92692",
    "sg:province":"CA",
    "sg:tags":[
        "game",
        "video",
        "dvd's"
    ],
    "wof:name":"GameStop",
    "wof:placetype":"venue"
},
  "geometry": {"coordinates":[-117.66911500000001,33.560819],"type":"Point"}
}