{
  "type": "Feature",
  "properties": {
    "iso:country":"US",
    "sg:address":"13615 Leffingwell Rd",
    "sg:city":"Whittier",
    "sg:classifiers":[
        {
            "category":"Professional",
            "subcategory":"Management & Consulting",
            "type":"Services"
        }
    ],
    "sg:phone":"+1 562 946 4458",
    "sg:postcode":"90605",
    "sg:province":"CA",
    "sg:tags":[
        "communications",
        "consultant"
    ],
    "wof:name":"L & P Interprice",
    "wof:placetype":"venue"
},
  "geometry": {"coordinates":[-118.041768,33.919893],"type":"Point"}
}