{
  "type": "Feature",
  "properties": {
    "addr:full":"539 44th Ave San Francisco CA 94121",
    "addr:housenumber":"539",
    "addr:postcode":"94121",
    "addr:street":"44Th Ave",
    "iso:country":"US",
    "sg:address":"539 44th Ave",
    "sg:city":"San Francisco",
    "sg:classifiers":[
        {
            "category":"Building & Trades",
            "subcategory":"Electrical",
            "type":"Services"
        }
    ],
    "sg:phone":"+1 415 221 6655",
    "sg:postcode":"94121",
    "sg:province":"CA",
    "sg:tags":[
        "telecommunication",
        "contractor"
    ],
    "wof:name":"Casey Communications",
    "wof:placetype":"venue"
},
  "geometry": {"coordinates":[-122.50506900000001,37.77798],"type":"Point"}
}