{
  "type": "Feature",
  "properties": {
    "addr:full":"1957 Elizondo Ave Simi Valley CA 93065",
    "addr:housenumber":"1957",
    "addr:postcode":"93065",
    "addr:street":"Elizondo Ave",
    "iso:country":"US",
    "sg:address":"1957 Elizondo Ave",
    "sg:city":"Simi Valley",
    "sg:classifiers":[
        {
            "category":"Home & Garden",
            "subcategory":"Building Materials",
            "type":"Retail Goods"
        }
    ],
    "sg:phone":"+1 805 526 6517",
    "sg:postcode":"93065",
    "sg:province":"CA",
    "sg:tags":[
        "insulation",
        "heat"
    ],
    "wof:name":"Nitron Industries",
    "wof:placetype":"venue"
},
  "geometry": {"coordinates":[-118.759291,34.264987],"type":"Point"}
}