{
  "type": "Feature",
  "properties": {
    "iso:country":"US",
    "sg:address":"42198 Ave Alvarado",
    "sg:city":"Temecula",
    "sg:classifiers":[
        {
            "category":"Wholesale",
            "subcategory":"Auto Parts",
            "type":"Manufacturing & Wholesale Goods"
        }
    ],
    "sg:phone":"+1 951 296 1171",
    "sg:postcode":"92590",
    "sg:province":"CA",
    "sg:tags":[
        "tire"
    ],
    "wof:name":"Sport Tire's Of America",
    "wof:placetype":"venue"
},
  "geometry": {"coordinates":[-117.171153,33.509495],"type":"Point"}
}