{
  "type": "Feature",
  "properties": {
    "addr:full":"39168 State St Fremont CA 94538",
    "addr:housenumber":"39168",
    "addr:postcode":"94538",
    "addr:street":"State St",
    "iso:country":"US",
    "sg:address":"39168 State St",
    "sg:city":"Fremont",
    "sg:classifiers":[
        {
            "category":"Personal",
            "subcategory":"Massage",
            "type":"Services"
        }
    ],
    "sg:phone":"+1 510 713 8808",
    "sg:postcode":"94538",
    "sg:province":"CA",
    "wof:name":"East Bay Healthcare Ctr",
    "wof:placetype":"venue"
},
  "geometry": {"coordinates":[-121.98288700000001,37.549227],"type":"Point"}
}