{
  "type": "Feature",
  "properties": {
    "addr:full":"200 Monterey Ave Capitola CA 95010",
    "addr:housenumber":"200",
    "addr:postcode":"95010",
    "addr:street":"Monterey Ave",
    "iso:country":"US",
    "sg:address":"200 Monterey Ave",
    "sg:city":"Capitola",
    "sg:classifiers":[
        {
            "category":"Shopping",
            "type":"Retail Goods"
        }
    ],
    "sg:phone":"+1 831 476 6000",
    "sg:postcode":"95010",
    "sg:province":"CA",
    "sg:tags":[
        "candle"
    ],
    "wof:name":"Luminescence",
    "wof:placetype":"venue"
},
  "geometry": {"coordinates":[-121.950998,36.971881],"type":"Point"}
}