{
  "type": "Feature",
  "properties": {
    "iso:country":"US",
    "sg:address":"39112 3rd St E",
    "sg:city":"Palmdale",
    "sg:classifiers":[
        {
            "category":"Building & Trades",
            "subcategory":"Construction",
            "type":"Services"
        }
    ],
    "sg:phone":"+1 661 273 5008",
    "sg:postcode":"93550",
    "sg:province":"CA",
    "sg:tags":[
        "concrete",
        "contractor"
    ],
    "wof:name":"Mike Rice Trenching",
    "wof:placetype":"venue"
},
  "geometry": {"coordinates":[-118.125305,34.592219],"type":"Point"}
}