{
  "type": "Feature",
  "properties": {
    "addr:full":"2234 Auburn Boulevard Sacramento CA 95821",
    "addr:housenumber":"2234",
    "addr:postcode":"95821",
    "addr:street":"Auburn Boulevard",
    "iso:country":"US",
    "sg:address":"2234 Auburn Boulevard",
    "sg:city":"Sacramento",
    "sg:classifiers":[
        {
            "category":"Shopping",
            "subcategory":"Hobbies, Toys, & Games",
            "type":"Retail Goods"
        }
    ],
    "sg:phone":"+1 916 925 7552",
    "sg:postcode":"95821",
    "sg:province":"CA",
    "sg:tags":[
        "shop",
        "hobby"
    ],
    "wof:name":"Capitol Billiard",
    "wof:placetype":"venue"
},
  "geometry": {"coordinates":[-121.414559,38.624731],"type":"Point"}
}