{
  "type": "Feature",
  "properties": {
    "addr:full":"33980 S River Rd Clarksburg CA 95612",
    "addr:housenumber":"33980",
    "addr:postcode":"95612",
    "addr:street":"S River Rd",
    "iso:country":"US",
    "sg:address":"33980 S River Rd",
    "sg:city":"Clarksburg",
    "sg:classifiers":[
        {
            "category":"Professional",
            "subcategory":"Management & Consulting",
            "type":"Services"
        }
    ],
    "sg:phone":"+1 916 665 2190",
    "sg:postcode":"95612",
    "sg:province":"CA",
    "sg:tags":[
        "agricultural",
        "consultant"
    ],
    "wof:name":"Johas & Assoc",
    "wof:placetype":"venue"
},
  "geometry": {"coordinates":[-121.505196,38.46269],"type":"Point"}
}