{
  "type": "Feature",
  "properties": {
    "addr:full":"1610 3rd St Wasco CA 93280",
    "addr:housenumber":"1610",
    "addr:postcode":"ca 93280",
    "addr:street":"3Rd St",
    "iso:country":"US",
    "sg:address":"1610 3rd St",
    "sg:city":"Wasco",
    "sg:classifiers":[
        {
            "category":"Organizations",
            "subcategory":"Religious Organization",
            "type":"Services"
        }
    ],
    "sg:phone":"+1 661 758 5515",
    "sg:postcode":"93280",
    "sg:province":"CA",
    "sg:tags":[
        "church"
    ],
    "wof:name":"Central Missionary Baptist Chr",
    "wof:placetype":"venue"
},
  "geometry": {"coordinates":[-119.343788,35.598895],"type":"Point"}
}