{
  "type": "Feature",
  "properties": {
    "addr:full":"9262 Bolsa Ave Westminster CA 92683",
    "addr:housenumber":"9262",
    "addr:postcode":"92683",
    "addr:street":"Bolsa Ave",
    "iso:country":"US",
    "sg:address":"9262 Bolsa Ave",
    "sg:city":"Westminster",
    "sg:classifiers":[
        {
            "category":"Restaurant",
            "type":"Food & Drink"
        }
    ],
    "sg:phone":"+1 714 895 6551",
    "sg:postcode":"92683",
    "sg:province":"CA",
    "sg:tags":[
        "vietnamese"
    ],
    "wof:name":"Huong Huong Food To Go-Bakery",
    "wof:placetype":"venue"
},
  "geometry": {"coordinates":[-117.967612,33.744491],"type":"Point"}
}