{
  "type": "Feature",
  "properties": {
    "iso:country":"US",
    "sg:address":"1530 Meridian Ave",
    "sg:city":"San Jose",
    "sg:classifiers":[
        {
            "category":"Real Estate",
            "subcategory":"Real Estate Agent",
            "type":"Services"
        }
    ],
    "sg:phone":"+1 408 243 7286",
    "sg:postcode":"95125",
    "sg:province":"CA",
    "sg:tags":[
        "appraiser"
    ],
    "wof:name":"J M Appraisal Svc",
    "wof:placetype":"venue"
},
  "geometry": {"coordinates":[-121.913483,37.296626],"type":"Point"}
}