{
  "type": "Feature",
  "properties": {
    "iso:country":"US",
    "sg:address":"600 Nesmith Ct",
    "sg:city":"Folsom",
    "sg:classifiers":[
        {
            "category":"Freight",
            "type":"Transportation"
        }
    ],
    "sg:phone":"+1 916 984 1000",
    "sg:postcode":"95630",
    "sg:province":"CA",
    "sg:tags":[
        "commercial",
        "storage"
    ],
    "wof:name":"Folsom Self Storage",
    "wof:placetype":"venue"
},
  "geometry": {"coordinates":[-121.130802,38.659987],"type":"Point"}
}