{
  "type": "Feature",
  "properties": {
    "iso:country":"US",
    "sg:address":"20561 Pascal Way",
    "sg:city":"Lake Forest",
    "sg:classifiers":[
        {
            "category":"Wholesale",
            "subcategory":"Durable Goods & Equipment",
            "type":"Manufacturing & Wholesale Goods"
        }
    ],
    "sg:phone":"+1 949 951 0600",
    "sg:postcode":"92630",
    "sg:province":"CA",
    "sg:tags":[
        "blind",
        "shade"
    ],
    "sg:website":"www.gwshutters.com",
    "wof:name":"Golden West Custom Wood Shutters",
    "wof:placetype":"venue"
},
  "geometry": {"coordinates":[-117.668999,33.662899],"type":"Point"}
}