{
  "type": "Feature",
  "properties": {
    "iso:country":"US",
    "sg:address":"501 Fair St",
    "sg:city":"Petaluma",
    "sg:classifiers":[
        {
            "category":"Building & Trades",
            "subcategory":"Construction",
            "type":"Services"
        }
    ],
    "sg:phone":"+1 707 778 6567",
    "sg:postcode":"94952",
    "sg:province":"CA",
    "sg:tags":[
        "residential"
    ],
    "wof:name":"Ce Construction",
    "wof:placetype":"venue"
},
  "geometry": {"coordinates":[-122.6493,38.2305],"type":"Point"}
}