{
  "type": "Feature",
  "properties": {
    "iso:country":"US",
    "sg:address":"725 W Town and Country Rd",
    "sg:city":"Orange",
    "sg:classifiers":[
        {
            "category":"Insurance",
            "subcategory":"Life Insurance",
            "type":"Services"
        }
    ],
    "sg:phone":"+1 714 750 7900",
    "sg:postcode":"92868",
    "sg:province":"CA",
    "sg:tags":[
        "carrier"
    ],
    "wof:name":"Fremont Leasing Corp",
    "wof:placetype":"venue"
},
  "geometry": {"coordinates":[-117.86283299999999,33.77692],"type":"Point"}
}