{
  "type": "Feature",
  "properties": {
    "addr:full":"2236 Foothill Blvd La Canada Flintridge CA 91011",
    "addr:housenumber":"2236",
    "addr:postcode":"91011",
    "addr:street":"Foothill Blvd",
    "iso:country":"US",
    "sg:address":"2236 Foothill Blvd",
    "sg:city":"La Canada Flintridge",
    "sg:classifiers":[
        {
            "category":"Restaurant",
            "type":"Food & Drink"
        }
    ],
    "sg:phone":"+1 818 957 1122",
    "sg:postcode":"91011",
    "sg:province":"CA",
    "sg:tags":[
        "sushi",
        "bar",
        "japanese"
    ],
    "wof:name":"Yuki Yama Japanese Restaurant",
    "wof:placetype":"venue"
},
  "geometry": {"coordinates":[-118.226421,34.216421],"type":"Point"}
}