{
  "type": "Feature",
  "properties": {
    "addr:full":"1605 Evans Rd Ceres CA 95307",
    "addr:housenumber":"1605",
    "addr:postcode":"95307",
    "addr:street":"Evans Rd",
    "iso:country":"US",
    "sg:address":"1605 Evans Rd",
    "sg:city":"Ceres",
    "sg:classifiers":[
        {
            "category":"Building & Trades",
            "subcategory":"Plumbing",
            "type":"Services"
        }
    ],
    "sg:phone":"+1 209 537 1195",
    "sg:postcode":"95307",
    "sg:province":"CA",
    "sg:tags":[
        "plumbing",
        "contractor"
    ],
    "wof:name":"Stephens Plumbing",
    "wof:placetype":"venue"
},
  "geometry": {"coordinates":[-120.96614599999999,37.602803],"type":"Point"}
}