{
  "type": "Feature",
  "properties": {
    "addr:full":"125 Rockwood Ave Calexico CA 92231",
    "addr:housenumber":"125",
    "addr:postcode":"92231",
    "addr:street":"Rockwood Ave",
    "iso:country":"US",
    "sg:address":"125 Rockwood Ave",
    "sg:city":"Calexico",
    "sg:classifiers":[
        {
            "category":"Shopping",
            "subcategory":"Clothing, Apparel, & Fashions",
            "type":"Retail Goods"
        }
    ],
    "sg:phone":"+1 760 357 0686",
    "sg:postcode":"92231",
    "sg:province":"CA",
    "sg:tags":[
        "sportswear"
    ],
    "wof:name":"L A Fashion",
    "wof:placetype":"venue"
},
  "geometry": {"coordinates":[-115.496359,32.666428],"type":"Point"}
}