{
  "type": "Feature",
  "properties": {
    "addr:full":"43033 Hwy 49 Ahwahnee CA 93601",
    "addr:housenumber":"43033",
    "addr:postcode":"93601",
    "addr:street":"Hwy 49",
    "iso:country":"US",
    "sg:address":"43033 Hwy 49",
    "sg:city":"Ahwahnee",
    "sg:classifiers":[
        {
            "category":"Government",
            "subcategory":"Fire Station",
            "type":"Public Place"
        }
    ],
    "sg:phone":"+1 559 683 4844",
    "sg:postcode":"93601",
    "sg:province":"CA",
    "sg:tags":[
        "state",
        "protection"
    ],
    "wof:name":"Ahwahnee Forest Fire Station",
    "wof:placetype":"venue"
},
  "geometry": {"coordinates":[-119.729784,37.375092],"type":"Point"}
}