{
  "type": "Feature",
  "properties": {
    "addr:full":"845 Bates Avenue El Cerrito CA 94530",
    "addr:housenumber":"845",
    "addr:postcode":"94530",
    "addr:street":"Bates Avenue",
    "iso:country":"US",
    "sg:address":"845 Bates Avenue",
    "sg:city":"El Cerrito",
    "sg:classifiers":[
        {
            "category":"Building & Trades",
            "subcategory":"Construction",
            "type":"Services"
        }
    ],
    "sg:phone":"+1 510 559 1824",
    "sg:postcode":"94530",
    "sg:province":"CA",
    "sg:tags":[
        "contractor"
    ],
    "wof:name":"Chapman & Gough",
    "wof:placetype":"venue"
},
  "geometry": {"coordinates":[-122.28800200000001,37.9179],"type":"Point"}
}