{
  "type": "Feature",
  "properties": {
    "iso:country":"US",
    "sg:address":"23717 State Rte 26",
    "sg:city":"West Point",
    "sg:classifiers":[
        {
            "category":"Organizations",
            "subcategory":"Religious Organization",
            "type":"Services"
        }
    ],
    "sg:phone":"+1 209 293 4161",
    "sg:postcode":"95255",
    "sg:province":"CA",
    "sg:tags":[
        "church"
    ],
    "wof:name":"Church Of The Living Word",
    "wof:placetype":"venue"
},
  "geometry": {"coordinates":[-120.541473,38.413165],"type":"Point"}
}