{
  "type": "Feature",
  "properties": {
    "addr:full":"5500 E Olympic Blvd Los Angeles CA 90022",
    "addr:housenumber":"5500",
    "addr:postcode":"90022",
    "addr:street":"E Olympic Blvd",
    "iso:country":"US",
    "sg:address":"5500 E Olympic Blvd",
    "sg:city":"Los Angeles",
    "sg:classifiers":[
        {
            "category":"Wholesale",
            "subcategory":"Non-durable Goods",
            "type":"Manufacturing & Wholesale Goods"
        }
    ],
    "sg:phone":"+1 562 883 8843",
    "sg:postcode":"90022",
    "sg:province":"CA",
    "wof:name":"Shye USA",
    "wof:placetype":"venue"
},
  "geometry": {"coordinates":[-118.15445800000001,34.01537],"type":"Point"}
}