{
  "type": "Feature",
  "properties": {
    "iso:country":"US",
    "sg:address":"45 Auto Center Dr Ste 108",
    "sg:city":"Foothill Ranch",
    "sg:classifiers":[
        {
            "category":"Building & Trades",
            "subcategory":"Construction",
            "type":"Services"
        }
    ],
    "sg:phone":"+1 949 273 8228",
    "sg:postcode":"92610",
    "sg:province":"CA",
    "sg:tags":[
        "interior",
        "design"
    ],
    "sg:website":"www.ilonabydezign.com",
    "wof:name":"Ilona By Dezign Inc",
    "wof:placetype":"venue"
},
  "geometry": {"coordinates":[-117.661742,33.676044],"type":"Point"}
}