{
  "type": "Feature",
  "properties": {
    "addr:full":"1139 S Placentia Ave Fullerton CA 92831",
    "addr:housenumber":"1139",
    "addr:postcode":"92831",
    "addr:street":"S Placentia Ave",
    "iso:country":"US",
    "sg:address":"1139 S Placentia Ave",
    "sg:city":"Fullerton",
    "sg:classifiers":[
        {
            "category":"Building & Trades",
            "subcategory":"Pest Control",
            "type":"Services"
        }
    ],
    "sg:phone":"+1 714 441 2285",
    "sg:postcode":"92831",
    "sg:province":"CA",
    "wof:name":"Builders Termite & Pest Control",
    "wof:placetype":"venue"
},
  "geometry": {"coordinates":[-117.882983,33.860785],"type":"Point"}
}