{
  "type": "Feature",
  "properties": {
    "addr:full":"939 Eddy St San Francisco CA 94109",
    "addr:housenumber":"939",
    "addr:postcode":"94109",
    "addr:street":"Eddy St",
    "iso:country":"US",
    "sg:address":"939 Eddy St",
    "sg:city":"San Francisco",
    "sg:classifiers":[
        {
            "category":"Real Estate",
            "subcategory":"Real Estate Agent",
            "type":"Services"
        }
    ],
    "sg:phone":"+1 415 929 5612",
    "sg:postcode":"94109",
    "sg:province":"CA",
    "sg:tags":[
        "authorities",
        "housing"
    ],
    "wof:name":"Housing Authority Site Office",
    "wof:placetype":"venue"
},
  "geometry": {"coordinates":[-122.423592,37.78248],"type":"Point"}
}