{
  "type": "Feature",
  "properties": {
    "addr:full":"11136 Long Beach Boulevard Lynwood CA 90262",
    "addr:housenumber":"11136",
    "addr:postcode":"90262",
    "addr:street":"Long Beach Boulevard",
    "iso:country":"US",
    "sg:address":"11136 Long Beach Boulevard",
    "sg:city":"Lynwood",
    "sg:classifiers":[
        {
            "category":"Restaurant",
            "type":"Food & Drink"
        }
    ],
    "sg:phone":"+1 310 638 1469",
    "sg:postcode":"90262",
    "sg:province":"CA",
    "wof:name":"Chinatown Express No 18",
    "wof:placetype":"venue"
},
  "geometry": {"coordinates":[-118.211625,33.930463],"type":"Point"}
}