{
  "type": "Feature",
  "properties": {
    "iso:country":"US",
    "sg:address":"2481 Berryessa Rd",
    "sg:city":"San Jose",
    "sg:classifiers":[
        {
            "category":"Fast Food",
            "type":"Food & Drink"
        },
        {
            "category":"Restaurant",
            "type":"Food & Drink"
        }
    ],
    "sg:postcode":"95133",
    "sg:province":"CA",
    "sg:tags":[
        "mexican"
    ],
    "sg:website":"www.tacobell.com",
    "wof:name":"Taco Bell",
    "wof:placetype":"venue"
},
  "geometry": {"coordinates":[-121.860865,37.386456],"type":"Point"}
}