{
  "type": "Feature",
  "properties": {
    "addr:full":"10801 S Prairie Ave Inglewood CA 90303",
    "addr:housenumber":"10801",
    "addr:postcode":"90303",
    "addr:street":"S Prairie Ave",
    "iso:country":"US",
    "sg:address":"10801 S Prairie Ave",
    "sg:city":"Inglewood",
    "sg:classifiers":[
        {
            "category":"Food & Beverages",
            "subcategory":"Groceries & Convenience Stores",
            "type":"Retail Goods"
        }
    ],
    "sg:phone":"+1 310 671 5913",
    "sg:postcode":"90303",
    "sg:province":"CA",
    "sg:tags":[
        "grocer",
        "liquor"
    ],
    "wof:name":"City Farm Market",
    "wof:placetype":"venue"
},
  "geometry": {"coordinates":[-118.344002,33.9375],"type":"Point"}
}