{
  "type": "Feature",
  "properties": {
    "iso:country":"US",
    "sg:address":"1124 Buchanan Rd",
    "sg:city":"Antioch",
    "sg:classifiers":[
        {
            "category":"Building & Trades",
            "subcategory":"Construction",
            "type":"Services"
        }
    ],
    "sg:phone":"+1 925 757 5201",
    "sg:postcode":"94509",
    "sg:province":"CA",
    "sg:tags":[
        "paper",
        "painting",
        "hanging"
    ],
    "wof:name":"Dewhitt Painting",
    "wof:placetype":"venue"
},
  "geometry": {"coordinates":[-121.82969,38.000419],"type":"Point"}
}