{
  "type": "Feature",
  "properties": {
    "addr:full":"33 Steven Dr Petaluma CA 94952",
    "addr:housenumber":"33",
    "addr:postcode":"94952",
    "addr:street":"Steven Dr",
    "iso:country":"US",
    "sg:address":"33 Steven Dr",
    "sg:city":"Petaluma",
    "sg:classifiers":[
        {
            "category":"Building & Trades",
            "subcategory":"Construction",
            "type":"Services"
        }
    ],
    "sg:phone":"+1 707 765 9933",
    "sg:postcode":"94952",
    "sg:province":"CA",
    "sg:tags":[
        "contractor"
    ],
    "wof:name":"Starke Structure",
    "wof:placetype":"venue"
},
  "geometry": {"coordinates":[-122.624591,38.223298],"type":"Point"}
}