{
  "type": "Feature",
  "properties": {
    "iso:country":"US",
    "sg:address":"21301 Lake Shore Dr",
    "sg:city":"California City",
    "sg:classifiers":[
        {
            "category":"Wholesale",
            "subcategory":"Auto Parts",
            "type":"Manufacturing & Wholesale Goods"
        }
    ],
    "sg:phone":"+1 760 373 8233",
    "sg:postcode":"93505",
    "sg:province":"CA",
    "sg:tags":[
        "automobile",
        "rebuilt"
    ],
    "wof:name":"Robert Crowder",
    "wof:placetype":"venue"
},
  "geometry": {"coordinates":[-117.94154899999999,35.13227],"type":"Point"}
}