{
  "type": "Feature",
  "properties": {
    "addr:full":"250 Clay St San Francisco CA 94199",
    "addr:housenumber":"250",
    "addr:postcode":"94199",
    "addr:street":"Clay St",
    "iso:country":"US",
    "sg:address":"250 Clay St",
    "sg:city":"San Francisco",
    "sg:classifiers":[
        {
            "category":"Retail",
            "subcategory":"Laundry & Dry Cleaning",
            "type":"Services"
        }
    ],
    "sg:phone":"+1 415 255 7500",
    "sg:postcode":"94199",
    "sg:province":"CA",
    "sg:website":"www.laundrylocker.com",
    "wof:name":"Laundry Locker",
    "wof:placetype":"venue"
},
  "geometry": {"coordinates":[-122.39847399999999,37.795696],"type":"Point"}
}