{
  "type": "Feature",
  "properties": {
    "addr:full":"15151 Foothill Blvd Fontana CA 92335",
    "addr:housenumber":"15151",
    "addr:postcode":"92335",
    "addr:street":"Foothill Blvd",
    "iso:country":"US",
    "sg:address":"15151 Foothill Blvd",
    "sg:city":"Fontana",
    "sg:classifiers":[
        {
            "category":"Retail",
            "subcategory":"Auto Rental",
            "type":"Services"
        }
    ],
    "sg:phone":"+1 909 823 7777",
    "sg:postcode":"92335",
    "sg:province":"CA",
    "sg:tags":[
        "renting",
        "automobile"
    ],
    "wof:name":"First Rental",
    "wof:placetype":"venue"
},
  "geometry": {"coordinates":[-117.472258,34.106424],"type":"Point"}
}