{
  "type": "Feature",
  "properties": {
    "addr:full":"580 Hawthorne Ave Palo Alto CA 94301",
    "addr:housenumber":"580",
    "addr:postcode":"94301",
    "addr:street":"Hawthorne Ave",
    "iso:country":"US",
    "sg:address":"580 Hawthorne Ave",
    "sg:city":"Palo Alto",
    "sg:classifiers":[
        {
            "category":"Real Estate",
            "subcategory":"Architect",
            "type":"Services"
        }
    ],
    "sg:phone":"+1 650 323 5961",
    "sg:postcode":"94301",
    "sg:province":"CA",
    "wof:name":"Lippert & Lippert Design",
    "wof:placetype":"venue"
},
  "geometry": {"coordinates":[-122.162031,37.451436],"type":"Point"}
}