{
  "type": "Feature",
  "properties": {
    "iso:country":"US",
    "sg:address":"1550 S Sunkist St",
    "sg:city":"Anaheim",
    "sg:classifiers":[
        {
            "category":"Retail",
            "subcategory":"Repair Shop",
            "type":"Services"
        },
        {
            "category":"Building & Trades",
            "subcategory":"Construction",
            "type":"Services"
        }
    ],
    "sg:phone":"+1 714 939 6516",
    "sg:postcode":"92806",
    "sg:province":"CA",
    "sg:tags":[
        "equipment",
        "installation",
        "elevator"
    ],
    "sg:website":"www.abm.com",
    "wof:name":"Amtech Elevator Svc",
    "wof:placetype":"venue"
},
  "geometry": {"coordinates":[-117.88379399999999,33.809185],"type":"Point"}
}