{
  "type": "Feature",
  "properties": {
    "addr:full":"1520 Butte House Rd Yuba City CA 95993",
    "addr:housenumber":"1520",
    "addr:postcode":"95993",
    "addr:street":"Butte House Rd",
    "iso:country":"US",
    "sg:address":"1520 Butte House Rd",
    "sg:city":"Yuba City",
    "sg:classifiers":[
        {
            "category":"Ice Cream",
            "type":"Food & Drink"
        }
    ],
    "sg:menulink":"http://www.allmenus.com/ca/yuba-city/230275-marble-slab-creamery/menu/",
    "sg:phone":"+1 530 822 9976",
    "sg:postcode":"95993",
    "sg:province":"CA",
    "sg:tags":[
        "american"
    ],
    "wof:name":"Marble Slab Creamery",
    "wof:placetype":"venue"
},
  "geometry": {"coordinates":[-121.642132,39.147528],"type":"Point"}
}