{
  "type": "Feature",
  "properties": {
    "addr:full":"25231 Pso de Alicia Laguna Hills CA 92653",
    "addr:housenumber":"25231",
    "addr:postcode":"92653",
    "addr:street":"Pso De Alicia",
    "iso:country":"US",
    "sg:address":"25231 Pso de Alicia",
    "sg:city":"Laguna Hills",
    "sg:classifiers":[
        {
            "category":"Professional",
            "subcategory":"Accounting & Tax Preparation",
            "type":"Services"
        }
    ],
    "sg:phone":"+1 949 581 2555",
    "sg:postcode":"92653",
    "sg:province":"CA",
    "sg:tags":[
        "accountant"
    ],
    "wof:name":"Kenefick & Favor",
    "wof:placetype":"venue"
},
  "geometry": {"coordinates":[-117.690836,33.601963],"type":"Point"}
}