{
  "type": "Feature",
  "properties": {
    "iso:country":"US",
    "sg:address":"816 Natoma St",
    "sg:city":"Folsom",
    "sg:classifiers":[
        {
            "category":"Building & Trades",
            "subcategory":"Construction",
            "type":"Services"
        }
    ],
    "sg:phone":"+1 916 357 5580",
    "sg:postcode":"95630",
    "sg:province":"CA",
    "sg:tags":[
        "roofing",
        "contractor"
    ],
    "wof:name":"Superb Enterprises Inc",
    "wof:placetype":"venue"
},
  "geometry": {"coordinates":[-121.17663400000001,38.674],"type":"Point"}
}