{
  "type": "Feature",
  "properties": {
    "iso:country":"US",
    "sg:address":"7125 Birds Landing Rd",
    "sg:city":"Birds Landing",
    "sg:classifiers":[
        {
            "category":"Professional",
            "subcategory":"Management & Consulting",
            "type":"Services"
        }
    ],
    "sg:phone":"+1 707 374 6529",
    "sg:postcode":"94512",
    "sg:province":"CA",
    "sg:tags":[
        "consultant",
        "business"
    ],
    "wof:name":"Dimensions Unlimited Inc",
    "wof:placetype":"venue"
},
  "geometry": {"coordinates":[-121.806145,38.181102],"type":"Point"}
}