{
  "type": "Feature",
  "properties": {
    "iso:country":"US",
    "sg:address":"5480 Dewey Dr",
    "sg:city":"Fair Oaks",
    "sg:classifiers":[
        {
            "category":"Personal",
            "subcategory":"Beauty Salon",
            "type":"Services"
        }
    ],
    "sg:phone":"+1 916 864 4145",
    "sg:postcode":"95628",
    "sg:province":"CA",
    "sg:tags":[
        "manicuring"
    ],
    "wof:name":"1 Crystal Nails",
    "wof:placetype":"venue"
},
  "geometry": {"coordinates":[-121.308541,38.665032],"type":"Point"}
}