{
  "type": "Feature",
  "properties": {
    "addr:full":"513 Union Pl Brea CA 92821",
    "addr:housenumber":"513",
    "addr:postcode":"92821",
    "addr:street":"Union Pl",
    "iso:country":"US",
    "sg:address":"513 Union Pl",
    "sg:city":"Brea",
    "sg:classifiers":[
        {
            "category":"Building & Trades",
            "subcategory":"Construction",
            "type":"Services"
        }
    ],
    "sg:phone":"+1 714 529 4659",
    "sg:postcode":"92821",
    "sg:province":"CA",
    "sg:tags":[
        "contractor"
    ],
    "wof:name":"Trg Construction Inc",
    "wof:placetype":"venue"
},
  "geometry": {"coordinates":[-117.895535,33.913765],"type":"Point"}
}