{
  "type": "Feature",
  "properties": {
    "iso:country":"US",
    "sg:address":"11433 Broaded St",
    "sg:city":"Santa Fe Springs",
    "sg:classifiers":[
        {
            "category":"Shopping",
            "subcategory":"Clothing, Apparel, & Fashions",
            "type":"Retail Goods"
        }
    ],
    "sg:phone":"+1 562 699 3840",
    "sg:postcode":"90670",
    "sg:province":"CA",
    "sg:tags":[
        "salvage",
        "surplus",
        "merchandise"
    ],
    "wof:name":"Independent Pallet Salvage",
    "wof:placetype":"venue"
},
  "geometry": {"coordinates":[-118.078611,33.955841],"type":"Point"}
}