{
  "type": "Feature",
  "properties": {
    "addr:full":"616 Alhambra Rd San Mateo CA 94402",
    "addr:housenumber":"616",
    "addr:postcode":"94402",
    "addr:street":"Alhambra Rd",
    "iso:country":"US",
    "sg:address":"616 Alhambra Rd",
    "sg:city":"San Mateo",
    "sg:classifiers":[
        {
            "category":"Wholesale",
            "subcategory":"Office Equipment",
            "type":"Manufacturing & Wholesale Goods"
        }
    ],
    "sg:phone":"+1 650 344 3810",
    "sg:postcode":"94402",
    "sg:province":"CA",
    "wof:name":"Bia Financial Svc",
    "wof:placetype":"venue"
},
  "geometry": {"coordinates":[-122.326685,37.55804],"type":"Point"}
}