{
  "type": "Feature",
  "properties": {
    "addr:full":"101 Torrance Blvd Redondo Beach CA 90277",
    "addr:housenumber":"101",
    "addr:postcode":"90277",
    "addr:street":"Torrance Blvd",
    "iso:country":"US",
    "sg:address":"101 Torrance Blvd",
    "sg:city":"Redondo Beach",
    "sg:classifiers":[
        {
            "category":"Parking",
            "type":"Transportation"
        }
    ],
    "sg:phone":"+1 310 374 4262",
    "sg:postcode":"90277",
    "sg:province":"CA",
    "sg:tags":[
        "garage"
    ],
    "wof:name":"Executive Parking Inc",
    "wof:placetype":"venue"
},
  "geometry": {"coordinates":[-118.38730700000001,33.838222],"type":"Point"}
}