{
  "type": "Feature",
  "properties": {
    "addr:full":"906 G St # 510 Sacramento CA 95814",
    "addr:housenumber":"906",
    "addr:postcode":"95814",
    "addr:street":"G St # 510",
    "iso:country":"US",
    "sg:address":"906 G St # 510",
    "sg:city":"Sacramento",
    "sg:classifiers":[
        {
            "category":"Government",
            "subcategory":"Office",
            "type":"Public Place"
        }
    ],
    "sg:phone":"+1 916 874 5278",
    "sg:postcode":"95814",
    "sg:province":"CA",
    "wof:name":"Sacramento County Tree Crdntr",
    "wof:placetype":"venue"
},
  "geometry": {"coordinates":[-121.493281,38.583917],"type":"Point"}
}