{
  "type": "Feature",
  "properties": {
    "addr:full":"1225 S West Ave Fresno CA 93706",
    "addr:housenumber":"1225",
    "addr:postcode":"93706",
    "addr:street":"S West Ave",
    "iso:country":"US",
    "sg:address":"1225 S West Ave",
    "sg:city":"Fresno",
    "sg:classifiers":[
        {
            "category":"Retail",
            "subcategory":"Auto Repair",
            "type":"Services"
        }
    ],
    "sg:phone":"+1 559 498 6130",
    "sg:postcode":"93706",
    "sg:province":"CA",
    "sg:tags":[
        "trailer"
    ],
    "wof:name":"J & N Trailer Repairs",
    "wof:placetype":"venue"
},
  "geometry": {"coordinates":[-119.82651199999999,36.728879],"type":"Point"}
}