{
  "type": "Feature",
  "properties": {
    "iso:country":"US",
    "sg:address":"1112 State Rte 66",
    "sg:city":"Glendora",
    "sg:classifiers":[
        {
            "category":"Professional",
            "subcategory":"Computer Services",
            "type":"Services"
        }
    ],
    "sg:phone":"+1 626 963 6694",
    "sg:postcode":"91740",
    "sg:province":"CA",
    "sg:tags":[
        "repair"
    ],
    "wof:name":"X-Engineers Inc",
    "wof:placetype":"venue"
},
  "geometry": {"coordinates":[-117.846754,34.128658],"type":"Point"}
}