{
  "type": "Feature",
  "properties": {
    "addr:full":"5446 N Fresno St Fresno CA 93710",
    "addr:housenumber":"5446",
    "addr:postcode":"93710",
    "addr:street":"N Fresno",
    "iso:country":"US",
    "sg:address":"5446 N Fresno St",
    "sg:city":"Fresno",
    "sg:classifiers":[
        {
            "category":"Manufacturing",
            "subcategory":"Retail Goods",
            "type":"Manufacturing & Wholesale Goods"
        }
    ],
    "sg:phone":"+1 559 439 4203",
    "sg:postcode":"93710",
    "sg:province":"CA",
    "sg:tags":[
        "patriotic",
        "merchandise",
        "manufacturer"
    ],
    "wof:name":"Spirit of America",
    "wof:placetype":"venue"
},
  "geometry": {"coordinates":[-119.781256,36.815777],"type":"Point"}
}