{
  "type": "Feature",
  "properties": {
    "iso:country":"US",
    "sg:address":"2220 10th Ave",
    "sg:city":"Oakland",
    "sg:classifiers":[
        {
            "category":"Real Estate",
            "subcategory":"Real Estate Operator",
            "type":"Services"
        }
    ],
    "sg:phone":"+1 510 533 6855",
    "sg:postcode":"94606",
    "sg:province":"CA",
    "sg:tags":[
        "apartment"
    ],
    "wof:name":"Santana Apartments",
    "wof:placetype":"venue"
},
  "geometry": {"coordinates":[-122.241997,37.797501],"type":"Point"}
}