{
  "type": "Feature",
  "properties": {
    "addr:full":"200 Pine St San Francisco CA 94104",
    "addr:housenumber":"200",
    "addr:postcode":"94104",
    "addr:street":"Pine St",
    "iso:country":"US",
    "sg:address":"200 Pine St",
    "sg:city":"San Francisco",
    "sg:classifiers":[
        {
            "category":"Shopping",
            "subcategory":"Computers & Home Electronics",
            "type":"Retail Goods"
        }
    ],
    "sg:phone":"+1 415 362 4555",
    "sg:postcode":"94104",
    "sg:province":"CA",
    "sg:tags":[
        "software"
    ],
    "sg:website":"www.davidcorp.com",
    "wof:name":"David Corp",
    "wof:placetype":"venue"
},
  "geometry": {"coordinates":[-122.40093299999999,37.792108],"type":"Point"}
}