{
  "type": "Feature",
  "properties": {
    "iso:country":"US",
    "sg:address":"1155 E Springfield Ave",
    "sg:city":"Reedley",
    "sg:classifiers":[
        {
            "category":"Professional",
            "subcategory":"Management & Consulting",
            "type":"Services"
        }
    ],
    "sg:phone":"+1 559 638 5090",
    "sg:postcode":"93654",
    "sg:province":"CA",
    "sg:tags":[
        "food"
    ],
    "wof:name":"Morrison Senior Dining",
    "wof:placetype":"venue"
},
  "geometry": {"coordinates":[-119.43686099999999,36.59683],"type":"Point"}
}