{
  "type": "Feature",
  "properties": {
    "iso:country":"US",
    "sg:address":"4748 Kruse Rd",
    "sg:city":"Willows",
    "sg:phone":"+1 530 438 2823",
    "sg:postcode":"95932",
    "sg:province":"CA",
    "sg:tags":[
        "farm",
        "rice"
    ],
    "wof:name":"Dewit Dairy",
    "wof:placetype":"venue"
},
  "geometry": {"coordinates":[-122.18257199999999,39.337793],"type":"Point"}
}