{
  "type": "Feature",
  "properties": {
    "addr:full":"7311 Maynard Ave West Hills CA 91307",
    "addr:housenumber":"7311",
    "addr:postcode":"91307",
    "addr:street":"Maynard Ave",
    "iso:country":"US",
    "sg:address":"7311 Maynard Ave",
    "sg:city":"West Hills",
    "sg:classifiers":[
        {
            "category":"Building & Trades",
            "subcategory":"Landscaping Services",
            "type":"Services"
        }
    ],
    "sg:phone":"+1 818 521 8878",
    "sg:postcode":"91307",
    "sg:province":"CA",
    "sg:tags":[
        "gardener"
    ],
    "wof:name":"Greenland Gardening SVC",
    "wof:placetype":"venue"
},
  "geometry": {"coordinates":[-118.621926,34.203149],"type":"Point"}
}