{
  "type": "Feature",
  "properties": {
    "addr:full":"11457 178th St Artesia CA 90701",
    "addr:housenumber":"11457",
    "addr:postcode":"90701",
    "addr:street":"178Th St",
    "iso:country":"US",
    "sg:address":"11457 178th St",
    "sg:city":"Artesia",
    "sg:classifiers":[
        {
            "category":"Building & Trades",
            "subcategory":"Construction",
            "type":"Services"
        }
    ],
    "sg:phone":"+1 562 865 3060",
    "sg:postcode":"90701",
    "sg:province":"CA",
    "sg:tags":[
        "contractor"
    ],
    "wof:name":"Chester Plastering",
    "wof:placetype":"venue"
},
  "geometry": {"coordinates":[-118.08736,33.869426],"type":"Point"}
}