{
  "type": "Feature",
  "properties": {
    "iso:country":"US",
    "sg:address":"16695 Condit Rd",
    "sg:city":"Morgan Hill",
    "sg:classifiers":[
        {
            "category":"Restaurant",
            "type":"Food & Drink"
        }
    ],
    "sg:phone":"+1 408 779 8085",
    "sg:postcode":"95037",
    "sg:province":"CA",
    "wof:name":"Golden Oak Restaurant",
    "wof:placetype":"venue"
},
  "geometry": {"coordinates":[-121.630498,37.131842],"type":"Point"}
}