{
  "type": "Feature",
  "properties": {
    "iso:country":"US",
    "sg:address":"1177 E San Bruno Ave",
    "sg:city":"Fresno",
    "sg:classifiers":[
        {
            "category":"Real Estate",
            "subcategory":"Real Estate Agent",
            "type":"Services"
        }
    ],
    "sg:phone":"+1 559 227 6555",
    "sg:postcode":"93710",
    "sg:province":"CA",
    "wof:name":"Integrated Concepts Inc",
    "wof:placetype":"venue"
},
  "geometry": {"coordinates":[-119.76739,36.813351],"type":"Point"}
}