{
  "type": "Feature",
  "properties": {
    "addr:full":"1777 S La Cienega Blvd Los Angeles CA 90035",
    "addr:housenumber":"1777",
    "addr:postcode":"90035",
    "addr:street":"S La Cienega Blvd",
    "iso:country":"US",
    "sg:address":"1777 S La Cienega Blvd",
    "sg:city":"Los Angeles",
    "sg:classifiers":[
        {
            "category":"Travel",
            "subcategory":"Hotels & Motels",
            "type":"Entertainment"
        }
    ],
    "sg:phone":"+1 310 837 5366",
    "sg:postcode":"90035",
    "sg:province":"CA",
    "wof:name":"Park Cienega Motor Hotel",
    "wof:placetype":"venue"
},
  "geometry": {"coordinates":[-118.376999,34.044601],"type":"Point"}
}