{
  "type": "Feature",
  "properties": {
    "iso:country":"US",
    "sg:address":"906 S Main St",
    "sg:city":"Burbank",
    "sg:classifiers":[
        {
            "category":"Social Services",
            "subcategory":"Child Care",
            "type":"Services"
        }
    ],
    "sg:phone":"+1 818 846 7837",
    "sg:postcode":"91506",
    "sg:province":"CA",
    "sg:tags":[
        "elementary",
        "kindergarten",
        "school",
        "academic"
    ],
    "sg:website":"www.teddybearps.com",
    "wof:name":"Teddy Bear Pre School",
    "wof:placetype":"venue"
},
  "geometry": {"coordinates":[-118.31199599999999,34.1642],"type":"Point"}
}