{
  "type": "Feature",
  "properties": {
    "iso:country":"US",
    "sg:address":"6580 Belleau Wood Ln B",
    "sg:city":"Sacramento",
    "sg:classifiers":[
        {
            "category":"Shopping",
            "subcategory":"Bicycles & Sporting Goods",
            "type":"Retail Goods"
        }
    ],
    "sg:phone":"+1 916 395 9600",
    "sg:postcode":"95822",
    "sg:province":"CA",
    "sg:tags":[
        "equipment",
        "skiing"
    ],
    "wof:name":"Mohn Ski Rack Company",
    "wof:placetype":"venue"
},
  "geometry": {"coordinates":[-121.504727,38.506439],"type":"Point"}
}