{
  "type": "Feature",
  "properties": {
    "addr:full":"12240 Pigeon Pass Rd Moreno Valley CA 92557",
    "addr:housenumber":"12240",
    "addr:postcode":"92557",
    "addr:street":"Pigeon Pass Rd",
    "iso:country":"US",
    "sg:address":"12240 Pigeon Pass Rd",
    "sg:city":"Moreno Valley",
    "sg:classifiers":[
        {
            "category":"Restaurant",
            "type":"Food & Drink"
        }
    ],
    "sg:menulink":"http://www.allmenus.com/ca/riverside/147926-farmer-boys/menu/",
    "sg:phone":"+1 951 924 9117",
    "sg:postcode":"92557",
    "sg:province":"CA",
    "sg:tags":[
        "american"
    ],
    "wof:name":"Farmer Boys",
    "wof:placetype":"venue"
},
  "geometry": {"coordinates":[-117.261433,33.942958],"type":"Point"}
}