{
  "type": "Feature",
  "properties": {
    "iso:country":"US",
    "sg:address":"16650 Harbor Blvd",
    "sg:city":"Fountain Valley",
    "sg:classifiers":[
        {
            "category":"Retail",
            "subcategory":"Auto Repair",
            "type":"Services"
        }
    ],
    "sg:phone":"+1 714 839 2684",
    "sg:postcode":"92708",
    "sg:province":"CA",
    "sg:website":"www.vortecusa.net",
    "wof:name":"Vortec USA Inc",
    "wof:placetype":"venue"
},
  "geometry": {"coordinates":[-117.920044,33.722477],"type":"Point"}
}