{
  "type": "Feature",
  "properties": {
    "iso:country":"US",
    "sg:address":"1611 S Pacific Coast Hwy",
    "sg:city":"Redondo Beach",
    "sg:classifiers":[
        {
            "category":"Professional",
            "subcategory":"Engineering",
            "type":"Services"
        }
    ],
    "sg:phone":"+1 310 792 5870",
    "sg:postcode":"90277",
    "sg:province":"CA",
    "sg:tags":[
        "engineer"
    ],
    "wof:name":"R C Costello & Assoc",
    "wof:placetype":"venue"
},
  "geometry": {"coordinates":[-118.385133,33.820017],"type":"Point"}
}