{
  "type": "Feature",
  "properties": {
    "addr:full":"257 E Redondo Beach Blvd Gardena CA 90248",
    "addr:housenumber":"257",
    "addr:postcode":"90248",
    "addr:street":"E Redondo Beach Blvd",
    "iso:country":"US",
    "sg:address":"257 E Redondo Beach Blvd",
    "sg:city":"Gardena",
    "sg:classifiers":[
        {
            "category":"Freight",
            "type":"Transportation"
        }
    ],
    "sg:phone":"+1 310 515 1550",
    "sg:postcode":"90248",
    "sg:province":"CA",
    "sg:tags":[
        "forwarder"
    ],
    "wof:name":"Fast Logistics Inc",
    "wof:placetype":"venue"
},
  "geometry": {"coordinates":[-118.268201,33.893231],"type":"Point"}
}