{
  "type": "Feature",
  "properties": {
    "iso:country":"US",
    "sg:address":"1220 E Howell Ave",
    "sg:city":"Anaheim",
    "sg:classifiers":[
        {
            "category":"Bakery",
            "type":"Food & Drink"
        }
    ],
    "sg:phone":"+1 714 634 8068",
    "sg:postcode":"92805",
    "sg:province":"CA",
    "wof:name":"Oroweat Entenmann's Food Co",
    "wof:placetype":"venue"
},
  "geometry": {"coordinates":[-117.896004,33.806801],"type":"Point"}
}