{
  "type": "Feature",
  "properties": {
    "addr:full":"1728 S Catalina Ave Redondo Beach CA 90277",
    "addr:housenumber":"1728",
    "addr:postcode":"90277",
    "addr:street":"S Catalina Ave",
    "iso:country":"US",
    "sg:address":"1728 S Catalina Ave",
    "sg:city":"Redondo Beach",
    "sg:classifiers":[
        {
            "category":"Personal",
            "subcategory":"Beauty Salon",
            "type":"Services"
        }
    ],
    "sg:phone":"+1 310 543 9606",
    "sg:postcode":"90277",
    "sg:province":"CA",
    "sg:tags":[
        "treatment",
        "skin"
    ],
    "sg:website":"www.imagecenterredondo.com",
    "wof:name":"Image Center",
    "wof:placetype":"venue"
},
  "geometry": {"coordinates":[-118.388143,33.818864],"type":"Point"}
}