{
  "type": "Feature",
  "properties": {
    "iso:country":"US",
    "sg:address":"1200 Main Street",
    "sg:city":"Irvine",
    "sg:classifiers":[
        {
            "category":"Professional",
            "subcategory":"Business Services",
            "type":"Services"
        }
    ],
    "sg:postcode":"92604",
    "sg:province":"CA",
    "sg:tags":[
        "gift-cards",
        "loyalty-rewards-programs",
        "gift-management",
        "frequent-flyer-miles"
    ],
    "sg:website":"http://www.leveragecard.com",
    "wof:name":"Leverage Card",
    "wof:placetype":"venue"
},
  "geometry": {"coordinates":[-118.00169,33.67208],"type":"Point"}
}