{
  "type": "Feature",
  "properties": {
    "addr:full":"107 Caledonia St Ste E Sausalito CA 94965",
    "addr:housenumber":"107",
    "addr:postcode":"94965",
    "addr:street":"Caledonia St Ste E",
    "iso:country":"US",
    "sg:address":"107 Caledonia St Ste E",
    "sg:city":"Sausalito",
    "sg:classifiers":[
        {
            "category":"Restaurant",
            "type":"Food & Drink"
        }
    ],
    "sg:phone":"+1 415 331 9101",
    "sg:postcode":"94965",
    "sg:province":"CA",
    "sg:tags":[
        "style",
        "family"
    ],
    "wof:name":"Real Restaurants",
    "wof:placetype":"venue"
},
  "geometry": {"coordinates":[-122.48542,37.858659],"type":"Point"}
}