{
  "type": "Feature",
  "properties": {
    "iso:country":"US",
    "sg:address":"26806 Cherry Hills Blvd",
    "sg:city":"Sun City",
    "sg:classifiers":[
        {
            "category":"Shopping",
            "subcategory":"Tobacco",
            "type":"Retail Goods"
        }
    ],
    "sg:phone":"+1 951 679 0448",
    "sg:postcode":"92586",
    "sg:province":"CA",
    "sg:tags":[
        "shop"
    ],
    "wof:name":"Smoke Shop",
    "wof:placetype":"venue"
},
  "geometry": {"coordinates":[-117.191002,33.7103],"type":"Point"}
}