{
  "type": "Feature",
  "properties": {
    "iso:country":"US",
    "sg:address":"1120 W Foothill Blvd",
    "sg:city":"Azusa",
    "sg:classifiers":[
        {
            "category":"Manufacturing",
            "subcategory":"Food",
            "type":"Manufacturing & Wholesale Goods"
        }
    ],
    "sg:phone":"+1 626 633 1609",
    "sg:postcode":"91702",
    "sg:province":"CA",
    "sg:tags":[
        "preparation",
        "mfg"
    ],
    "sg:website":"www.ctifoods.com",
    "wof:name":"S & S Foods",
    "wof:placetype":"venue"
},
  "geometry": {"coordinates":[-117.926763,34.133484],"type":"Point"}
}