{
  "type": "Feature",
  "properties": {
    "addr:full":"3355 Moorland Ave Santa Rosa CA 95407",
    "addr:housenumber":"3355",
    "addr:postcode":"95407",
    "addr:street":"Moorland Ave",
    "iso:country":"US",
    "sg:address":"3355 Moorland Ave",
    "sg:city":"Santa Rosa",
    "sg:classifiers":[
        {
            "category":"Manufacturing",
            "subcategory":"Toys & Sporting Goods",
            "type":"Manufacturing & Wholesale Goods"
        }
    ],
    "sg:phone":"+1 707 585 8699",
    "sg:postcode":"95407",
    "sg:province":"CA",
    "sg:tags":[
        "mfg"
    ],
    "wof:name":"Handmade In California",
    "wof:placetype":"venue"
},
  "geometry": {"coordinates":[-122.71864100000001,38.395725],"type":"Point"}
}