{
  "type": "Feature",
  "properties": {
    "addr:full":"901 W Lambert Rd La Habra CA 90631",
    "addr:housenumber":"901",
    "addr:postcode":"90631",
    "addr:street":"W Lambert Rd",
    "iso:country":"US",
    "sg:address":"901 W Lambert Rd",
    "sg:city":"La Habra",
    "sg:classifiers":[
        {
            "category":"Professional",
            "type":"Services"
        }
    ],
    "sg:phone":"+1 562 706 1918",
    "sg:postcode":"90631",
    "sg:province":"CA",
    "wof:name":"PST",
    "wof:placetype":"venue"
},
  "geometry": {"coordinates":[-117.95648300000001,33.924658],"type":"Point"}
}