{
  "type": "Feature",
  "properties": {
    "iso:country":"US",
    "sg:address":"1033 E Las Tunas Dr",
    "sg:city":"San Gabriel",
    "sg:classifiers":[
        {
            "category":"Banks & Credit Unions",
            "subcategory":"Bank",
            "type":"Services"
        }
    ],
    "sg:phone":"+1 626 286 2153",
    "sg:postcode":"91776",
    "sg:province":"CA",
    "sg:tags":[
        "escrow"
    ],
    "wof:name":"Alta Escrow Corp",
    "wof:placetype":"venue"
},
  "geometry": {"coordinates":[-118.083785,34.103439],"type":"Point"}
}