{
  "type": "Feature",
  "properties": {
    "addr:full":"3518 E Berkshire Ct F Orange CA 92869",
    "addr:housenumber":"3518",
    "addr:postcode":"92869",
    "addr:street":"E Berkshire Ct F",
    "iso:country":"US",
    "sg:address":"3518 E Berkshire Ct F",
    "sg:city":"Orange",
    "sg:classifiers":[
        {
            "category":"Shopping",
            "subcategory":"Bicycles & Sporting Goods",
            "type":"Retail Goods"
        },
        {
            "category":"Parking",
            "subcategory":"Bicycle",
            "type":"Transportation"
        }
    ],
    "sg:phone":"+1 714 322 2870",
    "sg:postcode":"92869",
    "sg:province":"CA",
    "sg:tags":[
        "shop",
        "security",
        "system",
        "rack"
    ],
    "wof:name":"Bike Liquidators",
    "wof:placetype":"venue"
},
  "geometry": {"coordinates":[-117.81609400000001,33.798791],"type":"Point"}
}