{
  "type": "Feature",
  "properties": {
    "addr:full":"1335 Cristina Ave San Jose CA 95125",
    "addr:housenumber":"1335",
    "addr:postcode":"95125",
    "addr:street":"Cristina Ave",
    "iso:country":"US",
    "sg:address":"1335 Cristina Ave",
    "sg:city":"San Jose",
    "sg:classifiers":[
        {
            "category":"Shopping",
            "subcategory":"Clothing, Apparel, & Fashions",
            "type":"Retail Goods"
        }
    ],
    "sg:phone":"+1 408 750 6300",
    "sg:postcode":"95125",
    "sg:province":"CA",
    "sg:tags":[
        "children's",
        "clothing"
    ],
    "sg:website":"www.gimmiedatgear.com",
    "wof:name":"Gimmie dat Gear",
    "wof:placetype":"venue"
},
  "geometry": {"coordinates":[-121.89366200000001,37.307599],"type":"Point"}
}