{
  "type": "Feature",
  "properties": {
    "addr:full":"3825 E Thousand Oaks Blvd Westlake Village CA 91362",
    "addr:housenumber":"3825",
    "addr:postcode":"91362",
    "addr:street":"E Thousand Oaks Blvd",
    "iso:country":"US",
    "sg:address":"3825 E Thousand Oaks Blvd",
    "sg:city":"Westlake Village",
    "sg:classifiers":[
        {
            "category":"Shopping",
            "subcategory":"Gifts & Souvenirs",
            "type":"Retail Goods"
        }
    ],
    "sg:phone":"+1 818 889 5591",
    "sg:postcode":"91362",
    "sg:province":"CA",
    "sg:tags":[
        "party",
        "supply"
    ],
    "wof:name":"Gymboree",
    "wof:placetype":"venue"
},
  "geometry": {"coordinates":[-118.824403,34.161697],"type":"Point"}
}