{
  "type": "Feature",
  "properties": {
    "iso:country":"US",
    "sg:address":"16113 Foothill Blvd",
    "sg:city":"Fontana",
    "sg:classifiers":[
        {
            "category":"Banks & Credit Unions",
            "subcategory":"Bank",
            "type":"Services"
        }
    ],
    "sg:phone":"+1 909 357 3163",
    "sg:postcode":"92335",
    "sg:province":"CA",
    "sg:tags":[
        "loan",
        "real estate"
    ],
    "wof:name":"Banca Financial",
    "wof:placetype":"venue"
},
  "geometry": {"coordinates":[-117.449157,34.106499],"type":"Point"}
}