{
  "type": "Feature",
  "properties": {
    "addr:full":"14006 Riverside Dr Sherman Oaks CA 91423",
    "addr:housenumber":"14006",
    "addr:postcode":"91423",
    "addr:street":"Riverside Dr",
    "iso:country":"US",
    "sg:address":"14006 Riverside Dr",
    "sg:city":"Sherman Oaks",
    "sg:classifiers":[
        {
            "category":"Shopping",
            "subcategory":"Clothing, Apparel, & Fashions",
            "type":"Retail Goods"
        }
    ],
    "sg:phone":"+1 818 789 3095",
    "sg:postcode":"91423",
    "sg:province":"CA",
    "sg:website":"www.gap.com",
    "wof:name":"Gap",
    "wof:placetype":"venue"
},
  "geometry": {"coordinates":[-118.436587,34.157534],"type":"Point"}
}