{
  "type": "Feature",
  "properties": {
    "addr:full":"2005 Raymer Ave Ste A Fullerton CA 92832",
    "addr:housenumber":"2005",
    "addr:postcode":"92832",
    "addr:street":"Raymer Ave Ste A",
    "iso:country":"US",
    "sg:address":"2005 Raymer Ave Ste A",
    "sg:city":"Fullerton",
    "sg:classifiers":[
        {
            "category":"Personal",
            "type":"Services"
        }
    ],
    "sg:phone":"+1 714 717 8422",
    "sg:postcode":"92832",
    "sg:province":"CA",
    "sg:tags":[
        "local"
    ],
    "sg:website":"www.profile.myspace.com/index.cf...",
    "wof:name":"The Fresh Prints Of Fullerton",
    "wof:placetype":"venue"
},
  "geometry": {"coordinates":[-117.967009,33.872329],"type":"Point"}
}