{
  "type": "Feature",
  "properties": {
    "addr:full":"1407 Center Ave Dos Palos CA 93620",
    "addr:housenumber":"1407",
    "addr:postcode":"93620",
    "addr:street":"Center Ave",
    "iso:country":"US",
    "sg:address":"1407 Center Ave",
    "sg:city":"Dos Palos",
    "sg:classifiers":[
        {
            "category":"Professional",
            "subcategory":"Business Services",
            "type":"Services"
        }
    ],
    "sg:phone":"+1 209 392 8017",
    "sg:postcode":"93620",
    "sg:province":"CA",
    "sg:tags":[
        "drafting"
    ],
    "wof:name":"International Design Svc",
    "wof:placetype":"venue"
},
  "geometry": {"coordinates":[-120.626529,36.986666],"type":"Point"}
}