{
  "type": "Feature",
  "properties": {
    "iso:country":"US",
    "sg:address":"1916 W San Carlos Street",
    "sg:city":"San Jose",
    "sg:classifiers":[
        {
            "category":"Insurance",
            "subcategory":"Hazard Insurance",
            "type":"Services"
        }
    ],
    "sg:phone":"+1 408 287 1973",
    "sg:postcode":"95128",
    "sg:province":"CA",
    "wof:name":"Strategic Synergy",
    "wof:placetype":"venue"
},
  "geometry": {"coordinates":[-121.92903200000001,37.323327],"type":"Point"}
}