{
  "type": "Feature",
  "properties": {
    "addr:full":"3408 Via Oporto Ste 1 Newport Beach CA 92663",
    "addr:housenumber":"3408",
    "addr:postcode":"92663",
    "addr:street":"Via Oporto Ste 1",
    "iso:country":"US",
    "sg:address":"3408 Via Oporto Ste 1",
    "sg:city":"Newport Beach",
    "sg:classifiers":[
        {
            "category":"Shopping",
            "subcategory":"Jewelry",
            "type":"Retail Goods"
        }
    ],
    "sg:phone":"+1 949 673 9334",
    "sg:postcode":"92663",
    "sg:province":"CA",
    "sg:tags":[
        "watch"
    ],
    "sg:website":"www.blackmanltd.com",
    "wof:name":"Blackman Limited Jewelers",
    "wof:placetype":"venue"
},
  "geometry": {"coordinates":[-117.92831200000001,33.618288],"type":"Point"}
}