{
  "type": "Feature",
  "properties": {
    "iso:country":"US",
    "sg:address":"350 W Aten Rd",
    "sg:city":"Imperial",
    "sg:phone":"+1 760 355 7900",
    "sg:postcode":"92251",
    "sg:province":"CA",
    "sg:tags":[
        "product",
        "petroleum"
    ],
    "wof:name":"Trinity Oil Inc",
    "wof:placetype":"venue"
},
  "geometry": {"coordinates":[-115.56565399999999,32.8256],"type":"Point"}
}