{
  "type": "Feature",
  "properties": {
    "iso:country":"US",
    "sg:address":"740 del Valle",
    "sg:city":"Aptos",
    "sg:classifiers":[
        {
            "category":"Professional",
            "subcategory":"Accounting & Tax Preparation",
            "type":"Services"
        }
    ],
    "sg:phone":"+1 831 761 3530",
    "sg:postcode":"95003",
    "sg:province":"CA",
    "sg:tags":[
        "accountant"
    ],
    "wof:name":"S J Kellerman & Assoc",
    "wof:placetype":"venue"
},
  "geometry": {"coordinates":[-121.825242,37.004659],"type":"Point"}
}