{
  "type": "Feature",
  "properties": {
    "iso:country":"US",
    "sg:address":"1166 Rialto Way",
    "sg:city":"Pomona",
    "sg:classifiers":[
        {
            "category":"Social Services",
            "type":"Services"
        }
    ],
    "sg:phone":"+1 909 622 2307",
    "sg:postcode":"91767",
    "sg:province":"CA",
    "sg:tags":[
        "referral"
    ],
    "wof:name":"General Electrical Appliance",
    "wof:placetype":"venue"
},
  "geometry": {"coordinates":[-117.732387,34.069558],"type":"Point"}
}