{
  "type": "Feature",
  "properties": {
    "iso:country":"US",
    "sg:address":"235 E Broadway",
    "sg:city":"Long Beach",
    "sg:classifiers":[
        {
            "category":"Professional",
            "subcategory":"Art Services",
            "type":"Services"
        }
    ],
    "sg:phone":"+1 562 432 2125",
    "sg:postcode":"90802",
    "sg:province":"CA",
    "sg:tags":[
        "graphic",
        "designer"
    ],
    "wof:name":"Bradfield Design Inc",
    "wof:placetype":"venue"
},
  "geometry": {"coordinates":[-118.189492,33.769362],"type":"Point"}
}