{
  "type": "Feature",
  "properties": {
    "iso:country":"US",
    "sg:address":"4679 Braemar Pl",
    "sg:city":"Riverside",
    "sg:classifiers":[
        {
            "category":"Real Estate",
            "subcategory":"Real Estate Services",
            "type":"Services"
        },
        {
            "category":"Real Estate",
            "subcategory":"Real Estate Operator",
            "type":"Services"
        }
    ],
    "sg:phone":"+1 951 684 0380",
    "sg:postcode":"92501",
    "sg:province":"CA",
    "sg:tags":[
        "vacancy",
        "apartment",
        "rental",
        "finder",
        "listing"
    ],
    "wof:name":"Braemar Cooperative Apartments",
    "wof:placetype":"venue"
},
  "geometry": {"coordinates":[-117.39096600000001,33.978054],"type":"Point"}
}