{
  "type": "Feature",
  "properties": {
    "addr:full":"249 Main St Pleasanton CA 94566",
    "addr:housenumber":"249",
    "addr:postcode":"94566",
    "addr:street":"Main St",
    "iso:country":"US",
    "sg:address":"249 Main St",
    "sg:city":"Pleasanton",
    "sg:classifiers":[
        {
            "category":"Banks & Credit Unions",
            "subcategory":"Bank",
            "type":"Services"
        },
        {
            "category":"Banks & Credit Unions",
            "subcategory":"Financial Services",
            "type":"Services"
        }
    ],
    "sg:phone":"+1 925 846 8811",
    "sg:postcode":"94566",
    "sg:province":"CA",
    "sg:tags":[
        "saving",
        "commercial",
        "mortgage"
    ],
    "sg:website":"http://www.firstrepublic.com",
    "wof:name":"First Republic Bank",
    "wof:placetype":"venue"
},
  "geometry": {"coordinates":[-121.877404,37.657729],"type":"Point"}
}