{
  "type": "Feature",
  "properties": {
    "iso:country":"US",
    "sg:address":"435 W Foothill Blvd",
    "sg:city":"Glendora",
    "sg:classifiers":[
        {
            "category":"Food & Beverages",
            "subcategory":"Groceries & Convenience Stores",
            "type":"Retail Goods"
        }
    ],
    "sg:phone":"+1 626 963 2913",
    "sg:postcode":"91741",
    "sg:province":"CA",
    "sg:tags":[
        "grocer"
    ],
    "wof:name":"Vons Co",
    "wof:placetype":"venue"
},
  "geometry": {"coordinates":[-117.871279,34.136118],"type":"Point"}
}