{
  "type": "Feature",
  "properties": {
    "addr:full":"3340 12th st Oakland CA 94601",
    "addr:housenumber":"3340",
    "addr:postcode":"94601",
    "addr:street":"12Th St",
    "iso:country":"US",
    "sg:address":"3340 12th st",
    "sg:city":"Oakland",
    "sg:classifiers":[
        {
            "category":"Wholesale",
            "subcategory":"Plants",
            "type":"Manufacturing & Wholesale Goods"
        },
        {
            "category":"Shopping",
            "subcategory":"Crafts & Fabrics",
            "type":"Retail Goods"
        },
        {
            "category":"Shopping",
            "subcategory":"Florist",
            "type":"Retail Goods"
        }
    ],
    "sg:phone":"+1 510 534 5039",
    "sg:postcode":"94601",
    "sg:province":"CA",
    "sg:tags":[
        "supplies-wholesale",
        "manufacturer",
        "florists'",
        "florists-wholesale"
    ],
    "wof:name":"Magdalena Flower Shop",
    "wof:placetype":"venue"
},
  "geometry": {"coordinates":[-122.224677,37.776195],"type":"Point"}
}