{
  "type": "Feature",
  "properties": {
    "iso:country":"US",
    "sg:address":"1035 Fedora St",
    "sg:city":"Los Angeles",
    "sg:classifiers":[
        {
            "category":"Social Services",
            "subcategory":"Child Care",
            "type":"Services"
        }
    ],
    "sg:phone":"+1 213 380 1010",
    "sg:postcode":"90006",
    "sg:province":"CA",
    "sg:tags":[
        "elementary",
        "kindergarten",
        "school",
        "academic"
    ],
    "wof:name":"Newton Preschool",
    "wof:placetype":"venue"
},
  "geometry": {"coordinates":[-118.297997,34.051701],"type":"Point"}
}