{
  "type": "Feature",
  "properties": {
    "addr:full":"3139 Santa Fe St Riverbank CA 95367",
    "addr:housenumber":"3139",
    "addr:postcode":"95367",
    "addr:street":"Santa Fe St",
    "iso:country":"US",
    "sg:address":"3139 Santa Fe St",
    "sg:city":"Riverbank",
    "sg:classifiers":[
        {
            "category":"Social Services",
            "subcategory":"Adult Care",
            "type":"Services"
        }
    ],
    "sg:phone":"+1 209 869 4415",
    "sg:postcode":"95367",
    "sg:province":"CA",
    "sg:tags":[
        "organization",
        "senior",
        "citizen"
    ],
    "wof:name":"Salvation Army",
    "wof:placetype":"venue"
},
  "geometry": {"coordinates":[-120.937859,37.736089],"type":"Point"}
}