{
  "type": "Feature",
  "properties": {
    "iso:country":"US",
    "sg:address":"3907 E Fremont St",
    "sg:city":"Stockton",
    "sg:classifiers":[
        {
            "category":"Real Estate",
            "subcategory":"Real Estate Operator",
            "type":"Services"
        }
    ],
    "sg:phone":"+1 209 462 8939",
    "sg:postcode":"95215",
    "sg:province":"CA",
    "sg:tags":[
        "mobile",
        "home",
        "community"
    ],
    "wof:name":"Big Wheel Mobile Home Park",
    "wof:placetype":"venue"
},
  "geometry": {"coordinates":[-121.24253299999999,37.971311],"type":"Point"}
}