{
  "type": "Feature",
  "properties": {
    "addr:full":"3638 Burly Ave Orange CA 92869",
    "addr:housenumber":"3638",
    "addr:postcode":"92869",
    "addr:street":"Burly Ave",
    "iso:country":"US",
    "sg:address":"3638 Burly Ave",
    "sg:city":"Orange",
    "sg:classifiers":[
        {
            "category":"Personal",
            "type":"Services"
        }
    ],
    "sg:phone":"+1 714 396 4018",
    "sg:postcode":"92869",
    "sg:province":"CA",
    "sg:tags":[
        "consultant",
        "planning",
        "wedding"
    ],
    "wof:name":"Wings Of Love",
    "wof:placetype":"venue"
},
  "geometry": {"coordinates":[-117.81487300000001,33.78566],"type":"Point"}
}