{
  "type": "Feature",
  "properties": {
    "addr:full":"1675 Champagne Ave Ontario CA 91761",
    "addr:housenumber":"1675",
    "addr:postcode":"91761",
    "addr:street":"Champagne Ave",
    "iso:country":"US",
    "sg:address":"1675 Champagne Ave",
    "sg:city":"Ontario",
    "sg:classifiers":[
        {
            "category":"Manufacturing",
            "subcategory":"Building Materials",
            "type":"Manufacturing & Wholesale Goods"
        }
    ],
    "sg:phone":"+1 614 792 4678",
    "sg:postcode":"91761",
    "sg:province":"CA",
    "sg:tags":[
        "mfg",
        "wood",
        "kitchen",
        "cabinet"
    ],
    "wof:name":"Schrock Cabinet Co",
    "wof:placetype":"venue"
},
  "geometry": {"coordinates":[-117.52957499999999,34.043946],"type":"Point"}
}