{
  "type": "Feature",
  "properties": {
    "iso:country":"US",
    "sg:address":"12860 Sierra Dr",
    "sg:city":"Truckee",
    "sg:classifiers":[
        {
            "category":"Building & Trades",
            "subcategory":"Construction",
            "type":"Services"
        }
    ],
    "sg:phone":"+1 530 587 3407",
    "sg:postcode":"96161",
    "sg:province":"CA",
    "sg:tags":[
        "contractor"
    ],
    "wof:name":"Orebaugh Construction",
    "wof:placetype":"venue"
},
  "geometry": {"coordinates":[-120.237028,39.327394],"type":"Point"}
}