{
  "type": "Feature",
  "properties": {
    "iso:country":"US",
    "sg:address":"318 E 3rd St",
    "sg:city":"Los Angeles",
    "sg:classifiers":[
        {
            "category":"Wholesale",
            "subcategory":"Durable Goods & Equipment",
            "type":"Manufacturing & Wholesale Goods"
        }
    ],
    "sg:phone":"+1 213 437 0210",
    "sg:postcode":"90013",
    "sg:province":"CA",
    "sg:tags":[
        "importer"
    ],
    "wof:name":"Top World & Tw USA Co",
    "wof:placetype":"venue"
},
  "geometry": {"coordinates":[-118.242738,34.047378],"type":"Point"}
}