{
  "type": "Feature",
  "properties": {
    "iso:country":"US",
    "sg:address":"11711 Monarch St",
    "sg:city":"Garden Grove",
    "sg:classifiers":[
        {
            "category":"Professional",
            "type":"Services"
        }
    ],
    "sg:phone":"+1 714 903 3110",
    "sg:postcode":"92841",
    "sg:province":"CA",
    "wof:name":"Charmzone USA Inc",
    "wof:placetype":"venue"
},
  "geometry": {"coordinates":[-118.006351,33.79052],"type":"Point"}
}