{
  "type": "Feature",
  "properties": {
    "addr:full":"2932 Poinsettia Dr San Diego CA 92106",
    "addr:housenumber":"2932",
    "addr:postcode":"92106",
    "addr:street":"Poinsettia Dr",
    "iso:country":"US",
    "sg:address":"2932 Poinsettia Dr",
    "sg:city":"San Diego",
    "sg:classifiers":[
        {
            "category":"Professional",
            "subcategory":"Management & Consulting",
            "type":"Services"
        }
    ],
    "sg:phone":"+1 619 223 7408",
    "sg:postcode":"92106",
    "sg:province":"CA",
    "sg:tags":[
        "town",
        "city",
        "regional",
        "planner"
    ],
    "wof:name":"Cinti Land Planning",
    "wof:placetype":"venue"
},
  "geometry": {"coordinates":[-117.22226000000001,32.749306],"type":"Point"}
}