{
  "type": "Feature",
  "properties": {
    "iso:country":"US",
    "sg:address":"2521 E California Ave",
    "sg:city":"Bakersfield",
    "sg:classifiers":[
        {
            "category":"Retail",
            "subcategory":"Auto Repair",
            "type":"Services"
        }
    ],
    "sg:phone":"+1 661 301 2485",
    "sg:postcode":"93307",
    "sg:province":"CA",
    "sg:tags":[
        "body",
        "automobile",
        "painting"
    ],
    "wof:name":"R Auto Body Shop",
    "wof:placetype":"venue"
},
  "geometry": {"coordinates":[-118.958865,35.368561],"type":"Point"}
}