{
  "type": "Feature",
  "properties": {
    "iso:country":"US",
    "sg:address":"120 Montgomery Street",
    "sg:city":"San Francisco",
    "sg:classifiers":[
        {
            "category":"Professional",
            "subcategory":"Accounting & Tax Preparation",
            "type":"Services"
        }
    ],
    "sg:phone":"+1 415 398 1100",
    "sg:postcode":"94104",
    "sg:province":"CA",
    "sg:tags":[
        "accountant"
    ],
    "wof:name":"Krakower David CPA",
    "wof:placetype":"venue"
},
  "geometry": {"coordinates":[-122.402214,37.790282],"type":"Point"}
}