{
  "type": "Feature",
  "properties": {
    "addr:full":"2447 Fletcher Pkwy El Cajon CA 92020",
    "addr:housenumber":"2447",
    "addr:postcode":"92020",
    "addr:street":"Fletcher Pkwy",
    "iso:country":"US",
    "sg:address":"2447 Fletcher Pkwy",
    "sg:city":"El Cajon",
    "sg:classifiers":[
        {
            "category":"Food & Beverages",
            "subcategory":"Liquor & Beverages",
            "type":"Retail Goods"
        }
    ],
    "sg:phone":"+1 619 469 8410",
    "sg:postcode":"92020",
    "sg:province":"CA",
    "sg:tags":[
        "pizza"
    ],
    "wof:name":"Fletcher Hills Bottle Shop",
    "wof:placetype":"venue"
},
  "geometry": {"coordinates":[-116.998001,32.8022],"type":"Point"}
}