{
  "type": "Feature",
  "properties": {
    "iso:country":"US",
    "sg:address":"41865 Boardwalk",
    "sg:city":"Palm Desert",
    "sg:classifiers":[
        {
            "category":"Banks & Credit Unions",
            "subcategory":"Bank",
            "type":"Services"
        }
    ],
    "sg:phone":"+1 760 773 0166",
    "sg:postcode":"92211",
    "sg:province":"CA",
    "sg:tags":[
        "escrow"
    ],
    "sg:website":"www.stsales.com",
    "wof:name":"Stewart Title Co",
    "wof:placetype":"venue"
},
  "geometry": {"coordinates":[-116.355108,33.745551],"type":"Point"}
}