{
  "type": "Feature",
  "properties": {
    "addr:full":"404 Live Oak Ave Irwindale CA 91706",
    "addr:housenumber":"404",
    "addr:postcode":"91706",
    "addr:street":"Live Oak Ave",
    "iso:country":"US",
    "sg:address":"404 Live Oak Ave",
    "sg:city":"Irwindale",
    "sg:classifiers":[
        {
            "category":"Home & Garden",
            "subcategory":"Hardware",
            "type":"Retail Goods"
        }
    ],
    "sg:phone":"+1 626 359 3606",
    "sg:postcode":"91706",
    "sg:province":"CA",
    "wof:name":"Ace Hardware",
    "wof:placetype":"venue"
},
  "geometry": {"coordinates":[-117.997328,34.112142],"type":"Point"}
}