{
  "type": "Feature",
  "properties": {
    "addr:full":"1102 Starwood Ct San Jose CA 95120",
    "addr:housenumber":"1102",
    "addr:postcode":"95120",
    "addr:street":"Starwood Ct",
    "iso:country":"US",
    "sg:address":"1102 Starwood Ct",
    "sg:city":"San Jose",
    "sg:classifiers":[
        {
            "category":"Professional",
            "subcategory":"Lawyer & Legal Services",
            "type":"Services"
        }
    ],
    "sg:phone":"+1 408 278 1600",
    "sg:postcode":"95120",
    "sg:province":"CA",
    "wof:name":"Landrum & Company Inc",
    "wof:placetype":"venue"
},
  "geometry": {"coordinates":[-121.876659,37.234642],"type":"Point"}
}