{
  "type": "Feature",
  "properties": {
    "iso:country":"US",
    "sg:address":"2710 Summit Dr",
    "sg:city":"Escondido",
    "sg:classifiers":[
        {
            "category":"Shopping",
            "type":"Retail Goods"
        }
    ],
    "sg:phone":"+1 760 745 0949",
    "sg:postcode":"92025",
    "sg:province":"CA",
    "sg:tags":[
        "art",
        "gallery",
        "dealer"
    ],
    "sg:website":"www.jonesgallery.com",
    "wof:name":"Jones Gallery",
    "wof:placetype":"venue"
},
  "geometry": {"coordinates":[-117.04154200000001,33.095534],"type":"Point"}
}