{
  "type": "Feature",
  "properties": {
    "iso:country":"US",
    "sg:address":"1077 Broadway",
    "sg:city":"El Cajon",
    "sg:classifiers":[
        {
            "category":"Shopping",
            "subcategory":"Jewelry",
            "type":"Retail Goods"
        }
    ],
    "sg:phone":"+1 619 442 3231",
    "sg:postcode":"92021",
    "sg:province":"CA",
    "sg:tags":[
        "jeweler"
    ],
    "wof:name":"Sentimental Values Resale Btq",
    "wof:placetype":"venue"
},
  "geometry": {"coordinates":[-116.946962,32.807627],"type":"Point"}
}