{
  "type": "Feature",
  "properties": {
    "addr:full":"1321 Howe Ave Ste 111 Sacramento CA 95825",
    "addr:housenumber":"1321",
    "addr:postcode":"95825",
    "addr:street":"Howe Ave Ste 111",
    "iso:country":"US",
    "sg:address":"1321 Howe Ave Ste 111",
    "sg:city":"Sacramento",
    "sg:classifiers":[
        {
            "category":"Banks & Credit Unions",
            "subcategory":"Investment Brokerage",
            "type":"Services"
        },
        {
            "category":"Banks & Credit Unions",
            "subcategory":"Financial Services",
            "type":"Services"
        }
    ],
    "sg:phone":"+1 916 286 7995",
    "sg:postcode":"95825",
    "sg:province":"CA",
    "sg:tags":[
        "advisory",
        "planner"
    ],
    "wof:name":"Ruth Maloney Taxes & Financial",
    "wof:placetype":"venue"
},
  "geometry": {"coordinates":[-121.41537099999999,38.589389],"type":"Point"}
}