{
  "type": "Feature",
  "properties": {
    "addr:full":"1127 Fee Drive Sacramento CA 95815",
    "addr:housenumber":"1127",
    "addr:postcode":"95815",
    "addr:street":"Fee Drive",
    "iso:country":"US",
    "sg:address":"1127 Fee Drive",
    "sg:city":"Sacramento",
    "sg:classifiers":[
        {
            "category":"Shopping",
            "subcategory":"Florist",
            "type":"Retail Goods"
        }
    ],
    "sg:phone":"+1 916 927 9767",
    "sg:postcode":"95815",
    "sg:province":"CA",
    "wof:name":"Flora Fresh",
    "wof:placetype":"venue"
},
  "geometry": {"coordinates":[-121.43922499999999,38.615253],"type":"Point"}
}