{
  "type": "Feature",
  "properties": {
    "iso:country":"US",
    "sg:address":"4814 Melrose Avenue",
    "sg:city":"Los Angeles",
    "sg:classifiers":[
        {
            "category":"Building & Trades",
            "subcategory":"Locksmith",
            "type":"Services"
        }
    ],
    "sg:phone":"+1 323 209 4319",
    "sg:postcode":"90029",
    "sg:province":"CA",
    "sg:tags":[
        "key"
    ],
    "wof:name":"1 24 7 Emergency Locks & Locksmith",
    "wof:placetype":"venue"
},
  "geometry": {"coordinates":[-118.30521,34.083638],"type":"Point"}
}