{
  "type": "Feature",
  "properties": {
    "iso:country":"US",
    "sg:address":"375 Vine Ave",
    "sg:city":"Upland",
    "sg:classifiers":[
        {
            "category":"Professional",
            "subcategory":"Business Services",
            "type":"Services"
        }
    ],
    "sg:phone":"+1 909 986 0883",
    "sg:postcode":"91786",
    "sg:province":"CA",
    "sg:tags":[
        "process",
        "server"
    ],
    "wof:name":"Yale Attorney Svc",
    "wof:placetype":"venue"
},
  "geometry": {"coordinates":[-117.656102,34.089712],"type":"Point"}
}