{
  "type": "Feature",
  "properties": {
    "addr:full":"7210 Jordan Ave Canoga Park CA 91303",
    "addr:housenumber":"7210",
    "addr:postcode":"91303",
    "addr:street":"Jordan Ave",
    "iso:country":"US",
    "sg:address":"7210 Jordan Ave",
    "sg:city":"Canoga Park",
    "sg:classifiers":[
        {
            "category":"Professional",
            "subcategory":"Computer Services",
            "type":"Services"
        }
    ],
    "sg:phone":"+1 818 274 9648",
    "sg:postcode":"91303",
    "sg:province":"CA",
    "sg:tags":[
        "consultant"
    ],
    "wof:name":"Velocity Network Solutions",
    "wof:placetype":"venue"
},
  "geometry": {"coordinates":[-118.60278599999999,34.202656],"type":"Point"}
}