{
  "type": "Feature",
  "properties": {
    "iso:country":"US",
    "sg:address":"245 E Louise Ave",
    "sg:city":"Lathrop",
    "sg:classifiers":[
        {
            "category":"Restaurant",
            "type":"Food & Drink"
        }
    ],
    "sg:phone":"+1 209 858 9262",
    "sg:postcode":"95330",
    "sg:province":"CA",
    "sg:tags":[
        "mexican"
    ],
    "wof:name":"Taqueria Vallarta 2",
    "wof:placetype":"venue"
},
  "geometry": {"coordinates":[-121.291037,37.81181],"type":"Point"}
}