{
  "type": "Feature",
  "properties": {
    "iso:country":"US",
    "sg:address":"134 N Grant Ave",
    "sg:city":"Manteca",
    "sg:classifiers":[
        {
            "category":"Manufacturing",
            "subcategory":"Tools & Machinery",
            "type":"Manufacturing & Wholesale Goods"
        }
    ],
    "sg:phone":"+1 209 825 9544",
    "sg:postcode":"95336",
    "sg:province":"CA",
    "sg:tags":[
        "measuring",
        "instrument",
        "electrical",
        "mfg"
    ],
    "wof:name":"Amps DMS",
    "wof:placetype":"venue"
},
  "geometry": {"coordinates":[-121.215153,37.797966],"type":"Point"}
}