{
  "type": "Feature",
  "properties": {
    "addr:full":"798 N State St Ukiah CA 95482",
    "addr:housenumber":"798",
    "addr:postcode":"ca 95482",
    "addr:street":"N State St",
    "iso:country":"US",
    "sg:address":"798 N State St",
    "sg:city":"Ukiah",
    "sg:classifiers":[
        {
            "category":"Government",
            "subcategory":"Jail",
            "type":"Public Place"
        }
    ],
    "sg:phone":"+1 707 463 5713",
    "sg:postcode":"95482",
    "sg:province":"CA",
    "sg:tags":[
        "govt",
        "state",
        "institution"
    ],
    "wof:name":"Corrections Dept",
    "wof:placetype":"venue"
},
  "geometry": {"coordinates":[-123.20849699999999,39.157537],"type":"Point"}
}