{
  "type": "Feature",
  "properties": {
    "addr:full":"9611 Garvey Ave Ste 103 South El Monte CA 91733",
    "addr:housenumber":"9611",
    "addr:postcode":"91733",
    "addr:street":"Garvey Ave Ste 103",
    "iso:country":"US",
    "sg:address":"9611 Garvey Ave Ste 103",
    "sg:city":"South El Monte",
    "sg:classifiers":[
        {
            "category":"Shopping",
            "subcategory":"Pets & Pet Supplies",
            "type":"Retail Goods"
        }
    ],
    "sg:phone":"+1 626 350 5751",
    "sg:postcode":"91733",
    "sg:province":"CA",
    "sg:tags":[
        "store"
    ],
    "wof:name":"Lee Pet Shop",
    "wof:placetype":"venue"
},
  "geometry": {"coordinates":[-118.05999799999999,34.062801],"type":"Point"}
}