{
  "type": "Feature",
  "properties": {
    "addr:full":"249 Omira Dr San Jose CA 95123",
    "addr:housenumber":"249",
    "addr:postcode":"95123",
    "addr:street":"Omira Dr",
    "iso:country":"US",
    "sg:address":"249 Omira Dr",
    "sg:city":"San Jose",
    "sg:classifiers":[
        {
            "category":"Professional",
            "subcategory":"Engineering",
            "type":"Services"
        }
    ],
    "sg:phone":"+1 408 972 1318",
    "sg:postcode":"95123",
    "sg:province":"CA",
    "sg:tags":[
        "engineer"
    ],
    "sg:website":"www.terminus-design.com",
    "wof:name":"Terminus Design",
    "wof:placetype":"venue"
},
  "geometry": {"coordinates":[-121.81461400000001,37.250677],"type":"Point"}
}