{
  "type": "Feature",
  "properties": {
    "iso:country":"US",
    "sg:address":"972 Admiral Callaghan Ln",
    "sg:city":"Vallejo",
    "sg:classifiers":[
        {
            "category":"Personal",
            "subcategory":"Beauty Salon",
            "type":"Services"
        }
    ],
    "sg:phone":"+1 707 644 5668",
    "sg:postcode":"94591",
    "sg:province":"CA",
    "wof:name":"Kim's Beauty Care",
    "wof:placetype":"venue"
},
  "geometry": {"coordinates":[-122.222263,38.134147],"type":"Point"}
}