{
  "type": "Feature",
  "properties": {
    "iso:country":"US",
    "sg:address":"1510 Spring Creek Ln",
    "sg:city":"Oceanside",
    "sg:classifiers":[
        {
            "category":"Building & Trades",
            "subcategory":"Construction",
            "type":"Services"
        }
    ],
    "sg:phone":"+1 760 941 8510",
    "sg:postcode":"92057",
    "sg:province":"CA",
    "sg:tags":[
        "contractor"
    ],
    "wof:name":"William J Olson Masonry",
    "wof:placetype":"venue"
},
  "geometry": {"coordinates":[-117.260777,33.248869],"type":"Point"}
}