{
  "type": "Feature",
  "properties": {
    "iso:country":"US",
    "sg:address":"1820 N Imperial Ave",
    "sg:city":"Calexico",
    "sg:classifiers":[
        {
            "category":"Retail",
            "subcategory":"Funeral Services",
            "type":"Services"
        }
    ],
    "sg:phone":"+1 760 357 3757",
    "sg:postcode":"92231",
    "sg:province":"CA",
    "sg:tags":[
        "director"
    ],
    "wof:name":"Hems Brothers Mortuary",
    "wof:placetype":"venue"
},
  "geometry": {"coordinates":[-115.56999399999999,32.814412],"type":"Point"}
}