{
  "type": "Feature",
  "properties": {
    "iso:country":"US",
    "sg:address":"4994 Bullion St",
    "sg:city":"Mariposa",
    "sg:classifiers":[
        {
            "category":"Travel",
            "subcategory":"Hotels & Motels",
            "type":"Entertainment"
        }
    ],
    "sg:phone":"+1 209 966 4344",
    "sg:postcode":"95338",
    "sg:province":"CA",
    "wof:name":"Comfort Inn",
    "wof:placetype":"venue"
},
  "geometry": {"coordinates":[-119.96445799999999,37.485377],"type":"Point"}
}