{
  "type": "Feature",
  "properties": {
    "iso:country":"US",
    "sg:address":"6801 Hollywood Blvd",
    "sg:city":"Los Angeles",
    "sg:classifiers":[
        {
            "category":"Museum",
            "type":"Entertainment"
        }
    ],
    "sg:phone":"+1 323 469 1839",
    "sg:postcode":"90028",
    "sg:province":"CA",
    "wof:name":"Starring You Kiosk",
    "wof:placetype":"venue"
},
  "geometry": {"coordinates":[-118.340109,34.101677],"type":"Point"}
}