{
  "type": "Feature",
  "properties": {
    "addr:full":"1350 Northwood Ct Fairfield CA 94534",
    "addr:housenumber":"1350",
    "addr:postcode":"94534",
    "addr:street":"Northwood Ct",
    "iso:country":"US",
    "sg:address":"1350 Northwood Ct",
    "sg:city":"Fairfield",
    "sg:classifiers":[
        {
            "category":"Building & Trades",
            "subcategory":"Electrical",
            "type":"Services"
        }
    ],
    "sg:phone":"+1 707 864 8414",
    "sg:postcode":"94534",
    "sg:province":"CA",
    "sg:tags":[
        "electric",
        "contractor"
    ],
    "wof:name":"A Plus Electrical Svc",
    "wof:placetype":"venue"
},
  "geometry": {"coordinates":[-122.135046,38.178612],"type":"Point"}
}