{
  "type": "Feature",
  "properties": {
    "addr:full":"1016 W Manchester Ave Los Angeles CA 90044",
    "addr:housenumber":"1016",
    "addr:postcode":"90044",
    "addr:street":"W Manchester Ave",
    "iso:country":"US",
    "sg:address":"1016 W Manchester Ave",
    "sg:city":"Los Angeles",
    "sg:classifiers":[
        {
            "category":"Organizations",
            "subcategory":"Religious Organization",
            "type":"Services"
        }
    ],
    "sg:phone":"+1 323 753 2696",
    "sg:postcode":"90044",
    "sg:province":"CA",
    "sg:tags":[
        "church"
    ],
    "wof:name":"St Michael Church",
    "wof:placetype":"venue"
},
  "geometry": {"coordinates":[-118.29226800000001,33.960099],"type":"Point"}
}