{
  "type": "Feature",
  "properties": {
    "addr:full":"408 18th St Bakersfield CA 93301",
    "addr:housenumber":"408",
    "addr:postcode":"93301",
    "addr:street":"18Th St",
    "iso:country":"US",
    "sg:address":"408 18th St",
    "sg:city":"Bakersfield",
    "sg:classifiers":[
        {
            "category":"Professional",
            "subcategory":"Lawyer & Legal Services",
            "type":"Services"
        }
    ],
    "sg:phone":"+1 661 395 1031",
    "sg:postcode":"93301",
    "sg:province":"CA",
    "sg:tags":[
        "attorney",
        "death",
        "personal",
        "disability",
        "worker",
        "compensation",
        "wrongful",
        "benefit",
        "social",
        "employee",
        "security",
        "injury",
        "law"
    ],
    "sg:website":"http://www.joepluta.net",
    "wof:name":"Pluta, Joseph",
    "wof:placetype":"venue"
},
  "geometry": {"coordinates":[-119.00608200000001,35.375228],"type":"Point"}
}