{
  "type": "Feature",
  "properties": {
    "iso:country":"US",
    "sg:address":"242 S Date St W",
    "sg:city":"Anaheim",
    "sg:classifiers":[
        {
            "category":"Building & Trades",
            "subcategory":"Construction",
            "type":"Services"
        }
    ],
    "sg:phone":"+1 714 776 0337",
    "sg:postcode":"92805",
    "sg:province":"CA",
    "sg:tags":[
        "hanging",
        "contractor"
    ],
    "wof:name":"John C Senne",
    "wof:placetype":"venue"
},
  "geometry": {"coordinates":[-117.89368,33.838654],"type":"Point"}
}