{
  "type": "Feature",
  "properties": {
    "iso:country":"US",
    "sg:address":"4555 E Pine Ave",
    "sg:city":"Fresno",
    "sg:classifiers":[
        {
            "category":"Autos & Motor Vehicles",
            "subcategory":"Automobile Sales",
            "type":"Retail Goods"
        }
    ],
    "sg:phone":"+1 559 255 8058",
    "sg:postcode":"93703",
    "sg:province":"CA",
    "sg:tags":[
        "car",
        "dealer"
    ],
    "wof:name":"California Automotive Remktg",
    "wof:placetype":"venue"
},
  "geometry": {"coordinates":[-119.745569,36.762367],"type":"Point"}
}