{
  "type": "Feature",
  "properties": {
    "iso:country":"US",
    "sg:address":"6185 Paseo Del Norte",
    "sg:city":"Carlsbad",
    "sg:classifiers":[
        {
            "category":"Banks & Credit Unions",
            "subcategory":"Financial Services",
            "type":"Services"
        }
    ],
    "sg:phone":"+1 760 710 3055",
    "sg:postcode":"92011",
    "sg:province":"CA",
    "sg:tags":[
        "broker",
        "mortgage"
    ],
    "wof:name":"Sunset Coast Capital",
    "wof:placetype":"venue"
},
  "geometry": {"coordinates":[-117.318792,33.118783],"type":"Point"}
}