{
  "type": "Feature",
  "properties": {
    "iso:country":"US",
    "sg:address":"9530 Pathway St",
    "sg:city":"Santee",
    "sg:classifiers":[
        {
            "category":"Manufacturing",
            "subcategory":"Electronics",
            "type":"Manufacturing & Wholesale Goods"
        }
    ],
    "sg:phone":"+1 619 449 0484",
    "sg:postcode":"92071",
    "sg:province":"CA",
    "wof:name":"Rozendal Associates",
    "wof:placetype":"venue"
},
  "geometry": {"coordinates":[-116.988981,32.8318],"type":"Point"}
}