{
  "type": "Feature",
  "properties": {
    "iso:country":"US",
    "sg:address":"1110 Seward St",
    "sg:city":"Los Angeles",
    "sg:classifiers":[
        {
            "category":"Arts & Performance",
            "subcategory":"Arts Center",
            "type":"Entertainment"
        }
    ],
    "sg:phone":"+1 323 466 7781",
    "sg:postcode":"90038",
    "sg:province":"CA",
    "sg:tags":[
        "performing"
    ],
    "wof:name":"Unknown Theater",
    "wof:placetype":"venue"
},
  "geometry": {"coordinates":[-118.333096,34.091173],"type":"Point"}
}