{
  "type": "Feature",
  "properties": {
    "addr:full":"1870 S Laspina St Tulare CA 93274",
    "addr:housenumber":"1870",
    "addr:postcode":"93274",
    "addr:street":"S Laspina St",
    "iso:country":"US",
    "sg:address":"1870 S Laspina St",
    "sg:city":"Tulare",
    "sg:classifiers":[
        {
            "category":"Education",
            "subcategory":"School",
            "type":"Public Place"
        }
    ],
    "sg:phone":"+1 559 685 7290",
    "sg:postcode":"93274",
    "sg:province":"CA",
    "wof:name":"Cypress School",
    "wof:placetype":"venue"
},
  "geometry": {"coordinates":[-119.324288,36.189333],"type":"Point"}
}