{
  "type": "Feature",
  "properties": {
    "iso:country":"US",
    "sg:address":"19510 Ventura Blvd",
    "sg:city":"Tarzana",
    "sg:classifiers":[
        {
            "category":"Banks & Credit Unions",
            "subcategory":"Investment Brokerage",
            "type":"Services"
        }
    ],
    "sg:phone":"+1 818 264 3961",
    "sg:postcode":"91356",
    "sg:province":"CA",
    "sg:tags":[
        "advisory",
        "financial"
    ],
    "wof:name":"Maxwell Financial Inc",
    "wof:placetype":"venue"
},
  "geometry": {"coordinates":[-118.559819,34.17273],"type":"Point"}
}