{
  "type": "Feature",
  "properties": {
    "addr:full":"18530 S Broadway St Gardena CA 90248",
    "addr:housenumber":"18530",
    "addr:postcode":"90248",
    "addr:street":"S Broadway St",
    "iso:country":"US",
    "sg:address":"18530 S Broadway St",
    "sg:city":"Gardena",
    "sg:classifiers":[
        {
            "category":"Home & Garden",
            "subcategory":"Building Materials",
            "type":"Retail Goods"
        }
    ],
    "sg:phone":"+1 310 371 2100",
    "sg:postcode":"90248",
    "sg:province":"CA",
    "sg:tags":[
        "door"
    ],
    "wof:name":"TWI Garage Door",
    "wof:placetype":"venue"
},
  "geometry": {"coordinates":[-118.2784,33.863186],"type":"Point"}
}