{
  "type": "Feature",
  "properties": {
    "addr:full":"3850 Jasmine Ave Culver City CA 90232",
    "addr:housenumber":"3850",
    "addr:postcode":"90232",
    "addr:street":"Jasmine Ave",
    "iso:country":"US",
    "sg:address":"3850 Jasmine Ave",
    "sg:city":"Culver City",
    "sg:classifiers":[
        {
            "category":"Professional",
            "type":"Services"
        }
    ],
    "sg:phone":"+1 310 388 4931",
    "sg:postcode":"90232",
    "sg:province":"CA",
    "wof:name":"Rapid Bail Bond",
    "wof:placetype":"venue"
},
  "geometry": {"coordinates":[-118.400864,34.02097],"type":"Point"}
}