{
  "type": "Feature",
  "properties": {
    "addr:full":"18 Skylark Dr Larkspur CA 94939",
    "addr:housenumber":"18",
    "addr:postcode":"94939",
    "addr:street":"Skylark Dr",
    "iso:country":"US",
    "sg:address":"18 Skylark Dr",
    "sg:city":"Larkspur",
    "sg:classifiers":[
        {
            "category":"Organizations",
            "subcategory":"Non-profit Organization",
            "type":"Services"
        }
    ],
    "sg:phone":"+1 415 927 7464",
    "sg:postcode":"94939",
    "sg:province":"CA",
    "wof:name":"Construction Roundtable",
    "wof:placetype":"venue"
},
  "geometry": {"coordinates":[-122.54364,37.94407],"type":"Point"}
}