{
  "type": "Feature",
  "properties": {
    "addr:full":"21634 Mann Rd Acampo CA 95220",
    "addr:postcode":"21634;95220",
    "addr:street":"Mann Rd",
    "iso:country":"US",
    "sg:address":"21634 Mann Rd",
    "sg:city":"Acampo",
    "sg:classifiers":[
        {
            "category":"Farming",
            "subcategory":"Farm & Veterinary Services",
            "type":"Manufacturing & Wholesale Goods"
        }
    ],
    "sg:phone":"+1 209 368 9293",
    "sg:postcode":"95220",
    "sg:province":"CA",
    "sg:tags":[
        "management"
    ],
    "wof:name":"Charles Starr",
    "wof:placetype":"venue"
},
  "geometry": {"coordinates":[-121.21485199999999,38.175983],"type":"Point"}
}