{
  "type": "Feature",
  "properties": {
    "iso:country":"US",
    "sg:address":"47224 Mission Falls Ct.",
    "sg:city":"Fremont",
    "sg:classifiers":[
        {
            "category":"Professional",
            "subcategory":"Research",
            "type":"Services"
        }
    ],
    "sg:phone":"+1 510 226 5860",
    "sg:postcode":"94539",
    "sg:province":"CA",
    "sg:website":"http://www.vioptix.com",
    "wof:name":"ViOptix",
    "wof:placetype":"venue"
},
  "geometry": {"coordinates":[-121.929024,37.48576],"type":"Point"}
}