{
  "type": "Feature",
  "properties": {
    "iso:country":"US",
    "sg:address":"120 Genoa Way",
    "sg:city":"Upland",
    "sg:classifiers":[
        {
            "category":"Professional",
            "type":"Services"
        }
    ],
    "sg:phone":"+1 909 946 9457",
    "sg:postcode":"91786",
    "sg:province":"CA",
    "wof:name":"Carey A Olcott",
    "wof:placetype":"venue"
},
  "geometry": {"coordinates":[-117.679077,34.092805],"type":"Point"}
}