{
  "type": "Feature",
  "properties": {
    "addr:full":"1663 Dominican Way Suite 210 Santa Cruz CA 95065",
    "addr:housenumber":"1663",
    "addr:postcode":"95065",
    "addr:street":"Dominican Way Suite 210",
    "iso:country":"US",
    "sg:address":"1663 Dominican Way Suite 210",
    "sg:city":"Santa Cruz",
    "sg:classifiers":[
        {
            "category":"Health Services",
            "subcategory":"Doctor",
            "type":"Services"
        }
    ],
    "sg:phone":"+1 831 462 5500",
    "sg:postcode":"95065",
    "sg:province":"CA",
    "sg:tags":[
        "orthopedist"
    ],
    "wof:name":"Harper Glenn E",
    "wof:placetype":"venue"
},
  "geometry": {"coordinates":[-121.98271800000001,36.9906],"type":"Point"}
}