{
  "type": "Feature",
  "properties": {
    "addr:full":"5401 E Jurupa St Ontario CA 91761",
    "addr:housenumber":"5401",
    "addr:postcode":"91761",
    "addr:street":"E Jurupa St",
    "iso:country":"US",
    "sg:address":"5401 E Jurupa St",
    "sg:city":"Ontario",
    "sg:classifiers":[
        {
            "category":"Professional",
            "subcategory":"Advertising",
            "type":"Services"
        }
    ],
    "sg:phone":"+1 909 390 6228",
    "sg:postcode":"91761",
    "sg:province":"CA",
    "sg:tags":[
        "mailing",
        "shipping"
    ],
    "wof:name":"Workflow Direct Inc",
    "wof:placetype":"venue"
},
  "geometry": {"coordinates":[-117.53438199999999,34.048146],"type":"Point"}
}