{
  "type": "Feature",
  "properties": {
    "iso:country":"US",
    "sg:address":"10629 Woodbridge St",
    "sg:city":"North Hollywood",
    "sg:classifiers":[
        {
            "category":"Professional",
            "type":"Services"
        }
    ],
    "sg:phone":"+1 818 509 8351",
    "sg:postcode":"91602",
    "sg:province":"CA",
    "sg:tags":[
        "establishment"
    ],
    "wof:name":"Tolucan Villas Homeowners Asso",
    "wof:placetype":"venue"
},
  "geometry": {"coordinates":[-118.363113,34.148925],"type":"Point"}
}