{
  "type": "Feature",
  "properties": {
    "addr:full":"13462 Magnolia Ave Corona CA 92879",
    "addr:housenumber":"13462",
    "addr:postcode":"92879",
    "addr:street":"Magnolia Ave",
    "iso:country":"US",
    "sg:address":"13462 Magnolia Ave",
    "sg:city":"Corona",
    "sg:classifiers":[
        {
            "category":"Organizations",
            "subcategory":"Religious Organization",
            "type":"Services"
        }
    ],
    "sg:phone":"+1 951 735 6953",
    "sg:postcode":"92879",
    "sg:province":"CA",
    "sg:tags":[
        "church"
    ],
    "wof:name":"Our Lady Of Tepeyac",
    "wof:placetype":"venue"
},
  "geometry": {"coordinates":[-117.519801,33.879118],"type":"Point"}
}