{
  "type": "Feature",
  "properties": {
    "iso:country":"US",
    "sg:address":"31145 Monte Vista Way",
    "sg:city":"Thousand Palms",
    "sg:classifiers":[
        {
            "category":"Building & Trades",
            "subcategory":"Landscaping Services",
            "type":"Services"
        }
    ],
    "sg:phone":"+1 760 343 2233",
    "sg:postcode":"92276",
    "sg:province":"CA",
    "sg:tags":[
        "landscape",
        "contractor"
    ],
    "wof:name":"Quality Green Landscaping",
    "wof:placetype":"venue"
},
  "geometry": {"coordinates":[-116.39215,33.821073],"type":"Point"}
}