{
  "type": "Feature",
  "properties": {
    "addr:full":"16623 Las Palmas St Hesperia CA 92345",
    "addr:housenumber":"16623",
    "addr:postcode":"92345",
    "addr:street":"Las Palmas St",
    "iso:country":"US",
    "sg:address":"16623 Las Palmas St",
    "sg:city":"Hesperia",
    "sg:classifiers":[
        {
            "category":"Retail",
            "subcategory":"Car Wash",
            "type":"Services"
        }
    ],
    "sg:phone":"+1 760 792 9635",
    "sg:postcode":"92345",
    "sg:province":"CA",
    "sg:tags":[
        "automobile",
        "detail",
        "clean"
    ],
    "wof:name":"Dynamic Detail",
    "wof:placetype":"venue"
},
  "geometry": {"coordinates":[-117.301106,34.454304],"type":"Point"}
}