{
  "type": "Feature",
  "properties": {
    "iso:country":"US",
    "sg:address":"1141 Lighthouse Ave",
    "sg:city":"Pacific Grove",
    "sg:classifiers":[
        {
            "category":"Real Estate",
            "subcategory":"Real Estate Operator",
            "type":"Services"
        }
    ],
    "sg:phone":"+1 831 372 6514",
    "sg:postcode":"93950",
    "sg:province":"CA",
    "sg:tags":[
        "apartment"
    ],
    "wof:name":"Villa Del Mar",
    "wof:placetype":"venue"
},
  "geometry": {"coordinates":[-121.93052900000001,36.629011],"type":"Point"}
}