{
  "type": "Feature",
  "properties": {
    "addr:full":"7347 Hastings Ave Hesperia CA 92345",
    "addr:housenumber":"7347",
    "addr:postcode":"92345",
    "addr:street":"Hastings Ave",
    "iso:country":"US",
    "sg:address":"7347 Hastings Ave",
    "sg:city":"Hesperia",
    "sg:classifiers":[
        {
            "category":"Health Services",
            "subcategory":"Clinic",
            "type":"Services"
        }
    ],
    "sg:phone":"+1 760 947 2426",
    "sg:postcode":"92345",
    "sg:province":"CA",
    "sg:tags":[
        "medical",
        "training",
        "emergency"
    ],
    "wof:name":"Learn Cpr 4 Life",
    "wof:placetype":"venue"
},
  "geometry": {"coordinates":[-117.28648,34.385765],"type":"Point"}
}