{
  "type": "Feature",
  "properties": {
    "addr:full":"1088 Sansome St San Francisco CA 94111",
    "addr:housenumber":"1088",
    "addr:postcode":"94111",
    "addr:street":"Sansome St",
    "iso:country":"US",
    "sg:address":"1088 Sansome St",
    "sg:city":"San Francisco",
    "sg:classifiers":[
        {
            "category":"Manufacturing",
            "subcategory":"Electronics",
            "type":"Manufacturing & Wholesale Goods"
        }
    ],
    "sg:phone":"+1 415 394 1288",
    "sg:postcode":"94111",
    "sg:province":"CA",
    "sg:tags":[
        "equipment",
        "electronic",
        "supply"
    ],
    "wof:name":"Leemah Electronics Inc",
    "wof:placetype":"venue"
},
  "geometry": {"coordinates":[-122.4024,37.799488],"type":"Point"}
}