{
  "type": "Feature",
  "properties": {
    "addr:full":"125 N Jackson Ave Jackson Medical Center Ste 204 San Jose CA 95116",
    "addr:housenumber":"125;ste 204",
    "addr:postcode":"95116",
    "addr:street":"N Jackson Ave",
    "iso:country":"US",
    "sg:address":"125 N Jackson Ave Jackson Medical Center Ste 204",
    "sg:city":"San Jose",
    "sg:classifiers":[
        {
            "category":"Health Services",
            "subcategory":"Clinic",
            "type":"Services"
        }
    ],
    "sg:phone":"+1 408 372 3777",
    "sg:postcode":"95116",
    "sg:province":"CA",
    "sg:tags":[
        "cannabis"
    ],
    "sg:website":"www.nchealthcenter.org",
    "wof:name":"Norcal Health Center",
    "wof:placetype":"venue"
},
  "geometry": {"coordinates":[-121.84713499999999,37.360842],"type":"Point"}
}