{
  "type": "Feature",
  "properties": {
    "addr:full":"14850 Victory Blvd Van Nuys CA 91411",
    "addr:housenumber":"14850",
    "addr:postcode":"91411",
    "addr:street":"Victory Blvd",
    "iso:country":"US",
    "sg:address":"14850 Victory Blvd",
    "sg:city":"Van Nuys",
    "sg:classifiers":[
        {
            "category":"Restaurant",
            "type":"Food & Drink"
        }
    ],
    "sg:menulink":"http://www.allmenus.com/ca/san-fernando-valley/216031-mcdonalds/menu/",
    "sg:postcode":"91411",
    "sg:province":"CA",
    "sg:tags":[
        "burger",
        "american"
    ],
    "wof:name":"McDonald's",
    "wof:placetype":"venue"
},
  "geometry": {"coordinates":[-118.457058,34.18634],"type":"Point"}
}