{
  "type": "Feature",
  "properties": {
    "iso:country":"US",
    "sg:address":"11931 Hillside Rd",
    "sg:city":"Forestville",
    "sg:classifiers":[
        {
            "category":"Manufacturing",
            "subcategory":"Buildings",
            "type":"Manufacturing & Wholesale Goods"
        },
        {
            "category":"Building & Trades",
            "subcategory":"Construction",
            "type":"Services"
        }
    ],
    "sg:phone":"+1 707 290 3610",
    "sg:postcode":"95436",
    "sg:province":"CA",
    "sg:tags":[
        "home",
        "builder",
        "contractor"
    ],
    "wof:name":"Big River Builders",
    "wof:placetype":"venue"
},
  "geometry": {"coordinates":[-122.94231499999999,38.497686],"type":"Point"}
}