{
  "type": "Feature",
  "properties": {
    "addr:full":"1450 E Front St Selma CA 93662",
    "addr:housenumber":"1450",
    "addr:postcode":"93662",
    "addr:street":"E Front St",
    "iso:country":"US",
    "sg:address":"1450 E Front St",
    "sg:city":"Selma",
    "sg:classifiers":[
        {
            "category":"Professional",
            "subcategory":"Accounting & Tax Preparation",
            "type":"Services"
        }
    ],
    "sg:phone":"+1 559 896 9178",
    "sg:postcode":"93662",
    "sg:province":"CA",
    "sg:tags":[
        "accountant"
    ],
    "wof:name":"Jim Sabbatini",
    "wof:placetype":"venue"
},
  "geometry": {"coordinates":[-119.60832600000001,36.563858],"type":"Point"}
}