{
  "type": "Feature",
  "properties": {
    "addr:full":"1680 Vine St Los Angeles CA 90028",
    "addr:housenumber":"1680",
    "addr:postcode":"90028",
    "addr:street":"Vine St",
    "iso:country":"US",
    "sg:address":"1680 Vine St",
    "sg:city":"Los Angeles",
    "sg:classifiers":[
        {
            "category":"Real Estate",
            "subcategory":"Architect",
            "type":"Services"
        }
    ],
    "sg:phone":"+1 323 462 6296",
    "sg:postcode":"90028",
    "sg:province":"CA",
    "wof:name":"Bridgwater Consulting Group",
    "wof:placetype":"venue"
},
  "geometry": {"coordinates":[-118.32659700000001,34.100129],"type":"Point"}
}