{
  "type": "Feature",
  "properties": {
    "addr:full":"4176 Piedmont Ave Oakland CA 94611",
    "addr:housenumber":"4176",
    "addr:postcode":"94611",
    "addr:street":"Piedmont Ave",
    "iso:country":"US",
    "sg:address":"4176 Piedmont Ave",
    "sg:city":"Oakland",
    "sg:classifiers":[
        {
            "category":"Shopping",
            "type":"Retail Goods"
        }
    ],
    "sg:phone":"+1 510 923 1222",
    "sg:postcode":"94611",
    "sg:province":"CA",
    "sg:tags":[
        "gallery",
        "merchandise"
    ],
    "wof:name":"Shamwari Gallery",
    "wof:placetype":"venue"
},
  "geometry": {"coordinates":[-122.251953,37.82673],"type":"Point"}
}