{
  "type": "Feature",
  "properties": {
    "iso:country":"US",
    "sg:address":"508 S Brookhurst St",
    "sg:city":"Anaheim",
    "sg:classifiers":[
        {
            "category":"Shopping",
            "subcategory":"Tobacco",
            "type":"Retail Goods"
        }
    ],
    "sg:phone":"+1 714 774 7467",
    "sg:postcode":"92804",
    "sg:province":"CA",
    "sg:tags":[
        "shop"
    ],
    "wof:name":"World Smoke Shop",
    "wof:placetype":"venue"
},
  "geometry": {"coordinates":[-117.958753,33.826036],"type":"Point"}
}