{
  "type": "Feature",
  "properties": {
    "addr:full":"663 N Heliotrope Dr Los Angeles CA 90004",
    "addr:housenumber":"663",
    "addr:postcode":"90004",
    "addr:street":"N Heliotrope Dr",
    "iso:country":"US",
    "sg:address":"663 N Heliotrope Dr",
    "sg:city":"Los Angeles",
    "sg:classifiers":[
        {
            "category":"Food & Beverages",
            "subcategory":"Groceries & Convenience Stores",
            "type":"Retail Goods"
        }
    ],
    "sg:phone":"+1 323 666 8767",
    "sg:postcode":"90004",
    "sg:province":"CA",
    "wof:name":"Iby Mini Market",
    "wof:placetype":"venue"
},
  "geometry": {"coordinates":[-118.29499800000001,34.083099],"type":"Point"}
}