{
  "type": "Feature",
  "properties": {
    "addr:full":"2401 E Valley Pkwy Escondido CA 92027",
    "addr:housenumber":"2401",
    "addr:postcode":"92027",
    "addr:street":"E Valley Pkwy",
    "iso:country":"US",
    "sg:address":"2401 E Valley Pkwy",
    "sg:city":"Escondido",
    "sg:classifiers":[
        {
            "category":"Autos & Motor Vehicles",
            "subcategory":"Auto Supplies",
            "type":"Retail Goods"
        },
        {
            "category":"Wholesale",
            "subcategory":"Auto Parts",
            "type":"Manufacturing & Wholesale Goods"
        }
    ],
    "sg:phone":"+1 760 746 6593",
    "sg:postcode":"92027",
    "sg:province":"CA",
    "sg:tags":[
        "body",
        "automobile",
        "truck",
        "equipment",
        "accessory"
    ],
    "sg:website":"http://www.oreillyauto.com?utm_source=yellowpages&utm_medium=iyp&utm_campaign=2627",
    "wof:name":"Kragen O'ReillyAuto Parts",
    "wof:placetype":"venue"
},
  "geometry": {"coordinates":[-117.04424299999999,33.14098],"type":"Point"}
}