{
  "type": "Feature",
  "properties": {
    "iso:country":"US",
    "sg:address":"11244 Tahoe St",
    "sg:city":"Auburn",
    "sg:classifiers":[
        {
            "category":"Retail",
            "subcategory":"Laundry & Dry Cleaning",
            "type":"Services"
        }
    ],
    "sg:phone":"+1 530 823 1911",
    "sg:postcode":"95602",
    "sg:province":"CA",
    "sg:tags":[
        "cleaner",
        "rug",
        "carpet"
    ],
    "wof:name":"Golden Carpet Cleaners Of Auburn",
    "wof:placetype":"venue"
},
  "geometry": {"coordinates":[-121.11421300000001,38.945487],"type":"Point"}
}