{
  "type": "Feature",
  "properties": {
    "addr:full":"530 Jackson St San Francisco CA 94133",
    "addr:housenumber":"530",
    "addr:postcode":"94133",
    "addr:street":"Jackson St",
    "iso:country":"US",
    "sg:address":"530 Jackson St",
    "sg:city":"San Francisco",
    "sg:classifiers":[
        {
            "category":"Professional",
            "subcategory":"Lawyer & Legal Services",
            "type":"Services"
        }
    ],
    "sg:phone":"+1 415 296 8844",
    "sg:postcode":"94133",
    "sg:province":"CA",
    "sg:website":"www.ladvashoker.com",
    "wof:name":"Ladva Shoker & Associates",
    "wof:placetype":"venue"
},
  "geometry": {"coordinates":[-122.40412499999999,37.796357],"type":"Point"}
}