{
  "type": "Feature",
  "properties": {
    "addr:full":"1027 Roosevelt St Monterey CA 93940",
    "addr:housenumber":"1027",
    "addr:postcode":"93940",
    "addr:street":"Roosevelt St",
    "iso:country":"US",
    "sg:address":"1027 Roosevelt St",
    "sg:city":"Monterey",
    "sg:classifiers":[
        {
            "category":"Building & Trades",
            "subcategory":"Construction",
            "type":"Services"
        }
    ],
    "sg:phone":"+1 831 646 0634",
    "sg:postcode":"93940",
    "sg:province":"CA",
    "sg:tags":[
        "contractor"
    ],
    "wof:name":"Davi Plastering",
    "wof:placetype":"venue"
},
  "geometry": {"coordinates":[-121.906536,36.601686],"type":"Point"}
}