{
  "type": "Feature",
  "properties": {
    "iso:country":"US",
    "sg:address":"1072 S de Anza Blvd",
    "sg:city":"San Jose",
    "sg:classifiers":[
        {
            "category":"Utilities",
            "subcategory":"Cable",
            "type":"Services"
        },
        {
            "category":"Shopping",
            "subcategory":"Computers & Home Electronics",
            "type":"Retail Goods"
        }
    ],
    "sg:phone":"+1 408 253 1490",
    "sg:postcode":"95129",
    "sg:province":"CA",
    "sg:tags":[
        "equipment",
        "television",
        "satellite",
        "system"
    ],
    "wof:name":"Dishnet Direct",
    "wof:placetype":"venue"
},
  "geometry": {"coordinates":[-122.032179,37.306894],"type":"Point"}
}