{
  "type": "Feature",
  "properties": {
    "addr:full":"300 W Lincoln St Banning CA 92220",
    "addr:housenumber":"300",
    "addr:postcode":"92220",
    "addr:street":"W Lincoln St",
    "iso:country":"US",
    "sg:address":"300 W Lincoln St",
    "sg:city":"Banning",
    "sg:classifiers":[
        {
            "category":"Personal",
            "type":"Services"
        }
    ],
    "sg:phone":"+1 951 846 6371",
    "sg:postcode":"92220",
    "sg:province":"CA",
    "sg:tags":[
        "mover"
    ],
    "sg:website":"www.burgessrelocation.com",
    "wof:name":"Burgess North American",
    "wof:placetype":"venue"
},
  "geometry": {"coordinates":[-116.879931,33.920977],"type":"Point"}
}