{
  "type": "Feature",
  "properties": {
    "iso:country":"US",
    "sg:address":"4125 Solano Ave",
    "sg:city":"Napa",
    "sg:classifiers":[
        {
            "category":"Organizations",
            "subcategory":"Community Association",
            "type":"Services"
        }
    ],
    "sg:phone":"+1 707 252 4159",
    "sg:postcode":"94558",
    "sg:province":"CA",
    "sg:tags":[
        "fraternal"
    ],
    "wof:name":"Masonic Lodge",
    "wof:placetype":"venue"
},
  "geometry": {"coordinates":[-122.318203,38.3309],"type":"Point"}
}