{
  "type": "Feature",
  "properties": {
    "iso:country":"US",
    "sg:address":"801 E Katella Ave Fl 3",
    "sg:city":"Anaheim",
    "sg:classifiers":[
        {
            "category":"Travel",
            "subcategory":"Travel Agent",
            "type":"Entertainment"
        }
    ],
    "sg:phone":"+1 714 935 0808",
    "sg:postcode":"92805",
    "sg:province":"CA",
    "sg:website":"www.contiki.com/",
    "wof:name":"Contiki Holidays",
    "wof:placetype":"venue"
},
  "geometry": {"coordinates":[-117.899002,33.803501],"type":"Point"}
}