{
  "type": "Feature",
  "properties": {
    "addr:full":"1817 Carleton Street Berkeley CA 94703",
    "addr:housenumber":"1817",
    "addr:postcode":"94703",
    "addr:street":"Carleton Street",
    "iso:country":"US",
    "sg:address":"1817 Carleton Street",
    "sg:city":"Berkeley",
    "sg:classifiers":[
        {
            "category":"Professional",
            "subcategory":"Lawyer & Legal Services",
            "type":"Services"
        }
    ],
    "sg:phone":"+1 510 841 7557",
    "sg:postcode":"94703",
    "sg:province":"CA",
    "wof:name":"Holt Len W Atty",
    "wof:placetype":"venue"
},
  "geometry": {"coordinates":[-122.273003,37.8606],"type":"Point"}
}