{
  "type": "Feature",
  "properties": {
    "iso:country":"US",
    "sg:address":"700 E 6th St",
    "sg:city":"Los Angeles",
    "sg:classifiers":[
        {
            "category":"Restaurant",
            "type":"Food & Drink"
        },
        {
            "category":"Food & Beverages",
            "subcategory":"Meat & Fish",
            "type":"Retail Goods"
        }
    ],
    "sg:phone":"+1 213 683 8345",
    "sg:postcode":"90021",
    "sg:province":"CA",
    "sg:tags":[
        "seafood",
        "market"
    ],
    "wof:name":"Pacific Fresh Fish",
    "wof:placetype":"venue"
},
  "geometry": {"coordinates":[-118.24400300000001,34.0411],"type":"Point"}
}