{
  "type": "Feature",
  "properties": {
    "iso:country":"US",
    "sg:address":"1029 Orange St",
    "sg:city":"Redlands",
    "sg:classifiers":[
        {
            "category":"Autos & Motor Vehicles",
            "subcategory":"Automobile Sales",
            "type":"Retail Goods"
        }
    ],
    "sg:phone":"+1 909 335 8600",
    "sg:postcode":"92374",
    "sg:province":"CA",
    "sg:tags":[
        "trade",
        "used",
        "contractor"
    ],
    "wof:name":"Hergot Enterprises",
    "wof:placetype":"venue"
},
  "geometry": {"coordinates":[-117.182586,34.066109],"type":"Point"}
}