{
  "type": "Feature",
  "properties": {
    "iso:country":"US",
    "sg:address":"1007 N Western Ave",
    "sg:city":"Los Angeles",
    "sg:classifiers":[
        {
            "category":"Fast Food",
            "type":"Food & Drink"
        }
    ],
    "sg:phone":"+1 323 465 3288",
    "sg:postcode":"90029",
    "sg:province":"CA",
    "sg:tags":[
        "burger"
    ],
    "sg:website":"www.mcdonalds.com",
    "wof:name":"McDonald's",
    "wof:placetype":"venue"
},
  "geometry": {"coordinates":[-118.309155,34.088631],"type":"Point"}
}