{
  "type": "Feature",
  "properties": {
    "addr:full":"686 Escobar St Martinez CA 94553",
    "addr:housenumber":"686",
    "addr:postcode":"94553",
    "addr:street":"Escobar St",
    "iso:country":"US",
    "sg:address":"686 Escobar St",
    "sg:city":"Martinez",
    "sg:classifiers":[
        {
            "category":"Wholesale",
            "subcategory":"Electrical",
            "type":"Manufacturing & Wholesale Goods"
        }
    ],
    "sg:phone":"+1 925 372 5832",
    "sg:postcode":"94553",
    "sg:province":"CA",
    "sg:tags":[
        "lighting",
        "fixture"
    ],
    "wof:name":"Lights Of Diablo",
    "wof:placetype":"venue"
},
  "geometry": {"coordinates":[-122.137417,38.01762],"type":"Point"}
}