{
  "type": "Feature",
  "properties": {
    "iso:country":"US",
    "sg:address":"17836 Hwy 67",
    "sg:city":"Ramona",
    "sg:classifiers":[
        {
            "category":"Professional",
            "subcategory":"Management & Consulting",
            "type":"Services"
        }
    ],
    "sg:phone":"+1 760 787 1089",
    "sg:postcode":"92065",
    "sg:province":"CA",
    "sg:tags":[
        "consultant",
        "telephone"
    ],
    "wof:name":"Kotcher Communications",
    "wof:placetype":"venue"
},
  "geometry": {"coordinates":[-116.921787,33.009289],"type":"Point"}
}