{
  "type": "Feature",
  "properties": {
    "iso:country":"US",
    "sg:address":"2050 Yoakim Bridge Rd",
    "sg:city":"Healdsburg",
    "sg:classifiers":[
        {
            "category":"Retail",
            "subcategory":"Repair Shop",
            "type":"Services"
        }
    ],
    "sg:phone":"+1 707 433 1081",
    "sg:postcode":"95448",
    "sg:province":"CA",
    "sg:tags":[
        "welding"
    ],
    "wof:name":"Guadagni Brothers Welding",
    "wof:placetype":"venue"
},
  "geometry": {"coordinates":[-122.95707,38.70123],"type":"Point"}
}