{
  "type": "Feature",
  "properties": {
    "addr:full":"1001 W Carson St Torrance CA 90502",
    "addr:housenumber":"1001",
    "addr:postcode":"90502",
    "addr:street":"W Carson St",
    "iso:country":"US",
    "sg:address":"1001 W Carson St",
    "sg:city":"Torrance",
    "sg:classifiers":[
        {
            "category":"Shopping",
            "type":"Retail Goods"
        }
    ],
    "sg:phone":"+1 310 320 2104",
    "sg:postcode":"90502",
    "sg:province":"CA",
    "sg:tags":[
        "telephone",
        "cellular"
    ],
    "wof:name":"Radio Shack",
    "wof:placetype":"venue"
},
  "geometry": {"coordinates":[-118.29292,33.831649],"type":"Point"}
}