{
  "type": "Feature",
  "properties": {
    "addr:full":"535 Octavia Blvd San Francisco CA 94102",
    "addr:housenumber":"535",
    "addr:postcode":"94102",
    "addr:street":"Octavia Blvd",
    "iso:country":"US",
    "sg:address":"535 Octavia Blvd",
    "sg:city":"San Francisco",
    "sg:classifiers":[
        {
            "category":"Home & Garden",
            "subcategory":"Carpets & Floor Coverings",
            "type":"Retail Goods"
        }
    ],
    "sg:phone":"+1 415 255 9940",
    "sg:postcode":"94102",
    "sg:province":"CA",
    "sg:tags":[
        "carpeting"
    ],
    "sg:website":"www.peaceindustry.com",
    "wof:name":"Peace Industry",
    "wof:placetype":"venue"
},
  "geometry": {"coordinates":[-122.424795,37.777291],"type":"Point"}
}