{
  "type": "Feature",
  "properties": {
    "iso:country":"US",
    "sg:address":"660 Eugene St",
    "sg:city":"Ferndale",
    "sg:classifiers":[
        {
            "category":"Freight",
            "type":"Transportation"
        }
    ],
    "sg:phone":"+1 707 786 9344",
    "sg:postcode":"95536",
    "sg:province":"CA",
    "sg:tags":[
        "operator",
        "local",
        "trucking"
    ],
    "wof:name":"Tim Cooney Trucking",
    "wof:placetype":"venue"
},
  "geometry": {"coordinates":[-124.263225,40.573276],"type":"Point"}
}