{
  "type": "Feature",
  "properties": {
    "addr:full":"324 E Santa Anita Ave Burbank CA 91502",
    "addr:housenumber":"324",
    "addr:postcode":"91502",
    "addr:street":"E Santa Anita Ave",
    "iso:country":"US",
    "sg:address":"324 E Santa Anita Ave",
    "sg:city":"Burbank",
    "sg:classifiers":[
        {
            "category":"Building & Trades",
            "subcategory":"Electrical",
            "type":"Services"
        }
    ],
    "sg:phone":"+1 818 848 8045",
    "sg:postcode":"91502",
    "sg:province":"CA",
    "sg:tags":[
        "electrical",
        "contractor"
    ],
    "wof:name":"All City Electric",
    "wof:placetype":"venue"
},
  "geometry": {"coordinates":[-118.302496,34.179993],"type":"Point"}
}