{
  "type": "Feature",
  "properties": {
    "addr:full":"3980 Fabian Way Palo Alto CA 94303",
    "addr:housenumber":"3980",
    "addr:postcode":"94303",
    "addr:street":"Fabian Way",
    "iso:country":"US",
    "sg:address":"3980 Fabian Way",
    "sg:city":"Palo Alto",
    "sg:classifiers":[
        {
            "category":"Shopping",
            "subcategory":"Computers & Home Electronics",
            "type":"Retail Goods"
        }
    ],
    "sg:phone":"+1 650 812 0565",
    "sg:postcode":"94303",
    "sg:province":"CA",
    "sg:tags":[
        "software"
    ],
    "wof:name":"Netli",
    "wof:placetype":"venue"
},
  "geometry": {"coordinates":[-122.10429499999999,37.428699],"type":"Point"}
}