{
  "type": "Feature",
  "properties": {
    "iso:country":"US",
    "sg:address":"5036 W Pico Blvd",
    "sg:city":"Los Angeles",
    "sg:classifiers":[
        {
            "category":"Cinema",
            "subcategory":"Movie Theater",
            "type":"Entertainment"
        }
    ],
    "sg:phone":"+1 323 938 4971",
    "sg:postcode":"90019",
    "sg:province":"CA",
    "wof:name":"Puget Sound",
    "wof:placetype":"venue"
},
  "geometry": {"coordinates":[-118.34699999999999,34.048],"type":"Point"}
}