{
  "type": "Feature",
  "properties": {
    "iso:country":"US",
    "sg:address":"1572 Taraval St",
    "sg:city":"San Francisco",
    "sg:classifiers":[
        {
            "category":"Personal",
            "subcategory":"Skin Care",
            "type":"Services"
        }
    ],
    "sg:phone":"+1 415 242 9688",
    "sg:postcode":"94116",
    "sg:province":"CA",
    "wof:name":"Flora Permanent Beauty Center",
    "wof:placetype":"venue"
},
  "geometry": {"coordinates":[-122.482923,37.74275],"type":"Point"}
}