{
  "type": "Feature",
  "properties": {
    "addr:full":"8184 Gravenstein Hwy Cotati CA 94931",
    "addr:postcode":"8184;94931",
    "addr:street":"Gravenstein Hwy",
    "iso:country":"US",
    "sg:address":"8184 Gravenstein Hwy",
    "sg:city":"Cotati",
    "sg:classifiers":[
        {
            "category":"Freight",
            "type":"Transportation"
        }
    ],
    "sg:phone":"+1 707 795 4564",
    "sg:postcode":"94931",
    "sg:province":"CA",
    "sg:tags":[
        "trucking"
    ],
    "wof:name":"Minatta Transportation Co",
    "wof:placetype":"venue"
},
  "geometry": {"coordinates":[-122.719274,38.33202],"type":"Point"}
}