{
  "type": "Feature",
  "properties": {
    "addr:full":"1235 Karen Ave Clovis CA 93612",
    "addr:housenumber":"1235",
    "addr:postcode":"93612",
    "addr:street":"Karen Ave",
    "iso:country":"US",
    "sg:address":"1235 Karen Ave",
    "sg:city":"Clovis",
    "sg:classifiers":[
        {
            "category":"Professional",
            "type":"Services"
        }
    ],
    "sg:phone":"+1 559 299 2253",
    "sg:postcode":"93612",
    "sg:province":"CA",
    "wof:name":"Medvert Inc",
    "wof:placetype":"venue"
},
  "geometry": {"coordinates":[-119.719672,36.814232],"type":"Point"}
}