{
  "type": "Feature",
  "properties": {
    "addr:full":"2739 Lancha St San Diego CA 92111",
    "addr:housenumber":"2739",
    "addr:postcode":"92111",
    "addr:street":"Lancha St",
    "iso:country":"US",
    "sg:address":"2739 Lancha St",
    "sg:city":"San Diego",
    "sg:classifiers":[
        {
            "category":"Wholesale",
            "subcategory":"Vending Machines",
            "type":"Manufacturing & Wholesale Goods"
        }
    ],
    "sg:phone":"+1 858 492 9846",
    "sg:postcode":"92111",
    "sg:province":"CA",
    "wof:name":"Cool Snacks",
    "wof:placetype":"venue"
},
  "geometry": {"coordinates":[-117.16775800000001,32.793551],"type":"Point"}
}