{
  "type": "Feature",
  "properties": {
    "addr:full":"301 Sycamore Valley Rd W Danville CA 94526",
    "addr:housenumber":"301",
    "addr:postcode":"94526",
    "addr:street":"Sycamore Valley Rd W",
    "iso:country":"US",
    "sg:address":"301 Sycamore Valley Rd W",
    "sg:city":"Danville",
    "sg:classifiers":[
        {
            "category":"Health Services",
            "subcategory":"Doctor",
            "type":"Services"
        }
    ],
    "sg:phone":"+1 925 820 6466",
    "sg:postcode":"94526",
    "sg:province":"CA",
    "sg:tags":[
        "dentist"
    ],
    "wof:name":"Livery Dental Ctr",
    "wof:placetype":"venue"
},
  "geometry": {"coordinates":[-121.997229,37.811804],"type":"Point"}
}