{
  "type": "Feature",
  "properties": {
    "iso:country":"US",
    "sg:address":"41333 Salt River Ct",
    "sg:city":"Temecula",
    "sg:classifiers":[
        {
            "category":"Professional",
            "subcategory":"Business Services",
            "type":"Services"
        }
    ],
    "sg:phone":"+1 951 699 8869",
    "sg:postcode":"92591",
    "sg:province":"CA",
    "sg:tags":[
        "plant",
        "design",
        "maintenance"
    ],
    "wof:name":"Temecula Plant Scape",
    "wof:placetype":"venue"
},
  "geometry": {"coordinates":[-117.123897,33.521636],"type":"Point"}
}