{
  "type": "Feature",
  "properties": {
    "addr:full":"14102 Willow Ln Westminster CA 92683",
    "addr:housenumber":"14102",
    "addr:postcode":"92683",
    "addr:street":"Willow Ln",
    "iso:country":"US",
    "sg:address":"14102 Willow Ln",
    "sg:city":"Westminster",
    "sg:classifiers":[
        {
            "category":"Retail",
            "subcategory":"Auto Repair",
            "type":"Services"
        }
    ],
    "sg:phone":"+1 714 890 5153",
    "sg:postcode":"92683",
    "sg:province":"CA",
    "sg:website":"www.upfd.com",
    "wof:name":"UPFD",
    "wof:placetype":"venue"
},
  "geometry": {"coordinates":[-118.01930299999999,33.756216],"type":"Point"}
}