{
  "type": "Feature",
  "properties": {
    "iso:country":"US",
    "sg:address":"121 Lenore Way",
    "sg:city":"Crescent City",
    "sg:classifiers":[
        {
            "category":"Manufacturing",
            "subcategory":"Glass & Minerals",
            "type":"Manufacturing & Wholesale Goods"
        }
    ],
    "sg:phone":"+1 707 464 4700",
    "sg:postcode":"95531",
    "sg:province":"CA",
    "sg:tags":[
        "product",
        "ceramic"
    ],
    "wof:name":"Intermat",
    "wof:placetype":"venue"
},
  "geometry": {"coordinates":[-124.144052,41.798104],"type":"Point"}
}