{
  "type": "Feature",
  "properties": {
    "addr:full":"201 Centre Plaza Dr Monterey Park CA 91754",
    "addr:housenumber":"201",
    "addr:postcode":"91754",
    "addr:street":"Centre Plaza Dr",
    "iso:country":"US",
    "sg:address":"201 Centre Plaza Dr",
    "sg:city":"Monterey Park",
    "sg:classifiers":[
        {
            "category":"Government",
            "subcategory":"Office",
            "type":"Public Place"
        }
    ],
    "sg:phone":"+1 323 526 6757",
    "sg:postcode":"91754",
    "sg:province":"CA",
    "wof:name":"Los Angeles Cnty IDC",
    "wof:placetype":"venue"
},
  "geometry": {"coordinates":[-118.166281,34.059392],"type":"Point"}
}