{
  "type": "Feature",
  "properties": {
    "iso:country":"US",
    "sg:address":"497 Reservation Rd",
    "sg:city":"Marina",
    "sg:classifiers":[
        {
            "category":"Freight",
            "type":"Transportation"
        }
    ],
    "sg:phone":"+1 831 384 1111",
    "sg:postcode":"93933",
    "sg:province":"CA",
    "sg:tags":[
        "commercial",
        "storage",
        "general"
    ],
    "wof:name":"Marina Mini Storage",
    "wof:placetype":"venue"
},
  "geometry": {"coordinates":[-121.78089,36.678824],"type":"Point"}
}