{
  "type": "Feature",
  "properties": {
    "addr:full":"541 Chetwood Street Oakland CA 94610",
    "addr:housenumber":"541",
    "addr:postcode":"94610",
    "addr:street":"Chetwood Street",
    "iso:country":"US",
    "sg:address":"541 Chetwood Street",
    "sg:city":"Oakland",
    "sg:classifiers":[
        {
            "category":"Professional",
            "subcategory":"Art Services",
            "type":"Services"
        }
    ],
    "sg:phone":"+1 415 350 7218",
    "sg:postcode":"94610",
    "sg:province":"CA",
    "sg:tags":[
        "photographer"
    ],
    "wof:name":"Ann Marie Donahue Photography",
    "wof:placetype":"venue"
},
  "geometry": {"coordinates":[-122.24959699999999,37.818544],"type":"Point"}
}