{
  "type": "Feature",
  "properties": {
    "iso:country":"US",
    "sg:address":"251 E Market St",
    "sg:city":"Salinas",
    "sg:classifiers":[
        {
            "category":"Building & Trades",
            "subcategory":"Plumbing",
            "type":"Services"
        }
    ],
    "sg:phone":"+1 831 757 5465",
    "sg:postcode":"93901",
    "sg:province":"CA",
    "sg:tags":[
        "plumbing",
        "contractor"
    ],
    "wof:name":"Alvarez Plumbing Inc",
    "wof:placetype":"venue"
},
  "geometry": {"coordinates":[-121.64827200000001,36.678658],"type":"Point"}
}