{
  "type": "Feature",
  "properties": {
    "iso:country":"US",
    "sg:address":"2980 Corvin Dr",
    "sg:city":"Santa Clara",
    "sg:classifiers":[
        {
            "category":"Wholesale",
            "subcategory":"Computers",
            "type":"Manufacturing & Wholesale Goods"
        }
    ],
    "sg:phone":"+1 408 738 1751",
    "sg:postcode":"95051",
    "sg:province":"CA",
    "sg:website":"www.mobileracks.com",
    "wof:name":"Leadman Electronics",
    "wof:placetype":"venue"
},
  "geometry": {"coordinates":[-121.987939,37.376154],"type":"Point"}
}