{
  "type": "Feature",
  "properties": {
    "addr:full":"3641 E 8th St Los Angeles CA 90023",
    "addr:housenumber":"3641",
    "addr:postcode":"90023",
    "addr:street":"E 8Th St",
    "iso:country":"US",
    "sg:address":"3641 E 8th St",
    "sg:city":"Los Angeles",
    "sg:classifiers":[
        {
            "category":"Government",
            "subcategory":"Post Office",
            "type":"Public Place"
        }
    ],
    "sg:phone":"+1 323 268 0102",
    "sg:postcode":"90023",
    "sg:province":"CA",
    "sg:tags":[
        "postal",
        "us"
    ],
    "wof:name":"Lugo Station",
    "wof:placetype":"venue"
},
  "geometry": {"coordinates":[-118.198554,34.01892],"type":"Point"}
}