{
  "type": "Feature",
  "properties": {
    "iso:country":"US",
    "sg:address":"4230 E Airport Dr",
    "sg:city":"Ontario",
    "sg:classifiers":[
        {
            "category":"Wholesale",
            "subcategory":"Construction Materials",
            "type":"Manufacturing & Wholesale Goods"
        }
    ],
    "sg:phone":"+1 909 390 7790",
    "sg:postcode":"91761",
    "sg:province":"CA",
    "sg:tags":[
        "building"
    ],
    "wof:name":"Paradise Bldg Specialties Inc",
    "wof:placetype":"venue"
},
  "geometry": {"coordinates":[-117.560554,34.062688],"type":"Point"}
}