{
  "type": "Feature",
  "properties": {
    "iso:country":"US",
    "sg:address":"10795 Wilshire Blvd",
    "sg:city":"Los Angeles",
    "sg:classifiers":[
        {
            "category":"Real Estate",
            "subcategory":"Real Estate Operator",
            "type":"Services"
        }
    ],
    "sg:phone":"+1 310 234 0233",
    "sg:postcode":"90024",
    "sg:province":"CA",
    "sg:tags":[
        "condominium"
    ],
    "wof:name":"Venezia",
    "wof:placetype":"venue"
},
  "geometry": {"coordinates":[-118.438411,34.06038],"type":"Point"}
}