{
  "type": "Feature",
  "properties": {
    "iso:country":"US",
    "sg:address":"901 Ocean Blvd",
    "sg:city":"Moss Beach",
    "sg:classifiers":[
        {
            "category":"Banks & Credit Unions",
            "subcategory":"Investment Brokerage",
            "type":"Services"
        }
    ],
    "sg:phone":"+1 650 728 0172",
    "sg:postcode":"94038",
    "sg:province":"CA",
    "sg:tags":[
        "advisory",
        "financial"
    ],
    "wof:name":"Seal Cove Financial",
    "wof:placetype":"venue"
},
  "geometry": {"coordinates":[-122.510801,37.513612],"type":"Point"}
}