{
  "type": "Feature",
  "properties": {
    "iso:country":"US",
    "sg:address":"660 Auburn Folsom Rd",
    "sg:city":"Auburn",
    "sg:classifiers":[
        {
            "category":"Real Estate",
            "subcategory":"Real Estate Services",
            "type":"Services"
        },
        {
            "category":"Banks & Credit Unions",
            "subcategory":"Financial Services",
            "type":"Services"
        }
    ],
    "sg:phone":"+1 530 823 9100",
    "sg:postcode":"95603",
    "sg:province":"CA",
    "sg:tags":[
        "loan",
        "mortgage"
    ],
    "wof:name":"Goldmine Financial Group",
    "wof:placetype":"venue"
},
  "geometry": {"coordinates":[-121.08068,38.876978],"type":"Point"}
}