{
  "type": "Feature",
  "properties": {
    "iso:country":"US",
    "sg:address":"420 Main St",
    "sg:city":"Placerville",
    "sg:classifiers":[
        {
            "category":"Shopping",
            "type":"Retail Goods"
        }
    ],
    "sg:phone":"+1 530 642 0177",
    "sg:postcode":"95667",
    "sg:province":"CA",
    "sg:tags":[
        "art",
        "gallery",
        "dealer"
    ],
    "wof:name":"Trilogy Gallery",
    "wof:placetype":"venue"
},
  "geometry": {"coordinates":[-120.800144,38.729364],"type":"Point"}
}