{
  "type": "Feature",
  "properties": {
    "addr:full":"2216 El Camino Real Ste 206 Oceanside CA 92054",
    "addr:housenumber":"2216",
    "addr:postcode":"92054",
    "addr:street":"El Camino Real Ste 206",
    "iso:country":"US",
    "sg:address":"2216 El Camino Real Ste 206",
    "sg:city":"Oceanside",
    "sg:classifiers":[
        {
            "category":"Personal",
            "subcategory":"Tanning Parlor",
            "type":"Services"
        }
    ],
    "sg:phone":"+1 760 730 5590",
    "sg:postcode":"92054",
    "sg:province":"CA",
    "sg:website":"www.titantan.com",
    "wof:name":"Titan Tan",
    "wof:placetype":"venue"
},
  "geometry": {"coordinates":[-117.32732799999999,33.185478],"type":"Point"}
}