{
  "type": "Feature",
  "properties": {
    "addr:full":"925 N Dudley St Pomona CA 91768",
    "addr:housenumber":"925",
    "addr:postcode":"91768",
    "addr:street":"N Dudley St",
    "iso:country":"US",
    "sg:address":"925 N Dudley St",
    "sg:city":"Pomona",
    "sg:classifiers":[
        {
            "category":"Health Services",
            "subcategory":"Nursing And Care Facility",
            "type":"Services"
        }
    ],
    "sg:phone":"+1 909 622 9924",
    "sg:postcode":"91768",
    "sg:province":"CA",
    "sg:tags":[
        "home",
        "convalescent"
    ],
    "wof:name":"Dudley's Guest Home",
    "wof:placetype":"venue"
},
  "geometry": {"coordinates":[-117.77749799999999,34.066211],"type":"Point"}
}