{
  "type": "Feature",
  "properties": {
    "iso:country":"US",
    "sg:address":"777 S Amber St",
    "sg:city":"Tulare",
    "sg:classifiers":[
        {
            "category":"Retail",
            "subcategory":"Auto Repair",
            "type":"Services"
        }
    ],
    "sg:phone":"+1 559 686 8009",
    "sg:postcode":"93274",
    "sg:province":"CA",
    "sg:tags":[
        "truck"
    ],
    "wof:name":"Freitas Maintenance",
    "wof:placetype":"venue"
},
  "geometry": {"coordinates":[-119.31719699999999,36.201383],"type":"Point"}
}