{
  "type": "Feature",
  "properties": {
    "iso:country":"US",
    "sg:address":"3234 Monier Cir",
    "sg:city":"Rancho Cordova",
    "sg:classifiers":[
        {
            "category":"Manufacturing",
            "subcategory":"Metals",
            "type":"Manufacturing & Wholesale Goods"
        }
    ],
    "sg:phone":"+1 916 638 9902",
    "sg:postcode":"95742",
    "sg:province":"CA",
    "sg:tags":[
        "brass",
        "product"
    ],
    "wof:name":"English Brass Mfg",
    "wof:placetype":"venue"
},
  "geometry": {"coordinates":[-121.261358,38.581711],"type":"Point"}
}