{
  "type": "Feature",
  "properties": {
    "addr:full":"226 Mill St Grass Valley CA 95945",
    "addr:housenumber":"226",
    "addr:postcode":"95945",
    "addr:street":"Mill St",
    "iso:country":"US",
    "sg:address":"226 Mill St",
    "sg:city":"Grass Valley",
    "sg:classifiers":[
        {
            "category":"Professional",
            "subcategory":"Computer Services",
            "type":"Services"
        }
    ],
    "sg:phone":"+1 530 273 8914",
    "sg:postcode":"95945",
    "sg:province":"CA",
    "sg:tags":[
        "website",
        "design"
    ],
    "wof:name":"Haden Designs For The Web",
    "wof:placetype":"venue"
},
  "geometry": {"coordinates":[-121.06363899999999,39.216919],"type":"Point"}
}