{
  "type": "Feature",
  "properties": {
    "addr:full":"14261 Ventura Blvd at Nadia's Rhythm Room Sherman Oaks CA 91423",
    "addr:housenumber":"14261",
    "addr:postcode":"91423",
    "addr:street":"Ventura Blvd At",
    "iso:country":"US",
    "sg:address":"14261 Ventura Blvd at Nadia's Rhythm Room",
    "sg:city":"Sherman Oaks",
    "sg:classifiers":[
        {
            "category":"Arts & Performance",
            "subcategory":"Arts Center",
            "type":"Entertainment"
        },
        {
            "category":"Arts & Performance",
            "subcategory":"Dance",
            "type":"Entertainment"
        }
    ],
    "sg:postcode":"91423",
    "sg:province":"CA",
    "sg:tags":[
        "school"
    ],
    "sg:website":"www.lablueskitchen.com",
    "wof:name":"LA Blues Kitchen",
    "wof:placetype":"venue"
},
  "geometry": {"coordinates":[-118.444271,34.150202],"type":"Point"}
}