{
  "type": "Feature",
  "properties": {
    "iso:country":"US",
    "sg:address":"112 S Brand Blvd",
    "sg:city":"Glendale",
    "sg:classifiers":[
        {
            "category":"Restaurant",
            "type":"Food & Drink"
        }
    ],
    "sg:phone":"+1 818 243 9455",
    "sg:postcode":"91204",
    "sg:province":"CA",
    "wof:name":"Sbarro",
    "wof:placetype":"venue"
},
  "geometry": {"coordinates":[-118.254972,34.145178],"type":"Point"}
}