{
  "type": "Feature",
  "properties": {
    "addr:full":"543 N Cloverdale Blvd Cloverdale CA 95425",
    "addr:housenumber":"543",
    "addr:postcode":"95425",
    "addr:street":"N Cloverdale Blvd",
    "iso:country":"US",
    "sg:address":"543 N Cloverdale Blvd",
    "sg:city":"Cloverdale",
    "sg:classifiers":[
        {
            "category":"Food & Beverages",
            "subcategory":"Bakery",
            "type":"Retail Goods"
        }
    ],
    "sg:phone":"+1 707 894 0211",
    "sg:postcode":"95425",
    "sg:province":"CA",
    "sg:tags":[
        "baker"
    ],
    "wof:name":"Schat's Bakery",
    "wof:placetype":"venue"
},
  "geometry": {"coordinates":[-123.021946,38.811782],"type":"Point"}
}