{
  "type": "Feature",
  "properties": {
    "iso:country":"US",
    "sg:address":"2466 Bay Rd",
    "sg:city":"Redwood City",
    "sg:classifiers":[
        {
            "category":"Building & Trades",
            "subcategory":"Plumbing",
            "type":"Services"
        }
    ],
    "sg:phone":"+1 650 326 0534",
    "sg:postcode":"94063",
    "sg:province":"CA",
    "sg:tags":[
        "plumbing",
        "contractor"
    ],
    "wof:name":"Frank Denny Plumbing Inc",
    "wof:placetype":"venue"
},
  "geometry": {"coordinates":[-122.21042199999999,37.484685],"type":"Point"}
}