{
  "type": "Feature",
  "properties": {
    "addr:full":"2301 Glendale Galleria Glendale CA 91210",
    "addr:housenumber":"2301",
    "addr:postcode":"91210",
    "addr:street":"Glendale Galleria",
    "iso:country":"US",
    "sg:address":"2301 Glendale Galleria",
    "sg:city":"Glendale",
    "sg:classifiers":[
        {
            "category":"Shopping",
            "subcategory":"Department Store",
            "type":"Retail Goods"
        }
    ],
    "sg:phone":"+1 818 240 7273",
    "sg:postcode":"91210",
    "sg:province":"CA",
    "sg:website":"www.eddiebauer.com",
    "wof:name":"Eddie Bauer Inc",
    "wof:placetype":"venue"
},
  "geometry": {"coordinates":[-118.257373,34.146402],"type":"Point"}
}