{
  "type": "Feature",
  "properties": {
    "addr:full":"108 N Ynez Ave Monterey Park CA 91754",
    "addr:housenumber":"108",
    "addr:postcode":"91754",
    "addr:street":"N Ynez Ave",
    "iso:country":"US",
    "sg:address":"108 N Ynez Ave",
    "sg:city":"Monterey Park",
    "sg:classifiers":[
        {
            "category":"Travel",
            "subcategory":"Travel Agent",
            "type":"Entertainment"
        }
    ],
    "sg:phone":"+1 626 571 6727",
    "sg:postcode":"91754",
    "sg:province":"CA",
    "sg:tags":[
        "agency"
    ],
    "wof:name":"Cathay Tour",
    "wof:placetype":"venue"
},
  "geometry": {"coordinates":[-118.129053,34.063614],"type":"Point"}
}