{
  "type": "Feature",
  "properties": {
    "addr:full":"7824 Florence Avenue Downey CA 90240",
    "addr:housenumber":"7824",
    "addr:postcode":"90240",
    "addr:street":"Florence Avenue",
    "iso:country":"US",
    "sg:address":"7824 Florence Avenue",
    "sg:city":"Downey",
    "sg:classifiers":[
        {
            "category":"Shopping",
            "subcategory":"Florist",
            "type":"Retail Goods"
        }
    ],
    "sg:phone":"+1 562 928 4147",
    "sg:postcode":"90240",
    "sg:province":"CA",
    "wof:name":"Downey Florist",
    "wof:placetype":"venue"
},
  "geometry": {"coordinates":[-118.135183,33.957238],"type":"Point"}
}