{
  "type": "Feature",
  "properties": {
    "addr:full":"17123 Lanark St Van Nuys CA 91406",
    "addr:housenumber":"17123",
    "addr:postcode":"91406",
    "addr:street":"Lanark St",
    "iso:country":"US",
    "sg:address":"17123 Lanark St",
    "sg:city":"Van Nuys",
    "sg:classifiers":[
        {
            "category":"Food & Beverages",
            "subcategory":"Bakery",
            "type":"Retail Goods"
        }
    ],
    "sg:phone":"+1 818 342 7953",
    "sg:postcode":"91406",
    "sg:province":"CA",
    "sg:tags":[
        "cookie",
        "cracker"
    ],
    "wof:name":"Cookie Fresh",
    "wof:placetype":"venue"
},
  "geometry": {"coordinates":[-118.508363,34.218139],"type":"Point"}
}