{
  "type": "Feature",
  "properties": {
    "addr:full":"5447 E American Ave Fresno CA 93725",
    "addr:housenumber":"5447",
    "addr:postcode":"93725",
    "addr:street":"E American Ave",
    "iso:country":"US",
    "sg:address":"5447 E American Ave",
    "sg:city":"Fresno",
    "sg:classifiers":[
        {
            "category":"Farming",
            "subcategory":"Vineyard",
            "type":"Manufacturing & Wholesale Goods"
        }
    ],
    "sg:phone":"+1 559 485 7678",
    "sg:postcode":"93725",
    "sg:province":"CA",
    "sg:tags":[
        "grape"
    ],
    "wof:name":"Gonzales Farms",
    "wof:placetype":"venue"
},
  "geometry": {"coordinates":[-119.69865,36.663488],"type":"Point"}
}