{
  "type": "Feature",
  "properties": {
    "iso:country":"US",
    "sg:address":"1030 W 45th St",
    "sg:city":"Los Angeles",
    "sg:classifiers":[
        {
            "category":"Manufacturing",
            "subcategory":"Tools & Machinery",
            "type":"Manufacturing & Wholesale Goods"
        }
    ],
    "sg:phone":"+1 323 234 2566",
    "sg:postcode":"90037",
    "sg:province":"CA",
    "sg:tags":[
        "machine",
        "vending"
    ],
    "wof:name":"Kareem Manufacturing Co",
    "wof:placetype":"venue"
},
  "geometry": {"coordinates":[-118.29316900000001,34.002583],"type":"Point"}
}