{
  "type": "Feature",
  "properties": {
    "iso:country":"US",
    "sg:address":"879 S McGlincey Ln",
    "sg:city":"Campbell",
    "sg:classifiers":[
        {
            "category":"Professional",
            "subcategory":"Testing Lab",
            "type":"Services"
        }
    ],
    "sg:phone":"+1 408 559 3097",
    "sg:postcode":"95008",
    "sg:province":"CA",
    "sg:tags":[
        "plate",
        "surface"
    ],
    "sg:website":"www.pit2go.com",
    "wof:name":"P W Calibrators Inc",
    "wof:placetype":"venue"
},
  "geometry": {"coordinates":[-121.945187,37.273109],"type":"Point"}
}