{
  "type": "Feature",
  "properties": {
    "iso:country":"US",
    "sg:address":"3493 Edison Way",
    "sg:city":"Menlo Park",
    "sg:classifiers":[
        {
            "category":"Professional",
            "subcategory":"Art Services",
            "type":"Services"
        }
    ],
    "sg:phone":"+1 650 968 0900",
    "sg:postcode":"94025",
    "sg:province":"CA",
    "sg:tags":[
        "photographer"
    ],
    "sg:website":"www.librapictures.com",
    "wof:name":"Joseph Quever Photographer",
    "wof:placetype":"venue"
},
  "geometry": {"coordinates":[-122.198199,37.476541],"type":"Point"}
}