{
  "type": "Feature",
  "properties": {
    "addr:full":"3608 N Ventura Ave Ventura CA 93001",
    "addr:housenumber":"3608",
    "addr:postcode":"93001",
    "addr:street":"N Ventura Ave",
    "iso:country":"US",
    "sg:address":"3608 N Ventura Ave",
    "sg:city":"Ventura",
    "sg:classifiers":[
        {
            "category":"Wholesale",
            "subcategory":"Machinery & Supplies",
            "type":"Manufacturing & Wholesale Goods"
        }
    ],
    "sg:phone":"+1 805 653 6666",
    "sg:postcode":"93001",
    "sg:province":"CA",
    "wof:name":"National Oilwell",
    "wof:placetype":"venue"
},
  "geometry": {"coordinates":[-119.290556,34.317139],"type":"Point"}
}