{
  "type": "Feature",
  "properties": {
    "addr:full":"3580 Redondo Beach Blvd Torrance CA 90504",
    "addr:housenumber":"3580",
    "addr:postcode":"90504",
    "addr:street":"Redondo Beach Blvd",
    "iso:country":"US",
    "sg:address":"3580 Redondo Beach Blvd",
    "sg:city":"Torrance",
    "sg:classifiers":[
        {
            "category":"Shopping",
            "subcategory":"Books",
            "type":"Retail Goods"
        }
    ],
    "sg:phone":"+1 310 527 2010",
    "sg:postcode":"90504",
    "sg:province":"CA",
    "sg:tags":[
        "dealer"
    ],
    "wof:name":"Native Hawaiian Books & Gllry",
    "wof:placetype":"venue"
},
  "geometry": {"coordinates":[-118.33323300000001,33.880734],"type":"Point"}
}