{
  "type": "Feature",
  "properties": {
    "addr:full":"8135 Langdon Ave Van Nuys CA 91406",
    "addr:housenumber":"8135",
    "addr:postcode":"91406",
    "addr:street":"Langdon Ave",
    "iso:country":"US",
    "sg:address":"8135 Langdon Ave",
    "sg:city":"Van Nuys",
    "sg:classifiers":[
        {
            "category":"Professional",
            "subcategory":"Management & Consulting",
            "type":"Services"
        }
    ],
    "sg:phone":"+1 818 787 0837",
    "sg:postcode":"91406",
    "sg:province":"CA",
    "sg:tags":[
        "consultant",
        "construction"
    ],
    "wof:name":"Almaraz Construction",
    "wof:placetype":"venue"
},
  "geometry": {"coordinates":[-118.46992400000001,34.219874],"type":"Point"}
}