{
  "type": "Feature",
  "properties": {
    "iso:country":"US",
    "sg:address":"4659 Las Positas Road Suite C",
    "sg:city":"Livermore",
    "sg:classifiers":[
        {
            "category":"Professional",
            "subcategory":"Research",
            "type":"Services"
        }
    ],
    "sg:phone":"+1 925 454 8506",
    "sg:postcode":"94551",
    "sg:province":"CA",
    "sg:tags":[
        "solar-power",
        "solar"
    ],
    "sg:website":"http://www.coolearthsolar.com/",
    "wof:name":"Cool Earth Solar",
    "wof:placetype":"venue"
},
  "geometry": {"coordinates":[-121.74190299999999,37.697175],"type":"Point"}
}