{
  "type": "Feature",
  "properties": {
    "iso:country":"US",
    "sg:address":"14043 Princeton Ct",
    "sg:city":"Fontana",
    "sg:classifiers":[
        {
            "category":"Real Estate",
            "subcategory":"Real Estate Agent",
            "type":"Services"
        }
    ],
    "sg:phone":"+1 909 835 5595",
    "sg:postcode":"92336",
    "sg:province":"CA",
    "wof:name":"Heart To Home Realty/Financial",
    "wof:placetype":"venue"
},
  "geometry": {"coordinates":[-117.49884,34.11649],"type":"Point"}
}