{
  "type": "Feature",
  "properties": {
    "iso:country":"US",
    "sg:address":"512 Moray Way",
    "sg:city":"Patterson",
    "sg:classifiers":[
        {
            "category":"Professional",
            "subcategory":"Business Services",
            "type":"Services"
        }
    ],
    "sg:phone":"+1 209 993 5671",
    "sg:postcode":"95363",
    "sg:province":"CA",
    "sg:tags":[
        "notary",
        "public"
    ],
    "wof:name":"Central Valley Notary Service",
    "wof:placetype":"venue"
},
  "geometry": {"coordinates":[-121.137196,37.463519],"type":"Point"}
}