{
  "type": "Feature",
  "properties": {
    "iso:country":"US",
    "sg:address":"556 E Weddell Drive Suite 3",
    "sg:city":"Sunnyvale",
    "sg:classifiers":[
        {
            "category":"Professional",
            "subcategory":"Computer Services",
            "type":"Services"
        }
    ],
    "sg:phone":"+1 408 745 9800",
    "sg:postcode":"94089",
    "sg:province":"CA",
    "sg:tags":[
        "repair"
    ],
    "wof:name":"All Laser Service",
    "wof:placetype":"venue"
},
  "geometry": {"coordinates":[-122.013879,37.398976],"type":"Point"}
}