{
  "type": "Feature",
  "properties": {
    "addr:full":"8026 Patton Ave Citrus Heights CA 95610",
    "addr:housenumber":"8026",
    "addr:postcode":"95610",
    "addr:street":"Patton Ave",
    "iso:country":"US",
    "sg:address":"8026 Patton Ave",
    "sg:city":"Citrus Heights",
    "sg:classifiers":[
        {
            "category":"Professional",
            "subcategory":"Management & Consulting",
            "type":"Services"
        }
    ],
    "sg:phone":"+1 916 723 3512",
    "sg:postcode":"95610",
    "sg:province":"CA",
    "sg:tags":[
        "consultant",
        "telecommunication"
    ],
    "wof:name":"Tingler Telecommunications",
    "wof:placetype":"venue"
},
  "geometry": {"coordinates":[-121.276449,38.709739],"type":"Point"}
}