{
  "type": "Feature",
  "properties": {
    "iso:country":"US",
    "sg:address":"3009 W Artesia Blvd",
    "sg:city":"Torrance",
    "sg:classifiers":[
        {
            "category":"Home & Garden",
            "subcategory":"Garden Supply",
            "type":"Retail Goods"
        }
    ],
    "sg:phone":"+1 310 323 4937",
    "sg:postcode":"90504",
    "sg:province":"CA",
    "sg:tags":[
        "nursery",
        "gardening"
    ],
    "sg:website":"losangeleshydro.com",
    "wof:name":"Los Angeles Hydroponics",
    "wof:placetype":"venue"
},
  "geometry": {"coordinates":[-118.325467,33.872936],"type":"Point"}
}