{
  "type": "Feature",
  "properties": {
    "addr:full":"372 Bel Marin Keys Blvd Novato CA 94949",
    "addr:housenumber":"372",
    "addr:postcode":"94949",
    "addr:street":"Bel Marin Keys Blvd",
    "iso:country":"US",
    "sg:address":"372 Bel Marin Keys Blvd",
    "sg:city":"Novato",
    "sg:classifiers":[
        {
            "category":"Professional",
            "type":"Services"
        }
    ],
    "sg:phone":"+1 415 884 2950",
    "sg:postcode":"94949",
    "sg:province":"CA",
    "sg:tags":[
        "sculptor"
    ],
    "wof:name":"Sculpture 3-Clasen Goodheart",
    "wof:placetype":"venue"
},
  "geometry": {"coordinates":[-122.537763,38.074514],"type":"Point"}
}