{
  "type": "Feature",
  "properties": {
    "iso:country":"US",
    "sg:address":"824 Duffin Dr",
    "sg:city":"Hollister",
    "sg:classifiers":[
        {
            "category":"Building & Trades",
            "subcategory":"Construction",
            "type":"Services"
        }
    ],
    "sg:phone":"+1 408 438 1329",
    "sg:postcode":"95023",
    "sg:province":"CA",
    "sg:tags":[
        "floor",
        "laying",
        "contractor"
    ],
    "wof:name":"Pinnacle Hardwood Floors",
    "wof:placetype":"venue"
},
  "geometry": {"coordinates":[-121.359634,36.807108],"type":"Point"}
}