{
  "type": "Feature",
  "properties": {
    "addr:full":"9205 Folsom Blvd Sacramento CA 95826",
    "addr:housenumber":"9205",
    "addr:postcode":"95826",
    "addr:street":"Folsom Blvd",
    "iso:country":"US",
    "sg:address":"9205 Folsom Blvd",
    "sg:city":"Sacramento",
    "sg:classifiers":[
        {
            "category":"Professional",
            "type":"Services"
        }
    ],
    "sg:phone":"+1 916 857 1280",
    "sg:postcode":"95826",
    "sg:province":"CA",
    "wof:name":"Alternative Specialties",
    "wof:placetype":"venue"
},
  "geometry": {"coordinates":[-121.354342,38.563531],"type":"Point"}
}