{
  "type": "Feature",
  "properties": {
    "addr:full":"61-A Victory Ln Los Gatos CA 95030",
    "addr:housenumber":"61-a",
    "addr:postcode":"95030",
    "addr:street":"Victory Ln",
    "iso:country":"US",
    "sg:address":"61-A Victory Ln",
    "sg:city":"Los Gatos",
    "sg:classifiers":[
        {
            "category":"Home & Garden",
            "subcategory":"Home Furnishings",
            "type":"Retail Goods"
        }
    ],
    "sg:phone":"+1 408 399 4472",
    "sg:postcode":"95030",
    "sg:province":"CA",
    "sg:tags":[
        "decor"
    ],
    "sg:website":"www.post61.com",
    "wof:name":"Post 61",
    "wof:placetype":"venue"
},
  "geometry": {"coordinates":[-121.983816,37.224323],"type":"Point"}
}