{
  "type": "Feature",
  "properties": {
    "iso:country":"US",
    "sg:address":"1917 E Daily Dr",
    "sg:city":"Camarillo",
    "sg:classifiers":[
        {
            "category":"Banks & Credit Unions",
            "subcategory":"Bank",
            "type":"Services"
        }
    ],
    "sg:phone":"+1 805 389 4000",
    "sg:postcode":"93010",
    "sg:province":"CA",
    "wof:name":"Washington Mutual",
    "wof:placetype":"venue"
},
  "geometry": {"coordinates":[-119.043999,34.217899],"type":"Point"}
}