{
  "type": "Feature",
  "properties": {
    "addr:full":"13921 Oaks Ave Chino CA 91710",
    "addr:housenumber":"13921",
    "addr:postcode":"91710",
    "addr:street":"Oaks Ave",
    "iso:country":"US",
    "sg:address":"13921 Oaks Ave",
    "sg:city":"Chino",
    "sg:classifiers":[
        {
            "category":"Manufacturing",
            "subcategory":"Electronics",
            "type":"Manufacturing & Wholesale Goods"
        }
    ],
    "sg:phone":"+1 909 628 4241",
    "sg:postcode":"91710",
    "sg:province":"CA",
    "sg:tags":[
        "printed",
        "circuit",
        "etched"
    ],
    "wof:name":"State Circuit Boards",
    "wof:placetype":"venue"
},
  "geometry": {"coordinates":[-117.67600299999999,34.00292],"type":"Point"}
}