{
  "type": "Feature",
  "properties": {
    "addr:full":"1243 W El Camino Real Mountain View CA 94040",
    "addr:housenumber":"1243",
    "addr:postcode":"94040",
    "addr:street":"W El Camino Real",
    "iso:country":"US",
    "sg:address":"1243 W El Camino Real",
    "sg:city":"Mountain View",
    "sg:classifiers":[
        {
            "category":"Retail",
            "subcategory":"Repair Shop",
            "type":"Services"
        },
        {
            "category":"Home & Garden",
            "subcategory":"Furniture",
            "type":"Retail Goods"
        }
    ],
    "sg:phone":"+1 650 961 8700",
    "sg:postcode":"94040",
    "sg:province":"CA",
    "sg:tags":[
        "reupholstery",
        "store"
    ],
    "sg:website":"www.sterlingcustomupholstery.com",
    "wof:name":"Sterling Custom Upholstery Company",
    "wof:placetype":"venue"
},
  "geometry": {"coordinates":[-122.088945,37.388024],"type":"Point"}
}