{
  "type": "Feature",
  "properties": {
    "iso:country":"US",
    "sg:address":"1061 N Davis Rd",
    "sg:city":"Salinas",
    "sg:classifiers":[
        {
            "category":"Restaurant",
            "type":"Food & Drink"
        }
    ],
    "sg:menulink":"http://www.allmenus.com/ca/salinas/170871-carls-jr/menu/",
    "sg:phone":"+1 831 754 1419",
    "sg:postcode":"93907",
    "sg:province":"CA",
    "sg:tags":[
        "burger",
        "american"
    ],
    "wof:name":"Carl's Jr.",
    "wof:placetype":"venue"
},
  "geometry": {"coordinates":[-121.67220500000001,36.688057],"type":"Point"}
}