{
  "type": "Feature",
  "properties": {
    "iso:country":"US",
    "sg:address":"1145 N Azusa Canyon Rd",
    "sg:city":"West Covina",
    "sg:classifiers":[
        {
            "category":"Government",
            "subcategory":"Office",
            "type":"Public Place"
        }
    ],
    "sg:phone":"+1 626 814 9466",
    "sg:postcode":"91790",
    "sg:province":"CA",
    "sg:tags":[
        "s",
        "utility"
    ],
    "sg:website":"www.sgvmosquito.org",
    "wof:name":"San Gabriel Valley Mosquito",
    "wof:placetype":"venue"
},
  "geometry": {"coordinates":[-117.943075,34.091981],"type":"Point"}
}