{
  "type": "Feature",
  "properties": {
    "iso:country":"US",
    "sg:address":"9818 S Figueroa St",
    "sg:city":"Los Angeles",
    "sg:classifiers":[
        {
            "category":"Recreation",
            "type":"Entertainment"
        }
    ],
    "sg:phone":"+1 323 754 1900",
    "sg:postcode":"90003",
    "sg:province":"CA",
    "sg:tags":[
        "martial",
        "arts",
        "instruction"
    ],
    "wof:name":"Avilez Tang Soo Doo Karate Sch",
    "wof:placetype":"venue"
},
  "geometry": {"coordinates":[-118.282559,33.946584],"type":"Point"}
}