{
  "type": "Feature",
  "properties": {
    "addr:full":"551 Weedpatch Hwy Bakersfield CA 93307",
    "addr:housenumber":"551",
    "addr:postcode":"93307",
    "addr:street":"Weedpatch Hwy",
    "iso:country":"US",
    "sg:address":"551 Weedpatch Hwy",
    "sg:city":"Bakersfield",
    "sg:classifiers":[
        {
            "category":"Restaurant",
            "type":"Food & Drink"
        }
    ],
    "sg:menulink":"http://www.allmenus.com/ca/bakersfield/214147-taco-bell/menu/",
    "sg:phone":"+1 661 366 9455",
    "sg:postcode":"93307",
    "sg:province":"CA",
    "sg:tags":[
        "mexican"
    ],
    "wof:name":"Taco Bell",
    "wof:placetype":"venue"
},
  "geometry": {"coordinates":[-118.913663,35.35024],"type":"Point"}
}