{
  "type": "Feature",
  "properties": {
    "iso:country":"US",
    "sg:address":"1391 W Merrill Ave",
    "sg:city":"Rialto",
    "sg:classifiers":[
        {
            "category":"Organizations",
            "subcategory":"Religious Organization",
            "type":"Services"
        }
    ],
    "sg:phone":"+1 909 820 7300",
    "sg:postcode":"92376",
    "sg:province":"CA",
    "sg:tags":[
        "church"
    ],
    "sg:website":"www.calvarychapelrialto.com",
    "wof:name":"Calvary Chapel Rialto",
    "wof:placetype":"venue"
},
  "geometry": {"coordinates":[-117.398937,34.092186],"type":"Point"}
}