{
  "type": "Feature",
  "properties": {
    "iso:country":"US",
    "sg:address":"8763 Balsa St",
    "sg:city":"Rancho Cucamonga",
    "sg:classifiers":[
        {
            "category":"Professional",
            "subcategory":"Business Services",
            "type":"Services"
        }
    ],
    "sg:phone":"+1 310 617 5125",
    "sg:postcode":"91730",
    "sg:province":"CA",
    "sg:tags":[
        "interior",
        "design"
    ],
    "wof:name":"Miller Interior Designs",
    "wof:placetype":"venue"
},
  "geometry": {"coordinates":[-117.614845,34.117599],"type":"Point"}
}