{
  "type": "Feature",
  "properties": {
    "addr:full":"6562 Stanford Ave Garden Grove CA 92845",
    "addr:housenumber":"6562",
    "addr:postcode":"92845",
    "addr:street":"Stanford Ave",
    "iso:country":"US",
    "sg:address":"6562 Stanford Ave",
    "sg:city":"Garden Grove",
    "sg:classifiers":[
        {
            "category":"Communications",
            "subcategory":"Radio Station",
            "type":"Services"
        }
    ],
    "sg:phone":"+1 714 379 1851",
    "sg:postcode":"92845",
    "sg:province":"CA",
    "sg:tags":[
        "school"
    ],
    "wof:name":"Aspen Education Group Inc",
    "wof:placetype":"venue"
},
  "geometry": {"coordinates":[-118.01874100000001,33.777654],"type":"Point"}
}