{
  "type": "Feature",
  "properties": {
    "addr:full":"2017 W Bullard Ave Fresno CA 93711",
    "addr:housenumber":"2017",
    "addr:postcode":"93711",
    "addr:street":"W Bullard Ave",
    "iso:country":"US",
    "sg:address":"2017 W Bullard Ave",
    "sg:city":"Fresno",
    "sg:classifiers":[
        {
            "category":"Shopping",
            "subcategory":"Books",
            "type":"Retail Goods"
        }
    ],
    "sg:phone":"+1 559 438 1561",
    "sg:postcode":"93711",
    "sg:province":"CA",
    "sg:tags":[
        "dealer"
    ],
    "wof:name":"Petunia's Place",
    "wof:placetype":"venue"
},
  "geometry": {"coordinates":[-119.830519,36.822663],"type":"Point"}
}