{
  "type": "Feature",
  "properties": {
    "addr:full":"150 S Main St Fort Bragg CA 95437",
    "addr:housenumber":"150",
    "addr:postcode":"95437",
    "addr:street":"S Main St",
    "iso:country":"US",
    "sg:address":"150 S Main St",
    "sg:city":"Fort Bragg",
    "sg:classifiers":[
        {
            "category":"Shopping",
            "subcategory":"Pharmacy",
            "type":"Retail Goods"
        }
    ],
    "sg:phone":"+1 707 961 0207",
    "sg:postcode":"95437",
    "sg:province":"CA",
    "sg:website":"www.longs.com",
    "wof:name":"Longs Drug",
    "wof:placetype":"venue"
},
  "geometry": {"coordinates":[-123.805826,39.441073],"type":"Point"}
}