{
  "type": "Feature",
  "properties": {
    "iso:country":"US",
    "sg:address":"739 16th Ave",
    "sg:city":"Menlo Park",
    "sg:classifiers":[
        {
            "category":"Building & Trades",
            "subcategory":"Landscaping Services",
            "type":"Services"
        }
    ],
    "sg:phone":"+1 650 327 6412",
    "sg:postcode":"94025",
    "sg:province":"CA",
    "wof:name":"Mario Lumber",
    "wof:placetype":"venue"
},
  "geometry": {"coordinates":[-122.19035,37.476017],"type":"Point"}
}