{
  "type": "Feature",
  "properties": {
    "iso:country":"US",
    "sg:address":"21860 Burbank Blvd",
    "sg:city":"Woodland Hills",
    "sg:classifiers":[
        {
            "category":"Real Estate",
            "subcategory":"Developer",
            "type":"Services"
        }
    ],
    "sg:phone":"+1 818 587 3800",
    "sg:postcode":"91367",
    "sg:province":"CA",
    "wof:name":"Warner Gateway",
    "wof:placetype":"venue"
},
  "geometry": {"coordinates":[-118.603422,34.172282],"type":"Point"}
}