{
  "type": "Feature",
  "properties": {
    "addr:full":"27082 Burbank Foothill Ranch CA 92610",
    "addr:housenumber":"27082",
    "addr:postcode":"92610",
    "addr:street":"Burbank",
    "iso:country":"US",
    "sg:address":"27082 Burbank",
    "sg:city":"Foothill Ranch",
    "sg:classifiers":[
        {
            "category":"Professional",
            "subcategory":"Testing Lab",
            "type":"Services"
        }
    ],
    "sg:phone":"+1 949 595 0641",
    "sg:postcode":"92610",
    "sg:province":"CA",
    "sg:tags":[
        "laboratory"
    ],
    "sg:website":"www.actalabs.com",
    "wof:name":"ACTA Laboratories",
    "wof:placetype":"venue"
},
  "geometry": {"coordinates":[-117.65541899999999,33.679378],"type":"Point"}
}