{
  "type": "Feature",
  "properties": {
    "addr:full":"4825 San Leandro St Oakland CA 94601",
    "addr:housenumber":"4825",
    "addr:postcode":"94601",
    "addr:street":"San Leandro St",
    "iso:country":"US",
    "sg:address":"4825 San Leandro St",
    "sg:city":"Oakland",
    "sg:classifiers":[
        {
            "category":"Retail",
            "subcategory":"Auto Repair",
            "type":"Services"
        }
    ],
    "sg:phone":"+1 510 532 5000",
    "sg:postcode":"94601",
    "sg:province":"CA",
    "sg:tags":[
        "towing",
        "wrecker"
    ],
    "sg:website":"www.KenBettsTowing.com",
    "wof:name":"Ken Betts Towing",
    "wof:placetype":"venue"
},
  "geometry": {"coordinates":[-122.212997,37.7677],"type":"Point"}
}