{
  "type": "Feature",
  "properties": {
    "addr:full":"2307 Oakdale Rd Modesto CA 95355",
    "addr:housenumber":"2307",
    "addr:postcode":"ca 95355",
    "addr:street":"Oakdale Rd",
    "iso:country":"US",
    "sg:address":"2307 Oakdale Rd",
    "sg:city":"Modesto",
    "sg:classifiers":[
        {
            "category":"Food & Beverages",
            "subcategory":"Meat & Fish",
            "type":"Retail Goods"
        }
    ],
    "sg:phone":"+1 209 551 4822",
    "sg:postcode":"95355",
    "sg:province":"CA",
    "sg:tags":[
        "shop",
        "seafood",
        "market"
    ],
    "wof:name":"Jonathans Fresh Fish No",
    "wof:placetype":"venue"
},
  "geometry": {"coordinates":[-120.95931899999999,37.675363],"type":"Point"}
}