{
  "type": "Feature",
  "properties": {
    "iso:country":"US",
    "sg:address":"10025 El Camino Real Spc 1",
    "sg:city":"Atascadero",
    "sg:classifiers":[
        {
            "category":"Building & Trades",
            "subcategory":"Construction",
            "type":"Services"
        },
        {
            "category":"Home & Garden",
            "subcategory":"Mobile Homes",
            "type":"Retail Goods"
        }
    ],
    "sg:phone":"+1 805 466 2400",
    "sg:postcode":"93422",
    "sg:province":"CA",
    "sg:tags":[
        "manufactured",
        "housing-communities",
        "park"
    ],
    "wof:name":"Rancho Del Bordo Mobile Home Estates",
    "wof:placetype":"venue"
},
  "geometry": {"coordinates":[-120.646241,35.463228],"type":"Point"}
}