{
  "type": "Feature",
  "properties": {
    "addr:full":"311 Hiddenlake Dr Sunnyvale CA 94089",
    "addr:housenumber":"311",
    "addr:postcode":"94089",
    "addr:street":"Hiddenlake Dr",
    "iso:country":"US",
    "sg:address":"311 Hiddenlake Dr",
    "sg:city":"Sunnyvale",
    "sg:classifiers":[
        {
            "category":"Building & Trades",
            "subcategory":"Equipment Rental",
            "type":"Services"
        }
    ],
    "sg:phone":"+1 408 541 9347",
    "sg:postcode":"94089",
    "sg:province":"CA",
    "sg:tags":[
        "party",
        "supply"
    ],
    "wof:name":"Bay Area Food Eqpt & Facility",
    "wof:placetype":"venue"
},
  "geometry": {"coordinates":[-122.007158,37.399226],"type":"Point"}
}