{
  "type": "Feature",
  "properties": {
    "addr:full":"608 Dittmar Way Sacramento CA 95819",
    "addr:housenumber":"608",
    "addr:postcode":"95819",
    "addr:street":"Dittmar Way",
    "iso:country":"US",
    "sg:address":"608 Dittmar Way",
    "sg:city":"Sacramento",
    "sg:classifiers":[
        {
            "category":"Professional",
            "subcategory":"Business Services",
            "type":"Services"
        }
    ],
    "sg:phone":"+1 916 256 5281",
    "sg:postcode":"95819",
    "sg:province":"CA",
    "sg:tags":[
        "recording",
        "studio"
    ],
    "wof:name":"Museum Records",
    "wof:placetype":"venue"
},
  "geometry": {"coordinates":[-121.43192000000001,38.569693],"type":"Point"}
}