{
  "type": "Feature",
  "properties": {
    "iso:country":"US",
    "sg:address":"17232 S Main St",
    "sg:city":"Gardena",
    "sg:classifiers":[
        {
            "category":"Wholesale",
            "subcategory":"Durable Goods & Equipment",
            "type":"Manufacturing & Wholesale Goods"
        }
    ],
    "sg:phone":"+1 310 767 7881",
    "sg:postcode":"90248",
    "sg:province":"CA",
    "sg:tags":[
        "distributor",
        "instrument",
        "importer",
        "musical"
    ],
    "wof:name":"Tmp West",
    "wof:placetype":"venue"
},
  "geometry": {"coordinates":[-118.275415,33.874746],"type":"Point"}
}