{
  "type": "Feature",
  "properties": {
    "addr:full":"151 Lynch Creek Way Petaluma CA 94954",
    "addr:housenumber":"151",
    "addr:postcode":"94954",
    "addr:street":"Lynch Creek Way",
    "iso:country":"US",
    "sg:address":"151 Lynch Creek Way",
    "sg:city":"Petaluma",
    "sg:classifiers":[
        {
            "category":"Health Services",
            "subcategory":"Doctor",
            "type":"Services"
        }
    ],
    "sg:phone":"+1 707 778 3551",
    "sg:postcode":"94954",
    "sg:province":"CA",
    "sg:tags":[
        "physician",
        "surgeon"
    ],
    "wof:name":"Workcare Occupational Health",
    "wof:placetype":"venue"
},
  "geometry": {"coordinates":[-122.634186,38.252115],"type":"Point"}
}