{
  "type": "Feature",
  "properties": {
    "iso:country":"US",
    "sg:address":"6530 Alameda St",
    "sg:city":"Huntington Park",
    "sg:classifiers":[
        {
            "category":"Professional",
            "type":"Services"
        },
        {
            "category":"Retail",
            "subcategory":"Auto Repair",
            "type":"Services"
        }
    ],
    "sg:phone":"+1 323 582 4104",
    "sg:postcode":"90255",
    "sg:province":"CA",
    "sg:tags":[
        "repairing",
        "automobile"
    ],
    "wof:name":"Servicio Automotriz Tony's",
    "wof:placetype":"venue"
},
  "geometry": {"coordinates":[-118.235371,33.980036],"type":"Point"}
}