{
  "type": "Feature",
  "properties": {
    "addr:full":"29713 Central Ave Castaic CA 91384",
    "addr:postcode":"29713;91384",
    "addr:street":"Central Ave",
    "iso:country":"US",
    "sg:address":"29713 Central Ave",
    "sg:city":"Castaic",
    "sg:classifiers":[
        {
            "category":"Building & Trades",
            "subcategory":"Construction",
            "type":"Services"
        }
    ],
    "sg:phone":"+1 661 257 9078",
    "sg:postcode":"91384",
    "sg:province":"CA",
    "sg:tags":[
        "contractor"
    ],
    "wof:name":"California Building Service",
    "wof:placetype":"venue"
},
  "geometry": {"coordinates":[-118.653655,34.44498],"type":"Point"}
}