{
  "type": "Feature",
  "properties": {
    "addr:full":"3665 N Harbor Dr Terminal 1 San Diego CA 92101",
    "addr:housenumber":"3665;1",
    "addr:postcode":"92101",
    "addr:street":"N Harbor Dr Terminal",
    "iso:country":"US",
    "sg:address":"3665 N Harbor Dr Terminal 1",
    "sg:city":"San Diego",
    "sg:classifiers":[
        {
            "category":"Personal",
            "subcategory":"Shoe Repair & Shine",
            "type":"Services"
        }
    ],
    "sg:phone":"+1 702 367 1757",
    "sg:postcode":"92101",
    "sg:province":"CA",
    "sg:website":"goodfellowsshoeshine.com/",
    "wof:name":"Goodfellows Shoeshine",
    "wof:placetype":"venue"
},
  "geometry": {"coordinates":[-117.202876,32.729497],"type":"Point"}
}