{
  "type": "Feature",
  "properties": {
    "iso:country":"US",
    "sg:address":"24173 View Pointe Ln",
    "sg:city":"Valencia",
    "sg:classifiers":[
        {
            "category":"Shopping",
            "subcategory":"Beauty & Cosmetics",
            "type":"Retail Goods"
        }
    ],
    "sg:phone":"+1 661 254 2895",
    "sg:postcode":"91355",
    "sg:province":"CA",
    "sg:tags":[
        "equipment",
        "supply"
    ],
    "wof:name":"Gabby B & H Inc.",
    "wof:placetype":"venue"
},
  "geometry": {"coordinates":[-118.56299300000001,34.427251],"type":"Point"}
}