{
  "type": "Feature",
  "properties": {
    "iso:country":"US",
    "sg:address":"4942 Siesta Dr",
    "sg:city":"Oceanside",
    "sg:classifiers":[
        {
            "category":"Professional",
            "subcategory":"Accounting & Tax Preparation",
            "type":"Services"
        }
    ],
    "sg:phone":"+1 760 722 4246",
    "sg:postcode":"92057",
    "sg:province":"CA",
    "wof:name":"Vincent M Vento",
    "wof:placetype":"venue"
},
  "geometry": {"coordinates":[-117.30485400000001,33.249238],"type":"Point"}
}