{
  "type": "Feature",
  "properties": {
    "addr:full":"7013 Katella Ave Stanton CA 90680",
    "addr:housenumber":"7013",
    "addr:postcode":"ca 90680",
    "addr:street":"Katella Ave",
    "iso:country":"US",
    "sg:address":"7013 Katella Ave",
    "sg:city":"Stanton",
    "sg:classifiers":[
        {
            "category":"Restaurant",
            "type":"Food & Drink"
        }
    ],
    "sg:menulink":"http://www.allmenus.com/ca/anaheim-santa-ana-garden-grove/28586-pho-today-restaurant/menu/",
    "sg:phone":"+1 714 226 9636",
    "sg:postcode":"90680",
    "sg:province":"CA",
    "sg:tags":[
        "asian",
        "vietnamese"
    ],
    "wof:name":"Pho Today Restaurant",
    "wof:placetype":"venue"
},
  "geometry": {"coordinates":[-118.010471,33.803082],"type":"Point"}
}