{
  "type": "Feature",
  "properties": {
    "addr:full":"523 E Mallard Cir Fresno CA 93730",
    "addr:housenumber":"523",
    "addr:postcode":"93730",
    "addr:street":"E Mallard Cir",
    "iso:country":"US",
    "sg:address":"523 E Mallard Cir",
    "sg:city":"Fresno",
    "sg:classifiers":[
        {
            "category":"Professional",
            "subcategory":"Lawyer & Legal Services",
            "type":"Services"
        }
    ],
    "sg:phone":"+1 559 434 4421",
    "sg:postcode":"93730",
    "sg:province":"CA",
    "sg:tags":[
        "attorney",
        "practice"
    ],
    "wof:name":"V Jones Law Corp",
    "wof:placetype":"venue"
},
  "geometry": {"coordinates":[-119.774038,36.882858],"type":"Point"}
}