{
  "type": "Feature",
  "properties": {
    "addr:full":"126 Layton St Ojai CA 93023",
    "addr:housenumber":"126",
    "addr:postcode":"93023",
    "addr:street":"Layton St",
    "iso:country":"US",
    "sg:address":"126 Layton St",
    "sg:city":"Ojai",
    "sg:classifiers":[
        {
            "category":"Wholesale",
            "subcategory":"Electrical",
            "type":"Manufacturing & Wholesale Goods"
        }
    ],
    "sg:phone":"+1 805 640 9661",
    "sg:postcode":"93023",
    "sg:province":"CA",
    "sg:tags":[
        "equipment"
    ],
    "wof:name":"Home Towne Security",
    "wof:placetype":"venue"
},
  "geometry": {"coordinates":[-119.256773,34.460296],"type":"Point"}
}