{
  "type": "Feature",
  "properties": {
    "addr:full":"1750 N Sycamore Avenue Los Angeles CA 90028",
    "addr:housenumber":"1750",
    "addr:postcode":"90028",
    "addr:street":"N Sycamore Avenue",
    "iso:country":"US",
    "sg:address":"1750 N Sycamore Avenue",
    "sg:city":"Los Angeles",
    "sg:classifiers":[
        {
            "category":"Real Estate",
            "subcategory":"Real Estate Operator",
            "type":"Services"
        }
    ],
    "sg:phone":"+1 323 969 8877",
    "sg:postcode":"90028",
    "sg:province":"CA",
    "sg:tags":[
        "apartment"
    ],
    "wof:name":"Sycamore Terrace",
    "wof:placetype":"venue"
},
  "geometry": {"coordinates":[-118.343317,34.102874],"type":"Point"}
}