{
  "type": "Feature",
  "properties": {
    "iso:country":"US",
    "sg:address":"50 W Tennyson Rd",
    "sg:city":"Hayward",
    "sg:classifiers":[
        {
            "category":"Food & Beverages",
            "subcategory":"Liquor & Beverages",
            "type":"Retail Goods"
        }
    ],
    "sg:phone":"+1 510 782 8040",
    "sg:postcode":"94544",
    "sg:province":"CA",
    "sg:tags":[
        "beer",
        "spirit",
        "wine"
    ],
    "wof:name":"Zach's Market",
    "wof:placetype":"venue"
},
  "geometry": {"coordinates":[-122.064003,37.634102],"type":"Point"}
}