{
  "type": "Feature",
  "properties": {
    "iso:country":"US",
    "sg:address":"21022 Anza Ave",
    "sg:city":"Torrance",
    "sg:classifiers":[
        {
            "category":"Real Estate",
            "subcategory":"Real Estate Operator",
            "type":"Services"
        }
    ],
    "sg:phone":"+1 310 542 7548",
    "sg:postcode":"90503",
    "sg:province":"CA",
    "sg:tags":[
        "apartment"
    ],
    "wof:name":"Bavarian Village Apts",
    "wof:placetype":"venue"
},
  "geometry": {"coordinates":[-118.362187,33.839325],"type":"Point"}
}