{
  "type": "Feature",
  "properties": {
    "iso:country":"US",
    "sg:address":"545 E Saint John St",
    "sg:city":"San Jose",
    "sg:classifiers":[
        {
            "category":"Professional",
            "subcategory":"Lawyer & Legal Services",
            "type":"Services"
        }
    ],
    "sg:phone":"+1 408 993 1551",
    "sg:postcode":"95112",
    "sg:province":"CA",
    "wof:name":"Nguyen Tam Atty",
    "wof:placetype":"venue"
},
  "geometry": {"coordinates":[-121.879997,37.343102],"type":"Point"}
}