{
  "type": "Feature",
  "properties": {
    "addr:full":"1456 E Mendocino St Altadena CA 91001",
    "addr:housenumber":"1456",
    "addr:postcode":"91001",
    "addr:street":"E Mendocino St",
    "iso:country":"US",
    "sg:address":"1456 E Mendocino St",
    "sg:city":"Altadena",
    "sg:classifiers":[
        {
            "category":"Sports & Exercise",
            "subcategory":"Golf",
            "type":"Entertainment"
        }
    ],
    "sg:phone":"+1 626 797 3821",
    "sg:postcode":"91001",
    "sg:province":"CA",
    "sg:website":"www.lacounty.info",
    "wof:name":"County of Los Angeles",
    "wof:placetype":"venue"
},
  "geometry": {"coordinates":[-118.120508,34.185732],"type":"Point"}
}