{
  "type": "Feature",
  "properties": {
    "addr:full":"212 Madonna Rd San Luis Obispo CA 93405",
    "addr:housenumber":"212",
    "addr:postcode":"93405",
    "addr:street":"Madonna Rd",
    "iso:country":"US",
    "sg:address":"212 Madonna Rd",
    "sg:city":"San Luis Obispo",
    "sg:classifiers":[
        {
            "category":"Restaurant",
            "type":"Food & Drink"
        }
    ],
    "sg:menulink":"http://www.allmenus.com/ca/san-luis-obispo/97104-ihop/menu/",
    "sg:phone":"+1 805 547 9140",
    "sg:postcode":"93405",
    "sg:province":"CA",
    "sg:tags":[
        "sandwich",
        "salad",
        "burger",
        "soup",
        "american",
        "steakhouse",
        "wrap"
    ],
    "wof:name":"IHOP",
    "wof:placetype":"venue"
},
  "geometry": {"coordinates":[-120.67685899999999,35.263829],"type":"Point"}
}