{
  "type": "Feature",
  "properties": {
    "addr:full":"2514 San Pablo Ave Berkeley CA 94702",
    "addr:housenumber":"2514",
    "addr:postcode":"94702",
    "addr:street":"San Pablo Ave",
    "iso:country":"US",
    "sg:address":"2514 San Pablo Ave",
    "sg:city":"Berkeley",
    "sg:classifiers":[
        {
            "category":"Professional",
            "subcategory":"Business Services",
            "type":"Services"
        }
    ],
    "sg:phone":"+1 888 882 7464",
    "sg:postcode":"94702",
    "sg:province":"CA",
    "sg:tags":[
        "designer",
        "jewelry"
    ],
    "wof:name":"Kiss My Ring",
    "wof:placetype":"venue"
},
  "geometry": {"coordinates":[-122.28943599999999,37.860666],"type":"Point"}
}