{
  "type": "Feature",
  "properties": {
    "addr:full":"1183 Comstock Rd Hollister CA 95023",
    "addr:housenumber":"1183",
    "addr:postcode":"hollister ca 95023",
    "addr:street":"Comstock Rd",
    "iso:country":"US",
    "sg:address":"1183 Comstock Rd",
    "sg:city":"Hollister",
    "sg:classifiers":[
        {
            "category":"Farming",
            "subcategory":"Livestock Farm",
            "type":"Manufacturing & Wholesale Goods"
        },
        {
            "category":"Arena",
            "subcategory":"Horse Racetrack",
            "type":"Entertainment"
        }
    ],
    "sg:phone":"+1 831 637 2222",
    "sg:postcode":"95023",
    "sg:province":"CA",
    "sg:tags":[
        "breeder"
    ],
    "wof:name":"Monterey Farm",
    "wof:placetype":"venue"
},
  "geometry": {"coordinates":[-121.346992,36.928379],"type":"Point"}
}