{
  "type": "Feature",
  "properties": {
    "iso:country":"US",
    "sg:address":"31332 Via Colinas",
    "sg:city":"Thousand Oaks",
    "sg:classifiers":[
        {
            "category":"Wholesale",
            "subcategory":"Hardware",
            "type":"Manufacturing & Wholesale Goods"
        }
    ],
    "sg:phone":"+1 818 706 0972",
    "sg:postcode":"91362",
    "sg:province":"CA",
    "sg:tags":[
        "industrial",
        "e"
    ],
    "wof:name":"I T T Standard",
    "wof:placetype":"venue"
},
  "geometry": {"coordinates":[-118.80633,34.156505],"type":"Point"}
}