{
  "type": "Feature",
  "properties": {
    "addr:full":"116 Alan Shepard Way Oakland CA 94621",
    "addr:housenumber":"116",
    "addr:postcode":"94621",
    "addr:street":"Alan Shepard Way",
    "iso:country":"US",
    "sg:address":"116 Alan Shepard Way",
    "sg:city":"Oakland",
    "sg:classifiers":[
        {
            "category":"Freight",
            "type":"Transportation"
        }
    ],
    "sg:phone":"+1 510 633 6969",
    "sg:postcode":"94621",
    "sg:province":"CA",
    "sg:tags":[
        "courier",
        "air"
    ],
    "wof:name":"UPS",
    "wof:placetype":"venue"
},
  "geometry": {"coordinates":[-122.214545,37.715101],"type":"Point"}
}