{
  "type": "Feature",
  "properties": {
    "addr:full":"18516 Beach Blvd Huntington Beach CA 92648",
    "addr:housenumber":"18516",
    "addr:postcode":"92648",
    "addr:street":"Beach Blvd",
    "iso:country":"US",
    "sg:address":"18516 Beach Blvd",
    "sg:city":"Huntington Beach",
    "sg:classifiers":[
        {
            "category":"Health Services",
            "subcategory":"Dentist",
            "type":"Services"
        }
    ],
    "sg:phone":"+1 714 962 5545",
    "sg:postcode":"92648",
    "sg:province":"CA",
    "wof:name":"Lisa Tilton, DDS",
    "wof:placetype":"venue"
},
  "geometry": {"coordinates":[-117.988711,33.69229],"type":"Point"}
}