{
  "type": "Feature",
  "properties": {
    "addr:full":"16582 Gothard St Ste O Huntington Beach CA 92647",
    "addr:housenumber":"16582",
    "addr:postcode":"92647",
    "addr:street":"Gothard St Ste O",
    "iso:country":"US",
    "sg:address":"16582 Gothard St Ste O",
    "sg:city":"Huntington Beach",
    "sg:classifiers":[
        {
            "category":"Coffee & Tea",
            "type":"Food & Drink"
        }
    ],
    "sg:phone":"+1 714 625 8699",
    "sg:postcode":"92647",
    "sg:province":"CA",
    "sg:website":"poverellocoffee.bizatomic.net",
    "wof:name":"Poverello Coffee",
    "wof:placetype":"venue"
},
  "geometry": {"coordinates":[-118.000141,33.720717],"type":"Point"}
}