{
  "type": "Feature",
  "properties": {
    "addr:full":"8780 19th St Rancho Cucamonga CA 91701",
    "addr:housenumber":"8780",
    "addr:postcode":"91701",
    "addr:street":"19Th St",
    "iso:country":"US",
    "sg:address":"8780 19th St",
    "sg:city":"Rancho Cucamonga",
    "sg:classifiers":[
        {
            "category":"Manufacturing",
            "subcategory":"Chemicals & Compounds",
            "type":"Manufacturing & Wholesale Goods"
        }
    ],
    "sg:phone":"+1 909 981 4929",
    "sg:postcode":"91701",
    "sg:province":"CA",
    "sg:tags":[
        "agricultural",
        "mfg"
    ],
    "wof:name":"Dupont",
    "wof:placetype":"venue"
},
  "geometry": {"coordinates":[-117.615255,34.132698],"type":"Point"}
}