{
  "type": "Feature",
  "properties": {
    "addr:full":"1017 Fedora St Los Angeles CA 90006",
    "addr:housenumber":"1017",
    "addr:postcode":"90006",
    "addr:street":"Fedora St",
    "iso:country":"US",
    "sg:address":"1017 Fedora St",
    "sg:city":"Los Angeles",
    "sg:classifiers":[
        {
            "category":"Health Services",
            "subcategory":"Health Practitioner",
            "type":"Services"
        }
    ],
    "sg:phone":"+1 213 386 4903",
    "sg:postcode":"90006",
    "sg:province":"CA",
    "sg:tags":[
        "acupuncture"
    ],
    "wof:name":"Han-Kook Herbs & Acupunture",
    "wof:placetype":"venue"
},
  "geometry": {"coordinates":[-118.29796,34.051168],"type":"Point"}
}