{
  "type": "Feature",
  "properties": {
    "addr:full":"321 N San Fernando Blvd Burbank CA 91502",
    "addr:housenumber":"321",
    "addr:postcode":"91502",
    "addr:street":"N San Fernando Blvd",
    "iso:country":"US",
    "sg:address":"321 N San Fernando Blvd",
    "sg:city":"Burbank",
    "sg:classifiers":[
        {
            "category":"Shopping",
            "subcategory":"Mobile Phones",
            "type":"Retail Goods"
        }
    ],
    "sg:phone":"+1 818 260 1977",
    "sg:postcode":"91502",
    "sg:province":"CA",
    "wof:name":"Sprint Pcs Personal Communication Services",
    "wof:placetype":"venue"
},
  "geometry": {"coordinates":[-118.310997,34.1824],"type":"Point"}
}