{
  "type": "Feature",
  "properties": {
    "iso:country":"US",
    "sg:address":"270 Mesa Rd",
    "sg:city":"Bolinas",
    "sg:classifiers":[
        {
            "category":"Professional",
            "subcategory":"Business Services",
            "type":"Services"
        }
    ],
    "sg:phone":"+1 415 868 2618",
    "sg:postcode":"94924",
    "sg:province":"CA",
    "sg:tags":[
        "recording",
        "studio"
    ],
    "wof:name":"Turner Studios",
    "wof:placetype":"venue"
},
  "geometry": {"coordinates":[-122.715571,37.918308],"type":"Point"}
}