{
  "type": "Feature",
  "properties": {
    "iso:country":"US",
    "sg:address":"234 Pico Blvd",
    "sg:city":"Santa Monica",
    "sg:classifiers":[
        {
            "category":"Sports & Exercise",
            "subcategory":"Bowling",
            "type":"Entertainment"
        }
    ],
    "sg:phone":"+1 310 399 7731",
    "sg:postcode":"90405",
    "sg:province":"CA",
    "sg:tags":[
        "center"
    ],
    "wof:name":"AMF Bay Shore Lanes",
    "wof:placetype":"venue"
},
  "geometry": {"coordinates":[-118.488946,34.008384],"type":"Point"}
}