{
  "type": "Feature",
  "properties": {
    "addr:full":"213 Church St Roseville CA 95678",
    "addr:housenumber":"213",
    "addr:postcode":"95678",
    "addr:street":"Church St",
    "iso:country":"US",
    "sg:address":"213 Church St",
    "sg:city":"Roseville",
    "sg:classifiers":[
        {
            "category":"Retail",
            "subcategory":"Repair Shop",
            "type":"Services"
        }
    ],
    "sg:phone":"+1 916 224 6274",
    "sg:postcode":"95678",
    "sg:province":"CA",
    "sg:tags":[
        "upholsterer"
    ],
    "wof:name":"AADLER UPHOLSTERY",
    "wof:placetype":"venue"
},
  "geometry": {"coordinates":[-121.286773,38.750573],"type":"Point"}
}