{
  "type": "Feature",
  "properties": {
    "addr:full":"51 Majestic Ct Moorpark CA 93021",
    "addr:housenumber":"51",
    "addr:postcode":"ca 93021",
    "addr:street":"Majestic Ct",
    "iso:country":"US",
    "sg:address":"51 Majestic Ct",
    "sg:city":"Moorpark",
    "sg:classifiers":[
        {
            "category":"Real Estate",
            "subcategory":"Real Estate Operator",
            "type":"Services"
        }
    ],
    "sg:phone":"+1 805 523 0727",
    "sg:postcode":"93021",
    "sg:province":"CA",
    "sg:tags":[
        "apartment"
    ],
    "sg:website":"www.starpointproperties.com",
    "wof:name":"Archstone Le Club",
    "wof:placetype":"venue"
},
  "geometry": {"coordinates":[-118.881297,34.276546],"type":"Point"}
}