{
  "type": "Feature",
  "properties": {
    "addr:full":"2967 Cowley Way San Diego CA 92117",
    "addr:housenumber":"2967",
    "addr:postcode":"92117",
    "addr:street":"Cowley Way",
    "iso:country":"US",
    "sg:address":"2967 Cowley Way",
    "sg:city":"San Diego",
    "sg:classifiers":[
        {
            "category":"Arts & Performance",
            "subcategory":"Theater",
            "type":"Entertainment"
        }
    ],
    "sg:phone":"+1 619 275 6935",
    "sg:postcode":"92117",
    "sg:province":"CA",
    "sg:tags":[
        "live",
        "music"
    ],
    "wof:name":"LA Boom",
    "wof:placetype":"venue"
},
  "geometry": {"coordinates":[-117.19166300000001,32.793431],"type":"Point"}
}