{
  "type": "Feature",
  "properties": {
    "addr:full":"329 Oakland Ave San Jose CA 95116",
    "addr:housenumber":"329",
    "addr:postcode":"95116",
    "addr:street":"Oakland Ave",
    "iso:country":"US",
    "sg:address":"329 Oakland Ave",
    "sg:city":"San Jose",
    "sg:classifiers":[
        {
            "category":"Retail",
            "subcategory":"Auto Repair",
            "type":"Services"
        }
    ],
    "sg:phone":"+1 408 929 4336",
    "sg:postcode":"95116",
    "sg:province":"CA",
    "sg:tags":[
        "repairing",
        "automobile"
    ],
    "wof:name":"Heredia's Auto Svc",
    "wof:placetype":"venue"
},
  "geometry": {"coordinates":[-121.84707899999999,37.350539],"type":"Point"}
}