{
  "type": "Feature",
  "properties": {
    "addr:full":"1109 Burlingame Ave Burlingame CA 94010",
    "addr:housenumber":"1109",
    "addr:postcode":"94010",
    "addr:street":"Burlingame Ave",
    "iso:country":"US",
    "sg:address":"1109 Burlingame Ave",
    "sg:city":"Burlingame",
    "sg:classifiers":[
        {
            "category":"Retail",
            "subcategory":"Photofinishing",
            "type":"Services"
        }
    ],
    "sg:phone":"+1 650 579 7768",
    "sg:postcode":"94010",
    "sg:province":"CA",
    "sg:tags":[
        "photo",
        "photography",
        "finishing",
        "store"
    ],
    "wof:name":"88 Photo",
    "wof:placetype":"venue"
},
  "geometry": {"coordinates":[-122.345001,37.5797],"type":"Point"}
}