{
  "type": "Feature",
  "properties": {
    "addr:full":"326 Elderberry Dr Petaluma CA 94952",
    "addr:housenumber":"326",
    "addr:postcode":"94952",
    "addr:street":"Elderberry Dr",
    "iso:country":"US",
    "sg:address":"326 Elderberry Dr",
    "sg:city":"Petaluma",
    "sg:classifiers":[
        {
            "category":"Wholesale",
            "subcategory":"Wine & Distilled Alcoholic Beverages",
            "type":"Manufacturing & Wholesale Goods"
        }
    ],
    "sg:phone":"+1 707 765 2091",
    "sg:postcode":"94952",
    "sg:province":"CA",
    "sg:tags":[
        "blend",
        "mfg"
    ],
    "wof:name":"William Grant & Sons Inc",
    "wof:placetype":"venue"
},
  "geometry": {"coordinates":[-122.63242700000001,38.210462],"type":"Point"}
}