{
  "type": "Feature",
  "properties": {
    "addr:full":"401 N Tustin St Orange CA 92867",
    "addr:housenumber":"401",
    "addr:postcode":"92867",
    "addr:street":"N Tustin St",
    "iso:country":"US",
    "sg:address":"401 N Tustin St",
    "sg:city":"Orange",
    "sg:classifiers":[
        {
            "category":"Home & Garden",
            "subcategory":"Household Appliances",
            "type":"Retail Goods"
        },
        {
            "category":"Retail",
            "subcategory":"Repair Shop",
            "type":"Services"
        },
        {
            "category":"Shopping",
            "subcategory":"Crafts & Fabrics",
            "type":"Retail Goods"
        }
    ],
    "sg:phone":"+1 714 538 7414",
    "sg:postcode":"92867",
    "sg:province":"CA",
    "sg:tags":[
        "machines-household",
        "cleaners-household-dealers",
        "sewing",
        "cleaners-repair",
        "machines-service",
        "vacuum"
    ],
    "sg:website":"http://www.dhsewvac.com",
    "wof:name":"D & H Sewing, Vacuum & Home Center",
    "wof:placetype":"venue"
},
  "geometry": {"coordinates":[-117.835705,33.793254],"type":"Point"}
}