{
  "type": "Feature",
  "properties": {
    "iso:country":"US",
    "sg:address":"7 Anna Ct",
    "sg:city":"Novato",
    "sg:classifiers":[
        {
            "category":"Professional",
            "subcategory":"Management & Consulting",
            "type":"Services"
        }
    ],
    "sg:phone":"+1 415 897 7167",
    "sg:postcode":"94945",
    "sg:province":"CA",
    "sg:tags":[
        "consultant"
    ],
    "wof:name":"Dover Court Consulting",
    "wof:placetype":"venue"
},
  "geometry": {"coordinates":[-122.58522600000001,38.114716],"type":"Point"}
}