{
  "type": "Feature",
  "properties": {
    "iso:country":"US",
    "sg:address":"375 N. La Cienega Blvd.",
    "sg:city":"Los Angeles",
    "sg:classifiers":[
        {
            "category":"Shopping",
            "type":"Retail Goods"
        }
    ],
    "sg:phone":"+1 949 677 5976",
    "sg:postcode":"90048",
    "sg:province":"CA",
    "wof:name":"EZ Christmas Trees",
    "wof:placetype":"venue"
},
  "geometry": {"coordinates":[-118.376982,34.078102],"type":"Point"}
}