{
  "type": "Feature",
  "properties": {
    "iso:country":"US",
    "sg:address":"131 Mirada Rd",
    "sg:city":"Half Moon Bay",
    "sg:classifiers":[
        {
            "category":"Restaurant",
            "type":"Food & Drink"
        }
    ],
    "sg:menulink":"http://www.allmenus.com/ca/south-coastside/270092-miramar-beach-restaurant/menu/",
    "sg:phone":"+1 650 726 9053",
    "sg:postcode":"94019",
    "sg:province":"CA",
    "sg:tags":[
        "seafood",
        "american"
    ],
    "wof:name":"Miramar Beach Restaurant",
    "wof:placetype":"venue"
},
  "geometry": {"coordinates":[-122.46229099999999,37.495683],"type":"Point"}
}