{
  "type": "Feature",
  "properties": {
    "iso:country":"US",
    "sg:address":"5 Holland Ste 105",
    "sg:city":"Irvine",
    "sg:classifiers":[
        {
            "category":"Place Of Worship",
            "type":"Public Place"
        }
    ],
    "sg:phone":"+1 949 600 5227",
    "sg:postcode":"92618",
    "sg:province":"CA",
    "sg:tags":[
        "church"
    ],
    "wof:name":"Grace Chapel Oc",
    "wof:placetype":"venue"
},
  "geometry": {"coordinates":[-117.720772,33.646469],"type":"Point"}
}