{
  "type": "Feature",
  "properties": {
    "addr:full":"115 E Calvin St Taft CA 93268",
    "addr:housenumber":"115",
    "addr:postcode":"93268",
    "addr:street":"E Calvin St",
    "iso:country":"US",
    "sg:address":"115 E Calvin St",
    "sg:city":"Taft",
    "sg:classifiers":[
        {
            "category":"Manufacturing",
            "subcategory":"Printing",
            "type":"Manufacturing & Wholesale Goods"
        }
    ],
    "sg:phone":"+1 661 765 2241",
    "sg:postcode":"93268",
    "sg:province":"CA",
    "sg:tags":[
        "book"
    ],
    "wof:name":"Nwo Things",
    "wof:placetype":"venue"
},
  "geometry": {"coordinates":[-119.451435,35.145721],"type":"Point"}
}