{
  "type": "Feature",
  "properties": {
    "iso:country":"US",
    "sg:address":"2861 Jasper Rd",
    "sg:city":"Rescue",
    "sg:classifiers":[
        {
            "category":"Building & Trades",
            "subcategory":"Construction",
            "type":"Services"
        }
    ],
    "sg:phone":"+1 530 677 6947",
    "sg:postcode":"95672",
    "sg:province":"CA",
    "sg:tags":[
        "concrete",
        "contractor"
    ],
    "wof:name":"Cummings Concrete",
    "wof:placetype":"venue"
},
  "geometry": {"coordinates":[-120.989405,38.760947],"type":"Point"}
}