{
  "type": "Feature",
  "properties": {
    "addr:full":"9851 Horn Rd Sacramento CA 95827",
    "addr:housenumber":"9851",
    "addr:postcode":"95827",
    "addr:street":"Horn Rd",
    "iso:country":"US",
    "sg:address":"9851 Horn Rd",
    "sg:city":"Sacramento",
    "sg:classifiers":[
        {
            "category":"Professional",
            "subcategory":"Lawyer & Legal Services",
            "type":"Services"
        }
    ],
    "sg:phone":"+1 916 857 6900",
    "sg:postcode":"95827",
    "sg:province":"CA",
    "sg:tags":[
        "attorney"
    ],
    "wof:name":"Pacific Justice Institute",
    "wof:placetype":"venue"
},
  "geometry": {"coordinates":[-121.32790199999999,38.574749],"type":"Point"}
}