{
  "type": "Feature",
  "properties": {
    "addr:full":"1419 University Ave San Diego CA 92103",
    "addr:housenumber":"1419",
    "addr:postcode":"92103",
    "addr:street":"University Ave",
    "iso:country":"US",
    "sg:address":"1419 University Ave",
    "sg:city":"San Diego",
    "sg:classifiers":[
        {
            "category":"Professional",
            "type":"Services"
        },
        {
            "category":"Personal",
            "type":"Services"
        }
    ],
    "sg:phone":"+1 619 296 6683",
    "sg:postcode":"92103",
    "sg:province":"CA",
    "sg:tags":[
        "consultant",
        "program",
        "health",
        "fitness"
    ],
    "wof:name":"Biokinetix",
    "wof:placetype":"venue"
},
  "geometry": {"coordinates":[-117.15025799999999,32.748416],"type":"Point"}
}