{
  "type": "Feature",
  "properties": {
    "addr:full":"3266 Adams Ave San Diego CA 92116",
    "addr:housenumber":"3266",
    "addr:postcode":"92116",
    "addr:street":"Adams Ave",
    "iso:country":"US",
    "sg:address":"3266 Adams Ave",
    "sg:city":"San Diego",
    "sg:classifiers":[
        {
            "category":"Personal",
            "subcategory":"Beauty Salon",
            "type":"Services"
        }
    ],
    "sg:phone":"+1 619 283 9770",
    "sg:postcode":"92116",
    "sg:province":"CA",
    "wof:name":"Queen Of Curls Beauty Salon",
    "wof:placetype":"venue"
},
  "geometry": {"coordinates":[-117.12318500000001,32.763438],"type":"Point"}
}