{
  "type": "Feature",
  "properties": {
    "addr:full":"1150 Bayhill Dr San Bruno CA 94066",
    "addr:housenumber":"1150",
    "addr:postcode":"94066",
    "addr:street":"Bayhill Dr",
    "iso:country":"US",
    "sg:address":"1150 Bayhill Dr",
    "sg:city":"San Bruno",
    "sg:classifiers":[
        {
            "category":"Shopping",
            "subcategory":"Computers & Home Electronics",
            "type":"Retail Goods"
        }
    ],
    "sg:phone":"+1 650 589 8986",
    "sg:postcode":"94066",
    "sg:province":"CA",
    "sg:tags":[
        "software"
    ],
    "wof:name":"Global Cross Border Svc LTD",
    "wof:placetype":"venue"
},
  "geometry": {"coordinates":[-122.4225,37.628108],"type":"Point"}
}