{
  "type": "Feature",
  "properties": {
    "iso:country":"US",
    "sg:address":"669 57th St",
    "sg:city":"Oakland",
    "sg:classifiers":[
        {
            "category":"Professional",
            "subcategory":"Business Services",
            "type":"Services"
        }
    ],
    "sg:phone":"+1 510 653 3733",
    "sg:postcode":"94609",
    "sg:province":"CA",
    "sg:tags":[
        "consultant",
        "coach"
    ],
    "wof:name":"Numerology Consulting",
    "wof:placetype":"venue"
},
  "geometry": {"coordinates":[-122.266772,37.842377],"type":"Point"}
}