{
  "type": "Feature",
  "properties": {
    "addr:full":"2653 Stranahan Dr Alhambra CA 91803",
    "addr:housenumber":"2653",
    "addr:postcode":"91803",
    "addr:street":"Stranahan Dr",
    "iso:country":"US",
    "sg:address":"2653 Stranahan Dr",
    "sg:city":"Alhambra",
    "sg:classifiers":[
        {
            "category":"Wholesale",
            "subcategory":"Durable Goods & Equipment",
            "type":"Manufacturing & Wholesale Goods"
        }
    ],
    "sg:phone":"+1 626 281 9514",
    "sg:postcode":"91803",
    "sg:province":"CA",
    "wof:name":"Junku Music",
    "wof:placetype":"venue"
},
  "geometry": {"coordinates":[-118.14450100000001,34.061851],"type":"Point"}
}