{
  "type": "Feature",
  "properties": {
    "iso:country":"US",
    "sg:address":"725 S Madera Ave Bldg Mail",
    "sg:city":"Madera",
    "sg:classifiers":[
        {
            "category":"Real Estate",
            "subcategory":"Real Estate Services",
            "type":"Services"
        },
        {
            "category":"Real Estate",
            "subcategory":"Real Estate Operator",
            "type":"Services"
        }
    ],
    "sg:phone":"+1 559 673 0061",
    "sg:postcode":"93637",
    "sg:province":"CA",
    "sg:tags":[
        "vacancy",
        "apartment",
        "rental",
        "listing"
    ],
    "wof:name":"Almond Wood Apts.",
    "wof:placetype":"venue"
},
  "geometry": {"coordinates":[-120.055993,36.946152],"type":"Point"}
}