{
  "type": "Feature",
  "properties": {
    "iso:country":"US",
    "sg:address":"622 4th St",
    "sg:city":"Clovis",
    "sg:classifiers":[
        {
            "category":"Shopping",
            "subcategory":"Clothing, Apparel, & Fashions",
            "type":"Retail Goods"
        },
        {
            "category":"Education",
            "subcategory":"Dance Studio",
            "type":"Public Place"
        },
        {
            "category":"Arts & Performance",
            "subcategory":"Dance",
            "type":"Entertainment"
        }
    ],
    "sg:phone":"+1 559 299 0312",
    "sg:postcode":"93612",
    "sg:province":"CA",
    "sg:tags":[
        "dancing",
        "supply",
        "instruction",
        "sportswear",
        "clothing",
        "store"
    ],
    "wof:name":"D A Designs Dancewear",
    "wof:placetype":"venue"
},
  "geometry": {"coordinates":[-119.701317,36.82526],"type":"Point"}
}