{
  "type": "Feature",
  "properties": {
    "iso:country":"US",
    "sg:address":"1819 S Hobart Blvd",
    "sg:city":"Los Angeles",
    "sg:classifiers":[
        {
            "category":"Social Services",
            "subcategory":"Adult Care",
            "type":"Services"
        }
    ],
    "sg:phone":"+1 323 732 3008",
    "sg:postcode":"90006",
    "sg:province":"CA",
    "sg:tags":[
        "home",
        "residential"
    ],
    "wof:name":"American Guest Home Inc",
    "wof:placetype":"venue"
},
  "geometry": {"coordinates":[-118.305351,34.042606],"type":"Point"}
}