{
  "type": "Feature",
  "properties": {
    "addr:full":"2975 Scott Boulevard San Jose CA 95101",
    "addr:housenumber":"2975",
    "addr:postcode":"95101",
    "addr:street":"Scott Boulevard",
    "iso:country":"US",
    "sg:address":"2975 Scott Boulevard",
    "sg:city":"San Jose",
    "sg:classifiers":[
        {
            "category":"Professional",
            "subcategory":"Employment Agencies",
            "type":"Services"
        }
    ],
    "sg:phone":"+1 408 727 1607",
    "sg:postcode":"95101",
    "sg:province":"CA",
    "sg:website":"www.selectpersonnel.com",
    "wof:name":"Select Personnel Services",
    "wof:placetype":"venue"
},
  "geometry": {"coordinates":[-121.959585,37.375555],"type":"Point"}
}