{
  "type": "Feature",
  "properties": {
    "addr:full":"845 W Pacheco Blvd Los Banos CA 93635",
    "addr:housenumber":"845",
    "addr:postcode":"93635",
    "addr:street":"W Pacheco Blvd",
    "iso:country":"US",
    "sg:address":"845 W Pacheco Blvd",
    "sg:city":"Los Banos",
    "sg:classifiers":[
        {
            "category":"Restaurant",
            "type":"Food & Drink"
        }
    ],
    "sg:phone":"+1 209 827 0805",
    "sg:postcode":"93635",
    "sg:province":"CA",
    "wof:name":"Country Waffles",
    "wof:placetype":"venue"
},
  "geometry": {"coordinates":[-120.864135,37.056793],"type":"Point"}
}