{
  "type": "Feature",
  "properties": {
    "addr:full":"1915 Douglas Blvd Roseville CA 95661",
    "addr:housenumber":"1915",
    "addr:postcode":"95661",
    "addr:street":"Douglas Blvd",
    "iso:country":"US",
    "sg:address":"1915 Douglas Blvd",
    "sg:city":"Roseville",
    "sg:phone":"+1 916 781 7845",
    "sg:postcode":"95661",
    "sg:province":"CA",
    "sg:website":"http://www.raleys.com/",
    "wof:name":"Raley's",
    "wof:placetype":"venue"
},
  "geometry": {"coordinates":[-121.256546,38.744237],"type":"Point"}
}