{
  "type": "Feature",
  "properties": {
    "addr:full":"5838 Franklin Blvd Sacramento CA 95824",
    "addr:housenumber":"5838",
    "addr:postcode":"95824",
    "addr:street":"Franklin Blvd",
    "iso:country":"US",
    "sg:address":"5838 Franklin Blvd",
    "sg:city":"Sacramento",
    "sg:classifiers":[
        {
            "category":"Professional",
            "subcategory":"Employment Agencies",
            "type":"Services"
        }
    ],
    "sg:phone":"+1 916 392 8010",
    "sg:postcode":"95824",
    "sg:province":"CA",
    "sg:tags":[
        "profit",
        "services-non"
    ],
    "wof:name":"Sacramento Asian American Minority Inc.",
    "wof:placetype":"venue"
},
  "geometry": {"coordinates":[-121.47072199999999,38.520667],"type":"Point"}
}