{
  "type": "Feature",
  "properties": {
    "iso:country":"US",
    "sg:address":"2519 6th St",
    "sg:city":"Hughson",
    "sg:classifiers":[
        {
            "category":"Manufacturing",
            "subcategory":"Metals",
            "type":"Manufacturing & Wholesale Goods"
        }
    ],
    "sg:phone":"+1 209 883 4322",
    "sg:postcode":"95326",
    "sg:province":"CA",
    "sg:tags":[
        "plating"
    ],
    "sg:website":"www.chrome.net",
    "wof:name":"Robinson's",
    "wof:placetype":"venue"
},
  "geometry": {"coordinates":[-120.862103,37.593159],"type":"Point"}
}