{
  "type": "Feature",
  "properties": {
    "addr:full":"1540 Broadway Placerville CA 95667",
    "addr:housenumber":"1540",
    "addr:postcode":"95667",
    "addr:street":"Broadway",
    "iso:country":"US",
    "sg:address":"1540 Broadway",
    "sg:city":"Placerville",
    "sg:classifiers":[
        {
            "category":"Retail",
            "subcategory":"Auto Repair",
            "type":"Services"
        }
    ],
    "sg:phone":"+1 530 622 4714",
    "sg:postcode":"95667",
    "sg:province":"CA",
    "wof:name":"Sierra Nevada Tire & Wheel",
    "wof:placetype":"venue"
},
  "geometry": {"coordinates":[-120.772051,38.73317],"type":"Point"}
}