{
  "type": "Feature",
  "properties": {
    "iso:country":"US",
    "sg:address":"25641 golden springs drive",
    "sg:city":"Diamond bar",
    "sg:classifiers":[
        {
            "category":"Professional",
            "subcategory":"Computer Services",
            "type":"Services"
        }
    ],
    "sg:phone":"+1 877 323 4707",
    "sg:postcode":"91765",
    "sg:province":"CA",
    "sg:tags":[
        "medical-billing",
        "medical-coding",
        "medical-billing-services",
        "medical-coding-services",
        "medical-billing-and-coding",
        "medical-insurance-billing-and-coding",
        "medical-billing-associates",
        "medical-billers-for-surgical-centers",
        "medical-billing-and-coding-online",
        "medi"
    ],
    "sg:website":"http://www.billingparadise.com/",
    "wof:name":"Billingparadise",
    "wof:placetype":"venue"
},
  "geometry": {"coordinates":[-117.79667499999999,34.026467],"type":"Point"}
}