{
  "type": "Feature",
  "properties": {
    "iso:country":"US",
    "sg:address":"266 Monterey Rd Ste A",
    "sg:city":"South Pasadena",
    "sg:classifiers":[
        {
            "category":"Coffee & Tea",
            "type":"Food & Drink"
        }
    ],
    "sg:postcode":"91030",
    "sg:province":"CA",
    "sg:website":"charliescoffeehouse.com/",
    "wof:name":"Charlie's Coffee House",
    "wof:placetype":"venue"
},
  "geometry": {"coordinates":[-118.170289,34.11175],"type":"Point"}
}